{
  "commit": "4a07ea9a6a236520c71d699f0b550693f79bb9b3",
  "repo_url": "https://github.com/unetworking/uwebsockets",
  "model": "gpt-4-turbo-2024-04-09",
  "chunk_hashes": [
    "076c4b9c8885dd20130d"
  ],
  "responses": [
    {
      "content": "```yaml\nleads:\n  - headline: \"SSL Certificate Hardcoded Password\"\n    analysis: |\n      The code uses a hardcoded password for SSL certificate management in the `createContext` function within the Networking module. It exposes systems using this library to potential risks, as attackers who gain access to the code can extract and misuse the SSL certificate by leveraging the hardcoded password.\n    cwe: CWE-798\n    function_names:\n      - createContext\n    filenames:\n      - src/Networking.cpp\n    classification: very promising\n\n  - headline: \"Improper Validation of Array Index\"\n    analysis: |\n      In the function `echo()` within the throughput benchmark, there's an expression that computes an index for accessing elements within the `sockets` array using `rand() % connections`. This usage could be problematic if the value of `connections` is not properly validated to ensure it is not zero before performing module operations, as this can lead to division by zero errors.\n    cwe: CWE-129\n    function_names:\n      - echo\n    filenames:\n      - benchmarks/throughput.cpp\n    classification: slightly promising\n\n  - headline: \"Use of Hard-coded Cryptographic Key in WebSocket Communication\"\n    analysis: |\n      Hard-coded cryptographic key 'x3JJHMbDL1EzLkh9GBhXDw==', which is used for per-message WebSocket security in establishing communication, is found within benchmark scripts. Using fixed keys can lead to security issues where the encryption becomes useless against an adversary aware of the hardcoded key.\n    cwe: CWE-321\n    function_names:\n      - main\n    filenames:\n      - benchmarks/throughput.cpp\n      - benchmarks/scalability.cpp\n    classification: very promising\n\n  - headline: \"Excessive Data Exposure Through Sent Data\"\n    analysis: |\n      In server and client benchmarks, messages including potentially sensitive information are sent over the network without proper sanitization or encryption. This may lead sensitive data being exposed to unauthorized actors if intercepted during transmission.\n    cwe: CWE-200\n    function_names:\n      - onData\n    filenames:\n      - benchmarks/ws.js\n      - benchmarks/wsPP.cpp\n    classification: slightly promising\n\n  - headline: \"Inadequate Separation of Data and Control Instructions\"\n    analysis: |\n      The application directly passes user input into control mechanisms, allowing command injection. For instance, `execvp` uses dynamically constructed command strings in the autobahn test suite runner, which can lead to command injection if the input is not carefully sanitized.\n    cwe: CWE-77\n    function_names:\n      - main\n    filenames:\n      - nodejs/tests/autobahn.js\n    classification: slightly promising\n```",
      "date": "2024-07-08T09:08:07.714986",
      "usage": {
        "prompt_tokens": 40631,
        "completion_tokens": 553,
        "cost": 0.4229
      }
    }
  ],
  "leads": [
    {
      "headline": "SSL Certificate Hardcoded Password",
      "analysis": "The code uses a hardcoded password for SSL certificate management in the createContext function within the Networking module. It exposes systems using this library to potential risks, as attackers who gain access to the code can extract and misuse the SSL certificate by leveraging the hardcoded password.\n",
      "classification": "very promising",
      "cwe": "CWE-798",
      "function_names": [
        "createContext"
      ],
      "filenames": [
        "src/Networking.cpp"
      ]
    },
    {
      "headline": "Improper Validation of Array Index",
      "analysis": "In the function echo() within the throughput benchmark, there's an expression that computes an index for accessing elements within the sockets array using rand() % connections. This usage could be problematic if the value of connections is not properly validated to ensure it is not zero before performing module operations, as this can lead to division by zero errors.\n",
      "classification": "slightly promising",
      "cwe": "CWE-129",
      "function_names": [
        "echo"
      ],
      "filenames": [
        "benchmarks/throughput.cpp"
      ]
    },
    {
      "headline": "Use of Hard-coded Cryptographic Key in WebSocket Communication",
      "analysis": "Hard-coded cryptographic key 'x3JJHMbDL1EzLkh9GBhXDw==', which is used for per-message WebSocket security in establishing communication, is found within benchmark scripts. Using fixed keys can lead to security issues where the encryption becomes useless against an adversary aware of the hardcoded key.\n",
      "classification": "very promising",
      "cwe": "CWE-321",
      "function_names": [
        "main"
      ],
      "filenames": [
        "benchmarks/throughput.cpp",
        "benchmarks/scalability.cpp"
      ]
    },
    {
      "headline": "Excessive Data Exposure Through Sent Data",
      "analysis": "In server and client benchmarks, messages including potentially sensitive information are sent over the network without proper sanitization or encryption. This may lead sensitive data being exposed to unauthorized actors if intercepted during transmission.\n",
      "classification": "slightly promising",
      "cwe": "CWE-200",
      "function_names": [
        "onData"
      ],
      "filenames": [
        "benchmarks/ws.js",
        "benchmarks/wsPP.cpp"
      ]
    },
    {
      "headline": "Inadequate Separation of Data and Control Instructions",
      "analysis": "The application directly passes user input into control mechanisms, allowing command injection. For instance, execvp uses dynamically constructed command strings in the autobahn test suite runner, which can lead to command injection if the input is not carefully sanitized.\n",
      "classification": "slightly promising",
      "cwe": "CWE-77",
      "function_names": [
        "main"
      ],
      "filenames": [
        "nodejs/tests/autobahn.js"
      ]
    }
  ],
  "scores": [
    {
      "stats": {
        "fn": 1,
        "tp": 0,
        "fp": 2
      },
      "mapping": {},
      "vuln_dates": {
        "CVE-2016-10544": "2018-05-31T20:29:01"
      },
      "scoring_model": "claude-3-5-sonnet-20240620",
      "type": "llm",
      "instruction_template_hash": "245ace12b6361954d0a2"
    }
  ],
  "instruction_template_hash": "10c0163db4740318a544",
  "version": "0.1.0"
}
