{
  "commit": "a6d143d1ae30cc58fce8e9769e2a489db1e55b7d",
  "repo_url": "https://github.com/xwikisas/identity-oauth",
  "model": "claude-3-haiku-20240307",
  "chunk_hashes": [
    "dbc8de846abdbb39fecc"
  ],
  "responses": [
    {
      "content": "Here is the YAML output for the security vulnerabilities in the provided codebase:\n\n```yaml\nleads:\n  - headline: Potential Command Injection Vulnerability in IdentityOAuthScriptService\n    analysis: |\n      The `processOAuthStart()` method in the `IdentityOAuthScriptService` class retrieves the `provider` parameter from the HTTP request and passes it to the `getActiveProvider()` method in the `DefaultIdentityOAuthManager` class. This parameter is not properly validated, which could lead to a command injection vulnerability if an attacker were to provide a malicious value for the `provider` parameter.\n    cwe: CWE-77\n    function_names:\n      - processOAuthStart\n    filenames:\n      - api/src/main/java/com/xwiki/identityoauth/IdentityOAuthScriptService.java\n    classification: very promising\n  - headline: Potential Information Disclosure in IdentityOAuthSessionInfo\n    analysis: |\n      The `IdentityOAuthSessionInfo` class stores sensitive information, such as authorization codes, tokens, and expiry dates, in the user's session. This information could be accessed by an attacker if the session is not properly secured or if the session is hijacked.\n    cwe: CWE-200\n    function_names:\n      - getAuthorizationCode\n      - getToken\n      - getTokenExpiry\n    filenames:\n      - api/src/main/java/com/xwiki/identityoauth/internal/IdentityOAuthSessionInfo.java\n    classification: slightly promising\n  - headline: Potential Cross-Site Scripting (XSS) Vulnerability in IdentityOAuthScriptService\n    analysis: |\n      The `renderLoginCodes()` method in the `IdentityOAuthScriptService` class retrieves and renders the `loginCode` property from the `IdentityOAuthProvider` objects. This property is not properly sanitized before being rendered, which could lead to a cross-site scripting (XSS) vulnerability if an attacker were to provide malicious content in the `loginCode` property.\n    cwe: CWE-79\n    function_names:\n      - renderLoginCodes\n    filenames:\n      - api/src/main/java/com/xwiki/identityoauth/IdentityOAuthScriptService.java\n    classification: very promising\n  - headline: Potential Privilege Escalation Vulnerability in IdentityOAuthScriptService\n    analysis: |\n      The `getProvider()` method in the `IdentityOAuthScriptService` class retrieves the `IdentityOAuthProvider` object for the specified provider name, but only if the user has the `ADMIN` right. This check may not be sufficient, as an attacker could potentially bypass the authorization check and access sensitive provider configuration information.\n    cwe: CWE-269\n    function_names:\n      - getProvider\n    filenames:\n      - api/src/main/java/com/xwiki/identityoauth/IdentityOAuthScriptService.java\n    classification: slightly promising\n  - headline: Potential Improper Neutralization of Input during Web Page Generation in IdentityOAuthConfigTools\n    analysis: |\n      The `createDataUrl()` method in the `IdentityOAuthConfigTools` class retrieves and encodes the content of an attachment as a data URL. However, the method does not properly validate the attachment reference, which could lead to an improper neutralization of input during web page generation vulnerability if an attacker were to provide a malicious attachment reference.\n    cwe: CWE-79\n    function_names:\n      - createDataUrl\n    filenames:\n      - api/src/main/java/com/xwiki/identityoauth/internal/IdentityOAuthConfigTools.java\n    classification: very promising\n  - headline: Potential Improper Handling of Exceptional Conditions in IdentityOAuthUserTools\n    analysis: |\n      The `updateXWikiUser()` method in the `IdentityOAuthUserTools` class catches and wraps various exceptions, but it does not handle the exceptions properly. This could lead to an improper handling of exceptional conditions vulnerability, where the application may not be able to recover from certain errors or may expose sensitive information to the user.\n    cwe: CWE-754\n    function_names:\n      - updateXWikiUser\n    filenames:\n      - api/src/main/java/com/xwiki/identityoauth/internal/IdentityOAuthUserTools.java\n    classification: slightly promising\n```",
      "date": "2024-06-09T15:33:06.959282",
      "usage": {
        "prompt_tokens": 32258,
        "completion_tokens": 1083,
        "cost": 0.00941825
      }
    }
  ],
  "leads": [
    {
      "headline": "Potential Command Injection Vulnerability in IdentityOAuthScriptService",
      "analysis": "The processOAuthStart() method in the IdentityOAuthScriptService class retrieves the provider parameter from the HTTP request and passes it to the getActiveProvider() method in the DefaultIdentityOAuthManager class. This parameter is not properly validated, which could lead to a command injection vulnerability if an attacker were to provide a malicious value for the provider parameter.\n",
      "classification": "very promising",
      "cwe": "CWE-77",
      "function_names": [
        "processOAuthStart"
      ],
      "filenames": [
        "api/src/main/java/com/xwiki/identityoauth/IdentityOAuthScriptService.java"
      ]
    },
    {
      "headline": "Potential Information Disclosure in IdentityOAuthSessionInfo",
      "analysis": "The IdentityOAuthSessionInfo class stores sensitive information, such as authorization codes, tokens, and expiry dates, in the user's session. This information could be accessed by an attacker if the session is not properly secured or if the session is hijacked.\n",
      "classification": "slightly promising",
      "cwe": "CWE-200",
      "function_names": [
        "getAuthorizationCode",
        "getToken",
        "getTokenExpiry"
      ],
      "filenames": [
        "api/src/main/java/com/xwiki/identityoauth/internal/IdentityOAuthSessionInfo.java"
      ]
    },
    {
      "headline": "Potential Cross-Site Scripting (XSS) Vulnerability in IdentityOAuthScriptService",
      "analysis": "The renderLoginCodes() method in the IdentityOAuthScriptService class retrieves and renders the loginCode property from the IdentityOAuthProvider objects. This property is not properly sanitized before being rendered, which could lead to a cross-site scripting (XSS) vulnerability if an attacker were to provide malicious content in the loginCode property.\n",
      "classification": "very promising",
      "cwe": "CWE-79",
      "function_names": [
        "renderLoginCodes"
      ],
      "filenames": [
        "api/src/main/java/com/xwiki/identityoauth/IdentityOAuthScriptService.java"
      ]
    },
    {
      "headline": "Potential Privilege Escalation Vulnerability in IdentityOAuthScriptService",
      "analysis": "The getProvider() method in the IdentityOAuthScriptService class retrieves the IdentityOAuthProvider object for the specified provider name, but only if the user has the ADMIN right. This check may not be sufficient, as an attacker could potentially bypass the authorization check and access sensitive provider configuration information.\n",
      "classification": "slightly promising",
      "cwe": "CWE-269",
      "function_names": [
        "getProvider"
      ],
      "filenames": [
        "api/src/main/java/com/xwiki/identityoauth/IdentityOAuthScriptService.java"
      ]
    },
    {
      "headline": "Potential Improper Neutralization of Input during Web Page Generation in IdentityOAuthConfigTools",
      "analysis": "The createDataUrl() method in the IdentityOAuthConfigTools class retrieves and encodes the content of an attachment as a data URL. However, the method does not properly validate the attachment reference, which could lead to an improper neutralization of input during web page generation vulnerability if an attacker were to provide a malicious attachment reference.\n",
      "classification": "very promising",
      "cwe": "CWE-79",
      "function_names": [
        "createDataUrl"
      ],
      "filenames": [
        "api/src/main/java/com/xwiki/identityoauth/internal/IdentityOAuthConfigTools.java"
      ]
    },
    {
      "headline": "Potential Improper Handling of Exceptional Conditions in IdentityOAuthUserTools",
      "analysis": "The updateXWikiUser() method in the IdentityOAuthUserTools class catches and wraps various exceptions, but it does not handle the exceptions properly. This could lead to an improper handling of exceptional conditions vulnerability, where the application may not be able to recover from certain errors or may expose sensitive information to the user.\n",
      "classification": "slightly promising",
      "cwe": "CWE-754",
      "function_names": [
        "updateXWikiUser"
      ],
      "filenames": [
        "api/src/main/java/com/xwiki/identityoauth/internal/IdentityOAuthUserTools.java"
      ]
    }
  ],
  "scores": [
    {
      "stats": {
        "fn": 1,
        "tp": 0,
        "fp": 3
      },
      "mapping": {},
      "vuln_dates": {
        "CVE-2023-45144": "2023-10-16T21:15:11"
      },
      "scoring_model": "gpt-4o-2024-05-13",
      "type": "llm",
      "instruction_template_hash": "8998f09cf57fca8a6e03"
    }
  ],
  "instruction_template_hash": "10c0163db4740318a544",
  "version": "0.1.0"
}
