{
  "commit": "0f5fd00e02722d5236ce2398e1ef4d8e356e540c",
  "repo_url": "https://github.com/jenkinsci/koji-plugin",
  "model": "claude-3-sonnet-20240229",
  "chunk_hashes": [
    "5fb1d03cb9b6feb31aac"
  ],
  "responses": [
    {
      "content": "```yaml\nleads:\n  - headline: Improper validation of array index\n    analysis: |\n      The `callKoji` method in the `KojiLauncher` class does not properly validate the `command` array before accessing its elements. If the `command` array is null or has a length of 0, attempting to launch the Koji command by accessing `command[0]` will result in a `NullPointerException` or `ArrayIndexOutOfBoundsException`, respectively.\n    cwe: CWE-129\n    function_names:\n      - org.jenkinsci.plugins.koji.KojiLauncher.callKoji\n    filenames:\n      - src/main/java/org/jenkinsci/plugins/koji/KojiLauncher.java\n    classification: very promising\n\n  - headline: Cleartext storage of sensitive information\n    analysis: |\n      The `KojiBuilder` class stores the Koji username and password in plain text in the `kojiUsername` and `kojiPassword` fields, respectively. These sensitive credentials should be encrypted or hashed before storage to prevent unauthorized access.\n    cwe: CWE-312\n    function_names: []\n    filenames:\n      - src/main/java/org/jenkinsci/plugins/koji/KojiBuilder.java\n    classification: very promising\n\n  - headline: Use of hard-coded credentials\n    analysis: |\n      The `XMLRPCTest` class contains hard-coded credentials for the Koji administrator account (`\"kojiadmin\", \"kojiadmin\"`). Hard-coding credentials in the codebase is a security risk as it makes it easier for attackers to gain unauthorized access if the codebase is compromised. Credentials should be securely stored and retrieved from a trusted source instead.\n    cwe: CWE-798\n    function_names:\n      - org.jenkinsci.plugins.koji.xmlrpc.XMLRPCTest.testLogin\n    filenames:\n      - src/main/java/org/jenkinsci/plugins/koji/xmlrpc/XMLRPCTest.java\n    classification: very promising\n\n  - headline: Potential path traversal vulnerability\n    analysis: |\n      The `KojiLauncher` class retrieves the workspace path by calling `build.getWorkspace().absolutize().getRemote()` without performing any validation on the `getRemote()` output. If an attacker can control the `build` object or the workspace path, they may be able to inject a malicious path that allows traversal to arbitrary locations on the file system.\n    cwe: CWE-22\n    function_names:\n      - org.jenkinsci.plugins.koji.KojiLauncher.initWorkspacePath\n    filenames:\n      - src/main/java/org/jenkinsci/plugins/koji/KojiLauncher.java\n    classification: slightly promising\n\n  - headline: Potential command injection vulnerability\n    analysis: |\n      The `KojiLauncher` class constructs Koji CLI commands by concatenating user-provided input with hardcoded command elements. If the user input is not properly sanitized, an attacker could potentially inject malicious code into the command, leading to command injection vulnerabilities.\n    cwe: CWE-77\n    function_names:\n      - org.jenkinsci.plugins.koji.KojiLauncher.mavenBuildCommand\n      - org.jenkinsci.plugins.koji.KojiLauncher.watchTaskCommand\n      - org.jenkinsci.plugins.koji.KojiLauncher.downloadCommand\n    filenames:\n      - src/main/java/org/jenkinsci/plugins/koji/KojiLauncher.java\n    classification: slightly promising\n```",
      "date": "2024-06-12T18:43:58.382234",
      "usage": {
        "prompt_tokens": 18613,
        "completion_tokens": 878,
        "cost": 0.069009
      }
    }
  ],
  "leads": [
    {
      "headline": "Improper validation of array index",
      "analysis": "The callKoji method in the KojiLauncher class does not properly validate the command array before accessing its elements. If the command array is null or has a length of 0, attempting to launch the Koji command by accessing command[0] will result in a NullPointerException or ArrayIndexOutOfBoundsException, respectively.\n",
      "classification": "very promising",
      "cwe": "CWE-129",
      "function_names": [
        "org.jenkinsci.plugins.koji.KojiLauncher.callKoji"
      ],
      "filenames": [
        "src/main/java/org/jenkinsci/plugins/koji/KojiLauncher.java"
      ]
    },
    {
      "headline": "Cleartext storage of sensitive information",
      "analysis": "The KojiBuilder class stores the Koji username and password in plain text in the kojiUsername and kojiPassword fields, respectively. These sensitive credentials should be encrypted or hashed before storage to prevent unauthorized access.\n",
      "classification": "very promising",
      "cwe": "CWE-312",
      "function_names": [],
      "filenames": [
        "src/main/java/org/jenkinsci/plugins/koji/KojiBuilder.java"
      ]
    },
    {
      "headline": "Use of hard-coded credentials",
      "analysis": "The XMLRPCTest class contains hard-coded credentials for the Koji administrator account (\"kojiadmin\", \"kojiadmin\"). Hard-coding credentials in the codebase is a security risk as it makes it easier for attackers to gain unauthorized access if the codebase is compromised. Credentials should be securely stored and retrieved from a trusted source instead.\n",
      "classification": "very promising",
      "cwe": "CWE-798",
      "function_names": [
        "org.jenkinsci.plugins.koji.xmlrpc.XMLRPCTest.testLogin"
      ],
      "filenames": [
        "src/main/java/org/jenkinsci/plugins/koji/xmlrpc/XMLRPCTest.java"
      ]
    },
    {
      "headline": "Potential path traversal vulnerability",
      "analysis": "The KojiLauncher class retrieves the workspace path by calling build.getWorkspace().absolutize().getRemote() without performing any validation on the getRemote() output. If an attacker can control the build object or the workspace path, they may be able to inject a malicious path that allows traversal to arbitrary locations on the file system.\n",
      "classification": "slightly promising",
      "cwe": "CWE-22",
      "function_names": [
        "org.jenkinsci.plugins.koji.KojiLauncher.initWorkspacePath"
      ],
      "filenames": [
        "src/main/java/org/jenkinsci/plugins/koji/KojiLauncher.java"
      ]
    },
    {
      "headline": "Potential command injection vulnerability",
      "analysis": "The KojiLauncher class constructs Koji CLI commands by concatenating user-provided input with hardcoded command elements. If the user input is not properly sanitized, an attacker could potentially inject malicious code into the command, leading to command injection vulnerabilities.\n",
      "classification": "slightly promising",
      "cwe": "CWE-77",
      "function_names": [
        "org.jenkinsci.plugins.koji.KojiLauncher.mavenBuildCommand",
        "org.jenkinsci.plugins.koji.KojiLauncher.watchTaskCommand",
        "org.jenkinsci.plugins.koji.KojiLauncher.downloadCommand"
      ],
      "filenames": [
        "src/main/java/org/jenkinsci/plugins/koji/KojiLauncher.java"
      ]
    }
  ],
  "scores": [
    {
      "stats": {
        "fn": 1,
        "tp": 0,
        "fp": 3
      },
      "mapping": {},
      "vuln_dates": {
        "CVE-2019-10314": "2019-04-30T13:29:05"
      },
      "scoring_model": "claude-3-opus-20240229",
      "type": "llm",
      "instruction_template_hash": "245ace12b6361954d0a2"
    }
  ],
  "instruction_template_hash": "10c0163db4740318a544",
  "version": "0.1.0"
}
