{
  "commit": "3551a20773e4463eea8678bd937ad654c9a72fd5",
  "repo_url": "https://github.com/jenkinsci/logstash-plugin",
  "model": "claude-3-haiku-20240307",
  "chunk_hashes": [
    "fb899b783dc080c59178"
  ],
  "responses": [
    {
      "content": "Based on the code provided, here are the security vulnerabilities I identified:\n\n```yaml\nleads:\n  - headline: Improper Input Validation\n    analysis: |\n      The code does not properly validate user input for the Elastic Search URI, RabbitMQ queue name, and Redis key. This can lead to injection vulnerabilities such as command injection or path traversal.\n    cwe: CWE-20\n    function_names:\n      - createDao\n      - doCheckUrl\n      - doCheckKey\n      - doCheckQueue\n    filenames:\n      - jenkins/plugins/logstash/persistence/ElasticSearchDao.java\n      - jenkins/plugins/logstash/configuration/RabbitMq.java\n      - jenkins/plugins/logstash/configuration/Redis.java\n    classification: very promising\n  - headline: Cleartext Transmission of Sensitive Information\n    analysis: |\n      The code does not properly encrypt or obfuscate sensitive information such as passwords and credentials when transmitted to the indexer servers. This can lead to sensitive information disclosure.\n    cwe: CWE-319\n    function_names:\n      - push\n    filenames:\n      - jenkins/plugins/logstash/persistence/ElasticSearchDao.java\n      - jenkins/plugins/logstash/persistence/RedisDao.java\n      - jenkins/plugins/logstash/persistence/RabbitMqDao.java\n    classification: very promising\n  - headline: Improper Neutralization of Special Elements used in an OS Command ('OS Command Injection')\n    analysis: |\n      The code uses user-controlled input to construct OS commands, which can lead to command injection vulnerabilities. This is particularly evident in the ElasticSearchDao and SyslogDao classes.\n    cwe: CWE-78\n    function_names:\n      - getHttpPost\n      - push\n    filenames:\n      - jenkins/plugins/logstash/persistence/ElasticSearchDao.java\n      - jenkins/plugins/logstash/persistence/SyslogDao.java\n    classification: very promising\n  - headline: Cross-Site Scripting (XSS)\n    analysis: |\n      The code does not properly sanitize or encode user input before displaying it in the web interface. This can lead to XSS vulnerabilities.\n    cwe: CWE-79\n    function_names:\n      - perform\n    filenames:\n      - jenkins/plugins/logstash/LogstashNotifier.java\n    classification: slightly promising\n  - headline: Incorrect Authentication\n    analysis: |\n      The code does not properly validate the authentication credentials provided by the user. This can lead to authentication bypass vulnerabilities.\n    cwe: CWE-863\n    function_names:\n      - push\n    filenames:\n      - jenkins/plugins/logstash/persistence/RedisDao.java\n      - jenkins/plugins/logstash/persistence/RabbitMqDao.java\n    classification: very promising\n  - headline: Improper Resource Shutdown or Release\n    analysis: |\n      The code does not properly close or release resources such as connections, channels, and sockets. This can lead to resource exhaustion vulnerabilities.\n    cwe: CWE-404\n    function_names:\n      - push\n    filenames:\n      - jenkins/plugins/logstash/persistence/RedisDao.java\n      - jenkins/plugins/logstash/persistence/RabbitMqDao.java\n      - jenkins/plugins/logstash/persistence/LogstashDao.java\n    classification: slightly promising\n```",
      "date": "2024-06-12T18:46:23.015954",
      "usage": {
        "prompt_tokens": 77758,
        "completion_tokens": 832,
        "cost": 0.0204795
      }
    }
  ],
  "leads": [
    {
      "headline": "Improper Input Validation",
      "analysis": "The code does not properly validate user input for the Elastic Search URI, RabbitMQ queue name, and Redis key. This can lead to injection vulnerabilities such as command injection or path traversal.\n",
      "classification": "very promising",
      "cwe": "CWE-20",
      "function_names": [
        "createDao",
        "doCheckUrl",
        "doCheckKey"
      ],
      "filenames": [
        "jenkins/plugins/logstash/persistence/ElasticSearchDao.java",
        "jenkins/plugins/logstash/configuration/RabbitMq.java",
        "jenkins/plugins/logstash/configuration/Redis.java"
      ]
    },
    {
      "headline": "Cleartext Transmission of Sensitive Information",
      "analysis": "The code does not properly encrypt or obfuscate sensitive information such as passwords and credentials when transmitted to the indexer servers. This can lead to sensitive information disclosure.\n",
      "classification": "very promising",
      "cwe": "CWE-319",
      "function_names": [
        "push"
      ],
      "filenames": [
        "jenkins/plugins/logstash/persistence/ElasticSearchDao.java",
        "jenkins/plugins/logstash/persistence/RedisDao.java",
        "jenkins/plugins/logstash/persistence/RabbitMqDao.java"
      ]
    },
    {
      "headline": "Improper Neutralization of Special Elements used in an OS Command ('OS Command Injection')",
      "analysis": "The code uses user-controlled input to construct OS commands, which can lead to command injection vulnerabilities. This is particularly evident in the ElasticSearchDao and SyslogDao classes.\n",
      "classification": "very promising",
      "cwe": "CWE-78",
      "function_names": [
        "getHttpPost",
        "push"
      ],
      "filenames": [
        "jenkins/plugins/logstash/persistence/ElasticSearchDao.java",
        "jenkins/plugins/logstash/persistence/SyslogDao.java"
      ]
    },
    {
      "headline": "Cross-Site Scripting (XSS)",
      "analysis": "The code does not properly sanitize or encode user input before displaying it in the web interface. This can lead to XSS vulnerabilities.\n",
      "classification": "slightly promising",
      "cwe": "CWE-79",
      "function_names": [
        "perform"
      ],
      "filenames": [
        "jenkins/plugins/logstash/LogstashNotifier.java"
      ]
    },
    {
      "headline": "Incorrect Authentication",
      "analysis": "The code does not properly validate the authentication credentials provided by the user. This can lead to authentication bypass vulnerabilities.\n",
      "classification": "very promising",
      "cwe": "CWE-863",
      "function_names": [
        "push"
      ],
      "filenames": [
        "jenkins/plugins/logstash/persistence/RedisDao.java",
        "jenkins/plugins/logstash/persistence/RabbitMqDao.java"
      ]
    },
    {
      "headline": "Improper Resource Shutdown or Release",
      "analysis": "The code does not properly close or release resources such as connections, channels, and sockets. This can lead to resource exhaustion vulnerabilities.\n",
      "classification": "slightly promising",
      "cwe": "CWE-404",
      "function_names": [
        "push"
      ],
      "filenames": [
        "jenkins/plugins/logstash/persistence/RedisDao.java",
        "jenkins/plugins/logstash/persistence/RabbitMqDao.java",
        "jenkins/plugins/logstash/persistence/LogstashDao.java"
      ]
    }
  ],
  "scores": [
    {
      "stats": {
        "fn": 0,
        "tp": 1,
        "fp": 3
      },
      "mapping": {
        "1": "CVE-2020-2143"
      },
      "vuln_dates": {
        "CVE-2020-2143": "2020-03-09T16:15:13"
      },
      "scoring_model": "claude-3-opus-20240229",
      "type": "llm",
      "instruction_template_hash": "245ace12b6361954d0a2"
    }
  ],
  "instruction_template_hash": "10c0163db4740318a544",
  "version": "0.1.0"
}
