{
  "commit": "228f357af22643dd8be7464c39e04e009af2d2ee",
  "repo_url": "https://github.com/maxtortime/setupbox",
  "model": "gpt-4o-2024-05-13",
  "chunk_hashes": [
    "12299c1340cd2175c350"
  ],
  "responses": [
    {
      "content": "```yaml\nleads:\n  - headline: \"Hardcoded Email Credentials in Configuration File\"\n    analysis: |\n      The `web_server/config.py` file contains hardcoded credentials (`setupboxtest@gmail.com`, `tptdjqqkrtm`) for email configuration. These credentials can easily be extracted by anyone with access to the source code, posing a risk to email account security.\n    cwe: CWE-798\n    function_names:\n      - N/A\n    filenames:\n      - web_server/config.py\n    classification: very promising\n\n  - headline: \"Initialization of System Command with User Inputs\"\n    analysis: |\n      In the `server_install.sh`, the `brew`, `pip`, and `npm` commands are initialized without proper validation. This could allow for injection vulnerabilities if user input is possible in these contexts. Additionally, use of `sudo` for pip installation can lead to privilege escalation if the script is run in an untrusted environment.\n    cwe: CWE-78\n    function_names:\n      - N/A\n    filenames:\n      - server_install.sh\n    classification: slightly promising\n\n  - headline: \"Usage of Insecure HTTP URL for External Resource\"\n    analysis: |\n      In `runserver.py`, the URL `http://www.gravatar.com/avatar/` is used for fetching gravatar images. Using HTTP instead of HTTPS subjects the application to potential man-in-the-middle attacks where user information can be intercepted or manipulated.\n    cwe: CWE-311\n    function_names:\n      - authTest\n      - explorer\n    filenames:\n      - web_server/runserver.py\n    classification: slightly promising\n\n  - headline: \"OS Command Injection in Shell Script\"\n    analysis: |\n      The `server_install.sh` uses backticks for command substitution inside conditional statements, which can be exploited to execute arbitrary commands. Using `$(...)` for command substitution is safer and can help prevent injection attacks to some extent.\n    cwe: CWE-77\n    function_names:\n      - N/A\n    filenames:\n      - server_install.sh\n    classification: slightly promising\n\n  - headline: \"Exposed Secret Key in Configuration File\"\n    analysis: |\n      The `config.py` file contains a secret key `SECRET_KEY = 'super-secret'` that is hardcoded. This is a significant security risk as attackers gaining access to the source code can use this key for various attacks against the application, such as session hijacking or CSRF.\n    cwe: CWE-321\n    function_names:\n      - N/A\n    filenames:\n      - web_server/config.py\n    classification: very promising\n\n  - headline: \"Potential Path Traversal Vulnerability\"\n    analysis: |\n      The `explorer` function in `runserver.py` constructs file paths using user-supplied data from the request's `path` parameter without proper sanitization. This could potentially allow an attacker to traverse directories and access files outside the intended directory.\n    cwe: CWE-22\n    function_names:\n      - explorer\n    filenames:\n      - web_server/runserver.py\n    classification: very promising\n\n  - headline: \"SQL Injection Risk with Raw SQL Queries\"\n    analysis: |\n      The `config.py` file uses an SQLite URI for database connectivity, but it's not clear if there are checks to prevent raw SQL queries with unescaped user input elsewhere in the application. This could lead to SQL injection vulnerabilities.\n    cwe: CWE-89\n    function_names:\n      - N/A \n    filenames:\n      - web_server/config.py\n    classification: slightly promising\n\n  - headline: \"Missing Input Validation in Email Handling\"\n    analysis: |\n      In `config.py`, the email handling configuration lacks adequate input validation. Improper validation or sanitization of email inputs can lead to various attack vectors, such as injection attacks and cross-site scripting (XSS).\n    cwe: CWE-20\n    function_names:\n      - N/A\n    filenames:\n      - web_server/config.py\n    classification: slightly promising\n```",
      "date": "2024-06-13T10:03:29.834694",
      "usage": {
        "prompt_tokens": 15174,
        "completion_tokens": 830,
        "cost": 0.08832
      }
    }
  ],
  "leads": [
    {
      "headline": "Hardcoded Email Credentials in Configuration File",
      "analysis": "The web_server/config.py file contains hardcoded credentials (setupboxtest@gmail.com, tptdjqqkrtm) for email configuration. These credentials can easily be extracted by anyone with access to the source code, posing a risk to email account security.\n",
      "classification": "very promising",
      "cwe": "CWE-798",
      "function_names": [
        "N/A"
      ],
      "filenames": [
        "web_server/config.py"
      ]
    },
    {
      "headline": "Initialization of System Command with User Inputs",
      "analysis": "In the server_install.sh, the brew, pip, and npm commands are initialized without proper validation. This could allow for injection vulnerabilities if user input is possible in these contexts. Additionally, use of sudo for pip installation can lead to privilege escalation if the script is run in an untrusted environment.\n",
      "classification": "slightly promising",
      "cwe": "CWE-78",
      "function_names": [
        "N/A"
      ],
      "filenames": [
        "server_install.sh"
      ]
    },
    {
      "headline": "Usage of Insecure HTTP URL for External Resource",
      "analysis": "In runserver.py, the URL http://www.gravatar.com/avatar/ is used for fetching gravatar images. Using HTTP instead of HTTPS subjects the application to potential man-in-the-middle attacks where user information can be intercepted or manipulated.\n",
      "classification": "slightly promising",
      "cwe": "CWE-311",
      "function_names": [
        "authTest",
        "explorer"
      ],
      "filenames": [
        "web_server/runserver.py"
      ]
    },
    {
      "headline": "OS Command Injection in Shell Script",
      "analysis": "The server_install.sh uses backticks for command substitution inside conditional statements, which can be exploited to execute arbitrary commands. Using $(...) for command substitution is safer and can help prevent injection attacks to some extent.\n",
      "classification": "slightly promising",
      "cwe": "CWE-77",
      "function_names": [
        "N/A"
      ],
      "filenames": [
        "server_install.sh"
      ]
    },
    {
      "headline": "Exposed Secret Key in Configuration File",
      "analysis": "The config.py file contains a secret key SECRET_KEY = 'super-secret' that is hardcoded. This is a significant security risk as attackers gaining access to the source code can use this key for various attacks against the application, such as session hijacking or CSRF.\n",
      "classification": "very promising",
      "cwe": "CWE-321",
      "function_names": [
        "N/A"
      ],
      "filenames": [
        "web_server/config.py"
      ]
    },
    {
      "headline": "Potential Path Traversal Vulnerability",
      "analysis": "The explorer function in runserver.py constructs file paths using user-supplied data from the request's path parameter without proper sanitization. This could potentially allow an attacker to traverse directories and access files outside the intended directory.\n",
      "classification": "very promising",
      "cwe": "CWE-22",
      "function_names": [
        "explorer"
      ],
      "filenames": [
        "web_server/runserver.py"
      ]
    },
    {
      "headline": "SQL Injection Risk with Raw SQL Queries",
      "analysis": "The config.py file uses an SQLite URI for database connectivity, but it's not clear if there are checks to prevent raw SQL queries with unescaped user input elsewhere in the application. This could lead to SQL injection vulnerabilities.\n",
      "classification": "slightly promising",
      "cwe": "CWE-89",
      "function_names": [
        "N/A"
      ],
      "filenames": [
        "web_server/config.py"
      ]
    },
    {
      "headline": "Missing Input Validation in Email Handling",
      "analysis": "In config.py, the email handling configuration lacks adequate input validation. Improper validation or sanitization of email inputs can lead to various attack vectors, such as injection attacks and cross-site scripting (XSS).\n",
      "classification": "slightly promising",
      "cwe": "CWE-20",
      "function_names": [
        "N/A"
      ],
      "filenames": [
        "web_server/config.py"
      ]
    }
  ],
  "scores": [
    {
      "stats": {
        "fn": 1,
        "tp": 0,
        "fp": 3
      },
      "mapping": {},
      "vuln_dates": {
        "CVE-2022-31543": "2022-07-11T01:15:09"
      },
      "scoring_model": "claude-3-opus-20240229",
      "type": "llm",
      "instruction_template_hash": "245ace12b6361954d0a2"
    }
  ],
  "instruction_template_hash": "10c0163db4740318a544",
  "version": "0.1.0"
}
