{
  "commit": "19bb72ef1cf1c4f291fd858ca2a44cef785c301c",
  "repo_url": "https://github.com/parisneo/lollms",
  "model": "gemini/gemini-1.5-pro",
  "chunk_hashes": [
    "56e7d085548432af961c"
  ],
  "responses": [
    {
      "content": "```yaml\nleads:\n  - headline: Insecure file filtering in setup.py\n    analysis: |\n      The function `get_all_files` in `setup.py` aims to filter out certain files and directories from being included in the package. However, it only filters based on simple string matching of the filename, which can be easily bypassed. For instance, creating a file named \".git.txt\" or \"__pycache__.py\" would evade the filter and potentially include sensitive files in the distribution package.\n    cwe: CWE-552\n    function_names:\n      - get_all_files\n    filenames:\n      - setup.py\n    classification: slightly promising\n  - headline: Potential arbitrary code execution in install_model function\n    analysis: |\n      The `install_model` function in `lollms/terminal.py` takes user input for a model path. If the user provides a malicious path, it might be possible to execute arbitrary code. The function doesn't validate the provided path and directly uses it with `self.lollms_app.config.reference_model(path)`. Depending on how `reference_model` handles the path, this could lead to code execution vulnerabilities.\n    cwe: CWE-94\n    function_names:\n      - install_model\n    filenames:\n      - lollms/terminal.py\n    classification: slightly promising\n  - headline: Insufficient input validation for URL in install_model function\n    analysis: |\n      The `install_model` function in `lollms/terminal.py` takes user input for a model URL. This URL is used directly in the `download_model` function. Without proper validation of the URL, an attacker could potentially supply a malicious URL, leading to issues like Server-Side Request Forgery (SSRF) or downloading and executing malicious code.\n    cwe: CWE-20\n    function_names:\n      - install_model\n    filenames:\n      - lollms/terminal.py\n    classification: slightly promising\n  - headline: Unvalidated user input in APScript.add_file\n    analysis: |\n      The `add_file` function in `lollms/personality.py` (within the `APScript` class) takes a file path as input and appends it to a list. If the file path is user-controlled and not properly sanitized, an attacker could potentially supply a path that leads to unauthorized file access or directory traversal vulnerabilities.\n    cwe: CWE-22\n    function_names:\n      - add_file\n    filenames:\n      - lollms/personality.py\n    classification: slightly promising\n  - headline: Potential for insecure deserialization in TextVectorizer\n    analysis: |\n      The `TextVectorizer` class in `lollms/utilities.py` uses `json.load` to load data from a file in the `load_from_json` function. Without proper validation and sanitization of the loaded data, an attacker could potentially exploit this to perform insecure deserialization, leading to arbitrary code execution.\n    cwe: CWE-502\n    function_names:\n      - load_from_json\n    filenames:\n      - lollms/utilities.py\n    classification: slightly promising\n  - headline: Unrestricted file upload in SocketIOFile\n    analysis: |\n      The `SocketIOFile` class in `lollms/data.py` allows receiving and saving files from a Socket.IO server. However, it does not seem to restrict file types or validate the content of the uploaded files. This could potentially allow attackers to upload malicious files, leading to code execution or other security issues.\n    cwe: CWE-434\n    function_names:\n      - receive_file\n    filenames:\n      - lollms/data.py\n    classification: very promising\n  - headline: Potential Server-Side Request Forgery (SSRF) in LOLLMSConfig\n    analysis: |\n      The `download_model` function in `lollms/main_config.py` takes a URL as input and downloads the model from that URL. If the URL is user-controlled and not properly validated, an attacker could supply a URL pointing to internal services or resources, potentially leading to SSRF vulnerabilities.\n    cwe: CWE-918\n    function_names:\n      - download_model\n    filenames:\n      - lollms/main_config.py\n    classification: slightly promising\n  - headline: Arbitrary code execution vulnerability in execute_python_code\n    analysis: |\n      The function `execute_python_code` in `lollms/apps/playground/__init__.py` directly executes user-supplied Python code using the `exec` function. This allows attackers to execute arbitrary code on the server, giving them complete control over the system.\n    cwe: CWE-94\n    function_names:\n      - execute_python_code\n    filenames:\n      - lollms/apps/playground/__init__.py\n    classification: very promising\n```",
      "date": "2024-06-12T13:34:07.821271",
      "usage": {
        "prompt_tokens": 78692,
        "completion_tokens": 987,
        "cost": 0.051033125000000006
      }
    }
  ],
  "leads": [
    {
      "headline": "Insecure file filtering in setup.py",
      "analysis": "The function get_all_files in setup.py aims to filter out certain files and directories from being included in the package. However, it only filters based on simple string matching of the filename, which can be easily bypassed. For instance, creating a file named \".git.txt\" or \"__pycache__.py\" would evade the filter and potentially include sensitive files in the distribution package.\n",
      "classification": "slightly promising",
      "cwe": "CWE-552",
      "function_names": [
        "get_all_files"
      ],
      "filenames": [
        "setup.py"
      ]
    },
    {
      "headline": "Potential arbitrary code execution in install_model function",
      "analysis": "The install_model function in lollms/terminal.py takes user input for a model path. If the user provides a malicious path, it might be possible to execute arbitrary code. The function doesn't validate the provided path and directly uses it with self.lollms_app.config.reference_model(path). Depending on how reference_model handles the path, this could lead to code execution vulnerabilities.\n",
      "classification": "slightly promising",
      "cwe": "CWE-94",
      "function_names": [
        "install_model"
      ],
      "filenames": [
        "lollms/terminal.py"
      ]
    },
    {
      "headline": "Insufficient input validation for URL in install_model function",
      "analysis": "The install_model function in lollms/terminal.py takes user input for a model URL. This URL is used directly in the download_model function. Without proper validation of the URL, an attacker could potentially supply a malicious URL, leading to issues like Server-Side Request Forgery (SSRF) or downloading and executing malicious code.\n",
      "classification": "slightly promising",
      "cwe": "CWE-20",
      "function_names": [
        "install_model"
      ],
      "filenames": [
        "lollms/terminal.py"
      ]
    },
    {
      "headline": "Unvalidated user input in APScript.add_file",
      "analysis": "The add_file function in lollms/personality.py (within the APScript class) takes a file path as input and appends it to a list. If the file path is user-controlled and not properly sanitized, an attacker could potentially supply a path that leads to unauthorized file access or directory traversal vulnerabilities.\n",
      "classification": "slightly promising",
      "cwe": "CWE-22",
      "function_names": [
        "add_file"
      ],
      "filenames": [
        "lollms/personality.py"
      ]
    },
    {
      "headline": "Potential for insecure deserialization in TextVectorizer",
      "analysis": "The TextVectorizer class in lollms/utilities.py uses json.load to load data from a file in the load_from_json function. Without proper validation and sanitization of the loaded data, an attacker could potentially exploit this to perform insecure deserialization, leading to arbitrary code execution.\n",
      "classification": "slightly promising",
      "cwe": "CWE-502",
      "function_names": [
        "load_from_json"
      ],
      "filenames": [
        "lollms/utilities.py"
      ]
    },
    {
      "headline": "Unrestricted file upload in SocketIOFile",
      "analysis": "The SocketIOFile class in lollms/data.py allows receiving and saving files from a Socket.IO server. However, it does not seem to restrict file types or validate the content of the uploaded files. This could potentially allow attackers to upload malicious files, leading to code execution or other security issues.\n",
      "classification": "very promising",
      "cwe": "CWE-434",
      "function_names": [
        "receive_file"
      ],
      "filenames": [
        "lollms/data.py"
      ]
    },
    {
      "headline": "Potential Server-Side Request Forgery (SSRF) in LOLLMSConfig",
      "analysis": "The download_model function in lollms/main_config.py takes a URL as input and downloads the model from that URL. If the URL is user-controlled and not properly validated, an attacker could supply a URL pointing to internal services or resources, potentially leading to SSRF vulnerabilities.\n",
      "classification": "slightly promising",
      "cwe": "CWE-918",
      "function_names": [
        "download_model"
      ],
      "filenames": [
        "lollms/main_config.py"
      ]
    },
    {
      "headline": "Arbitrary code execution vulnerability in execute_python_code",
      "analysis": "The function execute_python_code in lollms/apps/playground/__init__.py directly executes user-supplied Python code using the exec function. This allows attackers to execute arbitrary code on the server, giving them complete control over the system.\n",
      "classification": "very promising",
      "cwe": "CWE-94",
      "function_names": [
        "execute_python_code"
      ],
      "filenames": [
        "lollms/apps/playground/__init__.py"
      ]
    }
  ],
  "scores": [
    {
      "stats": {
        "fn": 0,
        "tp": 1,
        "fp": 1
      },
      "mapping": {
        "1": "CVE-2024-4078"
      },
      "vuln_dates": {
        "CVE-2024-4078": "2024-05-16T09:15:15"
      },
      "scoring_model": "claude-3-opus-20240229",
      "type": "llm",
      "instruction_template_hash": "245ace12b6361954d0a2"
    }
  ],
  "instruction_template_hash": "10c0163db4740318a544",
  "version": "0.1.0"
}
