{
  "commit": "0d0ddd43b3b0f0995bfaa34a45f046d47860a234",
  "repo_url": "https://github.com/skyscreamer/nevado",
  "model": "gpt-4o-2024-05-13",
  "chunk_hashes": [
    "fcababaa4ada245f9f81"
  ],
  "responses": [
    {
      "content": "```yaml\nleads:\n  - headline: Cleartext Storage of Sensitive AWS Credentials\n    analysis: |\n      In `nevado-jms/src/test/java/org/skyscreamer/nevado/jms/AbstractJMSTest.java`, AWS credentials are stored in cleartext in the `aws.properties` file, which could be included in the source control by mistake and expose the credentials to unauthorized actors. This is a common issue when credentials are stored in plaintext, making it easy for attackers to gain unauthorized access.\n    cwe: CWE-312\n    function_names: []\n    filenames:\n      - nevado-jms/src/test/java/org/skyscreamer/nevado/jms/AbstractJMSTest.java\n    classification: very promising\n\n  - headline: Potential Race Condition in MockSQSQueue\n    analysis: |\n      The implementation of `MockSQSQueue` in `nevado-jms/src/main/java/org/skyscreamer/nevado/jms/connector/mock/MockSQSQueue.java` allows concurrent access to its internal message list without proper synchronization in several places. This can introduce race conditions, resulting in unpredictable behavior if multiple threads interact with the queue simultaneously.\n    cwe: CWE-362\n    function_names: []\n    filenames:\n      - nevado-jms/src/main/java/org/skyscreamer/nevado/jms/connector/mock/MockSQSQueue.java\n    classification: slightly promising\n\n  - headline: Uncontrolled Resource Consumption in BackoffSleeper\n    analysis: |\n      The `BackoffSleeper` class in `nevado-jms/src/main/java/org/skyscreamer/nevado/jms/util/BackoffSleeper.java` incrementally increases the sleep duration without any maximum limit, potentially leading to uncontrolled resource consumption. This backoff mechanism, while useful for reducing load during low activity, could lead to excessive delays and system resource usage if unbounded.\n    cwe: CWE-400\n    function_names: []\n    filenames:\n      - nevado-jms/src/main/java/org/skyscreamer/nevado/jms/util/BackoffSleeper.java\n    classification: slightly promising\n\n  - headline: SQL Injection Potential via String Properties\n    analysis: |\n      In `AbstractMessage.java`, specifically the `setStringProperty` and `getObjectProperty` methods, the handling of string properties does not inherently sanitize or validate the contents. Since string properties can be used in various contexts, including SQL queries, if these properties are concatenated into SQL commands directly, they could introduce SQL injection vulnerabilities.\n    cwe: CWE-89\n    function_names:\n      - setStringProperty\n      - getObjectProperty\n    filenames:\n      - nevado-jms/src/main/java/org/skyscreamer/nevado/jms/message/AbstractMessage.java\n    classification: very promising\n\n  - headline: Insecure Default Configuration in MockSQSConnectorFactory\n    analysis: |\n      `MockSQSConnectorFactory` provides default mock configurations which might be insecure if used in a real environment. For example, using a mock factory that does not enforce endpoint validation or security policies could lead to a false sense of security and deployment of insecure defaults in production environments.\n    cwe: CWE-1188\n    function_names: []\n    filenames:\n      - nevado-jms/src/main/java/org/skyscreamer/nevado/jms/connector/mock/MockSQSConnectorFactory.java\n    classification: slightly promising\n\n  - headline: Sensitive Information Exposure through Logging\n    analysis: |\n      Various classes in the codebase use detailed logging, such as `AbstractSQSConnector.java` and `AmazonAwsSQSConnector.java`. If sensitive information like AWS credentials, message content, or other configuration details are logged, it could expose this information to unauthorized access through log files.\n    cwe: CWE-532\n    function_names: []\n    filenames:\n      - nevado-jms/src/main/java/org/skyscreamer/nevado/jms/connector/AbstractSQSConnector.java\n      - nevado-jms/src/main/java/org/skyscreamer/nevado/jms/connector/amazonaws/AmazonAwsSQSConnector.java\n    classification: slightly promising\n\n  - headline: Insufficient Error Handling in Asynchronous Processing\n    analysis: |\n      In the `NevadoMessageConsumer` class, particularly within the `processAsyncMessage` method, error handling is limited. While exceptions are logged, they aren't always propagated correctly, which could result in asynchronous message listeners failing silently, potentially leading to message loss or processing delays.\n    cwe: CWE-755\n    function_names:\n      - processAsyncMessage\n    filenames:\n      - nevado-jms/src/main/java/org/skyscreamer/nevado/jms/NevadoMessageConsumer.java\n    classification: slightly promising\n\n  - headline: Use of Predictable Random Values for Testing\n    analysis: |\n      The `RandomData` class is used to generate test data in a predictable manner using fixed seeds. While suitable for reproducibility in tests, relying on predictable random values in any production-related code could introduce vulnerabilities related to insufficient entropy or predictability of random values.\n    cwe: CWE-338\n    function_names: []\n    filenames:\n      - nevado-jms/src/main/java/org/skyscreamer/nevado/jms/util/RandomData.java\n    classification: not promising\n```",
      "date": "2024-06-13T11:46:28.907110",
      "usage": {
        "prompt_tokens": 126689,
        "completion_tokens": 1108,
        "cost": 0.650065
      }
    }
  ],
  "leads": [
    {
      "headline": "Cleartext Storage of Sensitive AWS Credentials",
      "analysis": "In nevado-jms/src/test/java/org/skyscreamer/nevado/jms/AbstractJMSTest.java, AWS credentials are stored in cleartext in the aws.properties file, which could be included in the source control by mistake and expose the credentials to unauthorized actors. This is a common issue when credentials are stored in plaintext, making it easy for attackers to gain unauthorized access.\n",
      "classification": "very promising",
      "cwe": "CWE-312",
      "function_names": [],
      "filenames": [
        "nevado-jms/src/test/java/org/skyscreamer/nevado/jms/AbstractJMSTest.java"
      ]
    },
    {
      "headline": "Potential Race Condition in MockSQSQueue",
      "analysis": "The implementation of MockSQSQueue in nevado-jms/src/main/java/org/skyscreamer/nevado/jms/connector/mock/MockSQSQueue.java allows concurrent access to its internal message list without proper synchronization in several places. This can introduce race conditions, resulting in unpredictable behavior if multiple threads interact with the queue simultaneously.\n",
      "classification": "slightly promising",
      "cwe": "CWE-362",
      "function_names": [],
      "filenames": [
        "nevado-jms/src/main/java/org/skyscreamer/nevado/jms/connector/mock/MockSQSQueue.java"
      ]
    },
    {
      "headline": "Uncontrolled Resource Consumption in BackoffSleeper",
      "analysis": "The BackoffSleeper class in nevado-jms/src/main/java/org/skyscreamer/nevado/jms/util/BackoffSleeper.java incrementally increases the sleep duration without any maximum limit, potentially leading to uncontrolled resource consumption. This backoff mechanism, while useful for reducing load during low activity, could lead to excessive delays and system resource usage if unbounded.\n",
      "classification": "slightly promising",
      "cwe": "CWE-400",
      "function_names": [],
      "filenames": [
        "nevado-jms/src/main/java/org/skyscreamer/nevado/jms/util/BackoffSleeper.java"
      ]
    },
    {
      "headline": "SQL Injection Potential via String Properties",
      "analysis": "In AbstractMessage.java, specifically the setStringProperty and getObjectProperty methods, the handling of string properties does not inherently sanitize or validate the contents. Since string properties can be used in various contexts, including SQL queries, if these properties are concatenated into SQL commands directly, they could introduce SQL injection vulnerabilities.\n",
      "classification": "very promising",
      "cwe": "CWE-89",
      "function_names": [
        "setStringProperty",
        "getObjectProperty"
      ],
      "filenames": [
        "nevado-jms/src/main/java/org/skyscreamer/nevado/jms/message/AbstractMessage.java"
      ]
    },
    {
      "headline": "Insecure Default Configuration in MockSQSConnectorFactory",
      "analysis": "MockSQSConnectorFactory provides default mock configurations which might be insecure if used in a real environment. For example, using a mock factory that does not enforce endpoint validation or security policies could lead to a false sense of security and deployment of insecure defaults in production environments.\n",
      "classification": "slightly promising",
      "cwe": "CWE-1188",
      "function_names": [],
      "filenames": [
        "nevado-jms/src/main/java/org/skyscreamer/nevado/jms/connector/mock/MockSQSConnectorFactory.java"
      ]
    },
    {
      "headline": "Sensitive Information Exposure through Logging",
      "analysis": "Various classes in the codebase use detailed logging, such as AbstractSQSConnector.java and AmazonAwsSQSConnector.java. If sensitive information like AWS credentials, message content, or other configuration details are logged, it could expose this information to unauthorized access through log files.\n",
      "classification": "slightly promising",
      "cwe": "CWE-532",
      "function_names": [],
      "filenames": [
        "nevado-jms/src/main/java/org/skyscreamer/nevado/jms/connector/AbstractSQSConnector.java",
        "nevado-jms/src/main/java/org/skyscreamer/nevado/jms/connector/amazonaws/AmazonAwsSQSConnector.java"
      ]
    },
    {
      "headline": "Insufficient Error Handling in Asynchronous Processing",
      "analysis": "In the NevadoMessageConsumer class, particularly within the processAsyncMessage method, error handling is limited. While exceptions are logged, they aren't always propagated correctly, which could result in asynchronous message listeners failing silently, potentially leading to message loss or processing delays.\n",
      "classification": "slightly promising",
      "cwe": "CWE-755",
      "function_names": [
        "processAsyncMessage"
      ],
      "filenames": [
        "nevado-jms/src/main/java/org/skyscreamer/nevado/jms/NevadoMessageConsumer.java"
      ]
    },
    {
      "headline": "Use of Predictable Random Values for Testing",
      "analysis": "The RandomData class is used to generate test data in a predictable manner using fixed seeds. While suitable for reproducibility in tests, relying on predictable random values in any production-related code could introduce vulnerabilities related to insufficient entropy or predictability of random values.\n",
      "classification": "not promising",
      "cwe": "CWE-338",
      "function_names": [],
      "filenames": [
        "nevado-jms/src/main/java/org/skyscreamer/nevado/jms/util/RandomData.java"
      ]
    }
  ],
  "scores": [
    {
      "stats": {
        "fn": 1,
        "tp": 0,
        "fp": 2
      },
      "mapping": {},
      "vuln_dates": {
        "CVE-2023-31826": "2023-05-23T01:15:10"
      },
      "scoring_model": "claude-3-opus-20240229",
      "type": "llm",
      "instruction_template_hash": "245ace12b6361954d0a2"
    },
    {
      "stats": {
        "fn": 1,
        "tp": 0,
        "fp": 2
      },
      "mapping": {},
      "vuln_dates": {
        "CVE-2023-31826": "2023-05-23T01:15:10"
      },
      "scoring_model": "claude-3-5-sonnet-20240620",
      "type": "llm",
      "instruction_template_hash": "245ace12b6361954d0a2"
    }
  ],
  "instruction_template_hash": "10c0163db4740318a544",
  "version": "0.1.0"
}
