{
  "commit": "085bb77ca3b493eb28c9ea0930e2e39c5a7bb72d",
  "repo_url": "https://github.com/tankywoo/simiki",
  "model": "gpt-4o-2024-05-13",
  "chunk_hashes": [
    "8b62a295714d576b3f09"
  ],
  "responses": [
    {
      "content": "```yaml\nleads:\n  - headline: \"Release script allows arbitrary command execution\"\n    analysis: |\n      The release.sh script allows passing arguments directly into commands without proper validation. Specifically, the readline parameter and the pandoc command are being used in unsafe ways, which can potentially allow an attacker to execute arbitrary commands.\n    cwe: CWE-78\n    function_names: []\n    filenames:\n      - release.sh\n    classification: very promising\n\n  - headline: \"Sensitive data exposure in setup.py\"\n    analysis: |\n      The setup.py script fetches email from a configuration file and uses it directly. If this file is publicly accessible or leaked, sensitive email information can be easily exposed.\n    cwe: CWE-532\n    function_names: []\n    filenames:\n      - setup.py\n    classification: slightly promising\n\n  - headline: \"Possible code injection in test_log.py\"\n    analysis: |\n      The test_log.py file uses dynamic logging initialization, which can be exploited to run arbitrary code if the logging configurations are tampered with. This is particularly risky when logging untrusted input directly.\n    cwe: CWE-94\n    function_names:\n      - logging_init\n    filenames:\n      - tests/test_log.py\n    classification: slightly promising\n\n  - headline: \"Hardcoded sensitive data in fabfile.py\"\n    analysis: |\n      The fabfile.py script uses hardcoded credentials for FTP deployment. These hardcoded credentials can be extracted, leading to unauthorized access to the FTP server.\n    cwe: CWE-798\n    function_names:\n      - deploy_ftp\n    filenames:\n      - simiki/conf_templates/fabfile.py\n    classification: very promising\n\n  - headline: \"Directory traversal in utils.py\"\n    analysis: |\n      The utils.py file contains a 'copytree' function that does not sanitize input paths properly. This can allow directory traversal attacks where an attacker can escape to parent directories and potentially overwrite critical files.\n    cwe: CWE-22\n    function_names:\n      - copytree\n    filenames:\n      - simiki/utils.py\n    classification: very promising\n\n  - headline: \"Command injection vulnerability in watcher utility\"\n    analysis: |\n      The watcher.py script uses os.system to execute shell commands, which can be manipulated to execute arbitrary commands if any part of the command comes from user input.\n    cwe: CWE-78\n    function_names: []\n    filenames:\n      - simiki/watcher.py\n    classification: very promising\n\n  - headline: \"Potential Cross-Site Scripting (XSS) in generated HTML\"\n    analysis: |\n      The HTML templates in the themes directory do not properly escape user-generated content. This can allow Cross-Site Scripting (XSS) attacks if user input is embedded into templates without proper sanitization.\n    cwe: CWE-79\n    function_names: []\n    filenames:\n      - simiki/themes/simple/page.html\n      - simiki/themes/simple2/page.html\n    classification: very promising\n```",
      "date": "2024-06-13T17:12:17.333672",
      "usage": {
        "prompt_tokens": 28882,
        "completion_tokens": 617,
        "cost": 0.153665
      }
    }
  ],
  "leads": [
    {
      "headline": "Release script allows arbitrary command execution",
      "analysis": "The release.sh script allows passing arguments directly into commands without proper validation. Specifically, the readline parameter and the pandoc command are being used in unsafe ways, which can potentially allow an attacker to execute arbitrary commands.\n",
      "classification": "very promising",
      "cwe": "CWE-78",
      "function_names": [],
      "filenames": [
        "release.sh"
      ]
    },
    {
      "headline": "Sensitive data exposure in setup.py",
      "analysis": "The setup.py script fetches email from a configuration file and uses it directly. If this file is publicly accessible or leaked, sensitive email information can be easily exposed.\n",
      "classification": "slightly promising",
      "cwe": "CWE-532",
      "function_names": [],
      "filenames": [
        "setup.py"
      ]
    },
    {
      "headline": "Possible code injection in test_log.py",
      "analysis": "The test_log.py file uses dynamic logging initialization, which can be exploited to run arbitrary code if the logging configurations are tampered with. This is particularly risky when logging untrusted input directly.\n",
      "classification": "slightly promising",
      "cwe": "CWE-94",
      "function_names": [
        "logging_init"
      ],
      "filenames": [
        "tests/test_log.py"
      ]
    },
    {
      "headline": "Hardcoded sensitive data in fabfile.py",
      "analysis": "The fabfile.py script uses hardcoded credentials for FTP deployment. These hardcoded credentials can be extracted, leading to unauthorized access to the FTP server.\n",
      "classification": "very promising",
      "cwe": "CWE-798",
      "function_names": [
        "deploy_ftp"
      ],
      "filenames": [
        "simiki/conf_templates/fabfile.py"
      ]
    },
    {
      "headline": "Directory traversal in utils.py",
      "analysis": "The utils.py file contains a 'copytree' function that does not sanitize input paths properly. This can allow directory traversal attacks where an attacker can escape to parent directories and potentially overwrite critical files.\n",
      "classification": "very promising",
      "cwe": "CWE-22",
      "function_names": [
        "copytree"
      ],
      "filenames": [
        "simiki/utils.py"
      ]
    },
    {
      "headline": "Command injection vulnerability in watcher utility",
      "analysis": "The watcher.py script uses os.system to execute shell commands, which can be manipulated to execute arbitrary commands if any part of the command comes from user input.\n",
      "classification": "very promising",
      "cwe": "CWE-78",
      "function_names": [],
      "filenames": [
        "simiki/watcher.py"
      ]
    },
    {
      "headline": "Potential Cross-Site Scripting (XSS) in generated HTML",
      "analysis": "The HTML templates in the themes directory do not properly escape user-generated content. This can allow Cross-Site Scripting (XSS) attacks if user input is embedded into templates without proper sanitization.\n",
      "classification": "very promising",
      "cwe": "CWE-79",
      "function_names": [],
      "filenames": [
        "simiki/themes/simple/page.html",
        "simiki/themes/simple2/page.html"
      ]
    }
  ],
  "scores": [
    {
      "stats": {
        "fn": 1,
        "tp": 1,
        "fp": 4
      },
      "mapping": {
        "4": "CVE-2020-19000"
      },
      "vuln_dates": {
        "CVE-2020-19001": "2021-08-27T19:15:07",
        "CVE-2020-19000": "2021-08-27T19:15:07"
      },
      "scoring_model": "claude-3-opus-20240229",
      "type": "llm",
      "instruction_template_hash": "245ace12b6361954d0a2"
    },
    {
      "stats": {
        "fn": 0,
        "tp": 2,
        "fp": 3
      },
      "mapping": {
        "3": "CVE-2020-19001",
        "4": "CVE-2020-19000"
      },
      "vuln_dates": {
        "CVE-2020-19001": "2021-08-27T19:15:07",
        "CVE-2020-19000": "2021-08-27T19:15:07"
      },
      "scoring_model": "claude-3-5-sonnet-20240620",
      "type": "llm",
      "instruction_template_hash": "245ace12b6361954d0a2"
    }
  ],
  "instruction_template_hash": "10c0163db4740318a544",
  "version": "0.1.0"
}
