{
  "commit": "42859fcee2b5061d3787cb43f04c7007f0b8bde1",
  "repo_url": "https://github.com/nervosnetwork/molecule",
  "model": "claude-3-sonnet-20240229",
  "chunk_hashes": [
    "9293f2889602bf17ecaa"
  ],
  "responses": [
    {
      "content": "Here is the YAML output identifying potential security vulnerabilities in the provided codebase:\n\n```yaml\nleads:\n  - headline: Potential buffer overflow vulnerability\n    analysis: |\n      The `mol_builder_set_by_offset` function copies `length` bytes from `data_ptr` to `builder->data_ptr+offset` without checking if the destination buffer has sufficient capacity. This could potentially lead to a buffer overflow if the `offset` plus `length` exceeds the allocated size of `builder->data_ptr`.\n    cwe: CWE-120\n    function_names:\n      - mol_builder_set_by_offset\n    filenames:\n      - bindings/c/include/molecule_builder.h\n    classification: very promising\n\n  - headline: Potential integer overflow vulnerability\n    analysis: |\n      The `mol_builder_initialize_with_capacity` function allocates memory for `builder->data_ptr` and `builder->number_ptr` based on the provided `data_capacity` and `number_capacity` values, respectively. However, there is no check for integer overflows during the allocation, which could potentially lead to heap corruption or other memory safety issues if the input values are very large.\n    cwe: CWE-190\n    function_names:\n      - mol_builder_initialize_with_capacity\n    filenames:\n      - bindings/c/include/molecule_builder.h\n    classification: very promising\n\n  - headline: Potential use of uninitialized memory\n    analysis: |\n      The `mol_builder_initialize_fixed_size` function initializes `builder->data_ptr` with zero bytes if `fixed_size` is non-zero, but it does not initialize `builder->number_ptr`. This could potentially lead to undefined behavior if `builder->number_ptr` is later used without being properly initialized.\n    cwe: CWE-908\n    function_names:\n      - mol_builder_initialize_fixed_size\n    filenames:\n      - bindings/c/include/molecule_builder.h\n    classification: very promising\n\n  - headline: Potential double free vulnerability\n    analysis: |\n      The `mol_dynvec_builder_finalize` function frees the `builder.data_ptr` and `builder.number_ptr` using `mol_builder_discard`. However, if an error occurs during the allocation of `res.seg.ptr`, the function could potentially return without freeing the previously allocated memory, leading to a double free vulnerability.\n    cwe: CWE-415\n    function_names:\n      - mol_dynvec_builder_finalize\n    filenames:\n      - bindings/c/include/molecule_builder.h\n    classification: slightly promising\n\n  - headline: Potential buffer over-read vulnerability\n    analysis: |\n      The `mol_unpack_number` function reads 4 bytes from `src` into a `uint32_t` variable without checking if `src` has at least 4 bytes available. This could potentially lead to a buffer over-read if the input buffer is shorter than 4 bytes.\n    cwe: CWE-125\n    function_names:\n      - mol_unpack_number\n    filenames:\n      - bindings/c/include/molecule_reader.h\n    classification: very promising\n\n  - headline: Potential null pointer dereference\n    analysis: |\n      Several functions in `molecule_builder.h` and `molecule_reader.h` dereference pointers without checking for null values. For example, `mol_pack_number` dereferences `dst` without checking if it is null. This could potentially lead to a null pointer dereference and undefined behavior if the input pointers are null.\n    cwe: CWE-476\n    function_names: []\n    filenames:\n      - bindings/c/include/molecule_builder.h\n      - bindings/c/include/molecule_reader.h\n    classification: very promising\n\n  - headline: Potential integer underflow vulnerability\n    analysis: |\n      The `mol_dynvec_slice_by_index` function retrieves the length of a dynamic vector by subtracting 1 from the value at `input->ptr + MOL_NUM_T_SIZE`. However, there is no check to ensure that the value is greater than 0 before the subtraction, which could potentially lead to an integer underflow if the value is 0 or a very small number.\n    cwe: CWE-191\n    function_names:\n      - mol_dynvec_slice_by_index\n    filenames:\n      - bindings/c/include/molecule_reader.h\n    classification: slightly promising\n\n  - headline: Potential integer truncation vulnerability\n    analysis: |\n      The `mol_table_actual_field_count` function calls `mol_dynvec_length` to get the number of fields in a table. However, `mol_dynvec_length` returns a `mol_num_t` value, which is a `uint32_t`. If the actual number of fields exceeds the maximum value of a `uint32_t`, the return value will be truncated, leading to potential integer truncation vulnerabilities.\n    cwe: CWE-197\n    function_names:\n      - mol_table_actual_field_count\n    filenames:\n      - bindings/c/include/molecule_reader.h\n    classification: slightly promising\n\n  - headline: Potential out-of-bounds read vulnerability\n    analysis: |\n      The `mol_fixvec_slice_raw_bytes` function returns a `mol_seg_t` structure with `seg.ptr` pointing to `input->ptr + MOL_NUM_T_SIZE` and `seg.size` set to the value at `input->ptr`. However, there is no check to ensure that the value at `input->ptr` does not exceed the size of the input buffer, which could potentially lead to an out-of-bounds read if the value is too large.\n    cwe: CWE-125\n    function_names:\n      - mol_fixvec_slice_raw_bytes\n    filenames:\n      - bindings/c/include/molecule_reader.h\n    classification: very promising\n```\n\nThis analysis covers potential vulnerabilities such as buffer overflows, integer overflows/underflows, use of uninitialized memory, double free vulnerabilities, null pointer dereferences, integer truncation vulnerabilities, and out-of-bounds reads. The classification is based on the severity and likelihood of exploitation for each potential vulnerability.\n\nNote that this analysis is based solely on the provided code and may not cover all potential vulnerabilities or accurately assess the risk level. A more comprehensive security review, including testing and dynamic analysis, would be recommended for a thorough assessment of the codebase's security posture.",
      "date": "2024-06-14T14:55:36.899939",
      "usage": {
        "prompt_tokens": 13135,
        "completion_tokens": 1562,
        "cost": 0.062835
      }
    }
  ],
  "leads": [
    {
      "headline": "Potential buffer overflow vulnerability",
      "analysis": "The mol_builder_set_by_offset function copies length bytes from data_ptr to builder->data_ptr+offset without checking if the destination buffer has sufficient capacity. This could potentially lead to a buffer overflow if the offset plus length exceeds the allocated size of builder->data_ptr.\n",
      "classification": "very promising",
      "cwe": "CWE-120",
      "function_names": [
        "mol_builder_set_by_offset"
      ],
      "filenames": [
        "bindings/c/include/molecule_builder.h"
      ]
    },
    {
      "headline": "Potential integer overflow vulnerability",
      "analysis": "The mol_builder_initialize_with_capacity function allocates memory for builder->data_ptr and builder->number_ptr based on the provided data_capacity and number_capacity values, respectively. However, there is no check for integer overflows during the allocation, which could potentially lead to heap corruption or other memory safety issues if the input values are very large.\n",
      "classification": "very promising",
      "cwe": "CWE-190",
      "function_names": [
        "mol_builder_initialize_with_capacity"
      ],
      "filenames": [
        "bindings/c/include/molecule_builder.h"
      ]
    },
    {
      "headline": "Potential use of uninitialized memory",
      "analysis": "The mol_builder_initialize_fixed_size function initializes builder->data_ptr with zero bytes if fixed_size is non-zero, but it does not initialize builder->number_ptr. This could potentially lead to undefined behavior if builder->number_ptr is later used without being properly initialized.\n",
      "classification": "very promising",
      "cwe": "CWE-908",
      "function_names": [
        "mol_builder_initialize_fixed_size"
      ],
      "filenames": [
        "bindings/c/include/molecule_builder.h"
      ]
    },
    {
      "headline": "Potential double free vulnerability",
      "analysis": "The mol_dynvec_builder_finalize function frees the builder.data_ptr and builder.number_ptr using mol_builder_discard. However, if an error occurs during the allocation of res.seg.ptr, the function could potentially return without freeing the previously allocated memory, leading to a double free vulnerability.\n",
      "classification": "slightly promising",
      "cwe": "CWE-415",
      "function_names": [
        "mol_dynvec_builder_finalize"
      ],
      "filenames": [
        "bindings/c/include/molecule_builder.h"
      ]
    },
    {
      "headline": "Potential buffer over-read vulnerability",
      "analysis": "The mol_unpack_number function reads 4 bytes from src into a uint32_t variable without checking if src has at least 4 bytes available. This could potentially lead to a buffer over-read if the input buffer is shorter than 4 bytes.\n",
      "classification": "very promising",
      "cwe": "CWE-125",
      "function_names": [
        "mol_unpack_number"
      ],
      "filenames": [
        "bindings/c/include/molecule_reader.h"
      ]
    },
    {
      "headline": "Potential null pointer dereference",
      "analysis": "Several functions in molecule_builder.h and molecule_reader.h dereference pointers without checking for null values. For example, mol_pack_number dereferences dst without checking if it is null. This could potentially lead to a null pointer dereference and undefined behavior if the input pointers are null.\n",
      "classification": "very promising",
      "cwe": "CWE-476",
      "function_names": [],
      "filenames": [
        "bindings/c/include/molecule_builder.h",
        "bindings/c/include/molecule_reader.h"
      ]
    },
    {
      "headline": "Potential integer underflow vulnerability",
      "analysis": "The mol_dynvec_slice_by_index function retrieves the length of a dynamic vector by subtracting 1 from the value at input->ptr + MOL_NUM_T_SIZE. However, there is no check to ensure that the value is greater than 0 before the subtraction, which could potentially lead to an integer underflow if the value is 0 or a very small number.\n",
      "classification": "slightly promising",
      "cwe": "CWE-191",
      "function_names": [
        "mol_dynvec_slice_by_index"
      ],
      "filenames": [
        "bindings/c/include/molecule_reader.h"
      ]
    },
    {
      "headline": "Potential integer truncation vulnerability",
      "analysis": "The mol_table_actual_field_count function calls mol_dynvec_length to get the number of fields in a table. However, mol_dynvec_length returns a mol_num_t value, which is a uint32_t. If the actual number of fields exceeds the maximum value of a uint32_t, the return value will be truncated, leading to potential integer truncation vulnerabilities.\n",
      "classification": "slightly promising",
      "cwe": "CWE-197",
      "function_names": [
        "mol_table_actual_field_count"
      ],
      "filenames": [
        "bindings/c/include/molecule_reader.h"
      ]
    },
    {
      "headline": "Potential out-of-bounds read vulnerability",
      "analysis": "The mol_fixvec_slice_raw_bytes function returns a mol_seg_t structure with seg.ptr pointing to input->ptr + MOL_NUM_T_SIZE and seg.size set to the value at input->ptr. However, there is no check to ensure that the value at input->ptr does not exceed the size of the input buffer, which could potentially lead to an out-of-bounds read if the value is too large.\n",
      "classification": "very promising",
      "cwe": "CWE-125",
      "function_names": [
        "mol_fixvec_slice_raw_bytes"
      ],
      "filenames": [
        "bindings/c/include/molecule_reader.h"
      ]
    }
  ],
  "scores": [
    {
      "stats": {
        "fn": 1,
        "tp": 0,
        "fp": 6
      },
      "mapping": {},
      "vuln_dates": {
        "CVE-2021-45697": "2021-12-27T00:15:09"
      },
      "scoring_model": "claude-3-opus-20240229",
      "type": "llm",
      "instruction_template_hash": "245ace12b6361954d0a2"
    },
    {
      "stats": {
        "fn": 0,
        "tp": 1,
        "fp": 5
      },
      "mapping": {
        "5": "CVE-2021-45697"
      },
      "vuln_dates": {
        "CVE-2021-45697": "2021-12-27T00:15:09"
      },
      "scoring_model": "claude-3-5-sonnet-20240620",
      "type": "llm",
      "instruction_template_hash": "245ace12b6361954d0a2"
    }
  ],
  "instruction_template_hash": "10c0163db4740318a544",
  "version": "0.1.0"
}
