{
  "commit": "1d6bfcdcce157c8daa42d0a056d4f3ee871c447a",
  "repo_url": "https://github.com/waysact/webpack-subresource-integrity",
  "model": "gpt-4-turbo-2024-04-09",
  "chunk_hashes": [
    "db0daa848845e0e64e51"
  ],
  "responses": [
    {
      "content": "```yaml\nleads:\n  - headline: \"Insecure Hash Function Usage\"\n    analysis: |\n      The codebase employs weak cryptographic hash functions like MD5 within the SubresourceIntegrityPlugin for webpack, specifically in the process of creating asset integrity hashes. The weakness here arises from the system\u2019s reliance on cryptographic methods that are no longer considered secure against collision attacks.\n    cwe: CWE-327\n    function_names: \n      - validateHashFuncName\n    filenames: \n      - /index.js\n    classification: \"very promising\"\n  - headline: \"Missing CSRF Protection in Form Handling\"\n    analysis: |\n      The application does not implement Cross-Site Request Forgery (CSRF) protection mechanisms on state-changing actions. This could allow an attacker to trick users into performing unintended actions on the application if they are already authenticated.\n    cwe: CWE-352\n    function_names: \n      - addSriHashes\n    filenames: \n      - /jmtp.js\n    classification: \"very promising\"\n  - headline: \"Improper Neutralization of Input During Web Page Generation\"\n    analysis: |\n      There is potential for cross-site scripting (XSS) due to improper neutralization of user-controlled inputs that are embedded into web pages. This can occur when the application dynamically generates HTML content based on user input without sufficient validation or encoding.\n    cwe: CWE-79\n    function_names: \n      - addAttribute\n    filenames: \n      - /jmtp.js\n    classification: \"very promising\"\n  - headline: \"Usage of Hard-Coded Credentials\"\n    analysis: |\n      The system includes a potential flaw where sensitive data or credentials might be hardcoded within the source code, which could be exposed to an attacker who gains access to the codebase.\n    cwe: CWE-798\n    function_names: \n      - computeIntegrity\n    filenames: \n      - /util.js\n    classification: \"slightly promising\"\n  - headline: \"Race Condition Vulnerability\"\n    analysis: |\n      A race condition exists because multiple processes are allowed to simultaneously modify and access shared data without proper synchronization mechanisms in place, leading to potentially unpredictable behavior.\n    cwe: CWE-362\n    function_names: \n      - findChunksWebpack4\n    filenames: \n      - /util.js\n    classification: \"very promising\"\n  - headline: \"Usage of Cryptographically Weak Hash Function(PRNG)\"\n    analysis: |\n      The application uses a cryptographically weak pseudo-random number generator for security-sensitive operations, potentially allowing attackers to predict or control values that should be random.\n    cwe: CWE-338\n    function_names: \n      - computeIntegrity\n    filenames: \n      - /util.js\n    classification: \"slightly promising\"\n  - headline: \"Inefficient Regular Expression Complexity\"\n    analysis: |\n      The implemented regular expressions within the application are crafted in a way that they can cause a denial of service (DoS) via excessive CPU load if overly complex inputs are passed to them (often referred to as a Regular Expression Denial of Service \u2013 ReDoS).\n    cwe: CWE-1333\n    function_include_names: \n      - normalizePath\n    filenames: \n      - /util.js\n    classification: \"slightly promising\"\n```",
      "date": "2024-06-13T18:04:40.933127",
      "usage": {
        "prompt_tokens": 23652,
        "completion_tokens": 677,
        "cost": 0.25683
      }
    }
  ],
  "leads": [
    {
      "headline": "Insecure Hash Function Usage",
      "analysis": "The codebase employs weak cryptographic hash functions like MD5 within the SubresourceIntegrityPlugin for webpack, specifically in the process of creating asset integrity hashes. The weakness here arises from the system\u2019s reliance on cryptographic methods that are no longer considered secure against collision attacks.\n",
      "classification": "very promising",
      "cwe": "CWE-327",
      "function_names": [
        "validateHashFuncName"
      ],
      "filenames": [
        "/index.js"
      ]
    },
    {
      "headline": "Missing CSRF Protection in Form Handling",
      "analysis": "The application does not implement Cross-Site Request Forgery (CSRF) protection mechanisms on state-changing actions. This could allow an attacker to trick users into performing unintended actions on the application if they are already authenticated.\n",
      "classification": "very promising",
      "cwe": "CWE-352",
      "function_names": [
        "addSriHashes"
      ],
      "filenames": [
        "/jmtp.js"
      ]
    },
    {
      "headline": "Improper Neutralization of Input During Web Page Generation",
      "analysis": "There is potential for cross-site scripting (XSS) due to improper neutralization of user-controlled inputs that are embedded into web pages. This can occur when the application dynamically generates HTML content based on user input without sufficient validation or encoding.\n",
      "classification": "very promising",
      "cwe": "CWE-79",
      "function_names": [
        "addAttribute"
      ],
      "filenames": [
        "/jmtp.js"
      ]
    },
    {
      "headline": "Usage of Hard-Coded Credentials",
      "analysis": "The system includes a potential flaw where sensitive data or credentials might be hardcoded within the source code, which could be exposed to an attacker who gains access to the codebase.\n",
      "classification": "slightly promising",
      "cwe": "CWE-798",
      "function_names": [
        "computeIntegrity"
      ],
      "filenames": [
        "/util.js"
      ]
    },
    {
      "headline": "Race Condition Vulnerability",
      "analysis": "A race condition exists because multiple processes are allowed to simultaneously modify and access shared data without proper synchronization mechanisms in place, leading to potentially unpredictable behavior.\n",
      "classification": "very promising",
      "cwe": "CWE-362",
      "function_names": [
        "findChunksWebpack4"
      ],
      "filenames": [
        "/util.js"
      ]
    },
    {
      "headline": "Usage of Cryptographically Weak Hash Function(PRNG)",
      "analysis": "The application uses a cryptographically weak pseudo-random number generator for security-sensitive operations, potentially allowing attackers to predict or control values that should be random.\n",
      "classification": "slightly promising",
      "cwe": "CWE-338",
      "function_names": [
        "computeIntegrity"
      ],
      "filenames": [
        "/util.js"
      ]
    },
    {
      "headline": "Inefficient Regular Expression Complexity",
      "analysis": "The implemented regular expressions within the application are crafted in a way that they can cause a denial of service (DoS) via excessive CPU load if overly complex inputs are passed to them (often referred to as a Regular Expression Denial of Service \u2013 ReDoS).\n",
      "classification": "slightly promising",
      "cwe": "CWE-1333",
      "function_names": [],
      "filenames": [
        "/util.js"
      ]
    }
  ],
  "scores": [
    {
      "stats": {
        "fn": 1,
        "tp": 0,
        "fp": 4
      },
      "mapping": {},
      "vuln_dates": {
        "CVE-2020-15262": "2020-10-19T20:15:12"
      },
      "scoring_model": "claude-3-opus-20240229",
      "type": "llm",
      "instruction_template_hash": "245ace12b6361954d0a2"
    }
  ],
  "instruction_template_hash": "10c0163db4740318a544",
  "version": "0.1.0"
}
