{
  "commit": "34e86f0d4bccee3232c0d1a6aff59a45cd04f1b9",
  "repo_url": "https://github.com/jenkinsci/dingding-notifications-plugin",
  "model": "claude-3-haiku-20240307",
  "chunk_hashes": [
    "c174494d01b51c2e0467"
  ],
  "responses": [
    {
      "content": "```yaml\nleads:\n  - headline: Improper Neutralization of Special Elements used in an SQL Command ('SQL Injection')\n    analysis: |\n      The DingdingServiceImpl class contains a method called sendLinkMessage() that constructs a JSON object and sends it to the Ding Talk API. The JSON object contains a \"link\" field that includes user-controlled data from the build object, such as the build URL and project/job name. If this data is not properly sanitized, it could lead to SQL injection vulnerabilities.\n    cwe: CWE-89\n    function_names:\n      - sendLinkMessage\n    filenames:\n      - src/main/java/com/ztbsuper/dingding/DingdingServiceImpl.java\n    classification: slightly promising\n\n  - headline: Improper Neutralization of Special Elements used in an OS Command ('OS Command Injection')\n    analysis: |\n      The DingdingServiceImpl class uses the Apache HttpClient library to send HTTP requests to the Ding Talk API. If the Jenkins URL or any other user-controlled data is not properly sanitized, it could lead to OS command injection vulnerabilities.\n    cwe: CWE-78\n    function_names:\n      - getHttpClient\n    filenames:\n      - src/main/java/com/ztbsuper/dingding/DingdingServiceImpl.java\n    classification: slightly promising\n\n  - headline: Improper Neutralization of Special Elements used in an Expression Language Statement ('Expression Language Injection')\n    analysis: |\n      The DingdingNotifier class uses Stapler (the Jenkins web framework) to handle user input, such as the Jenkins URL, access token, and notification settings. If these values are not properly sanitized, it could lead to expression language injection vulnerabilities.\n    cwe: CWE-917\n    function_names:\n      - DingdingNotifier\n      - DingdingNotifierDescriptor\n    filenames:\n      - src/main/java/com/ztbsuper/dingding/DingdingNotifier.java\n    classification: slightly promising\n\n  - headline: Improper Neutralization of Argument Delimiters in a Command ('Argument Injection')\n    analysis: |\n      The DingTalkNotifier class uses the DingTalkClient library to send messages to the Ding Talk API. If the access token, notify people, message, or any other user-controlled data is not properly sanitized, it could lead to argument injection vulnerabilities.\n    cwe: CWE-88\n    function_names:\n      - sendMessage\n    filenames:\n      - src/main/java/com/ztbsuper/dingtalk/DingTalkNotifier.java\n    classification: slightly promising\n\n  - headline: Improper Input Validation\n    analysis: |\n      The codebase does not consistently validate user input, such as the Jenkins URL, access token, and notification settings. This could lead to a variety of vulnerabilities, including SQL injection, OS command injection, and expression language injection.\n    cwe: CWE-20\n    function_names: []\n    filenames:\n      - src/main/java/com/ztbsuper/dingding/DingdingServiceImpl.java\n      - src/main/java/com/ztbsuper/dingding/DingdingNotifier.java\n      - src/main/java/com/ztbsuper/dingtalk/DingTalkNotifier.java\n    classification: slightly promising\n\n  - headline: Improper Encoding or Escaping of Output\n    analysis: |\n      The codebase does not consistently encode or escape user-controlled data before using it in output, such as the build URL and project/job name. This could lead to cross-site scripting (XSS) vulnerabilities.\n    cwe: CWE-116\n    function_names: []\n    filenames:\n      - src/main/java/com/ztbsuper/dingding/DingdingServiceImpl.java\n      - src/main/java/com/ztbsuper/dingtalk/DingTalkNotifier.java\n    classification: slightly promising\n\n  - headline: Improper Certificate Validation\n    analysis: |\n      The codebase uses the Apache HttpClient library to make HTTP requests to the Ding Talk API, but it does not appear to perform any certificate validation. This could lead to man-in-the-middle attacks and other vulnerabilities.\n    cwe: CWE-295\n    function_names:\n      - getHttpClient\n    filenames:\n      - src/main/java/com/ztbsuper/dingding/DingdingServiceImpl.java\n    classification: slightly promising\n```",
      "date": "2024-06-12T18:18:54.112623",
      "usage": {
        "prompt_tokens": 8046,
        "completion_tokens": 1119,
        "cost": 0.00341025
      }
    }
  ],
  "leads": [
    {
      "headline": "Improper Neutralization of Special Elements used in an SQL Command ('SQL Injection')",
      "analysis": "The DingdingServiceImpl class contains a method called sendLinkMessage() that constructs a JSON object and sends it to the Ding Talk API. The JSON object contains a \"link\" field that includes user-controlled data from the build object, such as the build URL and project/job name. If this data is not properly sanitized, it could lead to SQL injection vulnerabilities.\n",
      "classification": "slightly promising",
      "cwe": "CWE-89",
      "function_names": [
        "sendLinkMessage"
      ],
      "filenames": [
        "src/main/java/com/ztbsuper/dingding/DingdingServiceImpl.java"
      ]
    },
    {
      "headline": "Improper Neutralization of Special Elements used in an OS Command ('OS Command Injection')",
      "analysis": "The DingdingServiceImpl class uses the Apache HttpClient library to send HTTP requests to the Ding Talk API. If the Jenkins URL or any other user-controlled data is not properly sanitized, it could lead to OS command injection vulnerabilities.\n",
      "classification": "slightly promising",
      "cwe": "CWE-78",
      "function_names": [
        "getHttpClient"
      ],
      "filenames": [
        "src/main/java/com/ztbsuper/dingding/DingdingServiceImpl.java"
      ]
    },
    {
      "headline": "Improper Neutralization of Special Elements used in an Expression Language Statement ('Expression Language Injection')",
      "analysis": "The DingdingNotifier class uses Stapler (the Jenkins web framework) to handle user input, such as the Jenkins URL, access token, and notification settings. If these values are not properly sanitized, it could lead to expression language injection vulnerabilities.\n",
      "classification": "slightly promising",
      "cwe": "CWE-917",
      "function_names": [
        "DingdingNotifier",
        "DingdingNotifierDescriptor"
      ],
      "filenames": [
        "src/main/java/com/ztbsuper/dingding/DingdingNotifier.java"
      ]
    },
    {
      "headline": "Improper Neutralization of Argument Delimiters in a Command ('Argument Injection')",
      "analysis": "The DingTalkNotifier class uses the DingTalkClient library to send messages to the Ding Talk API. If the access token, notify people, message, or any other user-controlled data is not properly sanitized, it could lead to argument injection vulnerabilities.\n",
      "classification": "slightly promising",
      "cwe": "CWE-88",
      "function_names": [
        "sendMessage"
      ],
      "filenames": [
        "src/main/java/com/ztbsuper/dingtalk/DingTalkNotifier.java"
      ]
    },
    {
      "headline": "Improper Input Validation",
      "analysis": "The codebase does not consistently validate user input, such as the Jenkins URL, access token, and notification settings. This could lead to a variety of vulnerabilities, including SQL injection, OS command injection, and expression language injection.\n",
      "classification": "slightly promising",
      "cwe": "CWE-20",
      "function_names": [],
      "filenames": [
        "src/main/java/com/ztbsuper/dingding/DingdingServiceImpl.java",
        "src/main/java/com/ztbsuper/dingding/DingdingNotifier.java",
        "src/main/java/com/ztbsuper/dingtalk/DingTalkNotifier.java"
      ]
    },
    {
      "headline": "Improper Encoding or Escaping of Output",
      "analysis": "The codebase does not consistently encode or escape user-controlled data before using it in output, such as the build URL and project/job name. This could lead to cross-site scripting (XSS) vulnerabilities.\n",
      "classification": "slightly promising",
      "cwe": "CWE-116",
      "function_names": [],
      "filenames": [
        "src/main/java/com/ztbsuper/dingding/DingdingServiceImpl.java",
        "src/main/java/com/ztbsuper/dingtalk/DingTalkNotifier.java"
      ]
    },
    {
      "headline": "Improper Certificate Validation",
      "analysis": "The codebase uses the Apache HttpClient library to make HTTP requests to the Ding Talk API, but it does not appear to perform any certificate validation. This could lead to man-in-the-middle attacks and other vulnerabilities.\n",
      "classification": "slightly promising",
      "cwe": "CWE-295",
      "function_names": [
        "getHttpClient"
      ],
      "filenames": [
        "src/main/java/com/ztbsuper/dingding/DingdingServiceImpl.java"
      ]
    }
  ],
  "scores": [
    {
      "stats": {
        "fn": 1,
        "tp": 0,
        "fp": 0
      },
      "mapping": {},
      "vuln_dates": {
        "CVE-2019-10433": "2019-10-01T14:15:28"
      },
      "scoring_model": "claude-3-opus-20240229",
      "type": "llm",
      "instruction_template_hash": "245ace12b6361954d0a2"
    },
    {
      "stats": {
        "fn": 1,
        "tp": 0,
        "fp": 0
      },
      "mapping": {},
      "vuln_dates": {
        "CVE-2019-10433": "2019-10-01T14:15:28"
      },
      "scoring_model": "claude-3-5-sonnet-20240620",
      "type": "llm",
      "instruction_template_hash": "245ace12b6361954d0a2"
    }
  ],
  "instruction_template_hash": "10c0163db4740318a544",
  "version": "0.1.0"
}
