{
  "commit": "14c85144f2f1c45f938ce5257f30311fa1b11480",
  "repo_url": "https://github.com/csaf-tools/cvrf-csaf-converter",
  "model": "gpt-4-turbo-2024-04-09",
  "chunk_hashes": [
    "9dba9213b8fe8389a18f"
  ],
  "responses": [
    {
      "content": "```yaml\nleads:\n  - headline: \"Command Injection via Git Command in Version Extraction\"\n    analysis: |\n      The use of the subprocess module to execute a git command for version extraction in setup.py allows potential remote code execution if the function can be influenced by external input. By manipulating the inputs that form the git command string, an attacker could inject additional commands.\n    cwe: CWE-78\n    function_names:\n      - get_version\n    filenames:\n      - \"./setup.py\"\n    classification: \"very promising\"\n\n  - headline: \"Hardcoded package version retrieval may cause inconsistency\"\n    analysis: |\n      The method '__version__ = get_distribution(__name__).version' in cvrf2csaf/__init__.py can cause inconsistencies and potential failures if the package version does not exist, particularly if the software is not properly installed or if there are issues with the package's distribution infrastructure. This might not directly lead to a security vulnerability but can undermine the reliability and integrity of the application.\n    cwe: CWE-706\n    function_names:\n      - __init__\n    filenames:\n      - \"./cvrf2csaf/__init__.py\"\n    classification: \"slightly promising\"\n\n  - headline: \"Use of Insecure Temporary Files\"\n    analysis: |\n      The handle_boolean_config_values function from cvrf2csaf/common/utils.py does not ensure the directory for storing configurations exists or is secure prior to accessing it. This could lead to the exposure or manipulation of sensitive configuration files if an attacker has access to the filesystem, and can create or manipulate files in the expected directories.\n    cwe: CWE-378\n    function_names:\n      - handle_boolean_headline\n    filenames:\n      - \"./cvrf2csaf/common/utils.py\"\n    classification: \"slightly promising\"\n\n  - headline: \"Potential Information Exposure Through Error Messages\"\n    analysis: |\n      Various functions across the codebase use detailed error messages that include system file paths and internal state information, which is logged or returned upon catching exceptions. Should these error messages be exposed to an end-user, they could be leveraged by an attacker to gain insights into the internal workings or system structure, potentially facilitating further attacks.\n    cwe: CWE-209\n    function_names:\n      - critical_exit\n      - handle_boolean_config_values\n    filenames:\n      - \"./cvrf2csaf/common/utils.py\"\n    classification: \"slightly promising\"\n\n  - headline: \"Excessive Data Exposure Through Debug Information\"\n    analysis: |\n      Logging configuration in cvrf2csaf/cvrf2csaf.py is set to include potentially sensitive information, with a verbosity level that could expose internal state details like system paths, operational parameters, and process outputs in log files. If an attacker gains access to these logs, it could provide them with the ability to undertake more informed malicious activities against the system.\n    cwe: CWE-215\n    function_names:\n      - DocumentHandler\n    filenames:\n      - \"./cvrf2csaf/cvrf2csaf.py\"\n    classification: \"very promising\"\n```",
      "date": "2024-06-12T15:48:51.584439",
      "usage": {
        "prompt_tokens": 16798,
        "completion_tokens": 630,
        "cost": 0.18688
      }
    }
  ],
  "leads": [
    {
      "headline": "Command Injection via Git Command in Version Extraction",
      "analysis": "The use of the subprocess module to execute a git command for version extraction in setup.py allows potential remote code execution if the function can be influenced by external input. By manipulating the inputs that form the git command string, an attacker could inject additional commands.\n",
      "classification": "very promising",
      "cwe": "CWE-78",
      "function_names": [
        "get_version"
      ],
      "filenames": [
        "./setup.py"
      ]
    },
    {
      "headline": "Hardcoded package version retrieval may cause inconsistency",
      "analysis": "The method '__version__ = get_distribution(__name__).version' in cvrf2csaf/__init__.py can cause inconsistencies and potential failures if the package version does not exist, particularly if the software is not properly installed or if there are issues with the package's distribution infrastructure. This might not directly lead to a security vulnerability but can undermine the reliability and integrity of the application.\n",
      "classification": "slightly promising",
      "cwe": "CWE-706",
      "function_names": [
        "__init__"
      ],
      "filenames": [
        "./cvrf2csaf/__init__.py"
      ]
    },
    {
      "headline": "Use of Insecure Temporary Files",
      "analysis": "The handle_boolean_config_values function from cvrf2csaf/common/utils.py does not ensure the directory for storing configurations exists or is secure prior to accessing it. This could lead to the exposure or manipulation of sensitive configuration files if an attacker has access to the filesystem, and can create or manipulate files in the expected directories.\n",
      "classification": "slightly promising",
      "cwe": "CWE-378",
      "function_names": [
        "handle_boolean_headline"
      ],
      "filenames": [
        "./cvrf2csaf/common/utils.py"
      ]
    },
    {
      "headline": "Potential Information Exposure Through Error Messages",
      "analysis": "Various functions across the codebase use detailed error messages that include system file paths and internal state information, which is logged or returned upon catching exceptions. Should these error messages be exposed to an end-user, they could be leveraged by an attacker to gain insights into the internal workings or system structure, potentially facilitating further attacks.\n",
      "classification": "slightly promising",
      "cwe": "CWE-209",
      "function_names": [
        "critical_exit",
        "handle_boolean_config_values"
      ],
      "filenames": [
        "./cvrf2csaf/common/utils.py"
      ]
    },
    {
      "headline": "Excessive Data Exposure Through Debug Information",
      "analysis": "Logging configuration in cvrf2csaf/cvrf2csaf.py is set to include potentially sensitive information, with a verbosity level that could expose internal state details like system paths, operational parameters, and process outputs in log files. If an attacker gains access to these logs, it could provide them with the ability to undertake more informed malicious activities against the system.\n",
      "classification": "very promising",
      "cwe": "CWE-215",
      "function_names": [
        "DocumentHandler"
      ],
      "filenames": [
        "./cvrf2csaf/cvrf2csaf.py"
      ]
    }
  ],
  "scores": [
    {
      "stats": {
        "fn": 1,
        "tp": 0,
        "fp": 2
      },
      "mapping": {},
      "vuln_dates": {
        "CVE-2022-27193": "2022-03-15T05:15:07"
      },
      "scoring_model": "claude-3-opus-20240229",
      "type": "llm",
      "instruction_template_hash": "245ace12b6361954d0a2"
    }
  ],
  "instruction_template_hash": "10c0163db4740318a544",
  "version": "0.1.0"
}
