{
  "commit": "11e453ab63d0da1f61a68f4f2ab6c6b75e6be26f",
  "repo_url": "https://github.com/jenkinsci/accurev-plugin",
  "model": "gpt-4-turbo-2024-04-09",
  "chunk_hashes": [
    "eccb2e5b6e5aff05ddf2"
  ],
  "responses": [
    {
      "content": "```yaml\nleads:\n  - headline: \"Improper Validation of Specified Quantity in Input\"\n    analysis: |\n      The application fails to validate a specified quantity in a user-provided input \"subpath\", which is mentioned in two commands `Poll SCM` and `Sub-path` selection in Jenkins configuration page.  The mishandling occurs because it constructs an array from the comma-separated input without validating the individual entries in that list. This implies that there could be invalid directory paths or files specified, which may not exist or lead to unauthorized areas.\n    cwe: CWE-20\n    function_names:\n      - getSubPath\n    filenames:\n      - src/main/webapp/help/subpath.html\n    classification: \"very promising\"\n\n  - headline: \"Hard-coded Credentials and Insecure Storage of Sensitive Information\"\n    analysis: |\n      The class `MigrateIDAndCredentialTest` demonstrates the mishandling of sensitive information in two ways: the hard-coded password and username, and the insecure storage of these credentials. The hard-coded values are used in tests, which may accidentally end up in production environments, and the credentials are converted and stored without sufficient security measures, potentially leading to leakage if the information is accessed by unauthorized users.\n    cwe: CWE-798\n    function_names:\n      - setUp\n    filenames:\n      - src/test/java/hudson/plugins/accurev/MigrateIDAndCredentialTest.java\n    classification: \"very promising\"\n\n  - headline: \"Improper Restriction of XML External Entity Reference (XXE)\"\n    analysis: |\n      The use of `DocumentBuilderFactory`, `TransformerFactory`, and the parsing method for XML data in `ParseRefTreeExternalFile` without explicitly disabling external entity processing could allow XXE attacks. This issue arises because the application processes XML input that includes external entities without sufficient validation, paving the way for attackers to read arbitrary files, conduct SSRF attacks, or cause DoS.\n    cwe: CWE-611\n    function_names:\n      - parse\n    filenames:\n      - src/main/java/hudson/plugins/accurev/parsers/xml/ParseRefTreeExternalFile.java\n    classification: \"very promising\"\n\n  - headline: \"Command Injection via Unvalidated Input\"\n    analysis: |\n      In `SetProperty`, the function constructs a system command using input directly from the method arguments such as `colorCode` and `propertyName`, which could allow an attacker to inject additional system commands. This vulnerability stems from the lack of input validation and sanitation before using these inputs to construct a shell command.\n    cwe: CWE-77\n    function_names:\n      - setproperty\n    filenames:\n      - src/main/java/hudson/plugins/accurev/cmd/SetProperty.java\n    classification: \"very promising\"\n\n  - headline: \"Improper Access Control and Authentication Bypass\"\n    analysis: |\n      Functions within `AccurevSCMDescriptor` do not correctly authenticate or enforce access control when processing certain sensitive operations such as retrieving server information (`doFillServerNameItems` and `doTest` methods). Unprivileged users could potentially retrieve or manipulate server configuration details due to the weak enforcement of access restrictions.\n    cwe: CWE-862\n    function_names:\n      - doFillServerNameItems\n      - doTest\n    filenames:\n      - src/main/java/hudson/plugins/accurev/AccurevSCM.java\n    classification: \"very promising\"\n```",
      "date": "2024-06-12T17:31:19.090228",
      "usage": {
        "prompt_tokens": 59590,
        "completion_tokens": 704,
        "cost": 0.61702
      }
    }
  ],
  "leads": [
    {
      "headline": "Improper Validation of Specified Quantity in Input",
      "analysis": "The application fails to validate a specified quantity in a user-provided input \"subpath\", which is mentioned in two commands Poll SCM and Sub-path selection in Jenkins configuration page.  The mishandling occurs because it constructs an array from the comma-separated input without validating the individual entries in that list. This implies that there could be invalid directory paths or files specified, which may not exist or lead to unauthorized areas.\n",
      "classification": "very promising",
      "cwe": "CWE-20",
      "function_names": [
        "getSubPath"
      ],
      "filenames": [
        "src/main/webapp/help/subpath.html"
      ]
    },
    {
      "headline": "Hard-coded Credentials and Insecure Storage of Sensitive Information",
      "analysis": "The class MigrateIDAndCredentialTest demonstrates the mishandling of sensitive information in two ways: the hard-coded password and username, and the insecure storage of these credentials. The hard-coded values are used in tests, which may accidentally end up in production environments, and the credentials are converted and stored without sufficient security measures, potentially leading to leakage if the information is accessed by unauthorized users.\n",
      "classification": "very promising",
      "cwe": "CWE-798",
      "function_names": [
        "setUp"
      ],
      "filenames": [
        "src/test/java/hudson/plugins/accurev/MigrateIDAndCredentialTest.java"
      ]
    },
    {
      "headline": "Improper Restriction of XML External Entity Reference (XXE)",
      "analysis": "The use of DocumentBuilderFactory, TransformerFactory, and the parsing method for XML data in ParseRefTreeExternalFile without explicitly disabling external entity processing could allow XXE attacks. This issue arises because the application processes XML input that includes external entities without sufficient validation, paving the way for attackers to read arbitrary files, conduct SSRF attacks, or cause DoS.\n",
      "classification": "very promising",
      "cwe": "CWE-611",
      "function_names": [
        "parse"
      ],
      "filenames": [
        "src/main/java/hudson/plugins/accurev/parsers/xml/ParseRefTreeExternalFile.java"
      ]
    },
    {
      "headline": "Command Injection via Unvalidated Input",
      "analysis": "In SetProperty, the function constructs a system command using input directly from the method arguments such as colorCode and propertyName, which could allow an attacker to inject additional system commands. This vulnerability stems from the lack of input validation and sanitation before using these inputs to construct a shell command.\n",
      "classification": "very promising",
      "cwe": "CWE-77",
      "function_names": [
        "setproperty"
      ],
      "filenames": [
        "src/main/java/hudson/plugins/accurev/cmd/SetProperty.java"
      ]
    },
    {
      "headline": "Improper Access Control and Authentication Bypass",
      "analysis": "Functions within AccurevSCMDescriptor do not correctly authenticate or enforce access control when processing certain sensitive operations such as retrieving server information (doFillServerNameItems and doTest methods). Unprivileged users could potentially retrieve or manipulate server configuration details due to the weak enforcement of access restrictions.\n",
      "classification": "very promising",
      "cwe": "CWE-862",
      "function_names": [
        "doFillServerNameItems",
        "doTest"
      ],
      "filenames": [
        "src/main/java/hudson/plugins/accurev/AccurevSCM.java"
      ]
    }
  ],
  "scores": [
    {
      "stats": {
        "fn": 1,
        "tp": 0,
        "fp": 5
      },
      "mapping": {},
      "vuln_dates": {
        "CVE-2018-1999028": "2018-08-01T13:29:00"
      },
      "scoring_model": "claude-3-opus-20240229",
      "type": "llm",
      "instruction_template_hash": "245ace12b6361954d0a2"
    }
  ],
  "instruction_template_hash": "10c0163db4740318a544",
  "version": "0.1.0"
}
