{
  "commit": "0981f834e6f71c4522ebea75e046a46b6471b76b",
  "repo_url": "https://github.com/jtojnar/pengu",
  "model": "gpt-4-turbo-2024-04-09",
  "chunk_hashes": [
    "77c874eca6b7f90b72d8"
  ],
  "responses": [
    {
      "content": "```yaml\nleads:\n  - headline: Use of a Weak Random Number Generator for Security Purposes\n    analysis: |\n      The server configuration in 'server.js' utilizes Math.random() to generate a session secret. The values produced by Math.random() are not cryptographically secure and can be predicted, especially if an attacker can gather enough data about the generated values. This poses a significant vulnerability in scenarios where session secrets need to guarantee unpredictability to prevent session hijacking or fixation attacks.\n    cwe: CWE-330\n    function_names:\n      - originIsAllowed\n    filenames:\n      - server.js\n    classification: very promising\n  \n  - headline: Prototype Pollution via Object.prototype Modification\n    analysis: |\n      The server code in 'server.js' modifies the Object.prototype.removeItem method. This alteration of a fundamental JavaScript object prototype can lead to prototype pollution. It could cause unexpected behavior across the application, particularly if external libraries depend on the integrity of base prototypes. There is potential for unintended access or modification of properties, especially in a bigger codebase or in applications utilizing untrusted input to manipulate object properties.\n    cwe: CWE-1321\n    function_names:\n      - Array.prototype.getByKey\n      - Array.prototype.pushArray\n    filenames:\n      - server.js\n    classification: very promising\n\n  - headline: Potential SQL Injection via Unsanitized Input\n    analysis: |\n      The application directly uses parameters derived from the session commonly found in authentication forms, such as 'session.user' in 'server.js', without proper sanitization or parameterization, especially noted in SQL queries managing database logins and data management. This oversight could allow an attacker to execute arbitrary SQL code on the database if they can control the input to these parameters, such as by spoofing session data or through other injection vectors.\n    cwe: CWE-89\n    function_names:\n      - getTarget\n      - getPenguinsFromDb\n    filenames:\n      - server.js\n    classification: very promising\n\n  - headline: Session Fixation Vulnerability\n    analysis: |\n      In 'auth/simple.js', the session identifier is accepted from the incoming request query and used to set as the current user session without validations or regeneration of session identifiers. This could lead to session fixation where an attacker can fix the session prior to a victim logging in and then hijack the user's session post authentication.\n    cwe: CWE-384\n    function_names:\n      - module.exports\n    filenames:\n      - auth/simple.js\n    classification: very promising\n\n  - headline: Stored XSS through Client-Side Message Rendering\n    analysis: |\n      In 'client/client.js', there is a risk of stored cross-site scripting (XSS) where user-provided data, such as chat messages, can be stored and later displayed to other users without proper encoding. Although the stored data might be properly encoded in the backend, improper handling or sanitization in the frontend can lead to the execution of malicious scripts when other users load the affected chats.\n    cwe: CWE-79\n    function_names:\n      - connection.onmessage\n    filenames:\n      - client/client.js\n    classification: slightly promising\n\n  - headline: Cross-Site Scripting (XSS) in Authentication Redirect\n    analysis: |\n      The query parameter 'name' from the authentication request in 'auth/simple.js' is reflected in the HTTP response without sufficient sanitization or output encoding, leading to reflected cross-site scripting (XSS). An attacker could craft a malicious URL with script code in the 'name' parameter that gets executed in the browser of any user visiting the URL.\n    cwe: CWE-79\n    function_names:\n      - module.exports\n    filenames:\n      - auth/simple.js\n    classification: slightly promising\n```",
      "date": "2024-06-13T09:05:34.363957",
      "usage": {
        "prompt_tokens": 11171,
        "completion_tokens": 770,
        "cost": 0.13481
      }
    }
  ],
  "leads": [
    {
      "headline": "Use of a Weak Random Number Generator for Security Purposes",
      "analysis": "The server configuration in 'server.js' utilizes Math.random() to generate a session secret. The values produced by Math.random() are not cryptographically secure and can be predicted, especially if an attacker can gather enough data about the generated values. This poses a significant vulnerability in scenarios where session secrets need to guarantee unpredictability to prevent session hijacking or fixation attacks.\n",
      "classification": "very promising",
      "cwe": "CWE-330",
      "function_names": [
        "originIsAllowed"
      ],
      "filenames": [
        "server.js"
      ]
    },
    {
      "headline": "Prototype Pollution via Object.prototype Modification",
      "analysis": "The server code in 'server.js' modifies the Object.prototype.removeItem method. This alteration of a fundamental JavaScript object prototype can lead to prototype pollution. It could cause unexpected behavior across the application, particularly if external libraries depend on the integrity of base prototypes. There is potential for unintended access or modification of properties, especially in a bigger codebase or in applications utilizing untrusted input to manipulate object properties.\n",
      "classification": "very promising",
      "cwe": "CWE-1321",
      "function_names": [
        "Array.prototype.getByKey",
        "Array.prototype.pushArray"
      ],
      "filenames": [
        "server.js"
      ]
    },
    {
      "headline": "Potential SQL Injection via Unsanitized Input",
      "analysis": "The application directly uses parameters derived from the session commonly found in authentication forms, such as 'session.user' in 'server.js', without proper sanitization or parameterization, especially noted in SQL queries managing database logins and data management. This oversight could allow an attacker to execute arbitrary SQL code on the database if they can control the input to these parameters, such as by spoofing session data or through other injection vectors.\n",
      "classification": "very promising",
      "cwe": "CWE-89",
      "function_names": [
        "getTarget",
        "getPenguinsFromDb"
      ],
      "filenames": [
        "server.js"
      ]
    },
    {
      "headline": "Session Fixation Vulnerability",
      "analysis": "In 'auth/simple.js', the session identifier is accepted from the incoming request query and used to set as the current user session without validations or regeneration of session identifiers. This could lead to session fixation where an attacker can fix the session prior to a victim logging in and then hijack the user's session post authentication.\n",
      "classification": "very promising",
      "cwe": "CWE-384",
      "function_names": [
        "module.exports"
      ],
      "filenames": [
        "auth/simple.js"
      ]
    },
    {
      "headline": "Stored XSS through Client-Side Message Rendering",
      "analysis": "In 'client/client.js', there is a risk of stored cross-site scripting (XSS) where user-provided data, such as chat messages, can be stored and later displayed to other users without proper encoding. Although the stored data might be properly encoded in the backend, improper handling or sanitization in the frontend can lead to the execution of malicious scripts when other users load the affected chats.\n",
      "classification": "slightly promising",
      "cwe": "CWE-79",
      "function_names": [
        "connection.onmessage"
      ],
      "filenames": [
        "client/client.js"
      ]
    },
    {
      "headline": "Cross-Site Scripting (XSS) in Authentication Redirect",
      "analysis": "The query parameter 'name' from the authentication request in 'auth/simple.js' is reflected in the HTTP response without sufficient sanitization or output encoding, leading to reflected cross-site scripting (XSS). An attacker could craft a malicious URL with script code in the 'name' parameter that gets executed in the browser of any user visiting the URL.\n",
      "classification": "slightly promising",
      "cwe": "CWE-79",
      "function_names": [
        "module.exports"
      ],
      "filenames": [
        "auth/simple.js"
      ]
    }
  ],
  "scores": [
    {
      "stats": {
        "fn": 1,
        "tp": 0,
        "fp": 4
      },
      "mapping": {},
      "vuln_dates": {
        "CVE-2020-36623": "2022-12-21T19:15:12"
      },
      "scoring_model": "claude-3-opus-20240229",
      "type": "llm",
      "instruction_template_hash": "245ace12b6361954d0a2"
    },
    {
      "stats": {
        "fn": 1,
        "tp": 0,
        "fp": 4
      },
      "mapping": {},
      "vuln_dates": {
        "CVE-2020-36623": "2022-12-21T19:15:12"
      },
      "scoring_model": "claude-3-5-sonnet-20240620",
      "type": "llm",
      "instruction_template_hash": "245ace12b6361954d0a2"
    }
  ],
  "instruction_template_hash": "10c0163db4740318a544",
  "version": "0.1.0"
}
