{
  "commit": "2e2df20219f4e5aa557bac6f0a0031a40b5d422b",
  "repo_url": "https://github.com/jenkinsci/maven-release-cascade-plugin",
  "model": "claude-3-haiku-20240307",
  "chunk_hashes": [
    "adfef682080fb05d99f5"
  ],
  "responses": [
    {
      "content": "Here is the YAML output:\n\n```yaml\nleads:\n  - headline: Improper Input Validation\n    analysis: |\n      The codebase contains several instances of improper input validation, which could lead to various security vulnerabilities such as improper validation of specified quantity in input (CWE-1284) and improper validation of array index (CWE-129). These vulnerabilities could allow an attacker to perform unauthorized actions or access sensitive information.\n    cwe: CWE-20\n    function_names:\n      - executeProcess\n      - executeResult\n    filenames:\n      - src/test/java/design/process/ProcessUtil.java\n    classification: very promising\n  - headline: Code Injection\n    analysis: |\n      The codebase contains instances of improper neutralization of special elements used in an expression language statement (CWE-917), which could allow an attacker to inject malicious code and gain unauthorized access or control. This vulnerability is present in the JsonBean class.\n    cwe: CWE-917\n    function_names:\n      - test\n    filenames:\n      - src/test/java/bench/JsonBean.java\n    classification: very promising\n  - headline: Uncontrolled Resource Consumption\n    analysis: |\n      The codebase contains a potential vulnerability related to uncontrolled resource consumption (CWE-400), specifically in the factor method of the ProjectAction class. An attacker could potentially exploit this vulnerability to perform a denial-of-service attack by continuously calling the factor method and consuming excessive system resources.\n    cwe: CWE-400\n    function_names:\n      - factor\n    filenames:\n      - src/test/java/design/project/ProjectAction.java\n    classification: slightly promising\n  - headline: Improper Neutralization of Input During Web Page Generation\n    analysis: |\n      The codebase contains instances of improper neutralization of input during web page generation (CWE-79), which could lead to cross-site scripting (XSS) vulnerabilities. This vulnerability is present in the ProjectAction class, where user-supplied input is not properly sanitized before being used in the web page.\n    cwe: CWE-79\n    function_names:\n      - getValue\n    filenames:\n      - src/test/java/design/project/ProjectAction.java\n    classification: very promising\n  - headline: Deserialization of Untrusted Data\n    analysis: |\n      The codebase contains a potential vulnerability related to deserialization of untrusted data (CWE-502), which could allow an attacker to execute arbitrary code or gain unauthorized access. This vulnerability is present in the SerialClone class, where deserialization of untrusted data is performed without proper input validation or sanitization.\n    cwe: CWE-502\n    function_names:\n      - cloneX\n    filenames:\n      - src/test/java/bench/SerialClone.java\n    classification: very promising\n  - headline: Uncontrolled Recursion\n    analysis: |\n      The codebase contains a potential vulnerability related to uncontrolled recursion (CWE-674), which could lead to excessive resource consumption and potentially a denial-of-service attack. This vulnerability is present in the factor method of the ProjectAction class, where recursive calls are made without proper termination conditions.\n    cwe: CWE-674\n    function_names:\n      - factor\n    filenames:\n      - src/test/java/design/project/ProjectAction.java\n    classification: slightly promising\n  - headline: Improper Handling of Exceptional Conditions\n    analysis: |\n      The codebase contains instances of improper handling of exceptional conditions (CWE-755), which could lead to unexpected behavior or even crashes. This vulnerability is present in the Remote class, where exceptions are not properly handled or logged.\n    cwe: CWE-755\n    function_names:\n      - test\n    filenames:\n      - src/test/java/design/remote/Remote.java\n    classification: not promising\n```",
      "date": "2024-06-12T18:52:24.701679",
      "usage": {
        "prompt_tokens": 77611,
        "completion_tokens": 941,
        "cost": 0.020579
      }
    }
  ],
  "leads": [
    {
      "headline": "Improper Input Validation",
      "analysis": "The codebase contains several instances of improper input validation, which could lead to various security vulnerabilities such as improper validation of specified quantity in input (CWE-1284) and improper validation of array index (CWE-129). These vulnerabilities could allow an attacker to perform unauthorized actions or access sensitive information.\n",
      "classification": "very promising",
      "cwe": "CWE-20",
      "function_names": [
        "executeProcess",
        "executeResult"
      ],
      "filenames": [
        "src/test/java/design/process/ProcessUtil.java"
      ]
    },
    {
      "headline": "Code Injection",
      "analysis": "The codebase contains instances of improper neutralization of special elements used in an expression language statement (CWE-917), which could allow an attacker to inject malicious code and gain unauthorized access or control. This vulnerability is present in the JsonBean class.\n",
      "classification": "very promising",
      "cwe": "CWE-917",
      "function_names": [
        "test"
      ],
      "filenames": [
        "src/test/java/bench/JsonBean.java"
      ]
    },
    {
      "headline": "Uncontrolled Resource Consumption",
      "analysis": "The codebase contains a potential vulnerability related to uncontrolled resource consumption (CWE-400), specifically in the factor method of the ProjectAction class. An attacker could potentially exploit this vulnerability to perform a denial-of-service attack by continuously calling the factor method and consuming excessive system resources.\n",
      "classification": "slightly promising",
      "cwe": "CWE-400",
      "function_names": [
        "factor"
      ],
      "filenames": [
        "src/test/java/design/project/ProjectAction.java"
      ]
    },
    {
      "headline": "Improper Neutralization of Input During Web Page Generation",
      "analysis": "The codebase contains instances of improper neutralization of input during web page generation (CWE-79), which could lead to cross-site scripting (XSS) vulnerabilities. This vulnerability is present in the ProjectAction class, where user-supplied input is not properly sanitized before being used in the web page.\n",
      "classification": "very promising",
      "cwe": "CWE-79",
      "function_names": [
        "getValue"
      ],
      "filenames": [
        "src/test/java/design/project/ProjectAction.java"
      ]
    },
    {
      "headline": "Deserialization of Untrusted Data",
      "analysis": "The codebase contains a potential vulnerability related to deserialization of untrusted data (CWE-502), which could allow an attacker to execute arbitrary code or gain unauthorized access. This vulnerability is present in the SerialClone class, where deserialization of untrusted data is performed without proper input validation or sanitization.\n",
      "classification": "very promising",
      "cwe": "CWE-502",
      "function_names": [
        "cloneX"
      ],
      "filenames": [
        "src/test/java/bench/SerialClone.java"
      ]
    },
    {
      "headline": "Uncontrolled Recursion",
      "analysis": "The codebase contains a potential vulnerability related to uncontrolled recursion (CWE-674), which could lead to excessive resource consumption and potentially a denial-of-service attack. This vulnerability is present in the factor method of the ProjectAction class, where recursive calls are made without proper termination conditions.\n",
      "classification": "slightly promising",
      "cwe": "CWE-674",
      "function_names": [
        "factor"
      ],
      "filenames": [
        "src/test/java/design/project/ProjectAction.java"
      ]
    },
    {
      "headline": "Improper Handling of Exceptional Conditions",
      "analysis": "The codebase contains instances of improper handling of exceptional conditions (CWE-755), which could lead to unexpected behavior or even crashes. This vulnerability is present in the Remote class, where exceptions are not properly handled or logged.\n",
      "classification": "not promising",
      "cwe": "CWE-755",
      "function_names": [
        "test"
      ],
      "filenames": [
        "src/test/java/design/remote/Remote.java"
      ]
    }
  ],
  "scores": [
    {
      "stats": {
        "fn": 2,
        "tp": 0,
        "fp": 4
      },
      "mapping": {},
      "vuln_dates": {
        "CVE-2020-2295": "2020-10-08T13:15:11",
        "CVE-2020-2294": "2020-10-08T13:15:11"
      },
      "scoring_model": "claude-3-opus-20240229",
      "type": "llm",
      "instruction_template_hash": "245ace12b6361954d0a2"
    }
  ],
  "instruction_template_hash": "10c0163db4740318a544",
  "version": "0.1.0"
}
