{
  "commit": "3722c6c61e0808dcefeb1d633172dee833533901",
  "repo_url": "https://gitlab.com/libidn/libidn2",
  "model": "gpt-4o-2024-05-13",
  "chunk_hashes": [
    "db4af47a3909eba4e53a"
  ],
  "responses": [
    {
      "content": "```yaml\nleads:\n  - headline: \"Potential Command Injection Vulnerability\"\n    analysis: |\n      The `gen.idn-tld-tv.pl` script contains user input processing that could be vulnerable to command injection. The input variable `$2` is directly included in a system command (`unpacket(\"H*\", $2)`). If an attacker controls this input, they could inject arbitrary OS commands.\n    cwe: CWE-78\n    function_names:\n      - \"main\"\n    filenames:\n      - \"gen-idn-tld-tv.pl\"\n    classification: very promising\n\n  - headline: \"Unchecked User Input in Perl Script\"\n    analysis: |\n      The `gen-utc-test.pl` script uses user inputs without proper validation. This operation could allow an attacker to input malicious data that the script processes and runs. Specifically, `$2` and `$4` in a regex match aren\u2019t properly sanitized before use.\n    cwe: CWE-20\n    function_names:\n      - \"main\"\n    filenames:\n      - \"gen-utc-test.pl\"\n    classification: slightly promising\n\n  - headline: \"Memory Handling Issue in C Test Code\"\n    analysis: |\n      The `test-lookup.c` file contains several instances where memory allocated with `malloc` or similar functions is not properly freed in all code paths, potentially leading to memory leaks. For instance, the `idn2_lookup_u8` function calls in `test_homebrewed` do not ensure the allocated memory returned by `idn2_lookup_u8` is always freed in the case of errors.\n    cwe: CWE-401\n    function_names:\n      - \"test_homebrewed\"\n    filenames:\n      - \"tests/test-lookup.c\"\n    classification: slightly promising\n\n  - headline: \"Inadequate Error Handling\"\n    analysis: |\n      In `test-register.c`, there are multiple instances where functions that might fail (e.g., memory allocations or external library calls) do not adequately handle the errors. This may lead to undefined behavior or crashes. Functions like `idn2_register_u8` should have their return values checked more rigorously.\n    cwe: CWE-754\n    function_names:\n      - \"main\"\n    filenames:\n      - \"tests/test-register.c\"\n    classification: slightly promising\n\n  - headline: \"Buffer Overflow Risks in Lookup Function\"\n    analysis: |\n      In the `lookup.c` file, the `gen_idna_map_tables` function manipulates files and buffers without sufficient boundary checks. This may allow an attacker to overflow buffers or manipulate the system in unintended ways, especially while processing unusually large or malformed domain names.\n    cwe: CWE-120\n    function_names:\n      - \"gen_idna_map_tables\"\n    filenames:\n      - \"lib/lookup.c\"\n    classification: very promising\n\n  - headline: \"Improper Sanitization of File Operations\"\n    analysis: |\n      The `gen-tables-from-iana.pl` uses file operations without verifying the content or the source of the data being processed. Unchecked data from files could lead to injection attacks or command execution vulnerabilities.\n    cwe: CWE-74\n    function_names:\n      - \"main\"\n    filenames:\n      - \"lib/gen-tables-from-iana.pl\"\n    classification: very promising\n\n  - headline: \"Hardcoded Buffer Sizes and Limits\"\n    analysis: |\n      Functions throughout the codebase, especially in `test-tounicode.c`, `test-punycode.c`, and other `.c` files, utilize hardcoded buffer sizes, which can lead to buffer overflows if assumptions about the buffer size are surpassed. For example, the `_decodeIdnaTest` function in `test-lookup.c` assumes input will not exceed buffer capacity, lacking dynamic checks.\n    cwe: CWE-120\n    function_names:\n      - \"_decodeIdnaTest\"\n      - \"test_IdnaTest\"\n    filenames:\n      - \"lib/lookup.c\"\n      - \"tests/test-lookup.c\"\n    classification: very promising\n\n  - headline: \"Command Execution in Fuzz Testing\"\n    analysis: |\n      The `run-afl.sh` script calls external commands within shell scripts that are subject to user input. These external commands could be manipulated by an attacker to execute arbitrary commands within the script\u2019s context.\n    cwe: CWE-78\n    function_names:\n      - \"main\"\n    filenames:\n      - \"fuzz/run-afl.sh\"\n    classification: very promising\n\n  - headline: \"Use of Unsafe Functions\"\n    analysis: |\n      Throughout the C codebase, there are instances of using functions known to be unsafe, such as `strcpy`, `sprintf`, `scanf`, etc. These functions do not perform boundary checks, making them susceptible to buffer overflow attacks. Safer alternatives like `strncpy`, `snprintf`, and `fgets` should be used.\n    cwe: CWE-120\n    function_names:\n      - \"test-toascii.c\"\n      - \"test-tounicode.c\"\n    filenames:\n      - \"lib/decode.c\"\n      - \"lib/lookup.c\"\n    classification: very promising\n\n  - headline: \"Potential Information Disclosure\"\n    analysis: |\n      Error messages in `lib/error.c` may reveal sensitive information about the internal state of the application. For example, `idn2_strerror` prints out detailed error messages that could be exploited to gain more information about the environment or internal workings of the application.\n    cwe: CWE-209\n    function_names:\n      - \"idn2_strerror\"\n    filenames:\n      - \"lib/error.c\"\n    classification: slightly promising\n```",
      "date": "2024-07-08T09:37:28.629709",
      "usage": {
        "prompt_tokens": 89712,
        "completion_tokens": 1166,
        "cost": 0.46605
      }
    }
  ],
  "leads": [
    {
      "headline": "Potential Command Injection Vulnerability",
      "analysis": "The gen.idn-tld-tv.pl script contains user input processing that could be vulnerable to command injection. The input variable $2 is directly included in a system command (unpacket(\"H*\", $2)). If an attacker controls this input, they could inject arbitrary OS commands.\n",
      "classification": "very promising",
      "cwe": "CWE-78",
      "function_names": [
        "main"
      ],
      "filenames": [
        "gen-idn-tld-tv.pl"
      ]
    },
    {
      "headline": "Unchecked User Input in Perl Script",
      "analysis": "The gen-utc-test.pl script uses user inputs without proper validation. This operation could allow an attacker to input malicious data that the script processes and runs. Specifically, $2 and $4 in a regex match aren\u2019t properly sanitized before use.\n",
      "classification": "slightly promising",
      "cwe": "CWE-20",
      "function_names": [
        "main"
      ],
      "filenames": [
        "gen-utc-test.pl"
      ]
    },
    {
      "headline": "Memory Handling Issue in C Test Code",
      "analysis": "The test-lookup.c file contains several instances where memory allocated with malloc or similar functions is not properly freed in all code paths, potentially leading to memory leaks. For instance, the idn2_lookup_u8 function calls in test_homebrewed do not ensure the allocated memory returned by idn2_lookup_u8 is always freed in the case of errors.\n",
      "classification": "slightly promising",
      "cwe": "CWE-401",
      "function_names": [
        "test_homebrewed"
      ],
      "filenames": [
        "tests/test-lookup.c"
      ]
    },
    {
      "headline": "Inadequate Error Handling",
      "analysis": "In test-register.c, there are multiple instances where functions that might fail (e.g., memory allocations or external library calls) do not adequately handle the errors. This may lead to undefined behavior or crashes. Functions like idn2_register_u8 should have their return values checked more rigorously.\n",
      "classification": "slightly promising",
      "cwe": "CWE-754",
      "function_names": [
        "main"
      ],
      "filenames": [
        "tests/test-register.c"
      ]
    },
    {
      "headline": "Buffer Overflow Risks in Lookup Function",
      "analysis": "In the lookup.c file, the gen_idna_map_tables function manipulates files and buffers without sufficient boundary checks. This may allow an attacker to overflow buffers or manipulate the system in unintended ways, especially while processing unusually large or malformed domain names.\n",
      "classification": "very promising",
      "cwe": "CWE-120",
      "function_names": [
        "gen_idna_map_tables"
      ],
      "filenames": [
        "lib/lookup.c"
      ]
    },
    {
      "headline": "Improper Sanitization of File Operations",
      "analysis": "The gen-tables-from-iana.pl uses file operations without verifying the content or the source of the data being processed. Unchecked data from files could lead to injection attacks or command execution vulnerabilities.\n",
      "classification": "very promising",
      "cwe": "CWE-74",
      "function_names": [
        "main"
      ],
      "filenames": [
        "lib/gen-tables-from-iana.pl"
      ]
    },
    {
      "headline": "Hardcoded Buffer Sizes and Limits",
      "analysis": "Functions throughout the codebase, especially in test-tounicode.c, test-punycode.c, and other .c files, utilize hardcoded buffer sizes, which can lead to buffer overflows if assumptions about the buffer size are surpassed. For example, the _decodeIdnaTest function in test-lookup.c assumes input will not exceed buffer capacity, lacking dynamic checks.\n",
      "classification": "very promising",
      "cwe": "CWE-120",
      "function_names": [
        "_decodeIdnaTest",
        "test_IdnaTest"
      ],
      "filenames": [
        "lib/lookup.c",
        "tests/test-lookup.c"
      ]
    },
    {
      "headline": "Command Execution in Fuzz Testing",
      "analysis": "The run-afl.sh script calls external commands within shell scripts that are subject to user input. These external commands could be manipulated by an attacker to execute arbitrary commands within the script\u2019s context.\n",
      "classification": "very promising",
      "cwe": "CWE-78",
      "function_names": [
        "main"
      ],
      "filenames": [
        "fuzz/run-afl.sh"
      ]
    },
    {
      "headline": "Use of Unsafe Functions",
      "analysis": "Throughout the C codebase, there are instances of using functions known to be unsafe, such as strcpy, sprintf, scanf, etc. These functions do not perform boundary checks, making them susceptible to buffer overflow attacks. Safer alternatives like strncpy, snprintf, and fgets should be used.\n",
      "classification": "very promising",
      "cwe": "CWE-120",
      "function_names": [
        "test-toascii.c",
        "test-tounicode.c"
      ],
      "filenames": [
        "lib/decode.c",
        "lib/lookup.c"
      ]
    },
    {
      "headline": "Potential Information Disclosure",
      "analysis": "Error messages in lib/error.c may reveal sensitive information about the internal state of the application. For example, idn2_strerror prints out detailed error messages that could be exploited to gain more information about the environment or internal workings of the application.\n",
      "classification": "slightly promising",
      "cwe": "CWE-209",
      "function_names": [
        "idn2_strerror"
      ],
      "filenames": [
        "lib/error.c"
      ]
    }
  ],
  "scores": [
    {
      "stats": {
        "fn": 2,
        "tp": 0,
        "fp": 6
      },
      "mapping": {},
      "vuln_dates": {
        "CVE-2017-14061": "2017-08-31T16:29:00",
        "CVE-2017-14062": "2017-08-31T16:29:00"
      },
      "scoring_model": "claude-3-5-sonnet-20240620",
      "type": "llm",
      "instruction_template_hash": "245ace12b6361954d0a2"
    }
  ],
  "instruction_template_hash": "10c0163db4740318a544",
  "version": "0.1.0"
}
