{
  "commit": "13293140eaa6c2896d17c3fb2b62f780b5331ffb",
  "repo_url": "https://github.com/opensuse/obs-service-tar_scm",
  "model": "claude-3-opus-20240229",
  "chunk_hashes": [
    "684e2966b35746a8df1e"
  ],
  "responses": [
    {
      "content": "Here is the YAML output with security vulnerability leads:\n\n```yaml\nleads:\n  - headline: Improper Input Validation in tar_scm.py argument parsing \n    analysis: |\n      The Cli class in TarSCM/cli.py does not properly validate the --subdir argument. It prevents absolute paths and parent directory traversal, but still allows subdir values containing things like embedded Python code in backticks that could potentially be executed. The value is later used to construct file paths without further sanitization.\n    cwe: CWE-20\n    function_names:\n      - Cli.parse_args\n    filenames:\n      - TarSCM/cli.py  \n    classification: very promising\n\n  - headline: Improper Handling of Exceptional Conditions when extracting from tar\n    analysis: |  \n      The Tar.extract_from_archive function in TarSCM/archive.py uses shutil.move to move extracted files without checking for exceptions. If shutil.move fails for any reason, it will raise an exception which is not caught. This could leave the archive extraction in an unexpected inconsistent state. The error handling and logging around this operation is insufficient.\n    cwe: CWE-755\n    function_names:\n      - Tar.extract_from_archive\n    filenames:\n      - TarSCM/archive.py\n    classification: slightly promising\n    \n  - headline: Potential Command Injection via revision parameter\n    analysis: |\n      The get_rev function in TarSCM/scm/svn.py uses the num_commits parameter to construct an svn log command without sanitizing num_commits. If an attacker could control the num_commits value, they may be able to inject additional svn commands. However, it's unclear if num_commits comes from an untrusted source. More analysis is needed to determine exploitability.\n    cwe: CWE-78\n    function_names:\n      - Svn._get_rev  \n    filenames:\n      - TarSCM/scm/svn.py\n    classification: slightly promising\n\n  - headline: Unsafe use of YAML load in tasks.py\n    analysis: |\n      The generate_list function in TarSCM/tasks.py uses yaml.safe_load to parse YAML files. Although the safe_load function avoids code execution, it still allows construction of arbitrary Python objects. If the YAML came from an untrusted source, it could potentially result in security issues.\n    cwe: CWE-20\n    function_names:\n      - Tasks.generate_list\n    filenames:\n      - TarSCM/tasks.py  \n    classification: not promising\n\n  - headline: Potential MITM exposure via lack of server cert verification\n    analysis: |\n      The is_sslverify_enabled function in TarSCM/scm/base.py checks if server certificate verification is enabled before making HTTPS requests. If enabled, it relies on the default SSL certificate bundle. However, in some configurations, self-signed or internal CA certs may not be properly trusted, leading to failed verification. An attacker could potentially MITM connections in this scenario to provide malicious archive contents.\n    cwe: CWE-295 \n    function_names:\n      - Scm.is_sslverify_enabled\n    filenames:  \n      - TarSCM/scm/base.py\n    classification: not promising\n```\n\nThe leads focus on identifying potential input validation issues, command injection, unsafe deserialization, and SSL verification weaknesses. The analysis provides details on why each lead may be concerning from a security perspective. No code execution vulnerabilities were found from a high-level review, but a few areas warranted deeper investigation to determine their full impact and exploitability.",
      "date": "2024-06-13T10:54:52.537339",
      "usage": {
        "prompt_tokens": 57152,
        "completion_tokens": 876,
        "cost": 0.92298
      }
    }
  ],
  "leads": [
    {
      "headline": "Improper Input Validation in tar_scm.py argument parsing",
      "analysis": "The Cli class in TarSCM/cli.py does not properly validate the --subdir argument. It prevents absolute paths and parent directory traversal, but still allows subdir values containing things like embedded Python code in backticks that could potentially be executed. The value is later used to construct file paths without further sanitization.\n",
      "classification": "very promising",
      "cwe": "CWE-20",
      "function_names": [
        "Cli.parse_args"
      ],
      "filenames": [
        "TarSCM/cli.py"
      ]
    },
    {
      "headline": "Improper Handling of Exceptional Conditions when extracting from tar",
      "analysis": "The Tar.extract_from_archive function in TarSCM/archive.py uses shutil.move to move extracted files without checking for exceptions. If shutil.move fails for any reason, it will raise an exception which is not caught. This could leave the archive extraction in an unexpected inconsistent state. The error handling and logging around this operation is insufficient.\n",
      "classification": "slightly promising",
      "cwe": "CWE-755",
      "function_names": [
        "Tar.extract_from_archive"
      ],
      "filenames": [
        "TarSCM/archive.py"
      ]
    },
    {
      "headline": "Potential Command Injection via revision parameter",
      "analysis": "The get_rev function in TarSCM/scm/svn.py uses the num_commits parameter to construct an svn log command without sanitizing num_commits. If an attacker could control the num_commits value, they may be able to inject additional svn commands. However, it's unclear if num_commits comes from an untrusted source. More analysis is needed to determine exploitability.\n",
      "classification": "slightly promising",
      "cwe": "CWE-78",
      "function_names": [
        "Svn._get_rev"
      ],
      "filenames": [
        "TarSCM/scm/svn.py"
      ]
    },
    {
      "headline": "Unsafe use of YAML load in tasks.py",
      "analysis": "The generate_list function in TarSCM/tasks.py uses yaml.safe_load to parse YAML files. Although the safe_load function avoids code execution, it still allows construction of arbitrary Python objects. If the YAML came from an untrusted source, it could potentially result in security issues.\n",
      "classification": "not promising",
      "cwe": "CWE-20",
      "function_names": [
        "Tasks.generate_list"
      ],
      "filenames": [
        "TarSCM/tasks.py"
      ]
    },
    {
      "headline": "Potential MITM exposure via lack of server cert verification",
      "analysis": "The is_sslverify_enabled function in TarSCM/scm/base.py checks if server certificate verification is enabled before making HTTPS requests. If enabled, it relies on the default SSL certificate bundle. However, in some configurations, self-signed or internal CA certs may not be properly trusted, leading to failed verification. An attacker could potentially MITM connections in this scenario to provide malicious archive contents.\n",
      "classification": "not promising",
      "cwe": "CWE-295",
      "function_names": [
        "Scm.is_sslverify_enabled"
      ],
      "filenames": [
        "TarSCM/scm/base.py"
      ]
    }
  ],
  "scores": [
    {
      "stats": {
        "fn": 1,
        "tp": 0,
        "fp": 1
      },
      "mapping": {},
      "vuln_dates": {
        "CVE-2018-12473": "2018-10-02T15:29:00"
      },
      "scoring_model": "claude-3-opus-20240229",
      "type": "llm",
      "instruction_template_hash": "245ace12b6361954d0a2"
    },
    {
      "stats": {
        "fn": 1,
        "tp": 0,
        "fp": 1
      },
      "mapping": {},
      "vuln_dates": {
        "CVE-2018-12473": "2018-10-02T15:29:00"
      },
      "scoring_model": "claude-3-5-sonnet-20240620",
      "type": "llm",
      "instruction_template_hash": "245ace12b6361954d0a2"
    }
  ],
  "instruction_template_hash": "10c0163db4740318a544",
  "version": "0.1.0"
}
