{
  "commit": "0e348a825db7367fc6625f573343563bd93423ce",
  "repo_url": "https://github.com/jenkinsci/dashboard-view-plugin",
  "model": "gpt-4-turbo-2024-04-09",
  "chunk_hashes": [
    "dbd215c6e76af6b0e3d6"
  ],
  "responses": [
    {
      "content": "```yaml\nleads:\n  - headline: Insufficient permissions checks in Jenkins dashboard view plugin\n    analysis: |\n      The Jenkins dashboard view plugin lacks necessary permission checks on various operations, particularly in the behaviors delivered through AJAX endpoints and custom portlets. This deficiency enables unauthorized users to potentially access and manipulate data or perform actions without proper authorization, leading to unauthorized information disclosure or service disruption.\n    cwe: CWE-862\n    function_names:\n      - getTestResult\n      - getStats\n    filenames:\n      - src/main/java/hudson/plugins/view/dashboard/test/TestUtil.java\n      - src/main/java/hudson/plugins/view/dashboard/stats/StatSlaves.java\n    classification: very promising\n\n  - headline: Exposure of sensitive information due to detailed error messages\n    analysis: |\n      Various components, such as DashboardLog and certain portlets like IframePortlet, provide detailed error logging that includes configuration data or operational details. These logs may be exposed to users, logged to an accessible file, or monitored through unsafe methods, potentially leading to the exposure of sensitive system information.\n    cwe: CWE-532\n    function_names:\n      - error\n      - getEffectiveUrl\n    filenames:\n      - src/main/java/hudson/plugins/view/dashboard/DashboardLog.java\n      - src/main/java/hudson/plugins/view/dashboard/core/IframePortlet.java\n    classification: very promising\n\n  - headline: Cross-Site Scripting (XSS) risk in JS functions and iframe URL construction\n    analysis: |\n      The JavaScript functions `myshow` and `myhide` and the method `setIframeSource` in IframePortlet class manipulate DOM elements and URL strings in ways that are potentially unsafe, leading to DOM-based XSS vulnerabilities if user-supplied input is not correctly sanitized.\n    cwe: CWE-79\n    function_names:\n      - myshow\n      - myhide\n      - setIframeSource\n    filenames:\n      - src/main/webapp/js/dashboard-view.js\n      - src/main/java/hudson/plugins/view/dashboard/core/IframePortlet.java\n    classification: very promising\n\n  - headline: Inadequate session expiration handling\n    analysis: |\n      The system does not implement an effective session expiration mechanism. This weakness could allow an attacker to capture or reuse old sessions, facilitating attacks such as session fixation or hijacking.\n    cwe: CWE-613\n    function_names: []\n    filenames:\n      - src/main/java/hudson/plugins/view/dashboard/Dashboard.java\n    classification: very promising\n\n  - headline: Deserialization of untrusted data\n    analysis: |\n      The Dashboard class implements form submission handling (`submit` method) that directly processes untrusted input without adequate validation of the serialized data. This could lead to remote code execution if an attacker sends crafted serialized data exploiting the application's deserialization mechanism.\n    cwe: CWE-502\n    function_names:\n      - submit\n    filenames:\n      - src/main/java/hudson/plugins/view/dashboard/Dashboard.java\n    classification: very promising\n\n  - headline: SQL injection via parameter manipulation in query methods\n    analysis: |\n      Methods handling data queries in classes like LatestBuilds make use of parameters that, if manipulated with crafted input, could lead to SQL injection vulnerabilities. This is particularly likely where sorting or filtering parameters are incorporated directly into SQL queries.\n    cwe: CWE-89\n    function_names:\n      - getFinishedBuilds\n    filenames:\n      - src/main/java/hudson/plugins/view/dashboard/builds/LatestBuilds.java\n    classification: slightly promising\n```",
      "date": "2024-06-12T18:14:47.751626",
      "usage": {
        "prompt_tokens": 18795,
        "completion_tokens": 730,
        "cost": 0.20985
      }
    }
  ],
  "leads": [
    {
      "headline": "Insufficient permissions checks in Jenkins dashboard view plugin",
      "analysis": "The Jenkins dashboard view plugin lacks necessary permission checks on various operations, particularly in the behaviors delivered through AJAX endpoints and custom portlets. This deficiency enables unauthorized users to potentially access and manipulate data or perform actions without proper authorization, leading to unauthorized information disclosure or service disruption.\n",
      "classification": "very promising",
      "cwe": "CWE-862",
      "function_names": [
        "getTestResult",
        "getStats"
      ],
      "filenames": [
        "src/main/java/hudson/plugins/view/dashboard/test/TestUtil.java",
        "src/main/java/hudson/plugins/view/dashboard/stats/StatSlaves.java"
      ]
    },
    {
      "headline": "Exposure of sensitive information due to detailed error messages",
      "analysis": "Various components, such as DashboardLog and certain portlets like IframePortlet, provide detailed error logging that includes configuration data or operational details. These logs may be exposed to users, logged to an accessible file, or monitored through unsafe methods, potentially leading to the exposure of sensitive system information.\n",
      "classification": "very promising",
      "cwe": "CWE-532",
      "function_names": [
        "error",
        "getEffectiveUrl"
      ],
      "filenames": [
        "src/main/java/hudson/plugins/view/dashboard/DashboardLog.java",
        "src/main/java/hudson/plugins/view/dashboard/core/IframePortlet.java"
      ]
    },
    {
      "headline": "Cross-Site Scripting (XSS) risk in JS functions and iframe URL construction",
      "analysis": "The JavaScript functions myshow and myhide and the method setIframeSource in IframePortlet class manipulate DOM elements and URL strings in ways that are potentially unsafe, leading to DOM-based XSS vulnerabilities if user-supplied input is not correctly sanitized.\n",
      "classification": "very promising",
      "cwe": "CWE-79",
      "function_names": [
        "myshow",
        "myhide",
        "setIframeSource"
      ],
      "filenames": [
        "src/main/webapp/js/dashboard-view.js",
        "src/main/java/hudson/plugins/view/dashboard/core/IframePortlet.java"
      ]
    },
    {
      "headline": "Inadequate session expiration handling",
      "analysis": "The system does not implement an effective session expiration mechanism. This weakness could allow an attacker to capture or reuse old sessions, facilitating attacks such as session fixation or hijacking.\n",
      "classification": "very promising",
      "cwe": "CWE-613",
      "function_names": [],
      "filenames": [
        "src/main/java/hudson/plugins/view/dashboard/Dashboard.java"
      ]
    },
    {
      "headline": "Deserialization of untrusted data",
      "analysis": "The Dashboard class implements form submission handling (submit method) that directly processes untrusted input without adequate validation of the serialized data. This could lead to remote code execution if an attacker sends crafted serialized data exploiting the application's deserialization mechanism.\n",
      "classification": "very promising",
      "cwe": "CWE-502",
      "function_names": [
        "submit"
      ],
      "filenames": [
        "src/main/java/hudson/plugins/view/dashboard/Dashboard.java"
      ]
    },
    {
      "headline": "SQL injection via parameter manipulation in query methods",
      "analysis": "Methods handling data queries in classes like LatestBuilds make use of parameters that, if manipulated with crafted input, could lead to SQL injection vulnerabilities. This is particularly likely where sorting or filtering parameters are incorporated directly into SQL queries.\n",
      "classification": "slightly promising",
      "cwe": "CWE-89",
      "function_names": [
        "getFinishedBuilds"
      ],
      "filenames": [
        "src/main/java/hudson/plugins/view/dashboard/builds/LatestBuilds.java"
      ]
    }
  ],
  "scores": [
    {
      "stats": {
        "fn": 2,
        "tp": 1,
        "fp": 4
      },
      "mapping": {
        "2": "CVE-2022-27197"
      },
      "vuln_dates": {
        "CVE-2019-10396": "2019-09-12T14:15:11",
        "CVE-2022-27197": "2022-03-15T17:15:10",
        "CVE-2021-21649": "2021-05-11T15:15:07"
      },
      "scoring_model": "claude-3-opus-20240229",
      "type": "llm",
      "instruction_template_hash": "245ace12b6361954d0a2"
    }
  ],
  "instruction_template_hash": "10c0163db4740318a544",
  "version": "0.1.0"
}
