{
  "commit": "1a7e0e23227900f8fa68acb01c0ef2715c2d664b",
  "repo_url": "https://github.com/jenkinsci/parameterized-trigger-plugin",
  "model": "gpt-4o-2024-05-13",
  "chunk_hashes": [
    "0f11e820f7d5c7d04884"
  ],
  "responses": [
    {
      "content": "```yaml\nleads:\n  - headline: \"Hardcoded SVN URL\"\n    analysis: |\n      The code contains hardcoded SVN URLs for fetching resources. This could lead to potential security issues if these URLs are exposed or if the server becomes compromised. Hardcoding URLs also reduces flexibility in configuring different environments or adapting to server changes.\n    cwe: CWE-798\n    function_names:\n      - testRevisionParameter\n    filenames:\n      - src/test/java/hudson/plugins/parameterizedtrigger/test/SubversionRevisionBuildTriggerConfigTest.java\n    classification: slightly promising\n\n  - headline: \"Insufficient Error Handling in NoFilesFoundEnum\"\n    analysis: |\n      The `FileBuildParameterFactory.NoFilesFoundEnum` enum implements error handling for missing configuration files, but some options like \"SKIP\" might silently bypass intended operations without sufficient alerting. This can lead to misconfigurations going unnoticed.\n    cwe: CWE-754\n    function_names:\n      - failCheck\n    filenames:\n      - src/main/java/hudson/plugins/parameterizedtrigger/FileBuildParameterFactory.java\n    classification: slightly promising\n\n  - headline: \"Potential Race Condition in Job Scheduling\"\n    analysis: |\n      The `TriggerBuilder` and `ParameterizedDependency` classes have methods that perform continuous checking and scheduling without sufficient lock mechanisms, potentially causing race conditions. This can lead to unpredictable job execution orders.\n    cwe: CWE-362\n    function_names:\n      - perform\n      - shouldSchedule\n    filenames:\n      - src/main/java/hudson/plugins/parameterizedtrigger/TriggerBuilder.java\n      - src/main/java/hudson/plugins/parameterizedtrigger/ParameterizedDependency.java\n    classification: very promising\n\n  - headline: \"Static Use of Shell Expansion in FileBuildParameters\"\n    analysis: |\n      The `FileBuildParameters` class uses environment variables expanded via `env.expand()`. If the inputs are not properly sanitized, this could lead to shell injection vulnerabilities, especially if any user-provided data is involved in populating these variables.\n    cwe: CWE-78\n    function_names:\n      - getAction\n    filenames:\n      - src/main/java/hudson/plugins/parameterizedtrigger/FileBuildParameters.java\n    classification: slightly promising\n\n  - headline: \"Deserialization without Security Context\"\n    analysis: |\n      The `readResolve` method in multiple classes like `BuildInfoExporterAction` and `SubProjectData` reconstruct objects from a serialized state without enforcing a strict security context. This might allow deserialization attacks.\n    cwe: CWE-502\n    function_names:\n      - readResolve\n    filenames:\n      - src/main/java/hudson/plugins/parameterizedtrigger/BuildInfoExporterAction.java\n      - src/main/java/hudson/plugins/parameterizedtrigger/SubProjectData.java\n    classification: very promising\n\n  - headline: \"Uncontrolled Resource Consumption in Parameterized Triggers\"\n    analysis: |\n      The `BinaryFileParameterFactory` and similar classes could potentially process unbounded or very large sets of input files. Without proper controls, this might lead to Denial of Service (DoS) due to resource exhaustion.\n    cwe: CWE-400\n    function_names:\n      - getParameters\n    filenames:\n      - src/main/java/hudson/plugins/parameterizedtrigger/BinaryFileParameterFactory.java\n      - src/main/java/hudson/plugins/parameterizedtrigger/FileBuildParameterFactory.java\n    classification: very promising\n\n  - headline: \"Weak Error Messages in Exception Handling\"\n    analysis: |\n      Many classes including `BuildTriggerConfig` and `ParameterizedDependency` use generalized and weak error messages in exception handling. These might not provide sufficient information for diagnosing issues and can result in security weaknesses if errors are exposed.\n    cwe: CWE-209\n    function_names:\n      - perform\n      - shouldTriggerBuild\n    filenames:\n      - src/main/java/hudson/plugins/parameterizedtrigger/BuildTriggerConfig.java\n      - src/main/java/hudson/plugins/parameterizedtrigger/ParameterizedDependency.java\n    classification: not promising\n```",
      "date": "2024-06-12T18:59:56.318107",
      "usage": {
        "prompt_tokens": 52217,
        "completion_tokens": 843,
        "cost": 0.27373
      }
    }
  ],
  "leads": [
    {
      "headline": "Hardcoded SVN URL",
      "analysis": "The code contains hardcoded SVN URLs for fetching resources. This could lead to potential security issues if these URLs are exposed or if the server becomes compromised. Hardcoding URLs also reduces flexibility in configuring different environments or adapting to server changes.\n",
      "classification": "slightly promising",
      "cwe": "CWE-798",
      "function_names": [
        "testRevisionParameter"
      ],
      "filenames": [
        "src/test/java/hudson/plugins/parameterizedtrigger/test/SubversionRevisionBuildTriggerConfigTest.java"
      ]
    },
    {
      "headline": "Insufficient Error Handling in NoFilesFoundEnum",
      "analysis": "The FileBuildParameterFactory.NoFilesFoundEnum enum implements error handling for missing configuration files, but some options like \"SKIP\" might silently bypass intended operations without sufficient alerting. This can lead to misconfigurations going unnoticed.\n",
      "classification": "slightly promising",
      "cwe": "CWE-754",
      "function_names": [
        "failCheck"
      ],
      "filenames": [
        "src/main/java/hudson/plugins/parameterizedtrigger/FileBuildParameterFactory.java"
      ]
    },
    {
      "headline": "Potential Race Condition in Job Scheduling",
      "analysis": "The TriggerBuilder and ParameterizedDependency classes have methods that perform continuous checking and scheduling without sufficient lock mechanisms, potentially causing race conditions. This can lead to unpredictable job execution orders.\n",
      "classification": "very promising",
      "cwe": "CWE-362",
      "function_names": [
        "perform",
        "shouldSchedule"
      ],
      "filenames": [
        "src/main/java/hudson/plugins/parameterizedtrigger/TriggerBuilder.java",
        "src/main/java/hudson/plugins/parameterizedtrigger/ParameterizedDependency.java"
      ]
    },
    {
      "headline": "Static Use of Shell Expansion in FileBuildParameters",
      "analysis": "The FileBuildParameters class uses environment variables expanded via env.expand(). If the inputs are not properly sanitized, this could lead to shell injection vulnerabilities, especially if any user-provided data is involved in populating these variables.\n",
      "classification": "slightly promising",
      "cwe": "CWE-78",
      "function_names": [
        "getAction"
      ],
      "filenames": [
        "src/main/java/hudson/plugins/parameterizedtrigger/FileBuildParameters.java"
      ]
    },
    {
      "headline": "Deserialization without Security Context",
      "analysis": "The readResolve method in multiple classes like BuildInfoExporterAction and SubProjectData reconstruct objects from a serialized state without enforcing a strict security context. This might allow deserialization attacks.\n",
      "classification": "very promising",
      "cwe": "CWE-502",
      "function_names": [
        "readResolve"
      ],
      "filenames": [
        "src/main/java/hudson/plugins/parameterizedtrigger/BuildInfoExporterAction.java",
        "src/main/java/hudson/plugins/parameterizedtrigger/SubProjectData.java"
      ]
    },
    {
      "headline": "Uncontrolled Resource Consumption in Parameterized Triggers",
      "analysis": "The BinaryFileParameterFactory and similar classes could potentially process unbounded or very large sets of input files. Without proper controls, this might lead to Denial of Service (DoS) due to resource exhaustion.\n",
      "classification": "very promising",
      "cwe": "CWE-400",
      "function_names": [
        "getParameters"
      ],
      "filenames": [
        "src/main/java/hudson/plugins/parameterizedtrigger/BinaryFileParameterFactory.java",
        "src/main/java/hudson/plugins/parameterizedtrigger/FileBuildParameterFactory.java"
      ]
    },
    {
      "headline": "Weak Error Messages in Exception Handling",
      "analysis": "Many classes including BuildTriggerConfig and ParameterizedDependency use generalized and weak error messages in exception handling. These might not provide sufficient information for diagnosing issues and can result in security weaknesses if errors are exposed.\n",
      "classification": "not promising",
      "cwe": "CWE-209",
      "function_names": [
        "perform",
        "shouldTriggerBuild"
      ],
      "filenames": [
        "src/main/java/hudson/plugins/parameterizedtrigger/BuildTriggerConfig.java",
        "src/main/java/hudson/plugins/parameterizedtrigger/ParameterizedDependency.java"
      ]
    }
  ],
  "scores": [
    {
      "stats": {
        "fn": 2,
        "tp": 0,
        "fp": 3
      },
      "mapping": {},
      "vuln_dates": {
        "CVE-2017-1000084": "2017-10-05T01:29:03",
        "CVE-2022-27195": "2022-03-15T17:15:09"
      },
      "scoring_model": "claude-3-opus-20240229",
      "type": "llm",
      "instruction_template_hash": "245ace12b6361954d0a2"
    }
  ],
  "instruction_template_hash": "10c0163db4740318a544",
  "version": "0.1.0"
}
