{
  "commit": "27bbed0fe459b6a40568ca420f187945109550db",
  "repo_url": "https://github.com/jenkins-infra/update-center2",
  "model": "claude-3-5-sonnet-20240620",
  "chunk_hashes": [
    "f1aa3738f91cdefec20b"
  ],
  "responses": [
    {
      "content": "```yaml\nleads:\n  - headline: Cross-site scripting (XSS) vulnerability in update center JSON processing\n    analysis: |\n      The update center JSON is processed without proper escaping or sanitization of user-controlled input. Specifically, the UpdateCenterRoot class sets fields like 'id' and 'connectionCheckUrl' directly from user input without any validation or escaping. This could allow an attacker to inject malicious JavaScript that would be executed when the update center data is rendered in Jenkins.\n    cwe: CWE-79\n    function_names:\n      - UpdateCenterRoot.constructor\n    filenames:\n      - src/main/java/io/jenkins/update_center/json/UpdateCenterRoot.java\n    classification: slightly promising\n\n  - headline: Sensitive information exposure in exception handling\n    analysis: |\n      Several exception handling blocks log full exception details, including stack traces, at INFO or WARNING level. This could potentially expose sensitive information about the system configuration or internal workings. For example, in the GitHubSource class, the full exception from GitHub API calls is logged. A more secure approach would be to log only limited details at INFO/WARNING level and full details at DEBUG level.\n    cwe: CWE-209\n    function_names:\n      - GitHubSource.init\n      - PluginVersions.constructor\n    filenames:\n      - src/main/java/io/jenkins/update_center/GitHubSource.java\n      - src/main/java/io/jenkins/update_center/json/PluginVersions.java\n    classification: slightly promising\n\n  - headline: Potential path traversal vulnerability in file operations\n    analysis: |\n      The DirectoryTreeBuilder class performs file operations using user-supplied input for directory and file names without proper validation. An attacker could potentially exploit this to access files outside the intended directory structure. The stage() method in particular uses File.getParentFile() and new File() with untrusted input. While some checks are in place, a more robust path canonicalization and validation approach should be used.\n    cwe: CWE-22\n    function_names:\n      - DirectoryTreeBuilder.stage\n    filenames:\n      - src/main/java/io/jenkins/update_center/DirectoryTreeBuilder.java\n    classification: slightly promising\n\n  - headline: Unsafe deserialization of JSON data\n    analysis: |\n      The code uses the Alibaba FastJSON library for parsing JSON data from external sources like GitHub API responses. FastJSON has had vulnerabilities related to unsafe deserialization in the past. While no obvious misuse was found, the widespread use of FastJSON throughout the codebase for parsing untrusted data presents a potential risk if vulnerabilities are discovered in the future. Consider using a more security-focused JSON parsing library.\n    cwe: CWE-502\n    function_names: []\n    filenames:\n      - src/main/java/io/jenkins/update_center/GitHubSource.java\n      - src/main/java/io/jenkins/update_center/json/UpdateCenterRoot.java\n    classification: slightly promising\n\n  - headline: Inadequate access control for sensitive operations\n    analysis: |\n      The update center generation process does not appear to have strong access controls or authentication mechanisms in place. While some operations use credentials (e.g. GitHub API access), many sensitive operations like generating and signing the update center data rely solely on filesystem permissions. Consider implementing more robust authentication and access control, especially for operations that modify update center data.\n    cwe: CWE-284\n    function_names: []\n    filenames:\n      - src/main/java/io/jenkins/update_center/Main.java\n    classification: slightly promising\n```",
      "date": "2024-07-08T06:37:07.505744",
      "usage": {
        "prompt_tokens": 76032,
        "completion_tokens": 850,
        "cost": 0.240846
      }
    }
  ],
  "leads": [
    {
      "headline": "Cross-site scripting (XSS) vulnerability in update center JSON processing",
      "analysis": "The update center JSON is processed without proper escaping or sanitization of user-controlled input. Specifically, the UpdateCenterRoot class sets fields like 'id' and 'connectionCheckUrl' directly from user input without any validation or escaping. This could allow an attacker to inject malicious JavaScript that would be executed when the update center data is rendered in Jenkins.\n",
      "classification": "slightly promising",
      "cwe": "CWE-79",
      "function_names": [
        "UpdateCenterRoot.constructor"
      ],
      "filenames": [
        "src/main/java/io/jenkins/update_center/json/UpdateCenterRoot.java"
      ]
    },
    {
      "headline": "Sensitive information exposure in exception handling",
      "analysis": "Several exception handling blocks log full exception details, including stack traces, at INFO or WARNING level. This could potentially expose sensitive information about the system configuration or internal workings. For example, in the GitHubSource class, the full exception from GitHub API calls is logged. A more secure approach would be to log only limited details at INFO/WARNING level and full details at DEBUG level.\n",
      "classification": "slightly promising",
      "cwe": "CWE-209",
      "function_names": [
        "GitHubSource.init",
        "PluginVersions.constructor"
      ],
      "filenames": [
        "src/main/java/io/jenkins/update_center/GitHubSource.java",
        "src/main/java/io/jenkins/update_center/json/PluginVersions.java"
      ]
    },
    {
      "headline": "Potential path traversal vulnerability in file operations",
      "analysis": "The DirectoryTreeBuilder class performs file operations using user-supplied input for directory and file names without proper validation. An attacker could potentially exploit this to access files outside the intended directory structure. The stage() method in particular uses File.getParentFile() and new File() with untrusted input. While some checks are in place, a more robust path canonicalization and validation approach should be used.\n",
      "classification": "slightly promising",
      "cwe": "CWE-22",
      "function_names": [
        "DirectoryTreeBuilder.stage"
      ],
      "filenames": [
        "src/main/java/io/jenkins/update_center/DirectoryTreeBuilder.java"
      ]
    },
    {
      "headline": "Unsafe deserialization of JSON data",
      "analysis": "The code uses the Alibaba FastJSON library for parsing JSON data from external sources like GitHub API responses. FastJSON has had vulnerabilities related to unsafe deserialization in the past. While no obvious misuse was found, the widespread use of FastJSON throughout the codebase for parsing untrusted data presents a potential risk if vulnerabilities are discovered in the future. Consider using a more security-focused JSON parsing library.\n",
      "classification": "slightly promising",
      "cwe": "CWE-502",
      "function_names": [],
      "filenames": [
        "src/main/java/io/jenkins/update_center/GitHubSource.java",
        "src/main/java/io/jenkins/update_center/json/UpdateCenterRoot.java"
      ]
    },
    {
      "headline": "Inadequate access control for sensitive operations",
      "analysis": "The update center generation process does not appear to have strong access controls or authentication mechanisms in place. While some operations use credentials (e.g. GitHub API access), many sensitive operations like generating and signing the update center data rely solely on filesystem permissions. Consider implementing more robust authentication and access control, especially for operations that modify update center data.\n",
      "classification": "slightly promising",
      "cwe": "CWE-284",
      "function_names": [],
      "filenames": [
        "src/main/java/io/jenkins/update_center/Main.java"
      ]
    }
  ],
  "scores": [
    {
      "stats": {
        "fn": 1,
        "tp": 0,
        "fp": 0
      },
      "mapping": {},
      "vuln_dates": {
        "CVE-2023-27905": "2023-03-10T21:15:15"
      },
      "scoring_model": "claude-3-5-sonnet-20240620",
      "type": "llm",
      "instruction_template_hash": "245ace12b6361954d0a2"
    }
  ],
  "instruction_template_hash": "10c0163db4740318a544",
  "version": "0.1.0"
}
