{
  "commit": "0e0d8e1ba104ae59853f4d4c32522f97ddf30f92",
  "repo_url": "https://github.com/miniprofiler/rack-mini-profiler",
  "model": "gpt-4o-2024-05-13",
  "chunk_hashes": [
    "351253e190f16ed7f70a"
  ],
  "responses": [
    {
      "content": "```yaml\nleads:\n  - headline: \"Potential XSS vulnerability in profile_handler.js\"\n    analysis: |\n      In the file `profile_handler.js`, there is a piece of code that appends fetched data directly to the body. Specifically, the `data-path` attribute in the script tag and various other data-* attributes could be manipulated to inject malicious scripts, leading to a potential XSS vulnerability.\n    cwe: CWE-79\n    function_names:\n      - \"N/A\" # Vulnerability is not tied to a specific function, but rather the overall handling of data attributes.\n    filenames:\n      - \"lib/html/profile_handler.js\"\n    classification: very promising\n\n  - headline: \"Local Storage Security Issue in includes.js\"\n    analysis: |\n      The `includes.js` file contains a function `save` that stores data in `localStorage`. The function does not perform any sanitization or validation of the data being stored. This could potentially be exploited to store malicious scripts which might be executed in future contexts.\n    cwe: CWE-922\n    function_names:\n      - \"save\"\n    filenames:\n      - \"lib/html/includes.js\"\n    classification: slightly promising\n\n  - headline: \"Prototype Pollution in jquery.1.7.1.js\"\n    analysis: |\n      The jQuery version 1.7.1 library (in `jquery.1.7.1.js`) is vulnerable to prototype pollution. An attacker could manipulate the properties of `Object.prototype` which may lead to various forms of data corruption, DOS, or potential remote code execution depending on the application context.\n    cwe: CWE-1321\n    function_names:\n      - \"f.extend\"\n    filenames:\n      - \"lib/html/jquery.1.7.1.js\"\n    classification: slightly promising\n\n  - headline: \"Unrestricted AJAX Response in list.js\"\n    analysis: |\n      In the `list.js`, an AJAX request is made to fetch data and directly appends the data to the DOM without sanitization (`$('table tbody').append($(\"#rowTemplate\").tmpl(data));`). If an attacker gains control over the data source, this could lead to XSS vulnerabilities.\n    cwe: CWE-79\n    function_names:\n      - \"updateGrid\"\n    filenames:\n      - \"lib/html/list.js\"\n    classification: very promising\n\n  - headline: \"JSON Parsing without Validation in includes.js\"\n    analysis: |\n      `includes.js` contains a snippet that parses a JSON response from a server without performing sufficient validation on its structure or content. This could potentially lead to issues if the server response is tampered with.\n    cwe: CWE-502\n    function_names:\n      - \"$.ajax\"\n    filenames:\n      - \"lib/html/includes.js\"\n    classification: slightly promising\n\n  - headline: \"Weak jQuery Version Usage in includes.js\"\n    analysis: |\n      The script `includes.js` uses an outdated version of jQuery (1.7.1), which is known to have multiple vulnerabilities, including XSS, CSRF, and others. It is recommended to update jQuery to the latest stable version.\n    cwe: CWE-674\n    function_names:\n      - \"MiniProfiler.init\"\n    filenames:\n      - \"lib/html/includes.js\"\n    classification: very promising\n```",
      "date": "2024-06-13T10:09:55.933424",
      "usage": {
        "prompt_tokens": 55749,
        "completion_tokens": 682,
        "cost": 0.288975
      }
    }
  ],
  "leads": [
    {
      "headline": "Potential XSS vulnerability in profile_handler.js",
      "analysis": "In the file profile_handler.js, there is a piece of code that appends fetched data directly to the body. Specifically, the data-path attribute in the script tag and various other data-* attributes could be manipulated to inject malicious scripts, leading to a potential XSS vulnerability.\n",
      "classification": "very promising",
      "cwe": "CWE-79",
      "function_names": [
        "N/A"
      ],
      "filenames": [
        "lib/html/profile_handler.js"
      ]
    },
    {
      "headline": "Local Storage Security Issue in includes.js",
      "analysis": "The includes.js file contains a function save that stores data in localStorage. The function does not perform any sanitization or validation of the data being stored. This could potentially be exploited to store malicious scripts which might be executed in future contexts.\n",
      "classification": "slightly promising",
      "cwe": "CWE-922",
      "function_names": [
        "save"
      ],
      "filenames": [
        "lib/html/includes.js"
      ]
    },
    {
      "headline": "Prototype Pollution in jquery.1.7.1.js",
      "analysis": "The jQuery version 1.7.1 library (in jquery.1.7.1.js) is vulnerable to prototype pollution. An attacker could manipulate the properties of Object.prototype which may lead to various forms of data corruption, DOS, or potential remote code execution depending on the application context.\n",
      "classification": "slightly promising",
      "cwe": "CWE-1321",
      "function_names": [
        "f.extend"
      ],
      "filenames": [
        "lib/html/jquery.1.7.1.js"
      ]
    },
    {
      "headline": "Unrestricted AJAX Response in list.js",
      "analysis": "In the list.js, an AJAX request is made to fetch data and directly appends the data to the DOM without sanitization ($('table tbody').append($(\"#rowTemplate\").tmpl(data));). If an attacker gains control over the data source, this could lead to XSS vulnerabilities.\n",
      "classification": "very promising",
      "cwe": "CWE-79",
      "function_names": [
        "updateGrid"
      ],
      "filenames": [
        "lib/html/list.js"
      ]
    },
    {
      "headline": "JSON Parsing without Validation in includes.js",
      "analysis": "includes.js contains a snippet that parses a JSON response from a server without performing sufficient validation on its structure or content. This could potentially lead to issues if the server response is tampered with.\n",
      "classification": "slightly promising",
      "cwe": "CWE-502",
      "function_names": [
        "$.ajax"
      ],
      "filenames": [
        "lib/html/includes.js"
      ]
    },
    {
      "headline": "Weak jQuery Version Usage in includes.js",
      "analysis": "The script includes.js uses an outdated version of jQuery (1.7.1), which is known to have multiple vulnerabilities, including XSS, CSRF, and others. It is recommended to update jQuery to the latest stable version.\n",
      "classification": "very promising",
      "cwe": "CWE-674",
      "function_names": [
        "MiniProfiler.init"
      ],
      "filenames": [
        "lib/html/includes.js"
      ]
    }
  ],
  "scores": [
    {
      "stats": {
        "fn": 1,
        "tp": 0,
        "fp": 3
      },
      "mapping": {},
      "vuln_dates": {
        "CVE-2016-4442": "2017-05-02T14:59:00"
      },
      "scoring_model": "claude-3-opus-20240229",
      "type": "llm",
      "instruction_template_hash": "245ace12b6361954d0a2"
    },
    {
      "stats": {
        "fn": 1,
        "tp": 0,
        "fp": 3
      },
      "mapping": {},
      "vuln_dates": {
        "CVE-2016-4442": "2017-05-02T14:59:00"
      },
      "scoring_model": "claude-3-5-sonnet-20240620",
      "type": "llm",
      "instruction_template_hash": "245ace12b6361954d0a2"
    }
  ],
  "instruction_template_hash": "10c0163db4740318a544",
  "version": "0.1.0"
}
