{
  "commit": "a6d143d1ae30cc58fce8e9769e2a489db1e55b7d",
  "repo_url": "https://github.com/xwikisas/identity-oauth",
  "model": "gpt-4o-2024-05-13",
  "chunk_hashes": [
    "dbc8de846abdbb39fecc"
  ],
  "responses": [
    {
      "content": "```yaml\nleads:\n  - headline: \"Exposure of Sensitive Information via exception messages\"\n    analysis: |\n      The method `getProvider` in `IdentityOAuthScriptService` throws an `IllegalStateException` with a potentially sensitive message that could leak internal system details. Similarly, other exception messages in the module could reveal internal workings.\n    cwe: CWE-209\n    function_names:\n      - getProvider\n    filenames:\n      - api/src/main/java/com/xwiki/identityoauth/IdentityOAuthScriptService.java\n    classification: very promising\n\n  - headline: \"Hardcoded cryptographic secrets\"\n    analysis: |\n      The cryptographic key is read from a configuration source and potentially falls back to a hardcoded default key within the `CookieAuthenticationPersistence` class. Hardcoding such keys present a vulnerability as it can be easily exploited if discovered.\n    cwe: CWE-798\n    function_names:\n      - encryptText\n      - decryptText\n    filenames:\n      - api/src/main/java/com/xwiki/identityoauth/internal/CookieAuthenticationPersistence.java\n    classification: very promising\n\n  - headline: \"Inadequate validation for redirect URLs\"\n    analysis: |\n      In the `DefaultIdentityOAuthManager`, the redirect URL in OAuth flow may not be properly validated, opening the door for open redirect attacks. This occurs in the `processOAuthStart` method where the URL construction might be influenced by untrusted input.\n    cwe: CWE-601\n    function_names:\n      - processOAuthStart\n    filenames:\n      - api/src/main/java/com/xwiki/identityoauth/internal/DefaultIdentityOAuthManager.java\n    classification: very promising\n\n  - headline: \"Potential Cross-Site Scripting (XSS) in rendered HTML\"\n    analysis: |\n      The `renderLoginCodes` method in `DefaultIdentityOAuthManager` converts login codes to HTML without apparent sanitization, which might lead to XSS if inputs are controlled by attackers.\n    cwe: CWE-79\n    function_names:\n      - renderLoginCodes\n    filenames:\n      - api/src/main/java/com/xwiki/identityoauth/internal/DefaultIdentityOAuthManager.java\n    classification: slightly promising\n\n  - headline: \"Improper Error Handling\"\n    analysis: |\n      Multiple instances in the codebase utilize broad exception clauses such as `catch (Exception e)` which can lead to improper handling of unexpected conditions and might expose sensitive information or mask real issues.\n    cwe: CWE-754\n    function_names:\n      - checkAuth\n      - authenticate\n      - showLogin\n    filenames:\n      - api/src/main/java/com/xwiki/identityoauth/internal/IdentityOAuthAuthService.java\n    classification: slightly promising\n\n  - headline: \"Lack of request validation\"\n    analysis: |\n      The method `processOAuthStart` in `DefaultIdentityOAuthManager` does not appear to adequately validate its HttpServletRequest parameters, which could lead to issues like SQL injection, command injection, or other forms of attacks based on parameter manipulation.\n    cwe: CWE-20\n    function_names:\n      - processOAuthStart\n    filenames:\n      - api/src/main/java/com/xwiki/identityoauth/internal/DefaultIdentityOAuthManager.java\n    classification: very promising\n```",
      "date": "2024-06-09T15:33:04.686864",
      "usage": {
        "prompt_tokens": 24806,
        "completion_tokens": 667,
        "cost": 0.134035
      }
    }
  ],
  "leads": [
    {
      "headline": "Exposure of Sensitive Information via exception messages",
      "analysis": "The method getProvider in IdentityOAuthScriptService throws an IllegalStateException with a potentially sensitive message that could leak internal system details. Similarly, other exception messages in the module could reveal internal workings.\n",
      "classification": "very promising",
      "cwe": "CWE-209",
      "function_names": [
        "getProvider"
      ],
      "filenames": [
        "api/src/main/java/com/xwiki/identityoauth/IdentityOAuthScriptService.java"
      ]
    },
    {
      "headline": "Hardcoded cryptographic secrets",
      "analysis": "The cryptographic key is read from a configuration source and potentially falls back to a hardcoded default key within the CookieAuthenticationPersistence class. Hardcoding such keys present a vulnerability as it can be easily exploited if discovered.\n",
      "classification": "very promising",
      "cwe": "CWE-798",
      "function_names": [
        "encryptText",
        "decryptText"
      ],
      "filenames": [
        "api/src/main/java/com/xwiki/identityoauth/internal/CookieAuthenticationPersistence.java"
      ]
    },
    {
      "headline": "Inadequate validation for redirect URLs",
      "analysis": "In the DefaultIdentityOAuthManager, the redirect URL in OAuth flow may not be properly validated, opening the door for open redirect attacks. This occurs in the processOAuthStart method where the URL construction might be influenced by untrusted input.\n",
      "classification": "very promising",
      "cwe": "CWE-601",
      "function_names": [
        "processOAuthStart"
      ],
      "filenames": [
        "api/src/main/java/com/xwiki/identityoauth/internal/DefaultIdentityOAuthManager.java"
      ]
    },
    {
      "headline": "Potential Cross-Site Scripting (XSS) in rendered HTML",
      "analysis": "The renderLoginCodes method in DefaultIdentityOAuthManager converts login codes to HTML without apparent sanitization, which might lead to XSS if inputs are controlled by attackers.\n",
      "classification": "slightly promising",
      "cwe": "CWE-79",
      "function_names": [
        "renderLoginCodes"
      ],
      "filenames": [
        "api/src/main/java/com/xwiki/identityoauth/internal/DefaultIdentityOAuthManager.java"
      ]
    },
    {
      "headline": "Improper Error Handling",
      "analysis": "Multiple instances in the codebase utilize broad exception clauses such as catch (Exception e) which can lead to improper handling of unexpected conditions and might expose sensitive information or mask real issues.\n",
      "classification": "slightly promising",
      "cwe": "CWE-754",
      "function_names": [
        "checkAuth",
        "authenticate",
        "showLogin"
      ],
      "filenames": [
        "api/src/main/java/com/xwiki/identityoauth/internal/IdentityOAuthAuthService.java"
      ]
    },
    {
      "headline": "Lack of request validation",
      "analysis": "The method processOAuthStart in DefaultIdentityOAuthManager does not appear to adequately validate its HttpServletRequest parameters, which could lead to issues like SQL injection, command injection, or other forms of attacks based on parameter manipulation.\n",
      "classification": "very promising",
      "cwe": "CWE-20",
      "function_names": [
        "processOAuthStart"
      ],
      "filenames": [
        "api/src/main/java/com/xwiki/identityoauth/internal/DefaultIdentityOAuthManager.java"
      ]
    }
  ],
  "scores": [
    {
      "stats": {
        "fn": 1,
        "tp": 0,
        "fp": 4
      },
      "mapping": {},
      "vuln_dates": {
        "CVE-2023-45144": "2023-10-16T21:15:11"
      },
      "scoring_model": "gpt-4o-2024-05-13",
      "type": "llm",
      "instruction_template_hash": "8998f09cf57fca8a6e03"
    },
    {
      "stats": {
        "fn": 1,
        "tp": 0,
        "fp": 4
      },
      "mapping": {},
      "vuln_dates": {
        "CVE-2023-45144": "2023-10-16T21:15:11"
      },
      "scoring_model": "claude-3-opus-20240229",
      "type": "llm",
      "instruction_template_hash": "245ace12b6361954d0a2"
    }
  ],
  "instruction_template_hash": "10c0163db4740318a544",
  "version": "0.1.0"
}
