{
  "commit": "361fb8b9b31bd64c696105ef0b56ee253aa4ca0c",
  "repo_url": "https://github.com/pf4j/pf4j",
  "model": "claude-3-sonnet-20240229",
  "chunk_hashes": [
    "2fc1c7f1ea79316e13aa"
  ],
  "responses": [
    {
      "content": "```yaml\nleads:\n  - headline: Improper Input Validation (CWE-20)\n    analysis: |\n      The codebase contains instances where user input is not properly validated, potentially leading to security vulnerabilities such as code injection or path traversal attacks.\n    cwe: CWE-20\n    function_names:\n      - org.pf4j.DefaultPluginManager.loadPluginFromPath\n      - org.pf4j.DefaultPluginDescriptor.setDependencies\n    filenames:\n      - pf4j/src/main/java/org/pf4j/DefaultPluginManager.java\n      - pf4j/src/main/java/org/pf4j/DefaultPluginDescriptor.java\n    classification: very promising\n\n  - headline: Code Injection (CWE-94)\n    analysis: |\n      The codebase appears to dynamically load and execute code from external sources, such as plugins or extensions, without proper validation or sandboxing mechanisms in place. This could potentially lead to code injection vulnerabilities.\n    cwe: CWE-94\n    function_names:\n      - org.pf4j.DefaultPluginFactory.createInstance\n    filenames:\n      - pf4j/src/main/java/org/pf4j/DefaultPluginFactory.java\n    classification: very promising\n\n  - headline: Insecure Deserialization (CWE-502)\n    analysis: |\n      The codebase appears to deserialize untrusted data, which could potentially lead to insecure deserialization vulnerabilities if the deserialized objects are not properly validated or sanitized.\n    cwe: CWE-502\n    function_names:\n      - org.pf4j.DefaultPluginFactory.createInstance\n    filenames:\n      - pf4j/src/main/java/org/pf4j/DefaultPluginFactory.java\n    classification: slightly promising\n\n  - headline: Potential Path Traversal Vulnerability (CWE-22)\n    analysis: |\n      The codebase appears to use user-supplied input to construct file paths without proper validation, potentially leading to path traversal vulnerabilities.\n    cwe: CWE-22\n    function_names:\n      - org.pf4j.util.FileUtils.expandIfZip\n      - org.pf4j.util.FileUtils.getPath\n    filenames:\n      - pf4j/src/main/java/org/pf4j/util/FileUtils.java\n    classification: very promising\n\n  - headline: Potential Symbolic Link Traversal (CWE-59)\n    analysis: |\n      The codebase appears to handle symbolic links when processing file paths, which could potentially lead to symbolic link traversal vulnerabilities if the links are not properly validated.\n    cwe: CWE-59\n    function_names:\n      - org.pf4j.util.FileUtils.delete\n    filenames:\n      - pf4j/src/main/java/org/pf4j/util/FileUtils.java\n    classification: slightly promising\n```\n\nThe provided codebase is PF4J, which is a plugin framework for Java. Based on the analysis, I have identified a few potential security vulnerabilities in the codebase.\n\n1. **Improper Input Validation (CWE-20)**: The codebase appears to have instances where user input is not properly validated, potentially leading to security vulnerabilities such as code injection or path traversal attacks. This vulnerability is present in the `org.pf4j.DefaultPluginManager.loadPluginFromPath` and `org.pf4j.DefaultPluginDescriptor.setDependencies` methods.\n\n2. **Code Injection (CWE-94)**: The codebase dynamically loads and executes code from external sources, such as plugins or extensions, without proper validation or sandboxing mechanisms in place. This could potentially lead to code injection vulnerabilities. This vulnerability is present in the `org.pf4j.DefaultPluginFactory.createInstance` method.\n\n3. **Insecure Deserialization (CWE-502)**: The codebase appears to deserialize untrusted data, which could potentially lead to insecure deserialization vulnerabilities if the deserialized objects are not properly validated or sanitized. This vulnerability is also present in the `org.pf4j.DefaultPluginFactory.createInstance` method.\n\n4. **Potential Path Traversal Vulnerability (CWE-22)**: The codebase appears to use user-supplied input to construct file paths without proper validation, potentially leading to path traversal vulnerabilities. This vulnerability is present in the `org.pf4j.util.FileUtils.expandIfZip` and `org.pf4j.util.FileUtils.getPath` methods.\n\n5. **Potential Symbolic Link Traversal (CWE-59)**: The codebase appears to handle symbolic links when processing file paths, which could potentially lead to symbolic link traversal vulnerabilities if the links are not properly validated. This vulnerability is present in the `org.pf4j.util.FileUtils.delete` method.\n\nIt's important to note that these are potential vulnerabilities identified based on the analysis of the codebase. Further investigation and testing may be required to confirm the presence and severity of these vulnerabilities in the specific context of the application using PF4J.",
      "date": "2024-06-14T15:15:22.731338",
      "usage": {
        "prompt_tokens": 139870,
        "completion_tokens": 1259,
        "cost": 0.438495
      }
    }
  ],
  "leads": [
    {
      "headline": "Improper Input Validation (CWE-20)",
      "analysis": "The codebase contains instances where user input is not properly validated, potentially leading to security vulnerabilities such as code injection or path traversal attacks.\n",
      "classification": "very promising",
      "cwe": "CWE-20",
      "function_names": [
        "org.pf4j.DefaultPluginManager.loadPluginFromPath",
        "org.pf4j.DefaultPluginDescriptor.setDependencies"
      ],
      "filenames": [
        "pf4j/src/main/java/org/pf4j/DefaultPluginManager.java",
        "pf4j/src/main/java/org/pf4j/DefaultPluginDescriptor.java"
      ]
    },
    {
      "headline": "Code Injection (CWE-94)",
      "analysis": "The codebase appears to dynamically load and execute code from external sources, such as plugins or extensions, without proper validation or sandboxing mechanisms in place. This could potentially lead to code injection vulnerabilities.\n",
      "classification": "very promising",
      "cwe": "CWE-94",
      "function_names": [
        "org.pf4j.DefaultPluginFactory.createInstance"
      ],
      "filenames": [
        "pf4j/src/main/java/org/pf4j/DefaultPluginFactory.java"
      ]
    },
    {
      "headline": "Insecure Deserialization (CWE-502)",
      "analysis": "The codebase appears to deserialize untrusted data, which could potentially lead to insecure deserialization vulnerabilities if the deserialized objects are not properly validated or sanitized.\n",
      "classification": "slightly promising",
      "cwe": "CWE-502",
      "function_names": [
        "org.pf4j.DefaultPluginFactory.createInstance"
      ],
      "filenames": [
        "pf4j/src/main/java/org/pf4j/DefaultPluginFactory.java"
      ]
    },
    {
      "headline": "Potential Path Traversal Vulnerability (CWE-22)",
      "analysis": "The codebase appears to use user-supplied input to construct file paths without proper validation, potentially leading to path traversal vulnerabilities.\n",
      "classification": "very promising",
      "cwe": "CWE-22",
      "function_names": [
        "org.pf4j.util.FileUtils.expandIfZip",
        "org.pf4j.util.FileUtils.getPath"
      ],
      "filenames": [
        "pf4j/src/main/java/org/pf4j/util/FileUtils.java"
      ]
    },
    {
      "headline": "Potential Symbolic Link Traversal (CWE-59)",
      "analysis": "The codebase appears to handle symbolic links when processing file paths, which could potentially lead to symbolic link traversal vulnerabilities if the links are not properly validated.\n",
      "classification": "slightly promising",
      "cwe": "CWE-59",
      "function_names": [
        "org.pf4j.util.FileUtils.delete"
      ],
      "filenames": [
        "pf4j/src/main/java/org/pf4j/util/FileUtils.java"
      ]
    }
  ],
  "scores": [
    {
      "stats": {
        "fn": 2,
        "tp": 1,
        "fp": 2
      },
      "mapping": {
        "2": "CVE-2023-40828"
      },
      "vuln_dates": {
        "CVE-2023-40827": "2023-08-28T22:15:09",
        "CVE-2023-40826": "2023-08-28T22:15:09",
        "CVE-2023-40828": "2023-08-28T22:15:09"
      },
      "scoring_model": "claude-3-opus-20240229",
      "type": "llm",
      "instruction_template_hash": "245ace12b6361954d0a2"
    },
    {
      "stats": {
        "fn": 1,
        "tp": 2,
        "fp": 0
      },
      "mapping": {
        "0": "CVE-2023-40827",
        "1": "CVE-2023-40827",
        "2": "CVE-2023-40828"
      },
      "vuln_dates": {
        "CVE-2023-40827": "2023-08-28T22:15:09",
        "CVE-2023-40826": "2023-08-28T22:15:09",
        "CVE-2023-40828": "2023-08-28T22:15:09"
      },
      "scoring_model": "claude-3-5-sonnet-20240620",
      "type": "llm",
      "instruction_template_hash": "245ace12b6361954d0a2"
    }
  ],
  "instruction_template_hash": "10c0163db4740318a544",
  "version": "0.1.0"
}
