{
  "commit": "1253ad7edf2febaa0b644db3953650c70bc6c234",
  "repo_url": "https://github.com/mopemope/meinheld",
  "model": "claude-3-5-sonnet-20240620",
  "chunk_hashes": [
    "a9dea6c594dcaa3613ad"
  ],
  "responses": [
    {
      "content": "Based on my analysis, here are the main security vulnerabilities I identified in the Meinheld codebase:\n\n1. Buffer Overflow (CWE-120):\n   - In the `write2buf` function in buffer.c, there is potential for a buffer overflow if the new length exceeds the buffer size. The reallocation logic should be more robust to prevent overflows.\n\n2. Improper Input Validation (CWE-20):\n   - The URL parsing and request handling code in http_request_parser.c does not appear to do thorough input validation and sanitization, which could lead to injection attacks.\n\n3. Use of Broken or Risky Cryptographic Algorithm (CWE-327):\n   - The code uses MD5 hashing in a few places, which is considered cryptographically weak. More secure alternatives should be used.\n\n4. Integer Overflow (CWE-190):\n   - There are several places where integer arithmetic is performed without proper overflow checks, like in the timer and request handling code.\n\n5. Information Exposure (CWE-200): \n   - Error messages and logging may expose sensitive information about the server internals.\n\n6. Improper Privilege Management (CWE-269):\n   - The server does not appear to drop privileges after binding to low ports, potentially running with excess privileges.\n\n7. Use of Hard-coded Credentials (CWE-798):\n   - There are some hard-coded values used for things like buffer sizes that could potentially be exposed.\n\n8. Uncontrolled Resource Consumption (CWE-400):\n   - The request handling and connection management does not appear to have robust limits, which could allow denial of service attacks.\n\n9. Race Condition (CWE-362):\n   - The multi-threaded nature of the server introduces potential race conditions around shared state that are not fully protected.\n\nTo provide this analysis in the requested YAML format:\n\n```yaml\nleads:\n  - headline: Buffer overflow vulnerability in write2buf function\n    analysis: |\n      The write2buf function in buffer.c reallocates the buffer when more space is needed, but does not properly handle cases where the new length could exceed the maximum buffer size. This could potentially allow an attacker to cause a buffer overflow by sending carefully crafted input. The reallocation logic should be updated to have proper bounds checking and handle error cases more robustly.\n    cwe: CWE-120\n    function_names: \n      - write2buf\n    filenames:\n      - meinheld/server/buffer.c  \n    classification: very promising\n\n  - headline: Lack of input validation in HTTP request parsing\n    analysis: |\n      The HTTP request parsing code in http_request_parser.c does not appear to do thorough input validation and sanitization of incoming requests. This could potentially allow injection attacks or other malicious inputs to be processed. More rigorous validation should be added for all request components including headers, URLs, etc. Proper escaping and encoding should also be enforced.\n    cwe: CWE-20\n    function_names:\n      - parse_http_request  \n    filenames:\n      - meinheld/server/http_request_parser.c\n    classification: very promising\n\n  - headline: Use of weak MD5 hashing algorithm\n    analysis: |\n      The code uses the MD5 hashing algorithm in a few places, which is considered cryptographically weak and vulnerable to collision attacks. More secure hashing algorithms like SHA-256 should be used instead. The specific usage of MD5 should be audited to determine if it poses an actual security risk in this context.\n    cwe: CWE-327\n    function_names:\n      - http_parser_parse_url\n    filenames:\n      - meinheld/server/http_parser.c\n    classification: slightly promising\n\n  - headline: Potential integer overflows in timer and request handling\n    analysis: |\n      There are several places where integer arithmetic is performed without proper overflow checks, particularly in the timer management code and request size tracking. This could potentially be exploited to cause unexpected behavior. Explicit checks for integer overflow conditions should be added, and safer arithmetic operations used where possible.\n    cwe: CWE-190  \n    function_names:\n      - TimerObject_new\n      - parse_http_request\n    filenames:\n      - meinheld/server/timer.c\n      - meinheld/server/http_request_parser.c\n    classification: slightly promising\n\n  - headline: Excessive information in error messages and logs  \n    analysis: |\n      The error handling and logging code may expose more information about the internal server state and structure than necessary. This could potentially aid attackers in understanding and exploiting the system. Error messages and logs should be audited to ensure they do not contain sensitive information, and a consistent error handling approach should be implemented.\n    cwe: CWE-200\n    function_names:\n      - call_error_logger\n    filenames:\n      - meinheld/server/log.c\n    classification: slightly promising\n```\n\nThis covers the top 5 most significant vulnerabilities I identified. Let me know if you would like me to elaborate on any of these or provide additional findings.",
      "date": "2024-07-08T07:52:34.427902",
      "usage": {
        "prompt_tokens": 143737,
        "completion_tokens": 1183,
        "cost": 0.448956
      }
    }
  ],
  "leads": [
    {
      "headline": "Buffer overflow vulnerability in write2buf function",
      "analysis": "The write2buf function in buffer.c reallocates the buffer when more space is needed, but does not properly handle cases where the new length could exceed the maximum buffer size. This could potentially allow an attacker to cause a buffer overflow by sending carefully crafted input. The reallocation logic should be updated to have proper bounds checking and handle error cases more robustly.\n",
      "classification": "very promising",
      "cwe": "CWE-120",
      "function_names": [
        "write2buf"
      ],
      "filenames": [
        "meinheld/server/buffer.c"
      ]
    },
    {
      "headline": "Lack of input validation in HTTP request parsing",
      "analysis": "The HTTP request parsing code in http_request_parser.c does not appear to do thorough input validation and sanitization of incoming requests. This could potentially allow injection attacks or other malicious inputs to be processed. More rigorous validation should be added for all request components including headers, URLs, etc. Proper escaping and encoding should also be enforced.\n",
      "classification": "very promising",
      "cwe": "CWE-20",
      "function_names": [
        "parse_http_request"
      ],
      "filenames": [
        "meinheld/server/http_request_parser.c"
      ]
    },
    {
      "headline": "Use of weak MD5 hashing algorithm",
      "analysis": "The code uses the MD5 hashing algorithm in a few places, which is considered cryptographically weak and vulnerable to collision attacks. More secure hashing algorithms like SHA-256 should be used instead. The specific usage of MD5 should be audited to determine if it poses an actual security risk in this context.\n",
      "classification": "slightly promising",
      "cwe": "CWE-327",
      "function_names": [
        "http_parser_parse_url"
      ],
      "filenames": [
        "meinheld/server/http_parser.c"
      ]
    },
    {
      "headline": "Potential integer overflows in timer and request handling",
      "analysis": "There are several places where integer arithmetic is performed without proper overflow checks, particularly in the timer management code and request size tracking. This could potentially be exploited to cause unexpected behavior. Explicit checks for integer overflow conditions should be added, and safer arithmetic operations used where possible.\n",
      "classification": "slightly promising",
      "cwe": "CWE-190",
      "function_names": [
        "TimerObject_new",
        "parse_http_request"
      ],
      "filenames": [
        "meinheld/server/timer.c",
        "meinheld/server/http_request_parser.c"
      ]
    },
    {
      "headline": "Excessive information in error messages and logs",
      "analysis": "The error handling and logging code may expose more information about the internal server state and structure than necessary. This could potentially aid attackers in understanding and exploiting the system. Error messages and logs should be audited to ensure they do not contain sensitive information, and a consistent error handling approach should be implemented.\n",
      "classification": "slightly promising",
      "cwe": "CWE-200",
      "function_names": [
        "call_error_logger"
      ],
      "filenames": [
        "meinheld/server/log.c"
      ]
    }
  ],
  "scores": [
    {
      "stats": {
        "fn": 1,
        "tp": 0,
        "fp": 2
      },
      "mapping": {},
      "vuln_dates": {
        "CVE-2020-7658": "2020-05-22T16:15:10"
      },
      "scoring_model": "claude-3-5-sonnet-20240620",
      "type": "llm",
      "instruction_template_hash": "245ace12b6361954d0a2"
    }
  ],
  "instruction_template_hash": "10c0163db4740318a544",
  "version": "0.1.0"
}
