{
  "commit": "1b3e967ee51d409f223b36e42a55f88b76b10741",
  "repo_url": "https://github.com/jenkinsci/jira-plugin",
  "model": "claude-3-sonnet-20240229",
  "chunk_hashes": [
    "8a1723dfdad37b2df0b7"
  ],
  "responses": [
    {
      "content": "Here is the YAML response with the identified security vulnerabilities in the provided codebase:\n\n```yaml\nleads:\n  - headline: Use of Hard-coded Credentials\n    analysis: |\n      The JiraSite class contains hard-coded credentials (username and password) in its constructor, which are used to create a JiraRestClient instance. Hard-coding credentials in source code is a security vulnerability as it can expose sensitive information if the code is shared or accessed by unauthorized parties.\n    cwe: CWE-798\n    function_names:\n      - JiraSite.<init>\n      - JiraRestService.<init>\n    filenames:\n      - src/main/java/hudson/plugins/jira/JiraSite.java\n      - src/main/java/hudson/plugins/jira/JiraRestService.java\n    classification: very promising\n\n  - headline: Improper Neutralization of Special Elements used in an OS Command ('OS Command Injection')\n    analysis: |\n      The JiraSession class constructs a JQL query string by concatenating user input (the `query` parameter) without proper validation or sanitization. This could allow an attacker to inject malicious code into the query, potentially leading to OS command injection vulnerabilities.\n    cwe: CWE-78\n    function_names:\n      - JiraSession.replaceFixVersion\n      - JiraSession.migrateIssuesToFixVersion\n    filenames:\n      - src/main/java/hudson/plugins/jira/JiraSession.java\n    classification: very promising\n\n  - headline: Cleartext Storage of Sensitive Information\n    analysis: |\n      The JiraSite class stores the JIRA password in cleartext using the Secret class. While the Secret class may provide some obfuscation, storing sensitive information such as passwords in cleartext is a security vulnerability as it can be easily accessed by unauthorized parties if the code or data is compromised.\n    cwe: CWE-312\n    function_names:\n      - JiraSite.<init>\n    filenames:\n      - src/main/java/hudson/plugins/jira/JiraSite.java\n    classification: very promising\n\n  - headline: Improper Handling of Exceptional Conditions\n    analysis: |\n      The JiraRestService class catches exceptions in various methods but does not handle them properly. In many cases, it simply logs a warning message and continues execution, which could lead to unexpected behavior or vulnerabilities if the exception was caused by malicious input or other security issues.\n    cwe: CWE-755\n    function_names:\n      - JiraRestService.addComment\n      - JiraRestService.getIssue\n      - JiraRestService.getIssueTypes\n      - JiraRestService.getProjectsKeys\n      - JiraRestService.getIssuesFromJqlSearch\n      - JiraRestService.getVersions\n      - JiraRestService.addVersion\n      - JiraRestService.releaseVersion\n      - JiraRestService.createIssue\n      - JiraRestService.getUser\n      - JiraRestService.updateIssue\n      - JiraRestService.progressWorkflowAction\n      - JiraRestService.getAvailableActions\n      - JiraRestService.getStatuses\n      - JiraRestService.getComponents\n    filenames:\n      - src/main/java/hudson/plugins/jira/JiraRestService.java\n    classification: very promising\n\n  - headline: Improper Input Validation\n    analysis: |\n      Several classes, such as JiraVersionParameterDefinition, JiraIssueMigrator, JiraCreateReleaseNotes, and JiraVersionCreator, do not properly validate user input (e.g., project key, version name, JQL query) before using it in API calls or constructing queries. This could potentially lead to injection vulnerabilities or other security issues.\n    cwe: CWE-20\n    function_names:\n      - JiraVersionParameterDefinition.getVersions\n      - JiraIssueMigrator.perform\n      - JiraCreateReleaseNotes.setUp\n      - JiraVersionCreator.perform\n    filenames:\n      - src/main/java/hudson/plugins/jira/versionparameter/JiraVersionParameterDefinition.java\n      - src/main/java/hudson/plugins/jira/JiraIssueMigrator.java\n      - src/main/java/hudson/plugins/jira/JiraCreateReleaseNotes.java\n      - src/main/java/hudson/plugins/jira/JiraVersionCreator.java\n    classification: slightly promising\n\n  - headline: Missing Authentication for Critical Function\n    analysis: |\n      The JiraRestService class allows adding comments to JIRA issues without any authentication or authorization checks. This could potentially allow unauthorized parties to add comments to JIRA issues, which could be a security vulnerability.\n    cwe: CWE-306\n    function_names:\n      - JiraRestService.addCommentWithoutConstrains\n    filenames:\n      - src/main/java/hudson/plugins/jira/JiraRestService.java\n    classification: slightly promising\n\n  - headline: Insufficient Verification of Data Authenticity\n    analysis: |\n      The JiraCreateIssueNotifier class retrieves the JIRA issue ID from a file in the job's directory, but does not verify the authenticity or integrity of the data in the file. This could potentially allow an attacker to modify the file and cause unauthorized actions or data manipulation.\n    cwe: CWE-345\n    function_names:\n      - JiraCreateIssueNotifier.getIssue\n    filenames:\n      - src/main/java/hudson/plugins/jira/JiraCreateIssueNotifier.java\n    classification: slightly promising\n\n  - headline: Improper Restriction of Operations within the Bounds of a Memory Buffer\n    analysis: |\n      The JiraRestService class uses the `objectMapper.readValue` method to parse JSON responses from the JIRA API. If the JSON data is not properly validated or sanitized, it could potentially lead to buffer overflow vulnerabilities.\n    cwe: CWE-119\n    function_names:\n      - JiraRestService.getVersions\n      - JiraRestService.getComponents\n    filenames:\n      - src/main/java/hudson/plugins/jira/JiraRestService.java\n    classification: not promising\n\n  - headline: Use of Uninitialized Resource\n    analysis: |\n      The JiraSession class uses uninitialized resources (projectKeys and knownStatuses) in some methods, which could potentially lead to null pointer exceptions or other unexpected behavior.\n    cwe: CWE-908\n    function_names:\n      - JiraSession.getProjectKeys\n      - JiraSession.getStatusById\n    filenames:\n      - src/main/java/hudson/plugins/jira/JiraSession.java\n    classification: not promising\n```\n\nNote: The classification of the vulnerabilities is based on my subjective assessment of their potential impact and exploitability. It is recommended to thoroughly review and address all identified vulnerabilities, regardless of their classification.",
      "date": "2024-06-09T12:52:03.551311",
      "usage": {
        "prompt_tokens": 70030,
        "completion_tokens": 1675,
        "cost": 0.235215
      }
    }
  ],
  "leads": [
    {
      "headline": "Use of Hard-coded Credentials",
      "analysis": "The JiraSite class contains hard-coded credentials (username and password) in its constructor, which are used to create a JiraRestClient instance. Hard-coding credentials in source code is a security vulnerability as it can expose sensitive information if the code is shared or accessed by unauthorized parties.\n",
      "classification": "very promising",
      "cwe": "CWE-798",
      "function_names": [
        "JiraSite.<init>",
        "JiraRestService.<init>"
      ],
      "filenames": [
        "src/main/java/hudson/plugins/jira/JiraSite.java",
        "src/main/java/hudson/plugins/jira/JiraRestService.java"
      ]
    },
    {
      "headline": "Improper Neutralization of Special Elements used in an OS Command ('OS Command Injection')",
      "analysis": "The JiraSession class constructs a JQL query string by concatenating user input (the query parameter) without proper validation or sanitization. This could allow an attacker to inject malicious code into the query, potentially leading to OS command injection vulnerabilities.\n",
      "classification": "very promising",
      "cwe": "CWE-78",
      "function_names": [
        "JiraSession.replaceFixVersion",
        "JiraSession.migrateIssuesToFixVersion"
      ],
      "filenames": [
        "src/main/java/hudson/plugins/jira/JiraSession.java"
      ]
    },
    {
      "headline": "Cleartext Storage of Sensitive Information",
      "analysis": "The JiraSite class stores the JIRA password in cleartext using the Secret class. While the Secret class may provide some obfuscation, storing sensitive information such as passwords in cleartext is a security vulnerability as it can be easily accessed by unauthorized parties if the code or data is compromised.\n",
      "classification": "very promising",
      "cwe": "CWE-312",
      "function_names": [
        "JiraSite.<init>"
      ],
      "filenames": [
        "src/main/java/hudson/plugins/jira/JiraSite.java"
      ]
    },
    {
      "headline": "Improper Handling of Exceptional Conditions",
      "analysis": "The JiraRestService class catches exceptions in various methods but does not handle them properly. In many cases, it simply logs a warning message and continues execution, which could lead to unexpected behavior or vulnerabilities if the exception was caused by malicious input or other security issues.\n",
      "classification": "very promising",
      "cwe": "CWE-755",
      "function_names": [
        "JiraRestService.addComment",
        "JiraRestService.getIssue",
        "JiraRestService.getIssueTypes"
      ],
      "filenames": [
        "src/main/java/hudson/plugins/jira/JiraRestService.java"
      ]
    },
    {
      "headline": "Improper Input Validation",
      "analysis": "Several classes, such as JiraVersionParameterDefinition, JiraIssueMigrator, JiraCreateReleaseNotes, and JiraVersionCreator, do not properly validate user input (e.g., project key, version name, JQL query) before using it in API calls or constructing queries. This could potentially lead to injection vulnerabilities or other security issues.\n",
      "classification": "slightly promising",
      "cwe": "CWE-20",
      "function_names": [
        "JiraVersionParameterDefinition.getVersions",
        "JiraIssueMigrator.perform",
        "JiraCreateReleaseNotes.setUp"
      ],
      "filenames": [
        "src/main/java/hudson/plugins/jira/versionparameter/JiraVersionParameterDefinition.java",
        "src/main/java/hudson/plugins/jira/JiraIssueMigrator.java",
        "src/main/java/hudson/plugins/jira/JiraCreateReleaseNotes.java"
      ]
    },
    {
      "headline": "Missing Authentication for Critical Function",
      "analysis": "The JiraRestService class allows adding comments to JIRA issues without any authentication or authorization checks. This could potentially allow unauthorized parties to add comments to JIRA issues, which could be a security vulnerability.\n",
      "classification": "slightly promising",
      "cwe": "CWE-306",
      "function_names": [
        "JiraRestService.addCommentWithoutConstrains"
      ],
      "filenames": [
        "src/main/java/hudson/plugins/jira/JiraRestService.java"
      ]
    },
    {
      "headline": "Insufficient Verification of Data Authenticity",
      "analysis": "The JiraCreateIssueNotifier class retrieves the JIRA issue ID from a file in the job's directory, but does not verify the authenticity or integrity of the data in the file. This could potentially allow an attacker to modify the file and cause unauthorized actions or data manipulation.\n",
      "classification": "slightly promising",
      "cwe": "CWE-345",
      "function_names": [
        "JiraCreateIssueNotifier.getIssue"
      ],
      "filenames": [
        "src/main/java/hudson/plugins/jira/JiraCreateIssueNotifier.java"
      ]
    },
    {
      "headline": "Improper Restriction of Operations within the Bounds of a Memory Buffer",
      "analysis": "The JiraRestService class uses the objectMapper.readValue method to parse JSON responses from the JIRA API. If the JSON data is not properly validated or sanitized, it could potentially lead to buffer overflow vulnerabilities.\n",
      "classification": "not promising",
      "cwe": "CWE-119",
      "function_names": [
        "JiraRestService.getVersions",
        "JiraRestService.getComponents"
      ],
      "filenames": [
        "src/main/java/hudson/plugins/jira/JiraRestService.java"
      ]
    },
    {
      "headline": "Use of Uninitialized Resource",
      "analysis": "The JiraSession class uses uninitialized resources (projectKeys and knownStatuses) in some methods, which could potentially lead to null pointer exceptions or other unexpected behavior.\n",
      "classification": "not promising",
      "cwe": "CWE-908",
      "function_names": [
        "JiraSession.getProjectKeys",
        "JiraSession.getStatusById"
      ],
      "filenames": [
        "src/main/java/hudson/plugins/jira/JiraSession.java"
      ]
    }
  ],
  "scores": [
    {
      "stats": {
        "fn": 5,
        "tp": 0,
        "fp": 4
      },
      "mapping": {},
      "vuln_dates": {
        "CVE-2023-49653": "2023-11-29T14:15:07",
        "CVE-2023-49673": "2023-11-29T14:15:07",
        "CVE-2019-16541": "2019-11-21T15:15:14",
        "CVE-2018-1000412": "2019-01-09T23:29:02",
        "CVE-2022-29041": "2022-04-12T20:15:09"
      },
      "scoring_model": "gpt-4o-2024-05-13",
      "type": "llm",
      "instruction_template_hash": "8998f09cf57fca8a6e03"
    },
    {
      "stats": {
        "fn": 5,
        "tp": 0,
        "fp": 4
      },
      "mapping": {},
      "vuln_dates": {
        "CVE-2023-49653": "2023-11-29T14:15:07",
        "CVE-2023-49673": "2023-11-29T14:15:07",
        "CVE-2019-16541": "2019-11-21T15:15:14",
        "CVE-2018-1000412": "2019-01-09T23:29:02",
        "CVE-2022-29041": "2022-04-12T20:15:09"
      },
      "scoring_model": "claude-3-opus-20240229",
      "type": "llm",
      "instruction_template_hash": "245ace12b6361954d0a2"
    }
  ],
  "instruction_template_hash": "10c0163db4740318a544",
  "version": "0.1.0"
}
