{
  "commit": "1b0f3917b8f908c81bb646ce42f29cf7c86443a1",
  "repo_url": "https://github.com/lipnitsk/libcue",
  "model": "claude-3-sonnet-20240229",
  "chunk_hashes": [
    "05312507afe9cc8b8ce0"
  ],
  "responses": [
    {
      "content": "```yaml\nleads:\n  - headline: CWE-835 Loop with Unreachable Exit Condition ('Infinite Loop')\n    analysis: |\n      The `cd->ntrack` variable is incremented without any checks, allowing it to exceed the `MAXTRACK` limit defined as 99. This could potentially lead to an infinite loop when iterating over the `cd->track` array, causing excessive resource consumption.\n    cwe: CWE-834\n    function_names:\n      - cd_add_track\n    filenames:\n      - cd.c\n    classification: very promising\n\n  - headline: CWE-789 Uncontrolled Memory Allocation\n    analysis: |\n      The `track_init` function allocates memory for the `track` struct without any checks for successful allocation. If the allocation fails, it could lead to a NULL pointer dereference or other memory corruption issues.\n    cwe: CWE-789\n    function_names:\n      - track_init\n    filenames:\n      - cd.c\n    classification: very promising\n\n  - headline: CWE-252 Unchecked Return Value\n    analysis: |\n      The `cdtext_init` and `rem_new` functions do not check the return value of memory allocation functions like `calloc` and `malloc`. If the allocation fails, it could lead to a NULL pointer dereference or other memory corruption issues.\n    cwe: CWE-252\n    function_names:\n      - cdtext_init\n      - rem_new\n    filenames:\n      - cdtext.c\n      - rem.c\n    classification: very promising\n\n  - headline: CWE-690 Unchecked Return Value to NULL Pointer Dereference\n    analysis: |\n      The `cd_init` function does not check if the memory allocation for the `cd` struct was successful. If the allocation fails, it could lead to a NULL pointer dereference when accessing members of the `cd` struct.\n    cwe: CWE-690\n    function_names:\n      - cd_init\n    filenames:\n      - cd.c\n    classification: very promising\n\n  - headline: CWE-476 NULL Pointer Dereference\n    analysis: |\n      Several functions in the codebase do not check for NULL pointers before accessing or modifying struct members or dynamically allocated memory. This could lead to NULL pointer dereferences and crashes.\n    cwe: CWE-476\n    function_names:\n      - cd_delete\n      - track_delete\n      - cd_set_catalog\n      - cd_set_cdtextfile\n      - track_set_filename\n      - track_set_isrc\n    filenames:\n      - cd.c\n      - cdtext.c\n    classification: very promising\n\n  - headline: CWE-416 Use After Free\n    analysis: |\n      The `cd_set_catalog` and `cd_set_cdtextfile` functions free the existing memory for `cd->catalog` and `cd->cdtextfile` without checking if they are NULL pointers. If these pointers are already NULL, it could lead to a use-after-free vulnerability.\n    cwe: CWE-416\n    function_names:\n      - cd_set_catalog\n      - cd_set_cdtextfile\n    filenames:\n      - cd.c\n    classification: very promising\n\n  - headline: CWE-121 Stack-based Buffer Overflow\n    analysis: |\n      The `time_frame_to_mmssff` function uses a static buffer of fixed size to store the formatted time string. If the input frame value is large enough, it could lead to a stack-based buffer overflow vulnerability.\n    cwe: CWE-121\n    function_names:\n      - time_frame_to_mmssff\n    filenames:\n      - time.c\n    classification: very promising\n```",
      "date": "2024-06-09T13:13:50.411803",
      "usage": {
        "prompt_tokens": 20488,
        "completion_tokens": 908,
        "cost": 0.075084
      }
    }
  ],
  "leads": [
    {
      "headline": "CWE-835 Loop with Unreachable Exit Condition ('Infinite Loop')",
      "analysis": "The cd->ntrack variable is incremented without any checks, allowing it to exceed the MAXTRACK limit defined as 99. This could potentially lead to an infinite loop when iterating over the cd->track array, causing excessive resource consumption.\n",
      "classification": "very promising",
      "cwe": "CWE-834",
      "function_names": [
        "cd_add_track"
      ],
      "filenames": [
        "cd.c"
      ]
    },
    {
      "headline": "CWE-789 Uncontrolled Memory Allocation",
      "analysis": "The track_init function allocates memory for the track struct without any checks for successful allocation. If the allocation fails, it could lead to a NULL pointer dereference or other memory corruption issues.\n",
      "classification": "very promising",
      "cwe": "CWE-789",
      "function_names": [
        "track_init"
      ],
      "filenames": [
        "cd.c"
      ]
    },
    {
      "headline": "CWE-252 Unchecked Return Value",
      "analysis": "The cdtext_init and rem_new functions do not check the return value of memory allocation functions like calloc and malloc. If the allocation fails, it could lead to a NULL pointer dereference or other memory corruption issues.\n",
      "classification": "very promising",
      "cwe": "CWE-252",
      "function_names": [
        "cdtext_init",
        "rem_new"
      ],
      "filenames": [
        "cdtext.c",
        "rem.c"
      ]
    },
    {
      "headline": "CWE-690 Unchecked Return Value to NULL Pointer Dereference",
      "analysis": "The cd_init function does not check if the memory allocation for the cd struct was successful. If the allocation fails, it could lead to a NULL pointer dereference when accessing members of the cd struct.\n",
      "classification": "very promising",
      "cwe": "CWE-690",
      "function_names": [
        "cd_init"
      ],
      "filenames": [
        "cd.c"
      ]
    },
    {
      "headline": "CWE-476 NULL Pointer Dereference",
      "analysis": "Several functions in the codebase do not check for NULL pointers before accessing or modifying struct members or dynamically allocated memory. This could lead to NULL pointer dereferences and crashes.\n",
      "classification": "very promising",
      "cwe": "CWE-476",
      "function_names": [
        "cd_delete",
        "track_delete",
        "cd_set_catalog"
      ],
      "filenames": [
        "cd.c",
        "cdtext.c"
      ]
    },
    {
      "headline": "CWE-416 Use After Free",
      "analysis": "The cd_set_catalog and cd_set_cdtextfile functions free the existing memory for cd->catalog and cd->cdtextfile without checking if they are NULL pointers. If these pointers are already NULL, it could lead to a use-after-free vulnerability.\n",
      "classification": "very promising",
      "cwe": "CWE-416",
      "function_names": [
        "cd_set_catalog",
        "cd_set_cdtextfile"
      ],
      "filenames": [
        "cd.c"
      ]
    },
    {
      "headline": "CWE-121 Stack-based Buffer Overflow",
      "analysis": "The time_frame_to_mmssff function uses a static buffer of fixed size to store the formatted time string. If the input frame value is large enough, it could lead to a stack-based buffer overflow vulnerability.\n",
      "classification": "very promising",
      "cwe": "CWE-121",
      "function_names": [
        "time_frame_to_mmssff"
      ],
      "filenames": [
        "time.c"
      ]
    }
  ],
  "scores": [
    {
      "stats": {
        "fn": 1,
        "tp": 0,
        "fp": 7
      },
      "mapping": {},
      "vuln_dates": {
        "CVE-2023-43641": "2023-10-09T22:15:12"
      },
      "scoring_model": "gpt-4o-2024-05-13",
      "type": "llm",
      "instruction_template_hash": "8998f09cf57fca8a6e03"
    },
    {
      "stats": {
        "fn": 1,
        "tp": 0,
        "fp": 7
      },
      "mapping": {},
      "vuln_dates": {
        "CVE-2023-43641": "2023-10-09T22:15:12"
      },
      "scoring_model": "claude-3-opus-20240229",
      "type": "llm",
      "instruction_template_hash": "245ace12b6361954d0a2"
    },
    {
      "stats": {
        "fn": 1,
        "tp": 0,
        "fp": 7
      },
      "mapping": {},
      "vuln_dates": {
        "CVE-2023-43641": "2023-10-09T22:15:12"
      },
      "scoring_model": "claude-3-5-sonnet-20240620",
      "type": "llm",
      "instruction_template_hash": "245ace12b6361954d0a2"
    }
  ],
  "instruction_template_hash": "10c0163db4740318a544",
  "version": "0.1.0"
}
