{
  "commit": "8db648c6475c5b6bdab7d4452102f7ce125e2b46",
  "repo_url": "https://github.com/felixschwarz/mjml-python",
  "model": "claude-3-5-sonnet-20240620",
  "chunk_hashes": [
    "95b299d273c1eda98fe3"
  ],
  "responses": [
    {
      "content": "```yaml\nleads:\n  - headline: Potential Command Injection Vulnerability\n    analysis: |\n      There is a potential command injection vulnerability in the mjml.py script. The script passes user-supplied input (mjml_filename) directly to subprocess.run() without any sanitization or validation. An attacker could potentially inject malicious commands by providing a crafted filename.\n    cwe: CWE-78\n    function_names:\n      - main\n    filenames:\n      - mjml/scripts/mjml.py\n    classification: slightly promising\n\n  - headline: Use of Deprecated SSL/TLS Protocol\n    analysis: |\n      The code uses the 'https' protocol to fetch resources from external URLs (e.g. font URLs, social media icon URLs) without specifying a minimum TLS version. This could potentially allow the use of deprecated SSL/TLS protocols, exposing the application to known vulnerabilities.\n    cwe: CWE-327\n    function_names: []\n    filenames:\n      - mjml/elements/mj_social_element.py\n    classification: slightly promising\n\n  - headline: Potential Cross-Site Scripting (XSS) Vulnerability\n    analysis: |\n      The code generates HTML dynamically and inserts content from various sources without proper encoding or sanitization in multiple places. This could potentially lead to cross-site scripting vulnerabilities if malicious input is passed through to the generated HTML.\n    cwe: CWE-79 \n    function_names:\n      - render\n    filenames:\n      - mjml/elements/mj_text.py\n      - mjml/elements/mj_button.py\n    classification: slightly promising\n\n  - headline: Use of Hard-coded Credentials\n    analysis: |\n      The code contains hard-coded URLs for various resources like social media icons. While not credentials per se, these hard-coded URLs could pose a security risk if the referenced resources are compromised or if the URLs need to be updated frequently for security reasons.\n    cwe: CWE-798\n    function_names: []\n    filenames:\n      - mjml/elements/mj_social_element.py \n    classification: slightly promising\n\n  - headline: Potential Integer Overflow\n    analysis: |\n      The code performs mathematical operations on integers parsed from user input without proper bounds checking. This could potentially lead to integer overflows if very large values are provided.\n    cwe: CWE-190\n    function_names:\n      - getWidthAsPixel\n    filenames:  \n      - mjml/elements/mj_column.py\n    classification: slightly promising\n```",
      "date": "2024-07-07T21:07:26.522385",
      "usage": {
        "prompt_tokens": 133023,
        "completion_tokens": 601,
        "cost": 0.408084
      }
    }
  ],
  "leads": [
    {
      "headline": "Potential Command Injection Vulnerability",
      "analysis": "There is a potential command injection vulnerability in the mjml.py script. The script passes user-supplied input (mjml_filename) directly to subprocess.run() without any sanitization or validation. An attacker could potentially inject malicious commands by providing a crafted filename.\n",
      "classification": "slightly promising",
      "cwe": "CWE-78",
      "function_names": [
        "main"
      ],
      "filenames": [
        "mjml/scripts/mjml.py"
      ]
    },
    {
      "headline": "Use of Deprecated SSL/TLS Protocol",
      "analysis": "The code uses the 'https' protocol to fetch resources from external URLs (e.g. font URLs, social media icon URLs) without specifying a minimum TLS version. This could potentially allow the use of deprecated SSL/TLS protocols, exposing the application to known vulnerabilities.\n",
      "classification": "slightly promising",
      "cwe": "CWE-327",
      "function_names": [],
      "filenames": [
        "mjml/elements/mj_social_element.py"
      ]
    },
    {
      "headline": "Potential Cross-Site Scripting (XSS) Vulnerability",
      "analysis": "The code generates HTML dynamically and inserts content from various sources without proper encoding or sanitization in multiple places. This could potentially lead to cross-site scripting vulnerabilities if malicious input is passed through to the generated HTML.\n",
      "classification": "slightly promising",
      "cwe": "CWE-79",
      "function_names": [
        "render"
      ],
      "filenames": [
        "mjml/elements/mj_text.py",
        "mjml/elements/mj_button.py"
      ]
    },
    {
      "headline": "Use of Hard-coded Credentials",
      "analysis": "The code contains hard-coded URLs for various resources like social media icons. While not credentials per se, these hard-coded URLs could pose a security risk if the referenced resources are compromised or if the URLs need to be updated frequently for security reasons.\n",
      "classification": "slightly promising",
      "cwe": "CWE-798",
      "function_names": [],
      "filenames": [
        "mjml/elements/mj_social_element.py"
      ]
    },
    {
      "headline": "Potential Integer Overflow",
      "analysis": "The code performs mathematical operations on integers parsed from user input without proper bounds checking. This could potentially lead to integer overflows if very large values are provided.\n",
      "classification": "slightly promising",
      "cwe": "CWE-190",
      "function_names": [
        "getWidthAsPixel"
      ],
      "filenames": [
        "mjml/elements/mj_column.py"
      ]
    }
  ],
  "scores": [
    {
      "stats": {
        "fn": 1,
        "tp": 0,
        "fp": 0
      },
      "mapping": {},
      "vuln_dates": {
        "CVE-2024-26151": "2024-02-22T19:15:09"
      },
      "scoring_model": "claude-3-5-sonnet-20240620",
      "type": "llm",
      "instruction_template_hash": "245ace12b6361954d0a2"
    }
  ],
  "instruction_template_hash": "10c0163db4740318a544",
  "version": "0.1.0"
}
