{
  "commit": "022603ddf92d43d23dd3f70ad263591e24defda5",
  "repo_url": "https://github.com/gotify/server",
  "model": "claude-3-5-sonnet-20240620",
  "chunk_hashes": [
    "e4f4866deda34501a387"
  ],
  "responses": [
    {
      "content": "```yaml\nleads:\n  - headline: Hard-coded credentials in CurrentUser class\n    analysis: |\n      The CurrentUser class contains hard-coded credentials in the login method. Specifically, it creates a client with a hard-coded username and password for authentication. This could allow an attacker to gain unauthorized access if these credentials are compromised. The credentials are encoded in Base64, which provides no real security as Base64 is easily reversible.\n    cwe: CWE-798\n    function_names:\n      - login\n    filenames:\n      - ui/src/CurrentUser.ts\n    classification: very promising\n\n  - headline: Potential for Cross-Site Scripting (XSS) in message rendering\n    analysis: |\n      The message content is rendered directly in the UI without proper sanitization. While the content type is checked to determine if it should be rendered as Markdown or plain text, neither option appears to sanitize the input against XSS attacks. An attacker could potentially inject malicious scripts into message content that would then be executed when viewed by other users.\n    cwe: CWE-79\n    function_names:\n      - contentType\n    filenames:\n      - ui/src/message/extras.ts\n    classification: slightly promising\n\n  - headline: Insecure direct object references in API calls\n    analysis: |\n      Many of the API calls in the various store classes (AppStore, UserStore, etc.) directly use user-supplied IDs in the URL path without proper authorization checks. This could potentially allow an attacker to access or modify data they should not have permission for by simply changing the ID in the request. Proper authorization should be implemented on the server side for each request.\n    cwe: CWE-639\n    function_names:\n      - requestDelete\n      - update\n    filenames:\n      - ui/src/application/AppStore.ts\n      - ui/src/user/UserStore.ts\n      - ui/src/client/ClientStore.ts\n    classification: slightly promising\n\n  - headline: Insufficient input validation on user-supplied data\n    analysis: |\n      There appears to be minimal input validation on user-supplied data before it is sent to the server or used in API calls. This could potentially lead to injection attacks or other security issues if the server-side code does not properly validate and sanitize the input. Input validation should be implemented on both the client and server side.\n    cwe: CWE-20\n    function_names:\n      - create\n      - update\n    filenames:\n      - ui/src/application/AppStore.ts\n      - ui/src/user/UserStore.ts\n      - ui/src/client/ClientStore.ts\n    classification: slightly promising\n\n  - headline: Potential information leakage through error messages\n    analysis: |\n      Error messages from API calls are directly displayed to the user through the snack notification system. This could potentially leak sensitive information about the system's internal workings or structure to an attacker. Error messages should be generic and not include specific details that could be exploited.\n    cwe: CWE-209\n    function_names:\n      - snack\n    filenames:\n      - ui/src/apiAuth.ts\n    classification: slightly promising\n```",
      "date": "2024-07-08T06:25:42.425142",
      "usage": {
        "prompt_tokens": 24024,
        "completion_tokens": 736,
        "cost": 0.083112
      }
    }
  ],
  "leads": [
    {
      "headline": "Hard-coded credentials in CurrentUser class",
      "analysis": "The CurrentUser class contains hard-coded credentials in the login method. Specifically, it creates a client with a hard-coded username and password for authentication. This could allow an attacker to gain unauthorized access if these credentials are compromised. The credentials are encoded in Base64, which provides no real security as Base64 is easily reversible.\n",
      "classification": "very promising",
      "cwe": "CWE-798",
      "function_names": [
        "login"
      ],
      "filenames": [
        "ui/src/CurrentUser.ts"
      ]
    },
    {
      "headline": "Potential for Cross-Site Scripting (XSS) in message rendering",
      "analysis": "The message content is rendered directly in the UI without proper sanitization. While the content type is checked to determine if it should be rendered as Markdown or plain text, neither option appears to sanitize the input against XSS attacks. An attacker could potentially inject malicious scripts into message content that would then be executed when viewed by other users.\n",
      "classification": "slightly promising",
      "cwe": "CWE-79",
      "function_names": [
        "contentType"
      ],
      "filenames": [
        "ui/src/message/extras.ts"
      ]
    },
    {
      "headline": "Insecure direct object references in API calls",
      "analysis": "Many of the API calls in the various store classes (AppStore, UserStore, etc.) directly use user-supplied IDs in the URL path without proper authorization checks. This could potentially allow an attacker to access or modify data they should not have permission for by simply changing the ID in the request. Proper authorization should be implemented on the server side for each request.\n",
      "classification": "slightly promising",
      "cwe": "CWE-639",
      "function_names": [
        "requestDelete",
        "update"
      ],
      "filenames": [
        "ui/src/application/AppStore.ts",
        "ui/src/user/UserStore.ts",
        "ui/src/client/ClientStore.ts"
      ]
    },
    {
      "headline": "Insufficient input validation on user-supplied data",
      "analysis": "There appears to be minimal input validation on user-supplied data before it is sent to the server or used in API calls. This could potentially lead to injection attacks or other security issues if the server-side code does not properly validate and sanitize the input. Input validation should be implemented on both the client and server side.\n",
      "classification": "slightly promising",
      "cwe": "CWE-20",
      "function_names": [
        "create",
        "update"
      ],
      "filenames": [
        "ui/src/application/AppStore.ts",
        "ui/src/user/UserStore.ts",
        "ui/src/client/ClientStore.ts"
      ]
    },
    {
      "headline": "Potential information leakage through error messages",
      "analysis": "Error messages from API calls are directly displayed to the user through the snack notification system. This could potentially leak sensitive information about the system's internal workings or structure to an attacker. Error messages should be generic and not include specific details that could be exploited.\n",
      "classification": "slightly promising",
      "cwe": "CWE-209",
      "function_names": [
        "snack"
      ],
      "filenames": [
        "ui/src/apiAuth.ts"
      ]
    }
  ],
  "scores": [
    {
      "stats": {
        "fn": 1,
        "tp": 0,
        "fp": 1
      },
      "mapping": {},
      "vuln_dates": {
        "CVE-2022-46181": "2022-12-29T19:15:08"
      },
      "scoring_model": "claude-3-5-sonnet-20240620",
      "type": "llm",
      "instruction_template_hash": "245ace12b6361954d0a2"
    }
  ],
  "instruction_template_hash": "10c0163db4740318a544",
  "version": "0.1.0"
}
