{
  "commit": "7c8e93e6fb2420fb6003c54a741e267c4f883bab",
  "repo_url": "https://github.com/pixee/java-security-toolkit",
  "model": "claude-3-haiku-20240307",
  "chunk_hashes": [
    "02a412cc0ecfd4e6d948"
  ],
  "responses": [
    {
      "content": "Here is the YAML output representing the security vulnerabilities in the codebase:\n\n```yaml\nleads:\n  - headline: Improper Neutralization of Input During Web Page Generation ('Cross-site Scripting')\n    analysis: |\n      The HtmlEncoder class is used to escape user-provided input before rendering it in the application. However, the test cases provided do not exhaustively cover all possible XSS vectors, and the encoding logic may not be robust enough to handle all XSS scenarios. Attackers could potentially inject malicious scripts that bypass the current encoding and lead to XSS vulnerabilities.\n    cwe: CWE-79\n    function_names:\n      - HtmlEncoder.encode\n    filenames:\n      - src/main/java/io/github/pixee/security/HtmlEncoder.java\n    classification: slightly promising\n\n  - headline: Improper Neutralization of Special Elements used in a Command ('OS Command Injection')\n    analysis: |\n      The SystemCommand class provides utilities to run system commands, but the validation of the command arguments is not comprehensive. Attackers could potentially inject malicious commands or command delimiters that bypass the current checks and lead to OS command injection vulnerabilities.\n    cwe: CWE-78\n    function_names:\n      - SystemCommand.runChecks\n    filenames:\n      - src/main/java/io/github/pixee/security/SystemCommand.java\n    classification: slightly promising\n\n  - headline: Improper Neutralization of Special Elements used in an XML Document ('XML Injection')\n    analysis: |\n      The XMLInputFactorySecurity and DocumentBuilderFactorySecurity classes provide utilities to harden XML parsing against XXE vulnerabilities. However, the implementation may not be sufficient to protect against all possible XML injection vectors, and attackers could potentially find ways to bypass the current mitigation measures.\n    cwe: CWE-91\n    function_names:\n      - XMLInputFactorySecurity.hardenFactory\n      - DocumentBuilderFactorySecurity.hardenDocumentBuilderFactory\n    filenames:\n      - src/main/java/io/github/pixee/security/XMLInputFactorySecurity.java\n      - src/main/java/io/github/pixee/security/DocumentBuilderFactorySecurity.java\n    classification: slightly promising\n\n  - headline: Use of Uninitialized Resource\n    analysis: |\n      The BoundedLineReader class reads lines from a Reader, but it does not handle the case where the Reader is not properly initialized or closed. Attackers could potentially exploit this to cause resource exhaustion or other security issues.\n    cwe: CWE-908\n    function_names:\n      - BoundedLineReader.readLine\n    filenames:\n      - src/main/java/io/github/pixee/security/BoundedLineReader.java\n    classification: slightly promising\n\n  - headline: Improper Restriction of Rendered UI Layers or Frames\n    analysis: |\n      The Urls class provides utilities to create and validate URLs, but the host validation implementation may not be sufficient to protect against all SSRF vulnerabilities. Attackers could potentially find ways to bypass the current host validation checks and access sensitive internal resources.\n    cwe: CWE-1021\n    function_names:\n      - Urls.checkHostsAllowed\n    filenames:\n      - src/main/java/io/github/pixee/security/Urls.java\n    classification: slightly promising\n\n  - headline: Deserialization of Untrusted Data\n    analysis: |\n      The ValidatingObjectInputStreams and ObjectInputFilters classes provide utilities to secure Java deserialization, but the implementation may not be sufficient to protect against all possible deserialization attacks. Attackers could potentially find ways to bypass the current mitigation measures and execute arbitrary code through insecure deserialization.\n    cwe: CWE-502\n    function_names:\n      - ValidatingObjectInputStreams.from\n      - ObjectInputFilters.getHardenedObjectFilter\n    filenames:\n      - src/main/java/io/github/pixee/security/ValidatingObjectInputStreams.java\n      - src/main/java/io/github/pixee/security/ObjectInputFilters.java\n    classification: slightly promising\n\n  - headline: Improper Neutralization of Formula Elements in a CSV File\n    analysis: |\n      The Filenames class provides utilities to sanitize file names, but the implementation may not be sufficient to protect against all possible file name injection attacks. Attackers could potentially find ways to bypass the current sanitization and inject malicious content into the file name, leading to formula injection vulnerabilities in applications that use the sanitized file names.\n    cwe: CWE-1236\n    function_names:\n      - Filenames.toSimpleFileName\n    filenames:\n      - src/main/java/io/github/pixee/security/Filenames.java\n    classification: slightly promising\n\n```",
      "date": "2024-06-09T14:07:16.560624",
      "usage": {
        "prompt_tokens": 44458,
        "completion_tokens": 1152,
        "cost": 0.0125545
      }
    }
  ],
  "leads": [
    {
      "headline": "Improper Neutralization of Input During Web Page Generation ('Cross-site Scripting')",
      "analysis": "The HtmlEncoder class is used to escape user-provided input before rendering it in the application. However, the test cases provided do not exhaustively cover all possible XSS vectors, and the encoding logic may not be robust enough to handle all XSS scenarios. Attackers could potentially inject malicious scripts that bypass the current encoding and lead to XSS vulnerabilities.\n",
      "classification": "slightly promising",
      "cwe": "CWE-79",
      "function_names": [
        "HtmlEncoder.encode"
      ],
      "filenames": [
        "src/main/java/io/github/pixee/security/HtmlEncoder.java"
      ]
    },
    {
      "headline": "Improper Neutralization of Special Elements used in a Command ('OS Command Injection')",
      "analysis": "The SystemCommand class provides utilities to run system commands, but the validation of the command arguments is not comprehensive. Attackers could potentially inject malicious commands or command delimiters that bypass the current checks and lead to OS command injection vulnerabilities.\n",
      "classification": "slightly promising",
      "cwe": "CWE-78",
      "function_names": [
        "SystemCommand.runChecks"
      ],
      "filenames": [
        "src/main/java/io/github/pixee/security/SystemCommand.java"
      ]
    },
    {
      "headline": "Improper Neutralization of Special Elements used in an XML Document ('XML Injection')",
      "analysis": "The XMLInputFactorySecurity and DocumentBuilderFactorySecurity classes provide utilities to harden XML parsing against XXE vulnerabilities. However, the implementation may not be sufficient to protect against all possible XML injection vectors, and attackers could potentially find ways to bypass the current mitigation measures.\n",
      "classification": "slightly promising",
      "cwe": "CWE-91",
      "function_names": [
        "XMLInputFactorySecurity.hardenFactory",
        "DocumentBuilderFactorySecurity.hardenDocumentBuilderFactory"
      ],
      "filenames": [
        "src/main/java/io/github/pixee/security/XMLInputFactorySecurity.java",
        "src/main/java/io/github/pixee/security/DocumentBuilderFactorySecurity.java"
      ]
    },
    {
      "headline": "Use of Uninitialized Resource",
      "analysis": "The BoundedLineReader class reads lines from a Reader, but it does not handle the case where the Reader is not properly initialized or closed. Attackers could potentially exploit this to cause resource exhaustion or other security issues.\n",
      "classification": "slightly promising",
      "cwe": "CWE-908",
      "function_names": [
        "BoundedLineReader.readLine"
      ],
      "filenames": [
        "src/main/java/io/github/pixee/security/BoundedLineReader.java"
      ]
    },
    {
      "headline": "Improper Restriction of Rendered UI Layers or Frames",
      "analysis": "The Urls class provides utilities to create and validate URLs, but the host validation implementation may not be sufficient to protect against all SSRF vulnerabilities. Attackers could potentially find ways to bypass the current host validation checks and access sensitive internal resources.\n",
      "classification": "slightly promising",
      "cwe": "CWE-1021",
      "function_names": [
        "Urls.checkHostsAllowed"
      ],
      "filenames": [
        "src/main/java/io/github/pixee/security/Urls.java"
      ]
    },
    {
      "headline": "Deserialization of Untrusted Data",
      "analysis": "The ValidatingObjectInputStreams and ObjectInputFilters classes provide utilities to secure Java deserialization, but the implementation may not be sufficient to protect against all possible deserialization attacks. Attackers could potentially find ways to bypass the current mitigation measures and execute arbitrary code through insecure deserialization.\n",
      "classification": "slightly promising",
      "cwe": "CWE-502",
      "function_names": [
        "ValidatingObjectInputStreams.from",
        "ObjectInputFilters.getHardenedObjectFilter"
      ],
      "filenames": [
        "src/main/java/io/github/pixee/security/ValidatingObjectInputStreams.java",
        "src/main/java/io/github/pixee/security/ObjectInputFilters.java"
      ]
    },
    {
      "headline": "Improper Neutralization of Formula Elements in a CSV File",
      "analysis": "The Filenames class provides utilities to sanitize file names, but the implementation may not be sufficient to protect against all possible file name injection attacks. Attackers could potentially find ways to bypass the current sanitization and inject malicious content into the file name, leading to formula injection vulnerabilities in applications that use the sanitized file names.\n",
      "classification": "slightly promising",
      "cwe": "CWE-1236",
      "function_names": [
        "Filenames.toSimpleFileName"
      ],
      "filenames": [
        "src/main/java/io/github/pixee/security/Filenames.java"
      ]
    }
  ],
  "scores": [
    {
      "stats": {
        "fn": 1,
        "tp": 0,
        "fp": 0
      },
      "mapping": {},
      "vuln_dates": {
        "CVE-2024-24569": "2024-02-01T19:15:08"
      },
      "scoring_model": "gpt-4o-2024-05-13",
      "type": "llm",
      "instruction_template_hash": "8998f09cf57fca8a6e03"
    },
    {
      "stats": {
        "fn": 1,
        "tp": 0,
        "fp": 0
      },
      "mapping": {},
      "vuln_dates": {
        "CVE-2024-24569": "2024-02-01T19:15:08"
      },
      "scoring_model": "claude-3-opus-20240229",
      "type": "llm",
      "instruction_template_hash": "245ace12b6361954d0a2"
    },
    {
      "stats": {
        "fn": 1,
        "tp": 0,
        "fp": 0
      },
      "mapping": {},
      "vuln_dates": {
        "CVE-2024-24569": "2024-02-01T19:15:08"
      },
      "scoring_model": "claude-3-5-sonnet-20240620",
      "type": "llm",
      "instruction_template_hash": "245ace12b6361954d0a2"
    }
  ],
  "instruction_template_hash": "10c0163db4740318a544",
  "version": "0.1.0"
}
