{
  "commit": "422235ee8bc6d3370b496e9f5fc424d91a954cc2",
  "repo_url": "https://github.com/taviso/123elf",
  "model": "gemini/gemini-1.5-pro",
  "chunk_hashes": [
    "b752bb6ded6679f7b70e"
  ],
  "responses": [
    {
      "content": "```yaml\nleads:\n  - headline: Stack Overflow in display_column_labels()\n    analysis: |\n      The function `display_column_labels()` in `patch.c` allocates a buffer on the stack.\n      This buffer is a fixed size, but the width required is dependent on the value of `COLS`.\n      An attacker could cause a stack overflow by setting `COLS` to a very large value using the `COLUMNS` environment variable.\n    cwe: CWE-129\n    function_names:\n      - display_column_labels\n    filenames:\n      - patch.c\n    classification: slightly promising\n  - headline: Integer Overflow in tty_disp_grph_txt_size()\n    analysis: |\n      The function `tty_disp_grph_txt_size()` in `graphics.c` accepts a length argument of type `size_t`\n      but then returns it as an `int`. An attacker could pass a length value greater than `INT_MAX` and trigger\n      an integer overflow.\n    cwe: CWE-190\n    function_names:\n      - tty_disp_grph_txt_size\n    filenames:\n      - graphics.c\n    classification: not promising\n  - headline: Heap Overflow in __unix_uname()\n    analysis: |\n      The function `__unix_uname()` in `wrappers.c` uses `strncpy()` to copy a buffer of size `_UTSNAME_SYSNAME_LEN`,\n      which is defined to be 256 in `limits.h`. However, `strncpy()` is told to copy at most 48 bytes, so an attacker\n      could cause a heap overflow by setting the hostname to a value greater than 48 bytes.\n    cwe: CWE-120\n    function_names:\n      - __unix_uname\n    filenames:\n      - wrappers.c\n    classification: slightly promising\n  - headline: Possible Out-of-bounds Read in __unix_readdir()\n    analysis: |\n      The function `__unix_readdir()` in `wrappers.c` allocates a static buffer on the stack named `uent`\n      with a fixed size of 256 bytes for `d_name`. An attacker could create a filename with a length greater\n      than 256 bytes and cause an out-of-bounds read.\n    cwe: CWE-125\n    function_names:\n      - __unix_readdir\n    filenames:\n      - wrappers.c\n    classification: slightly promising\n  - headline: Symbolic Link Following in map_unix_pathname()\n    analysis: |\n      The function `map_unix_pathname()` in `filemap.c` calls `realpath()` on the untrusted value `wkspath` from main.c,\n      which is vulnerable to a symbolic link attack. By creating a symbolic link pointing to an arbitrary file,\n      an attacker can trick 1-2-3 into opening the file.\n    cwe: CWE-59\n    function_names:\n      - map_unix_pathname\n      - canonicalize_auto_worksheet\n    filenames:\n      - filemap.c\n      - main.c\n    classification: slightly promising\n  - headline: Possible Path Traversal in map_unix_pathname()\n    analysis: |\n      The function `map_unix_pathname()` in `filemap.c` uses `strrchr()` to find the last '/' in a path\n      supplied by the user. An attacker may be able to supply a path with no '/' at all,\n      which would cause `filename` to be `NULL`. The logic later in the function does not account for this\n      case, leading to a potential path traversal vulnerability.\n    cwe: CWE-22\n    function_names:\n      - map_unix_pathname\n    filenames:\n      - filemap.c\n    classification: slightly promising\n```",
      "date": "2024-07-08T08:55:52.605922",
      "usage": {
        "prompt_tokens": 63898,
        "completion_tokens": 761,
        "cost": 0.23163350000000002
      }
    }
  ],
  "leads": [
    {
      "headline": "Stack Overflow in display_column_labels()",
      "analysis": "The function display_column_labels() in patch.c allocates a buffer on the stack.\nThis buffer is a fixed size, but the width required is dependent on the value of COLS.\nAn attacker could cause a stack overflow by setting COLS to a very large value using the COLUMNS environment variable.\n",
      "classification": "slightly promising",
      "cwe": "CWE-129",
      "function_names": [
        "display_column_labels"
      ],
      "filenames": [
        "patch.c"
      ]
    },
    {
      "headline": "Integer Overflow in tty_disp_grph_txt_size()",
      "analysis": "The function tty_disp_grph_txt_size() in graphics.c accepts a length argument of type size_t\nbut then returns it as an int. An attacker could pass a length value greater than INT_MAX and trigger\nan integer overflow.\n",
      "classification": "not promising",
      "cwe": "CWE-190",
      "function_names": [
        "tty_disp_grph_txt_size"
      ],
      "filenames": [
        "graphics.c"
      ]
    },
    {
      "headline": "Heap Overflow in __unix_uname()",
      "analysis": "The function __unix_uname() in wrappers.c uses strncpy() to copy a buffer of size _UTSNAME_SYSNAME_LEN,\nwhich is defined to be 256 in limits.h. However, strncpy() is told to copy at most 48 bytes, so an attacker\ncould cause a heap overflow by setting the hostname to a value greater than 48 bytes.\n",
      "classification": "slightly promising",
      "cwe": "CWE-120",
      "function_names": [
        "__unix_uname"
      ],
      "filenames": [
        "wrappers.c"
      ]
    },
    {
      "headline": "Possible Out-of-bounds Read in __unix_readdir()",
      "analysis": "The function __unix_readdir() in wrappers.c allocates a static buffer on the stack named uent\nwith a fixed size of 256 bytes for d_name. An attacker could create a filename with a length greater\nthan 256 bytes and cause an out-of-bounds read.\n",
      "classification": "slightly promising",
      "cwe": "CWE-125",
      "function_names": [
        "__unix_readdir"
      ],
      "filenames": [
        "wrappers.c"
      ]
    },
    {
      "headline": "Symbolic Link Following in map_unix_pathname()",
      "analysis": "The function map_unix_pathname() in filemap.c calls realpath() on the untrusted value wkspath from main.c,\nwhich is vulnerable to a symbolic link attack. By creating a symbolic link pointing to an arbitrary file,\nan attacker can trick 1-2-3 into opening the file.\n",
      "classification": "slightly promising",
      "cwe": "CWE-59",
      "function_names": [
        "map_unix_pathname",
        "canonicalize_auto_worksheet"
      ],
      "filenames": [
        "filemap.c",
        "main.c"
      ]
    },
    {
      "headline": "Possible Path Traversal in map_unix_pathname()",
      "analysis": "The function map_unix_pathname() in filemap.c uses strrchr() to find the last '/' in a path\nsupplied by the user. An attacker may be able to supply a path with no '/' at all,\nwhich would cause filename to be NULL. The logic later in the function does not account for this\ncase, leading to a potential path traversal vulnerability.\n",
      "classification": "slightly promising",
      "cwe": "CWE-22",
      "function_names": [
        "map_unix_pathname"
      ],
      "filenames": [
        "filemap.c"
      ]
    }
  ],
  "scores": [
    {
      "stats": {
        "fn": 1,
        "tp": 0,
        "fp": 0
      },
      "mapping": {},
      "vuln_dates": {
        "CVE-2022-39843": "2022-09-05T07:15:08"
      },
      "scoring_model": "claude-3-5-sonnet-20240620",
      "type": "llm",
      "instruction_template_hash": "245ace12b6361954d0a2"
    }
  ],
  "instruction_template_hash": "10c0163db4740318a544",
  "version": "0.1.0"
}
