{
  "commit": "077018822d3594229daa8343310d0b40804b9ddc",
  "repo_url": "https://github.com/yourls/yourls",
  "model": "gpt-4-turbo-2024-04-09",
  "chunk_hashes": [
    "2ba5b9270cb3a652832f"
  ],
  "responses": [
    {
      "content": "```yaml\nleads:\n  - headline: \"Improper neutralization of input in URL parameter leading to Cross-site Scripting (XSS) vulnerability\"\n    analysis: |\n      The system does not properly sanitize the input fetched from the URL parameter before using it within the HTML output. This flaw can be typically exploited by an attacker by crafting malicious URLs that include script code. When a user accesses such URLs, the script embedded in the URL gets executed within the client\u2019s browser under the security context of the application. This vulnerability can lead to stealing of session tokens, performing actions on behalf of users, and other typical XSS impacts.\n    cwe: CWE-79\n    function_names:\n      - \"init_clipboard\"\n      - \"toggle\"\n    filenames:\n      - \"js/share.js\"\n      - \"readme.html\"\n    classification: \"very promising\"\n\n  - headline: \"Use of hard-coded credential within the application code.\"\n    analysis: |\n      The application code in the script contains a hard-coded password used for authentication purposes. This poses a security risk as anyone with access to the codebase can retrieve the password and potentially gain unauthorized access to the system or data that is protected by the password.\n    cwe: CWE-798\n    function_names:\n      - \"init\"\n    filenames:\n      - \"js/common.js\"\n    classification: \"very promising\"\n\n  - headline: \"Outdated interface does not support modern security protocols in the HTML meta tag.\"\n    analysis: |\n      The HTML code specifies an outdated X-UA-Compatible meta tag that forces the browser to use IE 9 compatibility mode, potentially disabling modern security features provided by newer browser versions. This may expose the site and its users to security vulnerabilities present in older browser technologies.\n    cwe: CWE-693\n    function_names: []\n    filenames:\n      - \"readme.html\"\n    classification: \"slightly promising\"\n\n  - headline: \"Insecure direct object references in API endpoint implementation.\"\n    analysis: |\n      The API endpoint constructed allows for direct references to internal objects without proper authorization checks. Attackers could potentially manipulate these references to access unauthorized data.\n    cwe: CWE-639\n    function_names:\n      - \"api_handle\"\n    filenames:\n      - \"js/api_endpoint.js\"\n    classification: \"very promising\"\n\n  - headline: \"Potential Path Traversal vulnerability in server configuration file access.\"\n    analysis: |\n      The server allows accessing configuration files from the user input without proper validation, potentially allowing an attacker to traverse the server's directory structure and access sensitive files outside of the intended directory.\n    cwe: CWE-22\n    function_names:\n      - \"load_config\"\n    filenames:\n      - \"includes/load-yourls.php\"\n    classification: \"slightly promising\"\n\n  - headline: \"Insufficient verification of data authenticity in plugin management.\"\n    analysis: |\n      The application does not adequately verify the authenticity of plugins being added or updated, which can lead to the execution of malicious code if an attacker is able to manipulate the plugins.\n    cwe: CWE-345\n    function_names:\n      - \"plugin_update\"\n    filenames:\n      - \"admin/plugin_interface.php\"\n    classification: \"very promising\"\n```",
      "date": "2024-06-14T11:01:29.282427",
      "usage": {
        "prompt_tokens": 25807,
        "completion_tokens": 654,
        "cost": 0.27769
      }
    }
  ],
  "leads": [
    {
      "headline": "Improper neutralization of input in URL parameter leading to Cross-site Scripting (XSS) vulnerability",
      "analysis": "The system does not properly sanitize the input fetched from the URL parameter before using it within the HTML output. This flaw can be typically exploited by an attacker by crafting malicious URLs that include script code. When a user accesses such URLs, the script embedded in the URL gets executed within the client\u2019s browser under the security context of the application. This vulnerability can lead to stealing of session tokens, performing actions on behalf of users, and other typical XSS impacts.\n",
      "classification": "very promising",
      "cwe": "CWE-79",
      "function_names": [
        "init_clipboard",
        "toggle"
      ],
      "filenames": [
        "js/share.js",
        "readme.html"
      ]
    },
    {
      "headline": "Use of hard-coded credential within the application code.",
      "analysis": "The application code in the script contains a hard-coded password used for authentication purposes. This poses a security risk as anyone with access to the codebase can retrieve the password and potentially gain unauthorized access to the system or data that is protected by the password.\n",
      "classification": "very promising",
      "cwe": "CWE-798",
      "function_names": [
        "init"
      ],
      "filenames": [
        "js/common.js"
      ]
    },
    {
      "headline": "Outdated interface does not support modern security protocols in the HTML meta tag.",
      "analysis": "The HTML code specifies an outdated X-UA-Compatible meta tag that forces the browser to use IE 9 compatibility mode, potentially disabling modern security features provided by newer browser versions. This may expose the site and its users to security vulnerabilities present in older browser technologies.\n",
      "classification": "slightly promising",
      "cwe": "CWE-693",
      "function_names": [],
      "filenames": [
        "readme.html"
      ]
    },
    {
      "headline": "Insecure direct object references in API endpoint implementation.",
      "analysis": "The API endpoint constructed allows for direct references to internal objects without proper authorization checks. Attackers could potentially manipulate these references to access unauthorized data.\n",
      "classification": "very promising",
      "cwe": "CWE-639",
      "function_names": [
        "api_handle"
      ],
      "filenames": [
        "js/api_endpoint.js"
      ]
    },
    {
      "headline": "Potential Path Traversal vulnerability in server configuration file access.",
      "analysis": "The server allows accessing configuration files from the user input without proper validation, potentially allowing an attacker to traverse the server's directory structure and access sensitive files outside of the intended directory.\n",
      "classification": "slightly promising",
      "cwe": "CWE-22",
      "function_names": [
        "load_config"
      ],
      "filenames": [
        "includes/load-yourls.php"
      ]
    },
    {
      "headline": "Insufficient verification of data authenticity in plugin management.",
      "analysis": "The application does not adequately verify the authenticity of plugins being added or updated, which can lead to the execution of malicious code if an attacker is able to manipulate the plugins.\n",
      "classification": "very promising",
      "cwe": "CWE-345",
      "function_names": [
        "plugin_update"
      ],
      "filenames": [
        "admin/plugin_interface.php"
      ]
    }
  ],
  "scores": [
    {
      "stats": {
        "fn": 4,
        "tp": 1,
        "fp": 3
      },
      "mapping": {
        "0": "CVE-2021-3785"
      },
      "vuln_dates": {
        "CVE-2019-14537": "2019-08-07T17:15:12",
        "CVE-2022-0088": "2022-04-03T09:15:08",
        "CVE-2021-3785": "2021-09-15T12:15:16",
        "CVE-2021-3783": "2021-09-15T12:15:16",
        "CVE-2021-3734": "2021-08-26T13:15:08"
      },
      "scoring_model": "claude-3-opus-20240229",
      "type": "llm",
      "instruction_template_hash": "245ace12b6361954d0a2"
    }
  ],
  "instruction_template_hash": "10c0163db4740318a544",
  "version": "0.1.0"
}
