{
  "commit": "21de53798172594993e41d27bba8d5d8cd0eee4d",
  "repo_url": "https://github.com/devfile/registry-support",
  "model": "gpt-4o-2024-05-13",
  "chunk_hashes": [
    "c2ef1eae7093cb1020b5"
  ],
  "responses": [
    {
      "content": "```yaml\nleads:\n  - headline: \"Potential Command Injection Vulnerability in build.sh\"\n    analysis: |\n      The script \"build_registry.sh\" does not sanitize user inputs or environment variables. Specifically, the script sources an external environment file \"setenv.sh\" which modifies the behavior of the script based on potentially user-controlled environment variables. This could lead to a command injection vulnerability wherein an attacker could set malicious environment variables to execute arbitrary commands on the server.\n    cwe: CWE-77\n    function_names: []\n    filenames:\n      - build_registry.sh\n    classification: very promising\n\n  - headline: \"Improper Management of Sensitive Data in cache_samples.sh\"\n    analysis: |\n      The \"cache_samples.sh\" script uses `git clone` to download samples from a repository into a temporary directory. If an attacker gains write access to this repository, they could push a malicious devfile, potentially exposing sensitive data or executing malicious code when the sample is used.\n    cwe: CWE-494\n    function_names:\n      - cache_sample\n    filenames:\n      - build-tools/cache_samples.sh\n    classification: very promising\n\n  - headline: \"Insecure Default Variable in setenv.sh\"\n    analysis: |\n      The script \"setenv.sh\" sets the `USE_PODMAN` variable with a default value of \"false\" if not set. This could lead to security issues if the script assumes podman is not used while it actually is. The script does not validate the environment variable causing potential inconsistencies and security concerns.\n    cwe: CWE-1188\n    function_names: []\n    filenames:\n      - setenv.sh\n    classification: slightly promising\n\n  - headline: \"Cleartext Transmission of Sensitive Data in docker-push.sh\"\n    analysis: |\n      The `docker-push.sh` script tags and pushes Docker images, potentially over a network. If the Docker daemon is not configured with encryption, this can lead to transmitting sensitive data (such as Docker images or credentials) in cleartext, exposing them to network attackers.\n    cwe: CWE-319\n    function_names:\n      - docker_push\n    filenames:\n      - tests/integration/docker-push.sh\n    classification: slightly promising\n\n  - headline: \"Improper Resource Shutdown in cache_samples.sh\"\n    analysis: |\n      In the script \"cache_samples.sh\", temporary directories and files are created but not always cleaned up after use. This can lead to resource exhaustion over time as temporary files accumulate, potentially causing the system to run out of disk space.\n    cwe: CWE-404\n    function_names:\n      - cache_sample\n      - cache_devfile\n    filenames:\n      - build-tools/cache_samples.sh\n    classification: slightly promising\n\n  - headline: \"Insecure Cloning from External Repositories in regen.sh\"\n    analysis: |\n      The \"regen.sh\" script clones a Git repository without verifying the integrity or authenticity of the source. An attacker could compromise the repository or perform a Man-in-the-Middle (MITM) attack to inject malicious code.\n    cwe: CWE-494\n    function_names: []\n    filenames:\n      - index/server/build.sh\n    classification: very promising\n\n  - headline: \"Cleartext Storage of Sensitive Information\"\n    analysis: |\n      Multiple scripts store temporary files and logs that could contain sensitive information (e.g., credentials, file paths) in insecure locations. This can potentially expose sensitive information to unauthorized users or processes on the same system.\n    cwe: CWE-312\n    function_names:\n      - cache_sample\n      - cache_devfile\n    filenames:\n      - build-tools/cache_samples.sh\n      - index/server/vendor/github.com/ugorji/go/codec/build.sh\n    classification: very promising\n```",
      "date": "2024-06-09T11:27:37.247446",
      "usage": {
        "prompt_tokens": 54511,
        "completion_tokens": 772,
        "cost": 0.284135
      }
    }
  ],
  "leads": [
    {
      "headline": "Potential Command Injection Vulnerability in build.sh",
      "analysis": "The script \"build_registry.sh\" does not sanitize user inputs or environment variables. Specifically, the script sources an external environment file \"setenv.sh\" which modifies the behavior of the script based on potentially user-controlled environment variables. This could lead to a command injection vulnerability wherein an attacker could set malicious environment variables to execute arbitrary commands on the server.\n",
      "classification": "very promising",
      "cwe": "CWE-77",
      "function_names": [],
      "filenames": [
        "build_registry.sh"
      ]
    },
    {
      "headline": "Improper Management of Sensitive Data in cache_samples.sh",
      "analysis": "The \"cache_samples.sh\" script uses git clone to download samples from a repository into a temporary directory. If an attacker gains write access to this repository, they could push a malicious devfile, potentially exposing sensitive data or executing malicious code when the sample is used.\n",
      "classification": "very promising",
      "cwe": "CWE-494",
      "function_names": [
        "cache_sample"
      ],
      "filenames": [
        "build-tools/cache_samples.sh"
      ]
    },
    {
      "headline": "Insecure Default Variable in setenv.sh",
      "analysis": "The script \"setenv.sh\" sets the USE_PODMAN variable with a default value of \"false\" if not set. This could lead to security issues if the script assumes podman is not used while it actually is. The script does not validate the environment variable causing potential inconsistencies and security concerns.\n",
      "classification": "slightly promising",
      "cwe": "CWE-1188",
      "function_names": [],
      "filenames": [
        "setenv.sh"
      ]
    },
    {
      "headline": "Cleartext Transmission of Sensitive Data in docker-push.sh",
      "analysis": "The docker-push.sh script tags and pushes Docker images, potentially over a network. If the Docker daemon is not configured with encryption, this can lead to transmitting sensitive data (such as Docker images or credentials) in cleartext, exposing them to network attackers.\n",
      "classification": "slightly promising",
      "cwe": "CWE-319",
      "function_names": [
        "docker_push"
      ],
      "filenames": [
        "tests/integration/docker-push.sh"
      ]
    },
    {
      "headline": "Improper Resource Shutdown in cache_samples.sh",
      "analysis": "In the script \"cache_samples.sh\", temporary directories and files are created but not always cleaned up after use. This can lead to resource exhaustion over time as temporary files accumulate, potentially causing the system to run out of disk space.\n",
      "classification": "slightly promising",
      "cwe": "CWE-404",
      "function_names": [
        "cache_sample",
        "cache_devfile"
      ],
      "filenames": [
        "build-tools/cache_samples.sh"
      ]
    },
    {
      "headline": "Insecure Cloning from External Repositories in regen.sh",
      "analysis": "The \"regen.sh\" script clones a Git repository without verifying the integrity or authenticity of the source. An attacker could compromise the repository or perform a Man-in-the-Middle (MITM) attack to inject malicious code.\n",
      "classification": "very promising",
      "cwe": "CWE-494",
      "function_names": [],
      "filenames": [
        "index/server/build.sh"
      ]
    },
    {
      "headline": "Cleartext Storage of Sensitive Information",
      "analysis": "Multiple scripts store temporary files and logs that could contain sensitive information (e.g., credentials, file paths) in insecure locations. This can potentially expose sensitive information to unauthorized users or processes on the same system.\n",
      "classification": "very promising",
      "cwe": "CWE-312",
      "function_names": [
        "cache_sample",
        "cache_devfile"
      ],
      "filenames": [
        "build-tools/cache_samples.sh",
        "index/server/vendor/github.com/ugorji/go/codec/build.sh"
      ]
    }
  ],
  "scores": [
    {
      "stats": {
        "fn": 1,
        "tp": 0,
        "fp": 4
      },
      "mapping": {},
      "vuln_dates": {
        "CVE-2024-1485": "2024-02-14T00:15:46"
      },
      "scoring_model": "gpt-4o-2024-05-13",
      "type": "llm",
      "instruction_template_hash": "8998f09cf57fca8a6e03"
    },
    {
      "stats": {
        "fn": 1,
        "tp": 0,
        "fp": 4
      },
      "mapping": {},
      "vuln_dates": {
        "CVE-2024-1485": "2024-02-14T00:15:46"
      },
      "scoring_model": "claude-3-opus-20240229",
      "type": "llm",
      "instruction_template_hash": "245ace12b6361954d0a2"
    }
  ],
  "instruction_template_hash": "10c0163db4740318a544",
  "version": "0.1.0"
}
