{
  "commit": "35ab210fb219029a7c388898d641915f869c2a36",
  "repo_url": "https://github.com/armmbed/ualloc",
  "model": "gpt-4o-2024-05-13",
  "chunk_hashes": [
    "b6b76d7bcf77c6962b07"
  ],
  "responses": [
    {
      "content": "```yaml\nleads:\n  - headline: Missing Return Value Check in ualloc\n    analysis: |\n      The `mbed_ualloc` and `mbed_urealloc` functions do not check the return values of `dlmalloc`, `dlcalloc`, and `dlrealloc` respectively before using them. This can lead to dereferencing null pointers if the memory allocation fails, resulting in a potential crash or denial of service.\n    cwe: CWE-476\n    function_names:\n      - mbed_ualloc_internal\n      - mbed_urealloc_internal\n    filenames:\n      - source/ualloc.c\n    classification: very promising\n\n  - headline: Improper Synchronization - Potential Reentrancy Issues\n    analysis: |\n      There is a static volatile integer `prevent_tracing` used in various locations to prevent recursive logging. However, this simple flag mechanism is not thread-safe and can lead to race conditions where multiple threads could modify this flag simultaneously. This could result in inconsistent state or corrupted logs.\n    cwe: CWE-362\n    function_names:\n      - mbed_ualloc\n      - mbed_urealloc\n      - mbed_ufree\n    filenames:\n      - source/ualloc.c\n    classification: very promising\n\n  - headline: Use of Potentially Unsafe Functions\n    analysis: |\n      The code contains uses of potentially unsafe functions such as `printf` for logging and `memset` without bounds checking. This can lead to buffer overflow vulnerabilities if the size parameters are not properly controlled or validated. In the context of the `mbed_sbrk` environment, this could corrupt the heap and result in undefined behavior or security risks.\n    cwe: CWE-120\n    function_names:\n      - ualloc_debug\n      - mbed_ualloc_internal\n    filenames:\n      - source/ualloc.c\n    classification: slightly promising\n\n  - headline: No Proper Error Handling in Memory Allocation Functions\n    analysis: |\n      In the memory allocation functions, there is no proper error handling if allocation fails. The error handling mechanism currently used (`printf` statements) does not effectively mitigate the failure impact or provide fallback handling. Proper error handling should include cleaning up resources and returning error codes to the caller.\n    cwe: CWE-252\n    function_names:\n      - mbed_ualloc\n      - mbed_urealloc\n    filenames:\n      - source/ualloc.c\n      - source/malloc.c\n    classification: slightly promising\n\n  - headline: Potential Information Leak via Debug Logs\n    analysis: |\n      Debug logs using `printf` can potentially leak sensitive information about memory addresses and allocation patterns which could be exploited by attackers to understand memory layout and employ attacks like heap spraying.\n    cwe: CWE-209\n    function_names:\n      - ualloc_debug\n    filenames:\n      - source/ualloc.c\n    classification: not promising\n```",
      "date": "2024-06-14T12:51:39.533147",
      "usage": {
        "prompt_tokens": 7721,
        "completion_tokens": 596,
        "cost": 0.047545
      }
    }
  ],
  "leads": [
    {
      "headline": "Missing Return Value Check in ualloc",
      "analysis": "The mbed_ualloc and mbed_urealloc functions do not check the return values of dlmalloc, dlcalloc, and dlrealloc respectively before using them. This can lead to dereferencing null pointers if the memory allocation fails, resulting in a potential crash or denial of service.\n",
      "classification": "very promising",
      "cwe": "CWE-476",
      "function_names": [
        "mbed_ualloc_internal",
        "mbed_urealloc_internal"
      ],
      "filenames": [
        "source/ualloc.c"
      ]
    },
    {
      "headline": "Improper Synchronization - Potential Reentrancy Issues",
      "analysis": "There is a static volatile integer prevent_tracing used in various locations to prevent recursive logging. However, this simple flag mechanism is not thread-safe and can lead to race conditions where multiple threads could modify this flag simultaneously. This could result in inconsistent state or corrupted logs.\n",
      "classification": "very promising",
      "cwe": "CWE-362",
      "function_names": [
        "mbed_ualloc",
        "mbed_urealloc",
        "mbed_ufree"
      ],
      "filenames": [
        "source/ualloc.c"
      ]
    },
    {
      "headline": "Use of Potentially Unsafe Functions",
      "analysis": "The code contains uses of potentially unsafe functions such as printf for logging and memset without bounds checking. This can lead to buffer overflow vulnerabilities if the size parameters are not properly controlled or validated. In the context of the mbed_sbrk environment, this could corrupt the heap and result in undefined behavior or security risks.\n",
      "classification": "slightly promising",
      "cwe": "CWE-120",
      "function_names": [
        "ualloc_debug",
        "mbed_ualloc_internal"
      ],
      "filenames": [
        "source/ualloc.c"
      ]
    },
    {
      "headline": "No Proper Error Handling in Memory Allocation Functions",
      "analysis": "In the memory allocation functions, there is no proper error handling if allocation fails. The error handling mechanism currently used (printf statements) does not effectively mitigate the failure impact or provide fallback handling. Proper error handling should include cleaning up resources and returning error codes to the caller.\n",
      "classification": "slightly promising",
      "cwe": "CWE-252",
      "function_names": [
        "mbed_ualloc",
        "mbed_urealloc"
      ],
      "filenames": [
        "source/ualloc.c",
        "source/malloc.c"
      ]
    },
    {
      "headline": "Potential Information Leak via Debug Logs",
      "analysis": "Debug logs using printf can potentially leak sensitive information about memory addresses and allocation patterns which could be exploited by attackers to understand memory layout and employ attacks like heap spraying.\n",
      "classification": "not promising",
      "cwe": "CWE-209",
      "function_names": [
        "ualloc_debug"
      ],
      "filenames": [
        "source/ualloc.c"
      ]
    }
  ],
  "scores": [
    {
      "stats": {
        "fn": 1,
        "tp": 0,
        "fp": 2
      },
      "mapping": {},
      "vuln_dates": {
        "CVE-2021-27433": "2022-05-03T21:15:08"
      },
      "scoring_model": "claude-3-opus-20240229",
      "type": "llm",
      "instruction_template_hash": "245ace12b6361954d0a2"
    }
  ],
  "instruction_template_hash": "10c0163db4740318a544",
  "version": "0.1.0"
}
