{
  "commit": "bb3bdac931014f62ecce3fddc743b2c6bf91bb89",
  "repo_url": "https://github.com/jeecgboot/jimureport",
  "model": "gpt-4o-2024-05-13",
  "chunk_hashes": [
    "ac1cd0e3d4173f218b50"
  ],
  "responses": [
    {
      "content": "```yaml\nleads:\n  - headline: Hardcoded Token and Username\n    analysis: |\n      The JimuReportTokenService class has hardcoded token and username values in the methods getToken and getUsername. This can allow an unauthorized user to guess or obtain the hardcoded token/username, leading to unauthorized access.\n    cwe: CWE-798\n    function_names:\n      - getToken\n      - getUsername\n    filenames:\n      - jimureport-example/src/main/java/com/jeecg/modules/jmreport/config/JimuReportTokenService.java\n    classification: very promising\n\n  - headline: CORS Configuration Allows All Origins\n    analysis: |\n      The CustomCorsConfiguration class allows all origins for CORS requests by setting allowedOriginPatterns to \"*\". This can enable CORS requests from any domain, which might expose the application to cross-origin attacks if sensitive data is exposed in certain endpoints.\n    cwe: CWE-20\n    function_names:\n      - addCorsMappings\n    filenames:\n      - jimureport-example/src/main/java/com/jeecg/modules/jmreport/config/CustomCorsConfiguration.java\n    classification: slightly promising\n\n  - headline: Insufficient Token Validation\n    analysis: |\n      The verifyToken method in JimuReportTokenService always returns true, indicating successful token verification regardless of the token's validity. This flawed logic allows any request with any token to be considered authorized, leading to potential unauthorized access.\n    cwe: CWE-306\n    function_names:\n      - verifyToken\n    filenames:\n      - jimureport-example/src/main/java/com/jeecg/modules/jmreport/config/JimuReportTokenService.java\n    classification: very promising\n\n  - headline: Direct Exposure of Token in Custom Headers\n    analysis: |\n      The customApiHeader method in JimuReportTokenService directly adds a token in the HTTP headers without encryption or obfuscation. This practice can lead to token exposure if headers are intercepted.\n    cwe: CWE-200\n    function_names:\n      - customApiHeader\n    filenames:\n      - jimureport-example/src/main/java/com/jeecg/modules/jmreport/config/JimuReportTokenService.java\n    classification: slightly promising\n\n  - headline: Sensitive Data in Log Statements\n    analysis: |\n      Logging of sensitive data such as cache limits, max rows, and parameters can be observed in TestController and TestRpSpringBean. This can expose sensitive application details in log files.\n    cwe: CWE-532\n    function_names:\n      - queryPageList\n      - createData\n      - createPageData\n    filenames:\n      - jimureport-example/src/main/java/com/jeecg/modules/jmreport/controller/TestController.java\n      - jimureport-example/src/main/java/com/jeecg/modules/jmreport/testdb/TestRpSpringBean.java\n    classification: slightly promising\n```",
      "date": "2024-06-09T12:42:57.572457",
      "usage": {
        "prompt_tokens": 4327,
        "completion_tokens": 597,
        "cost": 0.03059
      }
    }
  ],
  "leads": [
    {
      "headline": "Hardcoded Token and Username",
      "analysis": "The JimuReportTokenService class has hardcoded token and username values in the methods getToken and getUsername. This can allow an unauthorized user to guess or obtain the hardcoded token/username, leading to unauthorized access.\n",
      "classification": "very promising",
      "cwe": "CWE-798",
      "function_names": [
        "getToken",
        "getUsername"
      ],
      "filenames": [
        "jimureport-example/src/main/java/com/jeecg/modules/jmreport/config/JimuReportTokenService.java"
      ]
    },
    {
      "headline": "CORS Configuration Allows All Origins",
      "analysis": "The CustomCorsConfiguration class allows all origins for CORS requests by setting allowedOriginPatterns to \"*\". This can enable CORS requests from any domain, which might expose the application to cross-origin attacks if sensitive data is exposed in certain endpoints.\n",
      "classification": "slightly promising",
      "cwe": "CWE-20",
      "function_names": [
        "addCorsMappings"
      ],
      "filenames": [
        "jimureport-example/src/main/java/com/jeecg/modules/jmreport/config/CustomCorsConfiguration.java"
      ]
    },
    {
      "headline": "Insufficient Token Validation",
      "analysis": "The verifyToken method in JimuReportTokenService always returns true, indicating successful token verification regardless of the token's validity. This flawed logic allows any request with any token to be considered authorized, leading to potential unauthorized access.\n",
      "classification": "very promising",
      "cwe": "CWE-306",
      "function_names": [
        "verifyToken"
      ],
      "filenames": [
        "jimureport-example/src/main/java/com/jeecg/modules/jmreport/config/JimuReportTokenService.java"
      ]
    },
    {
      "headline": "Direct Exposure of Token in Custom Headers",
      "analysis": "The customApiHeader method in JimuReportTokenService directly adds a token in the HTTP headers without encryption or obfuscation. This practice can lead to token exposure if headers are intercepted.\n",
      "classification": "slightly promising",
      "cwe": "CWE-200",
      "function_names": [
        "customApiHeader"
      ],
      "filenames": [
        "jimureport-example/src/main/java/com/jeecg/modules/jmreport/config/JimuReportTokenService.java"
      ]
    },
    {
      "headline": "Sensitive Data in Log Statements",
      "analysis": "Logging of sensitive data such as cache limits, max rows, and parameters can be observed in TestController and TestRpSpringBean. This can expose sensitive application details in log files.\n",
      "classification": "slightly promising",
      "cwe": "CWE-532",
      "function_names": [
        "queryPageList",
        "createData",
        "createPageData"
      ],
      "filenames": [
        "jimureport-example/src/main/java/com/jeecg/modules/jmreport/controller/TestController.java",
        "jimureport-example/src/main/java/com/jeecg/modules/jmreport/testdb/TestRpSpringBean.java"
      ]
    }
  ],
  "scores": [
    {
      "stats": {
        "fn": 2,
        "tp": 0,
        "fp": 2
      },
      "mapping": {},
      "vuln_dates": {
        "CVE-2023-4450": "2023-08-21T03:15:13",
        "CVE-2023-6307": "2023-11-27T02:15:42"
      },
      "scoring_model": "gpt-4o-2024-05-13",
      "type": "llm",
      "instruction_template_hash": "8998f09cf57fca8a6e03"
    },
    {
      "stats": {
        "fn": 2,
        "tp": 0,
        "fp": 2
      },
      "mapping": {},
      "vuln_dates": {
        "CVE-2023-4450": "2023-08-21T03:15:13",
        "CVE-2023-6307": "2023-11-27T02:15:42"
      },
      "scoring_model": "claude-3-opus-20240229",
      "type": "llm",
      "instruction_template_hash": "245ace12b6361954d0a2"
    },
    {
      "stats": {
        "fn": 2,
        "tp": 0,
        "fp": 2
      },
      "mapping": {},
      "vuln_dates": {
        "CVE-2023-4450": "2023-08-21T03:15:13",
        "CVE-2023-6307": "2023-11-27T02:15:42"
      },
      "scoring_model": "claude-3-5-sonnet-20240620",
      "type": "llm",
      "instruction_template_hash": "245ace12b6361954d0a2"
    }
  ],
  "instruction_template_hash": "10c0163db4740318a544",
  "version": "0.1.0"
}
