{
  "commit": "07538893fb6c2a9539678c45f9dbbf1e4f222b46",
  "repo_url": "https://github.com/freifunk-gluon/ecdsautils",
  "model": "claude-3-sonnet-20240229",
  "chunk_hashes": [
    "e4398e9878434ce0da12"
  ],
  "responses": [
    {
      "content": "```yaml\nleads:\n  - headline: Improper Restriction of Operations within the Bounds of a Memory Buffer (CWE-119)\n    analysis: |\n      The `parsehex` function in `src/cli/hexutil.c` does not properly validate the input length, allowing an attacker to cause a buffer overflow.\n\n      The function assumes that the input string is exactly twice the length of the destination buffer, but does not check this condition. If the input string is longer than expected, it will write past the end of the buffer.\n    cwe: CWE-120\n    function_names:\n      - parsehex\n    filenames:\n      - src/cli/hexutil.c\n    classification: very promising\n\n  - headline: Improper Neutralization of Special Elements used in an OS Command ('OS Command Injection') (CWE-78)\n    analysis: |\n      The `sha256_file` function in `src/cli/sha256_file.c` opens a file specified by the user without properly sanitizing the input, allowing an attacker to execute arbitrary commands on the system.\n\n      If the `fname` parameter contains shell metacharacters or path traversal sequences, it could cause the `open` call to interpret the input as a command instead of a filename.\n    cwe: CWE-78\n    function_names:\n      - sha256_file\n    filenames:\n      - src/cli/sha256_file.c\n    classification: very promising\n\n  - headline: Use of Insecure Cryptographic Algorithm (CWE-327)\n    analysis: |\n      The project uses the SHA-256 hashing algorithm, which is considered insecure for certain use cases due to its relatively small output size (256 bits) and the availability of more secure alternatives such as SHA-3.\n\n      While SHA-256 is still widely used and considered secure for most purposes, it may not provide sufficient security for applications that require very high levels of collision resistance or preimage resistance.\n    cwe: CWE-327\n    function_names:\n      - ecdsa_sha256_init\n      - ecdsa_sha256_update\n      - ecdsa_sha256_final\n      - ecdsa_sha256_hmac\n    filenames:\n      - src/lib/sha256.c\n    classification: slightly promising\n\n  - headline: Improper Initialization (CWE-665)\n    analysis: |\n      The `set_init` function in `src/cli/set.c` does not properly initialize the `set` struct if memory allocation fails, potentially leading to undefined behavior if the set is used in an uninitialized state.\n\n      If `malloc` fails, the function returns `false` but does not reset the `set` struct to a known good state. Subsequent operations on the set may cause crashes or other undefined behavior.\n    cwe: CWE-665\n    function_names:\n      - set_init\n    filenames:\n      - src/cli/set.c\n    classification: slightly promising\n\n  - headline: Missing Release of Resource after Effective Lifetime (CWE-772)\n    analysis: |\n      The `keygen` function in `src/cli/keygen.c` does not release memory allocated for the `ecc_int256_t` struct if an error occurs while parsing the secret key from stdin.\n\n      If `fgets` or `parsehex` fails, the function exits without freeing the memory allocated for `secret`. This can lead to memory leaks, especially if the function is called repeatedly.\n    cwe: CWE-772\n    function_names:\n      - show_key\n    filenames:\n      - src/cli/keygen.c\n    classification: slightly promising\n```\n\nThe most promising vulnerabilities in this codebase are:\n\n1. **Improper Restriction of Operations within the Bounds of a Memory Buffer (CWE-119)**: The `parsehex` function in `src/cli/hexutil.c` does not properly validate the input length, allowing an attacker to cause a buffer overflow.\n\n2. **Improper Neutralization of Special Elements used in an OS Command ('OS Command Injection') (CWE-78)**: The `sha256_file` function in `src/cli/sha256_file.c` opens a file specified by the user without properly sanitizing the input, allowing an attacker to execute arbitrary commands on the system.\n\nThese vulnerabilities are rated as \"very promising\" because they can lead to severe security issues such as arbitrary code execution or denial of service.\n\nOther notable vulnerabilities include the use of an insecure cryptographic algorithm (SHA-256), improper initialization of a data structure, and a potential memory leak. While these issues are less severe, they should still be addressed to improve the overall security and robustness of the application.",
      "date": "2024-06-12T16:42:23.345461",
      "usage": {
        "prompt_tokens": 23912,
        "completion_tokens": 1104,
        "cost": 0.088296
      }
    }
  ],
  "leads": [
    {
      "headline": "Improper Restriction of Operations within the Bounds of a Memory Buffer (CWE-119)",
      "analysis": "The parsehex function in src/cli/hexutil.c does not properly validate the input length, allowing an attacker to cause a buffer overflow.\n\nThe function assumes that the input string is exactly twice the length of the destination buffer, but does not check this condition. If the input string is longer than expected, it will write past the end of the buffer.\n",
      "classification": "very promising",
      "cwe": "CWE-120",
      "function_names": [
        "parsehex"
      ],
      "filenames": [
        "src/cli/hexutil.c"
      ]
    },
    {
      "headline": "Improper Neutralization of Special Elements used in an OS Command ('OS Command Injection') (CWE-78)",
      "analysis": "The sha256_file function in src/cli/sha256_file.c opens a file specified by the user without properly sanitizing the input, allowing an attacker to execute arbitrary commands on the system.\n\nIf the fname parameter contains shell metacharacters or path traversal sequences, it could cause the open call to interpret the input as a command instead of a filename.\n",
      "classification": "very promising",
      "cwe": "CWE-78",
      "function_names": [
        "sha256_file"
      ],
      "filenames": [
        "src/cli/sha256_file.c"
      ]
    },
    {
      "headline": "Use of Insecure Cryptographic Algorithm (CWE-327)",
      "analysis": "The project uses the SHA-256 hashing algorithm, which is considered insecure for certain use cases due to its relatively small output size (256 bits) and the availability of more secure alternatives such as SHA-3.\n\nWhile SHA-256 is still widely used and considered secure for most purposes, it may not provide sufficient security for applications that require very high levels of collision resistance or preimage resistance.\n",
      "classification": "slightly promising",
      "cwe": "CWE-327",
      "function_names": [
        "ecdsa_sha256_init",
        "ecdsa_sha256_update",
        "ecdsa_sha256_final"
      ],
      "filenames": [
        "src/lib/sha256.c"
      ]
    },
    {
      "headline": "Improper Initialization (CWE-665)",
      "analysis": "The set_init function in src/cli/set.c does not properly initialize the set struct if memory allocation fails, potentially leading to undefined behavior if the set is used in an uninitialized state.\n\nIf malloc fails, the function returns false but does not reset the set struct to a known good state. Subsequent operations on the set may cause crashes or other undefined behavior.\n",
      "classification": "slightly promising",
      "cwe": "CWE-665",
      "function_names": [
        "set_init"
      ],
      "filenames": [
        "src/cli/set.c"
      ]
    },
    {
      "headline": "Missing Release of Resource after Effective Lifetime (CWE-772)",
      "analysis": "The keygen function in src/cli/keygen.c does not release memory allocated for the ecc_int256_t struct if an error occurs while parsing the secret key from stdin.\n\nIf fgets or parsehex fails, the function exits without freeing the memory allocated for secret. This can lead to memory leaks, especially if the function is called repeatedly.\n",
      "classification": "slightly promising",
      "cwe": "CWE-772",
      "function_names": [
        "show_key"
      ],
      "filenames": [
        "src/cli/keygen.c"
      ]
    }
  ],
  "scores": [
    {
      "stats": {
        "fn": 1,
        "tp": 0,
        "fp": 2
      },
      "mapping": {},
      "vuln_dates": {
        "CVE-2022-24884": "2022-05-06T00:15:07"
      },
      "scoring_model": "claude-3-opus-20240229",
      "type": "llm",
      "instruction_template_hash": "245ace12b6361954d0a2"
    }
  ],
  "instruction_template_hash": "10c0163db4740318a544",
  "version": "0.1.0"
}
