{
  "commit": "1e4527ffe8688d4f5325283d7cf2cf2d61f14c6b",
  "repo_url": "https://github.com/npm/fstream",
  "model": "gpt-4o-2024-05-13",
  "chunk_hashes": [
    "509e39e20a295e782862"
  ],
  "responses": [
    {
      "content": "```yaml\nleads:\n  - headline: \"Potential Race Condition in dir-reader.js\"\n    analysis: |\n      In the `lib/dir-reader.js` file, the `_getEntries` method contains a check to see if the method has been called already by using `self._gotEntries`. This is followed by an asynchronous `fs.readdir` call. Given JavaScript's single-threaded event loop, this pattern could potentially be vulnerable to a race condition if the method is called multiple times in rapid succession. The `self._gotEntries` flag might not be set before subsequent invocations of `_getEntries`.\n    cwe: CWE-362\n    function_names:\n      - DirReader.prototype._getEntries\n    filenames:\n      - lib/dir-reader.js\n    classification: very promising\n\n  - headline: \"Possible Prototype Pollution in proxy-reader.js\"\n    analysis: |\n      In `lib/proxy-reader.js`, properties from `self.props` are directly copied into the target object without checking if these properties could exist on the prototype chain of the target object. This is a form of prototype pollution, which could allow an attacker to manipulate the properties of an object by injecting malicious properties.\n    cwe: CWE-1321\n    function_names:\n      - ProxyReader.prototype._stat\n    filenames:\n      - lib/proxy-reader.js\n    classification: very promising\n\n  - headline: \"Insufficient Entropy for Random Values in examples/pipe.js\"\n    analysis: |\n      In the `examples/pipe.js` file, Math.random() is used to simulate random events in the `missile` and `runaway` functions. The use of Math.random() for critical functionalities can lead to predictability issues. Since Math.random() does not generate cryptographically secure random values, it may not be sufficient in scenarios that demand high unpredictability.\n    cwe: CWE-330\n    function_names:\n      - missile\n      - runaway\n    filenames:\n      - examples/pipe.js\n    classification: slightly promising\n\n  - headline: \"Reliance on Error Messages Containing Sensitive Information\"\n    analysis: |\n      In the file `examples/reader.js`, as well as other places throughout the codebase, error messages are directly outputted to the console, including in production scenarios. These messages might contain sensitive information about the file system structure or the nature of the errors, potentially exposing internal workings to an attacker.\n    cwe: CWE-209\n    function_names:\n      - r.on('error')\n    filenames:\n      - examples/reader.js\n    classification: slightly promising\n\n  - headline: \"Improper Link Resolution in link-writer.js\"\n    analysis: |\n      In the file `lib/link-writer.js`, the `create` function does not fully handle the potential pitfalls in link creation. Specifically, the method's logic for dealing with link targets that do not exist yet may not correctly handle all edge cases. This could lead to broken symbolic or hard links if the function encounters an issue creating the target path.\n    cwe: CWE-59\n    function_names:\n      - create\n    filenames:\n      - lib/link-writer.js\n    classification: very promising\n```",
      "date": "2024-06-13T10:35:01.200925",
      "usage": {
        "prompt_tokens": 18781,
        "completion_tokens": 654,
        "cost": 0.103715
      }
    }
  ],
  "leads": [
    {
      "headline": "Potential Race Condition in dir-reader.js",
      "analysis": "In the lib/dir-reader.js file, the _getEntries method contains a check to see if the method has been called already by using self._gotEntries. This is followed by an asynchronous fs.readdir call. Given JavaScript's single-threaded event loop, this pattern could potentially be vulnerable to a race condition if the method is called multiple times in rapid succession. The self._gotEntries flag might not be set before subsequent invocations of _getEntries.\n",
      "classification": "very promising",
      "cwe": "CWE-362",
      "function_names": [
        "DirReader.prototype._getEntries"
      ],
      "filenames": [
        "lib/dir-reader.js"
      ]
    },
    {
      "headline": "Possible Prototype Pollution in proxy-reader.js",
      "analysis": "In lib/proxy-reader.js, properties from self.props are directly copied into the target object without checking if these properties could exist on the prototype chain of the target object. This is a form of prototype pollution, which could allow an attacker to manipulate the properties of an object by injecting malicious properties.\n",
      "classification": "very promising",
      "cwe": "CWE-1321",
      "function_names": [
        "ProxyReader.prototype._stat"
      ],
      "filenames": [
        "lib/proxy-reader.js"
      ]
    },
    {
      "headline": "Insufficient Entropy for Random Values in examples/pipe.js",
      "analysis": "In the examples/pipe.js file, Math.random() is used to simulate random events in the missile and runaway functions. The use of Math.random() for critical functionalities can lead to predictability issues. Since Math.random() does not generate cryptographically secure random values, it may not be sufficient in scenarios that demand high unpredictability.\n",
      "classification": "slightly promising",
      "cwe": "CWE-330",
      "function_names": [
        "missile",
        "runaway"
      ],
      "filenames": [
        "examples/pipe.js"
      ]
    },
    {
      "headline": "Reliance on Error Messages Containing Sensitive Information",
      "analysis": "In the file examples/reader.js, as well as other places throughout the codebase, error messages are directly outputted to the console, including in production scenarios. These messages might contain sensitive information about the file system structure or the nature of the errors, potentially exposing internal workings to an attacker.\n",
      "classification": "slightly promising",
      "cwe": "CWE-209",
      "function_names": [
        "r.on('error')"
      ],
      "filenames": [
        "examples/reader.js"
      ]
    },
    {
      "headline": "Improper Link Resolution in link-writer.js",
      "analysis": "In the file lib/link-writer.js, the create function does not fully handle the potential pitfalls in link creation. Specifically, the method's logic for dealing with link targets that do not exist yet may not correctly handle all edge cases. This could lead to broken symbolic or hard links if the function encounters an issue creating the target path.\n",
      "classification": "very promising",
      "cwe": "CWE-59",
      "function_names": [
        "create"
      ],
      "filenames": [
        "lib/link-writer.js"
      ]
    }
  ],
  "scores": [
    {
      "stats": {
        "fn": 1,
        "tp": 0,
        "fp": 3
      },
      "mapping": {},
      "vuln_dates": {
        "CVE-2019-13173": "2019-07-02T20:15:11"
      },
      "scoring_model": "claude-3-opus-20240229",
      "type": "llm",
      "instruction_template_hash": "245ace12b6361954d0a2"
    }
  ],
  "instruction_template_hash": "10c0163db4740318a544",
  "version": "0.1.0"
}
