{
  "commit": "01b947e0058c79a77901a2c3afdb0cbfd4cf9427",
  "repo_url": "https://github.com/jenkinsci/eagle-tester-plugin",
  "model": "gpt-4o-2024-05-13",
  "chunk_hashes": [
    "10c0c29d7ba0f12451e3"
  ],
  "responses": [
    {
      "content": "```yaml\nleads:\n  - headline: \"Plaintext Credentials in Code\"\n    analysis: |\n      In the file `src/test/java/com/mobileenerlytics/eagle/tester/common/util/LargeFileUploadTest.java`, sensitive credentials such as username and password are hardcoded within the code. The same issue is present in several other parts of the codebase. Hardcoding credentials expose them to anyone who has access to the codebase, leading to potential misuse if the code is leaked or viewed by unauthorized personnel. This can result in unauthorized access to the application or system, compromising data security and possibly leading to other vulnerabilities.\n    cwe: CWE-798\n    function_names:\n      - uploadTest\n    filenames:\n      - src/test/java/com/mobileenerlytics/eagle/tester/common/util/LargeFileUploadTest.java\n      - src/main/java/com/mobileenerlytics/eagle/tester/jenkins/eagletesterjenkins/EagleWrapper.java\n    classification: very promising\n\n  - headline: \"Creation of Temporary Files with Insecure Permissions\"\n    analysis: |\n      In the `LargeFileUploadTest` class within `src/test/java/com/mobileenerlytics/eagle/tester/common/util/LargeFileUploadTest.java`, the code uses `Files.createTempFile()` to create a temporary file. However, the code does not specify secure file permissions, which can result in temporary files being accessible by unauthorized users. This can be exploited if other users on the system find and access these files, potentially leading to exposure of sensitive data.\n    cwe: CWE-377\n    function_names:\n      - uploadTest\n    filenames:\n      - src/test/java/com/mobileenerlytics/eagle/tester/common/util/LargeFileUploadTest.java\n    classification: very promising\n\n  - headline: \"Use of Insecure Random Generator\"\n    analysis: |\n      The password used in the `LicenseVerifier` class within `src/main/java/com/mobileenerlytics/eagle/tester/common/util/LicenseVerifier.java` is hardcoded, which follows an insecure practice of using predictable credentials. Moreover, the code lacks cryptographic measures to ensure the secure handling of generated or used keys and passwords. This can lead to potential cryptographic vulnerabilities.\n    cwe: CWE-330\n    function_names:\n      - verify\n      - getEncryptedPublicKeyData\n    filenames:\n      - src/main/java/com/mobileenerlytics/eagle/tester/common/util/LicenseVerifier.java\n    classification: very promising\n\n  - headline: \"Improper Input Validation in adb Commands\"\n    analysis: |\n      The `DeviceUtils` utility class within `src/main/java/com/mobileenerlytics/eagle/tester/common/util/DeviceUtils.java` constructs adb commands by concatenating strings based on user input. This approach can lead to injection vulnerabilities if user-provided inputs are not properly sanitized and validated. Specifically, constructing adb commands using unvalidated inputs can allow attackers to execute arbitrary commands on the device.\n    cwe: CWE-78\n    function_names:\n      - runAdb\n      - pullFromDevice\n      - rmFromDevice\n      - installApp\n      - forceStopApp\n      - getExternalStorage\n    filenames:\n      - src/main/java/com/mobileenerlytics/eagle/tester/common/util/DeviceUtils.java\n    classification: very promising\n\n  - headline: \"Exposure of Debug Information\"\n    analysis: |\n      The `Log` utility class within `src/main/java/com/mobileenerlytics/eagle/tester/common/util/Log.java` provides methods for logging various levels of information, including debug logs. The debug flag is set to true by default, potentially exposing sensitive operational information. This can be useful for attackers to gain insights into the application's internal operations and facilitate further exploitation.\n    cwe: CWE-209\n    function_names:\n      - i\n      - e\n      - w\n      - d\n    filenames:\n      - src/main/java/com/mobileenerlytics/eagle/tester/common/util/Log.java\n    classification: slightly promising\n\n  - headline: \"Resource Consumption Issues with Large File Upload\"\n    analysis: |\n      The `LargeFileUploadTest` class in `src/test/java/com/mobileenerlytics/eagle/tester/common/util/LargeFileUploadTest.java` creates a temporary file of 4GB to test file upload capabilities. Such large file operations can lead to resource exhaustion issues, such as excessive memory and disk usage on the system running the test. This can cause slowdown or crashing of the host system, affecting the availability of services.\n    cwe: CWE-400\n    function_names:\n      - uploadTest\n    filenames:\n      - src/test/java/com/mobileenerlytics/eagle/tester/common/util/LargeFileUploadTest.java\n    classification: slightly promising\n```",
      "date": "2024-06-12T18:22:22.527183",
      "usage": {
        "prompt_tokens": 9786,
        "completion_tokens": 987,
        "cost": 0.063735
      }
    }
  ],
  "leads": [
    {
      "headline": "Plaintext Credentials in Code",
      "analysis": "In the file src/test/java/com/mobileenerlytics/eagle/tester/common/util/LargeFileUploadTest.java, sensitive credentials such as username and password are hardcoded within the code. The same issue is present in several other parts of the codebase. Hardcoding credentials expose them to anyone who has access to the codebase, leading to potential misuse if the code is leaked or viewed by unauthorized personnel. This can result in unauthorized access to the application or system, compromising data security and possibly leading to other vulnerabilities.\n",
      "classification": "very promising",
      "cwe": "CWE-798",
      "function_names": [
        "uploadTest"
      ],
      "filenames": [
        "src/test/java/com/mobileenerlytics/eagle/tester/common/util/LargeFileUploadTest.java",
        "src/main/java/com/mobileenerlytics/eagle/tester/jenkins/eagletesterjenkins/EagleWrapper.java"
      ]
    },
    {
      "headline": "Creation of Temporary Files with Insecure Permissions",
      "analysis": "In the LargeFileUploadTest class within src/test/java/com/mobileenerlytics/eagle/tester/common/util/LargeFileUploadTest.java, the code uses Files.createTempFile() to create a temporary file. However, the code does not specify secure file permissions, which can result in temporary files being accessible by unauthorized users. This can be exploited if other users on the system find and access these files, potentially leading to exposure of sensitive data.\n",
      "classification": "very promising",
      "cwe": "CWE-377",
      "function_names": [
        "uploadTest"
      ],
      "filenames": [
        "src/test/java/com/mobileenerlytics/eagle/tester/common/util/LargeFileUploadTest.java"
      ]
    },
    {
      "headline": "Use of Insecure Random Generator",
      "analysis": "The password used in the LicenseVerifier class within src/main/java/com/mobileenerlytics/eagle/tester/common/util/LicenseVerifier.java is hardcoded, which follows an insecure practice of using predictable credentials. Moreover, the code lacks cryptographic measures to ensure the secure handling of generated or used keys and passwords. This can lead to potential cryptographic vulnerabilities.\n",
      "classification": "very promising",
      "cwe": "CWE-330",
      "function_names": [
        "verify",
        "getEncryptedPublicKeyData"
      ],
      "filenames": [
        "src/main/java/com/mobileenerlytics/eagle/tester/common/util/LicenseVerifier.java"
      ]
    },
    {
      "headline": "Improper Input Validation in adb Commands",
      "analysis": "The DeviceUtils utility class within src/main/java/com/mobileenerlytics/eagle/tester/common/util/DeviceUtils.java constructs adb commands by concatenating strings based on user input. This approach can lead to injection vulnerabilities if user-provided inputs are not properly sanitized and validated. Specifically, constructing adb commands using unvalidated inputs can allow attackers to execute arbitrary commands on the device.\n",
      "classification": "very promising",
      "cwe": "CWE-78",
      "function_names": [
        "runAdb",
        "pullFromDevice",
        "rmFromDevice"
      ],
      "filenames": [
        "src/main/java/com/mobileenerlytics/eagle/tester/common/util/DeviceUtils.java"
      ]
    },
    {
      "headline": "Exposure of Debug Information",
      "analysis": "The Log utility class within src/main/java/com/mobileenerlytics/eagle/tester/common/util/Log.java provides methods for logging various levels of information, including debug logs. The debug flag is set to true by default, potentially exposing sensitive operational information. This can be useful for attackers to gain insights into the application's internal operations and facilitate further exploitation.\n",
      "classification": "slightly promising",
      "cwe": "CWE-209",
      "function_names": [
        "i",
        "e",
        "w"
      ],
      "filenames": [
        "src/main/java/com/mobileenerlytics/eagle/tester/common/util/Log.java"
      ]
    },
    {
      "headline": "Resource Consumption Issues with Large File Upload",
      "analysis": "The LargeFileUploadTest class in src/test/java/com/mobileenerlytics/eagle/tester/common/util/LargeFileUploadTest.java creates a temporary file of 4GB to test file upload capabilities. Such large file operations can lead to resource exhaustion issues, such as excessive memory and disk usage on the system running the test. This can cause slowdown or crashing of the host system, affecting the availability of services.\n",
      "classification": "slightly promising",
      "cwe": "CWE-400",
      "function_names": [
        "uploadTest"
      ],
      "filenames": [
        "src/test/java/com/mobileenerlytics/eagle/tester/common/util/LargeFileUploadTest.java"
      ]
    }
  ],
  "scores": [
    {
      "stats": {
        "fn": 1,
        "tp": 0,
        "fp": 4
      },
      "mapping": {},
      "vuln_dates": {
        "CVE-2020-2129": "2020-02-12T15:15:14"
      },
      "scoring_model": "claude-3-opus-20240229",
      "type": "llm",
      "instruction_template_hash": "245ace12b6361954d0a2"
    },
    {
      "stats": {
        "fn": 0,
        "tp": 1,
        "fp": 3
      },
      "mapping": {
        "0": "CVE-2020-2129"
      },
      "vuln_dates": {
        "CVE-2020-2129": "2020-02-12T15:15:14"
      },
      "scoring_model": "claude-3-5-sonnet-20240620",
      "type": "llm",
      "instruction_template_hash": "245ace12b6361954d0a2"
    }
  ],
  "instruction_template_hash": "10c0163db4740318a544",
  "version": "0.1.0"
}
