{
  "commit": "03fcf987307a9b1963075007d9fe2e8720fa7e25",
  "repo_url": "https://github.com/xmldom/xmldom",
  "model": "claude-3-sonnet-20240229",
  "chunk_hashes": [
    "b9b0e05ceeb6ebe5e90e"
  ],
  "responses": [
    {
      "content": "Here are the potential security vulnerabilities I found in the codebase, represented as a YAML object of type LeadList:\n\n```yaml\nleads:\n  - headline: Improper Restriction of Recursive Entity References in DTDs ('XML Entity Expansion')\n    analysis: |\n      The codebase does not seem to have any protection against XML external entity (XXE) attacks. \n      An attacker could craft a malicious XML document that causes the parser to retrieve sensitive\n      data or execute arbitrary code on the server by defining an external entity that gets loaded\n      during parsing.\n    cwe: CWE-776\n    function_names:\n      - DOMParser.parseFromString\n      - XMLReader.parse\n    filenames:\n      - lib/dom-parser.js\n      - lib/sax.js\n    classification: very promising\n\n  - headline: Use of Externally-Controlled Input to Select Classes or Code ('Unsafe Reflection')\n    analysis: |\n      The codebase uses user input (tag names, attribute names, and values) to construct DOM nodes\n      without any validation or sanitization. An attacker could potentially leverage this to invoke\n      arbitrary code by providing crafted input that gets interpreted as code.\n    cwe: CWE-470\n    function_names:\n      - DOMParser.parseFromString\n      - XMLReader.parse\n    filenames:\n      - lib/dom-parser.js \n      - lib/sax.js\n    classification: very promising\n\n  - headline: Improper Input Validation\n    analysis: |\n      The codebase does not perform sufficient validation on user input (tag names, attribute names, \n      and values) before using it to construct DOM nodes. This could potentially allow an attacker\n      to inject malicious content or code by providing crafted input.\n    cwe: CWE-20\n    function_names:\n      - DOMParser.parseFromString\n      - XMLReader.parse\n    filenames:\n      - lib/dom-parser.js\n      - lib/sax.js  \n    classification: very promising\n\n  - headline: Improper Encoding or Escaping of Output\n    analysis: |\n      The `nodeSerializeToString` function in `lib/dom.js` does not properly escape all characters\n      that could be interpreted as markup when serializing nodes to a string. This could potentially\n      lead to cross-site scripting (XSS) vulnerabilities if the serialized output is embedded in an\n      HTML context without proper sanitization.\n    cwe: CWE-116\n    function_names:\n      - nodeSerializeToString\n    filenames:\n      - lib/dom.js\n    classification: very promising\n\n  - headline: Unrestricted Upload of File with Dangerous Type\n    analysis: |\n      The codebase appears to allow parsing any type of input as XML without restrictions. \n      An attacker could potentially upload files containing dangerous content (e.g. HTML, JavaScript)\n      and have them parsed and executed by the application, leading to various vulnerabilities.\n    cwe: CWE-434 \n    function_names:\n      - DOMParser.parseFromString\n    filenames:\n      - lib/dom-parser.js\n    classification: slightly promising\n\n  - headline: Exposure of Sensitive Information to an Unauthorized Actor\n    analysis: |\n      The `error` function in `lib/sax.js` logs error messages to the console without any filtering\n      or sanitization. If these error messages contain sensitive information from the parsed XML,\n      this could potentially expose that information to unauthorized actors.\n    cwe: CWE-200\n    function_names:\n      - error\n    filenames:\n      - lib/sax.js\n    classification: slightly promising  \n\n  - headline: Deserialization of Untrusted Data\n    analysis: |\n      The codebase appears to allow deserialization of any XML data without validation or sanitization.\n      An attacker could potentially leverage this to execute arbitrary code by providing a malicious\n      XML payload that gets deserialized by the application.\n    cwe: CWE-502\n    function_names:\n      - DOMParser.parseFromString\n    filenames:\n      - lib/dom-parser.js\n    classification: slightly promising\n```\n\nThis covers the main potential vulnerabilities I could identify in the provided codebase. Please note that a more thorough review and testing would be necessary to confirm the presence and severity of these issues.",
      "date": "2024-06-14T10:51:26.367063",
      "usage": {
        "prompt_tokens": 68698,
        "completion_tokens": 1031,
        "cost": 0.221559
      }
    }
  ],
  "leads": [
    {
      "headline": "Improper Restriction of Recursive Entity References in DTDs ('XML Entity Expansion')",
      "analysis": "The codebase does not seem to have any protection against XML external entity (XXE) attacks. \nAn attacker could craft a malicious XML document that causes the parser to retrieve sensitive\ndata or execute arbitrary code on the server by defining an external entity that gets loaded\nduring parsing.\n",
      "classification": "very promising",
      "cwe": "CWE-776",
      "function_names": [
        "DOMParser.parseFromString",
        "XMLReader.parse"
      ],
      "filenames": [
        "lib/dom-parser.js",
        "lib/sax.js"
      ]
    },
    {
      "headline": "Use of Externally-Controlled Input to Select Classes or Code ('Unsafe Reflection')",
      "analysis": "The codebase uses user input (tag names, attribute names, and values) to construct DOM nodes\nwithout any validation or sanitization. An attacker could potentially leverage this to invoke\narbitrary code by providing crafted input that gets interpreted as code.\n",
      "classification": "very promising",
      "cwe": "CWE-470",
      "function_names": [
        "DOMParser.parseFromString",
        "XMLReader.parse"
      ],
      "filenames": [
        "lib/dom-parser.js",
        "lib/sax.js"
      ]
    },
    {
      "headline": "Improper Input Validation",
      "analysis": "The codebase does not perform sufficient validation on user input (tag names, attribute names, \nand values) before using it to construct DOM nodes. This could potentially allow an attacker\nto inject malicious content or code by providing crafted input.\n",
      "classification": "very promising",
      "cwe": "CWE-20",
      "function_names": [
        "DOMParser.parseFromString",
        "XMLReader.parse"
      ],
      "filenames": [
        "lib/dom-parser.js",
        "lib/sax.js"
      ]
    },
    {
      "headline": "Improper Encoding or Escaping of Output",
      "analysis": "The nodeSerializeToString function in lib/dom.js does not properly escape all characters\nthat could be interpreted as markup when serializing nodes to a string. This could potentially\nlead to cross-site scripting (XSS) vulnerabilities if the serialized output is embedded in an\nHTML context without proper sanitization.\n",
      "classification": "very promising",
      "cwe": "CWE-116",
      "function_names": [
        "nodeSerializeToString"
      ],
      "filenames": [
        "lib/dom.js"
      ]
    },
    {
      "headline": "Unrestricted Upload of File with Dangerous Type",
      "analysis": "The codebase appears to allow parsing any type of input as XML without restrictions. \nAn attacker could potentially upload files containing dangerous content (e.g. HTML, JavaScript)\nand have them parsed and executed by the application, leading to various vulnerabilities.\n",
      "classification": "slightly promising",
      "cwe": "CWE-434",
      "function_names": [
        "DOMParser.parseFromString"
      ],
      "filenames": [
        "lib/dom-parser.js"
      ]
    },
    {
      "headline": "Exposure of Sensitive Information to an Unauthorized Actor",
      "analysis": "The error function in lib/sax.js logs error messages to the console without any filtering\nor sanitization. If these error messages contain sensitive information from the parsed XML,\nthis could potentially expose that information to unauthorized actors.\n",
      "classification": "slightly promising",
      "cwe": "CWE-200",
      "function_names": [
        "error"
      ],
      "filenames": [
        "lib/sax.js"
      ]
    },
    {
      "headline": "Deserialization of Untrusted Data",
      "analysis": "The codebase appears to allow deserialization of any XML data without validation or sanitization.\nAn attacker could potentially leverage this to execute arbitrary code by providing a malicious\nXML payload that gets deserialized by the application.\n",
      "classification": "slightly promising",
      "cwe": "CWE-502",
      "function_names": [
        "DOMParser.parseFromString"
      ],
      "filenames": [
        "lib/dom-parser.js"
      ]
    }
  ],
  "scores": [
    {
      "stats": {
        "fn": 1,
        "tp": 0,
        "fp": 4
      },
      "mapping": {},
      "vuln_dates": {
        "CVE-2022-37616": "2022-10-11T05:15:10"
      },
      "scoring_model": "claude-3-opus-20240229",
      "type": "llm",
      "instruction_template_hash": "245ace12b6361954d0a2"
    },
    {
      "stats": {
        "fn": 1,
        "tp": 0,
        "fp": 4
      },
      "mapping": {},
      "vuln_dates": {
        "CVE-2022-37616": "2022-10-11T05:15:10"
      },
      "scoring_model": "claude-3-5-sonnet-20240620",
      "type": "llm",
      "instruction_template_hash": "245ace12b6361954d0a2"
    }
  ],
  "instruction_template_hash": "10c0163db4740318a544",
  "version": "0.1.0"
}
