{
  "commit": "16d62322e6d7a0a0478357e5994a055a4645c557",
  "repo_url": "https://github.com/jenkinsci/radiatorview-plugin",
  "model": "gpt-4o-2024-05-13",
  "chunk_hashes": [
    "15ad9cc86e7933333cce"
  ],
  "responses": [
    {
      "content": "```yaml\nleads:\n  - headline: \"Lack of Data Validation in isValidAction Method\"\n    analysis: |\n      The function getActions in the ClaimWrapper class does not perform sufficient validation of input, which could allow an attacker to pass in invalid parameters. This could lead to unexpected behavior or security vulnerabilities if these parameters are used in sensitive operations.\n    cwe: CWE-20\n    function_names:\n      - getActions\n    filenames:\n      - src/main/java/hudson/model/ClaimWrapper.java\n    classification: very promising\n\n  - headline: \"Multiple ClaimBuildActions Warning Could Lead to Information Leakage\"\n    analysis: |\n      The code logs a warning when multiple ClaimBuildActions are found for a run using the Log.warn method. This information might be sensitive and should not be disclosed in logs as it may provide attackers with insights into the system\u2019s operations and configurations.\n    cwe: CWE-532\n    function_names:\n      - getClaimForRun\n    filenames:\n      - src/main/java/hudson/model/ClaimWrapper.java\n    classification: very promising\n\n  - headline: \"Potential Sensitive Data Exposure via getClaim Method\"\n    analysis: |\n      The getClaim method in the JobViewEntry class could expose potentially sensitive information such as the reason for the claim and the username of the person who made the claim. If this method is accessible by unauthorized users, this could lead to a privacy violation.\n    cwe: CWE-200\n    function_names:\n      - getClaim\n    filenames:\n      - src/main/java/hudson/model/JobViewEntry.java\n    classification: very promising\n\n  - headline: \"Use of getPreviousBuildInProgress Without Null Check\"\n    analysis: |\n      The method getBuildsInProgress in JobViewEntry class calls getPreviousBuildInProgress on run objects without performing null checks. This could lead to a NullPointerException if any run object does not have a previous build in progress.\n    cwe: CWE-476\n    function_names:\n      - getBuildsInProgress\n    filenames:\n      - src/main/java/hudson/model/JobViewEntry.java\n    classification: slightly promising\n\n  - headline: \"Hardcoded Colors in ViewEntryColors\"\n    analysis: |\n      The ViewEntryColors class has hard-coded color values for various background and foreground properties. Such hardcoded values might not be suitable for all accessibility needs and could be modified dynamically for higher flexibility.\n    cwe: CWE-778\n    function_names: []\n    filenames:\n      - src/main/java/hudson/model/ViewEntryColors.java\n    classification: not promising\n\n  - headline: \"Inadequate Handling of Regular Expression for Exclude Regex\"\n    analysis: |\n      The isExcluded method in RadiatorView class uses Pattern.matches which can throw PatternSyntaxException. This exception is not caught which could potentially lead to unexpected application behavior if invalid regex patterns are supplied.\n    cwe: CWE-754\n    function_names:\n      - isExcluded\n    filenames:\n      - src/main/java/hudson/model/RadiatorView.java\n    classification: very promising\n```",
      "date": "2024-06-12T19:05:12.976371",
      "usage": {
        "prompt_tokens": 12401,
        "completion_tokens": 641,
        "cost": 0.07162
      }
    }
  ],
  "leads": [
    {
      "headline": "Lack of Data Validation in isValidAction Method",
      "analysis": "The function getActions in the ClaimWrapper class does not perform sufficient validation of input, which could allow an attacker to pass in invalid parameters. This could lead to unexpected behavior or security vulnerabilities if these parameters are used in sensitive operations.\n",
      "classification": "very promising",
      "cwe": "CWE-20",
      "function_names": [
        "getActions"
      ],
      "filenames": [
        "src/main/java/hudson/model/ClaimWrapper.java"
      ]
    },
    {
      "headline": "Multiple ClaimBuildActions Warning Could Lead to Information Leakage",
      "analysis": "The code logs a warning when multiple ClaimBuildActions are found for a run using the Log.warn method. This information might be sensitive and should not be disclosed in logs as it may provide attackers with insights into the system\u2019s operations and configurations.\n",
      "classification": "very promising",
      "cwe": "CWE-532",
      "function_names": [
        "getClaimForRun"
      ],
      "filenames": [
        "src/main/java/hudson/model/ClaimWrapper.java"
      ]
    },
    {
      "headline": "Potential Sensitive Data Exposure via getClaim Method",
      "analysis": "The getClaim method in the JobViewEntry class could expose potentially sensitive information such as the reason for the claim and the username of the person who made the claim. If this method is accessible by unauthorized users, this could lead to a privacy violation.\n",
      "classification": "very promising",
      "cwe": "CWE-200",
      "function_names": [
        "getClaim"
      ],
      "filenames": [
        "src/main/java/hudson/model/JobViewEntry.java"
      ]
    },
    {
      "headline": "Use of getPreviousBuildInProgress Without Null Check",
      "analysis": "The method getBuildsInProgress in JobViewEntry class calls getPreviousBuildInProgress on run objects without performing null checks. This could lead to a NullPointerException if any run object does not have a previous build in progress.\n",
      "classification": "slightly promising",
      "cwe": "CWE-476",
      "function_names": [
        "getBuildsInProgress"
      ],
      "filenames": [
        "src/main/java/hudson/model/JobViewEntry.java"
      ]
    },
    {
      "headline": "Hardcoded Colors in ViewEntryColors",
      "analysis": "The ViewEntryColors class has hard-coded color values for various background and foreground properties. Such hardcoded values might not be suitable for all accessibility needs and could be modified dynamically for higher flexibility.\n",
      "classification": "not promising",
      "cwe": "CWE-778",
      "function_names": [],
      "filenames": [
        "src/main/java/hudson/model/ViewEntryColors.java"
      ]
    },
    {
      "headline": "Inadequate Handling of Regular Expression for Exclude Regex",
      "analysis": "The isExcluded method in RadiatorView class uses Pattern.matches which can throw PatternSyntaxException. This exception is not caught which could potentially lead to unexpected application behavior if invalid regex patterns are supplied.\n",
      "classification": "very promising",
      "cwe": "CWE-754",
      "function_names": [
        "isExcluded"
      ],
      "filenames": [
        "src/main/java/hudson/model/RadiatorView.java"
      ]
    }
  ],
  "scores": [
    {
      "stats": {
        "fn": 1,
        "tp": 0,
        "fp": 4
      },
      "mapping": {},
      "vuln_dates": {
        "CVE-2020-2263": "2020-09-16T14:15:13"
      },
      "scoring_model": "claude-3-opus-20240229",
      "type": "llm",
      "instruction_template_hash": "245ace12b6361954d0a2"
    },
    {
      "stats": {
        "fn": 1,
        "tp": 0,
        "fp": 4
      },
      "mapping": {},
      "vuln_dates": {
        "CVE-2020-2263": "2020-09-16T14:15:13"
      },
      "scoring_model": "claude-3-5-sonnet-20240620",
      "type": "llm",
      "instruction_template_hash": "245ace12b6361954d0a2"
    }
  ],
  "instruction_template_hash": "10c0163db4740318a544",
  "version": "0.1.0"
}
