{
  "commit": "1781b2d946ac3b37647d87f28ab6c47a81d705a7",
  "repo_url": "https://github.com/chainguard-dev/apko",
  "model": "claude-3-5-sonnet-20240620",
  "chunk_hashes": [
    "99962df97216f5b7d96a"
  ],
  "responses": [
    {
      "content": "```yaml\nleads:\n  - headline: Command injection vulnerability in generate.sh\n    analysis: |\n      The generate.sh script uses curl to download files from an external source and pipes the output directly to tar without proper input validation. An attacker could potentially inject malicious commands by manipulating the URL or response content. The script also redirects stderr to /dev/null, which could hide important error messages or warnings.\n    cwe: CWE-78\n    function_names: []\n    filenames:\n      - pkg/sbom/generator/spdx/testdata/generate.sh\n    classification: very promising\n\n  - headline: Potential command injection in build.sh\n    analysis: |\n      The build.sh script uses variables like $BASE_IMAGE and $apko_binary directly in commands without proper validation or escaping. If an attacker could control these variables, they could potentially inject malicious commands. Additionally, the script uses tar to extract files without validating the contents, which could lead to arbitrary file writes if the tar archive is maliciously crafted.\n    cwe: CWE-78\n    function_names: []\n    filenames:\n      - examples/on_top_of_base/build.sh\n    classification: slightly promising\n\n  - headline: Insecure use of environment variables in run-devenv.sh\n    analysis: |\n      The run-devenv.sh script uses environment variables like $@ directly in commands without proper validation or escaping. If an attacker could control these variables, they could potentially inject malicious commands. The script also mounts the current directory into a Docker container, which could lead to information disclosure if sensitive files are present.\n    cwe: CWE-78\n    function_names:\n      - run\n      - docker_run\n    filenames:\n      - hack/run-devenv.sh\n    classification: slightly promising\n\n  - headline: Potential command injection in make-devenv.sh\n    analysis: |\n      The make-devenv.sh script uses variables like $ARCH and $BUILD_UID directly in commands without proper validation or escaping. If an attacker could control these variables, they could potentially inject malicious commands. The script also mounts the current directory into a Docker container and runs commands as root, which could lead to privilege escalation if exploited.\n    cwe: CWE-78\n    function_names:\n      - run_builder\n      - build_image\n    filenames:\n      - hack/make-devenv.sh\n    classification: slightly promising\n\n  - headline: Insecure use of environment variables in update-packages.sh\n    analysis: |\n      The update-packages.sh script uses environment variables and external commands without proper validation. While the risk is lower since this is likely an internal script, it could still be vulnerable to command injection if an attacker can control the environment variables or compromise the external commands being called.\n    cwe: CWE-78\n    function_names: []\n    filenames:\n      - hack/update-packages.sh\n    classification: not promising\n\n  - headline: Potential path traversal in update-golden.sh\n    analysis: |\n      The update-golden.sh script uses relative paths without proper validation. While the risk is lower since this is likely an internal script, it could potentially be exploited for path traversal if an attacker can control the working directory or manipulate the paths being used.\n    cwe: CWE-22\n    function_names: []\n    filenames:\n      - hack/update-golden.sh\n    classification: not promising\n\n  - headline: Insecure use of environment variables in ci-tests.sh\n    analysis: |\n      The ci-tests.sh script uses environment variables like $APKO directly in commands without proper validation or escaping. If an attacker could control these variables, they could potentially inject malicious commands. The script also executes all .sh files in a directory, which could be dangerous if an attacker can place malicious scripts in that location.\n    cwe: CWE-78\n    function_names: []\n    filenames:\n      - hack/ci-tests.sh\n    classification: slightly promising\n\n  - headline: Insecure use of environment variables in 00-build.sh\n    analysis: |\n      The 00-build.sh script uses environment variables like $APKO and $f directly in commands without proper validation or escaping. If an attacker could control these variables, they could potentially inject malicious commands. The script also loads Docker images from a local tar file, which could be dangerous if the tar file is maliciously crafted.\n    cwe: CWE-78\n    function_names: []\n    filenames:\n      - hack/ci/00-build.sh\n    classification: slightly promising\n\n  - headline: Insecure use of environment variables in 01-publish.sh\n    analysis: |\n      The 01-publish.sh script uses environment variables like $PORT and $APKO directly in commands without proper validation or escaping. If an attacker could control these variables, they could potentially inject malicious commands. The script also runs a Docker registry container and publishes images to it, which could lead to unauthorized access if not properly secured.\n    cwe: CWE-78\n    function_names: []\n    filenames:\n      - hack/ci/01-publish.sh\n    classification: slightly promising\n```",
      "date": "2024-07-07T20:47:53.052513",
      "usage": {
        "prompt_tokens": 5988,
        "completion_tokens": 1223,
        "cost": 0.036309
      }
    }
  ],
  "leads": [
    {
      "headline": "Command injection vulnerability in generate.sh",
      "analysis": "The generate.sh script uses curl to download files from an external source and pipes the output directly to tar without proper input validation. An attacker could potentially inject malicious commands by manipulating the URL or response content. The script also redirects stderr to /dev/null, which could hide important error messages or warnings.\n",
      "classification": "very promising",
      "cwe": "CWE-78",
      "function_names": [],
      "filenames": [
        "pkg/sbom/generator/spdx/testdata/generate.sh"
      ]
    },
    {
      "headline": "Potential command injection in build.sh",
      "analysis": "The build.sh script uses variables like $BASE_IMAGE and $apko_binary directly in commands without proper validation or escaping. If an attacker could control these variables, they could potentially inject malicious commands. Additionally, the script uses tar to extract files without validating the contents, which could lead to arbitrary file writes if the tar archive is maliciously crafted.\n",
      "classification": "slightly promising",
      "cwe": "CWE-78",
      "function_names": [],
      "filenames": [
        "examples/on_top_of_base/build.sh"
      ]
    },
    {
      "headline": "Insecure use of environment variables in run-devenv.sh",
      "analysis": "The run-devenv.sh script uses environment variables like $@ directly in commands without proper validation or escaping. If an attacker could control these variables, they could potentially inject malicious commands. The script also mounts the current directory into a Docker container, which could lead to information disclosure if sensitive files are present.\n",
      "classification": "slightly promising",
      "cwe": "CWE-78",
      "function_names": [
        "run",
        "docker_run"
      ],
      "filenames": [
        "hack/run-devenv.sh"
      ]
    },
    {
      "headline": "Potential command injection in make-devenv.sh",
      "analysis": "The make-devenv.sh script uses variables like $ARCH and $BUILD_UID directly in commands without proper validation or escaping. If an attacker could control these variables, they could potentially inject malicious commands. The script also mounts the current directory into a Docker container and runs commands as root, which could lead to privilege escalation if exploited.\n",
      "classification": "slightly promising",
      "cwe": "CWE-78",
      "function_names": [
        "run_builder",
        "build_image"
      ],
      "filenames": [
        "hack/make-devenv.sh"
      ]
    },
    {
      "headline": "Insecure use of environment variables in update-packages.sh",
      "analysis": "The update-packages.sh script uses environment variables and external commands without proper validation. While the risk is lower since this is likely an internal script, it could still be vulnerable to command injection if an attacker can control the environment variables or compromise the external commands being called.\n",
      "classification": "not promising",
      "cwe": "CWE-78",
      "function_names": [],
      "filenames": [
        "hack/update-packages.sh"
      ]
    },
    {
      "headline": "Potential path traversal in update-golden.sh",
      "analysis": "The update-golden.sh script uses relative paths without proper validation. While the risk is lower since this is likely an internal script, it could potentially be exploited for path traversal if an attacker can control the working directory or manipulate the paths being used.\n",
      "classification": "not promising",
      "cwe": "CWE-22",
      "function_names": [],
      "filenames": [
        "hack/update-golden.sh"
      ]
    },
    {
      "headline": "Insecure use of environment variables in ci-tests.sh",
      "analysis": "The ci-tests.sh script uses environment variables like $APKO directly in commands without proper validation or escaping. If an attacker could control these variables, they could potentially inject malicious commands. The script also executes all .sh files in a directory, which could be dangerous if an attacker can place malicious scripts in that location.\n",
      "classification": "slightly promising",
      "cwe": "CWE-78",
      "function_names": [],
      "filenames": [
        "hack/ci-tests.sh"
      ]
    },
    {
      "headline": "Insecure use of environment variables in 00-build.sh",
      "analysis": "The 00-build.sh script uses environment variables like $APKO and $f directly in commands without proper validation or escaping. If an attacker could control these variables, they could potentially inject malicious commands. The script also loads Docker images from a local tar file, which could be dangerous if the tar file is maliciously crafted.\n",
      "classification": "slightly promising",
      "cwe": "CWE-78",
      "function_names": [],
      "filenames": [
        "hack/ci/00-build.sh"
      ]
    },
    {
      "headline": "Insecure use of environment variables in 01-publish.sh",
      "analysis": "The 01-publish.sh script uses environment variables like $PORT and $APKO directly in commands without proper validation or escaping. If an attacker could control these variables, they could potentially inject malicious commands. The script also runs a Docker registry container and publishes images to it, which could lead to unauthorized access if not properly secured.\n",
      "classification": "slightly promising",
      "cwe": "CWE-78",
      "function_names": [],
      "filenames": [
        "hack/ci/01-publish.sh"
      ]
    }
  ],
  "scores": [
    {
      "stats": {
        "fn": 1,
        "tp": 0,
        "fp": 1
      },
      "mapping": {},
      "vuln_dates": {
        "CVE-2024-36127": "2024-06-03T15:15:09"
      },
      "scoring_model": "claude-3-5-sonnet-20240620",
      "type": "llm",
      "instruction_template_hash": "245ace12b6361954d0a2"
    }
  ],
  "instruction_template_hash": "10c0163db4740318a544",
  "version": "0.1.0"
}
