{
  "commit": "13293140eaa6c2896d17c3fb2b62f780b5331ffb",
  "repo_url": "https://github.com/opensuse/obs-service-tar_scm",
  "model": "claude-3-haiku-20240307",
  "chunk_hashes": [
    "684e2966b35746a8df1e"
  ],
  "responses": [
    {
      "content": "```yaml\nleads:\n  - headline: Improper Input Validation\n    analysis: |\n      The codebase contains vulnerabilities related to improper input validation, such as insufficient validation of user input or lack of input sanitization. This could lead to security issues like command injection, SQL injection, or other injection attacks.\n    cwe: CWE-20\n    function_names:\n      - tar_scm_std\n    filenames:\n      - TarSCM/cli.py\n    classification: very promising\n\n  - headline: Improper Neutralization of Special Elements used in an OS Command\n    analysis: |\n      The codebase contains vulnerabilities related to improper neutralization of special elements used in OS commands. This could lead to OS command injection attacks, where an attacker could execute arbitrary commands on the system.\n    cwe: CWE-78\n    function_names:\n      - tar_scm_std\n    filenames:\n      - TarSCM/cli.py\n    classification: very promising\n\n  - headline: Improper Neutralization of Special Elements used in an SQL Command\n    analysis: |\n      The codebase contains vulnerabilities related to improper neutralization of special elements used in SQL commands. This could lead to SQL injection attacks, where an attacker could execute arbitrary SQL queries on the database.\n    cwe: CWE-89\n    function_names:\n      - tar_scm_std\n    filenames:\n      - TarSCM/cli.py\n    classification: very promising\n\n  - headline: Improper Neutralization of Input During Web Page Generation\n    analysis: |\n      The codebase contains vulnerabilities related to improper neutralization of input during web page generation. This could lead to cross-site scripting (XSS) attacks, where an attacker could inject malicious scripts into the web page.\n    cwe: CWE-79\n    function_names:\n      - tar_scm_std\n    filenames:\n      - TarSCM/cli.py\n    classification: very promising\n\n  - headline: Improper Restriction of XML External Entity Reference\n    analysis: |\n      The codebase contains vulnerabilities related to improper restriction of XML external entity references. This could lead to XML entity expansion attacks, where an attacker could perform denial-of-service (DoS) attacks or extract sensitive information from the system.\n    cwe: CWE-611\n    function_names:\n      - tar_scm_std\n    filenames:\n      - TarSCM/cli.py\n    classification: slightly promising\n\n  - headline: Incorrect Password Requirements\n    analysis: |\n      The codebase contains vulnerabilities related to incorrect password requirements. This could lead to weak password issues, where an attacker could easily guess or brute-force the password.\n    cwe: CWE-521\n    function_names:\n      - tar_scm_std\n    filenames:\n      - TarSCM/cli.py\n    classification: slightly promising\n\n  - headline: Improper Restriction of Recursive Entity References in DTDs\n    analysis: |\n      The codebase contains vulnerabilities related to improper restriction of recursive entity references in DTDs. This could lead to XML entity expansion attacks, where an attacker could perform denial-of-service (DoS) attacks or extract sensitive information from the system.\n    cwe: CWE-776\n    function_names:\n      - tar_scm_std\n    filenames:\n      - TarSCM/cli.py\n    classification: slightly promising\n\n  - headline: Improper Neutralization of Argument Delimiters in a Command\n    analysis: |\n      The codebase contains vulnerabilities related to improper neutralization of argument delimiters in a command. This could lead to argument injection attacks, where an attacker could inject malicious arguments into the command.\n    cwe: CWE-88\n    function_names:\n      - tar_scm_std\n    filenames:\n      - TarSCM/cli.py\n    classification: slightly promising\n\n  - headline: Improper Sanitization of Special Elements used in an Expression Language Statement\n    analysis: |\n      The codebase contains vulnerabilities related to improper sanitization of special elements used in an expression language statement. This could lead to expression language injection attacks, where an attacker could execute arbitrary code in the expression language.\n    cwe: CWE-917\n    function_names:\n      - tar_scm_std\n    filenames:\n      - TarSCM/cli.py\n    classification: slightly promising\n\n  - headline: Improper Neutralization of Formula Elements in a CSV File\n    analysis: |\n      The codebase contains vulnerabilities related to improper neutralization of formula elements in a CSV file. This could lead to CSV injection attacks, where an attacker could execute arbitrary formulas in the CSV file.\n    cwe: CWE-1236\n    function_names:\n      - tar_scm_std\n    filenames:\n      - TarSCM/cli.py\n    classification: slightly promising\n\n  - headline: Improper Control of Generation of Code\n    analysis: |\n      The codebase contains vulnerabilities related to improper control of generation of code. This could lead to code injection attacks, where an attacker could inject malicious code into the application.\n    cwe: CWE-94\n    function_names:\n      - tar_scm_std\n    filenames:\n      - TarSCM/cli.py\n    classification: slightly promising\n```",
      "date": "2024-06-13T10:53:06.935217",
      "usage": {
        "prompt_tokens": 57152,
        "completion_tokens": 1285,
        "cost": 0.01589425
      }
    }
  ],
  "leads": [
    {
      "headline": "Improper Input Validation",
      "analysis": "The codebase contains vulnerabilities related to improper input validation, such as insufficient validation of user input or lack of input sanitization. This could lead to security issues like command injection, SQL injection, or other injection attacks.\n",
      "classification": "very promising",
      "cwe": "CWE-20",
      "function_names": [
        "tar_scm_std"
      ],
      "filenames": [
        "TarSCM/cli.py"
      ]
    },
    {
      "headline": "Improper Neutralization of Special Elements used in an OS Command",
      "analysis": "The codebase contains vulnerabilities related to improper neutralization of special elements used in OS commands. This could lead to OS command injection attacks, where an attacker could execute arbitrary commands on the system.\n",
      "classification": "very promising",
      "cwe": "CWE-78",
      "function_names": [
        "tar_scm_std"
      ],
      "filenames": [
        "TarSCM/cli.py"
      ]
    },
    {
      "headline": "Improper Neutralization of Special Elements used in an SQL Command",
      "analysis": "The codebase contains vulnerabilities related to improper neutralization of special elements used in SQL commands. This could lead to SQL injection attacks, where an attacker could execute arbitrary SQL queries on the database.\n",
      "classification": "very promising",
      "cwe": "CWE-89",
      "function_names": [
        "tar_scm_std"
      ],
      "filenames": [
        "TarSCM/cli.py"
      ]
    },
    {
      "headline": "Improper Neutralization of Input During Web Page Generation",
      "analysis": "The codebase contains vulnerabilities related to improper neutralization of input during web page generation. This could lead to cross-site scripting (XSS) attacks, where an attacker could inject malicious scripts into the web page.\n",
      "classification": "very promising",
      "cwe": "CWE-79",
      "function_names": [
        "tar_scm_std"
      ],
      "filenames": [
        "TarSCM/cli.py"
      ]
    },
    {
      "headline": "Improper Restriction of XML External Entity Reference",
      "analysis": "The codebase contains vulnerabilities related to improper restriction of XML external entity references. This could lead to XML entity expansion attacks, where an attacker could perform denial-of-service (DoS) attacks or extract sensitive information from the system.\n",
      "classification": "slightly promising",
      "cwe": "CWE-611",
      "function_names": [
        "tar_scm_std"
      ],
      "filenames": [
        "TarSCM/cli.py"
      ]
    },
    {
      "headline": "Incorrect Password Requirements",
      "analysis": "The codebase contains vulnerabilities related to incorrect password requirements. This could lead to weak password issues, where an attacker could easily guess or brute-force the password.\n",
      "classification": "slightly promising",
      "cwe": "CWE-521",
      "function_names": [
        "tar_scm_std"
      ],
      "filenames": [
        "TarSCM/cli.py"
      ]
    },
    {
      "headline": "Improper Restriction of Recursive Entity References in DTDs",
      "analysis": "The codebase contains vulnerabilities related to improper restriction of recursive entity references in DTDs. This could lead to XML entity expansion attacks, where an attacker could perform denial-of-service (DoS) attacks or extract sensitive information from the system.\n",
      "classification": "slightly promising",
      "cwe": "CWE-776",
      "function_names": [
        "tar_scm_std"
      ],
      "filenames": [
        "TarSCM/cli.py"
      ]
    },
    {
      "headline": "Improper Neutralization of Argument Delimiters in a Command",
      "analysis": "The codebase contains vulnerabilities related to improper neutralization of argument delimiters in a command. This could lead to argument injection attacks, where an attacker could inject malicious arguments into the command.\n",
      "classification": "slightly promising",
      "cwe": "CWE-88",
      "function_names": [
        "tar_scm_std"
      ],
      "filenames": [
        "TarSCM/cli.py"
      ]
    },
    {
      "headline": "Improper Sanitization of Special Elements used in an Expression Language Statement",
      "analysis": "The codebase contains vulnerabilities related to improper sanitization of special elements used in an expression language statement. This could lead to expression language injection attacks, where an attacker could execute arbitrary code in the expression language.\n",
      "classification": "slightly promising",
      "cwe": "CWE-917",
      "function_names": [
        "tar_scm_std"
      ],
      "filenames": [
        "TarSCM/cli.py"
      ]
    },
    {
      "headline": "Improper Neutralization of Formula Elements in a CSV File",
      "analysis": "The codebase contains vulnerabilities related to improper neutralization of formula elements in a CSV file. This could lead to CSV injection attacks, where an attacker could execute arbitrary formulas in the CSV file.\n",
      "classification": "slightly promising",
      "cwe": "CWE-1236",
      "function_names": [
        "tar_scm_std"
      ],
      "filenames": [
        "TarSCM/cli.py"
      ]
    },
    {
      "headline": "Improper Control of Generation of Code",
      "analysis": "The codebase contains vulnerabilities related to improper control of generation of code. This could lead to code injection attacks, where an attacker could inject malicious code into the application.\n",
      "classification": "slightly promising",
      "cwe": "CWE-94",
      "function_names": [
        "tar_scm_std"
      ],
      "filenames": [
        "TarSCM/cli.py"
      ]
    }
  ],
  "scores": [
    {
      "stats": {
        "fn": 1,
        "tp": 0,
        "fp": 4
      },
      "mapping": {},
      "vuln_dates": {
        "CVE-2018-12473": "2018-10-02T15:29:00"
      },
      "scoring_model": "claude-3-opus-20240229",
      "type": "llm",
      "instruction_template_hash": "245ace12b6361954d0a2"
    },
    {
      "stats": {
        "fn": 1,
        "tp": 0,
        "fp": 4
      },
      "mapping": {},
      "vuln_dates": {
        "CVE-2018-12473": "2018-10-02T15:29:00"
      },
      "scoring_model": "claude-3-5-sonnet-20240620",
      "type": "llm",
      "instruction_template_hash": "245ace12b6361954d0a2"
    }
  ],
  "instruction_template_hash": "10c0163db4740318a544",
  "version": "0.1.0"
}
