{
  "commit": "63b7864ca5bca96de16598ef5865ec75c1240720",
  "repo_url": "https://github.com/rmountjoy92/dashmachine",
  "model": "gpt-4-turbo-2024-04-09",
  "chunk_hashes": [
    "09a55240a836d64b763b"
  ],
  "responses": [
    {
      "content": "```yaml\nleads:\n  - headline: Uncontrolled template content processed in the custom card UI rendering\n    analysis: |\n      The system dynamically constructs HTML content based on templates that integrate both static elements and external platform data. The server-side rendering using Flask's `render_template_string` integrates user-controlled input without proper validation, leading to potential XSS attacks where malicious JavaScript can be inserted into templates and executed in the browser of any user viewing the generated page.\n    cwe: CWE-94\n    function_names:\n      - process (in Platform class for Weather and PiHole)\n      - get_data_source\n    filenames:\n      - dashmachine/platform/weather.py\n      - dashmachine/platform/pihole.py\n    classification: very promising\n\n  - headline: Passwords managed with insecure practices\n    analysis: |\n      The password management technique in use involves caching hashed passwords in files, which poses a security risk as it could lead to exposure of hashed passwords if the filesystem's security is compromised. This file-based approach lacks best practices in secure password storage, such as leveraging in-memory solutions like HashiCorp Vault for storing secrets.\n    cwe: CWE-532\n    function_names:\n      - hash_and_cache_password\n      - get_cached_password\n      - clean_auth_cache\n    filenames:\n      - dashmachine/user_system/utils.py\n    classification: slightly promising\n\n  - headline: Database configuration data transmitted over non-secure channel\n    analysis: |\n      The application retrieves configuration data through a non-encrypted SQL connection string embedded in the application logic, which can cause sensitive database credentials to be exposed if the application traffic is intercepted. This places the system at risk of unauthorized database access or data breaches which could compromise system integrity and confidentiality.\n    cwe: CWE-319\n    function_names:\n      - run_migrations_online\n      - run_migrations_offline\n    filenames:\n      - dashmachine/migrations/env.py\n    classification: very promising\n\n  - headline: User authentication bypass via tampered session cookies or sessions\n    analysis: |\n      There appears to be minimal safeguarding against manipulation or replay of session tokens or cookies that handle user sessions, potentially allowing an attacker who has intercepted a valid session token to spoof another user's session, gaining unauthorized access to the system.\n    cwe: CWE-287\n    function_names:\n      - load_user\n    filenames:\n      - dashmachine/user_system/models.py\n    classification: slightly promising\n\n  - headline: Insecure direct object references in path configuration\n    analysis: |\n      The application directly appends user input to file system paths without proper sanitization or restriction. This could allow an attacker to modify the path intended by the user, leading to unauthorized file access or inclusion, potentially leading to information disclosure, system compromise, or manipulation of sensitive data.\n    cwe: CWE-22\n    function_names:\n      - get_root_folder\n    filenames:\n      - dashmachine/paths.py\n    classification: very promising\n```",
      "date": "2024-06-09T14:38:46.068794",
      "usage": {
        "prompt_tokens": 38673,
        "completion_tokens": 606,
        "cost": 0.40491
      }
    }
  ],
  "leads": [
    {
      "headline": "Uncontrolled template content processed in the custom card UI rendering",
      "analysis": "The system dynamically constructs HTML content based on templates that integrate both static elements and external platform data. The server-side rendering using Flask's render_template_string integrates user-controlled input without proper validation, leading to potential XSS attacks where malicious JavaScript can be inserted into templates and executed in the browser of any user viewing the generated page.\n",
      "classification": "very promising",
      "cwe": "CWE-94",
      "function_names": [
        "process (in Platform class for Weather and PiHole)",
        "get_data_source"
      ],
      "filenames": [
        "dashmachine/platform/weather.py",
        "dashmachine/platform/pihole.py"
      ]
    },
    {
      "headline": "Passwords managed with insecure practices",
      "analysis": "The password management technique in use involves caching hashed passwords in files, which poses a security risk as it could lead to exposure of hashed passwords if the filesystem's security is compromised. This file-based approach lacks best practices in secure password storage, such as leveraging in-memory solutions like HashiCorp Vault for storing secrets.\n",
      "classification": "slightly promising",
      "cwe": "CWE-532",
      "function_names": [
        "hash_and_cache_password",
        "get_cached_password",
        "clean_auth_cache"
      ],
      "filenames": [
        "dashmachine/user_system/utils.py"
      ]
    },
    {
      "headline": "Database configuration data transmitted over non-secure channel",
      "analysis": "The application retrieves configuration data through a non-encrypted SQL connection string embedded in the application logic, which can cause sensitive database credentials to be exposed if the application traffic is intercepted. This places the system at risk of unauthorized database access or data breaches which could compromise system integrity and confidentiality.\n",
      "classification": "very promising",
      "cwe": "CWE-319",
      "function_names": [
        "run_migrations_online",
        "run_migrations_offline"
      ],
      "filenames": [
        "dashmachine/migrations/env.py"
      ]
    },
    {
      "headline": "User authentication bypass via tampered session cookies or sessions",
      "analysis": "There appears to be minimal safeguarding against manipulation or replay of session tokens or cookies that handle user sessions, potentially allowing an attacker who has intercepted a valid session token to spoof another user's session, gaining unauthorized access to the system.\n",
      "classification": "slightly promising",
      "cwe": "CWE-287",
      "function_names": [
        "load_user"
      ],
      "filenames": [
        "dashmachine/user_system/models.py"
      ]
    },
    {
      "headline": "Insecure direct object references in path configuration",
      "analysis": "The application directly appends user input to file system paths without proper sanitization or restriction. This could allow an attacker to modify the path intended by the user, leading to unauthorized file access or inclusion, potentially leading to information disclosure, system compromise, or manipulation of sensitive data.\n",
      "classification": "very promising",
      "cwe": "CWE-22",
      "function_names": [
        "get_root_folder"
      ],
      "filenames": [
        "dashmachine/paths.py"
      ]
    }
  ],
  "scores": [
    {
      "stats": {
        "fn": 1,
        "tp": 1,
        "fp": 2
      },
      "mapping": {
        "2": "CVE-2023-6900"
      },
      "vuln_dates": {
        "CVE-2023-6899": "2023-12-17T13:15:42",
        "CVE-2023-6900": "2023-12-17T14:15:36"
      },
      "scoring_model": "gpt-4o-2024-05-13",
      "type": "llm",
      "instruction_template_hash": "8998f09cf57fca8a6e03"
    },
    {
      "stats": {
        "fn": 1,
        "tp": 1,
        "fp": 2
      },
      "mapping": {
        "2": "CVE-2023-6900"
      },
      "vuln_dates": {
        "CVE-2023-6899": "2023-12-17T13:15:42",
        "CVE-2023-6900": "2023-12-17T14:15:36"
      },
      "scoring_model": "claude-3-opus-20240229",
      "type": "llm",
      "instruction_template_hash": "245ace12b6361954d0a2"
    }
  ],
  "instruction_template_hash": "10c0163db4740318a544",
  "version": "0.1.0"
}
