{
  "commit": "1e840b652666108ac233b9bfde38487553a3dbaa",
  "repo_url": "https://github.com/spotipy-dev/spotipy",
  "model": "gpt-4o-2024-05-13",
  "chunk_hashes": [
    "2a3aaa030b715724b1e6"
  ],
  "responses": [
    {
      "content": "```yaml\nleads:\n  - headline: \"Test Credentials Hardcoded in Test files\"\n    analysis: |\n      The file `tests/unit/test_oauth.py` contains hardcoded credentials which are used across multiple tests (`_make_oauth`, `_make_implicitgrantauth`, `_make_pkceauth`). These hardcoded credentials (`client_id`, `client_secret`, `redirect_uri`, `state`) are security liabilities as they can expose sensitive information and tokens during testing.\n      Replace these credentials with environment variables or config files that can be controlled and secured outside of the codebase.\n    cwe: CWE-321\n    function_names:\n      - \"_make_oauth\"\n      - \"_make_implicitgrantauth\"\n      - \"_make_pkceauth\"\n    filenames:\n      - \"tests/unit/test_oauth.py\"\n    classification: very promising\n\n  - headline: \"Potential Command Injection Vulnerability\"\n    analysis: |\n      In the file `examples/app.py`, unsafe user-input in OAuth can lead to command injection in specific scenarios. The app retrieves the `code` parameter from the request and uses it to get a token, which may potentially be used in command injection.\n      If the app does not sanitize the user input effectively, an attacker could manipulate this parameter and execute arbitrary commands on the server.\n    cwe: CWE-77\n    function_names:\n      - \"index\"\n    filenames:\n      - \"examples/app.py\"\n    classification: very promising\n\n  - headline: \"Possible Exposure of Sensitive Data in Logs\"\n    analysis: |\n      In `examples/app.py` and other scripts, debug logging outputs sensitive information such as access tokens. An attacker with access to the logs can leverage this information to gain unauthorized access to user accounts.\n      Always ensure sensitive data is redacted or encrypted in logs.\n    cwe: CWE-532\n    function_names:\n      - \"main\"\n    filenames:\n      - \"examples/app.py\"\n      - \"examples/create_playlist.py\"\n      - \"examples/add_a_saved_album.py\"\n      - \"examples/add_tracks_to_playlist.py\"\n    classification: very promising\n  \n  - headline: \"Cleartext Storage of Sensitive Information\"\n    analysis: |\n      The application uses a file-based caching mechanism to store OAuth tokens which are not encrypted. The tokens stored in `.cache` files are in plaintext and can be easily read by anyone with access to the file system. This poses a risk if unsanctioned users gain access to the file system.\n      Implement a secure mechanism to store sensitive tokens, such as using environment variables, encryption, or a secure credential store.\n    cwe: CWE-312\n    function_names:\n      - \"save_token_to_cache\"\n    filenames:\n      - \"spotipy/cache_handler.py\"\n    classification: very promising\n\n  - headline: \"Improper Validation of Array Index in Playlist Modification\"\n    analysis: |\n      The code for handling track positions in playlists (e.g., `playlist_reorder_items` function) assumes that provided indices are valid without proper validation. This can lead to out-of-bounds array access leading to unexpected behavior or crashes.\n      Add proper validation to ensure that the provided positions are within the allowable range.\n    cwe: CWE-129\n    function_names:\n      - \"playlist_reorder_items\"\n    filenames:\n      - \"spotipy/client.py\"\n    classification: slightly promising\n```",
      "date": "2024-06-13T11:57:43.216342",
      "usage": {
        "prompt_tokens": 55191,
        "completion_tokens": 688,
        "cost": 0.286275
      }
    }
  ],
  "leads": [
    {
      "headline": "Test Credentials Hardcoded in Test files",
      "analysis": "The file tests/unit/test_oauth.py contains hardcoded credentials which are used across multiple tests (_make_oauth, _make_implicitgrantauth, _make_pkceauth). These hardcoded credentials (client_id, client_secret, redirect_uri, state) are security liabilities as they can expose sensitive information and tokens during testing.\nReplace these credentials with environment variables or config files that can be controlled and secured outside of the codebase.\n",
      "classification": "very promising",
      "cwe": "CWE-321",
      "function_names": [
        "_make_oauth",
        "_make_implicitgrantauth",
        "_make_pkceauth"
      ],
      "filenames": [
        "tests/unit/test_oauth.py"
      ]
    },
    {
      "headline": "Potential Command Injection Vulnerability",
      "analysis": "In the file examples/app.py, unsafe user-input in OAuth can lead to command injection in specific scenarios. The app retrieves the code parameter from the request and uses it to get a token, which may potentially be used in command injection.\nIf the app does not sanitize the user input effectively, an attacker could manipulate this parameter and execute arbitrary commands on the server.\n",
      "classification": "very promising",
      "cwe": "CWE-77",
      "function_names": [
        "index"
      ],
      "filenames": [
        "examples/app.py"
      ]
    },
    {
      "headline": "Possible Exposure of Sensitive Data in Logs",
      "analysis": "In examples/app.py and other scripts, debug logging outputs sensitive information such as access tokens. An attacker with access to the logs can leverage this information to gain unauthorized access to user accounts.\nAlways ensure sensitive data is redacted or encrypted in logs.\n",
      "classification": "very promising",
      "cwe": "CWE-532",
      "function_names": [
        "main"
      ],
      "filenames": [
        "examples/app.py",
        "examples/create_playlist.py",
        "examples/add_a_saved_album.py"
      ]
    },
    {
      "headline": "Cleartext Storage of Sensitive Information",
      "analysis": "The application uses a file-based caching mechanism to store OAuth tokens which are not encrypted. The tokens stored in .cache files are in plaintext and can be easily read by anyone with access to the file system. This poses a risk if unsanctioned users gain access to the file system.\nImplement a secure mechanism to store sensitive tokens, such as using environment variables, encryption, or a secure credential store.\n",
      "classification": "very promising",
      "cwe": "CWE-312",
      "function_names": [
        "save_token_to_cache"
      ],
      "filenames": [
        "spotipy/cache_handler.py"
      ]
    },
    {
      "headline": "Improper Validation of Array Index in Playlist Modification",
      "analysis": "The code for handling track positions in playlists (e.g., playlist_reorder_items function) assumes that provided indices are valid without proper validation. This can lead to out-of-bounds array access leading to unexpected behavior or crashes.\nAdd proper validation to ensure that the provided positions are within the allowable range.\n",
      "classification": "slightly promising",
      "cwe": "CWE-129",
      "function_names": [
        "playlist_reorder_items"
      ],
      "filenames": [
        "spotipy/client.py"
      ]
    }
  ],
  "scores": [
    {
      "stats": {
        "fn": 1,
        "tp": 0,
        "fp": 4
      },
      "mapping": {},
      "vuln_dates": {
        "CVE-2023-23608": "2023-01-26T21:18:13"
      },
      "scoring_model": "claude-3-opus-20240229",
      "type": "llm",
      "instruction_template_hash": "245ace12b6361954d0a2"
    },
    {
      "stats": {
        "fn": 1,
        "tp": 0,
        "fp": 4
      },
      "mapping": {},
      "vuln_dates": {
        "CVE-2023-23608": "2023-01-26T21:18:13"
      },
      "scoring_model": "claude-3-5-sonnet-20240620",
      "type": "llm",
      "instruction_template_hash": "245ace12b6361954d0a2"
    }
  ],
  "instruction_template_hash": "10c0163db4740318a544",
  "version": "0.1.0"
}
