{
  "commit": "8287691045fd3c0889bddd83964c5c743b4bc277",
  "repo_url": "https://github.com/bandoche/pypinksign",
  "model": "claude-3-opus-20240229",
  "chunk_hashes": [
    "5c7ab1b649a7edf8f7e3"
  ],
  "responses": [
    {
      "content": "Here is the YAML output for the security vulnerabilities I identified in the provided codebase:\n\n```yaml\nleads:\n  - headline: Use of weak cryptographic algorithm SEED-CBC for encryption\n    analysis: |\n      The codebase uses the SEED-CBC encryption algorithm, which is a weak 128-bit block cipher. SEED is outdated and has known weaknesses. Using weak crypto algorithms can allow attackers to more easily break the encryption and compromise sensitive data. The impacted functions are seed_cbc_128_encrypt, seed_cbc_128_decrypt, and related variants.\n    cwe: CWE-327\n    function_names: \n      - seed_cbc_128_encrypt\n      - seed_cbc_128_decrypt\n      - process_block\n    filenames:\n      - pypinksign/__init__.py\n      - pypinksign/pypinksign.py \n      - pypinksign/pypinkseed.py\n    classification: very promising\n\n  - headline: Use of insecure PBKDF1 key derivation function \n    analysis: |  \n      The pbkdf1 function implements the outdated PBKDF1 key derivation algorithm. PBKDF1 uses a simple construction that is prone to brute-force attacks, especially with a low iteration count. The recommended alternative is PBKDF2. Using a weak KDF makes derived encryption keys easier to guess. This affects the encrypt_decrypted_prikey function.\n    cwe: CWE-916\n    function_names:\n      - pbkdf1\n      - encrypt_decrypted_prikey\n    filenames:\n      - pypinksign/pypinksign.py\n    classification: very promising\n  \n  - headline: Insufficient iteration count for key derivation\n    analysis: |\n      The PBKDF1 and PBKDF2 key derivation functions are called with a low iteration count of 2048. This iteration count is insufficient to adequately slow down brute-force guessing attempts on derived keys. NIST currently recommends an iteration count of at least 10,000 for PBKDF2. Using a higher iteration count helps mitigate the risk of weak derived keys. The issue impacts the pbkdf1 function and get_private_key_decryption_key_for_pbes2 method.\n    cwe: CWE-310\n    function_names:\n      - pbkdf1\n      - get_private_key_decryption_key_for_pbes2  \n    filenames:\n      - pypinksign/pypinksign.py\n    classification: very promising\n\n  - headline: Storage of sensitive data using reversible encryption\n    analysis: |\n      The codebase uses reversible encryption (SEED-CBC) to store private keys. Storing sensitive data like private keys using reversible encryption is risky, as a compromise of the encryption key leads to exposure of the plaintext. A more secure approach would be to use non-reversible encryption like a hash function for stored secrets. The issue is prevalent in functions handling encrypted private keys.\n    cwe: CWE-312\n    function_names:\n      - load_prikey\n      - load_p12\n      - encrypt_decrypted_prikey\n    filenames:\n      - pypinksign/pypinksign.py  \n    classification: slightly promising\n\n  - headline: Generation of cryptographically weak random numbers\n    analysis: | \n      The seed_generator function generates random bytes that are used for cryptographic operations like IVs and salts. However, it uses Python's random module which is not a cryptographically secure pseudorandom number generator (CSPRNG). Using weak random numbers can compromise the security of cryptographic algorithms. The os.urandom or secrets modules should be used instead for crypto-strength randomness.\n    cwe: CWE-338\n    function_names:\n      - seed_generator\n    filenames: \n      - pypinksign/pypinksign.py\n    classification: very promising\n```\n\nIn summary, the most concerning issues are the use of the weak SEED-CBC cipher, insecure PBKDF1 key derivation, insufficient KDF iteration counts, and weak random number generation. I recommend upgrading to stronger standard encryption algorithms, using PBKDF2 with a high iteration count for key derivation, and switching to a CSPRNG for cryptographically-strong randomness.",
      "date": "2024-06-08T22:54:00.481327",
      "usage": {
        "prompt_tokens": 46782,
        "completion_tokens": 1026,
        "cost": 0.77868
      }
    }
  ],
  "leads": [
    {
      "headline": "Use of weak cryptographic algorithm SEED-CBC for encryption",
      "analysis": "The codebase uses the SEED-CBC encryption algorithm, which is a weak 128-bit block cipher. SEED is outdated and has known weaknesses. Using weak crypto algorithms can allow attackers to more easily break the encryption and compromise sensitive data. The impacted functions are seed_cbc_128_encrypt, seed_cbc_128_decrypt, and related variants.\n",
      "classification": "very promising",
      "cwe": "CWE-327",
      "function_names": [
        "seed_cbc_128_encrypt",
        "seed_cbc_128_decrypt",
        "process_block"
      ],
      "filenames": [
        "pypinksign/__init__.py",
        "pypinksign/pypinksign.py",
        "pypinksign/pypinkseed.py"
      ]
    },
    {
      "headline": "Use of insecure PBKDF1 key derivation function",
      "analysis": "The pbkdf1 function implements the outdated PBKDF1 key derivation algorithm. PBKDF1 uses a simple construction that is prone to brute-force attacks, especially with a low iteration count. The recommended alternative is PBKDF2. Using a weak KDF makes derived encryption keys easier to guess. This affects the encrypt_decrypted_prikey function.\n",
      "classification": "very promising",
      "cwe": "CWE-916",
      "function_names": [
        "pbkdf1",
        "encrypt_decrypted_prikey"
      ],
      "filenames": [
        "pypinksign/pypinksign.py"
      ]
    },
    {
      "headline": "Insufficient iteration count for key derivation",
      "analysis": "The PBKDF1 and PBKDF2 key derivation functions are called with a low iteration count of 2048. This iteration count is insufficient to adequately slow down brute-force guessing attempts on derived keys. NIST currently recommends an iteration count of at least 10,000 for PBKDF2. Using a higher iteration count helps mitigate the risk of weak derived keys. The issue impacts the pbkdf1 function and get_private_key_decryption_key_for_pbes2 method.\n",
      "classification": "very promising",
      "cwe": "CWE-310",
      "function_names": [
        "pbkdf1",
        "get_private_key_decryption_key_for_pbes2"
      ],
      "filenames": [
        "pypinksign/pypinksign.py"
      ]
    },
    {
      "headline": "Storage of sensitive data using reversible encryption",
      "analysis": "The codebase uses reversible encryption (SEED-CBC) to store private keys. Storing sensitive data like private keys using reversible encryption is risky, as a compromise of the encryption key leads to exposure of the plaintext. A more secure approach would be to use non-reversible encryption like a hash function for stored secrets. The issue is prevalent in functions handling encrypted private keys.\n",
      "classification": "slightly promising",
      "cwe": "CWE-312",
      "function_names": [
        "load_prikey",
        "load_p12",
        "encrypt_decrypted_prikey"
      ],
      "filenames": [
        "pypinksign/pypinksign.py"
      ]
    },
    {
      "headline": "Generation of cryptographically weak random numbers",
      "analysis": "The seed_generator function generates random bytes that are used for cryptographic operations like IVs and salts. However, it uses Python's random module which is not a cryptographically secure pseudorandom number generator (CSPRNG). Using weak random numbers can compromise the security of cryptographic algorithms. The os.urandom or secrets modules should be used instead for crypto-strength randomness.\n",
      "classification": "very promising",
      "cwe": "CWE-338",
      "function_names": [
        "seed_generator"
      ],
      "filenames": [
        "pypinksign/pypinksign.py"
      ]
    }
  ],
  "scores": [
    {
      "stats": {
        "fn": 0,
        "tp": 1,
        "fp": 3
      },
      "mapping": {
        "3": "CVE-2023-48056"
      },
      "vuln_dates": {
        "CVE-2023-48056": "2023-11-16T18:15:07"
      },
      "scoring_model": "gpt-4o-2024-05-13",
      "type": "llm",
      "instruction_template_hash": "8998f09cf57fca8a6e03"
    }
  ],
  "instruction_template_hash": "10c0163db4740318a544",
  "version": "0.1.0"
}
