{
  "commit": "43714f0463a14ef9d2cee55d689d2bc934e9e7f3",
  "repo_url": "https://github.com/jenkinsci/http-request-plugin",
  "model": "claude-3-opus-20240229",
  "chunk_hashes": [
    "d31cbb4440a21d1220fc"
  ],
  "responses": [
    {
      "content": "Here are the potential security vulnerabilities I identified in the provided codebase:\n\n```yaml\nleads:\n  - headline: Improper Certificate Validation\n    analysis: |\n      The CertificateAuthentication class loads a custom keystore to establish an SSL connection, but does not perform any validation on the server certificate. If the server presents an invalid or self-signed cert, it will be trusted.\n      \n      Similarly, the NoopTrustManager used when ignoreSslErrors is enabled accepts any SSL certificate without validation. This allows man-in-the-middle attacks if the client connects to a malicious server.\n    cwe: CWE-295\n    function_names:\n      - CertificateAuthentication.authenticate\n      - HttpRequestExecution.NoopTrustManager\n    filenames:\n      - src/main/java/jenkins/plugins/http_request/auth/CertificateAuthentication.java  \n      - src/main/java/jenkins/plugins/http_request/HttpRequestExecution.java\n    classification: very promising\n    \n  - headline: Credentials Stored in Plain Text\n    analysis: |  \n      The BasicDigestAuthentication class stores credentials in plain text fields. While these don't appear to be written to disk, they may be persisted in memory and accessible if Jenkins memory is compromised.\n    cwe: CWE-522\n    function_names:\n      - BasicDigestAuthentication\n    filenames:\n      - src/main/java/jenkins/plugins/http_request/auth/BasicDigestAuthentication.java\n    classification: slightly promising\n    \n  - headline: CSRF Token Not Validated\n    analysis: |\n      HTTP requests are initiated from Jenkins without any CSRF token validation. If an attacker can trick a Jenkins user into clicking a malicious link, they may be able to trigger unwanted HTTP requests from that user's Jenkins instance.\n    cwe: CWE-352\n    function_names:\n      - HttpRequest.perform\n    filenames:\n      - src/main/java/jenkins/plugins/http_request/HttpRequest.java\n    classification: slightly promising\n\n  - headline: Verbose Error Messages\n    analysis: |  \n      Exceptions during HTTP request setup and processing are written to the Jenkins console log. Stack traces and other verbose error details could expose sensitive system information.\n    cwe: CWE-209\n    function_names:\n      - HttpRequestExecution.authAndRequest\n    filenames:\n      - src/main/java/jenkins/plugins/http_request/HttpRequestExecution.java  \n    classification: slightly promising\n\n  - headline: Entity Expansion Not Limited  \n    analysis: |\n      The MultipartEntityBuilder used for file uploads does not appear to limit entity expansion. If user-controlled data like XML is included in the multipart request body without validation, it could lead to resource exhaustion via entity expansion attacks.\n    cwe: CWE-776\n    function_names:\n      - HttpRequestExecution.authAndRequest  \n    filenames:\n      - src/main/java/jenkins/plugins/http_request/HttpRequestExecution.java\n    classification: not promising\n```\n\nThe two most concerning issues are the improper certificate validation which could allow MitM attacks, and the lack of CSRF protection on triggering HTTP requests from Jenkins.\n\nThe other findings around plaintext credentials, verbose errors, and lack of entity expansion limits are lower severity but still worth investigating and hardening where possible.\n\nLet me know if you have any other questions!",
      "date": "2024-06-14T14:18:26.868856",
      "usage": {
        "prompt_tokens": 64909,
        "completion_tokens": 800,
        "cost": 1.033635
      }
    }
  ],
  "leads": [
    {
      "headline": "Improper Certificate Validation",
      "analysis": "The CertificateAuthentication class loads a custom keystore to establish an SSL connection, but does not perform any validation on the server certificate. If the server presents an invalid or self-signed cert, it will be trusted.\n\nSimilarly, the NoopTrustManager used when ignoreSslErrors is enabled accepts any SSL certificate without validation. This allows man-in-the-middle attacks if the client connects to a malicious server.\n",
      "classification": "very promising",
      "cwe": "CWE-295",
      "function_names": [
        "CertificateAuthentication.authenticate",
        "HttpRequestExecution.NoopTrustManager"
      ],
      "filenames": [
        "src/main/java/jenkins/plugins/http_request/auth/CertificateAuthentication.java",
        "src/main/java/jenkins/plugins/http_request/HttpRequestExecution.java"
      ]
    },
    {
      "headline": "Credentials Stored in Plain Text",
      "analysis": "The BasicDigestAuthentication class stores credentials in plain text fields. While these don't appear to be written to disk, they may be persisted in memory and accessible if Jenkins memory is compromised.\n",
      "classification": "slightly promising",
      "cwe": "CWE-522",
      "function_names": [
        "BasicDigestAuthentication"
      ],
      "filenames": [
        "src/main/java/jenkins/plugins/http_request/auth/BasicDigestAuthentication.java"
      ]
    },
    {
      "headline": "CSRF Token Not Validated",
      "analysis": "HTTP requests are initiated from Jenkins without any CSRF token validation. If an attacker can trick a Jenkins user into clicking a malicious link, they may be able to trigger unwanted HTTP requests from that user's Jenkins instance.\n",
      "classification": "slightly promising",
      "cwe": "CWE-352",
      "function_names": [
        "HttpRequest.perform"
      ],
      "filenames": [
        "src/main/java/jenkins/plugins/http_request/HttpRequest.java"
      ]
    },
    {
      "headline": "Verbose Error Messages",
      "analysis": "Exceptions during HTTP request setup and processing are written to the Jenkins console log. Stack traces and other verbose error details could expose sensitive system information.\n",
      "classification": "slightly promising",
      "cwe": "CWE-209",
      "function_names": [
        "HttpRequestExecution.authAndRequest"
      ],
      "filenames": [
        "src/main/java/jenkins/plugins/http_request/HttpRequestExecution.java"
      ]
    },
    {
      "headline": "Entity Expansion Not Limited",
      "analysis": "The MultipartEntityBuilder used for file uploads does not appear to limit entity expansion. If user-controlled data like XML is included in the multipart request body without validation, it could lead to resource exhaustion via entity expansion attacks.\n",
      "classification": "not promising",
      "cwe": "CWE-776",
      "function_names": [
        "HttpRequestExecution.authAndRequest"
      ],
      "filenames": [
        "src/main/java/jenkins/plugins/http_request/HttpRequestExecution.java"
      ]
    }
  ],
  "scores": [
    {
      "stats": {
        "fn": 1,
        "tp": 0,
        "fp": 1
      },
      "mapping": {},
      "vuln_dates": {
        "CVE-2022-36901": "2022-07-27T15:15:09"
      },
      "scoring_model": "claude-3-opus-20240229",
      "type": "llm",
      "instruction_template_hash": "245ace12b6361954d0a2"
    }
  ],
  "instruction_template_hash": "10c0163db4740318a544",
  "version": "0.1.0"
}
