{
  "commit": "4bb3596c4f7e760a379f29c410eed64689762ee1",
  "repo_url": "https://github.com/squirrellyjs/squirrelly",
  "model": "claude-3-opus-20240229",
  "chunk_hashes": [
    "5f78789c248c496eb33b"
  ],
  "responses": [
    {
      "content": "Here are the potential security vulnerabilities I found in the provided codebase:\n\n```yaml\nleads:\n  - headline: Improper handling of comments in parse()\n    analysis: |\n      The parse() function does not properly handle multi-line comments delimited by /* ... */. If the closing */ is missing, it can lead to code injection vulnerabilities. Any malicious JavaScript code placed after an opening /* would be evaluated.\n    cwe: CWE-1236\n    function_names:\n      - parse\n    filenames:\n      - src/parse.ts\n    classification: very promising\n\n  - headline: Arbitrary code execution with compile()\n    analysis: |\n      The compile() function uses the Function constructor to dynamically create a new function from the provided string. If an attacker can control the str parameter passed to compile(), they could inject arbitrary JavaScript code that would get executed. This could allow an attacker to perform malicious actions on the server.\n    cwe: CWE-94\n    function_names:\n      - compile\n    filenames:\n      - src/compile.ts\n    classification: very promising\n\n  - headline: Uncontrolled resource consumption with async filters\n    analysis: |  \n      The code allows defining custom async filter functions which are executed during template rendering. An attacker could define a malicious async filter that never resolves its promise, causing the server to wait indefinitely and potentially leading to denial-of-service. There are no timeout mechanisms or restrictions on the execution time of async filters.\n    cwe: CWE-400\n    function_names:\n      - filter\n    filenames:\n      - src/compile-string.ts\n    classification: slightly promising\n\n  - headline: Potential code injection with custom plugins\n    analysis: |\n      The PartialConfig interface allows specifying custom plugins that can modify the AST (processAST) and the compiled function string (processFnString). If an attacker can control the plugins array, they could inject malicious code during the AST processing or function string manipulation. However, it depends on how the plugins are specified by the user.\n    cwe: CWE-94\n    function_names:\n      - getConfig\n    filenames:\n      - src/config.ts\n    classification: slightly promising\n\n  - headline: Improper error handling in getPath() \n    analysis: |\n      The getPath() function throws an error if the included template file cannot be found. However, it includes the user-supplied path in the error message, which could potentially leak sensitive information about the server's file system structure.\n    cwe: CWE-209\n    function_names:\n      - getPath\n    filenames:  \n      - src/file-utils.ts\n    classification: not promising\n```\n\nThe analysis focuses on identifying potential code injection, arbitrary code execution, denial-of-service, and information disclosure vulnerabilities in the Squirrelly template engine. The most promising leads are related to improper comment handling and arbitrary code execution through the compile() function. Further investigation is recommended to determine the feasibility of exploiting these vulnerabilities and their impact on real-world usage scenarios.",
      "date": "2024-07-08T08:41:26.169153",
      "usage": {
        "prompt_tokens": 75889,
        "completion_tokens": 705,
        "cost": 1.19121
      }
    }
  ],
  "leads": [
    {
      "headline": "Improper handling of comments in parse()",
      "analysis": "The parse() function does not properly handle multi-line comments delimited by /* ... */. If the closing */ is missing, it can lead to code injection vulnerabilities. Any malicious JavaScript code placed after an opening /* would be evaluated.\n",
      "classification": "very promising",
      "cwe": "CWE-1236",
      "function_names": [
        "parse"
      ],
      "filenames": [
        "src/parse.ts"
      ]
    },
    {
      "headline": "Arbitrary code execution with compile()",
      "analysis": "The compile() function uses the Function constructor to dynamically create a new function from the provided string. If an attacker can control the str parameter passed to compile(), they could inject arbitrary JavaScript code that would get executed. This could allow an attacker to perform malicious actions on the server.\n",
      "classification": "very promising",
      "cwe": "CWE-94",
      "function_names": [
        "compile"
      ],
      "filenames": [
        "src/compile.ts"
      ]
    },
    {
      "headline": "Uncontrolled resource consumption with async filters",
      "analysis": "The code allows defining custom async filter functions which are executed during template rendering. An attacker could define a malicious async filter that never resolves its promise, causing the server to wait indefinitely and potentially leading to denial-of-service. There are no timeout mechanisms or restrictions on the execution time of async filters.\n",
      "classification": "slightly promising",
      "cwe": "CWE-400",
      "function_names": [
        "filter"
      ],
      "filenames": [
        "src/compile-string.ts"
      ]
    },
    {
      "headline": "Potential code injection with custom plugins",
      "analysis": "The PartialConfig interface allows specifying custom plugins that can modify the AST (processAST) and the compiled function string (processFnString). If an attacker can control the plugins array, they could inject malicious code during the AST processing or function string manipulation. However, it depends on how the plugins are specified by the user.\n",
      "classification": "slightly promising",
      "cwe": "CWE-94",
      "function_names": [
        "getConfig"
      ],
      "filenames": [
        "src/config.ts"
      ]
    },
    {
      "headline": "Improper error handling in getPath()",
      "analysis": "The getPath() function throws an error if the included template file cannot be found. However, it includes the user-supplied path in the error message, which could potentially leak sensitive information about the server's file system structure.\n",
      "classification": "not promising",
      "cwe": "CWE-209",
      "function_names": [
        "getPath"
      ],
      "filenames": [
        "src/file-utils.ts"
      ]
    }
  ],
  "scores": [
    {
      "stats": {
        "fn": 1,
        "tp": 0,
        "fp": 2
      },
      "mapping": {},
      "vuln_dates": {
        "CVE-2021-32819": "2021-05-14T19:15:07"
      },
      "scoring_model": "claude-3-5-sonnet-20240620",
      "type": "llm",
      "instruction_template_hash": "245ace12b6361954d0a2"
    }
  ],
  "instruction_template_hash": "10c0163db4740318a544",
  "version": "0.1.0"
}
