{
  "commit": "ea537d907d61dc693587fd41aab024e9df2e14b1",
  "repo_url": "https://github.com/expressjs/express",
  "model": "claude-3-5-sonnet-20240620",
  "chunk_hashes": [
    "9cac354876d178b30cc4"
  ],
  "responses": [
    {
      "content": "Here are the key security vulnerabilities I identified in the provided Express.js codebase:\n\n```yaml\nleads:\n  - headline: Directory Traversal Vulnerability\n    analysis: |\n      The sendFile() and sendfile() methods in res.js do not properly sanitize or validate the file path, allowing potential directory traversal attacks. An attacker could potentially access files outside the intended directory by using relative paths like '../'.\n    cwe: CWE-22\n    function_names:\n      - sendFile\n      - sendfile  \n    filenames:\n      - lib/response.js\n    classification: very promising\n    \n  - headline: Potential Command Injection in exec()\n    analysis: |\n      The exec() function is used in several places to execute system commands. If user input is passed to exec() without proper sanitization, it could lead to command injection vulnerabilities.\n    cwe: CWE-78\n    function_names:\n      - exec\n    filenames:\n      - examples/route-separation/index.js\n      - examples/auth/index.js  \n    classification: slightly promising\n    \n  - headline: Insufficient Input Validation\n    analysis: |\n      Many route handlers and middleware functions do not properly validate or sanitize user input before using it. This could potentially lead to injection attacks or unexpected behavior.\n    cwe: CWE-20\n    function_names:\n      - handle\n      - param\n    filenames:\n      - lib/router/index.js\n      - lib/application.js\n    classification: slightly promising\n\n  - headline: Weak Default Session Secret\n    analysis: | \n      Several examples use a hardcoded session secret ('keyboard cat'). Using a weak or hardcoded secret reduces the security of the session implementation.\n    cwe: CWE-798\n    function_names:\n      - createApp\n    filenames:\n      - examples/auth/index.js\n      - examples/session/index.js\n    classification: slightly promising\n```\n\nThese are some of the most notable security issues I identified in the codebase. The directory traversal vulnerability in sendFile() is particularly concerning and should be addressed. The other issues around input validation and hardcoded secrets are also important to review and improve. Let me know if you need any clarification or have additional questions!",
      "date": "2024-07-07T21:05:15.192788",
      "usage": {
        "prompt_tokens": 172163,
        "completion_tokens": 525,
        "cost": 0.524364
      }
    }
  ],
  "leads": [
    {
      "headline": "Directory Traversal Vulnerability",
      "analysis": "The sendFile() and sendfile() methods in res.js do not properly sanitize or validate the file path, allowing potential directory traversal attacks. An attacker could potentially access files outside the intended directory by using relative paths like '../'.\n",
      "classification": "very promising",
      "cwe": "CWE-22",
      "function_names": [
        "sendFile",
        "sendfile"
      ],
      "filenames": [
        "lib/response.js"
      ]
    },
    {
      "headline": "Potential Command Injection in exec()",
      "analysis": "The exec() function is used in several places to execute system commands. If user input is passed to exec() without proper sanitization, it could lead to command injection vulnerabilities.\n",
      "classification": "slightly promising",
      "cwe": "CWE-78",
      "function_names": [
        "exec"
      ],
      "filenames": [
        "examples/route-separation/index.js",
        "examples/auth/index.js"
      ]
    },
    {
      "headline": "Insufficient Input Validation",
      "analysis": "Many route handlers and middleware functions do not properly validate or sanitize user input before using it. This could potentially lead to injection attacks or unexpected behavior.\n",
      "classification": "slightly promising",
      "cwe": "CWE-20",
      "function_names": [
        "handle",
        "param"
      ],
      "filenames": [
        "lib/router/index.js",
        "lib/application.js"
      ]
    },
    {
      "headline": "Weak Default Session Secret",
      "analysis": "Several examples use a hardcoded session secret ('keyboard cat'). Using a weak or hardcoded secret reduces the security of the session implementation.\n",
      "classification": "slightly promising",
      "cwe": "CWE-798",
      "function_names": [
        "createApp"
      ],
      "filenames": [
        "examples/auth/index.js",
        "examples/session/index.js"
      ]
    }
  ],
  "scores": [
    {
      "stats": {
        "fn": 2,
        "tp": 0,
        "fp": 1
      },
      "mapping": {},
      "vuln_dates": {
        "CVE-2022-24999": "2022-11-26T22:15:10",
        "CVE-2024-29041": "2024-03-25T21:15:46"
      },
      "scoring_model": "claude-3-5-sonnet-20240620",
      "type": "llm",
      "instruction_template_hash": "245ace12b6361954d0a2"
    }
  ],
  "instruction_template_hash": "10c0163db4740318a544",
  "version": "0.1.0"
}
