{
  "commit": "ba3cadefbc2b5e6b102cad2d39f40dcb378428ea",
  "repo_url": "https://github.com/nc3-lu/testingplatform",
  "model": "gpt-4o-2024-05-13",
  "chunk_hashes": [
    "c92a485dc8918e493c75"
  ],
  "responses": [
    {
      "content": "```yaml\nleads:\n  - headline: Potential Command Injection in Ping Test\n    analysis: |\n      The `ping_test` function in `testing/views.py` sources a target value from the request payload, which is then processed by external command functions without proper sanitization. Malicious inputs can lead to command injection, enabling attackers to execute arbitrary commands on the server, gain unauthorized access, and potentially cause severe damage to the system.\n    cwe: CWE-77\n    function_names:\n      - ping_test\n    filenames:\n      - testing/views.py\n    classification: very promising\n\n  - headline: Insecure Direct Object Reference (IDOR) in DMARC Reporter\n    analysis: |\n      The function `dmarc_shower` in `testing/views.py` fetches records directly based on user-defined parameters without thorough permission checks. This can allow unauthorized users to access DMARC reports by manipulating inputs, leading to potential exposure of sensitive information.\n    cwe: CWE-639\n    function_names:\n      - dmarc_shower\n    filenames:\n      - testing/views.py\n    classification: very promising\n\n  - headline: SQL Injection in Domain Addition\n    analysis: |\n      When domains are added through `add_domain` and `add_mail_domain` functions, the user input for domain is processed and stored directly. Without proper input validation and escaping, attackers can exploit this to execute arbitrary SQL commands, resulting in data breaches, data loss, or unauthorized data manipulation.\n    cwe: CWE-89\n    function_names:\n      - add_domain\n      - add_mail_domain\n    filenames:\n      - authentication/views.py\n    classification: very promising\n\n  - headline: Local File Inclusion (LFI) via Template Rendering\n    analysis: |\n      The use of user-controlled paths to include template files in `django.template.loader.render_to_string` can lead to Local File Inclusion (LFI) vulnerabilities, enabling attackers to read arbitrary files from the server, potentially including sensitive configuration files, thereby escalating their privileges.\n    cwe: CWE-22\n    function_names:\n      - get_pdf_report\n    filenames:\n      - testing/helpers.py\n    classification: slightly promising\n\n  - headline: Cross-Site Scripting (XSS) in Web Report Display\n    analysis: |\n      The rendered templates in `testing/templates/web_report.html` include user-submitted data without proper escaping. This can lead to Cross-Site Scripting (XSS) attacks, where malicious scripts can be executed in the context of users' browsers, stealing sensitive information or performing unauthorized actions on behalf of the user.\n    cwe: CWE-79\n    function_names:\n    filenames:\n      - testing/templates/web_report.html\n      - testing/templates/check_website.html\n    classification: very promising\n\n  - headline: XML External Entity (XXE) Injection in XML Parsing\n    analysis: |\n      The parsing of XML data using `xmltodict.parse` in `dmarc_shower` function could lead to XML External Entity (XXE) injection. Without proper external entity restriction, attackers can exploit this flaw to read local files, send HTTP requests, or cause a denial-of-service (DoS) attack.\n    cwe: CWE-611\n    function_names:\n      - dmarc_shower\n    filenames:\n      - testing/views.py\n    classification: very promising\n\n  - headline: Insecure Credential Transmission without HTTPS\n    analysis: |\n      The platform may transmit sensitive credentials such as passwords over insecure channels if HTTPS is not enforced. This lack of encryption allows potential attackers to intercept these credentials in transit through man-in-the-middle (MITM) attacks, leading to unauthorized access.\n    cwe: CWE-319\n    function_names:\n      - login_user\n      - signup\n    filenames:\n      - authentication/views.py\n    classification: very promising\n\n  - headline: Insufficient Error Handling in User Authentication\n    analysis: |\n      The authentication mechanisms, particularly in `login_user` and `signup`, appear to lack robust error handling and logging mechanisms. This insufficiency might lead to improper error messages leaking which can provide attackers with valuable information during an exploitation attempt.\n    cwe: CWE-209\n    function_names:\n      - login_user\n      - signup\n    filenames:\n      - authentication/views.py\n    classification: slightly promising\n\n  - headline: Cleartext Storage of Sensitive Information in Production Logs\n    analysis: |\n      Sensitive information, including user credentials and tokens, might be logged in plaintext within production logs. Attackers gaining access to these logs can steal sensitive data and compromise user accounts without any sophisticated methods.\n    cwe: CWE-532\n    function_names:\n    filenames:\n    classification: slightly promising\n\n  - headline: Missing Rate Limiting on Critical Authentication Endpoints\n    analysis: |\n      The absence of rate limiting mechanisms on login and registration endpoints exposes the authentication processes to brute force and credential stuffing attacks, allowing attackers to gain unauthorized access to accounts by systematically guessing passwords.\n    cwe: CWE-307\n    function_names:\n    filenames:\n    classification: very promising\n\n  - headline: Weak Password Policy Enforcement\n    analysis: |\n      Weak or non-existent password policy enforcement (e.g., minimum length, complexity requirements) in the user registration and password update processes can lead to the creation of easily guessable passwords, increasing the susceptibility to brute-force attacks.\n    cwe: CWE-521\n    function_names:\n      - signup\n      - change_password\n    filenames:\n      - authentication/views.py\n    classification: very promising\n```\n",
      "date": "2024-06-09T13:43:27.574881",
      "usage": {
        "prompt_tokens": 98077,
        "completion_tokens": 1137,
        "cost": 0.50744
      }
    }
  ],
  "leads": [
    {
      "headline": "Potential Command Injection in Ping Test",
      "analysis": "The ping_test function in testing/views.py sources a target value from the request payload, which is then processed by external command functions without proper sanitization. Malicious inputs can lead to command injection, enabling attackers to execute arbitrary commands on the server, gain unauthorized access, and potentially cause severe damage to the system.\n",
      "classification": "very promising",
      "cwe": "CWE-77",
      "function_names": [
        "ping_test"
      ],
      "filenames": [
        "testing/views.py"
      ]
    },
    {
      "headline": "Insecure Direct Object Reference (IDOR) in DMARC Reporter",
      "analysis": "The function dmarc_shower in testing/views.py fetches records directly based on user-defined parameters without thorough permission checks. This can allow unauthorized users to access DMARC reports by manipulating inputs, leading to potential exposure of sensitive information.\n",
      "classification": "very promising",
      "cwe": "CWE-639",
      "function_names": [
        "dmarc_shower"
      ],
      "filenames": [
        "testing/views.py"
      ]
    },
    {
      "headline": "SQL Injection in Domain Addition",
      "analysis": "When domains are added through add_domain and add_mail_domain functions, the user input for domain is processed and stored directly. Without proper input validation and escaping, attackers can exploit this to execute arbitrary SQL commands, resulting in data breaches, data loss, or unauthorized data manipulation.\n",
      "classification": "very promising",
      "cwe": "CWE-89",
      "function_names": [
        "add_domain",
        "add_mail_domain"
      ],
      "filenames": [
        "authentication/views.py"
      ]
    },
    {
      "headline": "Local File Inclusion (LFI) via Template Rendering",
      "analysis": "The use of user-controlled paths to include template files in django.template.loader.render_to_string can lead to Local File Inclusion (LFI) vulnerabilities, enabling attackers to read arbitrary files from the server, potentially including sensitive configuration files, thereby escalating their privileges.\n",
      "classification": "slightly promising",
      "cwe": "CWE-22",
      "function_names": [
        "get_pdf_report"
      ],
      "filenames": [
        "testing/helpers.py"
      ]
    },
    {
      "headline": "XML External Entity (XXE) Injection in XML Parsing",
      "analysis": "The parsing of XML data using xmltodict.parse in dmarc_shower function could lead to XML External Entity (XXE) injection. Without proper external entity restriction, attackers can exploit this flaw to read local files, send HTTP requests, or cause a denial-of-service (DoS) attack.\n",
      "classification": "very promising",
      "cwe": "CWE-611",
      "function_names": [
        "dmarc_shower"
      ],
      "filenames": [
        "testing/views.py"
      ]
    },
    {
      "headline": "Insecure Credential Transmission without HTTPS",
      "analysis": "The platform may transmit sensitive credentials such as passwords over insecure channels if HTTPS is not enforced. This lack of encryption allows potential attackers to intercept these credentials in transit through man-in-the-middle (MITM) attacks, leading to unauthorized access.\n",
      "classification": "very promising",
      "cwe": "CWE-319",
      "function_names": [
        "login_user",
        "signup"
      ],
      "filenames": [
        "authentication/views.py"
      ]
    },
    {
      "headline": "Insufficient Error Handling in User Authentication",
      "analysis": "The authentication mechanisms, particularly in login_user and signup, appear to lack robust error handling and logging mechanisms. This insufficiency might lead to improper error messages leaking which can provide attackers with valuable information during an exploitation attempt.\n",
      "classification": "slightly promising",
      "cwe": "CWE-209",
      "function_names": [
        "login_user",
        "signup"
      ],
      "filenames": [
        "authentication/views.py"
      ]
    },
    {
      "headline": "Weak Password Policy Enforcement",
      "analysis": "Weak or non-existent password policy enforcement (e.g., minimum length, complexity requirements) in the user registration and password update processes can lead to the creation of easily guessable passwords, increasing the susceptibility to brute-force attacks.\n",
      "classification": "very promising",
      "cwe": "CWE-521",
      "function_names": [
        "signup",
        "change_password"
      ],
      "filenames": [
        "authentication/views.py"
      ]
    }
  ],
  "scores": [
    {
      "stats": {
        "fn": 1,
        "tp": 0,
        "fp": 6
      },
      "mapping": {},
      "vuln_dates": {
        "CVE-2023-48310": "2023-11-20T23:15:06"
      },
      "scoring_model": "gpt-4o-2024-05-13",
      "type": "llm",
      "instruction_template_hash": "8998f09cf57fca8a6e03"
    }
  ],
  "instruction_template_hash": "10c0163db4740318a544",
  "version": "0.1.0"
}
