{
  "commit": "4bb3596c4f7e760a379f29c410eed64689762ee1",
  "repo_url": "https://github.com/squirrellyjs/squirrelly",
  "model": "gpt-4o-2024-05-13",
  "chunk_hashes": [
    "5f78789c248c496eb33b"
  ],
  "responses": [
    {
      "content": "```yaml\nleads:\n  - headline: \"Potential XSS vulnerability in template rendering\"\n    analysis: |\n      The template rendering functionalities (e.g., `{{it.html | safe}}` and `{{* it.html}}`) could allow insertion of unescaped HTML content. This might enable an attacker to inject malicious scripts.\n    cwe: CWE-79\n    function_names:\n      - \"render\"\n    filenames:\n      - \"dist/squirrelly.es.js\"\n      - \"dist/squirrelly.cjs.js\"\n    classification: very promising\n  - headline: \"Lack of server-side validation for template paths\"\n    analysis: |\n      The `includeFile` and `loadFile` functions use `path` resolution without any sanitization or validation of the input path. This can lead to directory traversal attacks allowing access to arbitrary files.\n    cwe: CWE-22\n    function_names:\n      - \"includeFile\"\n      - \"loadFile\"\n    filenames:\n      - \"src/file-utils.ts\"\n      - \"src/file-handlers.ts\"\n    classification: very promising\n  - headline: \"Vulnerability to prototype pollution in configuration\"\n    analysis: |\n      The `copyProps` function is used extensively to copy properties without any checks. If the source object contains `__proto__` properties, it can modify the prototype chain of the target object, leading to potential prototype pollution vulnerabilities.\n    cwe: CWE-1321\n    function_names:\n      - \"copyProps\"\n    filenames:\n      - \"src/utils.ts\"\n    classification: very promising\n  - headline: \"Improper validation of template variable names\"\n    analysis: |\n      The template engine does not enforce strict checks on template variable names, allowing potential variable injection issues. This could lead to overwriting and misuse of sensitive variables.\n    cwe: CWE-20\n    function_names:\n      - \"parse\"\n    filenames:\n      - \"src/parse.ts\"\n    classification: slightly promising\n  - headline: \"Potential DOS through excessive recursion in template processing\"\n    analysis: |\n      The `parseContext` function recurses to parse nested templates. If given specially crafted templates with deep nestings, it could lead to stack overflow or excessive resource consumption, resulting in a denial of service.\n    cwe: CWE-674\n    function_names:\n      - \"parseContext\"\n    filenames:\n      - \"src/parse.ts\"\n    classification: slightly promising\n```",
      "date": "2024-07-08T08:40:29.437239",
      "usage": {
        "prompt_tokens": 60278,
        "completion_tokens": 502,
        "cost": 0.30892
      }
    }
  ],
  "leads": [
    {
      "headline": "Potential XSS vulnerability in template rendering",
      "analysis": "The template rendering functionalities (e.g., {{it.html | safe}} and {{* it.html}}) could allow insertion of unescaped HTML content. This might enable an attacker to inject malicious scripts.\n",
      "classification": "very promising",
      "cwe": "CWE-79",
      "function_names": [
        "render"
      ],
      "filenames": [
        "dist/squirrelly.es.js",
        "dist/squirrelly.cjs.js"
      ]
    },
    {
      "headline": "Lack of server-side validation for template paths",
      "analysis": "The includeFile and loadFile functions use path resolution without any sanitization or validation of the input path. This can lead to directory traversal attacks allowing access to arbitrary files.\n",
      "classification": "very promising",
      "cwe": "CWE-22",
      "function_names": [
        "includeFile",
        "loadFile"
      ],
      "filenames": [
        "src/file-utils.ts",
        "src/file-handlers.ts"
      ]
    },
    {
      "headline": "Vulnerability to prototype pollution in configuration",
      "analysis": "The copyProps function is used extensively to copy properties without any checks. If the source object contains __proto__ properties, it can modify the prototype chain of the target object, leading to potential prototype pollution vulnerabilities.\n",
      "classification": "very promising",
      "cwe": "CWE-1321",
      "function_names": [
        "copyProps"
      ],
      "filenames": [
        "src/utils.ts"
      ]
    },
    {
      "headline": "Improper validation of template variable names",
      "analysis": "The template engine does not enforce strict checks on template variable names, allowing potential variable injection issues. This could lead to overwriting and misuse of sensitive variables.\n",
      "classification": "slightly promising",
      "cwe": "CWE-20",
      "function_names": [
        "parse"
      ],
      "filenames": [
        "src/parse.ts"
      ]
    },
    {
      "headline": "Potential DOS through excessive recursion in template processing",
      "analysis": "The parseContext function recurses to parse nested templates. If given specially crafted templates with deep nestings, it could lead to stack overflow or excessive resource consumption, resulting in a denial of service.\n",
      "classification": "slightly promising",
      "cwe": "CWE-674",
      "function_names": [
        "parseContext"
      ],
      "filenames": [
        "src/parse.ts"
      ]
    }
  ],
  "scores": [
    {
      "stats": {
        "fn": 1,
        "tp": 0,
        "fp": 3
      },
      "mapping": {},
      "vuln_dates": {
        "CVE-2021-32819": "2021-05-14T19:15:07"
      },
      "scoring_model": "claude-3-5-sonnet-20240620",
      "type": "llm",
      "instruction_template_hash": "245ace12b6361954d0a2"
    }
  ],
  "instruction_template_hash": "10c0163db4740318a544",
  "version": "0.1.0"
}
