{
  "commit": "293124cd59d6abc69f508b7638e383cfc791b287",
  "repo_url": "https://github.com/linux-application-whitelisting/fapolicyd",
  "model": "claude-3-haiku-20240307",
  "chunk_hashes": [
    "a4be2d637bca0ce238f3"
  ],
  "responses": [
    {
      "content": "Here is the YAML output for the security vulnerabilities in the codebase:\n\n```yaml\nleads:\n  - headline: CWE-20 Improper Input Validation\n    analysis: |\n      The codebase does not properly validate user input in several places, leading to potential vulnerabilities. This includes parsing of configuration files, handling of file paths, and processing of command line arguments.\n    cwe: CWE-20\n    function_names:\n      - nv_split\n      - assign_subject\n      - assign_object\n    filenames:\n      - src/library/rules.c\n    classification: slightly promising\n\n  - headline: CWE-119 Improper Restriction of Operations within the Bounds of a Memory Buffer\n    analysis: |\n      The codebase uses unsafe string manipulation functions like strcpy and strcat that can lead to buffer overflow vulnerabilities. This is particularly problematic in functions that process untrusted input, such as those handling configuration files and command line arguments.\n    cwe: CWE-119\n    function_names:\n      - nv_split\n      - assign_subject\n      - assign_object\n    filenames:\n      - src/library/rules.c\n    classification: slightly promising\n\n  - headline: CWE-200 Exposure of Sensitive Information to an Unauthorized Actor\n    analysis: |\n      The codebase logs sensitive information, such as file paths and process details, which could potentially lead to information disclosure. This information could be leveraged by an attacker to gain further access or understand the system's internals.\n    cwe: CWE-200\n    function_names:\n      - msg\n    filenames:\n      - src/library/message.c\n    classification: slightly promising\n\n  - headline: CWE-287 Improper Authentication\n    analysis: |\n      The codebase does not properly authenticate users or processes, which could allow unauthorized access to privileged functionality. This is particularly concerning in the context of the fapolicyd daemon, which has elevated privileges and is responsible for enforcing security policies.\n    cwe: CWE-287\n    function_names:\n      - make_policy_decision\n    filenames:\n      - src/library/policy.c\n    classification: very promising\n\n  - headline: CWE-362 Concurrent Execution using Shared Resource with Improper Synchronization ('Race Condition')\n    analysis: |\n      The codebase uses shared resources, such as the trust database, without proper synchronization, which could lead to race conditions and inconsistent state. This is particularly problematic in the context of the fapolicyd daemon, which needs to ensure the integrity of the trust database.\n    cwe: CWE-362\n    function_names:\n      - lock_update_thread\n      - unlock_update_thread\n    filenames:\n      - src/library/database.c\n    classification: very promising\n```",
      "date": "2024-06-13T09:48:16.888629",
      "usage": {
        "prompt_tokens": 121668,
        "completion_tokens": 666,
        "cost": 0.0312495
      }
    }
  ],
  "leads": [
    {
      "headline": "CWE-20 Improper Input Validation",
      "analysis": "The codebase does not properly validate user input in several places, leading to potential vulnerabilities. This includes parsing of configuration files, handling of file paths, and processing of command line arguments.\n",
      "classification": "slightly promising",
      "cwe": "CWE-20",
      "function_names": [
        "nv_split",
        "assign_subject",
        "assign_object"
      ],
      "filenames": [
        "src/library/rules.c"
      ]
    },
    {
      "headline": "CWE-119 Improper Restriction of Operations within the Bounds of a Memory Buffer",
      "analysis": "The codebase uses unsafe string manipulation functions like strcpy and strcat that can lead to buffer overflow vulnerabilities. This is particularly problematic in functions that process untrusted input, such as those handling configuration files and command line arguments.\n",
      "classification": "slightly promising",
      "cwe": "CWE-119",
      "function_names": [
        "nv_split",
        "assign_subject",
        "assign_object"
      ],
      "filenames": [
        "src/library/rules.c"
      ]
    },
    {
      "headline": "CWE-200 Exposure of Sensitive Information to an Unauthorized Actor",
      "analysis": "The codebase logs sensitive information, such as file paths and process details, which could potentially lead to information disclosure. This information could be leveraged by an attacker to gain further access or understand the system's internals.\n",
      "classification": "slightly promising",
      "cwe": "CWE-200",
      "function_names": [
        "msg"
      ],
      "filenames": [
        "src/library/message.c"
      ]
    },
    {
      "headline": "CWE-287 Improper Authentication",
      "analysis": "The codebase does not properly authenticate users or processes, which could allow unauthorized access to privileged functionality. This is particularly concerning in the context of the fapolicyd daemon, which has elevated privileges and is responsible for enforcing security policies.\n",
      "classification": "very promising",
      "cwe": "CWE-287",
      "function_names": [
        "make_policy_decision"
      ],
      "filenames": [
        "src/library/policy.c"
      ]
    },
    {
      "headline": "CWE-362 Concurrent Execution using Shared Resource with Improper Synchronization ('Race Condition')",
      "analysis": "The codebase uses shared resources, such as the trust database, without proper synchronization, which could lead to race conditions and inconsistent state. This is particularly problematic in the context of the fapolicyd daemon, which needs to ensure the integrity of the trust database.\n",
      "classification": "very promising",
      "cwe": "CWE-362",
      "function_names": [
        "lock_update_thread",
        "unlock_update_thread"
      ],
      "filenames": [
        "src/library/database.c"
      ]
    }
  ],
  "scores": [
    {
      "stats": {
        "fn": 1,
        "tp": 0,
        "fp": 2
      },
      "mapping": {},
      "vuln_dates": {
        "CVE-2022-1117": "2022-08-29T15:15:10"
      },
      "scoring_model": "claude-3-opus-20240229",
      "type": "llm",
      "instruction_template_hash": "245ace12b6361954d0a2"
    },
    {
      "stats": {
        "fn": 1,
        "tp": 0,
        "fp": 2
      },
      "mapping": {},
      "vuln_dates": {
        "CVE-2022-1117": "2022-08-29T15:15:10"
      },
      "scoring_model": "claude-3-5-sonnet-20240620",
      "type": "llm",
      "instruction_template_hash": "245ace12b6361954d0a2"
    }
  ],
  "instruction_template_hash": "10c0163db4740318a544",
  "version": "0.1.0"
}
