{
  "commit": "22e9b99015f488aa40018ddda1c261eb5b50b2d0",
  "repo_url": "https://github.com/jenkinsci/compuware-ispw-operations-plugin",
  "model": "claude-3-haiku-20240307",
  "chunk_hashes": [
    "27ef7bb64e9f3996882e"
  ],
  "responses": [
    {
      "content": "```yaml\nleads:\n  - headline: Missing Encryption of Sensitive Data\n    analysis: |\n      The codebase uses JSON serialization/deserialization to handle sensitive data, such as credentials and authentication tokens, without proper encryption. This can lead to the exposure of sensitive information in the serialized JSON data, which may be stored or transmitted without proper protection. Attackers may be able to intercept and access this sensitive data, compromising the security of the application.\n    cwe: CWE-311\n    function_names:\n      - JsonGenerator.generate\n      - IspwRequestBean.setJsonRequest\n    filenames:\n      - src/main/java/com/compuware/ispw/restapi/JsonGenerator.java\n      - src/main/java/com/compuware/ispw/restapi/IspwRequestBean.java\n    classification: very promising\n\n  - headline: Externally Controlled Reference to a Resource in Another Sphere\n    analysis: |\n      The codebase uses user-controlled input to construct URLs and paths that are used to access sensitive resources, such as ISPW assignments and releases. Attackers may be able to craft malicious input to access unauthorized resources or perform server-side request forgery (SSRF) attacks, potentially leading to the compromise of the application or the underlying system.\n    cwe: CWE-610\n    function_names:\n      - IspwRestApiRequest.resolveUrl\n      - IspwRestApiRequestStep.Execution.run\n    filenames:\n      - src/main/java/com/compuware/ispw/restapi/IspwRestApiRequest.java\n      - src/main/java/com/compuware/ispw/restapi/IspwRestApiRequestStep.java\n    classification: very promising\n\n  - headline: Improper Neutralization of Special Elements used in an OS Command ('OS Command Injection')\n    analysis: |\n      The codebase uses user-controlled input to construct OS command strings, which are then executed by the application. Attackers may be able to inject malicious commands into these inputs, potentially leading to the execution of arbitrary commands on the system, a critical security vulnerability.\n    cwe: CWE-78\n    function_names:\n      - HttpClientUtil.appendParamsToUrl\n      - HttpClientUtil.paramsToString\n    filenames:\n      - src/main/java/com/compuware/ispw/restapi/util/HttpClientUtil.java\n    classification: very promising\n\n  - headline: Insufficient Verification of Data Authenticity\n    analysis: |\n      The codebase uses HTTP headers and parameters to control the behavior of the application, such as authentication and authorization. Attackers may be able to forge or tamper with these headers and parameters, potentially bypassing security checks and gaining unauthorized access to the application.\n    cwe: CWE-345\n    function_names:\n      - IspwRestApiRequest.resolveHeaders\n      - IspwRestApiRequestStep.Execution.run\n    filenames:\n      - src/main/java/com/compuware/ispw/restapi/IspwRestApiRequest.java\n      - src/main/java/com/compuware/ispw/restapi/IspwRestApiRequestStep.java\n    classification: very promising\n\n  - headline: Improper Validation of Specified Quantity in Input\n    analysis: |\n      The codebase uses user-controlled input to specify parameters for ISPW actions, such as assignment IDs, release IDs, and task IDs. Attackers may be able to provide malformed or out-of-range input, potentially leading to unexpected behavior or errors in the application.\n    cwe: CWE-1284\n    function_names:\n      - IspwRestApiRequest.resolveUrl\n      - IspwRestApiRequestStep.Execution.run\n    filenames:\n      - src/main/java/com/compuware/ispw/restapi/IspwRestApiRequest.java\n      - src/main/java/com/compuware/ispw/restapi/IspwRestApiRequestStep.java\n    classification: slightly promising\n\n  - headline: Improper Handling of Exceptional Conditions\n    analysis: |\n      The codebase does not consistently handle all possible exceptions and error conditions, which can lead to unexpected behavior or crashes in the application. Attackers may be able to trigger these errors to disrupt the application's functionality or potentially gain further access to the system.\n    cwe: CWE-755\n    function_names:\n      - HttpRequestExecution.call\n    filenames:\n      - src/main/java/com/compuware/ispw/restapi/HttpRequestExecution.java\n    classification: slightly promising\n\n```",
      "date": "2024-06-12T18:07:39.347868",
      "usage": {
        "prompt_tokens": 59957,
        "completion_tokens": 1110,
        "cost": 0.01637675
      }
    }
  ],
  "leads": [
    {
      "headline": "Missing Encryption of Sensitive Data",
      "analysis": "The codebase uses JSON serialization/deserialization to handle sensitive data, such as credentials and authentication tokens, without proper encryption. This can lead to the exposure of sensitive information in the serialized JSON data, which may be stored or transmitted without proper protection. Attackers may be able to intercept and access this sensitive data, compromising the security of the application.\n",
      "classification": "very promising",
      "cwe": "CWE-311",
      "function_names": [
        "JsonGenerator.generate",
        "IspwRequestBean.setJsonRequest"
      ],
      "filenames": [
        "src/main/java/com/compuware/ispw/restapi/JsonGenerator.java",
        "src/main/java/com/compuware/ispw/restapi/IspwRequestBean.java"
      ]
    },
    {
      "headline": "Externally Controlled Reference to a Resource in Another Sphere",
      "analysis": "The codebase uses user-controlled input to construct URLs and paths that are used to access sensitive resources, such as ISPW assignments and releases. Attackers may be able to craft malicious input to access unauthorized resources or perform server-side request forgery (SSRF) attacks, potentially leading to the compromise of the application or the underlying system.\n",
      "classification": "very promising",
      "cwe": "CWE-610",
      "function_names": [
        "IspwRestApiRequest.resolveUrl",
        "IspwRestApiRequestStep.Execution.run"
      ],
      "filenames": [
        "src/main/java/com/compuware/ispw/restapi/IspwRestApiRequest.java",
        "src/main/java/com/compuware/ispw/restapi/IspwRestApiRequestStep.java"
      ]
    },
    {
      "headline": "Improper Neutralization of Special Elements used in an OS Command ('OS Command Injection')",
      "analysis": "The codebase uses user-controlled input to construct OS command strings, which are then executed by the application. Attackers may be able to inject malicious commands into these inputs, potentially leading to the execution of arbitrary commands on the system, a critical security vulnerability.\n",
      "classification": "very promising",
      "cwe": "CWE-78",
      "function_names": [
        "HttpClientUtil.appendParamsToUrl",
        "HttpClientUtil.paramsToString"
      ],
      "filenames": [
        "src/main/java/com/compuware/ispw/restapi/util/HttpClientUtil.java"
      ]
    },
    {
      "headline": "Insufficient Verification of Data Authenticity",
      "analysis": "The codebase uses HTTP headers and parameters to control the behavior of the application, such as authentication and authorization. Attackers may be able to forge or tamper with these headers and parameters, potentially bypassing security checks and gaining unauthorized access to the application.\n",
      "classification": "very promising",
      "cwe": "CWE-345",
      "function_names": [
        "IspwRestApiRequest.resolveHeaders",
        "IspwRestApiRequestStep.Execution.run"
      ],
      "filenames": [
        "src/main/java/com/compuware/ispw/restapi/IspwRestApiRequest.java",
        "src/main/java/com/compuware/ispw/restapi/IspwRestApiRequestStep.java"
      ]
    },
    {
      "headline": "Improper Validation of Specified Quantity in Input",
      "analysis": "The codebase uses user-controlled input to specify parameters for ISPW actions, such as assignment IDs, release IDs, and task IDs. Attackers may be able to provide malformed or out-of-range input, potentially leading to unexpected behavior or errors in the application.\n",
      "classification": "slightly promising",
      "cwe": "CWE-1284",
      "function_names": [
        "IspwRestApiRequest.resolveUrl",
        "IspwRestApiRequestStep.Execution.run"
      ],
      "filenames": [
        "src/main/java/com/compuware/ispw/restapi/IspwRestApiRequest.java",
        "src/main/java/com/compuware/ispw/restapi/IspwRestApiRequestStep.java"
      ]
    },
    {
      "headline": "Improper Handling of Exceptional Conditions",
      "analysis": "The codebase does not consistently handle all possible exceptions and error conditions, which can lead to unexpected behavior or crashes in the application. Attackers may be able to trigger these errors to disrupt the application's functionality or potentially gain further access to the system.\n",
      "classification": "slightly promising",
      "cwe": "CWE-755",
      "function_names": [
        "HttpRequestExecution.call"
      ],
      "filenames": [
        "src/main/java/com/compuware/ispw/restapi/HttpRequestExecution.java"
      ]
    }
  ],
  "scores": [
    {
      "stats": {
        "fn": 2,
        "tp": 0,
        "fp": 4
      },
      "mapping": {},
      "vuln_dates": {
        "CVE-2022-36899": "2022-07-27T15:15:09",
        "CVE-2022-36898": "2022-07-27T15:15:09"
      },
      "scoring_model": "claude-3-opus-20240229",
      "type": "llm",
      "instruction_template_hash": "245ace12b6361954d0a2"
    }
  ],
  "instruction_template_hash": "10c0163db4740318a544",
  "version": "0.1.0"
}
