{
  "commit": "2b3eb35a9f2ad00afd09e26e4e2a988baac4dbaf",
  "repo_url": "https://github.com/matanui159/replaysorcery",
  "model": "gemini/gemini-1.5-pro",
  "chunk_hashes": [
    "666dff3c73c0fe01a546"
  ],
  "responses": [
    {
      "content": "```yaml\nleads:\n  - headline: Potential Integer Overflow in rsScaleSize\n    analysis: |\n      The `rsScaleSize` function in `src/util.c` calculates scaled width and height based on configuration values. \n      The calculations involve bit-shifting operations (`>>` and `<<`) which, if the input values are sufficiently large, may lead to integer overflows.\n      A malicious user could potentially exploit this by providing extreme values for width and height in the configuration, causing unexpected behavior or crashes.\n    cwe: CWE-190\n    function_names:\n      - rsScaleSize\n    filenames:\n      - src/util.c\n    classification: slightly promising\n  - headline: Uncontrolled Resource Consumption in rsFormatv\n    analysis: |\n      The `rsFormatv` function in `src/util.c` dynamically allocates memory using `av_malloc` based on the formatted string size. \n      The size is determined by `vsnprintf`, which can potentially return a large value if the format string or arguments are manipulated.\n      An attacker could craft a malicious format string or arguments that result in a huge memory allocation, leading to denial of service. \n    cwe: CWE-770\n    function_names:\n      - rsFormatv\n    filenames:\n      - src/util.c\n    classification: slightly promising\n  - headline: Potential Command Injection in rsOutputClose\n    analysis: |\n      The `rsOutputClose` function in `src/output.c` executes a command specified by the `outputCommand` configuration option using the `system` function.\n      If the `outputCommand` string is not properly sanitized and allows user input, an attacker could inject arbitrary commands into the system call.\n      This could lead to the execution of malicious commands on the user's system.\n    cwe: CWE-78\n    function_names:\n      - rsOutputClose\n    filenames:\n      - src/output.c\n    classification: very promising\n  - headline: Potential Information Exposure in rsOptionsDestroy\n    analysis: |\n      The `rsOptionsDestroy` function in `src/util.c` logs unused options from an `AVDictionary`. \n      This may unintentionally expose sensitive information, such as API keys or passwords, that were set as options but not used.\n      An attacker could potentially retrieve these sensitive details from the logs.\n    cwe: CWE-200\n    function_names:\n      - rsOptionsDestroy\n    filenames:\n      - src/util.c\n    classification: slightly promising\n  - headline: Potential Uncontrolled Resource Consumption in configParse\n    analysis: |\n      The `configParse` function in `src/config.c` reads the configuration file using `avio_read_to_bprint` with `INT_MAX` as the maximum size. \n      This could lead to excessive memory consumption if the configuration file is extremely large.\n      An attacker could create a massive configuration file, causing the program to exhaust available memory.\n    cwe: CWE-770\n    function_names:\n      - configParse\n    filenames:\n      - src/config.c\n    classification: slightly promising\n  - headline: Potential Race Condition in rsLogSilence\n    analysis: |\n      The `rsLogSilence` function in `src/log.c` uses a mutex (`silenceMutex`) to protect the `silenceCounter` variable.\n      However, there is a potential race condition between checking the counter and setting the log level.\n      Multiple threads could simultaneously access and modify the counter, leading to inconsistent log behavior.\n    cwe: CWE-362\n    function_names:\n      - rsLogSilence\n    filenames:\n      - src/log.c\n    classification: slightly promising\n```",
      "date": "2024-06-13T09:59:57.290527",
      "usage": {
        "prompt_tokens": 37476,
        "completion_tokens": 749,
        "cost": 0.024826875
      }
    }
  ],
  "leads": [
    {
      "headline": "Potential Integer Overflow in rsScaleSize",
      "analysis": "The rsScaleSize function in src/util.c calculates scaled width and height based on configuration values. \nThe calculations involve bit-shifting operations (>> and <<) which, if the input values are sufficiently large, may lead to integer overflows.\nA malicious user could potentially exploit this by providing extreme values for width and height in the configuration, causing unexpected behavior or crashes.\n",
      "classification": "slightly promising",
      "cwe": "CWE-190",
      "function_names": [
        "rsScaleSize"
      ],
      "filenames": [
        "src/util.c"
      ]
    },
    {
      "headline": "Uncontrolled Resource Consumption in rsFormatv",
      "analysis": "The rsFormatv function in src/util.c dynamically allocates memory using av_malloc based on the formatted string size. \nThe size is determined by vsnprintf, which can potentially return a large value if the format string or arguments are manipulated.\nAn attacker could craft a malicious format string or arguments that result in a huge memory allocation, leading to denial of service. \n",
      "classification": "slightly promising",
      "cwe": "CWE-770",
      "function_names": [
        "rsFormatv"
      ],
      "filenames": [
        "src/util.c"
      ]
    },
    {
      "headline": "Potential Command Injection in rsOutputClose",
      "analysis": "The rsOutputClose function in src/output.c executes a command specified by the outputCommand configuration option using the system function.\nIf the outputCommand string is not properly sanitized and allows user input, an attacker could inject arbitrary commands into the system call.\nThis could lead to the execution of malicious commands on the user's system.\n",
      "classification": "very promising",
      "cwe": "CWE-78",
      "function_names": [
        "rsOutputClose"
      ],
      "filenames": [
        "src/output.c"
      ]
    },
    {
      "headline": "Potential Information Exposure in rsOptionsDestroy",
      "analysis": "The rsOptionsDestroy function in src/util.c logs unused options from an AVDictionary. \nThis may unintentionally expose sensitive information, such as API keys or passwords, that were set as options but not used.\nAn attacker could potentially retrieve these sensitive details from the logs.\n",
      "classification": "slightly promising",
      "cwe": "CWE-200",
      "function_names": [
        "rsOptionsDestroy"
      ],
      "filenames": [
        "src/util.c"
      ]
    },
    {
      "headline": "Potential Uncontrolled Resource Consumption in configParse",
      "analysis": "The configParse function in src/config.c reads the configuration file using avio_read_to_bprint with INT_MAX as the maximum size. \nThis could lead to excessive memory consumption if the configuration file is extremely large.\nAn attacker could create a massive configuration file, causing the program to exhaust available memory.\n",
      "classification": "slightly promising",
      "cwe": "CWE-770",
      "function_names": [
        "configParse"
      ],
      "filenames": [
        "src/config.c"
      ]
    },
    {
      "headline": "Potential Race Condition in rsLogSilence",
      "analysis": "The rsLogSilence function in src/log.c uses a mutex (silenceMutex) to protect the silenceCounter variable.\nHowever, there is a potential race condition between checking the counter and setting the log level.\nMultiple threads could simultaneously access and modify the counter, leading to inconsistent log behavior.\n",
      "classification": "slightly promising",
      "cwe": "CWE-362",
      "function_names": [
        "rsLogSilence"
      ],
      "filenames": [
        "src/log.c"
      ]
    }
  ],
  "scores": [
    {
      "stats": {
        "fn": 2,
        "tp": 0,
        "fp": 1
      },
      "mapping": {},
      "vuln_dates": {
        "CVE-2021-26936": "2021-02-10T18:15:13",
        "CVE-2021-36983": "2021-07-30T14:15:18"
      },
      "scoring_model": "claude-3-opus-20240229",
      "type": "llm",
      "instruction_template_hash": "245ace12b6361954d0a2"
    }
  ],
  "instruction_template_hash": "10c0163db4740318a544",
  "version": "0.1.0"
}
