{
  "commit": "4084ea18f96d9a953315f5555fca45f26639b8be",
  "repo_url": "https://github.com/cyanomiko/dcnnt-py",
  "model": "claude-3-sonnet-20240229",
  "chunk_hashes": [
    "ae7b8d1efa8980c63a92"
  ],
  "responses": [
    {
      "content": "```yaml\nleads:\n  - headline: Improper restriction of operations within the bounds of a memory buffer\n    analysis: |\n      The code in `dcnnt/tcp_server.py` does not properly validate the size of data received from the socket before writing it to a buffer. Specifically, in the `DConnectHandler.recv` method, the code reads data from the socket into a bytearray buffer without checking if the size of the received data exceeds the capacity of the buffer. This can lead to a buffer overflow vulnerability, where an attacker can send a large amount of data to overwrite adjacent memory regions and potentially execute arbitrary code or cause a denial of service.\n    cwe: CWE-119\n    function_names:\n      - DConnectHandler.recv\n    filenames:\n      - dcnnt/tcp_server.py\n    classification: very promising\n\n  - headline: Use of hard-coded credentials\n    analysis: |\n      In `dcnnt/setup.py`, the code generates a random password for the server device and stores it in the configuration file `conf.json`. While this password is generated randomly, it is still hard-coded in the configuration file, which can pose a security risk if an attacker gains access to the file. Additionally, the same password is used for all devices connecting to the server, which violates the principle of least privilege.\n    cwe: CWE-798\n    function_names:\n      - setuptools.setup\n    filenames:\n      - dcnnt/setup.py\n    classification: very promising\n\n  - headline: Improper neutralization of special elements used in an OS command ('OS Command Injection')\n    analysis: |\n      The code in `dcnnt/plugins/opener.py` and `dcnnt/plugins/notifications.py` constructs and executes operating system commands using user-supplied data without proper sanitization. Specifically, the `on_download` and `cmd` configuration options are used to construct shell commands using string formatting, which can allow an attacker to inject malicious code if these options are not properly sanitized. This can lead to arbitrary command execution on the system.\n    cwe: CWE-78\n    function_names:\n      - OpenerPlugin.handle_open_file\n      - NotificationsPlugin.main\n    filenames:\n      - dcnnt/plugins/opener.py\n      - dcnnt/plugins/notifications.py\n    classification: very promising\n\n  - headline: Unrestricted upload of file with dangerous type\n    analysis: |\n      The code in `dcnnt/plugins/sync.py` allows unrestricted file uploads from clients to the server. An attacker could potentially upload and execute malicious code on the server by exploiting this functionality. While the code checks if a file is part of a configured list of synchronized files before merging it with a local version, it does not validate the file type or content during the initial upload process.\n    cwe: CWE-434\n    function_names:\n      - SyncPlugin.handle_dir_upload\n      - SyncPlugin.handle_file_upload\n    filenames:\n      - dcnnt/plugins/sync.py\n    classification: very promising\n\n  - headline: Improper restriction of excessive authentication attempts\n    analysis: |\n      The code does not implement any mechanism to restrict or limit the number of authentication attempts made by clients connecting to the server. An attacker could potentially perform a brute-force attack by repeatedly trying different credentials without any limitation. This could lead to unauthorized access if a weak password is used.\n    cwe: CWE-307\n    function_names: []\n    filenames: []\n    classification: slightly promising\n\n  - headline: Improper preservation of permissions\n    analysis: |\n      The code in `dcnnt/device_manager.py` stores device passwords in plaintext in JSON files within the `devices` directory. While the files are created with default permissions, there is no mechanism in place to ensure that these permissions are preserved over time. An attacker with access to the system could potentially gain unauthorized access to device passwords by modifying the file permissions.\n    cwe: CWE-281\n    function_names:\n      - DeviceManager.dump_device\n    filenames:\n      - dcnnt/device_manager.py\n    classification: slightly promising\n\n  - headline: Improper initialization of resource\n    analysis: |\n      In `dcnnt/app.py`, the `salt_send` and `salt_recv` attributes of the `DConnectHandler` class are initialized with insecure default values (bytes of all zeros). These values are used as nonces for encryption and decryption operations. Using a predictable or constant nonce can significantly weaken the security of the encryption scheme and make it vulnerable to attacks.\n    cwe: CWE-909\n    function_names:\n      - DConnectHandler.__init__\n    filenames:\n      - dcnnt/app.py\n    classification: slightly promising\n\n  - headline: Improper control of generation of code ('Code Injection')\n    analysis: |\n      The code in `dcnnt/plugins/remote_commands.py` allows clients to execute arbitrary shell commands on the server system. While the code attempts to validate the command before execution, it does not properly sanitize the input, potentially allowing an attacker to inject malicious code.\n    cwe: CWE-94\n    function_names:\n      - RemoteCommandsPlugin.handle_exec\n    filenames:\n      - dcnnt/plugins/remote_commands.py\n    classification: slightly promising\n```",
      "date": "2024-06-09T10:18:49.225361",
      "usage": {
        "prompt_tokens": 30039,
        "completion_tokens": 1265,
        "cost": 0.109092
      }
    }
  ],
  "leads": [
    {
      "headline": "Improper restriction of operations within the bounds of a memory buffer",
      "analysis": "The code in dcnnt/tcp_server.py does not properly validate the size of data received from the socket before writing it to a buffer. Specifically, in the DConnectHandler.recv method, the code reads data from the socket into a bytearray buffer without checking if the size of the received data exceeds the capacity of the buffer. This can lead to a buffer overflow vulnerability, where an attacker can send a large amount of data to overwrite adjacent memory regions and potentially execute arbitrary code or cause a denial of service.\n",
      "classification": "very promising",
      "cwe": "CWE-119",
      "function_names": [
        "DConnectHandler.recv"
      ],
      "filenames": [
        "dcnnt/tcp_server.py"
      ]
    },
    {
      "headline": "Use of hard-coded credentials",
      "analysis": "In dcnnt/setup.py, the code generates a random password for the server device and stores it in the configuration file conf.json. While this password is generated randomly, it is still hard-coded in the configuration file, which can pose a security risk if an attacker gains access to the file. Additionally, the same password is used for all devices connecting to the server, which violates the principle of least privilege.\n",
      "classification": "very promising",
      "cwe": "CWE-798",
      "function_names": [
        "setuptools.setup"
      ],
      "filenames": [
        "dcnnt/setup.py"
      ]
    },
    {
      "headline": "Improper neutralization of special elements used in an OS command ('OS Command Injection')",
      "analysis": "The code in dcnnt/plugins/opener.py and dcnnt/plugins/notifications.py constructs and executes operating system commands using user-supplied data without proper sanitization. Specifically, the on_download and cmd configuration options are used to construct shell commands using string formatting, which can allow an attacker to inject malicious code if these options are not properly sanitized. This can lead to arbitrary command execution on the system.\n",
      "classification": "very promising",
      "cwe": "CWE-78",
      "function_names": [
        "OpenerPlugin.handle_open_file",
        "NotificationsPlugin.main"
      ],
      "filenames": [
        "dcnnt/plugins/opener.py",
        "dcnnt/plugins/notifications.py"
      ]
    },
    {
      "headline": "Unrestricted upload of file with dangerous type",
      "analysis": "The code in dcnnt/plugins/sync.py allows unrestricted file uploads from clients to the server. An attacker could potentially upload and execute malicious code on the server by exploiting this functionality. While the code checks if a file is part of a configured list of synchronized files before merging it with a local version, it does not validate the file type or content during the initial upload process.\n",
      "classification": "very promising",
      "cwe": "CWE-434",
      "function_names": [
        "SyncPlugin.handle_dir_upload",
        "SyncPlugin.handle_file_upload"
      ],
      "filenames": [
        "dcnnt/plugins/sync.py"
      ]
    },
    {
      "headline": "Improper restriction of excessive authentication attempts",
      "analysis": "The code does not implement any mechanism to restrict or limit the number of authentication attempts made by clients connecting to the server. An attacker could potentially perform a brute-force attack by repeatedly trying different credentials without any limitation. This could lead to unauthorized access if a weak password is used.\n",
      "classification": "slightly promising",
      "cwe": "CWE-307",
      "function_names": [],
      "filenames": []
    },
    {
      "headline": "Improper preservation of permissions",
      "analysis": "The code in dcnnt/device_manager.py stores device passwords in plaintext in JSON files within the devices directory. While the files are created with default permissions, there is no mechanism in place to ensure that these permissions are preserved over time. An attacker with access to the system could potentially gain unauthorized access to device passwords by modifying the file permissions.\n",
      "classification": "slightly promising",
      "cwe": "CWE-281",
      "function_names": [
        "DeviceManager.dump_device"
      ],
      "filenames": [
        "dcnnt/device_manager.py"
      ]
    },
    {
      "headline": "Improper initialization of resource",
      "analysis": "In dcnnt/app.py, the salt_send and salt_recv attributes of the DConnectHandler class are initialized with insecure default values (bytes of all zeros). These values are used as nonces for encryption and decryption operations. Using a predictable or constant nonce can significantly weaken the security of the encryption scheme and make it vulnerable to attacks.\n",
      "classification": "slightly promising",
      "cwe": "CWE-909",
      "function_names": [
        "DConnectHandler.__init__"
      ],
      "filenames": [
        "dcnnt/app.py"
      ]
    },
    {
      "headline": "Improper control of generation of code ('Code Injection')",
      "analysis": "The code in dcnnt/plugins/remote_commands.py allows clients to execute arbitrary shell commands on the server system. While the code attempts to validate the command before execution, it does not properly sanitize the input, potentially allowing an attacker to inject malicious code.\n",
      "classification": "slightly promising",
      "cwe": "CWE-94",
      "function_names": [
        "RemoteCommandsPlugin.handle_exec"
      ],
      "filenames": [
        "dcnnt/plugins/remote_commands.py"
      ]
    }
  ],
  "scores": [
    {
      "stats": {
        "fn": 0,
        "tp": 1,
        "fp": 3
      },
      "mapping": {
        "2": "CVE-2023-1000"
      },
      "vuln_dates": {
        "CVE-2023-1000": "2024-04-27T09:15:08"
      },
      "scoring_model": "gpt-4o-2024-05-13",
      "type": "llm",
      "instruction_template_hash": "8998f09cf57fca8a6e03"
    }
  ],
  "instruction_template_hash": "10c0163db4740318a544",
  "version": "0.1.0"
}
