{
  "commit": "11f66fb1ee9cc511c882a877df2f9678e7b1af86",
  "repo_url": "https://github.com/cloudfoundry-incubator/bits-service-release",
  "model": "gpt-4-turbo-2024-04-09",
  "chunk_hashes": [
    "aa399f8f145d3322b689"
  ],
  "responses": [
    {
      "content": "```yaml\nleads:\n  - headline: Exposure of Sensitive Information in config file creation script\n    analysis: |\n      The script `get_instance_cookie_jars.sh` directly outputs sensitive information such as instance identifiers into cookie jar filenames and logs. This information could be leveraged by an attacker with local access or through a log exposure vulnerability to potentially understand and infiltrate specific user sessions, or deduce patterns in the session handling mechanism of the application.\n    cwe: CWE-532\n    function_names: []\n    filenames:\n      - src/github.com/cloudfoundry-incubator/bits-service-performance-tests/assets/dora/get_instance_cookie_jars.sh\n    classification: slightly promising\n\n  - headline: Hard-coded credential risks and improper handling of sensitive information in script\n    analysis: |\n      The environment script `run-system-tests.sh` contains hard-coded logic to handle credentials and configurations which are necessary to interact with different blobstore types such as 'webdav' or 'local'. The use of hard-coded paths to .private and explicit checks for credential environment variables might expose sensitive configuration details or encourage insecure practices.\n    cwe: CWE-798\n    function_names: []\n    filenames:\n      - scripts/run-system-tests.sh\n    classification: slightly promising\n\n  - headline: Insecure default permission and temporary file handling in PID management utility\n    analysis: |\n      The `pid_utils.sh` utility functions `pid_guard`, `wait_pid_death`, and `kill_and_wait` employ operations on PID files which may not securely handle the permissions or integrity of the PID files, leading to potential race conditions or privilege escalation if a malicious process interferes by substituting or modifying the PID file before it is read.\n    cwe: CWE-367\n    function_names:\n      - pid_guard\n      - wait_pid_death\n      - kill_and_wait\n    filenames:\n      - src/bits-common/pid_utils.sh\n    classification: slightly promising\n\n  - headline: Missing encryption of sensitive data when transferring credentials in bits service\n    analysis: |\n      The deployment scripts for the bits service, specifically in the script `run-system-tests.sh`, extensively use transfer of credentials and configurations in cleartext which could be intercepted by a local attacker or over insecure networks. The script should enforce encrypted channels or secure storage mechanisms when handling sensitive information.\n    cwe: CWE-319\n    function_names: []\n    filenames:\n      - scripts/run-system-tests.sh\n    classification: very promising\n\n  - headline: Insecure certificate handling in Kubernetes secret extraction\n    analysis: |\n      The Docker utility script `copy.sh` under cert-copier retrieves Kubernetes secrets, decodes them from base64, and stores them into a predetermined directory without adequately securing the destination or the transport mechanism. This poses a risk where the cryptographic material could be exposed to unauthorized entities during transport or storage.\n    cwe: CWE-922\n    function_names:\n      - copy-cert\n    filenames:\n      - docker/cert-copier/copy.sh\n    classification: slightly promising\n\n  - headline: Script injection risk in configuration JSON generation\n    analysis: |\n      The script present at `README.markdown` for setting the testing config uses inputs like `CF_DOMAIN`, `CF_ADMIN_USER`, and `CF_ADMIN_PASSWORD` to craft a JSON configuration, which is directly echoed and redirected into a file without sanitizing or encoding the inputs. This poses a risk of script injection where manipulated input values could compromise the configuration integrity or execute unintended commands.\n    cwe: CWE-74\n    function_names: []\n    filenames:\n      - src/github.com/cloudfoundry-incubator/bits-service-performance-tests/README.markdown\n    classification: slightly promising\n```",
      "date": "2024-06-12T15:40:27.763145",
      "usage": {
        "prompt_tokens": 4936,
        "completion_tokens": 761,
        "cost": 0.07219
      }
    }
  ],
  "leads": [
    {
      "headline": "Exposure of Sensitive Information in config file creation script",
      "analysis": "The script get_instance_cookie_jars.sh directly outputs sensitive information such as instance identifiers into cookie jar filenames and logs. This information could be leveraged by an attacker with local access or through a log exposure vulnerability to potentially understand and infiltrate specific user sessions, or deduce patterns in the session handling mechanism of the application.\n",
      "classification": "slightly promising",
      "cwe": "CWE-532",
      "function_names": [],
      "filenames": [
        "src/github.com/cloudfoundry-incubator/bits-service-performance-tests/assets/dora/get_instance_cookie_jars.sh"
      ]
    },
    {
      "headline": "Hard-coded credential risks and improper handling of sensitive information in script",
      "analysis": "The environment script run-system-tests.sh contains hard-coded logic to handle credentials and configurations which are necessary to interact with different blobstore types such as 'webdav' or 'local'. The use of hard-coded paths to .private and explicit checks for credential environment variables might expose sensitive configuration details or encourage insecure practices.\n",
      "classification": "slightly promising",
      "cwe": "CWE-798",
      "function_names": [],
      "filenames": [
        "scripts/run-system-tests.sh"
      ]
    },
    {
      "headline": "Insecure default permission and temporary file handling in PID management utility",
      "analysis": "The pid_utils.sh utility functions pid_guard, wait_pid_death, and kill_and_wait employ operations on PID files which may not securely handle the permissions or integrity of the PID files, leading to potential race conditions or privilege escalation if a malicious process interferes by substituting or modifying the PID file before it is read.\n",
      "classification": "slightly promising",
      "cwe": "CWE-367",
      "function_names": [
        "pid_guard",
        "wait_pid_death",
        "kill_and_wait"
      ],
      "filenames": [
        "src/bits-common/pid_utils.sh"
      ]
    },
    {
      "headline": "Missing encryption of sensitive data when transferring credentials in bits service",
      "analysis": "The deployment scripts for the bits service, specifically in the script run-system-tests.sh, extensively use transfer of credentials and configurations in cleartext which could be intercepted by a local attacker or over insecure networks. The script should enforce encrypted channels or secure storage mechanisms when handling sensitive information.\n",
      "classification": "very promising",
      "cwe": "CWE-319",
      "function_names": [],
      "filenames": [
        "scripts/run-system-tests.sh"
      ]
    },
    {
      "headline": "Insecure certificate handling in Kubernetes secret extraction",
      "analysis": "The Docker utility script copy.sh under cert-copier retrieves Kubernetes secrets, decodes them from base64, and stores them into a predetermined directory without adequately securing the destination or the transport mechanism. This poses a risk where the cryptographic material could be exposed to unauthorized entities during transport or storage.\n",
      "classification": "slightly promising",
      "cwe": "CWE-922",
      "function_names": [
        "copy-cert"
      ],
      "filenames": [
        "docker/cert-copier/copy.sh"
      ]
    },
    {
      "headline": "Script injection risk in configuration JSON generation",
      "analysis": "The script present at README.markdown for setting the testing config uses inputs like CF_DOMAIN, CF_ADMIN_USER, and CF_ADMIN_PASSWORD to craft a JSON configuration, which is directly echoed and redirected into a file without sanitizing or encoding the inputs. This poses a risk of script injection where manipulated input values could compromise the configuration integrity or execute unintended commands.\n",
      "classification": "slightly promising",
      "cwe": "CWE-74",
      "function_names": [],
      "filenames": [
        "src/github.com/cloudfoundry-incubator/bits-service-performance-tests/README.markdown"
      ]
    }
  ],
  "scores": [
    {
      "stats": {
        "fn": 1,
        "tp": 0,
        "fp": 1
      },
      "mapping": {},
      "vuln_dates": {
        "CVE-2018-15800": "2018-12-10T19:29:25"
      },
      "scoring_model": "claude-3-opus-20240229",
      "type": "llm",
      "instruction_template_hash": "245ace12b6361954d0a2"
    },
    {
      "stats": {
        "fn": 1,
        "tp": 0,
        "fp": 1
      },
      "mapping": {},
      "vuln_dates": {
        "CVE-2018-15800": "2018-12-10T19:29:25"
      },
      "scoring_model": "claude-3-5-sonnet-20240620",
      "type": "llm",
      "instruction_template_hash": "245ace12b6361954d0a2"
    }
  ],
  "instruction_template_hash": "10c0163db4740318a544",
  "version": "0.1.0"
}
