{
  "commit": "bb99293a17c12cf116dde66b9729d1a3d79ed551",
  "repo_url": "https://github.com/cdoco/php-jwt",
  "model": "gpt-4o-2024-05-13",
  "chunk_hashes": [
    "eab40c70683f345aadbe"
  ],
  "responses": [
    {
      "content": "```yaml\nleads:\n  - headline: \"Use of hard-coded cryptographic algorithms\"\n    analysis: |\n      The codebase has hardcoded cryptographic algorithms in the `jwt_sign_sha_hmac`, `jwt_verify_sha_hmac`, `jwt_sign_sha_pem`, and `jwt_verify_sha_pem` functions. This can lead to weak or outdated algorithms being used without the possibility of configuring stronger ones, posing a security risk. \n    cwe: CWE-327\n    function_names:\n      - jwt_sign_sha_hmac\n      - jwt_verify_sha_hmac\n      - jwt_sign_sha_pem\n    filenames:\n      - openssl.c\n    classification: very promising\n\n  - headline: \"Use of insecure random number generation\"\n    analysis: |\n      There is usage of memory allocation through functions such as `alloca` and `emalloc` without confirmation of successful allocation, which can lead to memory corruption or crashes when the system is under memory pressure.\n    cwe: CWE-338\n    function_names:\n      - jwt_b64_url_decode\n      - jwt_sign_sha_pem\n      - jwt_verify_sha_hmac\n    filenames:\n      - jwt.c\n      - openssl.c\n    classification: very promising\n\n  - headline: \"Use of cryptographic key stored as plain text\"\n    analysis: |\n      The cryptographic functions are using keys passed as plain text. Keeping keys in plain text and not securely wiping out the memory after use may lead to exposing the keys in memory dumps.\n    cwe: CWE-312\n    function_names:\n      - jwt_sign_sha_hmac\n      - jwt_verify_sha_hmac\n      - jwt_sign_sha_pem\n    filenames:\n      - openssl.c\n    classification: very promising\n\n  - headline: \"Improper error handling in cryptographic operations\"\n    analysis: |\n      The error handling in the crypto functions (e.g., `jwt_sign_sha_hmac`, `jwt_verify_sha_hmac`) is inconsistent and often defaults to returning general error codes without detailed error messages or proper cleanup of resources.\n    cwe: CWE-754\n    function_names:\n      - jwt_sign_sha_hmac\n      - jwt_verify_sha_hmac\n    filenames:\n      - openssl.c\n    classification: slightly promising\n\n  - headline: \"Potential buffer overflow in base64 encoding functions\"\n    analysis: |\n      The base64 encoding and decoding functions (`jwt_b64_url_encode`, `jwt_b64_url_decode`) perform manual string manipulations and buffer allocations that could result in buffer overflows if the length calculations are incorrect or if improper input is provided.\n    cwe: CWE-120\n    function_names:\n      - jwt_b64_url_encode\n      - jwt_b64_url_decode\n    filenames:\n      - jwt.c\n    classification: very promising\n```",
      "date": "2024-06-09T09:33:40.057835",
      "usage": {
        "prompt_tokens": 12263,
        "completion_tokens": 580,
        "cost": 0.070015
      }
    }
  ],
  "leads": [
    {
      "headline": "Use of hard-coded cryptographic algorithms",
      "analysis": "The codebase has hardcoded cryptographic algorithms in the jwt_sign_sha_hmac, jwt_verify_sha_hmac, jwt_sign_sha_pem, and jwt_verify_sha_pem functions. This can lead to weak or outdated algorithms being used without the possibility of configuring stronger ones, posing a security risk. \n",
      "classification": "very promising",
      "cwe": "CWE-327",
      "function_names": [
        "jwt_sign_sha_hmac",
        "jwt_verify_sha_hmac",
        "jwt_sign_sha_pem"
      ],
      "filenames": [
        "openssl.c"
      ]
    },
    {
      "headline": "Use of insecure random number generation",
      "analysis": "There is usage of memory allocation through functions such as alloca and emalloc without confirmation of successful allocation, which can lead to memory corruption or crashes when the system is under memory pressure.\n",
      "classification": "very promising",
      "cwe": "CWE-338",
      "function_names": [
        "jwt_b64_url_decode",
        "jwt_sign_sha_pem",
        "jwt_verify_sha_hmac"
      ],
      "filenames": [
        "jwt.c",
        "openssl.c"
      ]
    },
    {
      "headline": "Use of cryptographic key stored as plain text",
      "analysis": "The cryptographic functions are using keys passed as plain text. Keeping keys in plain text and not securely wiping out the memory after use may lead to exposing the keys in memory dumps.\n",
      "classification": "very promising",
      "cwe": "CWE-312",
      "function_names": [
        "jwt_sign_sha_hmac",
        "jwt_verify_sha_hmac",
        "jwt_sign_sha_pem"
      ],
      "filenames": [
        "openssl.c"
      ]
    },
    {
      "headline": "Improper error handling in cryptographic operations",
      "analysis": "The error handling in the crypto functions (e.g., jwt_sign_sha_hmac, jwt_verify_sha_hmac) is inconsistent and often defaults to returning general error codes without detailed error messages or proper cleanup of resources.\n",
      "classification": "slightly promising",
      "cwe": "CWE-754",
      "function_names": [
        "jwt_sign_sha_hmac",
        "jwt_verify_sha_hmac"
      ],
      "filenames": [
        "openssl.c"
      ]
    },
    {
      "headline": "Potential buffer overflow in base64 encoding functions",
      "analysis": "The base64 encoding and decoding functions (jwt_b64_url_encode, jwt_b64_url_decode) perform manual string manipulations and buffer allocations that could result in buffer overflows if the length calculations are incorrect or if improper input is provided.\n",
      "classification": "very promising",
      "cwe": "CWE-120",
      "function_names": [
        "jwt_b64_url_encode",
        "jwt_b64_url_decode"
      ],
      "filenames": [
        "jwt.c"
      ]
    }
  ],
  "scores": [
    {
      "stats": {
        "fn": 1,
        "tp": 0,
        "fp": 4
      },
      "mapping": {},
      "vuln_dates": {
        "CVE-2024-25191": "2024-02-08T17:15:11"
      },
      "scoring_model": "gpt-4o-2024-05-13",
      "type": "llm",
      "instruction_template_hash": "8998f09cf57fca8a6e03"
    }
  ],
  "instruction_template_hash": "10c0163db4740318a544",
  "version": "0.1.0"
}
