{
  "commit": "193579916bd4da46a36922cf899ecb37bb9afa6e",
  "repo_url": "https://github.com/jenkinsci/catalogic-ecx-plugin",
  "model": "gpt-4o-2024-05-13",
  "chunk_hashes": [
    "f1826a5bd387dc70d8f4"
  ],
  "responses": [
    {
      "content": "```yaml\nleads:\n  - headline: \"Hard-coded Credentials\"\n    analysis: |\n      The code contains hard-coded credentials in the `ECXSdk` class constructor and various methods which use these credentials for HTTP Basic Authentication. This is a significant security vulnerability as it exposes sensitive information directly in the source code.\n    cwe: CWE-798\n    function_names:\n      - \"ECXSdk\"\n      - \"doPostForSessionId\"\n    filenames:\n      - \"src/main/java/com/catalogic/ecx/sdk/ECXSdk.java\"\n    classification: \"very promising\"\n\n  - headline: \"Missing Encryption of Sensitive Data\"\n    analysis: |\n      The `ECXSdk` class transmits the username and password in plain text as part of the Basic Authentication header. Without using HTTPS, this can expose sensitive credentials to potential interceptors during transmission.\n    cwe: CWE-319\n    function_names:\n      - \"doPostForSessionId\"\n      - \"connect\"\n    filenames:\n      - \"src/main/java/com/catalogic/ecx/sdk/ECXSdk.java\"\n    classification: \"very promising\"\n\n  - headline: \"Insecure URL Handling\"\n    analysis: |\n      The URL passed to the `ECXSdk` class is concatenated with different endpoints when making HTTP requests without proper validation or sanitization. This could lead to URL manipulation attacks such as SSRF (Server-Side Request Forgery).\n    cwe: CWE-918\n    function_names:\n      - \"doPost\"\n      - \"doGet\"\n    filenames:\n      - \"src/main/java/com/catalogic/ecx/sdk/ECXSdk.java\"\n    classification: \"slightly promising\"\n\n  - headline: \"Improper Certificate Validation\"\n    analysis: |\n      When not in production mode, the SSL/TLS context in the `ECXSdk` class is set to trust all certificates without proper validation. This allows connections to potentially malicious servers with self-signed certificates.\n    cwe: CWE-295\n    function_names:\n      - \"_processRESTRequest\"\n    filenames:\n      - \"src/main/java/com/catalogic/ecx/sdk/ECXSdk.java\"\n    classification: \"very promising\"\n\n  - headline: \"Exception Handling and Error Messages Disclosure\"\n    analysis: |\n      The `processRESTRequest` and other methods frequently wrap exceptions in `RuntimeException` and print stack traces directly. This can leak sensitive information and make the system vulnerable to information disclosure attacks.\n    cwe: CWE-209\n    function_names:\n      - \"processRESTRequest\"\n      - \"convertStreamToString\"\n    filenames:\n      - \"src/main/java/com/catalogic/ecx/sdk/ECXSdk.java\"\n    classification: \"slightly promising\"\n\n  - headline: \"Observable Discrepancy in Error Code Validation\"\n    analysis: |\n      The `validateStatusLine` function throws a runtime exception when the expected HTTP status code does not match the actual response. If the discrepancy is observable, it can be exploited for information leakage about server-side logic.\n    cwe: CWE-203\n    function_names:\n      - \"validateStatusLine\"\n    filenames:\n      - \"src/main/java/com/catalogic/ecx/sdk/ECXSdk.java\"\n    classification: \"slightly promising\"\n\n  - headline: \"Cleartext Storage of Sensitive Information\"\n    analysis: |\n      The password is stored in plain text within the `ECXSdk` class and is susceptible to being logged or accidentally exposed.\n    cwe: CWE-312\n    function_names:\n      - \"ECXSdk\"\n    filenames:\n      - \"src/main/java/com/catalogic/ecx/sdk/ECXSdk.java\"\n    classification: \"slightly promising\"\n```",
      "date": "2024-06-12T18:01:11.027463",
      "usage": {
        "prompt_tokens": 7253,
        "completion_tokens": 761,
        "cost": 0.04768
      }
    }
  ],
  "leads": [
    {
      "headline": "Hard-coded Credentials",
      "analysis": "The code contains hard-coded credentials in the ECXSdk class constructor and various methods which use these credentials for HTTP Basic Authentication. This is a significant security vulnerability as it exposes sensitive information directly in the source code.\n",
      "classification": "very promising",
      "cwe": "CWE-798",
      "function_names": [
        "ECXSdk",
        "doPostForSessionId"
      ],
      "filenames": [
        "src/main/java/com/catalogic/ecx/sdk/ECXSdk.java"
      ]
    },
    {
      "headline": "Missing Encryption of Sensitive Data",
      "analysis": "The ECXSdk class transmits the username and password in plain text as part of the Basic Authentication header. Without using HTTPS, this can expose sensitive credentials to potential interceptors during transmission.\n",
      "classification": "very promising",
      "cwe": "CWE-319",
      "function_names": [
        "doPostForSessionId",
        "connect"
      ],
      "filenames": [
        "src/main/java/com/catalogic/ecx/sdk/ECXSdk.java"
      ]
    },
    {
      "headline": "Insecure URL Handling",
      "analysis": "The URL passed to the ECXSdk class is concatenated with different endpoints when making HTTP requests without proper validation or sanitization. This could lead to URL manipulation attacks such as SSRF (Server-Side Request Forgery).\n",
      "classification": "slightly promising",
      "cwe": "CWE-918",
      "function_names": [
        "doPost",
        "doGet"
      ],
      "filenames": [
        "src/main/java/com/catalogic/ecx/sdk/ECXSdk.java"
      ]
    },
    {
      "headline": "Improper Certificate Validation",
      "analysis": "When not in production mode, the SSL/TLS context in the ECXSdk class is set to trust all certificates without proper validation. This allows connections to potentially malicious servers with self-signed certificates.\n",
      "classification": "very promising",
      "cwe": "CWE-295",
      "function_names": [
        "_processRESTRequest"
      ],
      "filenames": [
        "src/main/java/com/catalogic/ecx/sdk/ECXSdk.java"
      ]
    },
    {
      "headline": "Exception Handling and Error Messages Disclosure",
      "analysis": "The processRESTRequest and other methods frequently wrap exceptions in RuntimeException and print stack traces directly. This can leak sensitive information and make the system vulnerable to information disclosure attacks.\n",
      "classification": "slightly promising",
      "cwe": "CWE-209",
      "function_names": [
        "processRESTRequest",
        "convertStreamToString"
      ],
      "filenames": [
        "src/main/java/com/catalogic/ecx/sdk/ECXSdk.java"
      ]
    },
    {
      "headline": "Observable Discrepancy in Error Code Validation",
      "analysis": "The validateStatusLine function throws a runtime exception when the expected HTTP status code does not match the actual response. If the discrepancy is observable, it can be exploited for information leakage about server-side logic.\n",
      "classification": "slightly promising",
      "cwe": "CWE-203",
      "function_names": [
        "validateStatusLine"
      ],
      "filenames": [
        "src/main/java/com/catalogic/ecx/sdk/ECXSdk.java"
      ]
    },
    {
      "headline": "Cleartext Storage of Sensitive Information",
      "analysis": "The password is stored in plain text within the ECXSdk class and is susceptible to being logged or accidentally exposed.\n",
      "classification": "slightly promising",
      "cwe": "CWE-312",
      "function_names": [
        "ECXSdk"
      ],
      "filenames": [
        "src/main/java/com/catalogic/ecx/sdk/ECXSdk.java"
      ]
    }
  ],
  "scores": [
    {
      "stats": {
        "fn": 1,
        "tp": 0,
        "fp": 3
      },
      "mapping": {},
      "vuln_dates": {
        "CVE-2020-2128": "2020-02-12T15:15:14"
      },
      "scoring_model": "claude-3-opus-20240229",
      "type": "llm",
      "instruction_template_hash": "245ace12b6361954d0a2"
    }
  ],
  "instruction_template_hash": "10c0163db4740318a544",
  "version": "0.1.0"
}
