{
  "commit": "0981f834e6f71c4522ebea75e046a46b6471b76b",
  "repo_url": "https://github.com/jtojnar/pengu",
  "model": "claude-3-sonnet-20240229",
  "chunk_hashes": [
    "77c874eca6b7f90b72d8"
  ],
  "responses": [
    {
      "content": "```yaml\nleads:\n  - headline: Cross-Site Scripting (XSS) vulnerability in client-side code\n    analysis: |\n      The application does not properly sanitize user input before rendering it in the browser, allowing attackers to inject arbitrary HTML and client-side scripts. The vulnerability arises specifically in the `speakForPlayer` function in `client.js`, where the `message` parameter from the server is directly inserted into the DOM without any validation or sanitization.\n    cwe: CWE-79\n    function_names:\n      - speakForPlayer\n    filenames:\n      - client/client.js\n    classification: very promising\n\n  - headline: Insecure WebSocket connections\n    analysis: |\n      The application establishes WebSocket connections over an unencrypted channel (ws://), transmitting sensitive information such as session data, user credentials, and chat messages in cleartext. An attacker capable of eavesdropping on the network traffic could intercept this data.\n    cwe: CWE-319\n    function_names: []\n    filenames:\n      - server.js\n      - client/client.js\n    classification: very promising\n\n  - headline: Lack of per-object access control mechanism\n    analysis: |\n      There is no access control mechanism in place to prevent users from modifying or accessing resources they do not have permission to access, such as modifying the state of other users, dressing in items they do not own, or moving to restricted areas. While the application handles access control at a coarse-grained level (e.g. admin, moderator, basic users), there is no fine-grained access control mechanism to prevent unauthorized actions on specific resources.\n    cwe: CWE-862\n    function_names: []\n    filenames:\n      - server.js\n    classification: very promising\n\n  - headline: Potential session fixation vulnerability\n    analysis: |\n      The application uses session IDs in a way that may allow an attacker to force a user to use a known session ID, potentially allowing the attacker to hijack the user's session. The session ID is stored in a cookie and passed to the server, but there is no evidence of mechanisms to prevent session fixation attacks, such as renewing the session ID after successful authentication or using session IDs that are difficult to guess.\n    cwe: CWE-384\n    function_names: []\n    filenames:\n      - server.js\n    classification: slightly promising\n\n  - headline: Lack of secure handling of player positioning\n    analysis: |\n      The application allows clients to arbitrarily set their position on the map by sending a `move` message to the server with the desired coordinates. There is no server-side validation to ensure that the requested position is valid or allowed, potentially allowing clients to bypass intended restrictions or access unauthorized areas.\n    cwe: CWE-20\n    function_names:\n      - getTarget\n    filenames:\n      - server.js\n    classification: very promising\n\n  - headline: Improper use of cryptographic functions\n    analysis: |\n      The application uses the `Math.random()` function to generate a secret value used for session management. This is not a cryptographically secure source of randomness and could allow an attacker to predict or brute-force the secret value, potentially compromising the integrity of the session management mechanism.\n    cwe: CWE-330\n    function_names: []\n    filenames:\n      - server.js\n    classification: slightly promising\n\n  - headline: Use of insecure HTTP headers\n    analysis: |\n      The application does not set security-related HTTP headers, such as the `X-XSS-Protection`, `X-Frame-Options`, `X-Content-Type-Options`, and `Strict-Transport-Security` headers. Omitting these headers increases the application's exposure to various web application vulnerabilities, such as XSS, Clickjacking, and protocol downgrade attacks.\n    cwe: CWE-116\n    function_names: []\n    filenames:\n      - server.js\n    classification: slightly promising\n\n  - headline: Potential regular expression denial of service (ReDoS) vulnerability\n    analysis: |\n      The application uses regular expressions for parsing and processing user input, such as in the `containsPoint` function of the `Polyline` and `Polygon` classes. While the specific regular expressions used are not provided, poorly constructed regular expressions can lead to denial of service vulnerabilities if an attacker can control the input matched against the regular expression.\n    cwe: CWE-1333\n    function_names:\n      - containsPoint\n    filenames:\n      - poly.js\n    classification: slightly promising\n```",
      "date": "2024-06-13T09:05:18.090770",
      "usage": {
        "prompt_tokens": 14456,
        "completion_tokens": 1066,
        "cost": 0.059358
      }
    }
  ],
  "leads": [
    {
      "headline": "Cross-Site Scripting (XSS) vulnerability in client-side code",
      "analysis": "The application does not properly sanitize user input before rendering it in the browser, allowing attackers to inject arbitrary HTML and client-side scripts. The vulnerability arises specifically in the speakForPlayer function in client.js, where the message parameter from the server is directly inserted into the DOM without any validation or sanitization.\n",
      "classification": "very promising",
      "cwe": "CWE-79",
      "function_names": [
        "speakForPlayer"
      ],
      "filenames": [
        "client/client.js"
      ]
    },
    {
      "headline": "Insecure WebSocket connections",
      "analysis": "The application establishes WebSocket connections over an unencrypted channel (ws://), transmitting sensitive information such as session data, user credentials, and chat messages in cleartext. An attacker capable of eavesdropping on the network traffic could intercept this data.\n",
      "classification": "very promising",
      "cwe": "CWE-319",
      "function_names": [],
      "filenames": [
        "server.js",
        "client/client.js"
      ]
    },
    {
      "headline": "Lack of per-object access control mechanism",
      "analysis": "There is no access control mechanism in place to prevent users from modifying or accessing resources they do not have permission to access, such as modifying the state of other users, dressing in items they do not own, or moving to restricted areas. While the application handles access control at a coarse-grained level (e.g. admin, moderator, basic users), there is no fine-grained access control mechanism to prevent unauthorized actions on specific resources.\n",
      "classification": "very promising",
      "cwe": "CWE-862",
      "function_names": [],
      "filenames": [
        "server.js"
      ]
    },
    {
      "headline": "Potential session fixation vulnerability",
      "analysis": "The application uses session IDs in a way that may allow an attacker to force a user to use a known session ID, potentially allowing the attacker to hijack the user's session. The session ID is stored in a cookie and passed to the server, but there is no evidence of mechanisms to prevent session fixation attacks, such as renewing the session ID after successful authentication or using session IDs that are difficult to guess.\n",
      "classification": "slightly promising",
      "cwe": "CWE-384",
      "function_names": [],
      "filenames": [
        "server.js"
      ]
    },
    {
      "headline": "Lack of secure handling of player positioning",
      "analysis": "The application allows clients to arbitrarily set their position on the map by sending a move message to the server with the desired coordinates. There is no server-side validation to ensure that the requested position is valid or allowed, potentially allowing clients to bypass intended restrictions or access unauthorized areas.\n",
      "classification": "very promising",
      "cwe": "CWE-20",
      "function_names": [
        "getTarget"
      ],
      "filenames": [
        "server.js"
      ]
    },
    {
      "headline": "Improper use of cryptographic functions",
      "analysis": "The application uses the Math.random() function to generate a secret value used for session management. This is not a cryptographically secure source of randomness and could allow an attacker to predict or brute-force the secret value, potentially compromising the integrity of the session management mechanism.\n",
      "classification": "slightly promising",
      "cwe": "CWE-330",
      "function_names": [],
      "filenames": [
        "server.js"
      ]
    },
    {
      "headline": "Use of insecure HTTP headers",
      "analysis": "The application does not set security-related HTTP headers, such as the X-XSS-Protection, X-Frame-Options, X-Content-Type-Options, and Strict-Transport-Security headers. Omitting these headers increases the application's exposure to various web application vulnerabilities, such as XSS, Clickjacking, and protocol downgrade attacks.\n",
      "classification": "slightly promising",
      "cwe": "CWE-116",
      "function_names": [],
      "filenames": [
        "server.js"
      ]
    },
    {
      "headline": "Potential regular expression denial of service (ReDoS) vulnerability",
      "analysis": "The application uses regular expressions for parsing and processing user input, such as in the containsPoint function of the Polyline and Polygon classes. While the specific regular expressions used are not provided, poorly constructed regular expressions can lead to denial of service vulnerabilities if an attacker can control the input matched against the regular expression.\n",
      "classification": "slightly promising",
      "cwe": "CWE-1333",
      "function_names": [
        "containsPoint"
      ],
      "filenames": [
        "poly.js"
      ]
    }
  ],
  "scores": [
    {
      "stats": {
        "fn": 1,
        "tp": 0,
        "fp": 4
      },
      "mapping": {},
      "vuln_dates": {
        "CVE-2020-36623": "2022-12-21T19:15:12"
      },
      "scoring_model": "claude-3-opus-20240229",
      "type": "llm",
      "instruction_template_hash": "245ace12b6361954d0a2"
    }
  ],
  "instruction_template_hash": "10c0163db4740318a544",
  "version": "0.1.0"
}
