{
  "commit": "20ce28ba0c25d8062323f82b4b9bcbbfbc5142d1",
  "repo_url": "https://github.com/pandora-analysis/pandora",
  "model": "gpt-4-turbo-2024-04-09",
  "chunk_hashes": [
    "248429ec84c3819aa582"
  ],
  "responses": [
    {
      "content": "```yaml\nleads:\n  - headline: \"Presence of several CWE 352: CSRF vulnerabilities in the web application\"\n    analysis: |\n      Multiple places in the web application do not implement any form of CSRF protection, which can allow an attacker to perform unauthorized actions on behalf of an authenticated user. Particularly, forms and AJAX requests are sent without anti-CSRF tokens, and the API endpoints do not validate the origin of requests. This could be exploited by crafting malicious web pages that, once visited by an authenticated user, can perform actions such as changing user settings or triggering actions within the application.\n    cwe: CWE-352\n    function_names:\n      - \"api_toggle_detailed_view\"\n      - \"load_user_from_request\"\n      - \"_load_user_from_request\"\n    filenames:\n      - \"website/web/__init__.py\"\n    classification: \"very promising\"\n\n  - headline: \"Use of Hard-Coded Cryptographic Key in session management\"\n    analysis: |\n      The application uses a hard-coded key for encrypting session tokens, which is insecure and makes it vulnerable to attacks where the attacker can predict or obtain the secret key. Hard-coded keys in source code can be easily discovered by an attacker through code analysis. This vulnerability further allows the attacker to potentially decrypt or forge session tokens, leading to session hijacking or impersonation attacks.\n    cwe: CWE-798\n    function_names:\n      - \"get_secret_key\"\n    filenames:\n      - \"website/web/helpers.py\"\n    classification: \"very promising\"\n\n  - headline: \"Improper Access Control allows unauthorized actions\"\n    analysis: |\n      The application does not consistently enforce access controls, particularly in functions that modify user roles and permission settings. Unauthorized users can potentially invoke certain functions to modify roles or perform administrative actions without proper checks. This vulnerability is primarily due to insufficient enforcement of permissions and improper session management.\n    cwe: CWE-284\n    function_names:\n      - \"api_roles\"\n      - \"api_admin_page\"\n      - \"api_admin_submit\"\n    filenames:\n      - \"website/web/generic_api.py\"\n    classification: \"very promising\"\n\n  - headline: \"Insecure Direct Object References leading to unauthorized access\"\n    analysis: |\n      The application's handling of object references (like task IDs or user IDs) directly provided by users allows an authenticated user to access data of other users without authorization. For instance, functions handling analysis results, tasks, or file downloads do not properly verify the user's entitlement to access the requested resources, leading to potential information disclosure.\n    cwe: CWE-639\n    function_names:\n      - \"api_analysis\"\n      - \"api_task_download\"\n    filenames:\n      - \"website/web/__init__.py\"\n    classification: \"very promising\"\n\n```",
      "date": "2024-06-13T10:59:44.004686",
      "usage": {
        "prompt_tokens": 86852,
        "completion_tokens": 563,
        "cost": 0.88541
      }
    }
  ],
  "leads": [
    {
      "headline": "Presence of several CWE 352: CSRF vulnerabilities in the web application",
      "analysis": "Multiple places in the web application do not implement any form of CSRF protection, which can allow an attacker to perform unauthorized actions on behalf of an authenticated user. Particularly, forms and AJAX requests are sent without anti-CSRF tokens, and the API endpoints do not validate the origin of requests. This could be exploited by crafting malicious web pages that, once visited by an authenticated user, can perform actions such as changing user settings or triggering actions within the application.\n",
      "classification": "very promising",
      "cwe": "CWE-352",
      "function_names": [
        "api_toggle_detailed_view",
        "load_user_from_request",
        "_load_user_from_request"
      ],
      "filenames": [
        "website/web/__init__.py"
      ]
    },
    {
      "headline": "Use of Hard-Coded Cryptographic Key in session management",
      "analysis": "The application uses a hard-coded key for encrypting session tokens, which is insecure and makes it vulnerable to attacks where the attacker can predict or obtain the secret key. Hard-coded keys in source code can be easily discovered by an attacker through code analysis. This vulnerability further allows the attacker to potentially decrypt or forge session tokens, leading to session hijacking or impersonation attacks.\n",
      "classification": "very promising",
      "cwe": "CWE-798",
      "function_names": [
        "get_secret_key"
      ],
      "filenames": [
        "website/web/helpers.py"
      ]
    },
    {
      "headline": "Improper Access Control allows unauthorized actions",
      "analysis": "The application does not consistently enforce access controls, particularly in functions that modify user roles and permission settings. Unauthorized users can potentially invoke certain functions to modify roles or perform administrative actions without proper checks. This vulnerability is primarily due to insufficient enforcement of permissions and improper session management.\n",
      "classification": "very promising",
      "cwe": "CWE-284",
      "function_names": [
        "api_roles",
        "api_admin_page",
        "api_admin_submit"
      ],
      "filenames": [
        "website/web/generic_api.py"
      ]
    },
    {
      "headline": "Insecure Direct Object References leading to unauthorized access",
      "analysis": "The application's handling of object references (like task IDs or user IDs) directly provided by users allows an authenticated user to access data of other users without authorization. For instance, functions handling analysis results, tasks, or file downloads do not properly verify the user's entitlement to access the requested resources, leading to potential information disclosure.\n",
      "classification": "very promising",
      "cwe": "CWE-639",
      "function_names": [
        "api_analysis",
        "api_task_download"
      ],
      "filenames": [
        "website/web/__init__.py"
      ]
    }
  ],
  "scores": [
    {
      "stats": {
        "fn": 1,
        "tp": 0,
        "fp": 4
      },
      "mapping": {},
      "vuln_dates": {
        "CVE-2023-22898": "2023-01-10T02:15:09"
      },
      "scoring_model": "claude-3-opus-20240229",
      "type": "llm",
      "instruction_template_hash": "245ace12b6361954d0a2"
    }
  ],
  "instruction_template_hash": "10c0163db4740318a544",
  "version": "0.1.0"
}
