{
  "commit": "80a4a094afa862ee730e8a948358a49e9735b521",
  "repo_url": "https://github.com/arc53/docsgpt",
  "model": "gpt-4o-2024-05-13",
  "chunk_hashes": [
    "9a5880ff46af14228dba"
  ],
  "responses": [
    {
      "content": "```yaml\nleads:\n  - headline: \"Hardcoded API Key Found\"\n    analysis: |\n      In `extensions/chatwoot/app.py`, the `chatwoot_token` and `docsgpt_key` are hardcoded.\n      This can potentially expose your API keys to unauthorized users if your code\n      becomes public or is accessed by third parties. To mitigate this, consider using\n      environment variables or a secure secrets management service to store and access your API keys.\n    cwe: CWE-798\n    function_names: []\n    filenames:\n      - \"extensions/chatwoot/app.py\"\n    classification: very promising\n\n  - headline: \"No Input Validation: Shell Injection Risk\"\n    analysis: |\n      In `setup.sh`, there's no input validation when reading the user's choice. \n      An attacker who successfully gets arbitrary data executed could manipulate the shell \n      and potentially run arbitrary system commands, leading to a command injection vulnerability.\n      For instance, validation is not performed on the `choice` variable.\n    cwe: CWE-20\n    function_names:\n      - prompt_user\n    filenames:\n      - \"setup.sh\"\n    classification: very promising\n\n  - headline: \"Insecure File Download: Potential Supply Chain Attack\"\n    analysis: |\n      In `setup.sh`, the model is being downloaded from a URL (`wget https://d3dg1063dc54p9.cloudfront.net/models/docsgpt-7b-f16.gguf`) without any integrity checks.\n      This exposes the application to man-in-the-middle (MITM) attacks or other forms of supply chain attacks.\n      The integrity of downloaded files should be verified using hashes or signatures to ensure they haven't been tampered with.\n    cwe: CWE-494\n    function_names: []\n    filenames:\n      - \"setup.sh\"\n    classification: very promising\n\n  - headline: \"Sensitive Information in Error Messages\"\n    analysis: |\n      The error handling in `application/api/answer/routes.py` prints the entire traceback,\n      including potentially sensitive information, to the logs.\n      This information could be leveraged by an attacker to gain more insight into the internal workings of the application, \n      which increases the attack surface.\n    cwe: CWE-209\n    function_names:\n      - api_answer\n    filenames:\n      - \"application/api/answer/routes.py\"\n    classification: very promising\n\n  - headline: \"Potential SSRF Vulnerability\"\n    analysis: |\n      In `application/worker.py`, the `requests.get` method is used to fetch URLs provided by the user.\n      This could lead to SSRF if the user-controlled input is not properly validated or sanitized, allowing an attacker to \n      craft requests that can access internal services and potentially exploit them.\n    cwe: CWE-918\n    function_names:\n      - ingest_worker\n    filenames:\n      - \"application/worker.py\"\n    classification: slightly promising\n\n  - headline: \"Cross-Site Scripting (XSS) Vulnerability\"\n    analysis: |\n      In `frontend/src/conversation/conversationApi.ts`, the responses from the API are directly rendered into the DOM on the client-side.\n      If the API response is not properly sanitized or encoded, it introduces a risk of XSS, where attackers can inject malicious scripts into the page.\n    cwe: CWE-79\n    function_names: []\n    filenames:\n      - \"frontend/src/conversation/conversationApi.ts\"\n    classification: very promising\n\n  - headline: \"Exposed Sensitive Information to Unauthorized Users\"\n    analysis: |\n      In `application/core/settings.py`, the `.env` file is loaded which could potentially contain sensitive information like API keys and database credentials.\n      If this file is exposed or misconfigured, unauthorized users could gain access to these credentials.\n      Consider using a secure secrets management service to handle sensitive information.\n    cwe: CWE-312\n    function_names: []\n    filenames:\n      - \"application/core/settings.py\"\n    classification: slightly promising\n\n  - headline: \"Missing Authentication for Important Functions\"\n    analysis: |\n      Many routes like `/api/upload`, `/stream`, and `/api/answer` in `application/api/answer/routes.py`,\n      do not require authentication for accessing critical functionalities which can lead to unauthorized use.\n      Proper authentication mechanisms should be in place to protect these endpoints.\n    cwe: CWE-306\n    function_names: []\n    filenames:\n      - \"application/api/answer/routes.py\"\n    classification: very promising\n\n  - headline: \"Hardcoded Secrets in JavaScript Files\"\n    analysis: |\n      In `frontend/src/store.ts`, it appears that API Keys and other credentials are stored directly in the code.\n      This is insecure because anyone with access to the codebase can see these secrets, leading to potential misuse.\n    cwe: CWE-798\n    function_names: []\n    filenames:\n      - \"frontend/src/store.ts\"\n    classification: very promising\n```",
      "date": "2024-06-08T22:37:37.944283",
      "usage": {
        "prompt_tokens": 63770,
        "completion_tokens": 1012,
        "cost": 0.33403
      }
    }
  ],
  "leads": [
    {
      "headline": "Hardcoded API Key Found",
      "analysis": "In extensions/chatwoot/app.py, the chatwoot_token and docsgpt_key are hardcoded.\nThis can potentially expose your API keys to unauthorized users if your code\nbecomes public or is accessed by third parties. To mitigate this, consider using\nenvironment variables or a secure secrets management service to store and access your API keys.\n",
      "classification": "very promising",
      "cwe": "CWE-798",
      "function_names": [],
      "filenames": [
        "extensions/chatwoot/app.py"
      ]
    },
    {
      "headline": "No Input Validation: Shell Injection Risk",
      "analysis": "In setup.sh, there's no input validation when reading the user's choice. \nAn attacker who successfully gets arbitrary data executed could manipulate the shell \nand potentially run arbitrary system commands, leading to a command injection vulnerability.\nFor instance, validation is not performed on the choice variable.\n",
      "classification": "very promising",
      "cwe": "CWE-20",
      "function_names": [
        "prompt_user"
      ],
      "filenames": [
        "setup.sh"
      ]
    },
    {
      "headline": "Insecure File Download: Potential Supply Chain Attack",
      "analysis": "In setup.sh, the model is being downloaded from a URL (wget https://d3dg1063dc54p9.cloudfront.net/models/docsgpt-7b-f16.gguf) without any integrity checks.\nThis exposes the application to man-in-the-middle (MITM) attacks or other forms of supply chain attacks.\nThe integrity of downloaded files should be verified using hashes or signatures to ensure they haven't been tampered with.\n",
      "classification": "very promising",
      "cwe": "CWE-494",
      "function_names": [],
      "filenames": [
        "setup.sh"
      ]
    },
    {
      "headline": "Sensitive Information in Error Messages",
      "analysis": "The error handling in application/api/answer/routes.py prints the entire traceback,\nincluding potentially sensitive information, to the logs.\nThis information could be leveraged by an attacker to gain more insight into the internal workings of the application, \nwhich increases the attack surface.\n",
      "classification": "very promising",
      "cwe": "CWE-209",
      "function_names": [
        "api_answer"
      ],
      "filenames": [
        "application/api/answer/routes.py"
      ]
    },
    {
      "headline": "Potential SSRF Vulnerability",
      "analysis": "In application/worker.py, the requests.get method is used to fetch URLs provided by the user.\nThis could lead to SSRF if the user-controlled input is not properly validated or sanitized, allowing an attacker to \ncraft requests that can access internal services and potentially exploit them.\n",
      "classification": "slightly promising",
      "cwe": "CWE-918",
      "function_names": [
        "ingest_worker"
      ],
      "filenames": [
        "application/worker.py"
      ]
    },
    {
      "headline": "Cross-Site Scripting (XSS) Vulnerability",
      "analysis": "In frontend/src/conversation/conversationApi.ts, the responses from the API are directly rendered into the DOM on the client-side.\nIf the API response is not properly sanitized or encoded, it introduces a risk of XSS, where attackers can inject malicious scripts into the page.\n",
      "classification": "very promising",
      "cwe": "CWE-79",
      "function_names": [],
      "filenames": [
        "frontend/src/conversation/conversationApi.ts"
      ]
    },
    {
      "headline": "Exposed Sensitive Information to Unauthorized Users",
      "analysis": "In application/core/settings.py, the .env file is loaded which could potentially contain sensitive information like API keys and database credentials.\nIf this file is exposed or misconfigured, unauthorized users could gain access to these credentials.\nConsider using a secure secrets management service to handle sensitive information.\n",
      "classification": "slightly promising",
      "cwe": "CWE-312",
      "function_names": [],
      "filenames": [
        "application/core/settings.py"
      ]
    },
    {
      "headline": "Missing Authentication for Important Functions",
      "analysis": "Many routes like /api/upload, /stream, and /api/answer in application/api/answer/routes.py,\ndo not require authentication for accessing critical functionalities which can lead to unauthorized use.\nProper authentication mechanisms should be in place to protect these endpoints.\n",
      "classification": "very promising",
      "cwe": "CWE-306",
      "function_names": [],
      "filenames": [
        "application/api/answer/routes.py"
      ]
    },
    {
      "headline": "Hardcoded Secrets in JavaScript Files",
      "analysis": "In frontend/src/store.ts, it appears that API Keys and other credentials are stored directly in the code.\nThis is insecure because anyone with access to the codebase can see these secrets, leading to potential misuse.\n",
      "classification": "very promising",
      "cwe": "CWE-798",
      "function_names": [],
      "filenames": [
        "frontend/src/store.ts"
      ]
    }
  ],
  "scores": [
    {
      "stats": {
        "fn": 0,
        "tp": 1,
        "fp": 6
      },
      "mapping": {
        "5": "CVE-2024-31451"
      },
      "vuln_dates": {
        "CVE-2024-31451": "2024-04-16T15:15:36"
      },
      "scoring_model": "gpt-4o-2024-05-13",
      "type": "llm",
      "instruction_template_hash": "8998f09cf57fca8a6e03"
    }
  ],
  "instruction_template_hash": "10c0163db4740318a544",
  "version": "0.1.0"
}
