{
  "commit": "29dffcc3ed65322f24dd866babe915da7d9381d4",
  "repo_url": "https://github.com/jenkinsci/android-lint-plugin",
  "model": "gpt-4-turbo-2024-04-09",
  "chunk_hashes": [
    "c910a362f6c47561898f"
  ],
  "responses": [
    {
      "content": "```yaml\nleads:\n  - headline: Vulnerability due to usage of outdated error handling patterns\n    analysis: |\n      The codebase uses outdated error message generation patterns that could leak sensitive data through error messages. Specifically, without proper escaping or handling of user input in error messages, attackers could gain insights about the internal state of the application or its data structures.\n    cwe: CWE-209\n    function_names:\n      - LintParser\n      - createDeltaMessage\n    filenames:\n      - src/main/java/org/jenkinsci/plugins/android_lint/parser/LintParser.java\n      - src/main/java/org/jenkinsci/plugins/android_lint/SummaryGenerator.java\n    classification: slightly promising\n\n  - headline: Permissions settings on AndroidLint potentially set insecurely resulting in insecure file permissions\n    analysis: |\n      Permissions and important document handling are hard-coded which could lead to insecure configurations or improper restrictions, potentially exposing sensitive data if the default settings are not secure or if they are improperly documented and adjusted by maintainers.\n    cwe: CWE-732\n    function_names:\n      - LintPlugin\n    filenames:\n      - src/main/java/org/jenkinsci/plugins/android_lint/LintPlugin.java\n    classification: slightly promising\n\n  - headline: Uncontrolled Resource Consumption due to improper synchronization mechanism\n    analysis: |\n      Unrestricted or inadequately controlled usage of system resources can lead to denial of service (DoS) attacks. In the provided codebase, synchronization primitives are not adequately protecting shared resources, potentially allowing multiple threads to cause race conditions.\n    cwe: CWE-400\n    function_names:\n      - LintAnnotationsAggregator\n    filenames:\n      - src/main/java/org/jenkinsci/plugins/android_lint/LintAnnotationsAggregator.java\n    classification: slightly promising\n\n  - headline: Use of potentially broken or risky cryptographic algorithm indicating insecure data handling\n    analysis: |\n      The codebase might be employing outdated or weak cryptographic methods that do not ensure confidentiality and integrity of data in transit or at rest, as evidenced by antiquated or simplistic encoding mechanisms and possible absence of robust cryptographic implementations.\n    cwe: CWE-327\n    function_names:\n      - LintResult\n    filenames:\n      - src/main/java/org/jenkinsci/plugins/android_lint/LintResult.java\n    classification: slightly promising\n\n  - headline: Improperly controlled modification of dynamically-managed code resources might lead to unauthorized actions\n    analysis: |\n      Code paths in the plugin handling that modify or execute code dynamically could be manipulated by providing crafted inputs, potentially leading to execution of unintended actions or access to sensitive data.\n    cwe: CWE-913\n    function_names:\n      - start\n    filenames:\n      - src/main/java/org/jenkinsci/plugins/android_lint/LintPlugin.java\n    classification: slightly promising\n\n  - headline: Exposure of sensitive information through error messages\n    analysis: |\n      The implementation has several instances where error handling might leak information about the internal state or expose sensitive data directly to users, which could be exploited by an attacker to gain further information about the system or to proceed with more targeted attacks.\n    cwe: CWE-209\n    function_names:\n      - parse\n    filenames:\n      - src/main/java/org/jenkinsci/plugins/android_lint/parser/LintParser.java\n    classification: slightly promising\n```",
      "date": "2024-06-12T17:32:34.016631",
      "usage": {
        "prompt_tokens": 18027,
        "completion_tokens": 687,
        "cost": 0.20088
      }
    }
  ],
  "leads": [
    {
      "headline": "Vulnerability due to usage of outdated error handling patterns",
      "analysis": "The codebase uses outdated error message generation patterns that could leak sensitive data through error messages. Specifically, without proper escaping or handling of user input in error messages, attackers could gain insights about the internal state of the application or its data structures.\n",
      "classification": "slightly promising",
      "cwe": "CWE-209",
      "function_names": [
        "LintParser",
        "createDeltaMessage"
      ],
      "filenames": [
        "src/main/java/org/jenkinsci/plugins/android_lint/parser/LintParser.java",
        "src/main/java/org/jenkinsci/plugins/android_lint/SummaryGenerator.java"
      ]
    },
    {
      "headline": "Permissions settings on AndroidLint potentially set insecurely resulting in insecure file permissions",
      "analysis": "Permissions and important document handling are hard-coded which could lead to insecure configurations or improper restrictions, potentially exposing sensitive data if the default settings are not secure or if they are improperly documented and adjusted by maintainers.\n",
      "classification": "slightly promising",
      "cwe": "CWE-732",
      "function_names": [
        "LintPlugin"
      ],
      "filenames": [
        "src/main/java/org/jenkinsci/plugins/android_lint/LintPlugin.java"
      ]
    },
    {
      "headline": "Uncontrolled Resource Consumption due to improper synchronization mechanism",
      "analysis": "Unrestricted or inadequately controlled usage of system resources can lead to denial of service (DoS) attacks. In the provided codebase, synchronization primitives are not adequately protecting shared resources, potentially allowing multiple threads to cause race conditions.\n",
      "classification": "slightly promising",
      "cwe": "CWE-400",
      "function_names": [
        "LintAnnotationsAggregator"
      ],
      "filenames": [
        "src/main/java/org/jenkinsci/plugins/android_lint/LintAnnotationsAggregator.java"
      ]
    },
    {
      "headline": "Use of potentially broken or risky cryptographic algorithm indicating insecure data handling",
      "analysis": "The codebase might be employing outdated or weak cryptographic methods that do not ensure confidentiality and integrity of data in transit or at rest, as evidenced by antiquated or simplistic encoding mechanisms and possible absence of robust cryptographic implementations.\n",
      "classification": "slightly promising",
      "cwe": "CWE-327",
      "function_names": [
        "LintResult"
      ],
      "filenames": [
        "src/main/java/org/jenkinsci/plugins/android_lint/LintResult.java"
      ]
    },
    {
      "headline": "Improperly controlled modification of dynamically-managed code resources might lead to unauthorized actions",
      "analysis": "Code paths in the plugin handling that modify or execute code dynamically could be manipulated by providing crafted inputs, potentially leading to execution of unintended actions or access to sensitive data.\n",
      "classification": "slightly promising",
      "cwe": "CWE-913",
      "function_names": [
        "start"
      ],
      "filenames": [
        "src/main/java/org/jenkinsci/plugins/android_lint/LintPlugin.java"
      ]
    },
    {
      "headline": "Exposure of sensitive information through error messages",
      "analysis": "The implementation has several instances where error handling might leak information about the internal state or expose sensitive data directly to users, which could be exploited by an attacker to gain further information about the system or to proceed with more targeted attacks.\n",
      "classification": "slightly promising",
      "cwe": "CWE-209",
      "function_names": [
        "parse"
      ],
      "filenames": [
        "src/main/java/org/jenkinsci/plugins/android_lint/parser/LintParser.java"
      ]
    }
  ],
  "scores": [
    {
      "stats": {
        "fn": 2,
        "tp": 0,
        "fp": 0
      },
      "mapping": {},
      "vuln_dates": {
        "CVE-2020-2262": "2020-09-16T14:15:13",
        "CVE-2018-1000055": "2018-02-09T23:29:01"
      },
      "scoring_model": "claude-3-opus-20240229",
      "type": "llm",
      "instruction_template_hash": "245ace12b6361954d0a2"
    }
  ],
  "instruction_template_hash": "10c0163db4740318a544",
  "version": "0.1.0"
}
