{
  "commit": "0d6592f5db6c86c11cf95799893cb0de81dc6636",
  "repo_url": "https://github.com/jenkinsci/contrast-continuous-application-security-plugin",
  "model": "claude-3-sonnet-20240229",
  "chunk_hashes": [
    "9bd18b3af0e852466c25"
  ],
  "responses": [
    {
      "content": "```yaml\nleads:\n  - headline: Improper Input Validation\n    analysis: |\n      The code may be vulnerable to improper input validation, which could lead to various security issues such as code injection, buffer overflows, or denial of service attacks. Proper input validation is crucial to ensure that user-supplied data is sanitized and checked for malicious content before processing.\n    cwe: CWE-20\n    function_names:\n      - performanceWrap\n    filenames:\n      - src/test/java/com/aspectsecurity/contrast/contrastjenkins/VulnerabilityTrendRecorderTest.java\n    classification: very promising\n\n  - headline: Code Injection\n    analysis: |\n      The code may be vulnerable to code injection attacks, which occur when untrusted input is passed to an interpreter as part of a command or query. This could allow an attacker to execute arbitrary code on the system, leading to a complete system compromise. Proper input validation and sanitization are necessary to mitigate this vulnerability.\n    cwe: CWE-94\n    function_names:\n      - performanceWrap\n    filenames:\n      - src/test/java/com/aspectsecurity/contrast/contrastjenkins/VulnerabilityTrendRecorderTest.java\n    classification: very promising\n\n  - headline: Path Traversal\n    analysis: |\n      The code may be vulnerable to path traversal attacks, which allow an attacker to access files and directories outside the intended directory. This vulnerability could lead to unauthorized file disclosure or modification. The code should properly validate and sanitize user input to prevent path traversal attacks.\n    cwe: CWE-22\n    function_names:\n      - buildResult\n    filenames:\n      - src/main/java/com/aspectsecurity/contrast/contrastjenkins/VulnerabilityTrendRecorder.java\n    classification: very promising\n\n  - headline: Improper Certificate Validation\n    analysis: |\n      The code may not be properly validating SSL/TLS certificates when establishing secure connections. This could allow an attacker to perform man-in-the-middle attacks or impersonate trusted entities. Proper certificate validation should be implemented to ensure the authenticity and integrity of the communication channel.\n    cwe: CWE-295\n    function_names:\n      - createSDK\n    filenames:\n      - src/main/java/com/aspectsecurity/contrast/contrastjenkins/VulnerabilityTrendHelper.java\n    classification: very promising\n\n  - headline: Use of Hard-coded Credentials\n    analysis: |\n      The code may be using hard-coded credentials, such as usernames and passwords, which could compromise the system's security if the credentials are discovered. Hard-coded credentials should be avoided, and proper credential management practices should be implemented, such as using secure credential stores or environment variables.\n    cwe: CWE-798\n    function_names:\n      - run\n    filenames:\n      - src/main/java/com/aspectsecurity/contrast/contrastjenkins/ContrastAgentStep.java\n    classification: very promising\n\n  - headline: Improper Authentication\n    analysis: |\n      The code may have improper authentication mechanisms, which could allow unauthorized access to sensitive data or functionality. Proper authentication measures, such as strong password policies, multi-factor authentication, and session management, should be implemented to mitigate this risk.\n    cwe: CWE-287\n    function_names:\n      - doTestTeamServerConnection\n    filenames:\n      - src/main/java/com/aspectsecurity/contrast/contrastjenkins/ContrastPluginConfig.java\n    classification: very promising\n\n  - headline: Insecure Cryptographic Storage\n    analysis: |\n      The code may be storing sensitive data, such as passwords or encryption keys, in an insecure manner, making them vulnerable to unauthorized access or tampering. Proper encryption and secure storage mechanisms should be implemented to protect sensitive data at rest.\n    cwe: CWE-312\n    function_names:\n      - getSecretApiKey\n      - getSecretServiceKey\n    filenames:\n      - src/main/java/com/aspectsecurity/contrast/contrastjenkins/TeamServerProfile.java\n    classification: very promising\n\n  - headline: Cleartext Transmission of Sensitive Information\n    analysis: |\n      The code may be transmitting sensitive information, such as credentials or personal data, over an unencrypted channel, making it vulnerable to interception and unauthorized access. Sensitive data should be encrypted in transit using secure protocols like HTTPS to mitigate this risk.\n    cwe: CWE-319\n    function_names:\n      - createSDK\n    filenames:\n      - src/main/java/com/aspectsecurity/contrast/contrastjenkins/VulnerabilityTrendHelper.java\n    classification: very promising\n\n  - headline: Improper Access Control\n    analysis: |\n      The code may have improper access control mechanisms, allowing unauthorized users to access sensitive data or functionality. Proper access control measures, such as role-based access control (RBAC) and principle of least privilege, should be implemented to mitigate this risk.\n    cwe: CWE-862\n    function_names:\n      - newInstance\n    filenames:\n      - src/main/java/com/aspectsecurity/contrast/contrastjenkins/VulnerabilityTrendRecorder.java\n    classification: very promising\n\n  - headline: Insecure Deserialization\n    analysis: |\n      The code may be vulnerable to insecure deserialization attacks, which could allow an attacker to execute arbitrary code or tamper with the application's state. Deserialization of untrusted data should be avoided, or proper validation and sanitization should be implemented to mitigate this risk.\n    cwe: CWE-502\n    function_names: []\n    filenames: []\n    classification: slightly promising\n```\n\nThe analysis covers various security vulnerabilities that may be present in the codebase, including improper input validation, code injection, path traversal, improper certificate validation, use of hard-coded credentials, improper authentication, insecure cryptographic storage, cleartext transmission of sensitive information, improper access control, and insecure deserialization.\n\nThe analysis provides a description of each vulnerability, the CWE (Common Weakness Enumeration) ID associated with the vulnerability, the function names and filenames where the vulnerability may be present, and a classification of the vulnerability's severity (very promising or slightly promising).\n\nIt's important to note that this analysis is based on the provided codebase and may not be exhaustive. Further manual code review and testing should be performed to identify and mitigate any potential security vulnerabilities.",
      "date": "2024-06-12T18:10:38.984864",
      "usage": {
        "prompt_tokens": 58988,
        "completion_tokens": 1551,
        "cost": 0.200229
      }
    }
  ],
  "leads": [
    {
      "headline": "Improper Input Validation",
      "analysis": "The code may be vulnerable to improper input validation, which could lead to various security issues such as code injection, buffer overflows, or denial of service attacks. Proper input validation is crucial to ensure that user-supplied data is sanitized and checked for malicious content before processing.\n",
      "classification": "very promising",
      "cwe": "CWE-20",
      "function_names": [
        "performanceWrap"
      ],
      "filenames": [
        "src/test/java/com/aspectsecurity/contrast/contrastjenkins/VulnerabilityTrendRecorderTest.java"
      ]
    },
    {
      "headline": "Code Injection",
      "analysis": "The code may be vulnerable to code injection attacks, which occur when untrusted input is passed to an interpreter as part of a command or query. This could allow an attacker to execute arbitrary code on the system, leading to a complete system compromise. Proper input validation and sanitization are necessary to mitigate this vulnerability.\n",
      "classification": "very promising",
      "cwe": "CWE-94",
      "function_names": [
        "performanceWrap"
      ],
      "filenames": [
        "src/test/java/com/aspectsecurity/contrast/contrastjenkins/VulnerabilityTrendRecorderTest.java"
      ]
    },
    {
      "headline": "Path Traversal",
      "analysis": "The code may be vulnerable to path traversal attacks, which allow an attacker to access files and directories outside the intended directory. This vulnerability could lead to unauthorized file disclosure or modification. The code should properly validate and sanitize user input to prevent path traversal attacks.\n",
      "classification": "very promising",
      "cwe": "CWE-22",
      "function_names": [
        "buildResult"
      ],
      "filenames": [
        "src/main/java/com/aspectsecurity/contrast/contrastjenkins/VulnerabilityTrendRecorder.java"
      ]
    },
    {
      "headline": "Improper Certificate Validation",
      "analysis": "The code may not be properly validating SSL/TLS certificates when establishing secure connections. This could allow an attacker to perform man-in-the-middle attacks or impersonate trusted entities. Proper certificate validation should be implemented to ensure the authenticity and integrity of the communication channel.\n",
      "classification": "very promising",
      "cwe": "CWE-295",
      "function_names": [
        "createSDK"
      ],
      "filenames": [
        "src/main/java/com/aspectsecurity/contrast/contrastjenkins/VulnerabilityTrendHelper.java"
      ]
    },
    {
      "headline": "Use of Hard-coded Credentials",
      "analysis": "The code may be using hard-coded credentials, such as usernames and passwords, which could compromise the system's security if the credentials are discovered. Hard-coded credentials should be avoided, and proper credential management practices should be implemented, such as using secure credential stores or environment variables.\n",
      "classification": "very promising",
      "cwe": "CWE-798",
      "function_names": [
        "run"
      ],
      "filenames": [
        "src/main/java/com/aspectsecurity/contrast/contrastjenkins/ContrastAgentStep.java"
      ]
    },
    {
      "headline": "Improper Authentication",
      "analysis": "The code may have improper authentication mechanisms, which could allow unauthorized access to sensitive data or functionality. Proper authentication measures, such as strong password policies, multi-factor authentication, and session management, should be implemented to mitigate this risk.\n",
      "classification": "very promising",
      "cwe": "CWE-287",
      "function_names": [
        "doTestTeamServerConnection"
      ],
      "filenames": [
        "src/main/java/com/aspectsecurity/contrast/contrastjenkins/ContrastPluginConfig.java"
      ]
    },
    {
      "headline": "Insecure Cryptographic Storage",
      "analysis": "The code may be storing sensitive data, such as passwords or encryption keys, in an insecure manner, making them vulnerable to unauthorized access or tampering. Proper encryption and secure storage mechanisms should be implemented to protect sensitive data at rest.\n",
      "classification": "very promising",
      "cwe": "CWE-312",
      "function_names": [
        "getSecretApiKey",
        "getSecretServiceKey"
      ],
      "filenames": [
        "src/main/java/com/aspectsecurity/contrast/contrastjenkins/TeamServerProfile.java"
      ]
    },
    {
      "headline": "Cleartext Transmission of Sensitive Information",
      "analysis": "The code may be transmitting sensitive information, such as credentials or personal data, over an unencrypted channel, making it vulnerable to interception and unauthorized access. Sensitive data should be encrypted in transit using secure protocols like HTTPS to mitigate this risk.\n",
      "classification": "very promising",
      "cwe": "CWE-319",
      "function_names": [
        "createSDK"
      ],
      "filenames": [
        "src/main/java/com/aspectsecurity/contrast/contrastjenkins/VulnerabilityTrendHelper.java"
      ]
    },
    {
      "headline": "Improper Access Control",
      "analysis": "The code may have improper access control mechanisms, allowing unauthorized users to access sensitive data or functionality. Proper access control measures, such as role-based access control (RBAC) and principle of least privilege, should be implemented to mitigate this risk.\n",
      "classification": "very promising",
      "cwe": "CWE-862",
      "function_names": [
        "newInstance"
      ],
      "filenames": [
        "src/main/java/com/aspectsecurity/contrast/contrastjenkins/VulnerabilityTrendRecorder.java"
      ]
    },
    {
      "headline": "Insecure Deserialization",
      "analysis": "The code may be vulnerable to insecure deserialization attacks, which could allow an attacker to execute arbitrary code or tamper with the application's state. Deserialization of untrusted data should be avoided, or proper validation and sanitization should be implemented to mitigate this risk.\n",
      "classification": "slightly promising",
      "cwe": "CWE-502",
      "function_names": [],
      "filenames": []
    }
  ],
  "scores": [
    {
      "stats": {
        "fn": 1,
        "tp": 0,
        "fp": 9
      },
      "mapping": {},
      "vuln_dates": {
        "CVE-2022-43420": "2022-10-19T16:15:11"
      },
      "scoring_model": "claude-3-opus-20240229",
      "type": "llm",
      "instruction_template_hash": "245ace12b6361954d0a2"
    }
  ],
  "instruction_template_hash": "10c0163db4740318a544",
  "version": "0.1.0"
}
