{
  "commit": "274d161185ee1a17229e780fd78701c7bd03e884",
  "repo_url": "https://github.com/jenkinsci/audit-trail-plugin",
  "model": "claude-3-sonnet-20240229",
  "chunk_hashes": [
    "eb37050a5a13dac3a48e"
  ],
  "responses": [
    {
      "content": "```yaml\nleads:\n  - headline: Potential path traversal vulnerability\n    analysis: |\n      The `AuditTrailFilter` class retrieves the path of the request using `req.getPathInfo()`. In some containers, this value can be unexpectedly null, which leads the code to construct the path using `req.getRequestURI().substring(req.getContextPath().length())`. This could potentially allow an attacker to traverse paths outside of the application's context by crafting a malicious request URI.\n    cwe: CWE-22\n    function_names:\n      - hudson.plugins.audit_trail.AuditTrailFilter.doFilter\n    filenames:\n      - src/main/java/hudson/plugins/audit_trail/AuditTrailFilter.java\n    classification: very promising\n\n  - headline: Potential lack of input validation\n    analysis: |\n      The `AuditTrailPlugin` class allows setting a regular expression pattern for logging requests via the `setPattern` method. However, there appears to be no validation or sanitization of the input pattern before compiling it into a `Pattern` object. An attacker could potentially supply a malicious regular expression that causes a denial of service or other unintended behavior.\n    cwe: CWE-20\n    function_names:\n      - hudson.plugins.audit_trail.AuditTrailPlugin.setPattern\n    filenames:\n      - src/main/java/hudson/plugins/audit_trail/AuditTrailPlugin.java\n    classification: very promising\n\n  - headline: Potential improper validation of file path\n    analysis: |\n      The `LogFileAuditLogger` class takes a file path as input in its constructor and attempts to create a `FileHandler` with that path. If the parent directories of the specified path do not exist, the code attempts to create them using `File.mkdirs()`. However, there is no validation or sanitization of the input file path before this operation, which could potentially allow directory traversal or creation of files in unintended locations.\n    cwe: CWE-22\n    function_names:\n      - hudson.plugins.audit_trail.LogFileAuditLogger.configure\n    filenames:\n      - src/main/java/hudson/plugins/audit_trail/LogFileAuditLogger.java\n    classification: very promising\n\n  - headline: Potential improper resource cleanup\n    analysis: |\n      The `LogFileAuditLogger` class creates a `FileHandler` object to log to a file, but it does not appear to properly close or release this resource when the plugin is stopped or unloaded. This could potentially lead to resource leaks or other issues if the plugin is frequently loaded and unloaded.\n    cwe: CWE-404\n    function_names:\n      - hudson.plugins.audit_trail.LogFileAuditLogger.cleanUp\n    filenames:\n      - src/main/java/hudson/plugins/audit_trail/LogFileAuditLogger.java\n    classification: slightly promising\n\n  - headline: Potential improper handling of exceptions\n    analysis: |\n      The `LogFileAuditLogger` class attempts to create a `FileHandler` object to log to a file. If an `IOException` occurs during this process, the exception is logged at a severe level, but the `handler` field is not set to null or any other sentinel value. This could potentially lead to null pointer exceptions or other issues when attempting to use the `handler` field later on.\n    cwe: CWE-755\n    function_names:\n      - hudson.plugins.audit_trail.LogFileAuditLogger.configure\n    filenames:\n      - src/main/java/hudson/plugins/audit_trail/LogFileAuditLogger.java\n    classification: slightly promising\n\n  - headline: Potential null pointer dereference\n    analysis: |\n      The `ConsoleAuditLogger` class dereferences the `out` field without first checking if it is null. This could potentially lead to null pointer exceptions if the `out` field is not properly initialized or if the `configure` method fails to set it correctly.\n    cwe: CWE-476\n    function_names:\n      - hudson.plugins.audit_trail.ConsoleAuditLogger.log\n    filenames:\n      - src/main/java/hudson/plugins/audit_trail/ConsoleAuditLogger.java\n    classification: slightly promising\n\n  - headline: Potential improper initialization of resources\n    analysis: |\n      The `ConsoleAuditLogger` class appears to initialize its `out` and `sdf` fields in the `configure` method, which is called from the constructor. However, if the `readResolve` method is called (e.g., after deserialization), it calls `configure` again, which could potentially overwrite the previously initialized values. This could lead to unexpected behavior or resource leaks if the resources are not properly cleaned up or reinitialized.\n    cwe: CWE-665\n    function_names:\n      - hudson.plugins.audit_trail.ConsoleAuditLogger.readResolve\n    filenames:\n      - src/main/java/hudson/plugins/audit_trail/ConsoleAuditLogger.java\n    classification: slightly promising\n\n  - headline: Potential improper synchronization\n    analysis: |\n      The `ConsoleAuditLogger` class uses a synchronized block to protect access to the `out` field, which is shared between multiple threads. However, the synchronization is only performed on the `output` field, which is an enum value. This could potentially lead to race conditions or other synchronization issues if the `out` field is accessed or modified by multiple threads concurrently.\n    cwe: CWE-662\n    function_names:\n      - hudson.plugins.audit_trail.ConsoleAuditLogger.log\n    filenames:\n      - src/main/java/hudson/plugins/audit_trail/ConsoleAuditLogger.java\n    classification: slightly promising\n\n  - headline: Potential improper validation of array index\n    analysis: |\n      The `AuditTrailFilter` class retrieves the queue item ID from the request URI using `Integer.parseInt(uri.substring(12, uri.indexOf('/', 13)))`. This assumes that the URI follows a specific format and that the substring operation will not produce an out-of-bounds index. However, there does not appear to be any validation or sanitization of the input URI to ensure that these assumptions hold true, which could potentially lead to array index out of bounds exceptions or other unintended behavior.\n    cwe: CWE-129\n    function_names:\n      - hudson.plugins.audit_trail.AuditTrailFilter.doFilter\n    filenames:\n      - src/main/java/hudson/plugins/audit_trail/AuditTrailFilter.java\n    classification: slightly promising\n\n  - headline: Potential improper handling of case sensitivity\n    analysis: |\n      The `SyslogAuditLogger` class appears to assume that the `facility` and `messageFormat` input strings are case-insensitive when converting them to enum values using `Facility.fromLabel` and `MessageFormat.valueOf`. However, if the input strings do not match the expected case, this could potentially lead to unexpected behavior or errors.\n    cwe: CWE-178\n    function_names:\n      - hudson.plugins.audit_trail.SyslogAuditLogger.<init>\n    filenames:\n      - src/main/java/hudson/plugins/audit_trail/SyslogAuditLogger.java\n    classification: not promising\n\n```",
      "date": "2024-06-12T17:52:53.966947",
      "usage": {
        "prompt_tokens": 19114,
        "completion_tokens": 1757,
        "cost": 0.083697
      }
    }
  ],
  "leads": [
    {
      "headline": "Potential path traversal vulnerability",
      "analysis": "The AuditTrailFilter class retrieves the path of the request using req.getPathInfo(). In some containers, this value can be unexpectedly null, which leads the code to construct the path using req.getRequestURI().substring(req.getContextPath().length()). This could potentially allow an attacker to traverse paths outside of the application's context by crafting a malicious request URI.\n",
      "classification": "very promising",
      "cwe": "CWE-22",
      "function_names": [
        "hudson.plugins.audit_trail.AuditTrailFilter.doFilter"
      ],
      "filenames": [
        "src/main/java/hudson/plugins/audit_trail/AuditTrailFilter.java"
      ]
    },
    {
      "headline": "Potential lack of input validation",
      "analysis": "The AuditTrailPlugin class allows setting a regular expression pattern for logging requests via the setPattern method. However, there appears to be no validation or sanitization of the input pattern before compiling it into a Pattern object. An attacker could potentially supply a malicious regular expression that causes a denial of service or other unintended behavior.\n",
      "classification": "very promising",
      "cwe": "CWE-20",
      "function_names": [
        "hudson.plugins.audit_trail.AuditTrailPlugin.setPattern"
      ],
      "filenames": [
        "src/main/java/hudson/plugins/audit_trail/AuditTrailPlugin.java"
      ]
    },
    {
      "headline": "Potential improper validation of file path",
      "analysis": "The LogFileAuditLogger class takes a file path as input in its constructor and attempts to create a FileHandler with that path. If the parent directories of the specified path do not exist, the code attempts to create them using File.mkdirs(). However, there is no validation or sanitization of the input file path before this operation, which could potentially allow directory traversal or creation of files in unintended locations.\n",
      "classification": "very promising",
      "cwe": "CWE-22",
      "function_names": [
        "hudson.plugins.audit_trail.LogFileAuditLogger.configure"
      ],
      "filenames": [
        "src/main/java/hudson/plugins/audit_trail/LogFileAuditLogger.java"
      ]
    },
    {
      "headline": "Potential improper resource cleanup",
      "analysis": "The LogFileAuditLogger class creates a FileHandler object to log to a file, but it does not appear to properly close or release this resource when the plugin is stopped or unloaded. This could potentially lead to resource leaks or other issues if the plugin is frequently loaded and unloaded.\n",
      "classification": "slightly promising",
      "cwe": "CWE-404",
      "function_names": [
        "hudson.plugins.audit_trail.LogFileAuditLogger.cleanUp"
      ],
      "filenames": [
        "src/main/java/hudson/plugins/audit_trail/LogFileAuditLogger.java"
      ]
    },
    {
      "headline": "Potential improper handling of exceptions",
      "analysis": "The LogFileAuditLogger class attempts to create a FileHandler object to log to a file. If an IOException occurs during this process, the exception is logged at a severe level, but the handler field is not set to null or any other sentinel value. This could potentially lead to null pointer exceptions or other issues when attempting to use the handler field later on.\n",
      "classification": "slightly promising",
      "cwe": "CWE-755",
      "function_names": [
        "hudson.plugins.audit_trail.LogFileAuditLogger.configure"
      ],
      "filenames": [
        "src/main/java/hudson/plugins/audit_trail/LogFileAuditLogger.java"
      ]
    },
    {
      "headline": "Potential null pointer dereference",
      "analysis": "The ConsoleAuditLogger class dereferences the out field without first checking if it is null. This could potentially lead to null pointer exceptions if the out field is not properly initialized or if the configure method fails to set it correctly.\n",
      "classification": "slightly promising",
      "cwe": "CWE-476",
      "function_names": [
        "hudson.plugins.audit_trail.ConsoleAuditLogger.log"
      ],
      "filenames": [
        "src/main/java/hudson/plugins/audit_trail/ConsoleAuditLogger.java"
      ]
    },
    {
      "headline": "Potential improper initialization of resources",
      "analysis": "The ConsoleAuditLogger class appears to initialize its out and sdf fields in the configure method, which is called from the constructor. However, if the readResolve method is called (e.g., after deserialization), it calls configure again, which could potentially overwrite the previously initialized values. This could lead to unexpected behavior or resource leaks if the resources are not properly cleaned up or reinitialized.\n",
      "classification": "slightly promising",
      "cwe": "CWE-665",
      "function_names": [
        "hudson.plugins.audit_trail.ConsoleAuditLogger.readResolve"
      ],
      "filenames": [
        "src/main/java/hudson/plugins/audit_trail/ConsoleAuditLogger.java"
      ]
    },
    {
      "headline": "Potential improper synchronization",
      "analysis": "The ConsoleAuditLogger class uses a synchronized block to protect access to the out field, which is shared between multiple threads. However, the synchronization is only performed on the output field, which is an enum value. This could potentially lead to race conditions or other synchronization issues if the out field is accessed or modified by multiple threads concurrently.\n",
      "classification": "slightly promising",
      "cwe": "CWE-662",
      "function_names": [
        "hudson.plugins.audit_trail.ConsoleAuditLogger.log"
      ],
      "filenames": [
        "src/main/java/hudson/plugins/audit_trail/ConsoleAuditLogger.java"
      ]
    },
    {
      "headline": "Potential improper validation of array index",
      "analysis": "The AuditTrailFilter class retrieves the queue item ID from the request URI using Integer.parseInt(uri.substring(12, uri.indexOf('/', 13))). This assumes that the URI follows a specific format and that the substring operation will not produce an out-of-bounds index. However, there does not appear to be any validation or sanitization of the input URI to ensure that these assumptions hold true, which could potentially lead to array index out of bounds exceptions or other unintended behavior.\n",
      "classification": "slightly promising",
      "cwe": "CWE-129",
      "function_names": [
        "hudson.plugins.audit_trail.AuditTrailFilter.doFilter"
      ],
      "filenames": [
        "src/main/java/hudson/plugins/audit_trail/AuditTrailFilter.java"
      ]
    },
    {
      "headline": "Potential improper handling of case sensitivity",
      "analysis": "The SyslogAuditLogger class appears to assume that the facility and messageFormat input strings are case-insensitive when converting them to enum values using Facility.fromLabel and MessageFormat.valueOf. However, if the input strings do not match the expected case, this could potentially lead to unexpected behavior or errors.\n",
      "classification": "not promising",
      "cwe": "CWE-178",
      "function_names": [
        "hudson.plugins.audit_trail.SyslogAuditLogger.<init>"
      ],
      "filenames": [
        "src/main/java/hudson/plugins/audit_trail/SyslogAuditLogger.java"
      ]
    }
  ],
  "scores": [
    {
      "stats": {
        "fn": 3,
        "tp": 0,
        "fp": 3
      },
      "mapping": {},
      "vuln_dates": {
        "CVE-2020-2140": "2020-03-09T16:15:13",
        "CVE-2020-2288": "2020-10-08T13:15:11",
        "CVE-2020-2287": "2020-10-08T13:15:11"
      },
      "scoring_model": "claude-3-opus-20240229",
      "type": "llm",
      "instruction_template_hash": "245ace12b6361954d0a2"
    }
  ],
  "instruction_template_hash": "10c0163db4740318a544",
  "version": "0.1.0"
}
