{
  "commit": "5cb6f414e6fac68038533b0f36814f765aa971de",
  "repo_url": "https://github.com/a-schild/jave2",
  "model": "claude-3-5-sonnet-20240620",
  "chunk_hashes": [
    "6c9dc8acb1d4fc2735b8"
  ],
  "responses": [
    {
      "content": "```yaml\nleads:\n  - headline: Potential command injection vulnerability\n    analysis: |\n      The EncoderException class allows arbitrary exception messages to be set, which are then displayed to the user. This could potentially allow command injection if untrusted input is used to construct error messages. A malicious user could potentially inject commands that would be executed when the error message is displayed.\n    cwe: CWE-77\n    function_names:\n      - EncoderException\n    filenames:\n      - jave-core/src/main/java/ws/schild/jave/EncoderException.java\n    classification: slightly promising\n\n  - headline: Unsafe resource loading\n    analysis: |\n      The DefaultFFMPEGLocator class loads and executes an ffmpeg binary from the classpath resources. If an attacker is able to modify the classpath or replace the ffmpeg binary, they could potentially execute arbitrary code. The code does not verify the integrity or authenticity of the loaded binary before executing it.\n    cwe: CWE-494\n    function_names:\n      - DefaultFFMPEGLocator\n      - copyFile\n    filenames:\n      - jave-core/src/main/java/ws/schild/jave/process/ffmpeg/DefaultFFMPEGLocator.java\n    classification: slightly promising\n\n  - headline: Potential XML external entity injection\n    analysis: |\n      The MultimediaObject class parses XML metadata from media files without explicitly disabling XML external entity processing. This could potentially allow XXE attacks if parsing untrusted input. An attacker could craft a malicious media file with XXE payloads in the metadata to exploit this.\n    cwe: CWE-611\n    function_names:\n      - parseMultimediaInfo  \n    filenames:\n      - jave-core/src/main/java/ws/schild/jave/MultimediaObject.java\n    classification: slightly promising\n\n  - headline: Unsafe temporary file creation\n    analysis: |\n      The DefaultFFMPEGLocator class creates temporary files in a predictable location (java.io.tmpdir) without proper access controls. An attacker with local access could potentially replace these files to execute arbitrary code. The code does not use secure APIs like Files.createTempFile() to create temporary files safely.\n    cwe: CWE-377\n    function_names:\n      - DefaultFFMPEGLocator\n    filenames:\n      - jave-core/src/main/java/ws/schild/jave/process/ffmpeg/DefaultFFMPEGLocator.java  \n    classification: slightly promising\n\n  - headline: Potential unvalidated input passed to file operations\n    analysis: |\n      Several classes like Encoder and MultimediaObject operate on files specified by user input without validating the paths. This could potentially allow path traversal attacks if a malicious user provides a crafted file path. The code should validate and sanitize file paths before using them in file operations.\n    cwe: CWE-22\n    function_names:\n      - Encoder.encode\n      - MultimediaObject.getInfo\n    filenames:\n      - jave-core/src/main/java/ws/schild/jave/Encoder.java\n      - jave-core/src/main/java/ws/schild/jave/MultimediaObject.java\n    classification: slightly promising\n```",
      "date": "2024-07-07T20:32:41.458274",
      "usage": {
        "prompt_tokens": 102101,
        "completion_tokens": 791,
        "cost": 0.318168
      }
    }
  ],
  "leads": [
    {
      "headline": "Potential command injection vulnerability",
      "analysis": "The EncoderException class allows arbitrary exception messages to be set, which are then displayed to the user. This could potentially allow command injection if untrusted input is used to construct error messages. A malicious user could potentially inject commands that would be executed when the error message is displayed.\n",
      "classification": "slightly promising",
      "cwe": "CWE-77",
      "function_names": [
        "EncoderException"
      ],
      "filenames": [
        "jave-core/src/main/java/ws/schild/jave/EncoderException.java"
      ]
    },
    {
      "headline": "Unsafe resource loading",
      "analysis": "The DefaultFFMPEGLocator class loads and executes an ffmpeg binary from the classpath resources. If an attacker is able to modify the classpath or replace the ffmpeg binary, they could potentially execute arbitrary code. The code does not verify the integrity or authenticity of the loaded binary before executing it.\n",
      "classification": "slightly promising",
      "cwe": "CWE-494",
      "function_names": [
        "DefaultFFMPEGLocator",
        "copyFile"
      ],
      "filenames": [
        "jave-core/src/main/java/ws/schild/jave/process/ffmpeg/DefaultFFMPEGLocator.java"
      ]
    },
    {
      "headline": "Potential XML external entity injection",
      "analysis": "The MultimediaObject class parses XML metadata from media files without explicitly disabling XML external entity processing. This could potentially allow XXE attacks if parsing untrusted input. An attacker could craft a malicious media file with XXE payloads in the metadata to exploit this.\n",
      "classification": "slightly promising",
      "cwe": "CWE-611",
      "function_names": [
        "parseMultimediaInfo"
      ],
      "filenames": [
        "jave-core/src/main/java/ws/schild/jave/MultimediaObject.java"
      ]
    },
    {
      "headline": "Unsafe temporary file creation",
      "analysis": "The DefaultFFMPEGLocator class creates temporary files in a predictable location (java.io.tmpdir) without proper access controls. An attacker with local access could potentially replace these files to execute arbitrary code. The code does not use secure APIs like Files.createTempFile() to create temporary files safely.\n",
      "classification": "slightly promising",
      "cwe": "CWE-377",
      "function_names": [
        "DefaultFFMPEGLocator"
      ],
      "filenames": [
        "jave-core/src/main/java/ws/schild/jave/process/ffmpeg/DefaultFFMPEGLocator.java"
      ]
    },
    {
      "headline": "Potential unvalidated input passed to file operations",
      "analysis": "Several classes like Encoder and MultimediaObject operate on files specified by user input without validating the paths. This could potentially allow path traversal attacks if a malicious user provides a crafted file path. The code should validate and sanitize file paths before using them in file operations.\n",
      "classification": "slightly promising",
      "cwe": "CWE-22",
      "function_names": [
        "Encoder.encode",
        "MultimediaObject.getInfo"
      ],
      "filenames": [
        "jave-core/src/main/java/ws/schild/jave/Encoder.java",
        "jave-core/src/main/java/ws/schild/jave/MultimediaObject.java"
      ]
    }
  ],
  "scores": [
    {
      "stats": {
        "fn": 1,
        "tp": 0,
        "fp": 0
      },
      "mapping": {},
      "vuln_dates": {
        "CVE-2023-48909": "2024-01-12T09:15:44"
      },
      "scoring_model": "claude-3-5-sonnet-20240620",
      "type": "llm",
      "instruction_template_hash": "245ace12b6361954d0a2"
    }
  ],
  "instruction_template_hash": "10c0163db4740318a544",
  "version": "0.1.0"
}
