{
  "commit": "d1cf36c67c2aa0e76882a08a5cd878b3306e0671",
  "repo_url": "https://github.com/vantage6/vantage6-ui",
  "model": "gpt-4-turbo-2024-04-09",
  "chunk_hashes": [
    "ed70b5454075361027ed"
  ],
  "responses": [
    {
      "content": "```yaml\nleads:\n  - headline: \"Improper Handling of Password and MFA Code in Frontend Login Logic\"\n    analysis: |\n      During login, the AuthService instance within the LoginFormComponent stores the username, password, and potentially the multi-factor authentication (MFA) code. This data is held in memory and is not removed after use, leading to a potential exposure where other scripts or a memory dump could capture sensitive information. This mishandling increases the risks of credential leakage, posing a serious breach of security principles that dictate sensitive data should be handled securely and disposed of immediately after it is no longer needed.\n    cwe: CWE-316\n    function_names:\n      - ngOnInit\n      - onSubmit\n      - login\n    filenames:\n      - src/app/components/login/login/login.component.ts\n      - src/app/auth/services/auth.service.ts\n    classification: slightly promising\n\n  - headline: \"Storage of Sensitive Information Without Encryption\"\n    analysis: |\n      The system stores sensitive data unencrypted both in browser storage and potentially on the server side, highlighted by the management of user session information that includes tokens and user states. The absence of encryption mechanisms for this kind of sensitive data opens up potential vectors for attackers to exploit, such as accessing tokens or other session data to impersonate users or misuse their session states.\n    cwe: CWE-312\n    function_names:\n      - saveToken\n      - getToken\n      - getRefreshToken\n    filenames:\n      - src/app/services/common/token-storage.service.ts\n    classification: very promising\n\n  - headline: \"Insecure Direct Object References (IDOR) Vulnerability\"\n    analysis: |\n      The application appears to fetch and manipulate data based on ID values received from client-side inputs without proper server-side checks to validate whether the logged-in user is authorized to perform these actions. This lack of proper authorization checks can lead to unauthorized data access or manipulation, commonly referred to as Insecure Direct Object References (IDOR). The function implementations do not verify the ownership or privileged association between the agent (user or third-party) making the request and the target resources.\n    cwe: CWE-639\n    function_names:\n      - get\n      - get_base\n      - list\n    filenames:\n      - src/app/services/data/base-data.service.ts\n      - src/app/services/api/base-api.service.ts\n    classification: very promising\n\n  - headline: \"Exposure of Environment-Specific Secrets in Codebase\"\n    analysis: |\n      The project's codebase directly references environment-specific variables and paths such as API URLs and database connections, which may inadvertently expose sensitive information if the codebase is shared or exposed. This exposure suggests a lapse in secure configuration management practices and could help an attacker understand the infrastructure and design of the application, thereby structuring more targeted attacks.\n    cwe: CWE-200\n    function_names:\n      - get\n    filenames:\n      - src/environments/environment.prod.ts\n      - src/environments/environment.ts\n    classification: slightly promising\n\n  - headline: \"Use of Insecure and Outdated Angular Libraries\"\n    analysis: |\n      The project is built on Angular, and the codebase demonstrates usage patterns reliant on older or non-current versions of Angular libraries. Outdated libraries often contain unresolved security vulnerabilities that could be exploited by an attacker to compromise the application or its data. Keeping dependencies updated is a critical task in maintaining the security posture of any web-based application.\n    cwe: CWE-937\n    function_names:\n      - ngOnInit\n    filenames:\n      - src/app/components/login/login/mfa-code/mfa-code.component.ts\n    classification: slightly promising\n```",
      "date": "2024-06-09T15:21:50.479191",
      "usage": {
        "prompt_tokens": 111936,
        "completion_tokens": 742,
        "cost": 1.14162
      }
    }
  ],
  "leads": [
    {
      "headline": "Improper Handling of Password and MFA Code in Frontend Login Logic",
      "analysis": "During login, the AuthService instance within the LoginFormComponent stores the username, password, and potentially the multi-factor authentication (MFA) code. This data is held in memory and is not removed after use, leading to a potential exposure where other scripts or a memory dump could capture sensitive information. This mishandling increases the risks of credential leakage, posing a serious breach of security principles that dictate sensitive data should be handled securely and disposed of immediately after it is no longer needed.\n",
      "classification": "slightly promising",
      "cwe": "CWE-316",
      "function_names": [
        "ngOnInit",
        "onSubmit",
        "login"
      ],
      "filenames": [
        "src/app/components/login/login/login.component.ts",
        "src/app/auth/services/auth.service.ts"
      ]
    },
    {
      "headline": "Storage of Sensitive Information Without Encryption",
      "analysis": "The system stores sensitive data unencrypted both in browser storage and potentially on the server side, highlighted by the management of user session information that includes tokens and user states. The absence of encryption mechanisms for this kind of sensitive data opens up potential vectors for attackers to exploit, such as accessing tokens or other session data to impersonate users or misuse their session states.\n",
      "classification": "very promising",
      "cwe": "CWE-312",
      "function_names": [
        "saveToken",
        "getToken",
        "getRefreshToken"
      ],
      "filenames": [
        "src/app/services/common/token-storage.service.ts"
      ]
    },
    {
      "headline": "Insecure Direct Object References (IDOR) Vulnerability",
      "analysis": "The application appears to fetch and manipulate data based on ID values received from client-side inputs without proper server-side checks to validate whether the logged-in user is authorized to perform these actions. This lack of proper authorization checks can lead to unauthorized data access or manipulation, commonly referred to as Insecure Direct Object References (IDOR). The function implementations do not verify the ownership or privileged association between the agent (user or third-party) making the request and the target resources.\n",
      "classification": "very promising",
      "cwe": "CWE-639",
      "function_names": [
        "get",
        "get_base",
        "list"
      ],
      "filenames": [
        "src/app/services/data/base-data.service.ts",
        "src/app/services/api/base-api.service.ts"
      ]
    },
    {
      "headline": "Exposure of Environment-Specific Secrets in Codebase",
      "analysis": "The project's codebase directly references environment-specific variables and paths such as API URLs and database connections, which may inadvertently expose sensitive information if the codebase is shared or exposed. This exposure suggests a lapse in secure configuration management practices and could help an attacker understand the infrastructure and design of the application, thereby structuring more targeted attacks.\n",
      "classification": "slightly promising",
      "cwe": "CWE-200",
      "function_names": [
        "get"
      ],
      "filenames": [
        "src/environments/environment.prod.ts",
        "src/environments/environment.ts"
      ]
    },
    {
      "headline": "Use of Insecure and Outdated Angular Libraries",
      "analysis": "The project is built on Angular, and the codebase demonstrates usage patterns reliant on older or non-current versions of Angular libraries. Outdated libraries often contain unresolved security vulnerabilities that could be exploited by an attacker to compromise the application or its data. Keeping dependencies updated is a critical task in maintaining the security posture of any web-based application.\n",
      "classification": "slightly promising",
      "cwe": "CWE-937",
      "function_names": [
        "ngOnInit"
      ],
      "filenames": [
        "src/app/components/login/login/mfa-code/mfa-code.component.ts"
      ]
    }
  ],
  "scores": [
    {
      "stats": {
        "fn": 2,
        "tp": 0,
        "fp": 2
      },
      "mapping": {},
      "vuln_dates": {
        "CVE-2024-24562": "2024-03-14T19:15:49",
        "CVE-2024-22200": "2024-01-30T16:15:48"
      },
      "scoring_model": "gpt-4o-2024-05-13",
      "type": "llm",
      "instruction_template_hash": "8998f09cf57fca8a6e03"
    },
    {
      "stats": {
        "fn": 2,
        "tp": 0,
        "fp": 2
      },
      "mapping": {},
      "vuln_dates": {
        "CVE-2024-24562": "2024-03-14T19:15:49",
        "CVE-2024-22200": "2024-01-30T16:15:48"
      },
      "scoring_model": "claude-3-opus-20240229",
      "type": "llm",
      "instruction_template_hash": "245ace12b6361954d0a2"
    }
  ],
  "instruction_template_hash": "10c0163db4740318a544",
  "version": "0.1.0"
}
