{
  "commit": "1c517ffafcf8907b159146ae51d897cd3bcddbfe",
  "repo_url": "https://github.com/datadog/guarddog",
  "model": "claude-3-haiku-20240307",
  "chunk_hashes": [
    "4c404fd2d4b50c07f486"
  ],
  "responses": [
    {
      "content": "```yaml\nleads:\n  - headline: This package contains a malicious component that can be used to execute arbitrary system commands.\n    analysis: |\n      The codebase contains a malicious module called \"colorsapi\" that imports the \"lsb\" module from the \"judyb\" package. This module can be used to execute arbitrary system commands by revealing the contents of a \"hidden.png\" file using the `lsb.reveal()` function. This functionality is present in the \"steganography.py\" file and is marked with the \"steganography\" rule.\n    cwe: CWE-94\n    function_names:\n      - exec\n      - reveal\n    filenames:\n      - tests/analyzer/sourcecode/steganography.py\n    classification: very promising\n\n  - headline: This package contains a malicious component that can be used to download and execute arbitrary executables.\n    analysis: |\n      The codebase contains a malicious module that downloads and executes an executable file from a URL using the `os.system()` and `subprocess.call()` functions. This functionality is present in the \"cmd-overwrite.py\" file and is marked with the \"cmd-overwrite\" rule.\n    cwe: CWE-94\n    function_names:\n      - os.system\n      - subprocess.call\n    filenames:\n      - tests/analyzer/sourcecode/cmd-overwrite.py\n    classification: very promising\n\n  - headline: This package contains a malicious component that can be used to execute arbitrary Python code.\n    analysis: |\n      The codebase contains multiple instances where the `exec()` and `eval()` functions are used to execute arbitrary Python code. This functionality is present in the \"exec-base64.py\" file and is marked with the \"exec-base64\" rule.\n    cwe: CWE-94\n    function_names:\n      - exec\n      - eval\n    filenames:\n      - tests/analyzer/sourcecode/exec-base64.py\n    classification: very promising\n\n  - headline: This package contains a malicious component that can be used to download and execute arbitrary executables.\n    analysis: |\n      The codebase contains a malicious module that downloads and executes an executable file from a URL using the `os.system()` and `subprocess.call()` functions. This functionality is present in the \"download-executable.py\" file and is marked with the \"download-executable\" rule.\n    cwe: CWE-94\n    function_names:\n      - os.system\n      - subprocess.call\n    filenames:\n      - tests/analyzer/sourcecode/download-executable.py\n    classification: very promising\n\n  - headline: This package contains a malicious component that can be used to obfuscate Python code.\n    analysis: |\n      The codebase contains multiple instances where the `eval()` function is used to execute obfuscated Python code. This functionality is present in the \"obfuscation.py\" file and is marked with the \"obfuscation\" rule.\n    cwe: CWE-94\n    function_names:\n      - eval\n    filenames:\n      - tests/analyzer/sourcecode/obfuscation.py\n    classification: very promising\n\n  - headline: This package attempts to exfiltrate sensitive information such as AWS credentials.\n    analysis: |\n      The codebase contains multiple instances where sensitive information, such as AWS credentials, is being exfiltrated to a remote server using the `requests.post()` and `requests.get()` functions. This functionality is present in the \"exfiltrate-sensitive-data.py\" file and is marked with the \"exfiltrate-sensitive-data\" rule.\n    cwe: CWE-200\n    function_names:\n      - requests.post\n      - requests.get\n    filenames:\n      - tests/analyzer/sourcecode/exfiltrate-sensitive-data.py\n    classification: very promising\n\n  - headline: This package attempts to execute arbitrary system commands.\n    analysis: |\n      The codebase contains multiple instances where the `os.system()`, `subprocess.call()`, `subprocess.Popen()`, and `eval()` functions are used to execute arbitrary system commands. This functionality is present in the \"code-execution.py\" file and is marked with the \"code-execution\" rule.\n    cwe: CWE-94\n    function_names:\n      - os.system\n      - subprocess.call\n      - subprocess.Popen\n      - eval\n    filenames:\n      - tests/analyzer/sourcecode/code-execution.py\n    classification: very promising\n```",
      "date": "2024-06-12T15:53:10.114302",
      "usage": {
        "prompt_tokens": 31967,
        "completion_tokens": 1068,
        "cost": 0.00932675
      }
    }
  ],
  "leads": [
    {
      "headline": "This package contains a malicious component that can be used to execute arbitrary system commands.",
      "analysis": "The codebase contains a malicious module called \"colorsapi\" that imports the \"lsb\" module from the \"judyb\" package. This module can be used to execute arbitrary system commands by revealing the contents of a \"hidden.png\" file using the lsb.reveal() function. This functionality is present in the \"steganography.py\" file and is marked with the \"steganography\" rule.\n",
      "classification": "very promising",
      "cwe": "CWE-94",
      "function_names": [
        "exec",
        "reveal"
      ],
      "filenames": [
        "tests/analyzer/sourcecode/steganography.py"
      ]
    },
    {
      "headline": "This package contains a malicious component that can be used to download and execute arbitrary executables.",
      "analysis": "The codebase contains a malicious module that downloads and executes an executable file from a URL using the os.system() and subprocess.call() functions. This functionality is present in the \"cmd-overwrite.py\" file and is marked with the \"cmd-overwrite\" rule.\n",
      "classification": "very promising",
      "cwe": "CWE-94",
      "function_names": [
        "os.system",
        "subprocess.call"
      ],
      "filenames": [
        "tests/analyzer/sourcecode/cmd-overwrite.py"
      ]
    },
    {
      "headline": "This package contains a malicious component that can be used to execute arbitrary Python code.",
      "analysis": "The codebase contains multiple instances where the exec() and eval() functions are used to execute arbitrary Python code. This functionality is present in the \"exec-base64.py\" file and is marked with the \"exec-base64\" rule.\n",
      "classification": "very promising",
      "cwe": "CWE-94",
      "function_names": [
        "exec",
        "eval"
      ],
      "filenames": [
        "tests/analyzer/sourcecode/exec-base64.py"
      ]
    },
    {
      "headline": "This package contains a malicious component that can be used to download and execute arbitrary executables.",
      "analysis": "The codebase contains a malicious module that downloads and executes an executable file from a URL using the os.system() and subprocess.call() functions. This functionality is present in the \"download-executable.py\" file and is marked with the \"download-executable\" rule.\n",
      "classification": "very promising",
      "cwe": "CWE-94",
      "function_names": [
        "os.system",
        "subprocess.call"
      ],
      "filenames": [
        "tests/analyzer/sourcecode/download-executable.py"
      ]
    },
    {
      "headline": "This package contains a malicious component that can be used to obfuscate Python code.",
      "analysis": "The codebase contains multiple instances where the eval() function is used to execute obfuscated Python code. This functionality is present in the \"obfuscation.py\" file and is marked with the \"obfuscation\" rule.\n",
      "classification": "very promising",
      "cwe": "CWE-94",
      "function_names": [
        "eval"
      ],
      "filenames": [
        "tests/analyzer/sourcecode/obfuscation.py"
      ]
    },
    {
      "headline": "This package attempts to exfiltrate sensitive information such as AWS credentials.",
      "analysis": "The codebase contains multiple instances where sensitive information, such as AWS credentials, is being exfiltrated to a remote server using the requests.post() and requests.get() functions. This functionality is present in the \"exfiltrate-sensitive-data.py\" file and is marked with the \"exfiltrate-sensitive-data\" rule.\n",
      "classification": "very promising",
      "cwe": "CWE-200",
      "function_names": [
        "requests.post",
        "requests.get"
      ],
      "filenames": [
        "tests/analyzer/sourcecode/exfiltrate-sensitive-data.py"
      ]
    },
    {
      "headline": "This package attempts to execute arbitrary system commands.",
      "analysis": "The codebase contains multiple instances where the os.system(), subprocess.call(), subprocess.Popen(), and eval() functions are used to execute arbitrary system commands. This functionality is present in the \"code-execution.py\" file and is marked with the \"code-execution\" rule.\n",
      "classification": "very promising",
      "cwe": "CWE-94",
      "function_names": [
        "os.system",
        "subprocess.call",
        "subprocess.Popen"
      ],
      "filenames": [
        "tests/analyzer/sourcecode/code-execution.py"
      ]
    }
  ],
  "scores": [
    {
      "stats": {
        "fn": 2,
        "tp": 0,
        "fp": 7
      },
      "mapping": {},
      "vuln_dates": {
        "CVE-2022-23530": "2022-12-16T23:15:09",
        "CVE-2022-23531": "2022-12-17T00:15:08"
      },
      "scoring_model": "claude-3-opus-20240229",
      "type": "llm",
      "instruction_template_hash": "245ace12b6361954d0a2"
    }
  ],
  "instruction_template_hash": "10c0163db4740318a544",
  "version": "0.1.0"
}
