{
  "commit": "18f6dc0a995c90af3daad2070902280adf925894",
  "repo_url": "https://github.com/cloudfoundry/bosh-system-metrics-server-release",
  "model": "claude-3-sonnet-20240229",
  "chunk_hashes": [
    "1994256da491363f8aac"
  ],
  "responses": [
    {
      "content": "```yaml\nleads:\n  - headline: Potential command injection vulnerability\n    analysis: |\n      The codebase contains a shell script (`vet.sh`) that executes external commands using bash. This script appears to be used for checking the Go codebase for various issues like formatting, linting, etc. However, the script does not sanitize the input arguments, which could potentially allow command injection if untrusted input is passed to the script.\n    cwe: CWE-77\n    function_names:\n      - main (in vet.sh)\n    filenames:\n      - src/github.com/cloudfoundry/bosh-system-metrics-server/vendor/google.golang.org/grpc/vet.sh\n    classification: slightly promising\n\n  - headline: Potential insecure deserialization vulnerability\n    analysis: |\n      The codebase contains code for generating Go code from protocol buffer definitions (`codegen.sh`). If the protocol buffer definitions come from an untrusted source and are not properly validated, it could potentially lead to insecure deserialization attacks.\n    cwe: CWE-502\n    function_names: []\n    filenames:\n      - src/github.com/cloudfoundry/bosh-system-metrics-server/vendor/google.golang.org/grpc/codegen.sh\n    classification: slightly promising\n\n  - headline: Potential script injection vulnerability\n    analysis: |\n      The `install_gae.sh` script downloads and extracts a zip file from a remote URL using curl and unzip commands. If the URL or the contents of the zip file are not properly validated, it could potentially lead to script injection or arbitrary code execution vulnerabilities.\n    cwe: CWE-94\n    function_names: []\n    filenames:\n      - src/github.com/cloudfoundry/bosh-system-metrics-server/vendor/google.golang.org/grpc/install_gae.sh\n    classification: slightly promising\n\n  - headline: Potential path traversal vulnerability\n    analysis: |\n      The script `mkerrors.sh` generates C code that includes system header files (e.g., `#include <errno.h>`). If the paths to these header files are not properly sanitized, it could potentially lead to path traversal vulnerabilities.\n    cwe: CWE-22\n    function_names: []\n    filenames:\n      - src/github.com/cloudfoundry/bosh-system-metrics-server/vendor/golang.org/x/sys/unix/mkerrors.sh\n    classification: slightly promising\n\n  - headline: Potential symlink attack vulnerability\n    analysis: |\n      The script `mksysnum_freebsd.pl` fetches a file from a remote URL using curl and processes it. If the remote file contains symlinks or the processing code does not properly handle symlinks, it could potentially lead to symlink attacks or path traversal vulnerabilities.\n    cwe: CWE-59\n    function_names: []\n    filenames:\n      - src/github.com/cloudfoundry/bosh-system-metrics-server/vendor/golang.org/x/sys/unix/mksysnum_freebsd.pl\n    classification: slightly promising\n\n  - headline: Potential code injection vulnerability\n    analysis: |\n      The script `mksyscall.pl` generates Go code from function prototypes marked with `//sys` comments. If the input source files containing these prototypes come from an untrusted source and are not properly validated, it could potentially lead to code injection vulnerabilities.\n    cwe: CWE-94\n    function_names: []\n    filenames:\n      - src/github.com/cloudfoundry/bosh-system-metrics-server/vendor/golang.org/x/sys/unix/mksyscall.pl\n    classification: slightly promising\n\n  - headline: Potential code injection vulnerability\n    analysis: |\n      The script `mksyscall_aix.pl` generates C and Go code from function prototypes marked with `//sys` comments. If the input source files containing these prototypes come from an untrusted source and are not properly validated, it could potentially lead to code injection vulnerabilities.\n    cwe: CWE-94\n    function_names: []\n    filenames:\n      - src/github.com/cloudfoundry/bosh-system-metrics-server/vendor/golang.org/x/sys/unix/mksyscall_aix.pl\n    classification: slightly promising\n\n  - headline: Potential code injection vulnerability\n    analysis: |\n      The script `mksyscall_solaris.pl` generates C and Go code from function prototypes marked with `//sys` comments. If the input source files containing these prototypes come from an untrusted source and are not properly validated, it could potentially lead to code injection vulnerabilities.\n    cwe: CWE-94\n    function_names: []\n    filenames:\n      - src/github.com/cloudfoundry/bosh-system-metrics-server/vendor/golang.org/x/sys/unix/mksyscall_solaris.pl\n    classification: slightly promising\n\n  - headline: Potential symlink attack vulnerability\n    analysis: |\n      The script `mksysnum_dragonfly.pl` fetches a file from a remote URL using curl and processes it. If the remote file contains symlinks or the processing code does not properly handle symlinks, it could potentially lead to symlink attacks or path traversal vulnerabilities.\n    cwe: CWE-59\n    function_names: []\n    filenames:\n      - src/github.com/cloudfoundry/bosh-system-metrics-server/vendor/golang.org/x/sys/unix/mksysnum_dragonfly.pl\n    classification: slightly promising\n\n  - headline: Potential symlink attack vulnerability\n    analysis: |\n      The script `mksysnum_netbsd.pl` fetches a file from a remote URL using curl and processes it. If the remote file contains symlinks or the processing code does not properly handle symlinks, it could potentially lead to symlink attacks or path traversal vulnerabilities.\n    cwe: CWE-59\n    function_names: []\n    filenames:\n      - src/github.com/cloudfoundry/bosh-system-metrics-server/vendor/golang.org/x/sys/unix/mksysnum_netbsd.pl\n    classification: slightly promising\n\n  - headline: Potential symlink attack vulnerability\n    analysis: |\n      The script `mksysnum_openbsd.pl` fetches a file from a remote URL using curl and processes it. If the remote file contains symlinks or the processing code does not properly handle symlinks, it could potentially lead to symlink attacks or path traversal vulnerabilities.\n    cwe: CWE-59\n    function_names: []\n    filenames:\n      - src/github.com/cloudfoundry/bosh-system-metrics-server/vendor/golang.org/x/sys/unix/mksysnum_openbsd.pl\n    classification: slightly promising\n\n  - headline: Potential symlink attack vulnerability\n    analysis: |\n      The script `mksysctl_openbsd.pl` includes system header files (e.g., `#include <sys/sysctl.h>`) and processes them. If the paths to these header files are not properly sanitized, it could potentially lead to symlink attacks or path traversal vulnerabilities.\n    cwe: CWE-22\n    function_names: []\n    filenames:\n      - src/github.com/cloudfoundry/bosh-system-metrics-server/vendor/golang.org/x/sys/unix/mksysctl_openbsd.pl\n    classification: slightly promising\n\n  - headline: Potential symlink attack vulnerability\n    analysis: |\n      The script `mksysnum_darwin.pl` includes system header files (e.g., `sys/syscall.h`) and processes them. If the paths to these header files are not properly sanitized, it could potentially lead to symlink attacks or path traversal vulnerabilities.\n    cwe: CWE-22\n    function_names: []\n    filenames:\n      - src/github.com/cloudfoundry/bosh-system-metrics-server/vendor/golang.org/x/sys/unix/mksysnum_darwin.pl\n    classification: slightly promising\n```\n\nThe codebase contains various shell scripts and Go code generators that process input files and external resources. While most of these scripts and tools are likely designed to be used in a trusted environment, there are potential security vulnerabilities if they are used with untrusted input or resources. The identified vulnerabilities include:\n\n1. **Command injection**: The `vet.sh` script executes external commands without sanitizing the input arguments, which could potentially lead to command injection vulnerabilities.\n\n2. **Insecure deserialization**: The `codegen.sh` script generates Go code from protocol buffer definitions. If these definitions come from an untrusted source and are not properly validated, it could lead to insecure deserialization vulnerabilities.\n\n3. **Script injection**: The `install_gae.sh` script downloads and extracts a remote zip file without validating the URL or the contents of the zip file, which could potentially lead to script injection or arbitrary code execution.\n\n4. **Path traversal**: The `mkerrors.sh` script includes system header files without sanitizing the file paths, which could potentially lead to path traversal vulnerabilities. Similar vulnerabilities may exist in other scripts that include or process files from untrusted sources.\n\n5. **Symlink attacks**: Several scripts (`mksysnum_freebsd.pl`, `mksysnum_dragonfly.pl`, `mksysnum_netbsd.pl`, `mksysnum_openbsd.pl`, `mksysctl_openbsd.pl`, and `mksysnum_darwin.pl`) fetch or process files from remote URLs or include system header files. If these files contain symlinks or the processing code does not properly handle symlinks, it could potentially lead to symlink attacks or path traversal vulnerabilities.\n\n6. **Code injection**: Scripts like `mksyscall.pl`, `mksyscall_aix.pl`, and `mksyscall_solaris.pl` generate Go or C code from function prototypes marked with comments. If the input source files containing these prototypes come from an untrusted source and are not properly validated, it could potentially lead to code injection vulnerabilities.\n\nIt is important to note that the classification of these vulnerabilities as \"slightly promising\" or \"not promising\" depends on the context in which these scripts and tools are used. If they are intended to be used in a trusted environment with trusted input sources, the likelihood of exploitation may be lower. However, if these scripts and tools are exposed to untrusted input or resources, the identified vulnerabilities could become more serious and require mitigation.",
      "date": "2024-06-12T15:41:16.632902",
      "usage": {
        "prompt_tokens": 32480,
        "completion_tokens": 2528,
        "cost": 0.13536
      }
    }
  ],
  "leads": [
    {
      "headline": "Potential command injection vulnerability",
      "analysis": "The codebase contains a shell script (vet.sh) that executes external commands using bash. This script appears to be used for checking the Go codebase for various issues like formatting, linting, etc. However, the script does not sanitize the input arguments, which could potentially allow command injection if untrusted input is passed to the script.\n",
      "classification": "slightly promising",
      "cwe": "CWE-77",
      "function_names": [
        "main (in vet.sh)"
      ],
      "filenames": [
        "src/github.com/cloudfoundry/bosh-system-metrics-server/vendor/google.golang.org/grpc/vet.sh"
      ]
    },
    {
      "headline": "Potential insecure deserialization vulnerability",
      "analysis": "The codebase contains code for generating Go code from protocol buffer definitions (codegen.sh). If the protocol buffer definitions come from an untrusted source and are not properly validated, it could potentially lead to insecure deserialization attacks.\n",
      "classification": "slightly promising",
      "cwe": "CWE-502",
      "function_names": [],
      "filenames": [
        "src/github.com/cloudfoundry/bosh-system-metrics-server/vendor/google.golang.org/grpc/codegen.sh"
      ]
    },
    {
      "headline": "Potential script injection vulnerability",
      "analysis": "The install_gae.sh script downloads and extracts a zip file from a remote URL using curl and unzip commands. If the URL or the contents of the zip file are not properly validated, it could potentially lead to script injection or arbitrary code execution vulnerabilities.\n",
      "classification": "slightly promising",
      "cwe": "CWE-94",
      "function_names": [],
      "filenames": [
        "src/github.com/cloudfoundry/bosh-system-metrics-server/vendor/google.golang.org/grpc/install_gae.sh"
      ]
    },
    {
      "headline": "Potential path traversal vulnerability",
      "analysis": "The script mkerrors.sh generates C code that includes system header files (e.g., #include <errno.h>). If the paths to these header files are not properly sanitized, it could potentially lead to path traversal vulnerabilities.\n",
      "classification": "slightly promising",
      "cwe": "CWE-22",
      "function_names": [],
      "filenames": [
        "src/github.com/cloudfoundry/bosh-system-metrics-server/vendor/golang.org/x/sys/unix/mkerrors.sh"
      ]
    },
    {
      "headline": "Potential symlink attack vulnerability",
      "analysis": "The script mksysnum_freebsd.pl fetches a file from a remote URL using curl and processes it. If the remote file contains symlinks or the processing code does not properly handle symlinks, it could potentially lead to symlink attacks or path traversal vulnerabilities.\n",
      "classification": "slightly promising",
      "cwe": "CWE-59",
      "function_names": [],
      "filenames": [
        "src/github.com/cloudfoundry/bosh-system-metrics-server/vendor/golang.org/x/sys/unix/mksysnum_freebsd.pl"
      ]
    },
    {
      "headline": "Potential code injection vulnerability",
      "analysis": "The script mksyscall.pl generates Go code from function prototypes marked with //sys comments. If the input source files containing these prototypes come from an untrusted source and are not properly validated, it could potentially lead to code injection vulnerabilities.\n",
      "classification": "slightly promising",
      "cwe": "CWE-94",
      "function_names": [],
      "filenames": [
        "src/github.com/cloudfoundry/bosh-system-metrics-server/vendor/golang.org/x/sys/unix/mksyscall.pl"
      ]
    },
    {
      "headline": "Potential code injection vulnerability",
      "analysis": "The script mksyscall_aix.pl generates C and Go code from function prototypes marked with //sys comments. If the input source files containing these prototypes come from an untrusted source and are not properly validated, it could potentially lead to code injection vulnerabilities.\n",
      "classification": "slightly promising",
      "cwe": "CWE-94",
      "function_names": [],
      "filenames": [
        "src/github.com/cloudfoundry/bosh-system-metrics-server/vendor/golang.org/x/sys/unix/mksyscall_aix.pl"
      ]
    },
    {
      "headline": "Potential code injection vulnerability",
      "analysis": "The script mksyscall_solaris.pl generates C and Go code from function prototypes marked with //sys comments. If the input source files containing these prototypes come from an untrusted source and are not properly validated, it could potentially lead to code injection vulnerabilities.\n",
      "classification": "slightly promising",
      "cwe": "CWE-94",
      "function_names": [],
      "filenames": [
        "src/github.com/cloudfoundry/bosh-system-metrics-server/vendor/golang.org/x/sys/unix/mksyscall_solaris.pl"
      ]
    },
    {
      "headline": "Potential symlink attack vulnerability",
      "analysis": "The script mksysnum_dragonfly.pl fetches a file from a remote URL using curl and processes it. If the remote file contains symlinks or the processing code does not properly handle symlinks, it could potentially lead to symlink attacks or path traversal vulnerabilities.\n",
      "classification": "slightly promising",
      "cwe": "CWE-59",
      "function_names": [],
      "filenames": [
        "src/github.com/cloudfoundry/bosh-system-metrics-server/vendor/golang.org/x/sys/unix/mksysnum_dragonfly.pl"
      ]
    },
    {
      "headline": "Potential symlink attack vulnerability",
      "analysis": "The script mksysnum_netbsd.pl fetches a file from a remote URL using curl and processes it. If the remote file contains symlinks or the processing code does not properly handle symlinks, it could potentially lead to symlink attacks or path traversal vulnerabilities.\n",
      "classification": "slightly promising",
      "cwe": "CWE-59",
      "function_names": [],
      "filenames": [
        "src/github.com/cloudfoundry/bosh-system-metrics-server/vendor/golang.org/x/sys/unix/mksysnum_netbsd.pl"
      ]
    },
    {
      "headline": "Potential symlink attack vulnerability",
      "analysis": "The script mksysnum_openbsd.pl fetches a file from a remote URL using curl and processes it. If the remote file contains symlinks or the processing code does not properly handle symlinks, it could potentially lead to symlink attacks or path traversal vulnerabilities.\n",
      "classification": "slightly promising",
      "cwe": "CWE-59",
      "function_names": [],
      "filenames": [
        "src/github.com/cloudfoundry/bosh-system-metrics-server/vendor/golang.org/x/sys/unix/mksysnum_openbsd.pl"
      ]
    },
    {
      "headline": "Potential symlink attack vulnerability",
      "analysis": "The script mksysctl_openbsd.pl includes system header files (e.g., #include <sys/sysctl.h>) and processes them. If the paths to these header files are not properly sanitized, it could potentially lead to symlink attacks or path traversal vulnerabilities.\n",
      "classification": "slightly promising",
      "cwe": "CWE-22",
      "function_names": [],
      "filenames": [
        "src/github.com/cloudfoundry/bosh-system-metrics-server/vendor/golang.org/x/sys/unix/mksysctl_openbsd.pl"
      ]
    },
    {
      "headline": "Potential symlink attack vulnerability",
      "analysis": "The script mksysnum_darwin.pl includes system header files (e.g., sys/syscall.h) and processes them. If the paths to these header files are not properly sanitized, it could potentially lead to symlink attacks or path traversal vulnerabilities.\n",
      "classification": "slightly promising",
      "cwe": "CWE-22",
      "function_names": [],
      "filenames": [
        "src/github.com/cloudfoundry/bosh-system-metrics-server/vendor/golang.org/x/sys/unix/mksysnum_darwin.pl"
      ]
    }
  ],
  "scores": [
    {
      "stats": {
        "fn": 1,
        "tp": 0,
        "fp": 0
      },
      "mapping": {},
      "vuln_dates": {
        "CVE-2020-5422": "2020-10-02T17:15:12"
      },
      "scoring_model": "claude-3-opus-20240229",
      "type": "llm",
      "instruction_template_hash": "245ace12b6361954d0a2"
    }
  ],
  "instruction_template_hash": "10c0163db4740318a544",
  "version": "0.1.0"
}
