{
  "commit": "0e8a1a49290b7b08f31c603d3895f60bb38d5bb7",
  "repo_url": "https://github.com/gentoo/soko",
  "model": "gpt-4o-2024-05-13",
  "chunk_hashes": [
    "3581d54cbb76fcd374bf"
  ],
  "responses": [
    {
      "content": "```yaml\nleads:\n  - headline: Use of outdated and insecure libraries\n    analysis: |\n      The use of outdated or insecure libraries can lead to a multitude of security vulnerabilities. Here, the JavaScript libraries jQuery and Tether are used without specifying versions. Not pinning versions can lead to eventual inclusion of known vulnerable versions.\n    cwe: CWE-327\n    function_names:\n      - N/A\n    filenames:\n      - webpack.config.js\n    classification: very promising\n\n  - headline: Potential for Cross-Site Scripting (XSS) in devMode\n    analysis: |\n      The devMode implementation dynamically updates HTML content based on the value of 'devMode' stored in localStorage without sanitization, risking XSS attacks if the value is tampered with.\n    cwe: CWE-79\n    function_names:\n      - N/A\n    filenames:\n      - web/packs/src/javascript/devMode.js\n    classification: very promising\n\n  - headline: Potential XSS vulnerability in graphiql.js\n    analysis: |\n      The script directly manipulates the DOM with user-controlled data for the \"Examples & History\" section as well as rendering the gentoo logo. Without sanitizing this data, it could allow XSS attacks.\n    cwe: CWE-79\n    function_names:\n      - N/A\n    filenames:\n      - web/packs/src/javascript/graphiql.js\n    classification: very promising\n\n  - headline: Insecure localStorage usage in graphiql.js\n    analysis: |\n      The code stores query-related and UI state information in localStorage without any form of encryption. Sensitive data in localStorage can be accessed by malicious scripts.\n    cwe: CWE-922\n    function_names:\n      - N/A\n    filenames:\n      - web/packs/src/javascript/graphiql.js\n    classification: slightly promising\n\n  - headline: Command injection risks in update scripts\n    analysis: |\n      The scripts accept user-controlled input and run shell commands without sufficient sanitation, potentially leading to command injection vulnerabilities.\n    cwe: CWE-78\n    function_names:\n      - update_repository\n      - update_md5cache\n    filenames:\n      - bin/update.sh\n      - bin/fullupdate.sh\n    classification: very promising\n```",
      "date": "2024-06-12T16:56:57.060824",
      "usage": {
        "prompt_tokens": 7024,
        "completion_tokens": 469,
        "cost": 0.042155
      }
    }
  ],
  "leads": [
    {
      "headline": "Use of outdated and insecure libraries",
      "analysis": "The use of outdated or insecure libraries can lead to a multitude of security vulnerabilities. Here, the JavaScript libraries jQuery and Tether are used without specifying versions. Not pinning versions can lead to eventual inclusion of known vulnerable versions.\n",
      "classification": "very promising",
      "cwe": "CWE-327",
      "function_names": [
        "N/A"
      ],
      "filenames": [
        "webpack.config.js"
      ]
    },
    {
      "headline": "Potential for Cross-Site Scripting (XSS) in devMode",
      "analysis": "The devMode implementation dynamically updates HTML content based on the value of 'devMode' stored in localStorage without sanitization, risking XSS attacks if the value is tampered with.\n",
      "classification": "very promising",
      "cwe": "CWE-79",
      "function_names": [
        "N/A"
      ],
      "filenames": [
        "web/packs/src/javascript/devMode.js"
      ]
    },
    {
      "headline": "Potential XSS vulnerability in graphiql.js",
      "analysis": "The script directly manipulates the DOM with user-controlled data for the \"Examples & History\" section as well as rendering the gentoo logo. Without sanitizing this data, it could allow XSS attacks.\n",
      "classification": "very promising",
      "cwe": "CWE-79",
      "function_names": [
        "N/A"
      ],
      "filenames": [
        "web/packs/src/javascript/graphiql.js"
      ]
    },
    {
      "headline": "Insecure localStorage usage in graphiql.js",
      "analysis": "The code stores query-related and UI state information in localStorage without any form of encryption. Sensitive data in localStorage can be accessed by malicious scripts.\n",
      "classification": "slightly promising",
      "cwe": "CWE-922",
      "function_names": [
        "N/A"
      ],
      "filenames": [
        "web/packs/src/javascript/graphiql.js"
      ]
    },
    {
      "headline": "Command injection risks in update scripts",
      "analysis": "The scripts accept user-controlled input and run shell commands without sufficient sanitation, potentially leading to command injection vulnerabilities.\n",
      "classification": "very promising",
      "cwe": "CWE-78",
      "function_names": [
        "update_repository",
        "update_md5cache"
      ],
      "filenames": [
        "bin/update.sh",
        "bin/fullupdate.sh"
      ]
    }
  ],
  "scores": [
    {
      "stats": {
        "fn": 2,
        "tp": 0,
        "fp": 4
      },
      "mapping": {},
      "vuln_dates": {
        "CVE-2023-26033": "2023-02-25T00:15:11",
        "CVE-2023-28424": "2023-03-20T13:15:11"
      },
      "scoring_model": "claude-3-opus-20240229",
      "type": "llm",
      "instruction_template_hash": "245ace12b6361954d0a2"
    }
  ],
  "instruction_template_hash": "10c0163db4740318a544",
  "version": "0.1.0"
}
