{
  "commit": "965591c4a2db2f22b38a415e422f38bddb6cf122",
  "repo_url": "https://github.com/nt1m/livemarks",
  "model": "claude-3-sonnet-20240229",
  "chunk_hashes": [
    "133d078375a8f28aa3f3"
  ],
  "responses": [
    {
      "content": "```yaml\nleads:\n  - headline: Potential command injection vulnerability\n    analysis: |\n      The `getSubscribeURL` function in `background/background.js` constructs a URL by concatenating unsanitized user input (the `feedUrl` parameter) with a hard-coded string. If the `feedUrl` parameter contains malicious code, it could potentially result in a command injection vulnerability.\n    cwe: CWE-78\n    function_names:\n      - getSubscribeURL\n    filenames:\n      - background/background.js\n    classification: very promising\n\n  - headline: Potential open redirect vulnerability\n    analysis: |\n      The `preview` function in `popup/popup.js` constructs a URL using the `feed_url` parameter, which comes from user input. If this parameter contains a malicious URL, it could potentially lead to an open redirect vulnerability.\n    cwe: CWE-601\n    function_names:\n      - preview\n    filenames:\n      - popup/popup.js\n    classification: very promising\n\n  - headline: Potential cross-site scripting (XSS) vulnerability\n    analysis: |\n      The `setPreviewContent` function in `pages/subscribe/subscribe.js` sets the `srcdoc` property of an `iframe` element using unsanitized HTML content from a feed. If the feed contains malicious script code, it could potentially lead to a cross-site scripting (XSS) vulnerability.\n    cwe: CWE-79\n    function_names:\n      - setPreviewContent\n    filenames:\n      - pages/subscribe/subscribe.js\n    classification: very promising\n\n  - headline: Potential lack of input validation\n    analysis: |\n      The `getParsedTextFromElement` function in `shared/feed-parser.js` uses the `DOMParser` and `parseFromString` methods to parse potentially untrusted input (feed item titles and descriptions) as HTML. If the input contains malicious code, it could potentially lead to various types of vulnerabilities.\n    cwe: CWE-20\n    function_names:\n      - getParsedTextFromElement\n    filenames:\n      - shared/feed-parser.js\n    classification: very promising\n\n  - headline: Potential lack of output encoding\n    analysis: |\n      The `getPreviewHTML` function in `pages/reader/reader.js` directly sets the `innerHTML` property of a DOM element with unsanitized user-supplied data (feed item descriptions). If the input contains malicious code, it could potentially lead to a cross-site scripting (XSS) vulnerability.\n    cwe: CWE-116\n    function_names:\n      - getPreviewHTML\n    filenames:\n      - pages/reader/reader.js\n    classification: very promising\n\n  - headline: Potential path traversal vulnerability\n    analysis: |\n      The `showEditFeedDialog` function in `pages/settings/settings.js` creates an `a` element with the `href` attribute set to a user-supplied `deleteButton.onclick` event handler. If the event handler contains a malicious path, it could potentially lead to a path traversal vulnerability.\n    cwe: CWE-22\n    function_names:\n      - showEditFeedDialog\n    filenames:\n      - pages/settings/settings.js\n    classification: slightly promising\n\n  - headline: Potential file inclusion vulnerability\n    analysis: |\n      The `importOPML` function in `pages/settings/opml-utils.js` parses an OPML file supplied by the user using the `DOMParser` and `parseFromString` methods. If the OPML file contains malicious code, it could potentially lead to various types of vulnerabilities, including file inclusion.\n    cwe: CWE-829\n    function_names:\n      - importOPML\n    filenames:\n      - pages/settings/opml-utils.js\n    classification: slightly promising\n\n  - headline: Potential cross-site request forgery (CSRF) vulnerability\n    analysis: |\n      The application does not appear to implement any CSRF protection mechanisms. This could potentially allow an attacker to perform unauthorized actions on behalf of a user, such as subscribing to a malicious feed or modifying settings.\n    cwe: CWE-352\n    function_names: []\n    filenames: []\n    classification: slightly promising\n\n  - headline: Potential insecure deserialization vulnerability\n    analysis: |\n      The `LivemarkStore.init` function in `shared/livemark-store.js` deserializes data from the browser storage without any validation or sanitization. If the stored data contains malicious code, it could potentially lead to an insecure deserialization vulnerability.\n    cwe: CWE-502\n    function_names:\n      - init\n    filenames:\n      - shared/livemark-store.js\n    classification: slightly promising\n```",
      "date": "2024-06-09T13:52:27.253867",
      "usage": {
        "prompt_tokens": 22901,
        "completion_tokens": 1132,
        "cost": 0.085683
      }
    }
  ],
  "leads": [
    {
      "headline": "Potential command injection vulnerability",
      "analysis": "The getSubscribeURL function in background/background.js constructs a URL by concatenating unsanitized user input (the feedUrl parameter) with a hard-coded string. If the feedUrl parameter contains malicious code, it could potentially result in a command injection vulnerability.\n",
      "classification": "very promising",
      "cwe": "CWE-78",
      "function_names": [
        "getSubscribeURL"
      ],
      "filenames": [
        "background/background.js"
      ]
    },
    {
      "headline": "Potential open redirect vulnerability",
      "analysis": "The preview function in popup/popup.js constructs a URL using the feed_url parameter, which comes from user input. If this parameter contains a malicious URL, it could potentially lead to an open redirect vulnerability.\n",
      "classification": "very promising",
      "cwe": "CWE-601",
      "function_names": [
        "preview"
      ],
      "filenames": [
        "popup/popup.js"
      ]
    },
    {
      "headline": "Potential cross-site scripting (XSS) vulnerability",
      "analysis": "The setPreviewContent function in pages/subscribe/subscribe.js sets the srcdoc property of an iframe element using unsanitized HTML content from a feed. If the feed contains malicious script code, it could potentially lead to a cross-site scripting (XSS) vulnerability.\n",
      "classification": "very promising",
      "cwe": "CWE-79",
      "function_names": [
        "setPreviewContent"
      ],
      "filenames": [
        "pages/subscribe/subscribe.js"
      ]
    },
    {
      "headline": "Potential lack of input validation",
      "analysis": "The getParsedTextFromElement function in shared/feed-parser.js uses the DOMParser and parseFromString methods to parse potentially untrusted input (feed item titles and descriptions) as HTML. If the input contains malicious code, it could potentially lead to various types of vulnerabilities.\n",
      "classification": "very promising",
      "cwe": "CWE-20",
      "function_names": [
        "getParsedTextFromElement"
      ],
      "filenames": [
        "shared/feed-parser.js"
      ]
    },
    {
      "headline": "Potential lack of output encoding",
      "analysis": "The getPreviewHTML function in pages/reader/reader.js directly sets the innerHTML property of a DOM element with unsanitized user-supplied data (feed item descriptions). If the input contains malicious code, it could potentially lead to a cross-site scripting (XSS) vulnerability.\n",
      "classification": "very promising",
      "cwe": "CWE-116",
      "function_names": [
        "getPreviewHTML"
      ],
      "filenames": [
        "pages/reader/reader.js"
      ]
    },
    {
      "headline": "Potential path traversal vulnerability",
      "analysis": "The showEditFeedDialog function in pages/settings/settings.js creates an a element with the href attribute set to a user-supplied deleteButton.onclick event handler. If the event handler contains a malicious path, it could potentially lead to a path traversal vulnerability.\n",
      "classification": "slightly promising",
      "cwe": "CWE-22",
      "function_names": [
        "showEditFeedDialog"
      ],
      "filenames": [
        "pages/settings/settings.js"
      ]
    },
    {
      "headline": "Potential file inclusion vulnerability",
      "analysis": "The importOPML function in pages/settings/opml-utils.js parses an OPML file supplied by the user using the DOMParser and parseFromString methods. If the OPML file contains malicious code, it could potentially lead to various types of vulnerabilities, including file inclusion.\n",
      "classification": "slightly promising",
      "cwe": "CWE-829",
      "function_names": [
        "importOPML"
      ],
      "filenames": [
        "pages/settings/opml-utils.js"
      ]
    },
    {
      "headline": "Potential cross-site request forgery (CSRF) vulnerability",
      "analysis": "The application does not appear to implement any CSRF protection mechanisms. This could potentially allow an attacker to perform unauthorized actions on behalf of a user, such as subscribing to a malicious feed or modifying settings.\n",
      "classification": "slightly promising",
      "cwe": "CWE-352",
      "function_names": [],
      "filenames": []
    },
    {
      "headline": "Potential insecure deserialization vulnerability",
      "analysis": "The LivemarkStore.init function in shared/livemark-store.js deserializes data from the browser storage without any validation or sanitization. If the stored data contains malicious code, it could potentially lead to an insecure deserialization vulnerability.\n",
      "classification": "slightly promising",
      "cwe": "CWE-502",
      "function_names": [
        "init"
      ],
      "filenames": [
        "shared/livemark-store.js"
      ]
    }
  ],
  "scores": [
    {
      "stats": {
        "fn": 1,
        "tp": 0,
        "fp": 5
      },
      "mapping": {},
      "vuln_dates": {
        "CVE-2024-30252": "2024-04-04T19:15:08"
      },
      "scoring_model": "gpt-4o-2024-05-13",
      "type": "llm",
      "instruction_template_hash": "8998f09cf57fca8a6e03"
    }
  ],
  "instruction_template_hash": "10c0163db4740318a544",
  "version": "0.1.0"
}
