{
  "commit": "39aaa2bb3cfba1101173b5706438a0d9d6d0b229",
  "repo_url": "https://github.com/mannyvergel/oils-js",
  "model": "gpt-4-turbo-2024-04-09",
  "chunk_hashes": [
    "0acce186267f69b8566a"
  ],
  "responses": [
    {
      "content": "```yaml\nleads:\n  - headline: Inadequate sanitization of user inputs leading to OS command injection\n    analysis: |\n      The application does not properly sanitize or validate user inputs before using them in OS command executions in extend() of core/Obj.js. Specifically, the input arguments including class name and properties are used to define new classes and modify existing ones without sanitization, which can be manipulated to inject malicious content and execute arbitrary OS commands.\n    cwe: CWE-78\n    function_names:\n      - extend\n    filenames:\n      - core/Obj.js\n    classification: very promising\n\n  - headline: Insufficient path sanitization leading to path traversal vulnerability\n    analysis: |\n      The Web.include() method in core/Web.js accepts file paths for inclusion without proper validation or sanitization. By manipulating the input paths, an attacker can traverse directories (../) and include arbitrary files from the server\u2019s file system.\n    cwe: CWE-22\n    function_names:\n      - include\n    filenames:\n      - core/Web.js\n    classification: very promising\n\n  - headline: Relying on potentially uninitialized variables\n    analysis: |\n      In the extend() function of core/Obj.js, the prototype properties are initialized in new instances without ensuring that all variables are correctly set before use. This results in potential use of undefined variables that can lead to unhandled exceptions or undefined behaviors.\n    cwe: CWE-908\n    function_names:\n      - extend\n    filenames:\n      - core/Obj.js\n    classification: slightly promising\n\n  - headline: Insecure implementation of server-side templates leading to injection attacks\n    analysis: |\n      The custom implementation of the filesystem loader in core/engines/nunjucks/filesystem.custom.js fails to effectively sanitize the template paths for special characters or malicious content, which can be used to achieve code injection or execution in the server's context.\n    cwe: CWE-94\n    function_names:\n      - getSource\n    filenames:\n      - core/engines/nunjucks/filesystem.custom.js\n    classification: very promising\n\n  - headline: Missing authentication for critical function\n    analysis: |\n      The Web.loadPlugins() function in core/Web.js dynamically loads and executes plugin modules based on configuration without adequately verifying the authenticity or integrity of the source, leading to remote code execution if a malicious plugin is inserted by an attacker.\n    cwe: CWE-306\n    function_names:\n      - loadPlugins\n    filenames:\n      - core/Web.js\n    classification: very promising\n\n  - headline: Missing error handling leads to potential denial of service\n    analysis: |\n      In core/loaders/lib/FsLoader.js, exception handling is omitted for file reading operations. This oversight can allow errors to propagate uncaught, possibly leading to a denial of service if the error crashes the module or script.\n    cwe: CWE-755\n    function_names:\n      - load\n    filenames:\n      - core/loaders/lib/FsLoader.js\n    classification: slightly promising\n\n  - headline: Use of insecure or weak cryptographic algorithms\n    analysis: |\n      The code utilizes weak or deprecated cryptographic configurations in its implementation of HTTPS within core/Web.js. The specified setup may use credentials that do not employ state-of-the-art cryptographic strengths, potentially allowing decryption of sensitive data traffic.\n    cwe: CWE-327\n    function_names:\n      - start\n    filenames:\n      - core/Web.js\n    classification: slightly promising\n```",
      "date": "2024-06-14T14:45:54.051993",
      "usage": {
        "prompt_tokens": 14167,
        "completion_tokens": 712,
        "cost": 0.16303
      }
    }
  ],
  "leads": [
    {
      "headline": "Inadequate sanitization of user inputs leading to OS command injection",
      "analysis": "The application does not properly sanitize or validate user inputs before using them in OS command executions in extend() of core/Obj.js. Specifically, the input arguments including class name and properties are used to define new classes and modify existing ones without sanitization, which can be manipulated to inject malicious content and execute arbitrary OS commands.\n",
      "classification": "very promising",
      "cwe": "CWE-78",
      "function_names": [
        "extend"
      ],
      "filenames": [
        "core/Obj.js"
      ]
    },
    {
      "headline": "Insufficient path sanitization leading to path traversal vulnerability",
      "analysis": "The Web.include() method in core/Web.js accepts file paths for inclusion without proper validation or sanitization. By manipulating the input paths, an attacker can traverse directories (../) and include arbitrary files from the server\u2019s file system.\n",
      "classification": "very promising",
      "cwe": "CWE-22",
      "function_names": [
        "include"
      ],
      "filenames": [
        "core/Web.js"
      ]
    },
    {
      "headline": "Relying on potentially uninitialized variables",
      "analysis": "In the extend() function of core/Obj.js, the prototype properties are initialized in new instances without ensuring that all variables are correctly set before use. This results in potential use of undefined variables that can lead to unhandled exceptions or undefined behaviors.\n",
      "classification": "slightly promising",
      "cwe": "CWE-908",
      "function_names": [
        "extend"
      ],
      "filenames": [
        "core/Obj.js"
      ]
    },
    {
      "headline": "Insecure implementation of server-side templates leading to injection attacks",
      "analysis": "The custom implementation of the filesystem loader in core/engines/nunjucks/filesystem.custom.js fails to effectively sanitize the template paths for special characters or malicious content, which can be used to achieve code injection or execution in the server's context.\n",
      "classification": "very promising",
      "cwe": "CWE-94",
      "function_names": [
        "getSource"
      ],
      "filenames": [
        "core/engines/nunjucks/filesystem.custom.js"
      ]
    },
    {
      "headline": "Missing authentication for critical function",
      "analysis": "The Web.loadPlugins() function in core/Web.js dynamically loads and executes plugin modules based on configuration without adequately verifying the authenticity or integrity of the source, leading to remote code execution if a malicious plugin is inserted by an attacker.\n",
      "classification": "very promising",
      "cwe": "CWE-306",
      "function_names": [
        "loadPlugins"
      ],
      "filenames": [
        "core/Web.js"
      ]
    },
    {
      "headline": "Missing error handling leads to potential denial of service",
      "analysis": "In core/loaders/lib/FsLoader.js, exception handling is omitted for file reading operations. This oversight can allow errors to propagate uncaught, possibly leading to a denial of service if the error crashes the module or script.\n",
      "classification": "slightly promising",
      "cwe": "CWE-755",
      "function_names": [
        "load"
      ],
      "filenames": [
        "core/loaders/lib/FsLoader.js"
      ]
    },
    {
      "headline": "Use of insecure or weak cryptographic algorithms",
      "analysis": "The code utilizes weak or deprecated cryptographic configurations in its implementation of HTTPS within core/Web.js. The specified setup may use credentials that do not employ state-of-the-art cryptographic strengths, potentially allowing decryption of sensitive data traffic.\n",
      "classification": "slightly promising",
      "cwe": "CWE-327",
      "function_names": [
        "start"
      ],
      "filenames": [
        "core/Web.js"
      ]
    }
  ],
  "scores": [
    {
      "stats": {
        "fn": 1,
        "tp": 0,
        "fp": 4
      },
      "mapping": {},
      "vuln_dates": {
        "CVE-2021-4260": "2022-12-19T14:15:10"
      },
      "scoring_model": "claude-3-opus-20240229",
      "type": "llm",
      "instruction_template_hash": "245ace12b6361954d0a2"
    },
    {
      "stats": {
        "fn": 1,
        "tp": 0,
        "fp": 4
      },
      "mapping": {},
      "vuln_dates": {
        "CVE-2021-4260": "2022-12-19T14:15:10"
      },
      "scoring_model": "claude-3-5-sonnet-20240620",
      "type": "llm",
      "instruction_template_hash": "245ace12b6361954d0a2"
    }
  ],
  "instruction_template_hash": "10c0163db4740318a544",
  "version": "0.1.0"
}
