{
  "commit": "11e453ab63d0da1f61a68f4f2ab6c6b75e6be26f",
  "repo_url": "https://github.com/jenkinsci/accurev-plugin",
  "model": "gpt-4o-2024-05-13",
  "chunk_hashes": [
    "eccb2e5b6e5aff05ddf2"
  ],
  "responses": [
    {
      "content": "```yaml\nleads:\n  - headline: \"Possible Command Injection via 'AccurevLauncher.runCommand' method\"\n    analysis: |\n      The runCommand method in the AccurevLauncher class constructs commands using ArgumentListBuilder without sufficiently validating user inputs. This can lead to potential command injection vulnerabilities, especially when inputs contain special characters or command sequences. It's crucial for security researchers to explore how these inputs can be manipulated to execute arbitrary commands on the server.\n    cwe: CWE-78\n    function_names:\n      - \"runCommand\"\n    filenames:\n      - \"src/main/java/hudson/plugins/accurev/AccurevLauncher.java\"\n    classification: very promising\n\n  - headline: \"Cleartext Storage of Sensitive Information\"\n    analysis: |\n      The credentials for AccurevServer are occasionally stored and transferred in cleartext, as indicated by the usage of Plaintext or unencrypted storage and transfer of passwords from UsernamePasswordCredentialsImpl. This exposure leaves sensitive information vulnerable to unauthorized access.\n    cwe: CWE-312\n    function_names:\n      - \"ensureLoggedInToAccurev\"\n      - \"accurevLogin\"\n    filenames:\n      - \"src/main/java/hudson/plugins/accurev/cmd/Login.java\"\n    classification: very promising\n\n  - headline: \"Outdated XML Parser Vulnerability\"\n    analysis: |\n      The XmlPullParserFactory used in several parts of the code, including ParseHistory and ParseShow... classes, might be vulnerable to XML External Entity (XXE) attacks if not properly configured. This suggests an inherent vulnerability due to insufficient validation or disabling of External DTDs.\n    cwe: CWE-611\n    function_names:\n      - \"getFactory\"\n      - \"runCommand\"\n    filenames:\n      - \"src/main/java/hudson/plugins/accurev/XmlParserFactory.java\"\n      - \"src/main/java/hudson/plugins/accurev/parsers/xml/*.java\"\n    classification: very promising\n\n  - headline: \"Use of Deprecated Authentication Methods\"\n    analysis: |\n      The code supports older, deprecated authentication methods such as OBF: obfuscated passwords and potential cleartext passwords, which are being transitioned into more secure methods but still exist and may be exploitable.\n    cwe: CWE-521\n    function_names:\n      - \"migrateCredentials\"\n      - \"setUsername\"\n      - \"getPasswordFromDeprecatedMethod\"\n    filenames:\n      - \"src/main/java/hudson/plugins/accurev/AccurevSCM.java\"\n    classification: slightly promising\n\n  - headline: \"Insecure Deserialization in Jenkins Plugin\"\n    analysis: |\n      The Jenkins plugin uses ObjectInputStream without proper validation, which can lead to insecure deserialization attacks. Ensure that data deserialization processes contain checks and proper validation to prevent injecting malicious serialized data payloads.\n    cwe: CWE-502\n    function_names:\n      - \"readObject\"\n    filenames:\n      - \"src/main/java/hudson/plugins/accurev/AccurevWorkspace.java\"\n    classification: very promising\n\n  - headline: \"Inadequate Credential Handling and Leakage\"\n    analysis: |\n      The plugin relies on several environmental variables and direct method calls that reference or handle credentials, potentially leading to leakage if these are logged improperly or should the environment be inadequately secured.\n    cwe: CWE-522\n    function_names:\n      - \"buildEnvVars\"\n    filenames:\n      - \"src/main/java/hudson/plugins/accurev/delegates/AbstractModeDelegate.java\"\n    classification: slightly promising\n\n  - headline: \"Potential Path Traversal Vulnerability\"\n    analysis: |\n      The code allows for constructing file paths using user input without sufficient sanitization, particularly in the getPopulateFilePath method, which may allow for path traversal attacks that could enable attackers to read or write unauthorized files.\n    cwe: CWE-22\n    function_names:\n      - \"getPopulateFilePath\"\n    filenames:\n      - \"src/main/java/hudson/plugins/accurev/delegates/AbstractModeDelegate.java\"\n    classification: very promising\n```",
      "date": "2024-06-12T17:30:57.486563",
      "usage": {
        "prompt_tokens": 61060,
        "completion_tokens": 853,
        "cost": 0.318095
      }
    }
  ],
  "leads": [
    {
      "headline": "Possible Command Injection via 'AccurevLauncher.runCommand' method",
      "analysis": "The runCommand method in the AccurevLauncher class constructs commands using ArgumentListBuilder without sufficiently validating user inputs. This can lead to potential command injection vulnerabilities, especially when inputs contain special characters or command sequences. It's crucial for security researchers to explore how these inputs can be manipulated to execute arbitrary commands on the server.\n",
      "classification": "very promising",
      "cwe": "CWE-78",
      "function_names": [
        "runCommand"
      ],
      "filenames": [
        "src/main/java/hudson/plugins/accurev/AccurevLauncher.java"
      ]
    },
    {
      "headline": "Cleartext Storage of Sensitive Information",
      "analysis": "The credentials for AccurevServer are occasionally stored and transferred in cleartext, as indicated by the usage of Plaintext or unencrypted storage and transfer of passwords from UsernamePasswordCredentialsImpl. This exposure leaves sensitive information vulnerable to unauthorized access.\n",
      "classification": "very promising",
      "cwe": "CWE-312",
      "function_names": [
        "ensureLoggedInToAccurev",
        "accurevLogin"
      ],
      "filenames": [
        "src/main/java/hudson/plugins/accurev/cmd/Login.java"
      ]
    },
    {
      "headline": "Outdated XML Parser Vulnerability",
      "analysis": "The XmlPullParserFactory used in several parts of the code, including ParseHistory and ParseShow... classes, might be vulnerable to XML External Entity (XXE) attacks if not properly configured. This suggests an inherent vulnerability due to insufficient validation or disabling of External DTDs.\n",
      "classification": "very promising",
      "cwe": "CWE-611",
      "function_names": [
        "getFactory",
        "runCommand"
      ],
      "filenames": [
        "src/main/java/hudson/plugins/accurev/XmlParserFactory.java",
        "src/main/java/hudson/plugins/accurev/parsers/xml/*.java"
      ]
    },
    {
      "headline": "Use of Deprecated Authentication Methods",
      "analysis": "The code supports older, deprecated authentication methods such as OBF: obfuscated passwords and potential cleartext passwords, which are being transitioned into more secure methods but still exist and may be exploitable.\n",
      "classification": "slightly promising",
      "cwe": "CWE-521",
      "function_names": [
        "migrateCredentials",
        "setUsername",
        "getPasswordFromDeprecatedMethod"
      ],
      "filenames": [
        "src/main/java/hudson/plugins/accurev/AccurevSCM.java"
      ]
    },
    {
      "headline": "Insecure Deserialization in Jenkins Plugin",
      "analysis": "The Jenkins plugin uses ObjectInputStream without proper validation, which can lead to insecure deserialization attacks. Ensure that data deserialization processes contain checks and proper validation to prevent injecting malicious serialized data payloads.\n",
      "classification": "very promising",
      "cwe": "CWE-502",
      "function_names": [
        "readObject"
      ],
      "filenames": [
        "src/main/java/hudson/plugins/accurev/AccurevWorkspace.java"
      ]
    },
    {
      "headline": "Inadequate Credential Handling and Leakage",
      "analysis": "The plugin relies on several environmental variables and direct method calls that reference or handle credentials, potentially leading to leakage if these are logged improperly or should the environment be inadequately secured.\n",
      "classification": "slightly promising",
      "cwe": "CWE-522",
      "function_names": [
        "buildEnvVars"
      ],
      "filenames": [
        "src/main/java/hudson/plugins/accurev/delegates/AbstractModeDelegate.java"
      ]
    },
    {
      "headline": "Potential Path Traversal Vulnerability",
      "analysis": "The code allows for constructing file paths using user input without sufficient sanitization, particularly in the getPopulateFilePath method, which may allow for path traversal attacks that could enable attackers to read or write unauthorized files.\n",
      "classification": "very promising",
      "cwe": "CWE-22",
      "function_names": [
        "getPopulateFilePath"
      ],
      "filenames": [
        "src/main/java/hudson/plugins/accurev/delegates/AbstractModeDelegate.java"
      ]
    }
  ],
  "scores": [
    {
      "stats": {
        "fn": 1,
        "tp": 0,
        "fp": 5
      },
      "mapping": {},
      "vuln_dates": {
        "CVE-2018-1999028": "2018-08-01T13:29:00"
      },
      "scoring_model": "claude-3-opus-20240229",
      "type": "llm",
      "instruction_template_hash": "245ace12b6361954d0a2"
    }
  ],
  "instruction_template_hash": "10c0163db4740318a544",
  "version": "0.1.0"
}
