{
  "commit": "19f0165580afa12b6a35e8a2b72e870021818866",
  "repo_url": "https://github.com/jenkinsci/skytap-cloud-plugin",
  "model": "gpt-4o-2024-05-13",
  "chunk_hashes": [
    "95a7e6e6460804524cac"
  ],
  "responses": [
    {
      "content": "```yaml\nleads:\n  - headline: \"Potential Sensitive Information Leakage through Logging\"\n    analysis: |\n      Several classes in the codebase use a JenkinsLogger to output messages, errors, and log information. \n      In some cases, this includes potentially sensitive data such as configuration IDs, VM IDs, and container IDs.\n      Since logs in Jenkins can be accessible to many users or potentially misconfigured to be published externally,\n      this could lead to sensitive information leakage.\n    cwe: CWE-532\n    function_names:\n      - \"log\"\n      - \"error\"\n    filenames:\n      - \"src/main/java/org/jenkinsci/plugins/skytap/SkytapUtils.java\"\n      - \"src/main/java/org/jenkinsci/plugins/skytap/JenkinsLogger.java\"\n    classification: very promising\n\n  - headline: \"Missing Authentication for Critical Function\"\n    analysis: |\n      The build-plugin.sh and cleanup-plugin.sh scripts can perform critical build and cleanup operations without any apparent access control mechanism.\n      These scripts can be executed by anyone with access to the system, leading to unauthorized build and cleanup operations.\n    cwe: CWE-306\n    function_names: []\n    filenames:\n      - \"build-plugin.sh\"\n      - \"cleanup-plugin.sh\"\n    classification: very promising\n\n  - headline: \"Cross-Site Scripting (XSS) via Help Files\"\n    analysis: |\n      The help text files for various configurations use raw HTML without proper escaping. This could lead to Cross-Site Scripting (XSS) attacks if user input is included or displayed without proper sanitization.\n    cwe: CWE-79\n    function_names: []\n    filenames:\n      - \"src/main/resources/org/jenkinsci/plugins/skytap/GetContainerMetaDataStep/help-configurationID.html\"\n      - \"src/main/resources/org/jenkinsci/plugins/skytap/GetContainerMetaDataStep/help-vmID.html\"\n      - \"src/main/resources/org/jenkinsci/plugins/skytap/CreateContainerStep/help-containerName.html\"\n      - \"src/main/resources/org/jenkinsci/plugins/skytap/CreatePublishURLStep/help-portalName.html\"\n    classification: very promising\n\n  - headline: \"Information Exposure Through Debug Information\"\n    analysis: |\n      Various Java classes in the codebase include debug logging that outputs sensitive information like configuration ID, VM ID, and container information. \n      Debug logs should avoid including such data or should be properly masked to prevent unintended exposure.\n    cwe: CWE-209\n    function_names:\n      - \"executeStep\"\n      - \"buildRequestURL\"\n      - \"sendStateChangeRequest\"\n    filenames:\n      - \"src/main/java/org/jenkinsci/plugins/skytap/CreateContainerStep.java\"\n      - \"src/main/java/org/jenkinsci/plugins/skytap/ChangeConfigurationStateStep.java\"\n      - \"src/main/java/org/jenkinsci/plugins/skytap/SkytapUtils.java\"\n    classification: very promising\n    \n  - headline: \"Improper Authentication Handling\"\n    analysis: |\n      The SkytapUtils class handles authentication within the `getAuthCredentials` method. It reads the user ID and API key from the build environment and uses them directly to authenticate API requests.\n      This approach might expose authentication data if mishandled, and it's better to use more secure methods such as environment variable management or secret vaults.\n    cwe: CWE-522\n    function_names:\n      - \"getAuthCredentials\"\n    filenames:\n      - \"src/main/java/org/jenkinsci/plugins/skytap/SkytapUtils.java\"\n    classification: very promising\n    \n  - headline: \"Missing Integrity Check for Sensitive Data\"\n    analysis: |\n      The SkytapUtils class handles sensitive operations involving Skytap environments and configurations. There are API calls that retrieve, modify, and create configurations and templates without validating the data's authenticity and integrity.\n      An attacker with man-in-the-middle capabilities or compromising the network could tamper with the responses, leading to incorrect or malicious behavior.\n    cwe: CWE-345\n    function_names:\n      - \"executeHttpRequest\"\n      - \"checkResponseForErrors\"\n    filenames:\n      - \"src/main/java/org/jenkinsci/plugins/skytap/SkytapUtils.java\"\n    classification: slightly promising\n\n  - headline: \"Use of Hard-coded Credentials\"\n    analysis: |\n      There were concerns about hard-coded credentials for accessing Skytap API within the configuration files or environment variables that are not encrypted or masked.\n    cwe: CWE-798\n    function_names: []\n    filenames:\n      - \"src/main/java/org/jenkinsci/plugins/skytap/SkytapBuildWrapper.java\"\n      - \"build-plugin.sh\"\n      - \"cleanup-plugin.sh\"\n    classification: very promising\n\n  - headline: \"External Control of Critical State Data\"\n    analysis: |\n      Several methods operating on states like ChangeConfigurationStateStep and ChangeContainerStateStep depend on external inputs to determine their execution path.\n      If these inputs are manipulated, it could lead to unauthorized state changes, potentially causing service disruptions or data corruption.\n    cwe: CWE-912\n    function_names:\n      - \"executeStep\"\n    filenames:\n      - \"src/main/java/org/jenkinsci/plugins/skytap/ChangeConfigurationStateStep.java\"\n      - \"src/main/java/org/jenkinsci/plugins/skytap/ChangeContainerStateStep.java\"\n    classification: slightly promising\n```",
      "date": "2024-06-12T19:13:44.638903",
      "usage": {
        "prompt_tokens": 63925,
        "completion_tokens": 1130,
        "cost": 0.336575
      }
    }
  ],
  "leads": [
    {
      "headline": "Potential Sensitive Information Leakage through Logging",
      "analysis": "Several classes in the codebase use a JenkinsLogger to output messages, errors, and log information. \nIn some cases, this includes potentially sensitive data such as configuration IDs, VM IDs, and container IDs.\nSince logs in Jenkins can be accessible to many users or potentially misconfigured to be published externally,\nthis could lead to sensitive information leakage.\n",
      "classification": "very promising",
      "cwe": "CWE-532",
      "function_names": [
        "log",
        "error"
      ],
      "filenames": [
        "src/main/java/org/jenkinsci/plugins/skytap/SkytapUtils.java",
        "src/main/java/org/jenkinsci/plugins/skytap/JenkinsLogger.java"
      ]
    },
    {
      "headline": "Missing Authentication for Critical Function",
      "analysis": "The build-plugin.sh and cleanup-plugin.sh scripts can perform critical build and cleanup operations without any apparent access control mechanism.\nThese scripts can be executed by anyone with access to the system, leading to unauthorized build and cleanup operations.\n",
      "classification": "very promising",
      "cwe": "CWE-306",
      "function_names": [],
      "filenames": [
        "build-plugin.sh",
        "cleanup-plugin.sh"
      ]
    },
    {
      "headline": "Cross-Site Scripting (XSS) via Help Files",
      "analysis": "The help text files for various configurations use raw HTML without proper escaping. This could lead to Cross-Site Scripting (XSS) attacks if user input is included or displayed without proper sanitization.\n",
      "classification": "very promising",
      "cwe": "CWE-79",
      "function_names": [],
      "filenames": [
        "src/main/resources/org/jenkinsci/plugins/skytap/GetContainerMetaDataStep/help-configurationID.html",
        "src/main/resources/org/jenkinsci/plugins/skytap/GetContainerMetaDataStep/help-vmID.html",
        "src/main/resources/org/jenkinsci/plugins/skytap/CreateContainerStep/help-containerName.html"
      ]
    },
    {
      "headline": "Information Exposure Through Debug Information",
      "analysis": "Various Java classes in the codebase include debug logging that outputs sensitive information like configuration ID, VM ID, and container information. \nDebug logs should avoid including such data or should be properly masked to prevent unintended exposure.\n",
      "classification": "very promising",
      "cwe": "CWE-209",
      "function_names": [
        "executeStep",
        "buildRequestURL",
        "sendStateChangeRequest"
      ],
      "filenames": [
        "src/main/java/org/jenkinsci/plugins/skytap/CreateContainerStep.java",
        "src/main/java/org/jenkinsci/plugins/skytap/ChangeConfigurationStateStep.java",
        "src/main/java/org/jenkinsci/plugins/skytap/SkytapUtils.java"
      ]
    },
    {
      "headline": "Improper Authentication Handling",
      "analysis": "The SkytapUtils class handles authentication within the getAuthCredentials method. It reads the user ID and API key from the build environment and uses them directly to authenticate API requests.\nThis approach might expose authentication data if mishandled, and it's better to use more secure methods such as environment variable management or secret vaults.\n",
      "classification": "very promising",
      "cwe": "CWE-522",
      "function_names": [
        "getAuthCredentials"
      ],
      "filenames": [
        "src/main/java/org/jenkinsci/plugins/skytap/SkytapUtils.java"
      ]
    },
    {
      "headline": "Missing Integrity Check for Sensitive Data",
      "analysis": "The SkytapUtils class handles sensitive operations involving Skytap environments and configurations. There are API calls that retrieve, modify, and create configurations and templates without validating the data's authenticity and integrity.\nAn attacker with man-in-the-middle capabilities or compromising the network could tamper with the responses, leading to incorrect or malicious behavior.\n",
      "classification": "slightly promising",
      "cwe": "CWE-345",
      "function_names": [
        "executeHttpRequest",
        "checkResponseForErrors"
      ],
      "filenames": [
        "src/main/java/org/jenkinsci/plugins/skytap/SkytapUtils.java"
      ]
    },
    {
      "headline": "Use of Hard-coded Credentials",
      "analysis": "There were concerns about hard-coded credentials for accessing Skytap API within the configuration files or environment variables that are not encrypted or masked.\n",
      "classification": "very promising",
      "cwe": "CWE-798",
      "function_names": [],
      "filenames": [
        "src/main/java/org/jenkinsci/plugins/skytap/SkytapBuildWrapper.java",
        "build-plugin.sh",
        "cleanup-plugin.sh"
      ]
    },
    {
      "headline": "External Control of Critical State Data",
      "analysis": "Several methods operating on states like ChangeConfigurationStateStep and ChangeContainerStateStep depend on external inputs to determine their execution path.\nIf these inputs are manipulated, it could lead to unauthorized state changes, potentially causing service disruptions or data corruption.\n",
      "classification": "slightly promising",
      "cwe": "CWE-912",
      "function_names": [
        "executeStep"
      ],
      "filenames": [
        "src/main/java/org/jenkinsci/plugins/skytap/ChangeConfigurationStateStep.java",
        "src/main/java/org/jenkinsci/plugins/skytap/ChangeContainerStateStep.java"
      ]
    }
  ],
  "scores": [
    {
      "stats": {
        "fn": 2,
        "tp": 0,
        "fp": 6
      },
      "mapping": {},
      "vuln_dates": {
        "CVE-2020-2157": "2020-03-09T16:15:15",
        "CVE-2019-10366": "2019-07-31T13:15:13"
      },
      "scoring_model": "claude-3-opus-20240229",
      "type": "llm",
      "instruction_template_hash": "245ace12b6361954d0a2"
    }
  ],
  "instruction_template_hash": "10c0163db4740318a544",
  "version": "0.1.0"
}
