{
  "commit": "2d54fcae4e1a4a8fbbbb35564e3f7a44c6ca6788",
  "repo_url": "https://github.com/wireapp/wire-desktop",
  "model": "claude-3-opus-20240229",
  "chunk_hashes": [
    "e41933e8f368b59634a2"
  ],
  "responses": [
    {
      "content": "Here are the potential security vulnerabilities I identified in the codebase:\n\n```yaml\nleads:\n  - headline: Insecure storage of sensitive data\n    analysis: |\n      The code stores sensitive data like AWS access keys, API tokens, and code signing keys directly in the codebase in plain text. This is very insecure as anyone with read access to the codebase can steal these secrets. Secrets should be stored securely outside the codebase.\n    cwe: CWE-922  \n    function_names:\n      - buildMacOSConfig\n      - buildWindowsConfig\n      - buildLinuxConfig\n    filenames:\n      - electron/src/main.ts\n      - bin/build-tools/lib/build-macos.ts  \n      - bin/build-tools/lib/build-windows.ts\n      - bin/build-tools/lib/build-linux.ts\n    classification: very promising\n\n  - headline: Improper neutralization of special elements used in an OS command ('OS Command Injection')\n    analysis: |  \n      The code uses child_process.exec() to execute shell commands by passing in unsanitized input that comes from environment variables. If an attacker can control the values of these env vars, they could inject arbitrary commands that get executed. The input needs to be properly validated and sanitized before passing to exec().\n    cwe: CWE-78\n    function_names:\n      - execAsync\n    filenames:\n      - bin/bin-utils.ts  \n    classification: very promising\n\n  - headline: Use of hard-coded credentials\n    analysis: |\n      The code has hard-coded credentials like default usernames and passwords. These act as a backdoor and should never be present in code. Usernames and passwords should be chosen by the user at runtime.\n    cwe: CWE-798\n    function_names:\n      - buildWindowsInstallerConfig\n    filenames: \n      - bin/build-tools/lib/build-windows-installer.ts\n    classification: very promising\n\n  - headline: Improper access control\n    analysis: |\n      The WindowManager class has functions like sendActionToPrimaryWindow and sendActionAndFocusWindow that allow sending arbitrary IPC events that get handled by the renderer process webContents. There doesn't seem to be any access control on which events can be sent this way. This could potentially allow a compromised renderer to perform unauthorized actions.\n    cwe: CWE-284  \n    function_names:\n      - sendActionToPrimaryWindow\n      - sendActionAndFocusWindow\n    filenames:\n      - electron/src/window/WindowManager.ts\n    classification: slightly promising\n  \n  - headline: Inadequate encryption strength\n    analysis: | \n      The SingleSignOn class derives an encryption key from a random secret to encrypt SSO login data. However, it only uses 24 bytes of randomness which is not sufficient. At least 32 bytes of entropy should be used for deriving a strong encryption key.\n    cwe: CWE-326\n    function_names:\n      - generateSecret\n    filenames:\n      - electron/src/sso/SingleSignOn.ts\n    classification: slightly promising\n```\n\nThe most serious issues are the insecure storage of secrets, command injection, and use of hard-coded credentials. These could easily allow compromise of the application. The access control and encryption strength issues are lower severity but still worth investigating and fixing. Let me know if you need any clarification or have additional questions!",
      "date": "2024-06-13T18:22:21.467095",
      "usage": {
        "prompt_tokens": 108588,
        "completion_tokens": 808,
        "cost": 1.68942
      }
    }
  ],
  "leads": [
    {
      "headline": "Insecure storage of sensitive data",
      "analysis": "The code stores sensitive data like AWS access keys, API tokens, and code signing keys directly in the codebase in plain text. This is very insecure as anyone with read access to the codebase can steal these secrets. Secrets should be stored securely outside the codebase.\n",
      "classification": "very promising",
      "cwe": "CWE-922",
      "function_names": [
        "buildMacOSConfig",
        "buildWindowsConfig",
        "buildLinuxConfig"
      ],
      "filenames": [
        "electron/src/main.ts",
        "bin/build-tools/lib/build-macos.ts",
        "bin/build-tools/lib/build-windows.ts"
      ]
    },
    {
      "headline": "Improper neutralization of special elements used in an OS command ('OS Command Injection')",
      "analysis": "The code uses child_process.exec() to execute shell commands by passing in unsanitized input that comes from environment variables. If an attacker can control the values of these env vars, they could inject arbitrary commands that get executed. The input needs to be properly validated and sanitized before passing to exec().\n",
      "classification": "very promising",
      "cwe": "CWE-78",
      "function_names": [
        "execAsync"
      ],
      "filenames": [
        "bin/bin-utils.ts"
      ]
    },
    {
      "headline": "Use of hard-coded credentials",
      "analysis": "The code has hard-coded credentials like default usernames and passwords. These act as a backdoor and should never be present in code. Usernames and passwords should be chosen by the user at runtime.\n",
      "classification": "very promising",
      "cwe": "CWE-798",
      "function_names": [
        "buildWindowsInstallerConfig"
      ],
      "filenames": [
        "bin/build-tools/lib/build-windows-installer.ts"
      ]
    },
    {
      "headline": "Improper access control",
      "analysis": "The WindowManager class has functions like sendActionToPrimaryWindow and sendActionAndFocusWindow that allow sending arbitrary IPC events that get handled by the renderer process webContents. There doesn't seem to be any access control on which events can be sent this way. This could potentially allow a compromised renderer to perform unauthorized actions.\n",
      "classification": "slightly promising",
      "cwe": "CWE-284",
      "function_names": [
        "sendActionToPrimaryWindow",
        "sendActionAndFocusWindow"
      ],
      "filenames": [
        "electron/src/window/WindowManager.ts"
      ]
    },
    {
      "headline": "Inadequate encryption strength",
      "analysis": "The SingleSignOn class derives an encryption key from a random secret to encrypt SSO login data. However, it only uses 24 bytes of randomness which is not sufficient. At least 32 bytes of entropy should be used for deriving a strong encryption key.\n",
      "classification": "slightly promising",
      "cwe": "CWE-326",
      "function_names": [
        "generateSecret"
      ],
      "filenames": [
        "electron/src/sso/SingleSignOn.ts"
      ]
    }
  ],
  "scores": [
    {
      "stats": {
        "fn": 2,
        "tp": 1,
        "fp": 2
      },
      "mapping": {
        "1": "CVE-2020-15258"
      },
      "vuln_dates": {
        "CVE-2020-15258": "2020-10-16T17:15:12",
        "CVE-2020-27853": "2020-10-27T18:15:12",
        "CVE-2022-43673": "2022-11-18T20:15:10"
      },
      "scoring_model": "claude-3-opus-20240229",
      "type": "llm",
      "instruction_template_hash": "245ace12b6361954d0a2"
    }
  ],
  "instruction_template_hash": "10c0163db4740318a544",
  "version": "0.1.0"
}
