{
  "commit": "28e9d6f553176b40a7c4bc1c9175b98bdfff860a",
  "repo_url": "https://github.com/voila-dashboards/voila",
  "model": "gpt-4o-2024-05-13",
  "chunk_hashes": [
    "9374ccdf3f546c9364f0"
  ],
  "responses": [
    {
      "content": "```yaml\nleads:\n  - headline: Shell command injection in lint-staged configuration\n    analysis: |\n      The `lint-staged.config.js` file contains a potential command injection vulnerability. The functions `escapeFileNames` use `shell-quote` to escape filenames, but there's still a risk of injection if `shell-quote` contains bugs or if input filenames aren't properly sanitized before being passed to shell commands like `prettier` and `eslint`.\n    cwe: CWE-78\n    function_names:\n      - escapeFileNames\n    filenames:\n      - lint-staged.config.js\n    classification: very promising\n\n  - headline: Insecure download of CSS files in Hatch build script\n    analysis: |\n      The `hatch_build.py` file downloads CSS files from external sources without verifying their integrity or using secure channels (like HTTPS). This can allow an attacker to manipulate the downloaded content if they manage to compromise the source or the integrity checks of the source file.\n    cwe: CWE-494\n    function_names:\n      - initialize\n    filenames:\n      - hatch_build.py\n    classification: very promising\n\n  - headline: Fixed sleep time in test fixtures\n    analysis: |\n      The test fixture `sleep_between_tests` in `tests/conftest.py` includes a fixed `time.sleep(1)` call. This fixed sleep time could lead to inefficient test execution, increasing the test suite run time significantly. A better approach would be to wait for a specific condition to be satisfied instead of sleeping for a fixed duration.\n    cwe: CWE-400\n    function_names:\n      - sleep_between_tests\n    filenames:\n      - tests/conftest.py\n    classification: slightly promising\n\n  - headline: Insecure default permissions in setup.py\n    analysis: |\n      The use of `.data_files.append` in `setup.py` for `test_template` can potentially overwrite sensitive files if the script is run with elevated privileges. Special care should be taken to ensure that only trusted files are included and that the file paths are properly validated and sanitized.\n    cwe: CWE-276\n    function_names:\n      - None\n    filenames:\n      - tests/test_template/setup.py\n    classification: slightly promising\n\n  - headline: Missing CSRF protection in shutdown handler\n    analysis: |\n      The `VoilaShutdownKernelHandler` in `voila/shutdown_kernel_handler.py` handles potentially sensitive operations without any form of CSRF protection, making it susceptible to CSRF attacks. Although authentication is used, adding CSRF protection would improve security.\n    cwe: CWE-352\n    function_names:\n      - post\n    filenames:\n      - voila/shutdown_kernel_handler.py\n    classification: slightly promising\n\n  - headline: Exposing sensitive environment variables in notebook execution\n    analysis: |\n      The `voila/utils.py` file includes code to wait for request info and set environment variables based on request headers. This may inadvertently expose sensitive information through environment variables.\n    cwe: CWE-922\n    function_names:\n      - wait_for_request\n    filenames:\n      - voila/utils.py\n    classification: very promising\n```",
      "date": "2024-06-09T15:23:02.649539",
      "usage": {
        "prompt_tokens": 54165,
        "completion_tokens": 646,
        "cost": 0.280515
      }
    }
  ],
  "leads": [
    {
      "headline": "Shell command injection in lint-staged configuration",
      "analysis": "The lint-staged.config.js file contains a potential command injection vulnerability. The functions escapeFileNames use shell-quote to escape filenames, but there's still a risk of injection if shell-quote contains bugs or if input filenames aren't properly sanitized before being passed to shell commands like prettier and eslint.\n",
      "classification": "very promising",
      "cwe": "CWE-78",
      "function_names": [
        "escapeFileNames"
      ],
      "filenames": [
        "lint-staged.config.js"
      ]
    },
    {
      "headline": "Insecure download of CSS files in Hatch build script",
      "analysis": "The hatch_build.py file downloads CSS files from external sources without verifying their integrity or using secure channels (like HTTPS). This can allow an attacker to manipulate the downloaded content if they manage to compromise the source or the integrity checks of the source file.\n",
      "classification": "very promising",
      "cwe": "CWE-494",
      "function_names": [
        "initialize"
      ],
      "filenames": [
        "hatch_build.py"
      ]
    },
    {
      "headline": "Fixed sleep time in test fixtures",
      "analysis": "The test fixture sleep_between_tests in tests/conftest.py includes a fixed time.sleep(1) call. This fixed sleep time could lead to inefficient test execution, increasing the test suite run time significantly. A better approach would be to wait for a specific condition to be satisfied instead of sleeping for a fixed duration.\n",
      "classification": "slightly promising",
      "cwe": "CWE-400",
      "function_names": [
        "sleep_between_tests"
      ],
      "filenames": [
        "tests/conftest.py"
      ]
    },
    {
      "headline": "Insecure default permissions in setup.py",
      "analysis": "The use of .data_files.append in setup.py for test_template can potentially overwrite sensitive files if the script is run with elevated privileges. Special care should be taken to ensure that only trusted files are included and that the file paths are properly validated and sanitized.\n",
      "classification": "slightly promising",
      "cwe": "CWE-276",
      "function_names": [
        "None"
      ],
      "filenames": [
        "tests/test_template/setup.py"
      ]
    },
    {
      "headline": "Missing CSRF protection in shutdown handler",
      "analysis": "The VoilaShutdownKernelHandler in voila/shutdown_kernel_handler.py handles potentially sensitive operations without any form of CSRF protection, making it susceptible to CSRF attacks. Although authentication is used, adding CSRF protection would improve security.\n",
      "classification": "slightly promising",
      "cwe": "CWE-352",
      "function_names": [
        "post"
      ],
      "filenames": [
        "voila/shutdown_kernel_handler.py"
      ]
    },
    {
      "headline": "Exposing sensitive environment variables in notebook execution",
      "analysis": "The voila/utils.py file includes code to wait for request info and set environment variables based on request headers. This may inadvertently expose sensitive information through environment variables.\n",
      "classification": "very promising",
      "cwe": "CWE-922",
      "function_names": [
        "wait_for_request"
      ],
      "filenames": [
        "voila/utils.py"
      ]
    }
  ],
  "scores": [
    {
      "stats": {
        "fn": 1,
        "tp": 0,
        "fp": 3
      },
      "mapping": {},
      "vuln_dates": {
        "CVE-2024-30265": "2024-04-03T23:15:13"
      },
      "scoring_model": "gpt-4o-2024-05-13",
      "type": "llm",
      "instruction_template_hash": "8998f09cf57fca8a6e03"
    }
  ],
  "instruction_template_hash": "10c0163db4740318a544",
  "version": "0.1.0"
}
