{
  "commit": "0d0ddd43b3b0f0995bfaa34a45f046d47860a234",
  "repo_url": "https://github.com/skyscreamer/nevado",
  "model": "claude-3-haiku-20240307",
  "chunk_hashes": [
    "fcababaa4ada245f9f81"
  ],
  "responses": [
    {
      "content": "Here is the YAML object equivalent to type LeadList, based on the provided Pydantic definitions:\n\n```yaml\nleads:\n  - headline: Potential buffer overflow in NevadoBytesMessage.readBytes()\n    analysis: |\n      The NevadoBytesMessage.readBytes() method does not perform proper bounds checking on the provided byte array buffer. This could lead to a buffer overflow vulnerability if the message body is larger than the provided buffer.\n    cwe: CWE-119\n    function_names:\n      - readBytes\n    filenames:\n      - nevado-jms/src/main/java/org/skyscreamer/nevado/jms/message/NevadoBytesMessage.java\n    classification: very promising\n  - headline: Potential integer overflow in NevadoStreamMessage.readInt()\n    analysis: |\n      The NevadoStreamMessage.readInt() method does not perform proper overflow checks on the read integer value. This could lead to an integer overflow vulnerability if the message body contains a crafted integer value.\n    cwe: CWE-190\n    function_names:\n      - readInt\n    filenames:\n      - nevado-jms/src/main/java/org/skyscreamer/nevado/jms/message/NevadoStreamMessage.java\n    classification: very promising\n  - headline: Potential XML injection in TextMessageTest.testXmlMessage()\n    analysis: |\n      The TextMessageTest.testXmlMessage() method does not properly sanitize the XML message body before parsing it. This could lead to an XML injection vulnerability if the message body contains malicious XML content.\n    cwe: CWE-91\n    function_names:\n      - testXmlMessage\n    filenames:\n      - nevado-jms/src/test/java/org/skyscreamer/nevado/jms/message/TextMessageTest.java\n    classification: slightly promising\n  - headline: Potential command injection in MockSQSConnector.sendSNSMessage()\n    analysis: |\n      The MockSQSConnector.sendSNSMessage() method does not properly sanitize the serialized message body before passing it to the SNS service. This could lead to a command injection vulnerability if the message body contains malicious code.\n    cwe: CWE-77\n    function_names:\n      - sendSNSMessage\n    filenames:\n      - nevado-jms/src/main/java/org/skyscreamer/nevado/jms/connector/mock/MockSQSConnector.java\n    classification: slightly promising\n  - headline: Potential SQL injection in PropertyConversionTest\n    analysis: |\n      The PropertyConversionTest class does not properly sanitize the input values for the property conversion methods. This could lead to a SQL injection vulnerability if the message properties contain malicious SQL content.\n    cwe: CWE-89\n    function_names:\n      - testValidValues\n      - testInvalidValues\n    filenames:\n      - nevado-jms/src/test/java/org/skyscreamer/nevado/jms/properties/PropertyConversionTest.java\n    classification: not promising\n```",
      "date": "2024-06-13T11:45:51.468081",
      "usage": {
        "prompt_tokens": 167401,
        "completion_tokens": 749,
        "cost": 0.0427865
      }
    }
  ],
  "leads": [
    {
      "headline": "Potential buffer overflow in NevadoBytesMessage.readBytes()",
      "analysis": "The NevadoBytesMessage.readBytes() method does not perform proper bounds checking on the provided byte array buffer. This could lead to a buffer overflow vulnerability if the message body is larger than the provided buffer.\n",
      "classification": "very promising",
      "cwe": "CWE-119",
      "function_names": [
        "readBytes"
      ],
      "filenames": [
        "nevado-jms/src/main/java/org/skyscreamer/nevado/jms/message/NevadoBytesMessage.java"
      ]
    },
    {
      "headline": "Potential integer overflow in NevadoStreamMessage.readInt()",
      "analysis": "The NevadoStreamMessage.readInt() method does not perform proper overflow checks on the read integer value. This could lead to an integer overflow vulnerability if the message body contains a crafted integer value.\n",
      "classification": "very promising",
      "cwe": "CWE-190",
      "function_names": [
        "readInt"
      ],
      "filenames": [
        "nevado-jms/src/main/java/org/skyscreamer/nevado/jms/message/NevadoStreamMessage.java"
      ]
    },
    {
      "headline": "Potential XML injection in TextMessageTest.testXmlMessage()",
      "analysis": "The TextMessageTest.testXmlMessage() method does not properly sanitize the XML message body before parsing it. This could lead to an XML injection vulnerability if the message body contains malicious XML content.\n",
      "classification": "slightly promising",
      "cwe": "CWE-91",
      "function_names": [
        "testXmlMessage"
      ],
      "filenames": [
        "nevado-jms/src/test/java/org/skyscreamer/nevado/jms/message/TextMessageTest.java"
      ]
    },
    {
      "headline": "Potential command injection in MockSQSConnector.sendSNSMessage()",
      "analysis": "The MockSQSConnector.sendSNSMessage() method does not properly sanitize the serialized message body before passing it to the SNS service. This could lead to a command injection vulnerability if the message body contains malicious code.\n",
      "classification": "slightly promising",
      "cwe": "CWE-77",
      "function_names": [
        "sendSNSMessage"
      ],
      "filenames": [
        "nevado-jms/src/main/java/org/skyscreamer/nevado/jms/connector/mock/MockSQSConnector.java"
      ]
    },
    {
      "headline": "Potential SQL injection in PropertyConversionTest",
      "analysis": "The PropertyConversionTest class does not properly sanitize the input values for the property conversion methods. This could lead to a SQL injection vulnerability if the message properties contain malicious SQL content.\n",
      "classification": "not promising",
      "cwe": "CWE-89",
      "function_names": [
        "testValidValues",
        "testInvalidValues"
      ],
      "filenames": [
        "nevado-jms/src/test/java/org/skyscreamer/nevado/jms/properties/PropertyConversionTest.java"
      ]
    }
  ],
  "scores": [
    {
      "stats": {
        "fn": 1,
        "tp": 0,
        "fp": 2
      },
      "mapping": {},
      "vuln_dates": {
        "CVE-2023-31826": "2023-05-23T01:15:10"
      },
      "scoring_model": "claude-3-opus-20240229",
      "type": "llm",
      "instruction_template_hash": "245ace12b6361954d0a2"
    }
  ],
  "instruction_template_hash": "10c0163db4740318a544",
  "version": "0.1.0"
}
