{
  "commit": "39aaa2bb3cfba1101173b5706438a0d9d6d0b229",
  "repo_url": "https://github.com/mannyvergel/oils-js",
  "model": "claude-3-5-sonnet-20240620",
  "chunk_hashes": [
    "0acce186267f69b8566a"
  ],
  "responses": [
    {
      "content": "```yaml\nleads:\n  - headline: Insecure handling of user input in routing\n    analysis: |\n      The routing logic in core/utils/routeUtils.js uses user-supplied input (route) directly when creating RegExp objects and adding routes. This could allow an attacker to inject malicious regular expressions, potentially leading to ReDoS (Regular Expression Denial of Service) attacks. The code does not properly sanitize or validate the route string before using it to create RegExp objects.\n    cwe: CWE-20\n    function_names:\n      - applyVerbs\n      - handleRequest  \n    filenames:\n      - core/utils/routeUtils.js\n    classification: very promising\n\n  - headline: Potential command injection in file system operations\n    analysis: |\n      The file system operations in core/utils/fileUtils.js use user-supplied input (file paths) directly without proper sanitization. This could potentially allow an attacker to inject malicious commands or access unauthorized files. The code does not validate or sanitize file paths before using them in fs operations like readdir, stat, etc.\n    cwe: CWE-78\n    function_names:\n      - recurseDir\n      - handleFile\n    filenames:  \n      - core/utils/fileUtils.js\n    classification: slightly promising\n\n  - headline: Improper error handling exposes sensitive information\n    analysis: |\n      The error handling in core/utils/routeUtils.js writes error stack traces directly to the response when in debug mode. This could expose sensitive application details to attackers. The code does not properly sanitize error messages before sending them to users.\n    cwe: CWE-209\n    function_names:\n      - showError\n    filenames:\n      - core/utils/routeUtils.js  \n    classification: slightly promising\n\n  - headline: Use of a broken cryptographic algorithm (MD5) \n    analysis: |\n      The code in core/engines/nunjucks/nunjucks.ext.js uses the marked library which defaults to using MD5 for generating heading IDs. MD5 is cryptographically broken and should not be used for security purposes. While this particular usage is likely not security-sensitive, it indicates the use of an outdated library version with potential vulnerabilities.\n    cwe: CWE-327\n    function_names:\n      - MarkedExtension\n    filenames:\n      - core/engines/nunjucks/nunjucks.ext.js\n    classification: not promising\n```",
      "date": "2024-07-08T07:45:52.797217",
      "usage": {
        "prompt_tokens": 18450,
        "completion_tokens": 575,
        "cost": 0.063975
      }
    }
  ],
  "leads": [
    {
      "headline": "Insecure handling of user input in routing",
      "analysis": "The routing logic in core/utils/routeUtils.js uses user-supplied input (route) directly when creating RegExp objects and adding routes. This could allow an attacker to inject malicious regular expressions, potentially leading to ReDoS (Regular Expression Denial of Service) attacks. The code does not properly sanitize or validate the route string before using it to create RegExp objects.\n",
      "classification": "very promising",
      "cwe": "CWE-20",
      "function_names": [
        "applyVerbs",
        "handleRequest"
      ],
      "filenames": [
        "core/utils/routeUtils.js"
      ]
    },
    {
      "headline": "Potential command injection in file system operations",
      "analysis": "The file system operations in core/utils/fileUtils.js use user-supplied input (file paths) directly without proper sanitization. This could potentially allow an attacker to inject malicious commands or access unauthorized files. The code does not validate or sanitize file paths before using them in fs operations like readdir, stat, etc.\n",
      "classification": "slightly promising",
      "cwe": "CWE-78",
      "function_names": [
        "recurseDir",
        "handleFile"
      ],
      "filenames": [
        "core/utils/fileUtils.js"
      ]
    },
    {
      "headline": "Improper error handling exposes sensitive information",
      "analysis": "The error handling in core/utils/routeUtils.js writes error stack traces directly to the response when in debug mode. This could expose sensitive application details to attackers. The code does not properly sanitize error messages before sending them to users.\n",
      "classification": "slightly promising",
      "cwe": "CWE-209",
      "function_names": [
        "showError"
      ],
      "filenames": [
        "core/utils/routeUtils.js"
      ]
    },
    {
      "headline": "Use of a broken cryptographic algorithm (MD5)",
      "analysis": "The code in core/engines/nunjucks/nunjucks.ext.js uses the marked library which defaults to using MD5 for generating heading IDs. MD5 is cryptographically broken and should not be used for security purposes. While this particular usage is likely not security-sensitive, it indicates the use of an outdated library version with potential vulnerabilities.\n",
      "classification": "not promising",
      "cwe": "CWE-327",
      "function_names": [
        "MarkedExtension"
      ],
      "filenames": [
        "core/engines/nunjucks/nunjucks.ext.js"
      ]
    }
  ],
  "scores": [
    {
      "stats": {
        "fn": 1,
        "tp": 0,
        "fp": 1
      },
      "mapping": {},
      "vuln_dates": {
        "CVE-2021-4260": "2022-12-19T14:15:10"
      },
      "scoring_model": "claude-3-5-sonnet-20240620",
      "type": "llm",
      "instruction_template_hash": "245ace12b6361954d0a2"
    }
  ],
  "instruction_template_hash": "10c0163db4740318a544",
  "version": "0.1.0"
}
