{
  "commit": "b43f3bf95421f0bd1bfec0a35cdf94f17616ecb3",
  "repo_url": "https://github.com/frostming/unearth",
  "model": "gpt-4o-2024-05-13",
  "chunk_hashes": [
    "53e287cee6b73de5b4a4"
  ],
  "responses": [
    {
      "content": "```yaml\nleads:\n  - headline: \"Insecure VCS Fetching\"\n    analysis: |\n      The current implementation of VCS (Version Control System) fetching does not validate SSL certificates by default. This allows the download of repositories over insecure connections. Such behavior can lead to Man-in-the-Middle (MitM) attacks where an attacker can intercept and modify the contents being fetched.\n    cwe: CWE-611\n    function_names:\n      - fetch\n    filenames:\n      - src/unearth/vcs/base.py\n      - src/unearth/vcs/git.py\n      - src/unearth/vcs/hg.py\n      - src/unearth/vcs/svn.py\n      - src/unearth/vcs/bazaar.py\n    classification: very promising\n\n  - headline: \"Unvalidated URLs in Index Page Processing\"\n    analysis: |\n      The method `_get_html_response` in `collector.py` processes and utilizes URLs from index pages without proper validation. These URLs are directly used in subsequent HTTP operations, which could lead to exposure and exploitation of untrusted links, causing potential security issues such as SSRF (Server-Side Request Forgery).\n    cwe: CWE-610\n    function_names:\n      - _get_html_response\n    filenames:\n      - src/unearth/collector.py\n    classification: very promising\n\n  - headline: \"Insecure Default Configuration for SVN\"\n    analysis: |\n      The Subversion (SVN) VCS integration does not handle secure authentication properly. The implementation makes use of 'svn' commands without securely handling potential user credentials in URLs or command-line parameters.\n    cwe: CWE-522\n    function_names:\n      - fetch_new\n      - update\n    filenames:\n      - src/unearth/vcs/svn.py\n    classification: very promising\n\n  - headline: \"Potential Directory Traversal in Archive Extraction\"\n    analysis: |\n      The archive extraction methods `_unzip_archive` and `_untar_archive` do not properly validate file paths within the archive. This can lead to directory traversal attacks where an attacker may place files outside the intended directory, potentially overwriting system files.\n    cwe: CWE-22\n    function_names:\n      - _unzip_archive\n      - _untar_archive\n    filenames:\n      - src/unearth/preparer.py\n    classification: very promising\n\n  - headline: \"Race Condition in Temporary Directory Creation\"\n    analysis: |\n      The use of `TemporaryDirectory` in `_unzip_archive` and `_untar_archive` for holding extracted files can introduce race conditions. An attacker could potentially replace the temporary directory with a symlink, causing the extraction to overwrite critical files.\n    cwe: CWE-367\n    function_names:\n      - _unzip_archive\n      - _untar_archive\n    filenames:\n      - src/unearth/preparer.py\n    classification: very promising\n\n  - headline: \"Untrusted Data in Logging\"\n    analysis: |\n      Several logging statements use user-provided URLs directly, which can lead to logging of malicious content. If logs are accessible by other services or users, this can lead to log injection attacks.\n    cwe: CWE-117\n    function_names:\n      - fetch\n    filenames:\n      - src/unearth/vcs/base.py\n    classification: slightly promising\n\n  - headline: \"Improper Validation of Command Exit Status\"\n    analysis: |\n      In various VCS backends, commands outputs are trusted and not properly validated. This behavior can lead to incorrect handling of command results, which may be manipulated by an attacker.\n    cwe: CWE-755\n    function_names:\n      - run_command\n    filenames:\n      - src/unearth/vcs/base.py\n    classification: slightly promising\n\n  - headline: \"Insufficient Directory Permissions\"\n    analysis: |\n      Directory operations, like those in the VCS fetch operations, do not explicitly set secure permissions, potentially leading to directories being writable by unintended users.\n    cwe: CWE-732\n    function_names:\n      - fetch\n    filenames:\n      - src/unearth/vcs/base.py\n    classification: slightly promising\n\n  - headline: \"Undocumented Feature Flags\"\n    analysis: |\n      Various flags, such as `UNEARTH_LOOSE_FILENAME`, control important aspects of security but are not well documented. This can result in insecure defaults in a user's deployment.\n    cwe: CWE-1284\n    function_names:\n      - evaluate_link\n    filenames:\n      - src/unearth/evaluator.py\n    classification: slightly promising\n```",
      "date": "2024-06-09T12:09:48.984332",
      "usage": {
        "prompt_tokens": 41805,
        "completion_tokens": 932,
        "cost": 0.223005
      }
    }
  ],
  "leads": [
    {
      "headline": "Insecure VCS Fetching",
      "analysis": "The current implementation of VCS (Version Control System) fetching does not validate SSL certificates by default. This allows the download of repositories over insecure connections. Such behavior can lead to Man-in-the-Middle (MitM) attacks where an attacker can intercept and modify the contents being fetched.\n",
      "classification": "very promising",
      "cwe": "CWE-611",
      "function_names": [
        "fetch"
      ],
      "filenames": [
        "src/unearth/vcs/base.py",
        "src/unearth/vcs/git.py",
        "src/unearth/vcs/hg.py"
      ]
    },
    {
      "headline": "Unvalidated URLs in Index Page Processing",
      "analysis": "The method _get_html_response in collector.py processes and utilizes URLs from index pages without proper validation. These URLs are directly used in subsequent HTTP operations, which could lead to exposure and exploitation of untrusted links, causing potential security issues such as SSRF (Server-Side Request Forgery).\n",
      "classification": "very promising",
      "cwe": "CWE-610",
      "function_names": [
        "_get_html_response"
      ],
      "filenames": [
        "src/unearth/collector.py"
      ]
    },
    {
      "headline": "Insecure Default Configuration for SVN",
      "analysis": "The Subversion (SVN) VCS integration does not handle secure authentication properly. The implementation makes use of 'svn' commands without securely handling potential user credentials in URLs or command-line parameters.\n",
      "classification": "very promising",
      "cwe": "CWE-522",
      "function_names": [
        "fetch_new",
        "update"
      ],
      "filenames": [
        "src/unearth/vcs/svn.py"
      ]
    },
    {
      "headline": "Potential Directory Traversal in Archive Extraction",
      "analysis": "The archive extraction methods _unzip_archive and _untar_archive do not properly validate file paths within the archive. This can lead to directory traversal attacks where an attacker may place files outside the intended directory, potentially overwriting system files.\n",
      "classification": "very promising",
      "cwe": "CWE-22",
      "function_names": [
        "_unzip_archive",
        "_untar_archive"
      ],
      "filenames": [
        "src/unearth/preparer.py"
      ]
    },
    {
      "headline": "Race Condition in Temporary Directory Creation",
      "analysis": "The use of TemporaryDirectory in _unzip_archive and _untar_archive for holding extracted files can introduce race conditions. An attacker could potentially replace the temporary directory with a symlink, causing the extraction to overwrite critical files.\n",
      "classification": "very promising",
      "cwe": "CWE-367",
      "function_names": [
        "_unzip_archive",
        "_untar_archive"
      ],
      "filenames": [
        "src/unearth/preparer.py"
      ]
    },
    {
      "headline": "Untrusted Data in Logging",
      "analysis": "Several logging statements use user-provided URLs directly, which can lead to logging of malicious content. If logs are accessible by other services or users, this can lead to log injection attacks.\n",
      "classification": "slightly promising",
      "cwe": "CWE-117",
      "function_names": [
        "fetch"
      ],
      "filenames": [
        "src/unearth/vcs/base.py"
      ]
    },
    {
      "headline": "Improper Validation of Command Exit Status",
      "analysis": "In various VCS backends, commands outputs are trusted and not properly validated. This behavior can lead to incorrect handling of command results, which may be manipulated by an attacker.\n",
      "classification": "slightly promising",
      "cwe": "CWE-755",
      "function_names": [
        "run_command"
      ],
      "filenames": [
        "src/unearth/vcs/base.py"
      ]
    },
    {
      "headline": "Insufficient Directory Permissions",
      "analysis": "Directory operations, like those in the VCS fetch operations, do not explicitly set secure permissions, potentially leading to directories being writable by unintended users.\n",
      "classification": "slightly promising",
      "cwe": "CWE-732",
      "function_names": [
        "fetch"
      ],
      "filenames": [
        "src/unearth/vcs/base.py"
      ]
    },
    {
      "headline": "Undocumented Feature Flags",
      "analysis": "Various flags, such as UNEARTH_LOOSE_FILENAME, control important aspects of security but are not well documented. This can result in insecure defaults in a user's deployment.\n",
      "classification": "slightly promising",
      "cwe": "CWE-1284",
      "function_names": [
        "evaluate_link"
      ],
      "filenames": [
        "src/unearth/evaluator.py"
      ]
    }
  ],
  "scores": [
    {
      "stats": {
        "fn": 1,
        "tp": 0,
        "fp": 5
      },
      "mapping": {},
      "vuln_dates": {
        "CVE-2023-45805": "2023-10-20T19:15:08"
      },
      "scoring_model": "gpt-4o-2024-05-13",
      "type": "llm",
      "instruction_template_hash": "8998f09cf57fca8a6e03"
    }
  ],
  "instruction_template_hash": "10c0163db4740318a544",
  "version": "0.1.0"
}
