{
  "commit": "409c30c0d2d357f3fbc3abd7a80d5c111a738aa2",
  "repo_url": "https://github.com/tadashi-aikawa/owlmixin",
  "model": "gpt-4-turbo-2024-04-09",
  "chunk_hashes": [
    "7e44a5a941e5eae71fc9"
  ],
  "responses": [
    {
      "content": "```yaml\nleads:\n  - headline: Exposure of sensitive data through environment variables\n    analysis: |\n      The deployment script 'release.sh' utilizes environment variables for handling sensitive data like PyPI passwords. This approach exposes sensitive data through the environment, which could be accessed by other processes running on the same or a connected system.\n    cwe: CWE-532\n    function_names: []\n    filenames:\n      - ./release.sh\n    classification: very promising\n\n  - headline: Inadequate encryption strength and insecure cryptographic storage\n    analysis: |\n      The script 'release.sh' uses environment variables to handle sensitive information without any form of encryption or secure storage practices, which could lead to exposure of sensitive data such as passwords.\n    cwe: CWE-312\n    function_names: []\n    filenames:\n      - ./release.sh\n    classification: very promising\n\n  - headline: Improper neutralization of input during web page generation\n    analysis: |\n      The project contains instances where special elements are not properly neutralized, which can lead to Cross-Site Scripting (XSS) attacks. Specifically, the usage of user input in function arguments without adequate sanitation could lead to the injection of malicious code into the web pages generated by the application.\n    cwe: CWE-79\n    function_names:\n      - replace_keys\n    filenames:\n      - ./owlmixin/util.py\n    classification: slightly promising\n\n  - headline: Insecure deserialization of untrusted data\n    analysis: |\n      The project deserializes data without sufficient validation, allowing attackers to modify the serialized objects before they are deserialized, potentially leading to arbitrary code execution.\n    cwe: CWE-502\n    function_names:\n      - load_json\n      - load_json_url\n    filenames:\n      - ./owlmixin/util.py\n    classification: very promising\n\n  - headline: Improper access control mechanisms\n    analysis: |\n      The application does not properly enforce access control mechanisms, which could allow unauthorized users to access sensitive functions or data that should be restricted.\n    cwe: CWE-284\n    function_names:\n      - from_dict\n      - from_json\n      - from_yaml\n    filenames:\n      - ./owlmixin/__init__.py\n    classification: slightly promising\n\n  - headline: Use of hard-coded credentials\n    analysis: |\n      Within the codebase, there are potential uses of hard-coded credentials which could lead to security vulnerabilities if the credentials are compromised or exposed.\n    cwe: CWE-798\n    function_names: []\n    filenames:\n      - ./release.sh\n    classification: slightly promising\n\n  - headline: Improper verification of cryptographic signature\n    analysis: |\n      There may be insufficient verification of cryptographic signatures within the project, potentially allowing attackers to alter data without detection.\n    cwe: CWE-347\n    function_names:\n      - verify_signature\n    filenames:\n      - ./owlmixin/owlenum.py\n    classification: slightly promising\n```",
      "date": "2024-07-08T08:53:15.272102",
      "usage": {
        "prompt_tokens": 33739,
        "completion_tokens": 612,
        "cost": 0.35575
      }
    }
  ],
  "leads": [
    {
      "headline": "Exposure of sensitive data through environment variables",
      "analysis": "The deployment script 'release.sh' utilizes environment variables for handling sensitive data like PyPI passwords. This approach exposes sensitive data through the environment, which could be accessed by other processes running on the same or a connected system.\n",
      "classification": "very promising",
      "cwe": "CWE-532",
      "function_names": [],
      "filenames": [
        "./release.sh"
      ]
    },
    {
      "headline": "Inadequate encryption strength and insecure cryptographic storage",
      "analysis": "The script 'release.sh' uses environment variables to handle sensitive information without any form of encryption or secure storage practices, which could lead to exposure of sensitive data such as passwords.\n",
      "classification": "very promising",
      "cwe": "CWE-312",
      "function_names": [],
      "filenames": [
        "./release.sh"
      ]
    },
    {
      "headline": "Improper neutralization of input during web page generation",
      "analysis": "The project contains instances where special elements are not properly neutralized, which can lead to Cross-Site Scripting (XSS) attacks. Specifically, the usage of user input in function arguments without adequate sanitation could lead to the injection of malicious code into the web pages generated by the application.\n",
      "classification": "slightly promising",
      "cwe": "CWE-79",
      "function_names": [
        "replace_keys"
      ],
      "filenames": [
        "./owlmixin/util.py"
      ]
    },
    {
      "headline": "Insecure deserialization of untrusted data",
      "analysis": "The project deserializes data without sufficient validation, allowing attackers to modify the serialized objects before they are deserialized, potentially leading to arbitrary code execution.\n",
      "classification": "very promising",
      "cwe": "CWE-502",
      "function_names": [
        "load_json",
        "load_json_url"
      ],
      "filenames": [
        "./owlmixin/util.py"
      ]
    },
    {
      "headline": "Improper access control mechanisms",
      "analysis": "The application does not properly enforce access control mechanisms, which could allow unauthorized users to access sensitive functions or data that should be restricted.\n",
      "classification": "slightly promising",
      "cwe": "CWE-284",
      "function_names": [
        "from_dict",
        "from_json",
        "from_yaml"
      ],
      "filenames": [
        "./owlmixin/__init__.py"
      ]
    },
    {
      "headline": "Use of hard-coded credentials",
      "analysis": "Within the codebase, there are potential uses of hard-coded credentials which could lead to security vulnerabilities if the credentials are compromised or exposed.\n",
      "classification": "slightly promising",
      "cwe": "CWE-798",
      "function_names": [],
      "filenames": [
        "./release.sh"
      ]
    },
    {
      "headline": "Improper verification of cryptographic signature",
      "analysis": "There may be insufficient verification of cryptographic signatures within the project, potentially allowing attackers to alter data without detection.\n",
      "classification": "slightly promising",
      "cwe": "CWE-347",
      "function_names": [
        "verify_signature"
      ],
      "filenames": [
        "./owlmixin/owlenum.py"
      ]
    }
  ],
  "scores": [
    {
      "stats": {
        "fn": 1,
        "tp": 0,
        "fp": 3
      },
      "mapping": {},
      "vuln_dates": {
        "CVE-2017-16618": "2017-11-08T03:29:00"
      },
      "scoring_model": "claude-3-5-sonnet-20240620",
      "type": "llm",
      "instruction_template_hash": "245ace12b6361954d0a2"
    }
  ],
  "instruction_template_hash": "10c0163db4740318a544",
  "version": "0.1.0"
}
