{
  "commit": "d8c4783fe099f56ae8c0ecb87048ded99ba72020",
  "repo_url": "https://github.com/latchset/jwcrypto",
  "model": "gpt-4-turbo-2024-04-09",
  "chunk_hashes": [
    "a94648c967cd870ac182"
  ],
  "responses": [
    {
      "content": "```yaml\nleads:\n  - headline: \"Insecure use of cryptography with RSA key of insufficient size\"\n    analysis: |\n      The RSA key used in the example is of 1024 bits, which is considered insecure due to advancements in computational power that make it feasible to factor such keys. Using such an insufficient key size undermines the security of the encryption and signing processes, making it potentially vulnerable to attacks which could lead to the disclosure of sensitive encrypted information or the forging of signatures.\n    cwe: CWE-326\n    function_names:\n      - generate_key\n    filenames:\n      - jwcrypto/tests.py\n    classification: very promising\n\n  - headline: \"Lack of proper error handling in JWT deserialization\"\n    analysis: |\n      The JWT deserialization process does not properly handle malformed JWTs, missing key IDs, or missing keys. This could lead to unhandled exceptions or security vulnerabilities if an attacker can manipulate the JWT payload or headers in such a way that triggers an error state not appropriately caught by the application logic.\n    cwe: CWE-755\n    function_names:\n      - deserialize\n    filenames:\n      - jwcrypto/jwt.py\n    classification: slightly promising\n\n  - headline: \"Use of hard-coded cryptographic key in JWT processing\"\n    analysis: |\n      Hard-coded cryptographic keys are found within the JWT processing code. These embedded keys can be extracted by an attacker, which would compromise the integrity and confidentiality of the tokenization process. Hard-coded keys limit the flexibility to rotate or change keys without modifying and redeploying the application.\n    cwe: CWE-321\n    function_names:\n      - test_A1\n      - test_A2\n    filenames:\n      - jwcrypto/tests.py\n    classification: very promising\n\n  - headline: \"Insufficient validation of JWT claims leading to bypass\"\n    analysis: |\n      JWT implementation lacks robust validation of claims such as expiration ('exp') and not before ('nbf') times, as well as checking for the presence of critical claims like 'iss' (issuer) and 'sub' (subject). Failure to properly validate these claims can allow attackers to use expired, not yet valid, or improperly issued tokens.\n    cwe: CWE-20\n    function_names:\n      - _check_provided_claims\n    filenames:\n      - jwcrypto/jwt.py\n    classification: slightly promising\n\n  - headline: \"Potential exposure of sensitive information via error messages\"\n    analysis: |\n      Error handling in the JWT and JWE implementations may expose sensitive information through detailed error messages that include stack traces or specific cryptographic states. This information might help an attacker infer the internal state of the application or cryptographic values.\n    cwe: CWE-209\n    function_names:\n      - JWTExpired\n      - JWTInvalidClaimValue\n    filenames:\n      - jwcrypto/jwt.py\n      - jwcrypto/jwe.py\n    classification: slightly promising\n\n  - headline: \"Use of deprecated cryptographic practices in JWT\"\n    analysis: |\n      Using RSA1_5 (RSAES-PKCS1-v1_5) for JWT encryption might lead to vulnerabilities. This padding scheme is considered insecure and susceptible to Bleichenbacher's attack, which could allow attackers to decrypt messages or forge a valid signature.\n    cwe: CWE-327\n    function_names:\n      - test_A1\n    filenames:\n      - jwcrypto/tests.py\n    classification: slightly promising\n```",
      "date": "2024-06-09T13:09:47.246139",
      "usage": {
        "prompt_tokens": 73423,
        "completion_tokens": 709,
        "cost": 0.7555
      }
    }
  ],
  "leads": [
    {
      "headline": "Insecure use of cryptography with RSA key of insufficient size",
      "analysis": "The RSA key used in the example is of 1024 bits, which is considered insecure due to advancements in computational power that make it feasible to factor such keys. Using such an insufficient key size undermines the security of the encryption and signing processes, making it potentially vulnerable to attacks which could lead to the disclosure of sensitive encrypted information or the forging of signatures.\n",
      "classification": "very promising",
      "cwe": "CWE-326",
      "function_names": [
        "generate_key"
      ],
      "filenames": [
        "jwcrypto/tests.py"
      ]
    },
    {
      "headline": "Lack of proper error handling in JWT deserialization",
      "analysis": "The JWT deserialization process does not properly handle malformed JWTs, missing key IDs, or missing keys. This could lead to unhandled exceptions or security vulnerabilities if an attacker can manipulate the JWT payload or headers in such a way that triggers an error state not appropriately caught by the application logic.\n",
      "classification": "slightly promising",
      "cwe": "CWE-755",
      "function_names": [
        "deserialize"
      ],
      "filenames": [
        "jwcrypto/jwt.py"
      ]
    },
    {
      "headline": "Use of hard-coded cryptographic key in JWT processing",
      "analysis": "Hard-coded cryptographic keys are found within the JWT processing code. These embedded keys can be extracted by an attacker, which would compromise the integrity and confidentiality of the tokenization process. Hard-coded keys limit the flexibility to rotate or change keys without modifying and redeploying the application.\n",
      "classification": "very promising",
      "cwe": "CWE-321",
      "function_names": [
        "test_A1",
        "test_A2"
      ],
      "filenames": [
        "jwcrypto/tests.py"
      ]
    },
    {
      "headline": "Insufficient validation of JWT claims leading to bypass",
      "analysis": "JWT implementation lacks robust validation of claims such as expiration ('exp') and not before ('nbf') times, as well as checking for the presence of critical claims like 'iss' (issuer) and 'sub' (subject). Failure to properly validate these claims can allow attackers to use expired, not yet valid, or improperly issued tokens.\n",
      "classification": "slightly promising",
      "cwe": "CWE-20",
      "function_names": [
        "_check_provided_claims"
      ],
      "filenames": [
        "jwcrypto/jwt.py"
      ]
    },
    {
      "headline": "Potential exposure of sensitive information via error messages",
      "analysis": "Error handling in the JWT and JWE implementations may expose sensitive information through detailed error messages that include stack traces or specific cryptographic states. This information might help an attacker infer the internal state of the application or cryptographic values.\n",
      "classification": "slightly promising",
      "cwe": "CWE-209",
      "function_names": [
        "JWTExpired",
        "JWTInvalidClaimValue"
      ],
      "filenames": [
        "jwcrypto/jwt.py",
        "jwcrypto/jwe.py"
      ]
    },
    {
      "headline": "Use of deprecated cryptographic practices in JWT",
      "analysis": "Using RSA1_5 (RSAES-PKCS1-v1_5) for JWT encryption might lead to vulnerabilities. This padding scheme is considered insecure and susceptible to Bleichenbacher's attack, which could allow attackers to decrypt messages or forge a valid signature.\n",
      "classification": "slightly promising",
      "cwe": "CWE-327",
      "function_names": [
        "test_A1"
      ],
      "filenames": [
        "jwcrypto/tests.py"
      ]
    }
  ],
  "scores": [
    {
      "stats": {
        "fn": 2,
        "tp": 0,
        "fp": 2
      },
      "mapping": {},
      "vuln_dates": {
        "CVE-2016-6298": "2016-09-01T23:59:01",
        "CVE-2024-28102": "2024-03-21T02:52:23"
      },
      "scoring_model": "gpt-4o-2024-05-13",
      "type": "llm",
      "instruction_template_hash": "8998f09cf57fca8a6e03"
    }
  ],
  "instruction_template_hash": "10c0163db4740318a544",
  "version": "0.1.0"
}
