{
  "commit": "571a251045877de6f537a259f1937f4a7ca873a4",
  "repo_url": "https://github.com/dogukanurker/flaskblog",
  "model": "gpt-4o-2024-05-13",
  "chunk_hashes": [
    "c3d0edf0098023bca88c"
  ],
  "responses": [
    {
      "content": "```yaml\nleads:\n  - headline: SQL Injection Vulnerability in deleteUser Function\n    analysis: |\n      The deleteUser function in delete.py is vulnerable to SQL Injection. In multiple instances, user-supplied input is directly placed into SQL commands without proper parameterization or escaping. This allows an attacker to potentially execute arbitrary SQL commands by manipulating the userName parameter. Specifically:\n      1. Lines like `cursor.execute(f'select * from users where lower(userName) = \"{userName.lower()}\"')` directly use the userName in the SQL statement.\n      2. The same issue persists across other similar lines in the function.\n    cwe: CWE-89\n    function_names:\n      - deleteUser\n    filenames:\n      - delete.py\n    classification: very promising\n\n  - headline: SQL Injection Vulnerability in deletePost Function\n    analysis: |\n      The deletePost function in delete.py is vulnerable to SQL Injection. User-supplied input postID is directly placed into SQL commands without parameterization. This exposes the function to potential attacks where an attacker can manipulate the postID to execute arbitrary SQL code. Specifically:\n      1. Lines like `cursor.execute(f\"select author from posts where id = {postID}\")` use postID directly in the SQL query.\n      2. This pattern is repeated in subsequent SQL commands within the function.\n    cwe: CWE-89\n    function_names:\n      - deletePost\n    filenames:\n      - delete.py\n    classification: very promising\n\n  - headline: SQL Injection Vulnerability in deleteComment Function\n    analysis: |\n      Similar to deleteUser and deletePost, the deleteComment function in delete.py is vulnerable to SQL Injection. The user-supplied commentID is placed directly into SQL queries without proper escaping or parameterization:\n      1. Lines like `cursor.execute(f\"select user from comments where id = {commentID}\")` use commentID directly in the SQL statement.\n    cwe: CWE-89\n    function_names:\n      - deleteComment\n    filenames:\n      - delete.py\n    classification: very promising\n\n  - headline: Insufficient Anti-CSRF Protection in Sensitive Routes\n    analysis: |\n      Several routes that perform critical actions such as deleting user accounts, comments, or posts lack sufficient anti-CSRF protection. These routes rely solely on session checks but do not employ CSRF tokens to ensure the legitimacy of the requests. For example:\n      1. The `/deletePost`, `/deleteUser`, and similar routes do not handle CSRF tokens or make use of the CSRF protection utility provided by flask_wtf, which might be implemented in different parts of the application but is overlooked in these critical areas.\n    cwe: CWE-352\n    function_names: []\n    filenames: []\n    classification: slightly promising\n\n  - headline: Hardcoded Credentials in Email Configuration\n    analysis: |\n      Hardcoded credentials for the email service are present in the passwordReset and verifyUser routes. The access information for the email account is hardcoded in the file, potentially exposing it to unauthorized access. For example:\n      1. Lines like `server.login(\"flaskblogdogukanurker@gmail.com\", \"lsooxsmnsfnhnixy\")` directly include email credentials.\n    cwe: CWE-798\n    function_names: []\n    filenames:\n      - routes/passwordReset.py\n      - routes/verifyUser.py\n    classification: very promising\n\n  - headline: Insecure Credential Storage and Management\n    analysis: |\n      User passwords are hashed using the sha256_crypt algorithm, but there are patterns that indicate possible inadequate password protections. For example:\n      1. Password checks are conducted by calling `sha256_crypt.verify(password, oldPassword)` which is secure, but the overall management and update mechanisms need to be reviewed.\n      2. There is a potential lack of salting before hashing.\n    cwe: CWE-522\n    function_names: []\n    filenames: []\n    classification: slightly promising\n\n  - headline: Cross-site Scripting (XSS) in Comment Handling\n    analysis: |\n      The application accepts and displays comments without proper escaping or sanitizing. This could lead to stored XSS vulnerabilities where a malicious user could inject scripts into comments that would execute in the context of other users viewing those comments:\n      1. The function `post` in the post route directly accepts and renders user comments using `form.comment` without apparent sanitization.\n    cwe: CWE-79\n    function_names:\n      - post\n    filenames:\n      - routes/post.py\n    classification: very promising\n\n  - headline: Possible Open Redirect in Redirect Functions\n    analysis: |\n      The redirect functionality implemented in the application potentially includes open redirects where user-supplied input (e.g., redirect paths) is used to construct URLs without sufficient validation. This might allow attackers to redirect users to malicious sites using crafted URLs.\n    cwe: CWE-601\n    function_names: []\n    filenames: []\n    classification: slightly promising\n```",
      "date": "2024-06-09T11:31:51.865536",
      "usage": {
        "prompt_tokens": 22965,
        "completion_tokens": 1042,
        "cost": 0.130455
      }
    }
  ],
  "leads": [
    {
      "headline": "SQL Injection Vulnerability in deleteUser Function",
      "analysis": "The deleteUser function in delete.py is vulnerable to SQL Injection. In multiple instances, user-supplied input is directly placed into SQL commands without proper parameterization or escaping. This allows an attacker to potentially execute arbitrary SQL commands by manipulating the userName parameter. Specifically:\n1. Lines like cursor.execute(f'select * from users where lower(userName) = \"{userName.lower()}\"') directly use the userName in the SQL statement.\n2. The same issue persists across other similar lines in the function.\n",
      "classification": "very promising",
      "cwe": "CWE-89",
      "function_names": [
        "deleteUser"
      ],
      "filenames": [
        "delete.py"
      ]
    },
    {
      "headline": "SQL Injection Vulnerability in deletePost Function",
      "analysis": "The deletePost function in delete.py is vulnerable to SQL Injection. User-supplied input postID is directly placed into SQL commands without parameterization. This exposes the function to potential attacks where an attacker can manipulate the postID to execute arbitrary SQL code. Specifically:\n1. Lines like cursor.execute(f\"select author from posts where id = {postID}\") use postID directly in the SQL query.\n2. This pattern is repeated in subsequent SQL commands within the function.\n",
      "classification": "very promising",
      "cwe": "CWE-89",
      "function_names": [
        "deletePost"
      ],
      "filenames": [
        "delete.py"
      ]
    },
    {
      "headline": "SQL Injection Vulnerability in deleteComment Function",
      "analysis": "Similar to deleteUser and deletePost, the deleteComment function in delete.py is vulnerable to SQL Injection. The user-supplied commentID is placed directly into SQL queries without proper escaping or parameterization:\n1. Lines like cursor.execute(f\"select user from comments where id = {commentID}\") use commentID directly in the SQL statement.\n",
      "classification": "very promising",
      "cwe": "CWE-89",
      "function_names": [
        "deleteComment"
      ],
      "filenames": [
        "delete.py"
      ]
    },
    {
      "headline": "Insufficient Anti-CSRF Protection in Sensitive Routes",
      "analysis": "Several routes that perform critical actions such as deleting user accounts, comments, or posts lack sufficient anti-CSRF protection. These routes rely solely on session checks but do not employ CSRF tokens to ensure the legitimacy of the requests. For example:\n1. The /deletePost, /deleteUser, and similar routes do not handle CSRF tokens or make use of the CSRF protection utility provided by flask_wtf, which might be implemented in different parts of the application but is overlooked in these critical areas.\n",
      "classification": "slightly promising",
      "cwe": "CWE-352",
      "function_names": [],
      "filenames": []
    },
    {
      "headline": "Hardcoded Credentials in Email Configuration",
      "analysis": "Hardcoded credentials for the email service are present in the passwordReset and verifyUser routes. The access information for the email account is hardcoded in the file, potentially exposing it to unauthorized access. For example:\n1. Lines like server.login(\"flaskblogdogukanurker@gmail.com\", \"lsooxsmnsfnhnixy\") directly include email credentials.\n",
      "classification": "very promising",
      "cwe": "CWE-798",
      "function_names": [],
      "filenames": [
        "routes/passwordReset.py",
        "routes/verifyUser.py"
      ]
    },
    {
      "headline": "Insecure Credential Storage and Management",
      "analysis": "User passwords are hashed using the sha256_crypt algorithm, but there are patterns that indicate possible inadequate password protections. For example:\n1. Password checks are conducted by calling sha256_crypt.verify(password, oldPassword) which is secure, but the overall management and update mechanisms need to be reviewed.\n2. There is a potential lack of salting before hashing.\n",
      "classification": "slightly promising",
      "cwe": "CWE-522",
      "function_names": [],
      "filenames": []
    },
    {
      "headline": "Cross-site Scripting (XSS) in Comment Handling",
      "analysis": "The application accepts and displays comments without proper escaping or sanitizing. This could lead to stored XSS vulnerabilities where a malicious user could inject scripts into comments that would execute in the context of other users viewing those comments:\n1. The function post in the post route directly accepts and renders user comments using form.comment without apparent sanitization.\n",
      "classification": "very promising",
      "cwe": "CWE-79",
      "function_names": [
        "post"
      ],
      "filenames": [
        "routes/post.py"
      ]
    },
    {
      "headline": "Possible Open Redirect in Redirect Functions",
      "analysis": "The redirect functionality implemented in the application potentially includes open redirects where user-supplied input (e.g., redirect paths) is used to construct URLs without sufficient validation. This might allow attackers to redirect users to malicious sites using crafted URLs.\n",
      "classification": "slightly promising",
      "cwe": "CWE-601",
      "function_names": [],
      "filenames": []
    }
  ],
  "scores": [
    {
      "stats": {
        "fn": 1,
        "tp": 0,
        "fp": 5
      },
      "mapping": {},
      "vuln_dates": {
        "CVE-2024-22414": "2024-01-17T21:15:12"
      },
      "scoring_model": "gpt-4o-2024-05-13",
      "type": "llm",
      "instruction_template_hash": "8998f09cf57fca8a6e03"
    },
    {
      "stats": {
        "fn": 0,
        "tp": 1,
        "fp": 4
      },
      "mapping": {
        "4": "CVE-2024-22414"
      },
      "vuln_dates": {
        "CVE-2024-22414": "2024-01-17T21:15:12"
      },
      "scoring_model": "claude-3-opus-20240229",
      "type": "llm",
      "instruction_template_hash": "245ace12b6361954d0a2"
    }
  ],
  "instruction_template_hash": "10c0163db4740318a544",
  "version": "0.1.0"
}
