{
  "commit": "128d5e30b4d958b8f73fb3829dcfb86082fd50ec",
  "repo_url": "https://github.com/jenkinsci/digitalocean-plugin",
  "model": "claude-3-opus-20240229",
  "chunk_hashes": [
    "7880725b1a534d9ac3f5"
  ],
  "responses": [
    {
      "content": "Here is the YAML output with the requested vulnerability leads:\n\n```yaml\nleads:\n  - headline: Unsafe deserialization in XStream2 usage\n    analysis: |\n      The DigitalOceanCloud class uses the XStream2 library to deserialize cloud configurations. \n      It registers a custom converter ConverterImpl that does not appear to restrict the types \n      of objects that can be deserialized. Deserializing untrusted data without type restrictions\n      can allow remote code execution attacks if an attacker can control the serialized data.\n      An attacker may be able to provide a malicious serialized object that executes code during\n      deserialization.\n    cwe: CWE-502\n    function_names: \n      - DigitalOceanCloud$ConverterImpl.unmarshal\n    filenames:\n      - src/main/java/com/dubture/jenkins/digitalocean/DigitalOceanCloud.java\n    classification: very promising\n    \n  - headline: SSRF in DigitalOcean API client \n    analysis: |\n      The DigitalOceanClient is used in various places to make API requests to DigitalOcean\n      to provision droplets, get information about images, sizes, regions etc. User controlled \n      parameters from Jenkins forms are passed to the client methods and used to construct URLs\n      for the API requests. If the parameters are not validated, an attacker could potentially\n      provide a URL pointing to a different host, leading to Server-Side Request Forgery (SSRF).\n      The impact depends on what the DigitalOcean service allows - an attacker may be able to\n      access internal endpoints or services.\n    cwe: CWE-918\n    function_names:\n      - DigitalOcean.getAvailableSizes\n      - DigitalOcean.getAvailableImages \n      - DigitalOcean.getAvailableRegions\n    filenames:\n      - src/main/java/com/dubture/jenkins/digitalocean/DigitalOcean.java\n      - src/main/java/com/dubture/jenkins/digitalocean/DigitalOceanCloud.java\n      - src/main/java/com/dubture/jenkins/digitalocean/SlaveTemplate.java  \n    classification: slightly promising\n\n  - headline: Improper authorization of API operations\n    analysis: |\n      The various build steps make DigitalOcean API calls using the configured access token \n      to perform operations like creating droplets, getting lists of droplets, deleting droplets etc.\n      However, there doesn't seem to be any authorization checks or restrictions on which API operations\n      each Jenkins user can perform. Any Jenkins user who can configure clouds and slaves can potentially\n      use the access token to perform any DigitalOcean API operations, even if their Jenkins permissions \n      wouldn't normally allow those actions.\n    cwe: CWE-862\n    function_names:\n      - DigitalOceanCloud.provision \n      - DigitalOcean.getDroplets\n      - DigitalOceanComputer.delete\n    filenames:\n      - src/main/java/com/dubture/jenkins/digitalocean/DigitalOceanCloud.java  \n      - src/main/java/com/dubture/jenkins/digitalocean/DigitalOcean.java\n      - src/main/java/com/dubture/jenkins/digitalocean/DigitalOceanComputer.java\n    classification: slightly promising\n    \n  - headline: Improper restriction of XML external entity reference in user-provided data\n    analysis: |  \n      The SlaveTemplate class allows configuring an optional \"User data\" field which gets passed \n      to the DigitalOcean API when creating droplets. This user data is not sanitized or validated.\n      If an attacker can control the user data, they may be able to provide an XML document with \n      an external entity reference to read arbitrary files accessible to the Jenkins server process.\n    cwe: CWE-611\n    function_names:\n      - SlaveTemplate.provision\n    filenames: \n      - src/main/java/com/dubture/jenkins/digitalocean/SlaveTemplate.java\n    classification: slightly promising\n\n```\n\nThe analysis focused on a few key areas that stood out as potential vulnerabilities based on the provided code. Let me know if you need any clarification or have additional questions!",
      "date": "2024-06-12T18:18:29.613835",
      "usage": {
        "prompt_tokens": 38437,
        "completion_tokens": 1051,
        "cost": 0.65538
      }
    }
  ],
  "leads": [
    {
      "headline": "Unsafe deserialization in XStream2 usage",
      "analysis": "The DigitalOceanCloud class uses the XStream2 library to deserialize cloud configurations. \nIt registers a custom converter ConverterImpl that does not appear to restrict the types \nof objects that can be deserialized. Deserializing untrusted data without type restrictions\ncan allow remote code execution attacks if an attacker can control the serialized data.\nAn attacker may be able to provide a malicious serialized object that executes code during\ndeserialization.\n",
      "classification": "very promising",
      "cwe": "CWE-502",
      "function_names": [
        "DigitalOceanCloud$ConverterImpl.unmarshal"
      ],
      "filenames": [
        "src/main/java/com/dubture/jenkins/digitalocean/DigitalOceanCloud.java"
      ]
    },
    {
      "headline": "SSRF in DigitalOcean API client",
      "analysis": "The DigitalOceanClient is used in various places to make API requests to DigitalOcean\nto provision droplets, get information about images, sizes, regions etc. User controlled \nparameters from Jenkins forms are passed to the client methods and used to construct URLs\nfor the API requests. If the parameters are not validated, an attacker could potentially\nprovide a URL pointing to a different host, leading to Server-Side Request Forgery (SSRF).\nThe impact depends on what the DigitalOcean service allows - an attacker may be able to\naccess internal endpoints or services.\n",
      "classification": "slightly promising",
      "cwe": "CWE-918",
      "function_names": [
        "DigitalOcean.getAvailableSizes",
        "DigitalOcean.getAvailableImages",
        "DigitalOcean.getAvailableRegions"
      ],
      "filenames": [
        "src/main/java/com/dubture/jenkins/digitalocean/DigitalOcean.java",
        "src/main/java/com/dubture/jenkins/digitalocean/DigitalOceanCloud.java",
        "src/main/java/com/dubture/jenkins/digitalocean/SlaveTemplate.java"
      ]
    },
    {
      "headline": "Improper authorization of API operations",
      "analysis": "The various build steps make DigitalOcean API calls using the configured access token \nto perform operations like creating droplets, getting lists of droplets, deleting droplets etc.\nHowever, there doesn't seem to be any authorization checks or restrictions on which API operations\neach Jenkins user can perform. Any Jenkins user who can configure clouds and slaves can potentially\nuse the access token to perform any DigitalOcean API operations, even if their Jenkins permissions \nwouldn't normally allow those actions.\n",
      "classification": "slightly promising",
      "cwe": "CWE-862",
      "function_names": [
        "DigitalOceanCloud.provision",
        "DigitalOcean.getDroplets",
        "DigitalOceanComputer.delete"
      ],
      "filenames": [
        "src/main/java/com/dubture/jenkins/digitalocean/DigitalOceanCloud.java",
        "src/main/java/com/dubture/jenkins/digitalocean/DigitalOcean.java",
        "src/main/java/com/dubture/jenkins/digitalocean/DigitalOceanComputer.java"
      ]
    },
    {
      "headline": "Improper restriction of XML external entity reference in user-provided data",
      "analysis": "The SlaveTemplate class allows configuring an optional \"User data\" field which gets passed \nto the DigitalOcean API when creating droplets. This user data is not sanitized or validated.\nIf an attacker can control the user data, they may be able to provide an XML document with \nan external entity reference to read arbitrary files accessible to the Jenkins server process.\n",
      "classification": "slightly promising",
      "cwe": "CWE-611",
      "function_names": [
        "SlaveTemplate.provision"
      ],
      "filenames": [
        "src/main/java/com/dubture/jenkins/digitalocean/SlaveTemplate.java"
      ]
    }
  ],
  "scores": [
    {
      "stats": {
        "fn": 1,
        "tp": 0,
        "fp": 1
      },
      "mapping": {},
      "vuln_dates": {
        "CVE-2020-2126": "2020-02-12T15:15:14"
      },
      "scoring_model": "claude-3-opus-20240229",
      "type": "llm",
      "instruction_template_hash": "245ace12b6361954d0a2"
    }
  ],
  "instruction_template_hash": "10c0163db4740318a544",
  "version": "0.1.0"
}
