{
  "commit": "88b2b6c0041ef8df4912f9ff0a9cbbec7a2784d0",
  "repo_url": "https://github.com/blinksocks/blinksocks",
  "model": "gemini/gemini-1.5-pro",
  "chunk_hashes": [
    "e1aa3a5cd7c60faac2da"
  ],
  "responses": [
    {
      "content": "```yaml\nleads:\n  - headline: Insecure default permissions for critical resource in ci-install-curl.sh\n    analysis: |\n      The `ci-install-curl.sh` script utilizes `sudo make install` to install curl. \n      By default, the installation may assign insecure permissions to critical curl files or directories, \n      potentially allowing unauthorized users to modify them.\n    cwe: CWE-732\n    function_names: []\n    filenames:\n      - ci-install-curl.sh\n    classification: slightly promising\n  - headline: Potential URL redirection vulnerability in relay.js\n    analysis: |\n      The `onPresetFailed` function in `relay.js` handles redirecting traffic based on the `config.redirect` setting. \n      If the `redirect` parameter is externally controllable and not properly validated, \n      it may be possible to redirect traffic to an arbitrary host, potentially leading to an open redirect vulnerability. \n      Exploiting this would require controlling the `redirect` parameter and triggering a preset failure scenario.\n    cwe: CWE-601\n    function_names:\n      - onPresetFailed\n    filenames:\n      - src/core/relay.js\n    classification: slightly promising\n  - headline: Potential argument injection vulnerability in ci-install-curl.sh\n    analysis: |\n      The script `ci-install-curl.sh` uses user-supplied arguments without proper sanitization when executing `wget` and `./configure`. \n      If an attacker can control these arguments, they may be able to inject malicious code or commands. \n      Exploitation requires the ability to influence arguments passed to the script.\n    cwe: CWE-88\n    function_names: []\n    filenames:\n      - ci-install-curl.sh\n    classification: slightly promising\n  - headline: Potential exposure of sensitive information in src/constants.js\n    analysis: |\n      In `src/constants.js`, a random APP_ID is generated using `randomBytes(16).toString('hex')`. \n      If the random number generator used by `randomBytes` has insufficient entropy, the generated APP_ID might be predictable. \n      While unlikely, an attacker who can predict the APP_ID might be able to impersonate or interfere with client-server communication.\n    cwe: CWE-330\n    function_names: []\n    filenames:\n      - src/constants.js\n    classification: not promising\n  - headline: Potential command injection vulnerability in ci-install-curl.sh\n    analysis: |\n      The script `ci-install-curl.sh` executes `wget` and `./configure` with user-provided arguments without proper sanitization. \n      This might lead to potential command injection vulnerabilities if the script is executed with attacker-controlled arguments.\n    cwe: CWE-77\n    function_names: []\n    filenames:\n      - ci-install-curl.sh\n    classification: not promising\n  - headline: Potential race condition vulnerability in relay.js\n    analysis: |\n      In `src/core/relay.js`, the `onBoundClose` function handles closing the relay. \n      However, there is a potential race condition: if `anotherBound` is closed between the check for `anotherBound.__closed` and the call to `this.destroy()`, \n      the relay might not be properly destroyed, leading to potential resource leaks or unexpected behavior.\n    cwe: CWE-362\n    function_names:\n      - onBoundClose\n    filenames:\n      - src/core/relay.js\n    classification: not promising\n  - headline: Uncontrolled recursion in src/core/acl.js\n    analysis: |\n      The `parseHost` function in `src/core/acl.js` recursively calls itself without a proper base case, potentially leading to a stack overflow vulnerability.\n    cwe: CWE-674\n    function_names:\n      - parseHost\n    filenames:\n      - src/core/acl.js\n    classification: not promising\n```",
      "date": "2024-06-12T11:49:13.733297",
      "usage": {
        "prompt_tokens": 158056,
        "completion_tokens": 792,
        "cost": 0.10027000000000001
      }
    }
  ],
  "leads": [
    {
      "headline": "Insecure default permissions for critical resource in ci-install-curl.sh",
      "analysis": "The ci-install-curl.sh script utilizes sudo make install to install curl. \nBy default, the installation may assign insecure permissions to critical curl files or directories, \npotentially allowing unauthorized users to modify them.\n",
      "classification": "slightly promising",
      "cwe": "CWE-732",
      "function_names": [],
      "filenames": [
        "ci-install-curl.sh"
      ]
    },
    {
      "headline": "Potential URL redirection vulnerability in relay.js",
      "analysis": "The onPresetFailed function in relay.js handles redirecting traffic based on the config.redirect setting. \nIf the redirect parameter is externally controllable and not properly validated, \nit may be possible to redirect traffic to an arbitrary host, potentially leading to an open redirect vulnerability. \nExploiting this would require controlling the redirect parameter and triggering a preset failure scenario.\n",
      "classification": "slightly promising",
      "cwe": "CWE-601",
      "function_names": [
        "onPresetFailed"
      ],
      "filenames": [
        "src/core/relay.js"
      ]
    },
    {
      "headline": "Potential argument injection vulnerability in ci-install-curl.sh",
      "analysis": "The script ci-install-curl.sh uses user-supplied arguments without proper sanitization when executing wget and ./configure. \nIf an attacker can control these arguments, they may be able to inject malicious code or commands. \nExploitation requires the ability to influence arguments passed to the script.\n",
      "classification": "slightly promising",
      "cwe": "CWE-88",
      "function_names": [],
      "filenames": [
        "ci-install-curl.sh"
      ]
    },
    {
      "headline": "Potential exposure of sensitive information in src/constants.js",
      "analysis": "In src/constants.js, a random APP_ID is generated using randomBytes(16).toString('hex'). \nIf the random number generator used by randomBytes has insufficient entropy, the generated APP_ID might be predictable. \nWhile unlikely, an attacker who can predict the APP_ID might be able to impersonate or interfere with client-server communication.\n",
      "classification": "not promising",
      "cwe": "CWE-330",
      "function_names": [],
      "filenames": [
        "src/constants.js"
      ]
    },
    {
      "headline": "Potential command injection vulnerability in ci-install-curl.sh",
      "analysis": "The script ci-install-curl.sh executes wget and ./configure with user-provided arguments without proper sanitization. \nThis might lead to potential command injection vulnerabilities if the script is executed with attacker-controlled arguments.\n",
      "classification": "not promising",
      "cwe": "CWE-77",
      "function_names": [],
      "filenames": [
        "ci-install-curl.sh"
      ]
    },
    {
      "headline": "Potential race condition vulnerability in relay.js",
      "analysis": "In src/core/relay.js, the onBoundClose function handles closing the relay. \nHowever, there is a potential race condition: if anotherBound is closed between the check for anotherBound.__closed and the call to this.destroy(), \nthe relay might not be properly destroyed, leading to potential resource leaks or unexpected behavior.\n",
      "classification": "not promising",
      "cwe": "CWE-362",
      "function_names": [
        "onBoundClose"
      ],
      "filenames": [
        "src/core/relay.js"
      ]
    },
    {
      "headline": "Uncontrolled recursion in src/core/acl.js",
      "analysis": "The parseHost function in src/core/acl.js recursively calls itself without a proper base case, potentially leading to a stack overflow vulnerability.\n",
      "classification": "not promising",
      "cwe": "CWE-674",
      "function_names": [
        "parseHost"
      ],
      "filenames": [
        "src/core/acl.js"
      ]
    }
  ],
  "scores": [
    {
      "stats": {
        "fn": 1,
        "tp": 0,
        "fp": 0
      },
      "mapping": {},
      "vuln_dates": {
        "CVE-2023-50481": "2023-12-21T11:15:08"
      },
      "scoring_model": "claude-3-opus-20240229",
      "type": "llm",
      "instruction_template_hash": "245ace12b6361954d0a2"
    }
  ],
  "instruction_template_hash": "10c0163db4740318a544",
  "version": "0.1.0"
}
