{
  "commit": "0c351e0378d893fad8b3e1a5f8ecddbc676de63a",
  "repo_url": "https://gitlab.com/marsat/ctparental",
  "model": "claude-3-haiku-20240307",
  "chunk_hashes": [
    "45758b93812f4692ce14"
  ],
  "responses": [
    {
      "content": "```yaml\nleads:\n  - headline: Improper Validation of Specified Quantity in Input\n    analysis: |\n      The `popitup()` function in the `test-pop-up.html` file appears to have a vulnerability where the URL passed as a parameter is not properly validated. The function opens a new window with the specified URL, which could potentially be used to redirect the user to a malicious website.\n    cwe: CWE-1284\n    function_names:\n      - popitup\n    filenames:\n      - test-pop-up.html\n    classification: slightly promising\n  - headline: Improper Neutralization of Special Elements used in an OS Command ('OS Command Injection')\n    analysis: |\n      The `conf_lighttpd/create-mime.conf.pl` script appears to be generating configuration files based on the contents of the `/etc/mime.types` file. However, the script does not properly sanitize the input, which could potentially lead to OS command injection vulnerabilities if the `/etc/mime.types` file contains malicious content.\n    cwe: CWE-78\n    function_names:\n      - add\n    filenames:\n      - conf_lighttpd/create-mime.conf.pl\n    classification: slightly promising\n  - headline: Improper Neutralization of Formula Elements in a CSV File\n    analysis: |\n      The `debian/po/templates.pot` file contains translatable strings that may be used in user input fields. If these strings are not properly sanitized when used in a CSV file, it could lead to formula injection vulnerabilities.\n    cwe: CWE-1236\n    function_names: []\n    filenames:\n      - debian/po/templates.pot\n    classification: slightly promising\n  - headline: Improper Neutralization of Argument Delimiters in a Command ('Argument Injection')\n    analysis: |\n      The `conf_lighttpd/include-conf-enabled.pl` script appears to be including configuration files based on the contents of the `conf-enabled/` directory. However, the script does not properly sanitize the filenames, which could potentially lead to argument injection vulnerabilities if the filenames contain malicious content.\n    cwe: CWE-88\n    function_names:\n      - bsd_glob\n    filenames:\n      - conf_lighttpd/include-conf-enabled.pl\n    classification: slightly promising\n  - headline: Improper Neutralization of Special Elements used in an OS Command ('OS Command Injection')\n    analysis: |\n      The `conf_lighttpd/use-ipv6.pl` script appears to be generating configuration files based on the contents of the `$ARGV[0]` parameter. However, the script does not properly sanitize this input, which could potentially lead to OS command injection vulnerabilities if the parameter contains malicious content.\n    cwe: CWE-78\n    function_names:\n      - socket\n    filenames:\n      - conf_lighttpd/use-ipv6.pl\n    classification: slightly promising\n  - headline: Improper Neutralization of Input During Web Page Generation ('Cross-site Scripting')\n    analysis: |\n      The `www/CTparental/js/npm.js` and `www/CTadmin/js/npm.js` files appear to be including various JavaScript files without properly sanitizing the paths. If an attacker can control the contents of these files, it could lead to cross-site scripting (XSS) vulnerabilities.\n    cwe: CWE-79\n    function_names: []\n    filenames:\n      - www/CTparental/js/npm.js\n      - www/CTadmin/js/npm.js\n    classification: slightly promising\n  - headline: Insufficient Entropy\n    analysis: |\n      The `locale/ctparental.pot` file contains various strings that may be used in user input fields. If these strings are not properly sanitized when used in sensitive operations, such as authentication or password reset functionality, it could lead to vulnerabilities related to insufficient entropy.\n    cwe: CWE-331\n    function_names: []\n    filenames:\n      - locale/ctparental.pot\n    classification: slightly promising\n  - headline: Improper Neutralization of Formula Elements in a CSV File\n    analysis: |\n      The `confe2guardian/template.html`, `confe2guardian/template-es.html`, and `confe2guardian/template-fr.html` files contain user-supplied input that is displayed in the generated HTML pages. If this input is not properly sanitized, it could lead to formula injection vulnerabilities in CSV files.\n    cwe: CWE-1236\n    function_names: []\n    filenames:\n      - confe2guardian/template.html\n      - confe2guardian/template-es.html\n      - confe2guardian/template-fr.html\n    classification: slightly promising\n```",
      "date": "2024-06-14T11:09:38.371796",
      "usage": {
        "prompt_tokens": 14578,
        "completion_tokens": 1140,
        "cost": 0.0050695
      }
    }
  ],
  "leads": [
    {
      "headline": "Improper Validation of Specified Quantity in Input",
      "analysis": "The popitup() function in the test-pop-up.html file appears to have a vulnerability where the URL passed as a parameter is not properly validated. The function opens a new window with the specified URL, which could potentially be used to redirect the user to a malicious website.\n",
      "classification": "slightly promising",
      "cwe": "CWE-1284",
      "function_names": [
        "popitup"
      ],
      "filenames": [
        "test-pop-up.html"
      ]
    },
    {
      "headline": "Improper Neutralization of Special Elements used in an OS Command ('OS Command Injection')",
      "analysis": "The conf_lighttpd/create-mime.conf.pl script appears to be generating configuration files based on the contents of the /etc/mime.types file. However, the script does not properly sanitize the input, which could potentially lead to OS command injection vulnerabilities if the /etc/mime.types file contains malicious content.\n",
      "classification": "slightly promising",
      "cwe": "CWE-78",
      "function_names": [
        "add"
      ],
      "filenames": [
        "conf_lighttpd/create-mime.conf.pl"
      ]
    },
    {
      "headline": "Improper Neutralization of Formula Elements in a CSV File",
      "analysis": "The debian/po/templates.pot file contains translatable strings that may be used in user input fields. If these strings are not properly sanitized when used in a CSV file, it could lead to formula injection vulnerabilities.\n",
      "classification": "slightly promising",
      "cwe": "CWE-1236",
      "function_names": [],
      "filenames": [
        "debian/po/templates.pot"
      ]
    },
    {
      "headline": "Improper Neutralization of Argument Delimiters in a Command ('Argument Injection')",
      "analysis": "The conf_lighttpd/include-conf-enabled.pl script appears to be including configuration files based on the contents of the conf-enabled/ directory. However, the script does not properly sanitize the filenames, which could potentially lead to argument injection vulnerabilities if the filenames contain malicious content.\n",
      "classification": "slightly promising",
      "cwe": "CWE-88",
      "function_names": [
        "bsd_glob"
      ],
      "filenames": [
        "conf_lighttpd/include-conf-enabled.pl"
      ]
    },
    {
      "headline": "Improper Neutralization of Special Elements used in an OS Command ('OS Command Injection')",
      "analysis": "The conf_lighttpd/use-ipv6.pl script appears to be generating configuration files based on the contents of the $ARGV[0] parameter. However, the script does not properly sanitize this input, which could potentially lead to OS command injection vulnerabilities if the parameter contains malicious content.\n",
      "classification": "slightly promising",
      "cwe": "CWE-78",
      "function_names": [
        "socket"
      ],
      "filenames": [
        "conf_lighttpd/use-ipv6.pl"
      ]
    },
    {
      "headline": "Improper Neutralization of Input During Web Page Generation ('Cross-site Scripting')",
      "analysis": "The www/CTparental/js/npm.js and www/CTadmin/js/npm.js files appear to be including various JavaScript files without properly sanitizing the paths. If an attacker can control the contents of these files, it could lead to cross-site scripting (XSS) vulnerabilities.\n",
      "classification": "slightly promising",
      "cwe": "CWE-79",
      "function_names": [],
      "filenames": [
        "www/CTparental/js/npm.js",
        "www/CTadmin/js/npm.js"
      ]
    },
    {
      "headline": "Insufficient Entropy",
      "analysis": "The locale/ctparental.pot file contains various strings that may be used in user input fields. If these strings are not properly sanitized when used in sensitive operations, such as authentication or password reset functionality, it could lead to vulnerabilities related to insufficient entropy.\n",
      "classification": "slightly promising",
      "cwe": "CWE-331",
      "function_names": [],
      "filenames": [
        "locale/ctparental.pot"
      ]
    },
    {
      "headline": "Improper Neutralization of Formula Elements in a CSV File",
      "analysis": "The confe2guardian/template.html, confe2guardian/template-es.html, and confe2guardian/template-fr.html files contain user-supplied input that is displayed in the generated HTML pages. If this input is not properly sanitized, it could lead to formula injection vulnerabilities in CSV files.\n",
      "classification": "slightly promising",
      "cwe": "CWE-1236",
      "function_names": [],
      "filenames": [
        "confe2guardian/template.html",
        "confe2guardian/template-es.html",
        "confe2guardian/template-fr.html"
      ]
    }
  ],
  "scores": [
    {
      "stats": {
        "fn": 3,
        "tp": 0,
        "fp": 0
      },
      "mapping": {},
      "vuln_dates": {
        "CVE-2021-37365": "2021-08-10T17:15:10",
        "CVE-2021-37367": "2021-08-10T17:15:10",
        "CVE-2021-37366": "2021-08-10T17:15:10"
      },
      "scoring_model": "claude-3-opus-20240229",
      "type": "llm",
      "instruction_template_hash": "245ace12b6361954d0a2"
    }
  ],
  "instruction_template_hash": "10c0163db4740318a544",
  "version": "0.1.0"
}
