{
  "commit": "4a19ccd252174bc042bcb9b4ef78e6d1d321c042",
  "repo_url": "https://github.com/tomas/network",
  "model": "gpt-4-turbo-2024-04-09",
  "chunk_hashes": [
    "1da0ec654af261b18a87"
  ],
  "responses": [
    {
      "content": "```yaml\nleads:\n  - headline: \"Insecure External Network Command Execution\"\n    analysis: |\n      The application\u2019s use of the `exec` function within the `lib/darwin.js`, `lib/linux.js`, and `lib/win32.js` files to execute system commands could expose it to command injection vulnerabilities if unsanitized input is processed in an insecure manner. This could happen if external input constructs or modifies commands run by the application, allowing an attacker to execute arbitrary commands.\n    cwe: CWE-78\n    function_names:\n      - trim_exec\n      - get_active_network_interface_name\n      - mac_address_for\n    filenames:\n      - lib/darwin.js\n      - lib/linux.js\n      - lib/win32.js\n    classification: \"very promising\"\n\n  - headline: \"Command Injection via Grep Usages\"\n    analysis: |\n      In multiple scripts, they construct command lines with user-supplied or network-derived input that isn't sanitized, particularly where `grep` is used in conjunction with `awk`. If an attacker can control parts of the input strings, they could inject additional commands or manipulate the behavior to leak information or disrupt operations.\n    cwe: CWE-77\n    function_names:\n      - get_active_network_interface_name\n      - interface_type_for\n    filenames:\n      - lib/darwin.js\n      - lib/linux.js\n    classification: \"very promising\"\n\n  - headline: \"Use of Weak Cryptographic Hash Functions\"\n    analysis: |\n      The application leverages insecure or outdated hashing mechanisms for processing sensitive data, as seen in `get_wmic_ip_value()` in `lib/win32.js`. The use of such weak hash functions can expose information to attackers by enabling them to easily reverse the hash or find collisions.\n    cwe: CWE-327\n    function_names:\n      - get_wmic_ip_value\n    filenames:\n      - lib/win32.js\n    classification: \"slightly promising\"\n\n  - headline: \"Insecure Information Handling in Error Messages\"\n    analysis: |\n      Throughout the given node.js libraries, various functions output or log error messages that could include sensitive information about the system or the network configurations. For instance, error handling in `get_public_ip` or `get_private_ip` could inadvertently expose network details or server configurations.\n    cwe: CWE-209\n    function_names:\n      - get_public_ip\n      - get_private_ip\n    filenames:\n      - lib/index.js\n    classification: \"slightly promising\"\n\n  - headline: \"Unchecked Return Values Leading to Unhandled Error States\"\n    analysis: |\n      Functions such as `trim_exec` in `lib/darwin.js` and `lib/linux.js` do not always check the return value of external commands executed. This could lead to unexpected states or behaviors especially if these commands fail or return undesirable results.\n    cwe: CWE-252\n    function_names:\n      - trim_exec\n    filenames:\n      - lib/darwin.js\n      - lib/linux.js\n    classification: \"not promising\"\n\n  - headline: \"Potential Exposure of Sensitive Network Configuration Details\"\n    analysis: |\n      The `lib/darwin.js` and `lib/linux.js` modules include functionality to retrieve various network settings and configurations which are then output to logs or external interfaces without sufficient guarding against unauthorized access or disclosure.\n    cwe: CWE-200\n    function_names:\n      - get_network_interfaces_list\n    filenames:\n      - lib/darwin.js\n      - lib/linux.js\n    classification: \"slightly promising\"\n```",
      "date": "2024-06-09T15:10:58.962963",
      "usage": {
        "prompt_tokens": 5855,
        "completion_tokens": 732,
        "cost": 0.08051
      }
    }
  ],
  "leads": [
    {
      "headline": "Insecure External Network Command Execution",
      "analysis": "The application\u2019s use of the exec function within the lib/darwin.js, lib/linux.js, and lib/win32.js files to execute system commands could expose it to command injection vulnerabilities if unsanitized input is processed in an insecure manner. This could happen if external input constructs or modifies commands run by the application, allowing an attacker to execute arbitrary commands.\n",
      "classification": "very promising",
      "cwe": "CWE-78",
      "function_names": [
        "trim_exec",
        "get_active_network_interface_name",
        "mac_address_for"
      ],
      "filenames": [
        "lib/darwin.js",
        "lib/linux.js",
        "lib/win32.js"
      ]
    },
    {
      "headline": "Command Injection via Grep Usages",
      "analysis": "In multiple scripts, they construct command lines with user-supplied or network-derived input that isn't sanitized, particularly where grep is used in conjunction with awk. If an attacker can control parts of the input strings, they could inject additional commands or manipulate the behavior to leak information or disrupt operations.\n",
      "classification": "very promising",
      "cwe": "CWE-77",
      "function_names": [
        "get_active_network_interface_name",
        "interface_type_for"
      ],
      "filenames": [
        "lib/darwin.js",
        "lib/linux.js"
      ]
    },
    {
      "headline": "Use of Weak Cryptographic Hash Functions",
      "analysis": "The application leverages insecure or outdated hashing mechanisms for processing sensitive data, as seen in get_wmic_ip_value() in lib/win32.js. The use of such weak hash functions can expose information to attackers by enabling them to easily reverse the hash or find collisions.\n",
      "classification": "slightly promising",
      "cwe": "CWE-327",
      "function_names": [
        "get_wmic_ip_value"
      ],
      "filenames": [
        "lib/win32.js"
      ]
    },
    {
      "headline": "Insecure Information Handling in Error Messages",
      "analysis": "Throughout the given node.js libraries, various functions output or log error messages that could include sensitive information about the system or the network configurations. For instance, error handling in get_public_ip or get_private_ip could inadvertently expose network details or server configurations.\n",
      "classification": "slightly promising",
      "cwe": "CWE-209",
      "function_names": [
        "get_public_ip",
        "get_private_ip"
      ],
      "filenames": [
        "lib/index.js"
      ]
    },
    {
      "headline": "Unchecked Return Values Leading to Unhandled Error States",
      "analysis": "Functions such as trim_exec in lib/darwin.js and lib/linux.js do not always check the return value of external commands executed. This could lead to unexpected states or behaviors especially if these commands fail or return undesirable results.\n",
      "classification": "not promising",
      "cwe": "CWE-252",
      "function_names": [
        "trim_exec"
      ],
      "filenames": [
        "lib/darwin.js",
        "lib/linux.js"
      ]
    },
    {
      "headline": "Potential Exposure of Sensitive Network Configuration Details",
      "analysis": "The lib/darwin.js and lib/linux.js modules include functionality to retrieve various network settings and configurations which are then output to logs or external interfaces without sufficient guarding against unauthorized access or disclosure.\n",
      "classification": "slightly promising",
      "cwe": "CWE-200",
      "function_names": [
        "get_network_interfaces_list"
      ],
      "filenames": [
        "lib/darwin.js",
        "lib/linux.js"
      ]
    }
  ],
  "scores": [
    {
      "stats": {
        "fn": 0,
        "tp": 1,
        "fp": 1
      },
      "mapping": {
        "0": "CVE-2024-21488"
      },
      "vuln_dates": {
        "CVE-2024-21488": "2024-01-30T05:15:09"
      },
      "scoring_model": "gpt-4o-2024-05-13",
      "type": "llm",
      "instruction_template_hash": "8998f09cf57fca8a6e03"
    },
    {
      "stats": {
        "fn": 0,
        "tp": 1,
        "fp": 1
      },
      "mapping": {
        "0": "CVE-2024-21488"
      },
      "vuln_dates": {
        "CVE-2024-21488": "2024-01-30T05:15:09"
      },
      "scoring_model": "claude-3-opus-20240229",
      "type": "llm",
      "instruction_template_hash": "245ace12b6361954d0a2"
    },
    {
      "stats": {
        "fn": 0,
        "tp": 1,
        "fp": 0
      },
      "mapping": {
        "0": "CVE-2024-21488",
        "1": "CVE-2024-21488"
      },
      "vuln_dates": {
        "CVE-2024-21488": "2024-01-30T05:15:09"
      },
      "scoring_model": "claude-3-5-sonnet-20240620",
      "type": "llm",
      "instruction_template_hash": "245ace12b6361954d0a2"
    }
  ],
  "instruction_template_hash": "10c0163db4740318a544",
  "version": "0.1.0"
}
