{
  "commit": "0e8a1a49290b7b08f31c603d3895f60bb38d5bb7",
  "repo_url": "https://github.com/gentoo/soko",
  "model": "gpt-4-turbo-2024-04-09",
  "chunk_hashes": [
    "3581d54cbb76fcd374bf"
  ],
  "responses": [
    {
      "content": "```yaml\nleads:\n  - headline: \"Use of Unsanitized Input in URL Redirection\"\n    analysis: |\n      The code directly uses user-provided inputs to construct a URL redirection which can be leveraged by an attacker to craft malicious URLs that redirect users to phishing or malicious sites. Specifically, the `typeahead.js` uses data coming in dynamically from input fields without proper validation to form URLs. This can be exploited using specially crafted inputs leading to open redirection vulnerabilities.\n    cwe: CWE-601\n    function_names:\n      - typeahead\n    filenames:\n      - web/packs/src/javascript/index/typeahead.js\n    classification: \"very promising\"\n\n  - headline: \"Insecure Permissions on Log Storage and Resource Upload\"\n    analysis: |\n      The scripts `update.sh` and `fullupdate.sh` use a hard-coded path to store sensitive data without enforcing security controls around the creation or management of these directories. This lax permission model on log and temporary file directories could allow local or even remote users, if other vulnerabilities exist, to access or tamper with these files, potentially leading to information disclosure or denial of service.\n    cwe: CWE-732\n    function_names:\n      - update_md5cache\n    filenames:\n      - bin/update.sh\n      - bin/fullupdate.sh\n    classification: \"slightly promising\"\n\n  - headline: \"Cross-Site Scripting (XSS) via Unsanitized Graphql Endpoint Output\"\n    analysis: |\n      In `graphiql.js`, the output of a GraphQL query is directly rendered into the HTML document without proper escaping or sanitization. Given that the query and its results are controlled by the user, this could lead to cross-site scripting (XSS) attacks where malicious scripts are injected into the page, executed by other users' browsers in the context of their session, leading to potential session hijacking, data theft, or malicious redirection.\n    cwe: CWE-79\n    function_names:\n      - graphQLFetcher\n    filenames:\n      - web/packs/src/javascript/graphiql.js\n    classification: \"very promising\"\n\n  - headline: \"Potential Insecure Direct Object References (IDOR) in AJAX Requests\"\n    analysis: |\n      The AJAX requests in `useflags/typeahead.js` and `packages/show.js` directly incorporate user input into REST API endpoints without proper authorization checks. This might allow attackers to access or modify information they normally wouldn't be able to, by manipulating the input parameters to access data related to other users.\n    cwe: CWE-639\n    function_names:\n      - typeahead\n      - undefined\n    filenames:\n      - web/packs/src/javascript/packages/show.js\n      - web/packs/src/javascript/useflags/typeaight.js\n    classification: \"slightly promising\"\n\n  - headline: \"Server-Side Request Forgery (SSRF) via External Image Source\"\n    analysis: |\n      The server hosts an insecure endpoint which fetches and sends back data from an external source based on user input without proper validation, shown in the use of dynamically set image URLs in the client-side configuration of `d3.layout.pack()`. This configuration could be exploited to cause the server to fetch data from arbitrary external sources which might be malicious.\n    cwe: CWE-918\n    function_names:\n      - createUseflagChart\n    filenames:\n      - web/packs/src/javascript/useflags/render-bubbles.js\n    classification: \"slightly promising\"\n```",
      "date": "2024-06-12T16:57:18.208228",
      "usage": {
        "prompt_tokens": 6791,
        "completion_tokens": 709,
        "cost": 0.08918
      }
    }
  ],
  "leads": [
    {
      "headline": "Use of Unsanitized Input in URL Redirection",
      "analysis": "The code directly uses user-provided inputs to construct a URL redirection which can be leveraged by an attacker to craft malicious URLs that redirect users to phishing or malicious sites. Specifically, the typeahead.js uses data coming in dynamically from input fields without proper validation to form URLs. This can be exploited using specially crafted inputs leading to open redirection vulnerabilities.\n",
      "classification": "very promising",
      "cwe": "CWE-601",
      "function_names": [
        "typeahead"
      ],
      "filenames": [
        "web/packs/src/javascript/index/typeahead.js"
      ]
    },
    {
      "headline": "Insecure Permissions on Log Storage and Resource Upload",
      "analysis": "The scripts update.sh and fullupdate.sh use a hard-coded path to store sensitive data without enforcing security controls around the creation or management of these directories. This lax permission model on log and temporary file directories could allow local or even remote users, if other vulnerabilities exist, to access or tamper with these files, potentially leading to information disclosure or denial of service.\n",
      "classification": "slightly promising",
      "cwe": "CWE-732",
      "function_names": [
        "update_md5cache"
      ],
      "filenames": [
        "bin/update.sh",
        "bin/fullupdate.sh"
      ]
    },
    {
      "headline": "Cross-Site Scripting (XSS) via Unsanitized Graphql Endpoint Output",
      "analysis": "In graphiql.js, the output of a GraphQL query is directly rendered into the HTML document without proper escaping or sanitization. Given that the query and its results are controlled by the user, this could lead to cross-site scripting (XSS) attacks where malicious scripts are injected into the page, executed by other users' browsers in the context of their session, leading to potential session hijacking, data theft, or malicious redirection.\n",
      "classification": "very promising",
      "cwe": "CWE-79",
      "function_names": [
        "graphQLFetcher"
      ],
      "filenames": [
        "web/packs/src/javascript/graphiql.js"
      ]
    },
    {
      "headline": "Potential Insecure Direct Object References (IDOR) in AJAX Requests",
      "analysis": "The AJAX requests in useflags/typeahead.js and packages/show.js directly incorporate user input into REST API endpoints without proper authorization checks. This might allow attackers to access or modify information they normally wouldn't be able to, by manipulating the input parameters to access data related to other users.\n",
      "classification": "slightly promising",
      "cwe": "CWE-639",
      "function_names": [
        "typeahead",
        "undefined"
      ],
      "filenames": [
        "web/packs/src/javascript/packages/show.js",
        "web/packs/src/javascript/useflags/typeaight.js"
      ]
    },
    {
      "headline": "Server-Side Request Forgery (SSRF) via External Image Source",
      "analysis": "The server hosts an insecure endpoint which fetches and sends back data from an external source based on user input without proper validation, shown in the use of dynamically set image URLs in the client-side configuration of d3.layout.pack(). This configuration could be exploited to cause the server to fetch data from arbitrary external sources which might be malicious.\n",
      "classification": "slightly promising",
      "cwe": "CWE-918",
      "function_names": [
        "createUseflagChart"
      ],
      "filenames": [
        "web/packs/src/javascript/useflags/render-bubbles.js"
      ]
    }
  ],
  "scores": [
    {
      "stats": {
        "fn": 2,
        "tp": 0,
        "fp": 2
      },
      "mapping": {},
      "vuln_dates": {
        "CVE-2023-26033": "2023-02-25T00:15:11",
        "CVE-2023-28424": "2023-03-20T13:15:11"
      },
      "scoring_model": "claude-3-opus-20240229",
      "type": "llm",
      "instruction_template_hash": "245ace12b6361954d0a2"
    }
  ],
  "instruction_template_hash": "10c0163db4740318a544",
  "version": "0.1.0"
}
