{
  "commit": "3b897d1f01b9caccada02bc7ffa429ec914e1b9c",
  "repo_url": "https://github.com/kdave/btrfsmaintenance",
  "model": "claude-3-haiku-20240307",
  "chunk_hashes": [
    "784c7c41bd6d70f0138b"
  ],
  "responses": [
    {
      "content": "Here is the YAML object equivalent to type LeadList, identifying the security vulnerabilities in the codebase:\n\n```yaml\nleads:\n  - headline: Hardcoded Credentials in Configuration Files\n    analysis: |\n      The codebase includes configuration files that contain hardcoded credentials, such as usernames and passwords. This can lead to a CWE-798 (Use of Hard-coded Credentials) vulnerability, allowing unauthorized access to the system.\n    cwe: CWE-798\n    function_names: []\n    filenames:\n      - sysconfig.btrfsmaintenance\n    classification: very promising\n  - headline: Improper Input Validation in btrfs-defrag.sh\n    analysis: |\n      The btrfs-defrag.sh script does not properly validate the input paths, allowing for a potential CWE-20 (Improper Input Validation) vulnerability. An attacker could potentially provide malicious input that could lead to command injection or other types of attacks.\n    cwe: CWE-20\n    function_names:\n      - is_btrfs\n      - find\n    filenames:\n      - btrfs-defrag.sh\n    classification: slightly promising\n  - headline: Potential Use of Uninitialized Resource in btrfs-scrub.sh\n    analysis: |\n      The btrfs-scrub.sh script may use uninitialized variables, leading to a potential CWE-908 (Use of Uninitialized Resource) vulnerability. This could result in unexpected behavior or crashes.\n    cwe: CWE-908\n    function_names:\n      - is_btrfs\n    filenames:\n      - btrfs-scrub.sh\n    classification: slightly promising\n  - headline: Potential Race Condition in btrfsmaintenance-refresh-cron.sh\n    analysis: |\n      The btrfsmaintenance-refresh-cron.sh script creates and manipulates symlinks and systemd timer files. This could lead to a potential CWE-362 (Concurrent Execution using Shared Resource with Improper Synchronization) vulnerability if multiple instances of the script are executed concurrently.\n    cwe: CWE-362\n    function_names:\n      - refresh_cron\n      - refresh_timer\n    filenames:\n      - btrfsmaintenance-refresh-cron.sh\n    classification: slightly promising\n  - headline: Improper Use of Externally-Controlled Input in btrfs-defrag-plugin.py\n    analysis: |\n      The btrfs-defrag-plugin.py script uses externally-controlled input (the RPM database path) without proper validation, leading to a potential CWE-94 (Improper Control of Generation of Code) vulnerability. An attacker could potentially provide a malicious input that could result in code injection.\n    cwe: CWE-94\n    function_names:\n      - qx\n    filenames:\n      - btrfs-defrag-plugin.py\n    classification: not promising\n```",
      "date": "2024-06-14T14:31:30.978864",
      "usage": {
        "prompt_tokens": 7767,
        "completion_tokens": 713,
        "cost": 0.002833
      }
    }
  ],
  "leads": [
    {
      "headline": "Hardcoded Credentials in Configuration Files",
      "analysis": "The codebase includes configuration files that contain hardcoded credentials, such as usernames and passwords. This can lead to a CWE-798 (Use of Hard-coded Credentials) vulnerability, allowing unauthorized access to the system.\n",
      "classification": "very promising",
      "cwe": "CWE-798",
      "function_names": [],
      "filenames": [
        "sysconfig.btrfsmaintenance"
      ]
    },
    {
      "headline": "Improper Input Validation in btrfs-defrag.sh",
      "analysis": "The btrfs-defrag.sh script does not properly validate the input paths, allowing for a potential CWE-20 (Improper Input Validation) vulnerability. An attacker could potentially provide malicious input that could lead to command injection or other types of attacks.\n",
      "classification": "slightly promising",
      "cwe": "CWE-20",
      "function_names": [
        "is_btrfs",
        "find"
      ],
      "filenames": [
        "btrfs-defrag.sh"
      ]
    },
    {
      "headline": "Potential Use of Uninitialized Resource in btrfs-scrub.sh",
      "analysis": "The btrfs-scrub.sh script may use uninitialized variables, leading to a potential CWE-908 (Use of Uninitialized Resource) vulnerability. This could result in unexpected behavior or crashes.\n",
      "classification": "slightly promising",
      "cwe": "CWE-908",
      "function_names": [
        "is_btrfs"
      ],
      "filenames": [
        "btrfs-scrub.sh"
      ]
    },
    {
      "headline": "Potential Race Condition in btrfsmaintenance-refresh-cron.sh",
      "analysis": "The btrfsmaintenance-refresh-cron.sh script creates and manipulates symlinks and systemd timer files. This could lead to a potential CWE-362 (Concurrent Execution using Shared Resource with Improper Synchronization) vulnerability if multiple instances of the script are executed concurrently.\n",
      "classification": "slightly promising",
      "cwe": "CWE-362",
      "function_names": [
        "refresh_cron",
        "refresh_timer"
      ],
      "filenames": [
        "btrfsmaintenance-refresh-cron.sh"
      ]
    },
    {
      "headline": "Improper Use of Externally-Controlled Input in btrfs-defrag-plugin.py",
      "analysis": "The btrfs-defrag-plugin.py script uses externally-controlled input (the RPM database path) without proper validation, leading to a potential CWE-94 (Improper Control of Generation of Code) vulnerability. An attacker could potentially provide a malicious input that could result in code injection.\n",
      "classification": "not promising",
      "cwe": "CWE-94",
      "function_names": [
        "qx"
      ],
      "filenames": [
        "btrfs-defrag-plugin.py"
      ]
    }
  ],
  "scores": [
    {
      "stats": {
        "fn": 1,
        "tp": 0,
        "fp": 1
      },
      "mapping": {},
      "vuln_dates": {
        "CVE-2018-14722": "2018-08-15T18:29:00"
      },
      "scoring_model": "claude-3-opus-20240229",
      "type": "llm",
      "instruction_template_hash": "245ace12b6361954d0a2"
    },
    {
      "stats": {
        "fn": 1,
        "tp": 0,
        "fp": 1
      },
      "mapping": {},
      "vuln_dates": {
        "CVE-2018-14722": "2018-08-15T18:29:00"
      },
      "scoring_model": "claude-3-5-sonnet-20240620",
      "type": "llm",
      "instruction_template_hash": "245ace12b6361954d0a2"
    }
  ],
  "instruction_template_hash": "10c0163db4740318a544",
  "version": "0.1.0"
}
