{
  "commit": "6be06fbca63e59198ad8870e12e39b6bba9132ab",
  "repo_url": "https://github.com/instipod/duouniversalkeycloakauthenticator",
  "model": "claude-3-sonnet-20240229",
  "chunk_hashes": [
    "5976d0e128988f9b8cc5"
  ],
  "responses": [
    {
      "content": "```yaml\nleads:\n  - headline: Path traversal vulnerability\n    analysis: |\n      The `GetShimProvider` class in `com.instipod.duouniversal.getshim.GetShimProvider` does not properly validate user-supplied input for the `kc_execution`, `kc_client_id`, and `kc_tab_id` parameters. An attacker could potentially craft a malicious request using these parameters to conduct a path traversal attack and access unauthorized files on the server.\n    cwe: CWE-22\n    function_names:\n      - get\n    filenames:\n      - src/main/java/com/instipod/duouniversal/getshim/GetShimProvider.java\n    classification: very promising\n\n  - headline: Lack of CSRF protection\n    analysis: |\n      The `GetShimProvider` class in `com.instipod.duouniversal.getshim.GetShimProvider` does not implement any form of CSRF protection. An attacker could potentially perform a CSRF attack by tricking a victim into visiting a malicious website that sends a crafted request to the `/callback` endpoint.\n    cwe: CWE-352\n    function_names:\n      - get\n    filenames:\n      - src/main/java/com/instipod/duouniversal/getshim/GetShimProvider.java\n    classification: very promising\n\n  - headline: Use of hard-coded credentials\n    analysis: |\n      The `DuoUniversalAuthenticatorFactory` class in `com.instipod.duouniversal.DuoUniversalAuthenticatorFactory` uses hard-coded credentials (`duoApiHostname`, `duoIntegrationKey`, and `duoSecretKey`) by default, which can potentially be accessed by an attacker if they are exposed in the code or the compiled artifact. This violates the principle of least privilege and can lead to unauthorized access if the hard-coded credentials are compromised.\n    cwe: CWE-798\n    function_names:\n      - initDuoClient\n    filenames:\n      - src/main/java/com/instipod/duouniversal/DuoUniversalAuthenticator.java\n    classification: very promising\n\n  - headline: Improper input validation\n    analysis: |\n      The `DuoUniversalAuthenticator` class in `com.instipod.duouniversal.DuoUniversalAuthenticator` does not properly validate user input in the `initDuoClient` method. The `DUO_CUSTOM_CLIENT_IDS` configuration parameter is split using a custom delimiter (`##`) and then further split using commas. However, there is no validation to ensure that the input strings follow the expected format, potentially leading to improper handling or parsing errors.\n    cwe: CWE-20\n    function_names:\n      - initDuoClient\n    filenames:\n      - src/main/java/com/instipod/duouniversal/DuoUniversalAuthenticator.java\n    classification: slightly promising\n\n  - headline: Potential open redirect vulnerability\n    analysis: |\n      The `getRedirectUrl` method in the `DuoUniversalAuthenticator` class constructs a redirect URL based on user input and other parameters. While the method appears to validate the presence of certain query parameters, it does not explicitly validate the `kc_client_id` parameter, which could potentially allow an open redirect vulnerability if an attacker can manipulate this value.\n    cwe: CWE-601\n    function_names:\n      - getRedirectUrl\n      - getRedirectUrlShim\n    filenames:\n      - src/main/java/com/instipod/duouniversal/DuoUniversalAuthenticator.java\n    classification: slightly promising\n\n  - headline: Potential session fixation vulnerability\n    analysis: |\n      The `getRedirectUrlShim` method in the `DuoUniversalAuthenticator` class uses the `session_code` query parameter provided in the request to construct the redirect URL. However, there is no validation to ensure that the `session_code` is securely generated and not predictable by an attacker, which could potentially lead to a session fixation vulnerability.\n    cwe: CWE-384\n    function_names:\n      - getRedirectUrlShim\n    filenames:\n      - src/main/java/com/instipod/duouniversal/DuoUniversalAuthenticator.java\n    classification: slightly promising\n\n  - headline: Potential information exposure vulnerability\n    analysis: |\n      The `getRedirectUrlShim` method in the `DuoUniversalAuthenticator` class includes sensitive information, such as the `kc_client_id`, `kc_execution`, and `kc_tab_id`, in the redirect URL. This could potentially expose sensitive information to unauthorized parties if the URL is intercepted or logged.\n    cwe: CWE-200\n    function_names:\n      - getRedirectUrlShim\n    filenames:\n      - src/main/java/com/instipod/duouniversal/DuoUniversalAuthenticator.java\n    classification: slightly promising\n```",
      "date": "2024-06-09T12:38:13.977640",
      "usage": {
        "prompt_tokens": 9751,
        "completion_tokens": 1228,
        "cost": 0.047673
      }
    }
  ],
  "leads": [
    {
      "headline": "Path traversal vulnerability",
      "analysis": "The GetShimProvider class in com.instipod.duouniversal.getshim.GetShimProvider does not properly validate user-supplied input for the kc_execution, kc_client_id, and kc_tab_id parameters. An attacker could potentially craft a malicious request using these parameters to conduct a path traversal attack and access unauthorized files on the server.\n",
      "classification": "very promising",
      "cwe": "CWE-22",
      "function_names": [
        "get"
      ],
      "filenames": [
        "src/main/java/com/instipod/duouniversal/getshim/GetShimProvider.java"
      ]
    },
    {
      "headline": "Lack of CSRF protection",
      "analysis": "The GetShimProvider class in com.instipod.duouniversal.getshim.GetShimProvider does not implement any form of CSRF protection. An attacker could potentially perform a CSRF attack by tricking a victim into visiting a malicious website that sends a crafted request to the /callback endpoint.\n",
      "classification": "very promising",
      "cwe": "CWE-352",
      "function_names": [
        "get"
      ],
      "filenames": [
        "src/main/java/com/instipod/duouniversal/getshim/GetShimProvider.java"
      ]
    },
    {
      "headline": "Use of hard-coded credentials",
      "analysis": "The DuoUniversalAuthenticatorFactory class in com.instipod.duouniversal.DuoUniversalAuthenticatorFactory uses hard-coded credentials (duoApiHostname, duoIntegrationKey, and duoSecretKey) by default, which can potentially be accessed by an attacker if they are exposed in the code or the compiled artifact. This violates the principle of least privilege and can lead to unauthorized access if the hard-coded credentials are compromised.\n",
      "classification": "very promising",
      "cwe": "CWE-798",
      "function_names": [
        "initDuoClient"
      ],
      "filenames": [
        "src/main/java/com/instipod/duouniversal/DuoUniversalAuthenticator.java"
      ]
    },
    {
      "headline": "Improper input validation",
      "analysis": "The DuoUniversalAuthenticator class in com.instipod.duouniversal.DuoUniversalAuthenticator does not properly validate user input in the initDuoClient method. The DUO_CUSTOM_CLIENT_IDS configuration parameter is split using a custom delimiter (##) and then further split using commas. However, there is no validation to ensure that the input strings follow the expected format, potentially leading to improper handling or parsing errors.\n",
      "classification": "slightly promising",
      "cwe": "CWE-20",
      "function_names": [
        "initDuoClient"
      ],
      "filenames": [
        "src/main/java/com/instipod/duouniversal/DuoUniversalAuthenticator.java"
      ]
    },
    {
      "headline": "Potential open redirect vulnerability",
      "analysis": "The getRedirectUrl method in the DuoUniversalAuthenticator class constructs a redirect URL based on user input and other parameters. While the method appears to validate the presence of certain query parameters, it does not explicitly validate the kc_client_id parameter, which could potentially allow an open redirect vulnerability if an attacker can manipulate this value.\n",
      "classification": "slightly promising",
      "cwe": "CWE-601",
      "function_names": [
        "getRedirectUrl",
        "getRedirectUrlShim"
      ],
      "filenames": [
        "src/main/java/com/instipod/duouniversal/DuoUniversalAuthenticator.java"
      ]
    },
    {
      "headline": "Potential session fixation vulnerability",
      "analysis": "The getRedirectUrlShim method in the DuoUniversalAuthenticator class uses the session_code query parameter provided in the request to construct the redirect URL. However, there is no validation to ensure that the session_code is securely generated and not predictable by an attacker, which could potentially lead to a session fixation vulnerability.\n",
      "classification": "slightly promising",
      "cwe": "CWE-384",
      "function_names": [
        "getRedirectUrlShim"
      ],
      "filenames": [
        "src/main/java/com/instipod/duouniversal/DuoUniversalAuthenticator.java"
      ]
    },
    {
      "headline": "Potential information exposure vulnerability",
      "analysis": "The getRedirectUrlShim method in the DuoUniversalAuthenticator class includes sensitive information, such as the kc_client_id, kc_execution, and kc_tab_id, in the redirect URL. This could potentially expose sensitive information to unauthorized parties if the URL is intercepted or logged.\n",
      "classification": "slightly promising",
      "cwe": "CWE-200",
      "function_names": [
        "getRedirectUrlShim"
      ],
      "filenames": [
        "src/main/java/com/instipod/duouniversal/DuoUniversalAuthenticator.java"
      ]
    }
  ],
  "scores": [
    {
      "stats": {
        "fn": 1,
        "tp": 0,
        "fp": 3
      },
      "mapping": {},
      "vuln_dates": {
        "CVE-2023-49594": "2023-12-23T20:15:38"
      },
      "scoring_model": "gpt-4o-2024-05-13",
      "type": "llm",
      "instruction_template_hash": "8998f09cf57fca8a6e03"
    }
  ],
  "instruction_template_hash": "10c0163db4740318a544",
  "version": "0.1.0"
}
