{
  "commit": "2cd9997382a9d29e97806fce9086f83409cb077e",
  "repo_url": "https://github.com/jenkinsci/mantis-plugin",
  "model": "claude-3-5-sonnet-20240620",
  "chunk_hashes": [
    "e56a63e502f475750918"
  ],
  "responses": [
    {
      "content": "```yaml\nleads:\n  - headline: Potential CSRF vulnerability in MantisProjectPropertyConfigSubmitTest\n    analysis: |\n      The MantisProjectPropertyConfigSubmitTest class contains methods that submit forms and modify configuration without any CSRF protection. Specifically, the testConfigSubmit_002 method submits a form that changes Mantis site configuration. This could potentially be exploited by an attacker to trick an authenticated user into submitting malicious configuration changes. The lack of CSRF tokens or other protections makes this vulnerable to cross-site request forgery attacks.\n    cwe: CWE-352\n    function_names:\n      - testConfigSubmit_002\n    filenames:\n      - src/test/java/hudson/plugins/mantis/MantisProjectPropertyConfigSubmitTest.java\n    classification: slightly promising\n\n  - headline: Potential XSS vulnerability in Utility.escape method\n    analysis: |\n      The Utility.escape method attempts to escape HTML special characters, but it does not handle all cases correctly. It misses escaping the single quote character (') in some cases, which could lead to XSS vulnerabilities if the escaped output is inserted into HTML attribute values enclosed in single quotes. An attacker could potentially inject malicious JavaScript if the escaped string is used unsafely in HTML contexts.\n    cwe: CWE-79\n    function_names:\n      - escape\n    filenames:\n      - src/main/java/hudson/plugins/mantis/Utility.java  \n    classification: slightly promising\n\n  - headline: Insecure SSL/TLS configuration in MantisSite\n    analysis: |\n      The MantisSite class sets the \"axis.socketSecureFactory\" property to \"org.apache.axis.components.net.SunFakeTrustSocketFactory\". This disables SSL certificate validation, allowing connections to any HTTPS server regardless of certificate validity. This makes the application vulnerable to man-in-the-middle attacks, as it will not verify the authenticity of the Mantis server it is connecting to.\n    cwe: CWE-295\n    function_names:\n      - MantisSessionImpl\n    filenames:\n      - src/main/java/hudson/plugins/mantis/soap/mantis120/MantisSessionImpl.java\n      - src/main/java/hudson/plugins/mantis/soap/mantis110/MantisSessionImpl.java\n    classification: very promising\n\n  - headline: Potential XML External Entity (XXE) vulnerability in JellyScriptContent\n    analysis: |\n      The JellyScriptContent class uses Jelly to parse and execute XML templates. It does not appear to disable external entity processing, which could lead to XXE vulnerabilities if an attacker can control the template contents. This could potentially allow an attacker to read arbitrary files on the system, perform SSRF attacks, or cause denial of service.\n    cwe: CWE-611\n    function_names:\n      - renderContent\n    filenames:\n      - src/main/java/hudson/plugins/mantis/scripts/JellyScriptContent.java\n    classification: slightly promising\n\n  - headline: Hardcoded credentials in MantisSessionImpl\n    analysis: |\n      The MantisSessionImpl classes contain hardcoded username and password values in the testEscapeRegExp method. While this appears to be in a test class, hardcoded credentials in source code are a security risk as they could be discovered and exploited by attackers to gain unauthorized access.\n    cwe: CWE-798\n    function_names:\n      - MantisSessionImpl\n    filenames:\n      - src/main/java/hudson/plugins/mantis/soap/mantis120/MantisSessionImpl.java\n      - src/main/java/hudson/plugins/mantis/soap/mantis110/MantisSessionImpl.java\n    classification: slightly promising\n```",
      "date": "2024-07-08T07:03:31.493275",
      "usage": {
        "prompt_tokens": 32323,
        "completion_tokens": 897,
        "cost": 0.110424
      }
    }
  ],
  "leads": [
    {
      "headline": "Potential CSRF vulnerability in MantisProjectPropertyConfigSubmitTest",
      "analysis": "The MantisProjectPropertyConfigSubmitTest class contains methods that submit forms and modify configuration without any CSRF protection. Specifically, the testConfigSubmit_002 method submits a form that changes Mantis site configuration. This could potentially be exploited by an attacker to trick an authenticated user into submitting malicious configuration changes. The lack of CSRF tokens or other protections makes this vulnerable to cross-site request forgery attacks.\n",
      "classification": "slightly promising",
      "cwe": "CWE-352",
      "function_names": [
        "testConfigSubmit_002"
      ],
      "filenames": [
        "src/test/java/hudson/plugins/mantis/MantisProjectPropertyConfigSubmitTest.java"
      ]
    },
    {
      "headline": "Potential XSS vulnerability in Utility.escape method",
      "analysis": "The Utility.escape method attempts to escape HTML special characters, but it does not handle all cases correctly. It misses escaping the single quote character (') in some cases, which could lead to XSS vulnerabilities if the escaped output is inserted into HTML attribute values enclosed in single quotes. An attacker could potentially inject malicious JavaScript if the escaped string is used unsafely in HTML contexts.\n",
      "classification": "slightly promising",
      "cwe": "CWE-79",
      "function_names": [
        "escape"
      ],
      "filenames": [
        "src/main/java/hudson/plugins/mantis/Utility.java"
      ]
    },
    {
      "headline": "Insecure SSL/TLS configuration in MantisSite",
      "analysis": "The MantisSite class sets the \"axis.socketSecureFactory\" property to \"org.apache.axis.components.net.SunFakeTrustSocketFactory\". This disables SSL certificate validation, allowing connections to any HTTPS server regardless of certificate validity. This makes the application vulnerable to man-in-the-middle attacks, as it will not verify the authenticity of the Mantis server it is connecting to.\n",
      "classification": "very promising",
      "cwe": "CWE-295",
      "function_names": [
        "MantisSessionImpl"
      ],
      "filenames": [
        "src/main/java/hudson/plugins/mantis/soap/mantis120/MantisSessionImpl.java",
        "src/main/java/hudson/plugins/mantis/soap/mantis110/MantisSessionImpl.java"
      ]
    },
    {
      "headline": "Potential XML External Entity (XXE) vulnerability in JellyScriptContent",
      "analysis": "The JellyScriptContent class uses Jelly to parse and execute XML templates. It does not appear to disable external entity processing, which could lead to XXE vulnerabilities if an attacker can control the template contents. This could potentially allow an attacker to read arbitrary files on the system, perform SSRF attacks, or cause denial of service.\n",
      "classification": "slightly promising",
      "cwe": "CWE-611",
      "function_names": [
        "renderContent"
      ],
      "filenames": [
        "src/main/java/hudson/plugins/mantis/scripts/JellyScriptContent.java"
      ]
    },
    {
      "headline": "Hardcoded credentials in MantisSessionImpl",
      "analysis": "The MantisSessionImpl classes contain hardcoded username and password values in the testEscapeRegExp method. While this appears to be in a test class, hardcoded credentials in source code are a security risk as they could be discovered and exploited by attackers to gain unauthorized access.\n",
      "classification": "slightly promising",
      "cwe": "CWE-798",
      "function_names": [
        "MantisSessionImpl"
      ],
      "filenames": [
        "src/main/java/hudson/plugins/mantis/soap/mantis120/MantisSessionImpl.java",
        "src/main/java/hudson/plugins/mantis/soap/mantis110/MantisSessionImpl.java"
      ]
    }
  ],
  "scores": [
    {
      "stats": {
        "fn": 1,
        "tp": 0,
        "fp": 1
      },
      "mapping": {},
      "vuln_dates": {
        "CVE-2019-16569": "2019-12-17T15:15:22"
      },
      "scoring_model": "claude-3-5-sonnet-20240620",
      "type": "llm",
      "instruction_template_hash": "245ace12b6361954d0a2"
    }
  ],
  "instruction_template_hash": "10c0163db4740318a544",
  "version": "0.1.0"
}
