{
  "commit": "03cb17a60ccad88599ccb5a3c231021bdda7f31a",
  "repo_url": "https://github.com/objective-see/lulu",
  "model": "gpt-4o-2024-05-13",
  "chunk_hashes": [
    "17944e37c8d57b1e5ce5"
  ],
  "responses": [
    {
      "content": "```yaml\nleads:\n  - headline: Hardcoded API Key in Source Code\n    analysis: |\n      The source code has a hardcoded API key in the file `loginItem/loginItem/VirusTotal.h`. Hardcoding sensitive information such as API keys directly into the source code can lead to unauthorized access if the source code is leaked or accessed by malicious actors. This vulnerability enables the potential misuse of the API key for purposes unintended by the original developers.\n    cwe: CWE-798\n    function_names:\n      - N/A\n    filenames:\n      - loginItem/loginItem/VirusTotal.h\n    classification: very promising\n  \n  - headline: Insecure Use of NSUnarchiver in Client/Server Communications\n    analysis: |\n      The use of `NSUnarchiver` and other similar API calls that are susceptible to deserialization attacks are present in the source code files related to the application\u2019s client-server communications. Deserialization of untrusted data can lead to arbitrary code execution, privilege escalation, or denial of service attacks.\n    cwe: CWE-502\n    function_names:\n      - monitor\n      - postRequest\n    filenames:\n      - loginItem/loginItem/AlertMonitor.h\n      - loginItem/loginItem/VirusTotal.h\n    classification: very promising\n\n  - headline: Potential Vulnerability in Memory Management With OSMalloc\n    analysis: |\n      The kernel extension code extensively uses `OSMalloc` for memory allocations without comprehensive checks on the allocation sizes, which could lead to memory leaks or buffer overflow attacks. Moreover, improper handling of allocated memory during cleanup operations can result in Use-After-Free conditions.\n    cwe: CWE-401\n    function_names:\n      - attach\n      - detach\n    filenames:\n      - kernelExtension/kernelExtension/socketEvents.cpp\n    classification: very promising\n\n  - headline: Insufficient Validation of Input Data\n    analysis: |\n      There are multiple instances where input data from network sources is processed without sufficient validation. This includes processing of DNS responses and socket input data where there is minimal to no validation to ensure the integrity and authenticity of the data being processed.\n    cwe: CWE-20\n    function_names:\n      - data_in\n    filenames:\n      - kernelExtension/kernelExtension/socketEvents.cpp\n    classification: very promising\n\n  - headline: Cleartext Transmission of Sensitive Information\n    analysis: |\n      The VirusTotal API integration transmits sensitive information over potentially insecure connections. Even though the endpoint may use HTTPS, using clear text transmission methods can still expose sensitive data if SSL/TLS certificates are not properly validated.\n    cwe: CWE-319\n    function_names:\n      - queryVT\n    filenames:\n      - loginItem/loginItem/VirusTotal.h\n    classification: slightly promising\n\n  - headline: Potential Privilege Escalation Through Setuid Execution\n    analysis: |\n      The code contains privileged operations that rely on user input or environmental variables without sufficient validation. This, in conjunction with the use of setuid binaries, could allow an attacker to manipulate the environment and escalate their privileges.\n    cwe: CWE-269\n    function_names:\n      - monitor\n    filenames:\n      - loginItem/loginItem/DaemonComms.h\n    classification: slightly promising\n```",
      "date": "2024-06-13T10:43:07.028086",
      "usage": {
        "prompt_tokens": 33878,
        "completion_tokens": 666,
        "cost": 0.17938
      }
    }
  ],
  "leads": [
    {
      "headline": "Hardcoded API Key in Source Code",
      "analysis": "The source code has a hardcoded API key in the file loginItem/loginItem/VirusTotal.h. Hardcoding sensitive information such as API keys directly into the source code can lead to unauthorized access if the source code is leaked or accessed by malicious actors. This vulnerability enables the potential misuse of the API key for purposes unintended by the original developers.\n",
      "classification": "very promising",
      "cwe": "CWE-798",
      "function_names": [
        "N/A"
      ],
      "filenames": [
        "loginItem/loginItem/VirusTotal.h"
      ]
    },
    {
      "headline": "Insecure Use of NSUnarchiver in Client/Server Communications",
      "analysis": "The use of NSUnarchiver and other similar API calls that are susceptible to deserialization attacks are present in the source code files related to the application\u2019s client-server communications. Deserialization of untrusted data can lead to arbitrary code execution, privilege escalation, or denial of service attacks.\n",
      "classification": "very promising",
      "cwe": "CWE-502",
      "function_names": [
        "monitor",
        "postRequest"
      ],
      "filenames": [
        "loginItem/loginItem/AlertMonitor.h",
        "loginItem/loginItem/VirusTotal.h"
      ]
    },
    {
      "headline": "Potential Vulnerability in Memory Management With OSMalloc",
      "analysis": "The kernel extension code extensively uses OSMalloc for memory allocations without comprehensive checks on the allocation sizes, which could lead to memory leaks or buffer overflow attacks. Moreover, improper handling of allocated memory during cleanup operations can result in Use-After-Free conditions.\n",
      "classification": "very promising",
      "cwe": "CWE-401",
      "function_names": [
        "attach",
        "detach"
      ],
      "filenames": [
        "kernelExtension/kernelExtension/socketEvents.cpp"
      ]
    },
    {
      "headline": "Insufficient Validation of Input Data",
      "analysis": "There are multiple instances where input data from network sources is processed without sufficient validation. This includes processing of DNS responses and socket input data where there is minimal to no validation to ensure the integrity and authenticity of the data being processed.\n",
      "classification": "very promising",
      "cwe": "CWE-20",
      "function_names": [
        "data_in"
      ],
      "filenames": [
        "kernelExtension/kernelExtension/socketEvents.cpp"
      ]
    },
    {
      "headline": "Cleartext Transmission of Sensitive Information",
      "analysis": "The VirusTotal API integration transmits sensitive information over potentially insecure connections. Even though the endpoint may use HTTPS, using clear text transmission methods can still expose sensitive data if SSL/TLS certificates are not properly validated.\n",
      "classification": "slightly promising",
      "cwe": "CWE-319",
      "function_names": [
        "queryVT"
      ],
      "filenames": [
        "loginItem/loginItem/VirusTotal.h"
      ]
    },
    {
      "headline": "Potential Privilege Escalation Through Setuid Execution",
      "analysis": "The code contains privileged operations that rely on user input or environmental variables without sufficient validation. This, in conjunction with the use of setuid binaries, could allow an attacker to manipulate the environment and escalate their privileges.\n",
      "classification": "slightly promising",
      "cwe": "CWE-269",
      "function_names": [
        "monitor"
      ],
      "filenames": [
        "loginItem/loginItem/DaemonComms.h"
      ]
    }
  ],
  "scores": [
    {
      "stats": {
        "fn": 1,
        "tp": 0,
        "fp": 4
      },
      "mapping": {},
      "vuln_dates": {
        "CVE-2018-10404": "2018-06-13T22:29:00"
      },
      "scoring_model": "claude-3-opus-20240229",
      "type": "llm",
      "instruction_template_hash": "245ace12b6361954d0a2"
    }
  ],
  "instruction_template_hash": "10c0163db4740318a544",
  "version": "0.1.0"
}
