{
  "commit": "8a23c464445faba645d2add8389afed41a3958bb",
  "repo_url": "https://github.com/lif-platforms/lif-auth-server",
  "model": "gpt-4-turbo-2024-04-09",
  "chunk_hashes": [
    "fa3bd30bd9d234850357"
  ],
  "responses": [
    {
      "content": "```yaml\nleads:\n  - headline: \"SQL Injection through unescaped user input in login paths\"\n    analysis: |\n      The application uses direct SQL statements that interpolate user inputs for the username and password fields without sufficient escaping or parameterization, specifically in 'login' and 'create_account' endpoints. If an attacker provides specially crafted input, it could be used to manipulate SQL queries to bypass authentication, extract data, alter data, or perform database operations unauthorized.\n    cwe: CWE-89\n    function_names:\n      - login\n      - create_account\n    filenames:\n      - src/auth_server.py\n    classification: \"very promising\"\n\n  - headline: \"Hardcoded sensitive data management\"\n    analysis: |\n      In 'db_interface.py', sensitive database details such as database credentials might be hardcoded in the application. After deploying the app, these credentials can be exposed and pose a major security risk by allowing unauthorized access.\n    cwe: CWE-798\n    function_names:\n      - load_config\n    filenames:\n      - src/utils/db_interface.py\n    classification: \"very promising\"\n\n  - headline: \"Improper filesystem permissions for important directories\"\n    analysis: |\n      The application does not set proper filesystem permissions while creating directories such as 'user_images/pfp'. This can lead to unauthorized access or disclosure of sensitive user data by local users on the server.\n    cwe: CWE-276\n    function_names:\n      - home\n    filenames:\n      - src/auth_server.py\n    classification: \"slightly promising\"\n\n  - headline: \"Vulnerable endpoint exposure due to deprecated practices\"\n    analysis: |\n      Several endpoints are annotated as 'DEPRECIATED' but remain active in the codebase, such as '/login/{username}/{password}'. This leaves deprecated code paths accessible, potentially exposing the application to known vulnerabilities associated with older practices.\n    cwe: CWE-676\n    function_names:\n      - login\n      - create_account\n    filenames:\n      - src/auth_server.py\n    classification: \"slightly promising\"\n\n  - headline: \"Lack of effective error handling promotes information leakage\"\n    analysis: |\n      The application's exception handling routines disclose excessive information about underlying operations. For example, database connection failures are displayed with details that might help an attacker determine further attack vectors or underlying technologies used.\n    cwe: CWE-209\n    function_names:\n      - connect_to_database\n    filenames:\n      - src/utils/db_client.py\n    classification: \"not promising\"\n\n  - headline: \"Insecure Cross-Origin Resource Sharing (CORS) Policy\"\n    analysis: |\n      The application configures CORS with an overly permissive policy by setting 'allow_origins' to \"*\", allowing potentially unsafe cross-origin requests from any domain, which can lead to data theft or unauthorized operation executions.\n    cwe: CWE-346\n    function_names:\n      - home\n    filenames:\n      - src/auth_server.py\n    qed: \"slightly promising\"\n\n  - headline: \"Inadequate password hashing mechanism leads to compromise of password data security\"\n    analysis: |\n      'password_hasher.py' incorrectly employs a basic SHA-256 hashing mechanism without sufficient salting, posing a major risk as attackers might easily crack hashed passwords using ordinary dictionaries and complex strategies such as rainbow table attacks.\n    cwe: CWE-916\n    function_names:\n      - get_hash_gen_salt\n    filenames:\n      - src/utils/password_hasher.py\n    classification: \"very promising\"\n\n  - headline: \"Information disclosure via detailed error messages\"\n    analysis: |\n      The application improperly handles error conditions and exceptions by providing detailed error messages that could lead to exposure of sensitive information about the backend processes, potentially giving attackers insights into the infrastructure.\n    cwe: CWE-215\n    function_names:\n      - update_account_info\n    filenames:\n      - src/auth_server.py\n    classification: \"slightly promising\"\n```",
      "date": "2024-06-09T13:13:11.457273",
      "usage": {
        "prompt_tokens": 9091,
        "completion_tokens": 801,
        "cost": 0.11494
      }
    }
  ],
  "leads": [
    {
      "headline": "SQL Injection through unescaped user input in login paths",
      "analysis": "The application uses direct SQL statements that interpolate user inputs for the username and password fields without sufficient escaping or parameterization, specifically in 'login' and 'create_account' endpoints. If an attacker provides specially crafted input, it could be used to manipulate SQL queries to bypass authentication, extract data, alter data, or perform database operations unauthorized.\n",
      "classification": "very promising",
      "cwe": "CWE-89",
      "function_names": [
        "login",
        "create_account"
      ],
      "filenames": [
        "src/auth_server.py"
      ]
    },
    {
      "headline": "Hardcoded sensitive data management",
      "analysis": "In 'db_interface.py', sensitive database details such as database credentials might be hardcoded in the application. After deploying the app, these credentials can be exposed and pose a major security risk by allowing unauthorized access.\n",
      "classification": "very promising",
      "cwe": "CWE-798",
      "function_names": [
        "load_config"
      ],
      "filenames": [
        "src/utils/db_interface.py"
      ]
    },
    {
      "headline": "Improper filesystem permissions for important directories",
      "analysis": "The application does not set proper filesystem permissions while creating directories such as 'user_images/pfp'. This can lead to unauthorized access or disclosure of sensitive user data by local users on the server.\n",
      "classification": "slightly promising",
      "cwe": "CWE-276",
      "function_names": [
        "home"
      ],
      "filenames": [
        "src/auth_server.py"
      ]
    },
    {
      "headline": "Vulnerable endpoint exposure due to deprecated practices",
      "analysis": "Several endpoints are annotated as 'DEPRECIATED' but remain active in the codebase, such as '/login/{username}/{password}'. This leaves deprecated code paths accessible, potentially exposing the application to known vulnerabilities associated with older practices.\n",
      "classification": "slightly promising",
      "cwe": "CWE-676",
      "function_names": [
        "login",
        "create_account"
      ],
      "filenames": [
        "src/auth_server.py"
      ]
    },
    {
      "headline": "Lack of effective error handling promotes information leakage",
      "analysis": "The application's exception handling routines disclose excessive information about underlying operations. For example, database connection failures are displayed with details that might help an attacker determine further attack vectors or underlying technologies used.\n",
      "classification": "not promising",
      "cwe": "CWE-209",
      "function_names": [
        "connect_to_database"
      ],
      "filenames": [
        "src/utils/db_client.py"
      ]
    },
    {
      "headline": "Inadequate password hashing mechanism leads to compromise of password data security",
      "analysis": "'password_hasher.py' incorrectly employs a basic SHA-256 hashing mechanism without sufficient salting, posing a major risk as attackers might easily crack hashed passwords using ordinary dictionaries and complex strategies such as rainbow table attacks.\n",
      "classification": "very promising",
      "cwe": "CWE-916",
      "function_names": [
        "get_hash_gen_salt"
      ],
      "filenames": [
        "src/utils/password_hasher.py"
      ]
    },
    {
      "headline": "Information disclosure via detailed error messages",
      "analysis": "The application improperly handles error conditions and exceptions by providing detailed error messages that could lead to exposure of sensitive information about the backend processes, potentially giving attackers insights into the infrastructure.\n",
      "classification": "slightly promising",
      "cwe": "CWE-215",
      "function_names": [
        "update_account_info"
      ],
      "filenames": [
        "src/auth_server.py"
      ]
    }
  ],
  "scores": [
    {
      "stats": {
        "fn": 1,
        "tp": 0,
        "fp": 3
      },
      "mapping": {},
      "vuln_dates": {
        "CVE-2023-49801": "2024-01-12T21:15:09"
      },
      "scoring_model": "gpt-4o-2024-05-13",
      "type": "llm",
      "instruction_template_hash": "8998f09cf57fca8a6e03"
    },
    {
      "stats": {
        "fn": 1,
        "tp": 0,
        "fp": 3
      },
      "mapping": {},
      "vuln_dates": {
        "CVE-2023-49801": "2024-01-12T21:15:09"
      },
      "scoring_model": "claude-3-opus-20240229",
      "type": "llm",
      "instruction_template_hash": "245ace12b6361954d0a2"
    }
  ],
  "instruction_template_hash": "10c0163db4740318a544",
  "version": "0.1.0"
}
