{
  "commit": "130c30e33df1e07590dbf8eaeb0c2c78b856a6ce",
  "repo_url": "https://github.com/snyk/kubernetes-monitor",
  "model": "gpt-4o-2024-05-13",
  "chunk_hashes": [
    "2a8a81b46a30739e8fca"
  ],
  "responses": [
    {
      "content": "```yaml\nleads:\n  - headline: Potential credential leakage in image scanning\n    analysis: |\n      In `src/scanner/images/skopeo.ts`, the `getCertificatesParameters` function sets the certificates directory path statically to `/srv/app/certs`. This could potentially expose sensitive credentials if the path is incorrect or misconfigured.\n    cwe: CWE-200\n    function_names:\n      - getCertificatesParameters\n    filenames:\n      - src/scanner/images/skopeo.ts\n    classification: very promising\n\n  - headline: Improper validation of input leading to command injection\n    analysis: |\n      In `src/supervisor/kuberenetes-api-wrappers.ts`, the `calculateSleepSeconds` function attempts to parse headers without thorough validation. If `Retry-After` header contains invalid input, it could lead to command injection.\n    cwe: CWE-20\n    function_names:\n      - calculateSleepSeconds\n    filenames:\n      - src/supervisor/kuberenetes-api-wrappers.ts\n    classification: very promising\n\n  - headline: Unsecured handling of sensitive data\n    analysis: |\n      In `src/data-scraper/index.ts`, the `scrapeData` function performs requests to external services including authorization headers directly as strings. This is risky if the logs are not adequately sanitized.\n    cwe: CWE-312\n    function_names:\n      - scrapeData\n    filenames:\n      - src/data-scraper/index.ts\n    classification: slightly promising\n\n  - headline: Insecure random seed generation\n    analysis: |\n      At multiple places in `src/scanner/images/skopeo.ts`, random identifiers are generated using process.hrtime(), which may not offer sufficient entropy for security-critical applications.\n    cwe: CWE-330\n    function_names:\n      - getUniqueIdentifier\n    filenames:\n      - src/scanner/images/skopeo.ts\n    classification: not promising\n\n  - headline: Race condition in logging of queue size\n    analysis: |\n      In `src/supervisor/watchers/handlers/queue.ts`, functions `queueWorkerWorkloadScan` and `reportQueueSize` use shared state without proper synchronization, which could lead to a race condition affecting the log size report.\n    cwe: CWE-362\n    function_names:\n      - queueWorkerWorkloadScan\n      - reportQueueSize\n    filenames:\n      - src/supervisor/watchers/handlers/queue.ts\n    classification: slightly promising\n\n  - headline: Missing validation for external input\n    analysis: |\n      In `src/common/config.ts`, external environment variables are loaded without validation or sanitization, making the system prone to configuration injection attacks.\n    cwe: CWE-20\n    function_names:\n      - loadConfig\n    filenames:\n      - src/common/config.ts\n    classification: very promising\n```",
      "date": "2024-06-13T11:53:55.140896",
      "usage": {
        "prompt_tokens": 99668,
        "completion_tokens": 587,
        "cost": 0.507145
      }
    }
  ],
  "leads": [
    {
      "headline": "Potential credential leakage in image scanning",
      "analysis": "In src/scanner/images/skopeo.ts, the getCertificatesParameters function sets the certificates directory path statically to /srv/app/certs. This could potentially expose sensitive credentials if the path is incorrect or misconfigured.\n",
      "classification": "very promising",
      "cwe": "CWE-200",
      "function_names": [
        "getCertificatesParameters"
      ],
      "filenames": [
        "src/scanner/images/skopeo.ts"
      ]
    },
    {
      "headline": "Improper validation of input leading to command injection",
      "analysis": "In src/supervisor/kuberenetes-api-wrappers.ts, the calculateSleepSeconds function attempts to parse headers without thorough validation. If Retry-After header contains invalid input, it could lead to command injection.\n",
      "classification": "very promising",
      "cwe": "CWE-20",
      "function_names": [
        "calculateSleepSeconds"
      ],
      "filenames": [
        "src/supervisor/kuberenetes-api-wrappers.ts"
      ]
    },
    {
      "headline": "Unsecured handling of sensitive data",
      "analysis": "In src/data-scraper/index.ts, the scrapeData function performs requests to external services including authorization headers directly as strings. This is risky if the logs are not adequately sanitized.\n",
      "classification": "slightly promising",
      "cwe": "CWE-312",
      "function_names": [
        "scrapeData"
      ],
      "filenames": [
        "src/data-scraper/index.ts"
      ]
    },
    {
      "headline": "Insecure random seed generation",
      "analysis": "At multiple places in src/scanner/images/skopeo.ts, random identifiers are generated using process.hrtime(), which may not offer sufficient entropy for security-critical applications.\n",
      "classification": "not promising",
      "cwe": "CWE-330",
      "function_names": [
        "getUniqueIdentifier"
      ],
      "filenames": [
        "src/scanner/images/skopeo.ts"
      ]
    },
    {
      "headline": "Race condition in logging of queue size",
      "analysis": "In src/supervisor/watchers/handlers/queue.ts, functions queueWorkerWorkloadScan and reportQueueSize use shared state without proper synchronization, which could lead to a race condition affecting the log size report.\n",
      "classification": "slightly promising",
      "cwe": "CWE-362",
      "function_names": [
        "queueWorkerWorkloadScan",
        "reportQueueSize"
      ],
      "filenames": [
        "src/supervisor/watchers/handlers/queue.ts"
      ]
    },
    {
      "headline": "Missing validation for external input",
      "analysis": "In src/common/config.ts, external environment variables are loaded without validation or sanitization, making the system prone to configuration injection attacks.\n",
      "classification": "very promising",
      "cwe": "CWE-20",
      "function_names": [
        "loadConfig"
      ],
      "filenames": [
        "src/common/config.ts"
      ]
    }
  ],
  "scores": [
    {
      "stats": {
        "fn": 1,
        "tp": 0,
        "fp": 3
      },
      "mapping": {},
      "vuln_dates": {
        "CVE-2023-1065": "2023-02-28T19:15:16"
      },
      "scoring_model": "claude-3-opus-20240229",
      "type": "llm",
      "instruction_template_hash": "245ace12b6361954d0a2"
    }
  ],
  "instruction_template_hash": "10c0163db4740318a544",
  "version": "0.1.0"
}
