{
  "commit": "46f66a9e091f752ed74dade8101ea4f201a95b5e",
  "repo_url": "https://github.com/operatorequals/wormnest",
  "model": "gpt-4-turbo-2024-04-09",
  "chunk_hashes": [
    "2ac50fb19139ae7e0977"
  ],
  "responses": [
    {
      "content": "```yaml\nleads:\n  - headline: Insecure File Upload Handling\n    analysis: |\n      The application allows users to upload files using simple form submissions with the intention of serving these files via generated URLs. This feature doesn't enforce any checks on the type of file being uploaded, proper validation of MIME types, or execution of uploaded files. Attackers could upload malicious scripts or executables, creating a vector for delivering malware or taking control over the server. \n    cwe: CWE-434\n    function_names:\n      - file_upload\n    filenames:\n      - /app.py\n    classification: very promising\n\n  - headline: Command Injection via Hook Scripts\n    analysis: |\n      The application allows the execution of custom hook scripts, which in turn execute system commands such as spawning subprocesses to run shell commands (`msfvenom` in this case). This can lead to command injection if any part of the command parameters can be influenced by user input, or if an attacker can manipulate the script's logic. Additionally, the commands can execute with the same privileges as the application, potentially leading to privilege escalation.\n    cwe: CWE-77\n    function_names:\n      - autogen_msf\n    filenames:\n      - /hooks/autogen_msf.py\n    classification: very promising\n\n  - headline: Lack of Proper Access Control and URL Alias Reuse\n    analysis: |\n      The application manages URL aliases without proper checks on URL uniqueness or expiration logic, leading to potential overwrites of existing aliases or access to expired links. There is also a risk of unauthorized access due to predictable URL paths or poorly managed deletion logic that relies solely on URL alias names without further validation of request origin or user permissions.\n    cwe: CWE-284\n    function_names:\n      - add_url\n      - del_url\n    filenames:\n      - /wormnest/db_handler.py\n    classification: slightly promising\n\n  - headline: SQL Injection via URL Path Handling\n    analysis: |\n      The application handles user input to construct database queries directly, notably in the `del_url` and `add_url` functions, where URL aliases are directly derived from user input without sufficient sanitization. This may allow for SQL injection if an attacker crafts input strings that alter the SQL commands, particularly if the aliases contain SQL control characters or statements.\n    cwe: CWE-89\n    function_names:\n      - del_url\n      - add_url\n    filenames:\n      - /wormnest/db_handler.py\n    classification: very promising\n\n  - headline: Inadequate Encryption Strength and Use of Default Credentials\n    analysis: |\n      Configuration settings allow for hardcoded, potentially weak defaults such as default administrative URLs, file paths, and server headers. These can be leveraged by an attacker to guess configuration parameters or benefit from weak security practices related to hard-coded or default credentials.\n    cwe: CWE-916\n    function_names:\n      - parse_config\n    filenames:\n      - /wormnest/utils.py\n    classification: slightly promising\n\n  - headline: User Enumeration through Error Messages\n    analysis: |\n      The application provides detailed error messages that might disclose whether certain operations, such as URL deletion or file management actions, were successful or not. This could aid an attacker in enumerating valid URLs, file paths, or operational states of the application, facilitating further targeted attacks.\n    cwe: CWE-203\n    function_names:\n      - del_url\n      - add_url\n    filenames:\n      - /app.py\n    classification: slightly promising\n\n  - headline: Insufficient Logging of Security-relevant Events\n    analysis: |\n      The application logs activities in a way that might omit important security-relevant details or does not ensure the integrity or confidentiality of log data. This could prevent effective forensic analysis or incident response due to lack of detailed or trustworthy logs concerning user actions, especially malicious activities.\n    cwe: CWE-778\n    function_names:\n      - req_log_hook\n    filenames:\n      - /hooks/req_log_hook.py\n    classification: slightly promising\n```",
      "date": "2024-06-14T15:05:28.108539",
      "usage": {
        "prompt_tokens": 10815,
        "completion_tokens": 828,
        "cost": 0.13299
      }
    }
  ],
  "leads": [
    {
      "headline": "Insecure File Upload Handling",
      "analysis": "The application allows users to upload files using simple form submissions with the intention of serving these files via generated URLs. This feature doesn't enforce any checks on the type of file being uploaded, proper validation of MIME types, or execution of uploaded files. Attackers could upload malicious scripts or executables, creating a vector for delivering malware or taking control over the server. \n",
      "classification": "very promising",
      "cwe": "CWE-434",
      "function_names": [
        "file_upload"
      ],
      "filenames": [
        "/app.py"
      ]
    },
    {
      "headline": "Command Injection via Hook Scripts",
      "analysis": "The application allows the execution of custom hook scripts, which in turn execute system commands such as spawning subprocesses to run shell commands (msfvenom in this case). This can lead to command injection if any part of the command parameters can be influenced by user input, or if an attacker can manipulate the script's logic. Additionally, the commands can execute with the same privileges as the application, potentially leading to privilege escalation.\n",
      "classification": "very promising",
      "cwe": "CWE-77",
      "function_names": [
        "autogen_msf"
      ],
      "filenames": [
        "/hooks/autogen_msf.py"
      ]
    },
    {
      "headline": "Lack of Proper Access Control and URL Alias Reuse",
      "analysis": "The application manages URL aliases without proper checks on URL uniqueness or expiration logic, leading to potential overwrites of existing aliases or access to expired links. There is also a risk of unauthorized access due to predictable URL paths or poorly managed deletion logic that relies solely on URL alias names without further validation of request origin or user permissions.\n",
      "classification": "slightly promising",
      "cwe": "CWE-284",
      "function_names": [
        "add_url",
        "del_url"
      ],
      "filenames": [
        "/wormnest/db_handler.py"
      ]
    },
    {
      "headline": "SQL Injection via URL Path Handling",
      "analysis": "The application handles user input to construct database queries directly, notably in the del_url and add_url functions, where URL aliases are directly derived from user input without sufficient sanitization. This may allow for SQL injection if an attacker crafts input strings that alter the SQL commands, particularly if the aliases contain SQL control characters or statements.\n",
      "classification": "very promising",
      "cwe": "CWE-89",
      "function_names": [
        "del_url",
        "add_url"
      ],
      "filenames": [
        "/wormnest/db_handler.py"
      ]
    },
    {
      "headline": "Inadequate Encryption Strength and Use of Default Credentials",
      "analysis": "Configuration settings allow for hardcoded, potentially weak defaults such as default administrative URLs, file paths, and server headers. These can be leveraged by an attacker to guess configuration parameters or benefit from weak security practices related to hard-coded or default credentials.\n",
      "classification": "slightly promising",
      "cwe": "CWE-916",
      "function_names": [
        "parse_config"
      ],
      "filenames": [
        "/wormnest/utils.py"
      ]
    },
    {
      "headline": "User Enumeration through Error Messages",
      "analysis": "The application provides detailed error messages that might disclose whether certain operations, such as URL deletion or file management actions, were successful or not. This could aid an attacker in enumerating valid URLs, file paths, or operational states of the application, facilitating further targeted attacks.\n",
      "classification": "slightly promising",
      "cwe": "CWE-203",
      "function_names": [
        "del_url",
        "add_url"
      ],
      "filenames": [
        "/app.py"
      ]
    },
    {
      "headline": "Insufficient Logging of Security-relevant Events",
      "analysis": "The application logs activities in a way that might omit important security-relevant details or does not ensure the integrity or confidentiality of log data. This could prevent effective forensic analysis or incident response due to lack of detailed or trustworthy logs concerning user actions, especially malicious activities.\n",
      "classification": "slightly promising",
      "cwe": "CWE-778",
      "function_names": [
        "req_log_hook"
      ],
      "filenames": [
        "/hooks/req_log_hook.py"
      ]
    }
  ],
  "scores": [
    {
      "stats": {
        "fn": 1,
        "tp": 0,
        "fp": 3
      },
      "mapping": {},
      "vuln_dates": {
        "CVE-2022-31502": "2022-07-11T01:15:08"
      },
      "scoring_model": "claude-3-opus-20240229",
      "type": "llm",
      "instruction_template_hash": "245ace12b6361954d0a2"
    },
    {
      "stats": {
        "fn": 1,
        "tp": 0,
        "fp": 3
      },
      "mapping": {},
      "vuln_dates": {
        "CVE-2022-31502": "2022-07-11T01:15:08"
      },
      "scoring_model": "claude-3-5-sonnet-20240620",
      "type": "llm",
      "instruction_template_hash": "245ace12b6361954d0a2"
    }
  ],
  "instruction_template_hash": "10c0163db4740318a544",
  "version": "0.1.0"
}
