{
  "commit": "39c4a78634966f9fb965ab1060f70eac41c52966",
  "repo_url": "https://github.com/turbowarp/desktop",
  "model": "gemini/gemini-1.5-pro",
  "chunk_hashes": [
    "0e73bcbe6a8a8501ff90"
  ],
  "responses": [
    {
      "content": "```yaml\nleads:\n  - headline: Path Traversal in Library File Protocol\n    analysis: |\n      The `tw-library-files` custom protocol handler in `src/main/library-files.js` is vulnerable to path traversal. While the code checks that `compressedFile.startsWith(baseDirectory)`, an attacker can construct a path like `../../evil.js` that passes the check because it starts with the correct base directory, but the `../` sequences escape the intended directory.  A malicious extension could use this vulnerability to get the Electron process to read arbitrary files on the user's computer.\n    cwe: CWE-22\n    function_names:\n      - decompressAsset\n    filenames:\n      - src/main/library-files.js\n    classification: slightly promising\n  - headline: Inadequate Validation of Project IDs in Project Metadata API\n    analysis: |\n      The `get-project-metadata` IPC handler in `src/main/index.js` does not adequately validate the supplied project ID before making a request to the Scratch API.  While it verifies that the ID is numeric, it does not check that the ID corresponds to a real project. This could be abused by malicious extensions to cause the TurboWarp Desktop process to send many useless requests to the Scratch API, potentially contributing to a denial-of-service attack.\n    cwe: CWE-20\n    function_names: []\n    filenames:\n      - src/main/index.js\n    classification: not promising\n  - headline: Lack of Sandboxing for Extensions\n    analysis: |\n      The `loadExtension` method, exposed via the preload script in `src/main/preload.js`, does not provide a sandboxed environment for extensions. Extensions are granted full access to Node.js and Electron APIs, posing a security risk as a malicious extension could compromise the user's system.\n    cwe: CWE-829\n    function_names:\n      - loadExtension\n    filenames:\n      - src/main/preload.js\n    classification: very promising\n  - headline: Unrestricted File Access for Packaged Projects\n    analysis: |\n      The `get-packager-html` IPC handler in `src/main/index.js` retrieves and serves the packager HTML file directly from the file system, potentially allowing a packaged project to access sensitive files or resources within the application's installation directory.\n    cwe: CWE-552\n    function_names: []\n    filenames:\n      - src/main/index.js\n    classification: slightly promising\n  - headline: Unfiltered URL Redirection\n    analysis: |\n      The code in `src/main/extensions.js` redirects any request to `https://extensions.turbowarp.org/*` to a custom `tw-extensions://` protocol. However, there is no validation or filtering of the path component of the URL.  A malicious extension website could potentially craft URLs that redirect users to external, potentially harmful, websites.\n    cwe: CWE-601\n    function_names: []\n    filenames:\n      - src/main/extensions.js\n    classification: slightly promising\n  - headline: Unsafe Usage of `session.fromPartition` in Data URLs\n    analysis: |\n      The `createDataWindow` function in `src/main/index.js` creates a new BrowserWindow for handling data URLs using `session.fromPartition('unsafe-data-url')`. However, this approach might not adequately isolate data URLs from the main application context. A malicious data URL could potentially exploit vulnerabilities in the renderer process or access resources outside the intended scope.\n    cwe: CWE-668\n    function_names:\n      - createDataWindow\n    filenames:\n      - src/main/index.js\n    classification: slightly promising\n  - headline: Potential for XSS in Advanced User Customizations\n    analysis: |\n      The code in `src/main/advanced-user-customizations.js` loads user-provided JavaScript and CSS code and injects it directly into the application's DOM without any sanitization or escaping. This could potentially allow an attacker to inject malicious code into the application, leading to XSS vulnerabilities.\n    cwe: CWE-79\n    function_names: []\n    filenames:\n      - src/main/advanced-user-customizations.js\n    classification: slightly promising\n  - headline: Unrestricted File Access for File Write Operations\n    analysis: |\n      The `write-file-with-port` IPC handler in `src/main/index.js` allows the renderer process to write data to any file on the system to which it has previously been granted access. While the code checks for prior authorization, it lacks sufficient restrictions on the types of files that can be written or modified. Malicious code in the renderer process could leverage this to overwrite system files or create new files in sensitive locations.\n    cwe: CWE-732\n    function_names: []\n    filenames:\n      - src/main/index.js\n    classification: very promising\n```",
      "date": "2024-07-08T09:03:43.054819",
      "usage": {
        "prompt_tokens": 57359,
        "completion_tokens": 973,
        "cost": 0.30139000000000005
      }
    }
  ],
  "leads": [
    {
      "headline": "Path Traversal in Library File Protocol",
      "analysis": "The tw-library-files custom protocol handler in src/main/library-files.js is vulnerable to path traversal. While the code checks that compressedFile.startsWith(baseDirectory), an attacker can construct a path like ../../evil.js that passes the check because it starts with the correct base directory, but the ../ sequences escape the intended directory.  A malicious extension could use this vulnerability to get the Electron process to read arbitrary files on the user's computer.\n",
      "classification": "slightly promising",
      "cwe": "CWE-22",
      "function_names": [
        "decompressAsset"
      ],
      "filenames": [
        "src/main/library-files.js"
      ]
    },
    {
      "headline": "Inadequate Validation of Project IDs in Project Metadata API",
      "analysis": "The get-project-metadata IPC handler in src/main/index.js does not adequately validate the supplied project ID before making a request to the Scratch API.  While it verifies that the ID is numeric, it does not check that the ID corresponds to a real project. This could be abused by malicious extensions to cause the TurboWarp Desktop process to send many useless requests to the Scratch API, potentially contributing to a denial-of-service attack.\n",
      "classification": "not promising",
      "cwe": "CWE-20",
      "function_names": [],
      "filenames": [
        "src/main/index.js"
      ]
    },
    {
      "headline": "Lack of Sandboxing for Extensions",
      "analysis": "The loadExtension method, exposed via the preload script in src/main/preload.js, does not provide a sandboxed environment for extensions. Extensions are granted full access to Node.js and Electron APIs, posing a security risk as a malicious extension could compromise the user's system.\n",
      "classification": "very promising",
      "cwe": "CWE-829",
      "function_names": [
        "loadExtension"
      ],
      "filenames": [
        "src/main/preload.js"
      ]
    },
    {
      "headline": "Unrestricted File Access for Packaged Projects",
      "analysis": "The get-packager-html IPC handler in src/main/index.js retrieves and serves the packager HTML file directly from the file system, potentially allowing a packaged project to access sensitive files or resources within the application's installation directory.\n",
      "classification": "slightly promising",
      "cwe": "CWE-552",
      "function_names": [],
      "filenames": [
        "src/main/index.js"
      ]
    },
    {
      "headline": "Unfiltered URL Redirection",
      "analysis": "The code in src/main/extensions.js redirects any request to https://extensions.turbowarp.org/* to a custom tw-extensions:// protocol. However, there is no validation or filtering of the path component of the URL.  A malicious extension website could potentially craft URLs that redirect users to external, potentially harmful, websites.\n",
      "classification": "slightly promising",
      "cwe": "CWE-601",
      "function_names": [],
      "filenames": [
        "src/main/extensions.js"
      ]
    },
    {
      "headline": "Unsafe Usage of session.fromPartition in Data URLs",
      "analysis": "The createDataWindow function in src/main/index.js creates a new BrowserWindow for handling data URLs using session.fromPartition('unsafe-data-url'). However, this approach might not adequately isolate data URLs from the main application context. A malicious data URL could potentially exploit vulnerabilities in the renderer process or access resources outside the intended scope.\n",
      "classification": "slightly promising",
      "cwe": "CWE-668",
      "function_names": [
        "createDataWindow"
      ],
      "filenames": [
        "src/main/index.js"
      ]
    },
    {
      "headline": "Potential for XSS in Advanced User Customizations",
      "analysis": "The code in src/main/advanced-user-customizations.js loads user-provided JavaScript and CSS code and injects it directly into the application's DOM without any sanitization or escaping. This could potentially allow an attacker to inject malicious code into the application, leading to XSS vulnerabilities.\n",
      "classification": "slightly promising",
      "cwe": "CWE-79",
      "function_names": [],
      "filenames": [
        "src/main/advanced-user-customizations.js"
      ]
    },
    {
      "headline": "Unrestricted File Access for File Write Operations",
      "analysis": "The write-file-with-port IPC handler in src/main/index.js allows the renderer process to write data to any file on the system to which it has previously been granted access. While the code checks for prior authorization, it lacks sufficient restrictions on the types of files that can be written or modified. Malicious code in the renderer process could leverage this to overwrite system files or create new files in sensitive locations.\n",
      "classification": "very promising",
      "cwe": "CWE-732",
      "function_names": [],
      "filenames": [
        "src/main/index.js"
      ]
    }
  ],
  "scores": [
    {
      "stats": {
        "fn": 0,
        "tp": 1,
        "fp": 1
      },
      "mapping": {
        "0": "CVE-2023-40168"
      },
      "vuln_dates": {
        "CVE-2023-40168": "2023-08-17T20:15:11"
      },
      "scoring_model": "claude-3-5-sonnet-20240620",
      "type": "llm",
      "instruction_template_hash": "245ace12b6361954d0a2"
    }
  ],
  "instruction_template_hash": "10c0163db4740318a544",
  "version": "0.1.0"
}
