{
  "commit": "18dd404526deba022102c9fe86a4dcbe481ca26b",
  "repo_url": "https://github.com/betterment/test_track",
  "model": "gpt-4o-2024-05-13",
  "chunk_hashes": [
    "545ebdd40c7cdc85d3da"
  ],
  "responses": [
    {
      "content": "```yaml\nleads:\n  - headline: \"Missing Input Validation in Dropdown Menus\"\n    analysis: |\n      In the `vendor/gems/style-closet/app/assets/javascripts/style-closet/dropdowns.js` file, there is no proper input validation for user interactions with dropdown menus. Specifically, the `optionSelected` function does not perform any validation or sanitization on the selected option before it is processed. This can potentially result in Injection vulnerabilities, including Cross-Site Scripting (XSS) if the dropdown values are influenced by user input.\n    cwe: CWE-20\n    function_names:\n      - toggleDropdown\n      - optionSelected\n    filenames:\n      - vendor/gems/style-closet/app/assets/javascripts/style-closet/dropdowns.js\n    classification: very promising\n  - headline: \"DOM-based Cross-Site Scripting (XSS) in Flash Messages\"\n    analysis: |\n      The `vendor/gems/style-closet/app/assets/javascripts/style-closet/flashes.js` file contains code for hiding flash messages. There is potential for DOM-based XSS if an attacker can manipulate the content of flash messages. The code directly interacts with the DOM without any sanitization, making it prone to XSS attacks if malicious content is injected into flash messages.\n    cwe: CWE-79\n    function_names:\n      - N/A\n    filenames:\n      - vendor/gems/style-closet/app/assets/javascripts/style-closet/flashes.js\n    classification: very promising\n  - headline: \"Clickjacking Vulnerability due to Lack of X-Frame-Options Header\"\n    analysis: |\n      The HTML files in the `public` directory do not include security headers that could mitigate clickjacking attacks. The missing X-Frame-Options header allows these pages to be embedded in iframes, potentially leading to clickjacking attacks where users are tricked into clicking on something different from what they perceive.\n    cwe: CWE-1021\n    function_names: []\n    filenames:\n      - public/500.html\n      - public/422.html\n      - public/404.html\n    classification: slightly promising\n  - headline: \"Weak JavaScript Code in Event Handlers\"\n    analysis: |\n      The JavaScript files found in `vendor/gems/style-closet/app/assets/javascripts` lack proper error handling and validation mechanisms. For example, the code in `base_inputs.js` and `radio_buttons.js` directly manipulates the DOM without checking for exceptional conditions or validating input values. This can lead to a variety of issues, including but not limited to inconsistent application states, unexpected behavior, and potential security risks.\n    cwe: CWE-754\n    function_names:\n      - selectRadioButton\n      - N/A (anonymous functions)\n    filenames:\n      - vendor/gems/style-closet/app/assets/javascripts/style-closet/base_inputs.js\n      - vendor/gems/style-closet/app/assets/javascripts/style-closet/radio_buttons.js\n    classification: not promising\n```",
      "date": "2024-06-12T15:11:33.774080",
      "usage": {
        "prompt_tokens": 5383,
        "completion_tokens": 637,
        "cost": 0.03647
      }
    }
  ],
  "leads": [
    {
      "headline": "Missing Input Validation in Dropdown Menus",
      "analysis": "In the vendor/gems/style-closet/app/assets/javascripts/style-closet/dropdowns.js file, there is no proper input validation for user interactions with dropdown menus. Specifically, the optionSelected function does not perform any validation or sanitization on the selected option before it is processed. This can potentially result in Injection vulnerabilities, including Cross-Site Scripting (XSS) if the dropdown values are influenced by user input.\n",
      "classification": "very promising",
      "cwe": "CWE-20",
      "function_names": [
        "toggleDropdown",
        "optionSelected"
      ],
      "filenames": [
        "vendor/gems/style-closet/app/assets/javascripts/style-closet/dropdowns.js"
      ]
    },
    {
      "headline": "DOM-based Cross-Site Scripting (XSS) in Flash Messages",
      "analysis": "The vendor/gems/style-closet/app/assets/javascripts/style-closet/flashes.js file contains code for hiding flash messages. There is potential for DOM-based XSS if an attacker can manipulate the content of flash messages. The code directly interacts with the DOM without any sanitization, making it prone to XSS attacks if malicious content is injected into flash messages.\n",
      "classification": "very promising",
      "cwe": "CWE-79",
      "function_names": [
        "N/A"
      ],
      "filenames": [
        "vendor/gems/style-closet/app/assets/javascripts/style-closet/flashes.js"
      ]
    },
    {
      "headline": "Clickjacking Vulnerability due to Lack of X-Frame-Options Header",
      "analysis": "The HTML files in the public directory do not include security headers that could mitigate clickjacking attacks. The missing X-Frame-Options header allows these pages to be embedded in iframes, potentially leading to clickjacking attacks where users are tricked into clicking on something different from what they perceive.\n",
      "classification": "slightly promising",
      "cwe": "CWE-1021",
      "function_names": [],
      "filenames": [
        "public/500.html",
        "public/422.html",
        "public/404.html"
      ]
    },
    {
      "headline": "Weak JavaScript Code in Event Handlers",
      "analysis": "The JavaScript files found in vendor/gems/style-closet/app/assets/javascripts lack proper error handling and validation mechanisms. For example, the code in base_inputs.js and radio_buttons.js directly manipulates the DOM without checking for exceptional conditions or validating input values. This can lead to a variety of issues, including but not limited to inconsistent application states, unexpected behavior, and potential security risks.\n",
      "classification": "not promising",
      "cwe": "CWE-754",
      "function_names": [
        "selectRadioButton",
        "N/A (anonymous functions)"
      ],
      "filenames": [
        "vendor/gems/style-closet/app/assets/javascripts/style-closet/base_inputs.js",
        "vendor/gems/style-closet/app/assets/javascripts/style-closet/radio_buttons.js"
      ]
    }
  ],
  "scores": [
    {
      "stats": {
        "fn": 1,
        "tp": 0,
        "fp": 2
      },
      "mapping": {},
      "vuln_dates": {
        "CVE-2017-1000068": "2017-07-17T13:18:18"
      },
      "scoring_model": "claude-3-opus-20240229",
      "type": "llm",
      "instruction_template_hash": "245ace12b6361954d0a2"
    },
    {
      "stats": {
        "fn": 1,
        "tp": 0,
        "fp": 2
      },
      "mapping": {},
      "vuln_dates": {
        "CVE-2017-1000068": "2017-07-17T13:18:18"
      },
      "scoring_model": "claude-3-5-sonnet-20240620",
      "type": "llm",
      "instruction_template_hash": "245ace12b6361954d0a2"
    }
  ],
  "instruction_template_hash": "10c0163db4740318a544",
  "version": "0.1.0"
}
