{
  "commit": "fa2b2f565d91332feca03ea49a5497a753cedf94",
  "repo_url": "https://github.com/luxiaoxun/nettyrpc",
  "model": "gpt-4o-2024-05-13",
  "chunk_hashes": [
    "e5fa36552e4d7bc9874b"
  ],
  "responses": [
    {
      "content": "```yaml\nleads:\n  - headline: \"Potential Insecure Deserialization\"\n    analysis: |\n      The JsonUtil and SerializationUtil classes in the codebase utilize libraries for the purpose of serialization and deserialization. Specifically, methods like `deserialize` in both `JsonUtil` and `SerializationUtil` instantiate classes or handle serialized data dynamically. If an attacker can control input to these methods, they might exploit deserialization to execute malicious code, leading to remote code execution (RCE).\n    cwe: CWE-502\n    function_names:\n      - deserialize\n    filenames:\n      - netty-rpc-common/src/main/java/com/netty/rpc/util/JsonUtil.java\n      - netty-rpc-common/src/main/java/com/netty/rpc/util/SerializationUtil.java\n    classification: very promising\n  \n  - headline: \"Null Pointer Dereference\"\n    analysis: |\n      In RpcClientHandler.java, the method `channelRead0` retrieves elements from `pendingRPC` map using the `requestId` key. If no corresponding value is found, the method will log a warning but continues to process. There is potential for null dereference or unexpected errors if other parts of the code do not handle this scenario effectively.\n    cwe: CWE-476\n    function_names:\n      - channelRead0\n    filenames:\n      - netty-rpc-client/src/main/java/com/netty/rpc/client/handler/RpcClientHandler.java\n    classification: slightly promising\n  \n  - headline: \"Uncontrolled Resource Consumption\"\n    analysis: |\n      The `RpcFuture` class in RpcFuture.java uses a list of `AsyncRPCCallback` objects for pending callbacks. If the `addCallback` method is invoked frequently or with large volumes, it can lead to uncontrolled resource consumption, potentially resulting in a denial of service (DoS) attack.\n    cwe: CWE-400\n    function_names:\n      - addCallback\n    filenames:\n      - netty-rpc-client/src/main/java/com/netty/rpc/client/handler/RpcFuture.java\n    classification: slightly promising\n\n  - headline: \"Weak Encryption Configuration\"\n    analysis: |\n      The `CuratorClient` class creates a connection with exponential backoff policy for retry mechanism. However, the configuration of this retry mechanism does not use any secured protocol for retry attempts or validation, making it susceptible to man-in-the-middle (MitM) attacks if misconfigured for use in production environments.\n    cwe: CWE-326\n    function_names:\n      - CuratorClient\n    filenames:\n      - netty-rpc-common/src/main/java/com/netty/rpc/zookeeper/CuratorClient.java\n    classification: not promising\n\n  - headline: \"Exposure of Sensitive Information in Logs\"\n    analysis: |\n      Logging statements within RpcClientHandler.java and similar files may expose sensitive information such as request IDs, method names, and parameters. This can potentially leak sensitive information useful for attackers.\n    cwe: CWE-532\n    function_names:\n      - channelRead0\n      - sendRequest\n      - invoke\n    filenames:\n      - netty-rpc-client/src/main/java/com/netty/rpc/client/handler/RpcClientHandler.java\n      - netty-rpc-client/src/main/java/com/netty/rpc/client/proxy/ObjectProxy.java\n    classification: slightly promising\n```",
      "date": "2024-06-09T13:19:55.499868",
      "usage": {
        "prompt_tokens": 24382,
        "completion_tokens": 687,
        "cost": 0.132215
      }
    }
  ],
  "leads": [
    {
      "headline": "Potential Insecure Deserialization",
      "analysis": "The JsonUtil and SerializationUtil classes in the codebase utilize libraries for the purpose of serialization and deserialization. Specifically, methods like deserialize in both JsonUtil and SerializationUtil instantiate classes or handle serialized data dynamically. If an attacker can control input to these methods, they might exploit deserialization to execute malicious code, leading to remote code execution (RCE).\n",
      "classification": "very promising",
      "cwe": "CWE-502",
      "function_names": [
        "deserialize"
      ],
      "filenames": [
        "netty-rpc-common/src/main/java/com/netty/rpc/util/JsonUtil.java",
        "netty-rpc-common/src/main/java/com/netty/rpc/util/SerializationUtil.java"
      ]
    },
    {
      "headline": "Null Pointer Dereference",
      "analysis": "In RpcClientHandler.java, the method channelRead0 retrieves elements from pendingRPC map using the requestId key. If no corresponding value is found, the method will log a warning but continues to process. There is potential for null dereference or unexpected errors if other parts of the code do not handle this scenario effectively.\n",
      "classification": "slightly promising",
      "cwe": "CWE-476",
      "function_names": [
        "channelRead0"
      ],
      "filenames": [
        "netty-rpc-client/src/main/java/com/netty/rpc/client/handler/RpcClientHandler.java"
      ]
    },
    {
      "headline": "Uncontrolled Resource Consumption",
      "analysis": "The RpcFuture class in RpcFuture.java uses a list of AsyncRPCCallback objects for pending callbacks. If the addCallback method is invoked frequently or with large volumes, it can lead to uncontrolled resource consumption, potentially resulting in a denial of service (DoS) attack.\n",
      "classification": "slightly promising",
      "cwe": "CWE-400",
      "function_names": [
        "addCallback"
      ],
      "filenames": [
        "netty-rpc-client/src/main/java/com/netty/rpc/client/handler/RpcFuture.java"
      ]
    },
    {
      "headline": "Weak Encryption Configuration",
      "analysis": "The CuratorClient class creates a connection with exponential backoff policy for retry mechanism. However, the configuration of this retry mechanism does not use any secured protocol for retry attempts or validation, making it susceptible to man-in-the-middle (MitM) attacks if misconfigured for use in production environments.\n",
      "classification": "not promising",
      "cwe": "CWE-326",
      "function_names": [
        "CuratorClient"
      ],
      "filenames": [
        "netty-rpc-common/src/main/java/com/netty/rpc/zookeeper/CuratorClient.java"
      ]
    },
    {
      "headline": "Exposure of Sensitive Information in Logs",
      "analysis": "Logging statements within RpcClientHandler.java and similar files may expose sensitive information such as request IDs, method names, and parameters. This can potentially leak sensitive information useful for attackers.\n",
      "classification": "slightly promising",
      "cwe": "CWE-532",
      "function_names": [
        "channelRead0",
        "sendRequest",
        "invoke"
      ],
      "filenames": [
        "netty-rpc-client/src/main/java/com/netty/rpc/client/handler/RpcClientHandler.java",
        "netty-rpc-client/src/main/java/com/netty/rpc/client/proxy/ObjectProxy.java"
      ]
    }
  ],
  "scores": [
    {
      "stats": {
        "fn": 0,
        "tp": 1,
        "fp": 0
      },
      "mapping": {
        "0": "CVE-2023-48886"
      },
      "vuln_dates": {
        "CVE-2023-48886": "2023-12-01T23:15:07"
      },
      "scoring_model": "gpt-4o-2024-05-13",
      "type": "llm",
      "instruction_template_hash": "8998f09cf57fca8a6e03"
    }
  ],
  "instruction_template_hash": "10c0163db4740318a544",
  "version": "0.1.0"
}
