{
  "commit": "48fe028f3ea4b3e7544f03bce21ed6c93320abd4",
  "repo_url": "https://github.com/mayankmetha/rucky",
  "model": "claude-3-5-sonnet-20240620",
  "chunk_hashes": [
    "e4f0e4e8d0741e6f0983"
  ],
  "responses": [
    {
      "content": "```yaml\nleads:\n  - headline: Command injection vulnerability in gencon.sh\n    analysis: |\n      The gencon.sh script contains a command injection vulnerability in the handling of the $commitMsg variable. This variable is used unsanitized in a git commit command, allowing an attacker to inject arbitrary commands that will be executed with the permissions of the script. An attacker could exploit this to run malicious commands on the system.\n    cwe: CWE-78\n    function_names:\n      - commitMsg\n    filenames: \n      - app/gencon.sh\n    classification: very promising\n\n  - headline: Insecure data storage of sensitive key material\n    analysis: |\n      The application stores sensitive cryptographic key material in SharedPreferences. SharedPreferences provides weak protection and the keys could potentially be extracted by an attacker with access to the device storage. A more secure key storage mechanism like the Android Keystore should be used instead.\n    cwe: CWE-312 \n    function_names:\n      - getKeyStore1\n      - setKeyStore1\n      - getKeyStore2  \n      - setKeyStore2\n    filenames:\n      - app/src/main/java/com/mayank/rucky/utils/Config.java\n    classification: very promising\n\n  - headline: Insecure use of cryptography with ECB mode\n    analysis: |\n      The application uses ECB mode for encryption, which is insecure as it does not provide semantic security. ECB mode can leak information about plaintext patterns. A more secure mode like CBC or GCM should be used instead.\n    cwe: CWE-327\n    function_names:\n      - security\n    filenames:\n      - app/src/main/java/com/mayank/rucky/fragment/SettingsFragment.java  \n    classification: very promising\n\n  - headline: Potential command injection in HID command execution\n    analysis: |\n      The application builds and executes shell commands to emulate HID devices based on user input. If this input is not properly sanitized, it could allow command injection. An attacker could potentially execute arbitrary commands on the device by crafting malicious HID scripts.\n    cwe: CWE-78\n    function_names:\n      - launchAttack\n      - fetchCommands  \n    filenames:\n      - app/src/main/java/com/mayank/rucky/activity/EditorActivity.java\n    classification: slightly promising\n\n  - headline: Insecure random number generation\n    analysis: |\n      The application uses java.util.Random seeded with the current time for generating random values. This is not cryptographically secure and could be predicted. For security-sensitive random number generation, a cryptographically secure random number generator should be used instead.\n    cwe: CWE-330\n    function_names:\n      - randomTheme\n    filenames:\n      - app/src/main/java/com/mayank/rucky/utils/Randoms.java\n    classification: slightly promising\n```",
      "date": "2024-07-08T07:48:20.495969",
      "usage": {
        "prompt_tokens": 54192,
        "completion_tokens": 701,
        "cost": 0.173091
      }
    }
  ],
  "leads": [
    {
      "headline": "Command injection vulnerability in gencon.sh",
      "analysis": "The gencon.sh script contains a command injection vulnerability in the handling of the $commitMsg variable. This variable is used unsanitized in a git commit command, allowing an attacker to inject arbitrary commands that will be executed with the permissions of the script. An attacker could exploit this to run malicious commands on the system.\n",
      "classification": "very promising",
      "cwe": "CWE-78",
      "function_names": [
        "commitMsg"
      ],
      "filenames": [
        "app/gencon.sh"
      ]
    },
    {
      "headline": "Insecure data storage of sensitive key material",
      "analysis": "The application stores sensitive cryptographic key material in SharedPreferences. SharedPreferences provides weak protection and the keys could potentially be extracted by an attacker with access to the device storage. A more secure key storage mechanism like the Android Keystore should be used instead.\n",
      "classification": "very promising",
      "cwe": "CWE-312",
      "function_names": [
        "getKeyStore1",
        "setKeyStore1",
        "getKeyStore2"
      ],
      "filenames": [
        "app/src/main/java/com/mayank/rucky/utils/Config.java"
      ]
    },
    {
      "headline": "Insecure use of cryptography with ECB mode",
      "analysis": "The application uses ECB mode for encryption, which is insecure as it does not provide semantic security. ECB mode can leak information about plaintext patterns. A more secure mode like CBC or GCM should be used instead.\n",
      "classification": "very promising",
      "cwe": "CWE-327",
      "function_names": [
        "security"
      ],
      "filenames": [
        "app/src/main/java/com/mayank/rucky/fragment/SettingsFragment.java"
      ]
    },
    {
      "headline": "Potential command injection in HID command execution",
      "analysis": "The application builds and executes shell commands to emulate HID devices based on user input. If this input is not properly sanitized, it could allow command injection. An attacker could potentially execute arbitrary commands on the device by crafting malicious HID scripts.\n",
      "classification": "slightly promising",
      "cwe": "CWE-78",
      "function_names": [
        "launchAttack",
        "fetchCommands"
      ],
      "filenames": [
        "app/src/main/java/com/mayank/rucky/activity/EditorActivity.java"
      ]
    },
    {
      "headline": "Insecure random number generation",
      "analysis": "The application uses java.util.Random seeded with the current time for generating random values. This is not cryptographically secure and could be predicted. For security-sensitive random number generation, a cryptographically secure random number generator should be used instead.\n",
      "classification": "slightly promising",
      "cwe": "CWE-330",
      "function_names": [
        "randomTheme"
      ],
      "filenames": [
        "app/src/main/java/com/mayank/rucky/utils/Randoms.java"
      ]
    }
  ],
  "scores": [
    {
      "stats": {
        "fn": 0,
        "tp": 1,
        "fp": 2
      },
      "mapping": {
        "2": "CVE-2021-41096"
      },
      "vuln_dates": {
        "CVE-2021-41096": "2021-09-27T20:15:07"
      },
      "scoring_model": "claude-3-5-sonnet-20240620",
      "type": "llm",
      "instruction_template_hash": "245ace12b6361954d0a2"
    }
  ],
  "instruction_template_hash": "10c0163db4740318a544",
  "version": "0.1.0"
}
