{
  "commit": "0ffb41e599c4828b710ed95e96bb85a883fc28ad",
  "repo_url": "https://github.com/jenkinsci/sounds-plugin",
  "model": "gpt-4o-2024-05-13",
  "chunk_hashes": [
    "737bac6e8ec14c66be7e"
  ],
  "responses": [
    {
      "content": "```yaml\nleads:\n  - headline: \"Improper use of 'HttpURLConnection' without any SSL/TLS certificate validation\"\n    analysis: |\n      In the `HudsonSoundsNotifier.java` file, the `doCheckSoundArchive` method validates HTTP URLs for `soundArchive` by simply opening a connection using `url.openConnection()`. However, there is no SSL/TLS certificate validation in the code, which can potentially allow for man-in-the-middle (MITM) attacks where an attacker could impersonate the source URL. This can lead to unauthorized access or manipulation of information transmitted between the server and the client.\n    cwe: CWE-295\n    function_names:\n      - doCheckSoundArchive\n    filenames:\n      - src/main/java/net/hurstfrost/hudson/sounds/HudsonSoundsNotifier.java\n    classification: very promising\n\n  - headline: \"Potential open redirect in doTestUrl method\"\n    analysis: |\n      The `doTestUrl` method in 'SoundsAgentAction.java' takes a user-provided URL and attempts to fetch and play the sound directly from it. There is no validation to ensure that the URL is pointing to a safe domain. This can lead to possible open redirect attacks where an attacker could trick users into visiting malicious websites by manipulating the URL parameter.\n    cwe: CWE-601\n    function_names:\n      - doTestUrl\n    filenames:\n      - src/main/java/net/hurstfrost/hudson/sounds/SoundsAgentAction.java\n    classification: slightly promising\n\n  - headline: \"Potential Path Traversal in rebuildSoundsIndex method\"\n    analysis: |\n      The `rebuildSoundsIndex` method in 'HudsonSoundsNotifier.java' takes a path provided by the user to rebuild the sounds index by iterating through a ZIP file. This method does not perform sufficient validation on the user-provided path, which might allow an attacker to use path traversal sequences to access or overwrite critical system files.\n    cwe: CWE-22\n    function_names:\n      - rebuildSoundsIndex\n    filenames:\n      - src/main/java/net/hurstfrost/hudson/sounds/HudsonSoundsNotifier.java\n    classification: very promising\n\n  - headline: \"Command Injection Vulnerability in playSoundBite method\"\n    analysis: |\n      The `playSoundBite` method in 'HudsonSoundsNotifier.java' uses `Runtime.getRuntime().exec(systemCommand)` to execute system commands. If the `systemCommand` includes user-controlled input without proper sanitization, it might allow for command injection attacks where an attacker can execute arbitrary system commands on the server hosting the application.\n    cwe: CWE-78\n    function_names:\n      - playSoundBite\n    filenames:\n      - src/main/java/net/hurstfrost/hudson/sounds/HudsonSoundsNotifier.java\n    classification: very promising\n\n  - headline: \"Resource exhaustion in playSoundBite method due to lack of proper timeouts\"\n    analysis: |\n      The `playSoundBite` method in 'HudsonSoundsNotifier.java' creates a new process and writes audio data to it. The `ProcessKiller` thread is supposed to kill the process after a specific timeout but does not necessarily ensure the proper cleanup of resources. This might lead to resource exhaustion if multiple audio streams are played simultaneously, eventually leading to service degradation or outage.\n    cwe: CWE-400\n    function_names:\n      - playSoundBite\n    filenames:\n      - src/main/java/net/hurstfrost/hudson/sounds/HudsonSoundsNotifier.java\n    classification: slightly promising\n\n  - headline: \"Missing or insufficient error messages sanitization\"\n    analysis: |\n      Multiple instances in the codebase, such as in the `playSound` and `doCheckSoundArchive` methods, print exception messages directly to the application logs or display them to the users without proper sanitization. If these messages include sensitive information or stack traces, it can lead to information disclosure vulnerabilities.\n    cwe: CWE-209\n    function_names:\n      - playSound\n      - doCheckSoundArchive\n    filenames:\n      - src/main/java/net/hurstfrost/hudson/sounds/HudsonSoundsNotifier.java\n    classification: slightly promising\n\n  - headline: \"Lack of proper exception handling in JSONHttpResponse class\"\n    analysis: |\n      The `JSONHttpResponse` class does not handle IOExceptions properly within the `generateResponse` method. If an error occurs while writing to the response stream, it may lead to inconsistent or partially written JSON data, which can be used by attackers to bypass security mechanisms that rely on well-formed JSON responses.\n    cwe: CWE-755\n    function_names:\n      - generateResponse\n    filenames:\n      - src/main/java/net/hurstfrost/hudson/sounds/JSONHttpResponse.java\n    classification: not promising\n```",
      "date": "2024-06-12T19:17:52.697323",
      "usage": {
        "prompt_tokens": 19896,
        "completion_tokens": 1011,
        "cost": 0.114645
      }
    }
  ],
  "leads": [
    {
      "headline": "Improper use of 'HttpURLConnection' without any SSL/TLS certificate validation",
      "analysis": "In the HudsonSoundsNotifier.java file, the doCheckSoundArchive method validates HTTP URLs for soundArchive by simply opening a connection using url.openConnection(). However, there is no SSL/TLS certificate validation in the code, which can potentially allow for man-in-the-middle (MITM) attacks where an attacker could impersonate the source URL. This can lead to unauthorized access or manipulation of information transmitted between the server and the client.\n",
      "classification": "very promising",
      "cwe": "CWE-295",
      "function_names": [
        "doCheckSoundArchive"
      ],
      "filenames": [
        "src/main/java/net/hurstfrost/hudson/sounds/HudsonSoundsNotifier.java"
      ]
    },
    {
      "headline": "Potential open redirect in doTestUrl method",
      "analysis": "The doTestUrl method in 'SoundsAgentAction.java' takes a user-provided URL and attempts to fetch and play the sound directly from it. There is no validation to ensure that the URL is pointing to a safe domain. This can lead to possible open redirect attacks where an attacker could trick users into visiting malicious websites by manipulating the URL parameter.\n",
      "classification": "slightly promising",
      "cwe": "CWE-601",
      "function_names": [
        "doTestUrl"
      ],
      "filenames": [
        "src/main/java/net/hurstfrost/hudson/sounds/SoundsAgentAction.java"
      ]
    },
    {
      "headline": "Potential Path Traversal in rebuildSoundsIndex method",
      "analysis": "The rebuildSoundsIndex method in 'HudsonSoundsNotifier.java' takes a path provided by the user to rebuild the sounds index by iterating through a ZIP file. This method does not perform sufficient validation on the user-provided path, which might allow an attacker to use path traversal sequences to access or overwrite critical system files.\n",
      "classification": "very promising",
      "cwe": "CWE-22",
      "function_names": [
        "rebuildSoundsIndex"
      ],
      "filenames": [
        "src/main/java/net/hurstfrost/hudson/sounds/HudsonSoundsNotifier.java"
      ]
    },
    {
      "headline": "Command Injection Vulnerability in playSoundBite method",
      "analysis": "The playSoundBite method in 'HudsonSoundsNotifier.java' uses Runtime.getRuntime().exec(systemCommand) to execute system commands. If the systemCommand includes user-controlled input without proper sanitization, it might allow for command injection attacks where an attacker can execute arbitrary system commands on the server hosting the application.\n",
      "classification": "very promising",
      "cwe": "CWE-78",
      "function_names": [
        "playSoundBite"
      ],
      "filenames": [
        "src/main/java/net/hurstfrost/hudson/sounds/HudsonSoundsNotifier.java"
      ]
    },
    {
      "headline": "Resource exhaustion in playSoundBite method due to lack of proper timeouts",
      "analysis": "The playSoundBite method in 'HudsonSoundsNotifier.java' creates a new process and writes audio data to it. The ProcessKiller thread is supposed to kill the process after a specific timeout but does not necessarily ensure the proper cleanup of resources. This might lead to resource exhaustion if multiple audio streams are played simultaneously, eventually leading to service degradation or outage.\n",
      "classification": "slightly promising",
      "cwe": "CWE-400",
      "function_names": [
        "playSoundBite"
      ],
      "filenames": [
        "src/main/java/net/hurstfrost/hudson/sounds/HudsonSoundsNotifier.java"
      ]
    },
    {
      "headline": "Missing or insufficient error messages sanitization",
      "analysis": "Multiple instances in the codebase, such as in the playSound and doCheckSoundArchive methods, print exception messages directly to the application logs or display them to the users without proper sanitization. If these messages include sensitive information or stack traces, it can lead to information disclosure vulnerabilities.\n",
      "classification": "slightly promising",
      "cwe": "CWE-209",
      "function_names": [
        "playSound",
        "doCheckSoundArchive"
      ],
      "filenames": [
        "src/main/java/net/hurstfrost/hudson/sounds/HudsonSoundsNotifier.java"
      ]
    },
    {
      "headline": "Lack of proper exception handling in JSONHttpResponse class",
      "analysis": "The JSONHttpResponse class does not handle IOExceptions properly within the generateResponse method. If an error occurs while writing to the response stream, it may lead to inconsistent or partially written JSON data, which can be used by attackers to bypass security mechanisms that rely on well-formed JSON responses.\n",
      "classification": "not promising",
      "cwe": "CWE-755",
      "function_names": [
        "generateResponse"
      ],
      "filenames": [
        "src/main/java/net/hurstfrost/hudson/sounds/JSONHttpResponse.java"
      ]
    }
  ],
  "scores": [
    {
      "stats": {
        "fn": 1,
        "tp": 1,
        "fp": 2
      },
      "mapping": {
        "2": "CVE-2020-2097"
      },
      "vuln_dates": {
        "CVE-2020-2098": "2020-01-15T16:15:15",
        "CVE-2020-2097": "2020-01-15T16:15:14"
      },
      "scoring_model": "claude-3-opus-20240229",
      "type": "llm",
      "instruction_template_hash": "245ace12b6361954d0a2"
    },
    {
      "stats": {
        "fn": 1,
        "tp": 1,
        "fp": 2
      },
      "mapping": {
        "2": "CVE-2020-2097"
      },
      "vuln_dates": {
        "CVE-2020-2098": "2020-01-15T16:15:15",
        "CVE-2020-2097": "2020-01-15T16:15:14"
      },
      "scoring_model": "claude-3-5-sonnet-20240620",
      "type": "llm",
      "instruction_template_hash": "245ace12b6361954d0a2"
    }
  ],
  "instruction_template_hash": "10c0163db4740318a544",
  "version": "0.1.0"
}
