{
  "commit": "9cc050cc97984d89cfc0423e430a87d8d11a43ee",
  "repo_url": "https://github.com/inc2734/smart-custom-fields",
  "model": "gpt-4-turbo-2024-04-09",
  "chunk_hashes": [
    "d9807f8a2c4dea514e46"
  ],
  "responses": [
    {
      "content": "```yaml\nleads:\n  - headline: \"Improper Neutralization of Input\"\n    analysis: |\n      The codebase contains multiple instances where user inputs are directly utilized without proper validation and sanitization, leading to risks of cross-side scripting and command injection attacks. For example, the file handling in 'js/editor.js' and the command geneation based on user input in 'js/settings-colorpicker.js' are susceptible to manipulations that could execute unintended commands or scripts.\n    cwe: CWE-79\n    function_names: \n      - add_repeat_group\n      - add_color_picker\n    filenames: \n      - js/editor.js\n      - js/settings-colorpicker.js\n    classification: \"very promising\"\n\n  - headline: \"SQL Injection through Dynamic Query Construction\"\n    analysis: |\n      The code constructs SQL queries directly using concatenation of strings sourced from input data in 'js/editor-relation-post-types.js'. This usage pattern is likely vulnerable to SQL Injection attacks in which malicious SQL code could be inserted into the dynamically constructed queries.\n    cwe: CWE-89\n    function_names:\n      - get_posts\n    filenames:\n      - js/editor-relation-post-types.js\n    classification: \"very promising\"\n\n  - headline: \"Uncontrolled File Upload allowing Arbitrary File Execution\"\n    analysis: |\n      In 'js/editor.js', there is a function that handles file uploads. The lack of content type checks and file validation on these uploads can lead to the uploading of undesirable file types, potentially leading to remote code execution if executable files are uploaded and subsequently executed by the server.\n    cwe: CWE-434\n    function_names:\n      - btn-add-file_click\n    filenames:\n      - js/editor.js\n    classification: \"slightly promising\"\n\n  - headline: \"Vulnerable External XML Entity Processing\"\n    analysis: |\n      The platform allows for processing XML uploads without restrictions or security checks as observed in multiple files like 'js/settings.js'. This might allow an attacker to include hostile XML external entities leading to typical XXE attacks including data exfiltration.\n    cwe: CWE-611\n    function_names: \n      - create_new_setting_field\n    filenames:\n      - js/settings.js\n    classification: \"very promising\"\n\n  - headline: \"Unrestricted Creation of Global Settings\"\n    analysis: |\n      A function in 'js/settings.js' allows creating settings without appropriate restrictions or validation, potentially allowing an attacker to create harmful configurations that could impact system behavior or security.\n    cwe: CWE-284\n    function_names:\n      - addNewGlobalSetting\n    filenames:\n      - js/settings.js\n    classification: \"slightly promising\"\n\n  - headline: \"Path Traversal via Improper Sanitization\"\n    analysis: |\n      The code in 'js/editor-wysiwyg.js' does not adequately sanitize file paths used in file operations, allowing for path traversal attacks where a malicious user could access or modify files outside of the restricted directories.\n    cwe: CWE-22\n    function_names:\n      - init_wysiwyg_editor\n    filenames:\n      - js/editor-wysiwyg.js\n    classification: \"very promising\"\n```",
      "date": "2024-06-09T12:36:11.686576",
      "usage": {
        "prompt_tokens": 52783,
        "completion_tokens": 648,
        "cost": 0.54727
      }
    }
  ],
  "leads": [
    {
      "headline": "Improper Neutralization of Input",
      "analysis": "The codebase contains multiple instances where user inputs are directly utilized without proper validation and sanitization, leading to risks of cross-side scripting and command injection attacks. For example, the file handling in 'js/editor.js' and the command geneation based on user input in 'js/settings-colorpicker.js' are susceptible to manipulations that could execute unintended commands or scripts.\n",
      "classification": "very promising",
      "cwe": "CWE-79",
      "function_names": [
        "add_repeat_group",
        "add_color_picker"
      ],
      "filenames": [
        "js/editor.js",
        "js/settings-colorpicker.js"
      ]
    },
    {
      "headline": "SQL Injection through Dynamic Query Construction",
      "analysis": "The code constructs SQL queries directly using concatenation of strings sourced from input data in 'js/editor-relation-post-types.js'. This usage pattern is likely vulnerable to SQL Injection attacks in which malicious SQL code could be inserted into the dynamically constructed queries.\n",
      "classification": "very promising",
      "cwe": "CWE-89",
      "function_names": [
        "get_posts"
      ],
      "filenames": [
        "js/editor-relation-post-types.js"
      ]
    },
    {
      "headline": "Uncontrolled File Upload allowing Arbitrary File Execution",
      "analysis": "In 'js/editor.js', there is a function that handles file uploads. The lack of content type checks and file validation on these uploads can lead to the uploading of undesirable file types, potentially leading to remote code execution if executable files are uploaded and subsequently executed by the server.\n",
      "classification": "slightly promising",
      "cwe": "CWE-434",
      "function_names": [
        "btn-add-file_click"
      ],
      "filenames": [
        "js/editor.js"
      ]
    },
    {
      "headline": "Vulnerable External XML Entity Processing",
      "analysis": "The platform allows for processing XML uploads without restrictions or security checks as observed in multiple files like 'js/settings.js'. This might allow an attacker to include hostile XML external entities leading to typical XXE attacks including data exfiltration.\n",
      "classification": "very promising",
      "cwe": "CWE-611",
      "function_names": [
        "create_new_setting_field"
      ],
      "filenames": [
        "js/settings.js"
      ]
    },
    {
      "headline": "Unrestricted Creation of Global Settings",
      "analysis": "A function in 'js/settings.js' allows creating settings without appropriate restrictions or validation, potentially allowing an attacker to create harmful configurations that could impact system behavior or security.\n",
      "classification": "slightly promising",
      "cwe": "CWE-284",
      "function_names": [
        "addNewGlobalSetting"
      ],
      "filenames": [
        "js/settings.js"
      ]
    },
    {
      "headline": "Path Traversal via Improper Sanitization",
      "analysis": "The code in 'js/editor-wysiwyg.js' does not adequately sanitize file paths used in file operations, allowing for path traversal attacks where a malicious user could access or modify files outside of the restricted directories.\n",
      "classification": "very promising",
      "cwe": "CWE-22",
      "function_names": [
        "init_wysiwyg_editor"
      ],
      "filenames": [
        "js/editor-wysiwyg.js"
      ]
    }
  ],
  "scores": [
    {
      "stats": {
        "fn": 1,
        "tp": 0,
        "fp": 4
      },
      "mapping": {},
      "vuln_dates": {
        "CVE-2024-1995": "2024-03-20T02:15:08"
      },
      "scoring_model": "gpt-4o-2024-05-13",
      "type": "llm",
      "instruction_template_hash": "8998f09cf57fca8a6e03"
    },
    {
      "stats": {
        "fn": 1,
        "tp": 0,
        "fp": 4
      },
      "mapping": {},
      "vuln_dates": {
        "CVE-2024-1995": "2024-03-20T02:15:08"
      },
      "scoring_model": "claude-3-opus-20240229",
      "type": "llm",
      "instruction_template_hash": "245ace12b6361954d0a2"
    }
  ],
  "instruction_template_hash": "10c0163db4740318a544",
  "version": "0.1.0"
}
