{
  "commit": "26050da0029ac0c62e23d76a8e8eef5d26fdf7af",
  "repo_url": "https://github.com/cloudavid/pparam",
  "model": "gpt-4-turbo-2024-04-09",
  "chunk_hashes": [
    "9f274787357d8f4efd13"
  ],
  "responses": [
    {
      "content": "```yaml\nleads:\n  - headline: \"Improper Exception Handling Allowing Termination of Service\"\n    analysis: |\n      The function 'xdel' in 'xlist.hpp' attempts to manage list nodes without proper checks for null pointers, potentially leading to dereferencing of null pointers. This can cause the application to crash, leading to a denial of service. The problem arises because the function assumes the 'iter' iterator points to a valid object, which may not always be the case in concurrent or erroneous conditions.\n    cwe: CWE-755\n    function_names:\n      - del\n      - xdel\n    filenames:\n      - src/xlist.hpp\n    classification: slightly promising\n  - headline: \"Weak Cryptographic Hash Used for Password Storage\"\n    analysis: |\n      The 'CryptoParam::encrypt_md2()' function within 'src/sparam.cpp' utilizes the MD5 hashing algorithm, which is considered cryptographically weak and vulnerable to collision attacks. This vulnerability could allow an attacker to generate the same hash with different passwords, leading to potential security breaches such as unauthorized access if password hashes are exposed.\n    cwe: CWE-327\n    function_names:\n      - encrypt_md5\n    filenames:\n      - src/sparam.cpp\n    classification: very promising\n  - headline: \"SQL Injection via Direct User Input in DB Query\"\n    analysis: |\n      In the 'SQLiteDBEngine::removeXParam' function in 'src/xdbengine.cpp', user input is directly included in SQL queries without proper sanitization or parameterization. This practice can allow an attacker to manipulate SQL queries by injecting arbitrary SQL code, leading to unauthorized database manipulation or data disclosure.\n    cwe: CWE-89\n    function_names:\n      - removeXParam\n    filenames:\n      - src/xdbengine.cpp\n    classification: very promising\n  - headline: \"Buffer Overflow Potential in Exception Handling\"\n    analysis: |\n      The function 'Exception::what()' in the 'Exception' class ('src/exception.cpp') constructs error messages using string concatenation without bounds checking. This could lead to buffer overflows if exceptionally long error messages are constructed, potentially allowing an attacker to execute arbitrary code.\n    cwe: CWE-120\n    function_names:\n      - what\n    filenames:\n      - src/exception.cpp\n    classification: slightly promising\n  - headline: \"Use of Uninitialized Memory in DateParam Constructor\"\n    analysis: |\n      In the 'DateParam' class constructor within 'src/sparam.cpp', member variables 'year', 'month', and 'day' are used before being initialized. This leads to indeterminate behavior and might cause the program to operate on garbage values, affecting the logic of date manipulations and comparisons.\n    cwe: CWE-908\n    function_names:\n      - DateParam\n    filenames:\n      - src/sparam.cpp\n    classification: not promising\n```",
      "date": "2024-06-12T15:38:48.337881",
      "usage": {
        "prompt_tokens": 77961,
        "completion_tokens": 595,
        "cost": 0.79746
      }
    }
  ],
  "leads": [
    {
      "headline": "Improper Exception Handling Allowing Termination of Service",
      "analysis": "The function 'xdel' in 'xlist.hpp' attempts to manage list nodes without proper checks for null pointers, potentially leading to dereferencing of null pointers. This can cause the application to crash, leading to a denial of service. The problem arises because the function assumes the 'iter' iterator points to a valid object, which may not always be the case in concurrent or erroneous conditions.\n",
      "classification": "slightly promising",
      "cwe": "CWE-755",
      "function_names": [
        "del",
        "xdel"
      ],
      "filenames": [
        "src/xlist.hpp"
      ]
    },
    {
      "headline": "Weak Cryptographic Hash Used for Password Storage",
      "analysis": "The 'CryptoParam::encrypt_md2()' function within 'src/sparam.cpp' utilizes the MD5 hashing algorithm, which is considered cryptographically weak and vulnerable to collision attacks. This vulnerability could allow an attacker to generate the same hash with different passwords, leading to potential security breaches such as unauthorized access if password hashes are exposed.\n",
      "classification": "very promising",
      "cwe": "CWE-327",
      "function_names": [
        "encrypt_md5"
      ],
      "filenames": [
        "src/sparam.cpp"
      ]
    },
    {
      "headline": "SQL Injection via Direct User Input in DB Query",
      "analysis": "In the 'SQLiteDBEngine::removeXParam' function in 'src/xdbengine.cpp', user input is directly included in SQL queries without proper sanitization or parameterization. This practice can allow an attacker to manipulate SQL queries by injecting arbitrary SQL code, leading to unauthorized database manipulation or data disclosure.\n",
      "classification": "very promising",
      "cwe": "CWE-89",
      "function_names": [
        "removeXParam"
      ],
      "filenames": [
        "src/xdbengine.cpp"
      ]
    },
    {
      "headline": "Buffer Overflow Potential in Exception Handling",
      "analysis": "The function 'Exception::what()' in the 'Exception' class ('src/exception.cpp') constructs error messages using string concatenation without bounds checking. This could lead to buffer overflows if exceptionally long error messages are constructed, potentially allowing an attacker to execute arbitrary code.\n",
      "classification": "slightly promising",
      "cwe": "CWE-120",
      "function_names": [
        "what"
      ],
      "filenames": [
        "src/exception.cpp"
      ]
    },
    {
      "headline": "Use of Uninitialized Memory in DateParam Constructor",
      "analysis": "In the 'DateParam' class constructor within 'src/sparam.cpp', member variables 'year', 'month', and 'day' are used before being initialized. This leads to indeterminate behavior and might cause the program to operate on garbage values, affecting the logic of date manipulations and comparisons.\n",
      "classification": "not promising",
      "cwe": "CWE-908",
      "function_names": [
        "DateParam"
      ],
      "filenames": [
        "src/sparam.cpp"
      ]
    }
  ],
  "scores": [
    {
      "stats": {
        "fn": 1,
        "tp": 0,
        "fp": 2
      },
      "mapping": {},
      "vuln_dates": {
        "CVE-2020-28723": "2020-11-16T17:15:13"
      },
      "scoring_model": "claude-3-opus-20240229",
      "type": "llm",
      "instruction_template_hash": "245ace12b6361954d0a2"
    }
  ],
  "instruction_template_hash": "10c0163db4740318a544",
  "version": "0.1.0"
}
