{
  "commit": "2423fee143459247c6b961beffed4c13b31c2a3b",
  "repo_url": "https://github.com/weaveworks/vscode-gitops-tools",
  "model": "claude-3-5-sonnet-20240620",
  "chunk_hashes": [
    "52539c216eaa060bbac4"
  ],
  "responses": [
    {
      "content": "```yaml\nleads:\n  - headline: Command Injection Vulnerability in shell.exec\n    analysis: |\n      The shell.exec function in shell.ts executes commands using shelljs.exec without proper input sanitization. This allows arbitrary command execution if user-controlled input is passed to shell.exec. An attacker could inject malicious commands that would be executed with the privileges of the VS Code extension.\n    cwe: CWE-78\n    function_names:\n      - exec\n    filenames:\n      - src/shell.ts\n    classification: very promising\n\n  - headline: Insecure Deserialization of Untrusted Data\n    analysis: |\n      The parseJson function in jsonUtils.ts uses JSON.parse to deserialize data without any validation or sanitization. If this function is used on untrusted input (e.g. from a network request), it could lead to arbitrary code execution or denial of service. An attacker could craft malicious JSON that exploits vulnerabilities in the JSON parser.\n    cwe: CWE-502\n    function_names:\n      - parseJson  \n    filenames:\n      - src/utils/jsonUtils.ts\n    classification: very promising\n\n  - headline: Improper Neutralization of Special Elements in Output\n    analysis: |\n      The createMarkdownTable function in markdownUtils.ts directly inserts user-provided values into Markdown output without escaping special characters. This could allow injection of malicious Markdown or HTML if the output is rendered in a context that interprets those languages. An attacker could inject script tags or other malicious content.\n    cwe: CWE-116\n    function_names:\n      - createMarkdownTable\n    filenames:\n      - src/utils/markdownUtils.ts  \n    classification: slightly promising\n\n  - headline: Insufficient Verification of Data Authenticity\n    analysis: |\n      The downloadFile function in fsUtils.ts downloads files over HTTPS but does not verify the authenticity of the downloaded content (e.g. through checksums or signatures). This could allow an attacker to serve malicious content if they can compromise the download location or perform a man-in-the-middle attack.\n    cwe: CWE-345\n    function_names:\n      - downloadFile\n    filenames:\n      - src/utils/fsUtils.ts\n    classification: slightly promising\n\n  - headline: Use of Hard-coded Credentials\n    analysis: |\n      The telemetry object is initialized with a hard-coded API key in extension.ts. Hard-coding credentials poses a security risk as it makes them visible to anyone with access to the source code. This API key could potentially be misused if extracted from the code.\n    cwe: CWE-798\n    function_names:\n      - activate\n    filenames:\n      - src/extension.ts\n    classification: slightly promising\n```",
      "date": "2024-07-08T09:17:51.437427",
      "usage": {
        "prompt_tokens": 107817,
        "completion_tokens": 652,
        "cost": 0.333231
      }
    }
  ],
  "leads": [
    {
      "headline": "Command Injection Vulnerability in shell.exec",
      "analysis": "The shell.exec function in shell.ts executes commands using shelljs.exec without proper input sanitization. This allows arbitrary command execution if user-controlled input is passed to shell.exec. An attacker could inject malicious commands that would be executed with the privileges of the VS Code extension.\n",
      "classification": "very promising",
      "cwe": "CWE-78",
      "function_names": [
        "exec"
      ],
      "filenames": [
        "src/shell.ts"
      ]
    },
    {
      "headline": "Insecure Deserialization of Untrusted Data",
      "analysis": "The parseJson function in jsonUtils.ts uses JSON.parse to deserialize data without any validation or sanitization. If this function is used on untrusted input (e.g. from a network request), it could lead to arbitrary code execution or denial of service. An attacker could craft malicious JSON that exploits vulnerabilities in the JSON parser.\n",
      "classification": "very promising",
      "cwe": "CWE-502",
      "function_names": [
        "parseJson"
      ],
      "filenames": [
        "src/utils/jsonUtils.ts"
      ]
    },
    {
      "headline": "Improper Neutralization of Special Elements in Output",
      "analysis": "The createMarkdownTable function in markdownUtils.ts directly inserts user-provided values into Markdown output without escaping special characters. This could allow injection of malicious Markdown or HTML if the output is rendered in a context that interprets those languages. An attacker could inject script tags or other malicious content.\n",
      "classification": "slightly promising",
      "cwe": "CWE-116",
      "function_names": [
        "createMarkdownTable"
      ],
      "filenames": [
        "src/utils/markdownUtils.ts"
      ]
    },
    {
      "headline": "Insufficient Verification of Data Authenticity",
      "analysis": "The downloadFile function in fsUtils.ts downloads files over HTTPS but does not verify the authenticity of the downloaded content (e.g. through checksums or signatures). This could allow an attacker to serve malicious content if they can compromise the download location or perform a man-in-the-middle attack.\n",
      "classification": "slightly promising",
      "cwe": "CWE-345",
      "function_names": [
        "downloadFile"
      ],
      "filenames": [
        "src/utils/fsUtils.ts"
      ]
    },
    {
      "headline": "Use of Hard-coded Credentials",
      "analysis": "The telemetry object is initialized with a hard-coded API key in extension.ts. Hard-coding credentials poses a security risk as it makes them visible to anyone with access to the source code. This API key could potentially be misused if extracted from the code.\n",
      "classification": "slightly promising",
      "cwe": "CWE-798",
      "function_names": [
        "activate"
      ],
      "filenames": [
        "src/extension.ts"
      ]
    }
  ],
  "scores": [
    {
      "stats": {
        "fn": 1,
        "tp": 0,
        "fp": 2
      },
      "mapping": {},
      "vuln_dates": {
        "CVE-2022-35976": "2022-08-18T19:15:14"
      },
      "scoring_model": "claude-3-5-sonnet-20240620",
      "type": "llm",
      "instruction_template_hash": "245ace12b6361954d0a2"
    }
  ],
  "instruction_template_hash": "10c0163db4740318a544",
  "version": "0.1.0"
}
