{
  "commit": "0d6592f5db6c86c11cf95799893cb0de81dc6636",
  "repo_url": "https://github.com/jenkinsci/contrast-continuous-application-security-plugin",
  "model": "claude-3-haiku-20240307",
  "chunk_hashes": [
    "9bd18b3af0e852466c25"
  ],
  "responses": [
    {
      "content": "Here is the YAML object equivalent to type LeadList, according to the provided Pydantic definitions:\n\n```yaml\nleads:\n  - headline: Improper Validation of Specified Quantity in Input\n    analysis: |\n      The code may be vulnerable to CWE-1284 Improper Validation of Specified Quantity in Input. This could occur if user input is not properly validated before being used in a security-critical context, such as in the number of resources allocated or in the size of a buffer. Exploitation could allow an attacker to trigger resource exhaustion or buffer overflow vulnerabilities.\n    cwe: CWE-1284\n    function_names:\n      - allocateResources\n      - processInput\n    filenames:\n      - src/main/java/com/aspectsecurity/contrast/contrastjenkins/VulnerabilityTrendRecorder.java\n      - src/main/java/com/aspectsecurity/contrast/contrastjenkins/VulnerabilityTrendStep.java\n    classification: slightly promising\n  - headline: Improper Validation of Array Index\n    analysis: |\n      The code may be vulnerable to CWE-129 Improper Validation of Array Index. This could occur if user input is used to index into an array without proper validation, potentially leading to out-of-bounds read or write vulnerabilities. Exploitation could allow an attacker to access or modify sensitive data.\n    cwe: CWE-129\n    function_names:\n      - processTraces\n      - buildFilterForm\n    filenames:\n      - src/main/java/com/aspectsecurity/contrast/contrastjenkins/VulnerabilityTrendRecorder.java\n      - src/main/java/com/aspectsecurity/contrast/contrastjenkins/VulnerabilityTrendStep.java\n    classification: slightly promising\n  - headline: Improper Neutralization of Special Elements in Output Used by a Downstream Component ('Injection')\n    analysis: |\n      The code may be vulnerable to CWE-74 Improper Neutralization of Special Elements in Output Used by a Downstream Component ('Injection'). This could occur if user input is used in a security-critical context, such as in a SQL query or operating system command, without proper sanitization. Exploitation could allow an attacker to inject malicious content and gain unauthorized access or execute arbitrary commands.\n    cwe: CWE-74\n    function_names:\n      - buildFilterForm\n      - makeFilterFormWithQueryBy\n    filenames:\n      - src/main/java/com/aspectsecurity/contrast/contrastjenkins/VulnerabilityTrendRecorder.java\n      - src/main/java/com/aspectsecurity/contrast/contrastjenkins/VulnerabilityTrendStep.java\n    classification: very promising\n  - headline: Improper Encoding or Escaping of Output\n    analysis: |\n      The code may be vulnerable to CWE-116 Improper Encoding or Escaping of Output. This could occur if user input is not properly encoded or escaped before being used in a security-critical context, such as in HTML output or in a SQL query. Exploitation could allow an attacker to inject malicious content and gain unauthorized access or execute arbitrary commands.\n    cwe: CWE-116\n    function_names:\n      - buildFilterForm\n      - makeFilterFormWithQueryBy\n    filenames:\n      - src/main/java/com/aspectsecurity/contrast/contrastjenkins/VulnerabilityTrendRecorder.java\n      - src/main/java/com/aspectsecurity/contrast/contrastjenkins/VulnerabilityTrendStep.java\n    classification: very promising\n  - headline: Improper Restriction of Operations within the Bounds of a Memory Buffer\n    analysis: |\n      The code may be vulnerable to CWE-119 Improper Restriction of Operations within the Bounds of a Memory Buffer. This could occur if user input is used in a way that could lead to buffer overflow vulnerabilities, such as in memory allocation or copying. Exploitation could allow an attacker to execute arbitrary code or trigger other security issues.\n    cwe: CWE-119\n    function_names:\n      - buildFilterForm\n      - makeFilterFormWithQueryBy\n    filenames:\n      - src/main/java/com/aspectsecurity/contrast/contrastjenkins/VulnerabilityTrendRecorder.java\n      - src/main/java/com/aspectsecurity/contrast/contrastjenkins/VulnerabilityTrendStep.java\n    classification: slightly promising\n  - headline: Improper Handling of Exceptional Conditions\n    analysis: |\n      The code may be vulnerable to CWE-755 Improper Handling of Exceptional Conditions. This could occur if the application does not properly handle and respond to unexpected or error conditions, potentially leading to security issues such as information disclosure or denial of service. Exploitation could allow an attacker to bypass security controls or cause the application to behave in an unintended way.\n    cwe: CWE-755\n    function_names:\n      - perform\n      - run\n    filenames:\n      - src/main/java/com/aspectsecurity/contrast/contrastjenkins/VulnerabilityTrendRecorder.java\n      - src/main/java/com/aspectsecurity/contrast/contrastjenkins/VulnerabilityTrendStep.java\n    classification: slightly promising\n```",
      "date": "2024-06-12T18:10:11.953970",
      "usage": {
        "prompt_tokens": 58988,
        "completion_tokens": 1276,
        "cost": 0.016342
      }
    }
  ],
  "leads": [
    {
      "headline": "Improper Validation of Specified Quantity in Input",
      "analysis": "The code may be vulnerable to CWE-1284 Improper Validation of Specified Quantity in Input. This could occur if user input is not properly validated before being used in a security-critical context, such as in the number of resources allocated or in the size of a buffer. Exploitation could allow an attacker to trigger resource exhaustion or buffer overflow vulnerabilities.\n",
      "classification": "slightly promising",
      "cwe": "CWE-1284",
      "function_names": [
        "allocateResources",
        "processInput"
      ],
      "filenames": [
        "src/main/java/com/aspectsecurity/contrast/contrastjenkins/VulnerabilityTrendRecorder.java",
        "src/main/java/com/aspectsecurity/contrast/contrastjenkins/VulnerabilityTrendStep.java"
      ]
    },
    {
      "headline": "Improper Validation of Array Index",
      "analysis": "The code may be vulnerable to CWE-129 Improper Validation of Array Index. This could occur if user input is used to index into an array without proper validation, potentially leading to out-of-bounds read or write vulnerabilities. Exploitation could allow an attacker to access or modify sensitive data.\n",
      "classification": "slightly promising",
      "cwe": "CWE-129",
      "function_names": [
        "processTraces",
        "buildFilterForm"
      ],
      "filenames": [
        "src/main/java/com/aspectsecurity/contrast/contrastjenkins/VulnerabilityTrendRecorder.java",
        "src/main/java/com/aspectsecurity/contrast/contrastjenkins/VulnerabilityTrendStep.java"
      ]
    },
    {
      "headline": "Improper Neutralization of Special Elements in Output Used by a Downstream Component ('Injection')",
      "analysis": "The code may be vulnerable to CWE-74 Improper Neutralization of Special Elements in Output Used by a Downstream Component ('Injection'). This could occur if user input is used in a security-critical context, such as in a SQL query or operating system command, without proper sanitization. Exploitation could allow an attacker to inject malicious content and gain unauthorized access or execute arbitrary commands.\n",
      "classification": "very promising",
      "cwe": "CWE-74",
      "function_names": [
        "buildFilterForm",
        "makeFilterFormWithQueryBy"
      ],
      "filenames": [
        "src/main/java/com/aspectsecurity/contrast/contrastjenkins/VulnerabilityTrendRecorder.java",
        "src/main/java/com/aspectsecurity/contrast/contrastjenkins/VulnerabilityTrendStep.java"
      ]
    },
    {
      "headline": "Improper Encoding or Escaping of Output",
      "analysis": "The code may be vulnerable to CWE-116 Improper Encoding or Escaping of Output. This could occur if user input is not properly encoded or escaped before being used in a security-critical context, such as in HTML output or in a SQL query. Exploitation could allow an attacker to inject malicious content and gain unauthorized access or execute arbitrary commands.\n",
      "classification": "very promising",
      "cwe": "CWE-116",
      "function_names": [
        "buildFilterForm",
        "makeFilterFormWithQueryBy"
      ],
      "filenames": [
        "src/main/java/com/aspectsecurity/contrast/contrastjenkins/VulnerabilityTrendRecorder.java",
        "src/main/java/com/aspectsecurity/contrast/contrastjenkins/VulnerabilityTrendStep.java"
      ]
    },
    {
      "headline": "Improper Restriction of Operations within the Bounds of a Memory Buffer",
      "analysis": "The code may be vulnerable to CWE-119 Improper Restriction of Operations within the Bounds of a Memory Buffer. This could occur if user input is used in a way that could lead to buffer overflow vulnerabilities, such as in memory allocation or copying. Exploitation could allow an attacker to execute arbitrary code or trigger other security issues.\n",
      "classification": "slightly promising",
      "cwe": "CWE-119",
      "function_names": [
        "buildFilterForm",
        "makeFilterFormWithQueryBy"
      ],
      "filenames": [
        "src/main/java/com/aspectsecurity/contrast/contrastjenkins/VulnerabilityTrendRecorder.java",
        "src/main/java/com/aspectsecurity/contrast/contrastjenkins/VulnerabilityTrendStep.java"
      ]
    },
    {
      "headline": "Improper Handling of Exceptional Conditions",
      "analysis": "The code may be vulnerable to CWE-755 Improper Handling of Exceptional Conditions. This could occur if the application does not properly handle and respond to unexpected or error conditions, potentially leading to security issues such as information disclosure or denial of service. Exploitation could allow an attacker to bypass security controls or cause the application to behave in an unintended way.\n",
      "classification": "slightly promising",
      "cwe": "CWE-755",
      "function_names": [
        "perform",
        "run"
      ],
      "filenames": [
        "src/main/java/com/aspectsecurity/contrast/contrastjenkins/VulnerabilityTrendRecorder.java",
        "src/main/java/com/aspectsecurity/contrast/contrastjenkins/VulnerabilityTrendStep.java"
      ]
    }
  ],
  "scores": [
    {
      "stats": {
        "fn": 1,
        "tp": 0,
        "fp": 2
      },
      "mapping": {},
      "vuln_dates": {
        "CVE-2022-43420": "2022-10-19T16:15:11"
      },
      "scoring_model": "claude-3-opus-20240229",
      "type": "llm",
      "instruction_template_hash": "245ace12b6361954d0a2"
    }
  ],
  "instruction_template_hash": "10c0163db4740318a544",
  "version": "0.1.0"
}
