{
  "commit": "3a0699d2a90544a0f8928c40947b119e9491c2fa",
  "repo_url": "https://github.com/senchalabs/connect",
  "model": "gpt-4o-2024-05-13",
  "chunk_hashes": [
    "1fe5273731f7746154fc"
  ],
  "responses": [
    {
      "content": "```yaml\nleads:\n  - headline: Environment variable-based module loading\n    analysis: |\n      The `index.js` file utilizes a JavaScript expression to conditionally load one of two modules based on an environment variable (`CONNECT_COV`). An attacker could potentially manipulate this environment variable to load a malicious module, especially if the environment variable is not properly sanitized or is exposed to untrusted input.\n    cwe: CWE-829\n    function_names: []\n    filenames:\n      - index.js\n    classification: very promising\n  - headline: Outdated jQuery 1.7.1 containing known vulnerabilities\n    analysis: |\n      The codebase includes jQuery version 1.7.1, which contains several known vulnerabilities, such as XSS and prototype pollution. These vulnerabilities can be exploited by attackers to perform attacks like DOM-based cross-site scripting (XSS).\n    cwe: CWE-79\n    function_names: []\n    filenames:\n      - docs/jquery.js\n    classification: very promising\n  - headline: Improper input validation in multipart form handling\n    analysis: |\n      In `multipart.js`, the code does not properly validate multipart form inputs. This can be exploited by attackers to perform various attacks, such as uploading malicious files or triggering unexpected behaviors in the server.\n    cwe: CWE-20\n    function_names:\n      - multipart\n    filenames:\n      - lib/middleware/multipart.js\n    classification: very promising\n  - headline: Hardcoded sensitive information in tests\n    analysis: |\n      The `test/compress.js` file and others contain hardcoded sensitive information such as secrets, thresholds, and API keys, which can be exposed through various unintended means. An attacker could use this information to compromise the security of the system.\n    cwe: CWE-798\n    function_names: \n      - app\n      - app2\n    filenames:\n      - test/compress.js\n      - test/limit.js\n      - test/session.js\n    classification: very promising\n  - headline: Potential for SQL injection due to usage of user-provided data without sanitization\n    analysis: |\n      The codebase has instances where user input is utilized in forming SQL queries without proper sanitization. This could enable SQL injection attacks, allowing attackers to read, modify, or delete sensitive information in the database.\n    cwe: CWE-89\n    function_names:\n      - query\n    filenames:\n      - lib/middleware/query.js\n    classification: very promising\n  - headline: Potential Denial of Service (DoS) due to server-side request forgery (SSRF)\n    analysis: |\n      The code might be vulnerable to SSRF, where attackers can send requests from the server to arbitrary locations, potentially accessing internal systems or causing denial of service (DoS).\n    cwe: CWE-918\n    function_names:\n      - handle\n    filenames:\n      - lib/proto.js\n    classification: very promising\n  - headline: Buffer overflow vulnerability in form data parsing\n    analysis: |\n      The `bodyParser.js` and `multipart.js` files do not have sufficient checks in place to prevent buffer overflow attacks when processing form data. Attackers could exploit these issues to execute arbitrary code on the server.\n    cwe: CWE-120\n    function_names:\n      - parse\n      - multipart\n    filenames:\n      - lib/middleware/bodyParser.js\n      - lib/middleware/multipart.js\n    classification: very promising\n  - headline: Directory traversal vulnerability in static file handling\n    analysis: |\n      The static file serving implementation in `static.js` does not properly validate file paths, making it susceptible to directory traversal attacks. Attackers could exploit this to read or write arbitrary files on the server.\n    cwe: CWE-22\n    function_names:\n      - static\n    filenames:\n      - lib/middleware/static.js\n    classification: very promising\n  - headline: Weak default configurations for session management\n    analysis: |\n      The default session management in `session.js` uses configurations that may not be secure, such as the default cookie settings. This could lead to session hijacking, fixation, or other attacks.\n    cwe: CWE-521\n    function_names:\n      - session\n      - handle\n    filenames:\n      - lib/middleware/session.js\n    classification: slightly promising\n```",
      "date": "2024-06-14T15:30:55.375051",
      "usage": {
        "prompt_tokens": 94406,
        "completion_tokens": 896,
        "cost": 0.48547
      }
    }
  ],
  "leads": [
    {
      "headline": "Environment variable-based module loading",
      "analysis": "The index.js file utilizes a JavaScript expression to conditionally load one of two modules based on an environment variable (CONNECT_COV). An attacker could potentially manipulate this environment variable to load a malicious module, especially if the environment variable is not properly sanitized or is exposed to untrusted input.\n",
      "classification": "very promising",
      "cwe": "CWE-829",
      "function_names": [],
      "filenames": [
        "index.js"
      ]
    },
    {
      "headline": "Outdated jQuery 1.7.1 containing known vulnerabilities",
      "analysis": "The codebase includes jQuery version 1.7.1, which contains several known vulnerabilities, such as XSS and prototype pollution. These vulnerabilities can be exploited by attackers to perform attacks like DOM-based cross-site scripting (XSS).\n",
      "classification": "very promising",
      "cwe": "CWE-79",
      "function_names": [],
      "filenames": [
        "docs/jquery.js"
      ]
    },
    {
      "headline": "Improper input validation in multipart form handling",
      "analysis": "In multipart.js, the code does not properly validate multipart form inputs. This can be exploited by attackers to perform various attacks, such as uploading malicious files or triggering unexpected behaviors in the server.\n",
      "classification": "very promising",
      "cwe": "CWE-20",
      "function_names": [
        "multipart"
      ],
      "filenames": [
        "lib/middleware/multipart.js"
      ]
    },
    {
      "headline": "Hardcoded sensitive information in tests",
      "analysis": "The test/compress.js file and others contain hardcoded sensitive information such as secrets, thresholds, and API keys, which can be exposed through various unintended means. An attacker could use this information to compromise the security of the system.\n",
      "classification": "very promising",
      "cwe": "CWE-798",
      "function_names": [
        "app",
        "app2"
      ],
      "filenames": [
        "test/compress.js",
        "test/limit.js",
        "test/session.js"
      ]
    },
    {
      "headline": "Potential for SQL injection due to usage of user-provided data without sanitization",
      "analysis": "The codebase has instances where user input is utilized in forming SQL queries without proper sanitization. This could enable SQL injection attacks, allowing attackers to read, modify, or delete sensitive information in the database.\n",
      "classification": "very promising",
      "cwe": "CWE-89",
      "function_names": [
        "query"
      ],
      "filenames": [
        "lib/middleware/query.js"
      ]
    },
    {
      "headline": "Potential Denial of Service (DoS) due to server-side request forgery (SSRF)",
      "analysis": "The code might be vulnerable to SSRF, where attackers can send requests from the server to arbitrary locations, potentially accessing internal systems or causing denial of service (DoS).\n",
      "classification": "very promising",
      "cwe": "CWE-918",
      "function_names": [
        "handle"
      ],
      "filenames": [
        "lib/proto.js"
      ]
    },
    {
      "headline": "Buffer overflow vulnerability in form data parsing",
      "analysis": "The bodyParser.js and multipart.js files do not have sufficient checks in place to prevent buffer overflow attacks when processing form data. Attackers could exploit these issues to execute arbitrary code on the server.\n",
      "classification": "very promising",
      "cwe": "CWE-120",
      "function_names": [
        "parse",
        "multipart"
      ],
      "filenames": [
        "lib/middleware/bodyParser.js",
        "lib/middleware/multipart.js"
      ]
    },
    {
      "headline": "Directory traversal vulnerability in static file handling",
      "analysis": "The static file serving implementation in static.js does not properly validate file paths, making it susceptible to directory traversal attacks. Attackers could exploit this to read or write arbitrary files on the server.\n",
      "classification": "very promising",
      "cwe": "CWE-22",
      "function_names": [
        "static"
      ],
      "filenames": [
        "lib/middleware/static.js"
      ]
    },
    {
      "headline": "Weak default configurations for session management",
      "analysis": "The default session management in session.js uses configurations that may not be secure, such as the default cookie settings. This could lead to session hijacking, fixation, or other attacks.\n",
      "classification": "slightly promising",
      "cwe": "CWE-521",
      "function_names": [
        "session",
        "handle"
      ],
      "filenames": [
        "lib/middleware/session.js"
      ]
    }
  ],
  "scores": [
    {
      "stats": {
        "fn": 1,
        "tp": 0,
        "fp": 8
      },
      "mapping": {},
      "vuln_dates": {
        "CVE-2018-3717": "2018-06-07T02:29:08"
      },
      "scoring_model": "claude-3-opus-20240229",
      "type": "llm",
      "instruction_template_hash": "245ace12b6361954d0a2"
    },
    {
      "stats": {
        "fn": 1,
        "tp": 0,
        "fp": 8
      },
      "mapping": {},
      "vuln_dates": {
        "CVE-2018-3717": "2018-06-07T02:29:08"
      },
      "scoring_model": "claude-3-5-sonnet-20240620",
      "type": "llm",
      "instruction_template_hash": "245ace12b6361954d0a2"
    }
  ],
  "instruction_template_hash": "10c0163db4740318a544",
  "version": "0.1.0"
}
