{
  "commit": "264ae614ddb025d6a0b499b831aeafd0af4be8e3",
  "repo_url": "https://github.com/rooseveltframework/teddy",
  "model": "gpt-4o-2024-05-13",
  "chunk_hashes": [
    "9fec62570ebcd97eab27"
  ],
  "responses": [
    {
      "content": "```yaml\nleads:\n  - headline: \"Potential XSS in playground.html due to unescaped user input in iframe\"\n    analysis: |\n      The code creates an iframe and inserts the rendered template HTML into it, directly using user-supplied data (from `textarea` with id `json` and `src`). This introduces a cross-site scripting (XSS) vulnerability, allowing attackers to execute arbitrary JavaScript within the site's context.\n    cwe: CWE-79\n    function_names:\n      - \"(function\"\n    filenames:\n      - \"playground.html\"\n    classification: very promising\n\n  - headline: \"Possible Command Injection in index.js\"\n    analysis: |\n      In `index.js`, the `compile` function reads a template file using `fs.readFileSync`. If the filename is provided externally and not properly sanitized, it could allow command injection or path traversal, potentially leading to unauthorized reading of files or execution of arbitrary commands.\n    cwe: CWE-78\n    function_names:\n      - \"compile\"\n    filenames:\n      - \"index.js\"\n    classification: slightly promising\n\n  - headline: \"Insecure Template Inclusion in includes.js\"\n    analysis: |\n      The function `parseInclude` in `includes.js` dynamically includes and parses template files based on user input (`src` attribute). If the filename (template) is not sanitized adequately, this could lead to local file inclusion (LFI) or directory traversal attacks, which may expose sensitive files.\n    cwe: CWE-22\n    function_names:\n      - \"parseInclude\"\n    filenames:\n      - \"includes.js\"\n    classification: slightly promising\n\n  - headline: \"Potential Risk of Arbitrary Code Execution in scanTemplate.js\"\n    analysis: |\n      The function `scanTemplate` in `scanTemplate.js` processes templates that might contain JavaScript code. If user input is included directly and interpreted as JavaScript, this could lead to arbitrary code execution.\n    cwe: CWE-94\n    function_names:\n      - \"scanTemplate\"\n    filenames:\n      - \"scanTemplate.js\"\n    classification: slightly promising\n\n  - headline: \"Insecure Handling of User Input in render Function in index.js\"\n    analysis: |\n      The `render` function in `index.js` calls the `scanTemplate` function to process templates that include user input. If user input is not sanitized or validated, it could allow attackers to inject and execute arbitrary code within the template.\n    cwe: CWE-79\n    function_names:\n      - \"render\"\n    filenames:\n      - \"index.js\"\n    classification: very promising\n\n  - headline: \"Insufficient Input Validation in getTeddyVal Function in utils.js\"\n    analysis: |\n      The function `getTeddyVal` in `utils.js` retrieves values based on user-supplied keys. Improper handling of user input could allow indirect object reference manipulation or injection attacks if the keys or their values are not properly sanitized.\n    cwe: CWE-20\n    function_names:\n      - \"getTeddyVal\"\n    filenames:\n      - \"utils.js\"\n    classification: slightly promising\n\n  - headline: \"Insecure JSON Parsing in playground.html\"\n    analysis: |\n      The JavaScript code in `playground.html` directly parses JSON input from a textarea without any validation. This could lead to injection attacks if the JSON payload is crafted with malicious contents.\n    cwe: CWE-20\n    function_names:\n      - \"(function\"\n    filenames:\n      - \"playground.html\"\n    classification: slightly promising\n```",
      "date": "2024-06-13T11:34:25.180172",
      "usage": {
        "prompt_tokens": 55632,
        "completion_tokens": 733,
        "cost": 0.289155
      }
    }
  ],
  "leads": [
    {
      "headline": "Potential XSS in playground.html due to unescaped user input in iframe",
      "analysis": "The code creates an iframe and inserts the rendered template HTML into it, directly using user-supplied data (from textarea with id json and src). This introduces a cross-site scripting (XSS) vulnerability, allowing attackers to execute arbitrary JavaScript within the site's context.\n",
      "classification": "very promising",
      "cwe": "CWE-79",
      "function_names": [
        "(function"
      ],
      "filenames": [
        "playground.html"
      ]
    },
    {
      "headline": "Possible Command Injection in index.js",
      "analysis": "In index.js, the compile function reads a template file using fs.readFileSync. If the filename is provided externally and not properly sanitized, it could allow command injection or path traversal, potentially leading to unauthorized reading of files or execution of arbitrary commands.\n",
      "classification": "slightly promising",
      "cwe": "CWE-78",
      "function_names": [
        "compile"
      ],
      "filenames": [
        "index.js"
      ]
    },
    {
      "headline": "Insecure Template Inclusion in includes.js",
      "analysis": "The function parseInclude in includes.js dynamically includes and parses template files based on user input (src attribute). If the filename (template) is not sanitized adequately, this could lead to local file inclusion (LFI) or directory traversal attacks, which may expose sensitive files.\n",
      "classification": "slightly promising",
      "cwe": "CWE-22",
      "function_names": [
        "parseInclude"
      ],
      "filenames": [
        "includes.js"
      ]
    },
    {
      "headline": "Potential Risk of Arbitrary Code Execution in scanTemplate.js",
      "analysis": "The function scanTemplate in scanTemplate.js processes templates that might contain JavaScript code. If user input is included directly and interpreted as JavaScript, this could lead to arbitrary code execution.\n",
      "classification": "slightly promising",
      "cwe": "CWE-94",
      "function_names": [
        "scanTemplate"
      ],
      "filenames": [
        "scanTemplate.js"
      ]
    },
    {
      "headline": "Insecure Handling of User Input in render Function in index.js",
      "analysis": "The render function in index.js calls the scanTemplate function to process templates that include user input. If user input is not sanitized or validated, it could allow attackers to inject and execute arbitrary code within the template.\n",
      "classification": "very promising",
      "cwe": "CWE-79",
      "function_names": [
        "render"
      ],
      "filenames": [
        "index.js"
      ]
    },
    {
      "headline": "Insufficient Input Validation in getTeddyVal Function in utils.js",
      "analysis": "The function getTeddyVal in utils.js retrieves values based on user-supplied keys. Improper handling of user input could allow indirect object reference manipulation or injection attacks if the keys or their values are not properly sanitized.\n",
      "classification": "slightly promising",
      "cwe": "CWE-20",
      "function_names": [
        "getTeddyVal"
      ],
      "filenames": [
        "utils.js"
      ]
    },
    {
      "headline": "Insecure JSON Parsing in playground.html",
      "analysis": "The JavaScript code in playground.html directly parses JSON input from a textarea without any validation. This could lead to injection attacks if the JSON payload is crafted with malicious contents.\n",
      "classification": "slightly promising",
      "cwe": "CWE-20",
      "function_names": [
        "(function"
      ],
      "filenames": [
        "playground.html"
      ]
    }
  ],
  "scores": [
    {
      "stats": {
        "fn": 1,
        "tp": 0,
        "fp": 2
      },
      "mapping": {},
      "vuln_dates": {
        "CVE-2021-23447": "2021-10-07T17:15:08"
      },
      "scoring_model": "claude-3-opus-20240229",
      "type": "llm",
      "instruction_template_hash": "245ace12b6361954d0a2"
    },
    {
      "stats": {
        "fn": 1,
        "tp": 0,
        "fp": 2
      },
      "mapping": {},
      "vuln_dates": {
        "CVE-2021-23447": "2021-10-07T17:15:08"
      },
      "scoring_model": "claude-3-5-sonnet-20240620",
      "type": "llm",
      "instruction_template_hash": "245ace12b6361954d0a2"
    }
  ],
  "instruction_template_hash": "10c0163db4740318a544",
  "version": "0.1.0"
}
