{
  "commit": "f229c1e8e0c5951213cf3652cfa32c2b7d10bbb8",
  "repo_url": "https://github.com/idurar/idurar-erp-crm",
  "model": "claude-3-5-sonnet-20240620",
  "chunk_hashes": [
    "a7346cd23da9c109d4d3"
  ],
  "responses": [
    {
      "content": "```yaml\nleads:\n  - headline: Potential Command Injection in exec()\n    analysis: |\n      The app uses exec() to execute system commands in several places, which could potentially allow command injection if user input is not properly sanitized before being passed to exec(). An attacker could potentially inject malicious commands to be executed on the system. The exec() function should be avoided if possible, or input should be very carefully validated and sanitized before use.\n    cwe: CWE-78\n    function_names:\n      - exec\n    filenames:\n      - controllers/corsControllers/custom.js\n    classification: very promising\n\n  - headline: Unvalidated File Paths\n    analysis: |\n      The app constructs file paths using user-supplied input in several places without proper validation. This could potentially allow directory traversal attacks if an attacker provides malicious input. File paths should be carefully validated and sanitized before use to prevent accessing files outside of intended directories.\n    cwe: CWE-22 \n    function_names:\n      - generatePdf\n    filenames:\n      - controllers/corsControllers/custom.js\n    classification: very promising\n\n  - headline: Insecure Direct Object References\n    analysis: |\n      The app uses object IDs from user input to directly access database records in many API routes without proper authorization checks. This could allow an attacker to access or modify data they should not have permission for by guessing or enumerating valid object IDs.\n    cwe: CWE-639\n    function_names:\n      - read\n      - update\n      - delete  \n    filenames:\n      - controllers/corsControllers/apiRest.js\n    classification: very promising\n\n  - headline: Missing Encryption for Sensitive Data\n    analysis: |\n      The app appears to store sensitive data like passwords and payment information in the database without encryption. This data should be encrypted at rest to protect it in case of a data breach. Implement field-level encryption for sensitive fields before storing in the database.\n    cwe: CWE-311\n    function_names: []\n    filenames:\n      - models/erpModels/Admin.js\n      - models/erpModels/Client.js\n    classification: very promising\n\n  - headline: Weak Password Hashing\n    analysis: |\n      The app uses bcrypt for password hashing, which is generally good, but the work factor is not specified. This could result in weak hashes if the default work factor is too low. Explicitly set a high work factor (e.g. 12+) when hashing passwords to increase resistance to cracking attempts.\n    cwe: CWE-916\n    function_names:\n      - generateHash\n    filenames: \n      - models/erpModels/Admin.js\n    classification: slightly promising\n```",
      "date": "2024-07-07T21:17:51.380055",
      "usage": {
        "prompt_tokens": 80488,
        "completion_tokens": 643,
        "cost": 0.251109
      }
    }
  ],
  "leads": [
    {
      "headline": "Potential Command Injection in exec()",
      "analysis": "The app uses exec() to execute system commands in several places, which could potentially allow command injection if user input is not properly sanitized before being passed to exec(). An attacker could potentially inject malicious commands to be executed on the system. The exec() function should be avoided if possible, or input should be very carefully validated and sanitized before use.\n",
      "classification": "very promising",
      "cwe": "CWE-78",
      "function_names": [
        "exec"
      ],
      "filenames": [
        "controllers/corsControllers/custom.js"
      ]
    },
    {
      "headline": "Unvalidated File Paths",
      "analysis": "The app constructs file paths using user-supplied input in several places without proper validation. This could potentially allow directory traversal attacks if an attacker provides malicious input. File paths should be carefully validated and sanitized before use to prevent accessing files outside of intended directories.\n",
      "classification": "very promising",
      "cwe": "CWE-22",
      "function_names": [
        "generatePdf"
      ],
      "filenames": [
        "controllers/corsControllers/custom.js"
      ]
    },
    {
      "headline": "Insecure Direct Object References",
      "analysis": "The app uses object IDs from user input to directly access database records in many API routes without proper authorization checks. This could allow an attacker to access or modify data they should not have permission for by guessing or enumerating valid object IDs.\n",
      "classification": "very promising",
      "cwe": "CWE-639",
      "function_names": [
        "read",
        "update",
        "delete"
      ],
      "filenames": [
        "controllers/corsControllers/apiRest.js"
      ]
    },
    {
      "headline": "Missing Encryption for Sensitive Data",
      "analysis": "The app appears to store sensitive data like passwords and payment information in the database without encryption. This data should be encrypted at rest to protect it in case of a data breach. Implement field-level encryption for sensitive fields before storing in the database.\n",
      "classification": "very promising",
      "cwe": "CWE-311",
      "function_names": [],
      "filenames": [
        "models/erpModels/Admin.js",
        "models/erpModels/Client.js"
      ]
    },
    {
      "headline": "Weak Password Hashing",
      "analysis": "The app uses bcrypt for password hashing, which is generally good, but the work factor is not specified. This could result in weak hashes if the default work factor is too low. Explicitly set a high work factor (e.g. 12+) when hashing passwords to increase resistance to cracking attempts.\n",
      "classification": "slightly promising",
      "cwe": "CWE-916",
      "function_names": [
        "generateHash"
      ],
      "filenames": [
        "models/erpModels/Admin.js"
      ]
    }
  ],
  "scores": [
    {
      "stats": {
        "fn": 1,
        "tp": 0,
        "fp": 4
      },
      "mapping": {},
      "vuln_dates": {
        "CVE-2023-52265": "2023-12-30T23:15:42"
      },
      "scoring_model": "claude-3-5-sonnet-20240620",
      "type": "llm",
      "instruction_template_hash": "245ace12b6361954d0a2"
    }
  ],
  "instruction_template_hash": "10c0163db4740318a544",
  "version": "0.1.0"
}
