{
  "commit": "03129504e89707cb046922cdeb9958d77d275913",
  "repo_url": "https://github.com/blitz-js/superjson",
  "model": "gpt-4o-2024-05-13",
  "chunk_hashes": [
    "edea9adfb9cce60bce31"
  ],
  "responses": [
    {
      "content": "```yaml\nleads:\n  - headline: \"Lack of input validation\"\n    analysis: |\n      The code does not properly validate or sanitize user input taken from various sources, leading to potential vulnerabilities such as injection attacks. In particular, values deserialized from SuperJSON are directly used without ensuring they are safe. This could make the application susceptible to various types of code injection attacks (SQL, NoSQL, Command, etc.).\n    cwe: CWE-20\n    function_names:\n      - \"deserialize\"\n    filenames:\n      - \"src/index.ts\"\n    classification: very promising\n\n  - headline: \"Potential Prototype Pollution\"\n    analysis: |\n      The function untransformValue in transformer.ts does not properly sanitize data before assignment, potentially allowing an attacker to manipulate the prototype of an object. This might lead to unintended object behaviors and security risks such as denial of service (DoS) or data corruption.\n    cwe: CWE-1321\n    function_names:\n      - \"untransformValue\"\n    filenames:\n      - \"src/transformer.ts\"\n    classification: very promising\n\n  - headline: \"Sensitive data exposure during serialization\"\n    analysis: |\n      The serialization process does not adequately address the inclusion of sensitive information like passwords or API keys within complex objects. If such objects are serialized without careful handling, sensitive data may get leaked.\n    cwe: CWE-522\n    function_names:\n      - \"serialize\"\n    filenames:\n      - \"src/index.ts\"\n    classification: very promising\n\n  - headline: \"Improper handling of error messages\"\n    analysis: |\n      The error handling logic in error-props.ts and transformer.ts includes generic and possibly unsafe error-catching mechanisms that do not sanitize error messages properly. This may lead to the leakage of sensitive application data through error messages.\n    cwe: CWE-209\n    function_names:\n      - \"applyValueAnnotations\"\n      - \"applyReferentialEqualityAnnotations\"\n      - \"serialize\"\n    filenames:\n      - \"src/plainer.ts\"\n      - \"src/index.ts\"\n      - \"src/transformer.ts\"\n    classification: slightly promising\n\n  - headline: \"Missing synchronization\"\n    analysis: |\n      The absence of proper synchronization mechanisms in registry.ts and custom-transformer-registry.ts may lead to race conditions in a multi-threaded environment. The codebase assumes that only a single thread manipulates the registry, which could lead to unpredictable behavior in concurrent environments.\n    cwe: CWE-662\n    function_names:\n      - \"register\"\n    filenames:\n      - \"src/registry.ts\"\n      - \"src/custom-transformer-registry.ts\"\n    classification: slightly promising\n\n  - headline: \"Improper handling of Object.prototype\"\n    analysis: |\n      Functions interacting with generic objects do not handle potential prototype-less objects (e.g., created via Object.create(null)). This could lead to unexpected behavior or errors when such objects are encountered.\n    cwe: CWE-704\n    function_names:\n      - \"isPlainObject\"\n    filenames:\n      - \"src/is.ts\"\n    classification: slightly promising\n\n  - headline: \"Potential information leakage in error messages\"\n    analysis: |\n      The application's handling of error messages might inadvertently expose sensitive information, as shown by the use of Error objects that include stack traces and other sensitive meta-data without sanitization.\n    cwe: CWE-209\n    function_names:\n      - \"Error\"\n    filenames:\n      - \"src/transformer.ts\"\n      - \"src/is.ts\"\n    classification: slightly promising\n```",
      "date": "2024-06-12T15:13:30.162941",
      "usage": {
        "prompt_tokens": 17022,
        "completion_tokens": 724,
        "cost": 0.09597
      }
    }
  ],
  "leads": [
    {
      "headline": "Lack of input validation",
      "analysis": "The code does not properly validate or sanitize user input taken from various sources, leading to potential vulnerabilities such as injection attacks. In particular, values deserialized from SuperJSON are directly used without ensuring they are safe. This could make the application susceptible to various types of code injection attacks (SQL, NoSQL, Command, etc.).\n",
      "classification": "very promising",
      "cwe": "CWE-20",
      "function_names": [
        "deserialize"
      ],
      "filenames": [
        "src/index.ts"
      ]
    },
    {
      "headline": "Potential Prototype Pollution",
      "analysis": "The function untransformValue in transformer.ts does not properly sanitize data before assignment, potentially allowing an attacker to manipulate the prototype of an object. This might lead to unintended object behaviors and security risks such as denial of service (DoS) or data corruption.\n",
      "classification": "very promising",
      "cwe": "CWE-1321",
      "function_names": [
        "untransformValue"
      ],
      "filenames": [
        "src/transformer.ts"
      ]
    },
    {
      "headline": "Sensitive data exposure during serialization",
      "analysis": "The serialization process does not adequately address the inclusion of sensitive information like passwords or API keys within complex objects. If such objects are serialized without careful handling, sensitive data may get leaked.\n",
      "classification": "very promising",
      "cwe": "CWE-522",
      "function_names": [
        "serialize"
      ],
      "filenames": [
        "src/index.ts"
      ]
    },
    {
      "headline": "Improper handling of error messages",
      "analysis": "The error handling logic in error-props.ts and transformer.ts includes generic and possibly unsafe error-catching mechanisms that do not sanitize error messages properly. This may lead to the leakage of sensitive application data through error messages.\n",
      "classification": "slightly promising",
      "cwe": "CWE-209",
      "function_names": [
        "applyValueAnnotations",
        "applyReferentialEqualityAnnotations",
        "serialize"
      ],
      "filenames": [
        "src/plainer.ts",
        "src/index.ts",
        "src/transformer.ts"
      ]
    },
    {
      "headline": "Missing synchronization",
      "analysis": "The absence of proper synchronization mechanisms in registry.ts and custom-transformer-registry.ts may lead to race conditions in a multi-threaded environment. The codebase assumes that only a single thread manipulates the registry, which could lead to unpredictable behavior in concurrent environments.\n",
      "classification": "slightly promising",
      "cwe": "CWE-662",
      "function_names": [
        "register"
      ],
      "filenames": [
        "src/registry.ts",
        "src/custom-transformer-registry.ts"
      ]
    },
    {
      "headline": "Improper handling of Object.prototype",
      "analysis": "Functions interacting with generic objects do not handle potential prototype-less objects (e.g., created via Object.create(null)). This could lead to unexpected behavior or errors when such objects are encountered.\n",
      "classification": "slightly promising",
      "cwe": "CWE-704",
      "function_names": [
        "isPlainObject"
      ],
      "filenames": [
        "src/is.ts"
      ]
    },
    {
      "headline": "Potential information leakage in error messages",
      "analysis": "The application's handling of error messages might inadvertently expose sensitive information, as shown by the use of Error objects that include stack traces and other sensitive meta-data without sanitization.\n",
      "classification": "slightly promising",
      "cwe": "CWE-209",
      "function_names": [
        "Error"
      ],
      "filenames": [
        "src/transformer.ts",
        "src/is.ts"
      ]
    }
  ],
  "scores": [
    {
      "stats": {
        "fn": 1,
        "tp": 0,
        "fp": 3
      },
      "mapping": {},
      "vuln_dates": {
        "CVE-2022-23631": "2022-02-09T22:15:07"
      },
      "scoring_model": "claude-3-opus-20240229",
      "type": "llm",
      "instruction_template_hash": "245ace12b6361954d0a2"
    },
    {
      "stats": {
        "fn": 0,
        "tp": 1,
        "fp": 2
      },
      "mapping": {
        "0": "CVE-2022-23631"
      },
      "vuln_dates": {
        "CVE-2022-23631": "2022-02-09T22:15:07"
      },
      "scoring_model": "claude-3-5-sonnet-20240620",
      "type": "llm",
      "instruction_template_hash": "245ace12b6361954d0a2"
    }
  ],
  "instruction_template_hash": "10c0163db4740318a544",
  "version": "0.1.0"
}
