{
  "commit": "39c4a78634966f9fb965ab1060f70eac41c52966",
  "repo_url": "https://github.com/turbowarp/desktop",
  "model": "gpt-4o-2024-05-13",
  "chunk_hashes": [
    "0e73bcbe6a8a8501ff90"
  ],
  "responses": [
    {
      "content": "```yaml\nleads:\n  - headline: \"Potential Unsanitized HTML Template Injection Vulnerability in template.html\"\n    analysis: |\n      The file `src/renderer/template.html` contains a JavaScript function that dynamically writes HTML content based on URL parameters. \n      This presents a risk if the URL parameters are not properly sanitized or validated, allowing attackers to inject malicious scripts.\n    cwe: CWE-79\n    function_names: []\n    filenames:\n      - src/renderer/template.html\n    classification: very promising\n\n  - headline: \"Inadequate Permission Management in Electron IPC Handlers\"\n    analysis: |\n      In `src/main/index.js`, various IPC handlers are implemented without comprehensive permission checks. For instance, handlers for file reading \n      and writing (`read-file` and `write-file-with-port`) should ensure thorough verification of allowed file paths to prevent unauthorized access. \n      Missing rigorous checks could lead to local file system access vulnerabilities.\n    cwe: CWE-269\n    function_names:\n      - handlePermissionRequest\n    filenames:\n      - src/main/index.js\n      - src/main/permissions.js\n    classification: very promising\n\n  - headline: \"Open Redirect via Unchecked External URLs\"\n    analysis: |\n      The code in `src/main/index.js` handles external URL opening without sufficient validation. An attacker could exploit this mechanism to \n      redirect users to malicious websites. The `isSafeOpenExternal` function should enforce stricter validation on URLs being opened.\n    cwe: CWE-601\n    function_names:\n      - isSafeOpenExternal\n    filenames:\n      - src/main/index.js\n    classification: slightly promising\n\n  - headline: \"Command Injection via `child_process` in Post-install Script\"\n    analysis: |\n      The post-install script `install.sh` in the repository allows arbitrary commands to be executed via unsanitized input. \n      This could be exploited to execute malicious commands on the host system. Proper sanitization and validation of input parameters is necessary.\n    cwe: CWE-78\n    function_names: []\n    filenames:\n      - docs/install.sh\n    classification: very promising\n\n  - headline: \"Cleartext Transmission of Sensitive Information in Update Checker\"\n    analysis: |\n      The `src/main/update-checker.js` script performs HTTP requests to check for updates without enforcing HTTPS. \n      This could expose sensitive information to MITM (Man-in-the-Middle) attacks. Switching to HTTPS is recommended.\n    cwe: CWE-319\n    function_names:\n      - getLatestVersions\n    filenames:\n      - src/main/update-checker.js\n    classification: very promising\n\n  - headline: \"Insecure Cryptographic Storage of Hashes\"\n    analysis: |\n      In `scripts/update-packager.js`, cryptographic hashes are computed using `crypto` but stored in plain text within JSON files. \n      This could compromise the integrity verification process. Storing hashes securely and ensuring proper integrity checks are necessary.\n    cwe: CWE-922\n    function_names: []\n    filenames:\n      - scripts/update-packager.js\n    classification: slightly promising\n\n  - headline: \"Potential Race Condition in Electron App Creation\"\n    analysis: |\n      The `src/main/index.js` contains race conditions during the creation of new browser windows. Using `setImmediate` to handle external URL openings \n      may lead to unintended behaviors if not properly synchronized, potentially causing inconsistencies in window creation.\n    cwe: CWE-362\n    function_names: []\n    filenames:\n      - src/main/index.js\n    classification: slightly promising\n\n  - headline: \"Hardcoded API Keys/Secrets in Electron Apps\"\n    analysis: |\n      The codebase potentially relies on hardcoded credentials or secrets for interacting with external APIs, such as Apple notarization keys in `scripts/after-sign.js`. \n      Exposing credentials in the source code makes them vulnerable to being extracted. It is recommended to use environment variables or secure vaults.\n    cwe: CWE-798\n    function_names: []\n    filenames:\n      - scripts/after-sign.js\n    classification: very promising\n```",
      "date": "2024-07-08T09:03:23.089131",
      "usage": {
        "prompt_tokens": 56380,
        "completion_tokens": 842,
        "cost": 0.29453
      }
    }
  ],
  "leads": [
    {
      "headline": "Potential Unsanitized HTML Template Injection Vulnerability in template.html",
      "analysis": "The file src/renderer/template.html contains a JavaScript function that dynamically writes HTML content based on URL parameters. \nThis presents a risk if the URL parameters are not properly sanitized or validated, allowing attackers to inject malicious scripts.\n",
      "classification": "very promising",
      "cwe": "CWE-79",
      "function_names": [],
      "filenames": [
        "src/renderer/template.html"
      ]
    },
    {
      "headline": "Inadequate Permission Management in Electron IPC Handlers",
      "analysis": "In src/main/index.js, various IPC handlers are implemented without comprehensive permission checks. For instance, handlers for file reading \nand writing (read-file and write-file-with-port) should ensure thorough verification of allowed file paths to prevent unauthorized access. \nMissing rigorous checks could lead to local file system access vulnerabilities.\n",
      "classification": "very promising",
      "cwe": "CWE-269",
      "function_names": [
        "handlePermissionRequest"
      ],
      "filenames": [
        "src/main/index.js",
        "src/main/permissions.js"
      ]
    },
    {
      "headline": "Open Redirect via Unchecked External URLs",
      "analysis": "The code in src/main/index.js handles external URL opening without sufficient validation. An attacker could exploit this mechanism to \nredirect users to malicious websites. The isSafeOpenExternal function should enforce stricter validation on URLs being opened.\n",
      "classification": "slightly promising",
      "cwe": "CWE-601",
      "function_names": [
        "isSafeOpenExternal"
      ],
      "filenames": [
        "src/main/index.js"
      ]
    },
    {
      "headline": "Command Injection via child_process in Post-install Script",
      "analysis": "The post-install script install.sh in the repository allows arbitrary commands to be executed via unsanitized input. \nThis could be exploited to execute malicious commands on the host system. Proper sanitization and validation of input parameters is necessary.\n",
      "classification": "very promising",
      "cwe": "CWE-78",
      "function_names": [],
      "filenames": [
        "docs/install.sh"
      ]
    },
    {
      "headline": "Cleartext Transmission of Sensitive Information in Update Checker",
      "analysis": "The src/main/update-checker.js script performs HTTP requests to check for updates without enforcing HTTPS. \nThis could expose sensitive information to MITM (Man-in-the-Middle) attacks. Switching to HTTPS is recommended.\n",
      "classification": "very promising",
      "cwe": "CWE-319",
      "function_names": [
        "getLatestVersions"
      ],
      "filenames": [
        "src/main/update-checker.js"
      ]
    },
    {
      "headline": "Insecure Cryptographic Storage of Hashes",
      "analysis": "In scripts/update-packager.js, cryptographic hashes are computed using crypto but stored in plain text within JSON files. \nThis could compromise the integrity verification process. Storing hashes securely and ensuring proper integrity checks are necessary.\n",
      "classification": "slightly promising",
      "cwe": "CWE-922",
      "function_names": [],
      "filenames": [
        "scripts/update-packager.js"
      ]
    },
    {
      "headline": "Potential Race Condition in Electron App Creation",
      "analysis": "The src/main/index.js contains race conditions during the creation of new browser windows. Using setImmediate to handle external URL openings \nmay lead to unintended behaviors if not properly synchronized, potentially causing inconsistencies in window creation.\n",
      "classification": "slightly promising",
      "cwe": "CWE-362",
      "function_names": [],
      "filenames": [
        "src/main/index.js"
      ]
    },
    {
      "headline": "Hardcoded API Keys/Secrets in Electron Apps",
      "analysis": "The codebase potentially relies on hardcoded credentials or secrets for interacting with external APIs, such as Apple notarization keys in scripts/after-sign.js. \nExposing credentials in the source code makes them vulnerable to being extracted. It is recommended to use environment variables or secure vaults.\n",
      "classification": "very promising",
      "cwe": "CWE-798",
      "function_names": [],
      "filenames": [
        "scripts/after-sign.js"
      ]
    }
  ],
  "scores": [
    {
      "stats": {
        "fn": 1,
        "tp": 0,
        "fp": 5
      },
      "mapping": {},
      "vuln_dates": {
        "CVE-2023-40168": "2023-08-17T20:15:11"
      },
      "scoring_model": "claude-3-5-sonnet-20240620",
      "type": "llm",
      "instruction_template_hash": "245ace12b6361954d0a2"
    }
  ],
  "instruction_template_hash": "10c0163db4740318a544",
  "version": "0.1.0"
}
