{
  "commit": "2886596b878273e30604c79e0369b3204e399b03",
  "repo_url": "https://github.com/gilbitron/raneto",
  "model": "gpt-4-turbo-2024-04-09",
  "chunk_hashes": [
    "8f516469a183636688ca"
  ],
  "responses": [
    {
      "content": "```yaml\nleads:\n  - headline: \"Sensitive Information Leak via Error Messages\"\n    analysis: |\n      The application exposes sensitive information when database queries fail. Such failures trigger error messages that are displayed to the user, potentially revealing the database schema, query structure, or other internal system details that could aid an attacker in further exploits.\n    cwe: CWE-209\n    function_names:\n      - route_page_delete\n    filenames:\n      - app/routes/page.delete.route.js\n    classification: \"very promising\"\n\n  - headline: \"MD5 Used for Sensitive Hashing in Authentication Handling\"\n    analysis: |\n      MD5 is used to hash sensitive data within the authentication handling process. Given that MD5 is widely considered to be cryptographically broken and unsuitable for further use, especially in sensitive settings such as password hashing, this usage exposes the application to the risk of attacks where hashed values are reversed or collisions are found, potentially compromising user data or system access.\n    cwe: CWE-327\n    function_names:\n      - route_login\n    filenames:\n      - app/routes/login.route.js\n    classification: \"very promising\"\n\n  - headline: \"Persistent Cross-Site Scripting (XSS) Vulnerability\"\n    analysis: |\n      The application fails to properly sanitize user input for special HTML characters such as <, >, or \" which are treated as part of the HTML/JavaScript code when inserted unescaped into the web page. This leads to a persistent XSS condition where an attacker could inject malicious scripts into content that will be saved and later presented to users, allowing for potential theft of cookies, session tokens, or other sensitive information accessible through client-side scripts.\n    cwe: CWE-79\n    function_names:\n      - route_page_edit\n    filenames:\n      - app/routes/page.edit.route.js\n    classification: \"very promising\"\n\n  - headline: \"Improper Access Control in Editing Features\"\n    analysis: |\n      The application improperly restricts access to the editing features, potentially allowing unauthorized users to access these functionalities. The check for 'loggedIn' status appears to be insufficient without a robust verification mechanism to ensure that the session has not been hijacked or tampered with.\n    cwe: CWE-285\n    function_names:\n      - middleware_authenticate\n    filenames:\n      - app/middleware/authenticate.js\n    classification: \"very promising\"\n\n  - headline: \"SQL Injection Through Unsanitized Input\"\n    analysis: |\n      User input from the front end is inserted directly into SQL queries without proper sanitization, making it possible for an attacker to manipulate these queries by injecting malicious SQL code. This can lead to unauthorized data access or manipulation and other database-level attacks.\n    cwe: CWE-89\n    function_names:\n      - route_page_delete\n    filenames:\n      - app/routes/page.delete.route.js\n    classification: \"very promising\"\n\n  - headline: \"Use of Hard-coded Credentials in Source Code\"\n    analysis: |\n      The application's source code contains hard-coded credentials, which represents a significant security risk. Hard-coded passwords may lead to unauthorized access if the codebase is exposed or accessed by unintended parties. This practice negates the benefits of password encryption or hashing normally used to secure credentials in storage.\n    cwe: CWE-798\n    function_names:\n      - route_login_page\n    filenames:\n      - app/routes/login_page.route.js\n    classification: \"very promising\"\n\n  - headline: \"Insufficient Logging of Authentication Failures\"\n    analysis: |\n      There is an absence of sufficient logging mechanisms for failed authentication attempts, which impedes the ability to detect or respond to repeated failed login attempts or brute-force attacks. Proper logging is essential for diagnosing potential security breaches and taking timely corrective action.\n    cwe: CWE-778\n    function_names:\n      - route_login\n    filenames:\n      - app/routes/login.route.js\n    classification: \"very promising\"\n\n  - headline: \"Directory Traversal via Unsanitized File Path Inputs\"\n    analysis: |\n      The application does not sufficiently sanitize user-supplied file paths, allowing for directory traversal attacks in which an attacker could access or modify files and directories that are stored outside the intended directory.\n    cwe: CWE-22\n    function_names:\n      - get_filepath\n    filenames:\n      - app/functions/get_filepath.js\n    classification: \"very promising\"\n```",
      "date": "2024-06-12T17:01:30.685684",
      "usage": {
        "prompt_tokens": 24775,
        "completion_tokens": 892,
        "cost": 0.27451
      }
    }
  ],
  "leads": [
    {
      "headline": "Sensitive Information Leak via Error Messages",
      "analysis": "The application exposes sensitive information when database queries fail. Such failures trigger error messages that are displayed to the user, potentially revealing the database schema, query structure, or other internal system details that could aid an attacker in further exploits.\n",
      "classification": "very promising",
      "cwe": "CWE-209",
      "function_names": [
        "route_page_delete"
      ],
      "filenames": [
        "app/routes/page.delete.route.js"
      ]
    },
    {
      "headline": "MD5 Used for Sensitive Hashing in Authentication Handling",
      "analysis": "MD5 is used to hash sensitive data within the authentication handling process. Given that MD5 is widely considered to be cryptographically broken and unsuitable for further use, especially in sensitive settings such as password hashing, this usage exposes the application to the risk of attacks where hashed values are reversed or collisions are found, potentially compromising user data or system access.\n",
      "classification": "very promising",
      "cwe": "CWE-327",
      "function_names": [
        "route_login"
      ],
      "filenames": [
        "app/routes/login.route.js"
      ]
    },
    {
      "headline": "Persistent Cross-Site Scripting (XSS) Vulnerability",
      "analysis": "The application fails to properly sanitize user input for special HTML characters such as <, >, or \" which are treated as part of the HTML/JavaScript code when inserted unescaped into the web page. This leads to a persistent XSS condition where an attacker could inject malicious scripts into content that will be saved and later presented to users, allowing for potential theft of cookies, session tokens, or other sensitive information accessible through client-side scripts.\n",
      "classification": "very promising",
      "cwe": "CWE-79",
      "function_names": [
        "route_page_edit"
      ],
      "filenames": [
        "app/routes/page.edit.route.js"
      ]
    },
    {
      "headline": "Improper Access Control in Editing Features",
      "analysis": "The application improperly restricts access to the editing features, potentially allowing unauthorized users to access these functionalities. The check for 'loggedIn' status appears to be insufficient without a robust verification mechanism to ensure that the session has not been hijacked or tampered with.\n",
      "classification": "very promising",
      "cwe": "CWE-285",
      "function_names": [
        "middleware_authenticate"
      ],
      "filenames": [
        "app/middleware/authenticate.js"
      ]
    },
    {
      "headline": "SQL Injection Through Unsanitized Input",
      "analysis": "User input from the front end is inserted directly into SQL queries without proper sanitization, making it possible for an attacker to manipulate these queries by injecting malicious SQL code. This can lead to unauthorized data access or manipulation and other database-level attacks.\n",
      "classification": "very promising",
      "cwe": "CWE-89",
      "function_names": [
        "route_page_delete"
      ],
      "filenames": [
        "app/routes/page.delete.route.js"
      ]
    },
    {
      "headline": "Use of Hard-coded Credentials in Source Code",
      "analysis": "The application's source code contains hard-coded credentials, which represents a significant security risk. Hard-coded passwords may lead to unauthorized access if the codebase is exposed or accessed by unintended parties. This practice negates the benefits of password encryption or hashing normally used to secure credentials in storage.\n",
      "classification": "very promising",
      "cwe": "CWE-798",
      "function_names": [
        "route_login_page"
      ],
      "filenames": [
        "app/routes/login_page.route.js"
      ]
    },
    {
      "headline": "Insufficient Logging of Authentication Failures",
      "analysis": "There is an absence of sufficient logging mechanisms for failed authentication attempts, which impedes the ability to detect or respond to repeated failed login attempts or brute-force attacks. Proper logging is essential for diagnosing potential security breaches and taking timely corrective action.\n",
      "classification": "very promising",
      "cwe": "CWE-778",
      "function_names": [
        "route_login"
      ],
      "filenames": [
        "app/routes/login.route.js"
      ]
    },
    {
      "headline": "Directory Traversal via Unsanitized File Path Inputs",
      "analysis": "The application does not sufficiently sanitize user-supplied file paths, allowing for directory traversal attacks in which an attacker could access or modify files and directories that are stored outside the intended directory.\n",
      "classification": "very promising",
      "cwe": "CWE-22",
      "function_names": [
        "get_filepath"
      ],
      "filenames": [
        "app/functions/get_filepath.js"
      ]
    }
  ],
  "scores": [
    {
      "stats": {
        "fn": 1,
        "tp": 2,
        "fp": 6
      },
      "mapping": {
        "2": "CVE-2022-35144",
        "6": "CVE-2022-35143"
      },
      "vuln_dates": {
        "CVE-2022-35144": "2022-08-04T20:15:19",
        "CVE-2022-35142": "2022-08-04T20:15:19",
        "CVE-2022-35143": "2022-08-04T20:15:19"
      },
      "scoring_model": "claude-3-opus-20240229",
      "type": "llm",
      "instruction_template_hash": "245ace12b6361954d0a2"
    }
  ],
  "instruction_template_hash": "10c0163db4740318a544",
  "version": "0.1.0"
}
