{
  "commit": "11e453ab63d0da1f61a68f4f2ab6c6b75e6be26f",
  "repo_url": "https://github.com/jenkinsci/accurev-plugin",
  "model": "claude-3-haiku-20240307",
  "chunk_hashes": [
    "eccb2e5b6e5aff05ddf2"
  ],
  "responses": [
    {
      "content": "Here is the YAML output for the security vulnerabilities in the provided codebase:\n\n```yaml\nleads:\n  - headline: Improper Input Validation\n    analysis: |\n      The code contains multiple instances of improper input validation, which could lead to security vulnerabilities such as command injection, SQL injection, or XML injection. These vulnerabilities are typically found in the AccurevSCM class and its related classes, where user-provided input is used without proper validation.\n    cwe: CWE-20\n    function_names:\n      - getPollingStream\n      - getDepot\n      - getStream\n    filenames:\n      - hudson/plugins/accurev/AccurevSCM.java\n      - hudson/plugins/accurev/cmd/Login.java\n      - hudson/plugins/accurev/cmd/ShowDepots.java\n    classification: slightly promising\n  - headline: Improper Neutralization of Special Elements in Output Used by a Downstream Component ('Injection')\n    analysis: |\n      The code is vulnerable to various injection attacks, such as command injection, SQL injection, and XML injection. These vulnerabilities are present in the AccurevSCM class and its related classes, where user-provided input is used to construct command-line arguments, SQL queries, or XML documents without proper sanitization.\n    cwe: CWE-74\n    function_names:\n      - checkout\n      - compareRemoteRevisionWith\n      - captureChangeLog\n    filenames:\n      - hudson/plugins/accurev/AccurevSCM.java\n      - hudson/plugins/accurev/cmd/ChangeLogCmd.java\n      - hudson/plugins/accurev/cmd/Login.java\n    classification: very promising\n  - headline: Improper Encoding or Escaping of Output\n    analysis: |\n      The code does not properly encode or escape output, which could lead to cross-site scripting (XSS) vulnerabilities. This issue is particularly evident in the AccurevSCM class and its related classes, where user-provided input is used in the construction of HTML output or other types of output without proper sanitization.\n    cwe: CWE-116\n    function_names:\n      - buildEnvVars\n      - buildEnvironment\n    filenames:\n      - hudson/plugins/accurev/AccurevSCM.java\n      - hudson/plugins/accurev/delegates/AbstractModeDelegate.java\n    classification: slightly promising\n  - headline: Improper Privilege Management\n    analysis: |\n      The code does not properly manage privileges, which could lead to privilege escalation vulnerabilities. This issue is particularly evident in the AccurevSCM class and its related classes, where the code runs with elevated privileges or does not properly restrict access to sensitive operations.\n    cwe: CWE-269\n    function_names:\n      - checkout\n      - compareRemoteRevisionWith\n    filenames:\n      - hudson/plugins/accurev/AccurevSCM.java\n      - hudson/plugins/accurev/delegates/AbstractModeDelegate.java\n    classification: slightly promising\n  - headline: Improper Authentication\n    analysis: |\n      The code does not properly implement authentication, which could lead to authentication bypass vulnerabilities. This issue is particularly evident in the Login class and the AccurevServer class, where the code does not properly validate user credentials or implement secure authentication mechanisms.\n    cwe: CWE-287\n    function_names:\n      - ensureLoggedInToAccurev\n      - accurevLoginFromGlobalConfig\n    filenames:\n      - hudson/plugins/accurev/cmd/Login.java\n      - hudson/plugins/accurev/AccurevSCM.java\n    classification: slightly promising\n  - headline: Missing Encryption of Sensitive Data\n    analysis: |\n      The code does not properly encrypt sensitive data, which could lead to data breaches. This issue is particularly evident in the AccurevSCM class and its related classes, where sensitive information, such as server credentials, is stored or transmitted without encryption.\n    cwe: CWE-311\n    function_names:\n      - getCredentials\n    filenames:\n      - hudson/plugins/accurev/AccurevSCM.java\n    classification: slightly promising\n  - headline: Incorrect Authorization\n    analysis: |\n      The code does not properly implement authorization, which could lead to unauthorized access vulnerabilities. This issue is particularly evident in the AccurevSCM class and its related classes, where the code does not properly restrict access to sensitive operations or resources based on user roles or permissions.\n    cwe: CWE-863\n    function_names:\n      - checkout\n      - compareRemoteRevisionWith\n    filenames:\n      - hudson/plugins/accurev/AccurevSCM.java\n      - hudson/plugins/accurev/delegates/AbstractModeDelegate.java\n    classification: slightly promising\n  - headline: Improper Control of Dynamically-Managed Code Resources\n    analysis: |\n      The code does not properly control dynamically-managed code resources, which could lead to code injection vulnerabilities. This issue is particularly evident in the AccurevSCM class and its related classes, where the code uses dynamic class loading or other mechanisms to execute user-provided code without proper validation or sandboxing.\n    cwe: CWE-913\n    function_names:\n      - getPollingStream\n      - buildEnvVars\n      - buildEnvironment\n    filenames:\n      - hudson/plugins/accurev/AccurevSCM.java\n      - hudson/plugins/accurev/delegates/AbstractModeDelegate.java\n    classification: slightly promising\n```",
      "date": "2024-06-12T17:30:42.177176",
      "usage": {
        "prompt_tokens": 77976,
        "completion_tokens": 1306,
        "cost": 0.0211265
      }
    }
  ],
  "leads": [
    {
      "headline": "Improper Input Validation",
      "analysis": "The code contains multiple instances of improper input validation, which could lead to security vulnerabilities such as command injection, SQL injection, or XML injection. These vulnerabilities are typically found in the AccurevSCM class and its related classes, where user-provided input is used without proper validation.\n",
      "classification": "slightly promising",
      "cwe": "CWE-20",
      "function_names": [
        "getPollingStream",
        "getDepot",
        "getStream"
      ],
      "filenames": [
        "hudson/plugins/accurev/AccurevSCM.java",
        "hudson/plugins/accurev/cmd/Login.java",
        "hudson/plugins/accurev/cmd/ShowDepots.java"
      ]
    },
    {
      "headline": "Improper Neutralization of Special Elements in Output Used by a Downstream Component ('Injection')",
      "analysis": "The code is vulnerable to various injection attacks, such as command injection, SQL injection, and XML injection. These vulnerabilities are present in the AccurevSCM class and its related classes, where user-provided input is used to construct command-line arguments, SQL queries, or XML documents without proper sanitization.\n",
      "classification": "very promising",
      "cwe": "CWE-74",
      "function_names": [
        "checkout",
        "compareRemoteRevisionWith",
        "captureChangeLog"
      ],
      "filenames": [
        "hudson/plugins/accurev/AccurevSCM.java",
        "hudson/plugins/accurev/cmd/ChangeLogCmd.java",
        "hudson/plugins/accurev/cmd/Login.java"
      ]
    },
    {
      "headline": "Improper Encoding or Escaping of Output",
      "analysis": "The code does not properly encode or escape output, which could lead to cross-site scripting (XSS) vulnerabilities. This issue is particularly evident in the AccurevSCM class and its related classes, where user-provided input is used in the construction of HTML output or other types of output without proper sanitization.\n",
      "classification": "slightly promising",
      "cwe": "CWE-116",
      "function_names": [
        "buildEnvVars",
        "buildEnvironment"
      ],
      "filenames": [
        "hudson/plugins/accurev/AccurevSCM.java",
        "hudson/plugins/accurev/delegates/AbstractModeDelegate.java"
      ]
    },
    {
      "headline": "Improper Privilege Management",
      "analysis": "The code does not properly manage privileges, which could lead to privilege escalation vulnerabilities. This issue is particularly evident in the AccurevSCM class and its related classes, where the code runs with elevated privileges or does not properly restrict access to sensitive operations.\n",
      "classification": "slightly promising",
      "cwe": "CWE-269",
      "function_names": [
        "checkout",
        "compareRemoteRevisionWith"
      ],
      "filenames": [
        "hudson/plugins/accurev/AccurevSCM.java",
        "hudson/plugins/accurev/delegates/AbstractModeDelegate.java"
      ]
    },
    {
      "headline": "Improper Authentication",
      "analysis": "The code does not properly implement authentication, which could lead to authentication bypass vulnerabilities. This issue is particularly evident in the Login class and the AccurevServer class, where the code does not properly validate user credentials or implement secure authentication mechanisms.\n",
      "classification": "slightly promising",
      "cwe": "CWE-287",
      "function_names": [
        "ensureLoggedInToAccurev",
        "accurevLoginFromGlobalConfig"
      ],
      "filenames": [
        "hudson/plugins/accurev/cmd/Login.java",
        "hudson/plugins/accurev/AccurevSCM.java"
      ]
    },
    {
      "headline": "Missing Encryption of Sensitive Data",
      "analysis": "The code does not properly encrypt sensitive data, which could lead to data breaches. This issue is particularly evident in the AccurevSCM class and its related classes, where sensitive information, such as server credentials, is stored or transmitted without encryption.\n",
      "classification": "slightly promising",
      "cwe": "CWE-311",
      "function_names": [
        "getCredentials"
      ],
      "filenames": [
        "hudson/plugins/accurev/AccurevSCM.java"
      ]
    },
    {
      "headline": "Incorrect Authorization",
      "analysis": "The code does not properly implement authorization, which could lead to unauthorized access vulnerabilities. This issue is particularly evident in the AccurevSCM class and its related classes, where the code does not properly restrict access to sensitive operations or resources based on user roles or permissions.\n",
      "classification": "slightly promising",
      "cwe": "CWE-863",
      "function_names": [
        "checkout",
        "compareRemoteRevisionWith"
      ],
      "filenames": [
        "hudson/plugins/accurev/AccurevSCM.java",
        "hudson/plugins/accurev/delegates/AbstractModeDelegate.java"
      ]
    },
    {
      "headline": "Improper Control of Dynamically-Managed Code Resources",
      "analysis": "The code does not properly control dynamically-managed code resources, which could lead to code injection vulnerabilities. This issue is particularly evident in the AccurevSCM class and its related classes, where the code uses dynamic class loading or other mechanisms to execute user-provided code without proper validation or sandboxing.\n",
      "classification": "slightly promising",
      "cwe": "CWE-913",
      "function_names": [
        "getPollingStream",
        "buildEnvVars",
        "buildEnvironment"
      ],
      "filenames": [
        "hudson/plugins/accurev/AccurevSCM.java",
        "hudson/plugins/accurev/delegates/AbstractModeDelegate.java"
      ]
    }
  ],
  "scores": [
    {
      "stats": {
        "fn": 1,
        "tp": 0,
        "fp": 1
      },
      "mapping": {},
      "vuln_dates": {
        "CVE-2018-1999028": "2018-08-01T13:29:00"
      },
      "scoring_model": "claude-3-opus-20240229",
      "type": "llm",
      "instruction_template_hash": "245ace12b6361954d0a2"
    },
    {
      "stats": {
        "fn": 1,
        "tp": 0,
        "fp": 1
      },
      "mapping": {},
      "vuln_dates": {
        "CVE-2018-1999028": "2018-08-01T13:29:00"
      },
      "scoring_model": "claude-3-5-sonnet-20240620",
      "type": "llm",
      "instruction_template_hash": "245ace12b6361954d0a2"
    }
  ],
  "instruction_template_hash": "10c0163db4740318a544",
  "version": "0.1.0"
}
