{
  "commit": "43d89db9c14fa92ce487128817be426deb3a19c4",
  "repo_url": "https://github.com/apollographql/apollo-client",
  "model": "claude-3-5-sonnet-20240620",
  "chunk_hashes": [
    "ef82121b84b28cdd0aad"
  ],
  "responses": [
    {
      "content": "Here's a summary of the security vulnerabilities identified in the codebase:\n\n```yaml\nleads:\n  - headline: Potential for XSS attacks in query string handling\n    analysis: |\n      The code does not appear to properly sanitize or escape query string parameters before using them. This could allow an attacker to inject malicious scripts via the query string that get executed on the client side. The `queryString` variable is used directly in several places without escaping.\n    cwe: CWE-79\n    function_names:\n      - storeKeyNameFromFieldNameAndArgs\n      - createMockFetch  \n    filenames:\n      - src/data/storeUtils.ts\n      - test/mocks/mockFetch.ts\n    classification: slightly promising\n\n  - headline: Potential prototype pollution vulnerability\n    analysis: | \n      The code uses Object.assign() to merge objects in several places without properly checking the source objects. This could allow an attacker to pollute the prototype chain of objects. For example, in src/data/writeToStore.ts, Object.assign is used to merge query results into the store state.\n    cwe: CWE-1321\n    function_names:\n      - writeSelectionSetToStore\n    filenames:\n      - src/data/writeToStore.ts\n    classification: slightly promising\n\n  - headline: Lack of input validation on GraphQL queries\n    analysis: |\n      The code does not appear to validate or sanitize GraphQL queries before executing them. This could allow an attacker to inject malicious queries that access or modify unintended data. The query is passed directly to the network interface in several places.\n    cwe: CWE-20\n    function_names:\n      - query\n      - mutate\n    filenames: \n      - src/core/QueryManager.ts\n    classification: slightly promising\n\n  - headline: Insecure randomness in subscription ID generation\n    analysis: |\n      The subscription ID generation uses a simple incrementing counter (this.subId++). This is predictable and could allow an attacker to guess valid subscription IDs. A cryptographically secure random number generator should be used instead.\n    cwe: CWE-330\n    function_names:\n      - generateSubscriptionId\n    filenames:\n      - test/mocks/mockNetworkInterface.ts  \n    classification: slightly promising\n```\n\nThis analysis identifies some potential security issues, but further investigation would be needed to determine their severity and exploitability in a real application. The codebase appears to be mostly test code and mocks, so some of these issues may not be present in production code. Proper input validation, output encoding, and security best practices should be followed when using this library in a production application.",
      "date": "2024-07-07T20:38:51.868378",
      "usage": {
        "prompt_tokens": 175513,
        "completion_tokens": 626,
        "cost": 0.535929
      }
    }
  ],
  "leads": [
    {
      "headline": "Potential for XSS attacks in query string handling",
      "analysis": "The code does not appear to properly sanitize or escape query string parameters before using them. This could allow an attacker to inject malicious scripts via the query string that get executed on the client side. The queryString variable is used directly in several places without escaping.\n",
      "classification": "slightly promising",
      "cwe": "CWE-79",
      "function_names": [
        "storeKeyNameFromFieldNameAndArgs",
        "createMockFetch"
      ],
      "filenames": [
        "src/data/storeUtils.ts",
        "test/mocks/mockFetch.ts"
      ]
    },
    {
      "headline": "Potential prototype pollution vulnerability",
      "analysis": "The code uses Object.assign() to merge objects in several places without properly checking the source objects. This could allow an attacker to pollute the prototype chain of objects. For example, in src/data/writeToStore.ts, Object.assign is used to merge query results into the store state.\n",
      "classification": "slightly promising",
      "cwe": "CWE-1321",
      "function_names": [
        "writeSelectionSetToStore"
      ],
      "filenames": [
        "src/data/writeToStore.ts"
      ]
    },
    {
      "headline": "Lack of input validation on GraphQL queries",
      "analysis": "The code does not appear to validate or sanitize GraphQL queries before executing them. This could allow an attacker to inject malicious queries that access or modify unintended data. The query is passed directly to the network interface in several places.\n",
      "classification": "slightly promising",
      "cwe": "CWE-20",
      "function_names": [
        "query",
        "mutate"
      ],
      "filenames": [
        "src/core/QueryManager.ts"
      ]
    },
    {
      "headline": "Insecure randomness in subscription ID generation",
      "analysis": "The subscription ID generation uses a simple incrementing counter (this.subId++). This is predictable and could allow an attacker to guess valid subscription IDs. A cryptographically secure random number generator should be used instead.\n",
      "classification": "slightly promising",
      "cwe": "CWE-330",
      "function_names": [
        "generateSubscriptionId"
      ],
      "filenames": [
        "test/mocks/mockNetworkInterface.ts"
      ]
    }
  ],
  "scores": [
    {
      "stats": {
        "fn": 1,
        "tp": 0,
        "fp": 0
      },
      "mapping": {},
      "vuln_dates": {
        "CVE-2024-23841": "2024-01-30T18:15:48"
      },
      "scoring_model": "claude-3-5-sonnet-20240620",
      "type": "llm",
      "instruction_template_hash": "245ace12b6361954d0a2"
    }
  ],
  "instruction_template_hash": "10c0163db4740318a544",
  "version": "0.1.0"
}
