{
  "commit": "24b3fd3309d1057dd87af3a568def0db01dbaade",
  "repo_url": "https://github.com/validatorjs/validator.js",
  "model": "gpt-4o-2024-05-13",
  "chunk_hashes": [
    "7fbab1fa9eef83356392"
  ],
  "responses": [
    {
      "content": "```yaml\nleads:\n  - headline: \"Usage of deprecated 'entry' option in 'rollup' configuration\"\n    analysis: |\n      The 'entry' option in the 'rollup' configuration is deprecated and should be replaced with 'input'. Using deprecated options can lead to compatibility issues with future versions of Rollup and may result in unexpected behavior.\n    cwe: CWE-662\n    function_names: []\n    filenames:\n      - \"build-browser.js\"\n    classification: \"slightly promising\"\n  - headline: \"Potential Path Traversal in 'fs.readFileSync' usage\"\n    analysis: |\n      The usage of `fs.readFileSync` without proper validation of the input path can lead to a Path Traversal vulnerability. An attacker could manipulate the input path, allowing access to unauthorized files on the system.\n    cwe: CWE-22\n    function_names: []\n    filenames:\n      - \"build-browser.js\"\n    classification: \"very promising\"\n  - headline: \"Insecure use of 'process.exit(1)'\"\n    analysis: |\n      Calling `process.exit(1)` on error can lead to process termination without proper cleanup, potentially leading to resource leaks and incomplete transactions. Instead, errors should be handled gracefully.\n    cwe: CWE-404\n    function_names: []\n    filenames:\n      - \"build-browser.js\"\n    classification: \"slightly promising\"\n  - headline: \"Possible Regular Expression Denial of Service (ReDoS) in 'whitelist.js'\"\n    analysis: |\n      The regular expression used in the 'whitelist' function can lead to a denial of service if an attacker provides a specially crafted input that triggers excessive backtracking.\n    cwe: CWE-407\n    function_names:\n      - \"whitelist\"\n    filenames:\n      - \"src/lib/whitelist.js\"\n    classification: \"very promising\"\n  - headline: \"Missing Validation of Regular Expressions in 'matches' function\"\n    analysis: |\n      The 'matches' function directly accepts user-supplied input as a regular expression. This could lead to potential ReDoS attacks if the input is not properly validated.\n    cwe: CWE-400\n    function_names:\n      - \"matches\"\n    filenames:\n      - \"src/lib/matches.js\"\n    classification: \"slightly promising\"\n  - headline: \"Improper Input Validation in 'isBefore' function\"\n    analysis: |\n      The function 'isBefore' does not properly validate the input date string or type. This can lead to incorrect behavior if the input date is not properly formatted.\n    cwe: CWE-20\n    function_names:\n      - \"isBefore\"\n    filenames:\n      - \"src/lib/isBefore.js\"\n    classification: \"slightly promising\"\n  - headline: \"Improper Input Validation in 'isAfter' function\"\n    analysis: |\n      Similar to 'isBefore', the 'isAfter' function does not properly validate the input date string or type, potentially leading to incorrect comparisons.\n    cwe: CWE-20\n    function_names:\n      - \"isAfter\"\n    filenames:\n      - \"src/lib/isAfter.js\"\n    classification: \"slightly promising\"\n  - headline: \"Potential Denial of Service from Inefficient Regex in 'isRgbColor'\"\n    analysis: |\n      The function 'isRgbColor' uses regular expressions that do not properly account for potential edge cases that could lead to excessive backtracking, resulting in Denial of Service.\n    cwe: CWE-407\n    function_names:\n      - \"isRgbColor\"\n    filenames:\n      - \"src/lib/isRgbColor.js\"\n    classification: \"slightly promising\"\n  - headline: \"Improper Error Handling in 'rollup' Promise chain\"\n    analysis: |\n      The promise chain in the 'rollup' configuration catches errors but immediately terminates the process. Proper error handling should include logging and recovery mechanisms.\n    cwe: CWE-755\n    function_names: []\n    filenames:\n      - \"build-browser.js\"\n    classification: \"slightly promising\"\n  - headline: \"Potential Path Traversal vulnerability in 'toDate' function\"\n    analysis: |\n      The 'toDate' function calls `Date.parse` on potentially untrusted input, which could be part of a larger attack involving path traversal or injection.\n    cwe: CWE-22\n    function_names:\n      - \"toDate\"\n    filenames:\n      - \"src/lib/toDate.js\"\n    classification: \"slightly promising\"\n```",
      "date": "2024-06-13T17:25:53.705343",
      "usage": {
        "prompt_tokens": 62174,
        "completion_tokens": 928,
        "cost": 0.32479
      }
    }
  ],
  "leads": [
    {
      "headline": "Usage of deprecated 'entry' option in 'rollup' configuration",
      "analysis": "The 'entry' option in the 'rollup' configuration is deprecated and should be replaced with 'input'. Using deprecated options can lead to compatibility issues with future versions of Rollup and may result in unexpected behavior.\n",
      "classification": "slightly promising",
      "cwe": "CWE-662",
      "function_names": [],
      "filenames": [
        "build-browser.js"
      ]
    },
    {
      "headline": "Potential Path Traversal in 'fs.readFileSync' usage",
      "analysis": "The usage of fs.readFileSync without proper validation of the input path can lead to a Path Traversal vulnerability. An attacker could manipulate the input path, allowing access to unauthorized files on the system.\n",
      "classification": "very promising",
      "cwe": "CWE-22",
      "function_names": [],
      "filenames": [
        "build-browser.js"
      ]
    },
    {
      "headline": "Insecure use of 'process.exit(1)'",
      "analysis": "Calling process.exit(1) on error can lead to process termination without proper cleanup, potentially leading to resource leaks and incomplete transactions. Instead, errors should be handled gracefully.\n",
      "classification": "slightly promising",
      "cwe": "CWE-404",
      "function_names": [],
      "filenames": [
        "build-browser.js"
      ]
    },
    {
      "headline": "Possible Regular Expression Denial of Service (ReDoS) in 'whitelist.js'",
      "analysis": "The regular expression used in the 'whitelist' function can lead to a denial of service if an attacker provides a specially crafted input that triggers excessive backtracking.\n",
      "classification": "very promising",
      "cwe": "CWE-407",
      "function_names": [
        "whitelist"
      ],
      "filenames": [
        "src/lib/whitelist.js"
      ]
    },
    {
      "headline": "Missing Validation of Regular Expressions in 'matches' function",
      "analysis": "The 'matches' function directly accepts user-supplied input as a regular expression. This could lead to potential ReDoS attacks if the input is not properly validated.\n",
      "classification": "slightly promising",
      "cwe": "CWE-400",
      "function_names": [
        "matches"
      ],
      "filenames": [
        "src/lib/matches.js"
      ]
    },
    {
      "headline": "Improper Input Validation in 'isBefore' function",
      "analysis": "The function 'isBefore' does not properly validate the input date string or type. This can lead to incorrect behavior if the input date is not properly formatted.\n",
      "classification": "slightly promising",
      "cwe": "CWE-20",
      "function_names": [
        "isBefore"
      ],
      "filenames": [
        "src/lib/isBefore.js"
      ]
    },
    {
      "headline": "Improper Input Validation in 'isAfter' function",
      "analysis": "Similar to 'isBefore', the 'isAfter' function does not properly validate the input date string or type, potentially leading to incorrect comparisons.\n",
      "classification": "slightly promising",
      "cwe": "CWE-20",
      "function_names": [
        "isAfter"
      ],
      "filenames": [
        "src/lib/isAfter.js"
      ]
    },
    {
      "headline": "Potential Denial of Service from Inefficient Regex in 'isRgbColor'",
      "analysis": "The function 'isRgbColor' uses regular expressions that do not properly account for potential edge cases that could lead to excessive backtracking, resulting in Denial of Service.\n",
      "classification": "slightly promising",
      "cwe": "CWE-407",
      "function_names": [
        "isRgbColor"
      ],
      "filenames": [
        "src/lib/isRgbColor.js"
      ]
    },
    {
      "headline": "Improper Error Handling in 'rollup' Promise chain",
      "analysis": "The promise chain in the 'rollup' configuration catches errors but immediately terminates the process. Proper error handling should include logging and recovery mechanisms.\n",
      "classification": "slightly promising",
      "cwe": "CWE-755",
      "function_names": [],
      "filenames": [
        "build-browser.js"
      ]
    },
    {
      "headline": "Potential Path Traversal vulnerability in 'toDate' function",
      "analysis": "The 'toDate' function calls Date.parse on potentially untrusted input, which could be part of a larger attack involving path traversal or injection.\n",
      "classification": "slightly promising",
      "cwe": "CWE-22",
      "function_names": [
        "toDate"
      ],
      "filenames": [
        "src/lib/toDate.js"
      ]
    }
  ],
  "scores": [
    {
      "stats": {
        "fn": 1,
        "tp": 0,
        "fp": 2
      },
      "mapping": {},
      "vuln_dates": {
        "CVE-2021-3765": "2021-11-02T07:15:07"
      },
      "scoring_model": "claude-3-opus-20240229",
      "type": "llm",
      "instruction_template_hash": "245ace12b6361954d0a2"
    }
  ],
  "instruction_template_hash": "10c0163db4740318a544",
  "version": "0.1.0"
}
