{
  "commit": "0d0ddd43b3b0f0995bfaa34a45f046d47860a234",
  "repo_url": "https://github.com/skyscreamer/nevado",
  "model": "claude-3-5-sonnet-20240620",
  "chunk_hashes": [
    "fcababaa4ada245f9f81"
  ],
  "responses": [
    {
      "content": "```yaml\nleads:\n  - headline: Insufficient input validation in message deserialization\n    analysis: |\n      The deserialization of messages in the deserializeMessage method of AbstractSQSConnector uses SerializeUtil.deserializeFromString without any input validation or type checking. This could allow an attacker to inject malicious serialized objects that get deserialized, potentially leading to remote code execution. The deserialized object is only checked to be an instance of NevadoMessage after deserialization has already occurred.\n    cwe: CWE-502\n    function_names:\n      - deserializeMessage\n    filenames:\n      - nevado-jms/src/main/java/org/skyscreamer/nevado/jms/connector/AbstractSQSConnector.java\n    classification: very promising\n\n  - headline: Insecure random number generation\n    analysis: |\n      The RandomData class uses java.util.Random for generating random data, which is not cryptographically secure. This could lead to predictable \"random\" values being used in security-sensitive contexts. The class is used in multiple places including generating IDs and temporary queue names. A cryptographically secure random number generator like SecureRandom should be used instead.\n    cwe: CWE-330\n    function_names:\n      - readString\n      - readInt  \n    filenames:\n      - nevado-jms/src/main/java/org/skyscreamer/nevado/jms/util/RandomData.java\n    classification: very promising\n\n  - headline: Potential XML external entity (XXE) vulnerability\n    analysis: |\n      The DocumentBuilderFactory used in TextMessageTest is not configured to disable external entity processing. This could allow XXE attacks if the XML parser processes untrusted XML input. While this is in a test file, it demonstrates unsafe XML parsing that could be replicated in production code. The factory should be configured to disable external entity processing.\n    cwe: CWE-611\n    function_names:\n      - testXmlMessage\n    filenames:  \n      - nevado-jms/src/test/java/org/skyscreamer/nevado/jms/message/TextMessageTest.java\n    classification: slightly promising\n\n  - headline: Use of null cipher in SSL configuration\n    analysis: |\n      The AmazonAwsSQSConnector allows configuring SSL to be disabled by setting isSecure to false. This could potentially allow the use of a null cipher, leading to unencrypted communication. While this may be intentional for testing, it should be carefully controlled to prevent accidental use in production environments.\n    cwe: CWE-327\n    function_names:\n      - AmazonAwsSQSConnector\n    filenames:\n      - nevado-jms/src/main/java/org/skyscreamer/nevado/jms/connector/amazonaws/AmazonAwsSQSConnector.java  \n    classification: slightly promising\n\n  - headline: Lack of input validation on queue and topic names\n    analysis: |\n      The createQueue and createTopic methods in AmazonAwsSQSConnector do not perform any input validation on the queue or topic names before creating them. This could potentially allow injection of malicious names if user input is passed directly to these methods. Proper validation and sanitization of queue/topic names should be implemented.\n    cwe: CWE-20\n    function_names: \n      - createQueue\n      - createTopic\n    filenames:\n      - nevado-jms/src/main/java/org/skyscreamer/nevado/jms/connector/amazonaws/AmazonAwsSQSConnector.java\n    classification: slightly promising\n```",
      "date": "2024-07-08T08:36:01.200816",
      "usage": {
        "prompt_tokens": 167401,
        "completion_tokens": 858,
        "cost": 0.515073
      }
    }
  ],
  "leads": [
    {
      "headline": "Insufficient input validation in message deserialization",
      "analysis": "The deserialization of messages in the deserializeMessage method of AbstractSQSConnector uses SerializeUtil.deserializeFromString without any input validation or type checking. This could allow an attacker to inject malicious serialized objects that get deserialized, potentially leading to remote code execution. The deserialized object is only checked to be an instance of NevadoMessage after deserialization has already occurred.\n",
      "classification": "very promising",
      "cwe": "CWE-502",
      "function_names": [
        "deserializeMessage"
      ],
      "filenames": [
        "nevado-jms/src/main/java/org/skyscreamer/nevado/jms/connector/AbstractSQSConnector.java"
      ]
    },
    {
      "headline": "Insecure random number generation",
      "analysis": "The RandomData class uses java.util.Random for generating random data, which is not cryptographically secure. This could lead to predictable \"random\" values being used in security-sensitive contexts. The class is used in multiple places including generating IDs and temporary queue names. A cryptographically secure random number generator like SecureRandom should be used instead.\n",
      "classification": "very promising",
      "cwe": "CWE-330",
      "function_names": [
        "readString",
        "readInt"
      ],
      "filenames": [
        "nevado-jms/src/main/java/org/skyscreamer/nevado/jms/util/RandomData.java"
      ]
    },
    {
      "headline": "Potential XML external entity (XXE) vulnerability",
      "analysis": "The DocumentBuilderFactory used in TextMessageTest is not configured to disable external entity processing. This could allow XXE attacks if the XML parser processes untrusted XML input. While this is in a test file, it demonstrates unsafe XML parsing that could be replicated in production code. The factory should be configured to disable external entity processing.\n",
      "classification": "slightly promising",
      "cwe": "CWE-611",
      "function_names": [
        "testXmlMessage"
      ],
      "filenames": [
        "nevado-jms/src/test/java/org/skyscreamer/nevado/jms/message/TextMessageTest.java"
      ]
    },
    {
      "headline": "Use of null cipher in SSL configuration",
      "analysis": "The AmazonAwsSQSConnector allows configuring SSL to be disabled by setting isSecure to false. This could potentially allow the use of a null cipher, leading to unencrypted communication. While this may be intentional for testing, it should be carefully controlled to prevent accidental use in production environments.\n",
      "classification": "slightly promising",
      "cwe": "CWE-327",
      "function_names": [
        "AmazonAwsSQSConnector"
      ],
      "filenames": [
        "nevado-jms/src/main/java/org/skyscreamer/nevado/jms/connector/amazonaws/AmazonAwsSQSConnector.java"
      ]
    },
    {
      "headline": "Lack of input validation on queue and topic names",
      "analysis": "The createQueue and createTopic methods in AmazonAwsSQSConnector do not perform any input validation on the queue or topic names before creating them. This could potentially allow injection of malicious names if user input is passed directly to these methods. Proper validation and sanitization of queue/topic names should be implemented.\n",
      "classification": "slightly promising",
      "cwe": "CWE-20",
      "function_names": [
        "createQueue",
        "createTopic"
      ],
      "filenames": [
        "nevado-jms/src/main/java/org/skyscreamer/nevado/jms/connector/amazonaws/AmazonAwsSQSConnector.java"
      ]
    }
  ],
  "scores": [
    {
      "stats": {
        "fn": 0,
        "tp": 1,
        "fp": 1
      },
      "mapping": {
        "0": "CVE-2023-31826"
      },
      "vuln_dates": {
        "CVE-2023-31826": "2023-05-23T01:15:10"
      },
      "scoring_model": "claude-3-5-sonnet-20240620",
      "type": "llm",
      "instruction_template_hash": "245ace12b6361954d0a2"
    }
  ],
  "instruction_template_hash": "10c0163db4740318a544",
  "version": "0.1.0"
}
