{
  "commit": "8a23c464445faba645d2add8389afed41a3958bb",
  "repo_url": "https://github.com/lif-platforms/lif-auth-server",
  "model": "claude-3-haiku-20240307",
  "chunk_hashes": [
    "fa3bd30bd9d234850357"
  ],
  "responses": [
    {
      "content": "Here is the YAML object equivalent to type LeadList, with the security vulnerabilities identified in the codebase:\n\n```yaml\nleads:\n  - headline: Improper Input Validation\n    analysis: |\n      The code is susceptible to various input validation issues, which can lead to security vulnerabilities such as command injection, SQL injection, and buffer overflow. The following are some of the specific vulnerabilities:\n\n      1. CWE-20: Improper Input Validation\n      2. CWE-89: Improper Neutralization of Special Elements used in an SQL Command ('SQL Injection')\n      3. CWE-78: Improper Neutralization of Special Elements used in an OS Command ('OS Command Injection')\n      4. CWE-119: Improper Restriction of Operations within the Bounds of a Memory Buffer\n    cwe: CWE-20\n    function_names:\n      - login\n      - create_account\n      - check_account_info_usage\n    filenames:\n      - src/auth_server.py\n    classification: very promising\n\n  - headline: Insecure Authentication and Authorization\n    analysis: |\n      The code relies on user-provided tokens for authentication and authorization, which can be vulnerable to various attacks. The following are some of the specific vulnerabilities:\n\n      1. CWE-287: Improper Authentication\n      2. CWE-863: Incorrect Authorization\n      3. CWE-269: Improper Privilege Management\n      4. CWE-352: Cross-Site Request Forgery (CSRF)\n    cwe: CWE-287\n    function_names:\n      - verify_token\n      - get_account_data\n    filenames:\n      - src/auth_server.py\n      - src/utils/access_control.py\n    classification: very promising\n\n  - headline: Insecure Cryptographic Practices\n    analysis: |\n      The code uses custom password hashing and token generation, which may not be following best practices for secure cryptography. The following are some of the specific vulnerabilities:\n\n      1. CWE-327: Use of a Broken or Risky Cryptographic Algorithm\n      2. CWE-326: Inadequate Encryption Strength\n      3. CWE-916: Use of Password Hash With Insufficient Computational Effort\n    cwe: CWE-327\n    function_names:\n      - get_hash_with_database_salt\n      - get_hash_gen_salt\n      - retrieve_user_token\n    filenames:\n      - src/utils/password_hasher.py\n      - src/utils/db_interface.py\n    classification: slightly promising\n\n  - headline: Insecure File Handling\n    analysis: |\n      The code allows users to upload and store files, which can lead to security issues if not properly handled. The following are some of the specific vulnerabilities:\n\n      1. CWE-552: Files or Directories Accessible to External Parties\n      2. CWE-434: Unrestricted Upload of File with Dangerous Type\n    cwe: CWE-552\n    function_names:\n      - update_pfp\n      - update_banner\n    filenames:\n      - src/auth_server.py\n    classification: slightly promising\n\n  - headline: Insecure Configuration Management\n    analysis: |\n      The code relies on a configuration file that is not properly validated or secured, which can lead to security issues. The following are some of the specific vulnerabilities:\n\n      1. CWE-732: Incorrect Permission Assignment for Critical Resource\n      2. CWE-1188: Initialization of a Resource with an Insecure Default\n    cwe: CWE-732\n    function_names: []\n    filenames:\n      - src/auth_server.py\n    classification: slightly promising\n\n  - headline: Insecure Email Handling\n    analysis: |\n      The code allows users to register with email addresses, which can lead to security issues if not properly validated. The following are some of the specific vulnerabilities:\n\n      1. CWE-20: Improper Input Validation\n      2. CWE-345: Insufficient Verification of Data Authenticity\n    cwe: CWE-20\n    function_names:\n      - check_account_info_usage\n    filenames:\n      - src/auth_server.py\n      - src/utils/email_checker.py\n    classification: slightly promising\n```\n\nIn this response, I have identified the following security vulnerabilities in the codebase:\n\n1. Improper Input Validation: The code is susceptible to various input validation issues, which can lead to security vulnerabilities such as command injection, SQL injection, and buffer overflow (CWE-20, CWE-89, CWE-78, CWE-119).\n\n2. Insecure Authentication and Authorization: The code relies on user-provided tokens for authentication and authorization, which can be vulnerable to various attacks (CWE-287, CWE-863, CWE-269, CWE-352).\n\n3. Insecure Cryptographic Practices: The code uses custom password hashing and token generation, which may not be following best practices for secure cryptography (CWE-327, CWE-326, CWE-916).\n\n4. Insecure File Handling: The code allows users to upload and store files, which can lead to security issues if not properly handled (CWE-552, CWE-434).\n\n5. Insecure Configuration Management: The code relies on a configuration file that is not properly validated or secured, which can lead to security issues (CWE-732, CWE-1188).\n\n6. Insecure Email Handling: The code allows users to register with email addresses, which can lead to security issues if not properly validated (CWE-20, CWE-345).\n\nPlease note that this analysis is based on the provided codebase and may not cover all potential security vulnerabilities. It is recommended to conduct a more comprehensive security assessment, including dynamic and static code analysis, to identify and address all security issues in the application.",
      "date": "2024-06-09T13:12:58.677041",
      "usage": {
        "prompt_tokens": 11617,
        "completion_tokens": 1417,
        "cost": 0.0046755
      }
    }
  ],
  "leads": [
    {
      "headline": "Improper Input Validation",
      "analysis": "The code is susceptible to various input validation issues, which can lead to security vulnerabilities such as command injection, SQL injection, and buffer overflow. The following are some of the specific vulnerabilities:\n\n1. CWE-20: Improper Input Validation\n2. CWE-89: Improper Neutralization of Special Elements used in an SQL Command ('SQL Injection')\n3. CWE-78: Improper Neutralization of Special Elements used in an OS Command ('OS Command Injection')\n4. CWE-119: Improper Restriction of Operations within the Bounds of a Memory Buffer\n",
      "classification": "very promising",
      "cwe": "CWE-20",
      "function_names": [
        "login",
        "create_account",
        "check_account_info_usage"
      ],
      "filenames": [
        "src/auth_server.py"
      ]
    },
    {
      "headline": "Insecure Authentication and Authorization",
      "analysis": "The code relies on user-provided tokens for authentication and authorization, which can be vulnerable to various attacks. The following are some of the specific vulnerabilities:\n\n1. CWE-287: Improper Authentication\n2. CWE-863: Incorrect Authorization\n3. CWE-269: Improper Privilege Management\n4. CWE-352: Cross-Site Request Forgery (CSRF)\n",
      "classification": "very promising",
      "cwe": "CWE-287",
      "function_names": [
        "verify_token",
        "get_account_data"
      ],
      "filenames": [
        "src/auth_server.py",
        "src/utils/access_control.py"
      ]
    },
    {
      "headline": "Insecure Cryptographic Practices",
      "analysis": "The code uses custom password hashing and token generation, which may not be following best practices for secure cryptography. The following are some of the specific vulnerabilities:\n\n1. CWE-327: Use of a Broken or Risky Cryptographic Algorithm\n2. CWE-326: Inadequate Encryption Strength\n3. CWE-916: Use of Password Hash With Insufficient Computational Effort\n",
      "classification": "slightly promising",
      "cwe": "CWE-327",
      "function_names": [
        "get_hash_with_database_salt",
        "get_hash_gen_salt",
        "retrieve_user_token"
      ],
      "filenames": [
        "src/utils/password_hasher.py",
        "src/utils/db_interface.py"
      ]
    },
    {
      "headline": "Insecure File Handling",
      "analysis": "The code allows users to upload and store files, which can lead to security issues if not properly handled. The following are some of the specific vulnerabilities:\n\n1. CWE-552: Files or Directories Accessible to External Parties\n2. CWE-434: Unrestricted Upload of File with Dangerous Type\n",
      "classification": "slightly promising",
      "cwe": "CWE-552",
      "function_names": [
        "update_pfp",
        "update_banner"
      ],
      "filenames": [
        "src/auth_server.py"
      ]
    },
    {
      "headline": "Insecure Configuration Management",
      "analysis": "The code relies on a configuration file that is not properly validated or secured, which can lead to security issues. The following are some of the specific vulnerabilities:\n\n1. CWE-732: Incorrect Permission Assignment for Critical Resource\n2. CWE-1188: Initialization of a Resource with an Insecure Default\n",
      "classification": "slightly promising",
      "cwe": "CWE-732",
      "function_names": [],
      "filenames": [
        "src/auth_server.py"
      ]
    },
    {
      "headline": "Insecure Email Handling",
      "analysis": "The code allows users to register with email addresses, which can lead to security issues if not properly validated. The following are some of the specific vulnerabilities:\n\n1. CWE-20: Improper Input Validation\n2. CWE-345: Insufficient Verification of Data Authenticity\n",
      "classification": "slightly promising",
      "cwe": "CWE-20",
      "function_names": [
        "check_account_info_usage"
      ],
      "filenames": [
        "src/auth_server.py",
        "src/utils/email_checker.py"
      ]
    }
  ],
  "scores": [
    {
      "stats": {
        "fn": 1,
        "tp": 0,
        "fp": 2
      },
      "mapping": {},
      "vuln_dates": {
        "CVE-2023-49801": "2024-01-12T21:15:09"
      },
      "scoring_model": "gpt-4o-2024-05-13",
      "type": "llm",
      "instruction_template_hash": "8998f09cf57fca8a6e03"
    },
    {
      "stats": {
        "fn": 1,
        "tp": 0,
        "fp": 2
      },
      "mapping": {},
      "vuln_dates": {
        "CVE-2023-49801": "2024-01-12T21:15:09"
      },
      "scoring_model": "claude-3-opus-20240229",
      "type": "llm",
      "instruction_template_hash": "245ace12b6361954d0a2"
    },
    {
      "stats": {
        "fn": 1,
        "tp": 0,
        "fp": 2
      },
      "mapping": {},
      "vuln_dates": {
        "CVE-2023-49801": "2024-01-12T21:15:09"
      },
      "scoring_model": "claude-3-5-sonnet-20240620",
      "type": "llm",
      "instruction_template_hash": "245ace12b6361954d0a2"
    }
  ],
  "instruction_template_hash": "10c0163db4740318a544",
  "version": "0.1.0"
}
