{
  "commit": "177ab3715b3c1070432258f91886373acb3ca2de",
  "repo_url": "https://github.com/ssshooter/mind-elixir-core",
  "model": "gpt-4-turbo-2024-04-09",
  "chunk_hashes": [
    "8af17bf551d116405d76"
  ],
  "responses": [
    {
      "content": "```yaml\nleads:\n  - headline: \"Exposure of Sensitive Information to an Unauthorized Actor\"\n    analysis: |\n      The 'jest.config.js' file specifies the directory for code coverage data using absolute paths which could expose sensitive information regarding device file structure through error messages or other outputs. This potentially allows an attacker to gain insight into the server's file system structure which can be used to orchestrate further attacks.\n    cwe: CWE-532\n    function_names: []\n    filenames:\n      - \"/jest.config.js\"\n    classification: \"very promising\"\n\n  - headline: \"Failure to Handle Leading Special Element on Command Line Argument\"\n    analysis: |\n      The webpack configuration file 'webpack.config.js' does not properly handle leading special elements, allowing for argument injection. If untrusted input is used to construct webpack commands, it may lead to code execution, exposure of sensitive data, or server compromise.\n    cwe: CWE-88\n    function_names: []\n    filenames:\n      - \"/webpack.config.js\"\n    classification: \"very promising\"\n\n  - headline: \"Improper Handling of Exceptional Conditions\"\n    analysis: |\n      Within the 'src/linkOperation.js', there is a failure to handle conditions if the links or nodes provided are null, specifically in the functions 'createLink', 'selectLink', and 'removeLink'. This may lead to uncaught exceptions which could crash the application or lead to denial of service.\n    cwe: CWE-755\n    function_names:\n      - \"createLink\"\n      - \"selectLink\"\n      - \"removeLink\"\n    filenames:\n      - \"/src/linkOperation.js\"\n    classification: \"slightly promising\"\n\n  - headline: \"Cross-Site Scripting through SVG Content\"\n    analysis: |\n      In 'src/linkDiv.js', SVG elements are dynamically created based on node properties without proper sanitization, potentially leading to Cross-Site Scripting (XSS) if a user input is used to generate the map. For instance, if unescaped user input ends up within SVG tags without validation, it can lead to execution of malicious scripts.\n    cwe: CWE-79\n    function_names:\n      - \"linkDiv\"\n    filenames:\n      - \"/src/linkDiv.js\"\n    classification: \"very promising\"\n\n  - headline: \"Command Injection via svg-to-png Conversion Function\"\n    analysis: |\n      'painter/index.js' uses user input directly in constructing a shell command for converting SVG to PNG. If the file name for saving the generated image is not correctly validated or sanitized, this can lead to command injection vulnerabilities, where arbitrary commands could be injected and run by a malicious user.\n    cwe: CWE-77\n    function_names:\n      - \"exportSvg\"\n      - \"exportPng\"\n    filenames:\n      - \"/painter/index.js\"\n    classification: \"very promising\"\n```",
      "date": "2024-06-13T12:00:50.639706",
      "usage": {
        "prompt_tokens": 81157,
        "completion_tokens": 587,
        "cost": 0.82918
      }
    }
  ],
  "leads": [
    {
      "headline": "Exposure of Sensitive Information to an Unauthorized Actor",
      "analysis": "The 'jest.config.js' file specifies the directory for code coverage data using absolute paths which could expose sensitive information regarding device file structure through error messages or other outputs. This potentially allows an attacker to gain insight into the server's file system structure which can be used to orchestrate further attacks.\n",
      "classification": "very promising",
      "cwe": "CWE-532",
      "function_names": [],
      "filenames": [
        "/jest.config.js"
      ]
    },
    {
      "headline": "Failure to Handle Leading Special Element on Command Line Argument",
      "analysis": "The webpack configuration file 'webpack.config.js' does not properly handle leading special elements, allowing for argument injection. If untrusted input is used to construct webpack commands, it may lead to code execution, exposure of sensitive data, or server compromise.\n",
      "classification": "very promising",
      "cwe": "CWE-88",
      "function_names": [],
      "filenames": [
        "/webpack.config.js"
      ]
    },
    {
      "headline": "Improper Handling of Exceptional Conditions",
      "analysis": "Within the 'src/linkOperation.js', there is a failure to handle conditions if the links or nodes provided are null, specifically in the functions 'createLink', 'selectLink', and 'removeLink'. This may lead to uncaught exceptions which could crash the application or lead to denial of service.\n",
      "classification": "slightly promising",
      "cwe": "CWE-755",
      "function_names": [
        "createLink",
        "selectLink",
        "removeLink"
      ],
      "filenames": [
        "/src/linkOperation.js"
      ]
    },
    {
      "headline": "Cross-Site Scripting through SVG Content",
      "analysis": "In 'src/linkDiv.js', SVG elements are dynamically created based on node properties without proper sanitization, potentially leading to Cross-Site Scripting (XSS) if a user input is used to generate the map. For instance, if unescaped user input ends up within SVG tags without validation, it can lead to execution of malicious scripts.\n",
      "classification": "very promising",
      "cwe": "CWE-79",
      "function_names": [
        "linkDiv"
      ],
      "filenames": [
        "/src/linkDiv.js"
      ]
    },
    {
      "headline": "Command Injection via svg-to-png Conversion Function",
      "analysis": "'painter/index.js' uses user input directly in constructing a shell command for converting SVG to PNG. If the file name for saving the generated image is not correctly validated or sanitized, this can lead to command injection vulnerabilities, where arbitrary commands could be injected and run by a malicious user.\n",
      "classification": "very promising",
      "cwe": "CWE-77",
      "function_names": [
        "exportSvg",
        "exportPng"
      ],
      "filenames": [
        "/painter/index.js"
      ]
    }
  ],
  "scores": [
    {
      "stats": {
        "fn": 0,
        "tp": 1,
        "fp": 3
      },
      "mapping": {
        "2": "CVE-2021-32851"
      },
      "vuln_dates": {
        "CVE-2021-32851": "2023-02-20T22:15:11"
      },
      "scoring_model": "claude-3-opus-20240229",
      "type": "llm",
      "instruction_template_hash": "245ace12b6361954d0a2"
    }
  ],
  "instruction_template_hash": "10c0163db4740318a544",
  "version": "0.1.0"
}
