{
  "commit": "1320ffa342f916b8d5e6bffab19f7d98979cde03",
  "repo_url": "https://github.com/bonitasoft/bonita-connector-webservice",
  "model": "claude-3-haiku-20240307",
  "chunk_hashes": [
    "15193ac23bdae5125d29"
  ],
  "responses": [
    {
      "content": "Here is the YAML output identifying the security vulnerabilities in the codebase:\n\n```yaml\nleads:\n  - headline: Improper Neutralization of Special Elements used in an OS Command ('OS Command Injection')\n    analysis: |\n      The codebase contains a vulnerability that allows for OS command injection. Specifically, the `execute()` method in the `SecureWSConnector` class takes a `String` parameter `request` that is passed to the `Dispatch` object without any sanitization. An attacker could potentially inject malicious OS commands into this parameter, allowing them to execute arbitrary code on the server.\n    cwe: CWE-78\n    function_names:\n      - execute\n    filenames:\n      - src/main/java/org/bonitasoft/connectors/ws/SecureWSConnector.java\n    classification: very promising\n\n  - headline: Improper Neutralization of Input During Web Page Generation ('Cross-site Scripting')\n    analysis: |\n      The codebase contains a vulnerability that allows for cross-site scripting (XSS) attacks. The `printRequestAndResponse()` method in the `SecureWSConnector` class directly prints the `sourceResponse`, `responseDocumentEnvelope`, and `responseDocumentBody` objects to the log without any input sanitization. An attacker could potentially inject malicious HTML or JavaScript into these values, allowing them to execute scripts in the context of the application's users.\n    cwe: CWE-79\n    function_names:\n      - printRequestAndResponse\n    filenames:\n      - src/main/java/org/bonitasoft/connectors/ws/SecureWSConnector.java\n    classification: very promising\n\n  - headline: Uncontrolled Resource Consumption\n    analysis: |\n      The codebase contains a vulnerability that allows for denial-of-service attacks through uncontrolled resource consumption. The `HelloTimeoutImpl` class contains a `sayHi()` method that sleeps for a duration specified by the input parameter. An attacker could send requests with large values for this parameter, causing the server to become unresponsive as it waits for the requests to complete.\n    cwe: CWE-400\n    function_names:\n      - sayHi\n    filenames:\n      - src/test/java/org/bonitasoft/connectors/ws/helloTimeout/HelloTimeoutImpl.java\n    classification: very promising\n\n  - headline: Improper Neutralization of Special Elements used in an SQL Command ('SQL Injection')\n    analysis: |\n      The codebase contains a vulnerability that allows for SQL injection attacks. The `ManageCustomerOrderInternalImpl` class contains an `executeStep()` method that takes input parameters without sanitization. An attacker could potentially inject malicious SQL queries into these parameters, allowing them to access or modify sensitive data in the database.\n    cwe: CWE-89\n    function_names:\n      - executeStep\n    filenames:\n      - src/test/java/org/bonitasoft/connectors/ws/customer/ManageCustomerOrderInternalImpl.java\n    classification: very promising\n\n  - headline: Improper Handling of Exceptional Conditions\n    analysis: |\n      The codebase contains a vulnerability that allows for exceptions to be improperly handled. The `SecureWSConnector` class catches a generic `Exception` in the `executeBusinessLogic()` method and simply throws a `ConnectorException` with the original exception. This can lead to information disclosure and unexpected behavior, as the original exception may contain sensitive information or cause unintended side effects.\n    cwe: CWE-755\n    function_names:\n      - executeBusinessLogic\n    filenames:\n      - src/main/java/org/bonitasoft/connectors/ws/SecureWSConnector.java\n    classification: slightly promising\n\n  - headline: Improper Initialization\n    analysis: |\n      The codebase contains a vulnerability related to improper initialization. The `SecureWSConnector` class initializes the `transformer` field in the `getTransformer()` method, but this method is not thread-safe. If multiple threads access this method concurrently, it could lead to race conditions and unexpected behavior.\n    cwe: CWE-665\n    function_names:\n      - getTransformer\n    filenames:\n      - src/main/java/org/bonitasoft/connectors/ws/SecureWSConnector.java\n    classification: slightly promising\n```",
      "date": "2024-06-12T15:16:35.777333",
      "usage": {
        "prompt_tokens": 17601,
        "completion_tokens": 1044,
        "cost": 0.00570525
      }
    }
  ],
  "leads": [
    {
      "headline": "Improper Neutralization of Special Elements used in an OS Command ('OS Command Injection')",
      "analysis": "The codebase contains a vulnerability that allows for OS command injection. Specifically, the execute() method in the SecureWSConnector class takes a String parameter request that is passed to the Dispatch object without any sanitization. An attacker could potentially inject malicious OS commands into this parameter, allowing them to execute arbitrary code on the server.\n",
      "classification": "very promising",
      "cwe": "CWE-78",
      "function_names": [
        "execute"
      ],
      "filenames": [
        "src/main/java/org/bonitasoft/connectors/ws/SecureWSConnector.java"
      ]
    },
    {
      "headline": "Improper Neutralization of Input During Web Page Generation ('Cross-site Scripting')",
      "analysis": "The codebase contains a vulnerability that allows for cross-site scripting (XSS) attacks. The printRequestAndResponse() method in the SecureWSConnector class directly prints the sourceResponse, responseDocumentEnvelope, and responseDocumentBody objects to the log without any input sanitization. An attacker could potentially inject malicious HTML or JavaScript into these values, allowing them to execute scripts in the context of the application's users.\n",
      "classification": "very promising",
      "cwe": "CWE-79",
      "function_names": [
        "printRequestAndResponse"
      ],
      "filenames": [
        "src/main/java/org/bonitasoft/connectors/ws/SecureWSConnector.java"
      ]
    },
    {
      "headline": "Uncontrolled Resource Consumption",
      "analysis": "The codebase contains a vulnerability that allows for denial-of-service attacks through uncontrolled resource consumption. The HelloTimeoutImpl class contains a sayHi() method that sleeps for a duration specified by the input parameter. An attacker could send requests with large values for this parameter, causing the server to become unresponsive as it waits for the requests to complete.\n",
      "classification": "very promising",
      "cwe": "CWE-400",
      "function_names": [
        "sayHi"
      ],
      "filenames": [
        "src/test/java/org/bonitasoft/connectors/ws/helloTimeout/HelloTimeoutImpl.java"
      ]
    },
    {
      "headline": "Improper Neutralization of Special Elements used in an SQL Command ('SQL Injection')",
      "analysis": "The codebase contains a vulnerability that allows for SQL injection attacks. The ManageCustomerOrderInternalImpl class contains an executeStep() method that takes input parameters without sanitization. An attacker could potentially inject malicious SQL queries into these parameters, allowing them to access or modify sensitive data in the database.\n",
      "classification": "very promising",
      "cwe": "CWE-89",
      "function_names": [
        "executeStep"
      ],
      "filenames": [
        "src/test/java/org/bonitasoft/connectors/ws/customer/ManageCustomerOrderInternalImpl.java"
      ]
    },
    {
      "headline": "Improper Handling of Exceptional Conditions",
      "analysis": "The codebase contains a vulnerability that allows for exceptions to be improperly handled. The SecureWSConnector class catches a generic Exception in the executeBusinessLogic() method and simply throws a ConnectorException with the original exception. This can lead to information disclosure and unexpected behavior, as the original exception may contain sensitive information or cause unintended side effects.\n",
      "classification": "slightly promising",
      "cwe": "CWE-755",
      "function_names": [
        "executeBusinessLogic"
      ],
      "filenames": [
        "src/main/java/org/bonitasoft/connectors/ws/SecureWSConnector.java"
      ]
    },
    {
      "headline": "Improper Initialization",
      "analysis": "The codebase contains a vulnerability related to improper initialization. The SecureWSConnector class initializes the transformer field in the getTransformer() method, but this method is not thread-safe. If multiple threads access this method concurrently, it could lead to race conditions and unexpected behavior.\n",
      "classification": "slightly promising",
      "cwe": "CWE-665",
      "function_names": [
        "getTransformer"
      ],
      "filenames": [
        "src/main/java/org/bonitasoft/connectors/ws/SecureWSConnector.java"
      ]
    }
  ],
  "scores": [
    {
      "stats": {
        "fn": 1,
        "tp": 0,
        "fp": 4
      },
      "mapping": {},
      "vuln_dates": {
        "CVE-2020-36640": "2023-01-05T10:15:09"
      },
      "scoring_model": "claude-3-opus-20240229",
      "type": "llm",
      "instruction_template_hash": "245ace12b6361954d0a2"
    }
  ],
  "instruction_template_hash": "10c0163db4740318a544",
  "version": "0.1.0"
}
