{
  "commit": "cee39e90449c34602e2ba70a845af9a913dce20f",
  "repo_url": "https://github.com/xuxueli/xxl-rpc",
  "model": "claude-3-5-sonnet-20240620",
  "chunk_hashes": [
    "9927c4e2bdf55e034899"
  ],
  "responses": [
    {
      "content": "Here are the main security vulnerabilities I identified in the codebase:\n\n```yaml\nleads:\n  - headline: Lack of input validation and sanitization\n    analysis: |\n      The code does not perform sufficient input validation or sanitization in many places. For example, in XxlRpcServerHandler.java, request parameters are passed directly to service methods without any validation. This could allow injection attacks if malicious input is provided. Similar issues exist throughout the codebase where external input is used without proper checking.\n    cwe: CWE-20\n    function_names:\n      - invokeService\n      - sayHi  \n    filenames:\n      - XxlRpcServerHandler.java\n      - DemoServiceImpl.java\n    classification: very promising\n\n  - headline: Hardcoded credentials\n    analysis: |\n      The code contains hardcoded credentials and sensitive information in multiple places. For example, in XxlRpcInvokerConfig.java there are hardcoded admin addresses and environment names. In XxlRpcProviderConfig.java there are also hardcoded config values. Hardcoding sensitive data like this is a security risk as it could be extracted from the compiled application.\n    cwe: CWE-798\n    function_names:\n      - xxlJobExecutor\n      - xxlRpcSpringProviderFactory\n    filenames:  \n      - XxlRpcInvokerConfig.java\n      - XxlRpcProviderConfig.java\n    classification: very promising\n\n  - headline: Lack of encryption for sensitive data\n    analysis: |\n      The codebase does not appear to use encryption when transmitting or storing sensitive data. For example, the XxlRpcRequest and XxlRpcResponse objects are serialized and sent over the network without encryption. This could allow sensitive information to be intercepted. Implementing transport layer security (TLS) and encrypting sensitive data at rest would improve security.\n    cwe: CWE-311\n    function_names:\n      - serialize\n      - deserialize\n    filenames:\n      - XxlRpcRequest.java  \n      - XxlRpcResponse.java\n    classification: very promising\n\n  - headline: Use of outdated/vulnerable dependencies  \n    analysis: |\n      The project uses some outdated dependencies that may contain vulnerabilities. For example, it uses an old version of Netty (4.1.48.Final) which has known security issues. Upgrading to the latest versions of dependencies, especially security-critical ones like Netty, would help mitigate potential vulnerabilities.\n    cwe: CWE-1104\n    function_names: []\n    filenames:\n      - pom.xml\n    classification: slightly promising\n\n  - headline: Lack of proper error handling\n    analysis: |\n      Error handling in parts of the code is insufficient. For example, in XxlRpcServerHandler exceptions are caught and logged, but not always handled properly. This could lead to information exposure through error messages or leave the application in an inconsistent state. Implementing proper error handling and avoiding exposure of sensitive details in error messages would improve security.\n    cwe: CWE-755\n    function_names:\n      - exceptionCaught\n    filenames:\n      - XxlRpcServerHandler.java\n    classification: slightly promising\n```\n\nLet me know if you would like me to elaborate on any of these vulnerabilities or identify additional security issues in the codebase.",
      "date": "2024-07-08T05:24:34.323426",
      "usage": {
        "prompt_tokens": 172955,
        "completion_tokens": 792,
        "cost": 0.530745
      }
    }
  ],
  "leads": [
    {
      "headline": "Lack of input validation and sanitization",
      "analysis": "The code does not perform sufficient input validation or sanitization in many places. For example, in XxlRpcServerHandler.java, request parameters are passed directly to service methods without any validation. This could allow injection attacks if malicious input is provided. Similar issues exist throughout the codebase where external input is used without proper checking.\n",
      "classification": "very promising",
      "cwe": "CWE-20",
      "function_names": [
        "invokeService",
        "sayHi"
      ],
      "filenames": [
        "XxlRpcServerHandler.java",
        "DemoServiceImpl.java"
      ]
    },
    {
      "headline": "Hardcoded credentials",
      "analysis": "The code contains hardcoded credentials and sensitive information in multiple places. For example, in XxlRpcInvokerConfig.java there are hardcoded admin addresses and environment names. In XxlRpcProviderConfig.java there are also hardcoded config values. Hardcoding sensitive data like this is a security risk as it could be extracted from the compiled application.\n",
      "classification": "very promising",
      "cwe": "CWE-798",
      "function_names": [
        "xxlJobExecutor",
        "xxlRpcSpringProviderFactory"
      ],
      "filenames": [
        "XxlRpcInvokerConfig.java",
        "XxlRpcProviderConfig.java"
      ]
    },
    {
      "headline": "Lack of encryption for sensitive data",
      "analysis": "The codebase does not appear to use encryption when transmitting or storing sensitive data. For example, the XxlRpcRequest and XxlRpcResponse objects are serialized and sent over the network without encryption. This could allow sensitive information to be intercepted. Implementing transport layer security (TLS) and encrypting sensitive data at rest would improve security.\n",
      "classification": "very promising",
      "cwe": "CWE-311",
      "function_names": [
        "serialize",
        "deserialize"
      ],
      "filenames": [
        "XxlRpcRequest.java",
        "XxlRpcResponse.java"
      ]
    },
    {
      "headline": "Use of outdated/vulnerable dependencies",
      "analysis": "The project uses some outdated dependencies that may contain vulnerabilities. For example, it uses an old version of Netty (4.1.48.Final) which has known security issues. Upgrading to the latest versions of dependencies, especially security-critical ones like Netty, would help mitigate potential vulnerabilities.\n",
      "classification": "slightly promising",
      "cwe": "CWE-1104",
      "function_names": [],
      "filenames": [
        "pom.xml"
      ]
    },
    {
      "headline": "Lack of proper error handling",
      "analysis": "Error handling in parts of the code is insufficient. For example, in XxlRpcServerHandler exceptions are caught and logged, but not always handled properly. This could lead to information exposure through error messages or leave the application in an inconsistent state. Implementing proper error handling and avoiding exposure of sensitive details in error messages would improve security.\n",
      "classification": "slightly promising",
      "cwe": "CWE-755",
      "function_names": [
        "exceptionCaught"
      ],
      "filenames": [
        "XxlRpcServerHandler.java"
      ]
    }
  ],
  "scores": [
    {
      "stats": {
        "fn": 2,
        "tp": 0,
        "fp": 3
      },
      "mapping": {},
      "vuln_dates": {
        "CVE-2023-45146": "2023-10-18T22:15:09",
        "CVE-2023-33496": "2023-06-07T21:15:13"
      },
      "scoring_model": "claude-3-5-sonnet-20240620",
      "type": "llm",
      "instruction_template_hash": "245ace12b6361954d0a2"
    }
  ],
  "instruction_template_hash": "10c0163db4740318a544",
  "version": "0.1.0"
}
