{
  "commit": "493ff934c1ef3f9164f500e2c25da94f9fc6e492",
  "repo_url": "https://github.com/jenkinsci/mongodb-plugin",
  "model": "gpt-4o-2024-05-13",
  "chunk_hashes": [
    "e0cc3104d44024e87e4b"
  ],
  "responses": [
    {
      "content": "```yaml\nleads:\n  - headline: \"Unrestricted Change of System Port\"\n    analysis: |\n      The MongoBuildWrapper class allows the user to specify the MongoDB port number through the \"port\" parameter, which is directly included in command-line arguments. While this alone isn't inherently insecure, combined with insufficient validation, it might be possible to supply destructive command-line arguments. Attackers could exploit this to change the service port to a system or reserved port, leading to denial-of-service attacks or other unintended behaviors.\n    cwe: CWE-77\n    function_names:\n      - isPortNumber\n      - setupCmd\n    filenames:\n      - src/main/java/org/jenkinsci/plugins/mongodb/MongoBuildWrapper.java\n      - src/main/java/org/jenkinsci/plugins/mongodb/MongoDBInstallation.java\n    classification: very promising\n\n  - headline: \"Use of Hardcoded Port in Connection\"\n    analysis: |\n      In the `WaitForStartCommand` class inside MongoBuildWrapper.java, the default port is hardcoded to \"27017\" if the `port` parameter is empty. This hardcoded value could be problematic in environments where the MongoDB service is configured to run on a different port, potentially leading to a false negative in determining if MongoDB has successfully started. Furthermore, hardcoding parameter values can lead to security vulnerabilities in different deployment scenarios where the default port is blocked or monitored.\n    cwe: CWE-489\n    function_names:\n      - WaitForStartCommand\n    filenames:\n      - src/main/java/org/jenkinsci/plugins/mongodb/MongoBuildWrapper.java\n    classification: slightly promising\n\n  - headline: \"Improper Validation of MongoDB Home Directory\"\n    analysis: |\n      Within the `doCheckHome` methods in MongoDBInstallation.java, the validation mechanism only checks for the existence of the directory and the presence of the \"bin/mongod\" file. This simplistic validation might not be sufficient, as it does not account for symbolic links or altered binaries. An attacker could replace \"mongod\" with a malicious executable, leading to potential unauthorized actions when MongoDB is started.\n    cwe: CWE-829\n    function_names:\n      - doCheckHome\n    filenames:\n      - src/main/java/org/jenkinsci/plugins/mongodb/MongoDBInstallation.java\n      - src/test/java/org/jenkinsci/plugins/mongodb/MongoDBInstallationValidationTest.java\n    classification: very promising\n\n  - headline: \"Potential Command Injection via Parameters\"\n    analysis: |\n      The `parameters` string added to the command line in `MongoBuildWrapper.setupCmd` is split without thorough sanitization. Arbitrary command-line arguments can be injected by carefully crafting the `parameters` input. This can potentially allow attackers to insert harmful MongoDB flags or even chain commands to other unwanted operations.\n    cwe: CWE-78\n    function_names:\n      - setupCmd\n    filenames:\n      - src/main/java/org/jenkinsci/plugins/mongodb/MongoBuildWrapper.java\n    classification: very promising\n\n  - headline: \"Cleartext Storage of Sensitive Information in Log Files\"\n    analysis: |\n      The MongoBuildWrapper.setupCmd method logs command execution including the command-line arguments. If these arguments contain sensitive information (such as `--auth` or other security-related parameters), this information will be stored in plaintext in the log files. An attacker with access to these logs can retrieve sensitive configuration or credentials.\n    cwe: CWE-312\n    function_names:\n      - log\n      - setupCmd\n    filenames:\n      - src/main/java/org/jenkinsci/plugins/mongodb/MongoBuildWrapper.java\n    classification: slightly promising\n\n  - headline: \"Failure to Validate External Resources\"\n    analysis: |\n      The `downloadFromUrl` method in `MongoDBInstaller` is vulnerable because it relies on URLs to download the MongoDB executable. If the source URL is compromised or a man-in-the-middle attack is performed, an attacker could serve a malicious executable. Furthermore, there is no integrity check (e.g., checksum verification) to ensure the downloaded file is the correct and expected MongoDB executable.\n    cwe: CWE-494\n    function_names:\n      - isApplicable\n    filenames:\n      - src/main/java/org/jenkinsci/plugins/mongodb/MongoDBInstaller.java\n    classification: very promising\n```",
      "date": "2024-06-14T14:21:38.402598",
      "usage": {
        "prompt_tokens": 11197,
        "completion_tokens": 899,
        "cost": 0.06947
      }
    }
  ],
  "leads": [
    {
      "headline": "Unrestricted Change of System Port",
      "analysis": "The MongoBuildWrapper class allows the user to specify the MongoDB port number through the \"port\" parameter, which is directly included in command-line arguments. While this alone isn't inherently insecure, combined with insufficient validation, it might be possible to supply destructive command-line arguments. Attackers could exploit this to change the service port to a system or reserved port, leading to denial-of-service attacks or other unintended behaviors.\n",
      "classification": "very promising",
      "cwe": "CWE-77",
      "function_names": [
        "isPortNumber",
        "setupCmd"
      ],
      "filenames": [
        "src/main/java/org/jenkinsci/plugins/mongodb/MongoBuildWrapper.java",
        "src/main/java/org/jenkinsci/plugins/mongodb/MongoDBInstallation.java"
      ]
    },
    {
      "headline": "Use of Hardcoded Port in Connection",
      "analysis": "In the WaitForStartCommand class inside MongoBuildWrapper.java, the default port is hardcoded to \"27017\" if the port parameter is empty. This hardcoded value could be problematic in environments where the MongoDB service is configured to run on a different port, potentially leading to a false negative in determining if MongoDB has successfully started. Furthermore, hardcoding parameter values can lead to security vulnerabilities in different deployment scenarios where the default port is blocked or monitored.\n",
      "classification": "slightly promising",
      "cwe": "CWE-489",
      "function_names": [
        "WaitForStartCommand"
      ],
      "filenames": [
        "src/main/java/org/jenkinsci/plugins/mongodb/MongoBuildWrapper.java"
      ]
    },
    {
      "headline": "Improper Validation of MongoDB Home Directory",
      "analysis": "Within the doCheckHome methods in MongoDBInstallation.java, the validation mechanism only checks for the existence of the directory and the presence of the \"bin/mongod\" file. This simplistic validation might not be sufficient, as it does not account for symbolic links or altered binaries. An attacker could replace \"mongod\" with a malicious executable, leading to potential unauthorized actions when MongoDB is started.\n",
      "classification": "very promising",
      "cwe": "CWE-829",
      "function_names": [
        "doCheckHome"
      ],
      "filenames": [
        "src/main/java/org/jenkinsci/plugins/mongodb/MongoDBInstallation.java",
        "src/test/java/org/jenkinsci/plugins/mongodb/MongoDBInstallationValidationTest.java"
      ]
    },
    {
      "headline": "Potential Command Injection via Parameters",
      "analysis": "The parameters string added to the command line in MongoBuildWrapper.setupCmd is split without thorough sanitization. Arbitrary command-line arguments can be injected by carefully crafting the parameters input. This can potentially allow attackers to insert harmful MongoDB flags or even chain commands to other unwanted operations.\n",
      "classification": "very promising",
      "cwe": "CWE-78",
      "function_names": [
        "setupCmd"
      ],
      "filenames": [
        "src/main/java/org/jenkinsci/plugins/mongodb/MongoBuildWrapper.java"
      ]
    },
    {
      "headline": "Cleartext Storage of Sensitive Information in Log Files",
      "analysis": "The MongoBuildWrapper.setupCmd method logs command execution including the command-line arguments. If these arguments contain sensitive information (such as --auth or other security-related parameters), this information will be stored in plaintext in the log files. An attacker with access to these logs can retrieve sensitive configuration or credentials.\n",
      "classification": "slightly promising",
      "cwe": "CWE-312",
      "function_names": [
        "log",
        "setupCmd"
      ],
      "filenames": [
        "src/main/java/org/jenkinsci/plugins/mongodb/MongoBuildWrapper.java"
      ]
    },
    {
      "headline": "Failure to Validate External Resources",
      "analysis": "The downloadFromUrl method in MongoDBInstaller is vulnerable because it relies on URLs to download the MongoDB executable. If the source URL is compromised or a man-in-the-middle attack is performed, an attacker could serve a malicious executable. Furthermore, there is no integrity check (e.g., checksum verification) to ensure the downloaded file is the correct and expected MongoDB executable.\n",
      "classification": "very promising",
      "cwe": "CWE-494",
      "function_names": [
        "isApplicable"
      ],
      "filenames": [
        "src/main/java/org/jenkinsci/plugins/mongodb/MongoDBInstaller.java"
      ]
    }
  ],
  "scores": [
    {
      "stats": {
        "fn": 2,
        "tp": 0,
        "fp": 4
      },
      "mapping": {},
      "vuln_dates": {
        "CVE-2020-2268": "2020-09-16T14:15:14",
        "CVE-2020-2267": "2020-09-16T14:15:14"
      },
      "scoring_model": "claude-3-opus-20240229",
      "type": "llm",
      "instruction_template_hash": "245ace12b6361954d0a2"
    },
    {
      "stats": {
        "fn": 2,
        "tp": 0,
        "fp": 4
      },
      "mapping": {},
      "vuln_dates": {
        "CVE-2020-2268": "2020-09-16T14:15:14",
        "CVE-2020-2267": "2020-09-16T14:15:14"
      },
      "scoring_model": "claude-3-5-sonnet-20240620",
      "type": "llm",
      "instruction_template_hash": "245ace12b6361954d0a2"
    }
  ],
  "instruction_template_hash": "10c0163db4740318a544",
  "version": "0.1.0"
}
