{
  "commit": "254001a345be10a77f150af0741248df44b7c811",
  "repo_url": "https://github.com/jenkinsci/deploy-plugin",
  "model": "gpt-4o-2024-05-13",
  "chunk_hashes": [
    "ca6953fb03f4a9972ea1"
  ],
  "responses": [
    {
      "content": "```yaml\nleads:\n  - headline: \"Use of Hardcoded Credentials\"\n    analysis: |\n      The code contains hardcoded credentials for the JMX connection in the `Foo` class and in several other test cases. This can be exploited by an attacker who has access to the source code or binary files to gain unauthorized access.\n    cwe: CWE-798\n    function_names:\n      - main\n      - jmain\n    filenames:\n      - src/test/java/hudson/plugins/deploy/Foo.java\n      - src/test/java/hudson/plugins/deploy/tomcat/Tomcat7xAdapterTest.java\n      - src/test/java/hudson/plugins/deploy/tomcat/Tomcat8xAdapterTest.java\n    classification: very promising\n\n  - headline: \"Cleartext Storage of Sensitive Information\"\n    analysis: |\n      Passwords and other sensitive credentials are stored in variables in cleartext. An attacker who can read the memory or the source files can retrieve these credentials easily.\n    cwe: CWE-312\n    function_names:\n      - getPassword\n    filenames:\n      - src/main/java/hudson/plugins/deploy/PasswordProtectedAdapterCargo.java\n      - src/test/java/hudson/plugins/deploy/tomcat/Tomcat7xAdapterTest.java\n      - src/test/java/hudson/plugins/deploy/tomcat/Tomcat8xAdapterTest.java\n      - src/test/java/hudson/plugins/deploy/glassfish/GlassFish3xAdapterTest.java\n    classification: very promising\n\n  - headline: \"Improper Input Validation in URL Handling\"\n    analysis: |\n      The code performs URL handling without proper validation which could be manipulated into performing unsafe behaviors, such as accepting malformed or malicious URLs.\n    cwe: CWE-20\n    function_names:\n      - configure\n    filenames:\n      - src/main/java/hudson/plugins/deploy/tomcat/Tomcat7xAdapter.java\n      - src/main/java/hudson/plugins/deploy/tomcat/Tomcat8xAdapter.java\n      - src/main/java/hudson/plugins/deploy/tomcat/TomcatAdapter.java\n    classification: slightly promising\n\n  - headline: \"Insecure Cryptographic Storage\"\n    analysis: |\n      The code uses a scrambler for protecting sensitive information which is not sufficient to securely protect sensitive data. Standard cryptographic methods should be used.\n    cwe: CWE-327\n    function_names:\n      - Scrambler\n    filenames:\n      - src/main/java/hudson/plugins/deploy/PasswordProtectedAdapterCargo.java\n    classification: slightly promising\n```",
      "date": "2024-06-12T18:16:43.596830",
      "usage": {
        "prompt_tokens": 15756,
        "completion_tokens": 543,
        "cost": 0.086925
      }
    }
  ],
  "leads": [
    {
      "headline": "Use of Hardcoded Credentials",
      "analysis": "The code contains hardcoded credentials for the JMX connection in the Foo class and in several other test cases. This can be exploited by an attacker who has access to the source code or binary files to gain unauthorized access.\n",
      "classification": "very promising",
      "cwe": "CWE-798",
      "function_names": [
        "main",
        "jmain"
      ],
      "filenames": [
        "src/test/java/hudson/plugins/deploy/Foo.java",
        "src/test/java/hudson/plugins/deploy/tomcat/Tomcat7xAdapterTest.java",
        "src/test/java/hudson/plugins/deploy/tomcat/Tomcat8xAdapterTest.java"
      ]
    },
    {
      "headline": "Cleartext Storage of Sensitive Information",
      "analysis": "Passwords and other sensitive credentials are stored in variables in cleartext. An attacker who can read the memory or the source files can retrieve these credentials easily.\n",
      "classification": "very promising",
      "cwe": "CWE-312",
      "function_names": [
        "getPassword"
      ],
      "filenames": [
        "src/main/java/hudson/plugins/deploy/PasswordProtectedAdapterCargo.java",
        "src/test/java/hudson/plugins/deploy/tomcat/Tomcat7xAdapterTest.java",
        "src/test/java/hudson/plugins/deploy/tomcat/Tomcat8xAdapterTest.java"
      ]
    },
    {
      "headline": "Improper Input Validation in URL Handling",
      "analysis": "The code performs URL handling without proper validation which could be manipulated into performing unsafe behaviors, such as accepting malformed or malicious URLs.\n",
      "classification": "slightly promising",
      "cwe": "CWE-20",
      "function_names": [
        "configure"
      ],
      "filenames": [
        "src/main/java/hudson/plugins/deploy/tomcat/Tomcat7xAdapter.java",
        "src/main/java/hudson/plugins/deploy/tomcat/Tomcat8xAdapter.java",
        "src/main/java/hudson/plugins/deploy/tomcat/TomcatAdapter.java"
      ]
    },
    {
      "headline": "Insecure Cryptographic Storage",
      "analysis": "The code uses a scrambler for protecting sensitive information which is not sufficient to securely protect sensitive data. Standard cryptographic methods should be used.\n",
      "classification": "slightly promising",
      "cwe": "CWE-327",
      "function_names": [
        "Scrambler"
      ],
      "filenames": [
        "src/main/java/hudson/plugins/deploy/PasswordProtectedAdapterCargo.java"
      ]
    }
  ],
  "scores": [
    {
      "stats": {
        "fn": 0,
        "tp": 1,
        "fp": 1
      },
      "mapping": {
        "1": "CVE-2017-1000113"
      },
      "vuln_dates": {
        "CVE-2017-1000113": "2017-10-05T01:29:04"
      },
      "scoring_model": "claude-3-opus-20240229",
      "type": "llm",
      "instruction_template_hash": "245ace12b6361954d0a2"
    }
  ],
  "instruction_template_hash": "10c0163db4740318a544",
  "version": "0.1.0"
}
