{
  "commit": "56284d80811fb5963a972b438f2870f175e5b7c8",
  "repo_url": "https://github.com/tj-actions/changed-files",
  "model": "gpt-4o-2024-05-13",
  "chunk_hashes": [
    "b983fdb822096c93f3ec"
  ],
  "responses": [
    {
      "content": "```yaml\nleads:\n  - headline: Use of unchecked outputs from shell commands\n    analysis: |\n      In the codebase, there are several instances where outputs from shell commands executed by the `exec` module are not properly checked for errors or sanitized for further usage. This can lead to security issues, as maliciously crafted outputs from these commands can exploit the application. For example, the `gitFetch` function in `src/utils.ts` does not properly handle the stderr output from the shell execution, which is simply logged using `core.warning`.\n    cwe: CWE-77\n    function_names:\n      - gitFetch\n    filenames:\n      - src/utils.ts\n    classification: very promising\n  - headline: Potential leakage of sensitive information\n    analysis: |\n      The codebase logs various inputs and outputs extensively for debugging purposes. While helpful during development, these logs may include sensitive information such as tokens, repository details, or other confidential data when running in a production environment. For example, environment variables and inputs are logged in the `getEnv` and `getInputs` functions.\n    cwe: CWE-532\n    function_names:\n      - getEnv\n      - getInputs\n    filenames:\n      - src/env.ts\n      - src/inputs.ts\n    classification: very promising\n  - headline: Deserialization of untrusted data\n    analysis: |\n      The code uses the `yaml` library to parse YAML content from potentially untrusted sources in the `getYamlFilePatternsFromContents` function in `src/utils.ts`. Parsing YAML data directly without validation can lead to deserialization attacks if the YAML content is crafted maliciously.\n    cwe: CWE-502\n    function_names:\n      - getYamlFilePatternsFromContents\n    filenames:\n      - src/utils.ts\n    classification: slightly promising\n  - headline: Missing validation of user inputs\n    analysis: |\n      Several functions in the codebase, such as `processChangedFiles` in `src/changedFiles.ts`, directly utilize inputs provided by users or external systems without proper validation. This can lead to various injection attacks if an attacker can manipulate the input values (e.g., file patterns) to include malicious content.\n    cwe: CWE-20\n    function_names:\n      - processChangedFiles\n    filenames:\n      - src/changedFiles.ts\n    classification: slightly promising\n  - headline: Improper usage of cryptographic API\n    analysis: |\n      Within the repository, there's a lack of securing input/output or sensitive data before processing. Specifically, the `core.setOutput` function in `src/utils.ts` uses the `jsonOutput` function to serialize objects, but it lacks cryptographic protections for the resulting outputs. This can lead to weaker data integrity and confidentiality.\n    cwe: CWE-327\n    function_names:\n      - setOutput\n      - jsonOutput\n    filenames:\n      - src/utils.ts\n    classification: not promising\n```",
      "date": "2024-06-09T15:08:46.250186",
      "usage": {
        "prompt_tokens": 43345,
        "completion_tokens": 605,
        "cost": 0.2258
      }
    }
  ],
  "leads": [
    {
      "headline": "Use of unchecked outputs from shell commands",
      "analysis": "In the codebase, there are several instances where outputs from shell commands executed by the exec module are not properly checked for errors or sanitized for further usage. This can lead to security issues, as maliciously crafted outputs from these commands can exploit the application. For example, the gitFetch function in src/utils.ts does not properly handle the stderr output from the shell execution, which is simply logged using core.warning.\n",
      "classification": "very promising",
      "cwe": "CWE-77",
      "function_names": [
        "gitFetch"
      ],
      "filenames": [
        "src/utils.ts"
      ]
    },
    {
      "headline": "Potential leakage of sensitive information",
      "analysis": "The codebase logs various inputs and outputs extensively for debugging purposes. While helpful during development, these logs may include sensitive information such as tokens, repository details, or other confidential data when running in a production environment. For example, environment variables and inputs are logged in the getEnv and getInputs functions.\n",
      "classification": "very promising",
      "cwe": "CWE-532",
      "function_names": [
        "getEnv",
        "getInputs"
      ],
      "filenames": [
        "src/env.ts",
        "src/inputs.ts"
      ]
    },
    {
      "headline": "Deserialization of untrusted data",
      "analysis": "The code uses the yaml library to parse YAML content from potentially untrusted sources in the getYamlFilePatternsFromContents function in src/utils.ts. Parsing YAML data directly without validation can lead to deserialization attacks if the YAML content is crafted maliciously.\n",
      "classification": "slightly promising",
      "cwe": "CWE-502",
      "function_names": [
        "getYamlFilePatternsFromContents"
      ],
      "filenames": [
        "src/utils.ts"
      ]
    },
    {
      "headline": "Missing validation of user inputs",
      "analysis": "Several functions in the codebase, such as processChangedFiles in src/changedFiles.ts, directly utilize inputs provided by users or external systems without proper validation. This can lead to various injection attacks if an attacker can manipulate the input values (e.g., file patterns) to include malicious content.\n",
      "classification": "slightly promising",
      "cwe": "CWE-20",
      "function_names": [
        "processChangedFiles"
      ],
      "filenames": [
        "src/changedFiles.ts"
      ]
    },
    {
      "headline": "Improper usage of cryptographic API",
      "analysis": "Within the repository, there's a lack of securing input/output or sensitive data before processing. Specifically, the core.setOutput function in src/utils.ts uses the jsonOutput function to serialize objects, but it lacks cryptographic protections for the resulting outputs. This can lead to weaker data integrity and confidentiality.\n",
      "classification": "not promising",
      "cwe": "CWE-327",
      "function_names": [
        "setOutput",
        "jsonOutput"
      ],
      "filenames": [
        "src/utils.ts"
      ]
    }
  ],
  "scores": [
    {
      "stats": {
        "fn": 1,
        "tp": 0,
        "fp": 2
      },
      "mapping": {},
      "vuln_dates": {
        "CVE-2023-51664": "2023-12-27T17:15:08"
      },
      "scoring_model": "gpt-4o-2024-05-13",
      "type": "llm",
      "instruction_template_hash": "8998f09cf57fca8a6e03"
    },
    {
      "stats": {
        "fn": 1,
        "tp": 0,
        "fp": 2
      },
      "mapping": {},
      "vuln_dates": {
        "CVE-2023-51664": "2023-12-27T17:15:08"
      },
      "scoring_model": "claude-3-opus-20240229",
      "type": "llm",
      "instruction_template_hash": "245ace12b6361954d0a2"
    }
  ],
  "instruction_template_hash": "10c0163db4740318a544",
  "version": "0.1.0"
}
