{
  "commit": "359b2ba87358224963986f709e593d799064ace6",
  "repo_url": "https://github.com/nmslib/hnswlib",
  "model": "gpt-4o-2024-05-13",
  "chunk_hashes": [
    "9305e1557e672ed299d8"
  ],
  "responses": [
    {
      "content": "```yaml\nleads:\n  - headline: \"Possible Command Injection Vulnerability in 'setup.py'\"\n    analysis: |\n      The `setup.py` script includes calls to `os.system()` without proper sanitization of inputs. This can lead to a command injection vulnerability if the arguments passed to the script are maliciously crafted. Specifically, in the `tests/python/git_tester.py` script, executing commands using `os.system` with values from `commit.msg` can lead to arbitrary code execution if an attacker controls these messages or inputs.\n    cwe: CWE-78\n    function_names:\n      - \"os.system\"\n    filenames:\n      - \"tests/python/git_tester.py\"\n      - \"setup.py\"\n    classification: very promising\n\n  - headline: \"Inconsistent Protection Against Exceptions During Multi-Threaded Operations\"\n    analysis: |\n      Concurrent operations in `ParallelFor` function from `python_bindings/bindings.cpp` and several other Python and C++ files lack consistent try/catch/finally structures necessary to handle exceptions safely and avoid deadlocks or inconsistent states. This can result in unpredictable behavior, potential data corruption, or crashes.\n    cwe: CWE-662\n    function_names:\n      - \"ParallelFor\"\n    filenames:\n      - \"python_bindings/bindings.cpp\"\n      - \"examples/cpp/example_mt_replace_deleted.cpp\"\n      - \"examples/cpp/example_mt_search.cpp\"\n    classification: slightly promising\n\n  - headline: \"Unsafe Use of file operations without Proper Permissions\"\n    analysis: |\n      The use of `open` operations in different files (for instance, saving and loading indices) assumes that file paths are secure and accessible. No checks for proper file permissions or any sandboxing mechanism are included, which can lead to file access issues or unauthorized data modification.\n    cwe: CWE-276\n    function_names:\n      - \"saveIndex\"\n      - \"loadIndex\"\n    filenames:\n      - \"hnswlib/hnswalg.h\"\n      - \"hnswlib/bruteforce.h\"\n      - \"examples/python/example_replace_deleted.py\"\n      - \"examples/cpp/example_replace_deleted.cpp\"\n    classification: slightly promising\n\n  - headline: \"Potential Integer Overflow in Array Index Calculations\"\n    analysis: |\n      Several files perform operations involving array indexing and memory allocations based on user-supplied dimensions (e.g., `dim` parameters). Without proper bounds checking, this can lead to integer overflows and subsequent out-of-bounds accesses, causing undefined behavior and potential security vulnerabilities.\n    cwe: CWE-190\n    function_names:\n      - \"allocate spaces in HierarchicalNSW\"\n      - \"resizeIndex\"\n    filenames:\n      - \"hnswlib/hnswalg.h\"\n      - \"examples/cpp/example.cpp\"\n      - \"python_bindings/bindings.cpp\"\n    classification: slightly promising\n\n  - headline: \"Use of Hardcoded Seed Value for Random Number Generators\"\n    analysis: |\n      The random number generators in several files, such as `python_bindings/bindings.cpp` and `tests/python/speedtest.py`, are initialized with a hardcoded seed value. This can lead to predictable results, which might be exploited in scenarios where randomization is critical for security.\n    cwe: CWE-330\n    function_names:\n      - \"std::mt19937\"\n    filenames:\n      - \"python_bindings/bindings.cpp\"\n      - \"tests/python/speedtest.py\"\n    classification: slightly promising\n```",
      "date": "2024-06-14T14:58:27.578865",
      "usage": {
        "prompt_tokens": 68213,
        "completion_tokens": 726,
        "cost": 0.351955
      }
    }
  ],
  "leads": [
    {
      "headline": "Possible Command Injection Vulnerability in 'setup.py'",
      "analysis": "The setup.py script includes calls to os.system() without proper sanitization of inputs. This can lead to a command injection vulnerability if the arguments passed to the script are maliciously crafted. Specifically, in the tests/python/git_tester.py script, executing commands using os.system with values from commit.msg can lead to arbitrary code execution if an attacker controls these messages or inputs.\n",
      "classification": "very promising",
      "cwe": "CWE-78",
      "function_names": [
        "os.system"
      ],
      "filenames": [
        "tests/python/git_tester.py",
        "setup.py"
      ]
    },
    {
      "headline": "Inconsistent Protection Against Exceptions During Multi-Threaded Operations",
      "analysis": "Concurrent operations in ParallelFor function from python_bindings/bindings.cpp and several other Python and C++ files lack consistent try/catch/finally structures necessary to handle exceptions safely and avoid deadlocks or inconsistent states. This can result in unpredictable behavior, potential data corruption, or crashes.\n",
      "classification": "slightly promising",
      "cwe": "CWE-662",
      "function_names": [
        "ParallelFor"
      ],
      "filenames": [
        "python_bindings/bindings.cpp",
        "examples/cpp/example_mt_replace_deleted.cpp",
        "examples/cpp/example_mt_search.cpp"
      ]
    },
    {
      "headline": "Unsafe Use of file operations without Proper Permissions",
      "analysis": "The use of open operations in different files (for instance, saving and loading indices) assumes that file paths are secure and accessible. No checks for proper file permissions or any sandboxing mechanism are included, which can lead to file access issues or unauthorized data modification.\n",
      "classification": "slightly promising",
      "cwe": "CWE-276",
      "function_names": [
        "saveIndex",
        "loadIndex"
      ],
      "filenames": [
        "hnswlib/hnswalg.h",
        "hnswlib/bruteforce.h",
        "examples/python/example_replace_deleted.py"
      ]
    },
    {
      "headline": "Potential Integer Overflow in Array Index Calculations",
      "analysis": "Several files perform operations involving array indexing and memory allocations based on user-supplied dimensions (e.g., dim parameters). Without proper bounds checking, this can lead to integer overflows and subsequent out-of-bounds accesses, causing undefined behavior and potential security vulnerabilities.\n",
      "classification": "slightly promising",
      "cwe": "CWE-190",
      "function_names": [
        "allocate spaces in HierarchicalNSW",
        "resizeIndex"
      ],
      "filenames": [
        "hnswlib/hnswalg.h",
        "examples/cpp/example.cpp",
        "python_bindings/bindings.cpp"
      ]
    },
    {
      "headline": "Use of Hardcoded Seed Value for Random Number Generators",
      "analysis": "The random number generators in several files, such as python_bindings/bindings.cpp and tests/python/speedtest.py, are initialized with a hardcoded seed value. This can lead to predictable results, which might be exploited in scenarios where randomization is critical for security.\n",
      "classification": "slightly promising",
      "cwe": "CWE-330",
      "function_names": [
        "std::mt19937"
      ],
      "filenames": [
        "python_bindings/bindings.cpp",
        "tests/python/speedtest.py"
      ]
    }
  ],
  "scores": [
    {
      "stats": {
        "fn": 1,
        "tp": 0,
        "fp": 1
      },
      "mapping": {},
      "vuln_dates": {
        "CVE-2023-37365": "2023-06-30T19:15:09"
      },
      "scoring_model": "claude-3-opus-20240229",
      "type": "llm",
      "instruction_template_hash": "245ace12b6361954d0a2"
    }
  ],
  "instruction_template_hash": "10c0163db4740318a544",
  "version": "0.1.0"
}
