{
  "commit": "26852ff123b07ebde3cc78ee0e3f0b399bffd293",
  "repo_url": "https://github.com/jenkinsci/gradle-plugin",
  "model": "gpt-4o-2024-05-13",
  "chunk_hashes": [
    "d1cb3bc34e3ecd7706c6"
  ],
  "responses": [
    {
      "content": "```yaml\nleads:\n  - headline: \"Potential Hard-coded Secret Key Exposure\"\n    analysis: |\n      The code contains a hard-coded secret key in `src/main/resources/hudson/plugins/gradle/injection/InjectionConfig/help-accessKey.html`. This is considered insecure as it may expose sensitive information. Any user having access to the source code repository can view the secret key.\n    cwe: CWE-798\n    function_names: []\n    filenames:\n      - \"src/main/resources/hudson/plugins/gradle/injection/InjectionConfig/help-accessKey.html\"\n    classification: \"very promising\"\n\n  - headline: \"Potential Log Injection Vulnerability\"\n    analysis: |\n      There are occurrences in the codebase where user-controlled input may be logged without sufficient sanitization, which could lead to log injection attacks. For instance, in `AbstractLogger.java`, the `info` and `error` methods log messages directly without context validation.\n    cwe: CWE-117\n    function_names:\n      - \"AbstractLogger.info\"\n      - \"AbstractLogger.error\"\n    filenames:\n      - \"src/main/java/hudson/plugins/gradle/AbstractLogger.java\"\n    classification: \"slightly promising\"\n\n  - headline: \"Potential Command Injection Vulnerability\"\n    analysis: |\n      In `GradleInstaller.java`, the method `getExeFile` executes a command that is built using user-controlled data. If not properly sanitized, this could lead to OS command injection vulnerabilities.\n    cwe: CWE-78\n    function_names:\n      - \"GradleInstallation.GetExeFile.call\"\n    filenames:\n      - \"src/main/java/hudson/plugins/gradle/GradleInstallation.java\"\n    classification: \"very promising\"\n\n  - headline: \"Cross-Site Scripting (XSS) Vulnerability\"\n    analysis: |\n      The script `GradleTaskNote/script.js` manipulates the DOM with user-controlled data, which could lead to cross-site scripting (XSS) attacks if the input is not properly validated and sanitized.\n    cwe: CWE-79\n    function_names:\n      - \"handle\"\n    filenames:\n      - \"src/main/resources/hudson/plugins/gradle/GradleTaskNote/script.js\"\n    classification: \"very promising\"\n\n  - headline: \"Insecure Deserialization\"\n    analysis: |\n      The project makes use of Jackson library to deserialize JSON data (e.g., in `ScanDetailService` class). If the input to these deserializers can be controlled by an attacker, it can lead to remote code execution or other security issues.\n    cwe: CWE-502\n    function_names:\n      - \"ScanDetailService.getScanDetail\"\n    filenames:\n      - \"src/main/java/hudson/plugins/gradle/enriched/ScanDetailService.java\"\n    classification: \"very promising\"\n\n  - headline: \"Potential XML External Entity Injection (XXE)\"\n    analysis: |\n      In the codebase, there are examples of XML parsing without secure configuration to prevent XXE attacks. For instance, in `EnrichedSummaryConfig.java`, it uses XML parsing which is potentially vulnerable to XXE attacks if not properly configured.\n    cwe: CWE-611\n    function_names: []\n    filenames:\n      - \"src/main/java/hudson/plugins/gradle/enriched/EnrichedSummaryConfig.java\"\n    classification: \"slightly promising\"\n```",
      "date": "2024-06-12T18:34:31.553144",
      "usage": {
        "prompt_tokens": 50292,
        "completion_tokens": 698,
        "cost": 0.26193
      }
    }
  ],
  "leads": [
    {
      "headline": "Potential Hard-coded Secret Key Exposure",
      "analysis": "The code contains a hard-coded secret key in src/main/resources/hudson/plugins/gradle/injection/InjectionConfig/help-accessKey.html. This is considered insecure as it may expose sensitive information. Any user having access to the source code repository can view the secret key.\n",
      "classification": "very promising",
      "cwe": "CWE-798",
      "function_names": [],
      "filenames": [
        "src/main/resources/hudson/plugins/gradle/injection/InjectionConfig/help-accessKey.html"
      ]
    },
    {
      "headline": "Potential Log Injection Vulnerability",
      "analysis": "There are occurrences in the codebase where user-controlled input may be logged without sufficient sanitization, which could lead to log injection attacks. For instance, in AbstractLogger.java, the info and error methods log messages directly without context validation.\n",
      "classification": "slightly promising",
      "cwe": "CWE-117",
      "function_names": [
        "AbstractLogger.info",
        "AbstractLogger.error"
      ],
      "filenames": [
        "src/main/java/hudson/plugins/gradle/AbstractLogger.java"
      ]
    },
    {
      "headline": "Potential Command Injection Vulnerability",
      "analysis": "In GradleInstaller.java, the method getExeFile executes a command that is built using user-controlled data. If not properly sanitized, this could lead to OS command injection vulnerabilities.\n",
      "classification": "very promising",
      "cwe": "CWE-78",
      "function_names": [
        "GradleInstallation.GetExeFile.call"
      ],
      "filenames": [
        "src/main/java/hudson/plugins/gradle/GradleInstallation.java"
      ]
    },
    {
      "headline": "Cross-Site Scripting (XSS) Vulnerability",
      "analysis": "The script GradleTaskNote/script.js manipulates the DOM with user-controlled data, which could lead to cross-site scripting (XSS) attacks if the input is not properly validated and sanitized.\n",
      "classification": "very promising",
      "cwe": "CWE-79",
      "function_names": [
        "handle"
      ],
      "filenames": [
        "src/main/resources/hudson/plugins/gradle/GradleTaskNote/script.js"
      ]
    },
    {
      "headline": "Insecure Deserialization",
      "analysis": "The project makes use of Jackson library to deserialize JSON data (e.g., in ScanDetailService class). If the input to these deserializers can be controlled by an attacker, it can lead to remote code execution or other security issues.\n",
      "classification": "very promising",
      "cwe": "CWE-502",
      "function_names": [
        "ScanDetailService.getScanDetail"
      ],
      "filenames": [
        "src/main/java/hudson/plugins/gradle/enriched/ScanDetailService.java"
      ]
    },
    {
      "headline": "Potential XML External Entity Injection (XXE)",
      "analysis": "In the codebase, there are examples of XML parsing without secure configuration to prevent XXE attacks. For instance, in EnrichedSummaryConfig.java, it uses XML parsing which is potentially vulnerable to XXE attacks if not properly configured.\n",
      "classification": "slightly promising",
      "cwe": "CWE-611",
      "function_names": [],
      "filenames": [
        "src/main/java/hudson/plugins/gradle/enriched/EnrichedSummaryConfig.java"
      ]
    }
  ],
  "scores": [
    {
      "stats": {
        "fn": 1,
        "tp": 0,
        "fp": 4
      },
      "mapping": {},
      "vuln_dates": {
        "CVE-2023-39152": "2023-07-26T14:15:10"
      },
      "scoring_model": "claude-3-opus-20240229",
      "type": "llm",
      "instruction_template_hash": "245ace12b6361954d0a2"
    }
  ],
  "instruction_template_hash": "10c0163db4740318a544",
  "version": "0.1.0"
}
