{
  "commit": "2cd9997382a9d29e97806fce9086f83409cb077e",
  "repo_url": "https://github.com/jenkinsci/mantis-plugin",
  "model": "claude-3-sonnet-20240229",
  "chunk_hashes": [
    "e56a63e502f475750918"
  ],
  "responses": [
    {
      "content": "```yaml\nleads:\n  - headline: Cross-Site Request Forgery (CSRF) vulnerability\n    analysis: |\n      The plugin does not implement any CSRF protection mechanisms, which could allow an attacker to perform unauthorized actions on behalf of an authenticated user.\n    cwe: CWE-352\n    function_names:\n      - MantisProjectPropertyConfigSubmitTest.testConfigSubmit_002\n    filenames:\n      - src/test/java/hudson/plugins/mantis/MantisProjectPropertyConfigSubmitTest.java\n    classification: very promising\n\n  - headline: Permissive Cross-Site Scripting (XSS) vulnerability\n    analysis: |\n      The plugin does not properly sanitize user-supplied data before including it in HTML responses, which could allow an attacker to inject malicious scripts and potentially conduct XSS attacks.\n    cwe: CWE-79\n    function_names:\n      - Utility.escape\n    filenames:\n      - src/main/java/hudson/plugins/mantis/Utility.java\n    classification: very promising\n\n  - headline: Use of broken or risky cryptographic algorithm\n    analysis: |\n      The plugin appears to use the DES algorithm for encrypting passwords, which is considered insecure and should not be used for new applications.\n    cwe: CWE-327\n    function_names:\n      - MantisSite.readResolve\n    filenames:\n      - src/main/java/hudson/plugins/mantis/MantisSite.java\n    classification: very promising\n\n  - headline: Potential authentication bypass using credential/session prediction\n    analysis: |\n      The plugin transmits user credentials in cleartext over the network when connecting to the Mantis server. An attacker could potentially sniff the credentials and gain unauthorized access.\n    cwe: CWE-522\n    function_names:\n      - MantisSessionImpl\n    filenames:\n      - src/main/java/hudson/plugins/mantis/soap/mantis110/MantisSessionImpl.java\n      - src/main/java/hudson/plugins/mantis/soap/mantis120/MantisSessionImpl.java\n    classification: very promising\n\n  - headline: Missing authentication for critical function\n    analysis: |\n      The plugin does not require authentication for certain critical operations like updating Mantis issues, which could allow an unauthorized party to make changes.\n    cwe: CWE-306  \n    function_names:\n      - Updater.perform\n      - MantisIssueRegister.perform\n    filenames:\n      - src/main/java/hudson/plugins/mantis/Updater.java \n      - src/main/java/hudson/plugins/mantis/MantisIssueRegister.java\n    classification: very promising\n\n  - headline: Use of insecure SunX509TrustManager for SSL connections\n    analysis: |\n      The plugin uses an insecure trust manager (SunFakeTrustSocketFactory) that accepts any SSL certificate, making it vulnerable to man-in-the-middle attacks when connecting to the Mantis server over HTTPS.\n    cwe: CWE-295\n    function_names:\n      - MantisSessionImpl\n    filenames:\n      - src/main/java/hudson/plugins/mantis/soap/mantis110/MantisSessionImpl.java\n      - src/main/java/hudson/plugins/mantis/soap/mantis120/MantisSessionImpl.java  \n    classification: very promising\n    \n  - headline: Improper input validation\n    analysis: |\n      The plugin does not properly validate user-supplied input such as the project ID and category name when creating new Mantis issues, which could lead to injection attacks.\n    cwe: CWE-20\n    function_names:\n      - MantisIssueRegister.createIssue\n    filenames:\n      - src/main/java/hudson/plugins/mantis/MantisIssueRegister.java\n    classification: slightly promising\n\n```",
      "date": "2024-06-12T18:49:24.764005",
      "usage": {
        "prompt_tokens": 32323,
        "completion_tokens": 948,
        "cost": 0.111189
      }
    }
  ],
  "leads": [
    {
      "headline": "Cross-Site Request Forgery (CSRF) vulnerability",
      "analysis": "The plugin does not implement any CSRF protection mechanisms, which could allow an attacker to perform unauthorized actions on behalf of an authenticated user.\n",
      "classification": "very promising",
      "cwe": "CWE-352",
      "function_names": [
        "MantisProjectPropertyConfigSubmitTest.testConfigSubmit_002"
      ],
      "filenames": [
        "src/test/java/hudson/plugins/mantis/MantisProjectPropertyConfigSubmitTest.java"
      ]
    },
    {
      "headline": "Permissive Cross-Site Scripting (XSS) vulnerability",
      "analysis": "The plugin does not properly sanitize user-supplied data before including it in HTML responses, which could allow an attacker to inject malicious scripts and potentially conduct XSS attacks.\n",
      "classification": "very promising",
      "cwe": "CWE-79",
      "function_names": [
        "Utility.escape"
      ],
      "filenames": [
        "src/main/java/hudson/plugins/mantis/Utility.java"
      ]
    },
    {
      "headline": "Use of broken or risky cryptographic algorithm",
      "analysis": "The plugin appears to use the DES algorithm for encrypting passwords, which is considered insecure and should not be used for new applications.\n",
      "classification": "very promising",
      "cwe": "CWE-327",
      "function_names": [
        "MantisSite.readResolve"
      ],
      "filenames": [
        "src/main/java/hudson/plugins/mantis/MantisSite.java"
      ]
    },
    {
      "headline": "Potential authentication bypass using credential/session prediction",
      "analysis": "The plugin transmits user credentials in cleartext over the network when connecting to the Mantis server. An attacker could potentially sniff the credentials and gain unauthorized access.\n",
      "classification": "very promising",
      "cwe": "CWE-522",
      "function_names": [
        "MantisSessionImpl"
      ],
      "filenames": [
        "src/main/java/hudson/plugins/mantis/soap/mantis110/MantisSessionImpl.java",
        "src/main/java/hudson/plugins/mantis/soap/mantis120/MantisSessionImpl.java"
      ]
    },
    {
      "headline": "Missing authentication for critical function",
      "analysis": "The plugin does not require authentication for certain critical operations like updating Mantis issues, which could allow an unauthorized party to make changes.\n",
      "classification": "very promising",
      "cwe": "CWE-306",
      "function_names": [
        "Updater.perform",
        "MantisIssueRegister.perform"
      ],
      "filenames": [
        "src/main/java/hudson/plugins/mantis/Updater.java",
        "src/main/java/hudson/plugins/mantis/MantisIssueRegister.java"
      ]
    },
    {
      "headline": "Use of insecure SunX509TrustManager for SSL connections",
      "analysis": "The plugin uses an insecure trust manager (SunFakeTrustSocketFactory) that accepts any SSL certificate, making it vulnerable to man-in-the-middle attacks when connecting to the Mantis server over HTTPS.\n",
      "classification": "very promising",
      "cwe": "CWE-295",
      "function_names": [
        "MantisSessionImpl"
      ],
      "filenames": [
        "src/main/java/hudson/plugins/mantis/soap/mantis110/MantisSessionImpl.java",
        "src/main/java/hudson/plugins/mantis/soap/mantis120/MantisSessionImpl.java"
      ]
    },
    {
      "headline": "Improper input validation",
      "analysis": "The plugin does not properly validate user-supplied input such as the project ID and category name when creating new Mantis issues, which could lead to injection attacks.\n",
      "classification": "slightly promising",
      "cwe": "CWE-20",
      "function_names": [
        "MantisIssueRegister.createIssue"
      ],
      "filenames": [
        "src/main/java/hudson/plugins/mantis/MantisIssueRegister.java"
      ]
    }
  ],
  "scores": [
    {
      "stats": {
        "fn": 1,
        "tp": 0,
        "fp": 6
      },
      "mapping": {},
      "vuln_dates": {
        "CVE-2019-16569": "2019-12-17T15:15:22"
      },
      "scoring_model": "claude-3-opus-20240229",
      "type": "llm",
      "instruction_template_hash": "245ace12b6361954d0a2"
    },
    {
      "stats": {
        "fn": 0,
        "tp": 1,
        "fp": 5
      },
      "mapping": {
        "0": "CVE-2019-16569"
      },
      "vuln_dates": {
        "CVE-2019-16569": "2019-12-17T15:15:22"
      },
      "scoring_model": "claude-3-5-sonnet-20240620",
      "type": "llm",
      "instruction_template_hash": "245ace12b6361954d0a2"
    }
  ],
  "instruction_template_hash": "10c0163db4740318a544",
  "version": "0.1.0"
}
