{
  "commit": "2212d4aaa50191daf1b7b14591d3abdc00c218fa",
  "repo_url": "https://github.com/smallrye/smallrye-config",
  "model": "claude-3-5-sonnet-20240620",
  "chunk_hashes": [
    "de3b58fb6c17879fee5a"
  ],
  "responses": [
    {
      "content": "```yaml\nleads:\n  - headline: Zookeeper configuration exposed over network\n    analysis: |\n      The ZooKeeperConfigSource class connects to a Zookeeper server specified by the \"io.smallrye.configsource.zookeeper.url\" property. This connection is made without any authentication or encryption. If the Zookeeper server is exposed on a network interface, it could allow unauthorized access to sensitive configuration data.\n    cwe: CWE-319\n    function_names:\n      - getCuratorClient\n    filenames:\n      - sources/zookeeper/src/main/java/io/smallrye/config/source/zookeeper/ZooKeeperConfigSource.java\n    classification: very promising\n\n  - headline: Potential injection of untrusted configuration data\n    analysis: |\n      The ConfigProducer class injects configuration values based on the @ConfigProperty annotation without any validation. If an attacker can control configuration sources, they may be able to inject malicious values that get executed in the application context. The getValue method should be enhanced to perform input validation before returning values.\n    cwe: CWE-20\n    function_names:\n      - getValue\n    filenames:\n      - implementation/src/main/java/io/smallrye/config/inject/ConfigProducer.java\n    classification: slightly promising\n\n  - headline: Insecure deserialization in ImplicitConverters\n    analysis: |\n      The ImplicitConverters class uses Java deserialization to reconstruct converter objects. If an attacker can control the serialized data, they may be able to execute arbitrary code during deserialization. The readResolve methods should be enhanced to validate the deserialized data before reconstructing objects.\n    cwe: CWE-502 \n    function_names:\n      - readResolve\n    filenames:\n      - implementation/src/main/java/io/smallrye/config/ImplicitConverters.java\n    classification: slightly promising\n\n  - headline: Potential XML external entity injection\n    analysis: |\n      The JsonArrayConverter and JsonObjectConverter classes use the default JSON parser configuration, which may be vulnerable to XML external entity (XXE) injection if parsing untrusted JSON data containing XML. The JSON parsers should be configured to disable XXE processing.\n    cwe: CWE-611\n    function_names:\n      - convert\n    filenames:\n      - converters/json/src/main/java/io/smallrye/config/converter/json/JsonArrayConverter.java\n      - converters/json/src/main/java/io/smallrye/config/converter/json/JsonObjectConverter.java  \n    classification: slightly promising\n\n  - headline: Potential expression language injection\n    analysis: |\n      The ConfigProducer class injects String configuration values without escaping or validating them. If an attacker can control configuration sources, they may be able to inject expression language syntax that gets evaluated. The getValue method should escape or validate string values before returning them.\n    cwe: CWE-917\n    function_names:\n      - getValue  \n    filenames:\n      - implementation/src/main/java/io/smallrye/config/inject/ConfigProducer.java\n    classification: slightly promising\n```",
      "date": "2024-07-08T08:36:47.895108",
      "usage": {
        "prompt_tokens": 83845,
        "completion_tokens": 758,
        "cost": 0.262905
      }
    }
  ],
  "leads": [
    {
      "headline": "Zookeeper configuration exposed over network",
      "analysis": "The ZooKeeperConfigSource class connects to a Zookeeper server specified by the \"io.smallrye.configsource.zookeeper.url\" property. This connection is made without any authentication or encryption. If the Zookeeper server is exposed on a network interface, it could allow unauthorized access to sensitive configuration data.\n",
      "classification": "very promising",
      "cwe": "CWE-319",
      "function_names": [
        "getCuratorClient"
      ],
      "filenames": [
        "sources/zookeeper/src/main/java/io/smallrye/config/source/zookeeper/ZooKeeperConfigSource.java"
      ]
    },
    {
      "headline": "Potential injection of untrusted configuration data",
      "analysis": "The ConfigProducer class injects configuration values based on the @ConfigProperty annotation without any validation. If an attacker can control configuration sources, they may be able to inject malicious values that get executed in the application context. The getValue method should be enhanced to perform input validation before returning values.\n",
      "classification": "slightly promising",
      "cwe": "CWE-20",
      "function_names": [
        "getValue"
      ],
      "filenames": [
        "implementation/src/main/java/io/smallrye/config/inject/ConfigProducer.java"
      ]
    },
    {
      "headline": "Insecure deserialization in ImplicitConverters",
      "analysis": "The ImplicitConverters class uses Java deserialization to reconstruct converter objects. If an attacker can control the serialized data, they may be able to execute arbitrary code during deserialization. The readResolve methods should be enhanced to validate the deserialized data before reconstructing objects.\n",
      "classification": "slightly promising",
      "cwe": "CWE-502",
      "function_names": [
        "readResolve"
      ],
      "filenames": [
        "implementation/src/main/java/io/smallrye/config/ImplicitConverters.java"
      ]
    },
    {
      "headline": "Potential XML external entity injection",
      "analysis": "The JsonArrayConverter and JsonObjectConverter classes use the default JSON parser configuration, which may be vulnerable to XML external entity (XXE) injection if parsing untrusted JSON data containing XML. The JSON parsers should be configured to disable XXE processing.\n",
      "classification": "slightly promising",
      "cwe": "CWE-611",
      "function_names": [
        "convert"
      ],
      "filenames": [
        "converters/json/src/main/java/io/smallrye/config/converter/json/JsonArrayConverter.java",
        "converters/json/src/main/java/io/smallrye/config/converter/json/JsonObjectConverter.java"
      ]
    },
    {
      "headline": "Potential expression language injection",
      "analysis": "The ConfigProducer class injects String configuration values without escaping or validating them. If an attacker can control configuration sources, they may be able to inject expression language syntax that gets evaluated. The getValue method should escape or validate string values before returning them.\n",
      "classification": "slightly promising",
      "cwe": "CWE-917",
      "function_names": [
        "getValue"
      ],
      "filenames": [
        "implementation/src/main/java/io/smallrye/config/inject/ConfigProducer.java"
      ]
    }
  ],
  "scores": [
    {
      "stats": {
        "fn": 1,
        "tp": 0,
        "fp": 1
      },
      "mapping": {},
      "vuln_dates": {
        "CVE-2020-1729": "2021-05-28T14:15:07"
      },
      "scoring_model": "claude-3-5-sonnet-20240620",
      "type": "llm",
      "instruction_template_hash": "245ace12b6361954d0a2"
    }
  ],
  "instruction_template_hash": "10c0163db4740318a544",
  "version": "0.1.0"
}
