{
  "commit": "39aaa2bb3cfba1101173b5706438a0d9d6d0b229",
  "repo_url": "https://github.com/mannyvergel/oils-js",
  "model": "claude-3-sonnet-20240229",
  "chunk_hashes": [
    "0acce186267f69b8566a"
  ],
  "responses": [
    {
      "content": "```yaml\nleads:\n  - headline: Improper Validation of Array Index (CWE-129)\n    analysis: |\n      In the `Web.includeModelObj` function of `Web.js`, an object is extended with a parent object without properly validating the indices of the schema object. If the parent schema contains a malicious value for an array index, it could lead to arbitrary code execution or denial of service when the resulting object is accessed.\n    cwe: CWE-129\n    function_names:\n      - Web.includeModelObj\n    filenames:\n      - core/Web.js\n    classification: very promising\n\n  - headline: Potential Uncontrolled Resource Consumption (CWE-770)\n    analysis: |\n      The `queueLoader` function in `queueLoader.js` takes a stack of functions to execute and calls them recursively without any limits or throttling. This could lead to excessive resource consumption if one of the functions takes a long time to complete or gets stuck in an infinite loop.\n    cwe: CWE-770\n    function_names:\n      - queueLoader\n    filenames:\n      - core/utils/queueLoader.js\n    classification: very promising\n\n  - headline: Potential Path Traversal (CWE-22)\n    analysis: |\n      In the `FsLoader` class of `FsLoader.js`, the `load` function reads files from the filesystem without properly validating or sanitizing the input path. An attacker could potentially traverse directories and access arbitrary files on the server by providing a malicious path.\n    cwe: CWE-22\n    function_names:\n      - FsLoader.load\n    filenames:\n      - core/loaders/lib/FsLoader.js\n    classification: very promising\n\n  - headline: Use of Externally-Controlled Input to Select Classes or Code ('Unsafe Reflection') (CWE-470)\n    analysis: |\n      In the `Plugins` function of `plugins.js`, the path to the plugin module is constructed using externally-controlled input (`pluginConf.pluginPath`). If an attacker can control this value, they could potentially load and execute arbitrary code on the server.\n    cwe: CWE-470\n    function_names:\n      - Plugins\n    filenames:\n      - core/loaders/plugins.js\n    classification: very promising\n\n  - headline: Potential Unvalidated Redirect (CWE-601)\n    analysis: |\n      In the `customResponse` middleware of `response.js`, the application redirects the user's request if the URL ends with a trailing slash. However, the redirect URL is not properly validated, which could potentially lead to an open redirect vulnerability where an attacker could redirect users to a malicious site.\n    cwe: CWE-601\n    function_names:\n      - customResponse\n    filenames:\n      - core/custom/response.js\n    classification: slightly promising\n\n  - headline: Potential Hardcoded Credentials (CWE-798)\n    analysis: |\n      The `initServer` function in `Web.js` sets a hardcoded cookie key (\"hello oils 2014\"). Using a hardcoded key for cookie encryption can make it easier for attackers to gain unauthorized access to user sessions if the key is discovered.\n    cwe: CWE-798\n    function_names:\n      - Web.initServer\n    filenames:\n      - core/Web.js\n    classification: slightly promising\n```\n\nThe vulnerabilities identified include improper validation of array indices, potential uncontrolled resource consumption, path traversal, use of externally-controlled input to select code, potential unvalidated redirects, and potential hardcoded credentials. These vulnerabilities could lead to various security issues such as arbitrary code execution, denial of service, unauthorized file access, and session hijacking.",
      "date": "2024-06-14T14:45:36.960060",
      "usage": {
        "prompt_tokens": 18450,
        "completion_tokens": 890,
        "cost": 0.0687
      }
    }
  ],
  "leads": [
    {
      "headline": "Improper Validation of Array Index (CWE-129)",
      "analysis": "In the Web.includeModelObj function of Web.js, an object is extended with a parent object without properly validating the indices of the schema object. If the parent schema contains a malicious value for an array index, it could lead to arbitrary code execution or denial of service when the resulting object is accessed.\n",
      "classification": "very promising",
      "cwe": "CWE-129",
      "function_names": [
        "Web.includeModelObj"
      ],
      "filenames": [
        "core/Web.js"
      ]
    },
    {
      "headline": "Potential Uncontrolled Resource Consumption (CWE-770)",
      "analysis": "The queueLoader function in queueLoader.js takes a stack of functions to execute and calls them recursively without any limits or throttling. This could lead to excessive resource consumption if one of the functions takes a long time to complete or gets stuck in an infinite loop.\n",
      "classification": "very promising",
      "cwe": "CWE-770",
      "function_names": [
        "queueLoader"
      ],
      "filenames": [
        "core/utils/queueLoader.js"
      ]
    },
    {
      "headline": "Potential Path Traversal (CWE-22)",
      "analysis": "In the FsLoader class of FsLoader.js, the load function reads files from the filesystem without properly validating or sanitizing the input path. An attacker could potentially traverse directories and access arbitrary files on the server by providing a malicious path.\n",
      "classification": "very promising",
      "cwe": "CWE-22",
      "function_names": [
        "FsLoader.load"
      ],
      "filenames": [
        "core/loaders/lib/FsLoader.js"
      ]
    },
    {
      "headline": "Use of Externally-Controlled Input to Select Classes or Code ('Unsafe Reflection') (CWE-470)",
      "analysis": "In the Plugins function of plugins.js, the path to the plugin module is constructed using externally-controlled input (pluginConf.pluginPath). If an attacker can control this value, they could potentially load and execute arbitrary code on the server.\n",
      "classification": "very promising",
      "cwe": "CWE-470",
      "function_names": [
        "Plugins"
      ],
      "filenames": [
        "core/loaders/plugins.js"
      ]
    },
    {
      "headline": "Potential Unvalidated Redirect (CWE-601)",
      "analysis": "In the customResponse middleware of response.js, the application redirects the user's request if the URL ends with a trailing slash. However, the redirect URL is not properly validated, which could potentially lead to an open redirect vulnerability where an attacker could redirect users to a malicious site.\n",
      "classification": "slightly promising",
      "cwe": "CWE-601",
      "function_names": [
        "customResponse"
      ],
      "filenames": [
        "core/custom/response.js"
      ]
    },
    {
      "headline": "Potential Hardcoded Credentials (CWE-798)",
      "analysis": "The initServer function in Web.js sets a hardcoded cookie key (\"hello oils 2014\"). Using a hardcoded key for cookie encryption can make it easier for attackers to gain unauthorized access to user sessions if the key is discovered.\n",
      "classification": "slightly promising",
      "cwe": "CWE-798",
      "function_names": [
        "Web.initServer"
      ],
      "filenames": [
        "core/Web.js"
      ]
    }
  ],
  "scores": [
    {
      "stats": {
        "fn": 1,
        "tp": 0,
        "fp": 4
      },
      "mapping": {},
      "vuln_dates": {
        "CVE-2021-4260": "2022-12-19T14:15:10"
      },
      "scoring_model": "claude-3-opus-20240229",
      "type": "llm",
      "instruction_template_hash": "245ace12b6361954d0a2"
    }
  ],
  "instruction_template_hash": "10c0163db4740318a544",
  "version": "0.1.0"
}
