{
  "commit": "5f1d0e9acabb97508869a6a5852c3f5cdf280691",
  "repo_url": "https://github.com/chewkeanho/automataci",
  "model": "gpt-4o-2024-05-13",
  "chunk_hashes": [
    "2b016cab4dfc9ad811ce"
  ],
  "responses": [
    {
      "content": "```yaml\nleads:\n  - headline: Potential Injection Vulnerability in Shell Script\n    analysis: |\n      The script reads input from the environment or user which isn't properly sanitized before being passed to shell commands. This can be exploited to execute arbitrary commands, as seen in numerous calls to `OS::is_command_available` without proper validation or escaping of the command being passed. This type of vulnerability can lead to remote code execution if untrusted input is used in these commands.\n    cwe: CWE-78\n    function_names:\n      - OS::is_command_available\n    filenames:\n      - automataCI/env_unix-any.sh\n      - automataCI/_package-docker_unix-any.sh\n    classification: very promising\n\n  - headline: Python Dependency and Virtual Environment Management Issue\n    analysis: |\n      The script assumes that the virtual environment setup works correctly without checking. If the environment is compromised or manipulated, this can lead to execution of malicious code with the same security context as the executing script. The script should validate the virtual environment and dependencies thoroughly.\n    cwe: CWE-908\n    function_names:\n      - PYTHON::activate_venv\n      - INSTALLER::setup_python\n    filenames:\n      - automataCI/services/compilers/python.sh\n      - automataCI/services/compilers/installer.sh\n    classification: slightly promising\n\n  - headline: Potential Insecure Temporary File Creation\n    analysis: |\n      There are multiple instances of creating temporary files in `/tmp` or similar directories without proper permissions or unique naming conventions, leading to potential file hijacking or privilege escalation. For example, `FS::make_directory` may create directories with insecure permissions.\n    cwe: CWE-377\n    function_names:\n      - FS::make_directory\n    filenames:\n      - automataCI/services/io/fs.sh\n    classification: very promising\n\n  - headline: Insufficient Validation of Command Execution\n    analysis: |\n      On multiple occasions, command execution within the shell scripts is done without appropriate validation. The `docker` commands in particular assume that the commands will succeed and do not handle negative cases appropriately, which can be potentially exploited to disrupt the build process or inject malicious commands.\n    cwe: CWE-74\n    function_names:\n      - DOCKER::create\n    filenames:\n      - automataCI/_package-docker_unix-any.sh\n    classification: very promising\n\n  - headline: Exposure of Sensitive Information\n    analysis: |\n      Some scripts log information that could potentially include sensitive data, such as environment variables, paths, filenames, and configuration details. Exposing such information in logs can assist attackers in collecting important data that can be used in further attacks.\n    cwe: CWE-532\n    function_names:\n      - OS::print_status\n    filenames:\n      - automataCI/release_unix-any.sh\n    classification: slightly promising\n```",
      "date": "2024-06-09T09:44:40.122717",
      "usage": {
        "prompt_tokens": 48892,
        "completion_tokens": 594,
        "cost": 0.25337
      }
    }
  ],
  "leads": [
    {
      "headline": "Potential Injection Vulnerability in Shell Script",
      "analysis": "The script reads input from the environment or user which isn't properly sanitized before being passed to shell commands. This can be exploited to execute arbitrary commands, as seen in numerous calls to OS::is_command_available without proper validation or escaping of the command being passed. This type of vulnerability can lead to remote code execution if untrusted input is used in these commands.\n",
      "classification": "very promising",
      "cwe": "CWE-78",
      "function_names": [
        "OS::is_command_available"
      ],
      "filenames": [
        "automataCI/env_unix-any.sh",
        "automataCI/_package-docker_unix-any.sh"
      ]
    },
    {
      "headline": "Python Dependency and Virtual Environment Management Issue",
      "analysis": "The script assumes that the virtual environment setup works correctly without checking. If the environment is compromised or manipulated, this can lead to execution of malicious code with the same security context as the executing script. The script should validate the virtual environment and dependencies thoroughly.\n",
      "classification": "slightly promising",
      "cwe": "CWE-908",
      "function_names": [
        "PYTHON::activate_venv",
        "INSTALLER::setup_python"
      ],
      "filenames": [
        "automataCI/services/compilers/python.sh",
        "automataCI/services/compilers/installer.sh"
      ]
    },
    {
      "headline": "Potential Insecure Temporary File Creation",
      "analysis": "There are multiple instances of creating temporary files in /tmp or similar directories without proper permissions or unique naming conventions, leading to potential file hijacking or privilege escalation. For example, FS::make_directory may create directories with insecure permissions.\n",
      "classification": "very promising",
      "cwe": "CWE-377",
      "function_names": [
        "FS::make_directory"
      ],
      "filenames": [
        "automataCI/services/io/fs.sh"
      ]
    },
    {
      "headline": "Insufficient Validation of Command Execution",
      "analysis": "On multiple occasions, command execution within the shell scripts is done without appropriate validation. The docker commands in particular assume that the commands will succeed and do not handle negative cases appropriately, which can be potentially exploited to disrupt the build process or inject malicious commands.\n",
      "classification": "very promising",
      "cwe": "CWE-74",
      "function_names": [
        "DOCKER::create"
      ],
      "filenames": [
        "automataCI/_package-docker_unix-any.sh"
      ]
    },
    {
      "headline": "Exposure of Sensitive Information",
      "analysis": "Some scripts log information that could potentially include sensitive data, such as environment variables, paths, filenames, and configuration details. Exposing such information in logs can assist attackers in collecting important data that can be used in further attacks.\n",
      "classification": "slightly promising",
      "cwe": "CWE-532",
      "function_names": [
        "OS::print_status"
      ],
      "filenames": [
        "automataCI/release_unix-any.sh"
      ]
    }
  ],
  "scores": [
    {
      "stats": {
        "fn": 1,
        "tp": 0,
        "fp": 3
      },
      "mapping": {},
      "vuln_dates": {
        "CVE-2023-42798": "2023-09-22T16:15:09"
      },
      "scoring_model": "gpt-4o-2024-05-13",
      "type": "llm",
      "instruction_template_hash": "8998f09cf57fca8a6e03"
    }
  ],
  "instruction_template_hash": "10c0163db4740318a544",
  "version": "0.1.0"
}
