{
  "commit": "0b32641e0c0d7b89ff7e07fc99ef7bde5f654be5",
  "repo_url": "https://github.com/praqma/compatibility-action-storage-plugin",
  "model": "gpt-4o-2024-05-13",
  "chunk_hashes": [
    "8f62e811f9ebf3756063"
  ],
  "responses": [
    {
      "content": "```yaml\nleads:\n  - headline: \"Hardcoded Host and Port Values\"\n    analysis: |\n      The host and port values used for database connections are hardcoded in the test class `MongoProviderImplTest.java`. This can lead to potential security risks as these values may reveal details about the environment and can be exploited if the test code is executed in production environments inadvertently. It is good practice to externalize these configurations.\n    cwe: CWE-798\n    function_names:\n      - \"createTestSuccess\"\n      - \"readTestSuccess\"\n      - \"setUp\"\n    filenames:\n      - \"src/test/java/org/jenkinsci/plugins/compatibilityaction/MongoProviderImplTest.java\"\n    classification: \"slightly promising\"\n  - headline: \"Lack of Encryption for Passwords\"\n    analysis: |\n      The MongoDB connection password is managed using the `hudson.util.Secret` class, which offers a basic level of encryption. However, it is important to ensure that the passwords are encrypted using strong encryption mechanisms both in transit and at rest to prevent unauthorized access. Review the implementation to make sure the encryption mechanisms are up-to-date and strong enough.\n    cwe: CWE-311\n    function_names:\n      - \"createClient\"\n      - \"testConnection\"\n    filenames:\n      - \"src/main/java/org/jenkinsci/plugins/compatibilityaction/MongoDBHolderService.java\"\n    classification: \"very promising\"\n  - headline: \"Potential Vulnerability to Injection Attacks\"\n    analysis: |\n      The test methods in `MongoProviderImplTest.java` use untrusted input directly in database queries through the use of `BasicDBObject` which might lead to injection attacks if not properly sanitized. Ensure that all inputs are sanitized and validated to prevent such attacks.\n    cwe: CWE-74\n    function_names:\n      - \"readManyTestSuccess\"\n      - \"countTestSuccess\"\n      - \"listAndSort\"\n    filenames:\n      - \"src/test/java/org/jenkinsci/plugins/compatibilityaction/MongoProviderImplTest.java\"\n    classification: \"very promising\"\n  - headline: \"Use of Deprecated Classes and Methods\"\n    analysis: |\n      The test class is using deprecated classes such as `com.mongodb.DBCollection` and methods which might not be updated with the latest security patches and improvements. This could expose the system to known vulnerabilities that have been fixed in newer classes or methods. It is recommended to use the current version of the MongoDB Java driver and update the implementation accordingly.\n    cwe: CWE-670\n    function_names:\n      - \"readMany\"\n      - \"count\"\n      - \"listAndSort\"\n    filenames:\n      - \"src/main/java/org/jenkinsci/plugins/compatibilityaction/MongoProviderImpl.java\"\n    classification: \"slightly promising\"\n```\n\n",
      "date": "2024-06-13T11:07:00.363280",
      "usage": {
        "prompt_tokens": 8427,
        "completion_tokens": 583,
        "cost": 0.05088
      }
    }
  ],
  "leads": [
    {
      "headline": "Hardcoded Host and Port Values",
      "analysis": "The host and port values used for database connections are hardcoded in the test class MongoProviderImplTest.java. This can lead to potential security risks as these values may reveal details about the environment and can be exploited if the test code is executed in production environments inadvertently. It is good practice to externalize these configurations.\n",
      "classification": "slightly promising",
      "cwe": "CWE-798",
      "function_names": [
        "createTestSuccess",
        "readTestSuccess",
        "setUp"
      ],
      "filenames": [
        "src/test/java/org/jenkinsci/plugins/compatibilityaction/MongoProviderImplTest.java"
      ]
    },
    {
      "headline": "Lack of Encryption for Passwords",
      "analysis": "The MongoDB connection password is managed using the hudson.util.Secret class, which offers a basic level of encryption. However, it is important to ensure that the passwords are encrypted using strong encryption mechanisms both in transit and at rest to prevent unauthorized access. Review the implementation to make sure the encryption mechanisms are up-to-date and strong enough.\n",
      "classification": "very promising",
      "cwe": "CWE-311",
      "function_names": [
        "createClient",
        "testConnection"
      ],
      "filenames": [
        "src/main/java/org/jenkinsci/plugins/compatibilityaction/MongoDBHolderService.java"
      ]
    },
    {
      "headline": "Potential Vulnerability to Injection Attacks",
      "analysis": "The test methods in MongoProviderImplTest.java use untrusted input directly in database queries through the use of BasicDBObject which might lead to injection attacks if not properly sanitized. Ensure that all inputs are sanitized and validated to prevent such attacks.\n",
      "classification": "very promising",
      "cwe": "CWE-74",
      "function_names": [
        "readManyTestSuccess",
        "countTestSuccess",
        "listAndSort"
      ],
      "filenames": [
        "src/test/java/org/jenkinsci/plugins/compatibilityaction/MongoProviderImplTest.java"
      ]
    },
    {
      "headline": "Use of Deprecated Classes and Methods",
      "analysis": "The test class is using deprecated classes such as com.mongodb.DBCollection and methods which might not be updated with the latest security patches and improvements. This could expose the system to known vulnerabilities that have been fixed in newer classes or methods. It is recommended to use the current version of the MongoDB Java driver and update the implementation accordingly.\n",
      "classification": "slightly promising",
      "cwe": "CWE-670",
      "function_names": [
        "readMany",
        "count",
        "listAndSort"
      ],
      "filenames": [
        "src/main/java/org/jenkinsci/plugins/compatibilityaction/MongoProviderImpl.java"
      ]
    }
  ],
  "scores": [
    {
      "stats": {
        "fn": 1,
        "tp": 0,
        "fp": 2
      },
      "mapping": {},
      "vuln_dates": {
        "CVE-2020-2217": "2020-07-02T15:15:18"
      },
      "scoring_model": "claude-3-opus-20240229",
      "type": "llm",
      "instruction_template_hash": "245ace12b6361954d0a2"
    },
    {
      "stats": {
        "fn": 1,
        "tp": 0,
        "fp": 2
      },
      "mapping": {},
      "vuln_dates": {
        "CVE-2020-2217": "2020-07-02T15:15:18"
      },
      "scoring_model": "claude-3-5-sonnet-20240620",
      "type": "llm",
      "instruction_template_hash": "245ace12b6361954d0a2"
    }
  ],
  "instruction_template_hash": "10c0163db4740318a544",
  "version": "0.1.0"
}
