{
  "commit": "3d92db495900bfe3e01ffa0c81de880355eb0387",
  "repo_url": "https://github.com/onc-healthit/code-validator-api",
  "model": "claude-3-haiku-20240307",
  "chunk_hashes": [
    "6a5c73f7d4d8ef6ef183"
  ],
  "responses": [
    {
      "content": "```yaml\nleads:\n  - headline: Improper Input Validation\n    analysis: |\n      The codebase contains several instances of improper input validation, which could lead to vulnerabilities such as buffer overflow, integer overflow, and SQL injection. These vulnerabilities are commonly found in the validation of user input, such as in the processing of XML files, CSV files, and command-line arguments.\n    cwe: CWE-20\n    function_names:\n      - RequiredNodeValidator.validateNode\n      - ValueSetCodeValidator.validateNode\n      - CodeSystemCodeValidator.validateNode\n    filenames:\n      - src/main/java/org/sitenv/vocabularies/validation/validators/nodetypes/RequiredNodeValidator.java\n      - src/main/java/org/sitenv/vocabularies/validation/validators/nodetypes/ValueSetCodeValidator.java\n      - src/main/java/org/sitenv/vocabularies/validation/validators/nodetypes/CodeSystemCodeValidator.java\n    classification: slightly promising\n\n  - headline: Improper Neutralization of Special Elements in Output Used by a Downstream Component\n    analysis: |\n      The codebase uses user-provided input to construct SQL queries and execute them, which could lead to SQL injection vulnerabilities. This is particularly evident in the `CodeRepository` and `VsacValuesSetRepository` classes, where user-provided input is used to build SQL queries without proper sanitization.\n    cwe: CWE-74\n    function_names:\n      - CodeRepository.findByCodeAndCodeSystemIn\n      - VsacValuesSetRepository.existsByCodeAndCodeSystemAndCodeSystemNameAndDisplayNameInValuesetOid\n      - VsacValuesSetRepository.codeExistsInValueset\n    filenames:\n      - src/main/java/org/sitenv/vocabularies/validation/repositories/CodeRepository.java\n      - src/main/java/org/sitenv/vocabularies/validation/repositories/VsacValuesSetRepository.java\n    classification: slightly promising\n\n  - headline: Improper Encoding or Escaping of Output\n    analysis: |\n      The codebase does not properly encode or escape output, which could lead to cross-site scripting (XSS) vulnerabilities. This is particularly evident in the processing of user-provided input, such as display names and code system names, which are used in the construction of SQL queries and output without proper sanitization.\n    cwe: CWE-116\n    function_names:\n      - CodeRepository.foundCodeAndDisplayNameInCodesystem\n      - VsacValuesSetRepository.displayNameExistsInValueset\n      - VsacValuesSetRepository.codeSystemNameExistsInValueset\n    filenames:\n      - src/main/java/org/sitenv/vocabularies/validation/repositories/CodeRepository.java\n      - src/main/java/org/sitenv/vocabularies/validation/repositories/VsacValuesSetRepository.java\n    classification: slightly promising\n\n  - headline: Improper Restriction of Operations within the Bounds of a Memory Buffer\n    analysis: |\n      The codebase uses string manipulation and array indexing operations without proper bounds checking, which could lead to buffer overflow vulnerabilities. This is particularly evident in the `IcdLoader` and `CptLoader` classes, where user-provided input is used to construct SQL queries without proper validation.\n    cwe: CWE-119\n    function_names:\n      - IcdLoader.buildDelimitedIcdCode\n      - CptLoader.load\n    filenames:\n      - src/main/java/org/sitenv/vocabularies/loader/code/IcdLoader.java\n      - src/main/java/org/sitenv/vocabularies/loader/code/CptLoader.java\n    classification: slightly promising\n\n  - headline: Exposure of Sensitive Information to an Unauthorized Actor\n    analysis: |\n      The codebase does not properly handle error messages and log files, which could lead to the exposure of sensitive information. This is particularly evident in the `VocabularyValidationService` class, where error messages and stack traces are logged without proper sanitization.\n    cwe: CWE-200\n    function_names:\n      - VocabularyValidationService.validate\n    filenames:\n      - src/main/java/org/sitenv/vocabularies/validation/services/VocabularyValidationService.java\n    classification: slightly promising\n\n  - headline: Missing Encryption of Sensitive Data\n    analysis: |\n      The codebase does not properly encrypt sensitive data, such as passwords and credentials, which could lead to the exposure of this information. This is particularly evident in the use of hard-coded credentials and the lack of encryption for sensitive data stored in the database.\n    cwe: CWE-311\n    function_names:\n      - CodeRepository.findByCodeAndCodeSystemIn\n      - VsacValuesSetRepository.existsByCodeAndCodeSystemAndCodeSystemNameAndDisplayNameInValuesetOid\n    filenames:\n      - src/main/java/org/sitenv/vocabularies/validation/repositories/CodeRepository.java\n      - src/main/java/org/sitenv/vocabularies/validation/repositories/VsacValuesSetRepository.java\n    classification: slightly promising\n\n  - headline: Improper Synchronization\n    analysis: |\n      The codebase does not properly handle concurrent access to shared resources, which could lead to race condition vulnerabilities. This is particularly evident in the `VocabularyValidationService` class, where multiple threads may attempt to access and modify the same data structures concurrently.\n    cwe: CWE-662\n    function_names:\n      - VocabularyValidationService.validate\n    filenames:\n      - src/main/java/org/sitenv/vocabularies/validation/services/VocabularyValidationService.java\n    classification: slightly promising\n\n  - headline: Incorrect Resource Transfer Between Spheres\n    analysis: |\n      The codebase does not properly validate the integrity of data transferred between different components, which could lead to vulnerabilities such as file upload vulnerabilities and unsanitized input vulnerabilities. This is particularly evident in the processing of XML and CSV files, where user-provided input is used without proper validation.\n    cwe: CWE-669\n    function_names:\n      - VsacLoader.load\n      - CdtLoader.load\n    filenames:\n      - src/main/java/org/sitenv/vocabularies/loader/valueset/VsacLoader.java\n      - src/main/java/org/sitenv/vocabularies/loader/code/CdtLoader.java\n    classification: slightly promising\n\n  - headline: Incorrect Comparison\n    analysis: |\n      The codebase contains several instances of incorrect comparison operations, which could lead to vulnerabilities such as logic flaws and information disclosure. This is particularly evident in the `VocabularyValidationService` class, where the `limitSeverityForDynamicallySetValidators` method performs comparisons on `VocabularyValidationResultLevel` objects without properly handling edge cases.\n    cwe: CWE-697\n    function_names:\n      - VocabularyValidationService.limitSeverityForDynamicallySetValidators\n    filenames:\n      - src/main/java/org/sitenv/vocabularies/validation/services/VocabularyValidationService.java\n    classification: slightly promising\n\n  - headline: Improper Handling of Exceptional Conditions\n    analysis: |\n      The codebase does not properly handle exceptional conditions, which could lead to denial of service vulnerabilities and information disclosure. This is particularly evident in the `VocabularyValidationService` class, where exceptions are caught and logged without proper handling.\n    cwe: CWE-755\n    function_names:\n      - VocabularyValidationService.validate\n    filenames:\n      - src/main/java/org/sitenv/vocabularies/validation/services/VocabularyValidationService.java\n    classification: slightly promising\n\n  - headline: Improperly Controlled Modification of Object Prototype Attributes\n    analysis: |\n      The codebase uses reflection and dynamic code execution, which could lead to prototype pollution vulnerabilities. This is particularly evident in the `VocabularyValidationService` class, where the `selectVocabularyValidator` method uses reflection to instantiate and return `NodeValidation` objects.\n    cwe: CWE-1321\n    function_names:\n      - VocabularyValidationService.selectVocabularyValidator\n    filenames:\n      - src/main/java/org/sitenv/vocabularies/validation/services/VocabularyValidationService.java\n    classification: not promising\n\n  - headline: Deserialization of Untrusted Data\n    analysis: |\n      The codebase deserializes user-provided input, which could lead to remote code execution vulnerabilities. This is particularly evident in the `ValidationConfigurationLoader` class, where the `xmlToObject` method deserializes XML data without proper validation.\n    cwe: CWE-502\n    function_names:\n      - ValidationConfigurationLoader.xmlToObject\n    filenames:\n      - src/main/java/org/sitenv/vocabularies/configuration/ValidationConfigurationLoader.java\n    classification: slightly promising\n```",
      "date": "2024-06-14T15:03:03.086965",
      "usage": {
        "prompt_tokens": 58969,
        "completion_tokens": 2179,
        "cost": 0.017466
      }
    }
  ],
  "leads": [
    {
      "headline": "Improper Input Validation",
      "analysis": "The codebase contains several instances of improper input validation, which could lead to vulnerabilities such as buffer overflow, integer overflow, and SQL injection. These vulnerabilities are commonly found in the validation of user input, such as in the processing of XML files, CSV files, and command-line arguments.\n",
      "classification": "slightly promising",
      "cwe": "CWE-20",
      "function_names": [
        "RequiredNodeValidator.validateNode",
        "ValueSetCodeValidator.validateNode",
        "CodeSystemCodeValidator.validateNode"
      ],
      "filenames": [
        "src/main/java/org/sitenv/vocabularies/validation/validators/nodetypes/RequiredNodeValidator.java",
        "src/main/java/org/sitenv/vocabularies/validation/validators/nodetypes/ValueSetCodeValidator.java",
        "src/main/java/org/sitenv/vocabularies/validation/validators/nodetypes/CodeSystemCodeValidator.java"
      ]
    },
    {
      "headline": "Improper Neutralization of Special Elements in Output Used by a Downstream Component",
      "analysis": "The codebase uses user-provided input to construct SQL queries and execute them, which could lead to SQL injection vulnerabilities. This is particularly evident in the CodeRepository and VsacValuesSetRepository classes, where user-provided input is used to build SQL queries without proper sanitization.\n",
      "classification": "slightly promising",
      "cwe": "CWE-74",
      "function_names": [
        "CodeRepository.findByCodeAndCodeSystemIn",
        "VsacValuesSetRepository.existsByCodeAndCodeSystemAndCodeSystemNameAndDisplayNameInValuesetOid",
        "VsacValuesSetRepository.codeExistsInValueset"
      ],
      "filenames": [
        "src/main/java/org/sitenv/vocabularies/validation/repositories/CodeRepository.java",
        "src/main/java/org/sitenv/vocabularies/validation/repositories/VsacValuesSetRepository.java"
      ]
    },
    {
      "headline": "Improper Encoding or Escaping of Output",
      "analysis": "The codebase does not properly encode or escape output, which could lead to cross-site scripting (XSS) vulnerabilities. This is particularly evident in the processing of user-provided input, such as display names and code system names, which are used in the construction of SQL queries and output without proper sanitization.\n",
      "classification": "slightly promising",
      "cwe": "CWE-116",
      "function_names": [
        "CodeRepository.foundCodeAndDisplayNameInCodesystem",
        "VsacValuesSetRepository.displayNameExistsInValueset",
        "VsacValuesSetRepository.codeSystemNameExistsInValueset"
      ],
      "filenames": [
        "src/main/java/org/sitenv/vocabularies/validation/repositories/CodeRepository.java",
        "src/main/java/org/sitenv/vocabularies/validation/repositories/VsacValuesSetRepository.java"
      ]
    },
    {
      "headline": "Improper Restriction of Operations within the Bounds of a Memory Buffer",
      "analysis": "The codebase uses string manipulation and array indexing operations without proper bounds checking, which could lead to buffer overflow vulnerabilities. This is particularly evident in the IcdLoader and CptLoader classes, where user-provided input is used to construct SQL queries without proper validation.\n",
      "classification": "slightly promising",
      "cwe": "CWE-119",
      "function_names": [
        "IcdLoader.buildDelimitedIcdCode",
        "CptLoader.load"
      ],
      "filenames": [
        "src/main/java/org/sitenv/vocabularies/loader/code/IcdLoader.java",
        "src/main/java/org/sitenv/vocabularies/loader/code/CptLoader.java"
      ]
    },
    {
      "headline": "Exposure of Sensitive Information to an Unauthorized Actor",
      "analysis": "The codebase does not properly handle error messages and log files, which could lead to the exposure of sensitive information. This is particularly evident in the VocabularyValidationService class, where error messages and stack traces are logged without proper sanitization.\n",
      "classification": "slightly promising",
      "cwe": "CWE-200",
      "function_names": [
        "VocabularyValidationService.validate"
      ],
      "filenames": [
        "src/main/java/org/sitenv/vocabularies/validation/services/VocabularyValidationService.java"
      ]
    },
    {
      "headline": "Missing Encryption of Sensitive Data",
      "analysis": "The codebase does not properly encrypt sensitive data, such as passwords and credentials, which could lead to the exposure of this information. This is particularly evident in the use of hard-coded credentials and the lack of encryption for sensitive data stored in the database.\n",
      "classification": "slightly promising",
      "cwe": "CWE-311",
      "function_names": [
        "CodeRepository.findByCodeAndCodeSystemIn",
        "VsacValuesSetRepository.existsByCodeAndCodeSystemAndCodeSystemNameAndDisplayNameInValuesetOid"
      ],
      "filenames": [
        "src/main/java/org/sitenv/vocabularies/validation/repositories/CodeRepository.java",
        "src/main/java/org/sitenv/vocabularies/validation/repositories/VsacValuesSetRepository.java"
      ]
    },
    {
      "headline": "Improper Synchronization",
      "analysis": "The codebase does not properly handle concurrent access to shared resources, which could lead to race condition vulnerabilities. This is particularly evident in the VocabularyValidationService class, where multiple threads may attempt to access and modify the same data structures concurrently.\n",
      "classification": "slightly promising",
      "cwe": "CWE-662",
      "function_names": [
        "VocabularyValidationService.validate"
      ],
      "filenames": [
        "src/main/java/org/sitenv/vocabularies/validation/services/VocabularyValidationService.java"
      ]
    },
    {
      "headline": "Incorrect Resource Transfer Between Spheres",
      "analysis": "The codebase does not properly validate the integrity of data transferred between different components, which could lead to vulnerabilities such as file upload vulnerabilities and unsanitized input vulnerabilities. This is particularly evident in the processing of XML and CSV files, where user-provided input is used without proper validation.\n",
      "classification": "slightly promising",
      "cwe": "CWE-669",
      "function_names": [
        "VsacLoader.load",
        "CdtLoader.load"
      ],
      "filenames": [
        "src/main/java/org/sitenv/vocabularies/loader/valueset/VsacLoader.java",
        "src/main/java/org/sitenv/vocabularies/loader/code/CdtLoader.java"
      ]
    },
    {
      "headline": "Incorrect Comparison",
      "analysis": "The codebase contains several instances of incorrect comparison operations, which could lead to vulnerabilities such as logic flaws and information disclosure. This is particularly evident in the VocabularyValidationService class, where the limitSeverityForDynamicallySetValidators method performs comparisons on VocabularyValidationResultLevel objects without properly handling edge cases.\n",
      "classification": "slightly promising",
      "cwe": "CWE-697",
      "function_names": [
        "VocabularyValidationService.limitSeverityForDynamicallySetValidators"
      ],
      "filenames": [
        "src/main/java/org/sitenv/vocabularies/validation/services/VocabularyValidationService.java"
      ]
    },
    {
      "headline": "Improper Handling of Exceptional Conditions",
      "analysis": "The codebase does not properly handle exceptional conditions, which could lead to denial of service vulnerabilities and information disclosure. This is particularly evident in the VocabularyValidationService class, where exceptions are caught and logged without proper handling.\n",
      "classification": "slightly promising",
      "cwe": "CWE-755",
      "function_names": [
        "VocabularyValidationService.validate"
      ],
      "filenames": [
        "src/main/java/org/sitenv/vocabularies/validation/services/VocabularyValidationService.java"
      ]
    },
    {
      "headline": "Improperly Controlled Modification of Object Prototype Attributes",
      "analysis": "The codebase uses reflection and dynamic code execution, which could lead to prototype pollution vulnerabilities. This is particularly evident in the VocabularyValidationService class, where the selectVocabularyValidator method uses reflection to instantiate and return NodeValidation objects.\n",
      "classification": "not promising",
      "cwe": "CWE-1321",
      "function_names": [
        "VocabularyValidationService.selectVocabularyValidator"
      ],
      "filenames": [
        "src/main/java/org/sitenv/vocabularies/validation/services/VocabularyValidationService.java"
      ]
    },
    {
      "headline": "Deserialization of Untrusted Data",
      "analysis": "The codebase deserializes user-provided input, which could lead to remote code execution vulnerabilities. This is particularly evident in the ValidationConfigurationLoader class, where the xmlToObject method deserializes XML data without proper validation.\n",
      "classification": "slightly promising",
      "cwe": "CWE-502",
      "function_names": [
        "ValidationConfigurationLoader.xmlToObject"
      ],
      "filenames": [
        "src/main/java/org/sitenv/vocabularies/configuration/ValidationConfigurationLoader.java"
      ]
    }
  ],
  "scores": [
    {
      "stats": {
        "fn": 1,
        "tp": 0,
        "fp": 0
      },
      "mapping": {},
      "vuln_dates": {
        "CVE-2021-4295": "2022-12-29T09:15:08"
      },
      "scoring_model": "claude-3-opus-20240229",
      "type": "llm",
      "instruction_template_hash": "245ace12b6361954d0a2"
    }
  ],
  "instruction_template_hash": "10c0163db4740318a544",
  "version": "0.1.0"
}
