{
  "commit": "4084ea18f96d9a953315f5555fca45f26639b8be",
  "repo_url": "https://github.com/cyanomiko/dcnnt-py",
  "model": "gemini/gemini-1.5-pro",
  "chunk_hashes": [
    "ae7b8d1efa8980c63a92"
  ],
  "responses": [
    {
      "content": "```yaml\nleads:\n  - headline: Cleartext storage of sensitive information in configuration files.\n    analysis: |\n      The application stores device passwords and potentially other sensitive information in plaintext within JSON configuration files. \n      These files are saved on the filesystem, potentially exposing the sensitive data if the filesystem is compromised.\n    cwe: CWE-312\n    function_names:\n      - dump_device\n      - dump\n    filenames:\n      - dcnnt/device_manager.py\n    classification: slightly promising\n  - headline: Missing input validation for plugin configuration.\n    analysis: |\n      The plugin configuration loading mechanism in `PluginInitializer` lacks proper input validation. \n      This could lead to vulnerabilities if malicious or malformed configurations are provided, potentially allowing for arbitrary code execution.\n    cwe: CWE-20\n    function_names:\n      - init_plugin\n    filenames:\n      - dcnnt/plugins/base.py\n    classification: slightly promising\n  - headline: Potential command injection vulnerability in TemplateEntry.\n    analysis: |\n      The `TemplateEntry` class, used for configuration entries containing templates, might be vulnerable to command injection. \n      If an attacker can control the values used for template replacements, they might be able to inject arbitrary commands that would be executed by the application.\n    cwe: CWE-77\n    function_names:\n      - check\n    filenames:\n      - dcnnt/common/jsonconf.py\n    classification: slightly promising\n  - headline: Unrestricted upload of file with dangerous type.\n    analysis: |\n      The application allows for file uploads from client devices without sufficient restrictions on file types or content. \n      This could potentially allow an attacker to upload and execute arbitrary files on the server.\n    cwe: CWE-434\n    function_names:\n      - handle_upload\n      - _receive_file\n      - receive_file_to_path\n      - receive_file\n    filenames:\n      - dcnnt/plugins/file_transfer.py\n      - dcnnt/plugins/base.py\n    classification: very promising\n  - headline: Potential command injection in SyncPlugin on_done and on_merge commands.\n    analysis: |\n      The SyncPlugin allows defining custom commands to be executed after synchronization tasks. \n      The 'on_done' and 'on_merge' parameters in the configuration can potentially be used for command injection if they are not properly sanitized. \n      An attacker could potentially modify these parameters to execute arbitrary commands on the server.\n    cwe: CWE-77\n    function_names:\n      - handle_dir_list\n      - common_upload_handler\n      - handle_file_upload\n    filenames:\n      - dcnnt/plugins/sync.py\n    classification: very promising\n  - headline: Lack of input validation for filenames in OpenerPlugin.\n    analysis: |\n      The OpenerPlugin does not sufficiently validate the filenames received in requests to open files. \n      An attacker could potentially craft a malicious filename that, when opened, could lead to arbitrary code execution or other security issues.\n    cwe: CWE-20\n    function_names:\n      - handle_open_file\n    filenames:\n      - dcnnt/plugins/opener.py\n    classification: slightly promising\n  - headline: Unquoted Search Path or Element in OpenerPlugin.\n    analysis: |\n      The OpenerPlugin constructs command strings using user-supplied data without proper quoting or escaping, particularly in `handle_open_file` and `handle_open_link`. \n      This lack of quoting allows an attacker who can control the supplied data to potentially inject arbitrary commands.\n    cwe: CWE-428\n    function_names:\n      - handle_open_file\n      - handle_open_link\n    filenames:\n      - dcnnt/plugins/opener.py\n    classification: very promising\n```",
      "date": "2024-06-12T12:00:00.532873",
      "usage": {
        "prompt_tokens": 22961,
        "completion_tokens": 758,
        "cost": 0.0883225
      }
    }
  ],
  "leads": [
    {
      "headline": "Cleartext storage of sensitive information in configuration files.",
      "analysis": "The application stores device passwords and potentially other sensitive information in plaintext within JSON configuration files. \nThese files are saved on the filesystem, potentially exposing the sensitive data if the filesystem is compromised.\n",
      "classification": "slightly promising",
      "cwe": "CWE-312",
      "function_names": [
        "dump_device",
        "dump"
      ],
      "filenames": [
        "dcnnt/device_manager.py"
      ]
    },
    {
      "headline": "Missing input validation for plugin configuration.",
      "analysis": "The plugin configuration loading mechanism in PluginInitializer lacks proper input validation. \nThis could lead to vulnerabilities if malicious or malformed configurations are provided, potentially allowing for arbitrary code execution.\n",
      "classification": "slightly promising",
      "cwe": "CWE-20",
      "function_names": [
        "init_plugin"
      ],
      "filenames": [
        "dcnnt/plugins/base.py"
      ]
    },
    {
      "headline": "Potential command injection vulnerability in TemplateEntry.",
      "analysis": "The TemplateEntry class, used for configuration entries containing templates, might be vulnerable to command injection. \nIf an attacker can control the values used for template replacements, they might be able to inject arbitrary commands that would be executed by the application.\n",
      "classification": "slightly promising",
      "cwe": "CWE-77",
      "function_names": [
        "check"
      ],
      "filenames": [
        "dcnnt/common/jsonconf.py"
      ]
    },
    {
      "headline": "Unrestricted upload of file with dangerous type.",
      "analysis": "The application allows for file uploads from client devices without sufficient restrictions on file types or content. \nThis could potentially allow an attacker to upload and execute arbitrary files on the server.\n",
      "classification": "very promising",
      "cwe": "CWE-434",
      "function_names": [
        "handle_upload",
        "_receive_file",
        "receive_file_to_path"
      ],
      "filenames": [
        "dcnnt/plugins/file_transfer.py",
        "dcnnt/plugins/base.py"
      ]
    },
    {
      "headline": "Potential command injection in SyncPlugin on_done and on_merge commands.",
      "analysis": "The SyncPlugin allows defining custom commands to be executed after synchronization tasks. \nThe 'on_done' and 'on_merge' parameters in the configuration can potentially be used for command injection if they are not properly sanitized. \nAn attacker could potentially modify these parameters to execute arbitrary commands on the server.\n",
      "classification": "very promising",
      "cwe": "CWE-77",
      "function_names": [
        "handle_dir_list",
        "common_upload_handler",
        "handle_file_upload"
      ],
      "filenames": [
        "dcnnt/plugins/sync.py"
      ]
    },
    {
      "headline": "Lack of input validation for filenames in OpenerPlugin.",
      "analysis": "The OpenerPlugin does not sufficiently validate the filenames received in requests to open files. \nAn attacker could potentially craft a malicious filename that, when opened, could lead to arbitrary code execution or other security issues.\n",
      "classification": "slightly promising",
      "cwe": "CWE-20",
      "function_names": [
        "handle_open_file"
      ],
      "filenames": [
        "dcnnt/plugins/opener.py"
      ]
    },
    {
      "headline": "Unquoted Search Path or Element in OpenerPlugin.",
      "analysis": "The OpenerPlugin constructs command strings using user-supplied data without proper quoting or escaping, particularly in handle_open_file and handle_open_link. \nThis lack of quoting allows an attacker who can control the supplied data to potentially inject arbitrary commands.\n",
      "classification": "very promising",
      "cwe": "CWE-428",
      "function_names": [
        "handle_open_file",
        "handle_open_link"
      ],
      "filenames": [
        "dcnnt/plugins/opener.py"
      ]
    }
  ],
  "scores": [
    {
      "stats": {
        "fn": 1,
        "tp": 0,
        "fp": 3
      },
      "mapping": {},
      "vuln_dates": {
        "CVE-2023-1000": "2024-04-27T09:15:08"
      },
      "scoring_model": "claude-3-opus-20240229",
      "type": "llm",
      "instruction_template_hash": "245ace12b6361954d0a2"
    },
    {
      "stats": {
        "fn": 1,
        "tp": 0,
        "fp": 3
      },
      "mapping": {},
      "vuln_dates": {
        "CVE-2023-1000": "2024-04-27T09:15:08"
      },
      "scoring_model": "claude-3-5-sonnet-20240620",
      "type": "llm",
      "instruction_template_hash": "245ace12b6361954d0a2"
    }
  ],
  "instruction_template_hash": "10c0163db4740318a544",
  "version": "0.1.0"
}
