{
  "commit": "73ccbe912fc1848957d8b2f6bbe5243804769d85",
  "repo_url": "https://github.com/filebrowser/filebrowser",
  "model": "gpt-4o-2024-05-13",
  "chunk_hashes": [
    "c095a0fb9ce1bbff2ee1"
  ],
  "responses": [
    {
      "content": "```yaml\nleads:\n  - headline: \"Potential XSS Vulnerability in i18n\"\n    analysis: |\n      The `detectLocale` function in `frontend/src/i18n/index.js` uses user-supplied input from the browser's language settings to dynamically set the application's locale. If an attacker can manipulate the browser's language settings or inject malicious input, they may be able to perform cross-site scripting (XSS) attacks by tricking the application into executing arbitrary scripts.\n    cwe: CWE-79\n    function_names:\n      - detectLocale\n    filenames:\n      - frontend/src/i18n/index.js\n    classification: very promising\n\n  - headline: \"Insufficient Authentication for Admin Features\"\n    analysis: |\n      In the router setup in `frontend/src/router/index.js`, there is a check for `requiresAdmin` to enforce administrative permissions. However, a missing or improper check might allow unauthorized users to access admin functionalities, potentially leading to privilege escalation.\n    cwe: CWE-287\n    function_names:\n      - router.beforeEach\n    filenames:\n      - frontend/src/router/index.js\n    classification: slightly promising\n\n  - headline: \"Potential Vulnerability Due to Hardcoded Secrets\"\n    analysis: |\n      The code in `frontend/src/utils/constants.js` defines various constants such as `recaptchaKey` that seem to include sensitive data. Hardcoding such secrets in the client-side code can expose them to attackers, leading to compromised security mechanisms.\n    cwe: CWE-798\n    function_names: []\n    filenames:\n      - frontend/src/utils/constants.js\n    classification: very promising\n\n  - headline: \"Insufficient Token Protection\"\n    analysis: |\n      The authentication mechanism saves the JWT token in the `localStorage` in `frontend/src/utils/auth.js`. LocalStorage is accessible via JavaScript and is therefore vulnerable to XSS attacks. A better approach would be to use `HttpOnly` cookies to store such sensitive tokens, preventing them from being accessible via JavaScript.\n    cwe: CWE-287\n    function_names:\n      - login\n      - renew\n    filenames:\n      - frontend/src/utils/auth.js\n    classification: very promising\n\n  - headline: \"Improper Error Handling in API Requests\"\n    analysis: |\n      Several API functions in `frontend/src/api` files handle errors by throwing the response status or response text, without sanitizing or logging the error details appropriately. This can leak sensitive information and is not user-friendly.\n    cwe: CWE-209\n    function_names: []\n    filenames:\n      - frontend/src/api/users.js\n      - frontend/src/api/files.js\n    classification: slightly promising\n\n  - headline: \"Insecure Configuration in 'vue.config.js'\"\n    analysis: |\n      The `frontend/vue.config.js` file sets potentially insecure default values for `publicPath`. Depending on the environment and usage, this might lead to exposure of sensitive paths or improper loading of assets.\n    cwe: CWE-1188\n    function_names: []\n    filenames:\n      - frontend/vue.config.js\n    classification: not promising\n```",
      "date": "2024-06-09T11:59:51.075657",
      "usage": {
        "prompt_tokens": 12890,
        "completion_tokens": 636,
        "cost": 0.07399
      }
    }
  ],
  "leads": [
    {
      "headline": "Potential XSS Vulnerability in i18n",
      "analysis": "The detectLocale function in frontend/src/i18n/index.js uses user-supplied input from the browser's language settings to dynamically set the application's locale. If an attacker can manipulate the browser's language settings or inject malicious input, they may be able to perform cross-site scripting (XSS) attacks by tricking the application into executing arbitrary scripts.\n",
      "classification": "very promising",
      "cwe": "CWE-79",
      "function_names": [
        "detectLocale"
      ],
      "filenames": [
        "frontend/src/i18n/index.js"
      ]
    },
    {
      "headline": "Insufficient Authentication for Admin Features",
      "analysis": "In the router setup in frontend/src/router/index.js, there is a check for requiresAdmin to enforce administrative permissions. However, a missing or improper check might allow unauthorized users to access admin functionalities, potentially leading to privilege escalation.\n",
      "classification": "slightly promising",
      "cwe": "CWE-287",
      "function_names": [
        "router.beforeEach"
      ],
      "filenames": [
        "frontend/src/router/index.js"
      ]
    },
    {
      "headline": "Potential Vulnerability Due to Hardcoded Secrets",
      "analysis": "The code in frontend/src/utils/constants.js defines various constants such as recaptchaKey that seem to include sensitive data. Hardcoding such secrets in the client-side code can expose them to attackers, leading to compromised security mechanisms.\n",
      "classification": "very promising",
      "cwe": "CWE-798",
      "function_names": [],
      "filenames": [
        "frontend/src/utils/constants.js"
      ]
    },
    {
      "headline": "Insufficient Token Protection",
      "analysis": "The authentication mechanism saves the JWT token in the localStorage in frontend/src/utils/auth.js. LocalStorage is accessible via JavaScript and is therefore vulnerable to XSS attacks. A better approach would be to use HttpOnly cookies to store such sensitive tokens, preventing them from being accessible via JavaScript.\n",
      "classification": "very promising",
      "cwe": "CWE-287",
      "function_names": [
        "login",
        "renew"
      ],
      "filenames": [
        "frontend/src/utils/auth.js"
      ]
    },
    {
      "headline": "Improper Error Handling in API Requests",
      "analysis": "Several API functions in frontend/src/api files handle errors by throwing the response status or response text, without sanitizing or logging the error details appropriately. This can leak sensitive information and is not user-friendly.\n",
      "classification": "slightly promising",
      "cwe": "CWE-209",
      "function_names": [],
      "filenames": [
        "frontend/src/api/users.js",
        "frontend/src/api/files.js"
      ]
    },
    {
      "headline": "Insecure Configuration in 'vue.config.js'",
      "analysis": "The frontend/vue.config.js file sets potentially insecure default values for publicPath. Depending on the environment and usage, this might lead to exposure of sensitive paths or improper loading of assets.\n",
      "classification": "not promising",
      "cwe": "CWE-1188",
      "function_names": [],
      "filenames": [
        "frontend/vue.config.js"
      ]
    }
  ],
  "scores": [
    {
      "stats": {
        "fn": 3,
        "tp": 0,
        "fp": 3
      },
      "mapping": {},
      "vuln_dates": {
        "CVE-2023-39612": "2023-09-16T01:15:07",
        "CVE-2021-46398": "2022-02-04T16:15:07",
        "CVE-2021-37794": "2021-08-31T18:15:08"
      },
      "scoring_model": "gpt-4o-2024-05-13",
      "type": "llm",
      "instruction_template_hash": "8998f09cf57fca8a6e03"
    }
  ],
  "instruction_template_hash": "10c0163db4740318a544",
  "version": "0.1.0"
}
