{
  "commit": "2ff197d53963d55dcba5b23d039e995307f94fee",
  "repo_url": "https://github.com/xpleaf/blog_mini",
  "model": "gpt-4-turbo-2024-04-09",
  "chunk_hashes": [
    "15dc9be9fb40fa12271f"
  ],
  "responses": [
    {
      "content": "```yaml\nleads:\n  - headline: Unrestricted File Upload via Blog Articles\n    analysis: |\n      The application allows administrative users to submit articles which include an unrestricted file upload functionality. This is evident in the submission forms where there is no validation on the types of files that can be uploaded, nor is there any sanitization performed on these files. This can lead to the upload of potentially malicious files that could be executed on the server or by other users, leading to severe security breaches such as executing arbitrary code, stealing sensitive information, or further exploiting the system.\n    cwe: CWE-434 Unrestricted Upload of File with Dangerous Type\n    function_names:\n      - submitArticles\n      - editArticles\n    filenames:\n      - app/admin/views.py\n      - app/templates/admin/submit_articles.html\n    classification: very promising\n\n  - headline: SQL Injection via Article and Comment Management\n    analysis: |\n      The application appears to permit SQL injection through various management interfaces. This issue arises because the application constructs SQL queries directly using form input data without proper sanitization or prepared statements. For example, in the 'delete_article', 'editArticles', and 'manage_articles' functions, user input is directly interpolated into SQL commands that are then executed. This could allow attackers to manipulate these queries to access, modify, or delete data in the SQL database, or gain unauthorized access to the database.\n    cwe: CWE-89 Improper Neutralization of Special Elements used in an SQL Command ('SQL Injection')\n    function_names:\n      - manage_articles\n      - delete_article\n      - editArticles\n    filenames:\n      - app/admin/views.py\n    classification: very promising\n\n  - headline: Cross-Site Scripting (XSS) in Comments and Article Fields\n    analysis: |\n      There is a potential for XSS where user-supplied input in comments or articles is reflected back to other users without proper input sanitization or output encoding. Malicious scripts could be injected through the comment or article content fields, which are then executed in the browser of any user viewing those comments or articles. This could further lead to session hijacking, website defacement, or redirection to malicious sites.\n    cwe: CWE-79 Improper Neutralization of Input During Web Page Generation ('Cross-site Scripting')\n    function_names:\n      - articleDetails\n      - submitArticles\n      - manage_comments\n    filenames:\n      - app/main/views.py\n      - app/templates/article_detials.html\n    classification: very promising\n\n  - headline: Insecure User Authentication Token Storage\n    analysis: |\n      The application appears to be storing session tokens and other sensitive authentication cookies without proper security attributes. This is indicated in the session management and CSRF protection implementations, which do not consistently use the 'HttpOnly' and 'Secure' flags. This could allow session tokens to be accessed by client-side scripts or intercepted over an insecure connection, leading to account takeovers or data breaches.\n    cwe: CWE-522 Insufficiently Protected Credentials\n    function_names:\n      - create_app\n    filenames:\n      - app/__init__.py\n    classification: slightly promising\n\n  - headline: Uncontrolled Application Resource Consumption\n    analysis: |\n      Through the administrative functions that allow bulk deletion or creation of articles, comments, or user accounts without rate limiting or other controls, an authenticated user could issue a large number of requests in a short time. This might lead to denial of service by overwhelming the application with a high load or depleting system resources.\n    cwe: CWE-770 Allocation of Resources Without Limits or Throttling\n    function_names:\n      - delete_articles\n      - manage_comments\n      - delete_comments\n    filenames:\n      - app/admin/views.py\n    classification: slightly promising\n```",
      "date": "2024-06-14T10:53:30.170081",
      "usage": {
        "prompt_tokens": 57917,
        "completion_tokens": 770,
        "cost": 0.60227
      }
    }
  ],
  "leads": [
    {
      "headline": "Unrestricted File Upload via Blog Articles",
      "analysis": "The application allows administrative users to submit articles which include an unrestricted file upload functionality. This is evident in the submission forms where there is no validation on the types of files that can be uploaded, nor is there any sanitization performed on these files. This can lead to the upload of potentially malicious files that could be executed on the server or by other users, leading to severe security breaches such as executing arbitrary code, stealing sensitive information, or further exploiting the system.\n",
      "classification": "very promising",
      "cwe": "CWE-434 Unrestricted Upload of File with Dangerous Type",
      "function_names": [
        "submitArticles",
        "editArticles"
      ],
      "filenames": [
        "app/admin/views.py",
        "app/templates/admin/submit_articles.html"
      ]
    },
    {
      "headline": "SQL Injection via Article and Comment Management",
      "analysis": "The application appears to permit SQL injection through various management interfaces. This issue arises because the application constructs SQL queries directly using form input data without proper sanitization or prepared statements. For example, in the 'delete_article', 'editArticles', and 'manage_articles' functions, user input is directly interpolated into SQL commands that are then executed. This could allow attackers to manipulate these queries to access, modify, or delete data in the SQL database, or gain unauthorized access to the database.\n",
      "classification": "very promising",
      "cwe": "CWE-89 Improper Neutralization of Special Elements used in an SQL Command ('SQL Injection')",
      "function_names": [
        "manage_articles",
        "delete_article",
        "editArticles"
      ],
      "filenames": [
        "app/admin/views.py"
      ]
    },
    {
      "headline": "Cross-Site Scripting (XSS) in Comments and Article Fields",
      "analysis": "There is a potential for XSS where user-supplied input in comments or articles is reflected back to other users without proper input sanitization or output encoding. Malicious scripts could be injected through the comment or article content fields, which are then executed in the browser of any user viewing those comments or articles. This could further lead to session hijacking, website defacement, or redirection to malicious sites.\n",
      "classification": "very promising",
      "cwe": "CWE-79 Improper Neutralization of Input During Web Page Generation ('Cross-site Scripting')",
      "function_names": [
        "articleDetails",
        "submitArticles",
        "manage_comments"
      ],
      "filenames": [
        "app/main/views.py",
        "app/templates/article_detials.html"
      ]
    },
    {
      "headline": "Insecure User Authentication Token Storage",
      "analysis": "The application appears to be storing session tokens and other sensitive authentication cookies without proper security attributes. This is indicated in the session management and CSRF protection implementations, which do not consistently use the 'HttpOnly' and 'Secure' flags. This could allow session tokens to be accessed by client-side scripts or intercepted over an insecure connection, leading to account takeovers or data breaches.\n",
      "classification": "slightly promising",
      "cwe": "CWE-522 Insufficiently Protected Credentials",
      "function_names": [
        "create_app"
      ],
      "filenames": [
        "app/__init__.py"
      ]
    },
    {
      "headline": "Uncontrolled Application Resource Consumption",
      "analysis": "Through the administrative functions that allow bulk deletion or creation of articles, comments, or user accounts without rate limiting or other controls, an authenticated user could issue a large number of requests in a short time. This might lead to denial of service by overwhelming the application with a high load or depleting system resources.\n",
      "classification": "slightly promising",
      "cwe": "CWE-770 Allocation of Resources Without Limits or Throttling",
      "function_names": [
        "delete_articles",
        "manage_comments",
        "delete_comments"
      ],
      "filenames": [
        "app/admin/views.py"
      ]
    }
  ],
  "scores": [
    {
      "stats": {
        "fn": 2,
        "tp": 1,
        "fp": 2
      },
      "mapping": {
        "2": "CVE-2019-9765"
      },
      "vuln_dates": {
        "CVE-2019-9765": "2019-03-14T09:29:00",
        "CVE-2020-18999": "2021-08-27T19:15:07",
        "CVE-2020-18998": "2021-08-27T19:15:07"
      },
      "scoring_model": "claude-3-opus-20240229",
      "type": "llm",
      "instruction_template_hash": "245ace12b6361954d0a2"
    }
  ],
  "instruction_template_hash": "10c0163db4740318a544",
  "version": "0.1.0"
}
