{
  "commit": "304fdc53ab0d648ccc668f88c2f4280e15182c5e",
  "repo_url": "https://github.com/e-contract/dssp",
  "model": "gpt-4o-2024-05-13",
  "chunk_hashes": [
    "0ffe498b582f920d18af"
  ],
  "responses": [
    {
      "content": "```yaml\nleads:\n  - headline: \"Potential Deserialization Vulnerability\"\n    analysis: |\n      The use of `ObjectOutputStream` for serialization and deserialization in `DigitalSignatureServiceSessionTest` can be risky if the serialized data is from an untrusted source. This can lead to deserialization attacks, where maliciously crafted input could lead to arbitrary code execution or other unwanted behavior.\n    cwe: CWE-502\n    function_names:\n      - testSerialization\n    filenames:\n      - dssp-client/src/test/java/test/unit/be/e_contract/dssp/client/DigitalSignatureServiceSessionTest.java\n    classification: very promising\n\n  - headline: \"Use of Hard-Coded Credentials\"\n    analysis: |\n      The class `CallbackTestHandler` contains public static variables `tokenKey` and `password` which are used to store credentials. Hard-coded credentials can lead to security vulnerabilities as they can be extracted and misused.\n    cwe: CWE-798\n    function_names:\n      - handle\n    filenames:\n      - dssp-client/src/test/java/test/unit/be/e_contract/dssp/client/CallbackTestHandler.java\n    classification: very promising\n\n  - headline: \"Weak Encryption Strength\"\n    analysis: |\n      The use of \"HMACSHA1\" in `PendingRequestFactory` and `SignResponseVerifier` is considered weak due to known vulnerabilities in SHA-1. It is recommended to use stronger algorithms like SHA-256.\n    cwe: CWE-326\n    function_names:\n      - sign\n    filenames:\n      - dssp-client/src/main/java/be/e_contract/dssp/client/PendingRequestFactory.java\n      - dssp-client/src/main/java/be/e_contract/dssp/client/SignResponseVerifier.java\n    classification: very promising\n\n  - headline: \"Missing Authorization Checks\"\n    analysis: |\n      The class `WSSecuritySOAPHandler` does not appear to have explicit authorization checks when processing the security tokens or user credentials. This could allow unauthorized access if other parts of the system rely on this handler for security enforcement.\n    cwe: CWE-862\n    function_names:\n      - handleMessage\n    filenames:\n      - dssp-client/src/main/java/be/e_contract/dssp/client/impl/WSSecuritySOAPHandler.java\n    classification: slightly promising\n\n  - headline: \"Insecure Random Number Generation\"\n    analysis: |\n      The use of `SecureRandom` without explicit seeding in cryptographic operations could result in predictable values on older Java versions where the default seeding mechanism may be weak.\n    cwe: CWE-330\n    function_names:\n      - <various>\n    filenames:\n      - dssp-client/src/test/java/test/unit/be/e_contract/dssp/client/SignResponseVerifierTest.java\n      - dssp-client/src/main/java/be/e_contract/dssp/client/DigitalSignatureServiceClient.java\n      - dssp-client/src/main/java/be/e_contract/dssp/client/SignResponseFactory.java\n    classification: slightly promising\n\n  - headline: \"Improper Validation of Certificate\"\n    analysis: |\n      The function `verifyTrust` in `WSSecurityCrypto` returns false unconditionally, indicating that trust validation logic might not be properly implemented. This could lead to accepting untrusted certificates.\n    cwe: CWE-295\n    function_names:\n      - verifyTrust\n    filenames:\n      - dssp-client/src/main/java/be/e_contract/dssp/client/impl/WSSecurityCrypto.java\n    classification: very promising\n\n  - headline: \"Missing Encryption of Sensitive Data\"\n    analysis: |\n      Sensitive information such as tokens and keys in `DigitalSignatureServiceSession` and `CallbackTestHandler` are stored in plain byte arrays and public static variables, respectively. They should be encrypted in storage to prevent unauthorized access.\n    cwe: CWE-311\n    function_names:\n      - <various>\n    filenames:\n      - dssp-client/src/main/java/be/e_contract/dssp/client/DigitalSignatureServiceSession.java\n      - dssp-client/src/test/java/test/unit/be/e_contract/dssp/client/CallbackTestHandler.java\n    classification: very promising\n```\n\nThis YAML object identifies potential security vulnerabilities in the codebase provided, following the LeadList schema defined using Pydantic. Each identified vulnerability includes a headline, an in-depth analysis, a relevant CWE ID, and associated function names and filenames for further inspection.",
      "date": "2024-06-12T16:06:34.765886",
      "usage": {
        "prompt_tokens": 75341,
        "completion_tokens": 896,
        "cost": 0.390145
      }
    }
  ],
  "leads": [
    {
      "headline": "Potential Deserialization Vulnerability",
      "analysis": "The use of ObjectOutputStream for serialization and deserialization in DigitalSignatureServiceSessionTest can be risky if the serialized data is from an untrusted source. This can lead to deserialization attacks, where maliciously crafted input could lead to arbitrary code execution or other unwanted behavior.\n",
      "classification": "very promising",
      "cwe": "CWE-502",
      "function_names": [
        "testSerialization"
      ],
      "filenames": [
        "dssp-client/src/test/java/test/unit/be/e_contract/dssp/client/DigitalSignatureServiceSessionTest.java"
      ]
    },
    {
      "headline": "Use of Hard-Coded Credentials",
      "analysis": "The class CallbackTestHandler contains public static variables tokenKey and password which are used to store credentials. Hard-coded credentials can lead to security vulnerabilities as they can be extracted and misused.\n",
      "classification": "very promising",
      "cwe": "CWE-798",
      "function_names": [
        "handle"
      ],
      "filenames": [
        "dssp-client/src/test/java/test/unit/be/e_contract/dssp/client/CallbackTestHandler.java"
      ]
    },
    {
      "headline": "Weak Encryption Strength",
      "analysis": "The use of \"HMACSHA1\" in PendingRequestFactory and SignResponseVerifier is considered weak due to known vulnerabilities in SHA-1. It is recommended to use stronger algorithms like SHA-256.\n",
      "classification": "very promising",
      "cwe": "CWE-326",
      "function_names": [
        "sign"
      ],
      "filenames": [
        "dssp-client/src/main/java/be/e_contract/dssp/client/PendingRequestFactory.java",
        "dssp-client/src/main/java/be/e_contract/dssp/client/SignResponseVerifier.java"
      ]
    },
    {
      "headline": "Missing Authorization Checks",
      "analysis": "The class WSSecuritySOAPHandler does not appear to have explicit authorization checks when processing the security tokens or user credentials. This could allow unauthorized access if other parts of the system rely on this handler for security enforcement.\n",
      "classification": "slightly promising",
      "cwe": "CWE-862",
      "function_names": [
        "handleMessage"
      ],
      "filenames": [
        "dssp-client/src/main/java/be/e_contract/dssp/client/impl/WSSecuritySOAPHandler.java"
      ]
    },
    {
      "headline": "Insecure Random Number Generation",
      "analysis": "The use of SecureRandom without explicit seeding in cryptographic operations could result in predictable values on older Java versions where the default seeding mechanism may be weak.\n",
      "classification": "slightly promising",
      "cwe": "CWE-330",
      "function_names": [
        "<various>"
      ],
      "filenames": [
        "dssp-client/src/test/java/test/unit/be/e_contract/dssp/client/SignResponseVerifierTest.java",
        "dssp-client/src/main/java/be/e_contract/dssp/client/DigitalSignatureServiceClient.java",
        "dssp-client/src/main/java/be/e_contract/dssp/client/SignResponseFactory.java"
      ]
    },
    {
      "headline": "Improper Validation of Certificate",
      "analysis": "The function verifyTrust in WSSecurityCrypto returns false unconditionally, indicating that trust validation logic might not be properly implemented. This could lead to accepting untrusted certificates.\n",
      "classification": "very promising",
      "cwe": "CWE-295",
      "function_names": [
        "verifyTrust"
      ],
      "filenames": [
        "dssp-client/src/main/java/be/e_contract/dssp/client/impl/WSSecurityCrypto.java"
      ]
    },
    {
      "headline": "Missing Encryption of Sensitive Data",
      "analysis": "Sensitive information such as tokens and keys in DigitalSignatureServiceSession and CallbackTestHandler are stored in plain byte arrays and public static variables, respectively. They should be encrypted in storage to prevent unauthorized access.\n",
      "classification": "very promising",
      "cwe": "CWE-311",
      "function_names": [
        "<various>"
      ],
      "filenames": [
        "dssp-client/src/main/java/be/e_contract/dssp/client/DigitalSignatureServiceSession.java",
        "dssp-client/src/test/java/test/unit/be/e_contract/dssp/client/CallbackTestHandler.java"
      ]
    }
  ],
  "scores": [
    {
      "stats": {
        "fn": 1,
        "tp": 0,
        "fp": 5
      },
      "mapping": {},
      "vuln_dates": {
        "CVE-2016-15011": "2023-01-06T10:15:09"
      },
      "scoring_model": "claude-3-opus-20240229",
      "type": "llm",
      "instruction_template_hash": "245ace12b6361954d0a2"
    }
  ],
  "instruction_template_hash": "10c0163db4740318a544",
  "version": "0.1.0"
}
