{
  "commit": "27c466a10b866a4ffac00e2d6e0e7268c1d9ef60",
  "repo_url": "https://github.com/jenkinsci/monitoring-plugin",
  "model": "claude-3-haiku-20240307",
  "chunk_hashes": [
    "e6d5fa60101d820de624"
  ],
  "responses": [
    {
      "content": "Here is the YAML output for the security vulnerabilities in the provided codebase:\n\n```yaml\nleads:\n  - headline: Improper Input Validation (CWE-20)\n    analysis: |\n      The codebase contains several instances of improper input validation, which could lead to vulnerabilities such as CWE-1284 (Improper Validation of Specified Quantity in Input) and CWE-129 (Improper Validation of Array Index). Specifically, the `HudsonMonitoringFilter` class does not properly validate the parameters passed in the HTTP request, which could lead to injection vulnerabilities if the input is not properly sanitized.\n    cwe: CWE-20\n    function_names:\n      - hasInvalidParameters\n    filenames:\n      - src/main/java/org/jvnet/hudson/plugins/monitoring/HudsonMonitoringFilter.java\n    classification: very promising\n\n  - headline: Improper Neutralization of Special Elements in Output Used by a Downstream Component (CWE-74)\n    analysis: |\n      The codebase contains several instances of improper neutralization of special characters in output, which could lead to injection vulnerabilities such as CWE-79 (Cross-site Scripting), CWE-88 (Improper Neutralization of Argument Delimiters in a Command), and CWE-94 (Improper Control of Generation of Code). Specifically, the `HudsonMonitoringFilter` class does not properly neutralize the parameters in the HTTP request before passing them to the downstream components, which could lead to injection vulnerabilities.\n    cwe: CWE-74\n    function_names:\n      - hasInvalidParameters\n      - doMonitoring\n    filenames:\n      - src/main/java/org/jvnet/hudson/plugins/monitoring/HudsonMonitoringFilter.java\n    classification: very promising\n\n  - headline: Improper Restriction of XML External Entity Reference (CWE-611)\n    analysis: |\n      The codebase does not properly restrict XML external entity references, which could lead to denial of service attacks or the disclosure of sensitive information. Specifically, the `RemoteCallHelper` class uses the `javax.servlet.http.HttpServletRequest` and `javax.servlet.http.HttpServletResponse` classes, which could be vulnerable to XXE attacks if the input is not properly sanitized.\n    cwe: CWE-611\n    function_names:\n      - collectDataByNodeName\n    filenames:\n      - src/main/java/net/bull/javamelody/RemoteCallHelper.java\n    classification: slightly promising\n\n  - headline: Improper Handling of Exceptional Conditions (CWE-755)\n    analysis: |\n      The codebase does not properly handle exceptional conditions, which could lead to denial of service attacks or the disclosure of sensitive information. Specifically, the `PluginImpl` class catches and logs all exceptions that occur during the plugin's initialization, which could hide important error messages and make it difficult to diagnose and fix issues.\n    cwe: CWE-755\n    function_names:\n      - start\n    filenames:\n      - src/main/java/org/jvnet/hudson/plugins/monitoring/PluginImpl.java\n    classification: slightly promising\n\n  - headline: Improper Synchronization (CWE-662)\n    analysis: |\n      The codebase does not properly synchronize access to shared resources, which could lead to race conditions and other concurrency-related vulnerabilities. Specifically, the `NodesListener` class schedules a task to collect node data, but does not properly synchronize access to the `NodesCollector` instance, which could lead to race conditions and other issues.\n    cwe: CWE-662\n    function_names:\n      - scheduleCollectNow\n    filenames:\n      - src/main/java/org/jvnet/hudson/plugins/monitoring/NodesListener.java\n    classification: slightly promising\n```",
      "date": "2024-06-12T18:55:37.909037",
      "usage": {
        "prompt_tokens": 21270,
        "completion_tokens": 938,
        "cost": 0.00649
      }
    }
  ],
  "leads": [
    {
      "headline": "Improper Input Validation (CWE-20)",
      "analysis": "The codebase contains several instances of improper input validation, which could lead to vulnerabilities such as CWE-1284 (Improper Validation of Specified Quantity in Input) and CWE-129 (Improper Validation of Array Index). Specifically, the HudsonMonitoringFilter class does not properly validate the parameters passed in the HTTP request, which could lead to injection vulnerabilities if the input is not properly sanitized.\n",
      "classification": "very promising",
      "cwe": "CWE-20",
      "function_names": [
        "hasInvalidParameters"
      ],
      "filenames": [
        "src/main/java/org/jvnet/hudson/plugins/monitoring/HudsonMonitoringFilter.java"
      ]
    },
    {
      "headline": "Improper Neutralization of Special Elements in Output Used by a Downstream Component (CWE-74)",
      "analysis": "The codebase contains several instances of improper neutralization of special characters in output, which could lead to injection vulnerabilities such as CWE-79 (Cross-site Scripting), CWE-88 (Improper Neutralization of Argument Delimiters in a Command), and CWE-94 (Improper Control of Generation of Code). Specifically, the HudsonMonitoringFilter class does not properly neutralize the parameters in the HTTP request before passing them to the downstream components, which could lead to injection vulnerabilities.\n",
      "classification": "very promising",
      "cwe": "CWE-74",
      "function_names": [
        "hasInvalidParameters",
        "doMonitoring"
      ],
      "filenames": [
        "src/main/java/org/jvnet/hudson/plugins/monitoring/HudsonMonitoringFilter.java"
      ]
    },
    {
      "headline": "Improper Restriction of XML External Entity Reference (CWE-611)",
      "analysis": "The codebase does not properly restrict XML external entity references, which could lead to denial of service attacks or the disclosure of sensitive information. Specifically, the RemoteCallHelper class uses the javax.servlet.http.HttpServletRequest and javax.servlet.http.HttpServletResponse classes, which could be vulnerable to XXE attacks if the input is not properly sanitized.\n",
      "classification": "slightly promising",
      "cwe": "CWE-611",
      "function_names": [
        "collectDataByNodeName"
      ],
      "filenames": [
        "src/main/java/net/bull/javamelody/RemoteCallHelper.java"
      ]
    },
    {
      "headline": "Improper Handling of Exceptional Conditions (CWE-755)",
      "analysis": "The codebase does not properly handle exceptional conditions, which could lead to denial of service attacks or the disclosure of sensitive information. Specifically, the PluginImpl class catches and logs all exceptions that occur during the plugin's initialization, which could hide important error messages and make it difficult to diagnose and fix issues.\n",
      "classification": "slightly promising",
      "cwe": "CWE-755",
      "function_names": [
        "start"
      ],
      "filenames": [
        "src/main/java/org/jvnet/hudson/plugins/monitoring/PluginImpl.java"
      ]
    },
    {
      "headline": "Improper Synchronization (CWE-662)",
      "analysis": "The codebase does not properly synchronize access to shared resources, which could lead to race conditions and other concurrency-related vulnerabilities. Specifically, the NodesListener class schedules a task to collect node data, but does not properly synchronize access to the NodesCollector instance, which could lead to race conditions and other issues.\n",
      "classification": "slightly promising",
      "cwe": "CWE-662",
      "function_names": [
        "scheduleCollectNow"
      ],
      "filenames": [
        "src/main/java/org/jvnet/hudson/plugins/monitoring/NodesListener.java"
      ]
    }
  ],
  "scores": [
    {
      "stats": {
        "fn": 1,
        "tp": 0,
        "fp": 2
      },
      "mapping": {},
      "vuln_dates": {
        "CVE-2019-1003022": "2019-02-06T16:29:01"
      },
      "scoring_model": "claude-3-opus-20240229",
      "type": "llm",
      "instruction_template_hash": "245ace12b6361954d0a2"
    }
  ],
  "instruction_template_hash": "10c0163db4740318a544",
  "version": "0.1.0"
}
