{
  "commit": "0a72c12090fb71ebefbc5036dc1b548b123a91a6",
  "repo_url": "https://github.com/kubernetes-sigs/aws-iam-authenticator",
  "model": "gpt-4o-2024-05-13",
  "chunk_hashes": [
    "de473a5f7e8bd73561eb"
  ],
  "responses": [
    {
      "content": "```yaml\nleads:\n  - headline: \"Potential Command Injection Vulnerability\"\n    analysis: |\n      The script `vendor/k8s.io/code-generator/generate-groups.sh` accepts user input through command-line arguments which are then passed to various `go` commands. This could potentially be exploited if an attacker is able to influence these inputs, leading to a command injection vulnerability.\n      Specifically, the variables `GENS`, `OUTPUT_PKG`, `APIS_PKG`, and `GROUPS_WITH_VERSIONS` are directly concatenated into command strings that are executed using subshells. Without proper sanitization, this could allow an attacker to inject arbitrary commands.\n    cwe: CWE-77\n    function_names:\n      - main\n    filenames:\n      - vendor/k8s.io/code-generator/generate-groups.sh\n      - vendor/k8s.io/code-generator/generate-internal-groups.sh\n    classification: very promising\n  - headline: \"Insecure Use of Shell Scripting in mkerrors.sh\"\n    analysis: |\n      The script `vendor/golang.org/x/sys/unix/mkerrors.sh` relies heavily on shell processing of C source files to generate Go files. It uses `gcc` to preprocess C headers and applies various `awk`, `sed`, and `grep` operations on the output to extract values. If user-supplied input can reach these operations, it may lead to command injection or resource exhaustion attacks.\n      The script does not seem to perform adequate sanitization on inputs and commands executed within subshells.\n    cwe: CWE-78\n    function_names:\n      - main\n    filenames:\n      - vendor/golang.org/x/sys/unix/mkerrors.sh\n    classification: slightly promising\n  - headline: \"Insecure Construction of File Paths\"\n    analysis: |\n      The script `hack/update-codegen.sh` constructs file paths by concatenating variable values. If an attacker can control those variables, they might be able to manipulate file paths to overwrite critical system files or project files.\n      Specifically, the `CODEGEN_PKG` variable is used to construct paths that are then fed into the `generate-groups.sh` script.\n    cwe: CWE-22\n    function_names:\n      - main\n    filenames:\n      - hack/update-codegen.sh\n      - vendor/k8s.io/code-generator/generate-groups.sh\n    classification: slightly promising\n  - headline: \"Use of insecure functions for processing JSON in Go and Shell scripts\"\n    analysis: |\n      In `test.sh` scripts, `jq` is used to parse JSON data from AWS CLI responses. However, if the input to `jq` is not properly sanitized beforehand, it could lead to potential injection attacks.\n      The script `test.sh` does not ensure that the input is sanitized when constructing JSON parsing commands.\n    cwe: CWE-20\n    function_names:\n      - test.sh\n    filenames:\n      - hack/test-integration.sh\n    classification: slightly promising\n  - headline: \"Potential Path Traversal in build.sh\"\n    analysis: |\n      The script `vendor/github.com/json-iterator/go/build.sh` takes user input which is used to set the `GOPATH` environment variable and constructs paths for creating directories and symbolic links. If these inputs are not properly sanitized, it can lead to path traversal attacks allowing malicious files to be created or existing files to be overwritten.\n    cwe: CWE-22\n    function_names: []\n    filenames:\n      - vendor/github.com/json-iterator/go/build.sh\n    classification: very promising\n  - headline: \"Arbitrary File Write via mkerrors.sh\"\n    analysis: |\n      The script `vendor/golang.org/x/sys/unix/mkerrors.sh` processes headers and writes processed content to an output Go file. If an attacker can manipulate the input headers or the way the script generates output, it may be possible to write arbitrary content to specific files.\n    cwe: CWE-22\n    function_names: []\n    filenames:\n      - vendor/golang.org/x/sys/unix/mkerrors.sh\n      - vendor/golang.org/x/sys/unix/gccgo_c.c\n    classification: very promising\n```",
      "date": "2024-06-13T09:24:30.088668",
      "usage": {
        "prompt_tokens": 27383,
        "completion_tokens": 867,
        "cost": 0.14992
      }
    }
  ],
  "leads": [
    {
      "headline": "Potential Command Injection Vulnerability",
      "analysis": "The script vendor/k8s.io/code-generator/generate-groups.sh accepts user input through command-line arguments which are then passed to various go commands. This could potentially be exploited if an attacker is able to influence these inputs, leading to a command injection vulnerability.\nSpecifically, the variables GENS, OUTPUT_PKG, APIS_PKG, and GROUPS_WITH_VERSIONS are directly concatenated into command strings that are executed using subshells. Without proper sanitization, this could allow an attacker to inject arbitrary commands.\n",
      "classification": "very promising",
      "cwe": "CWE-77",
      "function_names": [
        "main"
      ],
      "filenames": [
        "vendor/k8s.io/code-generator/generate-groups.sh",
        "vendor/k8s.io/code-generator/generate-internal-groups.sh"
      ]
    },
    {
      "headline": "Insecure Use of Shell Scripting in mkerrors.sh",
      "analysis": "The script vendor/golang.org/x/sys/unix/mkerrors.sh relies heavily on shell processing of C source files to generate Go files. It uses gcc to preprocess C headers and applies various awk, sed, and grep operations on the output to extract values. If user-supplied input can reach these operations, it may lead to command injection or resource exhaustion attacks.\nThe script does not seem to perform adequate sanitization on inputs and commands executed within subshells.\n",
      "classification": "slightly promising",
      "cwe": "CWE-78",
      "function_names": [
        "main"
      ],
      "filenames": [
        "vendor/golang.org/x/sys/unix/mkerrors.sh"
      ]
    },
    {
      "headline": "Insecure Construction of File Paths",
      "analysis": "The script hack/update-codegen.sh constructs file paths by concatenating variable values. If an attacker can control those variables, they might be able to manipulate file paths to overwrite critical system files or project files.\nSpecifically, the CODEGEN_PKG variable is used to construct paths that are then fed into the generate-groups.sh script.\n",
      "classification": "slightly promising",
      "cwe": "CWE-22",
      "function_names": [
        "main"
      ],
      "filenames": [
        "hack/update-codegen.sh",
        "vendor/k8s.io/code-generator/generate-groups.sh"
      ]
    },
    {
      "headline": "Use of insecure functions for processing JSON in Go and Shell scripts",
      "analysis": "In test.sh scripts, jq is used to parse JSON data from AWS CLI responses. However, if the input to jq is not properly sanitized beforehand, it could lead to potential injection attacks.\nThe script test.sh does not ensure that the input is sanitized when constructing JSON parsing commands.\n",
      "classification": "slightly promising",
      "cwe": "CWE-20",
      "function_names": [
        "test.sh"
      ],
      "filenames": [
        "hack/test-integration.sh"
      ]
    },
    {
      "headline": "Potential Path Traversal in build.sh",
      "analysis": "The script vendor/github.com/json-iterator/go/build.sh takes user input which is used to set the GOPATH environment variable and constructs paths for creating directories and symbolic links. If these inputs are not properly sanitized, it can lead to path traversal attacks allowing malicious files to be created or existing files to be overwritten.\n",
      "classification": "very promising",
      "cwe": "CWE-22",
      "function_names": [],
      "filenames": [
        "vendor/github.com/json-iterator/go/build.sh"
      ]
    },
    {
      "headline": "Arbitrary File Write via mkerrors.sh",
      "analysis": "The script vendor/golang.org/x/sys/unix/mkerrors.sh processes headers and writes processed content to an output Go file. If an attacker can manipulate the input headers or the way the script generates output, it may be possible to write arbitrary content to specific files.\n",
      "classification": "very promising",
      "cwe": "CWE-22",
      "function_names": [],
      "filenames": [
        "vendor/golang.org/x/sys/unix/mkerrors.sh",
        "vendor/golang.org/x/sys/unix/gccgo_c.c"
      ]
    }
  ],
  "scores": [
    {
      "stats": {
        "fn": 1,
        "tp": 0,
        "fp": 3
      },
      "mapping": {},
      "vuln_dates": {
        "CVE-2022-2385": "2022-07-12T19:15:08"
      },
      "scoring_model": "claude-3-opus-20240229",
      "type": "llm",
      "instruction_template_hash": "245ace12b6361954d0a2"
    }
  ],
  "instruction_template_hash": "10c0163db4740318a544",
  "version": "0.1.0"
}
