{
  "commit": "2e2df20219f4e5aa557bac6f0a0031a40b5d422b",
  "repo_url": "https://github.com/jenkinsci/maven-release-cascade-plugin",
  "model": "claude-3-opus-20240229",
  "chunk_hashes": [
    "adfef682080fb05d99f5"
  ],
  "responses": [
    {
      "content": "Based on the provided codebase, here are the potential security vulnerabilities I identified:\n\n```yaml\nleads:\n  - headline: Arbitrary Code Execution via Groovy Sandbox Bypass\n    analysis: |\n      The LayoutOptions and CascadeOptions classes use the @DataBoundConstructor annotation which allows them to be instantiated from user-controlled form data. The LayoutOptions constructor uses the httpStringParam method to read parameters from the request without any input validation or sanitization. This could potentially allow an attacker to submit malicious payloads that execute arbitrary code by bypassing the Groovy sandbox.\n    cwe: CWE-94\n    function_names:\n      - LayoutOptions.java:@DataBoundConstructor\n      - LayoutOptions.java:httpStringParam\n    filenames:\n      - src/main/java/com/barchart/jenkins/cascade/LayoutOptions.java\n      - src/main/java/com/barchart/jenkins/cascade/PluginUtilities.java\n    classification: very promising\n\n  - headline: Cross-Site Scripting (XSS)\n    analysis: |\n      Several classes like ProjectIdentity, LayoutBuildWrapper, and CascadeOptions use the @Jelly annotation on getter methods that return user-controlled data. If this data is not properly HTML escaped when rendered in Jelly views, it could result in stored cross-site scripting vulnerabilities that allow an attacker to inject malicious scripts.\n    cwe: CWE-79\n    function_names:\n      - ProjectIdentity.java:@Jelly\n      - LayoutBuildWrapper.java:@Jelly  \n      - CascadeOptions.java:@Jelly\n    filenames:\n      - src/main/java/com/barchart/jenkins/cascade/ProjectIdentity.java\n      - src/main/java/com/barchart/jenkins/cascade/LayoutBuildWrapper.java\n      - src/main/java/com/barchart/jenkins/cascade/CascadeOptions.java\n    classification: very promising\n    \n  - headline: Missing Authorization\n    analysis: |  \n      The PluginConfigurator class defines a doSubmit endpoint with the @Jelly annotation that saves global configuration. However, it does not perform any authorization checks to ensure the user has admin permissions. This could allow any authenticated user to modify global plugin settings they should not have access to.\n    cwe: CWE-862\n    function_names:\n      - PluginConfigurator.java:doSubmit\n    filenames:\n      - src/main/java/com/barchart/jenkins/cascade/PluginConfigurator.java  \n    classification: slightly promising\n\n  - headline: Insecure Randomness\n    analysis: |\n      The ProjectIdentity class generates supposedly unique project IDs using java.util.UUID. However, the randomness and uniqueness guarantees of UUID depend on the underlying system's random number generator. If an insecure random number generator is used, IDs may be predictable. Consider using a cryptographically secure random number generator instead.\n    cwe: CWE-330\n    function_names:  \n      - ProjectIdentity.java:ensureCascadeIdentity\n      - ProjectIdentity.java:ensureLayoutIdentity\n      - ProjectIdentity.java:ensureMemberIdentity\n    filenames:\n      - src/main/java/com/barchart/jenkins/cascade/ProjectIdentity.java\n    classification: slightly promising\n```\n\nThe analysis focuses on some of the most severe potential vulnerabilities I could identify in the provided codebase. Further manual code review and testing would be required to confirm these issues and identify any additional vulnerabilities. The CWE IDs classify the root causes based on the provided list. Let me know if you have any other questions!",
      "date": "2024-06-12T18:53:37.561075",
      "usage": {
        "prompt_tokens": 77611,
        "completion_tokens": 888,
        "cost": 1.230765
      }
    }
  ],
  "leads": [
    {
      "headline": "Arbitrary Code Execution via Groovy Sandbox Bypass",
      "analysis": "The LayoutOptions and CascadeOptions classes use the @DataBoundConstructor annotation which allows them to be instantiated from user-controlled form data. The LayoutOptions constructor uses the httpStringParam method to read parameters from the request without any input validation or sanitization. This could potentially allow an attacker to submit malicious payloads that execute arbitrary code by bypassing the Groovy sandbox.\n",
      "classification": "very promising",
      "cwe": "CWE-94",
      "function_names": [
        "LayoutOptions.java:@DataBoundConstructor",
        "LayoutOptions.java:httpStringParam"
      ],
      "filenames": [
        "src/main/java/com/barchart/jenkins/cascade/LayoutOptions.java",
        "src/main/java/com/barchart/jenkins/cascade/PluginUtilities.java"
      ]
    },
    {
      "headline": "Cross-Site Scripting (XSS)",
      "analysis": "Several classes like ProjectIdentity, LayoutBuildWrapper, and CascadeOptions use the @Jelly annotation on getter methods that return user-controlled data. If this data is not properly HTML escaped when rendered in Jelly views, it could result in stored cross-site scripting vulnerabilities that allow an attacker to inject malicious scripts.\n",
      "classification": "very promising",
      "cwe": "CWE-79",
      "function_names": [
        "ProjectIdentity.java:@Jelly",
        "LayoutBuildWrapper.java:@Jelly",
        "CascadeOptions.java:@Jelly"
      ],
      "filenames": [
        "src/main/java/com/barchart/jenkins/cascade/ProjectIdentity.java",
        "src/main/java/com/barchart/jenkins/cascade/LayoutBuildWrapper.java",
        "src/main/java/com/barchart/jenkins/cascade/CascadeOptions.java"
      ]
    },
    {
      "headline": "Missing Authorization",
      "analysis": "The PluginConfigurator class defines a doSubmit endpoint with the @Jelly annotation that saves global configuration. However, it does not perform any authorization checks to ensure the user has admin permissions. This could allow any authenticated user to modify global plugin settings they should not have access to.\n",
      "classification": "slightly promising",
      "cwe": "CWE-862",
      "function_names": [
        "PluginConfigurator.java:doSubmit"
      ],
      "filenames": [
        "src/main/java/com/barchart/jenkins/cascade/PluginConfigurator.java"
      ]
    },
    {
      "headline": "Insecure Randomness",
      "analysis": "The ProjectIdentity class generates supposedly unique project IDs using java.util.UUID. However, the randomness and uniqueness guarantees of UUID depend on the underlying system's random number generator. If an insecure random number generator is used, IDs may be predictable. Consider using a cryptographically secure random number generator instead.\n",
      "classification": "slightly promising",
      "cwe": "CWE-330",
      "function_names": [
        "ProjectIdentity.java:ensureCascadeIdentity",
        "ProjectIdentity.java:ensureLayoutIdentity",
        "ProjectIdentity.java:ensureMemberIdentity"
      ],
      "filenames": [
        "src/main/java/com/barchart/jenkins/cascade/ProjectIdentity.java"
      ]
    }
  ],
  "scores": [
    {
      "stats": {
        "fn": 2,
        "tp": 0,
        "fp": 2
      },
      "mapping": {},
      "vuln_dates": {
        "CVE-2020-2295": "2020-10-08T13:15:11",
        "CVE-2020-2294": "2020-10-08T13:15:11"
      },
      "scoring_model": "claude-3-opus-20240229",
      "type": "llm",
      "instruction_template_hash": "245ace12b6361954d0a2"
    },
    {
      "stats": {
        "fn": 2,
        "tp": 0,
        "fp": 2
      },
      "mapping": {},
      "vuln_dates": {
        "CVE-2020-2295": "2020-10-08T13:15:11",
        "CVE-2020-2294": "2020-10-08T13:15:11"
      },
      "scoring_model": "claude-3-5-sonnet-20240620",
      "type": "llm",
      "instruction_template_hash": "245ace12b6361954d0a2"
    }
  ],
  "instruction_template_hash": "10c0163db4740318a544",
  "version": "0.1.0"
}
