{
  "commit": "16ed41b22c2739838ec7cb0e6ba26d52f4c8db3e",
  "repo_url": "https://github.com/nanohttpd/nanohttpd",
  "model": "gpt-4-turbo-2024-04-09",
  "chunk_hashes": [
    "897b7a93d10e0b1c6258"
  ],
  "responses": [
    {
      "content": "```yaml\nleads:\n  - headline: \"Incorrect input validation in URL parsing\"\n    analysis: |\n      The web server improperly validates the input when processing URIs, which might allow a user to access unauthorized files by manipulating URL input to traverse directories (e.g., using \"../\"). This vulnerability can result in unauthorized information disclosure and potential execution of arbitrary files.\n    cwe: CWE-22\n    function_names:\n      - \"canServeUri\"\n      - \"normalizeUri\"\n      - \"serve\"\n    filenames:\n      - \"core/src/main/java/fi/iki/elonen/SimpleWebServer.java\"\n      - \"nanolets/src/main/java/fi/iki/elonen/router/RouterNanoHTTPD.java\"\n    classification: \"very promising\"\n\n  - headline: \"Execution of unvalidated data in MarkdownWebServerPlugin\"\n    analysis: |\n      The web server fails to sanitize and encode user input before executing it as HTML in generated markdown documents. Attackers can inject malicious code through crafted user input, which gets executed in the client\u2019s browser upon rendering without adequate encoding or escaping, leading to Cross-site Scripting (XSS) attacks.\n    cwe: CWE-79\n    function_names:\n      - \"readSource\"\n      - \"serveFile\"\n    filenames:\n      - \"markdown-plugin/src/main/java/fi/iki/elonen/MarkdownWebServerPlugin.java\"\n    classification: \"very promising\"\n      \n  - headline: \"Information Exposure Through an Error Message in TestNanolets\"\n    analysis: |\n      The web server outputs serval detailed error messages within different exception catch blocks. This information can reveal server configurations, internal statuses, or software versions to an unauthorized actor, potentially leading to further attacks or targeted exploits.\n    cwe: CWE-209\n    function_names:\n      - \"testGeneralHandlerGetStatus\"\n    filenames:\n      - \"nanolets/src/test/java/fi/iki/elonen/router/TestNanolets.java\"\n    classification: \"slightly promising\"\n\n  - headline: \"Denial of Service (DoS) risk via large frame payloads in WebSocket handling\"\n    analysis: |\n      The NanoWSD class improperly handles large WebSocket frames, resulting in exceptions or errors that could disrupt service. An attacker can potentially send frames with unusually large sizes or deep recursion to overwhelm server resources, causing Denial of Service (DoS).\n    cwe: CWE-400\n    function_names:\n      - \"readPayload\"\n      - \"sendFrame\"\n    filenames:\n      - \"websocket/src/main/java/fi/iki/elonen/NanoWSD.java\"\n    classification: \"slightly promising\"\n\n  - headline: \"Improper Access Control with Static Page Handling\"\n    analysis: |\n      The file access mechanism in StaticPageHandler does not reliably enforce access control, particularly with file visibility and directory listing capabilities. By altering request paths or using predictable resource locations, an attacker might be able to retrieve or manipulate resources that should be protected.\n    cwe: CWE-284\n    function_names:\n      - \"serveFile\"\n      - \"listDirectory\"\n    filenames:\n      - \"webserver/src/main/java/fi/iki/elonen/SimpleWebServer.java\"\n    classification: \"slightly promising\"\n```",
      "date": "2024-06-13T10:22:07.850747",
      "usage": {
        "prompt_tokens": 97767,
        "completion_tokens": 657,
        "cost": 0.99738
      }
    }
  ],
  "leads": [
    {
      "headline": "Incorrect input validation in URL parsing",
      "analysis": "The web server improperly validates the input when processing URIs, which might allow a user to access unauthorized files by manipulating URL input to traverse directories (e.g., using \"../\"). This vulnerability can result in unauthorized information disclosure and potential execution of arbitrary files.\n",
      "classification": "very promising",
      "cwe": "CWE-22",
      "function_names": [
        "canServeUri",
        "normalizeUri",
        "serve"
      ],
      "filenames": [
        "core/src/main/java/fi/iki/elonen/SimpleWebServer.java",
        "nanolets/src/main/java/fi/iki/elonen/router/RouterNanoHTTPD.java"
      ]
    },
    {
      "headline": "Execution of unvalidated data in MarkdownWebServerPlugin",
      "analysis": "The web server fails to sanitize and encode user input before executing it as HTML in generated markdown documents. Attackers can inject malicious code through crafted user input, which gets executed in the client\u2019s browser upon rendering without adequate encoding or escaping, leading to Cross-site Scripting (XSS) attacks.\n",
      "classification": "very promising",
      "cwe": "CWE-79",
      "function_names": [
        "readSource",
        "serveFile"
      ],
      "filenames": [
        "markdown-plugin/src/main/java/fi/iki/elonen/MarkdownWebServerPlugin.java"
      ]
    },
    {
      "headline": "Information Exposure Through an Error Message in TestNanolets",
      "analysis": "The web server outputs serval detailed error messages within different exception catch blocks. This information can reveal server configurations, internal statuses, or software versions to an unauthorized actor, potentially leading to further attacks or targeted exploits.\n",
      "classification": "slightly promising",
      "cwe": "CWE-209",
      "function_names": [
        "testGeneralHandlerGetStatus"
      ],
      "filenames": [
        "nanolets/src/test/java/fi/iki/elonen/router/TestNanolets.java"
      ]
    },
    {
      "headline": "Denial of Service (DoS) risk via large frame payloads in WebSocket handling",
      "analysis": "The NanoWSD class improperly handles large WebSocket frames, resulting in exceptions or errors that could disrupt service. An attacker can potentially send frames with unusually large sizes or deep recursion to overwhelm server resources, causing Denial of Service (DoS).\n",
      "classification": "slightly promising",
      "cwe": "CWE-400",
      "function_names": [
        "readPayload",
        "sendFrame"
      ],
      "filenames": [
        "websocket/src/main/java/fi/iki/elonen/NanoWSD.java"
      ]
    },
    {
      "headline": "Improper Access Control with Static Page Handling",
      "analysis": "The file access mechanism in StaticPageHandler does not reliably enforce access control, particularly with file visibility and directory listing capabilities. By altering request paths or using predictable resource locations, an attacker might be able to retrieve or manipulate resources that should be protected.\n",
      "classification": "slightly promising",
      "cwe": "CWE-284",
      "function_names": [
        "serveFile",
        "listDirectory"
      ],
      "filenames": [
        "webserver/src/main/java/fi/iki/elonen/SimpleWebServer.java"
      ]
    }
  ],
  "scores": [
    {
      "stats": {
        "fn": 1,
        "tp": 1,
        "fp": 1
      },
      "mapping": {
        "1": "CVE-2020-13697"
      },
      "vuln_dates": {
        "CVE-2022-21230": "2022-05-01T16:15:08",
        "CVE-2020-13697": "2021-02-23T08:15:11"
      },
      "scoring_model": "claude-3-opus-20240229",
      "type": "llm",
      "instruction_template_hash": "245ace12b6361954d0a2"
    },
    {
      "stats": {
        "fn": 1,
        "tp": 1,
        "fp": 1
      },
      "mapping": {
        "1": "CVE-2020-13697"
      },
      "vuln_dates": {
        "CVE-2022-21230": "2022-05-01T16:15:08",
        "CVE-2020-13697": "2021-02-23T08:15:11"
      },
      "scoring_model": "claude-3-5-sonnet-20240620",
      "type": "llm",
      "instruction_template_hash": "245ace12b6361954d0a2"
    }
  ],
  "instruction_template_hash": "10c0163db4740318a544",
  "version": "0.1.0"
}
