{
  "commit": "36f9e2a8cf83c3fb93cc7f880568a6b8377d2183",
  "repo_url": "https://github.com/nodeca/embedza",
  "model": "gpt-4o-2024-05-13",
  "chunk_hashes": [
    "3c43c00fefae3605f8a9"
  ],
  "responses": [
    {
      "content": "```yaml\nleads:\n  - headline: \"Potential SQL Injection in oembed fetcher\"\n    analysis: |\n      The URL used in the oembed fetcher is directly concatenated using user input without proper sanitization. This occurs in the fetcher where the `tpl.query.url` parameter is set based on the unprocessed `env.src`. This can lead to an SQL Injection vulnerability if the input is maliciously crafted.\n    cwe: CWE-89\n    function_names:\n      - vimeo_fetcher\n      - youtube_fetcher\n    filenames:\n      - lib/domains/vimeo.com.js\n      - lib/domains/youtube.com.js\n    classification: very promising\n\n  - headline: \"Improper Error Handling in Meta Fetcher\"\n    analysis: |\n      The meta fetcher does not properly handle errors during request processing and simply passes on the error without additional context or mitigation strategies. This can expose the application to potential denial of service attacks or leak internal error messages.\n    cwe: CWE-754\n    function_names: \n      - meta_fetcher\n    filenames:\n      - lib/fetchers.js\n    classification: slightly promising\n\n  - headline: \"Open Redirect via Unvalidated URL\"\n    analysis: |\n      The request method in `Embedza.prototype.request` can lead to open redirect vulnerabilities as it directly uses URLs without validation. This could be exploited by attackers to redirect users to malicious sites.\n    cwe: CWE-601\n    function_names:\n      - request\n    filenames:\n      - lib/index.js\n    classification: very promising\n\n  - headline: \"Insufficient Cache Control for Sensitive Data\"\n    analysis: |\n      The caching mechanism implemented in the Cache class is too simplistic and does not implement any verification, leading potentially to exposure or improper handling of sensitive data.\n    cwe: CWE-922\n    function_names: []\n    filenames:\n      - lib/cache.js\n    classification: not promising\n\n  - headline: \"Potential XSS via Unescaped Template Variables\"\n    analysis: |\n      When rendering templates, user-controlled data from the meta tags and oembed response is injected directly without sufficient escaping using lodash templates, which creates an XSS risk.\n    cwe: CWE-79\n    function_names: []\n    filenames:\n      - lib/templates/index.js\n    classification: very promising\n\n  - headline: \"Unprotected Race Condition in Cache Management\"\n    analysis: |\n      The Cache class does not have any synchronization mechanisms in place, which could lead to race conditions when multiple concurrent requests attempt to access or modify the cache.\n    cwe: CWE-362\n    function_names:\n      - get\n      - set\n    filenames:\n      - lib/cache.js\n    classification: slightly promising\n```",
      "date": "2024-06-14T14:59:39.609075",
      "usage": {
        "prompt_tokens": 28752,
        "completion_tokens": 562,
        "cost": 0.15219
      }
    }
  ],
  "leads": [
    {
      "headline": "Potential SQL Injection in oembed fetcher",
      "analysis": "The URL used in the oembed fetcher is directly concatenated using user input without proper sanitization. This occurs in the fetcher where the tpl.query.url parameter is set based on the unprocessed env.src. This can lead to an SQL Injection vulnerability if the input is maliciously crafted.\n",
      "classification": "very promising",
      "cwe": "CWE-89",
      "function_names": [
        "vimeo_fetcher",
        "youtube_fetcher"
      ],
      "filenames": [
        "lib/domains/vimeo.com.js",
        "lib/domains/youtube.com.js"
      ]
    },
    {
      "headline": "Improper Error Handling in Meta Fetcher",
      "analysis": "The meta fetcher does not properly handle errors during request processing and simply passes on the error without additional context or mitigation strategies. This can expose the application to potential denial of service attacks or leak internal error messages.\n",
      "classification": "slightly promising",
      "cwe": "CWE-754",
      "function_names": [
        "meta_fetcher"
      ],
      "filenames": [
        "lib/fetchers.js"
      ]
    },
    {
      "headline": "Open Redirect via Unvalidated URL",
      "analysis": "The request method in Embedza.prototype.request can lead to open redirect vulnerabilities as it directly uses URLs without validation. This could be exploited by attackers to redirect users to malicious sites.\n",
      "classification": "very promising",
      "cwe": "CWE-601",
      "function_names": [
        "request"
      ],
      "filenames": [
        "lib/index.js"
      ]
    },
    {
      "headline": "Insufficient Cache Control for Sensitive Data",
      "analysis": "The caching mechanism implemented in the Cache class is too simplistic and does not implement any verification, leading potentially to exposure or improper handling of sensitive data.\n",
      "classification": "not promising",
      "cwe": "CWE-922",
      "function_names": [],
      "filenames": [
        "lib/cache.js"
      ]
    },
    {
      "headline": "Potential XSS via Unescaped Template Variables",
      "analysis": "When rendering templates, user-controlled data from the meta tags and oembed response is injected directly without sufficient escaping using lodash templates, which creates an XSS risk.\n",
      "classification": "very promising",
      "cwe": "CWE-79",
      "function_names": [],
      "filenames": [
        "lib/templates/index.js"
      ]
    },
    {
      "headline": "Unprotected Race Condition in Cache Management",
      "analysis": "The Cache class does not have any synchronization mechanisms in place, which could lead to race conditions when multiple concurrent requests attempt to access or modify the cache.\n",
      "classification": "slightly promising",
      "cwe": "CWE-362",
      "function_names": [
        "get",
        "set"
      ],
      "filenames": [
        "lib/cache.js"
      ]
    }
  ],
  "scores": [
    {
      "stats": {
        "fn": 1,
        "tp": 0,
        "fp": 3
      },
      "mapping": {},
      "vuln_dates": {
        "CVE-2016-10569": "2018-05-31T20:29:02"
      },
      "scoring_model": "claude-3-opus-20240229",
      "type": "llm",
      "instruction_template_hash": "245ace12b6361954d0a2"
    }
  ],
  "instruction_template_hash": "10c0163db4740318a544",
  "version": "0.1.0"
}
