{
  "commit": "16d62322e6d7a0a0478357e5994a055a4645c557",
  "repo_url": "https://github.com/jenkinsci/radiatorview-plugin",
  "model": "claude-3-opus-20240229",
  "chunk_hashes": [
    "15ad9cc86e7933333cce"
  ],
  "responses": [
    {
      "content": "Here is my analysis of the provided codebase:\n\n```yaml\nleads:\n  - headline: Improper Neutralization of Formula Elements in a CSV File\n    analysis: |\n      The RadiatorView class allows specifying an excludeRegex parameter to exclude certain jobs from being displayed based on a regular expression match against the job name. However, this regex is included directly in the rendered view without proper escaping or neutralization. This could allow injection of malicious CSV formula elements if the regex is specified by an attacker.\n    cwe: CWE-1236\n    function_names:\n      - RadiatorView.getExcludeRegex\n      - RadiatorView.isExcluded  \n    filenames:\n      - src/main/java/hudson/model/RadiatorView.java\n    classification: slightly promising\n\n  - headline: Incorrect Permission Assignment for Critical Resource\n    analysis: |  \n      The getContents() method in RadiatorView retrieves all items (jobs) to display, including jobs inside folders, by recursively calling getItems() on folders. However, there does not appear to be any checking of user permissions when accessing and returning these job objects. All jobs the current user can access seem to be returned, even if they are inside folders with restricted permissions. This could allow lower-privileged users to view jobs they normally don't have permission to access.\n    cwe: CWE-732\n    function_names:\n      - RadiatorView.getContents\n      - RadiatorView.addItems\n    filenames:\n      - src/main/java/hudson/model/RadiatorView.java  \n    classification: very promising\n    \n  - headline: Improper Restriction of XML External Entity Reference\n    analysis: |\n      The claim description for a broken build is rendered as raw HTML in JobViewEntry.getClaim(). If this claim text comes from user input and includes malicious XML external entities, it could lead to XXE vulnerabilities when rendered.\n    cwe: CWE-611\n    function_names:\n      - JobViewEntry.getClaim\n      - ClaimWrapper.buildMatrixClaimString\n    filenames:\n      - src/main/java/hudson/model/JobViewEntry.java\n      - src/main/java/hudson/model/ClaimWrapper.java\n    classification: slightly promising\n    \n  - headline: Improper Neutralization of Special Elements used in an SQL Command ('SQL Injection')  \n    analysis: |\n      The excludeRegex parameter in RadiatorView, which contains a regex to filter job names, is set directly from the HTTP request parameter \"excludeRegex\" in the submit() method, without any validation or neutralization. If this value is used to construct SQL queries, it could allow SQL injection attacks. However, it's unclear if this specific parameter is ever used in SQL statements.\n    cwe: CWE-89\n    function_names:\n      - RadiatorView.submit\n    filenames:  \n      - src/main/java/hudson/model/RadiatorView.java\n    classification: not promising\n\n```\n\nThe CWE categories I felt were most applicable were Improper Neutralization of Formula Elements (CWE-1236) for not escaping the user-provided regex before including it in the view, Incorrect Permission Assignment (CWE-732) for potentially exposing restricted jobs, Improper Restriction of XML External Entity Reference (CWE-611) for rendering raw HTML that could contain XXE payloads, and to a lesser extent SQL Injection (CWE-89) for using unsanitized user input, though that one seems unlikely here.\n\nThe permission issue with accessing filtered jobs seems to be the most concerning, as it could allow unintended access to view jobs in restricted folders. The other issues rely on user-provided input being crafted maliciously. Overall though, a full security review, careful input validation, output escaping, and permission checks when aggregating jobs would help harden this plugin.",
      "date": "2024-06-12T19:05:49.531640",
      "usage": {
        "prompt_tokens": 16256,
        "completion_tokens": 910,
        "cost": 0.31209
      }
    }
  ],
  "leads": [
    {
      "headline": "Improper Neutralization of Formula Elements in a CSV File",
      "analysis": "The RadiatorView class allows specifying an excludeRegex parameter to exclude certain jobs from being displayed based on a regular expression match against the job name. However, this regex is included directly in the rendered view without proper escaping or neutralization. This could allow injection of malicious CSV formula elements if the regex is specified by an attacker.\n",
      "classification": "slightly promising",
      "cwe": "CWE-1236",
      "function_names": [
        "RadiatorView.getExcludeRegex",
        "RadiatorView.isExcluded"
      ],
      "filenames": [
        "src/main/java/hudson/model/RadiatorView.java"
      ]
    },
    {
      "headline": "Incorrect Permission Assignment for Critical Resource",
      "analysis": "The getContents() method in RadiatorView retrieves all items (jobs) to display, including jobs inside folders, by recursively calling getItems() on folders. However, there does not appear to be any checking of user permissions when accessing and returning these job objects. All jobs the current user can access seem to be returned, even if they are inside folders with restricted permissions. This could allow lower-privileged users to view jobs they normally don't have permission to access.\n",
      "classification": "very promising",
      "cwe": "CWE-732",
      "function_names": [
        "RadiatorView.getContents",
        "RadiatorView.addItems"
      ],
      "filenames": [
        "src/main/java/hudson/model/RadiatorView.java"
      ]
    },
    {
      "headline": "Improper Restriction of XML External Entity Reference",
      "analysis": "The claim description for a broken build is rendered as raw HTML in JobViewEntry.getClaim(). If this claim text comes from user input and includes malicious XML external entities, it could lead to XXE vulnerabilities when rendered.\n",
      "classification": "slightly promising",
      "cwe": "CWE-611",
      "function_names": [
        "JobViewEntry.getClaim",
        "ClaimWrapper.buildMatrixClaimString"
      ],
      "filenames": [
        "src/main/java/hudson/model/JobViewEntry.java",
        "src/main/java/hudson/model/ClaimWrapper.java"
      ]
    },
    {
      "headline": "Improper Neutralization of Special Elements used in an SQL Command ('SQL Injection')",
      "analysis": "The excludeRegex parameter in RadiatorView, which contains a regex to filter job names, is set directly from the HTTP request parameter \"excludeRegex\" in the submit() method, without any validation or neutralization. If this value is used to construct SQL queries, it could allow SQL injection attacks. However, it's unclear if this specific parameter is ever used in SQL statements.\n",
      "classification": "not promising",
      "cwe": "CWE-89",
      "function_names": [
        "RadiatorView.submit"
      ],
      "filenames": [
        "src/main/java/hudson/model/RadiatorView.java"
      ]
    }
  ],
  "scores": [
    {
      "stats": {
        "fn": 1,
        "tp": 0,
        "fp": 1
      },
      "mapping": {},
      "vuln_dates": {
        "CVE-2020-2263": "2020-09-16T14:15:13"
      },
      "scoring_model": "claude-3-opus-20240229",
      "type": "llm",
      "instruction_template_hash": "245ace12b6361954d0a2"
    }
  ],
  "instruction_template_hash": "10c0163db4740318a544",
  "version": "0.1.0"
}
