{
  "commit": "45633e713389cd70d4b9e38fce044c4b6c54dd49",
  "repo_url": "https://github.com/jenkinsci/htmlresource-plugin",
  "model": "gpt-4o-2024-05-13",
  "chunk_hashes": [
    "fdeff5a765a8440ba43b"
  ],
  "responses": [
    {
      "content": "```yaml\nleads:\n  - headline: \"Potential Command Injection\"\n    analysis: |\n      The `scriptler_initDetailLink` function dynamically constructs a URL using the user-specified `selId` without sanitization or validation. An attacker could exploit this by providing a specially crafted `selId` that contains malicious payloads, which might result in command injections when these URLs are further processed downstream.\n    cwe: CWE-77\n    function_names:\n      - scriptler_initDetailLink\n    filenames:\n      - src/main/webapp/lib/scriptler.js\n    classification: very promising\n  \n  - headline: \"Possible Cross-Site Scripting (XSS) in Script Description\"\n    analysis: |\n      The function `scriptler_descArguments` embeds parameters directly into the HTML without proper encoding. This could allow attackers to inject malicious scripts through specially crafted input parameters which could lead to cross-site scripting (XSS).\n    cwe: CWE-79\n    function_names:\n      - scriptler_descArguments\n    filenames:\n      - src/main/webapp/lib/scriptler.js\n    classification: very promising\n  \n  - headline: \"Potential XML External Entity (XXE) Vulnerability\"\n    analysis: |\n      The given code contains usage of the `StaplerRequest` class and subsequent XML parsing without explicitly disabling the resolution of external entities. This can lead to XML External Entity (XXE) attacks if user-controlled input is parsed and evaluated.\n    cwe: CWE-611\n    function_names: []\n    filenames: \n      - src/main/java/com/cwctravel/jenkinsci/plugins/htmlresource/HTMLResourceManagement.java\n    classification: very promising\n  \n  - headline: \"Improper Access Control for Sensitive Functions\"\n    analysis: |\n      The method `doUploadHTMLResource` does not implement sufficient checks before carrying out file upload operations, relying solely on `Hudson.ADMINISTER` permission. This could be abused to upload malicious files if there is any flaw or bypass in the permission system.\n    cwe: CWE-306\n    function_names:\n      - doUploadHTMLResource\n    filenames: \n      - src/main/java/com/cwctravel/jenkinsci/plugins/htmlresource/HTMLResourceManagement.java\n    classification: slightly promising\n  \n  - headline: \"Java Deserialization of Untrusted Data\"\n    analysis: |\n      The code uses `XStream` for XML serialization and deserialization. If any of the XML data might be controlled by an external user, this can lead to Java deserialization vulnerabilities which allow remote code execution (RCE).\n    cwe: CWE-502\n    function_names: []\n    filenames:\n      - src/main/java/com/cwctravel/jenkinsci/plugins/htmlresource/config/HTMLResourceConfiguration.java\n    classification: slightly promising\n  \n  - headline: \"Cleartext Transmission of Sensitive Information\"\n    analysis: |\n      The code mentions that resources are accessed through HTTP endpoints without indicating any form of encryption. This can lead to exposure of sensitive information when data is transmitted in clear text.\n    cwe: CWE-319\n    function_names: []\n    filenames: \n      - src/main/java/com/cwctravel/jenkinsci/plugins/htmlresource/HTMLResourcePageDecorator.java\n    classification: slightly promising\n  \n  - headline: \"Insecure Temporary File Creation\"\n    analysis: |\n      The function `saveHTMLResource` writes uploaded files directly to a directory using user-provided filenames. This can introduce race conditions and symlink attacks which can be exploited to overwrite or tamper with files.\n    cwe: CWE-377\n    function_names:\n      - saveHTMLResource\n    filenames: \n      - src/main/java/com/cwctravel/jenkinsci/plugins/htmlresource/HTMLResourceManagement.java\n    classification: not promising\n```",
      "date": "2024-06-09T12:50:28.926649",
      "usage": {
        "prompt_tokens": 11861,
        "completion_tokens": 777,
        "cost": 0.07096
      }
    }
  ],
  "leads": [
    {
      "headline": "Potential Command Injection",
      "analysis": "The scriptler_initDetailLink function dynamically constructs a URL using the user-specified selId without sanitization or validation. An attacker could exploit this by providing a specially crafted selId that contains malicious payloads, which might result in command injections when these URLs are further processed downstream.\n",
      "classification": "very promising",
      "cwe": "CWE-77",
      "function_names": [
        "scriptler_initDetailLink"
      ],
      "filenames": [
        "src/main/webapp/lib/scriptler.js"
      ]
    },
    {
      "headline": "Possible Cross-Site Scripting (XSS) in Script Description",
      "analysis": "The function scriptler_descArguments embeds parameters directly into the HTML without proper encoding. This could allow attackers to inject malicious scripts through specially crafted input parameters which could lead to cross-site scripting (XSS).\n",
      "classification": "very promising",
      "cwe": "CWE-79",
      "function_names": [
        "scriptler_descArguments"
      ],
      "filenames": [
        "src/main/webapp/lib/scriptler.js"
      ]
    },
    {
      "headline": "Potential XML External Entity (XXE) Vulnerability",
      "analysis": "The given code contains usage of the StaplerRequest class and subsequent XML parsing without explicitly disabling the resolution of external entities. This can lead to XML External Entity (XXE) attacks if user-controlled input is parsed and evaluated.\n",
      "classification": "very promising",
      "cwe": "CWE-611",
      "function_names": [],
      "filenames": [
        "src/main/java/com/cwctravel/jenkinsci/plugins/htmlresource/HTMLResourceManagement.java"
      ]
    },
    {
      "headline": "Improper Access Control for Sensitive Functions",
      "analysis": "The method doUploadHTMLResource does not implement sufficient checks before carrying out file upload operations, relying solely on Hudson.ADMINISTER permission. This could be abused to upload malicious files if there is any flaw or bypass in the permission system.\n",
      "classification": "slightly promising",
      "cwe": "CWE-306",
      "function_names": [
        "doUploadHTMLResource"
      ],
      "filenames": [
        "src/main/java/com/cwctravel/jenkinsci/plugins/htmlresource/HTMLResourceManagement.java"
      ]
    },
    {
      "headline": "Java Deserialization of Untrusted Data",
      "analysis": "The code uses XStream for XML serialization and deserialization. If any of the XML data might be controlled by an external user, this can lead to Java deserialization vulnerabilities which allow remote code execution (RCE).\n",
      "classification": "slightly promising",
      "cwe": "CWE-502",
      "function_names": [],
      "filenames": [
        "src/main/java/com/cwctravel/jenkinsci/plugins/htmlresource/config/HTMLResourceConfiguration.java"
      ]
    },
    {
      "headline": "Cleartext Transmission of Sensitive Information",
      "analysis": "The code mentions that resources are accessed through HTTP endpoints without indicating any form of encryption. This can lead to exposure of sensitive information when data is transmitted in clear text.\n",
      "classification": "slightly promising",
      "cwe": "CWE-319",
      "function_names": [],
      "filenames": [
        "src/main/java/com/cwctravel/jenkinsci/plugins/htmlresource/HTMLResourcePageDecorator.java"
      ]
    },
    {
      "headline": "Insecure Temporary File Creation",
      "analysis": "The function saveHTMLResource writes uploaded files directly to a directory using user-provided filenames. This can introduce race conditions and symlink attacks which can be exploited to overwrite or tamper with files.\n",
      "classification": "not promising",
      "cwe": "CWE-377",
      "function_names": [
        "saveHTMLResource"
      ],
      "filenames": [
        "src/main/java/com/cwctravel/jenkinsci/plugins/htmlresource/HTMLResourceManagement.java"
      ]
    }
  ],
  "scores": [
    {
      "stats": {
        "fn": 1,
        "tp": 0,
        "fp": 3
      },
      "mapping": {},
      "vuln_dates": {
        "CVE-2023-50774": "2023-12-13T18:15:44"
      },
      "scoring_model": "gpt-4o-2024-05-13",
      "type": "llm",
      "instruction_template_hash": "8998f09cf57fca8a6e03"
    },
    {
      "stats": {
        "fn": 1,
        "tp": 0,
        "fp": 3
      },
      "mapping": {},
      "vuln_dates": {
        "CVE-2023-50774": "2023-12-13T18:15:44"
      },
      "scoring_model": "claude-3-opus-20240229",
      "type": "llm",
      "instruction_template_hash": "245ace12b6361954d0a2"
    }
  ],
  "instruction_template_hash": "10c0163db4740318a544",
  "version": "0.1.0"
}
