{
  "commit": "1af4566991f5248fd0d3576ca4fbcc0a84293004",
  "repo_url": "https://github.com/benbusby/whoogle-search",
  "model": "claude-3-sonnet-20240229",
  "chunk_hashes": [
    "342bf80e2eb1c8a242cd"
  ],
  "responses": [
    {
      "content": "```yaml\nleads:\n  - headline: Potential Cross-Site Scripting (XSS) vulnerability\n    analysis: |\n      The application does not properly sanitize user input before rendering it in the response. This could potentially allow an attacker to inject malicious code (such as JavaScript) into the application's output, which could be executed in the victim's browser, leading to various attacks such as session hijacking, defacement, or data theft.\n    cwe: CWE-79\n    function_names:\n      - bold_search_terms\n      - add_ip_card\n      - add_currency_card\n    filenames:\n      - app/utils/results.py\n    classification: very promising\n\n  - headline: Potential Server-Side Request Forgery (SSRF) vulnerability\n    analysis: |\n      The application allows users to specify arbitrary URLs for fetching external resources such as images, audio files, and web pages. An attacker could potentially abuse this functionality to scan internal networks, perform port scanning, or access resources that should not be accessible from the application.\n    cwe: CWE-918\n    function_names:\n      - element\n    filenames:\n      - app/routes.py\n    classification: very promising\n\n  - headline: Potential Insecure Deserialization vulnerability\n    analysis: |\n      The application uses the pickle module to serialize and deserialize configuration data. Pickle is known to be insecure for deserializing untrusted data, as it can lead to arbitrary code execution. An attacker could potentially craft a malicious pickle payload and trick the application into deserializing it, leading to remote code execution.\n    cwe: CWE-502\n    function_names:\n      - load_config\n    filenames:\n      - app/routes.py\n    classification: very promising\n\n  - headline: Potential Open Redirect vulnerability\n    analysis: |\n      The application appears to redirect users to arbitrary URLs based on user input, without properly validating the target URL. This could potentially allow an attacker to craft a malicious URL and trick victims into visiting a malicious site, leading to phishing attacks or other types of social engineering attacks.\n    cwe: CWE-601\n    function_names:\n      - url\n    filenames:\n      - app/routes.py\n    classification: very promising\n\n  - headline: Potential Insecure Direct Object Reference vulnerability\n    analysis: |\n      The application allows users to load and save configuration files with arbitrary names. If the configuration files are not properly protected or sanitized, an attacker could potentially access or modify other users' configurations, leading to unauthorized access or data tampering.\n    cwe: CWE-639\n    function_names:\n      - load_config\n      - save_config\n    filenames:\n      - app/routes.py\n    classification: slightly promising\n\n  - headline: Potential Insufficiently Random Values vulnerability\n    analysis: |\n      The application generates user keys using the Fernet module from the cryptography library. While Fernet is a secure encryption mechanism, the key generation process may not provide sufficient entropy or use a cryptographically secure random number generator, potentially weakening the security of the encryption.\n    cwe: CWE-330\n    function_names:\n      - generate_user_key\n    filenames:\n      - app/utils/session.py\n    classification: slightly promising\n\n  - headline: Potential Security Misconfiguration\n    analysis: |\n      The application sets various security-related headers and configurations, such as Content Security Policy (CSP), session cookie settings, and X-Frame-Options. Misconfiguration of these settings could potentially weaken the application's security posture and make it more vulnerable to attacks like Cross-Site Scripting (XSS), Clickjacking, and others.\n    cwe: CWE-1035\n    function_names: []\n    filenames:\n      - app/__init__.py\n      - app/routes.py\n    classification: slightly promising\n\n  - headline: Potential Improper Authentication vulnerability\n    analysis: |\n      The application implements a basic authentication mechanism using environment variables. However, there is no clear indication of how the authentication credentials are securely stored or transmitted. Improper handling of authentication credentials could potentially lead to unauthorized access or credential theft.\n    cwe: CWE-287\n    function_names:\n      - auth_required\n    filenames:\n      - app/routes.py\n    classification: slightly promising\n\n  - headline: Potential Cleartext Storage of Sensitive Information\n    analysis: |\n      The application stores user session data, including configuration and encryption keys, in the filesystem. While the storage location is configurable, there is no indication that the data is encrypted or otherwise protected. Storing sensitive information in cleartext could potentially lead to data exposure if an attacker gains access to the filesystem.\n    cwe: CWE-312\n    function_names: []\n    filenames:\n      - app/utils/session.py\n      - app/__init__.py\n    classification: slightly promising\n```\n\nThe codebase for the Whoogle Search application contains several potential security vulnerabilities. Here's a summary of the most significant ones:\n\n1. **Cross-Site Scripting (XSS)**: The application does not properly sanitize user input before rendering it in the response, which could allow an attacker to inject malicious code (such as JavaScript) into the application's output.\n\n2. **Server-Side Request Forgery (SSRF)**: The application allows users to specify arbitrary URLs for fetching external resources, which an attacker could potentially abuse to scan internal networks, perform port scanning, or access resources that should not be accessible from the application.\n\n3. **Insecure Deserialization**: The application uses the `pickle` module to serialize and deserialize configuration data, which is known to be insecure for deserializing untrusted data and can lead to arbitrary code execution.\n\n4. **Open Redirect**: The application appears to redirect users to arbitrary URLs based on user input without properly validating the target URL, which could allow phishing attacks or other social engineering attacks.\n\n5. **Insecure Direct Object Reference**: The application allows users to load and save configuration files with arbitrary names, which could potentially lead to unauthorized access or data tampering if the configuration files are not properly protected or sanitized.\n\n6. **Insufficiently Random Values**: The application generates user keys using the `Fernet` module from the `cryptography` library, but the key generation process may not provide sufficient entropy or use a cryptographically secure random number generator, potentially weakening the security of the encryption.\n\n7. **Security Misconfiguration**: The application sets various security-related headers and configurations, but misconfiguration of these settings could weaken the application's security posture and make it more vulnerable to attacks like Cross-Site Scripting (XSS), Clickjacking, and others.\n\n8. **Improper Authentication**: The application implements a basic authentication mechanism using environment variables, but there is no clear indication of how the authentication credentials are securely stored or transmitted, which could lead to unauthorized access or credential theft.\n\n9. **Cleartext Storage of Sensitive Information**: The application stores user session data, including configuration and encryption keys, in the filesystem without encryption or other protection measures, which could potentially lead to data exposure if an attacker gains access to the filesystem.\n\nIt's important to note that the classification of these vulnerabilities as \"very promising,\" \"slightly promising,\" or \"not promising\" is subjective and depends on various factors such as the specific use case, deployment environment, and risk tolerance of the application.",
      "date": "2024-06-08T23:00:43.423095",
      "usage": {
        "prompt_tokens": 46540,
        "completion_tokens": 1705,
        "cost": 0.165195
      }
    }
  ],
  "leads": [
    {
      "headline": "Potential Cross-Site Scripting (XSS) vulnerability",
      "analysis": "The application does not properly sanitize user input before rendering it in the response. This could potentially allow an attacker to inject malicious code (such as JavaScript) into the application's output, which could be executed in the victim's browser, leading to various attacks such as session hijacking, defacement, or data theft.\n",
      "classification": "very promising",
      "cwe": "CWE-79",
      "function_names": [
        "bold_search_terms",
        "add_ip_card",
        "add_currency_card"
      ],
      "filenames": [
        "app/utils/results.py"
      ]
    },
    {
      "headline": "Potential Server-Side Request Forgery (SSRF) vulnerability",
      "analysis": "The application allows users to specify arbitrary URLs for fetching external resources such as images, audio files, and web pages. An attacker could potentially abuse this functionality to scan internal networks, perform port scanning, or access resources that should not be accessible from the application.\n",
      "classification": "very promising",
      "cwe": "CWE-918",
      "function_names": [
        "element"
      ],
      "filenames": [
        "app/routes.py"
      ]
    },
    {
      "headline": "Potential Insecure Deserialization vulnerability",
      "analysis": "The application uses the pickle module to serialize and deserialize configuration data. Pickle is known to be insecure for deserializing untrusted data, as it can lead to arbitrary code execution. An attacker could potentially craft a malicious pickle payload and trick the application into deserializing it, leading to remote code execution.\n",
      "classification": "very promising",
      "cwe": "CWE-502",
      "function_names": [
        "load_config"
      ],
      "filenames": [
        "app/routes.py"
      ]
    },
    {
      "headline": "Potential Open Redirect vulnerability",
      "analysis": "The application appears to redirect users to arbitrary URLs based on user input, without properly validating the target URL. This could potentially allow an attacker to craft a malicious URL and trick victims into visiting a malicious site, leading to phishing attacks or other types of social engineering attacks.\n",
      "classification": "very promising",
      "cwe": "CWE-601",
      "function_names": [
        "url"
      ],
      "filenames": [
        "app/routes.py"
      ]
    },
    {
      "headline": "Potential Insecure Direct Object Reference vulnerability",
      "analysis": "The application allows users to load and save configuration files with arbitrary names. If the configuration files are not properly protected or sanitized, an attacker could potentially access or modify other users' configurations, leading to unauthorized access or data tampering.\n",
      "classification": "slightly promising",
      "cwe": "CWE-639",
      "function_names": [
        "load_config",
        "save_config"
      ],
      "filenames": [
        "app/routes.py"
      ]
    },
    {
      "headline": "Potential Insufficiently Random Values vulnerability",
      "analysis": "The application generates user keys using the Fernet module from the cryptography library. While Fernet is a secure encryption mechanism, the key generation process may not provide sufficient entropy or use a cryptographically secure random number generator, potentially weakening the security of the encryption.\n",
      "classification": "slightly promising",
      "cwe": "CWE-330",
      "function_names": [
        "generate_user_key"
      ],
      "filenames": [
        "app/utils/session.py"
      ]
    },
    {
      "headline": "Potential Security Misconfiguration",
      "analysis": "The application sets various security-related headers and configurations, such as Content Security Policy (CSP), session cookie settings, and X-Frame-Options. Misconfiguration of these settings could potentially weaken the application's security posture and make it more vulnerable to attacks like Cross-Site Scripting (XSS), Clickjacking, and others.\n",
      "classification": "slightly promising",
      "cwe": "CWE-1035",
      "function_names": [],
      "filenames": [
        "app/__init__.py",
        "app/routes.py"
      ]
    },
    {
      "headline": "Potential Improper Authentication vulnerability",
      "analysis": "The application implements a basic authentication mechanism using environment variables. However, there is no clear indication of how the authentication credentials are securely stored or transmitted. Improper handling of authentication credentials could potentially lead to unauthorized access or credential theft.\n",
      "classification": "slightly promising",
      "cwe": "CWE-287",
      "function_names": [
        "auth_required"
      ],
      "filenames": [
        "app/routes.py"
      ]
    },
    {
      "headline": "Potential Cleartext Storage of Sensitive Information",
      "analysis": "The application stores user session data, including configuration and encryption keys, in the filesystem. While the storage location is configurable, there is no indication that the data is encrypted or otherwise protected. Storing sensitive information in cleartext could potentially lead to data exposure if an attacker gains access to the filesystem.\n",
      "classification": "slightly promising",
      "cwe": "CWE-312",
      "function_names": [],
      "filenames": [
        "app/utils/session.py",
        "app/__init__.py"
      ]
    }
  ],
  "scores": [
    {
      "stats": {
        "fn": 3,
        "tp": 2,
        "fp": 2
      },
      "mapping": {
        "1": "CVE-2024-22203",
        "2": "CVE-2024-22204"
      },
      "vuln_dates": {
        "CVE-2022-25303": "2022-07-12T15:15:09",
        "CVE-2024-22204": "2024-01-23T18:15:18",
        "CVE-2024-22203": "2024-01-23T18:15:18",
        "CVE-2024-22205": "2024-01-23T18:15:18",
        "CVE-2024-22417": "2024-01-23T18:15:18"
      },
      "scoring_model": "gpt-4o-2024-05-13",
      "type": "llm",
      "instruction_template_hash": "8998f09cf57fca8a6e03"
    }
  ],
  "instruction_template_hash": "10c0163db4740318a544",
  "version": "0.1.0"
}
