{
  "commit": "62fc70e40562c0e70573661ec686b0e28098b008",
  "repo_url": "https://github.com/cea-hpc/sshproxy",
  "model": "gpt-4o-2024-05-13",
  "chunk_hashes": [
    "268a7718fc29913cc8c7"
  ],
  "responses": [
    {
      "content": "```yaml\nleads:\n  - headline: \"Sensitive Information Hardcoded in Configuration\"\n    analysis: |\n      The configuration file `/etc/sshproxy/sshproxy.yaml` includes hardcoded sensitive information, such as passwords and TLS certificate keys. The presence of hardcoded sensitive information can result in unauthorized access if the configuration file is leaked or accessed by adversaries.\n    cwe: CWE-798\n    function_names: []\n    filenames:\n      - test/centos-image/gateway.sh\n    classification: very promising\n\n  - headline: \"Improper Cleanup of Docker Containers\"\n    analysis: |\n      The script `test/run.sh` defines a `cleanup` function to stop and remove Docker containers. However, if a critical failure occurs, the `cleanup` function will only be executed for certain signals and exit scenarios, not ensuring proper cleanup in all exceptional conditions.\n    cwe: CWE-404\n    function_names:\n      - cleanup\n    filenames:\n      - test/run.sh\n    classification: slightly promising\n\n  - headline: \"Plaintext Transmission of Sensitive Information\"\n    analysis: |\n      In the script `test/centos-image/etcd.sh`, the etcd process listens for client connections without encryption on the peer URLs, which can result in the plaintext transmission of sensitive information over the network.\n    cwe: CWE-319\n    function_names: []\n    filenames:\n      - test/centos-image/etcd.sh\n    classification: slightly promising\n\n  - headline: \"Shell Command Injection Vulnerability\"\n    analysis: |\n      The script `vendor/google.golang.org/grpc/vet.sh` uses user-controlled input for the `protoc` command line without appropriate sanitization, making it susceptible to shell command injection attacks.\n    cwe: CWE-78\n    function_names:\n      - main\n    filenames:\n      - vendor/google.golang.org/grpc/vet.sh\n    classification: very promising\n\n  - headline: \"Improper Handling of Git Commands\"\n    analysis: |\n      The script `vendor/google.golang.org/grpc/vet.sh` executes git commands without any sanitation or validation. This could lead to issues such as code execution if an attacker can influence the inputs to these git commands.\n    cwe: CWE-77\n    function_names:\n      - not\n      - die\n    filenames:\n      - vendor/google.golang.org/grpc/vet.sh\n    classification: slightly promising\n\n  - headline: \"Unprotected Temporary Files\"\n    analysis: |\n      The script `vendor/google.golang.org/grpc/regenerate.sh` creates temporary files in the directory obtained from `mktemp -d`, but it does not set restrictive permissions nor ensures that the directory is used securely.\n    cwe: CWE-362\n    function_names:\n      - regenerate\n    filenames:\n      - vendor/google.golang.org/grpc/regenerate.sh\n    classification: not promising\n\n  - headline: \"Weak Random Number Generation\"\n    analysis: |\n      The script `vendor/github.com/creack/pty/test_crosscompile.sh` may rely on weak or predictable sources of randomness without using a cryptographic random number generator, making it vulnerable to attacks predicting random outputs.\n    cwe: CWE-330\n    function_names: []\n    filenames:\n      - vendor/github.com/creack/pty/test_crosscompile.sh\n    classification: not promising\n```\n\nThis YAML object outlines the identified security vulnerabilities by highlighting their descriptions, root causes, relevant function names, filenames, and their classifications for further action.",
      "date": "2024-06-09T09:35:33.651613",
      "usage": {
        "prompt_tokens": 18956,
        "completion_tokens": 722,
        "cost": 0.10561
      }
    }
  ],
  "leads": [
    {
      "headline": "Sensitive Information Hardcoded in Configuration",
      "analysis": "The configuration file /etc/sshproxy/sshproxy.yaml includes hardcoded sensitive information, such as passwords and TLS certificate keys. The presence of hardcoded sensitive information can result in unauthorized access if the configuration file is leaked or accessed by adversaries.\n",
      "classification": "very promising",
      "cwe": "CWE-798",
      "function_names": [],
      "filenames": [
        "test/centos-image/gateway.sh"
      ]
    },
    {
      "headline": "Improper Cleanup of Docker Containers",
      "analysis": "The script test/run.sh defines a cleanup function to stop and remove Docker containers. However, if a critical failure occurs, the cleanup function will only be executed for certain signals and exit scenarios, not ensuring proper cleanup in all exceptional conditions.\n",
      "classification": "slightly promising",
      "cwe": "CWE-404",
      "function_names": [
        "cleanup"
      ],
      "filenames": [
        "test/run.sh"
      ]
    },
    {
      "headline": "Plaintext Transmission of Sensitive Information",
      "analysis": "In the script test/centos-image/etcd.sh, the etcd process listens for client connections without encryption on the peer URLs, which can result in the plaintext transmission of sensitive information over the network.\n",
      "classification": "slightly promising",
      "cwe": "CWE-319",
      "function_names": [],
      "filenames": [
        "test/centos-image/etcd.sh"
      ]
    },
    {
      "headline": "Shell Command Injection Vulnerability",
      "analysis": "The script vendor/google.golang.org/grpc/vet.sh uses user-controlled input for the protoc command line without appropriate sanitization, making it susceptible to shell command injection attacks.\n",
      "classification": "very promising",
      "cwe": "CWE-78",
      "function_names": [
        "main"
      ],
      "filenames": [
        "vendor/google.golang.org/grpc/vet.sh"
      ]
    },
    {
      "headline": "Improper Handling of Git Commands",
      "analysis": "The script vendor/google.golang.org/grpc/vet.sh executes git commands without any sanitation or validation. This could lead to issues such as code execution if an attacker can influence the inputs to these git commands.\n",
      "classification": "slightly promising",
      "cwe": "CWE-77",
      "function_names": [
        "not",
        "die"
      ],
      "filenames": [
        "vendor/google.golang.org/grpc/vet.sh"
      ]
    },
    {
      "headline": "Unprotected Temporary Files",
      "analysis": "The script vendor/google.golang.org/grpc/regenerate.sh creates temporary files in the directory obtained from mktemp -d, but it does not set restrictive permissions nor ensures that the directory is used securely.\n",
      "classification": "not promising",
      "cwe": "CWE-362",
      "function_names": [
        "regenerate"
      ],
      "filenames": [
        "vendor/google.golang.org/grpc/regenerate.sh"
      ]
    },
    {
      "headline": "Weak Random Number Generation",
      "analysis": "The script vendor/github.com/creack/pty/test_crosscompile.sh may rely on weak or predictable sources of randomness without using a cryptographic random number generator, making it vulnerable to attacks predicting random outputs.\n",
      "classification": "not promising",
      "cwe": "CWE-330",
      "function_names": [],
      "filenames": [
        "vendor/github.com/creack/pty/test_crosscompile.sh"
      ]
    }
  ],
  "scores": [
    {
      "stats": {
        "fn": 1,
        "tp": 0,
        "fp": 2
      },
      "mapping": {},
      "vuln_dates": {
        "CVE-2024-34713": "2024-05-14T16:17:27"
      },
      "scoring_model": "gpt-4o-2024-05-13",
      "type": "llm",
      "instruction_template_hash": "8998f09cf57fca8a6e03"
    }
  ],
  "instruction_template_hash": "10c0163db4740318a544",
  "version": "0.1.0"
}
