{
  "commit": "21c3403719e47a9d5b4da76897800eb64c351dad",
  "repo_url": "https://github.com/geopython/pycsw",
  "model": "gemini/gemini-1.5-pro",
  "chunk_hashes": [
    "a0fb9461c3aa6ed3cc7a"
  ],
  "responses": [
    {
      "content": "```yaml\nleads:\n  - headline: Potential SQL injection vulnerability in CQL queries\n    analysis: |\n      The `_cql_update_queryables_mappings` function in `pycsw/server.py` aims to transform properties in CQL queries to their corresponding database columns. \n      However, it directly replaces property names with database column names using string replacement. \n      If a malicious user provides a CQL query with a crafted property name that includes SQL syntax, it could lead to SQL injection.\n    cwe: CWE-89\n    function_names:\n      - _cql_update_queryables_mappings\n    filenames:\n      - pycsw/server.py\n    classification: slightly promising\n  - headline: Potential XML External Entity (XXE) Injection\n    analysis: |\n      The code uses `lxml` to parse XML data in several places. Notably, in `pycsw/server.py` during the parsing of POST data and in `pycsw/admin.py` during loading of records.\n      However, it's not evident if the `lxml` parser is configured to prevent XXE attacks. By default, `lxml` may allow resolution of external entities, which can be abused by attackers to read arbitrary files from the server or launch denial-of-service attacks.\n    cwe: CWE-611\n    function_names:\n      - parse_postdata\n      - load_records\n    filenames:\n      - pycsw/server.py\n      - pycsw/admin.py\n    classification: slightly promising\n  - headline: Improper Neutralization of Special Elements in Output Used by a Downstream Component ('Injection')\n    analysis: |\n      In `pycsw/admin.py`, the `export_records` function writes XML records retrieved from the database directly to files without proper escaping or sanitization. This could lead to injection vulnerabilities if the data within records contains malicious content like crafted JavaScript or HTML that would be executed in a downstream application or browser.\n    cwe: CWE-74\n    function_names:\n      - export_records\n    filenames:\n      - pycsw/admin.py\n    classification: not promising\n  - headline: Potential for Uncontrolled Resource Consumption (Denial of Service)\n    analysis: |\n      The `GetRecords` request in `pycsw/server.py` doesn't have adequate controls on the `maxrecords` parameter when it is not set in the configuration file.\n      A malicious user could potentially request a massive number of records, leading to excessive resource consumption on the server and a potential denial-of-service.\n    cwe: CWE-400\n    function_names:\n      - dispatch\n    filenames:\n      - pycsw/server.py\n    classification: not promising\n  - headline: Potential Information Exposure Through Error Messages\n    analysis: |\n      In multiple locations (`pycsw/server.py`, `pycsw/repository.py`, `pycsw/admin.py`), exception messages are logged or returned to the user directly without proper sanitization.\n      This might expose sensitive information like database connection details or internal file paths to an attacker.\n    cwe: CWE-209\n    function_names:\n      - dispatch_cgi\n      - dispatch_wsgi\n      - query\n      - insert\n      - update\n      - delete\n      - load_records\n      - export_records\n      - refresh_harvested_records\n      - post_xml\n      - validate_xml\n    filenames:\n      - pycsw/server.py\n      - pycsw/repository.py\n      - pycsw/admin.py\n    classification: not promising\n```",
      "date": "2024-06-12T16:58:17.245693",
      "usage": {
        "prompt_tokens": 104764,
        "completion_tokens": 725,
        "cost": 0.066836875
      }
    }
  ],
  "leads": [
    {
      "headline": "Potential SQL injection vulnerability in CQL queries",
      "analysis": "The _cql_update_queryables_mappings function in pycsw/server.py aims to transform properties in CQL queries to their corresponding database columns. \nHowever, it directly replaces property names with database column names using string replacement. \nIf a malicious user provides a CQL query with a crafted property name that includes SQL syntax, it could lead to SQL injection.\n",
      "classification": "slightly promising",
      "cwe": "CWE-89",
      "function_names": [
        "_cql_update_queryables_mappings"
      ],
      "filenames": [
        "pycsw/server.py"
      ]
    },
    {
      "headline": "Potential XML External Entity (XXE) Injection",
      "analysis": "The code uses lxml to parse XML data in several places. Notably, in pycsw/server.py during the parsing of POST data and in pycsw/admin.py during loading of records.\nHowever, it's not evident if the lxml parser is configured to prevent XXE attacks. By default, lxml may allow resolution of external entities, which can be abused by attackers to read arbitrary files from the server or launch denial-of-service attacks.\n",
      "classification": "slightly promising",
      "cwe": "CWE-611",
      "function_names": [
        "parse_postdata",
        "load_records"
      ],
      "filenames": [
        "pycsw/server.py",
        "pycsw/admin.py"
      ]
    },
    {
      "headline": "Improper Neutralization of Special Elements in Output Used by a Downstream Component ('Injection')",
      "analysis": "In pycsw/admin.py, the export_records function writes XML records retrieved from the database directly to files without proper escaping or sanitization. This could lead to injection vulnerabilities if the data within records contains malicious content like crafted JavaScript or HTML that would be executed in a downstream application or browser.\n",
      "classification": "not promising",
      "cwe": "CWE-74",
      "function_names": [
        "export_records"
      ],
      "filenames": [
        "pycsw/admin.py"
      ]
    },
    {
      "headline": "Potential for Uncontrolled Resource Consumption (Denial of Service)",
      "analysis": "The GetRecords request in pycsw/server.py doesn't have adequate controls on the maxrecords parameter when it is not set in the configuration file.\nA malicious user could potentially request a massive number of records, leading to excessive resource consumption on the server and a potential denial-of-service.\n",
      "classification": "not promising",
      "cwe": "CWE-400",
      "function_names": [
        "dispatch"
      ],
      "filenames": [
        "pycsw/server.py"
      ]
    },
    {
      "headline": "Potential Information Exposure Through Error Messages",
      "analysis": "In multiple locations (pycsw/server.py, pycsw/repository.py, pycsw/admin.py), exception messages are logged or returned to the user directly without proper sanitization.\nThis might expose sensitive information like database connection details or internal file paths to an attacker.\n",
      "classification": "not promising",
      "cwe": "CWE-209",
      "function_names": [
        "dispatch_cgi",
        "dispatch_wsgi",
        "query"
      ],
      "filenames": [
        "pycsw/server.py",
        "pycsw/repository.py",
        "pycsw/admin.py"
      ]
    }
  ],
  "scores": [
    {
      "stats": {
        "fn": 1,
        "tp": 0,
        "fp": 0
      },
      "mapping": {},
      "vuln_dates": {
        "CVE-2016-8640": "2018-08-01T18:29:00"
      },
      "scoring_model": "claude-3-opus-20240229",
      "type": "llm",
      "instruction_template_hash": "245ace12b6361954d0a2"
    },
    {
      "stats": {
        "fn": 1,
        "tp": 0,
        "fp": 0
      },
      "mapping": {},
      "vuln_dates": {
        "CVE-2016-8640": "2018-08-01T18:29:00"
      },
      "scoring_model": "claude-3-5-sonnet-20240620",
      "type": "llm",
      "instruction_template_hash": "245ace12b6361954d0a2"
    }
  ],
  "instruction_template_hash": "10c0163db4740318a544",
  "version": "0.1.0"
}
