{
  "commit": "05c3346ce8a7c6dfb389cda556c29245ff14a033",
  "repo_url": "https://github.com/jenkinsci/valgrind-plugin",
  "model": "claude-3-sonnet-20240229",
  "chunk_hashes": [
    "222f6aba8d96bc079781"
  ],
  "responses": [
    {
      "content": "Based on the code, I can identify the following potential security vulnerabilities:\n\n```yaml\nleads:\n  - headline: Lack of input validation\n    analysis: The code does not appear to perform any input validation on various user-supplied strings and configurations, which could potentially lead to injection vulnerabilities or unexpected behavior.\n    cwe: CWE-20\n    function_names:\n      - ValgrindBuilder\n      - ValgrindPublisher\n    filenames:\n      - src/main/java/org/jenkinsci/plugins/valgrind/ValgrindBuilder.java\n      - src/main/java/org/jenkinsci/plugins/valgrind/ValgrindPublisher.java\n    classification: very promising\n\n  - headline: Use of insecure communication channels\n    analysis: The code does not seem to enforce encryption or secure communication channels when transferring potentially sensitive data, such as source code files or build configurations.\n    cwe: CWE-319\n    function_names:\n      - ValgrindSourceGrabber\n    filenames:\n      - src/main/java/org/jenkinsci/plugins/valgrind/util/ValgrindSourceGrabber.java\n    classification: slightly promising\n\n  - headline: Potential path traversal vulnerability\n    analysis: The code constructs file paths based on user input, which could potentially lead to path traversal vulnerabilities if the input is not properly sanitized.\n    cwe: CWE-22\n    function_names:\n      - ValgrindSourceFile\n    filenames:\n      - src/main/java/org/jenkinsci/plugins/valgrind/util/ValgrindSourceFile.java\n    classification: slightly promising\n\n  - headline: Use of insecure pseudorandom number generator\n    analysis: The code does not appear to use cryptographically secure random number generators, which could potentially lead to predictable or weak random values being generated.\n    cwe: CWE-338\n    function_names: []\n    filenames: []\n    classification: not promising\n```\n\nThe main concerns identified are:\n\n1. Lack of input validation on various user-supplied strings and configurations, which could potentially lead to injection vulnerabilities or unexpected behavior.\n2. Use of insecure communication channels when transferring potentially sensitive data, such as source code files or build configurations.\n3. Potential path traversal vulnerability when constructing file paths based on user input.\n4. Potential use of insecure pseudorandom number generators, although no specific instances were found in the code.\n\nIt's important to note that a thorough security review would require a more comprehensive analysis, including testing and code review by security experts. However, this analysis provides an initial assessment of potential security vulnerabilities based on the provided code.",
      "date": "2024-06-12T19:30:04.949383",
      "usage": {
        "prompt_tokens": 53193,
        "completion_tokens": 622,
        "cost": 0.168909
      }
    }
  ],
  "leads": [
    {
      "headline": "Lack of input validation",
      "analysis": "The code does not appear to perform any input validation on various user-supplied strings and configurations, which could potentially lead to injection vulnerabilities or unexpected behavior.",
      "classification": "very promising",
      "cwe": "CWE-20",
      "function_names": [
        "ValgrindBuilder",
        "ValgrindPublisher"
      ],
      "filenames": [
        "src/main/java/org/jenkinsci/plugins/valgrind/ValgrindBuilder.java",
        "src/main/java/org/jenkinsci/plugins/valgrind/ValgrindPublisher.java"
      ]
    },
    {
      "headline": "Use of insecure communication channels",
      "analysis": "The code does not seem to enforce encryption or secure communication channels when transferring potentially sensitive data, such as source code files or build configurations.",
      "classification": "slightly promising",
      "cwe": "CWE-319",
      "function_names": [
        "ValgrindSourceGrabber"
      ],
      "filenames": [
        "src/main/java/org/jenkinsci/plugins/valgrind/util/ValgrindSourceGrabber.java"
      ]
    },
    {
      "headline": "Potential path traversal vulnerability",
      "analysis": "The code constructs file paths based on user input, which could potentially lead to path traversal vulnerabilities if the input is not properly sanitized.",
      "classification": "slightly promising",
      "cwe": "CWE-22",
      "function_names": [
        "ValgrindSourceFile"
      ],
      "filenames": [
        "src/main/java/org/jenkinsci/plugins/valgrind/util/ValgrindSourceFile.java"
      ]
    },
    {
      "headline": "Use of insecure pseudorandom number generator",
      "analysis": "The code does not appear to use cryptographically secure random number generators, which could potentially lead to predictable or weak random values being generated.",
      "classification": "not promising",
      "cwe": "CWE-338",
      "function_names": [],
      "filenames": []
    }
  ],
  "scores": [
    {
      "stats": {
        "fn": 2,
        "tp": 0,
        "fp": 1
      },
      "mapping": {},
      "vuln_dates": {
        "CVE-2020-2246": "2020-09-01T14:15:13",
        "CVE-2020-2245": "2020-09-01T14:15:13"
      },
      "scoring_model": "claude-3-opus-20240229",
      "type": "llm",
      "instruction_template_hash": "245ace12b6361954d0a2"
    },
    {
      "stats": {
        "fn": 2,
        "tp": 0,
        "fp": 1
      },
      "mapping": {},
      "vuln_dates": {
        "CVE-2020-2246": "2020-09-01T14:15:13",
        "CVE-2020-2245": "2020-09-01T14:15:13"
      },
      "scoring_model": "claude-3-5-sonnet-20240620",
      "type": "llm",
      "instruction_template_hash": "245ace12b6361954d0a2"
    }
  ],
  "instruction_template_hash": "10c0163db4740318a544",
  "version": "0.1.0"
}
