{
  "commit": "154672eb175a96f2066e7c7cfb890709868ef343",
  "repo_url": "https://github.com/thehive-project/cortex",
  "model": "gpt-4o-2024-05-13",
  "chunk_hashes": [
    "ae382d148cd45a0b8baa"
  ],
  "responses": [
    {
      "content": "```yaml\nleads:\n  - headline: \"Potential Command Injection in MISP Module Loader\"\n    analysis: |\n      The `--run` option section of the `contrib/misp-modules-loader.py` script uses `json.dumps` without any sanitization or validation on inputs. This could allow an attacker to inject a malicious Python command via a crafted JSON payload.\n    cwe: CWE-78\n    function_names:\n      - run\n    filenames:\n      - contrib/misp-modules-loader.py\n    classification: very promising\n\n  - headline: \"Express API Error Handling Weakness\"\n    analysis: |\n      Multiple endpoints in various controllers do not sanitize or properly manage error messages (e.g., `AuthenticationCtrl`, `UserCtrl`). This could lead to information leakage when an error occurs, potentially providing sensitive data about the system.\n    cwe: CWE-209\n    function_names:\n      - login\n      - create\n      - get\n      - update\n    filenames:\n      - app/org/thp/cortex/controllers/AuthenticationCtrl.scala\n      - app/org/thp/cortex/controllers/UserCtrl.scala\n    classification: very promising\n\n  - headline: \"Potential SQL Injection in Organization Service\"\n    analysis: |\n      User-supplied inputs are directly concatenated into SQL queries in the `findForOrganization` method of `OrganizationSrv`. This may allow an attacker to modify the behavior of SQL queries through specially crafted input.\n    cwe: CWE-89\n    function_names:\n      - findForOrganization\n    filenames:\n      - app/org/thp/cortex/services/OrganizationSrv.scala\n    classification: very promising\n\n  - headline: \"Unsafe File Handling in MISP File Processor\"\n    analysis: |\n      The `downloadZip` function in `AttachmentCtrl` uses user-supplied filenames without sufficient validation to ensure filenames are safe. This could lead to directory traversal attacks where an attacker gains access to restricted files.\n    cwe: CWE-22\n    function_names:\n      - downloadZip\n    filenames:\n      - app/org/thp/cortex/controllers/AttachmentCtrl.scala\n    classification: very promising\n\n  - headline: \" Hardcoded Password in Test Script\"\n    analysis: |\n      The `test/resources/test.sh` script uses a hardcoded password (\"malware\") for the ZIP file password. This can lead to unauthorized access if the script is deployed in a production environment.\n    cwe: CWE-798\n    function_names: []\n    filenames:\n      - test/resources/test.sh\n    classification: not promising\n```",
      "date": "2024-06-13T17:15:34.433760",
      "usage": {
        "prompt_tokens": 110115,
        "completion_tokens": 523,
        "cost": 0.55842
      }
    }
  ],
  "leads": [
    {
      "headline": "Potential Command Injection in MISP Module Loader",
      "analysis": "The --run option section of the contrib/misp-modules-loader.py script uses json.dumps without any sanitization or validation on inputs. This could allow an attacker to inject a malicious Python command via a crafted JSON payload.\n",
      "classification": "very promising",
      "cwe": "CWE-78",
      "function_names": [
        "run"
      ],
      "filenames": [
        "contrib/misp-modules-loader.py"
      ]
    },
    {
      "headline": "Express API Error Handling Weakness",
      "analysis": "Multiple endpoints in various controllers do not sanitize or properly manage error messages (e.g., AuthenticationCtrl, UserCtrl). This could lead to information leakage when an error occurs, potentially providing sensitive data about the system.\n",
      "classification": "very promising",
      "cwe": "CWE-209",
      "function_names": [
        "login",
        "create",
        "get"
      ],
      "filenames": [
        "app/org/thp/cortex/controllers/AuthenticationCtrl.scala",
        "app/org/thp/cortex/controllers/UserCtrl.scala"
      ]
    },
    {
      "headline": "Potential SQL Injection in Organization Service",
      "analysis": "User-supplied inputs are directly concatenated into SQL queries in the findForOrganization method of OrganizationSrv. This may allow an attacker to modify the behavior of SQL queries through specially crafted input.\n",
      "classification": "very promising",
      "cwe": "CWE-89",
      "function_names": [
        "findForOrganization"
      ],
      "filenames": [
        "app/org/thp/cortex/services/OrganizationSrv.scala"
      ]
    },
    {
      "headline": "Unsafe File Handling in MISP File Processor",
      "analysis": "The downloadZip function in AttachmentCtrl uses user-supplied filenames without sufficient validation to ensure filenames are safe. This could lead to directory traversal attacks where an attacker gains access to restricted files.\n",
      "classification": "very promising",
      "cwe": "CWE-22",
      "function_names": [
        "downloadZip"
      ],
      "filenames": [
        "app/org/thp/cortex/controllers/AttachmentCtrl.scala"
      ]
    },
    {
      "headline": " Hardcoded Password in Test Script",
      "analysis": "The test/resources/test.sh script uses a hardcoded password (\"malware\") for the ZIP file password. This can lead to unauthorized access if the script is deployed in a production environment.\n",
      "classification": "not promising",
      "cwe": "CWE-798",
      "function_names": [],
      "filenames": [
        "test/resources/test.sh"
      ]
    }
  ],
  "scores": [
    {
      "stats": {
        "fn": 1,
        "tp": 0,
        "fp": 4
      },
      "mapping": {},
      "vuln_dates": {
        "CVE-2018-20226": "2018-12-21T23:29:00"
      },
      "scoring_model": "claude-3-opus-20240229",
      "type": "llm",
      "instruction_template_hash": "245ace12b6361954d0a2"
    },
    {
      "stats": {
        "fn": 1,
        "tp": 0,
        "fp": 4
      },
      "mapping": {},
      "vuln_dates": {
        "CVE-2018-20226": "2018-12-21T23:29:00"
      },
      "scoring_model": "claude-3-5-sonnet-20240620",
      "type": "llm",
      "instruction_template_hash": "245ace12b6361954d0a2"
    }
  ],
  "instruction_template_hash": "10c0163db4740318a544",
  "version": "0.1.0"
}
