{
  "commit": "8a23c464445faba645d2add8389afed41a3958bb",
  "repo_url": "https://github.com/lif-platforms/lif-auth-server",
  "model": "gpt-4o-2024-05-13",
  "chunk_hashes": [
    "fa3bd30bd9d234850357"
  ],
  "responses": [
    {
      "content": "```yaml\nleads:\n  - headline: \"Possible improper logging of sensitive information\"\n    analysis: |\n      The `logger.py` utility logs messages, and it seems to include detailed information including date and time. Without proper scrutiny, this logging might inadvertently capture and store sensitive information such as passwords, tokens, etc. if they are part of the logs. Storing these in plaintext could lead to exposure of sensitive information if the log files are accessed by unauthorized users.\n    cwe: CWE-532\n    function_names:\n      - showInfo\n      - showWarning\n      - showError\n    filenames:\n      - src/utils/logger.py\n    classification: very promising\n\n  - headline: \"Unsanitized input in database operations\"\n    analysis: |\n      The `create_account`, `check_username`, and various other database functions in `db_interface.py` directly use input parameters in SQL queries without sanitization, making them potentially susceptible to SQL injection attacks. The usage of string interpolation with user inputs to form SQL queries is insecure and can lead to database compromise.\n    cwe: CWE-89\n    function_names:\n      - create_account\n      - check_username\n      - check_email\n    filenames:\n      - src/utils/db_interface.py\n    classification: very promising\n\n  - headline: \"Exposure of sensitive configuration data\"\n    analysis: |\n      Configuration files like `config.yml` and `access-control.yml` are being read and the content is stored in global variables without validation and further security checks. If these files contain sensitive information (e.g., database credentials), their exposure can lead to security risks.\n    cwe: CWE-200\n    function_names:\n    filenames:\n      - src/auth_server.py\n      - src/utils/access_control.py\n      - src/utils/db_interface.py\n    classification: slightly promising\n  \n  - headline: \"Insecure token validation process\"\n    analysis: |\n      The function `verify_credentials` in `db_interface.py` checks for the presence of a specific token in the database for verification but doesn\u2019t use any form of timed comparison or other protection methods that can prevent timing attacks. Additionally, tokens are stored and directly compared in plaintext, which is a potential security risk if intercepted.\n    cwe: CWE-287\n    function_names:\n      - verify_credentials\n      - check_token\n      - verify_token\n    filenames:\n      - src/utils/db_interface.py\n    classification: very promising\n\n  - headline: \"Cross-Site Scripting (XSS) vulnerability with user profile data\"\n    analysis: |\n      User inputs like bio and pronouns are being stored in the database and potentially rendered on web pages. If these inputs are not properly sanitized before storage and rendering, it could lead to Cross-Site Scripting (XSS) attacks where malicious scripts could be executed in the user's browser.\n    cwe: CWE-79\n    function_names:\n      - update_account_info\n    filenames:\n      - src/auth_server.py\n    classification: very promising\n```",
      "date": "2024-06-09T13:12:59.968259",
      "usage": {
        "prompt_tokens": 9229,
        "completion_tokens": 614,
        "cost": 0.055355
      }
    }
  ],
  "leads": [
    {
      "headline": "Possible improper logging of sensitive information",
      "analysis": "The logger.py utility logs messages, and it seems to include detailed information including date and time. Without proper scrutiny, this logging might inadvertently capture and store sensitive information such as passwords, tokens, etc. if they are part of the logs. Storing these in plaintext could lead to exposure of sensitive information if the log files are accessed by unauthorized users.\n",
      "classification": "very promising",
      "cwe": "CWE-532",
      "function_names": [
        "showInfo",
        "showWarning",
        "showError"
      ],
      "filenames": [
        "src/utils/logger.py"
      ]
    },
    {
      "headline": "Unsanitized input in database operations",
      "analysis": "The create_account, check_username, and various other database functions in db_interface.py directly use input parameters in SQL queries without sanitization, making them potentially susceptible to SQL injection attacks. The usage of string interpolation with user inputs to form SQL queries is insecure and can lead to database compromise.\n",
      "classification": "very promising",
      "cwe": "CWE-89",
      "function_names": [
        "create_account",
        "check_username",
        "check_email"
      ],
      "filenames": [
        "src/utils/db_interface.py"
      ]
    },
    {
      "headline": "Insecure token validation process",
      "analysis": "The function verify_credentials in db_interface.py checks for the presence of a specific token in the database for verification but doesn\u2019t use any form of timed comparison or other protection methods that can prevent timing attacks. Additionally, tokens are stored and directly compared in plaintext, which is a potential security risk if intercepted.\n",
      "classification": "very promising",
      "cwe": "CWE-287",
      "function_names": [
        "verify_credentials",
        "check_token",
        "verify_token"
      ],
      "filenames": [
        "src/utils/db_interface.py"
      ]
    },
    {
      "headline": "Cross-Site Scripting (XSS) vulnerability with user profile data",
      "analysis": "User inputs like bio and pronouns are being stored in the database and potentially rendered on web pages. If these inputs are not properly sanitized before storage and rendering, it could lead to Cross-Site Scripting (XSS) attacks where malicious scripts could be executed in the user's browser.\n",
      "classification": "very promising",
      "cwe": "CWE-79",
      "function_names": [
        "update_account_info"
      ],
      "filenames": [
        "src/auth_server.py"
      ]
    }
  ],
  "scores": [
    {
      "stats": {
        "fn": 1,
        "tp": 0,
        "fp": 4
      },
      "mapping": {},
      "vuln_dates": {
        "CVE-2023-49801": "2024-01-12T21:15:09"
      },
      "scoring_model": "gpt-4o-2024-05-13",
      "type": "llm",
      "instruction_template_hash": "8998f09cf57fca8a6e03"
    }
  ],
  "instruction_template_hash": "10c0163db4740318a544",
  "version": "0.1.0"
}
