{
  "commit": "22e9b99015f488aa40018ddda1c261eb5b50b2d0",
  "repo_url": "https://github.com/jenkinsci/compuware-ispw-operations-plugin",
  "model": "claude-3-sonnet-20240229",
  "chunk_hashes": [
    "27ef7bb64e9f3996882e"
  ],
  "responses": [
    {
      "content": "```yaml\nleads:\n  - headline: Potential Path Traversal Vulnerability\n    analysis: |\n      The code does not appear to properly validate or sanitize the `assignmentId`, `releaseId`, `taskId`, and other user-supplied input parameters used in constructing URLs for API requests. This could potentially allow an attacker to traverse the file system on the server by injecting malicious input containing directory traversal sequences like `../`.\n    cwe: CWE-22\n    function_names:\n      - com.compuware.ispw.restapi.action.AbstractGetAction.getIspwRequestBean\n      - com.compuware.ispw.restapi.action.SetInfoPostAction.getIspwRequestBean\n    filenames:\n      - src/main/java/com/compuware/ispw/restapi/action/AbstractGetAction.java\n      - src/main/java/com/compuware/ispw/restapi/action/SetInfoPostAction.java\n    classification: very promising\n\n  - headline: Potential Code Injection Vulnerability\n    analysis: |\n      The code uses reflection to set properties on objects based on user-supplied input in the `ispwRequestBody` parameter. While this can be a useful technique, it needs to be carefully implemented to prevent code injection attacks. An attacker could potentially supply malicious input to cause arbitrary code execution on the server.\n    cwe: CWE-94\n    function_names:\n      - com.compuware.ispw.restapi.util.RestApiUtils.reflectSetter\n    filenames:\n      - src/main/java/com/compuware/ispw/restapi/util/RestApiUtils.java\n    classification: very promising\n\n  - headline: Potential Improper Input Validation\n    analysis: |\n      The code does not appear to properly validate the `ispwRequestBody` parameter, which is used to construct JSON requests for the ISPW API. An attacker could potentially inject malicious input into this parameter to manipulate the resulting JSON request in unexpected ways.\n    cwe: CWE-20\n    function_names:\n      - com.compuware.ispw.restapi.action.AbstractPostAction.getIspwRequestBean\n      - com.compuware.ispw.restapi.action.SetInfoPostAction.getIspwRequestBean\n    filenames:\n      - src/main/java/com/compuware/ispw/restapi/action/AbstractPostAction.java\n      - src/main/java/com/compuware/ispw/restapi/action/SetInfoPostAction.java\n    classification: very promising\n\n  - headline: Missing Authentication for Critical Function\n    analysis: |\n      The code does not appear to implement any authentication mechanism to protect critical API functions like creating assignments or releases, generating tasks, promoting tasks, deploying tasks, etc. An attacker could potentially invoke these functions without proper authorization, leading to unauthorized access or actions.\n    cwe: CWE-306\n    function_names: []\n    filenames: []\n    classification: very promising\n\n  - headline: Use of Hardcoded Credentials\n    analysis: |\n      The code appears to use hardcoded credentials in the `JsonGenerator.test()` method, which is a security vulnerability. Hardcoded credentials should never be used in production code as they can be easily discovered and exploited by attackers.\n    cwe: CWE-798\n    function_names:\n      - com.compuware.ispw.restapi.JsonGenerator.test\n    filenames:\n      - src/main/java/com/compuware/ispw/restapi/JsonGenerator.java\n    classification: very promising\n\n  - headline: Potential Improper Authorization Vulnerability\n    analysis: |\n      The code does not appear to implement any authorization mechanism to ensure that authenticated users can only perform actions they are authorized for. For example, there does not seem to be any check to ensure that a user can only create assignments or releases for a specific application or stream that they have access to.\n    cwe: CWE-862\n    function_names: []\n    filenames: []\n    classification: slightly promising\n\n  - headline: Potential Improper Neutralization of Special Elements\n    analysis: |\n      The code does not appear to properly sanitize or encode user-supplied input parameters like `assignmentId`, `releaseId`, `taskId`, etc. before including them in URLs or JSON requests. This could potentially lead to injection vulnerabilities like Cross-Site Scripting (XSS) or SQL Injection if these parameters are not properly sanitized.\n    cwe: CWE-79\n    function_names: []\n    filenames: []\n    classification: slightly promising\n\n  - headline: Potential Insecure Trust of External Webhooks\n    analysis: |\n      The `WebhookRootAction` class appears to trust and execute any webhook that is posted to the `/ispw-webhook-step` endpoint without verifying its authenticity or integrity. An attacker could potentially trigger malicious webhooks by sending crafted requests to this endpoint.\n    cwe: CWE-346\n    function_names:\n      - com.compuware.ispw.restapi.WebhookRootAction.doDynamic\n    filenames:\n      - src/main/java/com/compuware/ispw/restapi/WebhookRootAction.java\n    classification: slightly promising\n\n  - headline: Potential Missing Release of Resource\n    analysis: |\n      The `ResponseContentSupplier` class does not appear to properly release or close the `InputStream` and `HttpClient` resources it uses. This could potentially lead to resource leaks or other issues if these resources are not properly managed and released after use.\n    cwe: CWE-772\n    function_names:\n      - com.compuware.ispw.restapi.ResponseContentSupplier.close\n    filenames:\n      - src/main/java/com/compuware/ispw/restapi/ResponseContentSupplier.java\n    classification: slightly promising\n```\n\nThe analysis identifies several potential security vulnerabilities in the codebase, including:\n\n1. **Path Traversal** vulnerability due to lack of input validation on user-supplied parameters used in constructing URLs.\n2. **Code Injection** vulnerability due to the use of reflection to set object properties based on user input.\n3. **Improper Input Validation** on the `ispwRequestBody` parameter used to construct JSON requests.\n4. **Missing Authentication** for critical API functions like creating assignments, generating tasks, etc.\n5. **Use of Hardcoded Credentials** in the `JsonGenerator.test()` method.\n6. **Improper Authorization** due to lack of access control mechanisms.\n7. **Improper Neutralization of Special Elements** when including user input in URLs or JSON requests.\n8. **Insecure Trust of External Webhooks** in the `WebhookRootAction` class.\n9. **Missing Release of Resources** in the `ResponseContentSupplier` class.\n\nThe analysis classifies most of these vulnerabilities as \"very promising\" or \"slightly promising,\" indicating that they are potentially serious issues that should be addressed. The classification is based on the CWE (Common Weakness Enumeration) identifiers and the potential impact of the vulnerabilities.",
      "date": "2024-06-12T18:08:08.765564",
      "usage": {
        "prompt_tokens": 59957,
        "completion_tokens": 1690,
        "cost": 0.205221
      }
    }
  ],
  "leads": [
    {
      "headline": "Potential Path Traversal Vulnerability",
      "analysis": "The code does not appear to properly validate or sanitize the assignmentId, releaseId, taskId, and other user-supplied input parameters used in constructing URLs for API requests. This could potentially allow an attacker to traverse the file system on the server by injecting malicious input containing directory traversal sequences like ../.\n",
      "classification": "very promising",
      "cwe": "CWE-22",
      "function_names": [
        "com.compuware.ispw.restapi.action.AbstractGetAction.getIspwRequestBean",
        "com.compuware.ispw.restapi.action.SetInfoPostAction.getIspwRequestBean"
      ],
      "filenames": [
        "src/main/java/com/compuware/ispw/restapi/action/AbstractGetAction.java",
        "src/main/java/com/compuware/ispw/restapi/action/SetInfoPostAction.java"
      ]
    },
    {
      "headline": "Potential Code Injection Vulnerability",
      "analysis": "The code uses reflection to set properties on objects based on user-supplied input in the ispwRequestBody parameter. While this can be a useful technique, it needs to be carefully implemented to prevent code injection attacks. An attacker could potentially supply malicious input to cause arbitrary code execution on the server.\n",
      "classification": "very promising",
      "cwe": "CWE-94",
      "function_names": [
        "com.compuware.ispw.restapi.util.RestApiUtils.reflectSetter"
      ],
      "filenames": [
        "src/main/java/com/compuware/ispw/restapi/util/RestApiUtils.java"
      ]
    },
    {
      "headline": "Potential Improper Input Validation",
      "analysis": "The code does not appear to properly validate the ispwRequestBody parameter, which is used to construct JSON requests for the ISPW API. An attacker could potentially inject malicious input into this parameter to manipulate the resulting JSON request in unexpected ways.\n",
      "classification": "very promising",
      "cwe": "CWE-20",
      "function_names": [
        "com.compuware.ispw.restapi.action.AbstractPostAction.getIspwRequestBean",
        "com.compuware.ispw.restapi.action.SetInfoPostAction.getIspwRequestBean"
      ],
      "filenames": [
        "src/main/java/com/compuware/ispw/restapi/action/AbstractPostAction.java",
        "src/main/java/com/compuware/ispw/restapi/action/SetInfoPostAction.java"
      ]
    },
    {
      "headline": "Missing Authentication for Critical Function",
      "analysis": "The code does not appear to implement any authentication mechanism to protect critical API functions like creating assignments or releases, generating tasks, promoting tasks, deploying tasks, etc. An attacker could potentially invoke these functions without proper authorization, leading to unauthorized access or actions.\n",
      "classification": "very promising",
      "cwe": "CWE-306",
      "function_names": [],
      "filenames": []
    },
    {
      "headline": "Use of Hardcoded Credentials",
      "analysis": "The code appears to use hardcoded credentials in the JsonGenerator.test() method, which is a security vulnerability. Hardcoded credentials should never be used in production code as they can be easily discovered and exploited by attackers.\n",
      "classification": "very promising",
      "cwe": "CWE-798",
      "function_names": [
        "com.compuware.ispw.restapi.JsonGenerator.test"
      ],
      "filenames": [
        "src/main/java/com/compuware/ispw/restapi/JsonGenerator.java"
      ]
    },
    {
      "headline": "Potential Improper Authorization Vulnerability",
      "analysis": "The code does not appear to implement any authorization mechanism to ensure that authenticated users can only perform actions they are authorized for. For example, there does not seem to be any check to ensure that a user can only create assignments or releases for a specific application or stream that they have access to.\n",
      "classification": "slightly promising",
      "cwe": "CWE-862",
      "function_names": [],
      "filenames": []
    },
    {
      "headline": "Potential Improper Neutralization of Special Elements",
      "analysis": "The code does not appear to properly sanitize or encode user-supplied input parameters like assignmentId, releaseId, taskId, etc. before including them in URLs or JSON requests. This could potentially lead to injection vulnerabilities like Cross-Site Scripting (XSS) or SQL Injection if these parameters are not properly sanitized.\n",
      "classification": "slightly promising",
      "cwe": "CWE-79",
      "function_names": [],
      "filenames": []
    },
    {
      "headline": "Potential Insecure Trust of External Webhooks",
      "analysis": "The WebhookRootAction class appears to trust and execute any webhook that is posted to the /ispw-webhook-step endpoint without verifying its authenticity or integrity. An attacker could potentially trigger malicious webhooks by sending crafted requests to this endpoint.\n",
      "classification": "slightly promising",
      "cwe": "CWE-346",
      "function_names": [
        "com.compuware.ispw.restapi.WebhookRootAction.doDynamic"
      ],
      "filenames": [
        "src/main/java/com/compuware/ispw/restapi/WebhookRootAction.java"
      ]
    },
    {
      "headline": "Potential Missing Release of Resource",
      "analysis": "The ResponseContentSupplier class does not appear to properly release or close the InputStream and HttpClient resources it uses. This could potentially lead to resource leaks or other issues if these resources are not properly managed and released after use.\n",
      "classification": "slightly promising",
      "cwe": "CWE-772",
      "function_names": [
        "com.compuware.ispw.restapi.ResponseContentSupplier.close"
      ],
      "filenames": [
        "src/main/java/com/compuware/ispw/restapi/ResponseContentSupplier.java"
      ]
    }
  ],
  "scores": [
    {
      "stats": {
        "fn": 2,
        "tp": 0,
        "fp": 5
      },
      "mapping": {},
      "vuln_dates": {
        "CVE-2022-36899": "2022-07-27T15:15:09",
        "CVE-2022-36898": "2022-07-27T15:15:09"
      },
      "scoring_model": "claude-3-opus-20240229",
      "type": "llm",
      "instruction_template_hash": "245ace12b6361954d0a2"
    },
    {
      "stats": {
        "fn": 2,
        "tp": 0,
        "fp": 5
      },
      "mapping": {},
      "vuln_dates": {
        "CVE-2022-36899": "2022-07-27T15:15:09",
        "CVE-2022-36898": "2022-07-27T15:15:09"
      },
      "scoring_model": "claude-3-5-sonnet-20240620",
      "type": "llm",
      "instruction_template_hash": "245ace12b6361954d0a2"
    }
  ],
  "instruction_template_hash": "10c0163db4740318a544",
  "version": "0.1.0"
}
