{
  "commit": "1368b4ce35ba2139328b9bd731fe2ea1ae5d9d27",
  "repo_url": "https://github.com/pingidentity/ssam",
  "model": "claude-3-haiku-20240307",
  "chunk_hashes": [
    "9d242986302f3ba4247b"
  ],
  "responses": [
    {
      "content": "```yaml\nleads:\n  - headline: Insecure Direct Object Reference Vulnerability\n    analysis: |\n      The code does not properly validate user input when constructing LDAP search filters. This could allow an attacker to bypass security controls and access sensitive information.\n    cwe: CWE-639\n    function_names:\n      - getPasswordResetToken\n    filenames:\n      - src/main/java/com/unboundid/webapp/ssam/SSAMController.java\n    classification: slightly promising\n\n  - headline: Sensitive Information Disclosure\n    analysis: |\n      The code does not properly handle exceptions and may expose sensitive information such as stack traces or error messages to the user. This could allow an attacker to gain valuable information about the application and its internals.\n    cwe: CWE-209\n    function_names:\n      - handleWebApplicationException\n    filenames:\n      - src/main/java/com/unboundid/webapp/ssam/SSAMController.java\n    classification: slightly promising\n\n  - headline: Improper Input Validation\n    analysis: |\n      The code does not properly validate user input when creating new user entries. This could allow an attacker to inject malicious data into the LDAP directory.\n    cwe: CWE-20\n    function_names:\n      - createUser\n    filenames:\n      - src/main/java/com/unboundid/webapp/ssam/SSAMController.java\n    classification: slightly promising\n\n  - headline: Potential CSRF Vulnerability\n    analysis: |\n      The code does not properly handle CSRF protection for certain sensitive actions, such as password changes and user deletions. This could allow an attacker to perform unauthorized actions on behalf of a legitimate user.\n    cwe: CWE-352\n    function_names:\n      - updatePassword\n      - deleteUser\n    filenames:\n      - src/main/java/com/unboundid/webapp/ssam/SSAMController.java\n    classification: slightly promising\n\n  - headline: Insecure Logging\n    analysis: |\n      The code does not properly handle sensitive information in log messages, which could lead to the exposure of sensitive data such as passwords or other user information.\n    cwe: CWE-532\n    function_names:\n      - log\n    filenames:\n      - src/main/java/com/unboundid/webapp/ssam/SSAMController.java\n    classification: slightly promising\n```",
      "date": "2024-06-13T11:02:30.358566",
      "usage": {
        "prompt_tokens": 71011,
        "completion_tokens": 575,
        "cost": 0.0184715
      }
    }
  ],
  "leads": [
    {
      "headline": "Insecure Direct Object Reference Vulnerability",
      "analysis": "The code does not properly validate user input when constructing LDAP search filters. This could allow an attacker to bypass security controls and access sensitive information.\n",
      "classification": "slightly promising",
      "cwe": "CWE-639",
      "function_names": [
        "getPasswordResetToken"
      ],
      "filenames": [
        "src/main/java/com/unboundid/webapp/ssam/SSAMController.java"
      ]
    },
    {
      "headline": "Sensitive Information Disclosure",
      "analysis": "The code does not properly handle exceptions and may expose sensitive information such as stack traces or error messages to the user. This could allow an attacker to gain valuable information about the application and its internals.\n",
      "classification": "slightly promising",
      "cwe": "CWE-209",
      "function_names": [
        "handleWebApplicationException"
      ],
      "filenames": [
        "src/main/java/com/unboundid/webapp/ssam/SSAMController.java"
      ]
    },
    {
      "headline": "Improper Input Validation",
      "analysis": "The code does not properly validate user input when creating new user entries. This could allow an attacker to inject malicious data into the LDAP directory.\n",
      "classification": "slightly promising",
      "cwe": "CWE-20",
      "function_names": [
        "createUser"
      ],
      "filenames": [
        "src/main/java/com/unboundid/webapp/ssam/SSAMController.java"
      ]
    },
    {
      "headline": "Potential CSRF Vulnerability",
      "analysis": "The code does not properly handle CSRF protection for certain sensitive actions, such as password changes and user deletions. This could allow an attacker to perform unauthorized actions on behalf of a legitimate user.\n",
      "classification": "slightly promising",
      "cwe": "CWE-352",
      "function_names": [
        "updatePassword",
        "deleteUser"
      ],
      "filenames": [
        "src/main/java/com/unboundid/webapp/ssam/SSAMController.java"
      ]
    },
    {
      "headline": "Insecure Logging",
      "analysis": "The code does not properly handle sensitive information in log messages, which could lead to the exposure of sensitive data such as passwords or other user information.\n",
      "classification": "slightly promising",
      "cwe": "CWE-532",
      "function_names": [
        "log"
      ],
      "filenames": [
        "src/main/java/com/unboundid/webapp/ssam/SSAMController.java"
      ]
    }
  ],
  "scores": [
    {
      "stats": {
        "fn": 1,
        "tp": 0,
        "fp": 0
      },
      "mapping": {},
      "vuln_dates": {
        "CVE-2018-25084": "2023-04-10T18:15:07"
      },
      "scoring_model": "claude-3-opus-20240229",
      "type": "llm",
      "instruction_template_hash": "245ace12b6361954d0a2"
    }
  ],
  "instruction_template_hash": "10c0163db4740318a544",
  "version": "0.1.0"
}
