{
  "commit": "2ce337dc2628b1af270341a5a7a81e361f4e355f",
  "repo_url": "https://github.com/relan/exfat",
  "model": "gpt-4o-2024-05-13",
  "chunk_hashes": [
    "879bb8acec44aec9fd9a"
  ],
  "responses": [
    {
      "content": "```yaml\nleads:\n  - headline: Buffer Overflow in exFAT FAT Handler\n    analysis: |\n      The function `fat_write_entries` in `mkfs/fat.c` writes entries to the File Allocation Table (FAT) without sufficient bounds checking. When writing entries, the function recursively writes until `cluster` is equal to `end - 1`. If the FAT table is not initialized properly, or if there is an unexpected invalid value, this could potentially lead to a buffer overflow by writing beyond the allocated FAT buffer, which can allow an attacker to overwrite adjacent memory. This behavior could lead to system crashes, data corruption, or code execution.\n    cwe: CWE-120\n    function_names:\n      - fat_write_entries\n    filenames:\n      - mkfs/fat.c\n    classification: very promising\n\n  - headline: Misuse of Uninitialized Variables in exFAT Node Handling\n    analysis: |\n      The `exfat_set_label` function in `libexfat/node.c` contains a potential issue where the variable `offset` is passed to the function `find_label` without being checked for initialization. If `find_label` fails and returns `-ENOENT`, the variable `offset` may remain uninitialized. Subsequent usage of this variable without proper initialization can lead to undefined behaviors including crashes and unpredictable memory corruptions.\n    cwe: CWE-824\n    function_names:\n      - exfat_set_label\n    filenames:\n      - libexfat/node.c\n    classification: very promising\n\n  - headline: Insecure Permission Assignments in exFAT Node Creation\n    analysis: |\n      In the functions `exfat_mknod` and `exfat_mkdir` located in `libexfat/node.c`, the file and directory creation processes use fixed permission values. Specifically, directories are created with `0777 & ~ef->dmask`, and files with `0777 & ~ef->fmask`. This approach doesn't consider secure default permissions and relies on user input masks, which may be improperly configured. This could allow for unintended access controls and can lead to privilege escalation if an attacker can create or control the mask values.\n    cwe: CWE-276\n    function_names:\n      - exfat_mknod\n      - exfat_mkdir\n    filenames:\n      - libexfat/node.c\n    classification: very promising\n\n  - headline: Insufficient Synchronicity Leading to Race Conditions in exFAT File System Operations\n    analysis: |\n      Multiple functions involved in file operations, like `exfat_generic_pread` and `exfat_generic_pwrite`, in `libexfat/io.c` do not properly synchronize reads/writes. Since these operations directly access and modify the FAT and cluster maps, concurrent access can lead to race conditions. These functions assume single-threaded, sequential execution which is unsafe in environments where multiple threads or processes might access the file system simultaneously. Hence, exploiting these race conditions could lead to surface data corruption or crashes.\n    cwe: CWE-362\n    function_names:\n      - exfat_generic_pread\n      - exfat_generic_pwrite\n    filenames:\n      - libexfat/io.c\n    classification: very promising\n\n  - headline: Vulnerability to Integer Overflow in exFAT File Truncation\n    analysis: |\n      In the `exfat_truncate` function in `libexfat/cluster.c`, the arithmetic operations to determine the new file size can lead to integer overflows. Specifically, calculations involving size adjustments (`node->size = size`) and comparisons might overflow, especially if the `size` variable is controlled by an attacker or if unexpected large values are used. This issue can potentially lead to improper allocation or deallocation, which can in turn be exploited to corrupt memory and cause denial of service, or allow arbitrary code execution.\n    cwe: CWE-190\n    function_names:\n      - exfat_truncate\n    filenames:\n      - libexfat/cluster.c\n    classification: very promising\n\n  - headline: Lack of Proper Input Validation in exFAT Command Line Tool\n    analysis: |\n      The `setup_spc_bits` function in `mkfs/main.c` does not properly validate user inputs, which can be abused to pass in unexpected values leading to potentially unsafe cluster/sector size calculations. If an attacker passes very large unexpected values, this may cause the mkfs tool to compute incorrect sector or cluster sizes. Consequently, this could lead to corruption of the file system structure when building or triggering buffer overflows.\n    cwe: CWE-20\n    function_names:\n      - setup_spc_bits\n    filenames:\n      - mkfs/main.c\n    classification: very promising\n```",
      "date": "2024-06-13T11:23:20.931328",
      "usage": {
        "prompt_tokens": 83417,
        "completion_tokens": 970,
        "cost": 0.431635
      }
    }
  ],
  "leads": [
    {
      "headline": "Buffer Overflow in exFAT FAT Handler",
      "analysis": "The function fat_write_entries in mkfs/fat.c writes entries to the File Allocation Table (FAT) without sufficient bounds checking. When writing entries, the function recursively writes until cluster is equal to end - 1. If the FAT table is not initialized properly, or if there is an unexpected invalid value, this could potentially lead to a buffer overflow by writing beyond the allocated FAT buffer, which can allow an attacker to overwrite adjacent memory. This behavior could lead to system crashes, data corruption, or code execution.\n",
      "classification": "very promising",
      "cwe": "CWE-120",
      "function_names": [
        "fat_write_entries"
      ],
      "filenames": [
        "mkfs/fat.c"
      ]
    },
    {
      "headline": "Misuse of Uninitialized Variables in exFAT Node Handling",
      "analysis": "The exfat_set_label function in libexfat/node.c contains a potential issue where the variable offset is passed to the function find_label without being checked for initialization. If find_label fails and returns -ENOENT, the variable offset may remain uninitialized. Subsequent usage of this variable without proper initialization can lead to undefined behaviors including crashes and unpredictable memory corruptions.\n",
      "classification": "very promising",
      "cwe": "CWE-824",
      "function_names": [
        "exfat_set_label"
      ],
      "filenames": [
        "libexfat/node.c"
      ]
    },
    {
      "headline": "Insecure Permission Assignments in exFAT Node Creation",
      "analysis": "In the functions exfat_mknod and exfat_mkdir located in libexfat/node.c, the file and directory creation processes use fixed permission values. Specifically, directories are created with 0777 & ~ef->dmask, and files with 0777 & ~ef->fmask. This approach doesn't consider secure default permissions and relies on user input masks, which may be improperly configured. This could allow for unintended access controls and can lead to privilege escalation if an attacker can create or control the mask values.\n",
      "classification": "very promising",
      "cwe": "CWE-276",
      "function_names": [
        "exfat_mknod",
        "exfat_mkdir"
      ],
      "filenames": [
        "libexfat/node.c"
      ]
    },
    {
      "headline": "Insufficient Synchronicity Leading to Race Conditions in exFAT File System Operations",
      "analysis": "Multiple functions involved in file operations, like exfat_generic_pread and exfat_generic_pwrite, in libexfat/io.c do not properly synchronize reads/writes. Since these operations directly access and modify the FAT and cluster maps, concurrent access can lead to race conditions. These functions assume single-threaded, sequential execution which is unsafe in environments where multiple threads or processes might access the file system simultaneously. Hence, exploiting these race conditions could lead to surface data corruption or crashes.\n",
      "classification": "very promising",
      "cwe": "CWE-362",
      "function_names": [
        "exfat_generic_pread",
        "exfat_generic_pwrite"
      ],
      "filenames": [
        "libexfat/io.c"
      ]
    },
    {
      "headline": "Vulnerability to Integer Overflow in exFAT File Truncation",
      "analysis": "In the exfat_truncate function in libexfat/cluster.c, the arithmetic operations to determine the new file size can lead to integer overflows. Specifically, calculations involving size adjustments (node->size = size) and comparisons might overflow, especially if the size variable is controlled by an attacker or if unexpected large values are used. This issue can potentially lead to improper allocation or deallocation, which can in turn be exploited to corrupt memory and cause denial of service, or allow arbitrary code execution.\n",
      "classification": "very promising",
      "cwe": "CWE-190",
      "function_names": [
        "exfat_truncate"
      ],
      "filenames": [
        "libexfat/cluster.c"
      ]
    },
    {
      "headline": "Lack of Proper Input Validation in exFAT Command Line Tool",
      "analysis": "The setup_spc_bits function in mkfs/main.c does not properly validate user inputs, which can be abused to pass in unexpected values leading to potentially unsafe cluster/sector size calculations. If an attacker passes very large unexpected values, this may cause the mkfs tool to compute incorrect sector or cluster sizes. Consequently, this could lead to corruption of the file system structure when building or triggering buffer overflows.\n",
      "classification": "very promising",
      "cwe": "CWE-20",
      "function_names": [
        "setup_spc_bits"
      ],
      "filenames": [
        "mkfs/main.c"
      ]
    }
  ],
  "scores": [
    {
      "stats": {
        "fn": 1,
        "tp": 0,
        "fp": 6
      },
      "mapping": {},
      "vuln_dates": {
        "CVE-2022-29973": "2022-05-02T12:16:28"
      },
      "scoring_model": "claude-3-opus-20240229",
      "type": "llm",
      "instruction_template_hash": "245ace12b6361954d0a2"
    }
  ],
  "instruction_template_hash": "10c0163db4740318a544",
  "version": "0.1.0"
}
