{
  "commit": "0d8065eb88df447410372de3be26c5bf533b2491",
  "repo_url": "https://github.com/inveniosoftware/invenio-records",
  "model": "claude-3-sonnet-20240229",
  "chunk_hashes": [
    "47de4d38b40fc9c76852"
  ],
  "responses": [
    {
      "content": "```yaml\nleads:\n  - headline: Possible shell injection vulnerability in app setup/teardown scripts\n    analysis: |\n      The `app-setup.sh` and `app-teardown.sh` scripts do not sanitize command-line arguments or environment variables before using them in shell commands, potentially allowing an attacker to inject arbitrary shell commands. For example, if the `DIR` environment variable contains malicious code, it could be executed by the script when it sets `cd $DIR`.\n    cwe: CWE-78\n    function_names:\n      - app-setup.sh\n      - app-teardown.sh\n    filenames:\n      - examples/app-setup.sh\n      - examples/app-teardown.sh\n    classification: very promising\n\n  - headline: Possible hardcoded credentials in Flask app\n    analysis: |\n      The Flask app configuration in `examples/app.py` sets `SECRET_KEY` and `SECURITY_PASSWORD_SALT` to hardcoded string values (`CHANGE_ME` and `CHANGE_ME_ALSO`). Using hardcoded credentials is a security risk as it makes it easier for attackers to gain unauthorized access to the application if the credentials are discovered.\n    cwe: CWE-798\n    function_names: []\n    filenames:\n      - examples/app.py\n    classification: very promising\n\n  - headline: Potential SQL injection vulnerability in records CLI\n    analysis: |\n      The `invenio_records/cli.py` module allows creating, patching, and deleting records from the command line. It reads input records from files specified as command-line arguments. If the input files are not properly sanitized, an attacker could potentially inject malicious SQL code into the database through the record data. The code does not appear to perform any validation or sanitization of the input record data before storing it in the database.\n    cwe: CWE-89\n    function_names:\n      - records\n      - create\n      - patch\n    filenames:\n      - invenio_records/cli.py\n    classification: very promising\n\n  - headline: Use of unsafe YAML deserialization\n    analysis: |\n      The YAML output format used in this codebase can be vulnerable to arbitrary code execution if user-supplied YAML input is not properly sanitized before deserialization. The code does not appear to use any defensive deserialization techniques, potentially allowing attackers to execute arbitrary code by inserting malicious YAML payloads.\n    cwe: CWE-502\n    function_names: []\n    filenames: []\n    classification: slightly promising\n\n  - headline: Lack of CSRF protection\n    analysis: |\n      The Flask application does not appear to implement any Cross-Site Request Forgery (CSRF) protection mechanisms. Web applications that do not protect against CSRF are vulnerable to unauthorized state changes, allowing attackers to perform actions on behalf of authenticated users.\n    cwe: CWE-352\n    function_names: []\n    filenames: []\n    classification: very promising\n```\n\nThe key potential security vulnerabilities in this codebase include:\n\n1. Shell injection in the setup/teardown scripts due to lack of input sanitization\n2. Use of hardcoded credentials in the Flask app configuration \n3. Potential SQL injection in the records CLI due to lack of input sanitization\n4. Use of potentially unsafe YAML deserialization without defensive techniques\n5. Lack of CSRF protection in the Flask application\n\nThe most critical issues are the shell injection, SQL injection, and lack of CSRF protection, as these could allow arbitrary code execution or unauthorized actions. The hardcoded credentials and unsafe deserialization are also significant risks that should be addressed.",
      "date": "2024-06-12T17:23:13.142113",
      "usage": {
        "prompt_tokens": 32724,
        "completion_tokens": 837,
        "cost": 0.110727
      }
    }
  ],
  "leads": [
    {
      "headline": "Possible shell injection vulnerability in app setup/teardown scripts",
      "analysis": "The app-setup.sh and app-teardown.sh scripts do not sanitize command-line arguments or environment variables before using them in shell commands, potentially allowing an attacker to inject arbitrary shell commands. For example, if the DIR environment variable contains malicious code, it could be executed by the script when it sets cd $DIR.\n",
      "classification": "very promising",
      "cwe": "CWE-78",
      "function_names": [
        "app-setup.sh",
        "app-teardown.sh"
      ],
      "filenames": [
        "examples/app-setup.sh",
        "examples/app-teardown.sh"
      ]
    },
    {
      "headline": "Possible hardcoded credentials in Flask app",
      "analysis": "The Flask app configuration in examples/app.py sets SECRET_KEY and SECURITY_PASSWORD_SALT to hardcoded string values (CHANGE_ME and CHANGE_ME_ALSO). Using hardcoded credentials is a security risk as it makes it easier for attackers to gain unauthorized access to the application if the credentials are discovered.\n",
      "classification": "very promising",
      "cwe": "CWE-798",
      "function_names": [],
      "filenames": [
        "examples/app.py"
      ]
    },
    {
      "headline": "Potential SQL injection vulnerability in records CLI",
      "analysis": "The invenio_records/cli.py module allows creating, patching, and deleting records from the command line. It reads input records from files specified as command-line arguments. If the input files are not properly sanitized, an attacker could potentially inject malicious SQL code into the database through the record data. The code does not appear to perform any validation or sanitization of the input record data before storing it in the database.\n",
      "classification": "very promising",
      "cwe": "CWE-89",
      "function_names": [
        "records",
        "create",
        "patch"
      ],
      "filenames": [
        "invenio_records/cli.py"
      ]
    },
    {
      "headline": "Use of unsafe YAML deserialization",
      "analysis": "The YAML output format used in this codebase can be vulnerable to arbitrary code execution if user-supplied YAML input is not properly sanitized before deserialization. The code does not appear to use any defensive deserialization techniques, potentially allowing attackers to execute arbitrary code by inserting malicious YAML payloads.\n",
      "classification": "slightly promising",
      "cwe": "CWE-502",
      "function_names": [],
      "filenames": []
    },
    {
      "headline": "Lack of CSRF protection",
      "analysis": "The Flask application does not appear to implement any Cross-Site Request Forgery (CSRF) protection mechanisms. Web applications that do not protect against CSRF are vulnerable to unauthorized state changes, allowing attackers to perform actions on behalf of authenticated users.\n",
      "classification": "very promising",
      "cwe": "CWE-352",
      "function_names": [],
      "filenames": []
    }
  ],
  "scores": [
    {
      "stats": {
        "fn": 1,
        "tp": 0,
        "fp": 4
      },
      "mapping": {},
      "vuln_dates": {
        "CVE-2019-1020003": "2019-07-29T15:15:11"
      },
      "scoring_model": "claude-3-opus-20240229",
      "type": "llm",
      "instruction_template_hash": "245ace12b6361954d0a2"
    }
  ],
  "instruction_template_hash": "10c0163db4740318a544",
  "version": "0.1.0"
}
