{
  "commit": "234b545cb11f9a570a7823767018ccdf419d6897",
  "repo_url": "https://github.com/jenkinsci/tikal-multijob-plugin",
  "model": "gpt-4-turbo-2024-04-09",
  "chunk_hashes": [
    "302ad03f57154554a870"
  ],
  "responses": [
    {
      "content": "```yaml\nleads:\n  - headline: \"Use of Uninitialized Resource in multi-job plugin\"\n    analysis: |\n      The code is utilizing resources that have not been properly initialized before use. Various components in the plugin, especially within the Jenkins job configurations, potentially access uninitialized objects or data structures, leading to unreliable plugin behavior or crashes.\n    cwe: CWE-908\n    function_names: []\n    filenames:\n      - src/main/java/com/tikal/jenkins/plugins/multijob/MultiJobBuilder.java\n      - src/main/java/com/tikal/jenkins/plugins/multijob/MultiJobProject.java\n    classification: \"very promising\"\n\n  - headline: \"Improper Access Control in multi-job configurations\"\n    analysis: |\n      The plugin does not adequately restrict access to its configuration settings, which could allow unauthorized modification of job configurations, potentially leading to execution of arbitrary code or unauthorized operations. The plugin needs to enforce permission checks correctly to prevent unauthorized access.\n    cwe: CWE-863\n    function_names:\n      - onLoad\n      - save\n    filenames:\n      - src/main/java/com/tikal/jenkins/plugins/multijob/views/ProjectWrapper.java\n    classification: \"very promising\"\n\n  - headline: \"Weak Cryptographic Hash in password handling\"\n    analysis: |\n      The codebase employs weak cryptographic hashing techniques for password handling within the plugin configurations. This issue makes it feasible for attackers to reverse the hashing and gain unauthorized access by cracking the weakened hashes.\n    cwe: CWE-916\n    function_names: []\n    filenames:\n      - src/main/java/com/tikal/jenkins/plugins/multijob/MultiJobProject.java\n    classification: \"very promising\"\n\n  - headline: \"Reflected Cross-Site Scripting (XSS) via Job Parameter Inputs\"\n    analysis: |\n      The application does not neutralize or incorrectly neutralizes user-controllable input before it is output in web pages. As a result, the application is vulnerable to reflected XSS attacks, potentially allowing attackers to execute arbitrary scripts in the context of the user's browser session.\n    cwe: CWE-79\n    function_names:\n      - getBuildParams\n    filenames:\n      - src/main/java/com/tikal/jenkins/plugins/multijob/views/ProjectWrapper.java\n    classification: \"very promising\"\n\n  - headline: \"Directory Traversal in File Parameter Handling\"\n    analysis: |\n      The code does not properly validate user-supplied file paths for file operations. This flaw could enable attackers to access or modify system files or other files that are critical to the application, leading to further compromise.\n    cwe: CWE-22\n    function_names:\n      - getAction\n    filenames:\n      - src/main/java/com/tikal/jenkins/plugins/multijob/FileBuildParameters.java\n    classification: \"very promising\"\n\n  - headline: \"Remote Code Execution via Deserialization of Untrusted Data\"\n    analysis: |\n      The application deserializes untrusted data without implementing comprehensive validation, creating an avenue for attackers to execute arbitrary code by providing specially crafted serialized objects.\n    cwe: CWE-502\n    function_names:\n      - onCopiedFrom\n      - onLoad\n    filenames:\n      - src/main/java/com/tikal/jenkins/plugins/multijob/views/ProjectWrapper.java\n    classification: \"very promising\"\n\n  - headline: \"Race Condition in Multijob Build Handling\"\n    analysis: |\n      The application's handling of multiple concurrent job executions does not properly synchronize shared resources, leading to race conditions. These conditions could cause erratic behavior or crashes, and could potentially be exploited to cause security vulnerabilities.\n    cwe: CWE-362\n    function_names:\n      - run\n    filenames:\n      - src/main/java/com/tikal/jenkins/plugins/multijob/MultiJobBuild.java\n    classification: \"very promising\"\n```",
      "date": "2024-06-12T19:28:03.753965",
      "usage": {
        "prompt_tokens": 41774,
        "completion_tokens": 791,
        "cost": 0.44147
      }
    }
  ],
  "leads": [
    {
      "headline": "Use of Uninitialized Resource in multi-job plugin",
      "analysis": "The code is utilizing resources that have not been properly initialized before use. Various components in the plugin, especially within the Jenkins job configurations, potentially access uninitialized objects or data structures, leading to unreliable plugin behavior or crashes.\n",
      "classification": "very promising",
      "cwe": "CWE-908",
      "function_names": [],
      "filenames": [
        "src/main/java/com/tikal/jenkins/plugins/multijob/MultiJobBuilder.java",
        "src/main/java/com/tikal/jenkins/plugins/multijob/MultiJobProject.java"
      ]
    },
    {
      "headline": "Improper Access Control in multi-job configurations",
      "analysis": "The plugin does not adequately restrict access to its configuration settings, which could allow unauthorized modification of job configurations, potentially leading to execution of arbitrary code or unauthorized operations. The plugin needs to enforce permission checks correctly to prevent unauthorized access.\n",
      "classification": "very promising",
      "cwe": "CWE-863",
      "function_names": [
        "onLoad",
        "save"
      ],
      "filenames": [
        "src/main/java/com/tikal/jenkins/plugins/multijob/views/ProjectWrapper.java"
      ]
    },
    {
      "headline": "Weak Cryptographic Hash in password handling",
      "analysis": "The codebase employs weak cryptographic hashing techniques for password handling within the plugin configurations. This issue makes it feasible for attackers to reverse the hashing and gain unauthorized access by cracking the weakened hashes.\n",
      "classification": "very promising",
      "cwe": "CWE-916",
      "function_names": [],
      "filenames": [
        "src/main/java/com/tikal/jenkins/plugins/multijob/MultiJobProject.java"
      ]
    },
    {
      "headline": "Reflected Cross-Site Scripting (XSS) via Job Parameter Inputs",
      "analysis": "The application does not neutralize or incorrectly neutralizes user-controllable input before it is output in web pages. As a result, the application is vulnerable to reflected XSS attacks, potentially allowing attackers to execute arbitrary scripts in the context of the user's browser session.\n",
      "classification": "very promising",
      "cwe": "CWE-79",
      "function_names": [
        "getBuildParams"
      ],
      "filenames": [
        "src/main/java/com/tikal/jenkins/plugins/multijob/views/ProjectWrapper.java"
      ]
    },
    {
      "headline": "Directory Traversal in File Parameter Handling",
      "analysis": "The code does not properly validate user-supplied file paths for file operations. This flaw could enable attackers to access or modify system files or other files that are critical to the application, leading to further compromise.\n",
      "classification": "very promising",
      "cwe": "CWE-22",
      "function_names": [
        "getAction"
      ],
      "filenames": [
        "src/main/java/com/tikal/jenkins/plugins/multijob/FileBuildParameters.java"
      ]
    },
    {
      "headline": "Remote Code Execution via Deserialization of Untrusted Data",
      "analysis": "The application deserializes untrusted data without implementing comprehensive validation, creating an avenue for attackers to execute arbitrary code by providing specially crafted serialized objects.\n",
      "classification": "very promising",
      "cwe": "CWE-502",
      "function_names": [
        "onCopiedFrom",
        "onLoad"
      ],
      "filenames": [
        "src/main/java/com/tikal/jenkins/plugins/multijob/views/ProjectWrapper.java"
      ]
    },
    {
      "headline": "Race Condition in Multijob Build Handling",
      "analysis": "The application's handling of multiple concurrent job executions does not properly synchronize shared resources, leading to race conditions. These conditions could cause erratic behavior or crashes, and could potentially be exploited to cause security vulnerabilities.\n",
      "classification": "very promising",
      "cwe": "CWE-362",
      "function_names": [
        "run"
      ],
      "filenames": [
        "src/main/java/com/tikal/jenkins/plugins/multijob/MultiJobBuild.java"
      ]
    }
  ],
  "scores": [
    {
      "stats": {
        "fn": 1,
        "tp": 0,
        "fp": 7
      },
      "mapping": {},
      "vuln_dates": {
        "CVE-2017-1000390": "2018-01-26T02:29:00"
      },
      "scoring_model": "claude-3-opus-20240229",
      "type": "llm",
      "instruction_template_hash": "245ace12b6361954d0a2"
    }
  ],
  "instruction_template_hash": "10c0163db4740318a544",
  "version": "0.1.0"
}
