{
  "commit": "27ed36c03297713d2cfa79431cdc8105602e80c2",
  "repo_url": "https://github.com/libimobiledevice/libplist",
  "model": "claude-3-sonnet-20240229",
  "chunk_hashes": [
    "4862f657edc6d17c409e"
  ],
  "responses": [
    {
      "content": "I will identify potential security vulnerabilities in the given codebase and provide them in a YAML object equivalent to type LeadList according to the provided Pydantic definitions.\n\n```yaml\nleads:\n  - headline: Potential Buffer Overflow in plist_from_xml\n    analysis: |\n      The function plist_from_xml in src/xplist.c does not properly validate the input XML data before parsing it with libxml2. A maliciously crafted XML input with excessive recursion or very large node/entity values could lead to a buffer overflow and potentially code execution.\n    cwe: CWE-120\n    function_names:\n      - plist_from_xml\n    filenames:\n      - src/xplist.c\n    classification: very promising\n\n  - headline: Potential Use of Insecure Random Values\n    analysis: |\n      The codebase does not appear to use any secure random number generator. If any functionality requires the generation of random values (e.g., for cryptographic operations or to prevent predictability), the use of insecure random values could lead to potential security vulnerabilities.\n    cwe: CWE-338\n    function_names: []\n    filenames: []\n    classification: slightly promising\n\n  - headline: Potential Integer Overflow in plist_from_bin\n    analysis: |\n      The function plist_from_bin in src/bplist.c does not properly validate the size values read from the binary plist data. A maliciously crafted binary plist with excessive size values could lead to an integer overflow and potentially code execution.\n    cwe: CWE-190\n    function_names:\n      - plist_from_bin\n    filenames:\n      - src/bplist.c\n    classification: very promising\n\n  - headline: Potential Improper Input Validation in plist_from_bin\n    analysis: |\n      The function plist_from_bin in src/bplist.c does not properly validate the magic number and version of the binary plist data before parsing it. A maliciously crafted binary plist with an invalid magic number or version could lead to unexpected behavior or potential code execution.\n    cwe: CWE-20\n    function_names:\n      - plist_from_bin\n    filenames:\n      - src/bplist.c\n    classification: very promising\n\n  - headline: Potential Improper Input Validation in parse_bin_node\n    analysis: |\n      The function parse_bin_node in src/bplist.c does not properly validate the input data before parsing it. A maliciously crafted binary plist with invalid or excessive data could lead to unexpected behavior or potential code execution.\n    cwe: CWE-20\n    function_names:\n      - parse_bin_node\n    filenames:\n      - src/bplist.c\n    classification: very promising\n\n  - headline: Potential Use of Externally-Controlled Input to Select Classes or Code in parse_bin_node\n    analysis: |\n      The function parse_bin_node in src/bplist.c uses externally-controlled input (the node type value) to select which code path to execute. A maliciously crafted binary plist with an invalid or unexpected node type value could lead to unexpected behavior or potential code execution.\n    cwe: CWE-470\n    function_names:\n      - parse_bin_node\n    filenames:\n      - src/bplist.c\n    classification: very promising\n\n  - headline: Potential Improper Handling of Exceptional Conditions in plist_to_xml\n    analysis: |\n      The function plist_to_xml in src/xplist.c does not properly handle exceptional conditions, such as failures in memory allocation or XML generation. Improper handling of exceptional conditions could lead to potential vulnerabilities such as denial of service or information leaks.\n    cwe: CWE-755\n    function_names:\n      - plist_to_xml\n    filenames:\n      - src/xplist.c\n    classification: slightly promising\n\n  - headline: Potential Information Exposure Through Error Messages\n    analysis: |\n      Several functions in the codebase, such as parse_bin_node in src/bplist.c and parse_unicode_node in src/xplist.c, print error messages to stderr without proper sanitization. These error messages could potentially expose sensitive information or implementation details, which could be useful for an attacker.\n    cwe: CWE-209\n    function_names:\n      - parse_bin_node\n      - parse_unicode_node\n    filenames:\n      - src/bplist.c\n      - src/xplist.c\n    classification: slightly promising\n\n  - headline: Potential Use of Hard-coded Credentials\n    analysis: |\n      The codebase does not appear to use any hard-coded credentials or sensitive information. However, it is a good practice to review the codebase thoroughly for any hard-coded credentials or sensitive information before deployment.\n    cwe: CWE-798\n    function_names: []\n    filenames: []\n    classification: not promising\n```\n\nThis analysis covers potential vulnerabilities related to buffer overflows, integer overflows, improper input validation, use of insecure random values, improper handling of exceptional conditions, information exposure through error messages, and the use of hard-coded credentials. However, it is important to note that a comprehensive security review would require a more in-depth analysis, including static and dynamic analysis techniques, as well as manual code review.",
      "date": "2024-06-13T09:42:53.922136",
      "usage": {
        "prompt_tokens": 72582,
        "completion_tokens": 1273,
        "cost": 0.236841
      }
    }
  ],
  "leads": [
    {
      "headline": "Potential Buffer Overflow in plist_from_xml",
      "analysis": "The function plist_from_xml in src/xplist.c does not properly validate the input XML data before parsing it with libxml2. A maliciously crafted XML input with excessive recursion or very large node/entity values could lead to a buffer overflow and potentially code execution.\n",
      "classification": "very promising",
      "cwe": "CWE-120",
      "function_names": [
        "plist_from_xml"
      ],
      "filenames": [
        "src/xplist.c"
      ]
    },
    {
      "headline": "Potential Use of Insecure Random Values",
      "analysis": "The codebase does not appear to use any secure random number generator. If any functionality requires the generation of random values (e.g., for cryptographic operations or to prevent predictability), the use of insecure random values could lead to potential security vulnerabilities.\n",
      "classification": "slightly promising",
      "cwe": "CWE-338",
      "function_names": [],
      "filenames": []
    },
    {
      "headline": "Potential Integer Overflow in plist_from_bin",
      "analysis": "The function plist_from_bin in src/bplist.c does not properly validate the size values read from the binary plist data. A maliciously crafted binary plist with excessive size values could lead to an integer overflow and potentially code execution.\n",
      "classification": "very promising",
      "cwe": "CWE-190",
      "function_names": [
        "plist_from_bin"
      ],
      "filenames": [
        "src/bplist.c"
      ]
    },
    {
      "headline": "Potential Improper Input Validation in plist_from_bin",
      "analysis": "The function plist_from_bin in src/bplist.c does not properly validate the magic number and version of the binary plist data before parsing it. A maliciously crafted binary plist with an invalid magic number or version could lead to unexpected behavior or potential code execution.\n",
      "classification": "very promising",
      "cwe": "CWE-20",
      "function_names": [
        "plist_from_bin"
      ],
      "filenames": [
        "src/bplist.c"
      ]
    },
    {
      "headline": "Potential Improper Input Validation in parse_bin_node",
      "analysis": "The function parse_bin_node in src/bplist.c does not properly validate the input data before parsing it. A maliciously crafted binary plist with invalid or excessive data could lead to unexpected behavior or potential code execution.\n",
      "classification": "very promising",
      "cwe": "CWE-20",
      "function_names": [
        "parse_bin_node"
      ],
      "filenames": [
        "src/bplist.c"
      ]
    },
    {
      "headline": "Potential Use of Externally-Controlled Input to Select Classes or Code in parse_bin_node",
      "analysis": "The function parse_bin_node in src/bplist.c uses externally-controlled input (the node type value) to select which code path to execute. A maliciously crafted binary plist with an invalid or unexpected node type value could lead to unexpected behavior or potential code execution.\n",
      "classification": "very promising",
      "cwe": "CWE-470",
      "function_names": [
        "parse_bin_node"
      ],
      "filenames": [
        "src/bplist.c"
      ]
    },
    {
      "headline": "Potential Improper Handling of Exceptional Conditions in plist_to_xml",
      "analysis": "The function plist_to_xml in src/xplist.c does not properly handle exceptional conditions, such as failures in memory allocation or XML generation. Improper handling of exceptional conditions could lead to potential vulnerabilities such as denial of service or information leaks.\n",
      "classification": "slightly promising",
      "cwe": "CWE-755",
      "function_names": [
        "plist_to_xml"
      ],
      "filenames": [
        "src/xplist.c"
      ]
    },
    {
      "headline": "Potential Information Exposure Through Error Messages",
      "analysis": "Several functions in the codebase, such as parse_bin_node in src/bplist.c and parse_unicode_node in src/xplist.c, print error messages to stderr without proper sanitization. These error messages could potentially expose sensitive information or implementation details, which could be useful for an attacker.\n",
      "classification": "slightly promising",
      "cwe": "CWE-209",
      "function_names": [
        "parse_bin_node",
        "parse_unicode_node"
      ],
      "filenames": [
        "src/bplist.c",
        "src/xplist.c"
      ]
    },
    {
      "headline": "Potential Use of Hard-coded Credentials",
      "analysis": "The codebase does not appear to use any hard-coded credentials or sensitive information. However, it is a good practice to review the codebase thoroughly for any hard-coded credentials or sensitive information before deployment.\n",
      "classification": "not promising",
      "cwe": "CWE-798",
      "function_names": [],
      "filenames": []
    }
  ],
  "scores": [
    {
      "stats": {
        "fn": 6,
        "tp": 1,
        "fp": 3
      },
      "mapping": {
        "1": "CVE-2017-7982",
        "3": "CVE-2017-7982"
      },
      "vuln_dates": {
        "CVE-2017-7982": "2017-04-20T14:59:00",
        "CVE-2017-6439": "2017-03-15T14:59:01",
        "CVE-2017-6440": "2017-03-15T14:59:01",
        "CVE-2017-6438": "2017-03-15T14:59:01",
        "CVE-2017-6437": "2017-03-15T14:59:01",
        "CVE-2017-6435": "2017-03-15T14:59:00",
        "CVE-2017-6436": "2017-03-15T14:59:00"
      },
      "scoring_model": "claude-3-opus-20240229",
      "type": "llm",
      "instruction_template_hash": "245ace12b6361954d0a2"
    }
  ],
  "instruction_template_hash": "10c0163db4740318a544",
  "version": "0.1.0"
}
