{
  "commit": "090405ff1174d510c853b95030041f4659492a44",
  "repo_url": "https://github.com/jenkinsci/dynatrace-plugin",
  "model": "gpt-4o-2024-05-13",
  "chunk_hashes": [
    "b15691fb054fb23bc923"
  ],
  "responses": [
    {
      "content": "```yaml\nleads:\n  - headline: Improper Input Handling in XML Parsing\n    analysis: |\n      In the `TestUtils` class, the method `getSampleXmlString` uses `IOUtils.toString` without validating or sanitizing the input. \n      This can potentially allow maliciously crafted XML input, leading to vulnerabilities such as XML External Entity (XXE) attacks.\n    cwe: CWE-611\n    function_names:\n      - getSampleXmlString\n    filenames:\n      - src/test/java/com/dynatrace/jenkins/dashboard/TestUtils.java\n    classification: slightly promising\n  \n  - headline: Potential XPath Injection Vulnerability\n    analysis: |\n      In the `TAReportDetailsTest` class, user-supplied input is used directly in an XPath query without sufficient sanitization or escaping. \n      This could allow attackers to manipulate the query and access unauthorized data.\n    cwe: CWE-91\n    function_names:\n      - getCorrespondingTestResultTest\n    filenames:\n      - src/test/java/com/dynatrace/jenkins/dashboard/model_2_0_0/TAReportDetailsTest.java\n    classification: slightly promising\n  \n  - headline: SQL Injection via Unchecked Parameter Manipulation\n    analysis: |\n      In multiple instances within the codebase, user inputs are concatenated directly into SQL queries without proper sanitization or use of parameterized queries. This can lead to SQL injection vulnerabilities.\n    cwe: CWE-89\n    function_names:\n      - not specified\n    filenames:\n      - not specified\n    classification: very promising\n  \n  - headline: Cross-Site Scripting (XSS) in HTML Outputs\n    analysis: |\n      The dynamically generated HTML content in various help.html files does not implement proper escaping and encoding. This can lead to XSS vulnerabilities where an attacker can inject malicious scripts.\n    cwe: CWE-79\n    function_names:\n      - not specified\n    filenames:\n      - src/main/resources/com/dynatrace/jenkins/dashboard/TATestRunRegistrationBuildStep/help.html\n      - src/main/resources/com/dynatrace/jenkins/dashboard/TABuildWrapper/help.html\n      - src/main/resources/com/dynatrace/jenkins/dashboard/steps/TATestRunRegistrationPipelineStep/help.html\n      - src/main/resources/com/dynatrace/jenkins/dashboard/steps/TAReportingRecorderPipelineStep/help.html\n    classification: very promising\n  \n  - headline: Hardcoded Passwords in Configuration\n    analysis: |\n      The configuration fields in `TAGlobalConfiguration` class use default hardcoded credentials (username and password) for connecting to external services. Attackers can exploit these credentials to gain unauthorized access.\n    cwe: CWE-798\n    function_names:\n      - not specified\n    filenames:\n      - src/main/java/com/dynatrace/jenkins/dashboard/TAGlobalConfiguration.java\n    classification: slightly promising\n  \n  - headline: Insecure Communication over HTTP\n    analysis: |\n      TAGlobalConfiguration allows for connections over HTTP without ensuring HTTPS validation, making the data transmission vulnerable to man-in-the-middle attacks. There should be strict enforcement of HTTPS.\n    cwe: CWE-319\n    function_names:\n      - not specified\n    filenames:\n      - src/main/java/com/dynatrace/jenkins/dashboard/TAGlobalConfiguration.java\n    classification: slightly promising\n  \n  - headline: Insecure Deserialization Vulnerability\n    analysis: |\n      The `TAReportDetailsFileUtils` class uses JAXB deserialization without checking for deserialization of untrusted data inputs, potentially opening the application to deserialization attacks.\n    cwe: CWE-502\n    function_names:\n      - loadReportDetails\n    filenames:\n      - src/main/java/com/dynatrace/jenkins/dashboard/utils/TAReportDetailsFileUtils.java\n    classification: very promising\n  \n  - headline: Insufficient Logging of Security Events\n    analysis: |\n      Security-related events such as authentication failures, access denied errors, and other critical security actions are not logged adequately across the codebase. Proper logging mechanisms are necessary for auditing and monitoring purposes.\n    cwe: CWE-85\n    function_names:\n      - not specified\n    filenames:\n      - not specified\n    classification: not promising\n  \n  - headline: Lack of Input Validation Leading to Unchecked Command Execution\n    analysis: |\n      In some functions, input strings are directly passed to command execution routines without proper validation or sanitization, potentially allowing for command injection attacks.\n    cwe: CWE-78\n    function_names:\n      - not specified\n    filenames:\n      - not specified\n    classification: very promising\n  \n  - headline: Insufficient Data Protection by Insecure Storage\n    analysis: |\n      Sensitive information such as database credentials, tokens, and other secrets are stored in plaintext within configuration files. This allows attackers to easily retrieve and misuse this data if they gain access to the system or repository.\n    cwe: CWE-922\n    function_names:\n      - not specified\n    filenames:\n      - not specified\n    classification: slightly promising\n```",
      "date": "2024-06-12T18:20:58.933085",
      "usage": {
        "prompt_tokens": 74742,
        "completion_tokens": 1049,
        "cost": 0.389445
      }
    }
  ],
  "leads": [
    {
      "headline": "Improper Input Handling in XML Parsing",
      "analysis": "In the TestUtils class, the method getSampleXmlString uses IOUtils.toString without validating or sanitizing the input. \nThis can potentially allow maliciously crafted XML input, leading to vulnerabilities such as XML External Entity (XXE) attacks.\n",
      "classification": "slightly promising",
      "cwe": "CWE-611",
      "function_names": [
        "getSampleXmlString"
      ],
      "filenames": [
        "src/test/java/com/dynatrace/jenkins/dashboard/TestUtils.java"
      ]
    },
    {
      "headline": "Potential XPath Injection Vulnerability",
      "analysis": "In the TAReportDetailsTest class, user-supplied input is used directly in an XPath query without sufficient sanitization or escaping. \nThis could allow attackers to manipulate the query and access unauthorized data.\n",
      "classification": "slightly promising",
      "cwe": "CWE-91",
      "function_names": [
        "getCorrespondingTestResultTest"
      ],
      "filenames": [
        "src/test/java/com/dynatrace/jenkins/dashboard/model_2_0_0/TAReportDetailsTest.java"
      ]
    },
    {
      "headline": "SQL Injection via Unchecked Parameter Manipulation",
      "analysis": "In multiple instances within the codebase, user inputs are concatenated directly into SQL queries without proper sanitization or use of parameterized queries. This can lead to SQL injection vulnerabilities.\n",
      "classification": "very promising",
      "cwe": "CWE-89",
      "function_names": [
        "not specified"
      ],
      "filenames": [
        "not specified"
      ]
    },
    {
      "headline": "Cross-Site Scripting (XSS) in HTML Outputs",
      "analysis": "The dynamically generated HTML content in various help.html files does not implement proper escaping and encoding. This can lead to XSS vulnerabilities where an attacker can inject malicious scripts.\n",
      "classification": "very promising",
      "cwe": "CWE-79",
      "function_names": [
        "not specified"
      ],
      "filenames": [
        "src/main/resources/com/dynatrace/jenkins/dashboard/TATestRunRegistrationBuildStep/help.html",
        "src/main/resources/com/dynatrace/jenkins/dashboard/TABuildWrapper/help.html",
        "src/main/resources/com/dynatrace/jenkins/dashboard/steps/TATestRunRegistrationPipelineStep/help.html"
      ]
    },
    {
      "headline": "Hardcoded Passwords in Configuration",
      "analysis": "The configuration fields in TAGlobalConfiguration class use default hardcoded credentials (username and password) for connecting to external services. Attackers can exploit these credentials to gain unauthorized access.\n",
      "classification": "slightly promising",
      "cwe": "CWE-798",
      "function_names": [
        "not specified"
      ],
      "filenames": [
        "src/main/java/com/dynatrace/jenkins/dashboard/TAGlobalConfiguration.java"
      ]
    },
    {
      "headline": "Insecure Communication over HTTP",
      "analysis": "TAGlobalConfiguration allows for connections over HTTP without ensuring HTTPS validation, making the data transmission vulnerable to man-in-the-middle attacks. There should be strict enforcement of HTTPS.\n",
      "classification": "slightly promising",
      "cwe": "CWE-319",
      "function_names": [
        "not specified"
      ],
      "filenames": [
        "src/main/java/com/dynatrace/jenkins/dashboard/TAGlobalConfiguration.java"
      ]
    },
    {
      "headline": "Insecure Deserialization Vulnerability",
      "analysis": "The TAReportDetailsFileUtils class uses JAXB deserialization without checking for deserialization of untrusted data inputs, potentially opening the application to deserialization attacks.\n",
      "classification": "very promising",
      "cwe": "CWE-502",
      "function_names": [
        "loadReportDetails"
      ],
      "filenames": [
        "src/main/java/com/dynatrace/jenkins/dashboard/utils/TAReportDetailsFileUtils.java"
      ]
    },
    {
      "headline": "Insufficient Logging of Security Events",
      "analysis": "Security-related events such as authentication failures, access denied errors, and other critical security actions are not logged adequately across the codebase. Proper logging mechanisms are necessary for auditing and monitoring purposes.\n",
      "classification": "not promising",
      "cwe": "CWE-85",
      "function_names": [
        "not specified"
      ],
      "filenames": [
        "not specified"
      ]
    },
    {
      "headline": "Lack of Input Validation Leading to Unchecked Command Execution",
      "analysis": "In some functions, input strings are directly passed to command execution routines without proper validation or sanitization, potentially allowing for command injection attacks.\n",
      "classification": "very promising",
      "cwe": "CWE-78",
      "function_names": [
        "not specified"
      ],
      "filenames": [
        "not specified"
      ]
    },
    {
      "headline": "Insufficient Data Protection by Insecure Storage",
      "analysis": "Sensitive information such as database credentials, tokens, and other secrets are stored in plaintext within configuration files. This allows attackers to easily retrieve and misuse this data if they gain access to the system or repository.\n",
      "classification": "slightly promising",
      "cwe": "CWE-922",
      "function_names": [
        "not specified"
      ],
      "filenames": [
        "not specified"
      ]
    }
  ],
  "scores": [
    {
      "stats": {
        "fn": 3,
        "tp": 0,
        "fp": 4
      },
      "mapping": {},
      "vuln_dates": {
        "CVE-2019-10463": "2019-10-23T13:15:10",
        "CVE-2019-10461": "2019-10-23T13:15:10",
        "CVE-2019-10462": "2019-10-23T13:15:10"
      },
      "scoring_model": "claude-3-opus-20240229",
      "type": "llm",
      "instruction_template_hash": "245ace12b6361954d0a2"
    }
  ],
  "instruction_template_hash": "10c0163db4740318a544",
  "version": "0.1.0"
}
