{
  "commit": "242465ac4b24956c8ee20ab613325cf20e389f22",
  "repo_url": "https://github.com/ionic-team/cordova-plugin-ionic-webview",
  "model": "claude-3-sonnet-20240229",
  "chunk_hashes": [
    "a4b8d6472caf961a14e7"
  ],
  "responses": [
    {
      "content": "```yaml\nleads:\n  - headline: Potential improper input validation in IonicWebViewEngine\n    analysis: |\n      The `IonicWebViewEngine` class appears to rely on user input for the `setServerBasePath` method, which could potentially introduce security vulnerabilities such as path traversal if the input is not properly sanitized.\n    cwe: CWE-22\n    function_names:\n      - setServerBasePath\n    filenames:\n      - src/android/com/ionicframework/cordova/webview/IonicWebViewEngine.java\n    classification: slightly promising\n\n  - headline: Potential code injection vulnerability in IonicWebView\n    analysis: |\n      The `IonicWebView` class seems to execute JavaScript code (`window.Ionic.WebView.convertFileSrc`) passed from the Ionic project, which could potentially allow for code injection if the input is not properly sanitized.\n    cwe: CWE-94\n    function_names:\n      - execute\n    filenames:\n      - src/android/com/ionicframework/cordova/webview/IonicWebView.java\n    classification: slightly promising\n\n  - headline: Potential insufficient session expiration in WebViewLocalServer\n    analysis: |\n      The `WebViewLocalServer` class does not appear to implement any mechanism for session expiration or session management, which could potentially lead to security vulnerabilities such as session fixation or session hijacking.\n    cwe: CWE-613\n    function_names: []\n    filenames:\n      - src/android/com/ionicframework/cordova/webview/WebViewLocalServer.java\n    classification: slightly promising\n\n  - headline: Potential improper input validation in WebViewLocalServer\n    analysis: |\n      The `WebViewLocalServer` class appears to rely on user input for file paths and URLs, which could potentially introduce security vulnerabilities such as path traversal or remote file inclusion if the input is not properly sanitized.\n    cwe: CWE-22\n    function_names:\n      - hostFiles\n      - hostAssets\n    filenames:\n      - src/android/com/ionicframework/cordova/webview/WebViewLocalServer.java\n    classification: slightly promising\n\n  - headline: Potential insecure storage of server base path\n    analysis: |\n      The `persistServerBasePath` method in `IonicWebView` appears to store the server base path in shared preferences, which could potentially expose sensitive information if the shared preferences are not properly secured or if the data is not properly sanitized before storage.\n    cwe: CWE-312\n    function_names:\n      - persistServerBasePath\n    filenames:\n      - src/android/com/ionicframework/cordova/webview/IonicWebView.java\n    classification: slightly promising\n\n  - headline: Potential cleartext transmission of sensitive information\n    analysis: |\n      The `WebViewLocalServer` class appears to transmit data over HTTP, which could potentially expose sensitive information if the data is not properly secured or encrypted.\n    cwe: CWE-319\n    function_names: []\n    filenames:\n      - src/android/com/ionicframework/cordova/webview/WebViewLocalServer.java\n    classification: slightly promising\n\n  - headline: Potential improper neutralization of special elements in WebViewLocalServer\n    analysis: |\n      The `WebViewLocalServer` class appears to handle user input for file paths and URLs, which could potentially introduce security vulnerabilities such as path traversal or remote file inclusion if special characters are not properly neutralized or escaped.\n    cwe: CWE-79\n    function_names:\n      - hostFiles\n      - hostAssets\n    filenames:\n      - src/android/com/ionicframework/cordova/webview/WebViewLocalServer.java\n    classification: slightly promising\n\n  - headline: Potential lack of authentication for critical functions\n    analysis: |\n      The codebase does not appear to implement any authentication mechanisms for critical functions or resources, which could potentially allow unauthorized access to sensitive data or functionality.\n    cwe: CWE-306\n    function_names: []\n    filenames: []\n    classification: slightly promising\n\n  - headline: Potential use of hard-coded credentials\n    analysis: |\n      The codebase appears to use hard-coded credentials or default authentication credentials, which could potentially introduce security vulnerabilities if these credentials are disclosed or used in production environments.\n    cwe: CWE-798\n    function_names: []\n    filenames: []\n    classification: slightly promising\n    \n  - headline: Potential improper neutralization of special elements in iOS wk-plugin\n    analysis: |\n      The `wk-plugin.js` file appears to handle user input for file URLs, which could potentially introduce security vulnerabilities such as path traversal or remote file inclusion if special characters are not properly neutralized or escaped.\n    cwe: CWE-79\n    function_names:\n      - normalizeURL\n      - wkRewriteURL\n    filenames:\n      - src/ios/wk-plugin.js\n    classification: slightly promising\n      \n```\n\nThe codebase appears to have several potential security vulnerabilities, including improper input validation, code injection, insufficient session expiration, insecure storage of sensitive information, cleartext transmission of sensitive data, improper neutralization of special elements, lack of authentication, and use of hard-coded credentials. While some of these vulnerabilities may be mitigated by the specific usage or configuration of the codebase, it is important to address them to ensure the security and robustness of the application.",
      "date": "2024-06-12T17:24:37.000812",
      "usage": {
        "prompt_tokens": 45239,
        "completion_tokens": 1287,
        "cost": 0.155022
      }
    }
  ],
  "leads": [
    {
      "headline": "Potential improper input validation in IonicWebViewEngine",
      "analysis": "The IonicWebViewEngine class appears to rely on user input for the setServerBasePath method, which could potentially introduce security vulnerabilities such as path traversal if the input is not properly sanitized.\n",
      "classification": "slightly promising",
      "cwe": "CWE-22",
      "function_names": [
        "setServerBasePath"
      ],
      "filenames": [
        "src/android/com/ionicframework/cordova/webview/IonicWebViewEngine.java"
      ]
    },
    {
      "headline": "Potential code injection vulnerability in IonicWebView",
      "analysis": "The IonicWebView class seems to execute JavaScript code (window.Ionic.WebView.convertFileSrc) passed from the Ionic project, which could potentially allow for code injection if the input is not properly sanitized.\n",
      "classification": "slightly promising",
      "cwe": "CWE-94",
      "function_names": [
        "execute"
      ],
      "filenames": [
        "src/android/com/ionicframework/cordova/webview/IonicWebView.java"
      ]
    },
    {
      "headline": "Potential insufficient session expiration in WebViewLocalServer",
      "analysis": "The WebViewLocalServer class does not appear to implement any mechanism for session expiration or session management, which could potentially lead to security vulnerabilities such as session fixation or session hijacking.\n",
      "classification": "slightly promising",
      "cwe": "CWE-613",
      "function_names": [],
      "filenames": [
        "src/android/com/ionicframework/cordova/webview/WebViewLocalServer.java"
      ]
    },
    {
      "headline": "Potential improper input validation in WebViewLocalServer",
      "analysis": "The WebViewLocalServer class appears to rely on user input for file paths and URLs, which could potentially introduce security vulnerabilities such as path traversal or remote file inclusion if the input is not properly sanitized.\n",
      "classification": "slightly promising",
      "cwe": "CWE-22",
      "function_names": [
        "hostFiles",
        "hostAssets"
      ],
      "filenames": [
        "src/android/com/ionicframework/cordova/webview/WebViewLocalServer.java"
      ]
    },
    {
      "headline": "Potential insecure storage of server base path",
      "analysis": "The persistServerBasePath method in IonicWebView appears to store the server base path in shared preferences, which could potentially expose sensitive information if the shared preferences are not properly secured or if the data is not properly sanitized before storage.\n",
      "classification": "slightly promising",
      "cwe": "CWE-312",
      "function_names": [
        "persistServerBasePath"
      ],
      "filenames": [
        "src/android/com/ionicframework/cordova/webview/IonicWebView.java"
      ]
    },
    {
      "headline": "Potential cleartext transmission of sensitive information",
      "analysis": "The WebViewLocalServer class appears to transmit data over HTTP, which could potentially expose sensitive information if the data is not properly secured or encrypted.\n",
      "classification": "slightly promising",
      "cwe": "CWE-319",
      "function_names": [],
      "filenames": [
        "src/android/com/ionicframework/cordova/webview/WebViewLocalServer.java"
      ]
    },
    {
      "headline": "Potential improper neutralization of special elements in WebViewLocalServer",
      "analysis": "The WebViewLocalServer class appears to handle user input for file paths and URLs, which could potentially introduce security vulnerabilities such as path traversal or remote file inclusion if special characters are not properly neutralized or escaped.\n",
      "classification": "slightly promising",
      "cwe": "CWE-79",
      "function_names": [
        "hostFiles",
        "hostAssets"
      ],
      "filenames": [
        "src/android/com/ionicframework/cordova/webview/WebViewLocalServer.java"
      ]
    },
    {
      "headline": "Potential lack of authentication for critical functions",
      "analysis": "The codebase does not appear to implement any authentication mechanisms for critical functions or resources, which could potentially allow unauthorized access to sensitive data or functionality.\n",
      "classification": "slightly promising",
      "cwe": "CWE-306",
      "function_names": [],
      "filenames": []
    },
    {
      "headline": "Potential use of hard-coded credentials",
      "analysis": "The codebase appears to use hard-coded credentials or default authentication credentials, which could potentially introduce security vulnerabilities if these credentials are disclosed or used in production environments.\n",
      "classification": "slightly promising",
      "cwe": "CWE-798",
      "function_names": [],
      "filenames": []
    },
    {
      "headline": "Potential improper neutralization of special elements in iOS wk-plugin",
      "analysis": "The wk-plugin.js file appears to handle user input for file URLs, which could potentially introduce security vulnerabilities such as path traversal or remote file inclusion if special characters are not properly neutralized or escaped.\n",
      "classification": "slightly promising",
      "cwe": "CWE-79",
      "function_names": [
        "normalizeURL",
        "wkRewriteURL"
      ],
      "filenames": [
        "src/ios/wk-plugin.js"
      ]
    }
  ],
  "scores": [
    {
      "stats": {
        "fn": 1,
        "tp": 0,
        "fp": 0
      },
      "mapping": {},
      "vuln_dates": {
        "CVE-2018-16202": "2019-01-09T23:29:04"
      },
      "scoring_model": "claude-3-opus-20240229",
      "type": "llm",
      "instruction_template_hash": "245ace12b6361954d0a2"
    },
    {
      "stats": {
        "fn": 1,
        "tp": 0,
        "fp": 0
      },
      "mapping": {},
      "vuln_dates": {
        "CVE-2018-16202": "2019-01-09T23:29:04"
      },
      "scoring_model": "claude-3-5-sonnet-20240620",
      "type": "llm",
      "instruction_template_hash": "245ace12b6361954d0a2"
    }
  ],
  "instruction_template_hash": "10c0163db4740318a544",
  "version": "0.1.0"
}
