{
  "commit": "0951f227aa9399ce0bb721cb7c51169eaa517633",
  "repo_url": "https://github.com/jenkinsci/ghprb-plugin",
  "model": "gpt-4o-2024-05-13",
  "chunk_hashes": [
    "00d65da818c2b6e67c66"
  ],
  "responses": [
    {
      "content": "```yaml\nleads:\n  - headline: \"Possible security vulnerability in GhprbRootActionTest's testUrlEncoded method\"\n    analysis: |\n      The method `GhprbRootActionTest::testUrlEncoded` constructs a `BufferedReader` directly from potentially unsafe user input with `URLEncoder.encode()`. This can lead to various injection attacks if user-controlled input is not properly sanitized or validated. This practice can lead to potentially dangerous side effects, particularly during testing when input can easily be manipulated.\n    cwe: CWE-20\n    function_names:\n      - testUrlEncoded\n    filenames:\n      - src/test/java/org/jenkinsci/plugins/ghprb/GhprbRootActionTest.java\n    classification: very promising\n\n  - headline: \"Insufficient comment validation in GhprbRepository\"\n    analysis: |\n      The code in `GhprbRepository::onIssueCommentHook` and `GhprbPullRequest::checkComment` does not adequately validate user-supplied comments. If these comments are not correctly escaped or validated, it can lead to injection vulnerabilities or unintended behavior when comments are processed.\n    cwe: CWE-20\n    function_names:\n      - onIssueCommentHook\n      - checkComment\n    filenames:\n      - src/main/java/org/jenkinsci/plugins/ghprb/GhprbRepository.java\n      - src/main/java/org/jenkinsci/plugins/ghprb/ GhprbPullRequest.java\n    classification: very promising\n\n  - headline: \"Inadequate signature verification in GhprbRootAction\"\n    analysis: |\n      In `GhprbRootAction::handleAction`, the checks for GitHub signatures can be bypassed if the content type is not application/json. This bypass can potentially allow unauthorized requests to manipulate the system.\n    cwe: CWE-20\n    function_names:\n      - handleAction\n    filenames:\n      - src/main/java/org/jenkinsci/plugins/ghprb/GhprbRootAction.java\n    classification: very promising\n\n  - headline: \"Risk of Use of Hardcoded Credentials in GhprbGitHubAuth\"\n    analysis: |\n      The class `GhprbGitHubAuth` constructs `GitHubBuilder` instances with various credentials in methods like `doTestGithubAccess`, `doTestComment`, `doTestUpdateStatus`, etc. There is a risk that these credentials could be hardcoded within environments or in testing, leading to unauthorized access if not properly secured.\n    cwe: CWE-798\n    function_names:\n      - doTestGithubAccess\n      - doTestComment\n      - doTestUpdateStatus\n    filenames:\n      - src/main/java/org/jenkinsci/plugins/ghprb/GhprbGitHubAuth.java\n    classification: slightly promising\n\n  - headline: \"Potential Race Condition in GhprbRootAction::handleAction\"\n    analysis: |\n      The method `GhprbRootAction::handleAction` modifies security context within a thread perform action possibly introducing a race condition where multiple threads could modify and access shared state leading to inconsistency and potential security issues.\n    cwe: CWE-362\n    function_names:\n      - handleAction\n    filenames:\n      - src/main/java/org/jenkinsci/plugins/ghprb/GhprbRootAction.java\n    classification: very promising\n\n  - headline: \"Unchecked null pointer dereference in GhprbPullRequestMerge\"\n    analysis: |\n      Inside `GhprbPullRequestMerge::perform`, if `fetch` method calls like `getActualPullRequest` return null objects, the method proceeds without adequate null checks, potentially leading to null pointer dereference and runtime exceptions.\n    cwe: CWE-476\n    function_names:\n      - perform\n    filenames:\n      - src/main/java/org/jenkinsci/plugins/ghprb/GhprbPullRequestMerge.java\n    classification: very promising\n\n  - headline: \"Improper handling of user-controlled input in GhprbTestUtil\"\n    analysis: |\n      The `GhprbTestUtil.setupGhprbTriggerDescriptor()` method sets up various GitHub testing configurations using potentially user-controlled URLs and tokens. Without input validation, there is a risk of injection attacks through malicious input in these testing configurations.\n    cwe: CWE-20\n    function_names:\n      - setupGhprbTriggerDescriptor\n    filenames:\n      - src/test/java/org/jenkinsci/plugins/ghprb/GhprbTestUtil.java\n    classification: slightly promising\n```",
      "date": "2024-06-12T18:26:40.772045",
      "usage": {
        "prompt_tokens": 91504,
        "completion_tokens": 943,
        "cost": 0.471665
      }
    }
  ],
  "leads": [
    {
      "headline": "Possible security vulnerability in GhprbRootActionTest's testUrlEncoded method",
      "analysis": "The method GhprbRootActionTest::testUrlEncoded constructs a BufferedReader directly from potentially unsafe user input with URLEncoder.encode(). This can lead to various injection attacks if user-controlled input is not properly sanitized or validated. This practice can lead to potentially dangerous side effects, particularly during testing when input can easily be manipulated.\n",
      "classification": "very promising",
      "cwe": "CWE-20",
      "function_names": [
        "testUrlEncoded"
      ],
      "filenames": [
        "src/test/java/org/jenkinsci/plugins/ghprb/GhprbRootActionTest.java"
      ]
    },
    {
      "headline": "Insufficient comment validation in GhprbRepository",
      "analysis": "The code in GhprbRepository::onIssueCommentHook and GhprbPullRequest::checkComment does not adequately validate user-supplied comments. If these comments are not correctly escaped or validated, it can lead to injection vulnerabilities or unintended behavior when comments are processed.\n",
      "classification": "very promising",
      "cwe": "CWE-20",
      "function_names": [
        "onIssueCommentHook",
        "checkComment"
      ],
      "filenames": [
        "src/main/java/org/jenkinsci/plugins/ghprb/GhprbRepository.java",
        "src/main/java/org/jenkinsci/plugins/ghprb/ GhprbPullRequest.java"
      ]
    },
    {
      "headline": "Inadequate signature verification in GhprbRootAction",
      "analysis": "In GhprbRootAction::handleAction, the checks for GitHub signatures can be bypassed if the content type is not application/json. This bypass can potentially allow unauthorized requests to manipulate the system.\n",
      "classification": "very promising",
      "cwe": "CWE-20",
      "function_names": [
        "handleAction"
      ],
      "filenames": [
        "src/main/java/org/jenkinsci/plugins/ghprb/GhprbRootAction.java"
      ]
    },
    {
      "headline": "Risk of Use of Hardcoded Credentials in GhprbGitHubAuth",
      "analysis": "The class GhprbGitHubAuth constructs GitHubBuilder instances with various credentials in methods like doTestGithubAccess, doTestComment, doTestUpdateStatus, etc. There is a risk that these credentials could be hardcoded within environments or in testing, leading to unauthorized access if not properly secured.\n",
      "classification": "slightly promising",
      "cwe": "CWE-798",
      "function_names": [
        "doTestGithubAccess",
        "doTestComment",
        "doTestUpdateStatus"
      ],
      "filenames": [
        "src/main/java/org/jenkinsci/plugins/ghprb/GhprbGitHubAuth.java"
      ]
    },
    {
      "headline": "Potential Race Condition in GhprbRootAction::handleAction",
      "analysis": "The method GhprbRootAction::handleAction modifies security context within a thread perform action possibly introducing a race condition where multiple threads could modify and access shared state leading to inconsistency and potential security issues.\n",
      "classification": "very promising",
      "cwe": "CWE-362",
      "function_names": [
        "handleAction"
      ],
      "filenames": [
        "src/main/java/org/jenkinsci/plugins/ghprb/GhprbRootAction.java"
      ]
    },
    {
      "headline": "Unchecked null pointer dereference in GhprbPullRequestMerge",
      "analysis": "Inside GhprbPullRequestMerge::perform, if fetch method calls like getActualPullRequest return null objects, the method proceeds without adequate null checks, potentially leading to null pointer dereference and runtime exceptions.\n",
      "classification": "very promising",
      "cwe": "CWE-476",
      "function_names": [
        "perform"
      ],
      "filenames": [
        "src/main/java/org/jenkinsci/plugins/ghprb/GhprbPullRequestMerge.java"
      ]
    },
    {
      "headline": "Improper handling of user-controlled input in GhprbTestUtil",
      "analysis": "The GhprbTestUtil.setupGhprbTriggerDescriptor() method sets up various GitHub testing configurations using potentially user-controlled URLs and tokens. Without input validation, there is a risk of injection attacks through malicious input in these testing configurations.\n",
      "classification": "slightly promising",
      "cwe": "CWE-20",
      "function_names": [
        "setupGhprbTriggerDescriptor"
      ],
      "filenames": [
        "src/test/java/org/jenkinsci/plugins/ghprb/GhprbTestUtil.java"
      ]
    }
  ],
  "scores": [
    {
      "stats": {
        "fn": 5,
        "tp": 1,
        "fp": 4
      },
      "mapping": {
        "2": "CVE-2023-24434"
      },
      "vuln_dates": {
        "CVE-2023-24436": "2023-01-26T21:18:17",
        "CVE-2023-24435": "2023-01-26T21:18:17",
        "CVE-2023-24434": "2023-01-26T21:18:17",
        "CVE-2018-1000143": "2018-04-05T13:29:00",
        "CVE-2018-1000142": "2018-04-05T13:29:00",
        "CVE-2018-1000186": "2018-06-05T20:29:00"
      },
      "scoring_model": "claude-3-opus-20240229",
      "type": "llm",
      "instruction_template_hash": "245ace12b6361954d0a2"
    }
  ],
  "instruction_template_hash": "10c0163db4740318a544",
  "version": "0.1.0"
}
