{
  "commit": "2f1d6d333669589edef08ec68b508ee7efd25865",
  "repo_url": "https://github.com/jenkinsci/publish-over-cifs-plugin",
  "model": "claude-3-sonnet-20240229",
  "chunk_hashes": [
    "001a71ad2bd060ed7735"
  ],
  "responses": [
    {
      "content": "Based on the provided codebase and the Pydantic models for Lead and LeadList, here is the YAML output identifying potential security vulnerabilities:\n\n```yaml\nleads:\n  - headline: Potential Command Injection Vulnerability\n    analysis: |\n      The CifsHostConfiguration class uses the encode method to encode the username and password for inclusion in the SMB URL. However, this encoding method does not properly sanitize the input, potentially allowing command injection if malicious input is provided for the username or password.\n    cwe: CWE-77\n    function_names:\n      - encode\n    filenames:\n      - src/main/java/jenkins/plugins/publish_over_cifs/CifsHostConfiguration.java\n    classification: very promising\n\n  - headline: Potential Directory Traversal Vulnerability\n    analysis: |\n      The CifsHostConfiguration class does not properly sanitize the remoteRootDir input, which could potentially allow directory traversal attacks if malicious input is provided.\n    cwe: CWE-22\n    function_names:\n      - addSharename\n    filenames:\n      - src/main/java/jenkins/plugins/publish_over_cifs/CifsHostConfiguration.java\n    classification: very promising\n\n  - headline: Potential Insecure Deserialization Vulnerability\n    analysis: |\n      The readResolve method in the CifsPublisherPlugin class and CifsPublisherPluginDescriptor class may be vulnerable to insecure deserialization attacks, as it is used to deserialize objects without proper validation.\n    cwe: CWE-502\n    function_names:\n      - readResolve\n    filenames:\n      - src/main/java/jenkins/plugins/publish_over_cifs/CifsPublisherPlugin.java\n      - src/main/java/jenkins/plugins/publish_over_cifs/descriptor/CifsPublisherPluginDescriptor.java\n    classification: slightly promising\n\n  - headline: Potential Hardcoded Credentials Vulnerability\n    analysis: |\n      The SecretHelper class contains a hardcoded secret key, which is a security vulnerability as it can potentially expose sensitive information if the key is compromised.\n    cwe: CWE-798\n    function_names:\n      - setSecretKey\n      - clearSecretKey\n    filenames:\n      - src/test/java/hudson/util/SecretHelper.java\n    classification: very promising\n\n  - headline: Potential Missing Authentication Vulnerability\n    analysis: |\n      The CifsHostConfiguration class does not appear to implement any authentication mechanism for accessing the SMB share, which could potentially lead to unauthorized access.\n    cwe: CWE-306\n    function_names: []\n    filenames:\n      - src/main/java/jenkins/plugins/publish_over_cifs/CifsHostConfiguration.java\n    classification: slightly promising\n```\n\nPlease note that this analysis is based on a static code review and may not cover all potential security vulnerabilities. It is recommended to perform thorough security testing and review to identify and mitigate any vulnerabilities in the application.",
      "date": "2024-06-12T19:02:53.858422",
      "usage": {
        "prompt_tokens": 60032,
        "completion_tokens": 726,
        "cost": 0.190986
      }
    }
  ],
  "leads": [
    {
      "headline": "Potential Command Injection Vulnerability",
      "analysis": "The CifsHostConfiguration class uses the encode method to encode the username and password for inclusion in the SMB URL. However, this encoding method does not properly sanitize the input, potentially allowing command injection if malicious input is provided for the username or password.\n",
      "classification": "very promising",
      "cwe": "CWE-77",
      "function_names": [
        "encode"
      ],
      "filenames": [
        "src/main/java/jenkins/plugins/publish_over_cifs/CifsHostConfiguration.java"
      ]
    },
    {
      "headline": "Potential Directory Traversal Vulnerability",
      "analysis": "The CifsHostConfiguration class does not properly sanitize the remoteRootDir input, which could potentially allow directory traversal attacks if malicious input is provided.\n",
      "classification": "very promising",
      "cwe": "CWE-22",
      "function_names": [
        "addSharename"
      ],
      "filenames": [
        "src/main/java/jenkins/plugins/publish_over_cifs/CifsHostConfiguration.java"
      ]
    },
    {
      "headline": "Potential Insecure Deserialization Vulnerability",
      "analysis": "The readResolve method in the CifsPublisherPlugin class and CifsPublisherPluginDescriptor class may be vulnerable to insecure deserialization attacks, as it is used to deserialize objects without proper validation.\n",
      "classification": "slightly promising",
      "cwe": "CWE-502",
      "function_names": [
        "readResolve"
      ],
      "filenames": [
        "src/main/java/jenkins/plugins/publish_over_cifs/CifsPublisherPlugin.java",
        "src/main/java/jenkins/plugins/publish_over_cifs/descriptor/CifsPublisherPluginDescriptor.java"
      ]
    },
    {
      "headline": "Potential Hardcoded Credentials Vulnerability",
      "analysis": "The SecretHelper class contains a hardcoded secret key, which is a security vulnerability as it can potentially expose sensitive information if the key is compromised.\n",
      "classification": "very promising",
      "cwe": "CWE-798",
      "function_names": [
        "setSecretKey",
        "clearSecretKey"
      ],
      "filenames": [
        "src/test/java/hudson/util/SecretHelper.java"
      ]
    },
    {
      "headline": "Potential Missing Authentication Vulnerability",
      "analysis": "The CifsHostConfiguration class does not appear to implement any authentication mechanism for accessing the SMB share, which could potentially lead to unauthorized access.\n",
      "classification": "slightly promising",
      "cwe": "CWE-306",
      "function_names": [],
      "filenames": [
        "src/main/java/jenkins/plugins/publish_over_cifs/CifsHostConfiguration.java"
      ]
    }
  ],
  "scores": [
    {
      "stats": {
        "fn": 1,
        "tp": 0,
        "fp": 3
      },
      "mapping": {},
      "vuln_dates": {
        "CVE-2018-1999038": "2018-08-01T13:29:00"
      },
      "scoring_model": "claude-3-opus-20240229",
      "type": "llm",
      "instruction_template_hash": "245ace12b6361954d0a2"
    },
    {
      "stats": {
        "fn": 1,
        "tp": 0,
        "fp": 3
      },
      "mapping": {},
      "vuln_dates": {
        "CVE-2018-1999038": "2018-08-01T13:29:00"
      },
      "scoring_model": "claude-3-5-sonnet-20240620",
      "type": "llm",
      "instruction_template_hash": "245ace12b6361954d0a2"
    }
  ],
  "instruction_template_hash": "10c0163db4740318a544",
  "version": "0.1.0"
}
