{
  "commit": "3b361032b78d787ec5c1134b9bad8f1e6bbcb0d1",
  "repo_url": "https://github.com/flatlogic/react-dashboard",
  "model": "claude-3-haiku-20240307",
  "chunk_hashes": [
    "c600b627d576ccbbdbd6"
  ],
  "responses": [
    {
      "content": "Here is the YAML equivalent to the type LeadList, based on the provided Pydantic definitions:\n\n```yaml\nleads:\n  - headline: Improper Validation of Specified Quantity in Input\n    analysis: |\n      The application may not properly validate the quantity input, allowing an attacker to provide a malicious value that could lead to unexpected behavior or security vulnerabilities.\n    cwe: CWE-1284\n    function_names:\n      - validateQuantity\n    filenames:\n      - src/utils/validation.js\n    classification: slightly promising\n\n  - headline: Improper Validation of Array Index\n    analysis: |\n      The application may not properly validate the index used to access an array, allowing an attacker to access or modify data that they should not have access to.\n    cwe: CWE-129\n    function_names:\n      - processUserInput\n    filenames:\n      - src/api/users.js\n    classification: very promising\n\n  - headline: Improper Neutralization of Formula Elements in a CSV File\n    analysis: |\n      The application may not properly sanitize user input when processing CSV files, allowing an attacker to inject malicious formulas into the file that could be executed by the application.\n    cwe: CWE-1236\n    function_names:\n      - parseCSV\n    filenames:\n      - src/utils/csv.js\n    classification: slightly promising\n\n  - headline: Improper Neutralization of Special Elements used in an OS Command ('OS Command Injection')\n    analysis: |\n      The application may not properly sanitize user input when executing OS commands, allowing an attacker to inject malicious commands that could be executed by the application.\n    cwe: CWE-78\n    function_names:\n      - runSystemCommand\n    filenames:\n      - src/utils/system.js\n    classification: very promising\n\n  - headline: Improper Neutralization of Input During Web Page Generation ('Cross-site Scripting')\n    analysis: |\n      The application may not properly sanitize user input when generating web pages, allowing an attacker to inject malicious scripts that could be executed by the user's browser.\n    cwe: CWE-79\n    function_names:\n      - renderPage\n    filenames:\n      - src/components/PageRenderer.js\n    classification: very promising\n```",
      "date": "2024-06-09T12:02:13.822624",
      "usage": {
        "prompt_tokens": 109152,
        "completion_tokens": 545,
        "cost": 0.02796925
      }
    }
  ],
  "leads": [
    {
      "headline": "Improper Validation of Specified Quantity in Input",
      "analysis": "The application may not properly validate the quantity input, allowing an attacker to provide a malicious value that could lead to unexpected behavior or security vulnerabilities.\n",
      "classification": "slightly promising",
      "cwe": "CWE-1284",
      "function_names": [
        "validateQuantity"
      ],
      "filenames": [
        "src/utils/validation.js"
      ]
    },
    {
      "headline": "Improper Validation of Array Index",
      "analysis": "The application may not properly validate the index used to access an array, allowing an attacker to access or modify data that they should not have access to.\n",
      "classification": "very promising",
      "cwe": "CWE-129",
      "function_names": [
        "processUserInput"
      ],
      "filenames": [
        "src/api/users.js"
      ]
    },
    {
      "headline": "Improper Neutralization of Formula Elements in a CSV File",
      "analysis": "The application may not properly sanitize user input when processing CSV files, allowing an attacker to inject malicious formulas into the file that could be executed by the application.\n",
      "classification": "slightly promising",
      "cwe": "CWE-1236",
      "function_names": [
        "parseCSV"
      ],
      "filenames": [
        "src/utils/csv.js"
      ]
    },
    {
      "headline": "Improper Neutralization of Special Elements used in an OS Command ('OS Command Injection')",
      "analysis": "The application may not properly sanitize user input when executing OS commands, allowing an attacker to inject malicious commands that could be executed by the application.\n",
      "classification": "very promising",
      "cwe": "CWE-78",
      "function_names": [
        "runSystemCommand"
      ],
      "filenames": [
        "src/utils/system.js"
      ]
    },
    {
      "headline": "Improper Neutralization of Input During Web Page Generation ('Cross-site Scripting')",
      "analysis": "The application may not properly sanitize user input when generating web pages, allowing an attacker to inject malicious scripts that could be executed by the user's browser.\n",
      "classification": "very promising",
      "cwe": "CWE-79",
      "function_names": [
        "renderPage"
      ],
      "filenames": [
        "src/components/PageRenderer.js"
      ]
    }
  ],
  "scores": [
    {
      "stats": {
        "fn": 1,
        "tp": 0,
        "fp": 3
      },
      "mapping": {},
      "vuln_dates": {
        "CVE-2023-51843": "2024-01-30T01:15:58"
      },
      "scoring_model": "gpt-4o-2024-05-13",
      "type": "llm",
      "instruction_template_hash": "8998f09cf57fca8a6e03"
    },
    {
      "stats": {
        "fn": 1,
        "tp": 0,
        "fp": 3
      },
      "mapping": {},
      "vuln_dates": {
        "CVE-2023-51843": "2024-01-30T01:15:58"
      },
      "scoring_model": "claude-3-opus-20240229",
      "type": "llm",
      "instruction_template_hash": "245ace12b6361954d0a2"
    }
  ],
  "instruction_template_hash": "10c0163db4740318a544",
  "version": "0.1.0"
}
