{
  "commit": "965591c4a2db2f22b38a415e422f38bddb6cf122",
  "repo_url": "https://github.com/nt1m/livemarks",
  "model": "gpt-4o-2024-05-13",
  "chunk_hashes": [
    "133d078375a8f28aa3f3"
  ],
  "responses": [
    {
      "content": "```yaml\nleads:\n  - headline: \"Insecure Fetch in feed-parser.js\"\n    analysis: |\n      The fetchXML method in feed-parser.js fetches and parses XML feeds without validating or sanitizing the XML content. An untrusted feed could potentially inject malicious scripts into the web page rendered through the subscribe.html page.\n    cwe: CWE-94\n    function_names:\n      - fetchXML\n      - setPreviewContent\n    filenames:\n      - shared/feed-parser.js\n      - pages/subscribe/subscribe.js\n    classification: very promising\n\n  - headline: \"Unsafe DOM Manipulation in reader.js\"\n    analysis: |\n      The getPreviewHTML function in reader.js directly injects HTML content from RSS feed items into an iframe. This could allow malicious feeds to execute scripts or HTML injection even within the sandbox constraints.\n    cwe: CWE-79\n    function_names:\n      - getPreviewHTML\n    filenames:\n      - pages/reader/reader.js\n    classification: very promising\n\n  - headline: \"Potential XSS in prefix-utils.js\"\n    analysis: |\n      The PrefixUtils object manipulates bookmark titles which may contain user-controlled input. Without proper sanitization, this could lead to Cross-Site Scripting (XSS) vulnerabilities if an attacker manipulates the title of a bookmark.\n    cwe: CWE-79\n    function_names:\n      - removePrefix\n      - addPrefix\n    filenames:\n      - shared/prefix-utils.js\n    classification: slightly promising\n\n  - headline: \"Unrestricted File Upload in opml-utils.js\"\n    analysis: |\n      The importOPML function in opml-utils.js does not impose restrictions on the kind of files that can be selected and processed. This poses a risk of importing malicious content if not handled securely.\n    cwe: CWE-434\n    function_names:\n      - importOPML\n    filenames:\n      - pages/settings/opml-utils.js\n    classification: slightly promising\n\n  - headline: \"Insecure Storage of Sensitive Information in settings.js\"\n    analysis: |\n      The settings object uses browser.storage.local and browser.storage.sync to store settings, which can include sensitive information like default folders without additional encryption or protection measures.\n    cwe: CWE-922\n    function_names:\n      - getSetting\n      - setSetting\n    filenames:\n      - shared/settings.js\n    classification: slightly promising\n```",
      "date": "2024-06-09T13:52:16.318224",
      "usage": {
        "prompt_tokens": 17993,
        "completion_tokens": 492,
        "cost": 0.097345
      }
    }
  ],
  "leads": [
    {
      "headline": "Insecure Fetch in feed-parser.js",
      "analysis": "The fetchXML method in feed-parser.js fetches and parses XML feeds without validating or sanitizing the XML content. An untrusted feed could potentially inject malicious scripts into the web page rendered through the subscribe.html page.\n",
      "classification": "very promising",
      "cwe": "CWE-94",
      "function_names": [
        "fetchXML",
        "setPreviewContent"
      ],
      "filenames": [
        "shared/feed-parser.js",
        "pages/subscribe/subscribe.js"
      ]
    },
    {
      "headline": "Unsafe DOM Manipulation in reader.js",
      "analysis": "The getPreviewHTML function in reader.js directly injects HTML content from RSS feed items into an iframe. This could allow malicious feeds to execute scripts or HTML injection even within the sandbox constraints.\n",
      "classification": "very promising",
      "cwe": "CWE-79",
      "function_names": [
        "getPreviewHTML"
      ],
      "filenames": [
        "pages/reader/reader.js"
      ]
    },
    {
      "headline": "Potential XSS in prefix-utils.js",
      "analysis": "The PrefixUtils object manipulates bookmark titles which may contain user-controlled input. Without proper sanitization, this could lead to Cross-Site Scripting (XSS) vulnerabilities if an attacker manipulates the title of a bookmark.\n",
      "classification": "slightly promising",
      "cwe": "CWE-79",
      "function_names": [
        "removePrefix",
        "addPrefix"
      ],
      "filenames": [
        "shared/prefix-utils.js"
      ]
    },
    {
      "headline": "Unrestricted File Upload in opml-utils.js",
      "analysis": "The importOPML function in opml-utils.js does not impose restrictions on the kind of files that can be selected and processed. This poses a risk of importing malicious content if not handled securely.\n",
      "classification": "slightly promising",
      "cwe": "CWE-434",
      "function_names": [
        "importOPML"
      ],
      "filenames": [
        "pages/settings/opml-utils.js"
      ]
    },
    {
      "headline": "Insecure Storage of Sensitive Information in settings.js",
      "analysis": "The settings object uses browser.storage.local and browser.storage.sync to store settings, which can include sensitive information like default folders without additional encryption or protection measures.\n",
      "classification": "slightly promising",
      "cwe": "CWE-922",
      "function_names": [
        "getSetting",
        "setSetting"
      ],
      "filenames": [
        "shared/settings.js"
      ]
    }
  ],
  "scores": [
    {
      "stats": {
        "fn": 1,
        "tp": 0,
        "fp": 2
      },
      "mapping": {},
      "vuln_dates": {
        "CVE-2024-30252": "2024-04-04T19:15:08"
      },
      "scoring_model": "gpt-4o-2024-05-13",
      "type": "llm",
      "instruction_template_hash": "8998f09cf57fca8a6e03"
    },
    {
      "stats": {
        "fn": 1,
        "tp": 0,
        "fp": 2
      },
      "mapping": {},
      "vuln_dates": {
        "CVE-2024-30252": "2024-04-04T19:15:08"
      },
      "scoring_model": "claude-3-opus-20240229",
      "type": "llm",
      "instruction_template_hash": "245ace12b6361954d0a2"
    },
    {
      "stats": {
        "fn": 1,
        "tp": 0,
        "fp": 2
      },
      "mapping": {},
      "vuln_dates": {
        "CVE-2024-30252": "2024-04-04T19:15:08"
      },
      "scoring_model": "claude-3-5-sonnet-20240620",
      "type": "llm",
      "instruction_template_hash": "245ace12b6361954d0a2"
    }
  ],
  "instruction_template_hash": "10c0163db4740318a544",
  "version": "0.1.0"
}
