{
  "commit": "4735e17287003b24e86b909f473af14771b8b32c",
  "repo_url": "https://github.com/pkgconf/pkgconf",
  "model": "gpt-4-turbo-2024-04-09",
  "chunk_hashes": [
    "e7734a1cd6c36150c98b"
  ],
  "responses": [
    {
      "content": "```yaml\nleads:\n  - headline: \"Unsafe use of uninitialized pointer\"\n    analysis: |\n      The function 'run_or_die' in the file autogen.sh may use a command string that could be uninitialized if the provided 'COMMAND' parameter is empty. This potentially leads to execution of an unintended command or could crash the script due to dereferencing a NULL pointer.\n    cwe: CWE-908\n    function_names:\n      - run_or_die\n    filenames:\n      - ./autogen.sh\n    classification: slightly promising\n\n  - headline: \"Command injection vulnerability in script\"\n    analysis: |\n      In 'tests/regress.sh', it uses 'atf_check' which indirectly can run arbitrary commands from input without proper sanitization or quoting. Specifically, the 'libs_only_body' function and others build commands dynamically and execute them, this can exploit the system if input is not properly controlled or sanitized which is not seen to be the case.\n    cwe: CWE-77\n    function_names:\n      - libs_never_mergeback_body\n      - libs_only_body\n    filenames:\n      - tests/regress.sh\n    classification: very promising\n\n  - headline: \"Buffer over-read possibility due to improper handling of strings\"\n    analysis: |\n      The 'pkgconf_argv_split' function in the file argvsplit.c does not properly validate the input size, potentially leading to buffer over-read. This occurs because it proceeds to manipulate the string without ensuring the size is adequate for operations like substring fetching and tokenization.\n    cwe: CWE-126\n    function_names:\n      - pkgconf_argv_split\n    filenames:\n      - cli/argvsplit.c\n    classification: slightly promising\n\n  - headline: \"Path traversal vulnerability due to improper filename sanitization\"\n    analysis: |\n      The function 'pkgconf_path_relocate' in path.c concatenates paths without sanitizing or filtering '../' sequences. An attacker could potentially provide a path that escapes the intended directory structure (such as in 'PKG_CONFIG_PATH'), leading to unauthorized file system access.\n    cwe: CWE-22\n    function_names:\n      - pkgconf_path_relocate\n    filenames:\n      - libpkgconf/path.c\n    classification: very promising\n\n  - headline: \"Inadequate error handling leading to information disclosure\"\n    analysis: |\n      The functions 'getopt_internal' and 'parse_long_options' in getopt_long.c do not properly handle errors that occur during option parsing. Detailed error messages are printed without regard to context, potentially leading to information disclosure about the environment or internal state.\n    cwe: CWE-209\n    function_names:\n      - getopt_internal\n      - parse_long_options\n    filenames:\n      - cli/getopt_long.c\n    classification: slightly promising\n\n  - headline: \"Risk of arbitrary command execution through environment variable manipulation\"\n    analysis: |\n      In main.c, the function 'apply_env' uses unchecked environment variables to influence subprocess commands (e.g., using PKG_CONFIG_PATH). An attacker controlling these variables could execute arbitrary commands, particularly if set to execute system calls or other sensitive operations.\n    cwe: CWE-78\n    function_names:\n      - main\n      - apply_env\n    filenames:\n      - cli/main.c\n    classification: very promising\n```",
      "date": "2024-06-14T15:19:44.385725",
      "usage": {
        "prompt_tokens": 87197,
        "completion_tokens": 675,
        "cost": 0.89222
      }
    }
  ],
  "leads": [
    {
      "headline": "Unsafe use of uninitialized pointer",
      "analysis": "The function 'run_or_die' in the file autogen.sh may use a command string that could be uninitialized if the provided 'COMMAND' parameter is empty. This potentially leads to execution of an unintended command or could crash the script due to dereferencing a NULL pointer.\n",
      "classification": "slightly promising",
      "cwe": "CWE-908",
      "function_names": [
        "run_or_die"
      ],
      "filenames": [
        "./autogen.sh"
      ]
    },
    {
      "headline": "Command injection vulnerability in script",
      "analysis": "In 'tests/regress.sh', it uses 'atf_check' which indirectly can run arbitrary commands from input without proper sanitization or quoting. Specifically, the 'libs_only_body' function and others build commands dynamically and execute them, this can exploit the system if input is not properly controlled or sanitized which is not seen to be the case.\n",
      "classification": "very promising",
      "cwe": "CWE-77",
      "function_names": [
        "libs_never_mergeback_body",
        "libs_only_body"
      ],
      "filenames": [
        "tests/regress.sh"
      ]
    },
    {
      "headline": "Buffer over-read possibility due to improper handling of strings",
      "analysis": "The 'pkgconf_argv_split' function in the file argvsplit.c does not properly validate the input size, potentially leading to buffer over-read. This occurs because it proceeds to manipulate the string without ensuring the size is adequate for operations like substring fetching and tokenization.\n",
      "classification": "slightly promising",
      "cwe": "CWE-126",
      "function_names": [
        "pkgconf_argv_split"
      ],
      "filenames": [
        "cli/argvsplit.c"
      ]
    },
    {
      "headline": "Path traversal vulnerability due to improper filename sanitization",
      "analysis": "The function 'pkgconf_path_relocate' in path.c concatenates paths without sanitizing or filtering '../' sequences. An attacker could potentially provide a path that escapes the intended directory structure (such as in 'PKG_CONFIG_PATH'), leading to unauthorized file system access.\n",
      "classification": "very promising",
      "cwe": "CWE-22",
      "function_names": [
        "pkgconf_path_relocate"
      ],
      "filenames": [
        "libpkgconf/path.c"
      ]
    },
    {
      "headline": "Inadequate error handling leading to information disclosure",
      "analysis": "The functions 'getopt_internal' and 'parse_long_options' in getopt_long.c do not properly handle errors that occur during option parsing. Detailed error messages are printed without regard to context, potentially leading to information disclosure about the environment or internal state.\n",
      "classification": "slightly promising",
      "cwe": "CWE-209",
      "function_names": [
        "getopt_internal",
        "parse_long_options"
      ],
      "filenames": [
        "cli/getopt_long.c"
      ]
    },
    {
      "headline": "Risk of arbitrary command execution through environment variable manipulation",
      "analysis": "In main.c, the function 'apply_env' uses unchecked environment variables to influence subprocess commands (e.g., using PKG_CONFIG_PATH). An attacker controlling these variables could execute arbitrary commands, particularly if set to execute system calls or other sensitive operations.\n",
      "classification": "very promising",
      "cwe": "CWE-78",
      "function_names": [
        "main",
        "apply_env"
      ],
      "filenames": [
        "cli/main.c"
      ]
    }
  ],
  "scores": [
    {
      "stats": {
        "fn": 1,
        "tp": 0,
        "fp": 3
      },
      "mapping": {},
      "vuln_dates": {
        "CVE-2018-1000221": "2018-08-20T20:29:01"
      },
      "scoring_model": "claude-3-opus-20240229",
      "type": "llm",
      "instruction_template_hash": "245ace12b6361954d0a2"
    },
    {
      "stats": {
        "fn": 1,
        "tp": 0,
        "fp": 3
      },
      "mapping": {},
      "vuln_dates": {
        "CVE-2018-1000221": "2018-08-20T20:29:01"
      },
      "scoring_model": "claude-3-5-sonnet-20240620",
      "type": "llm",
      "instruction_template_hash": "245ace12b6361954d0a2"
    }
  ],
  "instruction_template_hash": "10c0163db4740318a544",
  "version": "0.1.0"
}
