{
  "commit": "2cff6598cfe7bdecf4c081f2e214f0190758911a",
  "repo_url": "https://github.com/freepbx/voicemail",
  "model": "gpt-4o-2024-05-13",
  "chunk_hashes": [
    "255bf70d45147f3d6edf"
  ],
  "responses": [
    {
      "content": "```yaml\nleads:\n  - headline: \"Improper Neutralization of Input During Web Page Generation (XSS)\"\n    analysis: |\n      The function saveVmXSettings takes user-provided values and directly sends them as part of an HTTP POST request using jQuery's $.post function. If these values contain malicious JavaScript, they could be executed when JSON responses are parsed or used elsewhere on the page. Similar issues can arise in poll and other functions where unfiltered data from the server is processed.\n    cwe: CWE-79\n    function_names:\n      - saveVmXSettings\n      - poll\n    filenames:\n      - ucp/assets/js/global.js\n    classification: very promising\n  - headline: \"Cleartext Transmission of Sensitive Information\"\n    analysis: |\n      The codebase often sends data over the network using HTTP POST requests without any explicit mention of HTTPS. This could lead to sensitive information, such as voicemail settings or messages, being intercepted by attackers during transmission.\n    cwe: CWE-319\n    function_names:\n      - saveVmXSettings\n      - forwardVoicemail\n      - deleteVoicemail\n    filenames:\n      - ucp/assets/js/global.js\n    classification: slightly promising\n  - headline: \"Use of Insufficiently Random Values\"\n    analysis: |\n      The generateRandom function uses a simple method of generating a random number based on the current timestamp. This is not secure for cryptographic operations and predictable for generating unique IDs for security purposes.\n    cwe: CWE-338\n    function_names:\n      - generateRandom\n    filenames:\n      - ucp/assets/js/global.js\n    classification: very promising\n  - headline: \"Improper Validation of Input\"\n    analysis: |\n      Various inputs, such as voicemail settings, are directly taken from user inputs and sent to the server without proper validation. Specifically, when inputs are sent to functions like saveVmXSettings and poll, there is no sanitation or validation being performed.\n    cwe: CWE-20\n    function_names:\n      - saveVmXSettings\n      - poll\n      - deleteVoicemail\n    filenames:\n      - ucp/assets/js/global.js\n    classification: very promising\n  - headline: \"Cleartext Storage of Sensitive Information (Cookies)\"\n    analysis: |\n      Cookies are being set with voicemail refresh settings without specifying the secure flag, which means these cookies could be transmitted in clear text, potentially exposing sensitive information.\n    cwe: CWE-312\n    function_names:\n      - displayWidgetSettings\n    filenames:\n      - ucp/assets/js/global.js\n    classification: slightly promising\n  - headline: \"Exposure of Sensitive Information to an Unauthorized Actor\"\n    analysis: |\n      Sensitive data such as voicemail messages and settings are being logged using console.error in the error handling sections (e.g., within the poll function). If these logs are exposed to unauthorized actors, it can lead to a data breach.\n    cwe: CWE-200\n    function_names:\n      - poll\n    filenames:\n      - ucp/assets/js/global.js\n    classification: slightly promising\n```",
      "date": "2024-06-12T16:41:11.261255",
      "usage": {
        "prompt_tokens": 31152,
        "completion_tokens": 636,
        "cost": 0.1653
      }
    }
  ],
  "leads": [
    {
      "headline": "Improper Neutralization of Input During Web Page Generation (XSS)",
      "analysis": "The function saveVmXSettings takes user-provided values and directly sends them as part of an HTTP POST request using jQuery's $.post function. If these values contain malicious JavaScript, they could be executed when JSON responses are parsed or used elsewhere on the page. Similar issues can arise in poll and other functions where unfiltered data from the server is processed.\n",
      "classification": "very promising",
      "cwe": "CWE-79",
      "function_names": [
        "saveVmXSettings",
        "poll"
      ],
      "filenames": [
        "ucp/assets/js/global.js"
      ]
    },
    {
      "headline": "Cleartext Transmission of Sensitive Information",
      "analysis": "The codebase often sends data over the network using HTTP POST requests without any explicit mention of HTTPS. This could lead to sensitive information, such as voicemail settings or messages, being intercepted by attackers during transmission.\n",
      "classification": "slightly promising",
      "cwe": "CWE-319",
      "function_names": [
        "saveVmXSettings",
        "forwardVoicemail",
        "deleteVoicemail"
      ],
      "filenames": [
        "ucp/assets/js/global.js"
      ]
    },
    {
      "headline": "Use of Insufficiently Random Values",
      "analysis": "The generateRandom function uses a simple method of generating a random number based on the current timestamp. This is not secure for cryptographic operations and predictable for generating unique IDs for security purposes.\n",
      "classification": "very promising",
      "cwe": "CWE-338",
      "function_names": [
        "generateRandom"
      ],
      "filenames": [
        "ucp/assets/js/global.js"
      ]
    },
    {
      "headline": "Improper Validation of Input",
      "analysis": "Various inputs, such as voicemail settings, are directly taken from user inputs and sent to the server without proper validation. Specifically, when inputs are sent to functions like saveVmXSettings and poll, there is no sanitation or validation being performed.\n",
      "classification": "very promising",
      "cwe": "CWE-20",
      "function_names": [
        "saveVmXSettings",
        "poll",
        "deleteVoicemail"
      ],
      "filenames": [
        "ucp/assets/js/global.js"
      ]
    },
    {
      "headline": "Cleartext Storage of Sensitive Information (Cookies)",
      "analysis": "Cookies are being set with voicemail refresh settings without specifying the secure flag, which means these cookies could be transmitted in clear text, potentially exposing sensitive information.\n",
      "classification": "slightly promising",
      "cwe": "CWE-312",
      "function_names": [
        "displayWidgetSettings"
      ],
      "filenames": [
        "ucp/assets/js/global.js"
      ]
    },
    {
      "headline": "Exposure of Sensitive Information to an Unauthorized Actor",
      "analysis": "Sensitive data such as voicemail messages and settings are being logged using console.error in the error handling sections (e.g., within the poll function). If these logs are exposed to unauthorized actors, it can lead to a data breach.\n",
      "classification": "slightly promising",
      "cwe": "CWE-200",
      "function_names": [
        "poll"
      ],
      "filenames": [
        "ucp/assets/js/global.js"
      ]
    }
  ],
  "scores": [
    {
      "stats": {
        "fn": 2,
        "tp": 0,
        "fp": 3
      },
      "mapping": {},
      "vuln_dates": {
        "CVE-2021-4282": "2022-12-27T10:15:11",
        "CVE-2021-4283": "2022-12-27T10:15:11"
      },
      "scoring_model": "claude-3-opus-20240229",
      "type": "llm",
      "instruction_template_hash": "245ace12b6361954d0a2"
    }
  ],
  "instruction_template_hash": "10c0163db4740318a544",
  "version": "0.1.0"
}
