{
  "commit": "0a85fabd15aa3606630b06c95e13ab45a0985afd",
  "repo_url": "https://github.com/jenkinsci/hipchat-plugin",
  "model": "gpt-4o-2024-05-13",
  "chunk_hashes": [
    "82a77455f52843afd54a"
  ],
  "responses": [
    {
      "content": "```yaml\nleads:\n  - headline: \"Hard-Coded Credentials\"\n    analysis: |\n      The code contains several instances of hard-coded credentials in the plugin and its tests, specifically in the `HipChatV1Service` and `HipChatNotifier` classes. Hard-coded credentials can lead to security vulnerabilities since they can be harvested and misused by attackers.\n    cwe: \"CWE-798\"\n    function_names:\n      - \"getHipChatService\"\n      - \"HipChatV1Service\"\n      - \"HipChatV2Service\"\n    filenames:\n      - \"src/main/java/jenkins/plugins/hipchat/impl/HipChatV1Service.java\"\n      - \"src/main/java/jenkins/plugins/hipchat/HipChatNotifier.java\"\n      - \"src/test/java/jenkins/plugins/hipchat/workflow/HipChatSendStepTest.java\"\n    classification: \"very promising\"\n\n  - headline: \"Insufficiently Protected Credentials\"\n    analysis: |\n      Credentials are being passed via `String` parameters and not always securely handled or stored. For instance, tokens are directly used in URIs and method calls without sufficient masking or encryption, making them susceptible to interception and theft.\n    cwe: \"CWE-522\"\n    function_names:\n      - \"resolveCredential\"\n      - \"getHipChatService\"\n    filenames:\n      - \"src/main/java/jenkins/plugins/hipchat/utils/CredentialUtils.java\"\n      - \"src/main/java/jenkins/plugins/hipchat/HipChatNotifier.java\"\n    classification: \"very promising\"\n\n  - headline: \"Cleartext Transmission of Sensitive Information\"\n    analysis: |\n      The `HipChatV1Service` and `HipChatV2Service` classes are transmitting sensitive information such as tokens and messages over HTTP without ensuring that HTTPS is enforced, which could lead to the exposure of credentials.\n    cwe: \"CWE-319\"\n    function_names:\n      - \"publish\"\n    filenames:\n      - \"src/main/java/jenkins/plugins/hipchat/impl/HipChatV1Service.java\"\n      - \"src/main/java/jenkins/plugins/hipchat/impl/HipChatV2Service.java\"\n    classification: \"very promising\"\n\n  - headline: \"Improper Validation of Inputs\"\n    analysis: |\n      The code does not implement sufficient validation for inputs such as room names, icons, URLs, or credentials. This can be used by attackers to inject malicious inputs, leading to various vulnerabilities.\n    cwe: \"CWE-20\"\n    function_names:\n      - \"getResolvedRoom\"\n      - \"publishNotificationIfEnabled\"\n    filenames:\n      - \"src/main/java/jenkins/plugins/hipchat/HipChatNotifier.java\"\n    classification: \"slightly promising\"\n\n  - headline: \"Deserialization of Untrusted Data\"\n    analysis: |\n      The use of Jackson's `ObjectMapper` for JSON deserialization in the `HipChatV2Service`'s `publish` method is risky without proper controls. This could open up deserialization attacks if the input is not strictly controlled and validated.\n    cwe: \"CWE-502\"\n    function_names:\n      - \"publish\"\n    filenames:\n      - \"src/main/java/jenkins/plugins/hipchat/impl/HipChatV2Service.java\"\n    classification: \"slightly promising\"\n```",
      "date": "2024-06-12T18:36:00.448461",
      "usage": {
        "prompt_tokens": 29611,
        "completion_tokens": 696,
        "cost": 0.158495
      }
    }
  ],
  "leads": [
    {
      "headline": "Hard-Coded Credentials",
      "analysis": "The code contains several instances of hard-coded credentials in the plugin and its tests, specifically in the HipChatV1Service and HipChatNotifier classes. Hard-coded credentials can lead to security vulnerabilities since they can be harvested and misused by attackers.\n",
      "classification": "very promising",
      "cwe": "CWE-798",
      "function_names": [
        "getHipChatService",
        "HipChatV1Service",
        "HipChatV2Service"
      ],
      "filenames": [
        "src/main/java/jenkins/plugins/hipchat/impl/HipChatV1Service.java",
        "src/main/java/jenkins/plugins/hipchat/HipChatNotifier.java",
        "src/test/java/jenkins/plugins/hipchat/workflow/HipChatSendStepTest.java"
      ]
    },
    {
      "headline": "Insufficiently Protected Credentials",
      "analysis": "Credentials are being passed via String parameters and not always securely handled or stored. For instance, tokens are directly used in URIs and method calls without sufficient masking or encryption, making them susceptible to interception and theft.\n",
      "classification": "very promising",
      "cwe": "CWE-522",
      "function_names": [
        "resolveCredential",
        "getHipChatService"
      ],
      "filenames": [
        "src/main/java/jenkins/plugins/hipchat/utils/CredentialUtils.java",
        "src/main/java/jenkins/plugins/hipchat/HipChatNotifier.java"
      ]
    },
    {
      "headline": "Cleartext Transmission of Sensitive Information",
      "analysis": "The HipChatV1Service and HipChatV2Service classes are transmitting sensitive information such as tokens and messages over HTTP without ensuring that HTTPS is enforced, which could lead to the exposure of credentials.\n",
      "classification": "very promising",
      "cwe": "CWE-319",
      "function_names": [
        "publish"
      ],
      "filenames": [
        "src/main/java/jenkins/plugins/hipchat/impl/HipChatV1Service.java",
        "src/main/java/jenkins/plugins/hipchat/impl/HipChatV2Service.java"
      ]
    },
    {
      "headline": "Improper Validation of Inputs",
      "analysis": "The code does not implement sufficient validation for inputs such as room names, icons, URLs, or credentials. This can be used by attackers to inject malicious inputs, leading to various vulnerabilities.\n",
      "classification": "slightly promising",
      "cwe": "CWE-20",
      "function_names": [
        "getResolvedRoom",
        "publishNotificationIfEnabled"
      ],
      "filenames": [
        "src/main/java/jenkins/plugins/hipchat/HipChatNotifier.java"
      ]
    },
    {
      "headline": "Deserialization of Untrusted Data",
      "analysis": "The use of Jackson's ObjectMapper for JSON deserialization in the HipChatV2Service's publish method is risky without proper controls. This could open up deserialization attacks if the input is not strictly controlled and validated.\n",
      "classification": "slightly promising",
      "cwe": "CWE-502",
      "function_names": [
        "publish"
      ],
      "filenames": [
        "src/main/java/jenkins/plugins/hipchat/impl/HipChatV2Service.java"
      ]
    }
  ],
  "scores": [
    {
      "stats": {
        "fn": 1,
        "tp": 1,
        "fp": 2
      },
      "mapping": {
        "1": "CVE-2018-1000418"
      },
      "vuln_dates": {
        "CVE-2018-1000418": "2019-01-09T23:29:02",
        "CVE-2018-1000419": "2019-01-09T23:29:02"
      },
      "scoring_model": "claude-3-opus-20240229",
      "type": "llm",
      "instruction_template_hash": "245ace12b6361954d0a2"
    },
    {
      "stats": {
        "fn": 1,
        "tp": 1,
        "fp": 2
      },
      "mapping": {
        "1": "CVE-2018-1000418"
      },
      "vuln_dates": {
        "CVE-2018-1000418": "2019-01-09T23:29:02",
        "CVE-2018-1000419": "2019-01-09T23:29:02"
      },
      "scoring_model": "claude-3-5-sonnet-20240620",
      "type": "llm",
      "instruction_template_hash": "245ace12b6361954d0a2"
    }
  ],
  "instruction_template_hash": "10c0163db4740318a544",
  "version": "0.1.0"
}
