{
  "commit": "48063aeb0dd2065a8af7c976d6650d49980949a4",
  "repo_url": "https://github.com/snowflakedb/snowflake-hive-metastore-connector",
  "model": "gpt-4-turbo-2024-04-09",
  "chunk_hashes": [
    "cf53e68c6375f8df4e66"
  ],
  "responses": [
    {
      "content": "```yaml\nleads:\n  - headline: Insecure storage of sensitive information in environment variables\n    analysis: |\n      The deploy.sh script sets sensitive information directly into environment variables, which are inherently insecure as they can be dumped and are accessible to any process running in the same environment. This can lead to potential exposure of credentials.\n    cwe: CWE-532\n    function_names: []\n    filenames:\n      - deploy.sh\n    classification: very promising\n\n  - headline: Command injection vulnerability in deploy.sh script\n    analysis: |\n      The deploy.sh script constructs a command line for Maven based on variables that can be manipulated by setting environment variables or modifying files read by the scripts. If an attacker can inject malicious input into these variables or files, it could lead to arbitrary command execution.\n    cwe: CWE-77\n    function_names: []\n    filenames:\n      - deploy.sh\n    classification: very promising\n\n  - headline: Usage of hard-coded credentials\n    analysis: |\n      The scripts use hard-coded credentials or private keys for connecting to Snowflake, which are visible in plain text. This could lead to unauthorized access if these credentials are compromised.\n    cwe: CWE-798\n    function_names: []\n    filenames:\n      - scripts/add_snowflake_hive_metastore_connector_script_action.sh\n    classification: very promising\n\n  - headline: Lack of proper XML External Entity (XXE) handling in Pom XML file parsing\n    analysis: |\n      In scripts/get_project_info_from_pom.py and scripts/update_project_version.py, there is parsing of XML input without disincentivizing or properly handling XML External Entities, which could potentially allow an attacker to view files on the application's filesystem, carry out denial of service attacks, or server-side request forgery.\n    cwe: CWE-611\n    function_names:\n      - get_project_info_from_pom.py\n      - update_project_version.py\n    filenames: []\n    classification: very promising\n\n  - headline: Excessive permissions-to-external-libraries\n    analysis: |\n      The scripts explicitly change permissions to allow more access than necessary, using chmod 755 on various files. This increases the attack surface by allowing potential execution of these files by unauthorized users.\n    cwe: CWE-276\n    function_names: []\n    filenames:\n      - scripts/run_gh_actions.sh\n    classification: very promising\n\n  - headline: Inadequate encryption strength in configuring SSL\n    analysis: |\n      In SnowflakeConf.java, the `SNOWFLAKE_JDBC_SSL` config is used to enable or disable SSL, but there is no enforcement or configuration detail to ensure that strong protocols, cipher suites, or certificate validation are used. This may lead to weaker encryption than intended.\n    cwe: CWE-326\n    function_names:\n      - SnowflakeConf\n    filenames:\n      - src/main/java/net/snowflake/hivemetastoreconnector/SnowflakeConf.java\n    classification: slightly promising\n```",
      "date": "2024-06-09T14:51:18.551257",
      "usage": {
        "prompt_tokens": 52942,
        "completion_tokens": 612,
        "cost": 0.54778
      }
    }
  ],
  "leads": [
    {
      "headline": "Insecure storage of sensitive information in environment variables",
      "analysis": "The deploy.sh script sets sensitive information directly into environment variables, which are inherently insecure as they can be dumped and are accessible to any process running in the same environment. This can lead to potential exposure of credentials.\n",
      "classification": "very promising",
      "cwe": "CWE-532",
      "function_names": [],
      "filenames": [
        "deploy.sh"
      ]
    },
    {
      "headline": "Command injection vulnerability in deploy.sh script",
      "analysis": "The deploy.sh script constructs a command line for Maven based on variables that can be manipulated by setting environment variables or modifying files read by the scripts. If an attacker can inject malicious input into these variables or files, it could lead to arbitrary command execution.\n",
      "classification": "very promising",
      "cwe": "CWE-77",
      "function_names": [],
      "filenames": [
        "deploy.sh"
      ]
    },
    {
      "headline": "Usage of hard-coded credentials",
      "analysis": "The scripts use hard-coded credentials or private keys for connecting to Snowflake, which are visible in plain text. This could lead to unauthorized access if these credentials are compromised.\n",
      "classification": "very promising",
      "cwe": "CWE-798",
      "function_names": [],
      "filenames": [
        "scripts/add_snowflake_hive_metastore_connector_script_action.sh"
      ]
    },
    {
      "headline": "Lack of proper XML External Entity (XXE) handling in Pom XML file parsing",
      "analysis": "In scripts/get_project_info_from_pom.py and scripts/update_project_version.py, there is parsing of XML input without disincentivizing or properly handling XML External Entities, which could potentially allow an attacker to view files on the application's filesystem, carry out denial of service attacks, or server-side request forgery.\n",
      "classification": "very promising",
      "cwe": "CWE-611",
      "function_names": [
        "get_project_info_from_pom.py",
        "update_project_version.py"
      ],
      "filenames": []
    },
    {
      "headline": "Excessive permissions-to-external-libraries",
      "analysis": "The scripts explicitly change permissions to allow more access than necessary, using chmod 755 on various files. This increases the attack surface by allowing potential execution of these files by unauthorized users.\n",
      "classification": "very promising",
      "cwe": "CWE-276",
      "function_names": [],
      "filenames": [
        "scripts/run_gh_actions.sh"
      ]
    },
    {
      "headline": "Inadequate encryption strength in configuring SSL",
      "analysis": "In SnowflakeConf.java, the SNOWFLAKE_JDBC_SSL config is used to enable or disable SSL, but there is no enforcement or configuration detail to ensure that strong protocols, cipher suites, or certificate validation are used. This may lead to weaker encryption than intended.\n",
      "classification": "slightly promising",
      "cwe": "CWE-326",
      "function_names": [
        "SnowflakeConf"
      ],
      "filenames": [
        "src/main/java/net/snowflake/hivemetastoreconnector/SnowflakeConf.java"
      ]
    }
  ],
  "scores": [
    {
      "stats": {
        "fn": 1,
        "tp": 0,
        "fp": 5
      },
      "mapping": {},
      "vuln_dates": {
        "CVE-2024-28851": "2024-03-15T19:15:07"
      },
      "scoring_model": "gpt-4o-2024-05-13",
      "type": "llm",
      "instruction_template_hash": "8998f09cf57fca8a6e03"
    }
  ],
  "instruction_template_hash": "10c0163db4740318a544",
  "version": "0.1.0"
}
