{
  "commit": "1fec8f669d9dc965d12f108097f8d78e638b584a",
  "repo_url": "https://github.com/michaelforney/samurai",
  "model": "claude-3-haiku-20240307",
  "chunk_hashes": [
    "64efc91c546aabec74c4"
  ],
  "responses": [
    {
      "content": "Here is the YAML output for the security vulnerabilities in the codebase:\n\n```yaml\nleads:\n  - headline: Improper Validation of Input\n    analysis: |\n      The codebase does not properly validate user input, which could lead to security vulnerabilities such as command injection, SQL injection, or other injection-based attacks. This is a common issue that occurs when user-supplied data is not properly sanitized or validated before being used in operations like file paths, system commands, or database queries.\n    cwe: CWE-20\n    function_names:\n      - nodepath\n      - edgevar\n    filenames:\n      - util.c\n      - env.c\n    classification: slightly promising\n\n  - headline: Weak Cryptographic Algorithm\n    analysis: |\n      The codebase uses the murmurhash64a function to generate hashes, which is not a cryptographically secure hash algorithm. This could lead to security vulnerabilities if the hashes are used for sensitive operations like authentication or access control.\n    cwe: CWE-327\n    function_names:\n      - murmurhash64a\n    filenames:\n      - htab.c\n    classification: slightly promising\n\n  - headline: Insecure File Operations\n    analysis: |\n      The codebase performs various file operations, such as reading and writing files, without properly handling error conditions or checking for race conditions. This could lead to security vulnerabilities like directory traversal, file overwrite, or other file-based attacks.\n    cwe: CWE-404\n    function_names:\n      - writefile\n      - makedirs\n    filenames:\n      - util.c\n    classification: slightly promising\n\n  - headline: Improper Certificate Validation\n    analysis: |\n      The codebase does not appear to perform any certificate validation, which could lead to man-in-the-middle attacks or other security vulnerabilities when communicating with remote systems.\n    cwe: CWE-295\n    function_names: []\n    filenames: []\n    classification: not promising\n\n  - headline: Insecure Session Management\n    analysis: |\n      The codebase does not appear to have any session management mechanisms, which could lead to security vulnerabilities like session fixation or session hijacking.\n    cwe: CWE-613\n    function_names: []\n    filenames: []\n    classification: not promising\n```",
      "date": "2024-06-13T10:04:54.423077",
      "usage": {
        "prompt_tokens": 32819,
        "completion_tokens": 549,
        "cost": 0.008891
      }
    }
  ],
  "leads": [
    {
      "headline": "Improper Validation of Input",
      "analysis": "The codebase does not properly validate user input, which could lead to security vulnerabilities such as command injection, SQL injection, or other injection-based attacks. This is a common issue that occurs when user-supplied data is not properly sanitized or validated before being used in operations like file paths, system commands, or database queries.\n",
      "classification": "slightly promising",
      "cwe": "CWE-20",
      "function_names": [
        "nodepath",
        "edgevar"
      ],
      "filenames": [
        "util.c",
        "env.c"
      ]
    },
    {
      "headline": "Weak Cryptographic Algorithm",
      "analysis": "The codebase uses the murmurhash64a function to generate hashes, which is not a cryptographically secure hash algorithm. This could lead to security vulnerabilities if the hashes are used for sensitive operations like authentication or access control.\n",
      "classification": "slightly promising",
      "cwe": "CWE-327",
      "function_names": [
        "murmurhash64a"
      ],
      "filenames": [
        "htab.c"
      ]
    },
    {
      "headline": "Insecure File Operations",
      "analysis": "The codebase performs various file operations, such as reading and writing files, without properly handling error conditions or checking for race conditions. This could lead to security vulnerabilities like directory traversal, file overwrite, or other file-based attacks.\n",
      "classification": "slightly promising",
      "cwe": "CWE-404",
      "function_names": [
        "writefile",
        "makedirs"
      ],
      "filenames": [
        "util.c"
      ]
    },
    {
      "headline": "Improper Certificate Validation",
      "analysis": "The codebase does not appear to perform any certificate validation, which could lead to man-in-the-middle attacks or other security vulnerabilities when communicating with remote systems.\n",
      "classification": "not promising",
      "cwe": "CWE-295",
      "function_names": [],
      "filenames": []
    },
    {
      "headline": "Insecure Session Management",
      "analysis": "The codebase does not appear to have any session management mechanisms, which could lead to security vulnerabilities like session fixation or session hijacking.\n",
      "classification": "not promising",
      "cwe": "CWE-613",
      "function_names": [],
      "filenames": []
    }
  ],
  "scores": [
    {
      "stats": {
        "fn": 1,
        "tp": 0,
        "fp": 0
      },
      "mapping": {},
      "vuln_dates": {
        "CVE-2019-19795": "2019-12-13T22:15:11"
      },
      "scoring_model": "claude-3-opus-20240229",
      "type": "llm",
      "instruction_template_hash": "245ace12b6361954d0a2"
    }
  ],
  "instruction_template_hash": "10c0163db4740318a544",
  "version": "0.1.0"
}
