{
  "commit": "48fe028f3ea4b3e7544f03bce21ed6c93320abd4",
  "repo_url": "https://github.com/mayankmetha/rucky",
  "model": "gpt-4-turbo-2024-04-09",
  "chunk_hashes": [
    "e4f0e4e8d0741e6f0983"
  ],
  "responses": [
    {
      "content": "```yaml\nleads:\n  - headline: \"Insecure Key Generation\"\n    analysis: |\n      The application utilizes a custom key generation technique that lacks adherence to security best practices. It employs insecure PRNG (Pseudo-Random Number Generator) for key creation processes and fails to ensure the randomness and complexity required for cryptographic keys which are critical in keeping encrypted communications secure.\n    cwe: CWE-331\n    function_names:\n      - getKey \n      - generateHash \n    filenames:\n      - app/src/main/java/com/mayank/rucky/activity/UpdateActivity.java \n      - app/src/main/java/com/mayank/rucky/utils/Config.java\n    classification: \"very promising\"\n\n  - headline: \"Insecure Data Storage without integrity check\"\n    analysis: |\n      Configuration settings and key information are stored unencrypted, without maintaining integrity checks. This allows attackers to modify or spoof configuration settings or cryptographic keys, which could lead to unauthorized actions or data breaches.\n    cfe: CWE-311\n    function_names:\n      - getKeyStore1 \n      - getKeyStore2 \n      - setKeyStore1 \n      - setKeyStore2\n    filenames:\n      - app/src/main/java/com/mayank/rucky/utils/Config.java\n    classification: \"very promising\"\n\n  - headline: \"Command Injection via shell execution\"\n    analysis: |\n      Shell commands are constructed using user input without adequate sanitization. This can allow an attacker to inject arbitrary commands that the application will execute with its own privileges, potentially leading to unauthorized access or information disclosure.\n    cwe: CWE-77\n    function_names:\n      - parse\n    filenames:\n      - app/src/main/java/com/mayank/rucky/utils/HID2.java\n    classification: \"very promising\"\n\n  - headline: \"Hardcoded Encryption Keys\"\n    analysis: |\n      The application uses hardcoded cryptographic keys for encrypting configuration settings, which could be extracted from the application and used to decrypt sensitive information.\n    cwe: CWE-321\n    function_names:\n      - getKey\n    filenames:\n      - app/src/main/java/com/mayank/rucky/activity/SettingsActivity.java\n    classification: \"very promising\"\n\n  - headline: \"Lack of proper error handling in network requests\"\n    analysis: |\n      The application fails to handle errors adequately when network requests fail or when invalid responses are received. This can lead to the application crashing or behaving unpredictably, which can be utilized by an attacker to carry out denial of service attacks.\n    cwe: CWE-754\n    function_names:\n      - getNewAppVersion\n    filenames:\n      - app/src/main/java/com/mayank/rucky/activity/EditorActivity.java\n    classification: \"slightly promising\"\n```",
      "date": "2024-06-14T14:47:50.365669",
      "usage": {
        "prompt_tokens": 37089,
        "completion_tokens": 560,
        "cost": 0.38769
      }
    }
  ],
  "leads": [
    {
      "headline": "Insecure Key Generation",
      "analysis": "The application utilizes a custom key generation technique that lacks adherence to security best practices. It employs insecure PRNG (Pseudo-Random Number Generator) for key creation processes and fails to ensure the randomness and complexity required for cryptographic keys which are critical in keeping encrypted communications secure.\n",
      "classification": "very promising",
      "cwe": "CWE-331",
      "function_names": [
        "getKey",
        "generateHash"
      ],
      "filenames": [
        "app/src/main/java/com/mayank/rucky/activity/UpdateActivity.java",
        "app/src/main/java/com/mayank/rucky/utils/Config.java"
      ]
    },
    {
      "headline": "Insecure Data Storage without integrity check",
      "analysis": "Configuration settings and key information are stored unencrypted, without maintaining integrity checks. This allows attackers to modify or spoof configuration settings or cryptographic keys, which could lead to unauthorized actions or data breaches.\n",
      "classification": "very promising",
      "cwe": null,
      "function_names": [
        "getKeyStore1",
        "getKeyStore2",
        "setKeyStore1"
      ],
      "filenames": [
        "app/src/main/java/com/mayank/rucky/utils/Config.java"
      ]
    },
    {
      "headline": "Command Injection via shell execution",
      "analysis": "Shell commands are constructed using user input without adequate sanitization. This can allow an attacker to inject arbitrary commands that the application will execute with its own privileges, potentially leading to unauthorized access or information disclosure.\n",
      "classification": "very promising",
      "cwe": "CWE-77",
      "function_names": [
        "parse"
      ],
      "filenames": [
        "app/src/main/java/com/mayank/rucky/utils/HID2.java"
      ]
    },
    {
      "headline": "Hardcoded Encryption Keys",
      "analysis": "The application uses hardcoded cryptographic keys for encrypting configuration settings, which could be extracted from the application and used to decrypt sensitive information.\n",
      "classification": "very promising",
      "cwe": "CWE-321",
      "function_names": [
        "getKey"
      ],
      "filenames": [
        "app/src/main/java/com/mayank/rucky/activity/SettingsActivity.java"
      ]
    },
    {
      "headline": "Lack of proper error handling in network requests",
      "analysis": "The application fails to handle errors adequately when network requests fail or when invalid responses are received. This can lead to the application crashing or behaving unpredictably, which can be utilized by an attacker to carry out denial of service attacks.\n",
      "classification": "slightly promising",
      "cwe": "CWE-754",
      "function_names": [
        "getNewAppVersion"
      ],
      "filenames": [
        "app/src/main/java/com/mayank/rucky/activity/EditorActivity.java"
      ]
    }
  ],
  "scores": [
    {
      "stats": {
        "fn": 1,
        "tp": 0,
        "fp": 4
      },
      "mapping": {},
      "vuln_dates": {
        "CVE-2021-41096": "2021-09-27T20:15:07"
      },
      "scoring_model": "claude-3-opus-20240229",
      "type": "llm",
      "instruction_template_hash": "245ace12b6361954d0a2"
    },
    {
      "stats": {
        "fn": 1,
        "tp": 0,
        "fp": 4
      },
      "mapping": {},
      "vuln_dates": {
        "CVE-2021-41096": "2021-09-27T20:15:07"
      },
      "scoring_model": "claude-3-5-sonnet-20240620",
      "type": "llm",
      "instruction_template_hash": "245ace12b6361954d0a2"
    }
  ],
  "instruction_template_hash": "10c0163db4740318a544",
  "version": "0.1.0"
}
