{
  "commit": "49c6003f3259be3105995a8034510061c64dff16",
  "repo_url": "https://github.com/starkbank/ecdsa-node",
  "model": "claude-3-haiku-20240307",
  "chunk_hashes": [
    "2d1479fc1b59536285bb"
  ],
  "responses": [
    {
      "content": "```yaml\nleads:\n  - headline: Improper Input Validation\n    analysis: |\n      The code appears to lack proper input validation, which could lead to vulnerabilities such as integer overflow or wraparound (CWE-190), buffer overflows (CWE-120), and other types of input-related issues. Specific areas of concern include the handling of user-provided input, such as message data, file paths, and other parameters passed to the ECDSA-related functions. Malformed or crafted input could potentially allow attackers to bypass security checks, access sensitive information, or execute arbitrary code.\n    cwe: CWE-20\n    function_names:\n      - Ecdsa.sign\n      - Ecdsa.verify\n    filenames:\n      - ellipticcurve/ecdsa.js\n    classification: slightly promising\n\n  - headline: Unsafe Reflection\n    analysis: |\n      The code uses `require()` to dynamically load modules, which could potentially be abused to load and execute untrusted code (CWE-470). Attackers could potentially provide crafted input that leads to the loading of malicious modules, potentially allowing them to execute arbitrary code or gain unauthorized access to sensitive information.\n    cwe: CWE-470\n    function_names:\n      - require\n    filenames:\n      - index.js\n    classification: slightly promising\n\n  - headline: Deserialization of Untrusted Data\n    analysis: |\n      The code appears to use deserialization of user-provided data, such as in the `PrivateKey.fromDer()` and `PublicKey.fromDer()` functions. Deserialization of untrusted data can lead to code execution vulnerabilities (CWE-502) if the deserialization process is not properly secured and validated.\n    cwe: CWE-502\n    function_names:\n      - PrivateKey.fromDer\n      - PublicKey.fromDer\n    filenames:\n      - ellipticcurve/privateKey.js\n      - ellipticcurve/publicKey.js\n    classification: slightly promising\n\n  - headline: Incorrect Default Permissions\n    analysis: |\n      The code reads and writes files, such as in the `File.read()` function, without properly validating the permissions of the files being accessed. This could lead to issues where sensitive information is exposed or modified by unauthorized parties (CWE-276).\n    cwe: CWE-276\n    function_names:\n      - File.read\n    filenames:\n      - ellipticcurve/utils/file.js\n    classification: slightly promising\n\n  - headline: Improper Neutralization of Input During Web Page Generation\n    analysis: |\n      The code appears to handle user-provided input, such as messages, without properly sanitizing or validating the input. This could lead to cross-site scripting (XSS) vulnerabilities (CWE-79) if the input is not properly encoded or sanitized before being used in web page generation or output.\n    cwe: CWE-79\n    function_names:\n      - Ecdsa.sign\n      - Ecdsa.verify\n    filenames:\n      - ellipticcurve/ecdsa.js\n    classification: slightly promising\n```",
      "date": "2024-07-08T08:44:49.058638",
      "usage": {
        "prompt_tokens": 16662,
        "completion_tokens": 761,
        "cost": 0.00511675
      }
    }
  ],
  "leads": [
    {
      "headline": "Improper Input Validation",
      "analysis": "The code appears to lack proper input validation, which could lead to vulnerabilities such as integer overflow or wraparound (CWE-190), buffer overflows (CWE-120), and other types of input-related issues. Specific areas of concern include the handling of user-provided input, such as message data, file paths, and other parameters passed to the ECDSA-related functions. Malformed or crafted input could potentially allow attackers to bypass security checks, access sensitive information, or execute arbitrary code.\n",
      "classification": "slightly promising",
      "cwe": "CWE-20",
      "function_names": [
        "Ecdsa.sign",
        "Ecdsa.verify"
      ],
      "filenames": [
        "ellipticcurve/ecdsa.js"
      ]
    },
    {
      "headline": "Unsafe Reflection",
      "analysis": "The code uses require() to dynamically load modules, which could potentially be abused to load and execute untrusted code (CWE-470). Attackers could potentially provide crafted input that leads to the loading of malicious modules, potentially allowing them to execute arbitrary code or gain unauthorized access to sensitive information.\n",
      "classification": "slightly promising",
      "cwe": "CWE-470",
      "function_names": [
        "require"
      ],
      "filenames": [
        "index.js"
      ]
    },
    {
      "headline": "Deserialization of Untrusted Data",
      "analysis": "The code appears to use deserialization of user-provided data, such as in the PrivateKey.fromDer() and PublicKey.fromDer() functions. Deserialization of untrusted data can lead to code execution vulnerabilities (CWE-502) if the deserialization process is not properly secured and validated.\n",
      "classification": "slightly promising",
      "cwe": "CWE-502",
      "function_names": [
        "PrivateKey.fromDer",
        "PublicKey.fromDer"
      ],
      "filenames": [
        "ellipticcurve/privateKey.js",
        "ellipticcurve/publicKey.js"
      ]
    },
    {
      "headline": "Incorrect Default Permissions",
      "analysis": "The code reads and writes files, such as in the File.read() function, without properly validating the permissions of the files being accessed. This could lead to issues where sensitive information is exposed or modified by unauthorized parties (CWE-276).\n",
      "classification": "slightly promising",
      "cwe": "CWE-276",
      "function_names": [
        "File.read"
      ],
      "filenames": [
        "ellipticcurve/utils/file.js"
      ]
    },
    {
      "headline": "Improper Neutralization of Input During Web Page Generation",
      "analysis": "The code appears to handle user-provided input, such as messages, without properly sanitizing or validating the input. This could lead to cross-site scripting (XSS) vulnerabilities (CWE-79) if the input is not properly encoded or sanitized before being used in web page generation or output.\n",
      "classification": "slightly promising",
      "cwe": "CWE-79",
      "function_names": [
        "Ecdsa.sign",
        "Ecdsa.verify"
      ],
      "filenames": [
        "ellipticcurve/ecdsa.js"
      ]
    }
  ],
  "scores": [
    {
      "stats": {
        "fn": 1,
        "tp": 0,
        "fp": 0
      },
      "mapping": {},
      "vuln_dates": {
        "CVE-2021-43571": "2021-11-09T22:15:07"
      },
      "scoring_model": "claude-3-5-sonnet-20240620",
      "type": "llm",
      "instruction_template_hash": "245ace12b6361954d0a2"
    }
  ],
  "instruction_template_hash": "10c0163db4740318a544",
  "version": "0.1.0"
}
