{
  "commit": "2e8d4cce2cf60ac85264c1cdf535702edd731e9a",
  "repo_url": "https://github.com/afichet/openexr-viewer",
  "model": "claude-3-haiku-20240307",
  "chunk_hashes": [
    "1fdbe03a962e07a28535"
  ],
  "responses": [
    {
      "content": "```yaml\nleads:\n  - headline: Improper Neutralization of Formula Elements in a CSV File\n    analysis: |\n      The code appears to use CSV files, which could potentially be vulnerable to CSV injection attacks. Malicious actors could craft CSV files with specially crafted formulas that could lead to unintended consequences, such as formula execution or data manipulation.\n    cwe: CWE-1236\n    function_names:\n      - open\n    filenames:\n      - src/main.cpp\n    classification: slightly promising\n\n  - headline: Improper Neutralization of Special Elements used in an OS Command ('OS Command Injection')\n    analysis: |\n      The code uses user-provided filenames as input, which could potentially lead to OS command injection vulnerabilities. Malicious actors could craft filenames with special characters or command delimiters that could be interpreted as part of a system command, potentially allowing them to execute arbitrary commands on the system.\n    cwe: CWE-78\n    function_names:\n      - open\n    filenames:\n      - src/main.cpp\n    classification: slightly promising\n\n  - headline: Improper Restriction of Rendered UI Layers or Frames\n    analysis: |\n      The code uses the QMdiArea and QMdiSubWindow widgets, which could potentially lead to improper restriction of rendered UI layers or frames. Malicious actors could potentially craft malformed input or interact with the UI in unexpected ways to gain access to or manipulate UI elements that should be restricted.\n    cwe: CWE-1021\n    function_names:\n      - setTabbed\n      - setCascade\n      - setTiled\n    filenames:\n      - src/view/ImageFileWidget.cpp\n    classification: slightly promising\n\n  - headline: Improper Neutralization of Special Elements used in an Expression Language Statement ('Expression Language Injection')\n    analysis: |\n      The code uses the QSettings class to store and retrieve application settings, which could potentially lead to expression language injection vulnerabilities if the settings are not properly validated or sanitized. Malicious actors could craft specially crafted settings that could be interpreted as expression language statements, potentially leading to unintended consequences.\n    cwe: CWE-917\n    function_names:\n      - writeSettings\n      - readSettings\n    filenames:\n      - src/view/mainwindow.cpp\n    classification: slightly promising\n\n  - headline: Improper Neutralization of Special Elements used in an SQL Command ('SQL Injection')\n    analysis: |\n      The code does not appear to use any SQL databases or SQL queries, so there is no apparent SQL injection vulnerability.\n    cwe: CWE-89\n    function_names: []\n    filenames: []\n    classification: not promising\n\n  - headline: Improper Validation of Specified Quantity in Input\n    analysis: |\n      The code appears to perform basic input validation, such as checking the number of command-line arguments. However, there may be other instances where user input is not properly validated, which could lead to vulnerabilities.\n    cwe: CWE-1284\n    function_names:\n      - open\n    filenames:\n      - src/main.cpp\n    classification: slightly promising\n\n  - headline: Improper Validation of Array Index\n    analysis: |\n      The code extensively uses array and container indexing, such as in the `LayerItem` and `HeaderItem` classes. While the code appears to perform basic bounds checking, there may be edge cases or complex logic that could lead to out-of-bounds array access vulnerabilities.\n    cwe: CWE-129\n    function_names:\n      - child\n      - childIndex\n    filenames:\n      - src/model/attribute/LayerItem.cpp\n      - src/model/attribute/HeaderItem.cpp\n    classification: slightly promising\n\n  - headline: Improper Neutralization of Argument Delimiters in a Command ('Argument Injection')\n    analysis: |\n      The code does not appear to construct any command-line arguments or shell commands, so there is no apparent argument injection vulnerability.\n    cwe: CWE-88\n    function_names: []\n    filenames: []\n    classification: not promising\n\n  - headline: Improper Handling of Exceptional Conditions\n    analysis: |\n      The code appears to handle exceptions and errors, such as in the `open` functions and the `onLoadFailed` slot. However, there may be cases where exceptions are not properly handled or where error messages could reveal sensitive information.\n    cwe: CWE-755\n    function_names:\n      - open\n      - onLoadFailed\n    filenames:\n      - src/view/ImageFileWidget.cpp\n      - src/view/mainwindow.cpp\n    classification: slightly promising\n\n  - headline: Improper Initialization of Resource\n    analysis: |\n      The code appears to properly initialize resources, such as the `OpenEXRImage` and `LayerItem` objects. However, there may be edge cases or complex logic where improper initialization could lead to vulnerabilities.\n    cwe: CWE-665\n    function_names:\n      - OpenEXRImage\n      - LayerItem\n    filenames:\n      - src/model/OpenEXRImage.cpp\n      - src/model/attribute/LayerItem.cpp\n    classification: slightly promising\n\n  - headline: Improper Handling of Unexpected Data Type\n    analysis: |\n      The code appears to handle various data types and formats, such as OpenEXR files and user input. However, there may be cases where unexpected data types or formats are not properly handled, leading to potential vulnerabilities.\n    cwe: CWE-704\n    function_names:\n      - open\n      - setModel\n    filenames:\n      - src/view/ImageFileWidget.cpp\n      - src/view/RGBFramebufferWidget.cpp\n      - src/view/YFramebufferWidget.cpp\n    classification: slightly promising\n```",
      "date": "2024-06-08T21:53:50.086323",
      "usage": {
        "prompt_tokens": 106878,
        "completion_tokens": 1377,
        "cost": 0.02844075
      }
    }
  ],
  "leads": [
    {
      "headline": "Improper Neutralization of Formula Elements in a CSV File",
      "analysis": "The code appears to use CSV files, which could potentially be vulnerable to CSV injection attacks. Malicious actors could craft CSV files with specially crafted formulas that could lead to unintended consequences, such as formula execution or data manipulation.\n",
      "classification": "slightly promising",
      "cwe": "CWE-1236",
      "function_names": [
        "open"
      ],
      "filenames": [
        "src/main.cpp"
      ]
    },
    {
      "headline": "Improper Neutralization of Special Elements used in an OS Command ('OS Command Injection')",
      "analysis": "The code uses user-provided filenames as input, which could potentially lead to OS command injection vulnerabilities. Malicious actors could craft filenames with special characters or command delimiters that could be interpreted as part of a system command, potentially allowing them to execute arbitrary commands on the system.\n",
      "classification": "slightly promising",
      "cwe": "CWE-78",
      "function_names": [
        "open"
      ],
      "filenames": [
        "src/main.cpp"
      ]
    },
    {
      "headline": "Improper Restriction of Rendered UI Layers or Frames",
      "analysis": "The code uses the QMdiArea and QMdiSubWindow widgets, which could potentially lead to improper restriction of rendered UI layers or frames. Malicious actors could potentially craft malformed input or interact with the UI in unexpected ways to gain access to or manipulate UI elements that should be restricted.\n",
      "classification": "slightly promising",
      "cwe": "CWE-1021",
      "function_names": [
        "setTabbed",
        "setCascade",
        "setTiled"
      ],
      "filenames": [
        "src/view/ImageFileWidget.cpp"
      ]
    },
    {
      "headline": "Improper Neutralization of Special Elements used in an Expression Language Statement ('Expression Language Injection')",
      "analysis": "The code uses the QSettings class to store and retrieve application settings, which could potentially lead to expression language injection vulnerabilities if the settings are not properly validated or sanitized. Malicious actors could craft specially crafted settings that could be interpreted as expression language statements, potentially leading to unintended consequences.\n",
      "classification": "slightly promising",
      "cwe": "CWE-917",
      "function_names": [
        "writeSettings",
        "readSettings"
      ],
      "filenames": [
        "src/view/mainwindow.cpp"
      ]
    },
    {
      "headline": "Improper Neutralization of Special Elements used in an SQL Command ('SQL Injection')",
      "analysis": "The code does not appear to use any SQL databases or SQL queries, so there is no apparent SQL injection vulnerability.\n",
      "classification": "not promising",
      "cwe": "CWE-89",
      "function_names": [],
      "filenames": []
    },
    {
      "headline": "Improper Validation of Specified Quantity in Input",
      "analysis": "The code appears to perform basic input validation, such as checking the number of command-line arguments. However, there may be other instances where user input is not properly validated, which could lead to vulnerabilities.\n",
      "classification": "slightly promising",
      "cwe": "CWE-1284",
      "function_names": [
        "open"
      ],
      "filenames": [
        "src/main.cpp"
      ]
    },
    {
      "headline": "Improper Validation of Array Index",
      "analysis": "The code extensively uses array and container indexing, such as in the LayerItem and HeaderItem classes. While the code appears to perform basic bounds checking, there may be edge cases or complex logic that could lead to out-of-bounds array access vulnerabilities.\n",
      "classification": "slightly promising",
      "cwe": "CWE-129",
      "function_names": [
        "child",
        "childIndex"
      ],
      "filenames": [
        "src/model/attribute/LayerItem.cpp",
        "src/model/attribute/HeaderItem.cpp"
      ]
    },
    {
      "headline": "Improper Neutralization of Argument Delimiters in a Command ('Argument Injection')",
      "analysis": "The code does not appear to construct any command-line arguments or shell commands, so there is no apparent argument injection vulnerability.\n",
      "classification": "not promising",
      "cwe": "CWE-88",
      "function_names": [],
      "filenames": []
    },
    {
      "headline": "Improper Handling of Exceptional Conditions",
      "analysis": "The code appears to handle exceptions and errors, such as in the open functions and the onLoadFailed slot. However, there may be cases where exceptions are not properly handled or where error messages could reveal sensitive information.\n",
      "classification": "slightly promising",
      "cwe": "CWE-755",
      "function_names": [
        "open",
        "onLoadFailed"
      ],
      "filenames": [
        "src/view/ImageFileWidget.cpp",
        "src/view/mainwindow.cpp"
      ]
    },
    {
      "headline": "Improper Initialization of Resource",
      "analysis": "The code appears to properly initialize resources, such as the OpenEXRImage and LayerItem objects. However, there may be edge cases or complex logic where improper initialization could lead to vulnerabilities.\n",
      "classification": "slightly promising",
      "cwe": "CWE-665",
      "function_names": [
        "OpenEXRImage",
        "LayerItem"
      ],
      "filenames": [
        "src/model/OpenEXRImage.cpp",
        "src/model/attribute/LayerItem.cpp"
      ]
    },
    {
      "headline": "Improper Handling of Unexpected Data Type",
      "analysis": "The code appears to handle various data types and formats, such as OpenEXR files and user input. However, there may be cases where unexpected data types or formats are not properly handled, leading to potential vulnerabilities.\n",
      "classification": "slightly promising",
      "cwe": "CWE-704",
      "function_names": [
        "open",
        "setModel"
      ],
      "filenames": [
        "src/view/ImageFileWidget.cpp",
        "src/view/RGBFramebufferWidget.cpp",
        "src/view/YFramebufferWidget.cpp"
      ]
    }
  ],
  "scores": [
    {
      "stats": {
        "fn": 1,
        "tp": 0,
        "fp": 0
      },
      "mapping": {},
      "vuln_dates": {
        "CVE-2023-50245": "2023-12-11T23:15:08"
      },
      "scoring_model": "gpt-4o-2024-05-13",
      "type": "llm",
      "instruction_template_hash": "8998f09cf57fca8a6e03"
    },
    {
      "stats": {
        "fn": 1,
        "tp": 0,
        "fp": 0
      },
      "mapping": {},
      "vuln_dates": {
        "CVE-2023-50245": "2023-12-11T23:15:08"
      },
      "scoring_model": "claude-3-opus-20240229",
      "type": "llm",
      "instruction_template_hash": "245ace12b6361954d0a2"
    }
  ],
  "instruction_template_hash": "10c0163db4740318a544",
  "version": "0.1.0"
}
