{
  "commit": "46f66a9e091f752ed74dade8101ea4f201a95b5e",
  "repo_url": "https://github.com/operatorequals/wormnest",
  "model": "claude-3-5-sonnet-20240620",
  "chunk_hashes": [
    "2ac50fb19139ae7e0977"
  ],
  "responses": [
    {
      "content": "```yaml\nleads:\n  - headline: Command Injection vulnerability in file upload functionality\n    analysis: |\n      The file_upload function in app.py uses os.system() to execute a shell command with user-controlled input. The 'filename' variable is derived from user input and passed directly to os.system() without any sanitization or escaping. This allows an attacker to inject arbitrary OS commands by uploading a file with a specially crafted filename containing shell metacharacters.\n    cwe: CWE-78\n    function_names:\n      - file_upload\n    filenames:\n      - app.py\n    classification: very promising\n\n  - headline: Arbitrary file read via path traversal\n    analysis: |\n      The dir_listing function in app.py joins the user-supplied req_path parameter with the SRV_DIR base directory without proper sanitization. This allows an attacker to use path traversal sequences (e.g. ../) to access files outside of the intended directory, potentially exposing sensitive system files.\n    cwe: CWE-22  \n    function_names:\n      - dir_listing\n    filenames:\n      - app.py\n    classification: very promising\n\n  - headline: SQL Injection in database queries\n    analysis: |\n      The get_path function in db_handler.py constructs SQL queries using string formatting with user-supplied input (the alias parameter). This allows for potential SQL injection attacks if the alias contains malicious SQL fragments. The query should use parameterized queries instead of string formatting to properly escape user input.\n    cwe: CWE-89\n    function_names:\n      - get_path\n    filenames:\n      - wormnest/db_handler.py  \n    classification: very promising\n\n  - headline: Insecure deserialization of user-supplied JSON data\n    analysis: |\n      The autogen_msf hook in hooks/autogen_msf.py uses subprocess.run() to execute msfvenom with shell=True and user-controlled input. An attacker could potentially exploit this to execute arbitrary commands by injecting shell metacharacters into the filename or other parameters passed to msfvenom.\n    cwe: CWE-78\n    function_names:\n      - autogen_msf \n    filenames:\n      - hooks/autogen_msf.py\n    classification: very promising\n\n  - headline: Information exposure through error messages\n    analysis: |\n      The application returns detailed error messages and stack traces in several places, such as in the custom_error.html template. This can provide attackers with sensitive information about the application's internals and structure, aiding in further attacks.\n    cwe: CWE-209\n    function_names: []\n    filenames:\n      - templates/custom_error.html\n    classification: slightly promising\n\n  - headline: Use of hard-coded credentials\n    analysis: |\n      The autogen_msf hook in hooks/autogen_msf.py contains hard-coded IP addresses and ports for the C2 server. While these appear to be localhost values likely used for testing, hard-coding such values is generally a bad practice as it can lead to accidental exposure of real C2 infrastructure if not properly updated before deployment.\n    cwe: CWE-798\n    function_names:\n      - autogen_msf\n    filenames:  \n      - hooks/autogen_msf.py\n    classification: slightly promising\n```",
      "date": "2024-07-08T08:09:23.583772",
      "usage": {
        "prompt_tokens": 14169,
        "completion_tokens": 782,
        "cost": 0.054237
      }
    }
  ],
  "leads": [
    {
      "headline": "Command Injection vulnerability in file upload functionality",
      "analysis": "The file_upload function in app.py uses os.system() to execute a shell command with user-controlled input. The 'filename' variable is derived from user input and passed directly to os.system() without any sanitization or escaping. This allows an attacker to inject arbitrary OS commands by uploading a file with a specially crafted filename containing shell metacharacters.\n",
      "classification": "very promising",
      "cwe": "CWE-78",
      "function_names": [
        "file_upload"
      ],
      "filenames": [
        "app.py"
      ]
    },
    {
      "headline": "Arbitrary file read via path traversal",
      "analysis": "The dir_listing function in app.py joins the user-supplied req_path parameter with the SRV_DIR base directory without proper sanitization. This allows an attacker to use path traversal sequences (e.g. ../) to access files outside of the intended directory, potentially exposing sensitive system files.\n",
      "classification": "very promising",
      "cwe": "CWE-22",
      "function_names": [
        "dir_listing"
      ],
      "filenames": [
        "app.py"
      ]
    },
    {
      "headline": "SQL Injection in database queries",
      "analysis": "The get_path function in db_handler.py constructs SQL queries using string formatting with user-supplied input (the alias parameter). This allows for potential SQL injection attacks if the alias contains malicious SQL fragments. The query should use parameterized queries instead of string formatting to properly escape user input.\n",
      "classification": "very promising",
      "cwe": "CWE-89",
      "function_names": [
        "get_path"
      ],
      "filenames": [
        "wormnest/db_handler.py"
      ]
    },
    {
      "headline": "Insecure deserialization of user-supplied JSON data",
      "analysis": "The autogen_msf hook in hooks/autogen_msf.py uses subprocess.run() to execute msfvenom with shell=True and user-controlled input. An attacker could potentially exploit this to execute arbitrary commands by injecting shell metacharacters into the filename or other parameters passed to msfvenom.\n",
      "classification": "very promising",
      "cwe": "CWE-78",
      "function_names": [
        "autogen_msf"
      ],
      "filenames": [
        "hooks/autogen_msf.py"
      ]
    },
    {
      "headline": "Information exposure through error messages",
      "analysis": "The application returns detailed error messages and stack traces in several places, such as in the custom_error.html template. This can provide attackers with sensitive information about the application's internals and structure, aiding in further attacks.\n",
      "classification": "slightly promising",
      "cwe": "CWE-209",
      "function_names": [],
      "filenames": [
        "templates/custom_error.html"
      ]
    },
    {
      "headline": "Use of hard-coded credentials",
      "analysis": "The autogen_msf hook in hooks/autogen_msf.py contains hard-coded IP addresses and ports for the C2 server. While these appear to be localhost values likely used for testing, hard-coding such values is generally a bad practice as it can lead to accidental exposure of real C2 infrastructure if not properly updated before deployment.\n",
      "classification": "slightly promising",
      "cwe": "CWE-798",
      "function_names": [
        "autogen_msf"
      ],
      "filenames": [
        "hooks/autogen_msf.py"
      ]
    }
  ],
  "scores": [
    {
      "stats": {
        "fn": 0,
        "tp": 1,
        "fp": 3
      },
      "mapping": {
        "1": "CVE-2022-31502"
      },
      "vuln_dates": {
        "CVE-2022-31502": "2022-07-11T01:15:08"
      },
      "scoring_model": "claude-3-5-sonnet-20240620",
      "type": "llm",
      "instruction_template_hash": "245ace12b6361954d0a2"
    }
  ],
  "instruction_template_hash": "10c0163db4740318a544",
  "version": "0.1.0"
}
