{
  "commit": "235a1945749f88f040354596f7adff353ff72522",
  "repo_url": "https://github.com/jenkinsci/fabric-beta-publisher-plugin",
  "model": "gpt-4o-2024-05-13",
  "chunk_hashes": [
    "905b991a16ff1dbb5f26"
  ],
  "responses": [
    {
      "content": "```yaml\nleads:\n  - headline: \"Command Injection in CommandRunner.runCommand()\"\n    analysis: |\n      The `runCommand` method spawns a new process by passing a list of command strings to `ProcessBuilder`. If any element of the `command` list includes user-specified input, it could lead to command injection. An attacker could execute arbitrary commands on the server if they manage to control or influence the content of that list.\n    cwe: CWE-78\n    function_names:\n      - runCommand\n    filenames:\n      - src/main/java/fabric/beta/publisher/CommandRunner.java\n    classification: very promising\n\n  - headline: \"Uncontrolled Resource Consumption in FileUtils.createTempDirectory()\"\n    analysis: |\n      The `createTempDirectory` method creates a temporary directory, but there is no mechanism in place to limit the number of directories created or clean them up afterward. This could lead to uncontrolled consumption of file system resources, potentially leading to a denial of service (DoS) condition.\n    cwe: CWE-400\n    function_names:\n      - createTempDirectory\n    filenames:\n      - src/main/java/fabric/beta/publisher/FileUtils.java\n    classification: slightly promising\n\n  - headline: \"Improper Handling of Sensitive Data in EnvVarsAction\"\n    analysis: |\n      The `EnvVarsAction` class prints potentially sensitive environment variables to the logger. Additionally, it stores these variables in a HashMap, which could be accessed without proper security controls. This can expose sensitive information to unauthorized actors.\n    cwe: CWE-200\n    function_names:\n      - add\n    filenames:\n      - src/main/java/fabric/beta/publisher/EnvVarsAction.java\n    classification: very promising\n\n  - headline: \"Use of Hard-coded Credentials in FabricApi\"\n    analysis: |\n      The `FabricApi` class includes a base URL in the `retrofit` method, which can be considered a form of hard-coded configuration. If this base URL eventually includes API keys or secrets, it may lead to security risks.\n    cwe: CWE-798\n    function_names:\n      - retrofit\n    filenames:\n      - src/main/java/fabric/beta/publisher/FabricApi.java\n    classification: slightly promising\n\n  - headline: \"Possible Use of Insecure Hashing Algorithm in AppRelease.from\"\n    analysis: |\n      The `AppRelease.from` method handles APK files but lacks explicit checks for cryptographic context. If the properties file it processes includes sensitive information, the absence of a strong cryptographic hash function could be problematic.\n    cwe: CWE-327\n    function_names:\n      - from\n    filenames:\n      - src/main/java/fabric/beta/publisher/AppRelease.java\n    classification: slightly promising\n\n  - headline: \"Improper Neutralization of Special Elements used in an Argument ('Argument Injection') in FabricBetaPublisher.buildCrashlyticsCommand()\"\n    analysis: |\n      The `buildCrashlyticsCommand` method constructs a command to be executed using elements derived from environment variables or user input. This may allow for argument injection if those variables contain special characters or argument delimiters, which are not properly sanitized.\n    cwe: CWE-88\n    function_names:\n      - buildCrashlyticsCommand\n    filenames:\n      - src/main/java/fabric/beta/publisher/FabricBetaPublisher.java\n    classification: very promising\n```",
      "date": "2024-06-12T18:24:09.445626",
      "usage": {
        "prompt_tokens": 8773,
        "completion_tokens": 705,
        "cost": 0.05444
      }
    }
  ],
  "leads": [
    {
      "headline": "Command Injection in CommandRunner.runCommand()",
      "analysis": "The runCommand method spawns a new process by passing a list of command strings to ProcessBuilder. If any element of the command list includes user-specified input, it could lead to command injection. An attacker could execute arbitrary commands on the server if they manage to control or influence the content of that list.\n",
      "classification": "very promising",
      "cwe": "CWE-78",
      "function_names": [
        "runCommand"
      ],
      "filenames": [
        "src/main/java/fabric/beta/publisher/CommandRunner.java"
      ]
    },
    {
      "headline": "Uncontrolled Resource Consumption in FileUtils.createTempDirectory()",
      "analysis": "The createTempDirectory method creates a temporary directory, but there is no mechanism in place to limit the number of directories created or clean them up afterward. This could lead to uncontrolled consumption of file system resources, potentially leading to a denial of service (DoS) condition.\n",
      "classification": "slightly promising",
      "cwe": "CWE-400",
      "function_names": [
        "createTempDirectory"
      ],
      "filenames": [
        "src/main/java/fabric/beta/publisher/FileUtils.java"
      ]
    },
    {
      "headline": "Improper Handling of Sensitive Data in EnvVarsAction",
      "analysis": "The EnvVarsAction class prints potentially sensitive environment variables to the logger. Additionally, it stores these variables in a HashMap, which could be accessed without proper security controls. This can expose sensitive information to unauthorized actors.\n",
      "classification": "very promising",
      "cwe": "CWE-200",
      "function_names": [
        "add"
      ],
      "filenames": [
        "src/main/java/fabric/beta/publisher/EnvVarsAction.java"
      ]
    },
    {
      "headline": "Use of Hard-coded Credentials in FabricApi",
      "analysis": "The FabricApi class includes a base URL in the retrofit method, which can be considered a form of hard-coded configuration. If this base URL eventually includes API keys or secrets, it may lead to security risks.\n",
      "classification": "slightly promising",
      "cwe": "CWE-798",
      "function_names": [
        "retrofit"
      ],
      "filenames": [
        "src/main/java/fabric/beta/publisher/FabricApi.java"
      ]
    },
    {
      "headline": "Possible Use of Insecure Hashing Algorithm in AppRelease.from",
      "analysis": "The AppRelease.from method handles APK files but lacks explicit checks for cryptographic context. If the properties file it processes includes sensitive information, the absence of a strong cryptographic hash function could be problematic.\n",
      "classification": "slightly promising",
      "cwe": "CWE-327",
      "function_names": [
        "from"
      ],
      "filenames": [
        "src/main/java/fabric/beta/publisher/AppRelease.java"
      ]
    },
    {
      "headline": "Improper Neutralization of Special Elements used in an Argument ('Argument Injection') in FabricBetaPublisher.buildCrashlyticsCommand()",
      "analysis": "The buildCrashlyticsCommand method constructs a command to be executed using elements derived from environment variables or user input. This may allow for argument injection if those variables contain special characters or argument delimiters, which are not properly sanitized.\n",
      "classification": "very promising",
      "cwe": "CWE-88",
      "function_names": [
        "buildCrashlyticsCommand"
      ],
      "filenames": [
        "src/main/java/fabric/beta/publisher/FabricBetaPublisher.java"
      ]
    }
  ],
  "scores": [
    {
      "stats": {
        "fn": 1,
        "tp": 0,
        "fp": 3
      },
      "mapping": {},
      "vuln_dates": {
        "CVE-2019-1003088": "2019-04-04T16:29:01"
      },
      "scoring_model": "claude-3-opus-20240229",
      "type": "llm",
      "instruction_template_hash": "245ace12b6361954d0a2"
    }
  ],
  "instruction_template_hash": "10c0163db4740318a544",
  "version": "0.1.0"
}
