{
  "commit": "2def3797d882d02bfba1e5c9fb54ea667045530e",
  "repo_url": "https://github.com/holgerhees/cloudsync",
  "model": "claude-3-sonnet-20240229",
  "chunk_hashes": [
    "02a0104255e683ef3d8a"
  ],
  "responses": [
    {
      "content": "```yaml\nleads:\n  - headline: Improper input validation in cloudsync.sh\n    analysis: |\n      The `cloudsync.sh` script contains a potential command injection vulnerability when setting the `LANG` environment variable. If a user-controlled value is passed to this script, it could allow an attacker to execute arbitrary commands on the system.\n    cwe: CWE-77\n    function_names:\n      - main (top-level script code)\n    filenames:\n      - cloudsync.sh\n    classification: very promising\n\n  - headline: Potential path traversal vulnerability in LocalFilesystemConnector\n    analysis: |\n      The `LocalFilesystemConnector` class constructs file paths based on user-provided input (e.g., `item.getPath()`). If the input is not properly sanitized, it could allow an attacker to access files outside of the intended directory structure (path traversal).\n    cwe: CWE-22\n    function_names:\n      - getFileBinary\n      - readFolder\n      - getItem\n      - _getRemoteFile\n      - _getRemoteHistoryFile\n    filenames:\n      - src/main/java/cloudsync/connector/LocalFilesystemConnector.java\n    classification: very promising\n\n  - headline: Improper handling of symbolic links in LocalFilesystemConnector\n    analysis: |\n      The `LocalFilesystemConnector` class has a `followlinks` option to control how symbolic links are handled. When set to `FollowLinkType.EXTERNAL`, it follows symbolic links that point outside the current directory hierarchy without proper validation. This could potentially lead to unauthorized access to files or directories.\n    cwe: CWE-59\n    function_names:\n      - getItem\n    filenames:\n      - src/main/java/cloudsync/connector/LocalFilesystemConnector.java\n    classification: very promising\n\n  - headline: Improper validation of user-supplied include/exclude patterns\n    analysis: |\n      The `CmdOptions` class accepts user-supplied regular expression patterns for include and exclude filters. These patterns are not properly validated, which could potentially lead to ReDoS (Regular Expression Denial of Service) vulnerabilities if an attacker provides a malicious pattern.\n    cwe: CWE-1333\n    function_names:\n      - parse\n    filenames:\n      - src/main/java/cloudsync/helper/CmdOptions.java\n    classification: slightly promising\n\n  - headline: Potential deserialization issue in RemoteDropboxConnector\n    analysis: |\n      The `RemoteDropboxConnector` class deserializes data from a Dropbox API response without validating the input. If an attacker can manipulate the Dropbox response, it could potentially lead to code execution or other security issues due to insecure deserialization.\n    cwe: CWE-502\n    function_names:\n      - _prepareBackupItem\n    filenames:\n      - src/main/java/cloudsync/connector/RemoteDropboxConnector.java\n    classification: slightly promising\n\n  - headline: Potential uncontrolled resource consumption in RemoteGoogleDriveConnector\n    analysis: |\n      The `RemoteGoogleDriveConnector` class has a `MAX_RESULTS` constant that limits the number of items retrieved from the Google Drive API. However, this limit is still relatively high (1000), which could potentially lead to excessive memory consumption or other resource exhaustion issues if an attacker can control the amount of data returned.\n    cwe: CWE-770\n    function_names:\n      - _readFolder\n    filenames:\n      - src/main/java/cloudsync/connector/RemoteGoogleDriveConnector.java\n    classification: slightly promising\n\n  - headline: Use of hard-coded credentials in RemoteDropboxOptions\n    analysis: |\n      The `RemoteDropboxOptions` class retrieves the Dropbox API credentials from configuration properties. If these credentials are hard-coded in the application, it could potentially expose sensitive information and lead to unauthorized access to the Dropbox account.\n    cwe: CWE-798\n    function_names:\n      - RemoteDropboxOptions\n    filenames:\n      - src/main/java/cloudsync/connector/RemoteDropboxOptions.java\n    classification: slightly promising\n```\n\nThe codebase contains several potential security vulnerabilities, ranging from input validation issues to path traversal and symbolic link handling vulnerabilities. The most promising leads are:\n\n1. **Improper input validation in cloudsync.sh**: The `cloudsync.sh` script does not properly sanitize user input before setting the `LANG` environment variable, which could lead to command injection vulnerabilities.\n\n2. **Potential path traversal vulnerability in LocalFilesystemConnector**: The `LocalFilesystemConnector` class constructs file paths based on user input without proper validation, which could allow an attacker to access files outside the intended directory structure (path traversal).\n\n3. **Improper handling of symbolic links in LocalFilesystemConnector**: The `LocalFilesystemConnector` class follows symbolic links that point outside the current directory hierarchy without proper validation, which could lead to unauthorized file access.\n\nOther potential issues include ReDoS vulnerabilities in user-supplied regular expression patterns, deserialization issues in the `RemoteDropboxConnector`, uncontrolled resource consumption in the `RemoteGoogleDriveConnector`, and the use of hard-coded credentials in the `RemoteDropboxOptions` class.\n\nTo mitigate these vulnerabilities, the codebase should implement proper input validation, sanitization, and whitelisting of file paths and user-supplied data. Additionally, the handling of symbolic links should be carefully reviewed and restricted, and resource limits should be enforced to prevent excessive resource consumption. Finally, sensitive information such as API credentials should be securely stored and retrieved, rather than hard-coded in the application.",
      "date": "2024-06-12T17:16:28.968180",
      "usage": {
        "prompt_tokens": 59744,
        "completion_tokens": 1369,
        "cost": 0.199767
      }
    }
  ],
  "leads": [
    {
      "headline": "Improper input validation in cloudsync.sh",
      "analysis": "The cloudsync.sh script contains a potential command injection vulnerability when setting the LANG environment variable. If a user-controlled value is passed to this script, it could allow an attacker to execute arbitrary commands on the system.\n",
      "classification": "very promising",
      "cwe": "CWE-77",
      "function_names": [
        "main (top-level script code)"
      ],
      "filenames": [
        "cloudsync.sh"
      ]
    },
    {
      "headline": "Potential path traversal vulnerability in LocalFilesystemConnector",
      "analysis": "The LocalFilesystemConnector class constructs file paths based on user-provided input (e.g., item.getPath()). If the input is not properly sanitized, it could allow an attacker to access files outside of the intended directory structure (path traversal).\n",
      "classification": "very promising",
      "cwe": "CWE-22",
      "function_names": [
        "getFileBinary",
        "readFolder",
        "getItem"
      ],
      "filenames": [
        "src/main/java/cloudsync/connector/LocalFilesystemConnector.java"
      ]
    },
    {
      "headline": "Improper handling of symbolic links in LocalFilesystemConnector",
      "analysis": "The LocalFilesystemConnector class has a followlinks option to control how symbolic links are handled. When set to FollowLinkType.EXTERNAL, it follows symbolic links that point outside the current directory hierarchy without proper validation. This could potentially lead to unauthorized access to files or directories.\n",
      "classification": "very promising",
      "cwe": "CWE-59",
      "function_names": [
        "getItem"
      ],
      "filenames": [
        "src/main/java/cloudsync/connector/LocalFilesystemConnector.java"
      ]
    },
    {
      "headline": "Improper validation of user-supplied include/exclude patterns",
      "analysis": "The CmdOptions class accepts user-supplied regular expression patterns for include and exclude filters. These patterns are not properly validated, which could potentially lead to ReDoS (Regular Expression Denial of Service) vulnerabilities if an attacker provides a malicious pattern.\n",
      "classification": "slightly promising",
      "cwe": "CWE-1333",
      "function_names": [
        "parse"
      ],
      "filenames": [
        "src/main/java/cloudsync/helper/CmdOptions.java"
      ]
    },
    {
      "headline": "Potential deserialization issue in RemoteDropboxConnector",
      "analysis": "The RemoteDropboxConnector class deserializes data from a Dropbox API response without validating the input. If an attacker can manipulate the Dropbox response, it could potentially lead to code execution or other security issues due to insecure deserialization.\n",
      "classification": "slightly promising",
      "cwe": "CWE-502",
      "function_names": [
        "_prepareBackupItem"
      ],
      "filenames": [
        "src/main/java/cloudsync/connector/RemoteDropboxConnector.java"
      ]
    },
    {
      "headline": "Potential uncontrolled resource consumption in RemoteGoogleDriveConnector",
      "analysis": "The RemoteGoogleDriveConnector class has a MAX_RESULTS constant that limits the number of items retrieved from the Google Drive API. However, this limit is still relatively high (1000), which could potentially lead to excessive memory consumption or other resource exhaustion issues if an attacker can control the amount of data returned.\n",
      "classification": "slightly promising",
      "cwe": "CWE-770",
      "function_names": [
        "_readFolder"
      ],
      "filenames": [
        "src/main/java/cloudsync/connector/RemoteGoogleDriveConnector.java"
      ]
    },
    {
      "headline": "Use of hard-coded credentials in RemoteDropboxOptions",
      "analysis": "The RemoteDropboxOptions class retrieves the Dropbox API credentials from configuration properties. If these credentials are hard-coded in the application, it could potentially expose sensitive information and lead to unauthorized access to the Dropbox account.\n",
      "classification": "slightly promising",
      "cwe": "CWE-798",
      "function_names": [
        "RemoteDropboxOptions"
      ],
      "filenames": [
        "src/main/java/cloudsync/connector/RemoteDropboxOptions.java"
      ]
    }
  ],
  "scores": [
    {
      "stats": {
        "fn": 0,
        "tp": 1,
        "fp": 1
      },
      "mapping": {
        "1": "CVE-2022-4773",
        "2": "CVE-2022-4773"
      },
      "vuln_dates": {
        "CVE-2022-4773": "2022-12-28T00:15:15"
      },
      "scoring_model": "claude-3-opus-20240229",
      "type": "llm",
      "instruction_template_hash": "245ace12b6361954d0a2"
    }
  ],
  "instruction_template_hash": "10c0163db4740318a544",
  "version": "0.1.0"
}
