{
  "commit": "1115251555e88c9069027a63f5e38a377d5f1b89",
  "repo_url": "https://github.com/tinyproxy/tinyproxy",
  "model": "claude-3-opus-20240229",
  "chunk_hashes": [
    "26fd6194d1af7bf58372"
  ],
  "responses": [
    {
      "content": "Here is the YAML output with security vulnerability leads:\n\n```yaml\nleads:\n  - headline: Heap buffer overflow in get_peer_information()\n    analysis: |\n      The getpeer_information() function in src/sock.c reads the peer\n      address information into fixed-size stack buffers 'ipaddr' and\n      'string_addr' without proper bounds checking. An excessively long\n      peer address could overflow these buffers, resulting in a crash or\n      potential code execution.\n    cwe: CWE-120\n    function_names:\n      - getpeer_information\n    filenames:\n      - src/sock.c  \n    classification: very promising\n  \n  - headline: Command injection via reverse_rewrite_url()\n    analysis: |\n      The reverse_rewrite_url() function in src/reverse-proxy.c performs\n      string formatting into a heap-allocated buffer using snprintf(). The \n      URL path is inserted directly without input validation. A malicious\n      client request could inject shell metacharacters into the URL path\n      which get propagated when logging or displaying error pages, \n      allowing potential command injection attacks.\n    cwe: CWE-78\n    function_names:\n      - reverse_rewrite_url\n    filenames:\n      - src/reverse-proxy.c\n    classification: very promising\n\n  - headline: Integer overflows in various functions\n    analysis: |\n      Several functions including send_ssl_response(), write_message(),\n      and readline() perform arithmetic and memory allocation based on\n      request fields like content length without proper integer overflow\n      checks. Extremely large or malformed numeric values could trigger\n      integer overflows leading to insufficient memory allocation and\n      subsequent heap corruption.\n    cwe: CWE-190\n    function_names:\n      - send_ssl_response\n      - write_message\n      - readline\n    filenames:\n      - src/reqs.c\n      - src/network.c\n    classification: slightly promising\n\n  - headline: Unbounded memory allocation and copying in filter code\n    analysis: |\n      The filter_init() function in src/filter.c allocates memory and\n      copies filter rule strings without any upper bound on the size.\n      Maliciously large filter rules could cause excess memory allocation\n      and copying leading to out-of-memory or denial of service.\n    cwe: CWE-789\n    function_names:\n      - filter_init\n    filenames:\n      - src/filter.c  \n    classification: slightly promising\n```\n\nI tried to focus on some of the most promising potential vulnerabilities I could identify in this codebase, prioritizing issues that could lead to remote code execution, command injection, or denial of service. However, a full in-depth audit would likely uncover additional vulnerabilities. Let me know if you would like me to elaborate further on any of these issues or look for additional vulnerability classes.",
      "date": "2024-06-13T17:18:35.726899",
      "usage": {
        "prompt_tokens": 105479,
        "completion_tokens": 668,
        "cost": 1.632285
      }
    }
  ],
  "leads": [
    {
      "headline": "Heap buffer overflow in get_peer_information()",
      "analysis": "The getpeer_information() function in src/sock.c reads the peer\naddress information into fixed-size stack buffers 'ipaddr' and\n'string_addr' without proper bounds checking. An excessively long\npeer address could overflow these buffers, resulting in a crash or\npotential code execution.\n",
      "classification": "very promising",
      "cwe": "CWE-120",
      "function_names": [
        "getpeer_information"
      ],
      "filenames": [
        "src/sock.c"
      ]
    },
    {
      "headline": "Command injection via reverse_rewrite_url()",
      "analysis": "The reverse_rewrite_url() function in src/reverse-proxy.c performs\nstring formatting into a heap-allocated buffer using snprintf(). The \nURL path is inserted directly without input validation. A malicious\nclient request could inject shell metacharacters into the URL path\nwhich get propagated when logging or displaying error pages, \nallowing potential command injection attacks.\n",
      "classification": "very promising",
      "cwe": "CWE-78",
      "function_names": [
        "reverse_rewrite_url"
      ],
      "filenames": [
        "src/reverse-proxy.c"
      ]
    },
    {
      "headline": "Integer overflows in various functions",
      "analysis": "Several functions including send_ssl_response(), write_message(),\nand readline() perform arithmetic and memory allocation based on\nrequest fields like content length without proper integer overflow\nchecks. Extremely large or malformed numeric values could trigger\ninteger overflows leading to insufficient memory allocation and\nsubsequent heap corruption.\n",
      "classification": "slightly promising",
      "cwe": "CWE-190",
      "function_names": [
        "send_ssl_response",
        "write_message",
        "readline"
      ],
      "filenames": [
        "src/reqs.c",
        "src/network.c"
      ]
    },
    {
      "headline": "Unbounded memory allocation and copying in filter code",
      "analysis": "The filter_init() function in src/filter.c allocates memory and\ncopies filter rule strings without any upper bound on the size.\nMaliciously large filter rules could cause excess memory allocation\nand copying leading to out-of-memory or denial of service.\n",
      "classification": "slightly promising",
      "cwe": "CWE-789",
      "function_names": [
        "filter_init"
      ],
      "filenames": [
        "src/filter.c"
      ]
    }
  ],
  "scores": [
    {
      "stats": {
        "fn": 1,
        "tp": 0,
        "fp": 2
      },
      "mapping": {},
      "vuln_dates": {
        "CVE-2017-11747": "2017-07-30T16:29:00"
      },
      "scoring_model": "claude-3-opus-20240229",
      "type": "llm",
      "instruction_template_hash": "245ace12b6361954d0a2"
    }
  ],
  "instruction_template_hash": "10c0163db4740318a544",
  "version": "0.1.0"
}
