{
  "commit": "187a70cb600a3ce5c9a20385ba751ddaf845c5c4",
  "repo_url": "https://github.com/ossec/ossec-wui",
  "model": "gpt-4o-2024-05-13",
  "chunk_hashes": [
    "9a8e255fdd2a041bf995"
  ],
  "responses": [
    {
      "content": "```yaml\nleads:\n  - headline: \"Potential Command Injection in setup.sh\"\n    analysis: |\n      The function `ls \\`which $HTPWDCMD\\`` in `setup.sh` line 16 uses untrusted input from the variable `HTPWDCMD` without proper validation or sanitization. Leading to a command injection vulnerability if `HTPWDCMD` contains malicious content.\n    cwe: CWE-77\n    function_names: []\n    filenames:\n      - setup.sh\n    classification: very promising\n\n  - headline: \"Potential Privilege Escalation in setup.sh\"\n    analysis: |\n      In `setup.sh`, the script modifies the /etc/group file to add the web server user to the 'ossec' group by using `sed` without verifying the input values. This could allow for privilege escalation if an attacker is able to manipulate the input values.\n    cwe: CWE-269\n    function_names: []\n    filenames:\n      - setup.sh\n    classification: slightly promising\n\n  - headline: \"Hardcoded Credentials in setup.sh\"\n    analysis: |\n      The setup.sh script creates and stores a htpasswd file at `$PWD/.htpasswd` using potentially hard-coded or user-provided credentials, leading to the risk of unauthorized access if the file is not properly secured.\n    cwe: CWE-798\n    function_names: []\n    filenames:\n      - setup.sh\n    classification: slightly promising\n\n  - headline: \"Uncontrolled Resource Consumption in setup.sh\"\n    analysis: |\n      The creation of the temporary directory `tmp` with permission 777 and without any size limit or monitoring could lead to uncontrolled resource consumption, potentially resulting in a denial-of-service (DoS) condition.\n    cwe: CWE-400\n    function_names: []\n    filenames:\n      - setup.sh\n    classification: slightly promising\n\n  - headline: \"Missing Input Validation in js/calendar-setup.js\"\n    analysis: |\n      The `Calendar.setup` function takes various parameters from user input and uses them to directly manipulate the DOM and for calendar setup. There is no validation or sanitization for these parameters, leading to potential DOM-based XSS vulnerabilities.\n    cwe: CWE-20\n    function_names:\n      - Calendar.setup\n    filenames:\n      - js/calendar-setup.js\n    classification: very promising\n\n  - headline: \"Potential Cross-Site Scripting (XSS) in js/calendar.js\"\n    analysis: |\n      In `calendar.js`, the method `Calendar.prototype.create` directly inserts HTML into the document using `innerHTML`, which can lead to Cross-Site Scripting (XSS) vulnerabilities if any of the dynamically inserted values are manipulated by an attacker.\n    cwe: CWE-79\n    function_names:\n      - Calendar.prototype.create\n    filenames:\n      - js/calendar.js\n    classification: very promising\n\n  - headline: \"Potential Cross-Site Scripting (XSS) in js/prototype.js\"\n    analysis: |\n      In `js/prototype.js`, the method `Element.Methods.update` allows updating an element's inner HTML without any content sanitization, leading to possible XSS vulnerabilities.\n    cwe: CWE-79\n    function_names:\n      - Element.Methods.update\n    filenames:\n      - js/prototype.js\n    classification: very promising\n\n  - headline: \"Potential Cross-Site Scripting (XSS) in js/calendar.js\"\n    analysis: |\n      In `calendar.js`, the method `Date.prototype.print` interprets user-provided date format strings and uses them to format the output. If these strings are not properly sanitized, it can lead to XSS vulnerabilities.\n    cwe: CWE-79\n    function_names:\n      - Date.prototype.print\n    filenames:\n      - js/calendar.js\n    classification: very promising\n```",
      "date": "2024-06-13T10:56:39.304260",
      "usage": {
        "prompt_tokens": 52431,
        "completion_tokens": 788,
        "cost": 0.273975
      }
    }
  ],
  "leads": [
    {
      "headline": "Potential Command Injection in setup.sh",
      "analysis": "The function ls \\which $HTPWDCMD\\ in setup.sh line 16 uses untrusted input from the variable HTPWDCMD without proper validation or sanitization. Leading to a command injection vulnerability if HTPWDCMD contains malicious content.\n",
      "classification": "very promising",
      "cwe": "CWE-77",
      "function_names": [],
      "filenames": [
        "setup.sh"
      ]
    },
    {
      "headline": "Potential Privilege Escalation in setup.sh",
      "analysis": "In setup.sh, the script modifies the /etc/group file to add the web server user to the 'ossec' group by using sed without verifying the input values. This could allow for privilege escalation if an attacker is able to manipulate the input values.\n",
      "classification": "slightly promising",
      "cwe": "CWE-269",
      "function_names": [],
      "filenames": [
        "setup.sh"
      ]
    },
    {
      "headline": "Hardcoded Credentials in setup.sh",
      "analysis": "The setup.sh script creates and stores a htpasswd file at $PWD/.htpasswd using potentially hard-coded or user-provided credentials, leading to the risk of unauthorized access if the file is not properly secured.\n",
      "classification": "slightly promising",
      "cwe": "CWE-798",
      "function_names": [],
      "filenames": [
        "setup.sh"
      ]
    },
    {
      "headline": "Uncontrolled Resource Consumption in setup.sh",
      "analysis": "The creation of the temporary directory tmp with permission 777 and without any size limit or monitoring could lead to uncontrolled resource consumption, potentially resulting in a denial-of-service (DoS) condition.\n",
      "classification": "slightly promising",
      "cwe": "CWE-400",
      "function_names": [],
      "filenames": [
        "setup.sh"
      ]
    },
    {
      "headline": "Missing Input Validation in js/calendar-setup.js",
      "analysis": "The Calendar.setup function takes various parameters from user input and uses them to directly manipulate the DOM and for calendar setup. There is no validation or sanitization for these parameters, leading to potential DOM-based XSS vulnerabilities.\n",
      "classification": "very promising",
      "cwe": "CWE-20",
      "function_names": [
        "Calendar.setup"
      ],
      "filenames": [
        "js/calendar-setup.js"
      ]
    },
    {
      "headline": "Potential Cross-Site Scripting (XSS) in js/calendar.js",
      "analysis": "In calendar.js, the method Calendar.prototype.create directly inserts HTML into the document using innerHTML, which can lead to Cross-Site Scripting (XSS) vulnerabilities if any of the dynamically inserted values are manipulated by an attacker.\n",
      "classification": "very promising",
      "cwe": "CWE-79",
      "function_names": [
        "Calendar.prototype.create"
      ],
      "filenames": [
        "js/calendar.js"
      ]
    },
    {
      "headline": "Potential Cross-Site Scripting (XSS) in js/prototype.js",
      "analysis": "In js/prototype.js, the method Element.Methods.update allows updating an element's inner HTML without any content sanitization, leading to possible XSS vulnerabilities.\n",
      "classification": "very promising",
      "cwe": "CWE-79",
      "function_names": [
        "Element.Methods.update"
      ],
      "filenames": [
        "js/prototype.js"
      ]
    },
    {
      "headline": "Potential Cross-Site Scripting (XSS) in js/calendar.js",
      "analysis": "In calendar.js, the method Date.prototype.print interprets user-provided date format strings and uses them to format the output. If these strings are not properly sanitized, it can lead to XSS vulnerabilities.\n",
      "classification": "very promising",
      "cwe": "CWE-79",
      "function_names": [
        "Date.prototype.print"
      ],
      "filenames": [
        "js/calendar.js"
      ]
    }
  ],
  "scores": [
    {
      "stats": {
        "fn": 1,
        "tp": 0,
        "fp": 5
      },
      "mapping": {},
      "vuln_dates": {
        "CVE-2016-4847": "2017-04-20T17:59:00"
      },
      "scoring_model": "claude-3-opus-20240229",
      "type": "llm",
      "instruction_template_hash": "245ace12b6361954d0a2"
    }
  ],
  "instruction_template_hash": "10c0163db4740318a544",
  "version": "0.1.0"
}
