{
  "commit": "2b51da69f83cdafe99069b081a7a69aa35194c9d",
  "repo_url": "https://github.com/brettwooldridge/nuprocess",
  "model": "gpt-4o-2024-05-13",
  "chunk_hashes": [
    "a01011094f66212bdc99"
  ],
  "responses": [
    {
      "content": "```yaml\nleads:\n  - headline: Improper validation of array index\n    analysis: |\n      The main method directly assigns a value from command-line arguments to the variable PROCESSES without any validation.\n      This could lead to unexpected behavior if a non-numeric value is provided or if the numeric value is excessively large, causing resource exhaustion.\n      Additionally, improper handling of array indexes can cause array out-of-bound exceptions.\n    cwe: CWE-129\n    function_names:\n      - main\n    filenames:\n      - src/example/java/com/zaxxer/nuprocess/example/OldSchool.java\n    classification: very promising\n\n  - headline: Improper resource shutdown or release\n    analysis: |\n      The program doesn't guarantee that resources (file descriptors, process handles, input/output streams) are always released properly.\n      This can lead to resource leaks, especially if the program prematurely exits or throws exceptions.\n      For instance, LibC.close calls on file descriptors may not always happen, leading to exhaustion of file descriptors if many processes are run.\n    cwe: CWE-404\n    function_names:\n      - closePipes\n      - stdinClose\n      - LibC.close\n    filenames:\n      - src/main/java/com/zaxxer/nuprocess/internal/BasePosixProcess.java\n      - src/main/java/com/zaxxer/nuprocess/linux/LinuxProcess.java\n    classification: very promising\n\n  - headline: Potential for command injection via unvalidated external input\n    analysis: |\n      User-provided inputs are used directly in commands executed by ProcessBuilder without appropriate sanitization.\n      This could potentially lead to command injection if some of the inputs are improperly validated.\n      The program executes commands based on user inputs without sanitizing command line arguments, allowing an attacker to potentially execute arbitrary commands.\n    cwe: CWE-78\n    function_names:\n      - startProcess\n      - run\n    filenames:\n      - src/main/java/com/zaxxer/nuprocess/NuProcessBuilder.java\n      - src/main/java/com/zaxxer/nuprocess/example/NuSchool.java\n    classification: slightly promising\n\n  - headline: Missing release of resources after effective lifetime\n    analysis: |\n      Resource cleanup is not adequately handled in several locations, causing potentially resource leaks.\n      For instance, release of memory allocated for ByteBuffers or native pointers might be delayed, leading to increased memory usage.\n      Examples include the potential for lingering file descriptors or memory allocated for stdin/out/err buffers.\n    cwe: CWE-401\n    function_names:\n      - onExit\n      - close\n    filenames:\n      - src/main/java/com/zaxxer/nuprocess/internal/BasePosixProcess.java\n      - src/main/java/com/zaxxer/nuprocess/windows/WindowsProcess.java\n    classification: very promising\n```",
      "date": "2024-06-12T15:21:30.585973",
      "usage": {
        "prompt_tokens": 68214,
        "completion_tokens": 569,
        "cost": 0.349605
      }
    }
  ],
  "leads": [
    {
      "headline": "Improper validation of array index",
      "analysis": "The main method directly assigns a value from command-line arguments to the variable PROCESSES without any validation.\nThis could lead to unexpected behavior if a non-numeric value is provided or if the numeric value is excessively large, causing resource exhaustion.\nAdditionally, improper handling of array indexes can cause array out-of-bound exceptions.\n",
      "classification": "very promising",
      "cwe": "CWE-129",
      "function_names": [
        "main"
      ],
      "filenames": [
        "src/example/java/com/zaxxer/nuprocess/example/OldSchool.java"
      ]
    },
    {
      "headline": "Improper resource shutdown or release",
      "analysis": "The program doesn't guarantee that resources (file descriptors, process handles, input/output streams) are always released properly.\nThis can lead to resource leaks, especially if the program prematurely exits or throws exceptions.\nFor instance, LibC.close calls on file descriptors may not always happen, leading to exhaustion of file descriptors if many processes are run.\n",
      "classification": "very promising",
      "cwe": "CWE-404",
      "function_names": [
        "closePipes",
        "stdinClose",
        "LibC.close"
      ],
      "filenames": [
        "src/main/java/com/zaxxer/nuprocess/internal/BasePosixProcess.java",
        "src/main/java/com/zaxxer/nuprocess/linux/LinuxProcess.java"
      ]
    },
    {
      "headline": "Potential for command injection via unvalidated external input",
      "analysis": "User-provided inputs are used directly in commands executed by ProcessBuilder without appropriate sanitization.\nThis could potentially lead to command injection if some of the inputs are improperly validated.\nThe program executes commands based on user inputs without sanitizing command line arguments, allowing an attacker to potentially execute arbitrary commands.\n",
      "classification": "slightly promising",
      "cwe": "CWE-78",
      "function_names": [
        "startProcess",
        "run"
      ],
      "filenames": [
        "src/main/java/com/zaxxer/nuprocess/NuProcessBuilder.java",
        "src/main/java/com/zaxxer/nuprocess/example/NuSchool.java"
      ]
    },
    {
      "headline": "Missing release of resources after effective lifetime",
      "analysis": "Resource cleanup is not adequately handled in several locations, causing potentially resource leaks.\nFor instance, release of memory allocated for ByteBuffers or native pointers might be delayed, leading to increased memory usage.\nExamples include the potential for lingering file descriptors or memory allocated for stdin/out/err buffers.\n",
      "classification": "very promising",
      "cwe": "CWE-401",
      "function_names": [
        "onExit",
        "close"
      ],
      "filenames": [
        "src/main/java/com/zaxxer/nuprocess/internal/BasePosixProcess.java",
        "src/main/java/com/zaxxer/nuprocess/windows/WindowsProcess.java"
      ]
    }
  ],
  "scores": [
    {
      "stats": {
        "fn": 1,
        "tp": 0,
        "fp": 3
      },
      "mapping": {},
      "vuln_dates": {
        "CVE-2022-39243": "2022-09-26T14:15:10"
      },
      "scoring_model": "claude-3-opus-20240229",
      "type": "llm",
      "instruction_template_hash": "245ace12b6361954d0a2"
    }
  ],
  "instruction_template_hash": "10c0163db4740318a544",
  "version": "0.1.0"
}
