{
  "commit": "d0a22b624f551bbfbf642b2c0d0c8ffeb4803428",
  "repo_url": "https://github.com/edmundhung/conform",
  "model": "claude-3-haiku-20240307",
  "chunk_hashes": [
    "cc1a37217c19db301bd6"
  ],
  "responses": [
    {
      "content": "```yaml\nleads:\n  - headline: Improper Input Validation\n    analysis: |\n      The code does not properly validate the input data submitted through the form, which can lead to various vulnerabilities such as command injection, SQL injection, and XSS attacks.\n    cwe: CWE-20\n    function_names:\n      - parse\n      - parseField\n    filenames:\n      - packages/conform-dom/formdata.ts\n      - packages/conform-validitystate/index.ts\n    classification: very promising\n\n  - headline: Uninitialized Pointer\n    analysis: |\n      The `parseField` function in the `packages/conform-validitystate/index.ts` file may use an uninitialized pointer when accessing the `value` property of the `input` parameter, which can lead to undefined behavior and potential security vulnerabilities.\n    cwe: CWE-824\n    function_names:\n      - parseField\n    filenames:\n      - packages/conform-validitystate/index.ts\n    classification: slightly promising\n\n  - headline: Exposure of Sensitive Information to an Unauthorized Actor\n    analysis: |\n      The `packages/conform-dom/formdata.ts` file contains a function `getFormData` that constructs a `FormData` object with the submitter value. This can lead to the exposure of sensitive information, such as CSRF tokens, to unauthorized actors if the submitter value is not properly validated.\n    cwe: CWE-200\n    function_names:\n      - getFormData\n    filenames:\n      - packages/conform-dom/formdata.ts\n    classification: very promising\n\n  - headline: Improper Neutralization of Special Elements in Output Used by a Downstream Component ('Injection')\n    analysis: |\n      The `packages/conform-dom/formdata.ts` file contains a function `getValue` that retrieves the value from a target object by following the paths. This function does not properly sanitize the input, which can lead to injection vulnerabilities if the input is not properly validated.\n    cwe: CWE-74\n    function_names:\n      - getValue\n    filenames:\n      - packages/conform-dom/formdata.ts\n    classification: very promising\n\n  - headline: Improper Restriction of Operations within the Bounds of a Memory Buffer\n    analysis: |\n      The `packages/conform-dom/formdata.ts` file contains a function `setValue` that assigns a value to a target object by following the paths. This function does not properly validate the input, which can lead to out-of-bounds write vulnerabilities if the input is not properly sanitized.\n    cwe: CWE-119\n    function_names:\n      - setValue\n    filenames:\n      - packages/conform-dom/formdata.ts\n    classification: very promising\n\n  - headline: Improper Handling of Exceptional Conditions\n    analysis: |\n      The `packages/conform-validitystate/index.ts` file contains a function `parse` that parses form data and handles exceptional conditions, such as missing or invalid input. However, the function does not properly handle all possible exceptions, which can lead to security vulnerabilities if the input is not properly validated.\n    cwe: CWE-755\n    function_names:\n      - parse\n    filenames:\n      - packages/conform-validitystate/index.ts\n    classification: very promising\n\n  - headline: Improper Neutralization of Special Elements used in an OS Command ('OS Command Injection')\n    analysis: |\n      The `packages/conform-validitystate/index.ts` file contains a function `parseField` that parses form data and may not properly sanitize the input, which can lead to OS command injection vulnerabilities if the input is not properly validated.\n    cwe: CWE-78\n    function_names:\n      - parseField\n    filenames:\n      - packages/conform-validitystate/index.ts\n    classification: very promising\n\n  - headline: Improper Neutralization of Special Elements used in an SQL Command ('SQL Injection')\n    analysis: |\n      The `packages/conform-validitystate/index.ts` file contains a function `parseField` that parses form data and may not properly sanitize the input, which can lead to SQL injection vulnerabilities if the input is not properly validated.\n    cwe: CWE-89\n    function_names:\n      - parseField\n    filenames:\n      - packages/conform-validitystate/index.ts\n    classification: very promising\n\n  - headline: Improper Neutralization of Input During Web Page Generation ('Cross-site Scripting')\n    analysis: |\n      The `packages/conform-validitystate/index.ts` file contains a function `parseField` that parses form data and may not properly sanitize the input, which can lead to XSS vulnerabilities if the input is not properly validated.\n    cwe: CWE-79\n    function_names:\n      - parseField\n    filenames:\n      - packages/conform-validitystate/index.ts\n    classification: very promising\n\n```",
      "date": "2024-06-09T11:37:46.465559",
      "usage": {
        "prompt_tokens": 108049,
        "completion_tokens": 1175,
        "cost": 0.028481
      }
    }
  ],
  "leads": [
    {
      "headline": "Improper Input Validation",
      "analysis": "The code does not properly validate the input data submitted through the form, which can lead to various vulnerabilities such as command injection, SQL injection, and XSS attacks.\n",
      "classification": "very promising",
      "cwe": "CWE-20",
      "function_names": [
        "parse",
        "parseField"
      ],
      "filenames": [
        "packages/conform-dom/formdata.ts",
        "packages/conform-validitystate/index.ts"
      ]
    },
    {
      "headline": "Uninitialized Pointer",
      "analysis": "The parseField function in the packages/conform-validitystate/index.ts file may use an uninitialized pointer when accessing the value property of the input parameter, which can lead to undefined behavior and potential security vulnerabilities.\n",
      "classification": "slightly promising",
      "cwe": "CWE-824",
      "function_names": [
        "parseField"
      ],
      "filenames": [
        "packages/conform-validitystate/index.ts"
      ]
    },
    {
      "headline": "Exposure of Sensitive Information to an Unauthorized Actor",
      "analysis": "The packages/conform-dom/formdata.ts file contains a function getFormData that constructs a FormData object with the submitter value. This can lead to the exposure of sensitive information, such as CSRF tokens, to unauthorized actors if the submitter value is not properly validated.\n",
      "classification": "very promising",
      "cwe": "CWE-200",
      "function_names": [
        "getFormData"
      ],
      "filenames": [
        "packages/conform-dom/formdata.ts"
      ]
    },
    {
      "headline": "Improper Neutralization of Special Elements in Output Used by a Downstream Component ('Injection')",
      "analysis": "The packages/conform-dom/formdata.ts file contains a function getValue that retrieves the value from a target object by following the paths. This function does not properly sanitize the input, which can lead to injection vulnerabilities if the input is not properly validated.\n",
      "classification": "very promising",
      "cwe": "CWE-74",
      "function_names": [
        "getValue"
      ],
      "filenames": [
        "packages/conform-dom/formdata.ts"
      ]
    },
    {
      "headline": "Improper Restriction of Operations within the Bounds of a Memory Buffer",
      "analysis": "The packages/conform-dom/formdata.ts file contains a function setValue that assigns a value to a target object by following the paths. This function does not properly validate the input, which can lead to out-of-bounds write vulnerabilities if the input is not properly sanitized.\n",
      "classification": "very promising",
      "cwe": "CWE-119",
      "function_names": [
        "setValue"
      ],
      "filenames": [
        "packages/conform-dom/formdata.ts"
      ]
    },
    {
      "headline": "Improper Handling of Exceptional Conditions",
      "analysis": "The packages/conform-validitystate/index.ts file contains a function parse that parses form data and handles exceptional conditions, such as missing or invalid input. However, the function does not properly handle all possible exceptions, which can lead to security vulnerabilities if the input is not properly validated.\n",
      "classification": "very promising",
      "cwe": "CWE-755",
      "function_names": [
        "parse"
      ],
      "filenames": [
        "packages/conform-validitystate/index.ts"
      ]
    },
    {
      "headline": "Improper Neutralization of Special Elements used in an OS Command ('OS Command Injection')",
      "analysis": "The packages/conform-validitystate/index.ts file contains a function parseField that parses form data and may not properly sanitize the input, which can lead to OS command injection vulnerabilities if the input is not properly validated.\n",
      "classification": "very promising",
      "cwe": "CWE-78",
      "function_names": [
        "parseField"
      ],
      "filenames": [
        "packages/conform-validitystate/index.ts"
      ]
    },
    {
      "headline": "Improper Neutralization of Special Elements used in an SQL Command ('SQL Injection')",
      "analysis": "The packages/conform-validitystate/index.ts file contains a function parseField that parses form data and may not properly sanitize the input, which can lead to SQL injection vulnerabilities if the input is not properly validated.\n",
      "classification": "very promising",
      "cwe": "CWE-89",
      "function_names": [
        "parseField"
      ],
      "filenames": [
        "packages/conform-validitystate/index.ts"
      ]
    },
    {
      "headline": "Improper Neutralization of Input During Web Page Generation ('Cross-site Scripting')",
      "analysis": "The packages/conform-validitystate/index.ts file contains a function parseField that parses form data and may not properly sanitize the input, which can lead to XSS vulnerabilities if the input is not properly validated.\n",
      "classification": "very promising",
      "cwe": "CWE-79",
      "function_names": [
        "parseField"
      ],
      "filenames": [
        "packages/conform-validitystate/index.ts"
      ]
    }
  ],
  "scores": [
    {
      "stats": {
        "fn": 0,
        "tp": 1,
        "fp": 7
      },
      "mapping": {
        "0": "CVE-2024-32866"
      },
      "vuln_dates": {
        "CVE-2024-32866": "2024-04-23T21:15:48"
      },
      "scoring_model": "gpt-4o-2024-05-13",
      "type": "llm",
      "instruction_template_hash": "8998f09cf57fca8a6e03"
    },
    {
      "stats": {
        "fn": 0,
        "tp": 1,
        "fp": 7
      },
      "mapping": {
        "2": "CVE-2024-32866"
      },
      "vuln_dates": {
        "CVE-2024-32866": "2024-04-23T21:15:48"
      },
      "scoring_model": "claude-3-opus-20240229",
      "type": "llm",
      "instruction_template_hash": "245ace12b6361954d0a2"
    }
  ],
  "instruction_template_hash": "10c0163db4740318a544",
  "version": "0.1.0"
}
