{
  "commit": "16a41c377819fb57d8ecfbe2a65907a9de3fc17d",
  "repo_url": "https://github.com/jenkinsci/cloud-stats-plugin",
  "model": "gpt-4o-2024-05-13",
  "chunk_hashes": [
    "5dd9630ae80facea539a"
  ],
  "responses": [
    {
      "content": "```yaml\nleads:\n  - headline: \"Potential Command Injection in provisionAndFail()\"\n    analysis: |\n      The method `provisionAndFail()` in `CloudStatisticsTest` schedules a build and triggers provisioning using `triggerProvisioning()`. The cloud setup allows arbitrary execution of commands including potentially harmful commands since the `ThrowException` class can be extended to execute arbitrary code.\n    cwe: CWE-77\n    function_names:\n      - provisionAndFail\n    filenames:\n      - src/test/java/org/jenkinsci/plugins/cloudstats/CloudStatisticsTest.java\n    classification: very promising\n\n  - headline: \"Possible Unauthorized Data Access in CloudStatistics\"\n    analysis: |\n      The method `getActivities()` exposes all the activities without any proper authentication checks. This could lead to unauthorized users accessing data they shouldn't be able to see.\n    cwe: CWE-862\n    function_names:\n      - getActivities\n    filenames:\n      - src/main/java/org/jenkinsci/plugins/cloudstats/CloudStatistics.java\n    classification: slightly promising\n\n  - headline: \"Potential Null Pointer Dereference in getPhase()\"\n    analysis: |\n      The method `getPhase()` in `ProvisioningActivity` accesses a phase from a string without proper null checks. If the string does not map to an existing phase, it could cause a null pointer exception.\n    cwe: CWE-476\n    function_names:\n      - getPhase\n    filenames:\n      - src/main/java/org/jenkinsci/plugins/cloudstats/ProvisioningActivity.java\n    classification: slightly promising\n\n  - headline: \"ConcurrentModificationException Risk in CyclicThreadSafeCollection\"\n    analysis: |\n      The class `CyclicThreadSafeCollection` attempts to provide a thread-safe collection, but the way the `iterator()` and `toArray()` methods are designed can lead to `ConcurrentModificationException` if the underlying data is modified during iteration.\n    cwe: CWE-362\n    function_names:\n      - add\n      - iterator\n      - toArray\n    filenames:\n      - src/main/java/org/jenkinsci/plugins/cloudstats/CyclicThreadSafeCollection.java\n    classification: slightly promising\n\n  - headline: \"Missing Sensitive Data Masking in ExceptionAttachment\"\n    analysis: |\n      The `ExceptionAttachment` class uses `Functions.printThrowable()` to print exception details, which might include sensitive data. This data should be masked or sanitized to prevent exposure.\n    cwe: CWE-209\n    function_names:\n      - extractTitle\n    filenames:\n      - src/main/java/org/jenkinsci/plugins/cloudstats/PhaseExecutionAttachment.java\n    classification: slightly promising\n\n  - headline: \"Potential Insufficient Logging in SlaveCompletionDetector\"\n    analysis: |\n      The `onDeleted()` method in `SlaveCompletionDetector` doesn't log detailed information when it detects a completion. Logging more detailed information can help in debugging and audit trails.\n    cwe: CWE-778\n    function_names:\n      - onDeleted\n    filenames:\n      - src/main/java/org/jenkinsci/plugins/cloudstats/CloudStatistics.java\n    classification: slightly promising\n```",
      "date": "2024-06-12T18:03:16.376286",
      "usage": {
        "prompt_tokens": 36284,
        "completion_tokens": 645,
        "cost": 0.191095
      }
    }
  ],
  "leads": [
    {
      "headline": "Potential Command Injection in provisionAndFail()",
      "analysis": "The method provisionAndFail() in CloudStatisticsTest schedules a build and triggers provisioning using triggerProvisioning(). The cloud setup allows arbitrary execution of commands including potentially harmful commands since the ThrowException class can be extended to execute arbitrary code.\n",
      "classification": "very promising",
      "cwe": "CWE-77",
      "function_names": [
        "provisionAndFail"
      ],
      "filenames": [
        "src/test/java/org/jenkinsci/plugins/cloudstats/CloudStatisticsTest.java"
      ]
    },
    {
      "headline": "Possible Unauthorized Data Access in CloudStatistics",
      "analysis": "The method getActivities() exposes all the activities without any proper authentication checks. This could lead to unauthorized users accessing data they shouldn't be able to see.\n",
      "classification": "slightly promising",
      "cwe": "CWE-862",
      "function_names": [
        "getActivities"
      ],
      "filenames": [
        "src/main/java/org/jenkinsci/plugins/cloudstats/CloudStatistics.java"
      ]
    },
    {
      "headline": "Potential Null Pointer Dereference in getPhase()",
      "analysis": "The method getPhase() in ProvisioningActivity accesses a phase from a string without proper null checks. If the string does not map to an existing phase, it could cause a null pointer exception.\n",
      "classification": "slightly promising",
      "cwe": "CWE-476",
      "function_names": [
        "getPhase"
      ],
      "filenames": [
        "src/main/java/org/jenkinsci/plugins/cloudstats/ProvisioningActivity.java"
      ]
    },
    {
      "headline": "ConcurrentModificationException Risk in CyclicThreadSafeCollection",
      "analysis": "The class CyclicThreadSafeCollection attempts to provide a thread-safe collection, but the way the iterator() and toArray() methods are designed can lead to ConcurrentModificationException if the underlying data is modified during iteration.\n",
      "classification": "slightly promising",
      "cwe": "CWE-362",
      "function_names": [
        "add",
        "iterator",
        "toArray"
      ],
      "filenames": [
        "src/main/java/org/jenkinsci/plugins/cloudstats/CyclicThreadSafeCollection.java"
      ]
    },
    {
      "headline": "Missing Sensitive Data Masking in ExceptionAttachment",
      "analysis": "The ExceptionAttachment class uses Functions.printThrowable() to print exception details, which might include sensitive data. This data should be masked or sanitized to prevent exposure.\n",
      "classification": "slightly promising",
      "cwe": "CWE-209",
      "function_names": [
        "extractTitle"
      ],
      "filenames": [
        "src/main/java/org/jenkinsci/plugins/cloudstats/PhaseExecutionAttachment.java"
      ]
    },
    {
      "headline": "Potential Insufficient Logging in SlaveCompletionDetector",
      "analysis": "The onDeleted() method in SlaveCompletionDetector doesn't log detailed information when it detects a completion. Logging more detailed information can help in debugging and audit trails.\n",
      "classification": "slightly promising",
      "cwe": "CWE-778",
      "function_names": [
        "onDeleted"
      ],
      "filenames": [
        "src/main/java/org/jenkinsci/plugins/cloudstats/CloudStatistics.java"
      ]
    }
  ],
  "scores": [
    {
      "stats": {
        "fn": 1,
        "tp": 0,
        "fp": 1
      },
      "mapping": {},
      "vuln_dates": {
        "CVE-2021-21631": "2021-03-30T12:16:10"
      },
      "scoring_model": "claude-3-opus-20240229",
      "type": "llm",
      "instruction_template_hash": "245ace12b6361954d0a2"
    }
  ],
  "instruction_template_hash": "10c0163db4740318a544",
  "version": "0.1.0"
}
