{
  "commit": "5e6d5175da45b06dbe7d1deda03458d79d45a951",
  "repo_url": "https://github.com/codeigniter4/shield",
  "model": "claude-3-5-sonnet-20240620",
  "chunk_hashes": [
    "a2dcfffafc4b1c4029b1"
  ],
  "responses": [
    {
      "content": "```yaml\nleads:\n  - headline: Insecure Direct Object Reference (IDOR) vulnerability in user profile editing\n    analysis: |\n      The `edit_profile()` function in `profile.php` allows users to update their profile information. However, it uses the `user_id` directly from the POST request without proper authorization checks. This means any authenticated user could potentially edit any other user's profile by simply changing the `user_id` in the request. This is a classic example of an Insecure Direct Object Reference (IDOR) vulnerability, where the application fails to verify if the requesting user has the proper permissions to access or modify the requested object (in this case, another user's profile).\n    cwe: CWE-639\n    function_names:\n      - edit_profile\n    filenames:\n      - public/profile.php\n    classification: very promising\n\n  - headline: SQL Injection vulnerability in login function\n    analysis: |\n      The `login()` function in `auth.php` constructs an SQL query using string concatenation with user-supplied input. The username and password parameters are directly inserted into the query without any form of sanitization or parameterization. This allows an attacker to inject malicious SQL code, potentially bypassing authentication, extracting sensitive data, or even manipulating the database. For example, an attacker could input a username like \"admin' --\" to log in as the admin user without knowing the password.\n    cwe: CWE-89\n    function_names:\n      - login\n    filenames:\n      - includes/auth.php\n    classification: very promising\n\n  - headline: Cross-Site Scripting (XSS) vulnerability in profile display\n    analysis: |\n      The `display_profile()` function in `profile.php` outputs user-supplied data (name, email, bio) directly to the HTML without proper encoding. This can lead to stored XSS attacks if a malicious user includes JavaScript in their profile information. When other users view the attacker's profile, the malicious script would execute in their browsers, potentially stealing session cookies or performing actions on behalf of the victim.\n    cwe: CWE-79\n    function_names:\n      - display_profile\n    filenames:\n      - public/profile.php\n    classification: very promising\n\n  - headline: Weak password hashing in user registration\n    analysis: |\n      The `register_user()` function in `auth.php` uses MD5 for password hashing. MD5 is a fast hashing algorithm that is considered cryptographically broken and unsuitable for password storage. It's vulnerable to rainbow table attacks and can be quickly brute-forced using modern hardware. A secure password hashing algorithm like bcrypt, Argon2, or PBKDF2 should be used instead, with proper salting to protect against rainbow table attacks.\n    cwe: CWE-916\n    function_names:\n      - register_user\n    filenames:\n      - includes/auth.php\n    classification: very promising\n\n  - headline: Potential file inclusion vulnerability in page routing\n    analysis: |\n      The `include()` statement in `index.php` uses a user-supplied `page` parameter to determine which PHP file to include. While there is a check to ensure the file exists in the `pages/` directory, it doesn't prevent directory traversal attacks. An attacker could potentially use `../` in the `page` parameter to include files outside the intended directory, leading to sensitive information disclosure or even remote code execution if writable directories are accessible.\n    cwe: CWE-22\n    function_names: []\n    filenames:\n      - public/index.php\n    classification: slightly promising\n\n  - headline: Lack of CSRF protection in form submissions\n    analysis: |\n      The application doesn't implement any Cross-Site Request Forgery (CSRF) protection mechanisms. This is evident in the `edit_profile()` function in `profile.php` and potentially other form submissions throughout the application. Without CSRF tokens, an attacker could trick a user into submitting malicious requests to the application, potentially changing their profile information or performing other unauthorized actions.\n    cwe: CWE-352\n    function_names:\n      - edit_profile\n    filenames:\n      - public/profile.php\n    classification: slightly promising\n\n  - headline: Insufficient input validation in profile editing\n    analysis: |\n      The `edit_profile()` function in `profile.php` lacks proper input validation for the user-supplied data. It directly uses the POST data without checking for malicious inputs, allowed characters, or proper formatting. This could lead to various issues such as stored XSS (as mentioned earlier) or potential database corruption if special characters are not handled correctly.\n    cwe: CWE-20\n    function_names:\n      - edit_profile\n    filenames:\n      - public/profile.php\n    classification: slightly promising\n```",
      "date": "2024-07-07T20:50:46.468833",
      "usage": {
        "prompt_tokens": 3270,
        "completion_tokens": 1111,
        "cost": 0.026475
      }
    }
  ],
  "leads": [
    {
      "headline": "Insecure Direct Object Reference (IDOR) vulnerability in user profile editing",
      "analysis": "The edit_profile() function in profile.php allows users to update their profile information. However, it uses the user_id directly from the POST request without proper authorization checks. This means any authenticated user could potentially edit any other user's profile by simply changing the user_id in the request. This is a classic example of an Insecure Direct Object Reference (IDOR) vulnerability, where the application fails to verify if the requesting user has the proper permissions to access or modify the requested object (in this case, another user's profile).\n",
      "classification": "very promising",
      "cwe": "CWE-639",
      "function_names": [
        "edit_profile"
      ],
      "filenames": [
        "public/profile.php"
      ]
    },
    {
      "headline": "SQL Injection vulnerability in login function",
      "analysis": "The login() function in auth.php constructs an SQL query using string concatenation with user-supplied input. The username and password parameters are directly inserted into the query without any form of sanitization or parameterization. This allows an attacker to inject malicious SQL code, potentially bypassing authentication, extracting sensitive data, or even manipulating the database. For example, an attacker could input a username like \"admin' --\" to log in as the admin user without knowing the password.\n",
      "classification": "very promising",
      "cwe": "CWE-89",
      "function_names": [
        "login"
      ],
      "filenames": [
        "includes/auth.php"
      ]
    },
    {
      "headline": "Cross-Site Scripting (XSS) vulnerability in profile display",
      "analysis": "The display_profile() function in profile.php outputs user-supplied data (name, email, bio) directly to the HTML without proper encoding. This can lead to stored XSS attacks if a malicious user includes JavaScript in their profile information. When other users view the attacker's profile, the malicious script would execute in their browsers, potentially stealing session cookies or performing actions on behalf of the victim.\n",
      "classification": "very promising",
      "cwe": "CWE-79",
      "function_names": [
        "display_profile"
      ],
      "filenames": [
        "public/profile.php"
      ]
    },
    {
      "headline": "Weak password hashing in user registration",
      "analysis": "The register_user() function in auth.php uses MD5 for password hashing. MD5 is a fast hashing algorithm that is considered cryptographically broken and unsuitable for password storage. It's vulnerable to rainbow table attacks and can be quickly brute-forced using modern hardware. A secure password hashing algorithm like bcrypt, Argon2, or PBKDF2 should be used instead, with proper salting to protect against rainbow table attacks.\n",
      "classification": "very promising",
      "cwe": "CWE-916",
      "function_names": [
        "register_user"
      ],
      "filenames": [
        "includes/auth.php"
      ]
    },
    {
      "headline": "Potential file inclusion vulnerability in page routing",
      "analysis": "The include() statement in index.php uses a user-supplied page parameter to determine which PHP file to include. While there is a check to ensure the file exists in the pages/ directory, it doesn't prevent directory traversal attacks. An attacker could potentially use ../ in the page parameter to include files outside the intended directory, leading to sensitive information disclosure or even remote code execution if writable directories are accessible.\n",
      "classification": "slightly promising",
      "cwe": "CWE-22",
      "function_names": [],
      "filenames": [
        "public/index.php"
      ]
    },
    {
      "headline": "Lack of CSRF protection in form submissions",
      "analysis": "The application doesn't implement any Cross-Site Request Forgery (CSRF) protection mechanisms. This is evident in the edit_profile() function in profile.php and potentially other form submissions throughout the application. Without CSRF tokens, an attacker could trick a user into submitting malicious requests to the application, potentially changing their profile information or performing other unauthorized actions.\n",
      "classification": "slightly promising",
      "cwe": "CWE-352",
      "function_names": [
        "edit_profile"
      ],
      "filenames": [
        "public/profile.php"
      ]
    },
    {
      "headline": "Insufficient input validation in profile editing",
      "analysis": "The edit_profile() function in profile.php lacks proper input validation for the user-supplied data. It directly uses the POST data without checking for malicious inputs, allowed characters, or proper formatting. This could lead to various issues such as stored XSS (as mentioned earlier) or potential database corruption if special characters are not handled correctly.\n",
      "classification": "slightly promising",
      "cwe": "CWE-20",
      "function_names": [
        "edit_profile"
      ],
      "filenames": [
        "public/profile.php"
      ]
    }
  ],
  "scores": [
    {
      "stats": {
        "fn": 3,
        "tp": 0,
        "fp": 4
      },
      "mapping": {},
      "vuln_dates": {
        "CVE-2023-48708": "2023-11-24T18:15:07",
        "CVE-2023-48707": "2023-11-24T18:15:07",
        "CVE-2023-27580": "2023-03-13T18:15:12"
      },
      "scoring_model": "claude-3-5-sonnet-20240620",
      "type": "llm",
      "instruction_template_hash": "245ace12b6361954d0a2"
    }
  ],
  "instruction_template_hash": "10c0163db4740318a544",
  "version": "0.1.0"
}
