{
  "commit": "1d92eac8dea8efd4a271c0dd6ff59b0ef1d4dc9e",
  "repo_url": "https://github.com/jenkinsci/aws-codedeploy-plugin",
  "model": "claude-3-sonnet-20240229",
  "chunk_hashes": [
    "9cf6724ae4758a1b9ed7"
  ],
  "responses": [
    {
      "content": "```yaml\nleads:\n  - headline: Use of insecure HTTP protocol\n    analysis: |\n      The plugin uses the HTTP protocol to retrieve help content from external websites, which can potentially expose sensitive information transmitted over the network. The following URLs use the insecure HTTP protocol:\n      \n      - http://docs.aws.amazon.com/codedeploy/latest/userguide/how-to-create-application.html\n      - http://alpha-docs-aws.amazon.com/codedeploy/latest/userguide/how-to-create-application.html\n    cwe: CWE-319\n    function_names: []\n    filenames:\n      - src/main/resources/com/amazonaws/codedeploy/AWSCodeDeployPublisher/help-applicationName.html\n      - src/main/resources/com/amazonaws/codedeploy/AWSCodeDeployPublisher/help-deploymentGroupName.html\n    classification: slightly promising\n\n  - headline: Potential command injection vulnerability\n    analysis: |\n      The plugin uses the `Runtime.exec()` method to execute external commands, which can potentially lead to command injection vulnerabilities if the external command is constructed using untrusted input. However, the codebase does not appear to construct external commands using user input, so this vulnerability may not be exploitable in the current implementation.\n    cwe: CWE-78\n    function_names: []\n    filenames: []\n    classification: slightly promising\n\n  - headline: Use of insecure cryptographic algorithm\n    analysis: |\n      The plugin generates a random UUID using the `java.util.UUID` class, which may not be suitable for cryptographic purposes due to its lack of cryptographic strength and potential predictability. This could potentially lead to security vulnerabilities if the generated UUID is used for security-sensitive operations, such as generating encryption keys or session tokens.\n    cwe: CWE-327\n    function_names:\n      - setExternalId\n    filenames:\n      - src/main/java/com/amazonaws/codedeploy/AWSCodeDeployPublisher.DescriptorImpl.java\n    classification: slightly promising\n\n  - headline: Potential missing authentication in critical function\n    analysis: |\n      The `testConnection` method in the `AWSClients` class performs operations that require authentication, such as creating an S3 object and retrieving information about a CodeDeploy application. However, the method does not appear to perform any authentication checks or handle potential authentication failures explicitly. This could potentially lead to missing authentication vulnerabilities if the method is called with invalid or missing credentials.\n    cwe: CWE-306\n    function_names:\n      - testConnection\n    filenames:\n      - src/main/java/com/amazonaws/codedeploy/AWSClients.java\n    classification: slightly promising\n\n  - headline: Potential sensitive information exposure\n    analysis: |\n      The codebase logs AWS access and secret keys in cleartext, which could potentially expose sensitive information if the log files are accessed by unauthorized parties. While the keys are intended for use by the plugin during the build process, logging them in cleartext may not be a secure practice.\n    cwe: CWE-312\n    function_names:\n      - configure\n    filenames:\n      - src/main/java/com/amazonaws/codedeploy/AWSCodeDeployPublisher.DescriptorImpl.java\n    classification: very promising\n\n  - headline: Use of hard-coded credentials\n    analysis: |\n      The codebase contains hard-coded AWS access and secret keys in the `DescriptorImpl` class, which is a security vulnerability as these credentials can be easily extracted from the compiled code. Hard-coded credentials should be avoided, and more secure methods of credential storage and retrieval should be used instead.\n    cwe: CWE-798\n    function_names:\n      - configure\n      - getAwsSecretKey\n      - setAwsSecretKey\n      - getAwsAccessKey\n      - setAwsAccessKey\n    filenames:\n      - src/main/java/com/amazonaws/codedeploy/AWSCodeDeployPublisher.DescriptorImpl.java\n    classification: very promising\n\n  - headline: Potential insecure verification of data authenticity\n    analysis: |\n      The plugin performs file uploads to Amazon S3 and registers application revisions with AWS CodeDeploy based on these uploaded files. However, the codebase does not appear to perform any integrity checks or authenticity verification on the uploaded files or registered revisions. This could potentially lead to insecure verification of data authenticity vulnerabilities if an attacker can manipulate the uploaded files or registered revisions.\n    cwe: CWE-345\n    function_names:\n      - zipAndUpload\n      - registerRevision\n    filenames:\n      - src/main/java/com/amazonaws/codedeploy/AWSCodeDeployPublisher.java\n    classification: slightly promising\n\n  - headline: Potential lack of input validation\n    analysis: |\n      The plugin accepts user input through various configuration fields, such as S3 bucket name, application name, and deployment group name. However, the codebase does not appear to perform thorough input validation on these fields, which could potentially lead to input validation vulnerabilities if the input is not properly sanitized or validated.\n    cwe: CWE-20\n    function_names: []\n    filenames: []\n    classification: slightly promising\n```",
      "date": "2024-06-12T17:56:50.736395",
      "usage": {
        "prompt_tokens": 14906,
        "completion_tokens": 1255,
        "cost": 0.063543
      }
    }
  ],
  "leads": [
    {
      "headline": "Use of insecure HTTP protocol",
      "analysis": "The plugin uses the HTTP protocol to retrieve help content from external websites, which can potentially expose sensitive information transmitted over the network. The following URLs use the insecure HTTP protocol:\n\n- http://docs.aws.amazon.com/codedeploy/latest/userguide/how-to-create-application.html\n- http://alpha-docs-aws.amazon.com/codedeploy/latest/userguide/how-to-create-application.html\n",
      "classification": "slightly promising",
      "cwe": "CWE-319",
      "function_names": [],
      "filenames": [
        "src/main/resources/com/amazonaws/codedeploy/AWSCodeDeployPublisher/help-applicationName.html",
        "src/main/resources/com/amazonaws/codedeploy/AWSCodeDeployPublisher/help-deploymentGroupName.html"
      ]
    },
    {
      "headline": "Potential command injection vulnerability",
      "analysis": "The plugin uses the Runtime.exec() method to execute external commands, which can potentially lead to command injection vulnerabilities if the external command is constructed using untrusted input. However, the codebase does not appear to construct external commands using user input, so this vulnerability may not be exploitable in the current implementation.\n",
      "classification": "slightly promising",
      "cwe": "CWE-78",
      "function_names": [],
      "filenames": []
    },
    {
      "headline": "Use of insecure cryptographic algorithm",
      "analysis": "The plugin generates a random UUID using the java.util.UUID class, which may not be suitable for cryptographic purposes due to its lack of cryptographic strength and potential predictability. This could potentially lead to security vulnerabilities if the generated UUID is used for security-sensitive operations, such as generating encryption keys or session tokens.\n",
      "classification": "slightly promising",
      "cwe": "CWE-327",
      "function_names": [
        "setExternalId"
      ],
      "filenames": [
        "src/main/java/com/amazonaws/codedeploy/AWSCodeDeployPublisher.DescriptorImpl.java"
      ]
    },
    {
      "headline": "Potential missing authentication in critical function",
      "analysis": "The testConnection method in the AWSClients class performs operations that require authentication, such as creating an S3 object and retrieving information about a CodeDeploy application. However, the method does not appear to perform any authentication checks or handle potential authentication failures explicitly. This could potentially lead to missing authentication vulnerabilities if the method is called with invalid or missing credentials.\n",
      "classification": "slightly promising",
      "cwe": "CWE-306",
      "function_names": [
        "testConnection"
      ],
      "filenames": [
        "src/main/java/com/amazonaws/codedeploy/AWSClients.java"
      ]
    },
    {
      "headline": "Potential sensitive information exposure",
      "analysis": "The codebase logs AWS access and secret keys in cleartext, which could potentially expose sensitive information if the log files are accessed by unauthorized parties. While the keys are intended for use by the plugin during the build process, logging them in cleartext may not be a secure practice.\n",
      "classification": "very promising",
      "cwe": "CWE-312",
      "function_names": [
        "configure"
      ],
      "filenames": [
        "src/main/java/com/amazonaws/codedeploy/AWSCodeDeployPublisher.DescriptorImpl.java"
      ]
    },
    {
      "headline": "Use of hard-coded credentials",
      "analysis": "The codebase contains hard-coded AWS access and secret keys in the DescriptorImpl class, which is a security vulnerability as these credentials can be easily extracted from the compiled code. Hard-coded credentials should be avoided, and more secure methods of credential storage and retrieval should be used instead.\n",
      "classification": "very promising",
      "cwe": "CWE-798",
      "function_names": [
        "configure",
        "getAwsSecretKey",
        "setAwsSecretKey"
      ],
      "filenames": [
        "src/main/java/com/amazonaws/codedeploy/AWSCodeDeployPublisher.DescriptorImpl.java"
      ]
    },
    {
      "headline": "Potential insecure verification of data authenticity",
      "analysis": "The plugin performs file uploads to Amazon S3 and registers application revisions with AWS CodeDeploy based on these uploaded files. However, the codebase does not appear to perform any integrity checks or authenticity verification on the uploaded files or registered revisions. This could potentially lead to insecure verification of data authenticity vulnerabilities if an attacker can manipulate the uploaded files or registered revisions.\n",
      "classification": "slightly promising",
      "cwe": "CWE-345",
      "function_names": [
        "zipAndUpload",
        "registerRevision"
      ],
      "filenames": [
        "src/main/java/com/amazonaws/codedeploy/AWSCodeDeployPublisher.java"
      ]
    },
    {
      "headline": "Potential lack of input validation",
      "analysis": "The plugin accepts user input through various configuration fields, such as S3 bucket name, application name, and deployment group name. However, the codebase does not appear to perform thorough input validation on these fields, which could potentially lead to input validation vulnerabilities if the input is not properly sanitized or validated.\n",
      "classification": "slightly promising",
      "cwe": "CWE-20",
      "function_names": [],
      "filenames": []
    }
  ],
  "scores": [
    {
      "stats": {
        "fn": 1,
        "tp": 1,
        "fp": 0
      },
      "mapping": {
        "0": "CVE-2018-1000403",
        "1": "CVE-2018-1000403"
      },
      "vuln_dates": {
        "CVE-2018-1000402": "2018-07-09T13:29:00",
        "CVE-2018-1000403": "2018-07-09T13:29:00"
      },
      "scoring_model": "claude-3-opus-20240229",
      "type": "llm",
      "instruction_template_hash": "245ace12b6361954d0a2"
    }
  ],
  "instruction_template_hash": "10c0163db4740318a544",
  "version": "0.1.0"
}
