{
  "commit": "1a308463c7de8a89ff2c0b8518dd4d21c8247eb4",
  "repo_url": "https://github.com/jenkinsci/extra-columns-plugin",
  "model": "gpt-4o-2024-05-13",
  "chunk_hashes": [
    "6965c0833c98512460d9"
  ],
  "responses": [
    {
      "content": "```yaml\nleads:\n  - headline: \"Potential XSS in Description Formatting\"\n    analysis: |\n      The DescriptionColumn class does not sanitize or properly escape HTML content in the job descriptions. This can be exploited if an attacker is able to inject malicious scripts through job descriptions. Such scripts could be executed in the context of other users who view the job descriptions.\n    cwe: CWE-79\n    function_names:\n      - formatDescription\n      - getDescription\n      - getToolTip\n    filenames:\n      - src/main/java/jenkins/plugins/extracolumns/DescriptionColumn.java\n    classification: very promising\n\n  - headline: \"Use of Hardcoded Password in Code\"\n    analysis: |\n      In the DisableProjectColumn class, there is an alias mapping that binds a class name to another. This manipulation might hint at potential security misconfigurations related to obsolete mappings or legacy code defaults being preserved, posing a security risk when mixed with hardcoded administrative details.\n    cwe: CWE-798\n    function_names:\n      - DescriptorImpl.<init>\n    filenames:\n      - src/main/java/jenkins/plugins/extracolumns/DisableProjectColumn.java\n    classification: slightly promising\n\n  - headline: \"Insufficient Logging of Authentication Attempts\"\n    analysis: |\n      The UserNameColumn class retrieves the UserIdCause without logging this action. This might hinder security auditing, as there is no record of who accessed which job runs. It's important to maintain comprehensive logs for security audits.\n    cwe: CWE-522\n    function_names:\n      - getUserIdCause\n    filenames:\n      - src/main/java/jenkins/plugins/extracolumns/UserNameColumn.java\n    classification: slightly promising\n\n  - headline: \"Uncontrolled Resource Consumption\"\n    analysis: |\n      The BuildParametersColumn class concatenates parameter descriptions with a StringBuilder in getBuildParameters without implementing any controls or limits on data size. This could potentially lead to resource exhaustion issues if a job has a very large number of parameters.\n    cwe: CWE-400\n    function_names:\n      - getBuildParameters\n    filenames:\n      - src/main/java/jenkins/plugins/extracolumns/BuildParametersColumn.java\n    classification: slightly promising\n\n  - headline: \"Exposure of Sensitive Information in Logs\"\n    analysis: |\n      In the LastJobConfigurationModificationColumn class, logging configuration errors or warnings might inadvertently expose sensitive job configuration details in the logs. This is critical especially when logging exceptions that might contain job names, paths or other sensitive metadata.\n    cwe: CWE-532\n    function_names:\n      - getInfo\n    filenames:\n      - src/main/java/jenkins/plugins/extracolumns/LastJobConfigurationModificationColumn.java\n    classification: slightly promising\n```",
      "date": "2024-06-12T18:22:57.906528",
      "usage": {
        "prompt_tokens": 14753,
        "completion_tokens": 574,
        "cost": 0.082375
      }
    }
  ],
  "leads": [
    {
      "headline": "Potential XSS in Description Formatting",
      "analysis": "The DescriptionColumn class does not sanitize or properly escape HTML content in the job descriptions. This can be exploited if an attacker is able to inject malicious scripts through job descriptions. Such scripts could be executed in the context of other users who view the job descriptions.\n",
      "classification": "very promising",
      "cwe": "CWE-79",
      "function_names": [
        "formatDescription",
        "getDescription",
        "getToolTip"
      ],
      "filenames": [
        "src/main/java/jenkins/plugins/extracolumns/DescriptionColumn.java"
      ]
    },
    {
      "headline": "Use of Hardcoded Password in Code",
      "analysis": "In the DisableProjectColumn class, there is an alias mapping that binds a class name to another. This manipulation might hint at potential security misconfigurations related to obsolete mappings or legacy code defaults being preserved, posing a security risk when mixed with hardcoded administrative details.\n",
      "classification": "slightly promising",
      "cwe": "CWE-798",
      "function_names": [
        "DescriptorImpl.<init>"
      ],
      "filenames": [
        "src/main/java/jenkins/plugins/extracolumns/DisableProjectColumn.java"
      ]
    },
    {
      "headline": "Insufficient Logging of Authentication Attempts",
      "analysis": "The UserNameColumn class retrieves the UserIdCause without logging this action. This might hinder security auditing, as there is no record of who accessed which job runs. It's important to maintain comprehensive logs for security audits.\n",
      "classification": "slightly promising",
      "cwe": "CWE-522",
      "function_names": [
        "getUserIdCause"
      ],
      "filenames": [
        "src/main/java/jenkins/plugins/extracolumns/UserNameColumn.java"
      ]
    },
    {
      "headline": "Uncontrolled Resource Consumption",
      "analysis": "The BuildParametersColumn class concatenates parameter descriptions with a StringBuilder in getBuildParameters without implementing any controls or limits on data size. This could potentially lead to resource exhaustion issues if a job has a very large number of parameters.\n",
      "classification": "slightly promising",
      "cwe": "CWE-400",
      "function_names": [
        "getBuildParameters"
      ],
      "filenames": [
        "src/main/java/jenkins/plugins/extracolumns/BuildParametersColumn.java"
      ]
    },
    {
      "headline": "Exposure of Sensitive Information in Logs",
      "analysis": "In the LastJobConfigurationModificationColumn class, logging configuration errors or warnings might inadvertently expose sensitive job configuration details in the logs. This is critical especially when logging exceptions that might contain job names, paths or other sensitive metadata.\n",
      "classification": "slightly promising",
      "cwe": "CWE-532",
      "function_names": [
        "getInfo"
      ],
      "filenames": [
        "src/main/java/jenkins/plugins/extracolumns/LastJobConfigurationModificationColumn.java"
      ]
    }
  ],
  "scores": [
    {
      "stats": {
        "fn": 1,
        "tp": 1,
        "fp": 0
      },
      "mapping": {
        "0": "CVE-2016-3101"
      },
      "vuln_dates": {
        "CVE-2016-3101": "2017-02-09T15:59:00",
        "CVE-2021-21630": "2021-03-30T12:16:10"
      },
      "scoring_model": "claude-3-opus-20240229",
      "type": "llm",
      "instruction_template_hash": "245ace12b6361954d0a2"
    }
  ],
  "instruction_template_hash": "10c0163db4740318a544",
  "version": "0.1.0"
}
