{
  "commit": "493dc3d7c85f39c44e879941df9d5682865da109",
  "repo_url": "https://github.com/onsdigital/ras-collection-instrument",
  "model": "claude-3-5-sonnet-20240620",
  "chunk_hashes": [
    "a4309143678bbc515b9b"
  ],
  "responses": [
    {
      "content": "```yaml\nleads:\n  - headline: Hardcoded credentials in configuration\n    analysis: |\n      The application contains hardcoded default credentials in the config.py file. Specifically, there are default values set for SECURITY_USER_NAME and SECURITY_USER_PASSWORD. These credentials are used for basic authentication to protect API endpoints. Hardcoding credentials, even as defaults, is a security risk as it could lead to unauthorized access if the defaults are not changed in production.\n    cwe: CWE-798\n    function_names:\n      - Config\n    filenames:\n      - config.py\n    classification: very promising\n\n  - headline: Potential SQL injection vulnerability\n    analysis: |\n      The application uses string formatting to construct SQL queries in multiple places, such as in the CollectionInstrument class methods. This practice can lead to SQL injection vulnerabilities if user input is not properly sanitized before being inserted into queries. While the code does use some ORM methods, there are instances of raw SQL being executed with potentially unsanitized input.\n    cwe: CWE-89\n    function_names:\n      - _get_instruments_by_classifier\n      - upload_instrument\n    filenames:\n      - application/controllers/collection_instrument.py\n    classification: slightly promising\n\n  - headline: Insecure direct object reference\n    analysis: |\n      The application exposes endpoints that allow retrieving instruments by ID without proper authorization checks. For example, the /collectioninstrument/id/<instrument_id> endpoint retrieves and returns instrument data based solely on the provided ID, without verifying if the requester should have access to that specific instrument. This could allow attackers to access instruments they should not have permission to view.\n    cwe: CWE-639\n    function_names:\n      - collection_instrument_by_id\n    filenames:\n      - application/views/collection_instrument_view.py\n    classification: slightly promising\n\n  - headline: Insufficient input validation\n    analysis: |\n      The application lacks comprehensive input validation in several areas. For instance, when uploading collection instruments, there are only basic checks on file extension and name length, but no validation of the actual file contents. This could potentially allow malicious files to be uploaded and stored. Additionally, parameters like search strings and classifiers are used with minimal validation, which could lead to injection attacks or unexpected behavior.\n    cwe: CWE-20\n    function_names:\n      - upload_collection_instrument\n      - collection_instrument_by_search_string  \n    filenames:\n      - application/views/collection_instrument_view.py\n    classification: slightly promising\n\n  - headline: Sensitive data exposure in logs\n    analysis: |\n      The application logs sensitive information such as database connection strings, RabbitMQ credentials, and potentially PII like business reference numbers. While logging is important for debugging and monitoring, logging sensitive data increases the risk of unauthorized access to this information if log files are compromised. The logging should be reviewed to ensure sensitive data is not inadvertently exposed.\n    cwe: CWE-532\n    function_names: []\n    filenames:\n      - application/logger_config.py\n      - config.py\n    classification: slightly promising\n```",
      "date": "2024-07-08T08:06:42.246131",
      "usage": {
        "prompt_tokens": 43749,
        "completion_tokens": 732,
        "cost": 0.142227
      }
    }
  ],
  "leads": [
    {
      "headline": "Hardcoded credentials in configuration",
      "analysis": "The application contains hardcoded default credentials in the config.py file. Specifically, there are default values set for SECURITY_USER_NAME and SECURITY_USER_PASSWORD. These credentials are used for basic authentication to protect API endpoints. Hardcoding credentials, even as defaults, is a security risk as it could lead to unauthorized access if the defaults are not changed in production.\n",
      "classification": "very promising",
      "cwe": "CWE-798",
      "function_names": [
        "Config"
      ],
      "filenames": [
        "config.py"
      ]
    },
    {
      "headline": "Potential SQL injection vulnerability",
      "analysis": "The application uses string formatting to construct SQL queries in multiple places, such as in the CollectionInstrument class methods. This practice can lead to SQL injection vulnerabilities if user input is not properly sanitized before being inserted into queries. While the code does use some ORM methods, there are instances of raw SQL being executed with potentially unsanitized input.\n",
      "classification": "slightly promising",
      "cwe": "CWE-89",
      "function_names": [
        "_get_instruments_by_classifier",
        "upload_instrument"
      ],
      "filenames": [
        "application/controllers/collection_instrument.py"
      ]
    },
    {
      "headline": "Insecure direct object reference",
      "analysis": "The application exposes endpoints that allow retrieving instruments by ID without proper authorization checks. For example, the /collectioninstrument/id/<instrument_id> endpoint retrieves and returns instrument data based solely on the provided ID, without verifying if the requester should have access to that specific instrument. This could allow attackers to access instruments they should not have permission to view.\n",
      "classification": "slightly promising",
      "cwe": "CWE-639",
      "function_names": [
        "collection_instrument_by_id"
      ],
      "filenames": [
        "application/views/collection_instrument_view.py"
      ]
    },
    {
      "headline": "Insufficient input validation",
      "analysis": "The application lacks comprehensive input validation in several areas. For instance, when uploading collection instruments, there are only basic checks on file extension and name length, but no validation of the actual file contents. This could potentially allow malicious files to be uploaded and stored. Additionally, parameters like search strings and classifiers are used with minimal validation, which could lead to injection attacks or unexpected behavior.\n",
      "classification": "slightly promising",
      "cwe": "CWE-20",
      "function_names": [
        "upload_collection_instrument",
        "collection_instrument_by_search_string"
      ],
      "filenames": [
        "application/views/collection_instrument_view.py"
      ]
    },
    {
      "headline": "Sensitive data exposure in logs",
      "analysis": "The application logs sensitive information such as database connection strings, RabbitMQ credentials, and potentially PII like business reference numbers. While logging is important for debugging and monitoring, logging sensitive data increases the risk of unauthorized access to this information if log files are compromised. The logging should be reviewed to ensure sensitive data is not inadvertently exposed.\n",
      "classification": "slightly promising",
      "cwe": "CWE-532",
      "function_names": [],
      "filenames": [
        "application/logger_config.py",
        "config.py"
      ]
    }
  ],
  "scores": [
    {
      "stats": {
        "fn": 1,
        "tp": 0,
        "fp": 1
      },
      "mapping": {},
      "vuln_dates": {
        "CVE-2020-36762": "2023-07-18T15:15:11"
      },
      "scoring_model": "claude-3-5-sonnet-20240620",
      "type": "llm",
      "instruction_template_hash": "245ace12b6361954d0a2"
    }
  ],
  "instruction_template_hash": "10c0163db4740318a544",
  "version": "0.1.0"
}
