{
  "commit": "836b974c67a6e0213f68eca4dc18a2d25494907b",
  "repo_url": "https://github.com/python-social-auth/social-app-django",
  "model": "claude-3-sonnet-20240229",
  "chunk_hashes": [
    "2916b96533b3045b4ea0"
  ],
  "responses": [
    {
      "content": "```yaml\nleads:\n  - headline: Improper validation of array index (CWE-129)\n    analysis: |\n      The codebase does not appear to have any instances of improper validation of array indices. However, it is essential to validate array indices before accessing them to prevent out-of-bounds access, which can lead to application crashes or security vulnerabilities like information disclosure or code execution.\n    cwe: CWE-129\n    function_names: []\n    filenames: []\n    classification: not promising\n\n  - headline: Improper neutralization of input during web page generation ('Cross-site Scripting') (CWE-79)\n    analysis: |\n      The `render_template_string` function in `social_django/strategy.py` does not appear to sanitize or escape user input before rendering it as part of the HTML response. If unsanitized user input is included in the `html` parameter, it could lead to cross-site scripting (XSS) vulnerabilities.\n    cwe: CWE-79\n    function_names:\n      - render_template_string\n    filenames:\n      - social_django/strategy.py\n    classification: very promising\n\n  - headline: Use of a hard-coded password (CWE-798)\n    analysis: |\n      In `tests/test_admin.py`, the `setUp` method creates a superuser account with a hard-coded password `super-duper-test`. Using hard-coded credentials in code is a security risk, as it can lead to unauthorized access if the code is exposed or the credentials are discovered.\n    cwe: CWE-798\n    function_names:\n      - setUpTestData\n    filenames:\n      - tests/test_admin.py\n    classification: very promising\n\n  - headline: Potential SQL injection vulnerability (CWE-89)\n    analysis: |\n      The `UserSocialAuth.get_users_by_email` method in `social_django/models.py` constructs a Django ORM query using user-controlled data (the email parameter) without any input validation or sanitization. If the email parameter is not properly sanitized, it could potentially lead to SQL injection vulnerabilities.\n    cwe: CWE-89\n    function_names:\n      - get_users_by_email\n    filenames:\n      - social_django/models.py\n    classification: slightly promising\n\n  - headline: Improper handling of exceptions (CWE-755)\n    analysis: |\n      In `social_django/middleware.py`, the `process_exception` method catches and handles all exceptions raised by the `SocialAuthBaseException` class. However, it does not handle other types of exceptions that may occur, which could lead to unhandled exceptions and potential security vulnerabilities or application crashes.\n    cwe: CWE-755\n    function_names:\n      - process_exception\n    filenames:\n      - social_django/middleware.py\n    classification: slightly promising\n```\n\nThe provided codebase is a Django application for handling social authentication and integration with various social providers. While the codebase appears to be well-structured and follows Django conventions, there are a few potential security vulnerabilities that should be addressed:\n\n1. **Cross-Site Scripting (XSS)**: The `render_template_string` function in `social_django/strategy.py` does not sanitize or escape user input before rendering it as part of the HTML response. If unsanitized user input is included in the `html` parameter, it could lead to cross-site scripting (XSS) vulnerabilities.\n\n2. **Use of Hard-coded Credentials**: In `tests/test_admin.py`, a superuser account is created with a hard-coded password `super-duper-test`. Using hard-coded credentials in code is a security risk, as it can lead to unauthorized access if the code is exposed or the credentials are discovered.\n\n3. **Potential SQL Injection**: The `UserSocialAuth.get_users_by_email` method in `social_django/models.py` constructs a Django ORM query using user-controlled data (the email parameter) without any input validation or sanitization. If the email parameter is not properly sanitized, it could potentially lead to SQL injection vulnerabilities.\n\n4. **Improper Exception Handling**: In `social_django/middleware.py`, the `process_exception` method catches and handles all exceptions raised by the `SocialAuthBaseException` class. However, it does not handle other types of exceptions that may occur, which could lead to unhandled exceptions and potential security vulnerabilities or application crashes.\n\nWhile the codebase does not seem to have any instances of improper validation of array indices (CWE-129), it is still a best practice to validate array indices before accessing them to prevent out-of-bounds access, which can lead to application crashes or security vulnerabilities.\n\nIt is important to address these potential vulnerabilities by implementing proper input validation, sanitization, and escaping techniques, as well as following secure coding practices and handling exceptions appropriately.",
      "date": "2024-06-09T14:23:51.668283",
      "usage": {
        "prompt_tokens": 26687,
        "completion_tokens": 1148,
        "cost": 0.097281
      }
    }
  ],
  "leads": [
    {
      "headline": "Improper validation of array index (CWE-129)",
      "analysis": "The codebase does not appear to have any instances of improper validation of array indices. However, it is essential to validate array indices before accessing them to prevent out-of-bounds access, which can lead to application crashes or security vulnerabilities like information disclosure or code execution.\n",
      "classification": "not promising",
      "cwe": "CWE-129",
      "function_names": [],
      "filenames": []
    },
    {
      "headline": "Improper neutralization of input during web page generation ('Cross-site Scripting') (CWE-79)",
      "analysis": "The render_template_string function in social_django/strategy.py does not appear to sanitize or escape user input before rendering it as part of the HTML response. If unsanitized user input is included in the html parameter, it could lead to cross-site scripting (XSS) vulnerabilities.\n",
      "classification": "very promising",
      "cwe": "CWE-79",
      "function_names": [
        "render_template_string"
      ],
      "filenames": [
        "social_django/strategy.py"
      ]
    },
    {
      "headline": "Use of a hard-coded password (CWE-798)",
      "analysis": "In tests/test_admin.py, the setUp method creates a superuser account with a hard-coded password super-duper-test. Using hard-coded credentials in code is a security risk, as it can lead to unauthorized access if the code is exposed or the credentials are discovered.\n",
      "classification": "very promising",
      "cwe": "CWE-798",
      "function_names": [
        "setUpTestData"
      ],
      "filenames": [
        "tests/test_admin.py"
      ]
    },
    {
      "headline": "Potential SQL injection vulnerability (CWE-89)",
      "analysis": "The UserSocialAuth.get_users_by_email method in social_django/models.py constructs a Django ORM query using user-controlled data (the email parameter) without any input validation or sanitization. If the email parameter is not properly sanitized, it could potentially lead to SQL injection vulnerabilities.\n",
      "classification": "slightly promising",
      "cwe": "CWE-89",
      "function_names": [
        "get_users_by_email"
      ],
      "filenames": [
        "social_django/models.py"
      ]
    },
    {
      "headline": "Improper handling of exceptions (CWE-755)",
      "analysis": "In social_django/middleware.py, the process_exception method catches and handles all exceptions raised by the SocialAuthBaseException class. However, it does not handle other types of exceptions that may occur, which could lead to unhandled exceptions and potential security vulnerabilities or application crashes.\n",
      "classification": "slightly promising",
      "cwe": "CWE-755",
      "function_names": [
        "process_exception"
      ],
      "filenames": [
        "social_django/middleware.py"
      ]
    }
  ],
  "scores": [
    {
      "stats": {
        "fn": 1,
        "tp": 0,
        "fp": 2
      },
      "mapping": {},
      "vuln_dates": {
        "CVE-2024-32879": "2024-04-24T20:15:07"
      },
      "scoring_model": "gpt-4o-2024-05-13",
      "type": "llm",
      "instruction_template_hash": "8998f09cf57fca8a6e03"
    }
  ],
  "instruction_template_hash": "10c0163db4740318a544",
  "version": "0.1.0"
}
