{
  "commit": "73ccbe912fc1848957d8b2f6bbe5243804769d85",
  "repo_url": "https://github.com/filebrowser/filebrowser",
  "model": "gpt-4-turbo-2024-04-09",
  "chunk_hashes": [
    "c095a0fb9ce1bbff2ee1"
  ],
  "responses": [
    {
      "content": "```yaml\nleads:\n  - headline: Insecure handling of JWTs leading to potential unauthorized access\n    analysis: |\n      The system parses and stores JWT tokens in local storage without adequate validation and verification, which could result in unauthorized access if insecure tokens are injected. This also includes using JWTs without effective integrity and expiration checks, increasing the risk of expired or tampered tokens being misused.\n    cwe: CWE-287\n    function_names:\n      - validateLogin\n      - login\n      - renew\n    filenames:\n      - frontend/src/utils/auth.js\n    classification: very promising\n\n  - headline: Improper access control checks in router guards\n    analysis: |\n      The access control is defined by client-side route guards instead of server-side validation, which can be bypassed by accessing the JavaScript console or altering the client's state. An attacker could manipulate their local state to mimic permissions they do not possess, such as admin rights, enabling unauthorized access to restricted routes and possibly executing restricted actions.\n    cwe: CWE-284\n    function_names:\n      - beforeEach\n    filenames:\n      - frontend/src/router/index.js\n    classification: very promising\n\n  - headline: Exposure of sensitive information through console logs in production environment\n    analysis: |\n      The application logs sensitive error information to the console, which can leak potentially sensitive information about the system or its configuration, especially in a production environment where such details can be exploited for further attacks.\n    cwe: CWE-532\n    function_names:\n      - showSuccess\n      - showError\n      - loading\n      - done\n      - success\n    filenames:\n      - frontend/src/utils/vue.js\n      - frontend/src/utils/buttons.js\n    classification: slightly promising\n\n  - headline: Vulnerability to Cross-site Scripting (XSS) via dynamic insertion of unescaped external input into the DOM\n    analysis: |\n      The application dynamically generates certain parts of its DOM based on external input and configurations without proper sanitization and escaping. As a result, attackers could inject malicious scripts, potentially leading to XSS exploits where an attacker might steal session tokens or perform actions on behalf of the user.\n    cwe: CWE-79\n    function_names:\n      - start\n    filenames:\n      - frontend/src/main.js\n    classification: very promising\n\n  - headline: Lack of encryption in data storage exposing sensitive user information\n    analysis: |\n      Sensitive data including user details and authentication tokens are stored in plaintext within the client\u2019s local storage. This exposes users to various security threats, particularly on shared or insecure devices where malicious entities might read or corrupt the user's data.\n    cwe: CWE-311\n    function_names:\n      - parseToken\n      - login\n      - renew\n    filenames:\n      - frontend/src/utils/auth.js\n    classification: slightly promising\n\n  - headline: Weak server-side controls for file uploads and transfers could lead to arbitrary file write or uploads of unintended file types\n    analysis: |\n      The client-side application implements file uploads with minimal server-side control validation. This could allow attackers to upload dangerous file types, or conduct unintended actions via crafted requests, potentially leading to persistent XSS, server-side code execution, or system compromise if the server processes the uploaded files insecurely.\n    cwe: CWE-434\n    function_names:\n      - upload\n      - post\n    filenames:\n      - frontend/src/store/modules/upload.js\n      - frontend/src/api/files.js\n    classification: very promising\n```",
      "date": "2024-06-09T12:00:05.481127",
      "usage": {
        "prompt_tokens": 12732,
        "completion_tokens": 713,
        "cost": 0.14871
      }
    }
  ],
  "leads": [
    {
      "headline": "Insecure handling of JWTs leading to potential unauthorized access",
      "analysis": "The system parses and stores JWT tokens in local storage without adequate validation and verification, which could result in unauthorized access if insecure tokens are injected. This also includes using JWTs without effective integrity and expiration checks, increasing the risk of expired or tampered tokens being misused.\n",
      "classification": "very promising",
      "cwe": "CWE-287",
      "function_names": [
        "validateLogin",
        "login",
        "renew"
      ],
      "filenames": [
        "frontend/src/utils/auth.js"
      ]
    },
    {
      "headline": "Improper access control checks in router guards",
      "analysis": "The access control is defined by client-side route guards instead of server-side validation, which can be bypassed by accessing the JavaScript console or altering the client's state. An attacker could manipulate their local state to mimic permissions they do not possess, such as admin rights, enabling unauthorized access to restricted routes and possibly executing restricted actions.\n",
      "classification": "very promising",
      "cwe": "CWE-284",
      "function_names": [
        "beforeEach"
      ],
      "filenames": [
        "frontend/src/router/index.js"
      ]
    },
    {
      "headline": "Exposure of sensitive information through console logs in production environment",
      "analysis": "The application logs sensitive error information to the console, which can leak potentially sensitive information about the system or its configuration, especially in a production environment where such details can be exploited for further attacks.\n",
      "classification": "slightly promising",
      "cwe": "CWE-532",
      "function_names": [
        "showSuccess",
        "showError",
        "loading"
      ],
      "filenames": [
        "frontend/src/utils/vue.js",
        "frontend/src/utils/buttons.js"
      ]
    },
    {
      "headline": "Vulnerability to Cross-site Scripting (XSS) via dynamic insertion of unescaped external input into the DOM",
      "analysis": "The application dynamically generates certain parts of its DOM based on external input and configurations without proper sanitization and escaping. As a result, attackers could inject malicious scripts, potentially leading to XSS exploits where an attacker might steal session tokens or perform actions on behalf of the user.\n",
      "classification": "very promising",
      "cwe": "CWE-79",
      "function_names": [
        "start"
      ],
      "filenames": [
        "frontend/src/main.js"
      ]
    },
    {
      "headline": "Lack of encryption in data storage exposing sensitive user information",
      "analysis": "Sensitive data including user details and authentication tokens are stored in plaintext within the client\u2019s local storage. This exposes users to various security threats, particularly on shared or insecure devices where malicious entities might read or corrupt the user's data.\n",
      "classification": "slightly promising",
      "cwe": "CWE-311",
      "function_names": [
        "parseToken",
        "login",
        "renew"
      ],
      "filenames": [
        "frontend/src/utils/auth.js"
      ]
    },
    {
      "headline": "Weak server-side controls for file uploads and transfers could lead to arbitrary file write or uploads of unintended file types",
      "analysis": "The client-side application implements file uploads with minimal server-side control validation. This could allow attackers to upload dangerous file types, or conduct unintended actions via crafted requests, potentially leading to persistent XSS, server-side code execution, or system compromise if the server processes the uploaded files insecurely.\n",
      "classification": "very promising",
      "cwe": "CWE-434",
      "function_names": [
        "upload",
        "post"
      ],
      "filenames": [
        "frontend/src/store/modules/upload.js",
        "frontend/src/api/files.js"
      ]
    }
  ],
  "scores": [
    {
      "stats": {
        "fn": 2,
        "tp": 1,
        "fp": 3
      },
      "mapping": {
        "3": "CVE-2021-37794"
      },
      "vuln_dates": {
        "CVE-2023-39612": "2023-09-16T01:15:07",
        "CVE-2021-46398": "2022-02-04T16:15:07",
        "CVE-2021-37794": "2021-08-31T18:15:08"
      },
      "scoring_model": "gpt-4o-2024-05-13",
      "type": "llm",
      "instruction_template_hash": "8998f09cf57fca8a6e03"
    }
  ],
  "instruction_template_hash": "10c0163db4740318a544",
  "version": "0.1.0"
}
