{
  "commit": "1e4527ffe8688d4f5325283d7cf2cf2d61f14c6b",
  "repo_url": "https://github.com/npm/fstream",
  "model": "gpt-4-turbo-2024-04-09",
  "chunk_hashes": [
    "509e39e20a295e782862"
  ],
  "responses": [
    {
      "content": "```yaml\nleads:\n  - headline: Uncontrolled Resource Allocation in Directory Reader\n    analysis: |\n      The code fails to appropriately manage resource allocation when reading directories, particularly noticing the use of recursive filesystem operations without proper bounds checking in 'lib/dir-reader.js'. The `_read` method recursively processes entries without validating the depth or presence of cyclical links, which can cause excessive CPU and memory consumption. This vulnerability may be exploited to cause a Denial of Service (DoS) by crafting a filesystem structure that leads to infinite recursion or extremely deep nesting, overwhelming system resources.\n    cwe: CWE-400\n    function_names:\n      - DirReader.prototype._read\n    filenames:\n      - lib/dir-reader.js\n    classification: very promising\n\n  - headline: Insufficient Input Validation Leading to Arbitrary File Write\n    analysis: |\n      The code in 'lib/file-writer.js' and 'lib/dir-writer.js' allows for writing files and directories based on user input without sufficient validation of the input path, which might include directory traversal characters or other anomalies. This vulnerability could allow an attacker to write files to arbitrary locations on the filesystem subject to the privileges of the running process, potentially leading to privilege escalation or unauthorized information disclosure if system files or configuration files are overwritten.\n    cwe: CWE-73\n    function_names:\n      - FileWriter\n      - DirWriter\n    filenames:\n      - lib/file-writer.js\n      - lib/dir-writer.js\n    classification: very promising\n\n  - headline: Insecure Default File and Directory Permissions\n    analysis: |\n      The application sets potentially insecure default permissions for new files and directories as seen in 'lib/writer.js'. The permissions are calculated using a bitwise operation that does not properly account for restrictive permissions, potentially leaving sensitive files readable or writable by unauthorized users. This could lead to unauthorized access, modification of sensitive data, or execution of untrusted code.\n    cwe: CWE-276\n    function_names:\n      - Writer\n    filenames:\n      - lib/writer.js\n    classification: slightly promising\n\n  - headline: Potential Command Injection via Path Manipulation\n    analysis: |\n      Due to improper sanitization of file paths in various modules including file writers and directory readers, there exists a potential for command injection. For example, 'lib/dir-writer.js' accepts external input to determine filesystem paths without sufficiently cleansing the input for special characters or escape sequences. Attackers can exploit this behavior to execute unintended system commands, thus altering the flow or state of the application.\n    cwe: CWE-77\n    function_names:\n      - DirWriter._create\n    filenames:\n      - lib/dir-writer.js\n    classification: slightly promising\n\n  - headline: Race Condition in Proxy Object Handling\n    analysis: |\n      The code in 'lib/proxy-writer.js' handles asynchronous operations on proxy objects without ensuring proper synchronization. This can lead to a race condition where multiple threads or operations could corrupt the state of a single proxy object, leading to inconsistent data writes or unexpected behavior. This race condition is particularly concerning in a multi-threaded or high-load environment.\n    cwe: CWE-362\n    function_names:\n      - ProxyWriter._addProxy\n    filenames:\n      - lib/proxy-writer.js\n    classification: not promising\n\n  - headline: Explicit Error Messages Containing Sensitive Information\n    analysis: |\n      Several parts of the application, including error handlers in 'lib/abstract.js', emit detailed error messages including sensitive file system paths and potentially internal state or debugging information. These messages could be exposed to an end user or attacker, leading to information disclosure that could facilitate further attacks.\n    cwe: CWE-209\n    function_names:\n      - Abstract.prototype.error\n    filenames:\n      - lib/abstract.js\n    classification: slightly promising\n```",
      "date": "2024-06-13T10:35:29.372136",
      "usage": {
        "prompt_tokens": 18717,
        "completion_tokens": 783,
        "cost": 0.21066
      }
    }
  ],
  "leads": [
    {
      "headline": "Uncontrolled Resource Allocation in Directory Reader",
      "analysis": "The code fails to appropriately manage resource allocation when reading directories, particularly noticing the use of recursive filesystem operations without proper bounds checking in 'lib/dir-reader.js'. The _read method recursively processes entries without validating the depth or presence of cyclical links, which can cause excessive CPU and memory consumption. This vulnerability may be exploited to cause a Denial of Service (DoS) by crafting a filesystem structure that leads to infinite recursion or extremely deep nesting, overwhelming system resources.\n",
      "classification": "very promising",
      "cwe": "CWE-400",
      "function_names": [
        "DirReader.prototype._read"
      ],
      "filenames": [
        "lib/dir-reader.js"
      ]
    },
    {
      "headline": "Insufficient Input Validation Leading to Arbitrary File Write",
      "analysis": "The code in 'lib/file-writer.js' and 'lib/dir-writer.js' allows for writing files and directories based on user input without sufficient validation of the input path, which might include directory traversal characters or other anomalies. This vulnerability could allow an attacker to write files to arbitrary locations on the filesystem subject to the privileges of the running process, potentially leading to privilege escalation or unauthorized information disclosure if system files or configuration files are overwritten.\n",
      "classification": "very promising",
      "cwe": "CWE-73",
      "function_names": [
        "FileWriter",
        "DirWriter"
      ],
      "filenames": [
        "lib/file-writer.js",
        "lib/dir-writer.js"
      ]
    },
    {
      "headline": "Insecure Default File and Directory Permissions",
      "analysis": "The application sets potentially insecure default permissions for new files and directories as seen in 'lib/writer.js'. The permissions are calculated using a bitwise operation that does not properly account for restrictive permissions, potentially leaving sensitive files readable or writable by unauthorized users. This could lead to unauthorized access, modification of sensitive data, or execution of untrusted code.\n",
      "classification": "slightly promising",
      "cwe": "CWE-276",
      "function_names": [
        "Writer"
      ],
      "filenames": [
        "lib/writer.js"
      ]
    },
    {
      "headline": "Potential Command Injection via Path Manipulation",
      "analysis": "Due to improper sanitization of file paths in various modules including file writers and directory readers, there exists a potential for command injection. For example, 'lib/dir-writer.js' accepts external input to determine filesystem paths without sufficiently cleansing the input for special characters or escape sequences. Attackers can exploit this behavior to execute unintended system commands, thus altering the flow or state of the application.\n",
      "classification": "slightly promising",
      "cwe": "CWE-77",
      "function_names": [
        "DirWriter._create"
      ],
      "filenames": [
        "lib/dir-writer.js"
      ]
    },
    {
      "headline": "Race Condition in Proxy Object Handling",
      "analysis": "The code in 'lib/proxy-writer.js' handles asynchronous operations on proxy objects without ensuring proper synchronization. This can lead to a race condition where multiple threads or operations could corrupt the state of a single proxy object, leading to inconsistent data writes or unexpected behavior. This race condition is particularly concerning in a multi-threaded or high-load environment.\n",
      "classification": "not promising",
      "cwe": "CWE-362",
      "function_names": [
        "ProxyWriter._addProxy"
      ],
      "filenames": [
        "lib/proxy-writer.js"
      ]
    },
    {
      "headline": "Explicit Error Messages Containing Sensitive Information",
      "analysis": "Several parts of the application, including error handlers in 'lib/abstract.js', emit detailed error messages including sensitive file system paths and potentially internal state or debugging information. These messages could be exposed to an end user or attacker, leading to information disclosure that could facilitate further attacks.\n",
      "classification": "slightly promising",
      "cwe": "CWE-209",
      "function_names": [
        "Abstract.prototype.error"
      ],
      "filenames": [
        "lib/abstract.js"
      ]
    }
  ],
  "scores": [
    {
      "stats": {
        "fn": 0,
        "tp": 1,
        "fp": 1
      },
      "mapping": {
        "1": "CVE-2019-13173"
      },
      "vuln_dates": {
        "CVE-2019-13173": "2019-07-02T20:15:11"
      },
      "scoring_model": "claude-3-opus-20240229",
      "type": "llm",
      "instruction_template_hash": "245ace12b6361954d0a2"
    },
    {
      "stats": {
        "fn": 0,
        "tp": 1,
        "fp": 1
      },
      "mapping": {
        "1": "CVE-2019-13173"
      },
      "vuln_dates": {
        "CVE-2019-13173": "2019-07-02T20:15:11"
      },
      "scoring_model": "claude-3-5-sonnet-20240620",
      "type": "llm",
      "instruction_template_hash": "245ace12b6361954d0a2"
    }
  ],
  "instruction_template_hash": "10c0163db4740318a544",
  "version": "0.1.0"
}
