{
  "commit": "43714f0463a14ef9d2cee55d689d2bc934e9e7f3",
  "repo_url": "https://github.com/jenkinsci/http-request-plugin",
  "model": "gpt-4-turbo-2024-04-09",
  "chunk_hashes": [
    "d31cbb4440a21d1220fc"
  ],
  "responses": [
    {
      "content": "```yaml\nleads:\n  - headline: \"Sensitive Data Exposure Through Log Files\"\n    analysis: |\n      The application logs sensitive information which might include user credentials, tokens, or personal data in plaintext form. This can lead to unauthorized access if the logs are mishandled, improperly protected, or exposed to inappropriate parties. The `before.add()` function in various test files manipulates user credentials and other HTTP request details, which could be logged at various debug levels or by third-party services unintentionally.\n    cwe: CWE-532\n    function_names:\n      - \"before.add()\"\n    filenames:\n      - \"src/test/java/jenkins/plugins/http_request/HttpRequestRoundTripTest.java\"\n    classification: \"very promising\"\n  - headline: \"Lack of Input Validation on HTTP Request Headers and Body Content\"\n    analysis: |\n      There is no proper validation implemented for HTTP request headers or body contents before processing them. This flaw could potentially allow attackers to inject malicious content, leading to various forms of attacks such as SQL injection, Cross-site Scripting (XSS), Remote Code Execution, etc., depending on how the input data is being processed or interpreted by the receiving end.\n    cwe: CWE-20\n    function_names:\n      - \"HttpRequest.doCreateRequestBase()\"\n      - \"HttpRequest.resolveHeaders()\"\n    filenames:\n      - \"src/main/java/jenkins/plugins/http_request/util/HttpClientUtil.java\"\n      - \"src/main/java/jenkins/plugins/http_request/HttpRequest.java\"\n    classification: \"slightly promising\"\n  - headline: \"Improper Access Control on Critical Functions\"\n    analysis: |\n      Critical functions such as sending out HTTP requests and handling authentication procedures are not sufficiently guarded against improper access which might allow unauthorized users or systems to invoke these methods without restrictions. This could lead to unauthorized access to sensitive functions or data.\n    cwe: CWE-285\n    function_names:\n      - \"HttpRequest.authenticate()\"\n      - \"HttpRequest.executeRequest()\"\n    filenames:\n      - \"src/main/java/jenkins/plugins/http_request/HttpRequestExecution.java\"\n    classification: \"very promising\"\n  - headline: \"Vulnerable Dependency Introduced through Deprecated Authentication Classes\"\n    analysis: |\n      The system still maintains deprecated authentication classes for backward compatibility. These deprecated classes may depend on older, unsupported libraries or methods, potentially leading to vulnerabilities due to lack of updates or patches for found exploits.\n    cwe: CWE-1104\n    function_names:\n      - \"BasicDigestAuthentication.authenticate()\"\n    filenames:\n      - \"src/main/java/jenkins/plugins/http_request/auth/BasicDigestAuthentication.java\"\n    classification: \"not promising\"\n  - headline: \"SSL/TLS Certificate Validation Bypass\"\n    analysis: |\n      The code provides an option to bypass SSL/TLS certificate validation checks entirely, offering a configuration that could inadvertently suppress important security checks. This switch, if toggled, exposes communications to potential Man-In-The-Middle (MITM) attacks.\n    cwe: CWE-295\n    function_names:\n      - \"HttpRequestExecution.configureTimeoutAndSsl()\"\n    filenames:\n      - \"src/main/java/jenkins/plugins/http_request/HttpRequestExecution.java\"\n    classification: \"very promising\"\n  - headline: \"Insecure Data Transmission and Storage\"\n    analysis: |\n      Data such as API keys, passwords, and other sensitive information is transmitted in plaintext over HTTP and may also be stored or logged in an unsecured manner. This exposure can lead to unauthorized disclosure of sensitive information.\n    cwe: CWE-319\n    function_names:\n      - \"createRequestBase()\"\n    filenames:\n      - \"src/main/java/jenkins/plugins/http_request/util/HttpClientUtil.java\"\n    classification: \"very promising\"\n```",
      "date": "2024-06-14T14:17:51.033559",
      "usage": {
        "prompt_tokens": 48109,
        "completion_tokens": 752,
        "cost": 0.50365
      }
    }
  ],
  "leads": [
    {
      "headline": "Sensitive Data Exposure Through Log Files",
      "analysis": "The application logs sensitive information which might include user credentials, tokens, or personal data in plaintext form. This can lead to unauthorized access if the logs are mishandled, improperly protected, or exposed to inappropriate parties. The before.add() function in various test files manipulates user credentials and other HTTP request details, which could be logged at various debug levels or by third-party services unintentionally.\n",
      "classification": "very promising",
      "cwe": "CWE-532",
      "function_names": [
        "before.add()"
      ],
      "filenames": [
        "src/test/java/jenkins/plugins/http_request/HttpRequestRoundTripTest.java"
      ]
    },
    {
      "headline": "Lack of Input Validation on HTTP Request Headers and Body Content",
      "analysis": "There is no proper validation implemented for HTTP request headers or body contents before processing them. This flaw could potentially allow attackers to inject malicious content, leading to various forms of attacks such as SQL injection, Cross-site Scripting (XSS), Remote Code Execution, etc., depending on how the input data is being processed or interpreted by the receiving end.\n",
      "classification": "slightly promising",
      "cwe": "CWE-20",
      "function_names": [
        "HttpRequest.doCreateRequestBase()",
        "HttpRequest.resolveHeaders()"
      ],
      "filenames": [
        "src/main/java/jenkins/plugins/http_request/util/HttpClientUtil.java",
        "src/main/java/jenkins/plugins/http_request/HttpRequest.java"
      ]
    },
    {
      "headline": "Improper Access Control on Critical Functions",
      "analysis": "Critical functions such as sending out HTTP requests and handling authentication procedures are not sufficiently guarded against improper access which might allow unauthorized users or systems to invoke these methods without restrictions. This could lead to unauthorized access to sensitive functions or data.\n",
      "classification": "very promising",
      "cwe": "CWE-285",
      "function_names": [
        "HttpRequest.authenticate()",
        "HttpRequest.executeRequest()"
      ],
      "filenames": [
        "src/main/java/jenkins/plugins/http_request/HttpRequestExecution.java"
      ]
    },
    {
      "headline": "Vulnerable Dependency Introduced through Deprecated Authentication Classes",
      "analysis": "The system still maintains deprecated authentication classes for backward compatibility. These deprecated classes may depend on older, unsupported libraries or methods, potentially leading to vulnerabilities due to lack of updates or patches for found exploits.\n",
      "classification": "not promising",
      "cwe": "CWE-1104",
      "function_names": [
        "BasicDigestAuthentication.authenticate()"
      ],
      "filenames": [
        "src/main/java/jenkins/plugins/http_request/auth/BasicDigestAuthentication.java"
      ]
    },
    {
      "headline": "SSL/TLS Certificate Validation Bypass",
      "analysis": "The code provides an option to bypass SSL/TLS certificate validation checks entirely, offering a configuration that could inadvertently suppress important security checks. This switch, if toggled, exposes communications to potential Man-In-The-Middle (MITM) attacks.\n",
      "classification": "very promising",
      "cwe": "CWE-295",
      "function_names": [
        "HttpRequestExecution.configureTimeoutAndSsl()"
      ],
      "filenames": [
        "src/main/java/jenkins/plugins/http_request/HttpRequestExecution.java"
      ]
    },
    {
      "headline": "Insecure Data Transmission and Storage",
      "analysis": "Data such as API keys, passwords, and other sensitive information is transmitted in plaintext over HTTP and may also be stored or logged in an unsecured manner. This exposure can lead to unauthorized disclosure of sensitive information.\n",
      "classification": "very promising",
      "cwe": "CWE-319",
      "function_names": [
        "createRequestBase()"
      ],
      "filenames": [
        "src/main/java/jenkins/plugins/http_request/util/HttpClientUtil.java"
      ]
    }
  ],
  "scores": [
    {
      "stats": {
        "fn": 1,
        "tp": 0,
        "fp": 4
      },
      "mapping": {},
      "vuln_dates": {
        "CVE-2022-36901": "2022-07-27T15:15:09"
      },
      "scoring_model": "claude-3-opus-20240229",
      "type": "llm",
      "instruction_template_hash": "245ace12b6361954d0a2"
    },
    {
      "stats": {
        "fn": 0,
        "tp": 1,
        "fp": 3
      },
      "mapping": {
        "3": "CVE-2022-36901"
      },
      "vuln_dates": {
        "CVE-2022-36901": "2022-07-27T15:15:09"
      },
      "scoring_model": "claude-3-5-sonnet-20240620",
      "type": "llm",
      "instruction_template_hash": "245ace12b6361954d0a2"
    }
  ],
  "instruction_template_hash": "10c0163db4740318a544",
  "version": "0.1.0"
}
