{
  "commit": "13293140eaa6c2896d17c3fb2b62f780b5331ffb",
  "repo_url": "https://github.com/opensuse/obs-service-tar_scm",
  "model": "gpt-4o-2024-05-13",
  "chunk_hashes": [
    "684e2966b35746a8df1e"
  ],
  "responses": [
    {
      "content": "```yaml\nleads:\n  - headline: \"Potential Code Injection Vulnerability in tar_scm.py\"\n    analysis: |\n      The script `tar_scm.py` currently uses `sys.argv` to directly pass command-line arguments to `TarSCM.run()`.\n      If these arguments are not adequately sanitized, it could lead to a command injection vulnerability as the attackers could potentially manipulate the arguments, leading to arbitrary command execution in the underlying system.\n    cwe: CWE-94\n    function_names:\n      - \"run\"\n      - \"main\"\n    filenames:\n      - \"tar_scm.py\"\n      - \"TarSCM/__init__.py\"\n      - \"tests/test.py\"\n    classification: \"very promising\"\n  \n  - headline: \"Potential Path Traversal in Helper's `run_cmd`\"\n    analysis: |\n      In the file `TarSCM/helpers.py`, the `run_cmd` function executes commands using `subprocess.Popen` with parameters directly constructed from input arguments. If any of these inputs include untrusted values, it could result in path traversal or arbitrary command execution.\n      Specifically, the function does not sanitize `cmd` and `cwd`, which can be controlled externally. This can lead to directory traversal attacks, potentially accessing restricted files or directories.\n    cwe: CWE-22\n    function_names:\n      - \"run_cmd\"\n    filenames:\n      - \"TarSCM/helpers.py\"\n    classification: \"very promising\"\n    \n  - headline: \"Improper Neutralization of Special Elements in os.popen Call\"\n    analysis: |\n      In `tests/testenv.py`, the `run_cmd` method utilizes `os.popen` to execute shell commands. This form of command execution without proper sanitization or neutralization of special elements leaves the application vulnerable to shell injection attacks. Malicious inputs can exploit this to execute arbitrary shell commands.\n    cwe: CWE-78\n    function_names:\n      - \"run_cmd\"\n    filenames:\n      - \"tests/testenv.py\"\n    classification: \"very promising\"\n    \n  - headline: \"Weak Randomization in Temporary Directory Creation\"\n    analysis: |\n      The class `Scm`, specifically in the `prepare_clone_dir` method, uses `tempfile.mkdtemp` for temporary directory creation without additional security considerations. This can lead to predictable directory names making it vulnerable to symlink attacks. An attacker could potentially create a symlink from the predictable temp directory to another file location, causing the file access to be redirected.\n    cwe: CWE-338\n    function_names:\n      - \"prepare_clone_dir\"\n    filenames:\n      - \"TarSCM/scm/base.py\"\n    classification: \"slightly promising\"\n    \n  - headline: \"Insecure File Permissions on Temporary Files\"\n    analysis: |\n      The `Changes.write_changes` method in `TarSCM/changes.py` creates temporary files for changes updates without specifying secure file permissions. This omission might result in these temporary files being created with permissions that are too permissive, potentially exposing sensitive information to unauthorized users.\n    cwe: CWE-276\n    function_names:\n      - \"write_changes\"\n    filenames:\n      - \"TarSCM/changes.py\"\n    classification: \"slightly promising\"\n    \n  - headline: \"Cleartext Storage of Sensitive Information in Configuration Files\"\n    analysis: |\n      The configuration files across the repository, such as `.oscrc` files used for storing email credentials, potentially store sensitive information like API URLs and email addresses in clear text. This exposure can make it easier for attackers to intercept or exploit these credentials.\n    cwe: CWE-312\n    filenames:\n      - \"all configuration files\"\n    function_names: []\n    classification: \"slightly promising\"\n    \n  - headline: \"Code Vulnerability in XML Parsing Without Proper Validation\"\n    analysis: |\n      The class `Changes` in `TarSCM/changes.py` uses the `ET.parse` method for XML parsing without validating the input file effectively. This can leave the system vulnerable to XML external entity (XXE) processing attacks, where an attacker can craft malicious XML content to exploit system resources.\n    cwe: CWE-611\n    function_names:\n      - \"parse_servicedata_xml\"\n    filenames:\n      - \"TarSCM/changes.py\"\n    classification: \"slightly promising\"\n```",
      "date": "2024-06-13T10:53:21.252941",
      "usage": {
        "prompt_tokens": 43207,
        "completion_tokens": 890,
        "cost": 0.229385
      }
    }
  ],
  "leads": [
    {
      "headline": "Potential Code Injection Vulnerability in tar_scm.py",
      "analysis": "The script tar_scm.py currently uses sys.argv to directly pass command-line arguments to TarSCM.run().\nIf these arguments are not adequately sanitized, it could lead to a command injection vulnerability as the attackers could potentially manipulate the arguments, leading to arbitrary command execution in the underlying system.\n",
      "classification": "very promising",
      "cwe": "CWE-94",
      "function_names": [
        "run",
        "main"
      ],
      "filenames": [
        "tar_scm.py",
        "TarSCM/__init__.py",
        "tests/test.py"
      ]
    },
    {
      "headline": "Potential Path Traversal in Helper's run_cmd",
      "analysis": "In the file TarSCM/helpers.py, the run_cmd function executes commands using subprocess.Popen with parameters directly constructed from input arguments. If any of these inputs include untrusted values, it could result in path traversal or arbitrary command execution.\nSpecifically, the function does not sanitize cmd and cwd, which can be controlled externally. This can lead to directory traversal attacks, potentially accessing restricted files or directories.\n",
      "classification": "very promising",
      "cwe": "CWE-22",
      "function_names": [
        "run_cmd"
      ],
      "filenames": [
        "TarSCM/helpers.py"
      ]
    },
    {
      "headline": "Improper Neutralization of Special Elements in os.popen Call",
      "analysis": "In tests/testenv.py, the run_cmd method utilizes os.popen to execute shell commands. This form of command execution without proper sanitization or neutralization of special elements leaves the application vulnerable to shell injection attacks. Malicious inputs can exploit this to execute arbitrary shell commands.\n",
      "classification": "very promising",
      "cwe": "CWE-78",
      "function_names": [
        "run_cmd"
      ],
      "filenames": [
        "tests/testenv.py"
      ]
    },
    {
      "headline": "Weak Randomization in Temporary Directory Creation",
      "analysis": "The class Scm, specifically in the prepare_clone_dir method, uses tempfile.mkdtemp for temporary directory creation without additional security considerations. This can lead to predictable directory names making it vulnerable to symlink attacks. An attacker could potentially create a symlink from the predictable temp directory to another file location, causing the file access to be redirected.\n",
      "classification": "slightly promising",
      "cwe": "CWE-338",
      "function_names": [
        "prepare_clone_dir"
      ],
      "filenames": [
        "TarSCM/scm/base.py"
      ]
    },
    {
      "headline": "Insecure File Permissions on Temporary Files",
      "analysis": "The Changes.write_changes method in TarSCM/changes.py creates temporary files for changes updates without specifying secure file permissions. This omission might result in these temporary files being created with permissions that are too permissive, potentially exposing sensitive information to unauthorized users.\n",
      "classification": "slightly promising",
      "cwe": "CWE-276",
      "function_names": [
        "write_changes"
      ],
      "filenames": [
        "TarSCM/changes.py"
      ]
    },
    {
      "headline": "Cleartext Storage of Sensitive Information in Configuration Files",
      "analysis": "The configuration files across the repository, such as .oscrc files used for storing email credentials, potentially store sensitive information like API URLs and email addresses in clear text. This exposure can make it easier for attackers to intercept or exploit these credentials.\n",
      "classification": "slightly promising",
      "cwe": "CWE-312",
      "function_names": [],
      "filenames": [
        "all configuration files"
      ]
    },
    {
      "headline": "Code Vulnerability in XML Parsing Without Proper Validation",
      "analysis": "The class Changes in TarSCM/changes.py uses the ET.parse method for XML parsing without validating the input file effectively. This can leave the system vulnerable to XML external entity (XXE) processing attacks, where an attacker can craft malicious XML content to exploit system resources.\n",
      "classification": "slightly promising",
      "cwe": "CWE-611",
      "function_names": [
        "parse_servicedata_xml"
      ],
      "filenames": [
        "TarSCM/changes.py"
      ]
    }
  ],
  "scores": [
    {
      "stats": {
        "fn": 0,
        "tp": 1,
        "fp": 2
      },
      "mapping": {
        "1": "CVE-2018-12473"
      },
      "vuln_dates": {
        "CVE-2018-12473": "2018-10-02T15:29:00"
      },
      "scoring_model": "claude-3-opus-20240229",
      "type": "llm",
      "instruction_template_hash": "245ace12b6361954d0a2"
    },
    {
      "stats": {
        "fn": 0,
        "tp": 1,
        "fp": 2
      },
      "mapping": {
        "1": "CVE-2018-12473"
      },
      "vuln_dates": {
        "CVE-2018-12473": "2018-10-02T15:29:00"
      },
      "scoring_model": "claude-3-5-sonnet-20240620",
      "type": "llm",
      "instruction_template_hash": "245ace12b6361954d0a2"
    }
  ],
  "instruction_template_hash": "10c0163db4740318a544",
  "version": "0.1.0"
}
