{
  "commit": "35aa1494b3cb0554e33c26d998b024790c80d997",
  "repo_url": "https://github.com/orc/discount",
  "model": "gpt-4o-2024-05-13",
  "chunk_hashes": [
    "f738e2307daa0de922cf"
  ],
  "responses": [
    {
      "content": "```yaml\nleads:\n  - headline: Unsanitized URL allows potential XSS\n    analysis: |\n      The `printlinkyref` function in \"generate.c\" does not properly sanitize the URL before placing it in an HTML attribute. This could allow an attacker to inject a malicious URL that executes JavaScript when clicked.\n    cwe: CWE-79\n    function_names:\n      - printlinkyref\n    filenames:\n      - generate.c\n    classification: very promising\n  \n  - headline: Command Injection via mkd_e_url callback\n    analysis: |\n      The use of an external `mkd_e_url` callback function could allow an attacker to inject arbitrary shell commands if user input is passed unchecked to the callback. This can be exploited if the callback is used in the context of shell command execution.\n    cwe: CWE-78\n    function_names:\n      - e_basename\n    filenames:\n      - basename.c\n      - markdown.c\n    classification: slightly promising\n\n  - headline: Buffer Overflow in amalloc function\n    analysis: |\n      The custom memory allocation functions `amalloc`, `acalloc`, and `arealloc` in \"amalloc.c\" do not properly check the sizes being allocated. This can lead to buffer overflows if an attacker can control the size parameter passed to these functions.\n    cwe: CWE-120\n    function_names:\n      - amalloc\n      - acalloc\n      - arealloc\n    filenames:\n      - amalloc.c\n    classification: very promising\n\n  - headline: Insecure Temporary File Creation in hoptset function\n    analysis: |\n      In \"gethopt.c\", the `hoptset` function uses temporary files but does not ensure that these files are created securely. This could allow a local attacker to perform a symlink attack and gain access to or modify sensitive information.\n    cwe: CWE-377\n    function_names:\n      - hoptset\n    filenames:\n      - gethopt.c\n    classification: very promising\n\n  - headline: Format String Vulnerability in Csprintf function\n    analysis: |\n      The `Csprintf` function in \"Csio.c\" uses the `vsnprintf` function but does not properly handle the format string provided by the user. This might lead to format string vulnerabilities if user input is passed unchecked.\n    cwe: CWE-134\n    function_names:\n      - Csprintf\n    filenames:\n      - Csio.c\n    classification: very promising\n\n```",
      "date": "2024-06-14T15:06:26.120005",
      "usage": {
        "prompt_tokens": 81595,
        "completion_tokens": 514,
        "cost": 0.415685
      }
    }
  ],
  "leads": [
    {
      "headline": "Unsanitized URL allows potential XSS",
      "analysis": "The printlinkyref function in \"generate.c\" does not properly sanitize the URL before placing it in an HTML attribute. This could allow an attacker to inject a malicious URL that executes JavaScript when clicked.\n",
      "classification": "very promising",
      "cwe": "CWE-79",
      "function_names": [
        "printlinkyref"
      ],
      "filenames": [
        "generate.c"
      ]
    },
    {
      "headline": "Command Injection via mkd_e_url callback",
      "analysis": "The use of an external mkd_e_url callback function could allow an attacker to inject arbitrary shell commands if user input is passed unchecked to the callback. This can be exploited if the callback is used in the context of shell command execution.\n",
      "classification": "slightly promising",
      "cwe": "CWE-78",
      "function_names": [
        "e_basename"
      ],
      "filenames": [
        "basename.c",
        "markdown.c"
      ]
    },
    {
      "headline": "Buffer Overflow in amalloc function",
      "analysis": "The custom memory allocation functions amalloc, acalloc, and arealloc in \"amalloc.c\" do not properly check the sizes being allocated. This can lead to buffer overflows if an attacker can control the size parameter passed to these functions.\n",
      "classification": "very promising",
      "cwe": "CWE-120",
      "function_names": [
        "amalloc",
        "acalloc",
        "arealloc"
      ],
      "filenames": [
        "amalloc.c"
      ]
    },
    {
      "headline": "Insecure Temporary File Creation in hoptset function",
      "analysis": "In \"gethopt.c\", the hoptset function uses temporary files but does not ensure that these files are created securely. This could allow a local attacker to perform a symlink attack and gain access to or modify sensitive information.\n",
      "classification": "very promising",
      "cwe": "CWE-377",
      "function_names": [
        "hoptset"
      ],
      "filenames": [
        "gethopt.c"
      ]
    },
    {
      "headline": "Format String Vulnerability in Csprintf function",
      "analysis": "The Csprintf function in \"Csio.c\" uses the vsnprintf function but does not properly handle the format string provided by the user. This might lead to format string vulnerabilities if user input is passed unchecked.\n",
      "classification": "very promising",
      "cwe": "CWE-134",
      "function_names": [
        "Csprintf"
      ],
      "filenames": [
        "Csio.c"
      ]
    }
  ],
  "scores": [
    {
      "stats": {
        "fn": 4,
        "tp": 0,
        "fp": 4
      },
      "mapping": {},
      "vuln_dates": {
        "CVE-2018-11503": "2018-05-26T21:29:00",
        "CVE-2018-11468": "2018-05-25T13:29:00",
        "CVE-2018-11504": "2018-05-26T21:29:00",
        "CVE-2018-12495": "2018-06-15T18:29:00"
      },
      "scoring_model": "claude-3-opus-20240229",
      "type": "llm",
      "instruction_template_hash": "245ace12b6361954d0a2"
    }
  ],
  "instruction_template_hash": "10c0163db4740318a544",
  "version": "0.1.0"
}
