{
  "commit": "003dfa8122541972ad23999eafffdc40932cd5d5",
  "repo_url": "https://github.com/dreamyguy/validate-color",
  "model": "gpt-4o-2024-05-13",
  "chunk_hashes": [
    "575407589a604469c391"
  ],
  "responses": [
    {
      "content": "```yaml\nleads:\n  - headline: \"Command Injection in Service Worker Registration\"\n    analysis: |\n      In `src/serviceWorker.js`, URLs are constructed using values from environment variables and user input without adequate validation. This might lead to command injection if an attacker can control the environment variables or input values. Specifically, there's a risk when URLs are derived from `process.env.PUBLIC_URL` as this could be manipulated to include malicious input.\n    cwe: CWE-78\n    function_names:\n      - register\n      - registerValidSW\n    filenames:\n      - src/serviceWorker.js\n    classification: very promising\n\n  - headline: \"Potential Insecure Random Number Generation\"\n    analysis: |\n      In `src/validate-color/index.js`, various regex patterns for color validation include random number checks that are potentially insecure. Improper use of regex can lead to ReDoS (regular expression denial of service) attacks where improper input could cause the regex engine to consume excessive resources, thus leading to a denial of service.\n    cwe: CWE-1333\n    function_names:\n      - validateHTMLColorHsl\n      - validateHTMLColorHwb\n      - validateHTMLColorLab\n    filenames:\n      - src/validate-color/index.js\n    classification: slightly promising\n\n  - headline: \"Potential Information Exposure through Logs\"\n    analysis: |\n      In `src/utils/copyToClipboardUtil.js`, the `copyToClipboard` function logs the content that is being copied to the clipboard using `console.log`. This could potentially expose sensitive information to unauthorized actors if the logs are accessed. Logging functions like these may put sensitive information at risk if not controlled or sanitized properly.\n    cwe: CWE-532\n    function_names:\n      - copyToClipboard\n    filenames:\n      - src/utils/copyToClipboardUtil.js\n    classification: slightly promising\n\n  - headline: \"Unrestricted File Upload in build-npm script\"\n    analysis: |\n      In the `bin/postBuildNpm.sh` script, there's a command to copy files (`cp src/validate-color/index.d.ts lib/index.d.ts`) without any validation or restriction. This may allow unauthorized file uploads which can compromise the integrity of the build process, leading to potential code execution attacks.\n    cwe: CWE-434\n    function_names: []\n    filenames:\n      - bin/postBuildNpm.sh\n    classification: not promising\n```",
      "date": "2024-06-12T16:03:30.997862",
      "usage": {
        "prompt_tokens": 15345,
        "completion_tokens": 494,
        "cost": 0.084135
      }
    }
  ],
  "leads": [
    {
      "headline": "Command Injection in Service Worker Registration",
      "analysis": "In src/serviceWorker.js, URLs are constructed using values from environment variables and user input without adequate validation. This might lead to command injection if an attacker can control the environment variables or input values. Specifically, there's a risk when URLs are derived from process.env.PUBLIC_URL as this could be manipulated to include malicious input.\n",
      "classification": "very promising",
      "cwe": "CWE-78",
      "function_names": [
        "register",
        "registerValidSW"
      ],
      "filenames": [
        "src/serviceWorker.js"
      ]
    },
    {
      "headline": "Potential Insecure Random Number Generation",
      "analysis": "In src/validate-color/index.js, various regex patterns for color validation include random number checks that are potentially insecure. Improper use of regex can lead to ReDoS (regular expression denial of service) attacks where improper input could cause the regex engine to consume excessive resources, thus leading to a denial of service.\n",
      "classification": "slightly promising",
      "cwe": "CWE-1333",
      "function_names": [
        "validateHTMLColorHsl",
        "validateHTMLColorHwb",
        "validateHTMLColorLab"
      ],
      "filenames": [
        "src/validate-color/index.js"
      ]
    },
    {
      "headline": "Potential Information Exposure through Logs",
      "analysis": "In src/utils/copyToClipboardUtil.js, the copyToClipboard function logs the content that is being copied to the clipboard using console.log. This could potentially expose sensitive information to unauthorized actors if the logs are accessed. Logging functions like these may put sensitive information at risk if not controlled or sanitized properly.\n",
      "classification": "slightly promising",
      "cwe": "CWE-532",
      "function_names": [
        "copyToClipboard"
      ],
      "filenames": [
        "src/utils/copyToClipboardUtil.js"
      ]
    },
    {
      "headline": "Unrestricted File Upload in build-npm script",
      "analysis": "In the bin/postBuildNpm.sh script, there's a command to copy files (cp src/validate-color/index.d.ts lib/index.d.ts) without any validation or restriction. This may allow unauthorized file uploads which can compromise the integrity of the build process, leading to potential code execution attacks.\n",
      "classification": "not promising",
      "cwe": "CWE-434",
      "function_names": [],
      "filenames": [
        "bin/postBuildNpm.sh"
      ]
    }
  ],
  "scores": [
    {
      "stats": {
        "fn": 1,
        "tp": 0,
        "fp": 1
      },
      "mapping": {},
      "vuln_dates": {
        "CVE-2021-40892": "2022-06-24T14:15:07"
      },
      "scoring_model": "claude-3-opus-20240229",
      "type": "llm",
      "instruction_template_hash": "245ace12b6361954d0a2"
    }
  ],
  "instruction_template_hash": "10c0163db4740318a544",
  "version": "0.1.0"
}
