{
  "commit": "26703f4dd9798a493149b5a45517afc7bde6eb1c",
  "repo_url": "https://github.com/mansuf/mangadex-downloader",
  "model": "claude-3-opus-20240229",
  "chunk_hashes": [
    "7ca2164ca97959219b37"
  ],
  "responses": [
    {
      "content": "Here is the YAML output with potential security vulnerabilities in the provided Python codebase:\n\n```yaml\nleads:\n  - headline: Potential arbitrary code execution via user-controlled format strings\n    analysis: |\n      In mangadex_downloader/format/comic_book.py, the generate_Comicinfo function uses\n      unsanitized user input from the manga and chapter objects to construct an XML string\n      using string formatting. If the manga title, alternate names, authors, artists, \n      genres, summary, or chapter fields contain format string specifiers like %s, this \n      could allow arbitrary code execution.\n    cwe: CWE-134\n    function_names:\n      - generate_Comicinfo\n    filenames:\n      - mangadex_downloader/format/comic_book.py\n    classification: very promising\n\n  - headline: Potential arbitrary file write via ZipFile\n    analysis: |\n      Several places use the zipfile module to write downloaded chapter images to CBZ files.\n      The ZipFile is opened in append mode, and the filename is controlled by user input like \n      the chapter name and page number. If the filename is not properly sanitized, this could\n      allow writing arbitrary files. For example, a chapter name containing \"../../\" could \n      cause the CBZ to be written outside the intended directory.\n    cwe: CWE-22\n    function_names:\n      - main\n    filenames:\n      - mangadex_downloader/format/comic_book.py\n      - mangadex_downloader/format/sevenzip.py  \n    classification: slightly promising\n\n  - headline: Use of unsafe YAML load\n    analysis: |\n      The yaml.unsafe_load function is used to parse YAML input in several places. This function\n      is documented as unsafe and can lead to arbitrary code execution if the YAML contains \n      certain tags. However, the YAML appears to be loading a configuration file, not untrusted\n      user input, so the risk is likely low.\n    cwe: CWE-20\n    function_names:\n      - _load\n    filenames:\n      - mangadex_downloader/config.py\n    classification: not promising\n\n  - headline: Potential command injection in subprocess calls\n    analysis: |\n      The subprocess module is used in several places to execute external commands. If any \n      arguments to these commands are derived from user input and not properly escaped, it \n      could allow arbitrary command injection. However, the arguments appear to be hard-coded\n      or derived from the installation environment, not from untrusted input.\n    cwe: CWE-78\n    function_names:\n      - update_app\n      - main\n    filenames:  \n      - mangadex_downloader/update.py\n      - mangadex_downloader/__init__.py\n    classification: not promising\n\n  - headline: Potential XSS via user-controlled strings in GUI\n    analysis: |\n      User-controlled strings like manga titles, chapter names, etc. are displayed in a GUI \n      progress bar and log messages. If this GUI is web-based and the strings are not HTML-escaped, \n      it could allow stored XSS. However, the GUI appears to be a CLI not a web app, so the \n      risk of XSS is low.\n    cwe: CWE-79 \n    function_names:\n      - download\n      - _update_progress_bar  \n    filenames:\n      - mangadex_downloader/main.py\n      - mangadex_downloader/downloader.py\n    classification: not promising\n\n```\n\nThe most concerning vulnerability is the potential for arbitrary code execution via format string injection in the generate_Comicinfo function. The other leads around arbitrary file write, YAML parsing, command injection and XSS appear less concerning based on the context, but would still be worth further investigation to ensure user input is properly validated and sanitized in all cases.",
      "date": "2024-06-13T09:58:39.062599",
      "usage": {
        "prompt_tokens": 85591,
        "completion_tokens": 910,
        "cost": 1.352115
      }
    }
  ],
  "leads": [
    {
      "headline": "Potential arbitrary code execution via user-controlled format strings",
      "analysis": "In mangadex_downloader/format/comic_book.py, the generate_Comicinfo function uses\nunsanitized user input from the manga and chapter objects to construct an XML string\nusing string formatting. If the manga title, alternate names, authors, artists, \ngenres, summary, or chapter fields contain format string specifiers like %s, this \ncould allow arbitrary code execution.\n",
      "classification": "very promising",
      "cwe": "CWE-134",
      "function_names": [
        "generate_Comicinfo"
      ],
      "filenames": [
        "mangadex_downloader/format/comic_book.py"
      ]
    },
    {
      "headline": "Potential arbitrary file write via ZipFile",
      "analysis": "Several places use the zipfile module to write downloaded chapter images to CBZ files.\nThe ZipFile is opened in append mode, and the filename is controlled by user input like \nthe chapter name and page number. If the filename is not properly sanitized, this could\nallow writing arbitrary files. For example, a chapter name containing \"../../\" could \ncause the CBZ to be written outside the intended directory.\n",
      "classification": "slightly promising",
      "cwe": "CWE-22",
      "function_names": [
        "main"
      ],
      "filenames": [
        "mangadex_downloader/format/comic_book.py",
        "mangadex_downloader/format/sevenzip.py"
      ]
    },
    {
      "headline": "Use of unsafe YAML load",
      "analysis": "The yaml.unsafe_load function is used to parse YAML input in several places. This function\nis documented as unsafe and can lead to arbitrary code execution if the YAML contains \ncertain tags. However, the YAML appears to be loading a configuration file, not untrusted\nuser input, so the risk is likely low.\n",
      "classification": "not promising",
      "cwe": "CWE-20",
      "function_names": [
        "_load"
      ],
      "filenames": [
        "mangadex_downloader/config.py"
      ]
    },
    {
      "headline": "Potential command injection in subprocess calls",
      "analysis": "The subprocess module is used in several places to execute external commands. If any \narguments to these commands are derived from user input and not properly escaped, it \ncould allow arbitrary command injection. However, the arguments appear to be hard-coded\nor derived from the installation environment, not from untrusted input.\n",
      "classification": "not promising",
      "cwe": "CWE-78",
      "function_names": [
        "update_app",
        "main"
      ],
      "filenames": [
        "mangadex_downloader/update.py",
        "mangadex_downloader/__init__.py"
      ]
    },
    {
      "headline": "Potential XSS via user-controlled strings in GUI",
      "analysis": "User-controlled strings like manga titles, chapter names, etc. are displayed in a GUI \nprogress bar and log messages. If this GUI is web-based and the strings are not HTML-escaped, \nit could allow stored XSS. However, the GUI appears to be a CLI not a web app, so the \nrisk of XSS is low.\n",
      "classification": "not promising",
      "cwe": "CWE-79",
      "function_names": [
        "download",
        "_update_progress_bar"
      ],
      "filenames": [
        "mangadex_downloader/main.py",
        "mangadex_downloader/downloader.py"
      ]
    }
  ],
  "scores": [
    {
      "stats": {
        "fn": 1,
        "tp": 0,
        "fp": 1
      },
      "mapping": {},
      "vuln_dates": {
        "CVE-2022-36082": "2022-09-07T22:15:08"
      },
      "scoring_model": "claude-3-opus-20240229",
      "type": "llm",
      "instruction_template_hash": "245ace12b6361954d0a2"
    },
    {
      "stats": {
        "fn": 1,
        "tp": 0,
        "fp": 1
      },
      "mapping": {},
      "vuln_dates": {
        "CVE-2022-36082": "2022-09-07T22:15:08"
      },
      "scoring_model": "claude-3-5-sonnet-20240620",
      "type": "llm",
      "instruction_template_hash": "245ace12b6361954d0a2"
    }
  ],
  "instruction_template_hash": "10c0163db4740318a544",
  "version": "0.1.0"
}
