{
  "commit": "13edf4d6e598e2c8121956cccfb76e568d0b9722",
  "repo_url": "https://github.com/jenkinsci/cvs-plugin",
  "model": "gpt-4o-2024-05-13",
  "chunk_hashes": [
    "2ab44d0df8bd38b6438e"
  ],
  "responses": [
    {
      "content": "```yaml\nleads:\n  - headline: Use of Hardcoded CVS Credentials\n    analysis: |\n      The code contains several instances where CVS repository connections are established using hardcoded usernames and passwords. This practice is insecure as it risks exposing sensitive information, such as login credentials, to anyone with access to the codebase.\n    cwe: CWE-798\n    function_names: []\n    filenames:\n      - src/test/java/hudson/scm/CvsChangeLogHelperTest.java\n      - src/test/java/hudson/scm/IntegrationTest.java\n      - src/test/java/hudson/scm/LegacyConvertorTest.java\n    classification: very promising\n\n  - headline: Potential Path Traversal Issue Due to Lack of Input Sanitization\n    analysis: |\n      The code contains file handling operations where user input is used to construct file paths without adequate sanitization. This can potentially lead to path traversal attacks, allowing an attacker to access unauthorized files and directories on the server.\n    cwe: CWE-22\n    function_names:\n      - getFileContents\n    filenames:\n      - src/test/java/hudson/scm/CvsChangeLogHelperTest.java\n    classification: very promising\n\n  - headline: XML External Entity (XXE) Injection Vulnerability\n    analysis: |\n      The code uses XML parsers without disabling external entity resolution. This leaves the code vulnerable to XXE, which can be exploited to read arbitrary files on the server, perform SSRF attacks, and more.\n    cwe: CWE-611\n    function_names: []\n    filenames:\n      - src/test/java/hudson/scm/CVSChangeLogParserTest.java\n    classification: slightly promising\n\n  - headline: Insecure Pseudo-Random Number Generation\n    analysis: |\n      The code relies on java.util.Random for generating unique identifiers or tokens, which is not cryptographically secure. This can make it easier for attackers to predict the values and potentially exploit them.\n    cwe: CWE-338\n    function_names: []\n    filenames: []\n    classification: slightly promising\n\n  - headline: Insufficient Validation of User Input\n    analysis: |\n      Several instances in the code where user input is used in file operations, network communications, and command executions without sufficient validation. This could potentially allow malicious inputs to exploit the system.\n    cwe: CWE-20\n    function_names: []\n    filenames:\n      - src/main/java/hudson/scm/CvsTagsParamDefinition.java\n    classification: slightly promising\n\n  - headline: Use of a Hardcoded Key for SSH Authentication\n    analysis: |\n      The code sets up SSH authentication with hardcoded paths for private keys, which can be insecure if the keys or paths are exposed. Proper key management practices should be enforced to avoid unauthorized access.\n    cwe: CWE-798\n    function_names: []\n    filenames:\n      - src/main/java/hudson/scm/CVSRepositoryBrowser.java\n      - src/main/java/hudson/scm/AbstractCvs.java\n    classification: slightly promising\n\n  - headline: Improper Resource Cleanup\n    analysis: |\n      The code does not always perform adequate cleanup of resources such as file streams, sockets, and processes. This can lead to resource leaks, impacting system performance and reliability.\n    cwe: CWE-404\n    function_names:\n      - run\n      - saveChange\n    filenames:\n      - src/test/java/hudson/scm/IntegrationTest.java\n      - src/main/java/hudson/scm/CvsLog.java\n    classification: slightly promising\n```",
      "date": "2024-06-12T18:12:44.776828",
      "usage": {
        "prompt_tokens": 78426,
        "completion_tokens": 734,
        "cost": 0.40314
      }
    }
  ],
  "leads": [
    {
      "headline": "Use of Hardcoded CVS Credentials",
      "analysis": "The code contains several instances where CVS repository connections are established using hardcoded usernames and passwords. This practice is insecure as it risks exposing sensitive information, such as login credentials, to anyone with access to the codebase.\n",
      "classification": "very promising",
      "cwe": "CWE-798",
      "function_names": [],
      "filenames": [
        "src/test/java/hudson/scm/CvsChangeLogHelperTest.java",
        "src/test/java/hudson/scm/IntegrationTest.java",
        "src/test/java/hudson/scm/LegacyConvertorTest.java"
      ]
    },
    {
      "headline": "Potential Path Traversal Issue Due to Lack of Input Sanitization",
      "analysis": "The code contains file handling operations where user input is used to construct file paths without adequate sanitization. This can potentially lead to path traversal attacks, allowing an attacker to access unauthorized files and directories on the server.\n",
      "classification": "very promising",
      "cwe": "CWE-22",
      "function_names": [
        "getFileContents"
      ],
      "filenames": [
        "src/test/java/hudson/scm/CvsChangeLogHelperTest.java"
      ]
    },
    {
      "headline": "XML External Entity (XXE) Injection Vulnerability",
      "analysis": "The code uses XML parsers without disabling external entity resolution. This leaves the code vulnerable to XXE, which can be exploited to read arbitrary files on the server, perform SSRF attacks, and more.\n",
      "classification": "slightly promising",
      "cwe": "CWE-611",
      "function_names": [],
      "filenames": [
        "src/test/java/hudson/scm/CVSChangeLogParserTest.java"
      ]
    },
    {
      "headline": "Insecure Pseudo-Random Number Generation",
      "analysis": "The code relies on java.util.Random for generating unique identifiers or tokens, which is not cryptographically secure. This can make it easier for attackers to predict the values and potentially exploit them.\n",
      "classification": "slightly promising",
      "cwe": "CWE-338",
      "function_names": [],
      "filenames": []
    },
    {
      "headline": "Insufficient Validation of User Input",
      "analysis": "Several instances in the code where user input is used in file operations, network communications, and command executions without sufficient validation. This could potentially allow malicious inputs to exploit the system.\n",
      "classification": "slightly promising",
      "cwe": "CWE-20",
      "function_names": [],
      "filenames": [
        "src/main/java/hudson/scm/CvsTagsParamDefinition.java"
      ]
    },
    {
      "headline": "Use of a Hardcoded Key for SSH Authentication",
      "analysis": "The code sets up SSH authentication with hardcoded paths for private keys, which can be insecure if the keys or paths are exposed. Proper key management practices should be enforced to avoid unauthorized access.\n",
      "classification": "slightly promising",
      "cwe": "CWE-798",
      "function_names": [],
      "filenames": [
        "src/main/java/hudson/scm/CVSRepositoryBrowser.java",
        "src/main/java/hudson/scm/AbstractCvs.java"
      ]
    },
    {
      "headline": "Improper Resource Cleanup",
      "analysis": "The code does not always perform adequate cleanup of resources such as file streams, sockets, and processes. This can lead to resource leaks, impacting system performance and reliability.\n",
      "classification": "slightly promising",
      "cwe": "CWE-404",
      "function_names": [
        "run",
        "saveChange"
      ],
      "filenames": [
        "src/test/java/hudson/scm/IntegrationTest.java",
        "src/main/java/hudson/scm/CvsLog.java"
      ]
    }
  ],
  "scores": [
    {
      "stats": {
        "fn": 1,
        "tp": 0,
        "fp": 2
      },
      "mapping": {},
      "vuln_dates": {
        "CVE-2020-2184": "2020-05-06T13:15:14"
      },
      "scoring_model": "claude-3-opus-20240229",
      "type": "llm",
      "instruction_template_hash": "245ace12b6361954d0a2"
    }
  ],
  "instruction_template_hash": "10c0163db4740318a544",
  "version": "0.1.0"
}
