{
  "commit": "249091afd38e533c16d765cf47dbd537ea5de4e4",
  "repo_url": "https://github.com/jenkinsci/google-play-android-publisher-plugin",
  "model": "claude-3-haiku-20240307",
  "chunk_hashes": [
    "e1a29a8487b9ae418f62"
  ],
  "responses": [
    {
      "content": "```yaml\nleads:\n  - headline: Improper Input Validation (CWE-20)\n    analysis: |\n      The codebase contains several instances of improper input validation, which could lead to vulnerabilities such as Improper Validation of Specified Quantity in Input (CWE-1284) and Improper Validation of Array Index (CWE-129). For example, the `ApkUploadTask` class does not properly validate the user-provided expansion file patterns, which could allow an attacker to supply a malformed pattern that could lead to a path traversal vulnerability or other issues.\n    cwe: CWE-20\n    function_names:\n      - ApkUploadTask.applyExpansionFile\n      - ApkUploadTask.uploadExpansionFile\n    filenames:\n      - src/main/java/org/jenkinsci/plugins/googleplayandroidpublisher/ApkUploadTask.java\n    classification: slightly promising\n\n  - headline: Injection (CWE-74)\n    analysis: |\n      The codebase contains several instances of improper neutralization of special elements, which could lead to injection vulnerabilities such as Command Injection (CWE-78) and SQL Injection (CWE-89). For example, the `expand()` method in the `Util` class does not properly sanitize the input values before using them in token macro expansion, which could allow an attacker to inject malicious code into the build environment.\n    cwe: CWE-74\n    function_names:\n      - Util.expand\n    filenames:\n      - src/main/java/org/jenkinsci/plugins/googleplayandroidpublisher/Util.java\n    classification: slightly promising\n\n  - headline: Exposure of Sensitive Information (CWE-200)\n    analysis: |\n      The codebase contains several instances where sensitive information, such as Google Play API credentials, could be exposed to unauthorized actors. For example, the `CredentialsHandler` class logs the credential name, which could potentially expose sensitive information to the build logs.\n    cwe: CWE-200\n    function_names:\n      - CredentialsHandler.getServiceAccountCredentials\n    filenames:\n      - src/main/java/org/jenkinsci/plugins/googleplayandroidpublisher/CredentialsHandler.java\n    classification: slightly promising\n\n  - headline: Improper Synchronization (CWE-662)\n    analysis: |\n      The codebase uses several static variables (`currentBuild`, `currentListener`) to share state between different instances of the `GooglePlayBuilder` and `GooglePlayPublisher` classes. This could lead to race conditions and other synchronization issues if the plugin is used in a highly concurrent environment.\n    cwe: CWE-662\n    function_names:\n      - GooglePlayBuilder.perform\n      - GooglePlayPublisher.perform\n    filenames:\n      - src/main/java/org/jenkinsci/plugins/googleplayandroidpublisher/GooglePlayBuilder.java\n      - src/main/java/org/jenkinsci/plugins/googleplayandroidpublisher/GooglePlayPublisher.java\n    classification: slightly promising\n\n  - headline: Uncontrolled Resource Consumption (CWE-400)\n    analysis: |\n      The codebase does not appear to have any mechanisms to limit or throttle resource consumption, which could lead to Denial of Service (DoS) vulnerabilities. For example, the `ApkUploadTask` class could potentially upload a large number of APK files, expansion files, and mapping files, which could overwhelm the Google Play API and cause the Jenkins build to hang or fail.\n    cwe: CWE-400\n    function_names:\n      - ApkUploadTask.execute\n    filenames:\n      - src/main/java/org/jenkinsci/plugins/googleplayandroidpublisher/ApkUploadTask.java\n    classification: slightly promising\n\n  - headline: Incorrect Authorization (CWE-863)\n    analysis: |\n      The codebase does not appear to have any mechanisms to verify that the user or service account has the necessary permissions to perform the requested actions on the Google Play Developer Console. This could lead to Authorization Bypass Through User-Controlled Key (CWE-639) vulnerabilities, where an attacker could potentially gain unauthorized access to sensitive data or functionality.\n    cwe: CWE-863\n    function_names:\n      - CredentialsHandler.getServiceAccountCredentials\n    filenames:\n      - src/main/java/org/jenkinsci/plugins/googleplayandroidpublisher/CredentialsHandler.java\n    classification: slightly promising\n```",
      "date": "2024-06-12T18:33:03.903533",
      "usage": {
        "prompt_tokens": 32032,
        "completion_tokens": 1095,
        "cost": 0.00937675
      }
    }
  ],
  "leads": [
    {
      "headline": "Improper Input Validation (CWE-20)",
      "analysis": "The codebase contains several instances of improper input validation, which could lead to vulnerabilities such as Improper Validation of Specified Quantity in Input (CWE-1284) and Improper Validation of Array Index (CWE-129). For example, the ApkUploadTask class does not properly validate the user-provided expansion file patterns, which could allow an attacker to supply a malformed pattern that could lead to a path traversal vulnerability or other issues.\n",
      "classification": "slightly promising",
      "cwe": "CWE-20",
      "function_names": [
        "ApkUploadTask.applyExpansionFile",
        "ApkUploadTask.uploadExpansionFile"
      ],
      "filenames": [
        "src/main/java/org/jenkinsci/plugins/googleplayandroidpublisher/ApkUploadTask.java"
      ]
    },
    {
      "headline": "Injection (CWE-74)",
      "analysis": "The codebase contains several instances of improper neutralization of special elements, which could lead to injection vulnerabilities such as Command Injection (CWE-78) and SQL Injection (CWE-89). For example, the expand() method in the Util class does not properly sanitize the input values before using them in token macro expansion, which could allow an attacker to inject malicious code into the build environment.\n",
      "classification": "slightly promising",
      "cwe": "CWE-74",
      "function_names": [
        "Util.expand"
      ],
      "filenames": [
        "src/main/java/org/jenkinsci/plugins/googleplayandroidpublisher/Util.java"
      ]
    },
    {
      "headline": "Exposure of Sensitive Information (CWE-200)",
      "analysis": "The codebase contains several instances where sensitive information, such as Google Play API credentials, could be exposed to unauthorized actors. For example, the CredentialsHandler class logs the credential name, which could potentially expose sensitive information to the build logs.\n",
      "classification": "slightly promising",
      "cwe": "CWE-200",
      "function_names": [
        "CredentialsHandler.getServiceAccountCredentials"
      ],
      "filenames": [
        "src/main/java/org/jenkinsci/plugins/googleplayandroidpublisher/CredentialsHandler.java"
      ]
    },
    {
      "headline": "Improper Synchronization (CWE-662)",
      "analysis": "The codebase uses several static variables (currentBuild, currentListener) to share state between different instances of the GooglePlayBuilder and GooglePlayPublisher classes. This could lead to race conditions and other synchronization issues if the plugin is used in a highly concurrent environment.\n",
      "classification": "slightly promising",
      "cwe": "CWE-662",
      "function_names": [
        "GooglePlayBuilder.perform",
        "GooglePlayPublisher.perform"
      ],
      "filenames": [
        "src/main/java/org/jenkinsci/plugins/googleplayandroidpublisher/GooglePlayBuilder.java",
        "src/main/java/org/jenkinsci/plugins/googleplayandroidpublisher/GooglePlayPublisher.java"
      ]
    },
    {
      "headline": "Uncontrolled Resource Consumption (CWE-400)",
      "analysis": "The codebase does not appear to have any mechanisms to limit or throttle resource consumption, which could lead to Denial of Service (DoS) vulnerabilities. For example, the ApkUploadTask class could potentially upload a large number of APK files, expansion files, and mapping files, which could overwhelm the Google Play API and cause the Jenkins build to hang or fail.\n",
      "classification": "slightly promising",
      "cwe": "CWE-400",
      "function_names": [
        "ApkUploadTask.execute"
      ],
      "filenames": [
        "src/main/java/org/jenkinsci/plugins/googleplayandroidpublisher/ApkUploadTask.java"
      ]
    },
    {
      "headline": "Incorrect Authorization (CWE-863)",
      "analysis": "The codebase does not appear to have any mechanisms to verify that the user or service account has the necessary permissions to perform the requested actions on the Google Play Developer Console. This could lead to Authorization Bypass Through User-Controlled Key (CWE-639) vulnerabilities, where an attacker could potentially gain unauthorized access to sensitive data or functionality.\n",
      "classification": "slightly promising",
      "cwe": "CWE-863",
      "function_names": [
        "CredentialsHandler.getServiceAccountCredentials"
      ],
      "filenames": [
        "src/main/java/org/jenkinsci/plugins/googleplayandroidpublisher/CredentialsHandler.java"
      ]
    }
  ],
  "scores": [
    {
      "stats": {
        "fn": 1,
        "tp": 0,
        "fp": 0
      },
      "mapping": {},
      "vuln_dates": {
        "CVE-2018-1000109": "2018-03-13T13:29:00"
      },
      "scoring_model": "claude-3-opus-20240229",
      "type": "llm",
      "instruction_template_hash": "245ace12b6361954d0a2"
    },
    {
      "stats": {
        "fn": 1,
        "tp": 0,
        "fp": 0
      },
      "mapping": {},
      "vuln_dates": {
        "CVE-2018-1000109": "2018-03-13T13:29:00"
      },
      "scoring_model": "claude-3-5-sonnet-20240620",
      "type": "llm",
      "instruction_template_hash": "245ace12b6361954d0a2"
    }
  ],
  "instruction_template_hash": "10c0163db4740318a544",
  "version": "0.1.0"
}
