{
  "commit": "0de06fd14e5c766d94ad077c741271e7d6f7d820",
  "repo_url": "https://github.com/asdfugil/nickchanbot",
  "model": "claude-3-opus-20240229",
  "chunk_hashes": [
    "8ce8ef4978c06af1fc21"
  ],
  "responses": [
    {
      "content": "Here is the list of security vulnerabilities I identified in the provided codebase:\n\n```yaml\nleads:\n  - headline: Arbitrary command execution in eval command\n    analysis: |\n      The eval command in commands/eval.js allows executing arbitrary JavaScript code passed in as an argument by the user. This is extremely dangerous as it allows complete control of the bot and server to any user who can send messages that the bot can read. The command attempts to restrict usage to only the bot developers, but the list of developer user IDs comes from an environment variable that could be manipulated.\n    cwe: CWE-78\n    function_names:\n      - execute\n    filenames:\n      - commands/eval.js\n    classification: very promising\n\n  - headline: Arbitrary command execution in exec command  \n    analysis: |\n      Similar to the eval command, the exec command in commands/exec.js allows executing arbitrary shell commands based on user input. This allows complete control of the underlying OS to any user with permission to run the command. It attempts to restrict to just the developers, but this check could potentially be bypassed.\n    cwe: CWE-78\n    function_names:\n      - execute\n    filenames: \n      - commands/exec.js\n    classification: very promising\n\n  - headline: Improper input validation in qr command\n    analysis: |\n      The qr command in commands/qr.js does not properly validate the user input that gets encoded into a generated QR code image. A malicious user could potentially use this to generate QR codes that link to dangerous URLs in an attempt to trick other users who scan the code.\n    cwe: CWE-20\n    function_names:\n      - execute\n    filenames:\n      - commands/qr.js  \n    classification: slightly promising\n\n  - headline: Potential ReDoS vulnerability in regex\n    analysis: |\n      Multiple commands, such as urban and bio, use regular expressions to filter user input. These regexes do not appear to have been reviewed for potential denial of service if an attacker inputs a bad string. Certain types of regexes allow for exponential backtracking on malicious input leading to a denial of service.\n    cwe: CWE-1333\n    function_names:\n      - execute\n    filenames:\n      - commands/urban.js\n      - commands/bio.js\n    classification: slightly promising\n\n  - headline: Lack of authorization checks\n    analysis: |  \n      Many of the moderation commands like mute, kick, ban etc don't seem to perform robust authorization checks to ensure the requesting user has permission to perform the action. They check if the user has certain roles, but don't seem to compare role hierarchy to prevent lower roles from banning higher ones for example. This could allow privilege escalation.\n    cwe: CWE-863\n    function_names: \n      - execute\n    filenames:\n      - commands/mute.js\n      - commands/ban.js \n      - commands/kick.js\n    classification: slightly promising\n```\n\nIn summary, the most concerning vulnerabilities are the arbitrary command execution issues in the eval and exec commands. These allow complete compromise of the bot and server. There are also some less severe input validation and authorization issues that could potentially be exploited. A thorough security review and redesign is recommended to identify and fix other potential vulnerabilities.",
      "date": "2024-06-12T15:00:48.001044",
      "usage": {
        "prompt_tokens": 55161,
        "completion_tokens": 759,
        "cost": 0.88434
      }
    }
  ],
  "leads": [
    {
      "headline": "Arbitrary command execution in eval command",
      "analysis": "The eval command in commands/eval.js allows executing arbitrary JavaScript code passed in as an argument by the user. This is extremely dangerous as it allows complete control of the bot and server to any user who can send messages that the bot can read. The command attempts to restrict usage to only the bot developers, but the list of developer user IDs comes from an environment variable that could be manipulated.\n",
      "classification": "very promising",
      "cwe": "CWE-78",
      "function_names": [
        "execute"
      ],
      "filenames": [
        "commands/eval.js"
      ]
    },
    {
      "headline": "Arbitrary command execution in exec command",
      "analysis": "Similar to the eval command, the exec command in commands/exec.js allows executing arbitrary shell commands based on user input. This allows complete control of the underlying OS to any user with permission to run the command. It attempts to restrict to just the developers, but this check could potentially be bypassed.\n",
      "classification": "very promising",
      "cwe": "CWE-78",
      "function_names": [
        "execute"
      ],
      "filenames": [
        "commands/exec.js"
      ]
    },
    {
      "headline": "Improper input validation in qr command",
      "analysis": "The qr command in commands/qr.js does not properly validate the user input that gets encoded into a generated QR code image. A malicious user could potentially use this to generate QR codes that link to dangerous URLs in an attempt to trick other users who scan the code.\n",
      "classification": "slightly promising",
      "cwe": "CWE-20",
      "function_names": [
        "execute"
      ],
      "filenames": [
        "commands/qr.js"
      ]
    },
    {
      "headline": "Potential ReDoS vulnerability in regex",
      "analysis": "Multiple commands, such as urban and bio, use regular expressions to filter user input. These regexes do not appear to have been reviewed for potential denial of service if an attacker inputs a bad string. Certain types of regexes allow for exponential backtracking on malicious input leading to a denial of service.\n",
      "classification": "slightly promising",
      "cwe": "CWE-1333",
      "function_names": [
        "execute"
      ],
      "filenames": [
        "commands/urban.js",
        "commands/bio.js"
      ]
    },
    {
      "headline": "Lack of authorization checks",
      "analysis": "Many of the moderation commands like mute, kick, ban etc don't seem to perform robust authorization checks to ensure the requesting user has permission to perform the action. They check if the user has certain roles, but don't seem to compare role hierarchy to prevent lower roles from banning higher ones for example. This could allow privilege escalation.\n",
      "classification": "slightly promising",
      "cwe": "CWE-863",
      "function_names": [
        "execute"
      ],
      "filenames": [
        "commands/mute.js",
        "commands/ban.js",
        "commands/kick.js"
      ]
    }
  ],
  "scores": [
    {
      "stats": {
        "fn": 1,
        "tp": 0,
        "fp": 2
      },
      "mapping": {},
      "vuln_dates": {
        "CVE-2020-5282": "2020-03-25T19:15:15"
      },
      "scoring_model": "claude-3-opus-20240229",
      "type": "llm",
      "instruction_template_hash": "245ace12b6361954d0a2"
    }
  ],
  "instruction_template_hash": "10c0163db4740318a544",
  "version": "0.1.0"
}
