{
  "commit": "1a7e0e23227900f8fa68acb01c0ef2715c2d664b",
  "repo_url": "https://github.com/jenkinsci/parameterized-trigger-plugin",
  "model": "claude-3-sonnet-20240229",
  "chunk_hashes": [
    "0f11e820f7d5c7d04884"
  ],
  "responses": [
    {
      "content": "Here are the potential security vulnerabilities I've identified in the codebase, formatted as a YAML object of type LeadList:\n\n```yaml\nleads:\n  - headline: Cross-Site Scripting (XSS) vulnerability in FileBuildParameters\n    analysis: |\n      The `FileBuildParameters` class reads a properties file from the workspace and creates `StringParameterValue` objects from the key-value pairs in the file. However, it does not sanitize or escape the values, which could allow an attacker to inject malicious scripts if they can control the contents of the properties file.\n    cwe: CWE-79\n    function_names:\n      - hudson.plugins.parameterizedtrigger.FileBuildParameters.getAction\n    filenames:\n      - src/main/java/hudson/plugins/parameterizedtrigger/FileBuildParameters.java\n    classification: very promising\n\n  - headline: Improper Input Validation in BinaryFileParameterFactory\n    analysis: |\n      The `BinaryFileParameterFactory` class copies files from the workspace to the master node based on a user-provided file pattern. It does not validate or sanitize the file pattern, which could allow an attacker to copy arbitrary files from the master if they can control the file pattern.\n    cwe: CWE-20\n    function_names:\n      - hudson.plugins.parameterizedtrigger.BinaryFileParameterFactory.getParameters\n    filenames:\n      - src/main/java/hudson/plugins/parameterizedtrigger/BinaryFileParameterFactory.java\n    classification: very promising\n\n  - headline: Code Injection vulnerability in CounterBuildParameterFactory\n    analysis: |\n      The `CounterBuildParameterFactory` class evaluates a user-provided expression to generate build parameters. It does not sanitize or validate the expression, which could allow an attacker to inject arbitrary code if they can control the expression.\n    cwe: CWE-94\n    function_names:\n      - hudson.plugins.parameterizedtrigger.CounterBuildParameterFactory.getParameters\n    filenames:\n      - src/main/java/hudson/plugins/parameterizedtrigger/CounterBuildParameterFactory.java\n    classification: very promising\n\n  - headline: Path Traversal vulnerability in FileBuildParameterFactory\n    analysis: |\n      The `FileBuildParameterFactory` class reads files from the workspace based on a user-provided file pattern. It does not validate or sanitize the file pattern, which could allow an attacker to read arbitrary files on the master if they can control the file pattern.\n    cwe: CWE-22\n    function_names:\n      - hudson.plugins.parameterizedtrigger.FileBuildParameterFactory.getParameters\n    filenames:\n      - src/main/java/hudson/plugins/parameterizedtrigger/FileBuildParameterFactory.java\n    classification: very promising\n\n  - headline: Improper Neutralization of Special Elements in NodeParameters\n    analysis: |\n      The `NodeParameters` class passes the node name as a build parameter without properly sanitizing or escaping it. If an attacker can control the node name, they could potentially inject malicious code or exploit vulnerabilities in downstream projects.\n    cwe: CWE-116\n    function_names:\n      - hudson.plugins.parameterizedtrigger.NodeParameters.getAction\n    filenames:\n      - src/main/java/hudson/plugins/parameterizedtrigger/NodeParameters.java\n    classification: slightly promising\n\n  - headline: Missing Authentication for Critical Function in TriggerBuilder\n    analysis: |\n      The `TriggerBuilder` class allows triggering builds on other projects without authentication or authorization checks. An attacker with the ability to configure a project could potentially trigger malicious builds on other projects.\n    cwe: CWE-306\n    function_names:\n      - hudson.plugins.parameterizedtrigger.TriggerBuilder.perform\n    filenames:\n      - src/main/java/hudson/plugins/parameterizedtrigger/TriggerBuilder.java\n    classification: very promising\n\n  - headline: Use of Hard-coded Credentials in BuildTrigger\n    analysis: |\n      The `BuildTrigger` class uses hard-coded credentials to trigger builds on other projects. This could potentially expose sensitive information if the credentials are compromised.\n    cwe: CWE-798\n    function_names:\n      - hudson.plugins.parameterizedtrigger.BuildTrigger.perform\n    filenames:\n      - src/main/java/hudson/plugins/parameterizedtrigger/BuildTrigger.java\n    classification: not promising\n\n  - headline: Improper Restriction of Power Consumption in TriggerBuilder\n    analysis: |\n      The `TriggerBuilder` class could potentially trigger an excessive number of builds, leading to resource exhaustion and denial of service. There do not appear to be adequate safeguards or limits in place to prevent this.\n    cwe: CWE-920\n    function_names:\n      - hudson.plugins.parameterizedtrigger.TriggerBuilder.perform\n    filenames:\n      - src/main/java/hudson/plugins/parameterizedtrigger/TriggerBuilder.java\n    classification: slightly promising\n\n  - headline: Incorrect Handling of Exceptional Conditions in BuildTriggerConfig\n    analysis: |\n      The `BuildTriggerConfig` class does not properly handle exceptional conditions when triggering builds, such as failed parameter generation or project resolution. This could lead to unexpected behavior or vulnerabilities.\n    cwe: CWE-755\n    function_names:\n      - hudson.plugins.parameterizedtrigger.BuildTriggerConfig.perform2\n    filenames:\n      - src/main/java/hudson/plugins/parameterizedtrigger/BuildTriggerConfig.java\n    classification: slightly promising\n```\n\nNote that some of these vulnerabilities are more severe than others, and further investigation and remediation efforts may be required to fully address them.",
      "date": "2024-06-12T19:00:03.309520",
      "usage": {
        "prompt_tokens": 68686,
        "completion_tokens": 1408,
        "cost": 0.227178
      }
    }
  ],
  "leads": [
    {
      "headline": "Cross-Site Scripting (XSS) vulnerability in FileBuildParameters",
      "analysis": "The FileBuildParameters class reads a properties file from the workspace and creates StringParameterValue objects from the key-value pairs in the file. However, it does not sanitize or escape the values, which could allow an attacker to inject malicious scripts if they can control the contents of the properties file.\n",
      "classification": "very promising",
      "cwe": "CWE-79",
      "function_names": [
        "hudson.plugins.parameterizedtrigger.FileBuildParameters.getAction"
      ],
      "filenames": [
        "src/main/java/hudson/plugins/parameterizedtrigger/FileBuildParameters.java"
      ]
    },
    {
      "headline": "Improper Input Validation in BinaryFileParameterFactory",
      "analysis": "The BinaryFileParameterFactory class copies files from the workspace to the master node based on a user-provided file pattern. It does not validate or sanitize the file pattern, which could allow an attacker to copy arbitrary files from the master if they can control the file pattern.\n",
      "classification": "very promising",
      "cwe": "CWE-20",
      "function_names": [
        "hudson.plugins.parameterizedtrigger.BinaryFileParameterFactory.getParameters"
      ],
      "filenames": [
        "src/main/java/hudson/plugins/parameterizedtrigger/BinaryFileParameterFactory.java"
      ]
    },
    {
      "headline": "Code Injection vulnerability in CounterBuildParameterFactory",
      "analysis": "The CounterBuildParameterFactory class evaluates a user-provided expression to generate build parameters. It does not sanitize or validate the expression, which could allow an attacker to inject arbitrary code if they can control the expression.\n",
      "classification": "very promising",
      "cwe": "CWE-94",
      "function_names": [
        "hudson.plugins.parameterizedtrigger.CounterBuildParameterFactory.getParameters"
      ],
      "filenames": [
        "src/main/java/hudson/plugins/parameterizedtrigger/CounterBuildParameterFactory.java"
      ]
    },
    {
      "headline": "Path Traversal vulnerability in FileBuildParameterFactory",
      "analysis": "The FileBuildParameterFactory class reads files from the workspace based on a user-provided file pattern. It does not validate or sanitize the file pattern, which could allow an attacker to read arbitrary files on the master if they can control the file pattern.\n",
      "classification": "very promising",
      "cwe": "CWE-22",
      "function_names": [
        "hudson.plugins.parameterizedtrigger.FileBuildParameterFactory.getParameters"
      ],
      "filenames": [
        "src/main/java/hudson/plugins/parameterizedtrigger/FileBuildParameterFactory.java"
      ]
    },
    {
      "headline": "Improper Neutralization of Special Elements in NodeParameters",
      "analysis": "The NodeParameters class passes the node name as a build parameter without properly sanitizing or escaping it. If an attacker can control the node name, they could potentially inject malicious code or exploit vulnerabilities in downstream projects.\n",
      "classification": "slightly promising",
      "cwe": "CWE-116",
      "function_names": [
        "hudson.plugins.parameterizedtrigger.NodeParameters.getAction"
      ],
      "filenames": [
        "src/main/java/hudson/plugins/parameterizedtrigger/NodeParameters.java"
      ]
    },
    {
      "headline": "Missing Authentication for Critical Function in TriggerBuilder",
      "analysis": "The TriggerBuilder class allows triggering builds on other projects without authentication or authorization checks. An attacker with the ability to configure a project could potentially trigger malicious builds on other projects.\n",
      "classification": "very promising",
      "cwe": "CWE-306",
      "function_names": [
        "hudson.plugins.parameterizedtrigger.TriggerBuilder.perform"
      ],
      "filenames": [
        "src/main/java/hudson/plugins/parameterizedtrigger/TriggerBuilder.java"
      ]
    },
    {
      "headline": "Use of Hard-coded Credentials in BuildTrigger",
      "analysis": "The BuildTrigger class uses hard-coded credentials to trigger builds on other projects. This could potentially expose sensitive information if the credentials are compromised.\n",
      "classification": "not promising",
      "cwe": "CWE-798",
      "function_names": [
        "hudson.plugins.parameterizedtrigger.BuildTrigger.perform"
      ],
      "filenames": [
        "src/main/java/hudson/plugins/parameterizedtrigger/BuildTrigger.java"
      ]
    },
    {
      "headline": "Improper Restriction of Power Consumption in TriggerBuilder",
      "analysis": "The TriggerBuilder class could potentially trigger an excessive number of builds, leading to resource exhaustion and denial of service. There do not appear to be adequate safeguards or limits in place to prevent this.\n",
      "classification": "slightly promising",
      "cwe": "CWE-920",
      "function_names": [
        "hudson.plugins.parameterizedtrigger.TriggerBuilder.perform"
      ],
      "filenames": [
        "src/main/java/hudson/plugins/parameterizedtrigger/TriggerBuilder.java"
      ]
    },
    {
      "headline": "Incorrect Handling of Exceptional Conditions in BuildTriggerConfig",
      "analysis": "The BuildTriggerConfig class does not properly handle exceptional conditions when triggering builds, such as failed parameter generation or project resolution. This could lead to unexpected behavior or vulnerabilities.\n",
      "classification": "slightly promising",
      "cwe": "CWE-755",
      "function_names": [
        "hudson.plugins.parameterizedtrigger.BuildTriggerConfig.perform2"
      ],
      "filenames": [
        "src/main/java/hudson/plugins/parameterizedtrigger/BuildTriggerConfig.java"
      ]
    }
  ],
  "scores": [
    {
      "stats": {
        "fn": 1,
        "tp": 1,
        "fp": 4
      },
      "mapping": {
        "4": "CVE-2017-1000084"
      },
      "vuln_dates": {
        "CVE-2017-1000084": "2017-10-05T01:29:03",
        "CVE-2022-27195": "2022-03-15T17:15:09"
      },
      "scoring_model": "claude-3-opus-20240229",
      "type": "llm",
      "instruction_template_hash": "245ace12b6361954d0a2"
    }
  ],
  "instruction_template_hash": "10c0163db4740318a544",
  "version": "0.1.0"
}
