{
  "commit": "19d001695fe17f9b776633733a21a060c70bea82",
  "repo_url": "https://github.com/openzeppelin/cairo-contracts",
  "model": "gpt-4o-2024-05-13",
  "chunk_hashes": [
    "fb06edd579d2663c9ce2"
  ],
  "responses": [
    {
      "content": "```yaml\nleads:\n  - headline: \"Missing validation in setup.py\"\n    analysis: |\n      The `setup.py` script contains a bare `except` block that catches all exceptions, which can mask specific errors and make debugging difficult. It doesn't validate the type of error that occurs, which can lead to improper handling of different kinds of exceptions.\n    cwe: CWE-754\n    function_names:\n      - main\n    filenames:\n      - setup.py\n    classification: very promising\n\n  - headline: \"Private keys hardcoded in tests/signers.py\"\n    analysis: |\n      The file contains instances where private keys are hardcoded into the `MockSigner` and `MockEthSigner` classes. This is highly risky as it exposes sensitive information directly in the source code.\n    cwe: CWE-798\n    function_names: []\n    filenames:\n      - tests/signers.py\n    classification: very promising\n\n  - headline: \"Potential for Re-entrancy attacks in ERC721 token\"\n    analysis: |\n      The ERC721 implementation test file does not include protections for re-entrancy attacks. Functions like `transferFrom`, `safeTransferFrom`, etc., invoke external contracts without re-entrancy guards.\n    cwe: CWE-667\n    function_names:\n      - transferFrom\n      - safeTransferFrom\n    filenames:\n      - tests/token/erc721/test_ERC721_Mintable_Burnable.py\n    classification: very promising\n\n  - headline: \"Improper validation of nonces in account logic\"\n    analysis: |\n      Tests show that nonce validation is performed but doesn't cover edge cases such as wrap-arounds or handling of very large nonce values. This could be exploited if not handled properly.\n    cwe: CWE-190\n    function_names:\n      - test_nonce\n    filenames:\n      - tests/account/test_Account.py\n      - tests/account/test_EthAccount.py\n    classification: slightly promising\n\n  - headline: \"Usage of hardcoded addresses in contract deployment and initialization\"\n    analysis: |\n      The test files frequently hardcode addresses for contract deployment and initialization. This could lead to issues if these addresses are reused in a real environment.\n    cwe: CWE-117\n    function_names:\n      - deploy\n    filenames:\n      - tests/access/test_Ownable.py\n      - tests/access/test_AccessControl.py\n      - tests/token/erc20/test_ERC20.py\n    classification: slightly promising\n\n  - headline: \"Potential integer overflow in safe math contracts\"\n    analysis: |\n      Although the tests for SafeMath are extensive, specific edge cases for maximum and minimum boundary values are not thoroughly tested.\n    cwe: CWE-190\n    function_names:\n      - test_add_overflow\n      - test_sub_lt_overflow\n      - test_mul_overflow\n    filenames:\n      - tests/security/test_safemath.py\n    classification: slightly promising\n\n  - headline: \"Missing checks for critical functions in access control\"\n    analysis: |\n      The access control test files do not include test cases for missing checks on critical functions. This can lead to unauthorized access if function calls are not correctly restricted.\n    cwe: CWE-306\n    function_names:\n      - test_grant_role\n      - test_revoke_role\n    filenames:\n      - tests/access/test_AccessControl.py\n    classification: slightly promising\n\n  - headline: \"Lack of event emission checks for contract state changes\"\n    analysis: |\n      Some contract methods in the tests lack assertions to verify if events were emitted correctly, particularly where state changes occur.\n    cwe: CWE-754\n    function_names:\n      - test_set_value\n      - test_transfer\n    filenames:\n      - tests/upgrades/test_upgrades.py\n      - tests/token/erc20/test_ERC20.py\n    classification: not promising\n\n```",
      "date": "2024-06-13T10:55:24.445299",
      "usage": {
        "prompt_tokens": 38937,
        "completion_tokens": 798,
        "cost": 0.206655
      }
    }
  ],
  "leads": [
    {
      "headline": "Missing validation in setup.py",
      "analysis": "The setup.py script contains a bare except block that catches all exceptions, which can mask specific errors and make debugging difficult. It doesn't validate the type of error that occurs, which can lead to improper handling of different kinds of exceptions.\n",
      "classification": "very promising",
      "cwe": "CWE-754",
      "function_names": [
        "main"
      ],
      "filenames": [
        "setup.py"
      ]
    },
    {
      "headline": "Private keys hardcoded in tests/signers.py",
      "analysis": "The file contains instances where private keys are hardcoded into the MockSigner and MockEthSigner classes. This is highly risky as it exposes sensitive information directly in the source code.\n",
      "classification": "very promising",
      "cwe": "CWE-798",
      "function_names": [],
      "filenames": [
        "tests/signers.py"
      ]
    },
    {
      "headline": "Potential for Re-entrancy attacks in ERC721 token",
      "analysis": "The ERC721 implementation test file does not include protections for re-entrancy attacks. Functions like transferFrom, safeTransferFrom, etc., invoke external contracts without re-entrancy guards.\n",
      "classification": "very promising",
      "cwe": "CWE-667",
      "function_names": [
        "transferFrom",
        "safeTransferFrom"
      ],
      "filenames": [
        "tests/token/erc721/test_ERC721_Mintable_Burnable.py"
      ]
    },
    {
      "headline": "Improper validation of nonces in account logic",
      "analysis": "Tests show that nonce validation is performed but doesn't cover edge cases such as wrap-arounds or handling of very large nonce values. This could be exploited if not handled properly.\n",
      "classification": "slightly promising",
      "cwe": "CWE-190",
      "function_names": [
        "test_nonce"
      ],
      "filenames": [
        "tests/account/test_Account.py",
        "tests/account/test_EthAccount.py"
      ]
    },
    {
      "headline": "Usage of hardcoded addresses in contract deployment and initialization",
      "analysis": "The test files frequently hardcode addresses for contract deployment and initialization. This could lead to issues if these addresses are reused in a real environment.\n",
      "classification": "slightly promising",
      "cwe": "CWE-117",
      "function_names": [
        "deploy"
      ],
      "filenames": [
        "tests/access/test_Ownable.py",
        "tests/access/test_AccessControl.py",
        "tests/token/erc20/test_ERC20.py"
      ]
    },
    {
      "headline": "Potential integer overflow in safe math contracts",
      "analysis": "Although the tests for SafeMath are extensive, specific edge cases for maximum and minimum boundary values are not thoroughly tested.\n",
      "classification": "slightly promising",
      "cwe": "CWE-190",
      "function_names": [
        "test_add_overflow",
        "test_sub_lt_overflow",
        "test_mul_overflow"
      ],
      "filenames": [
        "tests/security/test_safemath.py"
      ]
    },
    {
      "headline": "Missing checks for critical functions in access control",
      "analysis": "The access control test files do not include test cases for missing checks on critical functions. This can lead to unauthorized access if function calls are not correctly restricted.\n",
      "classification": "slightly promising",
      "cwe": "CWE-306",
      "function_names": [
        "test_grant_role",
        "test_revoke_role"
      ],
      "filenames": [
        "tests/access/test_AccessControl.py"
      ]
    },
    {
      "headline": "Lack of event emission checks for contract state changes",
      "analysis": "Some contract methods in the tests lack assertions to verify if events were emitted correctly, particularly where state changes occur.\n",
      "classification": "not promising",
      "cwe": "CWE-754",
      "function_names": [
        "test_set_value",
        "test_transfer"
      ],
      "filenames": [
        "tests/upgrades/test_upgrades.py",
        "tests/token/erc20/test_ERC20.py"
      ]
    }
  ],
  "scores": [
    {
      "stats": {
        "fn": 1,
        "tp": 0,
        "fp": 3
      },
      "mapping": {},
      "vuln_dates": {
        "CVE-2023-23940": "2023-02-03T20:15:11"
      },
      "scoring_model": "claude-3-opus-20240229",
      "type": "llm",
      "instruction_template_hash": "245ace12b6361954d0a2"
    },
    {
      "stats": {
        "fn": 1,
        "tp": 0,
        "fp": 3
      },
      "mapping": {},
      "vuln_dates": {
        "CVE-2023-23940": "2023-02-03T20:15:11"
      },
      "scoring_model": "claude-3-5-sonnet-20240620",
      "type": "llm",
      "instruction_template_hash": "245ace12b6361954d0a2"
    }
  ],
  "instruction_template_hash": "10c0163db4740318a544",
  "version": "0.1.0"
}
