{
  "commit": "43714f0463a14ef9d2cee55d689d2bc934e9e7f3",
  "repo_url": "https://github.com/jenkinsci/http-request-plugin",
  "model": "claude-3-sonnet-20240229",
  "chunk_hashes": [
    "d31cbb4440a21d1220fc"
  ],
  "responses": [
    {
      "content": "The codebase provided contains Java code for the \"HTTP Request\" plugin for Jenkins. The key components and their functionalities are as follows:\n\n1. **HttpRequest.java**: This class represents the Jenkins build step that performs an HTTP request. It provides various configuration options such as URL, HTTP mode (GET, POST, etc.), request headers, request body, authentication, timeout, response validation, and output file.\n\n2. **HttpRequestStep.java**: This class represents the Pipeline step that performs an HTTP request. It provides similar configurations as the `HttpRequest` class but is designed to work with Jenkins Pipeline.\n\n3. **HttpRequestExecution.java**: This class handles the execution of the HTTP request, including authentication, proxy handling, SSL configuration, and response processing.\n\n4. **ResponseContentSupplier.java**: This class encapsulates the HTTP response content and provides methods to access the response status, headers, and content.\n\n5. **HttpRequestGlobalConfig.java**: This class manages the global configuration for the plugin, including basic/digest authentication and form authentication settings.\n\n6. **Authentication classes**: The codebase includes various classes for handling different types of authentication, such as `BasicDigestAuthentication`, `FormAuthentication`, `CredentialBasicAuthentication`, `CredentialNtlmAuthentication`, and `CertificateAuthentication`.\n\n7. **Utility classes**: There are several utility classes like `HttpRequestNameValuePair`, `HttpClientUtil`, `HttpRequestFormDataPart`, `RequestAction`, and `HttpRequestValidation` that provide helper methods for handling HTTP requests, form data, and validations.\n\n8. **Enumerations**: The codebase includes enumerations like `HttpMode`, `MimeType`, and `ResponseHandle` to represent different HTTP methods, MIME types, and response handling modes, respectively.\n\nThe key security vulnerabilities identified in the codebase are:\n\n1. **CWE-295: Improper Certificate Validation**\n   - The `HttpRequestExecution` class allows ignoring SSL errors and disabling certificate validation by setting `ignoreSslErrors` to `true`. This can potentially expose the application to man-in-the-middle attacks.\n\n2. **CWE-522: Insufficiently Protected Credentials**\n   - The `HttpRequestGlobalConfig` class stores credentials (username and password) for basic/digest authentication in plain text. These credentials should be encrypted or stored securely.\n\n3. **CWE-319: Cleartext Transmission of Sensitive Information**\n   - The `HttpRequest` and `HttpRequestStep` classes allow transmitting sensitive information (e.g., authentication credentials) in cleartext over HTTP. This should be avoided, and sensitive data should be transmitted over HTTPS.\n\n4. **CWE-798: Use of Hard-coded Credentials**\n   - The `BasicDigestAuthentication` class allows hard-coding credentials (username and password) in the Jenkins job configuration. This is a security risk as the credentials can be easily exposed.\n\n5. **CWE-759: Use of a One-Way Hash without a Salt**\n   - The codebase does not appear to use salted hashes for storing or transmitting passwords, which can make them vulnerable to dictionary attacks and rainbow table attacks.\n\nHere's the YAML representation of the identified leads:\n\n```yaml\nleads:\n  - headline: Improper Certificate Validation\n    analysis: |\n      The `HttpRequestExecution` class allows disabling SSL certificate validation by setting the `ignoreSslErrors` parameter to `true`. This can potentially expose the application to man-in-the-middle attacks, where an attacker can intercept and modify the communication between the client and server.\n    cwe: CWE-295\n    function_names:\n      - configureTimeoutAndSsl\n    filenames:\n      - src/main/java/jenkins/plugins/http_request/HttpRequestExecution.java\n    classification: very promising\n\n  - headline: Insufficiently Protected Credentials\n    analysis: |\n      The `HttpRequestGlobalConfig` class stores credentials (username and password) for basic/digest authentication in plain text. These credentials should be encrypted or stored securely to prevent unauthorized access.\n    cwe: CWE-522\n    function_names:\n      - getBasicDigestAuthentications\n      - setBasicDigestAuthentications\n    filenames:\n      - src/main/java/jenkins/plugins/http_request/HttpRequestGlobalConfig.java\n    classification: very promising\n\n  - headline: Cleartext Transmission of Sensitive Information\n    analysis: |\n      The `HttpRequest` and `HttpRequestStep` classes allow transmitting sensitive information (e.g., authentication credentials) in cleartext over HTTP. This can expose the sensitive information to potential eavesdropping and man-in-the-middle attacks. Sensitive data should be transmitted over HTTPS to ensure confidentiality.\n    cwe: CWE-319\n    function_names:\n      - HttpRequest\n      - HttpRequestStep\n    filenames:\n      - src/main/java/jenkins/plugins/http_request/HttpRequest.java\n      - src/main/java/jenkins/plugins/http_request/HttpRequestStep.java\n    classification: very promising\n\n  - headline: Use of Hard-coded Credentials\n    analysis: |\n      The `BasicDigestAuthentication` class allows hard-coding credentials (username and password) in the Jenkins job configuration. This is a security risk as the credentials can be easily exposed to unauthorized parties who have access to the job configuration files.\n    cwe: CWE-798\n    function_names:\n      - BasicDigestAuthentication\n    filenames:\n      - src/main/java/jenkins/plugins/http_request/auth/BasicDigestAuthentication.java\n    classification: very promising\n\n  - headline: Use of a One-Way Hash without a Salt\n    analysis: |\n      The codebase does not appear to use salted hashes for storing or transmitting passwords. This can make the passwords vulnerable to dictionary attacks and rainbow table attacks, where attackers can precompute hashes for common passwords and easily crack them.\n    cwe: CWE-916\n    function_names: []\n    filenames: []\n    classification: slightly promising\n```\n\nPlease note that the classification of the leads as \"very promising\" or \"slightly promising\" is based on the potential severity and impact of the vulnerabilities. Additionally, the analysis provided is based on the code review and may not cover all possible scenarios or vulnerabilities present in the codebase.",
      "date": "2024-06-14T14:17:42.635628",
      "usage": {
        "prompt_tokens": 64909,
        "completion_tokens": 1476,
        "cost": 0.216867
      }
    }
  ],
  "leads": [
    {
      "headline": "Improper Certificate Validation",
      "analysis": "The HttpRequestExecution class allows disabling SSL certificate validation by setting the ignoreSslErrors parameter to true. This can potentially expose the application to man-in-the-middle attacks, where an attacker can intercept and modify the communication between the client and server.\n",
      "classification": "very promising",
      "cwe": "CWE-295",
      "function_names": [
        "configureTimeoutAndSsl"
      ],
      "filenames": [
        "src/main/java/jenkins/plugins/http_request/HttpRequestExecution.java"
      ]
    },
    {
      "headline": "Insufficiently Protected Credentials",
      "analysis": "The HttpRequestGlobalConfig class stores credentials (username and password) for basic/digest authentication in plain text. These credentials should be encrypted or stored securely to prevent unauthorized access.\n",
      "classification": "very promising",
      "cwe": "CWE-522",
      "function_names": [
        "getBasicDigestAuthentications",
        "setBasicDigestAuthentications"
      ],
      "filenames": [
        "src/main/java/jenkins/plugins/http_request/HttpRequestGlobalConfig.java"
      ]
    },
    {
      "headline": "Cleartext Transmission of Sensitive Information",
      "analysis": "The HttpRequest and HttpRequestStep classes allow transmitting sensitive information (e.g., authentication credentials) in cleartext over HTTP. This can expose the sensitive information to potential eavesdropping and man-in-the-middle attacks. Sensitive data should be transmitted over HTTPS to ensure confidentiality.\n",
      "classification": "very promising",
      "cwe": "CWE-319",
      "function_names": [
        "HttpRequest",
        "HttpRequestStep"
      ],
      "filenames": [
        "src/main/java/jenkins/plugins/http_request/HttpRequest.java",
        "src/main/java/jenkins/plugins/http_request/HttpRequestStep.java"
      ]
    },
    {
      "headline": "Use of Hard-coded Credentials",
      "analysis": "The BasicDigestAuthentication class allows hard-coding credentials (username and password) in the Jenkins job configuration. This is a security risk as the credentials can be easily exposed to unauthorized parties who have access to the job configuration files.\n",
      "classification": "very promising",
      "cwe": "CWE-798",
      "function_names": [
        "BasicDigestAuthentication"
      ],
      "filenames": [
        "src/main/java/jenkins/plugins/http_request/auth/BasicDigestAuthentication.java"
      ]
    },
    {
      "headline": "Use of a One-Way Hash without a Salt",
      "analysis": "The codebase does not appear to use salted hashes for storing or transmitting passwords. This can make the passwords vulnerable to dictionary attacks and rainbow table attacks, where attackers can precompute hashes for common passwords and easily crack them.\n",
      "classification": "slightly promising",
      "cwe": "CWE-916",
      "function_names": [],
      "filenames": []
    }
  ],
  "scores": [
    {
      "stats": {
        "fn": 0,
        "tp": 1,
        "fp": 3
      },
      "mapping": {
        "1": "CVE-2022-36901"
      },
      "vuln_dates": {
        "CVE-2022-36901": "2022-07-27T15:15:09"
      },
      "scoring_model": "claude-3-opus-20240229",
      "type": "llm",
      "instruction_template_hash": "245ace12b6361954d0a2"
    }
  ],
  "instruction_template_hash": "10c0163db4740318a544",
  "version": "0.1.0"
}
