{
  "commit": "2006f3e1a71645886d1bd2eeb1d39f9c19f6fe33",
  "repo_url": "https://github.com/getgridea/gridea",
  "model": "gpt-4-turbo-2024-04-09",
  "chunk_hashes": [
    "136cfa74e16543c79b15"
  ],
  "responses": [
    {
      "content": "```yaml\nleads:\n  - headline: \"Improper Authorization in Posts and Tags Deletion\"\n    analysis: |\n      User validation is not performed when handling deletion requests for posts and tags in the Electron app. Anyone with local server access could trigger these deletions without providing user credentials or session verification, leading to potential unauthorized data manipulation.\n    cwe: CWE-285\n    function_names:\n      - deleteTag\n      - deletePost\n      - deleteMenu\n    filenames:\n      - src/server/events/tag.ts\n      - src/server/events/post.ts\n      - src/server/events/menu.ts\n    classification: \"very promising\"\n\n  - headline: \"Insecure Handling of External Links Opening\"\n    analysis: |\n      The application fails to explicitly set web preferences for URL loading, potentially allowing navigation to arbitrary URLs and execution of JavaScript. This concerns the handling of external site navigation and opening new browser windows which, without specific security configurations, exposes the app to common web vulnerabilities like Cross-Site Scripting (XSS) and Remote Code Execution (RCE).\n    cwe: CWE-829\n    function_names:\n      - createWindow\n    filenames:\n      - src/background.ts\n    classification: \"very promising\"\n\n  - headline: \"Remote Code Execution via Arbitrary File Execution\"\n    analysis: |\n      The application saves posts to the file system with insufficient validation of file paths or types which might result in saving executable content or scripts. This could allow an attacker who can influence the content to execute arbitrary code on the user's system. This is especially critical given that posts can contain scripts or commands that might be executed under the right conditions.\n    cwe: CWE-434\n    function_names:\n      - savePostToFile\n    filenames:\n      - src/server/posts.ts\n    classification: \"very promising\"\n\n  - headline: \"Exposure of Sensitive Application Data\"\n    analysis: |\n      The application logs sensitive data like API tokens and other configuration items to the debug log via console.log calls during some operations (e.g., theme customization save operation). If the logging mechanism or log access controls are not properly secured, this information could be exposed to unauthorized parties.\n    cwe: CWE-532\n    function_names:\n      - saveThemeCustomConfig\n    filenames:\n      - src/server/theme.ts\n    classification: \"very promising\"\n\n  - headline: \"Cross-Site Scripting (XSS) Through Markdown Rendering and Insecure Direct Object References\"\n    analysis: |\n      The application parses and renders user-controlled Markdown content without sufficient sanitization, leading to potential Cross-Site Scripting (XSS). There's also potential for unsanitized tag-based navigation, which might allow attackers to redirect users to malicious websites or execute arbitrary JavaScript through carefully crafted URLs.\n    cwe: CWE-79\n    function_names:\n      - renderPostDetail\n      - renderTags\n    filenames:\n      - src/server/renderer.ts\n    classification: \"very promising\"\n```",
      "date": "2024-06-12T17:00:10.079231",
      "usage": {
        "prompt_tokens": 24037,
        "completion_tokens": 603,
        "cost": 0.25846
      }
    }
  ],
  "leads": [
    {
      "headline": "Improper Authorization in Posts and Tags Deletion",
      "analysis": "User validation is not performed when handling deletion requests for posts and tags in the Electron app. Anyone with local server access could trigger these deletions without providing user credentials or session verification, leading to potential unauthorized data manipulation.\n",
      "classification": "very promising",
      "cwe": "CWE-285",
      "function_names": [
        "deleteTag",
        "deletePost",
        "deleteMenu"
      ],
      "filenames": [
        "src/server/events/tag.ts",
        "src/server/events/post.ts",
        "src/server/events/menu.ts"
      ]
    },
    {
      "headline": "Insecure Handling of External Links Opening",
      "analysis": "The application fails to explicitly set web preferences for URL loading, potentially allowing navigation to arbitrary URLs and execution of JavaScript. This concerns the handling of external site navigation and opening new browser windows which, without specific security configurations, exposes the app to common web vulnerabilities like Cross-Site Scripting (XSS) and Remote Code Execution (RCE).\n",
      "classification": "very promising",
      "cwe": "CWE-829",
      "function_names": [
        "createWindow"
      ],
      "filenames": [
        "src/background.ts"
      ]
    },
    {
      "headline": "Remote Code Execution via Arbitrary File Execution",
      "analysis": "The application saves posts to the file system with insufficient validation of file paths or types which might result in saving executable content or scripts. This could allow an attacker who can influence the content to execute arbitrary code on the user's system. This is especially critical given that posts can contain scripts or commands that might be executed under the right conditions.\n",
      "classification": "very promising",
      "cwe": "CWE-434",
      "function_names": [
        "savePostToFile"
      ],
      "filenames": [
        "src/server/posts.ts"
      ]
    },
    {
      "headline": "Exposure of Sensitive Application Data",
      "analysis": "The application logs sensitive data like API tokens and other configuration items to the debug log via console.log calls during some operations (e.g., theme customization save operation). If the logging mechanism or log access controls are not properly secured, this information could be exposed to unauthorized parties.\n",
      "classification": "very promising",
      "cwe": "CWE-532",
      "function_names": [
        "saveThemeCustomConfig"
      ],
      "filenames": [
        "src/server/theme.ts"
      ]
    },
    {
      "headline": "Cross-Site Scripting (XSS) Through Markdown Rendering and Insecure Direct Object References",
      "analysis": "The application parses and renders user-controlled Markdown content without sufficient sanitization, leading to potential Cross-Site Scripting (XSS). There's also potential for unsanitized tag-based navigation, which might allow attackers to redirect users to malicious websites or execute arbitrary JavaScript through carefully crafted URLs.\n",
      "classification": "very promising",
      "cwe": "CWE-79",
      "function_names": [
        "renderPostDetail",
        "renderTags"
      ],
      "filenames": [
        "src/server/renderer.ts"
      ]
    }
  ],
  "scores": [
    {
      "stats": {
        "fn": 2,
        "tp": 0,
        "fp": 5
      },
      "mapping": {},
      "vuln_dates": {
        "CVE-2019-12047": "2019-05-13T15:29:03",
        "CVE-2022-40274": "2022-09-30T17:15:13"
      },
      "scoring_model": "claude-3-opus-20240229",
      "type": "llm",
      "instruction_template_hash": "245ace12b6361954d0a2"
    }
  ],
  "instruction_template_hash": "10c0163db4740318a544",
  "version": "0.1.0"
}
