{
  "commit": "3551a20773e4463eea8678bd937ad654c9a72fd5",
  "repo_url": "https://github.com/jenkinsci/logstash-plugin",
  "model": "claude-3-5-sonnet-20240620",
  "chunk_hashes": [
    "fb899b783dc080c59178"
  ],
  "responses": [
    {
      "content": "Based on my analysis of the provided codebase, here are the potential security vulnerabilities I identified:\n\n```yaml\nleads:\n  - headline: Potential XSS vulnerability in LogstashWriter\n    analysis: |\n      The LogstashWriter class writes log data directly to the output stream without any sanitization or encoding. This could potentially allow injection of malicious scripts if the log data contains user-controllable content. An attacker could potentially exploit this to execute arbitrary JavaScript in the context of the Jenkins UI.\n    cwe: CWE-79\n    function_names:\n      - write\n      - writeBuildLog  \n    filenames:\n      - src/main/java/jenkins/plugins/logstash/LogstashWriter.java\n    classification: slightly promising\n\n  - headline: Insecure use of default TrustManager in SSLHelper\n    analysis: |\n      The SSLHelper class uses a custom TrustManager that falls back to the default TrustManager if certificate validation fails with the custom certificate. This could potentially allow man-in-the-middle attacks if an attacker is able to present an invalid certificate that is accepted by the default TrustManager. A more secure approach would be to fail closed if validation fails with the custom certificate.\n    cwe: CWE-295\n    function_names:\n      - createSSLContext\n    filenames:  \n      - src/main/java/jenkins/plugins/logstash/utils/SSLHelper.java\n    classification: slightly promising\n\n  - headline: Potential sensitive data exposure in BuildData\n    analysis: |\n      The BuildData class collects and stores build environment variables and other build metadata. This could potentially include sensitive information like API keys or passwords if they are set as environment variables. The sensitive variables are removed using a list of known sensitive variable names, but this approach may miss sensitive data with non-standard names. A more comprehensive approach to identifying and redacting sensitive data may be needed.\n    cwe: CWE-200\n    function_names:\n      - initData\n    filenames:\n      - src/main/java/jenkins/plugins/logstash/persistence/BuildData.java  \n    classification: slightly promising\n\n  - headline: Use of potentially insecure random number generation\n    analysis: |\n      The ElasticSearchDao class uses SecureRandom without explicitly specifying the algorithm. This could potentially result in use of a weak random number generator on some platforms. It's generally recommended to explicitly specify a strong algorithm like SHA1PRNG.\n    cwe: CWE-330\n    function_names:\n      - createServerSSLContext\n    filenames:\n      - src/test/java/jenkins/plugins/logstash/persistence/ElasticSearchSSLCertsTest.java\n    classification: slightly promising\n\n  - headline: Potential for race condition in RabbitMqDao\n    analysis: |\n      The RabbitMqDao class creates a new connection and channel for each push operation. In a multi-threaded environment, this could potentially lead to race conditions if multiple threads are trying to push data simultaneously. A connection/channel pooling approach may be more robust.\n    cwe: CWE-362\n    function_names:\n      - push\n    filenames:\n      - src/main/java/jenkins/plugins/logstash/persistence/RabbitMqDao.java\n    classification: slightly promising\n```\n\nThese potential vulnerabilities are based on static analysis of the code and would require further investigation to confirm their exploitability in practice. The classifications are \"slightly promising\" as they represent areas of potential concern but may have mitigating factors or limited real-world impact.",
      "date": "2024-07-08T07:02:27.407681",
      "usage": {
        "prompt_tokens": 77758,
        "completion_tokens": 829,
        "cost": 0.245709
      }
    }
  ],
  "leads": [
    {
      "headline": "Potential XSS vulnerability in LogstashWriter",
      "analysis": "The LogstashWriter class writes log data directly to the output stream without any sanitization or encoding. This could potentially allow injection of malicious scripts if the log data contains user-controllable content. An attacker could potentially exploit this to execute arbitrary JavaScript in the context of the Jenkins UI.\n",
      "classification": "slightly promising",
      "cwe": "CWE-79",
      "function_names": [
        "write",
        "writeBuildLog"
      ],
      "filenames": [
        "src/main/java/jenkins/plugins/logstash/LogstashWriter.java"
      ]
    },
    {
      "headline": "Insecure use of default TrustManager in SSLHelper",
      "analysis": "The SSLHelper class uses a custom TrustManager that falls back to the default TrustManager if certificate validation fails with the custom certificate. This could potentially allow man-in-the-middle attacks if an attacker is able to present an invalid certificate that is accepted by the default TrustManager. A more secure approach would be to fail closed if validation fails with the custom certificate.\n",
      "classification": "slightly promising",
      "cwe": "CWE-295",
      "function_names": [
        "createSSLContext"
      ],
      "filenames": [
        "src/main/java/jenkins/plugins/logstash/utils/SSLHelper.java"
      ]
    },
    {
      "headline": "Potential sensitive data exposure in BuildData",
      "analysis": "The BuildData class collects and stores build environment variables and other build metadata. This could potentially include sensitive information like API keys or passwords if they are set as environment variables. The sensitive variables are removed using a list of known sensitive variable names, but this approach may miss sensitive data with non-standard names. A more comprehensive approach to identifying and redacting sensitive data may be needed.\n",
      "classification": "slightly promising",
      "cwe": "CWE-200",
      "function_names": [
        "initData"
      ],
      "filenames": [
        "src/main/java/jenkins/plugins/logstash/persistence/BuildData.java"
      ]
    },
    {
      "headline": "Use of potentially insecure random number generation",
      "analysis": "The ElasticSearchDao class uses SecureRandom without explicitly specifying the algorithm. This could potentially result in use of a weak random number generator on some platforms. It's generally recommended to explicitly specify a strong algorithm like SHA1PRNG.\n",
      "classification": "slightly promising",
      "cwe": "CWE-330",
      "function_names": [
        "createServerSSLContext"
      ],
      "filenames": [
        "src/test/java/jenkins/plugins/logstash/persistence/ElasticSearchSSLCertsTest.java"
      ]
    },
    {
      "headline": "Potential for race condition in RabbitMqDao",
      "analysis": "The RabbitMqDao class creates a new connection and channel for each push operation. In a multi-threaded environment, this could potentially lead to race conditions if multiple threads are trying to push data simultaneously. A connection/channel pooling approach may be more robust.\n",
      "classification": "slightly promising",
      "cwe": "CWE-362",
      "function_names": [
        "push"
      ],
      "filenames": [
        "src/main/java/jenkins/plugins/logstash/persistence/RabbitMqDao.java"
      ]
    }
  ],
  "scores": [
    {
      "stats": {
        "fn": 1,
        "tp": 0,
        "fp": 0
      },
      "mapping": {},
      "vuln_dates": {
        "CVE-2020-2143": "2020-03-09T16:15:13"
      },
      "scoring_model": "claude-3-5-sonnet-20240620",
      "type": "llm",
      "instruction_template_hash": "245ace12b6361954d0a2"
    }
  ],
  "instruction_template_hash": "10c0163db4740318a544",
  "version": "0.1.0"
}
