{
  "commit": "1368b4ce35ba2139328b9bd731fe2ea1ae5d9d27",
  "repo_url": "https://github.com/pingidentity/ssam",
  "model": "gpt-4o-2024-05-13",
  "chunk_hashes": [
    "9d242986302f3ba4247b"
  ],
  "responses": [
    {
      "content": "```yaml\nleads:\n  - headline: Command Injection in Bootstrap\n    analysis: |\n      The `showAlert` function in `src/main/resources/static/js/ssam.js` uses untrusted data while constructing a jQuery-based command for HTML output. This opens up the possibility for command injection where an attacker might inject arbitrary HTML or JavaScript.\n    cwe: CWE-78\n    function_names:\n      - showAlert\n    filenames:\n      - src/main/resources/static/js/ssam.js\n    classification: slightly promising\n\n  - headline: SQL Injection in LDAP Search\n    analysis: |\n      In the `LDAPAuthenticationProvider` class, a customized LDAP search filter is constructed using user-supplied input without proper sanitization. An attacker can exploit this to perform unauthorized LDAP queries or manipulate LDAP search results.\n    cwe: CWE-89\n    function_names:\n      - authenticate\n    filenames:\n      - src/main/java/com/unboundid/webapp/ssam/LDAPAuthenticationProvider.java\n    classification: very promising\n\n  - headline: Cross-Site Scripting (XSS) in Bootstrap\n    analysis: |\n      The `showAlert` function in `src/main/resources/static/js/ssam.js` directly inserts untrusted user input into HTML, which can lead to stored XSS attacks if the input is not validated and sanitized.\n    cwe: CWE-79\n    function_names:\n      - showAlert\n    filenames:\n      - src/main/resources/static/js/ssam.js\n    classification: very promising\n\n  - headline: Cleartext Transmission of Sensitive Information\n    analysis: |\n      The `setUpSecureConnection` function in `SSAMInstaller.java` uses configurations that do not enforce TLS/SSL in all cases, resulting in possible cleartext transmission of sensitive credentials.\n    cwe: CWE-319\n    function_names:\n      - setUpSecureConnection\n    filenames:\n      - src/main/java/com/unboundid/webapp/ssam/SSAMInstaller.java\n    classification: slightly promising\n\n  - headline: Insufficient Logging and Monitoring in Error Handling\n    analysis: |\n      The exception handling in multiple locations such as `SSAMInstaller.java` and `LDAPAuthenticationProvider.java` avoids logging certain errors, which could hinder detection of successful attacks.\n    cwe: CWE-778\n    function_names:\n      - doToolProcessing\n      - authenticate\n    filenames:\n      - src/main/java/com/unboundid/webapp/ssam/SSAMInstaller.java\n      - src/main/java/com/unboundid/webapp/ssam/LDAPAuthenticationProvider.java\n    classification: slightly promising\n\n  - headline: Insecure Storage of Sensitive Information\n    analysis: |\n      The `writeToFile` function in `SSAMInstaller.java` stores sensitive information such as passwords in potentially accessible locations on the filesystem without additional encryption, increasing the risk of unauthorized access.\n    cwe: CWE-922\n    function_names:\n      - writeToFile\n    filenames:\n      - src/main/java/com/unboundid/webapp/ssam/SSAMInstaller.java\n    classification: slightly promising\n\n  - headline: Client-side Input Validation Bypass\n    analysis: |\n      In the JavaScript functions such as `verifyRequiredInputs` and `getVerificationCode` in `ssam.js`, input validation is performed on the client side, which can be bypassed by an attacker using tools like a proxy or browser's developer tools.\n    cwe: CWE-20\n    function_names:\n      - verifyRequiredInputs\n      - getVerificationCode\n    filenames:\n      - src/main/resources/static/js/ssam.js\n    classification: not promising\n```",
      "date": "2024-06-13T11:02:46.789476",
      "usage": {
        "prompt_tokens": 55664,
        "completion_tokens": 756,
        "cost": 0.28966
      }
    }
  ],
  "leads": [
    {
      "headline": "Command Injection in Bootstrap",
      "analysis": "The showAlert function in src/main/resources/static/js/ssam.js uses untrusted data while constructing a jQuery-based command for HTML output. This opens up the possibility for command injection where an attacker might inject arbitrary HTML or JavaScript.\n",
      "classification": "slightly promising",
      "cwe": "CWE-78",
      "function_names": [
        "showAlert"
      ],
      "filenames": [
        "src/main/resources/static/js/ssam.js"
      ]
    },
    {
      "headline": "SQL Injection in LDAP Search",
      "analysis": "In the LDAPAuthenticationProvider class, a customized LDAP search filter is constructed using user-supplied input without proper sanitization. An attacker can exploit this to perform unauthorized LDAP queries or manipulate LDAP search results.\n",
      "classification": "very promising",
      "cwe": "CWE-89",
      "function_names": [
        "authenticate"
      ],
      "filenames": [
        "src/main/java/com/unboundid/webapp/ssam/LDAPAuthenticationProvider.java"
      ]
    },
    {
      "headline": "Cross-Site Scripting (XSS) in Bootstrap",
      "analysis": "The showAlert function in src/main/resources/static/js/ssam.js directly inserts untrusted user input into HTML, which can lead to stored XSS attacks if the input is not validated and sanitized.\n",
      "classification": "very promising",
      "cwe": "CWE-79",
      "function_names": [
        "showAlert"
      ],
      "filenames": [
        "src/main/resources/static/js/ssam.js"
      ]
    },
    {
      "headline": "Cleartext Transmission of Sensitive Information",
      "analysis": "The setUpSecureConnection function in SSAMInstaller.java uses configurations that do not enforce TLS/SSL in all cases, resulting in possible cleartext transmission of sensitive credentials.\n",
      "classification": "slightly promising",
      "cwe": "CWE-319",
      "function_names": [
        "setUpSecureConnection"
      ],
      "filenames": [
        "src/main/java/com/unboundid/webapp/ssam/SSAMInstaller.java"
      ]
    },
    {
      "headline": "Insufficient Logging and Monitoring in Error Handling",
      "analysis": "The exception handling in multiple locations such as SSAMInstaller.java and LDAPAuthenticationProvider.java avoids logging certain errors, which could hinder detection of successful attacks.\n",
      "classification": "slightly promising",
      "cwe": "CWE-778",
      "function_names": [
        "doToolProcessing",
        "authenticate"
      ],
      "filenames": [
        "src/main/java/com/unboundid/webapp/ssam/SSAMInstaller.java",
        "src/main/java/com/unboundid/webapp/ssam/LDAPAuthenticationProvider.java"
      ]
    },
    {
      "headline": "Insecure Storage of Sensitive Information",
      "analysis": "The writeToFile function in SSAMInstaller.java stores sensitive information such as passwords in potentially accessible locations on the filesystem without additional encryption, increasing the risk of unauthorized access.\n",
      "classification": "slightly promising",
      "cwe": "CWE-922",
      "function_names": [
        "writeToFile"
      ],
      "filenames": [
        "src/main/java/com/unboundid/webapp/ssam/SSAMInstaller.java"
      ]
    },
    {
      "headline": "Client-side Input Validation Bypass",
      "analysis": "In the JavaScript functions such as verifyRequiredInputs and getVerificationCode in ssam.js, input validation is performed on the client side, which can be bypassed by an attacker using tools like a proxy or browser's developer tools.\n",
      "classification": "not promising",
      "cwe": "CWE-20",
      "function_names": [
        "verifyRequiredInputs",
        "getVerificationCode"
      ],
      "filenames": [
        "src/main/resources/static/js/ssam.js"
      ]
    }
  ],
  "scores": [
    {
      "stats": {
        "fn": 1,
        "tp": 0,
        "fp": 2
      },
      "mapping": {},
      "vuln_dates": {
        "CVE-2018-25084": "2023-04-10T18:15:07"
      },
      "scoring_model": "claude-3-opus-20240229",
      "type": "llm",
      "instruction_template_hash": "245ace12b6361954d0a2"
    }
  ],
  "instruction_template_hash": "10c0163db4740318a544",
  "version": "0.1.0"
}
