{
  "commit": "0de06fd14e5c766d94ad077c741271e7d6f7d820",
  "repo_url": "https://github.com/asdfugil/nickchanbot",
  "model": "claude-3-haiku-20240307",
  "chunk_hashes": [
    "8ce8ef4978c06af1fc21"
  ],
  "responses": [
    {
      "content": "Here is the YAML output representing the security vulnerabilities in the provided codebase:\n\n```yaml\nleads:\n  - headline: Path Traversal in index.js\n    analysis: |\n      The `require('dotenv').config()` line in `index.js` could allow an attacker to load arbitrary environment variables, potentially exposing sensitive information like API keys or database credentials.\n    cwe: CWE-22\n    function_names:\n      - require\n    filenames:\n      - index.js\n    classification: slightly promising\n\n  - headline: SQL Injection in Keyv instantiation\n    analysis: |\n      The Keyv instantiation in `server.js`, `bot.js`, and other files could be vulnerable to SQL injection if user input is not properly sanitized. An attacker could potentially execute arbitrary SQL queries on the SQLite database.\n    cwe: CWE-89\n    function_names:\n      - Keyv\n    filenames:\n      - server.js\n      - bot.js\n    classification: very promising\n\n  - headline: Code Injection in eval.js\n    analysis: |\n      The `eval()` function used in the `eval.js` command could allow an attacker to execute arbitrary code on the server. This is a dangerous vulnerability that could lead to complete system compromise.\n    cwe: CWE-94\n    function_names:\n      - eval\n    filenames:\n      - commands/eval.js\n    classification: very promising\n\n  - headline: Potential Denial of Service in play.js\n    analysis: |\n      The `play.js` command uses `ytdl-core` to fetch YouTube videos. An attacker could potentially trigger a Denial of Service by sending malformed or excessively long URLs, causing the bot to crash or become unresponsive.\n    cwe: CWE-400\n    function_names:\n      - play\n      - ytdl\n    filenames:\n      - commands/play.js\n    classification: slightly promising\n\n  - headline: Potential Elevation of Privilege in config.js\n    analysis: |\n      The `config.js` command allows users with the \"Manage Server\" permission to configure various settings, including log channels and the muted role. An attacker who can trick a user with the necessary permissions into running this command could potentially elevate their own privileges or gain access to sensitive information.\n    cwe: CWE-269\n    function_names:\n      - config\n    filenames:\n      - commands/config.js\n    classification: slightly promising\n\n  - headline: Potential Information Disclosure in loggers\n    analysis: |\n      The various logger modules, such as `message.js` and `channelUpdate.js`, could potentially leak sensitive information about the server, such as user details, message contents, and channel configuration. An attacker could use this information to further their attack.\n    cwe: CWE-200\n    function_names:\n      - execute\n    filenames:\n      - loggers/message.js\n      - loggers/channelUpdate.js\n    classification: slightly promising\n```",
      "date": "2024-06-12T14:59:56.616204",
      "usage": {
        "prompt_tokens": 55161,
        "completion_tokens": 709,
        "cost": 0.0146765
      }
    }
  ],
  "leads": [
    {
      "headline": "Path Traversal in index.js",
      "analysis": "The require('dotenv').config() line in index.js could allow an attacker to load arbitrary environment variables, potentially exposing sensitive information like API keys or database credentials.\n",
      "classification": "slightly promising",
      "cwe": "CWE-22",
      "function_names": [
        "require"
      ],
      "filenames": [
        "index.js"
      ]
    },
    {
      "headline": "SQL Injection in Keyv instantiation",
      "analysis": "The Keyv instantiation in server.js, bot.js, and other files could be vulnerable to SQL injection if user input is not properly sanitized. An attacker could potentially execute arbitrary SQL queries on the SQLite database.\n",
      "classification": "very promising",
      "cwe": "CWE-89",
      "function_names": [
        "Keyv"
      ],
      "filenames": [
        "server.js",
        "bot.js"
      ]
    },
    {
      "headline": "Code Injection in eval.js",
      "analysis": "The eval() function used in the eval.js command could allow an attacker to execute arbitrary code on the server. This is a dangerous vulnerability that could lead to complete system compromise.\n",
      "classification": "very promising",
      "cwe": "CWE-94",
      "function_names": [
        "eval"
      ],
      "filenames": [
        "commands/eval.js"
      ]
    },
    {
      "headline": "Potential Denial of Service in play.js",
      "analysis": "The play.js command uses ytdl-core to fetch YouTube videos. An attacker could potentially trigger a Denial of Service by sending malformed or excessively long URLs, causing the bot to crash or become unresponsive.\n",
      "classification": "slightly promising",
      "cwe": "CWE-400",
      "function_names": [
        "play",
        "ytdl"
      ],
      "filenames": [
        "commands/play.js"
      ]
    },
    {
      "headline": "Potential Elevation of Privilege in config.js",
      "analysis": "The config.js command allows users with the \"Manage Server\" permission to configure various settings, including log channels and the muted role. An attacker who can trick a user with the necessary permissions into running this command could potentially elevate their own privileges or gain access to sensitive information.\n",
      "classification": "slightly promising",
      "cwe": "CWE-269",
      "function_names": [
        "config"
      ],
      "filenames": [
        "commands/config.js"
      ]
    },
    {
      "headline": "Potential Information Disclosure in loggers",
      "analysis": "The various logger modules, such as message.js and channelUpdate.js, could potentially leak sensitive information about the server, such as user details, message contents, and channel configuration. An attacker could use this information to further their attack.\n",
      "classification": "slightly promising",
      "cwe": "CWE-200",
      "function_names": [
        "execute"
      ],
      "filenames": [
        "loggers/message.js",
        "loggers/channelUpdate.js"
      ]
    }
  ],
  "scores": [
    {
      "stats": {
        "fn": 1,
        "tp": 0,
        "fp": 2
      },
      "mapping": {},
      "vuln_dates": {
        "CVE-2020-5282": "2020-03-25T19:15:15"
      },
      "scoring_model": "claude-3-opus-20240229",
      "type": "llm",
      "instruction_template_hash": "245ace12b6361954d0a2"
    },
    {
      "stats": {
        "fn": 1,
        "tp": 0,
        "fp": 2
      },
      "mapping": {},
      "vuln_dates": {
        "CVE-2020-5282": "2020-03-25T19:15:15"
      },
      "scoring_model": "claude-3-5-sonnet-20240620",
      "type": "llm",
      "instruction_template_hash": "245ace12b6361954d0a2"
    }
  ],
  "instruction_template_hash": "10c0163db4740318a544",
  "version": "0.1.0"
}
