{
  "commit": "00658265d83d0573168a2f045af154227074870c",
  "repo_url": "https://github.com/open-iscsi/tcmu-runner",
  "model": "claude-3-sonnet-20240229",
  "chunk_hashes": [
    "0426eb50388f6e5c08a2"
  ],
  "responses": [
    {
      "content": "The provided code seems to be a combination of various C files related to the TCMU (TCMU - TCMU (Target Coupled Multimode) Userspace) project, which is a userspace driver framework for Linux-based storage virtualization. Here's a breakdown of the files and their purposes:\n\n1. **qcow.c**: This file implements support for the QCOW (QEMU Copy-On-Write) disk image format. It provides functions for reading and writing QCOW disk images.\n\n2. **libtcmu_priv.h**: This is a private header file for the libtcmu library, which defines internal structures and functions.\n\n3. **consumer.c**: This appears to be an example implementation of a TCMU handler (a plugin that handles a specific storage device type).\n\n4. **tcmu-synthesizer.c**: Another example implementation of a TCMU handler called \"syn\".\n\n5. **api.c**: This file is part of the libtcmu library and provides various helper functions for handling SCSI commands and emulating basic SCSI operations.\n\n6. **file_example.c**: Yet another example implementation of a TCMU handler that backs a device by a file.\n\n7. **main.c**: The main entry point of the tcmu-runner daemon, which loads and manages TCMU handler plugins.\n\n8. **qcow2.h**: Header file for the QCOW2 (QEMU Copy-On-Write version 2) disk image format.\n\n9. **tcmu-runner.h**: Header file defining the interface between tcmu-runner and its loadable subtype handlers.\n\n10. **glfs.c**: A TCMU handler implementation for backing devices by Gluster volumes.\n\n11. **libtcmu_common.h**: Common header file for both libtcmu users and tcmu-runner plugins.\n\n12. **libtcmu.h**: Header file defining the libtcmu API, which provides an interface for handling TCMU devices and events.\n\n13. **libtcmu.c**: Implementation of the libtcmu library.\n\n14. **qcow.h**: Header file for the QCOW (QEMU Copy-On-Write) disk image format.\n\n15. **libtcmu-register.c**: Part of the libtcmu library, responsible for registering TCMU handlers with the DBus service.\n\n16. **scsi_defs.h**: Header file defining various SCSI constants and opcodes.\n\n17. **darray.h**: A header file defining a dynamic array data structure.\n\nThe code appears to be a part of the TCMU project, which provides a userspace driver framework for Linux-based storage virtualization. It allows developers to create handlers (plugins) that can expose various storage backends (such as files, disk images, or remote storage) as SCSI devices to applications and operating systems.\n\nThe security vulnerabilities in this codebase might include:\n\n1. **Improper Input Validation**: Some parts of the code may be vulnerable to improper input validation, such as buffer overflows or integer overflows, when handling user-provided data or configuration strings.\n\n2. **Path Traversal**: Functions that handle file paths or configuration strings containing file paths may be vulnerable to path traversal attacks if the input is not properly sanitized.\n\n3. **Untrusted Search Path**: Some parts of the code may be vulnerable to untrusted search path issues, such as loading handler modules from an insecure directory.\n\n4. **Use of Insecure Functions**: The codebase may be using insecure functions, such as `strcpy` or `sprintf`, which could lead to buffer overflows or other memory corruption issues.\n\n5. **Lack of Error Handling**: Insufficient or improper error handling could lead to unexpected behavior or potential vulnerabilities.\n\n6. **Race Conditions**: Multithreaded portions of the code may be vulnerable to race conditions, leading to undefined behavior or security issues.\n\n7. **Improper Resource Management**: Improper management of resources, such as file descriptors or memory, could lead to resource leaks or other vulnerabilities.\n\n8. **Privilege Escalation**: Depending on how the TCMU handlers are designed and implemented, there may be potential for privilege escalation vulnerabilities.\n\n9. **Untrusted Data Handling**: The code may be handling untrusted data from external sources (e.g., disk images or remote storage) without proper sanitization or validation, leading to potential vulnerabilities.\n\nIt's important to note that a thorough code review and analysis would be necessary to identify and assess the specific vulnerabilities present in this codebase. Additionally, the severity and exploitability of any vulnerabilities would depend on the specific deployment environment and configuration of the TCMU components.\n\nHere is the YAML output for the identified vulnerabilities:\n\n```yaml\nleads:\n  - headline: Improper Input Validation\n    analysis: |\n      Some parts of the code may be vulnerable to improper input validation, such as buffer overflows or integer overflows, when handling user-provided data or configuration strings.\n    cwe: CWE-20\n    function_names:\n      - tcmu_glfs_open\n      - tcmu_glfs_handle_cmd\n    filenames:\n      - glfs.c\n    classification: very promising\n\n  - headline: Path Traversal\n    analysis: |\n      Functions that handle file paths or configuration strings containing file paths may be vulnerable to path traversal attacks if the input is not properly sanitized.\n    cwe: CWE-706\n    function_names:\n      - tcmu_glfs_open\n      - tcmu_glfs_handle_cmd\n    filenames:\n      - glfs.c\n    classification: very promising\n\n  - headline: Untrusted Search Path\n    analysis: |\n      Some parts of the code may be vulnerable to untrusted search path issues, such as loading handler modules from an insecure directory.\n    cwe: CWE-668\n    function_names:\n      - open_handlers\n    filenames:\n      - main.c\n    classification: very promising\n\n  - headline: Use of Insecure Functions\n    analysis: |\n      The codebase may be using insecure functions, such as `strcpy` or `sprintf`, which could lead to buffer overflows or other memory corruption issues.\n    cwe: CWE-676\n    function_names:\n      - tcmu_emulate_evpd_inquiry\n    filenames:\n      - api.c\n    classification: slightly promising\n\n  - headline: Lack of Error Handling\n    analysis: |\n      Insufficient or improper error handling could lead to unexpected behavior or potential vulnerabilities.\n    cwe: CWE-754\n    function_names:\n      - tcmu_glfs_open\n      - tcmu_glfs_handle_cmd\n    filenames:\n      - glfs.c\n    classification: slightly promising\n\n  - headline: Race Conditions\n    analysis: |\n      Multithreaded portions of the code may be vulnerable to race conditions, leading to undefined behavior or security issues.\n    cwe: CWE-362\n    function_names:\n      - file_handler_run\n    filenames:\n      - file_example.c\n    classification: slightly promising\n\n  - headline: Improper Resource Management\n    analysis: |\n      Improper management of resources, such as file descriptors or memory, could lead to resource leaks or other vulnerabilities.\n    cwe: CWE-404\n    function_names:\n      - qcow_image_open\n      - qcow2_image_open\n    filenames:\n      - qcow.c\n    classification: slightly promising\n\n  - headline: Privilege Escalation\n    analysis: |\n      Depending on how the TCMU handlers are designed and implemented, there may be potential for privilege escalation vulnerabilities.\n    cwe: CWE-862\n    function_names: []\n    filenames: []\n    classification: not promising\n\n  - headline: Untrusted Data Handling\n    analysis: |\n      The code may be handling untrusted data from external sources (e.g., disk images or remote storage) without proper sanitization or validation, leading to potential vulnerabilities.\n    cwe: CWE-345\n    function_names:\n      - qcow_preadv\n      - qcow_pwritev\n    filenames:\n      - qcow.c\n    classification: very promising\n```\n\nPlease note that this is a high-level assessment based on the provided code snippets. A more thorough code review and analysis would be necessary to identify and assess the specific vulnerabilities in detail.",
      "date": "2024-06-13T10:47:00.256256",
      "usage": {
        "prompt_tokens": 72200,
        "completion_tokens": 1989,
        "cost": 0.246435
      }
    }
  ],
  "leads": [
    {
      "headline": "Improper Input Validation",
      "analysis": "Some parts of the code may be vulnerable to improper input validation, such as buffer overflows or integer overflows, when handling user-provided data or configuration strings.\n",
      "classification": "very promising",
      "cwe": "CWE-20",
      "function_names": [
        "tcmu_glfs_open",
        "tcmu_glfs_handle_cmd"
      ],
      "filenames": [
        "glfs.c"
      ]
    },
    {
      "headline": "Path Traversal",
      "analysis": "Functions that handle file paths or configuration strings containing file paths may be vulnerable to path traversal attacks if the input is not properly sanitized.\n",
      "classification": "very promising",
      "cwe": "CWE-706",
      "function_names": [
        "tcmu_glfs_open",
        "tcmu_glfs_handle_cmd"
      ],
      "filenames": [
        "glfs.c"
      ]
    },
    {
      "headline": "Untrusted Search Path",
      "analysis": "Some parts of the code may be vulnerable to untrusted search path issues, such as loading handler modules from an insecure directory.\n",
      "classification": "very promising",
      "cwe": "CWE-668",
      "function_names": [
        "open_handlers"
      ],
      "filenames": [
        "main.c"
      ]
    },
    {
      "headline": "Use of Insecure Functions",
      "analysis": "The codebase may be using insecure functions, such as strcpy or sprintf, which could lead to buffer overflows or other memory corruption issues.\n",
      "classification": "slightly promising",
      "cwe": "CWE-676",
      "function_names": [
        "tcmu_emulate_evpd_inquiry"
      ],
      "filenames": [
        "api.c"
      ]
    },
    {
      "headline": "Lack of Error Handling",
      "analysis": "Insufficient or improper error handling could lead to unexpected behavior or potential vulnerabilities.\n",
      "classification": "slightly promising",
      "cwe": "CWE-754",
      "function_names": [
        "tcmu_glfs_open",
        "tcmu_glfs_handle_cmd"
      ],
      "filenames": [
        "glfs.c"
      ]
    },
    {
      "headline": "Race Conditions",
      "analysis": "Multithreaded portions of the code may be vulnerable to race conditions, leading to undefined behavior or security issues.\n",
      "classification": "slightly promising",
      "cwe": "CWE-362",
      "function_names": [
        "file_handler_run"
      ],
      "filenames": [
        "file_example.c"
      ]
    },
    {
      "headline": "Improper Resource Management",
      "analysis": "Improper management of resources, such as file descriptors or memory, could lead to resource leaks or other vulnerabilities.\n",
      "classification": "slightly promising",
      "cwe": "CWE-404",
      "function_names": [
        "qcow_image_open",
        "qcow2_image_open"
      ],
      "filenames": [
        "qcow.c"
      ]
    },
    {
      "headline": "Privilege Escalation",
      "analysis": "Depending on how the TCMU handlers are designed and implemented, there may be potential for privilege escalation vulnerabilities.\n",
      "classification": "not promising",
      "cwe": "CWE-862",
      "function_names": [],
      "filenames": []
    },
    {
      "headline": "Untrusted Data Handling",
      "analysis": "The code may be handling untrusted data from external sources (e.g., disk images or remote storage) without proper sanitization or validation, leading to potential vulnerabilities.\n",
      "classification": "very promising",
      "cwe": "CWE-345",
      "function_names": [
        "qcow_preadv",
        "qcow_pwritev"
      ],
      "filenames": [
        "qcow.c"
      ]
    }
  ],
  "scores": [
    {
      "stats": {
        "fn": 4,
        "tp": 0,
        "fp": 4
      },
      "mapping": {},
      "vuln_dates": {
        "CVE-2017-1000198": "2017-11-17T02:29:00",
        "CVE-2017-1000200": "2017-11-17T02:29:00",
        "CVE-2017-1000199": "2017-11-17T02:29:00",
        "CVE-2017-1000201": "2017-11-17T02:29:01"
      },
      "scoring_model": "claude-3-opus-20240229",
      "type": "llm",
      "instruction_template_hash": "245ace12b6361954d0a2"
    },
    {
      "stats": {
        "fn": 4,
        "tp": 0,
        "fp": 4
      },
      "mapping": {},
      "vuln_dates": {
        "CVE-2017-1000198": "2017-11-17T02:29:00",
        "CVE-2017-1000200": "2017-11-17T02:29:00",
        "CVE-2017-1000199": "2017-11-17T02:29:00",
        "CVE-2017-1000201": "2017-11-17T02:29:01"
      },
      "scoring_model": "claude-3-5-sonnet-20240620",
      "type": "llm",
      "instruction_template_hash": "245ace12b6361954d0a2"
    }
  ],
  "instruction_template_hash": "10c0163db4740318a544",
  "version": "0.1.0"
}
