{
  "commit": "22e9b99015f488aa40018ddda1c261eb5b50b2d0",
  "repo_url": "https://github.com/jenkinsci/compuware-ispw-operations-plugin",
  "model": "gemini/gemini-1.5-pro",
  "chunk_hashes": [
    "27ef7bb64e9f3996882e"
  ],
  "responses": [
    {
      "content": "```yaml\nleads:\n  - headline: Insecure default permissions for webhook\n    analysis: |\n      The webhook endpoint (`/ispw-webhook-step/{token}`) is registered as an `UnprotectedRootAction`, making it accessible without any authentication.\n      This means that any user, including unauthenticated users, can trigger the webhook, potentially leading to unintended actions in the pipeline.\n    cwe: CWE-732\n    function_names:\n      - doDynamic\n    filenames:\n      - src/main/java/com/compuware/ispw/restapi/WebhookRootAction.java\n    classification: slightly promising\n  - headline: Webhook content not validated\n    analysis: |\n      The content received by the webhook (`/ispw-webhook-step/{token}`) is not validated.\n      A malicious actor could send arbitrary data to this endpoint, which might be processed by the pipeline without proper sanitization or validation.\n    cwe: CWE-20\n    function_names:\n      - doDynamic\n    filenames:\n      - src/main/java/com/compuware/ispw/restapi/WebhookRootAction.java\n    classification: slightly promising\n  - headline: Cleartext storage and transmission of ISPW token\n    analysis: |\n      The ISPW token is stored as a system property (`ces.ispw.token`), which could be accessed by unauthorized users on the system.\n      Furthermore, the token is transmitted in plain text in the `Authorization` header of HTTP requests, making it vulnerable to eavesdropping.\n    cwe: CWE-319\n    function_names:\n      - perform\n      - run\n    filenames:\n      - src/main/java/com/compuware/ispw/restapi/IspwRestApiRequest.java\n      - src/main/java/com/compuware/ispw/restapi/IspwRestApiRequestStep.java\n    classification: very promising\n  - headline: Unrestricted URL in EventCallback\n    analysis: |\n      The `EventCallback` object allows setting an arbitrary URL for webhook notifications.\n      If an attacker can control this value, they could redirect notifications to a malicious server under their control.\n    cwe: CWE-601\n    function_names:\n      - reflectSetter\n    filenames:\n      - src/main/java/com/compuware/ispw/restapi/util/RestApiUtils.java\n    classification: slightly promising\n  - headline: Lack of input validation for ISPW parameters\n    analysis: |\n      The `ispwRequestBody` parameter is used to construct URLs and JSON payloads for ISPW API requests.\n      However, there is no validation or sanitization of the input, potentially leading to injection vulnerabilities if an attacker can control this parameter.\n    cwe: CWE-20\n    function_names:\n      - getIspwRequestBean\n    filenames:\n      - src/main/java/com/compuware/ispw/restapi/action/AbstractGetAction.java\n      - src/main/java/com/compuware/ispw/restapi/action/AbstractPostAction.java\n      - src/main/java/com/compuware/ispw/restapi/action/SetInfoPostAction.java\n    classification: slightly promising\n  - headline: Unvalidated redirect after authentication\n    analysis: |\n      The `FormAuthentication` class performs a series of requests for authentication, but it doesn't validate the final redirect location.\n      This could allow an attacker to redirect the user to a malicious website after successful authentication.\n    cwe: CWE-601\n    function_names:\n      - authenticate\n    filenames:\n      - src/main/java/com/compuware/ispw/restapi/auth/FormAuthentication.java\n    classification: slightly promising\n```",
      "date": "2024-06-12T18:08:05.850241",
      "usage": {
        "prompt_tokens": 43699,
        "completion_tokens": 743,
        "cost": 0.028705
      }
    }
  ],
  "leads": [
    {
      "headline": "Insecure default permissions for webhook",
      "analysis": "The webhook endpoint (/ispw-webhook-step/{token}) is registered as an UnprotectedRootAction, making it accessible without any authentication.\nThis means that any user, including unauthenticated users, can trigger the webhook, potentially leading to unintended actions in the pipeline.\n",
      "classification": "slightly promising",
      "cwe": "CWE-732",
      "function_names": [
        "doDynamic"
      ],
      "filenames": [
        "src/main/java/com/compuware/ispw/restapi/WebhookRootAction.java"
      ]
    },
    {
      "headline": "Webhook content not validated",
      "analysis": "The content received by the webhook (/ispw-webhook-step/{token}) is not validated.\nA malicious actor could send arbitrary data to this endpoint, which might be processed by the pipeline without proper sanitization or validation.\n",
      "classification": "slightly promising",
      "cwe": "CWE-20",
      "function_names": [
        "doDynamic"
      ],
      "filenames": [
        "src/main/java/com/compuware/ispw/restapi/WebhookRootAction.java"
      ]
    },
    {
      "headline": "Cleartext storage and transmission of ISPW token",
      "analysis": "The ISPW token is stored as a system property (ces.ispw.token), which could be accessed by unauthorized users on the system.\nFurthermore, the token is transmitted in plain text in the Authorization header of HTTP requests, making it vulnerable to eavesdropping.\n",
      "classification": "very promising",
      "cwe": "CWE-319",
      "function_names": [
        "perform",
        "run"
      ],
      "filenames": [
        "src/main/java/com/compuware/ispw/restapi/IspwRestApiRequest.java",
        "src/main/java/com/compuware/ispw/restapi/IspwRestApiRequestStep.java"
      ]
    },
    {
      "headline": "Unrestricted URL in EventCallback",
      "analysis": "The EventCallback object allows setting an arbitrary URL for webhook notifications.\nIf an attacker can control this value, they could redirect notifications to a malicious server under their control.\n",
      "classification": "slightly promising",
      "cwe": "CWE-601",
      "function_names": [
        "reflectSetter"
      ],
      "filenames": [
        "src/main/java/com/compuware/ispw/restapi/util/RestApiUtils.java"
      ]
    },
    {
      "headline": "Lack of input validation for ISPW parameters",
      "analysis": "The ispwRequestBody parameter is used to construct URLs and JSON payloads for ISPW API requests.\nHowever, there is no validation or sanitization of the input, potentially leading to injection vulnerabilities if an attacker can control this parameter.\n",
      "classification": "slightly promising",
      "cwe": "CWE-20",
      "function_names": [
        "getIspwRequestBean"
      ],
      "filenames": [
        "src/main/java/com/compuware/ispw/restapi/action/AbstractGetAction.java",
        "src/main/java/com/compuware/ispw/restapi/action/AbstractPostAction.java",
        "src/main/java/com/compuware/ispw/restapi/action/SetInfoPostAction.java"
      ]
    },
    {
      "headline": "Unvalidated redirect after authentication",
      "analysis": "The FormAuthentication class performs a series of requests for authentication, but it doesn't validate the final redirect location.\nThis could allow an attacker to redirect the user to a malicious website after successful authentication.\n",
      "classification": "slightly promising",
      "cwe": "CWE-601",
      "function_names": [
        "authenticate"
      ],
      "filenames": [
        "src/main/java/com/compuware/ispw/restapi/auth/FormAuthentication.java"
      ]
    }
  ],
  "scores": [
    {
      "stats": {
        "fn": 2,
        "tp": 0,
        "fp": 1
      },
      "mapping": {},
      "vuln_dates": {
        "CVE-2022-36899": "2022-07-27T15:15:09",
        "CVE-2022-36898": "2022-07-27T15:15:09"
      },
      "scoring_model": "claude-3-opus-20240229",
      "type": "llm",
      "instruction_template_hash": "245ace12b6361954d0a2"
    },
    {
      "stats": {
        "fn": 2,
        "tp": 0,
        "fp": 1
      },
      "mapping": {},
      "vuln_dates": {
        "CVE-2022-36899": "2022-07-27T15:15:09",
        "CVE-2022-36898": "2022-07-27T15:15:09"
      },
      "scoring_model": "claude-3-5-sonnet-20240620",
      "type": "llm",
      "instruction_template_hash": "245ace12b6361954d0a2"
    }
  ],
  "instruction_template_hash": "10c0163db4740318a544",
  "version": "0.1.0"
}
