{
  "commit": "249091afd38e533c16d765cf47dbd537ea5de4e4",
  "repo_url": "https://github.com/jenkinsci/google-play-android-publisher-plugin",
  "model": "gpt-4o-2024-05-13",
  "chunk_hashes": [
    "e1a29a8487b9ae418f62"
  ],
  "responses": [
    {
      "content": "```yaml\nleads:\n  - headline: \"Credentials Exposure via Exception Handling\"\n    analysis: |\n      The `getServiceAccountCredentials` method in `CredentialsHandler.java` catches exceptions such as `GoogleRobotPrivateKeyCredentials.AccountIdNotSetException` and `GoogleRobotPrivateKeyCredentials.PrivateKeyNotSetException`, and includes detailed error messages from these exceptions. This can potentially expose sensitive configurations if these exceptions are not handled properly and are logged or displayed to unauthorized users.\n    cwe: CWE-209\n    function_names:\n      - \"getServiceAccountCredentials\"\n    filenames:\n      - \"src/main/java/org/jenkinsci/plugins/googleplayandroidpublisher/CredentialsHandler.java\"\n    classification: slightly promising\n  \n  - headline: \"Multiple Initialization Issues with Expansions Files Handling\"\n    analysis: |\n      There are multiple instances in `ApkUploadTask.java` where initialization logic for expansion files is handled multiple times and in different places making it difficult to track initialization manually. This can lead to inconsistent states if not managed correctly.\n    cwe: CWE-908\n    function_names:\n      - \"fetchLatestExpansionFileVersionCodes\"\n      - \"applyExpansionFile\"\n    filenames:\n      - \"src/main/java/org/jenkinsci/plugins/googleplayandroidpublisher/ApkUploadTask.java\"\n    classification: slightly promising\n  \n  - headline: \"Improper Input Validation in User-Provided Patterns\"\n    analysis: |\n      The `FindFilesTask` class and methods in `ApkPublisher.java` and `ReleaseTrackAssignmentBuilder.java` rely on user-provided file patterns or inputs. These inputs are used directly without proper validation to ensure they are not malicious or lead to denial of service by causing expensive filesystem operations.\n    cwe: CWE-20\n    function_names:\n      - \"invoke\"\n      - \"publishApk\"\n      - \"assignApk\"\n    filenames:\n      - \"src/main/java/org/jenkinsci/plugins/googleplayandroidpublisher/FindFilesTask.java\"\n      - \"src/main/java/org/jenkinsci/plugins/googleplayandroidpublisher/ApkPublisher.java\"\n      - \"src/main/java/org/jenkinsci/plugins/googleplayandroidpublisher/ReleaseTrackAssignmentBuilder.java\"\n    classification: very promising\n  \n  - headline: \"Potential Exposure of API Secrets\"\n    analysis: |\n      The `GooglePlayPublisher` and `CredentialsHandler` potentially hold credentials directly within their instances which can be retrievable through other means if not securely managed.\n    cwe: CWE-522\n    function_names:\n      - \"getServiceAccountCredentials\"\n    filenames:\n      - \"src/main/java/org/jenkinsci/plugins/googleplayandroidpublisher/CredentialsHandler.java\"\n      - \"src/main/java/org/jenkinsci/plugins/googleplayandroidpublisher/GooglePlayPublisher.java\"\n    classification: slightly promising\n\n  - headline: \"Observable Discrepancy from Exception Messages\"\n    analysis: |\n      The exception handling in `TrackAssignmentTask.java` uses different error messages for different exceptions. These tailored error messages can potentially be observed by an attacker to infer about the internal state or configuration of the application.\n    cwe: CWE-203\n    function_names:\n      - \"execute\"\n    filenames:\n      - \"src/main/java/org/jenkinsci/plugins/googleplayandroidpublisher/TrackAssignmentTask.java\"\n    classification: not promising\n```",
      "date": "2024-06-12T18:33:20.484417",
      "usage": {
        "prompt_tokens": 24392,
        "completion_tokens": 687,
        "cost": 0.132265
      }
    }
  ],
  "leads": [
    {
      "headline": "Credentials Exposure via Exception Handling",
      "analysis": "The getServiceAccountCredentials method in CredentialsHandler.java catches exceptions such as GoogleRobotPrivateKeyCredentials.AccountIdNotSetException and GoogleRobotPrivateKeyCredentials.PrivateKeyNotSetException, and includes detailed error messages from these exceptions. This can potentially expose sensitive configurations if these exceptions are not handled properly and are logged or displayed to unauthorized users.\n",
      "classification": "slightly promising",
      "cwe": "CWE-209",
      "function_names": [
        "getServiceAccountCredentials"
      ],
      "filenames": [
        "src/main/java/org/jenkinsci/plugins/googleplayandroidpublisher/CredentialsHandler.java"
      ]
    },
    {
      "headline": "Multiple Initialization Issues with Expansions Files Handling",
      "analysis": "There are multiple instances in ApkUploadTask.java where initialization logic for expansion files is handled multiple times and in different places making it difficult to track initialization manually. This can lead to inconsistent states if not managed correctly.\n",
      "classification": "slightly promising",
      "cwe": "CWE-908",
      "function_names": [
        "fetchLatestExpansionFileVersionCodes",
        "applyExpansionFile"
      ],
      "filenames": [
        "src/main/java/org/jenkinsci/plugins/googleplayandroidpublisher/ApkUploadTask.java"
      ]
    },
    {
      "headline": "Improper Input Validation in User-Provided Patterns",
      "analysis": "The FindFilesTask class and methods in ApkPublisher.java and ReleaseTrackAssignmentBuilder.java rely on user-provided file patterns or inputs. These inputs are used directly without proper validation to ensure they are not malicious or lead to denial of service by causing expensive filesystem operations.\n",
      "classification": "very promising",
      "cwe": "CWE-20",
      "function_names": [
        "invoke",
        "publishApk",
        "assignApk"
      ],
      "filenames": [
        "src/main/java/org/jenkinsci/plugins/googleplayandroidpublisher/FindFilesTask.java",
        "src/main/java/org/jenkinsci/plugins/googleplayandroidpublisher/ApkPublisher.java",
        "src/main/java/org/jenkinsci/plugins/googleplayandroidpublisher/ReleaseTrackAssignmentBuilder.java"
      ]
    },
    {
      "headline": "Potential Exposure of API Secrets",
      "analysis": "The GooglePlayPublisher and CredentialsHandler potentially hold credentials directly within their instances which can be retrievable through other means if not securely managed.\n",
      "classification": "slightly promising",
      "cwe": "CWE-522",
      "function_names": [
        "getServiceAccountCredentials"
      ],
      "filenames": [
        "src/main/java/org/jenkinsci/plugins/googleplayandroidpublisher/CredentialsHandler.java",
        "src/main/java/org/jenkinsci/plugins/googleplayandroidpublisher/GooglePlayPublisher.java"
      ]
    },
    {
      "headline": "Observable Discrepancy from Exception Messages",
      "analysis": "The exception handling in TrackAssignmentTask.java uses different error messages for different exceptions. These tailored error messages can potentially be observed by an attacker to infer about the internal state or configuration of the application.\n",
      "classification": "not promising",
      "cwe": "CWE-203",
      "function_names": [
        "execute"
      ],
      "filenames": [
        "src/main/java/org/jenkinsci/plugins/googleplayandroidpublisher/TrackAssignmentTask.java"
      ]
    }
  ],
  "scores": [
    {
      "stats": {
        "fn": 1,
        "tp": 0,
        "fp": 1
      },
      "mapping": {},
      "vuln_dates": {
        "CVE-2018-1000109": "2018-03-13T13:29:00"
      },
      "scoring_model": "claude-3-opus-20240229",
      "type": "llm",
      "instruction_template_hash": "245ace12b6361954d0a2"
    },
    {
      "stats": {
        "fn": 1,
        "tp": 0,
        "fp": 1
      },
      "mapping": {},
      "vuln_dates": {
        "CVE-2018-1000109": "2018-03-13T13:29:00"
      },
      "scoring_model": "claude-3-5-sonnet-20240620",
      "type": "llm",
      "instruction_template_hash": "245ace12b6361954d0a2"
    }
  ],
  "instruction_template_hash": "10c0163db4740318a544",
  "version": "0.1.0"
}
