{
  "commit": "0e306cc8ed5c3713ed3f51272720414d3e75d332",
  "repo_url": "https://github.com/sonnyp/json8",
  "model": "claude-3-haiku-20240307",
  "chunk_hashes": [
    "22c8f7b998458c07b1f9"
  ],
  "responses": [
    {
      "content": "```yaml\nleads:\n  - headline: Improper Neutralization of Input During Web Page Generation ('Cross-site Scripting')\n    analysis: |\n      The codebase includes several instances of improper neutralization of input during web page generation, which can lead to cross-site scripting (XSS) vulnerabilities. This allows an attacker to inject malicious scripts into web pages, which can be executed in the context of the victim's browser, potentially leading to data theft, session hijacking, and other malicious activities.\n    cwe: CWE-79\n    function_names:\n      - decode\n      - unescape\n    filenames:\n      - packages/pointer/lib/decode.js\n      - packages/pointer/lib/unescape.js\n    classification: very promising\n\n  - headline: Improper Neutralization of Special Elements used in an SQL Command ('SQL Injection')\n    analysis: |\n      The codebase includes several functions that handle user input, such as `decode` and `unescape`, without proper sanitization. This can lead to SQL injection vulnerabilities, where an attacker can inject malicious SQL statements into the application's queries, potentially allowing them to read, modify, or delete sensitive data from the database.\n    cwe: CWE-89\n    function_names:\n      - decode\n      - unescape\n    filenames:\n      - packages/pointer/lib/decode.js\n      - packages/pointer/lib/unescape.js\n    classification: very promising\n\n  - headline: Improper Restriction of XML External Entity Reference\n    analysis: |\n      The codebase includes functionality for parsing and serializing JSON data, which could be vulnerable to XML External Entity (XXE) attacks if the XML parser is not properly configured to restrict the parsing of external entities. This could allow an attacker to access sensitive files or system resources on the server, or even execute arbitrary code.\n    cwe: CWE-611\n    function_names:\n      - parse\n      - serialize\n    filenames:\n      - packages/json8/lib/parse.js\n      - packages/json8/lib/serialize.js\n    classification: slightly promising\n\n  - headline: Allocation of Resources Without Limits or Throttling\n    analysis: |\n      The codebase includes functionality for parsing and serializing large JSON data, which could lead to resource exhaustion vulnerabilities if an attacker is able to send large or malformed payloads. This could result in denial of service attacks, where the application's resources (such as memory or CPU) are consumed, causing the application to become unresponsive.\n    cwe: CWE-770\n    function_names:\n      - parse\n      - serialize\n    filenames:\n      - packages/json8/lib/parse.js\n      - packages/json8/lib/serialize.js\n    classification: slightly promising\n\n  - headline: Improper Certificate Validation\n    analysis: |\n      The codebase does not include any functionality related to certificate validation or secure communication protocols. However, if the application that uses this codebase relies on external libraries or services for these functionalities, it could be vulnerable to man-in-the-middle attacks or other security issues if the certificate validation is not properly implemented.\n    cwe: CWE-295\n    function_names: []\n    filenames: []\n    classification: not promising\n```",
      "date": "2024-06-13T11:55:38.340261",
      "usage": {
        "prompt_tokens": 60208,
        "completion_tokens": 767,
        "cost": 0.01601075
      }
    }
  ],
  "leads": [
    {
      "headline": "Improper Neutralization of Input During Web Page Generation ('Cross-site Scripting')",
      "analysis": "The codebase includes several instances of improper neutralization of input during web page generation, which can lead to cross-site scripting (XSS) vulnerabilities. This allows an attacker to inject malicious scripts into web pages, which can be executed in the context of the victim's browser, potentially leading to data theft, session hijacking, and other malicious activities.\n",
      "classification": "very promising",
      "cwe": "CWE-79",
      "function_names": [
        "decode",
        "unescape"
      ],
      "filenames": [
        "packages/pointer/lib/decode.js",
        "packages/pointer/lib/unescape.js"
      ]
    },
    {
      "headline": "Improper Neutralization of Special Elements used in an SQL Command ('SQL Injection')",
      "analysis": "The codebase includes several functions that handle user input, such as decode and unescape, without proper sanitization. This can lead to SQL injection vulnerabilities, where an attacker can inject malicious SQL statements into the application's queries, potentially allowing them to read, modify, or delete sensitive data from the database.\n",
      "classification": "very promising",
      "cwe": "CWE-89",
      "function_names": [
        "decode",
        "unescape"
      ],
      "filenames": [
        "packages/pointer/lib/decode.js",
        "packages/pointer/lib/unescape.js"
      ]
    },
    {
      "headline": "Improper Restriction of XML External Entity Reference",
      "analysis": "The codebase includes functionality for parsing and serializing JSON data, which could be vulnerable to XML External Entity (XXE) attacks if the XML parser is not properly configured to restrict the parsing of external entities. This could allow an attacker to access sensitive files or system resources on the server, or even execute arbitrary code.\n",
      "classification": "slightly promising",
      "cwe": "CWE-611",
      "function_names": [
        "parse",
        "serialize"
      ],
      "filenames": [
        "packages/json8/lib/parse.js",
        "packages/json8/lib/serialize.js"
      ]
    },
    {
      "headline": "Allocation of Resources Without Limits or Throttling",
      "analysis": "The codebase includes functionality for parsing and serializing large JSON data, which could lead to resource exhaustion vulnerabilities if an attacker is able to send large or malformed payloads. This could result in denial of service attacks, where the application's resources (such as memory or CPU) are consumed, causing the application to become unresponsive.\n",
      "classification": "slightly promising",
      "cwe": "CWE-770",
      "function_names": [
        "parse",
        "serialize"
      ],
      "filenames": [
        "packages/json8/lib/parse.js",
        "packages/json8/lib/serialize.js"
      ]
    },
    {
      "headline": "Improper Certificate Validation",
      "analysis": "The codebase does not include any functionality related to certificate validation or secure communication protocols. However, if the application that uses this codebase relies on external libraries or services for these functionalities, it could be vulnerable to man-in-the-middle attacks or other security issues if the certificate validation is not properly implemented.\n",
      "classification": "not promising",
      "cwe": "CWE-295",
      "function_names": [],
      "filenames": []
    }
  ],
  "scores": [
    {
      "stats": {
        "fn": 1,
        "tp": 0,
        "fp": 2
      },
      "mapping": {},
      "vuln_dates": {
        "CVE-2020-7770": "2020-11-12T11:15:11"
      },
      "scoring_model": "claude-3-opus-20240229",
      "type": "llm",
      "instruction_template_hash": "245ace12b6361954d0a2"
    }
  ],
  "instruction_template_hash": "10c0163db4740318a544",
  "version": "0.1.0"
}
