{
  "commit": "20ce28ba0c25d8062323f82b4b9bcbbfbc5142d1",
  "repo_url": "https://github.com/pandora-analysis/pandora",
  "model": "claude-3-sonnet-20240229",
  "chunk_hashes": [
    "248429ec84c3819aa582"
  ],
  "responses": [
    {
      "content": "```yaml\nleads:\n  - headline: Potential shell injection vulnerability in run_kvrocks.sh\n    analysis: |\n      The script `run_kvrocks.sh` directly executes the `kvrocks` binary without sanitizing the input command line arguments. This could potentially allow an attacker to inject arbitrary shell commands if the `kvrocks` binary is vulnerable to command injection or if the script is executed with untrusted input.\n    cwe: CWE-78\n    function_names:\n      - run_kvrocks.sh\n    filenames:\n      - storage/run_kvrocks.sh\n    classification: very promising\n\n  - headline: Potential shell injection vulnerability in run_redis.sh\n    analysis: |\n      The script `run_redis.sh` directly executes the `redis-server` binary without sanitizing the input command line arguments. This could potentially allow an attacker to inject arbitrary shell commands if the `redis-server` binary is vulnerable to command injection or if the script is executed with untrusted input.\n    cwe: CWE-78\n    function_names:\n      - run_redis.sh\n    filenames:\n      - cache/run_redis.sh\n    classification: very promising\n\n  - headline: Potential arbitrary file upload vulnerability in api_submit\n    analysis: |\n      The `api_submit` function in `generic_api.py` allows users to upload arbitrary files to the server. While it checks if the user has the `submit_file` permission, there is no validation of the file content or type. An attacker with the `submit_file` permission could potentially upload malicious files that could be executed on the server or used for other attacks.\n    cwe: CWE-434\n    function_names:\n      - api_submit\n    filenames:\n      - website/web/generic_api.py\n    classification: very promising\n\n  - headline: Potential directory traversal vulnerability in update_task_paths.py\n    analysis: |\n      The `update_task_paths.py` script uses the `shutil.move` function to move task files from one directory to another. However, it does not validate the source and destination paths, which could potentially allow an attacker to perform directory traversal attacks and move files to arbitrary locations on the file system.\n    cwe: CWE-22\n    function_names:\n      - update_task_paths.py\n    filenames:\n      - tools/update_task_paths.py\n    classification: very promising\n\n  - headline: Potential uncontrolled resource consumption vulnerability in archive extraction\n    analysis: |\n      The `Extractor` class in `extractor.py` does not properly limit the number of files or the total size of extracted files from archives. An attacker could potentially craft a malicious archive file that extracts an excessive number of files or consumes an excessive amount of disk space, leading to a denial of service condition.\n    cwe: CWE-770\n    function_names:\n      - analyse\n    filenames:\n      - pandora/workers/extractor.py\n    classification: very promising\n\n  - headline: Potential open redirect vulnerability in api_analysis\n    analysis: |\n      The `api_analysis` function in `__init__.py` does not properly validate the `seed` parameter, which is used to construct a URL. An attacker could potentially pass a malicious `seed` value that causes the URL to redirect to an untrusted external site, leading to an open redirect vulnerability.\n    cwe: CWE-601\n    function_names:\n      - api_analysis\n    filenames:\n      - website/web/__init__.py\n    classification: very promising\n\n  - headline: Potential cryptographic failure in password storage\n    analysis: |\n      The `build_users_table` function in `helpers.py` appears to store user passwords in plain text or using a weak hashing algorithm. Storing passwords in plain text or using weak hashing algorithms is a cryptographic failure that could allow an attacker to compromise user accounts if the password data is accessed.\n    cwe: CWE-327\n    function_names:\n      - build_users_table\n    filenames:\n      - website/web/helpers.py\n    classification: very promising\n\n  - headline: Potential race condition vulnerability in AbstractManager\n    analysis: |\n      The `AbstractManager` class in `abstractmanager.py` uses a Redis database to store information about running scripts and services. However, the `is_running` method does not use any locking mechanism, which could potentially lead to race conditions if multiple processes try to access and modify the same data simultaneously.\n    cwe: CWE-362\n    function_names:\n      - is_running\n    filenames:\n      - pandora/default/abstractmanager.py\n    classification: slightly promising\n\n  - headline: Potential privilege escalation vulnerability in api_admin_submit\n    analysis: |\n      The `api_admin_submit` function in `__init__.py` appears to allow users to log in as an admin by providing the correct username and password. However, there is no validation to ensure that the user is authorized to perform this action, which could potentially lead to privilege escalation if an attacker can obtain the admin credentials.\n    cwe: CWE-269\n    function_names:\n      - api_admin_submit\n    filenames:\n      - website/web/__init__.py\n    classification: very promising\n\n  - headline: Potential unsecured file upload vulnerability in api_task_download\n    analysis: |\n      The `api_task_download` function in `__init__.py` allows users to download various types of files related to a task, such as images, PDFs, and text files. However, there is no validation to ensure that the requesting user is authorized to access the requested file, which could potentially allow an attacker to download files they should not have access to.\n    cwe: CWE-434\n    function_names:\n      - api_task_download\n    filenames:\n      - website/web/__init__.py\n    classification: very promising\n\n  - headline: Potential session fixation vulnerability in user_init\n    analysis: |\n      The `User` class in `user.py` appears to use the session ID as the user identifier. However, there is no validation to ensure that the session ID is securely generated and not predictable or fixable by an attacker. This could potentially lead to a session fixation vulnerability, where an attacker can set a known session ID and hijack a user's session.\n    cwe: CWE-384\n    function_names:\n      - __init__\n    filenames:\n      - pandora/user.py\n    classification: slightly promising\n\n  - headline: Potential XML external entity (XXE) vulnerability in parsing XML files\n    analysis: |\n      The codebase appears to use various XML parsing libraries, such as `defusedxml` and `lxml`. However, it is not clear if these libraries are properly configured to prevent XML external entity (XXE) attacks. An XXE vulnerability could allow an attacker to potentially disclose sensitive information or perform other types of attacks by including external entities in an XML file.\n    cwe: CWE-611\n    function_names: []\n    filenames: []\n    classification: slightly promising\n```\n\nThe analysis covers a range of potential security vulnerabilities in the codebase, including injection vulnerabilities, file upload vulnerabilities, uncontrolled resource consumption, open redirect vulnerabilities, cryptographic failures, race conditions, privilege escalation vulnerabilities, session fixation vulnerabilities, and XML external entity vulnerabilities.\n\nSome of the more critical issues include:\n\n- Potential arbitrary file upload vulnerability in the `api_submit` function, which could allow an attacker to upload malicious files.\n- Potential directory traversal vulnerability in the `update_task_paths.py` script, which could allow an attacker to move files to arbitrary locations on the file system.\n- Potential uncontrolled resource consumption vulnerability in the `Extractor` class, which could lead to a denial of service condition.\n- Potential open redirect vulnerability in the `api_analysis` function, which could allow an attacker to redirect users to untrusted external sites.\n- Potential cryptographic failure in the `build_users_table` function, which appears to store user passwords in plain text or using a weak hashing algorithm.\n- Potential privilege escalation vulnerability in the `api_admin_submit` function, which could allow an attacker to gain admin privileges if they obtain the admin credentials.\n- Potential unsecured file upload vulnerability in the `api_task_download` function, which could allow an attacker to download files they should not have access to.\n\nThe analysis also includes some less critical issues, such as potential shell injection vulnerabilities in scripts, a potential race condition vulnerability in the `AbstractManager` class, a potential session fixation vulnerability in the `User` class initialization, and a potential XML external entity (XXE) vulnerability in parsing XML files.\n\nOverall, the analysis identifies several potential security vulnerabilities that should be addressed to improve the security of the codebase.",
      "date": "2024-06-13T10:59:48.920234",
      "usage": {
        "prompt_tokens": 112468,
        "completion_tokens": 2061,
        "cost": 0.368319
      }
    }
  ],
  "leads": [
    {
      "headline": "Potential shell injection vulnerability in run_kvrocks.sh",
      "analysis": "The script run_kvrocks.sh directly executes the kvrocks binary without sanitizing the input command line arguments. This could potentially allow an attacker to inject arbitrary shell commands if the kvrocks binary is vulnerable to command injection or if the script is executed with untrusted input.\n",
      "classification": "very promising",
      "cwe": "CWE-78",
      "function_names": [
        "run_kvrocks.sh"
      ],
      "filenames": [
        "storage/run_kvrocks.sh"
      ]
    },
    {
      "headline": "Potential shell injection vulnerability in run_redis.sh",
      "analysis": "The script run_redis.sh directly executes the redis-server binary without sanitizing the input command line arguments. This could potentially allow an attacker to inject arbitrary shell commands if the redis-server binary is vulnerable to command injection or if the script is executed with untrusted input.\n",
      "classification": "very promising",
      "cwe": "CWE-78",
      "function_names": [
        "run_redis.sh"
      ],
      "filenames": [
        "cache/run_redis.sh"
      ]
    },
    {
      "headline": "Potential arbitrary file upload vulnerability in api_submit",
      "analysis": "The api_submit function in generic_api.py allows users to upload arbitrary files to the server. While it checks if the user has the submit_file permission, there is no validation of the file content or type. An attacker with the submit_file permission could potentially upload malicious files that could be executed on the server or used for other attacks.\n",
      "classification": "very promising",
      "cwe": "CWE-434",
      "function_names": [
        "api_submit"
      ],
      "filenames": [
        "website/web/generic_api.py"
      ]
    },
    {
      "headline": "Potential directory traversal vulnerability in update_task_paths.py",
      "analysis": "The update_task_paths.py script uses the shutil.move function to move task files from one directory to another. However, it does not validate the source and destination paths, which could potentially allow an attacker to perform directory traversal attacks and move files to arbitrary locations on the file system.\n",
      "classification": "very promising",
      "cwe": "CWE-22",
      "function_names": [
        "update_task_paths.py"
      ],
      "filenames": [
        "tools/update_task_paths.py"
      ]
    },
    {
      "headline": "Potential uncontrolled resource consumption vulnerability in archive extraction",
      "analysis": "The Extractor class in extractor.py does not properly limit the number of files or the total size of extracted files from archives. An attacker could potentially craft a malicious archive file that extracts an excessive number of files or consumes an excessive amount of disk space, leading to a denial of service condition.\n",
      "classification": "very promising",
      "cwe": "CWE-770",
      "function_names": [
        "analyse"
      ],
      "filenames": [
        "pandora/workers/extractor.py"
      ]
    },
    {
      "headline": "Potential open redirect vulnerability in api_analysis",
      "analysis": "The api_analysis function in __init__.py does not properly validate the seed parameter, which is used to construct a URL. An attacker could potentially pass a malicious seed value that causes the URL to redirect to an untrusted external site, leading to an open redirect vulnerability.\n",
      "classification": "very promising",
      "cwe": "CWE-601",
      "function_names": [
        "api_analysis"
      ],
      "filenames": [
        "website/web/__init__.py"
      ]
    },
    {
      "headline": "Potential cryptographic failure in password storage",
      "analysis": "The build_users_table function in helpers.py appears to store user passwords in plain text or using a weak hashing algorithm. Storing passwords in plain text or using weak hashing algorithms is a cryptographic failure that could allow an attacker to compromise user accounts if the password data is accessed.\n",
      "classification": "very promising",
      "cwe": "CWE-327",
      "function_names": [
        "build_users_table"
      ],
      "filenames": [
        "website/web/helpers.py"
      ]
    },
    {
      "headline": "Potential race condition vulnerability in AbstractManager",
      "analysis": "The AbstractManager class in abstractmanager.py uses a Redis database to store information about running scripts and services. However, the is_running method does not use any locking mechanism, which could potentially lead to race conditions if multiple processes try to access and modify the same data simultaneously.\n",
      "classification": "slightly promising",
      "cwe": "CWE-362",
      "function_names": [
        "is_running"
      ],
      "filenames": [
        "pandora/default/abstractmanager.py"
      ]
    },
    {
      "headline": "Potential privilege escalation vulnerability in api_admin_submit",
      "analysis": "The api_admin_submit function in __init__.py appears to allow users to log in as an admin by providing the correct username and password. However, there is no validation to ensure that the user is authorized to perform this action, which could potentially lead to privilege escalation if an attacker can obtain the admin credentials.\n",
      "classification": "very promising",
      "cwe": "CWE-269",
      "function_names": [
        "api_admin_submit"
      ],
      "filenames": [
        "website/web/__init__.py"
      ]
    },
    {
      "headline": "Potential unsecured file upload vulnerability in api_task_download",
      "analysis": "The api_task_download function in __init__.py allows users to download various types of files related to a task, such as images, PDFs, and text files. However, there is no validation to ensure that the requesting user is authorized to access the requested file, which could potentially allow an attacker to download files they should not have access to.\n",
      "classification": "very promising",
      "cwe": "CWE-434",
      "function_names": [
        "api_task_download"
      ],
      "filenames": [
        "website/web/__init__.py"
      ]
    },
    {
      "headline": "Potential session fixation vulnerability in user_init",
      "analysis": "The User class in user.py appears to use the session ID as the user identifier. However, there is no validation to ensure that the session ID is securely generated and not predictable or fixable by an attacker. This could potentially lead to a session fixation vulnerability, where an attacker can set a known session ID and hijack a user's session.\n",
      "classification": "slightly promising",
      "cwe": "CWE-384",
      "function_names": [
        "__init__"
      ],
      "filenames": [
        "pandora/user.py"
      ]
    },
    {
      "headline": "Potential XML external entity (XXE) vulnerability in parsing XML files",
      "analysis": "The codebase appears to use various XML parsing libraries, such as defusedxml and lxml. However, it is not clear if these libraries are properly configured to prevent XML external entity (XXE) attacks. An XXE vulnerability could allow an attacker to potentially disclose sensitive information or perform other types of attacks by including external entities in an XML file.\n",
      "classification": "slightly promising",
      "cwe": "CWE-611",
      "function_names": [],
      "filenames": []
    }
  ],
  "scores": [
    {
      "stats": {
        "fn": 0,
        "tp": 1,
        "fp": 8
      },
      "mapping": {
        "4": "CVE-2023-22898"
      },
      "vuln_dates": {
        "CVE-2023-22898": "2023-01-10T02:15:09"
      },
      "scoring_model": "claude-3-opus-20240229",
      "type": "llm",
      "instruction_template_hash": "245ace12b6361954d0a2"
    }
  ],
  "instruction_template_hash": "10c0163db4740318a544",
  "version": "0.1.0"
}
