{
  "commit": "154672eb175a96f2066e7c7cfb890709868ef343",
  "repo_url": "https://github.com/thehive-project/cortex",
  "model": "claude-3-5-sonnet-20240620",
  "chunk_hashes": [
    "ae382d148cd45a0b8baa"
  ],
  "responses": [
    {
      "content": "Here's a summary of the potential security vulnerabilities I identified in the codebase:\n\n```yaml\nleads:\n  - headline: Potential command injection vulnerability in job execution\n    analysis: |\n      The JobSrv class executes shell commands using the Process class, passing in user-controlled input. \n      This could allow command injection if the input is not properly sanitized. The code uses osexec() \n      to escape the command on Windows, but does not appear to do any escaping on other platforms.\n    cwe: CWE-78  \n    function_names:\n      - run\n    filenames:\n      - app/org/thp/cortex/services/JobSrv.scala\n    classification: very promising\n\n  - headline: Weak cryptographic hashing for password storage\n    analysis: |\n      The LocalAuthSrv class uses SHA-256 for password hashing, which is not considered sufficiently \n      slow for password storage. A dedicated password hashing algorithm like bcrypt or Argon2 should \n      be used instead to make brute-force attacks more difficult.\n    cwe: CWE-916\n    function_names:\n      - doAuthenticate\n      - setPassword  \n    filenames:\n      - app/org/thp/cortex/services/LocalAuthSrv.scala\n    classification: very promising\n\n  - headline: Insecure random number generation for authentication tokens\n    analysis: |\n      The KeyAuthSrv class uses scala.util.Random to generate authentication tokens, which is not \n      cryptographically secure. A cryptographically secure random number generator should be used \n      instead for security-sensitive random values like authentication tokens.\n    cwe: CWE-338\n    function_names:\n      - generateKey\n    filenames:  \n      - app/org/thp/cortex/services/KeyAuthSrv.scala\n    classification: very promising\n\n  - headline: Potential exposure of sensitive information in logs\n    analysis: |\n      There are multiple instances of logging sensitive information like passwords, API keys, etc. \n      This could expose sensitive data if logs are compromised. Sensitive data should be redacted \n      before logging.\n    cwe: CWE-532\n    function_names: []\n    filenames:\n      - app/org/thp/cortex/services/ErrorHandler.scala\n      - app/org/thp/cortex/services/StreamSrv.scala  \n    classification: slightly promising\n\n  - headline: Missing CSRF protection on some API endpoints\n    analysis: |\n      The CSRFFilter only applies CSRF protection to /api routes that have a session. Some API \n      endpoints may be missing CSRF protection, potentially allowing CSRF attacks.\n    cwe: CWE-352\n    function_names:\n      - shouldProtect\n    filenames:\n      - app/org/thp/cortex/services/CSRFFilter.scala\n    classification: slightly promising\n```\n\nThis identifies some of the most critical potential vulnerabilities I found in the codebase. The command injection and weak cryptography issues are particularly concerning and should be prioritized for remediation. Let me know if you need any clarification or have additional questions!",
      "date": "2024-07-08T08:56:52.339113",
      "usage": {
        "prompt_tokens": 145876,
        "completion_tokens": 744,
        "cost": 0.448788
      }
    }
  ],
  "leads": [
    {
      "headline": "Potential command injection vulnerability in job execution",
      "analysis": "The JobSrv class executes shell commands using the Process class, passing in user-controlled input. \nThis could allow command injection if the input is not properly sanitized. The code uses osexec() \nto escape the command on Windows, but does not appear to do any escaping on other platforms.\n",
      "classification": "very promising",
      "cwe": "CWE-78",
      "function_names": [
        "run"
      ],
      "filenames": [
        "app/org/thp/cortex/services/JobSrv.scala"
      ]
    },
    {
      "headline": "Weak cryptographic hashing for password storage",
      "analysis": "The LocalAuthSrv class uses SHA-256 for password hashing, which is not considered sufficiently \nslow for password storage. A dedicated password hashing algorithm like bcrypt or Argon2 should \nbe used instead to make brute-force attacks more difficult.\n",
      "classification": "very promising",
      "cwe": "CWE-916",
      "function_names": [
        "doAuthenticate",
        "setPassword"
      ],
      "filenames": [
        "app/org/thp/cortex/services/LocalAuthSrv.scala"
      ]
    },
    {
      "headline": "Insecure random number generation for authentication tokens",
      "analysis": "The KeyAuthSrv class uses scala.util.Random to generate authentication tokens, which is not \ncryptographically secure. A cryptographically secure random number generator should be used \ninstead for security-sensitive random values like authentication tokens.\n",
      "classification": "very promising",
      "cwe": "CWE-338",
      "function_names": [
        "generateKey"
      ],
      "filenames": [
        "app/org/thp/cortex/services/KeyAuthSrv.scala"
      ]
    },
    {
      "headline": "Potential exposure of sensitive information in logs",
      "analysis": "There are multiple instances of logging sensitive information like passwords, API keys, etc. \nThis could expose sensitive data if logs are compromised. Sensitive data should be redacted \nbefore logging.\n",
      "classification": "slightly promising",
      "cwe": "CWE-532",
      "function_names": [],
      "filenames": [
        "app/org/thp/cortex/services/ErrorHandler.scala",
        "app/org/thp/cortex/services/StreamSrv.scala"
      ]
    },
    {
      "headline": "Missing CSRF protection on some API endpoints",
      "analysis": "The CSRFFilter only applies CSRF protection to /api routes that have a session. Some API \nendpoints may be missing CSRF protection, potentially allowing CSRF attacks.\n",
      "classification": "slightly promising",
      "cwe": "CWE-352",
      "function_names": [
        "shouldProtect"
      ],
      "filenames": [
        "app/org/thp/cortex/services/CSRFFilter.scala"
      ]
    }
  ],
  "scores": [
    {
      "stats": {
        "fn": 1,
        "tp": 0,
        "fp": 3
      },
      "mapping": {},
      "vuln_dates": {
        "CVE-2018-20226": "2018-12-21T23:29:00"
      },
      "scoring_model": "claude-3-5-sonnet-20240620",
      "type": "llm",
      "instruction_template_hash": "245ace12b6361954d0a2"
    }
  ],
  "instruction_template_hash": "10c0163db4740318a544",
  "version": "0.1.0"
}
