{
  "commit": "2209aff509bd15e8641cb9ae3c9bbb8056f7dd7b",
  "repo_url": "https://github.com/adrianlopezroche/fdupes",
  "model": "claude-3-5-sonnet-20240620",
  "chunk_hashes": [
    "f2b383d87be58450bdbe"
  ],
  "responses": [
    {
      "content": "```yaml\nleads:\n  - headline: Command injection vulnerability in command execution\n    analysis: |\n      The fdupes program uses system() to execute the help command string defined in HELP_COMMAND_STRING. This allows an attacker to inject arbitrary commands if they can control the HELP_COMMAND_STRING value at compile time. The system() function executes commands using the system shell, which can interpret special characters and execute multiple commands. An attacker could potentially execute malicious commands with the privileges of the fdupes process.\n    cwe: CWE-78\n    function_names:\n      - deletefiles_ncurses\n    filenames:\n      - ncurses-interface.c\n    classification: very promising\n\n  - headline: Use of uninitialized pointer in log_open function\n    analysis: |\n      In the log_open function in log.c, the info pointer is used to access members like info->file before checking if malloc succeeded. If malloc fails and returns NULL, this will result in a null pointer dereference when trying to access info->file. This could lead to a crash or potentially exploitable memory corruption.\n    cwe: CWE-824\n    function_names:\n      - log_open\n    filenames:\n      - log.c  \n    classification: very promising\n\n  - headline: Buffer overflow in mbstowcs_escape_invalid function\n    analysis: |\n      The mbstowcs_escape_invalid function in mbstowcs_escape_invalid.c does not properly check buffer sizes when copying data. It assumes the destination buffer is large enough to hold the converted string, but does not verify this. This could allow an attacker to cause a buffer overflow by providing a specially crafted input string that is longer than the destination buffer after conversion.\n    cwe: CWE-120\n    function_names:\n      - mbstowcs_escape_invalid\n    filenames:\n      - mbstowcs_escape_invalid.c\n    classification: very promising\n\n  - headline: Insecure use of system() for executing help command\n    analysis: |\n      The deletefiles_ncurses function uses system() to execute the help command defined in HELP_COMMAND_STRING. Using system() is inherently dangerous as it executes commands through a shell, which can interpret special characters. This could allow command injection if HELP_COMMAND_STRING is not properly sanitized. A safer alternative would be to use execve() instead.\n    cwe: CWE-78\n    function_names:\n      - deletefiles_ncurses  \n    filenames:\n      - ncurses-interface.c\n    classification: slightly promising\n\n  - headline: Use of strcpy() and strcat() for string manipulation\n    analysis: |\n      The code uses unsafe string functions like strcpy() and strcat() in multiple places, for example in the escapefilename function in fdupes.c. These functions do not perform bounds checking and can lead to buffer overflows if the destination buffer is not large enough to hold the copied data. Using safer alternatives like strncpy() and strncat() with proper bounds checking would be advisable.\n    cwe: CWE-120\n    function_names:\n      - escapefilename\n    filenames:\n      - fdupes.c\n    classification: slightly promising\n\n  - headline: Potential integer overflow in memory allocation\n    analysis: |\n      In multiple places, the code performs calculations to determine allocation sizes without checking for potential integer overflows. For example, in deletefiles_ncurses, it calculates \"sizeof(wchar_t) * (wcslen(commandbuffer_in)+1)\" without checking if the multiplication could overflow. This could lead to allocating less memory than expected and potentially cause buffer overflows.\n    cwe: CWE-190\n    function_names:\n      - deletefiles_ncurses\n    filenames:\n      - ncurses-interface.c\n    classification: slightly promising\n```",
      "date": "2024-07-07T20:33:08.173991",
      "usage": {
        "prompt_tokens": 65834,
        "completion_tokens": 896,
        "cost": 0.210942
      }
    }
  ],
  "leads": [
    {
      "headline": "Command injection vulnerability in command execution",
      "analysis": "The fdupes program uses system() to execute the help command string defined in HELP_COMMAND_STRING. This allows an attacker to inject arbitrary commands if they can control the HELP_COMMAND_STRING value at compile time. The system() function executes commands using the system shell, which can interpret special characters and execute multiple commands. An attacker could potentially execute malicious commands with the privileges of the fdupes process.\n",
      "classification": "very promising",
      "cwe": "CWE-78",
      "function_names": [
        "deletefiles_ncurses"
      ],
      "filenames": [
        "ncurses-interface.c"
      ]
    },
    {
      "headline": "Use of uninitialized pointer in log_open function",
      "analysis": "In the log_open function in log.c, the info pointer is used to access members like info->file before checking if malloc succeeded. If malloc fails and returns NULL, this will result in a null pointer dereference when trying to access info->file. This could lead to a crash or potentially exploitable memory corruption.\n",
      "classification": "very promising",
      "cwe": "CWE-824",
      "function_names": [
        "log_open"
      ],
      "filenames": [
        "log.c"
      ]
    },
    {
      "headline": "Buffer overflow in mbstowcs_escape_invalid function",
      "analysis": "The mbstowcs_escape_invalid function in mbstowcs_escape_invalid.c does not properly check buffer sizes when copying data. It assumes the destination buffer is large enough to hold the converted string, but does not verify this. This could allow an attacker to cause a buffer overflow by providing a specially crafted input string that is longer than the destination buffer after conversion.\n",
      "classification": "very promising",
      "cwe": "CWE-120",
      "function_names": [
        "mbstowcs_escape_invalid"
      ],
      "filenames": [
        "mbstowcs_escape_invalid.c"
      ]
    },
    {
      "headline": "Insecure use of system() for executing help command",
      "analysis": "The deletefiles_ncurses function uses system() to execute the help command defined in HELP_COMMAND_STRING. Using system() is inherently dangerous as it executes commands through a shell, which can interpret special characters. This could allow command injection if HELP_COMMAND_STRING is not properly sanitized. A safer alternative would be to use execve() instead.\n",
      "classification": "slightly promising",
      "cwe": "CWE-78",
      "function_names": [
        "deletefiles_ncurses"
      ],
      "filenames": [
        "ncurses-interface.c"
      ]
    },
    {
      "headline": "Use of strcpy() and strcat() for string manipulation",
      "analysis": "The code uses unsafe string functions like strcpy() and strcat() in multiple places, for example in the escapefilename function in fdupes.c. These functions do not perform bounds checking and can lead to buffer overflows if the destination buffer is not large enough to hold the copied data. Using safer alternatives like strncpy() and strncat() with proper bounds checking would be advisable.\n",
      "classification": "slightly promising",
      "cwe": "CWE-120",
      "function_names": [
        "escapefilename"
      ],
      "filenames": [
        "fdupes.c"
      ]
    },
    {
      "headline": "Potential integer overflow in memory allocation",
      "analysis": "In multiple places, the code performs calculations to determine allocation sizes without checking for potential integer overflows. For example, in deletefiles_ncurses, it calculates \"sizeof(wchar_t) * (wcslen(commandbuffer_in)+1)\" without checking if the multiplication could overflow. This could lead to allocating less memory than expected and potentially cause buffer overflows.\n",
      "classification": "slightly promising",
      "cwe": "CWE-190",
      "function_names": [
        "deletefiles_ncurses"
      ],
      "filenames": [
        "ncurses-interface.c"
      ]
    }
  ],
  "scores": [
    {
      "stats": {
        "fn": 1,
        "tp": 0,
        "fp": 3
      },
      "mapping": {},
      "vuln_dates": {
        "CVE-2022-48682": "2024-04-26T01:15:45"
      },
      "scoring_model": "claude-3-5-sonnet-20240620",
      "type": "llm",
      "instruction_template_hash": "245ace12b6361954d0a2"
    }
  ],
  "instruction_template_hash": "10c0163db4740318a544",
  "version": "0.1.0"
}
