{
  "commit": "4a5f40eb495df48b726d60b72e11238f78111df5",
  "repo_url": "https://github.com/xsmo/image-uploader-and-browser-for-ckeditor",
  "model": "claude-3-sonnet-20240229",
  "chunk_hashes": [
    "68c03cda509c51165d4a"
  ],
  "responses": [
    {
      "content": "```yaml\nleads:\n  - headline: Cross-Site Request Forgery (CSRF) vulnerability\n    analysis: |\n      The application does not appear to implement any CSRF protection mechanisms. An attacker could potentially construct a malicious request that causes the victim's browser to perform unintended actions on the application, such as deleting images or modifying settings.\n    cwe: CWE-352\n    function_names:\n      - deleteImg\n      - updateImagePath\n      - useHistoryPath\n      - extensionSettings\n    filenames:\n      - function.js\n    classification: very promising\n\n  - headline: Potential Cross-Site Scripting (XSS) vulnerability\n    analysis: |\n      The application appears to directly render user-supplied data in the response without proper sanitization or encoding. For example, the function `showEditBar` constructs HTML elements using unsanitized data from the server response. An attacker could potentially inject malicious scripts into these elements.\n    cwe: CWE-79\n    function_names:\n      - showEditBar\n    filenames:\n      - function.js\n    classification: very promising\n\n  - headline: Potential path traversal vulnerability\n    analysis: |\n      The application allows users to modify the upload path for images. If this path is not properly sanitized, an attacker could potentially traverse the filesystem and access or overwrite arbitrary files on the server.\n    cwe: CWE-22\n    function_names:\n      - updateImagePath\n      - useHistoryPath\n    filenames:\n      - function.js\n    classification: very promising\n\n  - headline: Potential insecure deserialization vulnerability\n    analysis: |\n      The application appears to use cookies to store user preferences and session data. If these cookies are not properly validated or encrypted, an attacker could potentially forge or tamper with the data they contain, leading to potential security issues such as privilege escalation or data tampering.\n    cwe: CWE-502\n    function_names: []\n    filenames: []\n    classification: slightly promising\n\n  - headline: Potential open redirect vulnerability\n    analysis: |\n      The application provides a link to download a new version of the plugin. If the URL for this download is not properly validated, an attacker could potentially redirect users to a malicious site.\n    cwe: CWE-601\n    function_names: []\n    filenames: []\n    classification: slightly promising\n\n  - headline: Potential denial of service vulnerability\n    analysis: |\n      The application allows users to upload files without any apparent restrictions or validation. An attacker could potentially upload a large number of files or extremely large files, potentially causing a denial of service condition on the server.\n    cwe: CWE-770\n    function_names: []\n    filenames: []\n    classification: slightly promising\n\n  - headline: Potential file upload vulnerability\n    analysis: |\n      The application allows users to upload files, but does not appear to validate the file type or content. An attacker could potentially upload malicious scripts or other types of files, leading to potential code execution or other vulnerabilities.\n    cwe: CWE-434\n    function_names: []\n    filenames: []\n    classification: slightly promising\n```",
      "date": "2024-07-08T09:23:35.644938",
      "usage": {
        "prompt_tokens": 6383,
        "completion_tokens": 733,
        "cost": 0.030144
      }
    }
  ],
  "leads": [
    {
      "headline": "Cross-Site Request Forgery (CSRF) vulnerability",
      "analysis": "The application does not appear to implement any CSRF protection mechanisms. An attacker could potentially construct a malicious request that causes the victim's browser to perform unintended actions on the application, such as deleting images or modifying settings.\n",
      "classification": "very promising",
      "cwe": "CWE-352",
      "function_names": [
        "deleteImg",
        "updateImagePath",
        "useHistoryPath"
      ],
      "filenames": [
        "function.js"
      ]
    },
    {
      "headline": "Potential Cross-Site Scripting (XSS) vulnerability",
      "analysis": "The application appears to directly render user-supplied data in the response without proper sanitization or encoding. For example, the function showEditBar constructs HTML elements using unsanitized data from the server response. An attacker could potentially inject malicious scripts into these elements.\n",
      "classification": "very promising",
      "cwe": "CWE-79",
      "function_names": [
        "showEditBar"
      ],
      "filenames": [
        "function.js"
      ]
    },
    {
      "headline": "Potential path traversal vulnerability",
      "analysis": "The application allows users to modify the upload path for images. If this path is not properly sanitized, an attacker could potentially traverse the filesystem and access or overwrite arbitrary files on the server.\n",
      "classification": "very promising",
      "cwe": "CWE-22",
      "function_names": [
        "updateImagePath",
        "useHistoryPath"
      ],
      "filenames": [
        "function.js"
      ]
    },
    {
      "headline": "Potential insecure deserialization vulnerability",
      "analysis": "The application appears to use cookies to store user preferences and session data. If these cookies are not properly validated or encrypted, an attacker could potentially forge or tamper with the data they contain, leading to potential security issues such as privilege escalation or data tampering.\n",
      "classification": "slightly promising",
      "cwe": "CWE-502",
      "function_names": [],
      "filenames": []
    },
    {
      "headline": "Potential open redirect vulnerability",
      "analysis": "The application provides a link to download a new version of the plugin. If the URL for this download is not properly validated, an attacker could potentially redirect users to a malicious site.\n",
      "classification": "slightly promising",
      "cwe": "CWE-601",
      "function_names": [],
      "filenames": []
    },
    {
      "headline": "Potential denial of service vulnerability",
      "analysis": "The application allows users to upload files without any apparent restrictions or validation. An attacker could potentially upload a large number of files or extremely large files, potentially causing a denial of service condition on the server.\n",
      "classification": "slightly promising",
      "cwe": "CWE-770",
      "function_names": [],
      "filenames": []
    },
    {
      "headline": "Potential file upload vulnerability",
      "analysis": "The application allows users to upload files, but does not appear to validate the file type or content. An attacker could potentially upload malicious scripts or other types of files, leading to potential code execution or other vulnerabilities.\n",
      "classification": "slightly promising",
      "cwe": "CWE-434",
      "function_names": [],
      "filenames": []
    }
  ],
  "scores": [
    {
      "stats": {
        "fn": 1,
        "tp": 0,
        "fp": 3
      },
      "mapping": {},
      "vuln_dates": {
        "CVE-2019-19502": "2019-12-02T16:15:12"
      },
      "scoring_model": "claude-3-5-sonnet-20240620",
      "type": "llm",
      "instruction_template_hash": "245ace12b6361954d0a2"
    }
  ],
  "instruction_template_hash": "10c0163db4740318a544",
  "version": "0.1.0"
}
