{
  "commit": "4a5f40eb495df48b726d60b72e11238f78111df5",
  "repo_url": "https://github.com/xsmo/image-uploader-and-browser-for-ckeditor",
  "model": "gpt-4-turbo-2024-04-09",
  "chunk_hashes": [
    "68c03cda509c51165d4a"
  ],
  "responses": [
    {
      "content": "```yaml\nleads:\n  - headline: \"Exposure of sensitive actions without proper confirmation\"\n    analysis: |\n      The 'useImage' function uses URL parameters to steer critical functionality without proper validation checks, allowing attackers to potentially execute unauthorized actions by manipulating URL parameters in malicious query strings. This may lead to a significant risk as users can be tricked into unauthorized actions like changing the editor's content or image uploads, exploiting the naive use of URL parameters.\n    cwe: CWE-807\n    function_names:\n      - useImage\n    filenames:\n      - /plugin.js\n    classification: \"very promising\"\n  \n  - headline: \"Improper user input sanitization leading to XSS vulnerability\"\n    analysis: |\n      The system directly injects user-provided inputs into the web page within functions like `showEditBar` and `showImage`, using unescaped additions to the DOM and dynamic attribute settings. This behavior can be exploited by an attacker to inject malicious scripts that can run in the context of another user's browser session, leading to data theft or unauthorized actions.\n    cwe: CWE-79\n    function_names:\n      - showImage\n      - showEditBar\n    filenames:\n      - /function.js\n    classification: \"very promising\"\n\n  - headline: \"Cross-site request forgery (CSRF) vulnerability due to lack of state validation\"\n    analysis: |\n      The application does not implement any CSRF tokens or equivalent mechanisms for state changes (such as enabling/disabling plugins or settings), leading to potential cross-site request forgery attacks where the attacker could manipulate the victim's settings, impacting overall system integrity.\n    cwe: CWE-352\n    function_names:\n      - pluginSettings\n      - extensionSettings\n    filenames:\n      - /function.js\n    classification: \"very promising\"\n\n  - headline: \"Open redirect vulnerabilities through improper input handling\"\n    analysis: |\n      Security-sensitive actions (such as logging out or navigating to another screen) utilize user input without adequate validation or sanitization. This can be manipulated to redirect users to a malicious website, limiting trust and integrity within the application.\n    cwe: CWE-601\n    function_names:\n      - logOut\n      - enableNews\n    filenames:\n      - /function.js\n    classification: \"slightly promising\"\n\n  - headline: \"Unrestricted file upload leading to arbitrary file execution\"\n    analysis: |\n      The application accepts files of any types and properties without restrictions or security checks, allowing uploading potentially harmful contents which can be executed or processed, thereby leading to system compromise or data leakage.\n    cwe: CWE-434\n    function_names:\n      - drop\n    filenames:\n      - /function.js\n    classification: \"very promising\"\n```",
      "date": "2024-07-08T09:23:44.394068",
      "usage": {
        "prompt_tokens": 4854,
        "completion_tokens": 560,
        "cost": 0.06534
      }
    }
  ],
  "leads": [
    {
      "headline": "Exposure of sensitive actions without proper confirmation",
      "analysis": "The 'useImage' function uses URL parameters to steer critical functionality without proper validation checks, allowing attackers to potentially execute unauthorized actions by manipulating URL parameters in malicious query strings. This may lead to a significant risk as users can be tricked into unauthorized actions like changing the editor's content or image uploads, exploiting the naive use of URL parameters.\n",
      "classification": "very promising",
      "cwe": "CWE-807",
      "function_names": [
        "useImage"
      ],
      "filenames": [
        "/plugin.js"
      ]
    },
    {
      "headline": "Improper user input sanitization leading to XSS vulnerability",
      "analysis": "The system directly injects user-provided inputs into the web page within functions like showEditBar and showImage, using unescaped additions to the DOM and dynamic attribute settings. This behavior can be exploited by an attacker to inject malicious scripts that can run in the context of another user's browser session, leading to data theft or unauthorized actions.\n",
      "classification": "very promising",
      "cwe": "CWE-79",
      "function_names": [
        "showImage",
        "showEditBar"
      ],
      "filenames": [
        "/function.js"
      ]
    },
    {
      "headline": "Cross-site request forgery (CSRF) vulnerability due to lack of state validation",
      "analysis": "The application does not implement any CSRF tokens or equivalent mechanisms for state changes (such as enabling/disabling plugins or settings), leading to potential cross-site request forgery attacks where the attacker could manipulate the victim's settings, impacting overall system integrity.\n",
      "classification": "very promising",
      "cwe": "CWE-352",
      "function_names": [
        "pluginSettings",
        "extensionSettings"
      ],
      "filenames": [
        "/function.js"
      ]
    },
    {
      "headline": "Open redirect vulnerabilities through improper input handling",
      "analysis": "Security-sensitive actions (such as logging out or navigating to another screen) utilize user input without adequate validation or sanitization. This can be manipulated to redirect users to a malicious website, limiting trust and integrity within the application.\n",
      "classification": "slightly promising",
      "cwe": "CWE-601",
      "function_names": [
        "logOut",
        "enableNews"
      ],
      "filenames": [
        "/function.js"
      ]
    },
    {
      "headline": "Unrestricted file upload leading to arbitrary file execution",
      "analysis": "The application accepts files of any types and properties without restrictions or security checks, allowing uploading potentially harmful contents which can be executed or processed, thereby leading to system compromise or data leakage.\n",
      "classification": "very promising",
      "cwe": "CWE-434",
      "function_names": [
        "drop"
      ],
      "filenames": [
        "/function.js"
      ]
    }
  ],
  "scores": [
    {
      "stats": {
        "fn": 1,
        "tp": 0,
        "fp": 4
      },
      "mapping": {},
      "vuln_dates": {
        "CVE-2019-19502": "2019-12-02T16:15:12"
      },
      "scoring_model": "claude-3-5-sonnet-20240620",
      "type": "llm",
      "instruction_template_hash": "245ace12b6361954d0a2"
    }
  ],
  "instruction_template_hash": "10c0163db4740318a544",
  "version": "0.1.0"
}
