{
  "commit": "bb99293a17c12cf116dde66b9729d1a3d79ed551",
  "repo_url": "https://github.com/cdoco/php-jwt",
  "model": "claude-3-sonnet-20240229",
  "chunk_hashes": [
    "eab40c70683f345aadbe"
  ],
  "responses": [
    {
      "content": "```yaml\nleads:\n  - headline: Potential information exposure via error messages\n    analysis: |\n      The jwt_verify_body function in jwt.c constructs error messages containing sensitive information such as expiration times and other claims from the JWT payload. These error messages could potentially reveal sensitive data to unauthorized parties if triggered by an attacker.\n    cwe: CWE-209\n    function_names:\n      - jwt_verify_body\n    filenames:\n      - jwt.c\n    classification: slightly promising\n\n  - headline: Missing input validation in jwt_b64_url_encode_ex function\n    analysis: |\n      The jwt_b64_url_encode_ex function in jwt.c modifies the input string in-place without performing any input validation or bounds checking. This could potentially lead to buffer overflows or other memory corruption vulnerabilities if the input string is crafted in a specific way.\n    cwe: CWE-120\n    function_names:\n      - jwt_b64_url_encode_ex\n    filenames:\n      - jwt.c\n    classification: very promising\n\n  - headline: Potential integer overflow in jwt_verify_sha_hmac function\n    analysis: |\n      The jwt_verify_sha_hmac function in openssl.c uses the output of the HMAC function without validating its length. If an attacker can cause an integer overflow in the length value, it could potentially lead to a buffer overflow or other memory corruption vulnerability.\n    cwe: CWE-190\n    function_names:\n      - jwt_verify_sha_hmac\n    filenames:\n      - openssl.c\n    classification: slightly promising\n\n  - headline: Potential use-after-free vulnerability in jwt_verify_sha_pem function\n    analysis: |\n      The jwt_verify_sha_pem function in openssl.c allocates memory for the signature buffer using efree, but does not properly free this memory in all error cases. This could potentially lead to a use-after-free vulnerability if an attacker can trigger a specific error path.\n    cwe: CWE-416\n    function_names:\n      - jwt_verify_sha_pem\n    filenames:\n      - openssl.c\n    classification: slightly promising\n\n  - headline: Potential null pointer dereference in jwt_hash_str_find_long function\n    analysis: |\n      The jwt_hash_str_find_long function in jwt.c does not properly validate the return value of zend_hash_str_find before dereferencing it. This could potentially lead to a null pointer dereference if the key is not found in the hash table.\n    cwe: CWE-476\n    function_names:\n      - jwt_hash_str_find_long\n    filenames:\n      - jwt.c\n    classification: slightly promising\n\n  - headline: Potential infinite loop in jwt_array_equals function\n    analysis: |\n      The jwt_array_equals function in jwt.c contains a loop that iterates over the elements of an array without proper bounds checking. If the array contains a large number of elements or is malformed, this could potentially lead to an infinite loop or excessive resource consumption.\n    cwe: CWE-835\n    function_names:\n      - jwt_array_equals\n    filenames:\n      - jwt.c\n    classification: slightly promising\n\n  - headline: Potential path traversal vulnerability in jwt_verify_body function\n    analysis: |\n      The jwt_verify_body function in jwt.c decodes a base64-encoded string without properly validating its contents. If an attacker can inject special characters or directory traversal sequences into the encoded string, it could potentially lead to path traversal or other file system vulnerabilities.\n    cwe: CWE-22\n    function_names:\n      - jwt_verify_body\n    filenames:\n      - jwt.c\n    classification: slightly promising\n```",
      "date": "2024-06-09T09:32:41.352972",
      "usage": {
        "prompt_tokens": 16885,
        "completion_tokens": 894,
        "cost": 0.064065
      }
    }
  ],
  "leads": [
    {
      "headline": "Potential information exposure via error messages",
      "analysis": "The jwt_verify_body function in jwt.c constructs error messages containing sensitive information such as expiration times and other claims from the JWT payload. These error messages could potentially reveal sensitive data to unauthorized parties if triggered by an attacker.\n",
      "classification": "slightly promising",
      "cwe": "CWE-209",
      "function_names": [
        "jwt_verify_body"
      ],
      "filenames": [
        "jwt.c"
      ]
    },
    {
      "headline": "Missing input validation in jwt_b64_url_encode_ex function",
      "analysis": "The jwt_b64_url_encode_ex function in jwt.c modifies the input string in-place without performing any input validation or bounds checking. This could potentially lead to buffer overflows or other memory corruption vulnerabilities if the input string is crafted in a specific way.\n",
      "classification": "very promising",
      "cwe": "CWE-120",
      "function_names": [
        "jwt_b64_url_encode_ex"
      ],
      "filenames": [
        "jwt.c"
      ]
    },
    {
      "headline": "Potential integer overflow in jwt_verify_sha_hmac function",
      "analysis": "The jwt_verify_sha_hmac function in openssl.c uses the output of the HMAC function without validating its length. If an attacker can cause an integer overflow in the length value, it could potentially lead to a buffer overflow or other memory corruption vulnerability.\n",
      "classification": "slightly promising",
      "cwe": "CWE-190",
      "function_names": [
        "jwt_verify_sha_hmac"
      ],
      "filenames": [
        "openssl.c"
      ]
    },
    {
      "headline": "Potential use-after-free vulnerability in jwt_verify_sha_pem function",
      "analysis": "The jwt_verify_sha_pem function in openssl.c allocates memory for the signature buffer using efree, but does not properly free this memory in all error cases. This could potentially lead to a use-after-free vulnerability if an attacker can trigger a specific error path.\n",
      "classification": "slightly promising",
      "cwe": "CWE-416",
      "function_names": [
        "jwt_verify_sha_pem"
      ],
      "filenames": [
        "openssl.c"
      ]
    },
    {
      "headline": "Potential null pointer dereference in jwt_hash_str_find_long function",
      "analysis": "The jwt_hash_str_find_long function in jwt.c does not properly validate the return value of zend_hash_str_find before dereferencing it. This could potentially lead to a null pointer dereference if the key is not found in the hash table.\n",
      "classification": "slightly promising",
      "cwe": "CWE-476",
      "function_names": [
        "jwt_hash_str_find_long"
      ],
      "filenames": [
        "jwt.c"
      ]
    },
    {
      "headline": "Potential infinite loop in jwt_array_equals function",
      "analysis": "The jwt_array_equals function in jwt.c contains a loop that iterates over the elements of an array without proper bounds checking. If the array contains a large number of elements or is malformed, this could potentially lead to an infinite loop or excessive resource consumption.\n",
      "classification": "slightly promising",
      "cwe": "CWE-835",
      "function_names": [
        "jwt_array_equals"
      ],
      "filenames": [
        "jwt.c"
      ]
    },
    {
      "headline": "Potential path traversal vulnerability in jwt_verify_body function",
      "analysis": "The jwt_verify_body function in jwt.c decodes a base64-encoded string without properly validating its contents. If an attacker can inject special characters or directory traversal sequences into the encoded string, it could potentially lead to path traversal or other file system vulnerabilities.\n",
      "classification": "slightly promising",
      "cwe": "CWE-22",
      "function_names": [
        "jwt_verify_body"
      ],
      "filenames": [
        "jwt.c"
      ]
    }
  ],
  "scores": [
    {
      "stats": {
        "fn": 1,
        "tp": 0,
        "fp": 1
      },
      "mapping": {},
      "vuln_dates": {
        "CVE-2024-25191": "2024-02-08T17:15:11"
      },
      "scoring_model": "gpt-4o-2024-05-13",
      "type": "llm",
      "instruction_template_hash": "8998f09cf57fca8a6e03"
    },
    {
      "stats": {
        "fn": 1,
        "tp": 0,
        "fp": 1
      },
      "mapping": {},
      "vuln_dates": {
        "CVE-2024-25191": "2024-02-08T17:15:11"
      },
      "scoring_model": "claude-3-opus-20240229",
      "type": "llm",
      "instruction_template_hash": "245ace12b6361954d0a2"
    }
  ],
  "instruction_template_hash": "10c0163db4740318a544",
  "version": "0.1.0"
}
