{
  "commit": "2d96bb7259731a19a0de45abf8a2582ddd28cc10",
  "repo_url": "https://github.com/freepbx/contactmanager",
  "model": "gpt-4o-2024-05-13",
  "chunk_hashes": [
    "033a3f34edf3f44c79f8"
  ],
  "responses": [
    {
      "content": "```yaml\nleads:\n  - headline: \"Improperly Validated User Inputs in groupClick Function\"\n    analysis: |\n      The groupClick function constructs an AJAX URL parameter using user-controlled input from 'group' without validating or encoding it. This can lead to SQL Injection if the backend script directly uses these inputs in SQL queries. The vulnerability lies in the direct concatenation of user input into the URL.\n    cwe: CWE-79\n    function_names:\n      - groupClick\n    filenames:\n      - ucp/assets/js/global.js\n    classification: very promising\n  \n  - headline: \"Use of Unchecked Return Values from jQuery Operations\"\n    analysis: |\n      The code does not check the return values of jQuery operations such as those in the displayEditContact function. This can lead to issues as the code presumes that the elements exist and are correctly manipulated. Skipping error handling might make it difficult to detect or handle errors.\n    cwe: CWE-754\n    function_names:\n      - displayEditContact\n      - addNumber\n    filenames:\n      - ucp/assets/js/global.js\n      - assets/js/contactmanager.js\n    classification: slightly promising\n  \n  - headline: \"Full Client-Side Validation Relied\"\n    analysis: |\n      Functions like addNumber, addXMPP, addEmail, and addWebsite rely on client-side JavaScript validation without additional server-side checks. This can be bypassed by an attacker, leading to injections and other attacks.\n    cwe: CWE-20\n    function_names:\n      - addNumber\n      - addXMPP\n      - addEmail\n      - addWebsite\n    filenames:\n      - ucp/assets/js/global.js\n      - assets/js/contactmanager.js\n    classification: very promising\n  \n  - headline: \"Failure to Sanitize File Uploads\"\n    analysis: |\n      The file upload functions in both global.js and contactmanager.js are vulnerable as they don't sanitize filenames properly, allowing potential malicious characters, including unsafe file types that might lead to code execution or malicious file uploads.\n    cwe: CWE-434\n    function_names:\n      - '#imageupload.fileupload.add'\n    filenames:\n      - ucp/assets/js/global.js\n      - assets/js/contactmanager.js\n    classification: very promising\n  \n  - headline: \"Hardcoded Language and Locale Values\"\n    analysis: |\n      Hardcoded language and locale values like cmlocale are used directly within the scripts. This may lead to a lack of flexibility and potential issues when running in different environments or locales.\n    cwe: CWE-1188\n    function_names:\n      - N/A\n    filenames:\n      - ucp/assets/js/global.js\n      - assets/js/contactmanager.js\n    classification: not promising\n```",
      "date": "2024-06-12T16:39:29.063171",
      "usage": {
        "prompt_tokens": 17968,
        "completion_tokens": 569,
        "cost": 0.098375
      }
    }
  ],
  "leads": [
    {
      "headline": "Improperly Validated User Inputs in groupClick Function",
      "analysis": "The groupClick function constructs an AJAX URL parameter using user-controlled input from 'group' without validating or encoding it. This can lead to SQL Injection if the backend script directly uses these inputs in SQL queries. The vulnerability lies in the direct concatenation of user input into the URL.\n",
      "classification": "very promising",
      "cwe": "CWE-79",
      "function_names": [
        "groupClick"
      ],
      "filenames": [
        "ucp/assets/js/global.js"
      ]
    },
    {
      "headline": "Use of Unchecked Return Values from jQuery Operations",
      "analysis": "The code does not check the return values of jQuery operations such as those in the displayEditContact function. This can lead to issues as the code presumes that the elements exist and are correctly manipulated. Skipping error handling might make it difficult to detect or handle errors.\n",
      "classification": "slightly promising",
      "cwe": "CWE-754",
      "function_names": [
        "displayEditContact",
        "addNumber"
      ],
      "filenames": [
        "ucp/assets/js/global.js",
        "assets/js/contactmanager.js"
      ]
    },
    {
      "headline": "Full Client-Side Validation Relied",
      "analysis": "Functions like addNumber, addXMPP, addEmail, and addWebsite rely on client-side JavaScript validation without additional server-side checks. This can be bypassed by an attacker, leading to injections and other attacks.\n",
      "classification": "very promising",
      "cwe": "CWE-20",
      "function_names": [
        "addNumber",
        "addXMPP",
        "addEmail"
      ],
      "filenames": [
        "ucp/assets/js/global.js",
        "assets/js/contactmanager.js"
      ]
    },
    {
      "headline": "Failure to Sanitize File Uploads",
      "analysis": "The file upload functions in both global.js and contactmanager.js are vulnerable as they don't sanitize filenames properly, allowing potential malicious characters, including unsafe file types that might lead to code execution or malicious file uploads.\n",
      "classification": "very promising",
      "cwe": "CWE-434",
      "function_names": [
        "#imageupload.fileupload.add"
      ],
      "filenames": [
        "ucp/assets/js/global.js",
        "assets/js/contactmanager.js"
      ]
    },
    {
      "headline": "Hardcoded Language and Locale Values",
      "analysis": "Hardcoded language and locale values like cmlocale are used directly within the scripts. This may lead to a lack of flexibility and potential issues when running in different environments or locales.\n",
      "classification": "not promising",
      "cwe": "CWE-1188",
      "function_names": [
        "N/A"
      ],
      "filenames": [
        "ucp/assets/js/global.js",
        "assets/js/contactmanager.js"
      ]
    }
  ],
  "scores": [
    {
      "stats": {
        "fn": 1,
        "tp": 0,
        "fp": 3
      },
      "mapping": {},
      "vuln_dates": {
        "CVE-2019-16966": "2019-10-21T19:15:11"
      },
      "scoring_model": "claude-3-opus-20240229",
      "type": "llm",
      "instruction_template_hash": "245ace12b6361954d0a2"
    },
    {
      "stats": {
        "fn": 1,
        "tp": 0,
        "fp": 3
      },
      "mapping": {},
      "vuln_dates": {
        "CVE-2019-16966": "2019-10-21T19:15:11"
      },
      "scoring_model": "claude-3-5-sonnet-20240620",
      "type": "llm",
      "instruction_template_hash": "245ace12b6361954d0a2"
    }
  ],
  "instruction_template_hash": "10c0163db4740318a544",
  "version": "0.1.0"
}
