{
  "commit": "da953f20cca0f7b03fa56eaa65aba8d9a45afbe9",
  "repo_url": "https://github.com/saleor/auth-sdk",
  "model": "claude-3-haiku-20240307",
  "chunk_hashes": [
    "37d05c897b4b2ccfb168"
  ],
  "responses": [
    {
      "content": "```yaml\nleads:\n  - headline: Improper Validation of Specified Quantity in Input\n    analysis: |\n      The code does not validate the input data, which could lead to security vulnerabilities such as Improper Input Validation (CWE-1284) and Buffer Overflow (CWE-120). Attackers could potentially craft malicious inputs to exploit these vulnerabilities and execute arbitrary code or cause other types of security breaches.\n    cwe: CWE-1284\n    function_names:\n      - decodeToken\n      - getTokenExpiry\n    filenames:\n      - src/utils.ts\n    classification: very promising\n\n  - headline: Improper Neutralization of Input During Web Page Generation ('Cross-site Scripting')\n    analysis: |\n      The code does not properly sanitize or validate the input data, which could lead to Cross-site Scripting (XSS) vulnerabilities (CWE-79). Attackers could potentially inject malicious scripts into the application, which could be executed by the user's browser and lead to the theft of sensitive information or other types of security breaches.\n    cwe: CWE-79\n    function_names:\n      - getRequestData\n    filenames:\n      - src/utils.ts\n    classification: very promising\n\n  - headline: Insufficient Entropy\n    analysis: |\n      The code does not use a sufficiently random value when generating tokens, which could lead to Insufficient Entropy vulnerabilities (CWE-331). Attackers could potentially guess or brute-force the token values and gain unauthorized access to the application.\n    cwe: CWE-331\n    function_names:\n      - getTokenExpiry\n    filenames:\n      - src/utils.ts\n    classification: slightly promising\n\n  - headline: Improper Restriction of Excessive Authentication Attempts\n    analysis: |\n      The code does not implement any mechanism to limit the number of authentication attempts, which could lead to Improper Restriction of Excessive Authentication Attempts vulnerabilities (CWE-307). Attackers could potentially perform brute-force attacks to guess user credentials and gain unauthorized access to the application.\n    cwe: CWE-307\n    function_names: []\n    filenames: []\n    classification: slightly promising\n\n  - headline: Cleartext Storage of Sensitive Information\n    analysis: |\n      The code stores sensitive information, such as tokens and refresh tokens, in plain text, which could lead to Cleartext Storage of Sensitive Information vulnerabilities (CWE-312). Attackers could potentially gain access to this sensitive information and use it to compromise the application or the user's account.\n    cwe: CWE-312\n    function_names:\n      - setRefreshToken\n      - getRefreshToken\n    filenames:\n      - src/SaleorRefreshTokenStorageHandler.ts\n    classification: very promising\n\n  - headline: Cleartext Transmission of Sensitive Information\n    analysis: |\n      The code transmits sensitive information, such as tokens and refresh tokens, without encryption, which could lead to Cleartext Transmission of Sensitive Information vulnerabilities (CWE-319). Attackers could potentially intercept this information during transit and use it to compromise the application or the user's account.\n    cwe: CWE-319\n    function_names:\n      - runAuthorizedRequest\n      - handleRequestWithTokenRefresh\n    filenames:\n      - src/SaleorAuthClient.ts\n    classification: very promising\n\n  - headline: Improper Verification of Cryptographic Signature\n    analysis: |\n      The code does not properly verify the cryptographic signature of the tokens it receives, which could lead to Improper Verification of Cryptographic Signature vulnerabilities (CWE-347). Attackers could potentially create forged tokens and use them to gain unauthorized access to the application.\n    cwe: CWE-347\n    function_names:\n      - decodeToken\n    filenames:\n      - src/utils.ts\n    classification: very promising\n```",
      "date": "2024-06-09T14:42:36.294560",
      "usage": {
        "prompt_tokens": 15453,
        "completion_tokens": 929,
        "cost": 0.0050245
      }
    }
  ],
  "leads": [
    {
      "headline": "Improper Validation of Specified Quantity in Input",
      "analysis": "The code does not validate the input data, which could lead to security vulnerabilities such as Improper Input Validation (CWE-1284) and Buffer Overflow (CWE-120). Attackers could potentially craft malicious inputs to exploit these vulnerabilities and execute arbitrary code or cause other types of security breaches.\n",
      "classification": "very promising",
      "cwe": "CWE-1284",
      "function_names": [
        "decodeToken",
        "getTokenExpiry"
      ],
      "filenames": [
        "src/utils.ts"
      ]
    },
    {
      "headline": "Improper Neutralization of Input During Web Page Generation ('Cross-site Scripting')",
      "analysis": "The code does not properly sanitize or validate the input data, which could lead to Cross-site Scripting (XSS) vulnerabilities (CWE-79). Attackers could potentially inject malicious scripts into the application, which could be executed by the user's browser and lead to the theft of sensitive information or other types of security breaches.\n",
      "classification": "very promising",
      "cwe": "CWE-79",
      "function_names": [
        "getRequestData"
      ],
      "filenames": [
        "src/utils.ts"
      ]
    },
    {
      "headline": "Insufficient Entropy",
      "analysis": "The code does not use a sufficiently random value when generating tokens, which could lead to Insufficient Entropy vulnerabilities (CWE-331). Attackers could potentially guess or brute-force the token values and gain unauthorized access to the application.\n",
      "classification": "slightly promising",
      "cwe": "CWE-331",
      "function_names": [
        "getTokenExpiry"
      ],
      "filenames": [
        "src/utils.ts"
      ]
    },
    {
      "headline": "Improper Restriction of Excessive Authentication Attempts",
      "analysis": "The code does not implement any mechanism to limit the number of authentication attempts, which could lead to Improper Restriction of Excessive Authentication Attempts vulnerabilities (CWE-307). Attackers could potentially perform brute-force attacks to guess user credentials and gain unauthorized access to the application.\n",
      "classification": "slightly promising",
      "cwe": "CWE-307",
      "function_names": [],
      "filenames": []
    },
    {
      "headline": "Cleartext Storage of Sensitive Information",
      "analysis": "The code stores sensitive information, such as tokens and refresh tokens, in plain text, which could lead to Cleartext Storage of Sensitive Information vulnerabilities (CWE-312). Attackers could potentially gain access to this sensitive information and use it to compromise the application or the user's account.\n",
      "classification": "very promising",
      "cwe": "CWE-312",
      "function_names": [
        "setRefreshToken",
        "getRefreshToken"
      ],
      "filenames": [
        "src/SaleorRefreshTokenStorageHandler.ts"
      ]
    },
    {
      "headline": "Cleartext Transmission of Sensitive Information",
      "analysis": "The code transmits sensitive information, such as tokens and refresh tokens, without encryption, which could lead to Cleartext Transmission of Sensitive Information vulnerabilities (CWE-319). Attackers could potentially intercept this information during transit and use it to compromise the application or the user's account.\n",
      "classification": "very promising",
      "cwe": "CWE-319",
      "function_names": [
        "runAuthorizedRequest",
        "handleRequestWithTokenRefresh"
      ],
      "filenames": [
        "src/SaleorAuthClient.ts"
      ]
    },
    {
      "headline": "Improper Verification of Cryptographic Signature",
      "analysis": "The code does not properly verify the cryptographic signature of the tokens it receives, which could lead to Improper Verification of Cryptographic Signature vulnerabilities (CWE-347). Attackers could potentially create forged tokens and use them to gain unauthorized access to the application.\n",
      "classification": "very promising",
      "cwe": "CWE-347",
      "function_names": [
        "decodeToken"
      ],
      "filenames": [
        "src/utils.ts"
      ]
    }
  ],
  "scores": [
    {
      "stats": {
        "fn": 1,
        "tp": 0,
        "fp": 5
      },
      "mapping": {},
      "vuln_dates": {
        "CVE-2024-29036": "2024-03-20T21:15:31"
      },
      "scoring_model": "gpt-4o-2024-05-13",
      "type": "llm",
      "instruction_template_hash": "8998f09cf57fca8a6e03"
    }
  ],
  "instruction_template_hash": "10c0163db4740318a544",
  "version": "0.1.0"
}
