{
  "commit": "ca25f6388005288aae7ed4978f37e7f1b02fc5e1",
  "repo_url": "https://github.com/ubertidavide/fastbots",
  "model": "gpt-4-turbo-2024-04-09",
  "chunk_hashes": [
    "fbf7a2b5b5e2583d9963"
  ],
  "responses": [
    {
      "content": "```yaml\nleads:\n  - headline: Configuration Injection via Unverified URL\n    analysis: |\n      The application relies on a configuration file to specify URLs for navigation but does not verify or sanitize these URLs before usage. This can potentially allow an attacker to alter the configuration, pointing URLs to malicious sites which could lead to phishing attacks, spreading malware or other exploits targeting the end users. If configuration files can be manipulated or if user input can influence URL settings without stringent checks, it poses a significant security risk.\n    cwe: CWE-74\n    function_names:\n      - check_page_url\n    filenames:\n      - fastbots/page.py\n    classification: very promising\n  \n  - headline: Exposure of Sensitive Information via Logging\n    analysis: |\n      The application logs potentially sensitive information without sufficient controls over the log's access and storage. Logging detailed error messages or sensitive information without ensuring the logs are stored securely, access controlled, and properly sanitized can expose sensitive information to unauthorized actors or lead to other malicious activities if an attacker gains access to these logs.\n    cwe: CWE-532\n    function_names:\n      - on_failure\n    filenames:\n      - fastbots/task.py\n    classification: slightly promising\n\n  - headline: Insecure Temporary File Usage\n    analysis: |\n      The application uses temporary directories to store downloaded files and handles configurations for screenshots and HTML content that might contain sensitive information, without adequate controls to secure the contents. Temporary files can be exposed to other local users, especially on shared systems, and can lead to unauthorized access to sensitive data if the filesystem permissions are not appropriately restrictive.\n    cwe: CWE-379\n    function_names:\n      - __init__\n      - save_screenshot\n      - save_html\n    filenames:\n      - fastbots/bot.py\n    classification: slightly promising\n\n  - headline: Insufficient Error Handling Resulting in Potential DoS\n    analysis: |\n      The application encapsulates retry logic in __call__ without adequately recognizing different types of exceptions; for instance, connection issues versus application errors. This broad retry strategy without backoff mechanisms or limits on the nature of errors that trigger retries can lead to resource exhaustion and denial of service, particularly if the error is related to resource constraints or external system problems.\n    cwe: CWE-730\n    function_names:\n      - __call__\n    filenames:\n      - fastbots/task.py\n    classification: slightly promising\n\n  - headline: Misuse of Cookie Storage\n    analysis: |\n      Cookies are stored and loaded from local storage without ensuring integrity or confidentiality of the cookie data, exposing them to various risks such as alteration and eavesdropping if not transmitted over secure channels or accessed by unauthorized applications. The security of cookie management is vital to prevent unauthorized access to session tokens and other sensitive information stored in cookies.\n    cwe: CWE-311\n    function_names:\n      - save_cookies\n      - load_cookies\n    filenames:\n      - fastbots/bot.py\n    classification: slightly promising\n```",
      "date": "2024-06-09T15:16:57.543827",
      "usage": {
        "prompt_tokens": 8895,
        "completion_tokens": 612,
        "cost": 0.10731
      }
    }
  ],
  "leads": [
    {
      "headline": "Configuration Injection via Unverified URL",
      "analysis": "The application relies on a configuration file to specify URLs for navigation but does not verify or sanitize these URLs before usage. This can potentially allow an attacker to alter the configuration, pointing URLs to malicious sites which could lead to phishing attacks, spreading malware or other exploits targeting the end users. If configuration files can be manipulated or if user input can influence URL settings without stringent checks, it poses a significant security risk.\n",
      "classification": "very promising",
      "cwe": "CWE-74",
      "function_names": [
        "check_page_url"
      ],
      "filenames": [
        "fastbots/page.py"
      ]
    },
    {
      "headline": "Exposure of Sensitive Information via Logging",
      "analysis": "The application logs potentially sensitive information without sufficient controls over the log's access and storage. Logging detailed error messages or sensitive information without ensuring the logs are stored securely, access controlled, and properly sanitized can expose sensitive information to unauthorized actors or lead to other malicious activities if an attacker gains access to these logs.\n",
      "classification": "slightly promising",
      "cwe": "CWE-532",
      "function_names": [
        "on_failure"
      ],
      "filenames": [
        "fastbots/task.py"
      ]
    },
    {
      "headline": "Insecure Temporary File Usage",
      "analysis": "The application uses temporary directories to store downloaded files and handles configurations for screenshots and HTML content that might contain sensitive information, without adequate controls to secure the contents. Temporary files can be exposed to other local users, especially on shared systems, and can lead to unauthorized access to sensitive data if the filesystem permissions are not appropriately restrictive.\n",
      "classification": "slightly promising",
      "cwe": "CWE-379",
      "function_names": [
        "__init__",
        "save_screenshot",
        "save_html"
      ],
      "filenames": [
        "fastbots/bot.py"
      ]
    },
    {
      "headline": "Insufficient Error Handling Resulting in Potential DoS",
      "analysis": "The application encapsulates retry logic in __call__ without adequately recognizing different types of exceptions; for instance, connection issues versus application errors. This broad retry strategy without backoff mechanisms or limits on the nature of errors that trigger retries can lead to resource exhaustion and denial of service, particularly if the error is related to resource constraints or external system problems.\n",
      "classification": "slightly promising",
      "cwe": "CWE-730",
      "function_names": [
        "__call__"
      ],
      "filenames": [
        "fastbots/task.py"
      ]
    },
    {
      "headline": "Misuse of Cookie Storage",
      "analysis": "Cookies are stored and loaded from local storage without ensuring integrity or confidentiality of the cookie data, exposing them to various risks such as alteration and eavesdropping if not transmitted over secure channels or accessed by unauthorized applications. The security of cookie management is vital to prevent unauthorized access to session tokens and other sensitive information stored in cookies.\n",
      "classification": "slightly promising",
      "cwe": "CWE-311",
      "function_names": [
        "save_cookies",
        "load_cookies"
      ],
      "filenames": [
        "fastbots/bot.py"
      ]
    }
  ],
  "scores": [
    {
      "stats": {
        "fn": 1,
        "tp": 0,
        "fp": 1
      },
      "mapping": {},
      "vuln_dates": {
        "CVE-2023-48699": "2023-11-21T23:15:08"
      },
      "scoring_model": "gpt-4o-2024-05-13",
      "type": "llm",
      "instruction_template_hash": "8998f09cf57fca8a6e03"
    }
  ],
  "instruction_template_hash": "10c0163db4740318a544",
  "version": "0.1.0"
}
