{
  "commit": "3a0699d2a90544a0f8928c40947b119e9491c2fa",
  "repo_url": "https://github.com/senchalabs/connect",
  "model": "claude-3-sonnet-20240229",
  "chunk_hashes": [
    "1fe5273731f7746154fc"
  ],
  "responses": [
    {
      "content": "According to the code, here are the potential security vulnerabilities identified, in the YAML format requested:\n\n```yaml\nleads:\n  - headline: Potential Cross-Site Scripting (XSS) vulnerability\n    analysis: |\n      The code in `docs/jquery.js` does not properly escape user input before rendering it on the page. This could allow an attacker to inject malicious scripts into the application, leading to Cross-Site Scripting (XSS) attacks.\n    cwe: CWE-79\n    function_names:\n      - highlight\n    filenames:\n      - docs/jquery.js\n    classification: very promising\n\n  - headline: Potential Arbitrary File Write vulnerability\n    analysis: |\n      The `upload` function in `examples/upload.js` does not properly validate the file path or name before writing the uploaded file to the file system. This could potentially allow an attacker to write files to arbitrary locations on the server, leading to various attacks such as path traversal or code execution.\n    cwe: CWE-22\n    function_names:\n      - upload\n    filenames:\n      - examples/upload.js\n    classification: very promising\n\n  - headline: Potential Insecure Handling of Temporary Files\n    analysis: |\n      The `multipart` middleware in `lib/middleware/multipart.js` uses temporary files to store uploaded files, but does not automatically clean up these files. This could lead to disk space exhaustion or disclosure of sensitive information if the temporary files are not properly managed.\n    cwe: CWE-404\n    function_names:\n      - multipart\n    filenames:\n      - lib/middleware/multipart.js\n    classification: slightly promising\n\n  - headline: Potential Insecure Use of Cryptography\n    analysis: |\n      The `utils.sign` and `utils.unsign` functions in `lib/utils.js` use a custom implementation of cryptographic signing and verification, which may not follow best practices or be secure against various attacks. It is generally recommended to use well-established and peer-reviewed cryptographic libraries instead of custom implementations.\n    cwe: CWE-327\n    function_names:\n      - sign\n      - unsign\n    filenames:\n      - lib/utils.js\n    classification: slightly promising\n\n  - headline: Potential Insecure Generation of Pseudorandom Values\n    analysis: |\n      The `generateSalt` function in `lib/middleware/csrf.js` uses `Math.random()` to generate a pseudorandom salt, which may not be sufficiently random or secure for cryptographic purposes. It is generally recommended to use a cryptographically secure pseudorandom number generator (CSPRNG) for generating values used in security contexts.\n    cwe: CWE-338\n    function_names:\n      - generateSalt\n    filenames:\n      - lib/middleware/csrf.js\n    classification: slightly promising\n```\n\nPlease note that this analysis is based solely on the provided code and may not cover all potential vulnerabilities or security concerns. It is always recommended to perform thorough security testing and review before deploying an application to a production environment.",
      "date": "2024-06-14T15:31:10.472627",
      "usage": {
        "prompt_tokens": 125120,
        "completion_tokens": 718,
        "cost": 0.38613
      }
    }
  ],
  "leads": [
    {
      "headline": "Potential Cross-Site Scripting (XSS) vulnerability",
      "analysis": "The code in docs/jquery.js does not properly escape user input before rendering it on the page. This could allow an attacker to inject malicious scripts into the application, leading to Cross-Site Scripting (XSS) attacks.\n",
      "classification": "very promising",
      "cwe": "CWE-79",
      "function_names": [
        "highlight"
      ],
      "filenames": [
        "docs/jquery.js"
      ]
    },
    {
      "headline": "Potential Arbitrary File Write vulnerability",
      "analysis": "The upload function in examples/upload.js does not properly validate the file path or name before writing the uploaded file to the file system. This could potentially allow an attacker to write files to arbitrary locations on the server, leading to various attacks such as path traversal or code execution.\n",
      "classification": "very promising",
      "cwe": "CWE-22",
      "function_names": [
        "upload"
      ],
      "filenames": [
        "examples/upload.js"
      ]
    },
    {
      "headline": "Potential Insecure Handling of Temporary Files",
      "analysis": "The multipart middleware in lib/middleware/multipart.js uses temporary files to store uploaded files, but does not automatically clean up these files. This could lead to disk space exhaustion or disclosure of sensitive information if the temporary files are not properly managed.\n",
      "classification": "slightly promising",
      "cwe": "CWE-404",
      "function_names": [
        "multipart"
      ],
      "filenames": [
        "lib/middleware/multipart.js"
      ]
    },
    {
      "headline": "Potential Insecure Use of Cryptography",
      "analysis": "The utils.sign and utils.unsign functions in lib/utils.js use a custom implementation of cryptographic signing and verification, which may not follow best practices or be secure against various attacks. It is generally recommended to use well-established and peer-reviewed cryptographic libraries instead of custom implementations.\n",
      "classification": "slightly promising",
      "cwe": "CWE-327",
      "function_names": [
        "sign",
        "unsign"
      ],
      "filenames": [
        "lib/utils.js"
      ]
    },
    {
      "headline": "Potential Insecure Generation of Pseudorandom Values",
      "analysis": "The generateSalt function in lib/middleware/csrf.js uses Math.random() to generate a pseudorandom salt, which may not be sufficiently random or secure for cryptographic purposes. It is generally recommended to use a cryptographically secure pseudorandom number generator (CSPRNG) for generating values used in security contexts.\n",
      "classification": "slightly promising",
      "cwe": "CWE-338",
      "function_names": [
        "generateSalt"
      ],
      "filenames": [
        "lib/middleware/csrf.js"
      ]
    }
  ],
  "scores": [
    {
      "stats": {
        "fn": 1,
        "tp": 0,
        "fp": 2
      },
      "mapping": {},
      "vuln_dates": {
        "CVE-2018-3717": "2018-06-07T02:29:08"
      },
      "scoring_model": "claude-3-opus-20240229",
      "type": "llm",
      "instruction_template_hash": "245ace12b6361954d0a2"
    }
  ],
  "instruction_template_hash": "10c0163db4740318a544",
  "version": "0.1.0"
}
