{
  "commit": "4739d208c03ce5e03147e1b4eed08dda81a29a85",
  "repo_url": "https://github.com/swisspol/gcdwebserver",
  "model": "claude-3-sonnet-20240229",
  "chunk_hashes": [
    "9d55ea890a2de32b4318"
  ],
  "responses": [
    {
      "content": "```yaml\nleads:\n  - headline: Potential directory traversal vulnerability\n    analysis: |\n      The function `GCDWebServerNormalizePath` in `GCDWebServerFunctions.h` is used to remove \"//\", \"/./\" and \"/../\" components from paths as well as any trailing slash. However, it does not appear to properly handle paths starting with \"../\" or symbolic links. An attacker could potentially craft a malicious path to access files outside the intended directory.\n    cwe: CWE-706\n    function_names:\n      - GCDWebServerNormalizePath\n    filenames:\n      - GCDWebServer/Core/GCDWebServerFunctions.h\n    classification: very promising\n\n  - headline: Potential path traversal vulnerability in file handling\n    analysis: |\n      The methods that handle file uploads and file operations in `GCDWebUploader` and `GCDWebDAVServer` appear to rely on the `GCDWebServerNormalizePath` function to sanitize paths. If the normalization function is vulnerable to directory traversal, an attacker could potentially access or modify files outside the intended upload directory. \n    cwe: CWE-22\n    function_names:\n      - initWithUploadDirectory\n      - shouldUploadFileAtPath\n      - shouldMoveItemFromPath\n      - shouldCopyItemFromPath\n      - shouldDeleteItemAtPath\n      - shouldCreateDirectoryAtPath\n    filenames:\n      - GCDWebUploader/GCDWebUploader.h\n      - GCDWebDAVServer/GCDWebDAVServer.h\n    classification: very promising\n    \n  - headline: Potential command injection in shell script\n    analysis: |\n      The `Run-Tests.sh` script appears to be running shell commands using eval and passing user input (file paths) without proper sanitization. An attacker could potentially inject malicious shell commands by crafting a file path containing shell metacharacters.\n    cwe: CWE-78\n    function_names: []\n    filenames:\n      - Run-Tests.sh\n    classification: very promising\n\n  - headline: Use of hard-coded credentials in format-source script\n    analysis: |\n      The `format-source.sh` script appears to be downloading the SwiftFormat binary from a hard-coded URL without any integrity checks. An attacker who can compromise the server hosting this binary could potentially inject malicious code into the project.\n    cwe: CWE-798\n    function_names: []\n    filenames:\n      - format-source.sh \n    classification: slightly promising\n\n  - headline: Potential open redirect vulnerability\n    analysis: |\n      The `GCDWebServerConnection` class contains a method `rewriteRequestURL` which could potentially be used to rewrite the request URL to an arbitrary location, leading to an open redirect vulnerability if not properly validated.\n    cwe: CWE-601\n    function_names:\n      - rewriteRequestURL\n    filenames:\n      - GCDWebServer/Core/GCDWebServerConnection.h\n    classification: slightly promising\n```\n\nThe major security issues identified in the codebase are:\n\n1. **Potential directory traversal vulnerability**: The `GCDWebServerNormalizePath` function used to sanitize paths does not appear to properly handle paths starting with \"../\" or symbolic links, potentially allowing an attacker to access files outside the intended directory.\n\n2. **Potential path traversal vulnerability in file handling**: The file handling methods in `GCDWebUploader` and `GCDWebDAVServer` rely on the potentially vulnerable `GCDWebServerNormalizePath` function, which could lead to path traversal vulnerabilities if an attacker can craft malicious paths.\n\n3. **Potential command injection in shell script**: The `Run-Tests.sh` script appears to be running shell commands using eval and passing user input (file paths) without proper sanitization, potentially allowing an attacker to inject malicious shell commands.\n\n4. **Use of hard-coded credentials in format-source script**: The `format-source.sh` script downloads a binary from a hard-coded URL without any integrity checks, which could potentially lead to code injection if the server hosting the binary is compromised.\n\n5. **Potential open redirect vulnerability**: The `rewriteRequestURL` method in the `GCDWebServerConnection` class could potentially be used to rewrite the request URL to an arbitrary location, leading to an open redirect vulnerability if not properly validated.\n\nThe analysis also identifies some less severe issues, such as the lack of proper sanitization for header values and the potential for symbolic link attacks when handling file paths.\n\nOverall, the codebase appears to have several potential security vulnerabilities related to path traversal, command injection, and insecure coding practices. These issues should be addressed to ensure the security and integrity of the application.",
      "date": "2024-07-08T08:50:03.966128",
      "usage": {
        "prompt_tokens": 69289,
        "completion_tokens": 1114,
        "cost": 0.224577
      }
    }
  ],
  "leads": [
    {
      "headline": "Potential directory traversal vulnerability",
      "analysis": "The function GCDWebServerNormalizePath in GCDWebServerFunctions.h is used to remove \"//\", \"/./\" and \"/../\" components from paths as well as any trailing slash. However, it does not appear to properly handle paths starting with \"../\" or symbolic links. An attacker could potentially craft a malicious path to access files outside the intended directory.\n",
      "classification": "very promising",
      "cwe": "CWE-706",
      "function_names": [
        "GCDWebServerNormalizePath"
      ],
      "filenames": [
        "GCDWebServer/Core/GCDWebServerFunctions.h"
      ]
    },
    {
      "headline": "Potential path traversal vulnerability in file handling",
      "analysis": "The methods that handle file uploads and file operations in GCDWebUploader and GCDWebDAVServer appear to rely on the GCDWebServerNormalizePath function to sanitize paths. If the normalization function is vulnerable to directory traversal, an attacker could potentially access or modify files outside the intended upload directory. \n",
      "classification": "very promising",
      "cwe": "CWE-22",
      "function_names": [
        "initWithUploadDirectory",
        "shouldUploadFileAtPath",
        "shouldMoveItemFromPath"
      ],
      "filenames": [
        "GCDWebUploader/GCDWebUploader.h",
        "GCDWebDAVServer/GCDWebDAVServer.h"
      ]
    },
    {
      "headline": "Potential command injection in shell script",
      "analysis": "The Run-Tests.sh script appears to be running shell commands using eval and passing user input (file paths) without proper sanitization. An attacker could potentially inject malicious shell commands by crafting a file path containing shell metacharacters.\n",
      "classification": "very promising",
      "cwe": "CWE-78",
      "function_names": [],
      "filenames": [
        "Run-Tests.sh"
      ]
    },
    {
      "headline": "Use of hard-coded credentials in format-source script",
      "analysis": "The format-source.sh script appears to be downloading the SwiftFormat binary from a hard-coded URL without any integrity checks. An attacker who can compromise the server hosting this binary could potentially inject malicious code into the project.\n",
      "classification": "slightly promising",
      "cwe": "CWE-798",
      "function_names": [],
      "filenames": [
        "format-source.sh"
      ]
    },
    {
      "headline": "Potential open redirect vulnerability",
      "analysis": "The GCDWebServerConnection class contains a method rewriteRequestURL which could potentially be used to rewrite the request URL to an arbitrary location, leading to an open redirect vulnerability if not properly validated.\n",
      "classification": "slightly promising",
      "cwe": "CWE-601",
      "function_names": [
        "rewriteRequestURL"
      ],
      "filenames": [
        "GCDWebServer/Core/GCDWebServerConnection.h"
      ]
    }
  ],
  "scores": [
    {
      "stats": {
        "fn": 1,
        "tp": 0,
        "fp": 3
      },
      "mapping": {},
      "vuln_dates": {
        "CVE-2019-14924": "2019-08-10T19:15:10"
      },
      "scoring_model": "claude-3-5-sonnet-20240620",
      "type": "llm",
      "instruction_template_hash": "245ace12b6361954d0a2"
    }
  ],
  "instruction_template_hash": "10c0163db4740318a544",
  "version": "0.1.0"
}
