{
  "commit": "33de054efd033a0f8e3edbeb8c6b479aee5dc669",
  "repo_url": "https://gitlab.com/esr/gif2png",
  "model": "claude-3-haiku-20240307",
  "chunk_hashes": [
    "a598446895fcbe1087dc"
  ],
  "responses": [
    {
      "content": "Based on the provided codebase, here are the identified security vulnerabilities:\n\n```yaml\nleads:\n  - headline: Improper Neutralization of Special Elements used in an OS Command ('OS Command Injection')\n    analysis: |\n      The `gifread.c` file contains a `GetDataBlock` function that reads data from the input file and stores it in a buffer. The buffer size is not properly validated, which could lead to a buffer overflow vulnerability if the input file contains maliciously crafted data. This could potentially allow an attacker to execute arbitrary OS commands on the system running the `gif2png` application.\n    cwe: CWE-78\n    function_names:\n      - GetDataBlock\n    filenames:\n      - gifread.c\n    classification: very promising\n\n  - headline: Improper Neutralization of Special Elements used in an SQL Command ('SQL Injection')\n    analysis: |\n      The `gifread.c` file contains a `nextCode` function that reads and processes the input data. The function does not properly validate the input, which could lead to a SQL injection vulnerability if the input file contains maliciously crafted data. This could potentially allow an attacker to execute arbitrary SQL commands on the database used by the `gif2png` application.\n    cwe: CWE-89\n    function_names:\n      - nextCode\n    filenames:\n      - gifread.c\n    classification: very promising\n\n  - headline: Improper Neutralization of Input During Web Page Generation ('Cross-site Scripting')\n    analysis: |\n      The `test/test.html` file contains several `IMG` tags that reference GIF images. If the `gif2png` application is used to convert these GIF images to PNG format, and the resulting PNG files are then served by a web server, an attacker could potentially include malicious code in the file names, leading to a cross-site scripting (XSS) vulnerability. This could allow the attacker to execute arbitrary JavaScript code in the context of the victim's web browser.\n    cwe: CWE-79\n    function_names: []\n    filenames:\n      - test/test.html\n    classification: slightly promising\n\n  - headline: Improper Neutralization of Argument Delimiters in a Command ('Argument Injection')\n    analysis: |\n      The `gifread.c` file contains a `nextCode` function that reads and processes the input data. The function does not properly validate the input, which could lead to an argument injection vulnerability if the input file contains maliciously crafted data. This could potentially allow an attacker to inject arbitrary arguments into the command execution performed by the `gif2png` application.\n    cwe: CWE-88\n    function_names:\n      - nextCode\n    filenames:\n      - gifread.c\n    classification: very promising\n\n  - headline: Improper Neutralization of Formula Elements in a CSV File\n    analysis: |\n      The `gifread.c` file contains a `DoExtension` function that processes comment extensions in the input GIF file. If the comment extension contains maliciously crafted data, it could lead to a formula injection vulnerability in the resulting CSV file generated by the `gif2png` application.\n    cwe: CWE-1236\n    function_names:\n      - DoExtension\n    filenames:\n      - gifread.c\n    classification: slightly promising\n\n  - headline: Improper Validation of Array Index\n    analysis: |\n      The `gifread.c` file contains a `nextCode` function that reads and processes the input data. The function does not properly validate the array indices used to access the `buf` array, which could lead to an out-of-bounds read vulnerability if the input file contains maliciously crafted data.\n    cwe: CWE-129\n    function_names:\n      - nextCode\n    filenames:\n      - gifread.c\n    classification: very promising\n\n  - headline: Improper Restriction of Power Consumption\n    analysis: |\n      The `gif2png.c` file contains a `writefile` function that writes the output PNG file. The function does not properly limit the amount of resources (e.g., memory, CPU) consumed during the conversion process, which could lead to a denial-of-service vulnerability if the input file contains maliciously crafted data.\n    cwe: CWE-920\n    function_names:\n      - writefile\n    filenames:\n      - gif2png.c\n    classification: slightly promising\n\n  - headline: Improper Neutralization of Input During Web Page Generation ('Cross-site Scripting')\n    analysis: |\n      The `links2.js` file contains a JavaScript code snippet that generates HTML links based on an array of link information. If the `linkName` variable is not properly sanitized, it could lead to a cross-site scripting (XSS) vulnerability in the generated HTML.\n    cwe: CWE-79\n    function_names: []\n    filenames:\n      - test/links2.js\n    classification: slightly promising\n```",
      "date": "2024-06-14T11:08:39.155723",
      "usage": {
        "prompt_tokens": 25501,
        "completion_tokens": 1162,
        "cost": 0.00782775
      }
    }
  ],
  "leads": [
    {
      "headline": "Improper Neutralization of Special Elements used in an OS Command ('OS Command Injection')",
      "analysis": "The gifread.c file contains a GetDataBlock function that reads data from the input file and stores it in a buffer. The buffer size is not properly validated, which could lead to a buffer overflow vulnerability if the input file contains maliciously crafted data. This could potentially allow an attacker to execute arbitrary OS commands on the system running the gif2png application.\n",
      "classification": "very promising",
      "cwe": "CWE-78",
      "function_names": [
        "GetDataBlock"
      ],
      "filenames": [
        "gifread.c"
      ]
    },
    {
      "headline": "Improper Neutralization of Special Elements used in an SQL Command ('SQL Injection')",
      "analysis": "The gifread.c file contains a nextCode function that reads and processes the input data. The function does not properly validate the input, which could lead to a SQL injection vulnerability if the input file contains maliciously crafted data. This could potentially allow an attacker to execute arbitrary SQL commands on the database used by the gif2png application.\n",
      "classification": "very promising",
      "cwe": "CWE-89",
      "function_names": [
        "nextCode"
      ],
      "filenames": [
        "gifread.c"
      ]
    },
    {
      "headline": "Improper Neutralization of Input During Web Page Generation ('Cross-site Scripting')",
      "analysis": "The test/test.html file contains several IMG tags that reference GIF images. If the gif2png application is used to convert these GIF images to PNG format, and the resulting PNG files are then served by a web server, an attacker could potentially include malicious code in the file names, leading to a cross-site scripting (XSS) vulnerability. This could allow the attacker to execute arbitrary JavaScript code in the context of the victim's web browser.\n",
      "classification": "slightly promising",
      "cwe": "CWE-79",
      "function_names": [],
      "filenames": [
        "test/test.html"
      ]
    },
    {
      "headline": "Improper Neutralization of Argument Delimiters in a Command ('Argument Injection')",
      "analysis": "The gifread.c file contains a nextCode function that reads and processes the input data. The function does not properly validate the input, which could lead to an argument injection vulnerability if the input file contains maliciously crafted data. This could potentially allow an attacker to inject arbitrary arguments into the command execution performed by the gif2png application.\n",
      "classification": "very promising",
      "cwe": "CWE-88",
      "function_names": [
        "nextCode"
      ],
      "filenames": [
        "gifread.c"
      ]
    },
    {
      "headline": "Improper Neutralization of Formula Elements in a CSV File",
      "analysis": "The gifread.c file contains a DoExtension function that processes comment extensions in the input GIF file. If the comment extension contains maliciously crafted data, it could lead to a formula injection vulnerability in the resulting CSV file generated by the gif2png application.\n",
      "classification": "slightly promising",
      "cwe": "CWE-1236",
      "function_names": [
        "DoExtension"
      ],
      "filenames": [
        "gifread.c"
      ]
    },
    {
      "headline": "Improper Validation of Array Index",
      "analysis": "The gifread.c file contains a nextCode function that reads and processes the input data. The function does not properly validate the array indices used to access the buf array, which could lead to an out-of-bounds read vulnerability if the input file contains maliciously crafted data.\n",
      "classification": "very promising",
      "cwe": "CWE-129",
      "function_names": [
        "nextCode"
      ],
      "filenames": [
        "gifread.c"
      ]
    },
    {
      "headline": "Improper Restriction of Power Consumption",
      "analysis": "The gif2png.c file contains a writefile function that writes the output PNG file. The function does not properly limit the amount of resources (e.g., memory, CPU) consumed during the conversion process, which could lead to a denial-of-service vulnerability if the input file contains maliciously crafted data.\n",
      "classification": "slightly promising",
      "cwe": "CWE-920",
      "function_names": [
        "writefile"
      ],
      "filenames": [
        "gif2png.c"
      ]
    },
    {
      "headline": "Improper Neutralization of Input During Web Page Generation ('Cross-site Scripting')",
      "analysis": "The links2.js file contains a JavaScript code snippet that generates HTML links based on an array of link information. If the linkName variable is not properly sanitized, it could lead to a cross-site scripting (XSS) vulnerability in the generated HTML.\n",
      "classification": "slightly promising",
      "cwe": "CWE-79",
      "function_names": [],
      "filenames": [
        "test/links2.js"
      ]
    }
  ],
  "scores": [
    {
      "stats": {
        "fn": 1,
        "tp": 0,
        "fp": 4
      },
      "mapping": {},
      "vuln_dates": {
        "CVE-2019-17371": "2019-10-09T13:15:14"
      },
      "scoring_model": "claude-3-opus-20240229",
      "type": "llm",
      "instruction_template_hash": "245ace12b6361954d0a2"
    },
    {
      "stats": {
        "fn": 1,
        "tp": 0,
        "fp": 4
      },
      "mapping": {},
      "vuln_dates": {
        "CVE-2019-17371": "2019-10-09T13:15:14"
      },
      "scoring_model": "claude-3-5-sonnet-20240620",
      "type": "llm",
      "instruction_template_hash": "245ace12b6361954d0a2"
    }
  ],
  "instruction_template_hash": "10c0163db4740318a544",
  "version": "0.1.0"
}
