{
  "commit": "4ad36ac736b95ce617fa0dfb708a8a73618e3340",
  "repo_url": "https://github.com/nickzren/alsdb",
  "model": "claude-3-opus-20240229",
  "chunk_hashes": [
    "618d3f14538df0d8a296"
  ],
  "responses": [
    {
      "content": "Here are the potential security vulnerabilities I found in the provided codebase:\n\n```yaml\nleads:\n  - headline: SQL Injection in DBManager.executeQuery()\n    analysis: |\n      The DBManager.executeQuery() method executes raw SQL queries constructed by concatenating user input.\n      For example, in Input.initRegionListByGeneName(), the SQL query includes the geneName parameter directly without sanitization:\n        String sql = \"SELECT * FROM gene_region WHERE gene_name='\" + geneName + \"'\";\n      This allows attackers to inject malicious SQL and manipulate the query. The same issue exists in other methods like initRvisByGene() and initVariant().\n    cwe: CWE-89\n    function_names:\n      - DBManager.executeQuery\n      - Input.initRegionListByGeneName\n      - Output.initVariant\n    filenames:\n      - src/main/java/igm/alsdb/util/DBManager.java\n      - src/main/java/igm/alsdb/model/Input.java  \n      - src/main/java/igm/alsdb/model/Output.java\n    classification: very promising\n\n  - headline: HTTP Verb Tampering and Improper Access Control\n    analysis: |\n      The Search servlet has both doGet() and doPost() methods call processRequest() to handle requests. \n      The processRequest() method does not properly validate the HTTP method nor restrict access based on the method.\n      This allows attackers to bypass any access controls that may be in place by using an alternate HTTP method.\n    cwe: CWE-285\n    function_names:\n      - Search.doGet\n      - Search.doPost \n      - Search.processRequest\n    filenames:\n      - src/main/java/igm/alsdb/controller/Search.java\n    classification: slightly promising\n\n  - headline: Missing Input Validation in Output.initVariantList()\n    analysis: |\n      The Output.initVariantList() method constructs a SQL query to fetch variant data based on the Input.regionList. \n      However, it does not validate the chromosome name and start/end positions in each Region object.\n      This could allow attackers to provide overly large start/end values leading to excessively large result sets being returned.\n    cwe: CWE-20 \n    function_names:\n      - Output.initVariantList\n      - Output.addRegionSql\n    filenames:\n      - src/main/java/igm/alsdb/model/Output.java\n    classification: slightly promising\n\n  - headline: Potential XSS via Unvalidated Query Parameter\n    analysis: |\n      The Search servlet includes the unvalidated \"query\" request parameter in the request attributes when forwarding to JSP pages. \n      If this query value is rendered in HTML output without escaping, it could allow stored XSS attacks.\n    cwe: CWE-79\n    function_names:  \n      - Search.setRequest\n    filenames:\n      - src/main/java/igm/alsdb/controller/Search.java\n    classification: slightly promising\n\n  - headline: Path Traversal in Download File Generation\n    analysis: |\n      The Download.generateFile() method constructs a file path using the user-provided query value.\n      It attempts to restrict the file to certain folders, but the user input is not properly sanitized. \n      An attacker could potentially provide a crafted query value containing path traversal sequences (e.g. ../../) to access arbitrary files.\n    cwe: CWE-22\n    function_names:\n      - Download.generateFile  \n    filenames:\n      - src/main/java/igm/alsdb/model/Download.java\n    classification: slightly promising\n```\n\nThe SQL injection vulnerabilities, especially in the DBManager.executeQuery() method, are the most severe issues that should be prioritized for remediation. The others are also worth investigating and fixing to harden the application's security posture. Let me know if you need any clarification or have additional questions!",
      "date": "2024-06-14T14:57:32.845891",
      "usage": {
        "prompt_tokens": 67274,
        "completion_tokens": 944,
        "cost": 1.07991
      }
    }
  ],
  "leads": [
    {
      "headline": "SQL Injection in DBManager.executeQuery()",
      "analysis": "The DBManager.executeQuery() method executes raw SQL queries constructed by concatenating user input.\nFor example, in Input.initRegionListByGeneName(), the SQL query includes the geneName parameter directly without sanitization:\n  String sql = \"SELECT * FROM gene_region WHERE gene_name='\" + geneName + \"'\";\nThis allows attackers to inject malicious SQL and manipulate the query. The same issue exists in other methods like initRvisByGene() and initVariant().\n",
      "classification": "very promising",
      "cwe": "CWE-89",
      "function_names": [
        "DBManager.executeQuery",
        "Input.initRegionListByGeneName",
        "Output.initVariant"
      ],
      "filenames": [
        "src/main/java/igm/alsdb/util/DBManager.java",
        "src/main/java/igm/alsdb/model/Input.java",
        "src/main/java/igm/alsdb/model/Output.java"
      ]
    },
    {
      "headline": "HTTP Verb Tampering and Improper Access Control",
      "analysis": "The Search servlet has both doGet() and doPost() methods call processRequest() to handle requests. \nThe processRequest() method does not properly validate the HTTP method nor restrict access based on the method.\nThis allows attackers to bypass any access controls that may be in place by using an alternate HTTP method.\n",
      "classification": "slightly promising",
      "cwe": "CWE-285",
      "function_names": [
        "Search.doGet",
        "Search.doPost",
        "Search.processRequest"
      ],
      "filenames": [
        "src/main/java/igm/alsdb/controller/Search.java"
      ]
    },
    {
      "headline": "Missing Input Validation in Output.initVariantList()",
      "analysis": "The Output.initVariantList() method constructs a SQL query to fetch variant data based on the Input.regionList. \nHowever, it does not validate the chromosome name and start/end positions in each Region object.\nThis could allow attackers to provide overly large start/end values leading to excessively large result sets being returned.\n",
      "classification": "slightly promising",
      "cwe": "CWE-20",
      "function_names": [
        "Output.initVariantList",
        "Output.addRegionSql"
      ],
      "filenames": [
        "src/main/java/igm/alsdb/model/Output.java"
      ]
    },
    {
      "headline": "Potential XSS via Unvalidated Query Parameter",
      "analysis": "The Search servlet includes the unvalidated \"query\" request parameter in the request attributes when forwarding to JSP pages. \nIf this query value is rendered in HTML output without escaping, it could allow stored XSS attacks.\n",
      "classification": "slightly promising",
      "cwe": "CWE-79",
      "function_names": [
        "Search.setRequest"
      ],
      "filenames": [
        "src/main/java/igm/alsdb/controller/Search.java"
      ]
    },
    {
      "headline": "Path Traversal in Download File Generation",
      "analysis": "The Download.generateFile() method constructs a file path using the user-provided query value.\nIt attempts to restrict the file to certain folders, but the user input is not properly sanitized. \nAn attacker could potentially provide a crafted query value containing path traversal sequences (e.g. ../../) to access arbitrary files.\n",
      "classification": "slightly promising",
      "cwe": "CWE-22",
      "function_names": [
        "Download.generateFile"
      ],
      "filenames": [
        "src/main/java/igm/alsdb/model/Download.java"
      ]
    }
  ],
  "scores": [
    {
      "stats": {
        "fn": 0,
        "tp": 1,
        "fp": 0
      },
      "mapping": {
        "0": "CVE-2016-15021"
      },
      "vuln_dates": {
        "CVE-2016-15021": "2023-01-17T16:15:16"
      },
      "scoring_model": "claude-3-opus-20240229",
      "type": "llm",
      "instruction_template_hash": "245ace12b6361954d0a2"
    },
    {
      "stats": {
        "fn": 0,
        "tp": 1,
        "fp": 0
      },
      "mapping": {
        "0": "CVE-2016-15021"
      },
      "vuln_dates": {
        "CVE-2016-15021": "2023-01-17T16:15:16"
      },
      "scoring_model": "claude-3-5-sonnet-20240620",
      "type": "llm",
      "instruction_template_hash": "245ace12b6361954d0a2"
    }
  ],
  "instruction_template_hash": "10c0163db4740318a544",
  "version": "0.1.0"
}
