{
  "commit": "c6484d59f1fad41352e2a5bdba894e7f4aed1877",
  "repo_url": "https://github.com/lkw199711/smanga",
  "model": "gpt-4-turbo-2024-04-09",
  "chunk_hashes": [
    "5fad4101fc86f90d2d3a"
  ],
  "responses": [
    {
      "content": "```yaml\nleads:\n  - headline: \"Insecure Direct Object References (IDOR) in manga and chapter management\"\n    analysis: |\n      The system allows users to access and manipulate manga and chapter data using direct object references such as 'mangaId', 'chapterId', and 'mediaId' without proper authorization checks. This could enable an authenticated user to access or modify data belonging to other users by simply changing these parameter values in requests. It's a typical IDOR vulnerability where access control mechanisms are not properly implemented, exposing sensitive data manipulation to unauthorized users.\n    cwe: CWE-639\n    function_names:\n      - handleEdit\n      - delete_path\n      - update_media\n    filenames:\n      - src/views/manga-setting/script/index.ts\n      - src/views/path-setting/script/index.ts\n      - src/views/media-setting/script/index.ts\n    classification: \"very promising\"\n\n  - headline: \"Exposure of Sensitive Information to an Unauthorized Actor\"\n    analysis: |\n      The application seems to be logging sensitive debugging information that could provide clues about its architecture or technology stack. This information could potentially help an attacker craft further attacks against the system. The debugging information should not be accessible in the production environment or should be protected to ensure it doesn't expose any sensitive data or insights about the underlying system.\n    cwe: CWE-532\n    function_names:\n      - ajax\n    filenames:\n      - src/api/index.ts\n    classification: \"slightly promising\"\n\n  - headline: \"Cross-site Scripting (XSS) through user-controllable data\"\n    analysis: |\n      User-input values such as 'username', 'mediaName', 'chapterName', etc., are directly used within the application's pages without proper sanitization or encoding. This practice could allow attackers to inject malicious scripts into the web pages, which would be executed in the context of the user's session, leading to session hijacking, data theft, or malicious redirection, among other threats.\n    cwe: CWE-79\n    function_names:\n      - handleEdit\n      - update_manga\n      - delete_manga\n    filenames:\n      - src/views/manga-setting/script/index.ts\n      - src/views/chapter-setting/script/index.ts\n    classification: \"very promising\"\n\n  - headline: \"SQL Injection in browsing data functionality\"\n    analysis: |\n      The parameters such as 'recordStart' and 'pageSize' used in the SQL queries within the browsing data fetching functionality are taken from user input without sufficient sanitation, making them susceptible to SQL injection. This could allow an attacker to inject malicious SQL queries that could read, modify, or delete database information or interfere with application logic.\n    cwe: CWE-89\n    function_names:\n      - load_table\n      - get_path\n      - get_chapter\n    filenames:\n      - src/views/account/script/index.ts\n      - src/api/path.ts\n      - src/api/chapter.ts\n    classification: \"very promising\"\n\n  - headline: \"Unrestricted File Upload leading to Arbitrary Code Execution\"\n    analysis: |\n      The file upload functionality does not properly validate the uploaded file types, nor does it sanitize the file names. This could allow an attacker to upload a script file (e.g., PHP, Python) disguised with a double extension, leading to its execution on the server upon access. This may further lead to unauthorized command execution within the server environment or access to sensitive information.\n    cwe: CWE-434\n    function_names:\n      - add_path\n      - update_media\n    filenames:\n      - src/api/path.ts\n      - src/api/media.ts\n    classification: \"very promising\"\n\n  - headline: \"Improper Error Handling Revealing Sensitive Information to User\"\n    analysis: |\n      The exception handling routines across various parts of the application might leak sensitive information about the underlying operation, backend services, or frameworks, especially when database operations fail or other critical functions encounter errors. This exposure can assist attackers in developing more precise attacks against the application.\n    cwe: CWE-209\n    function_names:\n      - register\n      - login\n      - delete_account\n    filenames:\n      - src/api/account.ts\n    classification: \"slightly promising\"\n\n  - headline: \"Information Exposure Through Debug Information\"\n    analysis: |\n      Debugging code that outputs detailed error messages, path information, and server specifics has been left within the application's production environment. This could facilitate an attacker in crafting attacks by providing insights into the application's structure and potential security misconfigurations.\n    cwe: CWE-215\n    function_names:\n      - ajax\n    filenames:\n      - src/api/index.ts\n    classification: \"slightly promising\"\n\n  - headline: \"Use of Hard-coded Credentials in Database Administration\"\n    analysis: |\n      The application source code contains hard-coded credentials used for database connections. This bad practice might allow an attacker who has gained access to the source code the ability to connect to the database and manipulate or steal data, assuming these credentials have not been changed in the live environment.\n    cwe: CWE-798\n    function_names:\n      - database_set\n      - database_check\n    filenames:\n      - src/api/login.ts\n    classification: \"slightly promising\"\n```",
      "date": "2024-06-09T13:15:13.609234",
      "usage": {
        "prompt_tokens": 69261,
        "completion_tokens": 1075,
        "cost": 0.72486
      }
    }
  ],
  "leads": [
    {
      "headline": "Insecure Direct Object References (IDOR) in manga and chapter management",
      "analysis": "The system allows users to access and manipulate manga and chapter data using direct object references such as 'mangaId', 'chapterId', and 'mediaId' without proper authorization checks. This could enable an authenticated user to access or modify data belonging to other users by simply changing these parameter values in requests. It's a typical IDOR vulnerability where access control mechanisms are not properly implemented, exposing sensitive data manipulation to unauthorized users.\n",
      "classification": "very promising",
      "cwe": "CWE-639",
      "function_names": [
        "handleEdit",
        "delete_path",
        "update_media"
      ],
      "filenames": [
        "src/views/manga-setting/script/index.ts",
        "src/views/path-setting/script/index.ts",
        "src/views/media-setting/script/index.ts"
      ]
    },
    {
      "headline": "Exposure of Sensitive Information to an Unauthorized Actor",
      "analysis": "The application seems to be logging sensitive debugging information that could provide clues about its architecture or technology stack. This information could potentially help an attacker craft further attacks against the system. The debugging information should not be accessible in the production environment or should be protected to ensure it doesn't expose any sensitive data or insights about the underlying system.\n",
      "classification": "slightly promising",
      "cwe": "CWE-532",
      "function_names": [
        "ajax"
      ],
      "filenames": [
        "src/api/index.ts"
      ]
    },
    {
      "headline": "Cross-site Scripting (XSS) through user-controllable data",
      "analysis": "User-input values such as 'username', 'mediaName', 'chapterName', etc., are directly used within the application's pages without proper sanitization or encoding. This practice could allow attackers to inject malicious scripts into the web pages, which would be executed in the context of the user's session, leading to session hijacking, data theft, or malicious redirection, among other threats.\n",
      "classification": "very promising",
      "cwe": "CWE-79",
      "function_names": [
        "handleEdit",
        "update_manga",
        "delete_manga"
      ],
      "filenames": [
        "src/views/manga-setting/script/index.ts",
        "src/views/chapter-setting/script/index.ts"
      ]
    },
    {
      "headline": "SQL Injection in browsing data functionality",
      "analysis": "The parameters such as 'recordStart' and 'pageSize' used in the SQL queries within the browsing data fetching functionality are taken from user input without sufficient sanitation, making them susceptible to SQL injection. This could allow an attacker to inject malicious SQL queries that could read, modify, or delete database information or interfere with application logic.\n",
      "classification": "very promising",
      "cwe": "CWE-89",
      "function_names": [
        "load_table",
        "get_path",
        "get_chapter"
      ],
      "filenames": [
        "src/views/account/script/index.ts",
        "src/api/path.ts",
        "src/api/chapter.ts"
      ]
    },
    {
      "headline": "Unrestricted File Upload leading to Arbitrary Code Execution",
      "analysis": "The file upload functionality does not properly validate the uploaded file types, nor does it sanitize the file names. This could allow an attacker to upload a script file (e.g., PHP, Python) disguised with a double extension, leading to its execution on the server upon access. This may further lead to unauthorized command execution within the server environment or access to sensitive information.\n",
      "classification": "very promising",
      "cwe": "CWE-434",
      "function_names": [
        "add_path",
        "update_media"
      ],
      "filenames": [
        "src/api/path.ts",
        "src/api/media.ts"
      ]
    },
    {
      "headline": "Improper Error Handling Revealing Sensitive Information to User",
      "analysis": "The exception handling routines across various parts of the application might leak sensitive information about the underlying operation, backend services, or frameworks, especially when database operations fail or other critical functions encounter errors. This exposure can assist attackers in developing more precise attacks against the application.\n",
      "classification": "slightly promising",
      "cwe": "CWE-209",
      "function_names": [
        "register",
        "login",
        "delete_account"
      ],
      "filenames": [
        "src/api/account.ts"
      ]
    },
    {
      "headline": "Information Exposure Through Debug Information",
      "analysis": "Debugging code that outputs detailed error messages, path information, and server specifics has been left within the application's production environment. This could facilitate an attacker in crafting attacks by providing insights into the application's structure and potential security misconfigurations.\n",
      "classification": "slightly promising",
      "cwe": "CWE-215",
      "function_names": [
        "ajax"
      ],
      "filenames": [
        "src/api/index.ts"
      ]
    },
    {
      "headline": "Use of Hard-coded Credentials in Database Administration",
      "analysis": "The application source code contains hard-coded credentials used for database connections. This bad practice might allow an attacker who has gained access to the source code the ability to connect to the database and manipulate or steal data, assuming these credentials have not been changed in the live environment.\n",
      "classification": "slightly promising",
      "cwe": "CWE-798",
      "function_names": [
        "database_set",
        "database_check"
      ],
      "filenames": [
        "src/api/login.ts"
      ]
    }
  ],
  "scores": [
    {
      "stats": {
        "fn": 1,
        "tp": 0,
        "fp": 4
      },
      "mapping": {},
      "vuln_dates": {
        "CVE-2023-36076": "2023-09-01T16:15:07"
      },
      "scoring_model": "gpt-4o-2024-05-13",
      "type": "llm",
      "instruction_template_hash": "8998f09cf57fca8a6e03"
    }
  ],
  "instruction_template_hash": "10c0163db4740318a544",
  "version": "0.1.0"
}
