{
  "commit": "5cb6f414e6fac68038533b0f36814f765aa971de",
  "repo_url": "https://github.com/a-schild/jave2",
  "model": "gpt-4-turbo-2024-04-09",
  "chunk_hashes": [
    "6c9dc8acb1d4fc2735b8"
  ],
  "responses": [
    {
      "content": "```yaml\nleads:\n  - headline: \"Insecure File Handling in FileVideoEncoderTest\"\n    analysis: |\n      The 'FileVideoEncoderTest' class in 'jave-core-test/src/test/java/ws/schild/jave/FileVideoEncoderTest.java' involves sequences of file operations that do not check for the return value of file deletion. The assumption is that the associated file operations are successful without verification, potentially leading to unhandled conditions where leftover or locked files could affect the output of the test or subsequent file operations.\n    cwe: CWE-39\n    function_names:\n      - testEncodeVideo1\n      - testEncodeVideo2\n    filenames:\n      - \"jave-core-test/src/test/java/ws/schild/jave/FileVideoEncoderTest.java\"\n    classification: \"slightly promising\"\n\n  - headline: \"Hard-coded URL in MultimediaObjectTest in Java 11 Codebase\"\n    analysis: |\n      The 'MultimediaObjectTest' class in 'jave-core-test-java11/src/test/java/ws/schild/jave/MultimediaObjectTest.java' uses hard-coded URL 'https://samples.ffmpeg.org/MPEG1/zelda%20first%20commercial.mpeg'. The use of fixed URL restricts the flexibility and could pose security risks if the URL is no longer available or is compromised.\n    cwe: CWE-259\n    function_names:\n      - testRenderImage_01\n      - testRenderImage_02\n    filenames:\n      - \"jave-core-test-java11/src/test/java/ws/schild/jave/MultimediaObjectTest.java\"\n    classification: \"not promising\"\n\n  - headline: \"Use of potentially insecure temporary file generation method in 'DefaultFFMPEGLocator'\"\n    analysis: |\n      The 'DefaultFFMPEGLocator' class within 'jave-core/src/main/java/ws/schild/jave/process/ffmpeg/DefaultFFMPEGLocator.java' does not incorporate measures to securely create temporary directories or files. This may lead to vulnerabilities where an attacker could access, modify, or delete temporary files, potentially influencing the behavior of an application.\n    cwe: CWE-377\n    function_names: \n      - \"<init>\"\n    filenames:\n      - \"jave-core/src/main/java/ws/schild/jave/process/ffmpeg/DefaultFFMPEGLocator.java\"\n    classification: \"slightly promising\"\n\n  - headline: \"Exposure of Sensitive Information in Encode Failure\"\n    analysis: |\n      When 'Encoder' class from 'jave-core/src/main/java/ws/schild/jave/Encoder.java' encounters an encoding failure, it throws an exception with an error message which may include sensitive information about the file path or encoding parameters used. This information may aid attackers in crafting further attacks or gaining unauthorized access to the system.\n    cwe: CWE-209\n    function_names:\n      - encode\n    filenames:\n      - \"jave-core/src/main/java/ws/schild/jave/Encoder.java\"\n    classification: \"slightly promising\"\n\n  - headline: \"Insecure random number generation for temp file/folder naming\"\n    analysis: |\n      Within 'FFMPEGProcess' and 'DefaultFFMPEGLocator' in 'jave-core/src/main/java/ws/schild/jave/process/ffmpeg', there appears to be the use of insecure random or predictable names for temporary files or folders. Using predictable file names may allow attackers to easily guess or find out file names and paths, which could lead to unauthorized access to these files.\n    cwe: CWE-330\n    function_names:\n      - createExecutor\n      - \"<init>\"\n    filenames:\n      - \"jave-core/src/main/java/ws/schild/jave/process/ffmpeg/DefaultFFMPEGLocator.java\"\n      - \"jave-core/src/main/java/ws/schild/jave/process/ffmpeg/FFMPEGProcess.java\"\n    classification: \"slightly promising\"\n```",
      "date": "2024-06-08T21:50:33.214067",
      "usage": {
        "prompt_tokens": 78204,
        "completion_tokens": 802,
        "cost": 0.8061
      }
    }
  ],
  "leads": [
    {
      "headline": "Insecure File Handling in FileVideoEncoderTest",
      "analysis": "The 'FileVideoEncoderTest' class in 'jave-core-test/src/test/java/ws/schild/jave/FileVideoEncoderTest.java' involves sequences of file operations that do not check for the return value of file deletion. The assumption is that the associated file operations are successful without verification, potentially leading to unhandled conditions where leftover or locked files could affect the output of the test or subsequent file operations.\n",
      "classification": "slightly promising",
      "cwe": "CWE-39",
      "function_names": [
        "testEncodeVideo1",
        "testEncodeVideo2"
      ],
      "filenames": [
        "jave-core-test/src/test/java/ws/schild/jave/FileVideoEncoderTest.java"
      ]
    },
    {
      "headline": "Hard-coded URL in MultimediaObjectTest in Java 11 Codebase",
      "analysis": "The 'MultimediaObjectTest' class in 'jave-core-test-java11/src/test/java/ws/schild/jave/MultimediaObjectTest.java' uses hard-coded URL 'https://samples.ffmpeg.org/MPEG1/zelda%20first%20commercial.mpeg'. The use of fixed URL restricts the flexibility and could pose security risks if the URL is no longer available or is compromised.\n",
      "classification": "not promising",
      "cwe": "CWE-259",
      "function_names": [
        "testRenderImage_01",
        "testRenderImage_02"
      ],
      "filenames": [
        "jave-core-test-java11/src/test/java/ws/schild/jave/MultimediaObjectTest.java"
      ]
    },
    {
      "headline": "Use of potentially insecure temporary file generation method in 'DefaultFFMPEGLocator'",
      "analysis": "The 'DefaultFFMPEGLocator' class within 'jave-core/src/main/java/ws/schild/jave/process/ffmpeg/DefaultFFMPEGLocator.java' does not incorporate measures to securely create temporary directories or files. This may lead to vulnerabilities where an attacker could access, modify, or delete temporary files, potentially influencing the behavior of an application.\n",
      "classification": "slightly promising",
      "cwe": "CWE-377",
      "function_names": [
        "<init>"
      ],
      "filenames": [
        "jave-core/src/main/java/ws/schild/jave/process/ffmpeg/DefaultFFMPEGLocator.java"
      ]
    },
    {
      "headline": "Exposure of Sensitive Information in Encode Failure",
      "analysis": "When 'Encoder' class from 'jave-core/src/main/java/ws/schild/jave/Encoder.java' encounters an encoding failure, it throws an exception with an error message which may include sensitive information about the file path or encoding parameters used. This information may aid attackers in crafting further attacks or gaining unauthorized access to the system.\n",
      "classification": "slightly promising",
      "cwe": "CWE-209",
      "function_names": [
        "encode"
      ],
      "filenames": [
        "jave-core/src/main/java/ws/schild/jave/Encoder.java"
      ]
    },
    {
      "headline": "Insecure random number generation for temp file/folder naming",
      "analysis": "Within 'FFMPEGProcess' and 'DefaultFFMPEGLocator' in 'jave-core/src/main/java/ws/schild/jave/process/ffmpeg', there appears to be the use of insecure random or predictable names for temporary files or folders. Using predictable file names may allow attackers to easily guess or find out file names and paths, which could lead to unauthorized access to these files.\n",
      "classification": "slightly promising",
      "cwe": "CWE-330",
      "function_names": [
        "createExecutor",
        "<init>"
      ],
      "filenames": [
        "jave-core/src/main/java/ws/schild/jave/process/ffmpeg/DefaultFFMPEGLocator.java",
        "jave-core/src/main/java/ws/schild/jave/process/ffmpeg/FFMPEGProcess.java"
      ]
    }
  ],
  "scores": [
    {
      "stats": {
        "fn": 1,
        "tp": 0,
        "fp": 0
      },
      "mapping": {},
      "vuln_dates": {
        "CVE-2023-48909": "2024-01-12T09:15:44"
      },
      "scoring_model": "gpt-4o-2024-05-13",
      "type": "llm",
      "instruction_template_hash": "8998f09cf57fca8a6e03"
    }
  ],
  "instruction_template_hash": "10c0163db4740318a544",
  "version": "0.1.0"
}
