{
  "commit": "2ceec8e61cb0058a61239b9ac45861b703c9c1cf",
  "repo_url": "https://github.com/troglobit/libuev",
  "model": "gpt-4o-2024-05-13",
  "chunk_hashes": [
    "2dd4edf570ed560dac8f"
  ],
  "responses": [
    {
      "content": "```yaml\nleads:\n  - headline: \"Potential File Descriptor Leak\"\n    analysis: |\n      In the file `src/io.c`, the function `uev_io_set` does not handle the case where an error occurs during the re-initialization of the I/O watcher. If `_uev_watcher_rearm` returns an error, the file descriptor `fd` might remain open and cause a file descriptor leak.\n    cwe: CWE-401\n    function_names:\n      - uev_io_set\n    filenames:\n      - src/io.c\n    classification: very promising\n\n  - headline: \"Improper Handling of Signal Mask\"\n    analysis: |\n      In the file `src/signal.c`, the function `uev_signal_set` modifies the signal mask without saving and restoring the original signal mask. This could lead to unintended behavior in other parts of the program that rely on the signal mask.\n    cwe: CWE-667\n    function_names:\n      - uev_signal_set\n    filenames:\n      - src/signal.c\n    classification: slightly promising\n\n  - headline: \"Possible Race Condition in Timer Handling\"\n    analysis: |\n      In the file `src/timer.c`, the functions `uev_timer_set` and `uev_timer_start` involve restarting timers. If these functions are invoked simultaneously from different threads, it may cause a race condition leading to unexpected behavior or crashes.\n    cwe: CWE-362\n    function_names:\n      - uev_timer_set\n      - uev_timer_start\n    filenames:\n      - src/timer.c\n    classification: slightly promising\n\n  - headline: \"Unchecked Return Value in Timer Read Callback\"\n    analysis: |\n      In the file `src/timer.c`, the return value of the `read` system call in function `uev_timer_cb` is not checked for errors. This might lead to undetected errors and potential issues in timer management.\n    cwe: CWE-252\n    function_names:\n      - uev_timer_cb\n    filenames:\n      - src/timer.c\n    classification: slightly promising\n\n  - headline: \"Unchecked Buffer Size in Read Operations\"\n    analysis: |\n      In multiple watcher callback functions across the codebase (e.g., `pipe_read_cb` in `test/complete.c`), there are potential issues with buffer size validation. If the buffer size is not properly validated against the read size, it could lead to buffer overflows.\n    cwe: CWE-120\n    function_names:\n      - pipe_read_cb\n    filenames:\n      - test/complete.c\n    classification: very promising\n\n  - headline: \"Signal Handling in Multithreaded Context\"\n    analysis: |\n      In the file `test/signal.c`, the signal handling function `sig_cb` handles signals in a multithreaded context without ensuring proper synchronization. This can cause race conditions if the signal handler is executed concurrently with signal-sensitive operations in other threads.\n    cwe: CWE-362\n    function_names:\n      - sig_cb\n    filenames:\n      - test/signal.c\n    classification: very promising\n```",
      "date": "2024-06-09T15:13:36.625658",
      "usage": {
        "prompt_tokens": 23251,
        "completion_tokens": 643,
        "cost": 0.1259
      }
    }
  ],
  "leads": [
    {
      "headline": "Potential File Descriptor Leak",
      "analysis": "In the file src/io.c, the function uev_io_set does not handle the case where an error occurs during the re-initialization of the I/O watcher. If _uev_watcher_rearm returns an error, the file descriptor fd might remain open and cause a file descriptor leak.\n",
      "classification": "very promising",
      "cwe": "CWE-401",
      "function_names": [
        "uev_io_set"
      ],
      "filenames": [
        "src/io.c"
      ]
    },
    {
      "headline": "Improper Handling of Signal Mask",
      "analysis": "In the file src/signal.c, the function uev_signal_set modifies the signal mask without saving and restoring the original signal mask. This could lead to unintended behavior in other parts of the program that rely on the signal mask.\n",
      "classification": "slightly promising",
      "cwe": "CWE-667",
      "function_names": [
        "uev_signal_set"
      ],
      "filenames": [
        "src/signal.c"
      ]
    },
    {
      "headline": "Possible Race Condition in Timer Handling",
      "analysis": "In the file src/timer.c, the functions uev_timer_set and uev_timer_start involve restarting timers. If these functions are invoked simultaneously from different threads, it may cause a race condition leading to unexpected behavior or crashes.\n",
      "classification": "slightly promising",
      "cwe": "CWE-362",
      "function_names": [
        "uev_timer_set",
        "uev_timer_start"
      ],
      "filenames": [
        "src/timer.c"
      ]
    },
    {
      "headline": "Unchecked Return Value in Timer Read Callback",
      "analysis": "In the file src/timer.c, the return value of the read system call in function uev_timer_cb is not checked for errors. This might lead to undetected errors and potential issues in timer management.\n",
      "classification": "slightly promising",
      "cwe": "CWE-252",
      "function_names": [
        "uev_timer_cb"
      ],
      "filenames": [
        "src/timer.c"
      ]
    },
    {
      "headline": "Unchecked Buffer Size in Read Operations",
      "analysis": "In multiple watcher callback functions across the codebase (e.g., pipe_read_cb in test/complete.c), there are potential issues with buffer size validation. If the buffer size is not properly validated against the read size, it could lead to buffer overflows.\n",
      "classification": "very promising",
      "cwe": "CWE-120",
      "function_names": [
        "pipe_read_cb"
      ],
      "filenames": [
        "test/complete.c"
      ]
    },
    {
      "headline": "Signal Handling in Multithreaded Context",
      "analysis": "In the file test/signal.c, the signal handling function sig_cb handles signals in a multithreaded context without ensuring proper synchronization. This can cause race conditions if the signal handler is executed concurrently with signal-sensitive operations in other threads.\n",
      "classification": "very promising",
      "cwe": "CWE-362",
      "function_names": [
        "sig_cb"
      ],
      "filenames": [
        "test/signal.c"
      ]
    }
  ],
  "scores": [
    {
      "stats": {
        "fn": 1,
        "tp": 0,
        "fp": 3
      },
      "mapping": {},
      "vuln_dates": {
        "CVE-2022-48620": "2024-01-12T04:15:08"
      },
      "scoring_model": "gpt-4o-2024-05-13",
      "type": "llm",
      "instruction_template_hash": "8998f09cf57fca8a6e03"
    },
    {
      "stats": {
        "fn": 1,
        "tp": 0,
        "fp": 3
      },
      "mapping": {},
      "vuln_dates": {
        "CVE-2022-48620": "2024-01-12T04:15:08"
      },
      "scoring_model": "claude-3-opus-20240229",
      "type": "llm",
      "instruction_template_hash": "245ace12b6361954d0a2"
    }
  ],
  "instruction_template_hash": "10c0163db4740318a544",
  "version": "0.1.0"
}
