{
  "commit": "2f98656940ee16d8a083128fdd3e5274086905e5",
  "repo_url": "https://github.com/jenkinsci/websphere-deployer-plugin",
  "model": "gpt-4o-2024-05-13",
  "chunk_hashes": [
    "01428c9cca38e8c643e7"
  ],
  "responses": [
    {
      "content": "```yaml\nleads:\n  - headline: Hardcoded credentials present in WebSphereDeployerPlugin.java\n    analysis: |\n      The file WebSphereDeployerPlugin.java contains hardcoded credentials, which are a significant security flaw as they could be easily exploited if the source code is leaked or accessed by unauthorized users. This could lead to unauthorized access to sensitive systems and data.\n    cwe: CWE-798\n    function_names:\n      - WebSphereDeployerPlugin\n    filenames:\n      - src/main/java/org/jenkinsci/plugins/websphere_deployer/WebSphereDeployerPlugin.java\n    classification: very promising\n\n  - headline: Insecure password storage in LibertyDeployerPlugin.java\n    analysis: |\n      The file LibertyDeployerPlugin.java uses the Scrambler utility to \"scramble\" passwords, which may not provide sufficient protection against reverse engineering or brute force attacks. This can lead to the exposure of sensitive information such as passwords, increasing the risk of unauthorized access.\n    cwe: CWE-311\n    function_names:\n      - LibertyDeployerPlugin\n    filenames:\n      - src/main/java/org/jenkinsci/plugins/websphere_deployer/LibertyDeployerPlugin.java\n    classification: very promising\n\n  - headline: Insecure password storage in WebSphereSecurity.java\n    analysis: |\n      Similar to LibertyDeployerPlugin.java, WebSphereSecurity.java also uses the Scrambler utility to store passwords. This method does not provide strong encryption and can be easily compromised, leading to potential unauthorized access to sensitive systems.\n    cwe: CWE-311\n    function_names:\n      - WebSphereSecurity\n    filenames:\n      - src/main/java/org/jenkinsci/plugins/websphere_deployer/WebSphereSecurity.java\n    classification: very promising\n\n  - headline: Trusting all SSL connections in SSLUtilities.java\n    analysis: |\n      The file SSLUtilities.java includes functionality that is designed to trust all SSL certificates and hostnames, which completely bypasses SSL certificate validation. This makes man-in-the-middle (MitM) attacks trivially easy and allows attackers to intercept and potentially modify sensitive data being transmitted over SSL connections.\n    cwe: CWE-295\n    function_names:\n      - trustAllHostnames\n      - trustAllHttpsCertificates\n    filenames:\n      - src/main/java/org/jenkinsci/plugins/websphere/services/deployment/SSLUtilities.java\n    classification: very promising\n\n  - headline: Potential NullPointerException in LibertyDeploymentService.java\n    analysis: |\n      In the LibertyDeploymentService.java file, several instances where the client is used without null checks could lead to a NullPointerException if the client connection fails or is not initialized properly. This can lead to unexpected crashes and denial of service.\n    cwe: CWE-476\n    function_names:\n      - installArtifact\n      - uninstallArtifact\n      - startArtifact\n      - stopArtifact\n      - isArtifactInstalled\n    filenames:\n      - src/main/java/org/jenkinsci/plugins/websphere/services/deployment/LibertyDeploymentService.java\n    classification: slightly promising\n\n  - headline: Missing exception handling in WebSphereDeployerPlugin.java\n    analysis: |\n      The file WebSphereDeployerPlugin.java contains operations that rely on external systems (such as stopping, uninstalling, and starting artifacts) that could throw various exceptions. These exceptions are not always handled properly, which could result in application crashes or undefined behaviors.\n    cwe: CWE-248\n    function_names:\n      - stopArtifact\n      - uninstallArtifact\n      - startArtifact\n    filenames:\n      - src/main/java/org/jenkinsci/plugins/websphere_deployer/WebSphereDeployerPlugin.java\n    classification: slightly promising\n\n  - headline: Incorrect type conversion in Artifact.java\n    analysis: |\n      In Artifact.java, there are several places where type conversion is performed without proper validation, which could lead to runtime exceptions or incorrect behavior if the conversion fails.\n    cwe: CWE-704\n    function_names:\n      - setType\n    filenames:\n      - src/main/java/org/jenkinsci/plugins/websphere/services/deployment/Artifact.java\n    classification: slightly promising\n```",
      "date": "2024-06-12T19:30:56.537009",
      "usage": {
        "prompt_tokens": 26039,
        "completion_tokens": 854,
        "cost": 0.143005
      }
    }
  ],
  "leads": [
    {
      "headline": "Hardcoded credentials present in WebSphereDeployerPlugin.java",
      "analysis": "The file WebSphereDeployerPlugin.java contains hardcoded credentials, which are a significant security flaw as they could be easily exploited if the source code is leaked or accessed by unauthorized users. This could lead to unauthorized access to sensitive systems and data.\n",
      "classification": "very promising",
      "cwe": "CWE-798",
      "function_names": [
        "WebSphereDeployerPlugin"
      ],
      "filenames": [
        "src/main/java/org/jenkinsci/plugins/websphere_deployer/WebSphereDeployerPlugin.java"
      ]
    },
    {
      "headline": "Insecure password storage in LibertyDeployerPlugin.java",
      "analysis": "The file LibertyDeployerPlugin.java uses the Scrambler utility to \"scramble\" passwords, which may not provide sufficient protection against reverse engineering or brute force attacks. This can lead to the exposure of sensitive information such as passwords, increasing the risk of unauthorized access.\n",
      "classification": "very promising",
      "cwe": "CWE-311",
      "function_names": [
        "LibertyDeployerPlugin"
      ],
      "filenames": [
        "src/main/java/org/jenkinsci/plugins/websphere_deployer/LibertyDeployerPlugin.java"
      ]
    },
    {
      "headline": "Insecure password storage in WebSphereSecurity.java",
      "analysis": "Similar to LibertyDeployerPlugin.java, WebSphereSecurity.java also uses the Scrambler utility to store passwords. This method does not provide strong encryption and can be easily compromised, leading to potential unauthorized access to sensitive systems.\n",
      "classification": "very promising",
      "cwe": "CWE-311",
      "function_names": [
        "WebSphereSecurity"
      ],
      "filenames": [
        "src/main/java/org/jenkinsci/plugins/websphere_deployer/WebSphereSecurity.java"
      ]
    },
    {
      "headline": "Trusting all SSL connections in SSLUtilities.java",
      "analysis": "The file SSLUtilities.java includes functionality that is designed to trust all SSL certificates and hostnames, which completely bypasses SSL certificate validation. This makes man-in-the-middle (MitM) attacks trivially easy and allows attackers to intercept and potentially modify sensitive data being transmitted over SSL connections.\n",
      "classification": "very promising",
      "cwe": "CWE-295",
      "function_names": [
        "trustAllHostnames",
        "trustAllHttpsCertificates"
      ],
      "filenames": [
        "src/main/java/org/jenkinsci/plugins/websphere/services/deployment/SSLUtilities.java"
      ]
    },
    {
      "headline": "Potential NullPointerException in LibertyDeploymentService.java",
      "analysis": "In the LibertyDeploymentService.java file, several instances where the client is used without null checks could lead to a NullPointerException if the client connection fails or is not initialized properly. This can lead to unexpected crashes and denial of service.\n",
      "classification": "slightly promising",
      "cwe": "CWE-476",
      "function_names": [
        "installArtifact",
        "uninstallArtifact",
        "startArtifact"
      ],
      "filenames": [
        "src/main/java/org/jenkinsci/plugins/websphere/services/deployment/LibertyDeploymentService.java"
      ]
    },
    {
      "headline": "Missing exception handling in WebSphereDeployerPlugin.java",
      "analysis": "The file WebSphereDeployerPlugin.java contains operations that rely on external systems (such as stopping, uninstalling, and starting artifacts) that could throw various exceptions. These exceptions are not always handled properly, which could result in application crashes or undefined behaviors.\n",
      "classification": "slightly promising",
      "cwe": "CWE-248",
      "function_names": [
        "stopArtifact",
        "uninstallArtifact",
        "startArtifact"
      ],
      "filenames": [
        "src/main/java/org/jenkinsci/plugins/websphere_deployer/WebSphereDeployerPlugin.java"
      ]
    },
    {
      "headline": "Incorrect type conversion in Artifact.java",
      "analysis": "In Artifact.java, there are several places where type conversion is performed without proper validation, which could lead to runtime exceptions or incorrect behavior if the conversion fails.\n",
      "classification": "slightly promising",
      "cwe": "CWE-704",
      "function_names": [
        "setType"
      ],
      "filenames": [
        "src/main/java/org/jenkinsci/plugins/websphere/services/deployment/Artifact.java"
      ]
    }
  ],
  "scores": [
    {
      "stats": {
        "fn": 3,
        "tp": 1,
        "fp": 3
      },
      "mapping": {
        "3": "CVE-2019-16561"
      },
      "vuln_dates": {
        "CVE-2020-2108": "2020-01-29T16:15:12",
        "CVE-2019-16560": "2019-12-17T15:15:18",
        "CVE-2019-16561": "2019-12-17T15:15:18",
        "CVE-2019-16559": "2019-12-17T15:15:18"
      },
      "scoring_model": "claude-3-opus-20240229",
      "type": "llm",
      "instruction_template_hash": "245ace12b6361954d0a2"
    },
    {
      "stats": {
        "fn": 3,
        "tp": 1,
        "fp": 3
      },
      "mapping": {
        "3": "CVE-2019-16561"
      },
      "vuln_dates": {
        "CVE-2020-2108": "2020-01-29T16:15:12",
        "CVE-2019-16560": "2019-12-17T15:15:18",
        "CVE-2019-16561": "2019-12-17T15:15:18",
        "CVE-2019-16559": "2019-12-17T15:15:18"
      },
      "scoring_model": "claude-3-5-sonnet-20240620",
      "type": "llm",
      "instruction_template_hash": "245ace12b6361954d0a2"
    }
  ],
  "instruction_template_hash": "10c0163db4740318a544",
  "version": "0.1.0"
}
