{
  "commit": "22e9b99015f488aa40018ddda1c261eb5b50b2d0",
  "repo_url": "https://github.com/jenkinsci/compuware-ispw-operations-plugin",
  "model": "gpt-4-turbo-2024-04-09",
  "chunk_hashes": [
    "27ef7bb64e9f3996882e"
  ],
  "responses": [
    {
      "content": "```yaml\nleads:\n  - headline: \"Insecure Authentication Vulnerability\"\n    analysis: |\n      The application uses hard-coded credentials for authentication purposes in multiple actions (e.g., in CreateAssignment, GenerateTasksInRelease). This poses a serious security risk as malicious users who gain access to the codebase can retrieve and misuse these credentials. Further investigation is required to determine how widespread the use of hard-coded credentials is and to which systems or data these credentials provide access.\n    cwe: CWE-798\n    function_names:\n      - \"createAction\"\n      - \"getIspwRequestBean\"\n    filenames:\n      - \"src/main/java/com/compuware/ispw/restapi/action/CreateAssignmentAction.java\"\n      - \"src/main/java/com/compuware/ispw/restapi/action/GenerateTasksInReleaseAction.java\"\n    classification: \"very promising\"\n\n  - headline: \"Improper Access Control leads to Unauthorized Information Exposure\"\n    analysis: |\n      The application does not properly implement access controls, allowing unauthorized users to access sensitive data via exposed methods and actions related to assignment and release information management. The lack of robust authentication and authorization checks could lead to data breaches, including exposure of sensitive project management details and operational parameters.\n    cwe: CWE-284\n    function_names:\n      - \"DeployReleaseAction\"\n      - \"GetReleaseInfoAction\"\n    filenames:\n      - \"src/main/java/com/compuware/ispw/restapi/action/DeployReleaseAction.java\"\n      - \"src/main/java/com/compuware/ispw/restapi/action/GetReleaseInfoAction.java\"\n    classification: \"very promising\"\n\n  - headline: \"Use of Insecure and Hardcoded Cryptographic Credentials\"\n    analysis: |\n      The system's source code includes hardcoded cryptographic credentials used in HTTP requests, potentially exposing all data transmitted or received via these requests to unauthorized interception or manipulation. This vulnerability not only poses a risk of data leakage but also compromises the integrity and confidentiality of the data sent in ISPW operations.\n    cwe: CWE-321\n    function_names:\n      - \"getIspwRequestBean\"\n      - \"create\"\n    filenames:\n      - \"src/main/java/com/compuware/ispw/restapi/action/RegenerateTasksInAssignmentAction.java\"\n      - \"src/main/java/com/compuware/ispw/restapi/util/RestApiUtils.java\"\n    classification: \"slightly promising\"\n\n  - headline: \"Exposure of Sensitive Information through Error Messages\"\n    analysis: |\n      System error messages (for example, those handled during HTTP requests or process execution) are generated in a way that includes sensitive information about the underlying systems. This could provide attackers with insights into the system that could aid in further attacks or exploitations.\n    cwe: CWE-209\n    function_names:\n      - \"executeRequest\"\n      - \"authAndRequest\"\n    filenames:\n      - \"src/main/java/com/compuware/ispw/restapi/HttpRequestExecution.java\"\n    classification: \"slightly promising\"\n\n  - headline: \"Poor Session Management Risk\"\n    analysis: |\n      The session tokens used in the WebhookTokenManager and during webhook operations are not managed securely. They are generated predictably and do not incorporate proper mechanisms to prevent attacks such as session fixation or session hijacking, potentially allowing unauthorized access to the session tokens.\n    cwe: CWE-384\n    function_names:\n      - \"RegisterWebhookExecution\"\n      - \"run\"\n    filenames:\n      - \"src/main/java/com/compuware/ispw/restapi/RegisterWebhookExecution.java\"\n    classification: \"very promising\"\n```",
      "date": "2024-06-12T18:08:20.730588",
      "usage": {
        "prompt_tokens": 43706,
        "completion_tokens": 744,
        "cost": 0.45938
      }
    }
  ],
  "leads": [
    {
      "headline": "Insecure Authentication Vulnerability",
      "analysis": "The application uses hard-coded credentials for authentication purposes in multiple actions (e.g., in CreateAssignment, GenerateTasksInRelease). This poses a serious security risk as malicious users who gain access to the codebase can retrieve and misuse these credentials. Further investigation is required to determine how widespread the use of hard-coded credentials is and to which systems or data these credentials provide access.\n",
      "classification": "very promising",
      "cwe": "CWE-798",
      "function_names": [
        "createAction",
        "getIspwRequestBean"
      ],
      "filenames": [
        "src/main/java/com/compuware/ispw/restapi/action/CreateAssignmentAction.java",
        "src/main/java/com/compuware/ispw/restapi/action/GenerateTasksInReleaseAction.java"
      ]
    },
    {
      "headline": "Improper Access Control leads to Unauthorized Information Exposure",
      "analysis": "The application does not properly implement access controls, allowing unauthorized users to access sensitive data via exposed methods and actions related to assignment and release information management. The lack of robust authentication and authorization checks could lead to data breaches, including exposure of sensitive project management details and operational parameters.\n",
      "classification": "very promising",
      "cwe": "CWE-284",
      "function_names": [
        "DeployReleaseAction",
        "GetReleaseInfoAction"
      ],
      "filenames": [
        "src/main/java/com/compuware/ispw/restapi/action/DeployReleaseAction.java",
        "src/main/java/com/compuware/ispw/restapi/action/GetReleaseInfoAction.java"
      ]
    },
    {
      "headline": "Use of Insecure and Hardcoded Cryptographic Credentials",
      "analysis": "The system's source code includes hardcoded cryptographic credentials used in HTTP requests, potentially exposing all data transmitted or received via these requests to unauthorized interception or manipulation. This vulnerability not only poses a risk of data leakage but also compromises the integrity and confidentiality of the data sent in ISPW operations.\n",
      "classification": "slightly promising",
      "cwe": "CWE-321",
      "function_names": [
        "getIspwRequestBean",
        "create"
      ],
      "filenames": [
        "src/main/java/com/compuware/ispw/restapi/action/RegenerateTasksInAssignmentAction.java",
        "src/main/java/com/compuware/ispw/restapi/util/RestApiUtils.java"
      ]
    },
    {
      "headline": "Exposure of Sensitive Information through Error Messages",
      "analysis": "System error messages (for example, those handled during HTTP requests or process execution) are generated in a way that includes sensitive information about the underlying systems. This could provide attackers with insights into the system that could aid in further attacks or exploitations.\n",
      "classification": "slightly promising",
      "cwe": "CWE-209",
      "function_names": [
        "executeRequest",
        "authAndRequest"
      ],
      "filenames": [
        "src/main/java/com/compuware/ispw/restapi/HttpRequestExecution.java"
      ]
    },
    {
      "headline": "Poor Session Management Risk",
      "analysis": "The session tokens used in the WebhookTokenManager and during webhook operations are not managed securely. They are generated predictably and do not incorporate proper mechanisms to prevent attacks such as session fixation or session hijacking, potentially allowing unauthorized access to the session tokens.\n",
      "classification": "very promising",
      "cwe": "CWE-384",
      "function_names": [
        "RegisterWebhookExecution",
        "run"
      ],
      "filenames": [
        "src/main/java/com/compuware/ispw/restapi/RegisterWebhookExecution.java"
      ]
    }
  ],
  "scores": [
    {
      "stats": {
        "fn": 1,
        "tp": 1,
        "fp": 2
      },
      "mapping": {
        "1": "CVE-2022-36898"
      },
      "vuln_dates": {
        "CVE-2022-36899": "2022-07-27T15:15:09",
        "CVE-2022-36898": "2022-07-27T15:15:09"
      },
      "scoring_model": "claude-3-opus-20240229",
      "type": "llm",
      "instruction_template_hash": "245ace12b6361954d0a2"
    },
    {
      "stats": {
        "fn": 2,
        "tp": 0,
        "fp": 3
      },
      "mapping": {},
      "vuln_dates": {
        "CVE-2022-36899": "2022-07-27T15:15:09",
        "CVE-2022-36898": "2022-07-27T15:15:09"
      },
      "scoring_model": "claude-3-5-sonnet-20240620",
      "type": "llm",
      "instruction_template_hash": "245ace12b6361954d0a2"
    }
  ],
  "instruction_template_hash": "10c0163db4740318a544",
  "version": "0.1.0"
}
