{
  "commit": "0fb08666020dbc455fe29dd7fd39e4e889036990",
  "repo_url": "https://github.com/cf-platform-eng/tile-generator",
  "model": "gpt-4o-2024-05-13",
  "chunk_hashes": [
    "26ef276cd94080109d12"
  ],
  "responses": [
    {
      "content": "```yaml\nleads:\n  - headline: \"Potential Command Injection in `build.sh`\"\n    analysis: |\n      The `build.sh` script takes a directory path as an argument and uses it in a `cp -r` command without proper validation or sanitization. \n      This allows for command injection if the `BUILD_DIR` variable contains malicious content.\n    cwe: CWE-78\n    function_names: []\n    filenames:\n      - sample/src/build.sh\n    classification: very promising\n\n  - headline: \"Potential Command Injection in `pcf-restore.sh`\"\n    analysis: |\n      In `pcf-restore.sh`, the `TILE_FILE` and `PRODUCT` variables are derived from user inputs and used in shell commands without validation or sanitization. \n      This can lead to command injection vulnerabilities if these variables contain malicious content.\n    cwe: CWE-78\n    function_names: []\n    filenames:\n      - ci/scripts/pcf-restore.sh\n    classification: very promising\n\n  - headline: \"Command Injection in Deployment Test Scripts\"\n    analysis: |\n      The deployment test scripts (e.g., `app2_deploymenttest.py`) call the `requests.get` function with URLs that include user-specified parameters. \n      If these parameters are not properly validated, an attacker could potentially conduct URL-based attacks or CSRF via specially crafted URLs.\n    cwe: CWE-918\n    function_names: []\n    filenames:\n      - ci/deployment-tests/app2_deploymenttest.py\n      - ci/deployment-tests/app4_deploymenttest.py\n      - ci/deployment-tests/app3_deploymenttest.py\n      - ci/deployment-tests/app1_deploymenttest.py\n    classification: slightly promising\n\n  - headline: \"Information Disclosure via Environment Variables\"\n    analysis: |\n      In `app.py` and other files, environment variables are used and potentially stored into logs or error messages. \n      This could disclose sensitive information if these variables include API keys or passwords when an error occurs.\n    cwe: CWE-209\n    function_names: []\n    filenames:\n      - sample/src/binary-app/binary-app.py\n      - sample/src/app/app.py\n      - ci/deployment-tests/app2_deploymenttest.py\n      - ci/deployment-tests/app4_deploymenttest.py\n      - ci/deployment-tests/app3_deploymenttest.py\n      - ci/deployment-tests/app1_deploymenttest.py\n    classification: very promising\n\n  - headline: \"Potential SQL Injection in `opsmgr.py`\"\n    analysis: |\n      In `opsmgr.py`, various functions use user-provided input directly in SQL queries without proper sanitization. \n      This can potentially lead to SQL injection vulnerabilities if an attacker can influence these inputs.\n    cwe: CWE-89\n    function_names: []\n    filenames:\n      - tile_generator/opsmgr.py\n    classification: very promising\n\n  - headline: \"Cleartext Transmission of Sensitive Information\"\n    analysis: |\n      The use of HTTP URLs instead of HTTPS in several files potentially exposes sensitive data to interception through man-in-the-middle attacks.\n    cwe: CWE-319\n    function_names: []\n    filenames:\n      - tile_generator/bosh.py\n      - tile_generator/util.py\n    classification: slightly promising\n\n  - headline: \"Insecure Dependence on External Systems\"\n    analysis: |\n      The scripts rely heavily on external systems (like Docker and various APIs) without validating the integrity and authenticity of the data received. \n      This could lead to various types of injection attacks or dependency confusion.\n    cwe: CWE-494\n    function_names: []\n    filenames:\n      - sample/src/build.sh\n      - ci/scripts/tile-build.sh\n      - ci/scripts/pcf-restore.sh\n      - ci/scripts/pcf-backup.sh\n      - ci/scripts/run-deploytile.sh\n      - ci/scripts/run-deploymenttests.sh\n      - ci/scripts/run-removetile.sh\n    classification: slightly promising\n\n  - headline: \"XML External Entity (XXE) Processing\"\n    analysis: |\n      There is no evidence of proper XML parsing protections against XXE in the `tile.py` and other files that process XML content. \n      This could lead to various security issues like SSRF, file disclosure, and DOS attacks.\n      Some of the cli commands in tile.py use raw XML data without any validations.\n    cwe: CWE-611\n    function_names: []\n    filenames:\n      - tile_generator/tile.py\n    classification: very promising\n```",
      "date": "2024-06-12T15:33:52.186394",
      "usage": {
        "prompt_tokens": 47574,
        "completion_tokens": 941,
        "cost": 0.251985
      }
    }
  ],
  "leads": [
    {
      "headline": "Potential Command Injection in build.sh",
      "analysis": "The build.sh script takes a directory path as an argument and uses it in a cp -r command without proper validation or sanitization. \nThis allows for command injection if the BUILD_DIR variable contains malicious content.\n",
      "classification": "very promising",
      "cwe": "CWE-78",
      "function_names": [],
      "filenames": [
        "sample/src/build.sh"
      ]
    },
    {
      "headline": "Potential Command Injection in pcf-restore.sh",
      "analysis": "In pcf-restore.sh, the TILE_FILE and PRODUCT variables are derived from user inputs and used in shell commands without validation or sanitization. \nThis can lead to command injection vulnerabilities if these variables contain malicious content.\n",
      "classification": "very promising",
      "cwe": "CWE-78",
      "function_names": [],
      "filenames": [
        "ci/scripts/pcf-restore.sh"
      ]
    },
    {
      "headline": "Command Injection in Deployment Test Scripts",
      "analysis": "The deployment test scripts (e.g., app2_deploymenttest.py) call the requests.get function with URLs that include user-specified parameters. \nIf these parameters are not properly validated, an attacker could potentially conduct URL-based attacks or CSRF via specially crafted URLs.\n",
      "classification": "slightly promising",
      "cwe": "CWE-918",
      "function_names": [],
      "filenames": [
        "ci/deployment-tests/app2_deploymenttest.py",
        "ci/deployment-tests/app4_deploymenttest.py",
        "ci/deployment-tests/app3_deploymenttest.py"
      ]
    },
    {
      "headline": "Information Disclosure via Environment Variables",
      "analysis": "In app.py and other files, environment variables are used and potentially stored into logs or error messages. \nThis could disclose sensitive information if these variables include API keys or passwords when an error occurs.\n",
      "classification": "very promising",
      "cwe": "CWE-209",
      "function_names": [],
      "filenames": [
        "sample/src/binary-app/binary-app.py",
        "sample/src/app/app.py",
        "ci/deployment-tests/app2_deploymenttest.py"
      ]
    },
    {
      "headline": "Potential SQL Injection in opsmgr.py",
      "analysis": "In opsmgr.py, various functions use user-provided input directly in SQL queries without proper sanitization. \nThis can potentially lead to SQL injection vulnerabilities if an attacker can influence these inputs.\n",
      "classification": "very promising",
      "cwe": "CWE-89",
      "function_names": [],
      "filenames": [
        "tile_generator/opsmgr.py"
      ]
    },
    {
      "headline": "Cleartext Transmission of Sensitive Information",
      "analysis": "The use of HTTP URLs instead of HTTPS in several files potentially exposes sensitive data to interception through man-in-the-middle attacks.\n",
      "classification": "slightly promising",
      "cwe": "CWE-319",
      "function_names": [],
      "filenames": [
        "tile_generator/bosh.py",
        "tile_generator/util.py"
      ]
    },
    {
      "headline": "Insecure Dependence on External Systems",
      "analysis": "The scripts rely heavily on external systems (like Docker and various APIs) without validating the integrity and authenticity of the data received. \nThis could lead to various types of injection attacks or dependency confusion.\n",
      "classification": "slightly promising",
      "cwe": "CWE-494",
      "function_names": [],
      "filenames": [
        "sample/src/build.sh",
        "ci/scripts/tile-build.sh",
        "ci/scripts/pcf-restore.sh"
      ]
    },
    {
      "headline": "XML External Entity (XXE) Processing",
      "analysis": "There is no evidence of proper XML parsing protections against XXE in the tile.py and other files that process XML content. \nThis could lead to various security issues like SSRF, file disclosure, and DOS attacks.\nSome of the cli commands in tile.py use raw XML data without any validations.\n",
      "classification": "very promising",
      "cwe": "CWE-611",
      "function_names": [],
      "filenames": [
        "tile_generator/tile.py"
      ]
    }
  ],
  "scores": [
    {
      "stats": {
        "fn": 1,
        "tp": 0,
        "fp": 5
      },
      "mapping": {},
      "vuln_dates": {
        "CVE-2017-4975": "2017-06-13T06:29:00"
      },
      "scoring_model": "claude-3-opus-20240229",
      "type": "llm",
      "instruction_template_hash": "245ace12b6361954d0a2"
    },
    {
      "stats": {
        "fn": 1,
        "tp": 0,
        "fp": 5
      },
      "mapping": {},
      "vuln_dates": {
        "CVE-2017-4975": "2017-06-13T06:29:00"
      },
      "scoring_model": "claude-3-5-sonnet-20240620",
      "type": "llm",
      "instruction_template_hash": "245ace12b6361954d0a2"
    }
  ],
  "instruction_template_hash": "10c0163db4740318a544",
  "version": "0.1.0"
}
