{
  "commit": "8b6241c1b81a99dac8ad636aa2b237b31628e82e",
  "repo_url": "https://github.com/fastify/session",
  "model": "gpt-4-turbo-2024-04-09",
  "chunk_hashes": [
    "7b137dc98b984b871e21"
  ],
  "responses": [
    {
      "content": "```yaml\nleads:\n  - headline: Session identifier is predictable\n    analysis: |\n      The session identifier is generated using a predictable method, which makes it susceptible to session prediction attacks. Predictable session IDs can allow an attacker to bypass authentication and authorization checks by guessing or calculating a valid session ID, potentially gaining unauthorized access to user sessions.\n    cwe: CWE-330\n    function_names:\n      - idGenerator\n    filenames:\n      - lib/fastifySession.js\n    classification: very promising\n\n  - headline: Use of insecure cookie configuration\n    analysis: |\n      The session cookies are configured without explicitly setting the HttpOnly and Secure flags in some cases, depending on certain conditions and configuration. This can expose the application to risks where the session cookie might be accessed by client-side scripts or intercepted over an insecure channel.\n    cwe: CWE-614\n    function_names:\n      - onRequest\n    filenames:\n      - lib/fastifySession.js\n    classification: slightly promising\n\n  - headline: Risk of session fixation through cookie reuse\n    analysis: |\n      The application appears to reuse session identifiers and does not consistently regenerate new identifiers when the authentication state changes (e.g., upon user login). This could allow an attacker to fixate a session ID beforehand and then lure a victim into authenticating with that session ID, gaining access to the authenticated session.\n    cwe: CWE-384\n    function_names:\n      - regenerate\n    filenames:\n      - lib/session.js\n    classification: slightly promising\n\n  - headline: Potential exposure of sensitive session data through server-side logs\n    analysis: |\n      The session data, including potentially sensitive information, is exposed to any server-side logs that capture unhandled exceptions or debug output, especially when error handling related to session operations (set, get, destroy) fails for various reasons, such as connection issues or serialization problems.\n    cwe: CWE-532\n    function_names:\n      - set\n      - get\n      - destroy\n    filenames:\n      - lib/store.js\n    classification: slightly promising\n\n  - headline: Insufficient transport security for session cookies\n    analysis: |\n      The application permits session cookies to be transmitted over non-HTTPS connections when not configured with the 'secure' flag explicitly as true. This can allow an attacker to intercept these cookies through Man-in-the-Middle (MitM) attacks, particularly in environments where HTTPS is not enforced.\n    cwe: CWE-319\n    function_names:\n      - onRequest\n    filenames:\n      - lib/fastifySession.js\n    classification: very promising\n\n  - headline: Weak cryptographic strength for session identifier\n    analysis: |\n      The session management utilizes a cryptographic function with potentially insufficient strength to generate session identifiers. This can lead to scenarios where session identifiers are more susceptible to being guessed or brute-forced by attackers.\n    cwe: CWE-326\n    function sentences:\n      - idGenerator\n    filenames:\n      - lib/fastifySession.js\n    classification: slightly promising\n```",
      "date": "2024-06-09T11:51:37.324544",
      "usage": {
        "prompt_tokens": 32344,
        "completion_tokens": 614,
        "cost": 0.34186
      }
    }
  ],
  "leads": [
    {
      "headline": "Session identifier is predictable",
      "analysis": "The session identifier is generated using a predictable method, which makes it susceptible to session prediction attacks. Predictable session IDs can allow an attacker to bypass authentication and authorization checks by guessing or calculating a valid session ID, potentially gaining unauthorized access to user sessions.\n",
      "classification": "very promising",
      "cwe": "CWE-330",
      "function_names": [
        "idGenerator"
      ],
      "filenames": [
        "lib/fastifySession.js"
      ]
    },
    {
      "headline": "Use of insecure cookie configuration",
      "analysis": "The session cookies are configured without explicitly setting the HttpOnly and Secure flags in some cases, depending on certain conditions and configuration. This can expose the application to risks where the session cookie might be accessed by client-side scripts or intercepted over an insecure channel.\n",
      "classification": "slightly promising",
      "cwe": "CWE-614",
      "function_names": [
        "onRequest"
      ],
      "filenames": [
        "lib/fastifySession.js"
      ]
    },
    {
      "headline": "Risk of session fixation through cookie reuse",
      "analysis": "The application appears to reuse session identifiers and does not consistently regenerate new identifiers when the authentication state changes (e.g., upon user login). This could allow an attacker to fixate a session ID beforehand and then lure a victim into authenticating with that session ID, gaining access to the authenticated session.\n",
      "classification": "slightly promising",
      "cwe": "CWE-384",
      "function_names": [
        "regenerate"
      ],
      "filenames": [
        "lib/session.js"
      ]
    },
    {
      "headline": "Potential exposure of sensitive session data through server-side logs",
      "analysis": "The session data, including potentially sensitive information, is exposed to any server-side logs that capture unhandled exceptions or debug output, especially when error handling related to session operations (set, get, destroy) fails for various reasons, such as connection issues or serialization problems.\n",
      "classification": "slightly promising",
      "cwe": "CWE-532",
      "function_names": [
        "set",
        "get",
        "destroy"
      ],
      "filenames": [
        "lib/store.js"
      ]
    },
    {
      "headline": "Insufficient transport security for session cookies",
      "analysis": "The application permits session cookies to be transmitted over non-HTTPS connections when not configured with the 'secure' flag explicitly as true. This can allow an attacker to intercept these cookies through Man-in-the-Middle (MitM) attacks, particularly in environments where HTTPS is not enforced.\n",
      "classification": "very promising",
      "cwe": "CWE-319",
      "function_names": [
        "onRequest"
      ],
      "filenames": [
        "lib/fastifySession.js"
      ]
    },
    {
      "headline": "Weak cryptographic strength for session identifier",
      "analysis": "The session management utilizes a cryptographic function with potentially insufficient strength to generate session identifiers. This can lead to scenarios where session identifiers are more susceptible to being guessed or brute-forced by attackers.\n",
      "classification": "slightly promising",
      "cwe": "CWE-326",
      "function_names": [],
      "filenames": [
        "lib/fastifySession.js"
      ]
    }
  ],
  "scores": [
    {
      "stats": {
        "fn": 1,
        "tp": 0,
        "fp": 2
      },
      "mapping": {},
      "vuln_dates": {
        "CVE-2024-35220": "2024-05-21T21:15:08"
      },
      "scoring_model": "gpt-4o-2024-05-13",
      "type": "llm",
      "instruction_template_hash": "8998f09cf57fca8a6e03"
    }
  ],
  "instruction_template_hash": "10c0163db4740318a544",
  "version": "0.1.0"
}
