{
  "commit": "95374e0fb62521b28d7de2272c8df5fc49813771",
  "repo_url": "https://github.com/psi-4ward/psitransfer",
  "model": "claude-3-sonnet-20240229",
  "chunk_hashes": [
    "e8aa0b6c44703039bf18"
  ],
  "responses": [
    {
      "content": "Here are the potential security vulnerabilities I identified in the codebase, represented as a YAML object of type LeadList:\n\n```yaml\nleads:\n  - headline: User-supplied input used in require() function\n    analysis: |\n      In the file `app.js`, the `require()` function is used with a user-supplied input to load plugins. If an attacker can control the `pluginName` parameter, they could potentially load and execute arbitrary code on the server.\n    cwe: CWE-98\n    function_names:\n      - \"\"\n    filenames:\n      - app.js\n    classification: very promising\n\n  - headline: Use of unsafe regular expression could lead to denial of service\n    analysis: |\n      In the file `lib/tusboy/tus-header-parser.js`, a regular expression is used to validate user-supplied input without any anchors or other safety measures. An attacker could potentially craft a malicious input that causes an Exponential Vulnerability in the regular expression, leading to excessive CPU and memory consumption, causing a denial of service condition.\n    cwe: CWE-1333\n    function_names:\n      - nonNegativeInteger\n    filenames:\n      - lib/tusboy/tus-header-parser.js\n    classification: very promising\n\n  - headline: Improper input validation\n    analysis: |\n      In multiple places throughout the codebase, user-supplied input is used without proper validation or sanitization. This could potentially lead to various injection attacks, such as path traversal, code injection, or other vulnerabilities, depending on how the input is used.\n    cwe: CWE-20\n    function_names:\n      - \"\"\n    filenames:\n      - app.js\n      - lib/db.js\n      - lib/endpoints.js\n      - lib/store.js\n      - lib/tusboy/handlers/post.js\n      - lib/tusboy/tus-header-parser.js\n    classification: very promising\n\n  - headline: Lack of authentication for critical functionality\n    analysis: |\n      The `/admin` endpoint in `lib/endpoints.js` does not enforce any authentication mechanism by default. An attacker could potentially access sensitive information or perform unauthorized actions by accessing this endpoint.\n    cwe: CWE-306\n    function_names:\n      - \"\"\n    filenames:\n      - lib/endpoints.js\n    classification: very promising\n\n  - headline: Use of hard-coded credentials\n    analysis: |\n      The `config.dev.js` file contains hard-coded credentials (`adminPass` and `uploadPass`). Hard-coded credentials can lead to unauthorized access if the credentials are compromised or if the application is deployed with the default credentials intact.\n    cwe: CWE-798\n    function_names:\n      - \"\"\n    filenames:\n      - config.dev.js\n    classification: very promising\n\n  - headline: Use of insecure cryptographic algorithm\n    analysis: |\n      The codebase uses the MD5 algorithm for generating session IDs and other purposes. MD5 is considered a broken algorithm and should not be used for cryptographic purposes due to its high susceptibility to collisions.\n    cwe: CWE-327\n    function_names:\n      - \"\"\n    filenames:\n      - app/src/Upload/store/upload.js\n      - lib/endpoints.js\n    classification: very promising\n\n  - headline: Potential path traversal vulnerability\n    analysis: |\n      In the `Store` class in `lib/store.js`, the `getFilename` method constructs file paths based on user-supplied input (`fid`). While there is a check to ensure the constructed path is within the `targetDir` directory, the check may be insufficient to prevent path traversal attacks if the input is not properly sanitized.\n    cwe: CWE-22\n    function_names:\n      - getFilename\n    filenames:\n      - lib/store.js\n    classification: slightly promising\n```\n\nNote that this analysis is based on a static code review and may not cover all potential vulnerabilities. Dynamic testing and further code review may be necessary to identify additional vulnerabilities or false positives.",
      "date": "2024-06-09T14:19:22.499243",
      "usage": {
        "prompt_tokens": 87774,
        "completion_tokens": 957,
        "cost": 0.277677
      }
    }
  ],
  "leads": [
    {
      "headline": "User-supplied input used in require() function",
      "analysis": "In the file app.js, the require() function is used with a user-supplied input to load plugins. If an attacker can control the pluginName parameter, they could potentially load and execute arbitrary code on the server.\n",
      "classification": "very promising",
      "cwe": "CWE-98",
      "function_names": [
        ""
      ],
      "filenames": [
        "app.js"
      ]
    },
    {
      "headline": "Use of unsafe regular expression could lead to denial of service",
      "analysis": "In the file lib/tusboy/tus-header-parser.js, a regular expression is used to validate user-supplied input without any anchors or other safety measures. An attacker could potentially craft a malicious input that causes an Exponential Vulnerability in the regular expression, leading to excessive CPU and memory consumption, causing a denial of service condition.\n",
      "classification": "very promising",
      "cwe": "CWE-1333",
      "function_names": [
        "nonNegativeInteger"
      ],
      "filenames": [
        "lib/tusboy/tus-header-parser.js"
      ]
    },
    {
      "headline": "Improper input validation",
      "analysis": "In multiple places throughout the codebase, user-supplied input is used without proper validation or sanitization. This could potentially lead to various injection attacks, such as path traversal, code injection, or other vulnerabilities, depending on how the input is used.\n",
      "classification": "very promising",
      "cwe": "CWE-20",
      "function_names": [
        ""
      ],
      "filenames": [
        "app.js",
        "lib/db.js",
        "lib/endpoints.js"
      ]
    },
    {
      "headline": "Lack of authentication for critical functionality",
      "analysis": "The /admin endpoint in lib/endpoints.js does not enforce any authentication mechanism by default. An attacker could potentially access sensitive information or perform unauthorized actions by accessing this endpoint.\n",
      "classification": "very promising",
      "cwe": "CWE-306",
      "function_names": [
        ""
      ],
      "filenames": [
        "lib/endpoints.js"
      ]
    },
    {
      "headline": "Use of hard-coded credentials",
      "analysis": "The config.dev.js file contains hard-coded credentials (adminPass and uploadPass). Hard-coded credentials can lead to unauthorized access if the credentials are compromised or if the application is deployed with the default credentials intact.\n",
      "classification": "very promising",
      "cwe": "CWE-798",
      "function_names": [
        ""
      ],
      "filenames": [
        "config.dev.js"
      ]
    },
    {
      "headline": "Use of insecure cryptographic algorithm",
      "analysis": "The codebase uses the MD5 algorithm for generating session IDs and other purposes. MD5 is considered a broken algorithm and should not be used for cryptographic purposes due to its high susceptibility to collisions.\n",
      "classification": "very promising",
      "cwe": "CWE-327",
      "function_names": [
        ""
      ],
      "filenames": [
        "app/src/Upload/store/upload.js",
        "lib/endpoints.js"
      ]
    },
    {
      "headline": "Potential path traversal vulnerability",
      "analysis": "In the Store class in lib/store.js, the getFilename method constructs file paths based on user-supplied input (fid). While there is a check to ensure the constructed path is within the targetDir directory, the check may be insufficient to prevent path traversal attacks if the input is not properly sanitized.\n",
      "classification": "slightly promising",
      "cwe": "CWE-22",
      "function_names": [
        "getFilename"
      ],
      "filenames": [
        "lib/store.js"
      ]
    }
  ],
  "scores": [
    {
      "stats": {
        "fn": 2,
        "tp": 0,
        "fp": 6
      },
      "mapping": {},
      "vuln_dates": {
        "CVE-2024-31454": "2024-04-09T18:15:10",
        "CVE-2024-31453": "2024-04-09T18:15:09"
      },
      "scoring_model": "gpt-4o-2024-05-13",
      "type": "llm",
      "instruction_template_hash": "8998f09cf57fca8a6e03"
    }
  ],
  "instruction_template_hash": "10c0163db4740318a544",
  "version": "0.1.0"
}
