{
  "commit": "4839574e4a63aaa65b0c1fdde176b7c700b3ae74",
  "repo_url": "https://github.com/snoyberg/keter",
  "model": "gpt-4-turbo-2024-04-09",
  "chunk_hashes": [
    "1c19dd32590c38df41d3"
  ],
  "responses": [
    {
      "content": "```yaml\nleads:\n  - headline: \"Improper Neutralization of Special Elements used in a Command in setup script\"\n    analysis: |\n      The setup-keter.sh script uses improperly neutralized user-controlled input by incorporating system variables into a shell command using bash. This script directly calls 'sudo mkdir' and 'sudo cp' with paths that include user input without filtering or validation.\n    cwe: CWE-78\n    function_names: []\n    filenames:\n      - /setup-keter.sh\n    classification: very promising\n\n  - headline: \"Unauthorized modification by symlink following in process-tracker.c\"\n    analysis: |\n      The C code in process tracker does not check if the 'fd' file descriptor points to a symbolic link anywhere within its path or check the legitimacy of the file it points to before writing to it. An attacker could use a symlink component within the expected path to force 'write' operations to unauthorized locations, leading to arbitrary file access or modification, such as altering system files or configurations.\n    cwe: CWE-59\n    function_names:\n      - launch_process_tracker\n      - track_process\n    filenames:\n      - /cbits/process-tracker.c\n    classification: very promising\n\n  - headline: \"Buffer Overflow in Process Tracker C Code\"\n    analysis: |\n      The function 'track_process' in cbits/process-tracker.c uses a fixed-size buffer 'buffer' into which data is written without bounds checking. This can allow attackers to cause a buffer overflow via crafted input, possibly allowing code execution or crashing the application.\n    cwe: CWE-120\n    function_names:\n      - track_process\n    filenames:\n      - /cbits/process-tracker.c\n    classification: very promising\n\n  - headline: \"Directory Traversal via Unchecked Filename in Log Files\"\n    analysis: |\n      The RotateLog component in Data/Conduit/LogFile.hs involves creating and writing to log files derived from untrusted input without sufficiently verifying that the filename doesn't contain directory traversal specifiers ('../'). An attacker can exploit this behavior to write logs to arbitrary locations on the filesystem.\n    cwe: CWE-22\n    function_names:\n      - openRotatingLog\n    filenames:\n      - /Data/Conduit/LogFile.hs\n    classification: very promising\n\n  - headline: \"Insecure File Permissions in Log Files Initialization\"\n    analysis: |\n      In Data/Conduit/LogFile.hs, the function 'openRotatingLog' uses 'setOwnerAndGroup' to change ownership of a new log file, which may inadvertently set insecure file permissions briefly before correcting them, leading to a window during which unauthorized users could access or modify log files.\n    cwe: CWE-732\n    function_names:\n      - openRotatingLog\n      - createTreeUID\n    filenames:\n      - /Data/Conduit/LogFile.hs\n    classification: very promising\n\n  - headline: \"Improper Privilege Management and Command Injection in setup-keter.sh\"\n    analysis: |\n      The shell script 'setup-keter.sh' performs critical system operations such as installing packages and managing service configurations as part of installation without adequate privilege level checks. Additionally, the script excutes commands constructed from external input, potentially leading to command injection.\n    cwe: CWE-269\n    function_names: []\n    filenames:\n      - /setup-keter.sh\n    classification: very promising\n\n  - headline: \"Use of Hard-coded Credentials in Database Configuration\"\n    analysis: |\n      In the script 'setup-keter.sh', database setup operations such as creating a user and database use hard-coded credentials. This practice could lead to unauthorized database access if these defaults are not changed post-deployment.\n    cwe: CWE-798\n    function_names: []\n    filenames:\n      - /setup-keter.sh\n    classification: very promising\n```",
      "date": "2024-07-08T08:37:30.611424",
      "usage": {
        "prompt_tokens": 43409,
        "completion_tokens": 789,
        "cost": 0.45776
      }
    }
  ],
  "leads": [
    {
      "headline": "Improper Neutralization of Special Elements used in a Command in setup script",
      "analysis": "The setup-keter.sh script uses improperly neutralized user-controlled input by incorporating system variables into a shell command using bash. This script directly calls 'sudo mkdir' and 'sudo cp' with paths that include user input without filtering or validation.\n",
      "classification": "very promising",
      "cwe": "CWE-78",
      "function_names": [],
      "filenames": [
        "/setup-keter.sh"
      ]
    },
    {
      "headline": "Unauthorized modification by symlink following in process-tracker.c",
      "analysis": "The C code in process tracker does not check if the 'fd' file descriptor points to a symbolic link anywhere within its path or check the legitimacy of the file it points to before writing to it. An attacker could use a symlink component within the expected path to force 'write' operations to unauthorized locations, leading to arbitrary file access or modification, such as altering system files or configurations.\n",
      "classification": "very promising",
      "cwe": "CWE-59",
      "function_names": [
        "launch_process_tracker",
        "track_process"
      ],
      "filenames": [
        "/cbits/process-tracker.c"
      ]
    },
    {
      "headline": "Buffer Overflow in Process Tracker C Code",
      "analysis": "The function 'track_process' in cbits/process-tracker.c uses a fixed-size buffer 'buffer' into which data is written without bounds checking. This can allow attackers to cause a buffer overflow via crafted input, possibly allowing code execution or crashing the application.\n",
      "classification": "very promising",
      "cwe": "CWE-120",
      "function_names": [
        "track_process"
      ],
      "filenames": [
        "/cbits/process-tracker.c"
      ]
    },
    {
      "headline": "Directory Traversal via Unchecked Filename in Log Files",
      "analysis": "The RotateLog component in Data/Conduit/LogFile.hs involves creating and writing to log files derived from untrusted input without sufficiently verifying that the filename doesn't contain directory traversal specifiers ('../'). An attacker can exploit this behavior to write logs to arbitrary locations on the filesystem.\n",
      "classification": "very promising",
      "cwe": "CWE-22",
      "function_names": [
        "openRotatingLog"
      ],
      "filenames": [
        "/Data/Conduit/LogFile.hs"
      ]
    },
    {
      "headline": "Insecure File Permissions in Log Files Initialization",
      "analysis": "In Data/Conduit/LogFile.hs, the function 'openRotatingLog' uses 'setOwnerAndGroup' to change ownership of a new log file, which may inadvertently set insecure file permissions briefly before correcting them, leading to a window during which unauthorized users could access or modify log files.\n",
      "classification": "very promising",
      "cwe": "CWE-732",
      "function_names": [
        "openRotatingLog",
        "createTreeUID"
      ],
      "filenames": [
        "/Data/Conduit/LogFile.hs"
      ]
    },
    {
      "headline": "Improper Privilege Management and Command Injection in setup-keter.sh",
      "analysis": "The shell script 'setup-keter.sh' performs critical system operations such as installing packages and managing service configurations as part of installation without adequate privilege level checks. Additionally, the script excutes commands constructed from external input, potentially leading to command injection.\n",
      "classification": "very promising",
      "cwe": "CWE-269",
      "function_names": [],
      "filenames": [
        "/setup-keter.sh"
      ]
    },
    {
      "headline": "Use of Hard-coded Credentials in Database Configuration",
      "analysis": "In the script 'setup-keter.sh', database setup operations such as creating a user and database use hard-coded credentials. This practice could lead to unauthorized database access if these defaults are not changed post-deployment.\n",
      "classification": "very promising",
      "cwe": "CWE-798",
      "function_names": [],
      "filenames": [
        "/setup-keter.sh"
      ]
    }
  ],
  "scores": [
    {
      "stats": {
        "fn": 1,
        "tp": 0,
        "fp": 7
      },
      "mapping": {},
      "vuln_dates": {
        "CVE-2022-4877": "2023-01-05T10:15:10"
      },
      "scoring_model": "claude-3-5-sonnet-20240620",
      "type": "llm",
      "instruction_template_hash": "245ace12b6361954d0a2"
    }
  ],
  "instruction_template_hash": "10c0163db4740318a544",
  "version": "0.1.0"
}
