{
  "commit": "072e81abd274b6c022faf1f2a1d87c8185cdb93c",
  "repo_url": "https://github.com/jenkinsci/github-branch-source-plugin",
  "model": "gpt-4o-2024-05-13",
  "chunk_hashes": [
    "0b28ec36c8fcb09bd160"
  ],
  "responses": [
    {
      "content": "```yaml\nleads:\n  - headline: Improper Input Validation in GitHubSCMNavigator\n    analysis: |\n      In the `GitHubSCMNavigator` class, the pattern used to filter repository names is taken directly from the user input.\n      There is no validation or sanitization applied to this pattern, which could lead to potential Regular Expression Denial of Service (ReDoS) attacks if a malicious user supplies a carefully crafted regex pattern.\n    cwe: CWE-20\n    function_names:\n      - setPattern\n    filenames:\n      - src/main/java/org/jenkinsci/plugins/github_branch_source/GitHubSCMNavigator.java\n    classification: very promising\n\n  - headline: Cleartext Storage of Sensitive Information in HttpsRepositoryUriResolver\n    analysis: |\n      The `HttpsRepositoryUriResolver` class stores the GitHub API URL in cleartext, which could be extracted by an attacker.\n      While this is a lesser vulnerability in comparison, it still poses a risk of sensitive information disclosure.\n    cwe: CWE-312\n    function_names:\n      - getRepositoryUri\n    filenames:\n      - src/main/java/org/jenkinsci/plugins/github_branch_source/HttpsRepositoryUriResolver.java\n    classification: slightly promising\n\n  - headline: Missing Validation of Repository URL in RepositoryUriResolver\n    analysis: |\n      In the class `RepositoryUriResolver`, the method `hostnameFromApiUri` does not perform robust validation to ensure that the input URL is well-formed.\n      This could lead to unintended behavior if an invalid URL is provided.\n    cwe: CWE-20\n    function_names:\n      - hostnameFromApiUri\n    filenames:\n      - src/main/java/org/jenkinsci/plugins/github_branch_source/RepositoryUriResolver.java\n    classification: very promising\n\n  - headline: Exposure of Sensitive Information to Unauthorized Actors in OriginGitHubSCMSource\n    analysis: |\n      The `OriginGitHubSCMSource` class logs potentially sensitive information such as API URLs and repository names using the `TaskListener`.\n      If the logs are accessible to unauthorized actors, this could result in information disclosure.\n    cwe: CWE-200\n    function_names:\n      - doRetrieve\n    filenames:\n      - src/main/java/org/jenkinsci/plugins/github_branch_source/OriginGitHubSCMSource.java\n    classification: slightly promising\n\n  - headline: Insecure Storage of Sensitive Information in AbstractGitHubSCMSource\n    analysis: |\n      The `AbstractGitHubSCMSource` class exposes potentially sensitive information such as API URIs and credentials IDs via getter methods.\n      This presents a risk if these methods are called by untrusted code or logged improperly.\n    cwe: CWE-922\n    function_names:\n      - getCredentialsId\n    filenames:\n      - src/main/java/org/jenkinsci/plugins/github_branch_source/AbstractGitHubSCMSource.java\n    classification: not promising\n\n  - headline: Insecure Defaults for Password Storage in Connector\n    analysis: |\n      The `Connector` class uses basic authentication (username and password) derived from `StandardUsernamePasswordCredentials` for connecting to GitHub.\n      Basic authentication credentials might be exposed if logged or if the authentication method is intercepted.\n    cwe: CWE-522\n    function_names:\n      - connect\n    filenames:\n      - src/main/java/org/jenkinsci/plugins/github_branch_source/Connector.java\n    classification: slightly promising\n```",
      "date": "2024-06-12T18:29:46.157656",
      "usage": {
        "prompt_tokens": 13375,
        "completion_tokens": 710,
        "cost": 0.077525
      }
    }
  ],
  "leads": [
    {
      "headline": "Improper Input Validation in GitHubSCMNavigator",
      "analysis": "In the GitHubSCMNavigator class, the pattern used to filter repository names is taken directly from the user input.\nThere is no validation or sanitization applied to this pattern, which could lead to potential Regular Expression Denial of Service (ReDoS) attacks if a malicious user supplies a carefully crafted regex pattern.\n",
      "classification": "very promising",
      "cwe": "CWE-20",
      "function_names": [
        "setPattern"
      ],
      "filenames": [
        "src/main/java/org/jenkinsci/plugins/github_branch_source/GitHubSCMNavigator.java"
      ]
    },
    {
      "headline": "Cleartext Storage of Sensitive Information in HttpsRepositoryUriResolver",
      "analysis": "The HttpsRepositoryUriResolver class stores the GitHub API URL in cleartext, which could be extracted by an attacker.\nWhile this is a lesser vulnerability in comparison, it still poses a risk of sensitive information disclosure.\n",
      "classification": "slightly promising",
      "cwe": "CWE-312",
      "function_names": [
        "getRepositoryUri"
      ],
      "filenames": [
        "src/main/java/org/jenkinsci/plugins/github_branch_source/HttpsRepositoryUriResolver.java"
      ]
    },
    {
      "headline": "Missing Validation of Repository URL in RepositoryUriResolver",
      "analysis": "In the class RepositoryUriResolver, the method hostnameFromApiUri does not perform robust validation to ensure that the input URL is well-formed.\nThis could lead to unintended behavior if an invalid URL is provided.\n",
      "classification": "very promising",
      "cwe": "CWE-20",
      "function_names": [
        "hostnameFromApiUri"
      ],
      "filenames": [
        "src/main/java/org/jenkinsci/plugins/github_branch_source/RepositoryUriResolver.java"
      ]
    },
    {
      "headline": "Exposure of Sensitive Information to Unauthorized Actors in OriginGitHubSCMSource",
      "analysis": "The OriginGitHubSCMSource class logs potentially sensitive information such as API URLs and repository names using the TaskListener.\nIf the logs are accessible to unauthorized actors, this could result in information disclosure.\n",
      "classification": "slightly promising",
      "cwe": "CWE-200",
      "function_names": [
        "doRetrieve"
      ],
      "filenames": [
        "src/main/java/org/jenkinsci/plugins/github_branch_source/OriginGitHubSCMSource.java"
      ]
    },
    {
      "headline": "Insecure Storage of Sensitive Information in AbstractGitHubSCMSource",
      "analysis": "The AbstractGitHubSCMSource class exposes potentially sensitive information such as API URIs and credentials IDs via getter methods.\nThis presents a risk if these methods are called by untrusted code or logged improperly.\n",
      "classification": "not promising",
      "cwe": "CWE-922",
      "function_names": [
        "getCredentialsId"
      ],
      "filenames": [
        "src/main/java/org/jenkinsci/plugins/github_branch_source/AbstractGitHubSCMSource.java"
      ]
    },
    {
      "headline": "Insecure Defaults for Password Storage in Connector",
      "analysis": "The Connector class uses basic authentication (username and password) derived from StandardUsernamePasswordCredentials for connecting to GitHub.\nBasic authentication credentials might be exposed if logged or if the authentication method is intercepted.\n",
      "classification": "slightly promising",
      "cwe": "CWE-522",
      "function_names": [
        "connect"
      ],
      "filenames": [
        "src/main/java/org/jenkinsci/plugins/github_branch_source/Connector.java"
      ]
    }
  ],
  "scores": [
    {
      "stats": {
        "fn": 3,
        "tp": 0,
        "fp": 2
      },
      "mapping": {},
      "vuln_dates": {
        "CVE-2017-1000091": "2017-10-05T01:29:03",
        "CVE-2017-1000087": "2017-10-05T01:29:03",
        "CVE-2018-1000185": "2018-06-05T20:29:00"
      },
      "scoring_model": "claude-3-opus-20240229",
      "type": "llm",
      "instruction_template_hash": "245ace12b6361954d0a2"
    }
  ],
  "instruction_template_hash": "10c0163db4740318a544",
  "version": "0.1.0"
}
