{
  "commit": "95374e0fb62521b28d7de2272c8df5fc49813771",
  "repo_url": "https://github.com/psi-4ward/psitransfer",
  "model": "gpt-4o-2024-05-13",
  "chunk_hashes": [
    "e8aa0b6c44703039bf18"
  ],
  "responses": [
    {
      "content": "```yaml\nleads:\n  - headline: \"Hard-coded admin password\"\n    analysis: |\n      The `config.dev.js` file contains a hard-coded admin password \"admin\" in the property `adminPass`. Hard-coded credentials can be easily discovered and exploited by malicious actors, leading to unauthorized access and control over the application.\n    cwe: CWE-798\n    function_names: []\n    filenames:\n      - config.dev.js\n    classification: very promising\n  \n  - headline: \"Default adminPass configuration could allow unauthorized access\"\n    analysis: |\n      In `config.js`, `adminPass` is set to `false` by default, potentially disabling the /admin page. If this configuration is used in a production environment without being set, it may lead to unauthorized access, especially if not properly handled.\n    cwe: CWE-306\n    function_names: []\n    filenames:\n      - config.js\n    classification: slightly promising\n\n  - headline: \"Weak password for uploading files\"\n    analysis: |\n      The `config.dev.js` file uses the property `uploadPass` set to `false`. If not properly configured in the production environment, this could lead to unauthorized file uploads, opening up the system to potential abuse.\n    cwe: CWE-521\n    function_names: []\n    filenames:\n      - config.dev.js\n    classification: slightly promising\n\n  - headline: \"Potential Exposure of Sensitive Information to an Unauthorized Actor\"\n    analysis: |\n      In `app.js`, the system prints shutdown messages in plain text to the console which may inadvertently leak operational information. This logging behavior can be leveraged by attackers to gain insights into the system's operation and any potential vulnerabilities.\n    cwe: CWE-209\n    function_names: \n      - shutdown\n    filenames:\n      - app.js\n    classification: slightly promising\n\n  - headline: \"Potential Open Redirect Vulnerability\"\n    analysis: |\n      In `endpoints.js`, the application uses a configuration property `forceHttps` to redirect HTTP to HTTPS. If this property is not set or misconfigured, it may result in improper redirects, which attackers could exploit to facilitate phishing or man-in-the-middle attacks.\n    cwe: CWE-601\n    function_names: []\n    filenames:\n      - lib/endpoints.js\n    classification: very promising\n\n  - headline: \"Missing Input Validation in File Upload\"\n    analysis: |\n      In `lib/endpoints.js`, the file upload functionality lacks thorough input validation. The metadata fields such as `sid`, `retention`, `password`, and `name` are not validated for malicious inputs, which could lead to injection attacks or other vulnerabilities.\n    cwe: CWE-20\n    function_names: \n      - (inline validation within middleware)\n    filenames:\n      - lib/endpoints.js\n    classification: very promising\n\n  - headline: \"Unrestricted File Upload\"\n    analysis: |\n      The application uses `tusboy` for file uploads, with a basic implementation that lacks restrictions on file types and extensions. This can allow attackers to upload malicious files, which may lead to executing arbitrary code or other malicious activities.\n    cwe: CWE-434\n    function_names: \n      - (inline file upload handling)\n    filenames:\n      - lib/tusboy/index.js\n    classification: very promising\n\n  - headline: \"Server-Side Request Forgery (SSRF) Potential\"\n    analysis: |\n      The system fetches resources and makes HTTP requests based on user input without sufficient validation of the input URLs in `lib/common/util.js`. This can be exploited to initiate requests to internal services or conduct scans, leading to SSRF vulnerabilities.\n    cwe: CWE-918\n    function_names: \n      - httpGet\n      - httpPost\n    filenames:\n      - app/src/common/util.js\n    classification: slightly promising\n\n  - headline: \"Code Injection Vulnerability\"\n    analysis: |\n      In `app/webpack.config.js`, user-controlled input might influence the `execSync` function used for fetching the commit SHA ID. Without appropriate sanitization, this could lead to code execution and potential compromise of the server.\n    cwe: CWE-94\n    function_names: \n      - (inline command execution)\n    filenames:\n      - app/webpack.config.js\n    classification: very promising\n\n  - headline: \"Exposure of Sensitive Data in Error Messages\"\n    analysis: |\n      Error messages throughout the application provide detailed information about the underlying system, which may include revealing sensitive data to unauthorized users. This can assist attackers in crafting more sophisticated attacks.\n    cwe: CWE-209\n    function_names: \n      - (errors in different endpoints)\n    filenames: []\n    classification: slightly promising\n```",
      "date": "2024-06-09T14:19:19.362418",
      "usage": {
        "prompt_tokens": 68017,
        "completion_tokens": 968,
        "cost": 0.354605
      }
    }
  ],
  "leads": [
    {
      "headline": "Hard-coded admin password",
      "analysis": "The config.dev.js file contains a hard-coded admin password \"admin\" in the property adminPass. Hard-coded credentials can be easily discovered and exploited by malicious actors, leading to unauthorized access and control over the application.\n",
      "classification": "very promising",
      "cwe": "CWE-798",
      "function_names": [],
      "filenames": [
        "config.dev.js"
      ]
    },
    {
      "headline": "Default adminPass configuration could allow unauthorized access",
      "analysis": "In config.js, adminPass is set to false by default, potentially disabling the /admin page. If this configuration is used in a production environment without being set, it may lead to unauthorized access, especially if not properly handled.\n",
      "classification": "slightly promising",
      "cwe": "CWE-306",
      "function_names": [],
      "filenames": [
        "config.js"
      ]
    },
    {
      "headline": "Weak password for uploading files",
      "analysis": "The config.dev.js file uses the property uploadPass set to false. If not properly configured in the production environment, this could lead to unauthorized file uploads, opening up the system to potential abuse.\n",
      "classification": "slightly promising",
      "cwe": "CWE-521",
      "function_names": [],
      "filenames": [
        "config.dev.js"
      ]
    },
    {
      "headline": "Potential Exposure of Sensitive Information to an Unauthorized Actor",
      "analysis": "In app.js, the system prints shutdown messages in plain text to the console which may inadvertently leak operational information. This logging behavior can be leveraged by attackers to gain insights into the system's operation and any potential vulnerabilities.\n",
      "classification": "slightly promising",
      "cwe": "CWE-209",
      "function_names": [
        "shutdown"
      ],
      "filenames": [
        "app.js"
      ]
    },
    {
      "headline": "Potential Open Redirect Vulnerability",
      "analysis": "In endpoints.js, the application uses a configuration property forceHttps to redirect HTTP to HTTPS. If this property is not set or misconfigured, it may result in improper redirects, which attackers could exploit to facilitate phishing or man-in-the-middle attacks.\n",
      "classification": "very promising",
      "cwe": "CWE-601",
      "function_names": [],
      "filenames": [
        "lib/endpoints.js"
      ]
    },
    {
      "headline": "Missing Input Validation in File Upload",
      "analysis": "In lib/endpoints.js, the file upload functionality lacks thorough input validation. The metadata fields such as sid, retention, password, and name are not validated for malicious inputs, which could lead to injection attacks or other vulnerabilities.\n",
      "classification": "very promising",
      "cwe": "CWE-20",
      "function_names": [
        "(inline validation within middleware)"
      ],
      "filenames": [
        "lib/endpoints.js"
      ]
    },
    {
      "headline": "Unrestricted File Upload",
      "analysis": "The application uses tusboy for file uploads, with a basic implementation that lacks restrictions on file types and extensions. This can allow attackers to upload malicious files, which may lead to executing arbitrary code or other malicious activities.\n",
      "classification": "very promising",
      "cwe": "CWE-434",
      "function_names": [
        "(inline file upload handling)"
      ],
      "filenames": [
        "lib/tusboy/index.js"
      ]
    },
    {
      "headline": "Server-Side Request Forgery (SSRF) Potential",
      "analysis": "The system fetches resources and makes HTTP requests based on user input without sufficient validation of the input URLs in lib/common/util.js. This can be exploited to initiate requests to internal services or conduct scans, leading to SSRF vulnerabilities.\n",
      "classification": "slightly promising",
      "cwe": "CWE-918",
      "function_names": [
        "httpGet",
        "httpPost"
      ],
      "filenames": [
        "app/src/common/util.js"
      ]
    },
    {
      "headline": "Code Injection Vulnerability",
      "analysis": "In app/webpack.config.js, user-controlled input might influence the execSync function used for fetching the commit SHA ID. Without appropriate sanitization, this could lead to code execution and potential compromise of the server.\n",
      "classification": "very promising",
      "cwe": "CWE-94",
      "function_names": [
        "(inline command execution)"
      ],
      "filenames": [
        "app/webpack.config.js"
      ]
    },
    {
      "headline": "Exposure of Sensitive Data in Error Messages",
      "analysis": "Error messages throughout the application provide detailed information about the underlying system, which may include revealing sensitive data to unauthorized users. This can assist attackers in crafting more sophisticated attacks.\n",
      "classification": "slightly promising",
      "cwe": "CWE-209",
      "function_names": [
        "(errors in different endpoints)"
      ],
      "filenames": []
    }
  ],
  "scores": [
    {
      "stats": {
        "fn": 2,
        "tp": 0,
        "fp": 5
      },
      "mapping": {},
      "vuln_dates": {
        "CVE-2024-31454": "2024-04-09T18:15:10",
        "CVE-2024-31453": "2024-04-09T18:15:09"
      },
      "scoring_model": "gpt-4o-2024-05-13",
      "type": "llm",
      "instruction_template_hash": "8998f09cf57fca8a6e03"
    },
    {
      "stats": {
        "fn": 1,
        "tp": 1,
        "fp": 4
      },
      "mapping": {
        "3": "CVE-2024-31453"
      },
      "vuln_dates": {
        "CVE-2024-31454": "2024-04-09T18:15:10",
        "CVE-2024-31453": "2024-04-09T18:15:09"
      },
      "scoring_model": "claude-3-opus-20240229",
      "type": "llm",
      "instruction_template_hash": "245ace12b6361954d0a2"
    }
  ],
  "instruction_template_hash": "10c0163db4740318a544",
  "version": "0.1.0"
}
