{
  "commit": "3f09a47887e25c5056a4e434d7558d4542bf049b",
  "repo_url": "https://github.com/dcit/perl-crypt-jwt",
  "model": "gpt-4-turbo-2024-04-09",
  "chunk_hashes": [
    "9acc2d1641def2752823"
  ],
  "responses": [
    {
      "content": "```yaml\nleads:\n  - headline: \"Insecure Randomness in Cryptographic Functions\"\n    analysis: |\n      The codebase utilizes functions like `random_bytes` in `lib/Crypt/JWT.pm` to generate cryptographic keys, which are essential for securing JWT tokens. However, despite promising a level of randomness, randomness in cryptographic functions can potentially be insufficient or predictable, particularly if not adequately seeded.\n    cwe: CWE-330\n    function_names:\n      - _encrypt_jwe_cek\n      - _decrypt_jwe_cek\n    filenames:\n      - lib/Crypt/JWT.pm\n    classification: \"very promising\"  \n\n  - headline: \"Insufficient Key Size for PBKDF2\"\n    analysis: |\n      In the `lib/Crypt/KeyWrap.pm` file, the PBKDF2 key-wrapping implementation (`pbes2_key_wrap` and `pbes2_key_unwrap`) uses variable iteration counts (`p2c`) and salt sizes (`p2s`). Lower iterations counts and smaller salt sizes can make the key derivation process less secure, increasing the vulnerability to brute-force attacks.\n    cwe: CWE-916\n    function_names:\n      - pbes2_key_wrap\n      - pbes2_key_unwrap\n    filenames:\n      - lib/Crypt/KeyWrap.pm\n    classification: \"slightly promising\"\n\n  - headline: \"RSA Key Exfiltration via Side-Channel Analysis\"\n    analysis: |\n      The implementation of RSA key operations (`rsa_key_wrap` and `rsa_key_unwrap`) in `lib/Crypt/KeyWrap.pm` does not explicitly defend against side-channel attacks such as timing analysis, which could allow an attacker to deduce the RSA private key using statistical analysis of operation times.\n    cwe: CWE-200\n    function_names:\n      - rsa_key_wrap\n      - rsa_key_unwrap\n    filenames:\n      - lib/Crypt/KeyWrap.pm\n    classification: \"very promising\"\n\n  - headline: \"Potential Lack of Entropy in RSA Key Generation\"\n    analysis: |\n      The RSA key generation mechanism used in the codebase (`rsa_key_wrap`, `rsa_key_unwrap`) assumes the security of the underlying random number generator. There is no evidence in the provided code fragments of using a high-quality entropy source. This could result in predictable or weak cryptographic keys.\n    cwe: CWE-331\n    function_names:\n      - rsa_key_wrap\n      - rsa_key_unwrap\n    filenames:\n      - lib/Crypt/KeyWrap.pm\n    classification: \"slightly promising\"  \n\n  - headline: \"Hardcoded Cryptographic Keys\"\n    analysis: |\n      The observed approach to handling cryptographic keys within various functions of the JWT and KeyWrap modules (e.g., `decode_jwt`, `ecdhaes_key_unwrap`) suggests potential hardcoded or inadequately protected keys which might lead to unauthorized actions or data disclosure if exposed or mishandled.\n    cwe: CWE-321\n    function_names:\n      - decode_jwt\n      - ecdhaes_key_unwrap\n    filenames:\n      - lib/Crypt/JWT.pm\n      - lib/Crypt/KeyWrap.pm\n    classification: \"slightly promising\"\n```",
      "date": "2024-06-14T13:15:53.999780",
      "usage": {
        "prompt_tokens": 96165,
        "completion_tokens": 665,
        "cost": 0.9816
      }
    }
  ],
  "leads": [
    {
      "headline": "Insecure Randomness in Cryptographic Functions",
      "analysis": "The codebase utilizes functions like random_bytes in lib/Crypt/JWT.pm to generate cryptographic keys, which are essential for securing JWT tokens. However, despite promising a level of randomness, randomness in cryptographic functions can potentially be insufficient or predictable, particularly if not adequately seeded.\n",
      "classification": "very promising",
      "cwe": "CWE-330",
      "function_names": [
        "_encrypt_jwe_cek",
        "_decrypt_jwe_cek"
      ],
      "filenames": [
        "lib/Crypt/JWT.pm"
      ]
    },
    {
      "headline": "Insufficient Key Size for PBKDF2",
      "analysis": "In the lib/Crypt/KeyWrap.pm file, the PBKDF2 key-wrapping implementation (pbes2_key_wrap and pbes2_key_unwrap) uses variable iteration counts (p2c) and salt sizes (p2s). Lower iterations counts and smaller salt sizes can make the key derivation process less secure, increasing the vulnerability to brute-force attacks.\n",
      "classification": "slightly promising",
      "cwe": "CWE-916",
      "function_names": [
        "pbes2_key_wrap",
        "pbes2_key_unwrap"
      ],
      "filenames": [
        "lib/Crypt/KeyWrap.pm"
      ]
    },
    {
      "headline": "RSA Key Exfiltration via Side-Channel Analysis",
      "analysis": "The implementation of RSA key operations (rsa_key_wrap and rsa_key_unwrap) in lib/Crypt/KeyWrap.pm does not explicitly defend against side-channel attacks such as timing analysis, which could allow an attacker to deduce the RSA private key using statistical analysis of operation times.\n",
      "classification": "very promising",
      "cwe": "CWE-200",
      "function_names": [
        "rsa_key_wrap",
        "rsa_key_unwrap"
      ],
      "filenames": [
        "lib/Crypt/KeyWrap.pm"
      ]
    },
    {
      "headline": "Potential Lack of Entropy in RSA Key Generation",
      "analysis": "The RSA key generation mechanism used in the codebase (rsa_key_wrap, rsa_key_unwrap) assumes the security of the underlying random number generator. There is no evidence in the provided code fragments of using a high-quality entropy source. This could result in predictable or weak cryptographic keys.\n",
      "classification": "slightly promising",
      "cwe": "CWE-331",
      "function_names": [
        "rsa_key_wrap",
        "rsa_key_unwrap"
      ],
      "filenames": [
        "lib/Crypt/KeyWrap.pm"
      ]
    },
    {
      "headline": "Hardcoded Cryptographic Keys",
      "analysis": "The observed approach to handling cryptographic keys within various functions of the JWT and KeyWrap modules (e.g., decode_jwt, ecdhaes_key_unwrap) suggests potential hardcoded or inadequately protected keys which might lead to unauthorized actions or data disclosure if exposed or mishandled.\n",
      "classification": "slightly promising",
      "cwe": "CWE-321",
      "function_names": [
        "decode_jwt",
        "ecdhaes_key_unwrap"
      ],
      "filenames": [
        "lib/Crypt/JWT.pm",
        "lib/Crypt/KeyWrap.pm"
      ]
    }
  ],
  "scores": [
    {
      "stats": {
        "fn": 1,
        "tp": 0,
        "fp": 2
      },
      "mapping": {},
      "vuln_dates": {
        "CVE-2019-1010263": "2019-07-17T21:15:10"
      },
      "scoring_model": "claude-3-opus-20240229",
      "type": "llm",
      "instruction_template_hash": "245ace12b6361954d0a2"
    }
  ],
  "instruction_template_hash": "10c0163db4740318a544",
  "version": "0.1.0"
}
