{
  "commit": "26852ff123b07ebde3cc78ee0e3f0b399bffd293",
  "repo_url": "https://github.com/jenkinsci/gradle-plugin",
  "model": "gpt-4-turbo-2024-04-09",
  "chunk_hashes": [
    "d1cb3bc34e3ecd7706c6"
  ],
  "responses": [
    {
      "content": "```yaml\nleads:\n  - headline: \"Improper Neutralization of Formula Elements in CSV File\"\n    analysis: |\n      The application includes functionality to inject Maven and Gradle configurations as user-specified or system-provided input. However, it fails to properly sanitize this input to prevent the insertion of special elements like formulas in CSV files. This could potentially lead to formula injection attacks where malicious formulas could be executed on the user's machine when the CSV file is opened in a spreadsheet application.\n    cwe: CWE-1236\n    function_names:\n      - \"handleToken\"\n      - \"handleUpload\"\n    filenames:\n      - \"/src/main/java/hudson/plugins/gradle/Gradle.java\"\n      - \"/src/main/java/hudson/plugins/gradle/injection/GradleEnterpriseInjector.java\"\n    classification: \"very promising\"\n\n  - headline: \"Weak Password Requirements and Missing Encryption of Sensitive Data\"\n    analysis: |\n      The system lacks robust password policies and does not enforce strong password requirements (CWE-521). Furthermore, sensitive data, such as access keys for Gradle Enterprise, are transmitted over the network without proper encryption (CWE-319). These vulnerabilities expose the system to potential unauthorized access and data breaches.\n    cwe: CWE-521\n    function_names:\n      - \"doCheckAccessKey\"\n    filenames:\n      - \"/src/main/java/hudson/plugins/gradle/injection/InjectionConfig.java\"\n    classification: \"slightly promising\"\n\n  - headline: \"Improper Handling of Exceptional Conditions in Build Agents\"\n    analysis: |\n      The Gradle and Maven build processes managed by Jenkins do not properly handle errors or exceptional conditions that may occur during the build. Failures in the integration components might not halt the process or might fail silently, leading to incomplete or erroneous build results without adequate notice to the users or system administrators.\n    cwe: CWE-755\n    function_names:\n      - \"doGetScanDetail\"\n      - \"processLogLine\"\n    filenames:\n      - \"/src/main/java/hudson/plugins/gradle/enriched/ScanDetailService.java\"\n      - \"/src/main/java/hudson/plugins/gradle/injection/GradleEnterpriseExceptionLogProcessor.java\"\n    classification: \"very promising\"\n\n  - headline: \"Use of Hard-coded Credentials in Script Handling\"\n    analysis: |\n      The script for handling Gradle tasks within Jenkins jobs contains hard-coded credentials, which can lead to unauthorized access if these credentials are exposed or discovered. This represents a severe security risk as attackers could gain access to sensitive parts of the system or perform unauthorized actions.\n    cwe: CWE-798\n    function_names:\n      - \"GradleConsoleAnnotator\"\n    filenames:\n      - \"/src/main/java/hudson/plugins/gradle/GradleConsoleAnnotator.java\"\n    classification: \"slightly promising\"\n```",
      "date": "2024-06-12T18:34:36.188125",
      "usage": {
        "prompt_tokens": 49532,
        "completion_tokens": 588,
        "cost": 0.51296
      }
    }
  ],
  "leads": [
    {
      "headline": "Improper Neutralization of Formula Elements in CSV File",
      "analysis": "The application includes functionality to inject Maven and Gradle configurations as user-specified or system-provided input. However, it fails to properly sanitize this input to prevent the insertion of special elements like formulas in CSV files. This could potentially lead to formula injection attacks where malicious formulas could be executed on the user's machine when the CSV file is opened in a spreadsheet application.\n",
      "classification": "very promising",
      "cwe": "CWE-1236",
      "function_names": [
        "handleToken",
        "handleUpload"
      ],
      "filenames": [
        "/src/main/java/hudson/plugins/gradle/Gradle.java",
        "/src/main/java/hudson/plugins/gradle/injection/GradleEnterpriseInjector.java"
      ]
    },
    {
      "headline": "Weak Password Requirements and Missing Encryption of Sensitive Data",
      "analysis": "The system lacks robust password policies and does not enforce strong password requirements (CWE-521). Furthermore, sensitive data, such as access keys for Gradle Enterprise, are transmitted over the network without proper encryption (CWE-319). These vulnerabilities expose the system to potential unauthorized access and data breaches.\n",
      "classification": "slightly promising",
      "cwe": "CWE-521",
      "function_names": [
        "doCheckAccessKey"
      ],
      "filenames": [
        "/src/main/java/hudson/plugins/gradle/injection/InjectionConfig.java"
      ]
    },
    {
      "headline": "Improper Handling of Exceptional Conditions in Build Agents",
      "analysis": "The Gradle and Maven build processes managed by Jenkins do not properly handle errors or exceptional conditions that may occur during the build. Failures in the integration components might not halt the process or might fail silently, leading to incomplete or erroneous build results without adequate notice to the users or system administrators.\n",
      "classification": "very promising",
      "cwe": "CWE-755",
      "function_names": [
        "doGetScanDetail",
        "processLogLine"
      ],
      "filenames": [
        "/src/main/java/hudson/plugins/gradle/enriched/ScanDetailService.java",
        "/src/main/java/hudson/plugins/gradle/injection/GradleEnterpriseExceptionLogProcessor.java"
      ]
    },
    {
      "headline": "Use of Hard-coded Credentials in Script Handling",
      "analysis": "The script for handling Gradle tasks within Jenkins jobs contains hard-coded credentials, which can lead to unauthorized access if these credentials are exposed or discovered. This represents a severe security risk as attackers could gain access to sensitive parts of the system or perform unauthorized actions.\n",
      "classification": "slightly promising",
      "cwe": "CWE-798",
      "function_names": [
        "GradleConsoleAnnotator"
      ],
      "filenames": [
        "/src/main/java/hudson/plugins/gradle/GradleConsoleAnnotator.java"
      ]
    }
  ],
  "scores": [
    {
      "stats": {
        "fn": 1,
        "tp": 0,
        "fp": 2
      },
      "mapping": {},
      "vuln_dates": {
        "CVE-2023-39152": "2023-07-26T14:15:10"
      },
      "scoring_model": "claude-3-opus-20240229",
      "type": "llm",
      "instruction_template_hash": "245ace12b6361954d0a2"
    }
  ],
  "instruction_template_hash": "10c0163db4740318a544",
  "version": "0.1.0"
}
