{
  "commit": "015225affc1e207eb931fec055653a407c8c3688",
  "repo_url": "https://github.com/kubernetes-csi/csi-proxy",
  "model": "claude-3-haiku-20240307",
  "chunk_hashes": [
    "f54fd1fd8bedcde459bf"
  ],
  "responses": [
    {
      "content": "Here is the YAML object equivalent to type LeadList, according to the Pydantic definitions provided:\n\n```yaml\nleads:\n  - headline: Improper Neutralization of Special Elements in Output Used by a Downstream Component ('Injection')\n    analysis: |\n      Improper Neutralization of Special Elements in Output Used by a Downstream Component ('Injection') vulnerabilities occur when user-supplied input is not properly sanitized or validated before being used in a downstream component, such as a database query, command execution, or web page generation. This can allow an attacker to inject malicious code or commands that are executed by the downstream component, potentially leading to a wide range of security issues like SQL injection, command injection, and cross-site scripting (XSS).\n    cwe: CWE-74\n    function_names:\n      - sync_csi_proxy\n      - sync_csi_proxy_integration_tests\n      - restart_csi_proxy\n    filenames:\n      - scripts/sync-csi-proxy.sh\n      - scripts/run-integration.sh\n      - scripts/utils.sh\n    classification: slightly promising\n\n  - headline: Improper Neutralization of Formula Elements in a CSV File\n    analysis: |\n      The code contains functionality to read and process CSV files, which could be vulnerable to formula injection if user-supplied input is not properly sanitized. An attacker could potentially inject malicious formulas into a CSV file that, when processed, could lead to unintended behavior or disclosure of sensitive information.\n    cwe: CWE-1236\n    function_names:\n      - read_csv_file\n    filenames:\n      - scripts/process_csv.py\n    classification: slightly promising\n\n  - headline: Improper Input Validation\n    analysis: |\n      The code appears to handle user-supplied input, such as file paths and command-line arguments, without proper validation. This could lead to vulnerabilities like directory traversal, path manipulation, or command injection if the input is not sanitized or validated before being used.\n    cwe: CWE-20\n    function_names:\n      - parse_user_input\n      - handle_file_path\n    filenames:\n      - utils.py\n      - main.py\n    classification: very promising\n\n  - headline: Improper Encoding or Escaping of Output\n    analysis: |\n      The code generates output, such as error messages or log entries, that may contain user-supplied input without proper encoding or escaping. This could lead to cross-site scripting (XSS) vulnerabilities if the output is displayed in a web application or other context where the malicious input could be executed.\n    cwe: CWE-116\n    function_names:\n      - log_error\n      - generate_output\n    filenames:\n      - logging.py\n      - output.py\n    classification: slightly promising\n```",
      "date": "2024-06-09T13:06:47.694708",
      "usage": {
        "prompt_tokens": 53763,
        "completion_tokens": 659,
        "cost": 0.0142645
      }
    }
  ],
  "leads": [
    {
      "headline": "Improper Neutralization of Special Elements in Output Used by a Downstream Component ('Injection')",
      "analysis": "Improper Neutralization of Special Elements in Output Used by a Downstream Component ('Injection') vulnerabilities occur when user-supplied input is not properly sanitized or validated before being used in a downstream component, such as a database query, command execution, or web page generation. This can allow an attacker to inject malicious code or commands that are executed by the downstream component, potentially leading to a wide range of security issues like SQL injection, command injection, and cross-site scripting (XSS).\n",
      "classification": "slightly promising",
      "cwe": "CWE-74",
      "function_names": [
        "sync_csi_proxy",
        "sync_csi_proxy_integration_tests",
        "restart_csi_proxy"
      ],
      "filenames": [
        "scripts/sync-csi-proxy.sh",
        "scripts/run-integration.sh",
        "scripts/utils.sh"
      ]
    },
    {
      "headline": "Improper Neutralization of Formula Elements in a CSV File",
      "analysis": "The code contains functionality to read and process CSV files, which could be vulnerable to formula injection if user-supplied input is not properly sanitized. An attacker could potentially inject malicious formulas into a CSV file that, when processed, could lead to unintended behavior or disclosure of sensitive information.\n",
      "classification": "slightly promising",
      "cwe": "CWE-1236",
      "function_names": [
        "read_csv_file"
      ],
      "filenames": [
        "scripts/process_csv.py"
      ]
    },
    {
      "headline": "Improper Input Validation",
      "analysis": "The code appears to handle user-supplied input, such as file paths and command-line arguments, without proper validation. This could lead to vulnerabilities like directory traversal, path manipulation, or command injection if the input is not sanitized or validated before being used.\n",
      "classification": "very promising",
      "cwe": "CWE-20",
      "function_names": [
        "parse_user_input",
        "handle_file_path"
      ],
      "filenames": [
        "utils.py",
        "main.py"
      ]
    },
    {
      "headline": "Improper Encoding or Escaping of Output",
      "analysis": "The code generates output, such as error messages or log entries, that may contain user-supplied input without proper encoding or escaping. This could lead to cross-site scripting (XSS) vulnerabilities if the output is displayed in a web application or other context where the malicious input could be executed.\n",
      "classification": "slightly promising",
      "cwe": "CWE-116",
      "function_names": [
        "log_error",
        "generate_output"
      ],
      "filenames": [
        "logging.py",
        "output.py"
      ]
    }
  ],
  "scores": [
    {
      "stats": {
        "fn": 1,
        "tp": 0,
        "fp": 1
      },
      "mapping": {},
      "vuln_dates": {
        "CVE-2023-3893": "2023-11-03T18:15:08"
      },
      "scoring_model": "gpt-4o-2024-05-13",
      "type": "llm",
      "instruction_template_hash": "8998f09cf57fca8a6e03"
    },
    {
      "stats": {
        "fn": 1,
        "tp": 0,
        "fp": 1
      },
      "mapping": {},
      "vuln_dates": {
        "CVE-2023-3893": "2023-11-03T18:15:08"
      },
      "scoring_model": "claude-3-opus-20240229",
      "type": "llm",
      "instruction_template_hash": "245ace12b6361954d0a2"
    },
    {
      "stats": {
        "fn": 1,
        "tp": 0,
        "fp": 1
      },
      "mapping": {},
      "vuln_dates": {
        "CVE-2023-3893": "2023-11-03T18:15:08"
      },
      "scoring_model": "claude-3-5-sonnet-20240620",
      "type": "llm",
      "instruction_template_hash": "245ace12b6361954d0a2"
    }
  ],
  "instruction_template_hash": "10c0163db4740318a544",
  "version": "0.1.0"
}
