{
  "commit": "8287691045fd3c0889bddd83964c5c743b4bc277",
  "repo_url": "https://github.com/bandoche/pypinksign",
  "model": "gpt-4o-2024-05-13",
  "chunk_hashes": [
    "5c7ab1b649a7edf8f7e3"
  ],
  "responses": [
    {
      "content": "```yaml\nleads:\n  - headline: \"Hard-coded Cryptographic Key in pypinkseed.py\"\n    analysis: |\n      The code contains hard-coded cryptographic keys, which can lead to various vulnerabilities such as unauthorized access and data breaches. Specifically, the IV (Initialization Vector) and key for the SEED algorithm\u2019s encryption/decryption functions are hard-coded. If these keys are known, an attacker can decrypt sensitive information. The IV in `process_block()` is set to `b'0123456789012345'`, and the hard-coded key is present in functions `encrypt_decrypted_prikey` and `get_private_key_decryption_key_for_seed_cbc`.\n    cwe: CWE-321\n    function_names:\n      - \"seed_cbc_128_encrypt_pure\"\n      - \"seed_cbc_128_decrypt_pure\"\n    filenames:\n      - \"pypinksign/pypinksign.py\"\n      - \"pypinksign/pypinkseed.py\"\n    classification: \"very promising\"\n\n  - headline: \"Use of Insecure Cryptographic Algorithms in pypinksign.py\"\n    analysis: |\n      The code uses outdated and insecure cryptographic algorithms like SEED and PBKDF1 for key derivation. These algorithms are considered weak and can be vulnerable to attacks such as brute force and cryptanalysis. Functions such as `encrypt_decrypted_prikey`, `seed_cbc_128_encrypt_pure`, and `seed_cbc_128_decrypt_pure` currently rely on these algorithms.\n    cwe: CWE-327\n    function_names:\n      - \"seed_cbc_128_encrypt_pure\"\n      - \"seed_cbc_128_decrypt_pure\"\n      - \"encrypt_decrypted_prikey\"\n    filenames:\n      - \"pypinksign/pypinksign.py\"\n      - \"pypinksign/pypinkseed.py\"\n    classification: \"very promising\"\n\n  - headline: \"Improper Error Handling in Prikey Loading Functions\"\n    analysis: |\n      Error handling in functions such as `load_prikey`, `get_private_key_decryption_key_for_seed_cbc_with_sha1`, and `get_private_key_decryption_key_for_pbes2` is minimal. These functions could be improved by thoroughly checking for potential errors and ensuring proper exceptions are raised. In the `load_prikey` function, if the wrong type of private key is used, a vague ValueError is thrown without sufficient context.\n    cwe: CWE-755\n    function_names:\n      - \"load_prikey\"\n      - \"get_private_key_decryption_key_for_seed_cbc_with_sha1\"\n      - \"get_private_key_decryption_key_for_pbes2\"\n    filenames:\n      - \"pypinksign/pypinksign.py\"\n    classification: \"slightly promising\"\n\n  - headline: \"Potential Information Exposure in Debug Logging\"\n    analysis: |\n      The `process_block` function logs cryptographic keys and data in debug mode, which can expose sensitive information in logs. This can be exploited if an attacker gains access to log files, revealing cryptographic materials and leading to potential decryption of sensitive data.\n    cwe: CWE-532\n    function_names:\n      - \"process_block\"\n    filenames:\n      - \"pypinksign/pypinkseed.py\"\n    classification: \"slightly promising\"\n\n  - headline: \"Weak Password Checking Mechanism\"\n    analysis: |\n      The mechanism for checking passwords and deriving keys in `pbkdf1` uses a fixed iteration count and a SHA-1 hash function. This approach is weak and susceptible to brute force attacks. Modern alternatives like PBKDF2, bcrypt, or Argon2 should be considered.\n    cwe: CWE-916\n    function_names:\n      - \"pbkdf1\"\n      - \"get_private_key_decryption_key_for_seed_cbc_with_sha1\"\n      - \"get_private_key_decryption_key_for_pbes2\"\n    filenames:\n      - \"pypinksign/pypinksign.py\"\n    classification: \"slightly promising\"\n```",
      "date": "2024-06-08T22:54:21.413986",
      "usage": {
        "prompt_tokens": 37908,
        "completion_tokens": 838,
        "cost": 0.20211
      }
    }
  ],
  "leads": [
    {
      "headline": "Hard-coded Cryptographic Key in pypinkseed.py",
      "analysis": "The code contains hard-coded cryptographic keys, which can lead to various vulnerabilities such as unauthorized access and data breaches. Specifically, the IV (Initialization Vector) and key for the SEED algorithm\u2019s encryption/decryption functions are hard-coded. If these keys are known, an attacker can decrypt sensitive information. The IV in process_block() is set to b'0123456789012345', and the hard-coded key is present in functions encrypt_decrypted_prikey and get_private_key_decryption_key_for_seed_cbc.\n",
      "classification": "very promising",
      "cwe": "CWE-321",
      "function_names": [
        "seed_cbc_128_encrypt_pure",
        "seed_cbc_128_decrypt_pure"
      ],
      "filenames": [
        "pypinksign/pypinksign.py",
        "pypinksign/pypinkseed.py"
      ]
    },
    {
      "headline": "Use of Insecure Cryptographic Algorithms in pypinksign.py",
      "analysis": "The code uses outdated and insecure cryptographic algorithms like SEED and PBKDF1 for key derivation. These algorithms are considered weak and can be vulnerable to attacks such as brute force and cryptanalysis. Functions such as encrypt_decrypted_prikey, seed_cbc_128_encrypt_pure, and seed_cbc_128_decrypt_pure currently rely on these algorithms.\n",
      "classification": "very promising",
      "cwe": "CWE-327",
      "function_names": [
        "seed_cbc_128_encrypt_pure",
        "seed_cbc_128_decrypt_pure",
        "encrypt_decrypted_prikey"
      ],
      "filenames": [
        "pypinksign/pypinksign.py",
        "pypinksign/pypinkseed.py"
      ]
    },
    {
      "headline": "Improper Error Handling in Prikey Loading Functions",
      "analysis": "Error handling in functions such as load_prikey, get_private_key_decryption_key_for_seed_cbc_with_sha1, and get_private_key_decryption_key_for_pbes2 is minimal. These functions could be improved by thoroughly checking for potential errors and ensuring proper exceptions are raised. In the load_prikey function, if the wrong type of private key is used, a vague ValueError is thrown without sufficient context.\n",
      "classification": "slightly promising",
      "cwe": "CWE-755",
      "function_names": [
        "load_prikey",
        "get_private_key_decryption_key_for_seed_cbc_with_sha1",
        "get_private_key_decryption_key_for_pbes2"
      ],
      "filenames": [
        "pypinksign/pypinksign.py"
      ]
    },
    {
      "headline": "Potential Information Exposure in Debug Logging",
      "analysis": "The process_block function logs cryptographic keys and data in debug mode, which can expose sensitive information in logs. This can be exploited if an attacker gains access to log files, revealing cryptographic materials and leading to potential decryption of sensitive data.\n",
      "classification": "slightly promising",
      "cwe": "CWE-532",
      "function_names": [
        "process_block"
      ],
      "filenames": [
        "pypinksign/pypinkseed.py"
      ]
    },
    {
      "headline": "Weak Password Checking Mechanism",
      "analysis": "The mechanism for checking passwords and deriving keys in pbkdf1 uses a fixed iteration count and a SHA-1 hash function. This approach is weak and susceptible to brute force attacks. Modern alternatives like PBKDF2, bcrypt, or Argon2 should be considered.\n",
      "classification": "slightly promising",
      "cwe": "CWE-916",
      "function_names": [
        "pbkdf1",
        "get_private_key_decryption_key_for_seed_cbc_with_sha1",
        "get_private_key_decryption_key_for_pbes2"
      ],
      "filenames": [
        "pypinksign/pypinksign.py"
      ]
    }
  ],
  "scores": [
    {
      "stats": {
        "fn": 1,
        "tp": 0,
        "fp": 2
      },
      "mapping": {},
      "vuln_dates": {
        "CVE-2023-48056": "2023-11-16T18:15:07"
      },
      "scoring_model": "gpt-4o-2024-05-13",
      "type": "llm",
      "instruction_template_hash": "8998f09cf57fca8a6e03"
    }
  ],
  "instruction_template_hash": "10c0163db4740318a544",
  "version": "0.1.0"
}
