{
  "commit": "dc7dd0003d39adcd0ca15a592e7e14a7c4af216f",
  "repo_url": "https://github.com/plone/plone.rest",
  "model": "gpt-4-turbo-2024-04-09",
  "chunk_hashes": [
    "3b7c364d133447d5aa4d"
  ],
  "responses": [
    {
      "content": "```yaml\nleads:\n  - headline: Missing input validation in configuration procedure\n    analysis: |\n      The setup.py file allows the user to specify classifiers, package name, version, and other critical settings without validating these inputs. An attacker could manipulate the input data to trigger unexpected behavior, potentially leading to arbitrary code execution or manipulation of package behavior.\n    cwe: CWE-20\n    function_names:\n      - read\n    filenames:\n      - setup.py\n    classification: very promising\n\n  - headline: Usage of potentially hard-coded credentials\n    analysis: |\n      The presence of the '__before_publishing_traverse__' function in patches.py, which checks and possibly alters HTTP request handling, could be vulnerable if the patch does not consider user credentials or if it lacks adequate permissions checks. Execution could bypass expected security filters leading to unauthorized system access.\n    cwe: CWE-798\n    function_names:\n      - __before_publishing_traverse__\n    filenames:\n      - src/plone/rest/patches.py\n    classification: slightly promising\n\n  - headline: Insecure usage of CORS policy\n    analysis: |\n      The erroneous or wide-ranging CORS configurations observed in cors.py allow external domains possibly more access than intended. The use of wildcards and poor validation of origins or headers in CORS requests might allow cross-origin attackers to access resources that should have restricted accessibility, leading to data breaches.\n    cwe: CWE-346\n    function_names:\n      - process_preflight_request\n      - process_simple_request\n    filenames:\n      - src/plone/rest/cors.py\n    classification: very promising\n\n  - headline: Cross-site scripting possibility due to unrestricted file types in uploads\n    analysis: |\n      The system as depicted in the test cases allows unrestricted uploads of file types and unsanitized input handling. This can result in Cross-Site Scripting (XSS) where malicious scripts are uploaded as files and executed in the browser of any user viewing these files, compromising client-side security.\n    cwe: CWE-79\n    function_names:\n      - test_unrestricted_upload_of_file_with_dangerous_type\n    filenames:\n      - src/plone/rest/tests/test_redirects.py\n    classification: very promising\n\n  - headline: Insufficient authentication checks on API endpoints\n    analysis: |\n      The API does not appear to have strong controls and checks for authentication and authorization, particularly in service classes. Endpoints are defined with possibly generic or unprotecting checks, leading to potential unauthorized access or escalation of privileges by exploiting the lack of rigid enforcement of user credentials verification.\n    cwe: CWE-306\n    function_names:\n      - __call__\n    filenames:\n      - src/plone/rest/service.py\n    classification: slightly promising\n```",
      "date": "2024-06-09T14:12:35.072936",
      "usage": {
        "prompt_tokens": 24842,
        "completion_tokens": 561,
        "cost": 0.26525
      }
    }
  ],
  "leads": [
    {
      "headline": "Missing input validation in configuration procedure",
      "analysis": "The setup.py file allows the user to specify classifiers, package name, version, and other critical settings without validating these inputs. An attacker could manipulate the input data to trigger unexpected behavior, potentially leading to arbitrary code execution or manipulation of package behavior.\n",
      "classification": "very promising",
      "cwe": "CWE-20",
      "function_names": [
        "read"
      ],
      "filenames": [
        "setup.py"
      ]
    },
    {
      "headline": "Usage of potentially hard-coded credentials",
      "analysis": "The presence of the '__before_publishing_traverse__' function in patches.py, which checks and possibly alters HTTP request handling, could be vulnerable if the patch does not consider user credentials or if it lacks adequate permissions checks. Execution could bypass expected security filters leading to unauthorized system access.\n",
      "classification": "slightly promising",
      "cwe": "CWE-798",
      "function_names": [
        "__before_publishing_traverse__"
      ],
      "filenames": [
        "src/plone/rest/patches.py"
      ]
    },
    {
      "headline": "Insecure usage of CORS policy",
      "analysis": "The erroneous or wide-ranging CORS configurations observed in cors.py allow external domains possibly more access than intended. The use of wildcards and poor validation of origins or headers in CORS requests might allow cross-origin attackers to access resources that should have restricted accessibility, leading to data breaches.\n",
      "classification": "very promising",
      "cwe": "CWE-346",
      "function_names": [
        "process_preflight_request",
        "process_simple_request"
      ],
      "filenames": [
        "src/plone/rest/cors.py"
      ]
    },
    {
      "headline": "Cross-site scripting possibility due to unrestricted file types in uploads",
      "analysis": "The system as depicted in the test cases allows unrestricted uploads of file types and unsanitized input handling. This can result in Cross-Site Scripting (XSS) where malicious scripts are uploaded as files and executed in the browser of any user viewing these files, compromising client-side security.\n",
      "classification": "very promising",
      "cwe": "CWE-79",
      "function_names": [
        "test_unrestricted_upload_of_file_with_dangerous_type"
      ],
      "filenames": [
        "src/plone/rest/tests/test_redirects.py"
      ]
    },
    {
      "headline": "Insufficient authentication checks on API endpoints",
      "analysis": "The API does not appear to have strong controls and checks for authentication and authorization, particularly in service classes. Endpoints are defined with possibly generic or unprotecting checks, leading to potential unauthorized access or escalation of privileges by exploiting the lack of rigid enforcement of user credentials verification.\n",
      "classification": "slightly promising",
      "cwe": "CWE-306",
      "function_names": [
        "__call__"
      ],
      "filenames": [
        "src/plone/rest/service.py"
      ]
    }
  ],
  "scores": [
    {
      "stats": {
        "fn": 1,
        "tp": 0,
        "fp": 3
      },
      "mapping": {},
      "vuln_dates": {
        "CVE-2023-42457": "2023-09-21T15:15:10"
      },
      "scoring_model": "gpt-4o-2024-05-13",
      "type": "llm",
      "instruction_template_hash": "8998f09cf57fca8a6e03"
    }
  ],
  "instruction_template_hash": "10c0163db4740318a544",
  "version": "0.1.0"
}
