{
  "commit": "0d0ddd43b3b0f0995bfaa34a45f046d47860a234",
  "repo_url": "https://github.com/skyscreamer/nevado",
  "model": "gpt-4-turbo-2024-04-09",
  "chunk_hashes": [
    "fcababaa4ada245f9f81"
  ],
  "responses": [
    {
      "content": "```yaml\nleads:\n  - headline: \"Improper Validation of Wildcards in AWS Library for Messages.\"\n    analysis: |\n      The application does not perform adequate validation of wildcards during serialization and deserialization of messages with the Amazon AWS library. It allows for unfiltered data to be sent over the network, which may lead to manipulations or data injection if the message content is not properly sanitized.\n    cwe: CWE-20\n    function_names:\n      - serializeMessage\n      - deserializeMessage\n    filenames:\n      - src/main/java/org/skyscreamer/nevado/jms/connector/amazonaws/AmazonAwsSQSConnector.java\n    classification: \"slightly promising\"\n\n  - headline: \"Usage of Insecure Libraries in Message Serialization.\"\n    analysis: |\n      The system utilizes serializations libraries such as 'SerializeUtil' which might be vulnerable or not fully secure. Functions like deserialize and serialize lack comprehensive checks or validation logic which might expose the system to various injection attacks or unintended data manipulation.\n    cwe: CWE-502\n    function_names:\n      - serializeToString\n      - deserializeFromString\n    filenames:\n      - src/main/java/org/skyscreamer/nevado/jms/util/SerializeUtil.java\n    classification: \"very promising\"\n  \n  - headline: \"Lack of Synchronization in Performance Service Leads to Race Condition\"\n    analysis: |\n      PerformanceService allows multiple threads to access and modify shared resources without proper synchronization mechanisms. This can lead to race conditions where the shared data may get corrupted, leading to unreliable performance metrics and potential denial of service through resource exhaustion.\n    cwe: CWE-362\n    function_names:\n      - runSample\n    filenames:\n      - src/main/java/org/skyscreamer/nevado/jms/performance/PerformanceService.java\n    classification: \"very promising\"\n  \n  - headline: \"Exposure of Sensitive Information in Mock Components\"\n    analysis: |\n      MockSQSConnector and MockSQSQueue classes are used within the application, potentially logging sensitive information which may include credentials or data contents. This information could be logged to unsecured logs or output streams, potentially exposing sensitive data.\n    cwe: CWE-532\n    function_names:\n      - sendMessage\n      - receiveMessage\n    filenames:\n      - src/main/java/org/skyscreamer/nevado/jms/connector/mock/MockSQSConnector.java\n      - src/main/java/org/skyscreamer/nevado/jms/connector/mock/MockSQSMessage.java\n    classification: \"slightly promising\"\n\n  - headline: \"Insufficient Authentication in AWS Connector Implementation\"\n    analysis: |\n      The AWS connector services do not enforce strict authentication mechanisms, potentially allowing unauthorized access to message queues or topics. This could lead to unauthorized message consumption or publishing, thereby compromising the integrity of the message handling system.\n    cwe: CWE-306\n    function_names:\n      - getAmazonSQS\n      - getAmazonSNS\n    filenames:\n      - src/main/java/org/skyscreamer/nevado/jms/connector/amazonaws/AmazonAwsSQSConnector.java\n    classification: \"slightly promising\"\n```",
      "date": "2024-06-13T11:46:52.753805",
      "usage": {
        "prompt_tokens": 125302,
        "completion_tokens": 657,
        "cost": 1.27273
      }
    }
  ],
  "leads": [
    {
      "headline": "Improper Validation of Wildcards in AWS Library for Messages.",
      "analysis": "The application does not perform adequate validation of wildcards during serialization and deserialization of messages with the Amazon AWS library. It allows for unfiltered data to be sent over the network, which may lead to manipulations or data injection if the message content is not properly sanitized.\n",
      "classification": "slightly promising",
      "cwe": "CWE-20",
      "function_names": [
        "serializeMessage",
        "deserializeMessage"
      ],
      "filenames": [
        "src/main/java/org/skyscreamer/nevado/jms/connector/amazonaws/AmazonAwsSQSConnector.java"
      ]
    },
    {
      "headline": "Usage of Insecure Libraries in Message Serialization.",
      "analysis": "The system utilizes serializations libraries such as 'SerializeUtil' which might be vulnerable or not fully secure. Functions like deserialize and serialize lack comprehensive checks or validation logic which might expose the system to various injection attacks or unintended data manipulation.\n",
      "classification": "very promising",
      "cwe": "CWE-502",
      "function_names": [
        "serializeToString",
        "deserializeFromString"
      ],
      "filenames": [
        "src/main/java/org/skyscreamer/nevado/jms/util/SerializeUtil.java"
      ]
    },
    {
      "headline": "Lack of Synchronization in Performance Service Leads to Race Condition",
      "analysis": "PerformanceService allows multiple threads to access and modify shared resources without proper synchronization mechanisms. This can lead to race conditions where the shared data may get corrupted, leading to unreliable performance metrics and potential denial of service through resource exhaustion.\n",
      "classification": "very promising",
      "cwe": "CWE-362",
      "function_names": [
        "runSample"
      ],
      "filenames": [
        "src/main/java/org/skyscreamer/nevado/jms/performance/PerformanceService.java"
      ]
    },
    {
      "headline": "Exposure of Sensitive Information in Mock Components",
      "analysis": "MockSQSConnector and MockSQSQueue classes are used within the application, potentially logging sensitive information which may include credentials or data contents. This information could be logged to unsecured logs or output streams, potentially exposing sensitive data.\n",
      "classification": "slightly promising",
      "cwe": "CWE-532",
      "function_names": [
        "sendMessage",
        "receiveMessage"
      ],
      "filenames": [
        "src/main/java/org/skyscreamer/nevado/jms/connector/mock/MockSQSConnector.java",
        "src/main/java/org/skyscreamer/nevado/jms/connector/mock/MockSQSMessage.java"
      ]
    },
    {
      "headline": "Insufficient Authentication in AWS Connector Implementation",
      "analysis": "The AWS connector services do not enforce strict authentication mechanisms, potentially allowing unauthorized access to message queues or topics. This could lead to unauthorized message consumption or publishing, thereby compromising the integrity of the message handling system.\n",
      "classification": "slightly promising",
      "cwe": "CWE-306",
      "function_names": [
        "getAmazonSQS",
        "getAmazonSNS"
      ],
      "filenames": [
        "src/main/java/org/skyscreamer/nevado/jms/connector/amazonaws/AmazonAwsSQSConnector.java"
      ]
    }
  ],
  "scores": [
    {
      "stats": {
        "fn": 0,
        "tp": 1,
        "fp": 1
      },
      "mapping": {
        "0": "CVE-2023-31826"
      },
      "vuln_dates": {
        "CVE-2023-31826": "2023-05-23T01:15:10"
      },
      "scoring_model": "claude-3-opus-20240229",
      "type": "llm",
      "instruction_template_hash": "245ace12b6361954d0a2"
    }
  ],
  "instruction_template_hash": "10c0163db4740318a544",
  "version": "0.1.0"
}
