{
  "commit": "323469fce4daedea93416148c2c3c3facd67fab8",
  "repo_url": "https://github.com/leonnnn/pyxtrlock",
  "model": "gpt-4o-2024-05-13",
  "chunk_hashes": [
    "ff8e401330ebd3913f31"
  ],
  "responses": [
    {
      "content": "```yaml\nleads:\n  - headline: Missing Proper Validation for Bitmap Image Sizes\n    analysis: |\n      The code does not perform proper validation on bitmap image sizes provided by the user. As a result, it may result in reading or writing outside of allocated memory if the bitmap size does not match the expected dimensions, leading to potential memory corruption or out-of-bounds errors.\n    cwe: CWE-1284\n    function_names:\n      - _guess_size\n      - _stroke\n      - Bitmap.__init__\n    filenames:\n      - bin/make_lock.py\n    classification: very promising\n\n  - headline: Inadequate Input Validation on Command-Line Arguments\n    analysis: |\n      The handling of command-line arguments relies on default `argparse` parsing without additional safeguards, which could be exploited if an attacker manipulates input values to cause unexpected behavior. This might include providing overly large sizes or invalid colors, leading to potential denial of service or arbitrary code execution.\n    cwe: CWE-20\n    function_names:\n      - <module>\n      - __init__\n    filenames:\n      - bin/make_lock.py\n    classification: slightly promising\n\n  - headline: Incorrect Handling of System Library Loading\n    analysis: |\n      In `pyxtrlock/utils.py`, the `check_and_load_library` function loads system libraries based on the names provided. If these libraries can be manipulated (e.g., through path hijacking or Tampering with library-loading mechanisms in shared environments), it could lead to loading malicious libraries, causing arbitrary code execution.\n    cwe: CWE-426\n    function_names:\n      - check_and_load_library\n    filenames:\n      - pyxtrlock/utils.py\n    classification: very promising\n\n  - headline: Potential Information Disclosure in Error Messages\n    analysis: |\n      Functions such as `panic` in `pyxtrlock/__init__.py` print error messages directly which could potentially disclose sensitive information. An attacker could exploit verbose error messages to gain detailed insights into the application's inner workings or uncover sensitive paths and data.\n    cwe: CWE-209\n    function_names:\n      - panic\n    filenames:\n      - pyxtrlock/__init__.py\n    classification: slightly promising\n\n  - headline: Use of Hardcoded Color Values\n    analysis: |\n      The code includes hardcoded color values and bitmap buffer content that might not be well-tested for all possible cases or might not follow user-defined customizations. While not a direct security issue, it could potentially expose additional attack surfaces or cause unexpected behaviors in edge-case scenarios.\n    cwe: CWE-922\n    function_names: []\n    filenames:\n      - pyxtrlock/default_cursor.py\n    classification: not promising\n\n  - headline: Missing Security Validations in Cursor File Handling\n    analysis: |\n      Functions responsible for saving and loading cursor files do not enforce strong security checks on the content length and data integrity. This might be exploited through crafted cursor files to cause buffer overflows or data corruption.\n    cwe: CWE-787\n    function_names:\n      - save_cursor\n      - load_cursor\n    filenames:\n      - pyxtrlock/cursor_file.py\n    classification: very promising\n```",
      "date": "2024-06-13T09:37:51.734641",
      "usage": {
        "prompt_tokens": 13465,
        "completion_tokens": 659,
        "cost": 0.07721
      }
    }
  ],
  "leads": [
    {
      "headline": "Missing Proper Validation for Bitmap Image Sizes",
      "analysis": "The code does not perform proper validation on bitmap image sizes provided by the user. As a result, it may result in reading or writing outside of allocated memory if the bitmap size does not match the expected dimensions, leading to potential memory corruption or out-of-bounds errors.\n",
      "classification": "very promising",
      "cwe": "CWE-1284",
      "function_names": [
        "_guess_size",
        "_stroke",
        "Bitmap.__init__"
      ],
      "filenames": [
        "bin/make_lock.py"
      ]
    },
    {
      "headline": "Inadequate Input Validation on Command-Line Arguments",
      "analysis": "The handling of command-line arguments relies on default argparse parsing without additional safeguards, which could be exploited if an attacker manipulates input values to cause unexpected behavior. This might include providing overly large sizes or invalid colors, leading to potential denial of service or arbitrary code execution.\n",
      "classification": "slightly promising",
      "cwe": "CWE-20",
      "function_names": [
        "<module>",
        "__init__"
      ],
      "filenames": [
        "bin/make_lock.py"
      ]
    },
    {
      "headline": "Incorrect Handling of System Library Loading",
      "analysis": "In pyxtrlock/utils.py, the check_and_load_library function loads system libraries based on the names provided. If these libraries can be manipulated (e.g., through path hijacking or Tampering with library-loading mechanisms in shared environments), it could lead to loading malicious libraries, causing arbitrary code execution.\n",
      "classification": "very promising",
      "cwe": "CWE-426",
      "function_names": [
        "check_and_load_library"
      ],
      "filenames": [
        "pyxtrlock/utils.py"
      ]
    },
    {
      "headline": "Potential Information Disclosure in Error Messages",
      "analysis": "Functions such as panic in pyxtrlock/__init__.py print error messages directly which could potentially disclose sensitive information. An attacker could exploit verbose error messages to gain detailed insights into the application's inner workings or uncover sensitive paths and data.\n",
      "classification": "slightly promising",
      "cwe": "CWE-209",
      "function_names": [
        "panic"
      ],
      "filenames": [
        "pyxtrlock/__init__.py"
      ]
    },
    {
      "headline": "Use of Hardcoded Color Values",
      "analysis": "The code includes hardcoded color values and bitmap buffer content that might not be well-tested for all possible cases or might not follow user-defined customizations. While not a direct security issue, it could potentially expose additional attack surfaces or cause unexpected behaviors in edge-case scenarios.\n",
      "classification": "not promising",
      "cwe": "CWE-922",
      "function_names": [],
      "filenames": [
        "pyxtrlock/default_cursor.py"
      ]
    },
    {
      "headline": "Missing Security Validations in Cursor File Handling",
      "analysis": "Functions responsible for saving and loading cursor files do not enforce strong security checks on the content length and data integrity. This might be exploited through crafted cursor files to cause buffer overflows or data corruption.\n",
      "classification": "very promising",
      "cwe": "CWE-787",
      "function_names": [
        "save_cursor",
        "load_cursor"
      ],
      "filenames": [
        "pyxtrlock/cursor_file.py"
      ]
    }
  ],
  "scores": [
    {
      "stats": {
        "fn": 1,
        "tp": 0,
        "fp": 3
      },
      "mapping": {},
      "vuln_dates": {
        "CVE-2019-1010316": "2019-07-11T20:15:12"
      },
      "scoring_model": "claude-3-opus-20240229",
      "type": "llm",
      "instruction_template_hash": "245ace12b6361954d0a2"
    }
  ],
  "instruction_template_hash": "10c0163db4740318a544",
  "version": "0.1.0"
}
