{
  "commit": "3f49324c1feac191a7643e58c590745ae68a8ec7",
  "repo_url": "https://github.com/dotnet/vscode-dotnet-runtime",
  "model": "claude-3-sonnet-20240229",
  "chunk_hashes": [
    "808b4f28ce66766fe591"
  ],
  "responses": [
    {
      "content": "```yaml\nleads:\n  - headline: Potential command injection vulnerability\n    analysis: |\n      The application is using `cp.exec` and `cp.spawnSync` to execute external commands with user-supplied arguments. This can potentially lead to command injection vulnerabilities if the user input is not properly sanitized or validated. An attacker could potentially inject malicious code into the arguments, leading to arbitrary command execution on the system.\n    cwe: CWE-78\n    function_names:\n      - activate\n      - setPathEnvVar\n      - runPathCommand\n      - ensureDependenciesRegistration\n    filenames: \n      - vscode-dotnet-sdk-extension/src/extension.ts\n      - vscode-dotnet-runtime-extension/src/extension.ts\n      - vscode-dotnet-runtime-library/src/Acquisition/AcquisitionInvoker.ts\n    classification: very promising\n\n  - headline: Potential uncontrolled resource consumption\n    analysis: |\n      The application is using regular expressions without any anchors or word boundaries, which can lead to catastrophic backtracking and uncontrolled resource consumption (e.g., CPU cycles, memory) for certain types of input. This can potentially lead to a denial-of-service vulnerability if an attacker can supply crafted input that triggers the worst-case behavior of the regular expression engine.\n    cwe: CWE-400\n    function_names: []\n    filenames:\n      - vscode-dotnet-runtime-library/src/Utils/ContentSantizer.ts\n    classification: slightly promising\n\n  - headline: Potential path traversal vulnerability\n    analysis: |\n      The application is constructing file paths using user-supplied input without proper validation or sanitization. An attacker could potentially exploit this by injecting directory traversal sequences (e.g., `../`) into the input, allowing them to access or modify files outside of the intended directory.\n    cwe: CWE-22\n    function_names:\n      - DotnetInstallationValidationError.getFileStructure\n    filenames:\n      - vscode-dotnet-runtime-library/src/EventStream/EventStreamEvents.ts\n    classification: very promising\n\n  - headline: Potential improper input validation\n    analysis: |\n      The application is parsing JSON data from an external source without proper input validation or sanitization. An attacker could potentially supply malicious JSON data that could lead to unexpected behavior or vulnerabilities when parsed by the application.\n    cwe: CWE-20\n    function_names:\n      - ReleasesResult\n    filenames:\n      - vscode-dotnet-runtime-library/src/Acquisition/ReleasesResult.ts\n    classification: very promising\n\n  - headline: Potential insecure storage of sensitive information\n    analysis: |\n      The application is writing log files and potentially sensitive information to disk without any encryption or protection. An attacker with access to the file system could potentially access this sensitive information.\n    cwe: CWE-312\n    function_names:\n      - LoggingObserver.dispose\n    filenames:\n      - vscode-dotnet-runtime-library/src/EventStream/LoggingObserver.ts\n    classification: slightly promising\n\n  - headline: Potential code injection vulnerability\n    analysis: |\n      The application is using user-supplied input to construct and execute code dynamically, which can potentially lead to code injection vulnerabilities if the input is not properly sanitized or validated. An attacker could potentially inject malicious code into the input, leading to arbitrary code execution.\n    cwe: CWE-94\n    function_names: []\n    filenames: []\n    classification: not promising\n```",
      "date": "2024-06-14T13:20:31.153829",
      "usage": {
        "prompt_tokens": 59251,
        "completion_tokens": 848,
        "cost": 0.190473
      }
    }
  ],
  "leads": [
    {
      "headline": "Potential command injection vulnerability",
      "analysis": "The application is using cp.exec and cp.spawnSync to execute external commands with user-supplied arguments. This can potentially lead to command injection vulnerabilities if the user input is not properly sanitized or validated. An attacker could potentially inject malicious code into the arguments, leading to arbitrary command execution on the system.\n",
      "classification": "very promising",
      "cwe": "CWE-78",
      "function_names": [
        "activate",
        "setPathEnvVar",
        "runPathCommand"
      ],
      "filenames": [
        "vscode-dotnet-sdk-extension/src/extension.ts",
        "vscode-dotnet-runtime-extension/src/extension.ts",
        "vscode-dotnet-runtime-library/src/Acquisition/AcquisitionInvoker.ts"
      ]
    },
    {
      "headline": "Potential uncontrolled resource consumption",
      "analysis": "The application is using regular expressions without any anchors or word boundaries, which can lead to catastrophic backtracking and uncontrolled resource consumption (e.g., CPU cycles, memory) for certain types of input. This can potentially lead to a denial-of-service vulnerability if an attacker can supply crafted input that triggers the worst-case behavior of the regular expression engine.\n",
      "classification": "slightly promising",
      "cwe": "CWE-400",
      "function_names": [],
      "filenames": [
        "vscode-dotnet-runtime-library/src/Utils/ContentSantizer.ts"
      ]
    },
    {
      "headline": "Potential path traversal vulnerability",
      "analysis": "The application is constructing file paths using user-supplied input without proper validation or sanitization. An attacker could potentially exploit this by injecting directory traversal sequences (e.g., ../) into the input, allowing them to access or modify files outside of the intended directory.\n",
      "classification": "very promising",
      "cwe": "CWE-22",
      "function_names": [
        "DotnetInstallationValidationError.getFileStructure"
      ],
      "filenames": [
        "vscode-dotnet-runtime-library/src/EventStream/EventStreamEvents.ts"
      ]
    },
    {
      "headline": "Potential improper input validation",
      "analysis": "The application is parsing JSON data from an external source without proper input validation or sanitization. An attacker could potentially supply malicious JSON data that could lead to unexpected behavior or vulnerabilities when parsed by the application.\n",
      "classification": "very promising",
      "cwe": "CWE-20",
      "function_names": [
        "ReleasesResult"
      ],
      "filenames": [
        "vscode-dotnet-runtime-library/src/Acquisition/ReleasesResult.ts"
      ]
    },
    {
      "headline": "Potential insecure storage of sensitive information",
      "analysis": "The application is writing log files and potentially sensitive information to disk without any encryption or protection. An attacker with access to the file system could potentially access this sensitive information.\n",
      "classification": "slightly promising",
      "cwe": "CWE-312",
      "function_names": [
        "LoggingObserver.dispose"
      ],
      "filenames": [
        "vscode-dotnet-runtime-library/src/EventStream/LoggingObserver.ts"
      ]
    },
    {
      "headline": "Potential code injection vulnerability",
      "analysis": "The application is using user-supplied input to construct and execute code dynamically, which can potentially lead to code injection vulnerabilities if the input is not properly sanitized or validated. An attacker could potentially inject malicious code into the input, leading to arbitrary code execution.\n",
      "classification": "not promising",
      "cwe": "CWE-94",
      "function_names": [],
      "filenames": []
    }
  ],
  "scores": [
    {
      "stats": {
        "fn": 0,
        "tp": 1,
        "fp": 2
      },
      "mapping": {
        "0": "CVE-2021-34477"
      },
      "vuln_dates": {
        "CVE-2021-34477": "2021-07-14T18:15:11"
      },
      "scoring_model": "claude-3-opus-20240229",
      "type": "llm",
      "instruction_template_hash": "245ace12b6361954d0a2"
    }
  ],
  "instruction_template_hash": "10c0163db4740318a544",
  "version": "0.1.0"
}
