{
  "commit": "3b7508567d8ba09d2d8a9e11e8583096189ca8ef",
  "repo_url": "https://github.com/gruntjs/grunt",
  "model": "gpt-4o-2024-05-13",
  "chunk_hashes": [
    "28df4943720055d3c4d3"
  ],
  "responses": [
    {
      "content": "```yaml\nleads:\n  - headline: Insecure Temporary File Creation\n    analysis: |\n      The `lib/grunt/fail.js` file contains code that creates temporary files using the `Temporary` library without setting secure file permissions. This can lead to permission issues where other users on the system can access these temporary files, leading to potential information disclosure or file overwrites.\n    cwe: CWE-377\n    function_names:\n      - None\n    filenames:\n      - lib/grunt/fail.js\n    classification: very promising\n\n  - headline: Insecure Usage of eval\n    analysis: |\n      The `grunt` function uses `eval` to load and execute JavaScript code dynamically. This can be exploited if an attacker can influence the string being executed, leading to remote code execution vulnerabilities.\n    cwe: CWE-95\n    function_names:\n      - eval\n    filenames:\n      - lib/grunt/cli.js\n    classification: very promising\n\n  - headline: Command Injection via grunt.util.spawn\n    analysis: |\n      The use of `grunt.util.spawn` in `internal-tasks/subgrunt.js` to run sub-grunt files may be susceptible to command injection, particularly if input is not properly sanitized before being passed to spawn commands. This could allow an attacker to execute arbitrary commands on the system.\n    cwe: CWE-77\n    function_names:\n      - spawn\n    filenames:\n      - internal-tasks/subgrunt.js\n    classification: very promising\n\n  - headline: Potential Path Traversal in expandMapping\n    analysis: |\n      The `expandMapping` function in `lib/grunt/file.js` processes file paths based on user input. If not properly sanitized, this could allow an attacker to conduct path traversal attacks, potentially accessing files outside the intended directory.\n    cwe: CWE-22\n    function_names:\n      - expandMapping\n    filenames:\n      - lib/grunt/file.js\n    classification: very promising\n\n  - headline: Insufficient Validation of Task Plugin Dependencies\n    analysis: |\n      The function `loadNpmTasks` in `lib/grunt/task.js` does not sufficiently validate or restrict the loading of task plugins from NPM modules. If an attacker can inject a malicious module, this could lead to arbitrary code execution.\n    cwe: CWE-829\n    function_names:\n      - loadNpmTasks\n    filenames:\n      - lib/grunt/task.js\n    classification: slightly promising\n\n  - headline: Improper Use of child_process.exec\n    analysis: |\n      The `grunt.util.spawn` method in `lib/util/task.js` is used to execute commands. If input passed to `exec` is not properly sanitized, it could lead to command injection attacks, allowing an attacker to execute arbitrary commands with the privilege of the running script.\n    cwe: CWE-78\n    function_names:\n      - exec\n    filenames:\n      - lib/util/task.js\n    classification: very promising\n\n  - headline: Insufficient Entropy for Temporary Filename Generation\n    analysis: |\n      The function for creating temporary filenames appears to lack sufficient randomness to prevent filename collisions under high load. This could lead to attackers predicting the file names and attempting to exploit this.\n    cwe: CWE-331\n    function_names:\n      - None\n    filenames:\n      - lib/grunt/file.js\n    classification: slightly promising\n\n  - headline: Hardcoded Credential Storage Detected\n    analysis: |\n      Hardcoded credentials found within configuration initialization in `lib/grunt/option.js` file. This can lead to unauthorized access if the source code is leaked or accessed by unauthorized parties.\n    cwe: CWE-798\n    function_names:\n      - option.init\n    filenames:\n      - lib/grunt/option.js\n    classification: slightly promising\n    \n  - headline: Missing SSL/TLS Verification\n    analysis: |\n      If external network calls are made (e.g., within `grunt.util.spawn`), ensure that SSL/TLS verification is enabled. Lack of this can lead to man-in-the-middle attacks where an attacker intercepts or alters sensitive data.\n    cwe: CWE-295\n    function_names:\n      - spawn\n    filenames:\n      - lib/util/task.js\n    classification: very promising\n```",
      "date": "2024-06-14T13:40:34.658985",
      "usage": {
        "prompt_tokens": 46001,
        "completion_tokens": 876,
        "cost": 0.243145
      }
    }
  ],
  "leads": [
    {
      "headline": "Insecure Temporary File Creation",
      "analysis": "The lib/grunt/fail.js file contains code that creates temporary files using the Temporary library without setting secure file permissions. This can lead to permission issues where other users on the system can access these temporary files, leading to potential information disclosure or file overwrites.\n",
      "classification": "very promising",
      "cwe": "CWE-377",
      "function_names": [
        "None"
      ],
      "filenames": [
        "lib/grunt/fail.js"
      ]
    },
    {
      "headline": "Insecure Usage of eval",
      "analysis": "The grunt function uses eval to load and execute JavaScript code dynamically. This can be exploited if an attacker can influence the string being executed, leading to remote code execution vulnerabilities.\n",
      "classification": "very promising",
      "cwe": "CWE-95",
      "function_names": [
        "eval"
      ],
      "filenames": [
        "lib/grunt/cli.js"
      ]
    },
    {
      "headline": "Command Injection via grunt.util.spawn",
      "analysis": "The use of grunt.util.spawn in internal-tasks/subgrunt.js to run sub-grunt files may be susceptible to command injection, particularly if input is not properly sanitized before being passed to spawn commands. This could allow an attacker to execute arbitrary commands on the system.\n",
      "classification": "very promising",
      "cwe": "CWE-77",
      "function_names": [
        "spawn"
      ],
      "filenames": [
        "internal-tasks/subgrunt.js"
      ]
    },
    {
      "headline": "Potential Path Traversal in expandMapping",
      "analysis": "The expandMapping function in lib/grunt/file.js processes file paths based on user input. If not properly sanitized, this could allow an attacker to conduct path traversal attacks, potentially accessing files outside the intended directory.\n",
      "classification": "very promising",
      "cwe": "CWE-22",
      "function_names": [
        "expandMapping"
      ],
      "filenames": [
        "lib/grunt/file.js"
      ]
    },
    {
      "headline": "Insufficient Validation of Task Plugin Dependencies",
      "analysis": "The function loadNpmTasks in lib/grunt/task.js does not sufficiently validate or restrict the loading of task plugins from NPM modules. If an attacker can inject a malicious module, this could lead to arbitrary code execution.\n",
      "classification": "slightly promising",
      "cwe": "CWE-829",
      "function_names": [
        "loadNpmTasks"
      ],
      "filenames": [
        "lib/grunt/task.js"
      ]
    },
    {
      "headline": "Improper Use of child_process.exec",
      "analysis": "The grunt.util.spawn method in lib/util/task.js is used to execute commands. If input passed to exec is not properly sanitized, it could lead to command injection attacks, allowing an attacker to execute arbitrary commands with the privilege of the running script.\n",
      "classification": "very promising",
      "cwe": "CWE-78",
      "function_names": [
        "exec"
      ],
      "filenames": [
        "lib/util/task.js"
      ]
    },
    {
      "headline": "Insufficient Entropy for Temporary Filename Generation",
      "analysis": "The function for creating temporary filenames appears to lack sufficient randomness to prevent filename collisions under high load. This could lead to attackers predicting the file names and attempting to exploit this.\n",
      "classification": "slightly promising",
      "cwe": "CWE-331",
      "function_names": [
        "None"
      ],
      "filenames": [
        "lib/grunt/file.js"
      ]
    },
    {
      "headline": "Hardcoded Credential Storage Detected",
      "analysis": "Hardcoded credentials found within configuration initialization in lib/grunt/option.js file. This can lead to unauthorized access if the source code is leaked or accessed by unauthorized parties.\n",
      "classification": "slightly promising",
      "cwe": "CWE-798",
      "function_names": [
        "option.init"
      ],
      "filenames": [
        "lib/grunt/option.js"
      ]
    },
    {
      "headline": "Missing SSL/TLS Verification",
      "analysis": "If external network calls are made (e.g., within grunt.util.spawn), ensure that SSL/TLS verification is enabled. Lack of this can lead to man-in-the-middle attacks where an attacker intercepts or alters sensitive data.\n",
      "classification": "very promising",
      "cwe": "CWE-295",
      "function_names": [
        "spawn"
      ],
      "filenames": [
        "lib/util/task.js"
      ]
    }
  ],
  "scores": [
    {
      "stats": {
        "fn": 2,
        "tp": 1,
        "fp": 5
      },
      "mapping": {
        "3": "CVE-2022-0436"
      },
      "vuln_dates": {
        "CVE-2020-7729": "2020-09-03T09:15:10",
        "CVE-2022-1537": "2022-05-10T14:15:08",
        "CVE-2022-0436": "2022-04-12T21:15:07"
      },
      "scoring_model": "claude-3-opus-20240229",
      "type": "llm",
      "instruction_template_hash": "245ace12b6361954d0a2"
    },
    {
      "stats": {
        "fn": 2,
        "tp": 1,
        "fp": 5
      },
      "mapping": {
        "3": "CVE-2022-0436"
      },
      "vuln_dates": {
        "CVE-2020-7729": "2020-09-03T09:15:10",
        "CVE-2022-1537": "2022-05-10T14:15:08",
        "CVE-2022-0436": "2022-04-12T21:15:07"
      },
      "scoring_model": "claude-3-5-sonnet-20240620",
      "type": "llm",
      "instruction_template_hash": "245ace12b6361954d0a2"
    }
  ],
  "instruction_template_hash": "10c0163db4740318a544",
  "version": "0.1.0"
}
