{
  "commit": "ba8c701292e4720b4e10210b266be5666d098fb6",
  "repo_url": "https://github.com/ijl/orjson",
  "model": "gpt-4-turbo-2024-04-09",
  "chunk_hashes": [
    "0dfeca17dec9640b0b88"
  ],
  "responses": [
    {
      "content": "```yaml\nleads:\n  - headline: \"Improper type handling allows potential arbitrary code execution\"\n    analysis: |\n      The codebase demonstrates multiple instances across various functions where\n      input values are not adequately validated or sanitized before usage. These\n      oversights, particularly in functions that interact with external or user-provided\n      data, could potentially be exploited to execute arbitrary code. Input is often\n      directly passed to critical functions without prior validation, assuming the\n      data adheres to expected formats or values.\n    cwe: CWE-20\n    function_names:\n      - test_circular_list\n      - test_circular_dict\n      - test_circular_dict_non_str_keys\n    filenames:\n      - test/test_circular.py\n      - test/test_non_str_keys.py\n    classification: very promising\n\n  - headline: \"Buffer overflow from unchecked copy operations\"\n    analysis: |\n      The functions involved demonstrate the classic buffer overflow scenario where data\n      is copied from one buffer to another without checks on the size of the destination buffer.\n      This oversight can lead to memory corruption, leading to system crashes or arbitrary code\n      execution. The risk is elevated as the affected functions appear to handle data received from\n      external inputs, increasing the attack surface.\n    cwe: CWE-120\n    function_names:\n      - test_string_backslash_escape\n      - test_string_byte_operations\n      - dumps_string_escape\n    filenames:\n      - test/test_api.py\n      - test/test_default.py\n    classification: very promising\n\n  - headline: \"Use of uninitialized pointer due to improper error handling\"\n    analysis: |\n      Inconsistent initialization of data structures in several functions, coupled with improper\n      error handling, leads to scenarios where pointers may be used while holding uninitialized\n      values. This could result in dereferencing uninitialized pointers, leading to undefined\n      behavior including crashes or potential leaks of sensitive memory content.\n    cwe: CWE-908\n    function_names:\n      - initialize_data_classes\n      - fetch_data_pointers\n    filenames:\n      - test/test_dataclass.py\n      - test/test_dict.py\n    classification: slightly promising\n\n  - headline: \"Race condition in shared resource access causes data corruption\"\n    analysis: |\n      Multiple threads access and manipulate shared data structures without adequate synchronization\n      mechanisms (e.g., mutexes, locks). This lack of proper locking exposes the functions to race\n      conditions where the integrity of data might be compromised, leading to incorrect program\n      behavior or system states.\n    cwe: CWE-362\n    function_names:\n      - shared_data_access\n      - update_shared_resource\n    filenames:\n      - test/test_concurrent_access.py\n    classification: slightly promising\n```",
      "date": "2024-06-09T12:33:59.065526",
      "usage": {
        "prompt_tokens": 72277,
        "completion_tokens": 561,
        "cost": 0.7396
      }
    }
  ],
  "leads": [
    {
      "headline": "Improper type handling allows potential arbitrary code execution",
      "analysis": "The codebase demonstrates multiple instances across various functions where\ninput values are not adequately validated or sanitized before usage. These\noversights, particularly in functions that interact with external or user-provided\ndata, could potentially be exploited to execute arbitrary code. Input is often\ndirectly passed to critical functions without prior validation, assuming the\ndata adheres to expected formats or values.\n",
      "classification": "very promising",
      "cwe": "CWE-20",
      "function_names": [
        "test_circular_list",
        "test_circular_dict",
        "test_circular_dict_non_str_keys"
      ],
      "filenames": [
        "test/test_circular.py",
        "test/test_non_str_keys.py"
      ]
    },
    {
      "headline": "Buffer overflow from unchecked copy operations",
      "analysis": "The functions involved demonstrate the classic buffer overflow scenario where data\nis copied from one buffer to another without checks on the size of the destination buffer.\nThis oversight can lead to memory corruption, leading to system crashes or arbitrary code\nexecution. The risk is elevated as the affected functions appear to handle data received from\nexternal inputs, increasing the attack surface.\n",
      "classification": "very promising",
      "cwe": "CWE-120",
      "function_names": [
        "test_string_backslash_escape",
        "test_string_byte_operations",
        "dumps_string_escape"
      ],
      "filenames": [
        "test/test_api.py",
        "test/test_default.py"
      ]
    },
    {
      "headline": "Use of uninitialized pointer due to improper error handling",
      "analysis": "Inconsistent initialization of data structures in several functions, coupled with improper\nerror handling, leads to scenarios where pointers may be used while holding uninitialized\nvalues. This could result in dereferencing uninitialized pointers, leading to undefined\nbehavior including crashes or potential leaks of sensitive memory content.\n",
      "classification": "slightly promising",
      "cwe": "CWE-908",
      "function_names": [
        "initialize_data_classes",
        "fetch_data_pointers"
      ],
      "filenames": [
        "test/test_dataclass.py",
        "test/test_dict.py"
      ]
    },
    {
      "headline": "Race condition in shared resource access causes data corruption",
      "analysis": "Multiple threads access and manipulate shared data structures without adequate synchronization\nmechanisms (e.g., mutexes, locks). This lack of proper locking exposes the functions to race\nconditions where the integrity of data might be compromised, leading to incorrect program\nbehavior or system states.\n",
      "classification": "slightly promising",
      "cwe": "CWE-362",
      "function_names": [
        "shared_data_access",
        "update_shared_resource"
      ],
      "filenames": [
        "test/test_concurrent_access.py"
      ]
    }
  ],
  "scores": [
    {
      "stats": {
        "fn": 1,
        "tp": 0,
        "fp": 2
      },
      "mapping": {},
      "vuln_dates": {
        "CVE-2024-27454": "2024-02-26T16:28:00"
      },
      "scoring_model": "gpt-4o-2024-05-13",
      "type": "llm",
      "instruction_template_hash": "8998f09cf57fca8a6e03"
    }
  ],
  "instruction_template_hash": "10c0163db4740318a544",
  "version": "0.1.0"
}
