{
  "commit": "00658265d83d0573168a2f045af154227074870c",
  "repo_url": "https://github.com/open-iscsi/tcmu-runner",
  "model": "gpt-4o-2024-05-13",
  "chunk_hashes": [
    "0426eb50388f6e5c08a2"
  ],
  "responses": [
    {
      "content": "```yaml\nleads:\n  - headline: Buffer Overflow in qcow_header_bswap Function\n    analysis: |\n      The function `qcow_header_bswap` copies data from a source structure `be` to a destination structure `dst` without checking the length or boundaries. This lack of boundary checking may lead to a buffer overflow vulnerability if the source data exceeds the expected size.\n    cwe: CWE-120\n    function_names:\n      - qcow_header_bswap\n    filenames:\n      - qcow.c\n    classification: very promising\n\n  - headline: Integer Overflow in L1 Table Size Calculation\n    analysis: |\n      In the function `qcow_image_open`, the calculation for `l1_size` involves adding a large cluster size shift value to check if the image size is within bounds. If `header.size` is very large, it can cause an integer overflow, leading to improper memory allocation or corruption.\n    cwe: CWE-190\n    function_names:\n      - qcow_image_open\n    filenames:\n      - qcow.c\n    classification: very promising\n\n  - headline: Command Injection in Error Messages\n    analysis: |\n      Throughout the code, there are several instances where error messages are formatted directly with user or system data using `snprintf` and `sprintf` without sanitization. This could lead to command injection vulnerabilities if malicious data is provided. \n    cwe: CWE-88\n    function_names: []\n    filenames:\n      - qcow.c\n      - api.c\n      - qcow2.c\n    classification: slightly promising\n\n  - headline: Use of Potentially Unsafe Alloca Function\n    analysis: |\n      The `alloca` function is used multiple times for allocating memory on the stack. This can lead to stack overflow if the size of the allocation is too large or controlled by a user, leading to potential security vulnerabilities.\n    cwe: CWE-362\n    function_names:\n      - qcow_setup_backing_file\n    filenames:\n      - qcow.c\n    classification: slightly promising\n\n  - headline: Missing Return Value Check in Functions\n    analysis: |\n      Several system call functions such as `pread` and `pwrite` do not have their return values properly checked for errors. This can lead to ignoring critical errors like partial reads/writes or failures, resulting in inconsistent or undefined behavior.\n    cwe: CWE-252\n    function_names: []\n    filenames:\n      - qcow.c\n    classification: very promising\n\n  - headline: Potential Race Condition During File Access\n    analysis: |\n      Functions performing operations with open file descriptors (`openat`, `pread`, `pwrite`) are vulnerable to race conditions if the state of the file is changed between calls. Without proper locking or synchronization, this can lead to data corruption or unauthorized access.\n    cwe: CWE-362\n    function_names: []\n    filenames:\n      - qcow.c\n    classification: very promising\n\n  - headline: Insecure Handling of Encryption Methods\n    analysis: |\n      The validation functions `qcow_validate_header` and `qcow2_validate_header` only print an error when encountering invalid encryption methods but proceed without strong validation of acceptable methods. This can lead to the use of weak or broken encryption algorithms.\n    cwe: CWE-326\n    function_names:\n      - qcow_validate_header\n      - qcow2_validate_header\n    filenames:\n      - qcow.c\n    classification: slightly promising\n\n  - headline: Exposure of Sensitive Information in Log Messages\n    analysis: |\n      Throughout the code, various functions use error printing with potentially sensitive information such as file paths, user inputs, and system states. If logs are accessible to unauthorized users, this can lead to the exposure of sensitive data.\n    cwe: CWE-532\n    function_names: []\n    filenames:\n      - qcow.c\n      - api.c\n    classification: slightly promising\n\n  - headline: Improper Input Validation in qcow_setup_backing_file\n    analysis: |\n      The function `qcow_setup_backing_file` reads the length and path of the backing file without validating the lengths of the input parameters. This can cause overflows or memory corruption if the backing file path length is too large.\n    cwe: CWE-20\n    function_names:\n      - qcow_setup_backing_file\n    filenames:\n      - qcow.c\n    classification: very promising\n\n  - headline: Inadequate Error Handling for malloc and calloc\n    analysis: |\n      There are multiple instances where the return values of `malloc` and `calloc` are not checked. This can lead to null pointer dereference in case of memory allocation failures, which may cause segmentation faults or application crashes.\n    cwe: CWE-476\n    function_names: []\n    filenames:\n      - qcow.c\n    classification: very promising\n```",
      "date": "2024-06-13T10:46:54.106104",
      "usage": {
        "prompt_tokens": 53995,
        "completion_tokens": 1002,
        "cost": 0.285005
      }
    }
  ],
  "leads": [
    {
      "headline": "Buffer Overflow in qcow_header_bswap Function",
      "analysis": "The function qcow_header_bswap copies data from a source structure be to a destination structure dst without checking the length or boundaries. This lack of boundary checking may lead to a buffer overflow vulnerability if the source data exceeds the expected size.\n",
      "classification": "very promising",
      "cwe": "CWE-120",
      "function_names": [
        "qcow_header_bswap"
      ],
      "filenames": [
        "qcow.c"
      ]
    },
    {
      "headline": "Integer Overflow in L1 Table Size Calculation",
      "analysis": "In the function qcow_image_open, the calculation for l1_size involves adding a large cluster size shift value to check if the image size is within bounds. If header.size is very large, it can cause an integer overflow, leading to improper memory allocation or corruption.\n",
      "classification": "very promising",
      "cwe": "CWE-190",
      "function_names": [
        "qcow_image_open"
      ],
      "filenames": [
        "qcow.c"
      ]
    },
    {
      "headline": "Command Injection in Error Messages",
      "analysis": "Throughout the code, there are several instances where error messages are formatted directly with user or system data using snprintf and sprintf without sanitization. This could lead to command injection vulnerabilities if malicious data is provided. \n",
      "classification": "slightly promising",
      "cwe": "CWE-88",
      "function_names": [],
      "filenames": [
        "qcow.c",
        "api.c",
        "qcow2.c"
      ]
    },
    {
      "headline": "Use of Potentially Unsafe Alloca Function",
      "analysis": "The alloca function is used multiple times for allocating memory on the stack. This can lead to stack overflow if the size of the allocation is too large or controlled by a user, leading to potential security vulnerabilities.\n",
      "classification": "slightly promising",
      "cwe": "CWE-362",
      "function_names": [
        "qcow_setup_backing_file"
      ],
      "filenames": [
        "qcow.c"
      ]
    },
    {
      "headline": "Missing Return Value Check in Functions",
      "analysis": "Several system call functions such as pread and pwrite do not have their return values properly checked for errors. This can lead to ignoring critical errors like partial reads/writes or failures, resulting in inconsistent or undefined behavior.\n",
      "classification": "very promising",
      "cwe": "CWE-252",
      "function_names": [],
      "filenames": [
        "qcow.c"
      ]
    },
    {
      "headline": "Potential Race Condition During File Access",
      "analysis": "Functions performing operations with open file descriptors (openat, pread, pwrite) are vulnerable to race conditions if the state of the file is changed between calls. Without proper locking or synchronization, this can lead to data corruption or unauthorized access.\n",
      "classification": "very promising",
      "cwe": "CWE-362",
      "function_names": [],
      "filenames": [
        "qcow.c"
      ]
    },
    {
      "headline": "Insecure Handling of Encryption Methods",
      "analysis": "The validation functions qcow_validate_header and qcow2_validate_header only print an error when encountering invalid encryption methods but proceed without strong validation of acceptable methods. This can lead to the use of weak or broken encryption algorithms.\n",
      "classification": "slightly promising",
      "cwe": "CWE-326",
      "function_names": [
        "qcow_validate_header",
        "qcow2_validate_header"
      ],
      "filenames": [
        "qcow.c"
      ]
    },
    {
      "headline": "Exposure of Sensitive Information in Log Messages",
      "analysis": "Throughout the code, various functions use error printing with potentially sensitive information such as file paths, user inputs, and system states. If logs are accessible to unauthorized users, this can lead to the exposure of sensitive data.\n",
      "classification": "slightly promising",
      "cwe": "CWE-532",
      "function_names": [],
      "filenames": [
        "qcow.c",
        "api.c"
      ]
    },
    {
      "headline": "Improper Input Validation in qcow_setup_backing_file",
      "analysis": "The function qcow_setup_backing_file reads the length and path of the backing file without validating the lengths of the input parameters. This can cause overflows or memory corruption if the backing file path length is too large.\n",
      "classification": "very promising",
      "cwe": "CWE-20",
      "function_names": [
        "qcow_setup_backing_file"
      ],
      "filenames": [
        "qcow.c"
      ]
    },
    {
      "headline": "Inadequate Error Handling for malloc and calloc",
      "analysis": "There are multiple instances where the return values of malloc and calloc are not checked. This can lead to null pointer dereference in case of memory allocation failures, which may cause segmentation faults or application crashes.\n",
      "classification": "very promising",
      "cwe": "CWE-476",
      "function_names": [],
      "filenames": [
        "qcow.c"
      ]
    }
  ],
  "scores": [
    {
      "stats": {
        "fn": 3,
        "tp": 1,
        "fp": 1
      },
      "mapping": {
        "0": "CVE-2017-1000199",
        "1": "CVE-2017-1000199",
        "2": "CVE-2017-1000199",
        "3": "CVE-2017-1000199",
        "4": "CVE-2017-1000199"
      },
      "vuln_dates": {
        "CVE-2017-1000198": "2017-11-17T02:29:00",
        "CVE-2017-1000200": "2017-11-17T02:29:00",
        "CVE-2017-1000199": "2017-11-17T02:29:00",
        "CVE-2017-1000201": "2017-11-17T02:29:01"
      },
      "scoring_model": "claude-3-opus-20240229",
      "type": "llm",
      "instruction_template_hash": "245ace12b6361954d0a2"
    },
    {
      "stats": {
        "fn": 4,
        "tp": 0,
        "fp": 6
      },
      "mapping": {},
      "vuln_dates": {
        "CVE-2017-1000198": "2017-11-17T02:29:00",
        "CVE-2017-1000200": "2017-11-17T02:29:00",
        "CVE-2017-1000199": "2017-11-17T02:29:00",
        "CVE-2017-1000201": "2017-11-17T02:29:01"
      },
      "scoring_model": "claude-3-5-sonnet-20240620",
      "type": "llm",
      "instruction_template_hash": "245ace12b6361954d0a2"
    }
  ],
  "instruction_template_hash": "10c0163db4740318a544",
  "version": "0.1.0"
}
