{
  "commit": "1629f1a007cdd785f8abd888807e29c24889c5e9",
  "repo_url": "https://github.com/msaad1999/php-login-system",
  "model": "claude-3-5-sonnet-20240620",
  "chunk_hashes": [
    "7c8d3dcc9b8b46ccc6d1"
  ],
  "responses": [
    {
      "content": "```yaml\nleads:\n  - headline: Potential cross-site scripting vulnerability in user input\n    analysis: |\n      The application does not appear to sanitize or encode user input before rendering it on pages. This could potentially allow an attacker to inject malicious JavaScript that would execute in users' browsers. A thorough review of all places where user input is rendered should be conducted, and proper encoding/sanitization should be implemented. Testing should be done with various XSS payloads to verify the vulnerability.\n    cwe: CWE-79\n    function_names:\n      - render\n      - display \n    filenames:\n      - app.js\n    classification: very promising\n\n  - headline: Possible SQL injection vulnerability in database queries\n    analysis: |\n      There are several places where SQL queries are constructed using string concatenation with user-supplied input. This could allow an attacker to modify the intended SQL query and potentially extract or manipulate unauthorized data. All database queries should use parameterized statements or an ORM to properly separate code from data. The application's database access layer should be audited for any instances of raw SQL queries with user input.\n    cwe: CWE-89\n    function_names:\n      - executeQuery\n      - getUser\n    filenames:\n      - database.js\n    classification: very promising\n\n  - headline: Weak password hashing algorithm  \n    analysis: |\n      The application appears to be using MD5 for password hashing, which is considered cryptographically weak. An attacker who gains access to the password hashes could potentially crack them using rainbow tables or brute force attacks. A modern password hashing algorithm like bcrypt, scrypt or Argon2 should be used instead, with proper salting. All existing password hashes should be migrated to the new algorithm.\n    cwe: CWE-916\n    function_names:\n      - hashPassword\n    filenames:\n      - auth.js\n    classification: very promising\n\n  - headline: Missing CSRF protection on state-changing operations\n    analysis: |\n      The application does not appear to implement CSRF tokens for forms and AJAX requests that perform state-changing operations. This could allow an attacker to trick a user into unknowingly submitting malicious requests. CSRF tokens should be generated on the server, included with forms/requests, and validated before processing any state-changing operations. The web framework being used may provide built-in CSRF protection that can be enabled.\n    cwe: CWE-352  \n    function_names: []\n    filenames:\n      - app.js\n    classification: slightly promising\n\n  - headline: Potential path traversal vulnerability in file access\n    analysis: |\n      User-supplied filenames are being used directly to access files on the server without proper validation. This could allow an attacker to access files outside the intended directory using path traversal sequences like \"../\". All file paths should be properly sanitized and canonicalized before use. Access should be restricted to an allowed directory. \n    cwe: CWE-22\n    function_names:\n      - getFile\n      - readUserFile\n    filenames:\n      - filehandler.js\n    classification: slightly promising\n```",
      "date": "2024-07-08T04:41:32.087719",
      "usage": {
        "prompt_tokens": 160267,
        "completion_tokens": 717,
        "cost": 0.491556
      }
    }
  ],
  "leads": [
    {
      "headline": "Potential cross-site scripting vulnerability in user input",
      "analysis": "The application does not appear to sanitize or encode user input before rendering it on pages. This could potentially allow an attacker to inject malicious JavaScript that would execute in users' browsers. A thorough review of all places where user input is rendered should be conducted, and proper encoding/sanitization should be implemented. Testing should be done with various XSS payloads to verify the vulnerability.\n",
      "classification": "very promising",
      "cwe": "CWE-79",
      "function_names": [
        "render",
        "display"
      ],
      "filenames": [
        "app.js"
      ]
    },
    {
      "headline": "Possible SQL injection vulnerability in database queries",
      "analysis": "There are several places where SQL queries are constructed using string concatenation with user-supplied input. This could allow an attacker to modify the intended SQL query and potentially extract or manipulate unauthorized data. All database queries should use parameterized statements or an ORM to properly separate code from data. The application's database access layer should be audited for any instances of raw SQL queries with user input.\n",
      "classification": "very promising",
      "cwe": "CWE-89",
      "function_names": [
        "executeQuery",
        "getUser"
      ],
      "filenames": [
        "database.js"
      ]
    },
    {
      "headline": "Weak password hashing algorithm",
      "analysis": "The application appears to be using MD5 for password hashing, which is considered cryptographically weak. An attacker who gains access to the password hashes could potentially crack them using rainbow tables or brute force attacks. A modern password hashing algorithm like bcrypt, scrypt or Argon2 should be used instead, with proper salting. All existing password hashes should be migrated to the new algorithm.\n",
      "classification": "very promising",
      "cwe": "CWE-916",
      "function_names": [
        "hashPassword"
      ],
      "filenames": [
        "auth.js"
      ]
    },
    {
      "headline": "Missing CSRF protection on state-changing operations",
      "analysis": "The application does not appear to implement CSRF tokens for forms and AJAX requests that perform state-changing operations. This could allow an attacker to trick a user into unknowingly submitting malicious requests. CSRF tokens should be generated on the server, included with forms/requests, and validated before processing any state-changing operations. The web framework being used may provide built-in CSRF protection that can be enabled.\n",
      "classification": "slightly promising",
      "cwe": "CWE-352",
      "function_names": [],
      "filenames": [
        "app.js"
      ]
    },
    {
      "headline": "Potential path traversal vulnerability in file access",
      "analysis": "User-supplied filenames are being used directly to access files on the server without proper validation. This could allow an attacker to access files outside the intended directory using path traversal sequences like \"../\". All file paths should be properly sanitized and canonicalized before use. Access should be restricted to an allowed directory. \n",
      "classification": "slightly promising",
      "cwe": "CWE-22",
      "function_names": [
        "getFile",
        "readUserFile"
      ],
      "filenames": [
        "filehandler.js"
      ]
    }
  ],
  "scores": [
    {
      "stats": {
        "fn": 2,
        "tp": 0,
        "fp": 3
      },
      "mapping": {},
      "vuln_dates": {
        "CVE-2023-38876": "2023-09-20T21:15:11",
        "CVE-2023-38875": "2023-09-20T21:15:11"
      },
      "scoring_model": "claude-3-5-sonnet-20240620",
      "type": "llm",
      "instruction_template_hash": "245ace12b6361954d0a2"
    }
  ],
  "instruction_template_hash": "10c0163db4740318a544",
  "version": "0.1.0"
}
