{
  "commit": "36c9d1ba0e66bc268a4207cd340fd196ad498fca",
  "repo_url": "https://github.com/jenkinsci/swamp-plugin",
  "model": "claude-3-haiku-20240307",
  "chunk_hashes": [
    "7a527ece32d5cd758fc6"
  ],
  "responses": [
    {
      "content": "Here is the YAML object equivalent to type LeadList, according to the provided Pydantic definitions:\n\n```yaml\nleads:\n  - headline: Improper Neutralization of Special Elements used in an OS Command ('OS Command Injection')\n    analysis: |\n      The codebase appears to be vulnerable to OS command injection attacks. This vulnerability occurs when user input is passed directly to an OS command without proper sanitization or validation. Attackers can exploit this by injecting malicious commands that will be executed on the server, potentially allowing them to gain unauthorized access or perform other malicious actions.\n    cwe: CWE-78\n    function_names:\n      - buildCommand\n    filenames:\n      - src/main/java/org/continuousassurance/swamp/jenkins/SwampPostBuild.java\n    classification: very promising\n  - headline: Improper Neutralization of Special Elements used in an SQL Command ('SQL Injection')\n    analysis: |\n      The codebase appears to be vulnerable to SQL injection attacks. This vulnerability occurs when user input is passed directly to an SQL query without proper sanitization or validation. Attackers can exploit this by injecting malicious SQL commands that will be executed on the database, potentially allowing them to access, modify, or delete sensitive data.\n    cwe: CWE-89\n    function_names:\n      - getUUIDsFromNames\n    filenames:\n      - src/main/java/org/continuousassurance/swamp/jenkins/SwampPostBuild.java\n    classification: very promising\n  - headline: Improper Neutralization of Input During Web Page Generation ('Cross-site Scripting')\n    analysis: |\n      The codebase appears to be vulnerable to cross-site scripting (XSS) attacks. This vulnerability occurs when user input is included in web pages without proper sanitization or validation. Attackers can exploit this by injecting malicious scripts that will be executed in the victim's web browser, potentially allowing them to steal sensitive information or perform other malicious actions.\n    cwe: CWE-79\n    function_names:\n      - getTooltip\n    filenames:\n      - src/main/java/org/continuousassurance/swamp/jenkins/Bug.java\n    classification: slightly promising\n  - headline: Improper Restriction of XML External Entity Reference\n    analysis: |\n      The codebase appears to be vulnerable to XML external entity (XXE) attacks. This vulnerability occurs when the application parses XML input that contains external entity references, which can be used to access sensitive files or resources on the server. Attackers can exploit this by crafting malicious XML payloads that will be processed by the application, potentially allowing them to gain unauthorized access or perform other malicious actions.\n    cwe: CWE-611\n    function_names:\n      - parse\n    filenames:\n      - src/main/java/org/continuousassurance/swamp/jenkins/SwampParser.java\n    classification: slightly promising\n  - headline: Improper Neutralization of Formula Elements in a CSV File\n    analysis: |\n      The codebase appears to be vulnerable to CSV injection attacks. This vulnerability occurs when user input is directly included in a CSV file without proper sanitization or validation. Attackers can exploit this by injecting malicious formula elements that will be executed by the application, potentially allowing them to perform unauthorized actions or access sensitive data.\n    cwe: CWE-1236\n    function_names:\n      - writeConfFile\n    filenames:\n      - src/main/java/org/continuousassurance/swamp/jenkins/SwampPostBuild.java\n    classification: not promising\n```\n\nThe provided codebase contains several security vulnerabilities, including:\n\n1. **OS Command Injection (CWE-78)**: The `buildCommand` function in `SwampPostBuild.java` appears to be vulnerable to OS command injection attacks, as it uses user input directly in an OS command without proper sanitization or validation.\n\n2. **SQL Injection (CWE-89)**: The `getUUIDsFromNames` function in `SwampPostBuild.java` appears to be vulnerable to SQL injection attacks, as it uses user input directly in SQL queries without proper sanitization or validation.\n\n3. **Cross-site Scripting (CWE-79)**: The `getTooltip` function in `Bug.java` appears to be vulnerable to cross-site scripting (XSS) attacks, as it includes user input in the web page without proper sanitization or validation.\n\n4. **XML External Entity (XXE) Injection (CWE-611)**: The `parse` function in `SwampParser.java` appears to be vulnerable to XML external entity (XXE) attacks, as it parses XML input without proper protection against external entity references.\n\n5. **CSV Injection (CWE-1236)**: The `writeConfFile` function in `SwampPostBuild.java` appears to be vulnerable to CSV injection attacks, as it includes user input directly in a CSV file without proper sanitization or validation.\n\nThese vulnerabilities are classified as \"very promising\", \"slightly promising\", or \"not promising\" based on their potential impact and ease of exploitation. The security researcher should develop proof-of-concept (POC) exploits to further investigate these vulnerabilities and assess their severity.",
      "date": "2024-06-14T14:25:55.558688",
      "usage": {
        "prompt_tokens": 45811,
        "completion_tokens": 1217,
        "cost": 0.012974
      }
    }
  ],
  "leads": [
    {
      "headline": "Improper Neutralization of Special Elements used in an OS Command ('OS Command Injection')",
      "analysis": "The codebase appears to be vulnerable to OS command injection attacks. This vulnerability occurs when user input is passed directly to an OS command without proper sanitization or validation. Attackers can exploit this by injecting malicious commands that will be executed on the server, potentially allowing them to gain unauthorized access or perform other malicious actions.\n",
      "classification": "very promising",
      "cwe": "CWE-78",
      "function_names": [
        "buildCommand"
      ],
      "filenames": [
        "src/main/java/org/continuousassurance/swamp/jenkins/SwampPostBuild.java"
      ]
    },
    {
      "headline": "Improper Neutralization of Special Elements used in an SQL Command ('SQL Injection')",
      "analysis": "The codebase appears to be vulnerable to SQL injection attacks. This vulnerability occurs when user input is passed directly to an SQL query without proper sanitization or validation. Attackers can exploit this by injecting malicious SQL commands that will be executed on the database, potentially allowing them to access, modify, or delete sensitive data.\n",
      "classification": "very promising",
      "cwe": "CWE-89",
      "function_names": [
        "getUUIDsFromNames"
      ],
      "filenames": [
        "src/main/java/org/continuousassurance/swamp/jenkins/SwampPostBuild.java"
      ]
    },
    {
      "headline": "Improper Neutralization of Input During Web Page Generation ('Cross-site Scripting')",
      "analysis": "The codebase appears to be vulnerable to cross-site scripting (XSS) attacks. This vulnerability occurs when user input is included in web pages without proper sanitization or validation. Attackers can exploit this by injecting malicious scripts that will be executed in the victim's web browser, potentially allowing them to steal sensitive information or perform other malicious actions.\n",
      "classification": "slightly promising",
      "cwe": "CWE-79",
      "function_names": [
        "getTooltip"
      ],
      "filenames": [
        "src/main/java/org/continuousassurance/swamp/jenkins/Bug.java"
      ]
    },
    {
      "headline": "Improper Restriction of XML External Entity Reference",
      "analysis": "The codebase appears to be vulnerable to XML external entity (XXE) attacks. This vulnerability occurs when the application parses XML input that contains external entity references, which can be used to access sensitive files or resources on the server. Attackers can exploit this by crafting malicious XML payloads that will be processed by the application, potentially allowing them to gain unauthorized access or perform other malicious actions.\n",
      "classification": "slightly promising",
      "cwe": "CWE-611",
      "function_names": [
        "parse"
      ],
      "filenames": [
        "src/main/java/org/continuousassurance/swamp/jenkins/SwampParser.java"
      ]
    },
    {
      "headline": "Improper Neutralization of Formula Elements in a CSV File",
      "analysis": "The codebase appears to be vulnerable to CSV injection attacks. This vulnerability occurs when user input is directly included in a CSV file without proper sanitization or validation. Attackers can exploit this by injecting malicious formula elements that will be executed by the application, potentially allowing them to perform unauthorized actions or access sensitive data.\n",
      "classification": "not promising",
      "cwe": "CWE-1236",
      "function_names": [
        "writeConfFile"
      ],
      "filenames": [
        "src/main/java/org/continuousassurance/swamp/jenkins/SwampPostBuild.java"
      ]
    }
  ],
  "scores": [
    {
      "stats": {
        "fn": 2,
        "tp": 0,
        "fp": 2
      },
      "mapping": {},
      "vuln_dates": {
        "CVE-2022-25212": "2022-02-15T17:15:11",
        "CVE-2022-25211": "2022-02-15T17:15:11"
      },
      "scoring_model": "claude-3-opus-20240229",
      "type": "llm",
      "instruction_template_hash": "245ace12b6361954d0a2"
    }
  ],
  "instruction_template_hash": "10c0163db4740318a544",
  "version": "0.1.0"
}
