{
  "commit": "0b32641e0c0d7b89ff7e07fc99ef7bde5f654be5",
  "repo_url": "https://github.com/praqma/compatibility-action-storage-plugin",
  "model": "gpt-4-turbo-2024-04-09",
  "chunk_hashes": [
    "8f62e811f9ebf3756063"
  ],
  "responses": [
    {
      "content": "```yaml\nleads:\n  - headline: \"Use of Hard-coded Database Connection Details in Tests\"\n    analysis: |\n      The source code uses hardcoded connection details (host and port) for database connections in the test class (MongoProviderImplTest). This practice lacks flexibility and exposes the system to risks if deployed unchanged in a production environment, where secure and possibly dynamic configuration management should be used.\n    cwe: CWE-798\n    function_names:\n      - \"setUp\"\n    filenames:\n      - \"src/test/java/org/jenkinsci/plugins/compatibilityaction/MongoProviderImplTest.java\"\n    classification: \"slightly promising\"\n\n  - headline: \"Potential Resource Leak Due to Incomplete Exception Handling\"\n    analysis: |\n      The application code includes several places where database connections are opened (`client = getService().createClient();`) but not adequately closed on all code paths, particularly where exceptions are thrown (`CompatibilityDataException`). This can lead to database connections remaining open longer than necessary, consuming resources.\n    cwe: CWE-404\n    function_names:\n      - \"create\"\n      - \"create (TaskListener version)\"\n      - \"read\"\n      - \"readMany\"\n      - \"count\"\n      - \"listAndSort\"\n    filenames:\n      - \"src/main/java/org/jenkinsci/plugins/compatibilityaction/MongoProviderImpl.java\"\n    classification: \"very promising\"\n    \n  - headline: \"Insufficient Authentication Handling in MongoDB Connection Service\"\n    analysis: |\n      The code relies on a plain authentication mechanism wherein credentials are provided as constructor parameters to the MongoDBHolderService. Although it uses the Secret class to handle the password, the practice of handling database credentials directly within application code could lead to improper management or exposure of credentials.\n    cwe: CWE-522\n    function_names:\n      - \"createClient\"\n    filenames:\n      - \"src/main/java/org/jenkinsci/plugins/compatibilityaction/MongoDBHolderService.java\"\n    classification: \"slightly promising\"\n\n  - headline: \"Lack of Proper Error Handling in Database Test Connection\"\n    analysis: |\n      The `testConnection` method in MongoDBHolderService could reveal sensitive information about the database schema or configuration details through its error messages or through the printed debug information when a connection test fails or succeeds.\n    cwe: CWE-209\n    function_names:\n      - \"testConnection\"\n    filenames:\n      - \"src/main/java/org/jenkinsci/plugins/compatibilityaction/MongoDBHolderService.java\"\n    classification: \"slightly promising\"\n\n  - headline: \"Possible Exposure of Internal State and File Structure through Descriptive Error Messages\"\n    analysis: |\n      Custom exception messages in CompatibilityDataException detail internal state or configuration, such as describing problems with object insertions or missed collections, which could aid attackers in tailoring further attacks or understanding the system's setup more deeply.\n    cwe: CWE-209\n    function_names:\n      - \"create\"\n      - \"read\"\n      - \"readMany\"\n      - \"listAndSort\"\n    filenames:\n      - \"src/main/java/org/jenkinsci/plugins/compatibilityaction/MongoProviderImpl.java\"\n      - \"src/main/java/org/jenkinsci/plugins/compatibilityaction/CompatibilityDataException.java\"\n    classification: \"slightly promising\"\n\n  - headline: \"Use of Potentially Unsecure or Obsolete MongoDB Version in Testing\"\n    analysis: |\n      The test setup in `MongoProviderImplTest` class explicitly uses the `.version(Version.Main.PRODUCTION)` which may refer to an outdated or no longer securely supported MongoDB server version for testing purposes, potentially exposing the test environment to known vulnerabilities.\n    cwe: CWE-917\n    function_names:\n      - \"setUp\"\n    filenames:\n      - \"src/test/java/org/jenkinsci/plugins/compatibilityaction/MongoProviderImplTest.java\"\n    classification: \"slightly promising\"\n```",
      "date": "2024-06-13T11:07:22.588080",
      "usage": {
        "prompt_tokens": 8213,
        "completion_tokens": 796,
        "cost": 0.10601
      }
    }
  ],
  "leads": [
    {
      "headline": "Use of Hard-coded Database Connection Details in Tests",
      "analysis": "The source code uses hardcoded connection details (host and port) for database connections in the test class (MongoProviderImplTest). This practice lacks flexibility and exposes the system to risks if deployed unchanged in a production environment, where secure and possibly dynamic configuration management should be used.\n",
      "classification": "slightly promising",
      "cwe": "CWE-798",
      "function_names": [
        "setUp"
      ],
      "filenames": [
        "src/test/java/org/jenkinsci/plugins/compatibilityaction/MongoProviderImplTest.java"
      ]
    },
    {
      "headline": "Potential Resource Leak Due to Incomplete Exception Handling",
      "analysis": "The application code includes several places where database connections are opened (client = getService().createClient();) but not adequately closed on all code paths, particularly where exceptions are thrown (CompatibilityDataException). This can lead to database connections remaining open longer than necessary, consuming resources.\n",
      "classification": "very promising",
      "cwe": "CWE-404",
      "function_names": [
        "create",
        "create (TaskListener version)",
        "read"
      ],
      "filenames": [
        "src/main/java/org/jenkinsci/plugins/compatibilityaction/MongoProviderImpl.java"
      ]
    },
    {
      "headline": "Insufficient Authentication Handling in MongoDB Connection Service",
      "analysis": "The code relies on a plain authentication mechanism wherein credentials are provided as constructor parameters to the MongoDBHolderService. Although it uses the Secret class to handle the password, the practice of handling database credentials directly within application code could lead to improper management or exposure of credentials.\n",
      "classification": "slightly promising",
      "cwe": "CWE-522",
      "function_names": [
        "createClient"
      ],
      "filenames": [
        "src/main/java/org/jenkinsci/plugins/compatibilityaction/MongoDBHolderService.java"
      ]
    },
    {
      "headline": "Lack of Proper Error Handling in Database Test Connection",
      "analysis": "The testConnection method in MongoDBHolderService could reveal sensitive information about the database schema or configuration details through its error messages or through the printed debug information when a connection test fails or succeeds.\n",
      "classification": "slightly promising",
      "cwe": "CWE-209",
      "function_names": [
        "testConnection"
      ],
      "filenames": [
        "src/main/java/org/jenkinsci/plugins/compatibilityaction/MongoDBHolderService.java"
      ]
    },
    {
      "headline": "Possible Exposure of Internal State and File Structure through Descriptive Error Messages",
      "analysis": "Custom exception messages in CompatibilityDataException detail internal state or configuration, such as describing problems with object insertions or missed collections, which could aid attackers in tailoring further attacks or understanding the system's setup more deeply.\n",
      "classification": "slightly promising",
      "cwe": "CWE-209",
      "function_names": [
        "create",
        "read",
        "readMany"
      ],
      "filenames": [
        "src/main/java/org/jenkinsci/plugins/compatibilityaction/MongoProviderImpl.java",
        "src/main/java/org/jenkinsci/plugins/compatibilityaction/CompatibilityDataException.java"
      ]
    },
    {
      "headline": "Use of Potentially Unsecure or Obsolete MongoDB Version in Testing",
      "analysis": "The test setup in MongoProviderImplTest class explicitly uses the .version(Version.Main.PRODUCTION) which may refer to an outdated or no longer securely supported MongoDB server version for testing purposes, potentially exposing the test environment to known vulnerabilities.\n",
      "classification": "slightly promising",
      "cwe": "CWE-917",
      "function_names": [
        "setUp"
      ],
      "filenames": [
        "src/test/java/org/jenkinsci/plugins/compatibilityaction/MongoProviderImplTest.java"
      ]
    }
  ],
  "scores": [
    {
      "stats": {
        "fn": 1,
        "tp": 0,
        "fp": 1
      },
      "mapping": {},
      "vuln_dates": {
        "CVE-2020-2217": "2020-07-02T15:15:18"
      },
      "scoring_model": "claude-3-opus-20240229",
      "type": "llm",
      "instruction_template_hash": "245ace12b6361954d0a2"
    },
    {
      "stats": {
        "fn": 1,
        "tp": 0,
        "fp": 1
      },
      "mapping": {},
      "vuln_dates": {
        "CVE-2020-2217": "2020-07-02T15:15:18"
      },
      "scoring_model": "claude-3-5-sonnet-20240620",
      "type": "llm",
      "instruction_template_hash": "245ace12b6361954d0a2"
    }
  ],
  "instruction_template_hash": "10c0163db4740318a544",
  "version": "0.1.0"
}
