{
  "commit": "1559c2a94bc2655696817861af1c51f307e6d8dd",
  "repo_url": "https://github.com/shutterstock/ntfserver",
  "model": "claude-3-sonnet-20240229",
  "chunk_hashes": [
    "cffca0d287633afddf84"
  ],
  "responses": [
    {
      "content": "Here is the YAML output identifying potential security vulnerabilities in the given codebase, formatted according to the provided Pydantic model definitions:\n\n```yaml\nleads:\n  - headline: Potential SQL Injection vulnerability\n    analysis: |\n      The codebase uses string concatenation to construct SQL queries, which can potentially allow for SQL injection attacks if user input is not properly sanitized before being included in the query string.\n    cwe: CWE-89\n    function_names:\n      - handleAssertion\n      - handleMeta\n      - handleTest\n      - handleSuite\n    filenames:\n      - lib/store.js\n    classification: very promising\n\n  - headline: Potential Command Injection vulnerability\n    analysis: |\n      The codebase uses the 'heapdump' module to write heap snapshots to /tmp, which could potentially be abused to execute arbitrary commands if the file path is not properly sanitized.\n    cwe: CWE-77\n    function_names:\n      - createServer\n    filenames:\n      - lib/index.js\n    classification: slightly promising\n\n  - headline: Potential Cross-Site Scripting (XSS) vulnerability\n    analysis: |\n      The codebase renders user-supplied data in HTML templates without proper sanitization, which could potentially lead to Cross-Site Scripting (XSS) attacks if malicious input is included in the data.\n    cwe: CWE-79\n    function_names:\n      - renderAssertionResult\n      - renderEvent\n      - renderStatus\n      - renderSuite\n      - renderSuiteResult\n      - renderTest\n      - renderTestResult\n    filenames:\n      - lib/api.js\n    classification: very promising\n\n  - headline: Potential Improper Authentication vulnerability\n    analysis: |\n      The codebase does not appear to implement any authentication or authorization mechanisms, potentially allowing unauthorized access to sensitive data or functionality.\n    cwe: CWE-306\n    function_names: []\n    filenames: []\n    classification: very promising\n\n  - headline: Potential Insecure Transmission of Sensitive Information vulnerability\n    analysis: |\n      The codebase does not appear to implement any encryption or secure communication mechanisms, potentially allowing sensitive data (such as database credentials or session tokens) to be transmitted in cleartext.\n    cwe: CWE-319\n    function_names: []\n    filenames: []\n    classification: very promising\n\n  - headline: Potential Use of Hard-coded Credentials vulnerability\n    analysis: |\n      The codebase appears to use hard-coded credentials for the MySQL database connection, which could potentially lead to unauthorized access if these credentials are compromised.\n    cwe: CWE-798\n    function_names:\n      - createServer\n    filenames:\n      - lib/index.js\n    classification: very promising\n\n  - headline: Potential Improper Resource Shutdown or Release vulnerability\n    analysis: |\n      The codebase does not properly clean up or release resources (such as database connections or event emitters) when the application exits, which could potentially lead to resource leaks or other issues.\n    cwe: CWE-404\n    function_names:\n      - tearDownSql\n    filenames:\n      - test/assets/helper.js\n    classification: slightly promising\n```\n\nNote that this analysis is based on a static review of the provided code and may not be exhaustive. Additional vulnerabilities could potentially exist, and further testing and analysis would be required to ensure the security of the application.",
      "date": "2024-06-13T11:41:56.850563",
      "usage": {
        "prompt_tokens": 31793,
        "completion_tokens": 811,
        "cost": 0.107544
      }
    }
  ],
  "leads": [
    {
      "headline": "Potential SQL Injection vulnerability",
      "analysis": "The codebase uses string concatenation to construct SQL queries, which can potentially allow for SQL injection attacks if user input is not properly sanitized before being included in the query string.\n",
      "classification": "very promising",
      "cwe": "CWE-89",
      "function_names": [
        "handleAssertion",
        "handleMeta",
        "handleTest"
      ],
      "filenames": [
        "lib/store.js"
      ]
    },
    {
      "headline": "Potential Command Injection vulnerability",
      "analysis": "The codebase uses the 'heapdump' module to write heap snapshots to /tmp, which could potentially be abused to execute arbitrary commands if the file path is not properly sanitized.\n",
      "classification": "slightly promising",
      "cwe": "CWE-77",
      "function_names": [
        "createServer"
      ],
      "filenames": [
        "lib/index.js"
      ]
    },
    {
      "headline": "Potential Cross-Site Scripting (XSS) vulnerability",
      "analysis": "The codebase renders user-supplied data in HTML templates without proper sanitization, which could potentially lead to Cross-Site Scripting (XSS) attacks if malicious input is included in the data.\n",
      "classification": "very promising",
      "cwe": "CWE-79",
      "function_names": [
        "renderAssertionResult",
        "renderEvent",
        "renderStatus"
      ],
      "filenames": [
        "lib/api.js"
      ]
    },
    {
      "headline": "Potential Improper Authentication vulnerability",
      "analysis": "The codebase does not appear to implement any authentication or authorization mechanisms, potentially allowing unauthorized access to sensitive data or functionality.\n",
      "classification": "very promising",
      "cwe": "CWE-306",
      "function_names": [],
      "filenames": []
    },
    {
      "headline": "Potential Insecure Transmission of Sensitive Information vulnerability",
      "analysis": "The codebase does not appear to implement any encryption or secure communication mechanisms, potentially allowing sensitive data (such as database credentials or session tokens) to be transmitted in cleartext.\n",
      "classification": "very promising",
      "cwe": "CWE-319",
      "function_names": [],
      "filenames": []
    },
    {
      "headline": "Potential Use of Hard-coded Credentials vulnerability",
      "analysis": "The codebase appears to use hard-coded credentials for the MySQL database connection, which could potentially lead to unauthorized access if these credentials are compromised.\n",
      "classification": "very promising",
      "cwe": "CWE-798",
      "function_names": [
        "createServer"
      ],
      "filenames": [
        "lib/index.js"
      ]
    },
    {
      "headline": "Potential Improper Resource Shutdown or Release vulnerability",
      "analysis": "The codebase does not properly clean up or release resources (such as database connections or event emitters) when the application exits, which could potentially lead to resource leaks or other issues.\n",
      "classification": "slightly promising",
      "cwe": "CWE-404",
      "function_names": [
        "tearDownSql"
      ],
      "filenames": [
        "test/assets/helper.js"
      ]
    }
  ],
  "scores": [
    {
      "stats": {
        "fn": 1,
        "tp": 0,
        "fp": 5
      },
      "mapping": {},
      "vuln_dates": {
        "CVE-2016-10650": "2018-05-29T20:29:01"
      },
      "scoring_model": "claude-3-opus-20240229",
      "type": "llm",
      "instruction_template_hash": "245ace12b6361954d0a2"
    },
    {
      "stats": {
        "fn": 1,
        "tp": 0,
        "fp": 5
      },
      "mapping": {},
      "vuln_dates": {
        "CVE-2016-10650": "2018-05-29T20:29:01"
      },
      "scoring_model": "claude-3-5-sonnet-20240620",
      "type": "llm",
      "instruction_template_hash": "245ace12b6361954d0a2"
    }
  ],
  "instruction_template_hash": "10c0163db4740318a544",
  "version": "0.1.0"
}
