{
  "commit": "40aaeff558035334fd29dca90f5c140c43664041",
  "repo_url": "https://github.com/zenoss/zenpacks.zenoss.dashboard",
  "model": "claude-3-haiku-20240307",
  "chunk_hashes": [
    "d6f69be0314a3fd48b26"
  ],
  "responses": [
    {
      "content": "```yaml\nleads:\n  - headline: Cleartext Transmission of Sensitive Information\n    analysis: |\n      The codebase does not properly handle the transmission of sensitive information, such as authentication credentials, over unencrypted communication channels. This can lead to the exposure of sensitive data to unauthorized parties, potentially enabling attacks like eavesdropping and man-in-the-middle attacks.\n    cwe: CWE-319\n    function_names:\n      - saveDashboard\n      - _updateDashboardServerState\n    filenames:\n      - ZenPacks/zenoss/Dashboard/browser/resources/js/controller/DashboardController.js\n    classification: very promising\n\n  - headline: Improper Neutralization of Special Elements used in an OS Command ('OS Command Injection')\n    analysis: |\n      The codebase does not properly sanitize user input before using it in OS commands, potentially allowing an attacker to inject malicious commands and gain unauthorized access or elevate their privileges on the system. This vulnerability could be exploited through the 'saveDashboard' and 'deleteDashboard' functions.\n    cwe: CWE-78\n    function_names:\n      - saveDashboard\n      - deleteDashboard\n    filenames:\n      - ZenPacks/zenoss/Dashboard/browser/resources/js/controller/DashboardController.js\n    classification: very promising\n\n  - headline: Improper Neutralization of Special Elements used in an SQL Command ('SQL Injection')\n    analysis: |\n      The codebase does not properly sanitize user input before using it in SQL queries, potentially allowing an attacker to inject malicious SQL commands and gain unauthorized access to the system's database. This vulnerability could be exploited through the 'saveDashboard' and 'deleteDashboard' functions.\n    cwe: CWE-89\n    function_names:\n      - saveDashboard\n      - deleteDashboard\n    filenames:\n      - ZenPacks/zenoss/Dashboard/browser/resources/js/controller/DashboardController.js\n    classification: very promising\n\n  - headline: Cross-Site Scripting (XSS)\n    analysis: |\n      The codebase does not properly sanitize user input before displaying it on the web page, potentially allowing an attacker to inject malicious scripts that can be executed by the victim's browser. This vulnerability could be exploited through the 'addPortlet' and 'extractPortlet' functions.\n    cwe: CWE-79\n    function_names:\n      - addPortlet\n      - extractPortlet\n    filenames:\n      - ZenPacks/zenoss/Dashboard/browser/resources/js/controller/DashboardController.js\n    classification: very promising\n\n  - headline: Insufficient Verification of Data Authenticity\n    analysis: |\n      The codebase does not properly verify the authenticity of the data received from the server, potentially allowing an attacker to modify the dashboard state and execute arbitrary code on the client-side. This vulnerability could be exploited through the 'saveDashboardState' and 'renderCurrentDashboard' functions.\n    cwe: CWE-345\n    function_names:\n      - saveDashboardState\n      - renderCurrentDashboard\n    filenames:\n      - ZenPacks/zenoss/Dashboard/browser/resources/js/controller/DashboardController.js\n    classification: very promising\n\n  - headline: Improper Neutralization of Formula Elements in a CSV File\n    analysis: |\n      The codebase does not properly sanitize the input used to generate the CSV file, potentially allowing an attacker to inject malicious formulas that can be executed by the spreadsheet software. This vulnerability could be exploited through the 'eventRenderer' function.\n    cwe: CWE-1236\n    function_names:\n      - eventRenderer\n    filenames:\n      - ZenPacks/zenoss/Dashboard/browser/resources/js/defaultportlets.js\n    classification: slightly promising\n\n  - headline: Improper Encoding or Escaping of Output\n    analysis: |\n      The codebase does not properly encode or escape the output before displaying it on the web page, potentially allowing an attacker to inject malicious HTML or JavaScript code. This vulnerability could be exploited through the 'convertToValidHTMLString' function.\n    cwe: CWE-116\n    function_names:\n      - convertToValidHTMLString\n    filenames:\n      - ZenPacks/zenoss/Dashboard/browser/resources/js/defaultportlets.js\n    classification: slightly promising\n```",
      "date": "2024-07-08T09:33:10.841735",
      "usage": {
        "prompt_tokens": 58626,
        "completion_tokens": 1067,
        "cost": 0.01599025
      }
    }
  ],
  "leads": [
    {
      "headline": "Cleartext Transmission of Sensitive Information",
      "analysis": "The codebase does not properly handle the transmission of sensitive information, such as authentication credentials, over unencrypted communication channels. This can lead to the exposure of sensitive data to unauthorized parties, potentially enabling attacks like eavesdropping and man-in-the-middle attacks.\n",
      "classification": "very promising",
      "cwe": "CWE-319",
      "function_names": [
        "saveDashboard",
        "_updateDashboardServerState"
      ],
      "filenames": [
        "ZenPacks/zenoss/Dashboard/browser/resources/js/controller/DashboardController.js"
      ]
    },
    {
      "headline": "Improper Neutralization of Special Elements used in an OS Command ('OS Command Injection')",
      "analysis": "The codebase does not properly sanitize user input before using it in OS commands, potentially allowing an attacker to inject malicious commands and gain unauthorized access or elevate their privileges on the system. This vulnerability could be exploited through the 'saveDashboard' and 'deleteDashboard' functions.\n",
      "classification": "very promising",
      "cwe": "CWE-78",
      "function_names": [
        "saveDashboard",
        "deleteDashboard"
      ],
      "filenames": [
        "ZenPacks/zenoss/Dashboard/browser/resources/js/controller/DashboardController.js"
      ]
    },
    {
      "headline": "Improper Neutralization of Special Elements used in an SQL Command ('SQL Injection')",
      "analysis": "The codebase does not properly sanitize user input before using it in SQL queries, potentially allowing an attacker to inject malicious SQL commands and gain unauthorized access to the system's database. This vulnerability could be exploited through the 'saveDashboard' and 'deleteDashboard' functions.\n",
      "classification": "very promising",
      "cwe": "CWE-89",
      "function_names": [
        "saveDashboard",
        "deleteDashboard"
      ],
      "filenames": [
        "ZenPacks/zenoss/Dashboard/browser/resources/js/controller/DashboardController.js"
      ]
    },
    {
      "headline": "Cross-Site Scripting (XSS)",
      "analysis": "The codebase does not properly sanitize user input before displaying it on the web page, potentially allowing an attacker to inject malicious scripts that can be executed by the victim's browser. This vulnerability could be exploited through the 'addPortlet' and 'extractPortlet' functions.\n",
      "classification": "very promising",
      "cwe": "CWE-79",
      "function_names": [
        "addPortlet",
        "extractPortlet"
      ],
      "filenames": [
        "ZenPacks/zenoss/Dashboard/browser/resources/js/controller/DashboardController.js"
      ]
    },
    {
      "headline": "Insufficient Verification of Data Authenticity",
      "analysis": "The codebase does not properly verify the authenticity of the data received from the server, potentially allowing an attacker to modify the dashboard state and execute arbitrary code on the client-side. This vulnerability could be exploited through the 'saveDashboardState' and 'renderCurrentDashboard' functions.\n",
      "classification": "very promising",
      "cwe": "CWE-345",
      "function_names": [
        "saveDashboardState",
        "renderCurrentDashboard"
      ],
      "filenames": [
        "ZenPacks/zenoss/Dashboard/browser/resources/js/controller/DashboardController.js"
      ]
    },
    {
      "headline": "Improper Neutralization of Formula Elements in a CSV File",
      "analysis": "The codebase does not properly sanitize the input used to generate the CSV file, potentially allowing an attacker to inject malicious formulas that can be executed by the spreadsheet software. This vulnerability could be exploited through the 'eventRenderer' function.\n",
      "classification": "slightly promising",
      "cwe": "CWE-1236",
      "function_names": [
        "eventRenderer"
      ],
      "filenames": [
        "ZenPacks/zenoss/Dashboard/browser/resources/js/defaultportlets.js"
      ]
    },
    {
      "headline": "Improper Encoding or Escaping of Output",
      "analysis": "The codebase does not properly encode or escape the output before displaying it on the web page, potentially allowing an attacker to inject malicious HTML or JavaScript code. This vulnerability could be exploited through the 'convertToValidHTMLString' function.\n",
      "classification": "slightly promising",
      "cwe": "CWE-116",
      "function_names": [
        "convertToValidHTMLString"
      ],
      "filenames": [
        "ZenPacks/zenoss/Dashboard/browser/resources/js/defaultportlets.js"
      ]
    }
  ],
  "scores": [
    {
      "stats": {
        "fn": 1,
        "tp": 0,
        "fp": 5
      },
      "mapping": {},
      "vuln_dates": {
        "CVE-2018-25063": "2023-01-01T09:15:09"
      },
      "scoring_model": "claude-3-5-sonnet-20240620",
      "type": "llm",
      "instruction_template_hash": "245ace12b6361954d0a2"
    }
  ],
  "instruction_template_hash": "10c0163db4740318a544",
  "version": "0.1.0"
}
