{
  "commit": "27bbed0fe459b6a40568ca420f187945109550db",
  "repo_url": "https://github.com/jenkins-infra/update-center2",
  "model": "claude-3-opus-20240229",
  "chunk_hashes": [
    "f1aa3738f91cdefec20b"
  ],
  "responses": [
    {
      "content": "Here are the potential security vulnerabilities I found in the provided codebase:\n\n```yaml\nleads:\n  - headline: Insecure temporary file creation\n    analysis: |\n      In src/main/java/io/jenkins/update_center/ArtifactoryRepositoryImpl.java, the getFile method creates temporary files to cache downloaded artifacts. However, it does not securely create these files. File creation should use the Java NIO Files.createTempFile method to ensure files are created securely and with unique names to avoid predictability and symlink following attacks.\n    cwe: CWE-379\n    function_names:\n      - getFile\n    filenames:\n      - src/main/java/io/jenkins/update_center/ArtifactoryRepositoryImpl.java\n    classification: very promising\n\n  - headline: Use of HTTP instead of HTTPS\n    analysis: |\n      Some code references HTTP URLs instead of HTTPS. For example, HTTP_TO_HTTPS_OVERRIDES in src/main/java/io/jenkins/update_center/HPI.java contains HTTP URLs. Using HTTP exposes communication to eavesdropping and man-in-the-middle attacks. All URLs should consistently use HTTPS.\n    cwe: CWE-319\n    function_names:\n      - referenceHttpUrl\n    filenames:\n      - src/main/java/io/jenkins/update_center/HPI.java\n    classification: very promising\n    \n  - headline: XML parsing vulnerable to XXE\n    analysis: | \n      The XML parsing code in src/main/java/io/jenkins/update_center/HPI.java does not disable external entities when configuring the SAXReader. This could allow XML eXternal Entities (XXE) attacks to access local files or network resources. The SAXReader should be configured with setFeature(\"http://apache.org/xml/features/disallow-doctype-decl\", true) to prevent XXE.\n    cwe: CWE-611\n    function_names:\n      - readCache\n      - createXmlReader\n    filenames:\n      - src/main/java/io/jenkins/update_center/HPI.java\n      - src/main/java/io/jenkins/update_center/XmlCache.java\n    classification: very promising\n\n  - headline: Command injection\n    analysis: |\n      The stage function in DirectoryTreeBuilder.java uses user-controlled input in a command executed using ProcessBuilder. Insufficiently validated, this could allow arbitrary command injection. Input used to construct OS commands should be carefully validated and escaped.\n    cwe: CWE-78\n    function_names:\n      - stage\n    filenames: \n      - src/main/java/io/jenkins/update_center/DirectoryTreeBuilder.java\n    classification: very promising\n\n  - headline: Lack of CSRF protection\n    analysis: |  \n      The update-center.json and other JSON metadata generation endpoints do not appear to implement CSRF protection. Without CSRF protection, forged requests could be submitted to admins to trigger unintended actions. Proper CSRF tokens should be required.\n    cwe: CWE-352\n    function_names:\n      - run\n    filenames:\n      - src/main/java/io/jenkins/update_center/Main.java  \n    classification: slightly promising\n```\n\nThe leads focus on insecure file creation, use of HTTP instead of HTTPS, XML parsing vulnerable to XXE injection, potential OS command injection via ProcessBuilder, and lack of CSRF protection on metadata endpoints. I've included an analysis of each issue, the relevant CWE, and the affected files and functions. Let me know if you need any clarification or have additional questions!",
      "date": "2024-06-12T17:30:18.653760",
      "usage": {
        "prompt_tokens": 76032,
        "completion_tokens": 859,
        "cost": 1.204905
      }
    }
  ],
  "leads": [
    {
      "headline": "Insecure temporary file creation",
      "analysis": "In src/main/java/io/jenkins/update_center/ArtifactoryRepositoryImpl.java, the getFile method creates temporary files to cache downloaded artifacts. However, it does not securely create these files. File creation should use the Java NIO Files.createTempFile method to ensure files are created securely and with unique names to avoid predictability and symlink following attacks.\n",
      "classification": "very promising",
      "cwe": "CWE-379",
      "function_names": [
        "getFile"
      ],
      "filenames": [
        "src/main/java/io/jenkins/update_center/ArtifactoryRepositoryImpl.java"
      ]
    },
    {
      "headline": "Use of HTTP instead of HTTPS",
      "analysis": "Some code references HTTP URLs instead of HTTPS. For example, HTTP_TO_HTTPS_OVERRIDES in src/main/java/io/jenkins/update_center/HPI.java contains HTTP URLs. Using HTTP exposes communication to eavesdropping and man-in-the-middle attacks. All URLs should consistently use HTTPS.\n",
      "classification": "very promising",
      "cwe": "CWE-319",
      "function_names": [
        "referenceHttpUrl"
      ],
      "filenames": [
        "src/main/java/io/jenkins/update_center/HPI.java"
      ]
    },
    {
      "headline": "XML parsing vulnerable to XXE",
      "analysis": "The XML parsing code in src/main/java/io/jenkins/update_center/HPI.java does not disable external entities when configuring the SAXReader. This could allow XML eXternal Entities (XXE) attacks to access local files or network resources. The SAXReader should be configured with setFeature(\"http://apache.org/xml/features/disallow-doctype-decl\", true) to prevent XXE.\n",
      "classification": "very promising",
      "cwe": "CWE-611",
      "function_names": [
        "readCache",
        "createXmlReader"
      ],
      "filenames": [
        "src/main/java/io/jenkins/update_center/HPI.java",
        "src/main/java/io/jenkins/update_center/XmlCache.java"
      ]
    },
    {
      "headline": "Command injection",
      "analysis": "The stage function in DirectoryTreeBuilder.java uses user-controlled input in a command executed using ProcessBuilder. Insufficiently validated, this could allow arbitrary command injection. Input used to construct OS commands should be carefully validated and escaped.\n",
      "classification": "very promising",
      "cwe": "CWE-78",
      "function_names": [
        "stage"
      ],
      "filenames": [
        "src/main/java/io/jenkins/update_center/DirectoryTreeBuilder.java"
      ]
    },
    {
      "headline": "Lack of CSRF protection",
      "analysis": "The update-center.json and other JSON metadata generation endpoints do not appear to implement CSRF protection. Without CSRF protection, forged requests could be submitted to admins to trigger unintended actions. Proper CSRF tokens should be required.\n",
      "classification": "slightly promising",
      "cwe": "CWE-352",
      "function_names": [
        "run"
      ],
      "filenames": [
        "src/main/java/io/jenkins/update_center/Main.java"
      ]
    }
  ],
  "scores": [
    {
      "stats": {
        "fn": 1,
        "tp": 0,
        "fp": 4
      },
      "mapping": {},
      "vuln_dates": {
        "CVE-2023-27905": "2023-03-10T21:15:15"
      },
      "scoring_model": "claude-3-opus-20240229",
      "type": "llm",
      "instruction_template_hash": "245ace12b6361954d0a2"
    },
    {
      "stats": {
        "fn": 1,
        "tp": 0,
        "fp": 4
      },
      "mapping": {},
      "vuln_dates": {
        "CVE-2023-27905": "2023-03-10T21:15:15"
      },
      "scoring_model": "claude-3-5-sonnet-20240620",
      "type": "llm",
      "instruction_template_hash": "245ace12b6361954d0a2"
    }
  ],
  "instruction_template_hash": "10c0163db4740318a544",
  "version": "0.1.0"
}
