{
  "commit": "43714f0463a14ef9d2cee55d689d2bc934e9e7f3",
  "repo_url": "https://github.com/jenkinsci/http-request-plugin",
  "model": "gpt-4o-2024-05-13",
  "chunk_hashes": [
    "d31cbb4440a21d1220fc"
  ],
  "responses": [
    {
      "content": "```yaml\nleads:\n  - headline: \"Insecure credentials storage\"\n    analysis: |\n      The method `registerBasicCredential` stores credentials in a map without any encryption. This could allow attackers with access to system memory to retrieve plain text credentials.\n    cwe: CWE-312\n    function_names:\n      - registerBasicCredential\n    filenames:\n      - src/test/java/jenkins/plugins/http_request/HttpRequestTestBase.java\n    classification: very promising\n\n  - headline: \"Hardcoded credentials\"\n    analysis: |\n      The code uses hardcoded credentials in multiple places for authentication (e.g., \"username1\", \"password1\"). This is visible in the source code and can be exploited by anyone with access to the codebase or the server.\n    cwe: CWE-798\n    function_names:\n      - registerBasicCredential\n      - canDoBasicDigestAuthentication\n    filenames:\n      - src/test/java/jenkins/plugins/http_request/HttpRequestTestBase.java\n      - src/test/java/jenkins/plugins/http_request/HttpRequestTest.java\n    classification: very promising\n\n  - headline: \"Missing encryption for sensitive data\"\n    analysis: |\n      HTTP request bodies and form data are being transmitted without SSL encryption in various parts of the code, especially concerning the upload file or form submissions. This exposes sensitive data to potential sniffers or intermediate proxies.\n    cwe: CWE-311\n    function_names:\n      - sendFileUpload\n      - resolveFormDataParts\n    filenames:\n      - src/test/java/jenkins/plugins/http_request/HttpRequestTest.java\n      - src/test/java/jenkins/plugins/http_request/HttpRequestStepTest.java\n    classification: slightly promising\n\n  - headline: \"Improper validation of input\"\n    analysis: |\n      The method `resolveFormDataParts` doesn't properly validate the filenames which might allow for directory traversal attacks if filenames contain sequences like \"../\".\n    cwe: CWE-20\n    function_names:\n      - resolveFormDataParts\n    filenames:\n      - src/main/java/jenkins/plugins/http_request/HttpRequest.java\n    classification: slightly promising\n\n  - headline: \"Command injection vulnerability\"\n    analysis: |\n      Arguments passed to the HTTP client through the headers or body are not sanitized correctly. User inputs can manipulate HTTP commands, potentially leading to command injection attacks.\n    cwe: CWE-78\n    function_names:\n      - createRequestBase\n      - registerBasicCredential\n    filenames:\n      - src/main/java/jenkins/plugins/http_request/util/HttpClientUtil.java\n      - src/main/java/jenkins/plugins/http_request/HttpRequestTestBase.java\n    classification: very promising\n\n  - headline: \"Incomplete validation of HTTP response codes\"\n    analysis: |\n      The method `responseCodeIsValid` under specific circumstances (such as ranges given in invalid format) permits inappropriate response codes to be deemed acceptable, potentially allowing unwanted HTTP responses to be considered valid.\n    cwe: CWE-20\n    function_names:\n      - responseCodeIsValid\n    filenames:\n      - src/main/java/jenkins/plugins/http_request/HttpRequestExecution.java\n    classification: very promising\n\n  - headline: \"Cleartext transmission of sensitive information\"\n    analysis: |\n      During HTTP requests, if SSL is not configured correctly, sensitive information like credentials and tokens might be transmitted in plaintext, exposing it to interception. This is particularly risky in `doRequest` and `sendAllContentTypes`.\n    cwe: CWE-319\n    function_names:\n      - doRequest\n      - sendAllContentTypes\n    filenames:\n      - src/test/java/jenkins/plugins/http_request/HttpRequestTest.java\n      - src/test/java/jenkins/plugins/http_request/HttpRequestStepTest.java\n    classification: very promising\n\n  - headline: \"Potential reflection attack\"\n    analysis: |\n      The usage of user-controlled inputs in the `HttpRequestExecution` class's logging facilities allows for reflection injection attacks that can manipulate log files or re-pollute request logs.\n    cwe: CWE-913\n    function_names:\n      - call\n    filenames:\n      - src/main/java/jenkins/plugins/http_request/HttpRequestExecution.java\n    classification: very promising\n```",
      "date": "2024-06-14T14:17:29.452510",
      "usage": {
        "prompt_tokens": 50232,
        "completion_tokens": 874,
        "cost": 0.26427
      }
    }
  ],
  "leads": [
    {
      "headline": "Insecure credentials storage",
      "analysis": "The method registerBasicCredential stores credentials in a map without any encryption. This could allow attackers with access to system memory to retrieve plain text credentials.\n",
      "classification": "very promising",
      "cwe": "CWE-312",
      "function_names": [
        "registerBasicCredential"
      ],
      "filenames": [
        "src/test/java/jenkins/plugins/http_request/HttpRequestTestBase.java"
      ]
    },
    {
      "headline": "Hardcoded credentials",
      "analysis": "The code uses hardcoded credentials in multiple places for authentication (e.g., \"username1\", \"password1\"). This is visible in the source code and can be exploited by anyone with access to the codebase or the server.\n",
      "classification": "very promising",
      "cwe": "CWE-798",
      "function_names": [
        "registerBasicCredential",
        "canDoBasicDigestAuthentication"
      ],
      "filenames": [
        "src/test/java/jenkins/plugins/http_request/HttpRequestTestBase.java",
        "src/test/java/jenkins/plugins/http_request/HttpRequestTest.java"
      ]
    },
    {
      "headline": "Missing encryption for sensitive data",
      "analysis": "HTTP request bodies and form data are being transmitted without SSL encryption in various parts of the code, especially concerning the upload file or form submissions. This exposes sensitive data to potential sniffers or intermediate proxies.\n",
      "classification": "slightly promising",
      "cwe": "CWE-311",
      "function_names": [
        "sendFileUpload",
        "resolveFormDataParts"
      ],
      "filenames": [
        "src/test/java/jenkins/plugins/http_request/HttpRequestTest.java",
        "src/test/java/jenkins/plugins/http_request/HttpRequestStepTest.java"
      ]
    },
    {
      "headline": "Improper validation of input",
      "analysis": "The method resolveFormDataParts doesn't properly validate the filenames which might allow for directory traversal attacks if filenames contain sequences like \"../\".\n",
      "classification": "slightly promising",
      "cwe": "CWE-20",
      "function_names": [
        "resolveFormDataParts"
      ],
      "filenames": [
        "src/main/java/jenkins/plugins/http_request/HttpRequest.java"
      ]
    },
    {
      "headline": "Command injection vulnerability",
      "analysis": "Arguments passed to the HTTP client through the headers or body are not sanitized correctly. User inputs can manipulate HTTP commands, potentially leading to command injection attacks.\n",
      "classification": "very promising",
      "cwe": "CWE-78",
      "function_names": [
        "createRequestBase",
        "registerBasicCredential"
      ],
      "filenames": [
        "src/main/java/jenkins/plugins/http_request/util/HttpClientUtil.java",
        "src/main/java/jenkins/plugins/http_request/HttpRequestTestBase.java"
      ]
    },
    {
      "headline": "Incomplete validation of HTTP response codes",
      "analysis": "The method responseCodeIsValid under specific circumstances (such as ranges given in invalid format) permits inappropriate response codes to be deemed acceptable, potentially allowing unwanted HTTP responses to be considered valid.\n",
      "classification": "very promising",
      "cwe": "CWE-20",
      "function_names": [
        "responseCodeIsValid"
      ],
      "filenames": [
        "src/main/java/jenkins/plugins/http_request/HttpRequestExecution.java"
      ]
    },
    {
      "headline": "Cleartext transmission of sensitive information",
      "analysis": "During HTTP requests, if SSL is not configured correctly, sensitive information like credentials and tokens might be transmitted in plaintext, exposing it to interception. This is particularly risky in doRequest and sendAllContentTypes.\n",
      "classification": "very promising",
      "cwe": "CWE-319",
      "function_names": [
        "doRequest",
        "sendAllContentTypes"
      ],
      "filenames": [
        "src/test/java/jenkins/plugins/http_request/HttpRequestTest.java",
        "src/test/java/jenkins/plugins/http_request/HttpRequestStepTest.java"
      ]
    },
    {
      "headline": "Potential reflection attack",
      "analysis": "The usage of user-controlled inputs in the HttpRequestExecution class's logging facilities allows for reflection injection attacks that can manipulate log files or re-pollute request logs.\n",
      "classification": "very promising",
      "cwe": "CWE-913",
      "function_names": [
        "call"
      ],
      "filenames": [
        "src/main/java/jenkins/plugins/http_request/HttpRequestExecution.java"
      ]
    }
  ],
  "scores": [
    {
      "stats": {
        "fn": 0,
        "tp": 1,
        "fp": 5
      },
      "mapping": {
        "0": "CVE-2022-36901"
      },
      "vuln_dates": {
        "CVE-2022-36901": "2022-07-27T15:15:09"
      },
      "scoring_model": "claude-3-opus-20240229",
      "type": "llm",
      "instruction_template_hash": "245ace12b6361954d0a2"
    },
    {
      "stats": {
        "fn": 0,
        "tp": 1,
        "fp": 5
      },
      "mapping": {
        "0": "CVE-2022-36901"
      },
      "vuln_dates": {
        "CVE-2022-36901": "2022-07-27T15:15:09"
      },
      "scoring_model": "claude-3-5-sonnet-20240620",
      "type": "llm",
      "instruction_template_hash": "245ace12b6361954d0a2"
    }
  ],
  "instruction_template_hash": "10c0163db4740318a544",
  "version": "0.1.0"
}
