{
  "commit": "f229c1e8e0c5951213cf3652cfa32c2b7d10bbb8",
  "repo_url": "https://github.com/idurar/idurar-erp-crm",
  "model": "gpt-4-turbo-2024-04-09",
  "chunk_hashes": [
    "a7346cd23da9c109d4d3"
  ],
  "responses": [
    {
      "content": "```yaml\nleads:\n  - headline: Unsanitized Input Leading to Cross-site Scripting (XSS) in Emergency App\n    analysis: |\n      In the emergency app, user input is directly incorporated into the webpage without proper sanitization or validation, potentially allowing an attacker to inject malicious scripts that will be executed in the browser of any user viewing the affected page. This can lead to unauthorized actions being performed, data theft, and other unwanted behaviors within the context of the affected user\u2019s session.\n    cwe: CWE-79\n    function_names:\n      - SendInvoice\n    filenames:\n      - emailTemplate/SendInvoice.js\n    classification: very promising\n  - headline: Insecure Direct Object Reference (IDOR) in ERP Download Function\n    analysis: |\n      The ERP application's download feature allows users to retrieve files from specific directories using path parameters that are directly included in the request without sufficient access control checks. This could allow an authenticated attacker to access sensitive files hosted on the server by manipulating these parameters.\n    cwe: CWE-22\n    function_names:\n      - erpDownloadRouter\n    filenames:\n      - routes/erpRoutes/erpDownloadRouter.js\n    classification: very promising\n  - headline: No Input Validation for PDF Generation Leads to Uncontrolled Resource Consumption\n    analysis: |\n      The application's section for generating PDFs does not validate input properly which results in uncontrolled resource consumption. If an attacker continuously requests PDF generation with complex input, it might overwhelm the system resources, potentially leading to denial-of-service conditions.\n    cwe: CWE-400\n    function_names:\n      - generatePdf\n    filenames:\n      - controllers/corsControllers/custom.js\n    classification: slightly promising\n  - headline: Exposure of Sensitive Information Due to Use of Predictable Resource Locations\n    analysis: |\n      Photos and icons in the system are stored at predictable locations and are directly accessible by changing URL parameters. This could lead to unauthorized disclosure of sensitive data.\n    cwe: CWE-552\n    function_names:\n      - icon\n      - image\n    filenames:\n      - helpers.js\n    classification: slightly promising\n  - headline: User Authentication Credential Leak Via Unprotected Logger Output\n    analysis: |\n      Sensitive information about user credentials and other data is logged without sufficient protection mechanisms. If an attacker gains access to these logs, it might compromise user accounts or other confidential information.\n    cwe: CWE-532\n    function_names:\n      - login\n      - create\n    filenames:\n      - controllers/erpControllers/authJwtController.js\n      - controllers/erpControllers/adminController.js\n    classification: slightly promising\n```",
      "date": "2024-06-09T12:32:29.521076",
      "usage": {
        "prompt_tokens": 60949,
        "completion_tokens": 544,
        "cost": 0.62581
      }
    }
  ],
  "leads": [
    {
      "headline": "Unsanitized Input Leading to Cross-site Scripting (XSS) in Emergency App",
      "analysis": "In the emergency app, user input is directly incorporated into the webpage without proper sanitization or validation, potentially allowing an attacker to inject malicious scripts that will be executed in the browser of any user viewing the affected page. This can lead to unauthorized actions being performed, data theft, and other unwanted behaviors within the context of the affected user\u2019s session.\n",
      "classification": "very promising",
      "cwe": "CWE-79",
      "function_names": [
        "SendInvoice"
      ],
      "filenames": [
        "emailTemplate/SendInvoice.js"
      ]
    },
    {
      "headline": "Insecure Direct Object Reference (IDOR) in ERP Download Function",
      "analysis": "The ERP application's download feature allows users to retrieve files from specific directories using path parameters that are directly included in the request without sufficient access control checks. This could allow an authenticated attacker to access sensitive files hosted on the server by manipulating these parameters.\n",
      "classification": "very promising",
      "cwe": "CWE-22",
      "function_names": [
        "erpDownloadRouter"
      ],
      "filenames": [
        "routes/erpRoutes/erpDownloadRouter.js"
      ]
    },
    {
      "headline": "No Input Validation for PDF Generation Leads to Uncontrolled Resource Consumption",
      "analysis": "The application's section for generating PDFs does not validate input properly which results in uncontrolled resource consumption. If an attacker continuously requests PDF generation with complex input, it might overwhelm the system resources, potentially leading to denial-of-service conditions.\n",
      "classification": "slightly promising",
      "cwe": "CWE-400",
      "function_names": [
        "generatePdf"
      ],
      "filenames": [
        "controllers/corsControllers/custom.js"
      ]
    },
    {
      "headline": "Exposure of Sensitive Information Due to Use of Predictable Resource Locations",
      "analysis": "Photos and icons in the system are stored at predictable locations and are directly accessible by changing URL parameters. This could lead to unauthorized disclosure of sensitive data.\n",
      "classification": "slightly promising",
      "cwe": "CWE-552",
      "function_names": [
        "icon",
        "image"
      ],
      "filenames": [
        "helpers.js"
      ]
    },
    {
      "headline": "User Authentication Credential Leak Via Unprotected Logger Output",
      "analysis": "Sensitive information about user credentials and other data is logged without sufficient protection mechanisms. If an attacker gains access to these logs, it might compromise user accounts or other confidential information.\n",
      "classification": "slightly promising",
      "cwe": "CWE-532",
      "function_names": [
        "login",
        "create"
      ],
      "filenames": [
        "controllers/erpControllers/authJwtController.js",
        "controllers/erpControllers/adminController.js"
      ]
    }
  ],
  "scores": [
    {
      "stats": {
        "fn": 1,
        "tp": 0,
        "fp": 2
      },
      "mapping": {},
      "vuln_dates": {
        "CVE-2023-52265": "2023-12-30T23:15:42"
      },
      "scoring_model": "gpt-4o-2024-05-13",
      "type": "llm",
      "instruction_template_hash": "8998f09cf57fca8a6e03"
    }
  ],
  "instruction_template_hash": "10c0163db4740318a544",
  "version": "0.1.0"
}
