{
  "commit": "48fe028f3ea4b3e7544f03bce21ed6c93320abd4",
  "repo_url": "https://github.com/mayankmetha/rucky",
  "model": "claude-3-haiku-20240307",
  "chunk_hashes": [
    "e4f0e4e8d0741e6f0983"
  ],
  "responses": [
    {
      "content": "```yaml\nleads:\n  - headline: Improper Neutralization of Special Elements used in an OS Command ('OS Command Injection')\n    analysis: |\n      The code in the `USBReceiver` class contains a potential OS command injection vulnerability. The `getRoot()` method uses the `Runtime.getRuntime().exec(\"su\")` call to execute the \"id\" command and check if the device is rooted. However, the output of this command is not properly sanitized, which could allow an attacker to inject and execute arbitrary OS commands.\n    cwe: CWE-78\n    function_names:\n      - getRoot\n    filenames:\n      - app/src/main/java/com/mayank/rucky/receiver/USBReceiver.java\n    classification: very promising\n\n  - headline: Improper Neutralization of Special Elements used in an Expression Language Statement ('Expression Language Injection')\n    analysis: |\n      The `EditorActivity` class uses the `jsonRead()` method to read and parse JSON files. However, the method does not properly validate the input JSON data, which could allow an attacker to inject malicious expression language statements and potentially execute arbitrary code.\n    cwe: CWE-917\n    function_names:\n      - jsonRead\n    filenames:\n      - app/src/main/java/com/mayank/rucky/activity/EditorActivity.java\n    classification: very promising\n\n  - headline: Improper Neutralization of Argument Delimiters in a Command ('Argument Injection')\n    analysis: |\n      The `launchAttack()` method in the `EditorActivity` class concatenates user-provided input (the `scripts` parameter) with hardcoded command strings. This could allow an attacker to inject malicious arguments and potentially execute arbitrary commands.\n    cwe: CWE-88\n    function_names:\n      - launchAttack\n    filenames:\n      - app/src/main/java/com/mayank/rucky/activity/EditorActivity.java\n    classification: very promising\n\n  - headline: Improper Neutralization of Special Elements in Output Used by a Downstream Component ('Injection')\n    analysis: |\n      The `KeylistActivity` class uses the `jsonWrite()` method to write the updated JSON data back to the file. However, the method does not properly sanitize the input data, which could allow an attacker to inject malicious content into the JSON file, potentially leading to further vulnerabilities.\n    cwe: CWE-74\n    function_names:\n      - jsonWrite\n    filenames:\n      - app/src/main/java/com/mayank/rucky/activity/KeylistActivity.java\n    classification: very promising\n\n  - headline: Improper Neutralization of Input During Web Page Generation ('Cross-site Scripting')\n    analysis: |\n      The `BrowserActivity` class loads user-provided URLs in a WebView, which could allow an attacker to inject malicious scripts and execute them in the context of the application, potentially leading to cross-site scripting (XSS) vulnerabilities.\n    cwe: CWE-79\n    function_names:\n      - onCreate\n    filenames:\n      - app/src/main/java/com/mayank/rucky/activity/BrowserActivity.java\n    classification: slightly promising\n\n  - headline: Improper Input Validation\n    analysis: |\n      The `config.getNetworkAddress()` method in the `ConfigActivity` class does not properly validate the input network address, which could allow an attacker to provide a malformed or invalid address and potentially cause issues with the application's functionality.\n    cwe: CWE-20\n    function_names:\n      - networkAddress\n    filenames:\n      - app/src/main/java/com/mayank/rucky/activity/ConfigActivity.java\n    classification: slightly promising\n\n  - headline: Improper Neutralization of Formula Elements in a CSV File\n    analysis: |\n      The `EditorActivity` class saves user-provided scripts to a file, but does not properly sanitize the input, which could allow an attacker to inject malicious formula elements into the saved file and potentially execute them in a spreadsheet or other application that processes the file.\n    cwe: CWE-1236\n    function_names:\n      - SaveBtn.setOnClickListener\n    filenames:\n      - app/src/main/java/com/mayank/rucky/activity/EditorActivity.java\n    classification: slightly promising\n```",
      "date": "2024-06-14T14:47:30.371081",
      "usage": {
        "prompt_tokens": 54192,
        "completion_tokens": 1046,
        "cost": 0.0148555
      }
    }
  ],
  "leads": [
    {
      "headline": "Improper Neutralization of Special Elements used in an OS Command ('OS Command Injection')",
      "analysis": "The code in the USBReceiver class contains a potential OS command injection vulnerability. The getRoot() method uses the Runtime.getRuntime().exec(\"su\") call to execute the \"id\" command and check if the device is rooted. However, the output of this command is not properly sanitized, which could allow an attacker to inject and execute arbitrary OS commands.\n",
      "classification": "very promising",
      "cwe": "CWE-78",
      "function_names": [
        "getRoot"
      ],
      "filenames": [
        "app/src/main/java/com/mayank/rucky/receiver/USBReceiver.java"
      ]
    },
    {
      "headline": "Improper Neutralization of Special Elements used in an Expression Language Statement ('Expression Language Injection')",
      "analysis": "The EditorActivity class uses the jsonRead() method to read and parse JSON files. However, the method does not properly validate the input JSON data, which could allow an attacker to inject malicious expression language statements and potentially execute arbitrary code.\n",
      "classification": "very promising",
      "cwe": "CWE-917",
      "function_names": [
        "jsonRead"
      ],
      "filenames": [
        "app/src/main/java/com/mayank/rucky/activity/EditorActivity.java"
      ]
    },
    {
      "headline": "Improper Neutralization of Argument Delimiters in a Command ('Argument Injection')",
      "analysis": "The launchAttack() method in the EditorActivity class concatenates user-provided input (the scripts parameter) with hardcoded command strings. This could allow an attacker to inject malicious arguments and potentially execute arbitrary commands.\n",
      "classification": "very promising",
      "cwe": "CWE-88",
      "function_names": [
        "launchAttack"
      ],
      "filenames": [
        "app/src/main/java/com/mayank/rucky/activity/EditorActivity.java"
      ]
    },
    {
      "headline": "Improper Neutralization of Special Elements in Output Used by a Downstream Component ('Injection')",
      "analysis": "The KeylistActivity class uses the jsonWrite() method to write the updated JSON data back to the file. However, the method does not properly sanitize the input data, which could allow an attacker to inject malicious content into the JSON file, potentially leading to further vulnerabilities.\n",
      "classification": "very promising",
      "cwe": "CWE-74",
      "function_names": [
        "jsonWrite"
      ],
      "filenames": [
        "app/src/main/java/com/mayank/rucky/activity/KeylistActivity.java"
      ]
    },
    {
      "headline": "Improper Neutralization of Input During Web Page Generation ('Cross-site Scripting')",
      "analysis": "The BrowserActivity class loads user-provided URLs in a WebView, which could allow an attacker to inject malicious scripts and execute them in the context of the application, potentially leading to cross-site scripting (XSS) vulnerabilities.\n",
      "classification": "slightly promising",
      "cwe": "CWE-79",
      "function_names": [
        "onCreate"
      ],
      "filenames": [
        "app/src/main/java/com/mayank/rucky/activity/BrowserActivity.java"
      ]
    },
    {
      "headline": "Improper Input Validation",
      "analysis": "The config.getNetworkAddress() method in the ConfigActivity class does not properly validate the input network address, which could allow an attacker to provide a malformed or invalid address and potentially cause issues with the application's functionality.\n",
      "classification": "slightly promising",
      "cwe": "CWE-20",
      "function_names": [
        "networkAddress"
      ],
      "filenames": [
        "app/src/main/java/com/mayank/rucky/activity/ConfigActivity.java"
      ]
    },
    {
      "headline": "Improper Neutralization of Formula Elements in a CSV File",
      "analysis": "The EditorActivity class saves user-provided scripts to a file, but does not properly sanitize the input, which could allow an attacker to inject malicious formula elements into the saved file and potentially execute them in a spreadsheet or other application that processes the file.\n",
      "classification": "slightly promising",
      "cwe": "CWE-1236",
      "function_names": [
        "SaveBtn.setOnClickListener"
      ],
      "filenames": [
        "app/src/main/java/com/mayank/rucky/activity/EditorActivity.java"
      ]
    }
  ],
  "scores": [
    {
      "stats": {
        "fn": 1,
        "tp": 0,
        "fp": 4
      },
      "mapping": {},
      "vuln_dates": {
        "CVE-2021-41096": "2021-09-27T20:15:07"
      },
      "scoring_model": "claude-3-opus-20240229",
      "type": "llm",
      "instruction_template_hash": "245ace12b6361954d0a2"
    }
  ],
  "instruction_template_hash": "10c0163db4740318a544",
  "version": "0.1.0"
}
