{
  "commit": "1320ffa342f916b8d5e6bffab19f7d98979cde03",
  "repo_url": "https://github.com/bonitasoft/bonita-connector-webservice",
  "model": "gpt-4o-2024-05-13",
  "chunk_hashes": [
    "15193ac23bdae5125d29"
  ],
  "responses": [
    {
      "content": "```yaml\nleads:\n  - headline: \"Hardcoded Credentials in SecureWSConnector\"\n    analysis: |\n      The `SecureWSConnector` class uses hardcoded credentials when invoking web services. Specifically, the \"guest\" username and password are used multiple times in SecureWSConnectorTest methods, making it vulnerable to unauthorized access if these credentials are discovered.\n    cwe: CWE-798\n    function_names:\n      - execute\n      - executeBusinessLogic\n    filenames:\n      - src/main/java/org/bonitasoft/connectors/ws/SecureWSConnector.java\n      - src/test/java/org/bonitasoft/connectors/ws/SecureWSConnectorTest.java\n    classification: \"very promising\"\n\n  - headline: \"XML Injection Vulnerability\"\n    analysis: |\n      The `sanitizeString` method in `SecureWSConnector` uses a lookup translator to remove illegal XML characters but does not enforce any strict XML schema validation, making it possible for crafted XML inputs to bypass sanitization. This can lead to XML injection attacks.\n    cwe: CWE-91\n    function_names:\n      - sanitizeString\n    filenames:\n      - src/main/java/org/bonitasoft/connectors/ws/SecureWSConnector.java\n    classification: \"slightly promising\"\n\n  - headline: \"Information Exposure Through Exception Handling\"\n    analysis: |\n      The exception handling in `ServerThread` and other parts of the codebase may unintentionally expose sensitive information. Logging the stacktrace and exception messages directly without sanitizing the output can leak sensitive internal information to the logs.\n    cwe: CWE-209\n    function_names:\n      - run\n      - execute\n    filenames:\n      - src/test/java/org/bonitasoft/connectors/ws/ServerThread.java\n      - src/main/java/org/bonitasoft/connectors/ws/SecureWSConnector.java\n    classification: \"slightly promising\"\n\n  - headline: \"Unchecked Return Values\"\n    analysis: |\n      The `setInputParameters` and `validateInputParameters` methods in `SecureWSConnector` do not sufficiently check the return values and exceptions of operations like XML transformations. This can result in undefined behavior if invalid data is passed.\n    cwe: CWE-252\n    function_names:\n      - setInputParameters\n      - validateInputParameters\n    filenames:\n      - src/main/java/org/bonitasoft/connectors/ws/SecureWSConnector.java\n    classification: \"slightly promising\"\n\n  - headline: \"Potential Insecure XML Parsing\"\n    analysis: |\n      The `buildResponseDocumentEnvelope`, `buildResponseDocumentBody`, and `getEnvelopeBodyContent` methods in `SecureWSConnector` use XML parsers without properly configuring them to disable external entity expansion (XXE), making the code vulnerable to XXE attacks.\n    cwe: CWE-611\n    function_names:\n      - buildResponseDocumentEnvelope\n      - buildResponseDocumentBody\n      - getEnvelopeBodyContent\n    filenames:\n      - src/main/java/org/bonitasoft/connectors/ws/SecureWSConnector.java\n    classification: \"very promising\"\n```",
      "date": "2024-06-12T15:16:31.630147",
      "usage": {
        "prompt_tokens": 13393,
        "completion_tokens": 630,
        "cost": 0.076415
      }
    }
  ],
  "leads": [
    {
      "headline": "Hardcoded Credentials in SecureWSConnector",
      "analysis": "The SecureWSConnector class uses hardcoded credentials when invoking web services. Specifically, the \"guest\" username and password are used multiple times in SecureWSConnectorTest methods, making it vulnerable to unauthorized access if these credentials are discovered.\n",
      "classification": "very promising",
      "cwe": "CWE-798",
      "function_names": [
        "execute",
        "executeBusinessLogic"
      ],
      "filenames": [
        "src/main/java/org/bonitasoft/connectors/ws/SecureWSConnector.java",
        "src/test/java/org/bonitasoft/connectors/ws/SecureWSConnectorTest.java"
      ]
    },
    {
      "headline": "XML Injection Vulnerability",
      "analysis": "The sanitizeString method in SecureWSConnector uses a lookup translator to remove illegal XML characters but does not enforce any strict XML schema validation, making it possible for crafted XML inputs to bypass sanitization. This can lead to XML injection attacks.\n",
      "classification": "slightly promising",
      "cwe": "CWE-91",
      "function_names": [
        "sanitizeString"
      ],
      "filenames": [
        "src/main/java/org/bonitasoft/connectors/ws/SecureWSConnector.java"
      ]
    },
    {
      "headline": "Information Exposure Through Exception Handling",
      "analysis": "The exception handling in ServerThread and other parts of the codebase may unintentionally expose sensitive information. Logging the stacktrace and exception messages directly without sanitizing the output can leak sensitive internal information to the logs.\n",
      "classification": "slightly promising",
      "cwe": "CWE-209",
      "function_names": [
        "run",
        "execute"
      ],
      "filenames": [
        "src/test/java/org/bonitasoft/connectors/ws/ServerThread.java",
        "src/main/java/org/bonitasoft/connectors/ws/SecureWSConnector.java"
      ]
    },
    {
      "headline": "Unchecked Return Values",
      "analysis": "The setInputParameters and validateInputParameters methods in SecureWSConnector do not sufficiently check the return values and exceptions of operations like XML transformations. This can result in undefined behavior if invalid data is passed.\n",
      "classification": "slightly promising",
      "cwe": "CWE-252",
      "function_names": [
        "setInputParameters",
        "validateInputParameters"
      ],
      "filenames": [
        "src/main/java/org/bonitasoft/connectors/ws/SecureWSConnector.java"
      ]
    },
    {
      "headline": "Potential Insecure XML Parsing",
      "analysis": "The buildResponseDocumentEnvelope, buildResponseDocumentBody, and getEnvelopeBodyContent methods in SecureWSConnector use XML parsers without properly configuring them to disable external entity expansion (XXE), making the code vulnerable to XXE attacks.\n",
      "classification": "very promising",
      "cwe": "CWE-611",
      "function_names": [
        "buildResponseDocumentEnvelope",
        "buildResponseDocumentBody",
        "getEnvelopeBodyContent"
      ],
      "filenames": [
        "src/main/java/org/bonitasoft/connectors/ws/SecureWSConnector.java"
      ]
    }
  ],
  "scores": [
    {
      "stats": {
        "fn": 0,
        "tp": 1,
        "fp": 1
      },
      "mapping": {
        "1": "CVE-2020-36640"
      },
      "vuln_dates": {
        "CVE-2020-36640": "2023-01-05T10:15:09"
      },
      "scoring_model": "claude-3-opus-20240229",
      "type": "llm",
      "instruction_template_hash": "245ace12b6361954d0a2"
    }
  ],
  "instruction_template_hash": "10c0163db4740318a544",
  "version": "0.1.0"
}
