{
  "commit": "4ab0c77e301576320bf476af2f03918322041bcd",
  "repo_url": "https://github.com/pypiserver/pypiserver",
  "model": "gpt-4o-2024-05-13",
  "chunk_hashes": [
    "c062928a4396721e0dc4"
  ],
  "responses": [
    {
      "content": "```yaml\nleads:\n  - headline: \"Possible Command Injection via URL Usage\"\n    analysis: |\n      The section of the code that loads the distribute_setup.py script from a URL (http://python-distribute.org/distribute_setup.py) and executes it via `exec` in the bootstrap.py file is potentially vulnerable to command injection. If the URL or the content fetched from it were tampered with, arbitrary code could be executed.\n    cwe: CWE-94\n    function_names:\n      - exec\n    filenames:\n      - bootstrap.py\n    classification: very promising\n    \n  - headline: \"Hardcoded HTTP URL Without HTTPS\"\n    analysis: |\n      The URL in the bootstrap.py file used to fetch the distribute_setup.py script is using HTTP instead of HTTPS. This leaves the possibility of a man-in-the-middle attack where the content of the script could be altered during transit.\n    cwe: CWE-311\n    function_names:\n      - exec\n    filenames:\n      - bootstrap.py\n    classification: slightly promising\n\n  - headline: \"Bad Practise - Use of eval in Command Line Argument Parsing\"\n    analysis: |\n      In setup.py, using `eval()` for `do_exec` can potentially open up the codebase for exploitation if the input is tampered with before execution. This functionality should be replaced with a safer alternative.\n    cwe: CWE-94\n    function_names:\n      - do_exec\n    filenames:\n      - setup.py\n    classification: very promising\n\n  - headline: \"Potential Information Disclosure via Error Messages\"\n    analysis: |\n      In various parts of the codebase (particularly in `pypiserver/core.py`), logging may potentially expose sensitive information due to verbosity settings and detailed error logging which include stack traces.\n    cwe: CWE-209\n    function_names:\n      - _logwrite\n    filenames:\n      - pypiserver/core.py\n    classification: slightly promising\n\n  - headline: \"Insufficient Randomness in entropic Function\"\n    analysis: |\n      The use of `random` within pypiserver, if weakly seeded, could lead to predictable values in use cases where strong randomness is required.\n    cwe: CWE-330\n    function_names:\n      - _logwrite\n    filenames:\n      - pypiserver/core.py\n    classification: slightly promising\n\n  - headline: \"Mutable Default Arguments in Function Definitions\"\n    analysis: |\n      Functions like those in `bottle` and other parts of the codebase use mutable default arguments which could lead to unexpected behavior through shared state among all instances of the function call.\n    cwe: CWE-710\n    function_names:\n      - execute\n    filenames:\n      - pypiserver/core.py\n    classification: slightly promising\n\n  - headline: \"Possible Race Condition from Concurrent Execution\"\n    analysis: |\n      The caching mechanism in `pypiserver/cache.py` may have potential race conditions as it uses multithreading and mutual exclusions on directories but there's potential for multiple races on the cache state.\n    cwe: CWE-362\n    function_names:\n      - listdir\n      - digest_file\n    filenames:\n      - pypiserver/cache.py\n    classification: slightly promising\n\n  - headline: \"Insufficient URL Validation Leading to SSRF\"\n    analysis: |\n      URL inputs and operations within the codebase are insufficiently vetted, leading to the potential of exploiting server-side request forgery vulnerabilities. \n    cwe: CWE-918\n    function_names:\n      - urlopen\n    filenames:\n      - bootstrap.py\n    classification: not promising\n\n  - headline: \"Improper Restriction of Filename Extensions in File Handling\"\n    analysis: |\n      In test management functionalities where files are handled, if the filename extensions are not properly vetted, it may allow attackers to upload dangerous files.\n    cwe: CWE-434\n    function_names:\n      - file_upload\n    filenames:\n      - pypiserver/_app.py\n    classification: slightly promising\n\n  - headline: \"Weak Error Handling Implementation\"\n    analysis: |\n      Error handling patterns featuring broad `except` clauses may hide errors or implement insufficient measures when critical exceptions occur.\n    cwe: CWE-754\n    function_names:\n      - file_upload\n      - _logwrite\n    filenames:\n      - pypiserver/_app.py\n      - pypiserver/core.py\n    classification: slightly promising\n```",
      "date": "2024-06-14T15:23:25.600507",
      "usage": {
        "prompt_tokens": 65020,
        "completion_tokens": 916,
        "cost": 0.33884
      }
    }
  ],
  "leads": [
    {
      "headline": "Possible Command Injection via URL Usage",
      "analysis": "The section of the code that loads the distribute_setup.py script from a URL (http://python-distribute.org/distribute_setup.py) and executes it via exec in the bootstrap.py file is potentially vulnerable to command injection. If the URL or the content fetched from it were tampered with, arbitrary code could be executed.\n",
      "classification": "very promising",
      "cwe": "CWE-94",
      "function_names": [
        "exec"
      ],
      "filenames": [
        "bootstrap.py"
      ]
    },
    {
      "headline": "Hardcoded HTTP URL Without HTTPS",
      "analysis": "The URL in the bootstrap.py file used to fetch the distribute_setup.py script is using HTTP instead of HTTPS. This leaves the possibility of a man-in-the-middle attack where the content of the script could be altered during transit.\n",
      "classification": "slightly promising",
      "cwe": "CWE-311",
      "function_names": [
        "exec"
      ],
      "filenames": [
        "bootstrap.py"
      ]
    },
    {
      "headline": "Bad Practise - Use of eval in Command Line Argument Parsing",
      "analysis": "In setup.py, using eval() for do_exec can potentially open up the codebase for exploitation if the input is tampered with before execution. This functionality should be replaced with a safer alternative.\n",
      "classification": "very promising",
      "cwe": "CWE-94",
      "function_names": [
        "do_exec"
      ],
      "filenames": [
        "setup.py"
      ]
    },
    {
      "headline": "Potential Information Disclosure via Error Messages",
      "analysis": "In various parts of the codebase (particularly in pypiserver/core.py), logging may potentially expose sensitive information due to verbosity settings and detailed error logging which include stack traces.\n",
      "classification": "slightly promising",
      "cwe": "CWE-209",
      "function_names": [
        "_logwrite"
      ],
      "filenames": [
        "pypiserver/core.py"
      ]
    },
    {
      "headline": "Insufficient Randomness in entropic Function",
      "analysis": "The use of random within pypiserver, if weakly seeded, could lead to predictable values in use cases where strong randomness is required.\n",
      "classification": "slightly promising",
      "cwe": "CWE-330",
      "function_names": [
        "_logwrite"
      ],
      "filenames": [
        "pypiserver/core.py"
      ]
    },
    {
      "headline": "Mutable Default Arguments in Function Definitions",
      "analysis": "Functions like those in bottle and other parts of the codebase use mutable default arguments which could lead to unexpected behavior through shared state among all instances of the function call.\n",
      "classification": "slightly promising",
      "cwe": "CWE-710",
      "function_names": [
        "execute"
      ],
      "filenames": [
        "pypiserver/core.py"
      ]
    },
    {
      "headline": "Possible Race Condition from Concurrent Execution",
      "analysis": "The caching mechanism in pypiserver/cache.py may have potential race conditions as it uses multithreading and mutual exclusions on directories but there's potential for multiple races on the cache state.\n",
      "classification": "slightly promising",
      "cwe": "CWE-362",
      "function_names": [
        "listdir",
        "digest_file"
      ],
      "filenames": [
        "pypiserver/cache.py"
      ]
    },
    {
      "headline": "Insufficient URL Validation Leading to SSRF",
      "analysis": "URL inputs and operations within the codebase are insufficiently vetted, leading to the potential of exploiting server-side request forgery vulnerabilities. \n",
      "classification": "not promising",
      "cwe": "CWE-918",
      "function_names": [
        "urlopen"
      ],
      "filenames": [
        "bootstrap.py"
      ]
    },
    {
      "headline": "Improper Restriction of Filename Extensions in File Handling",
      "analysis": "In test management functionalities where files are handled, if the filename extensions are not properly vetted, it may allow attackers to upload dangerous files.\n",
      "classification": "slightly promising",
      "cwe": "CWE-434",
      "function_names": [
        "file_upload"
      ],
      "filenames": [
        "pypiserver/_app.py"
      ]
    },
    {
      "headline": "Weak Error Handling Implementation",
      "analysis": "Error handling patterns featuring broad except clauses may hide errors or implement insufficient measures when critical exceptions occur.\n",
      "classification": "slightly promising",
      "cwe": "CWE-754",
      "function_names": [
        "file_upload",
        "_logwrite"
      ],
      "filenames": [
        "pypiserver/_app.py",
        "pypiserver/core.py"
      ]
    }
  ],
  "scores": [
    {
      "stats": {
        "fn": 1,
        "tp": 0,
        "fp": 2
      },
      "mapping": {},
      "vuln_dates": {
        "CVE-2019-6802": "2019-01-25T04:29:00"
      },
      "scoring_model": "claude-3-opus-20240229",
      "type": "llm",
      "instruction_template_hash": "245ace12b6361954d0a2"
    }
  ],
  "instruction_template_hash": "10c0163db4740318a544",
  "version": "0.1.0"
}
