{
  "commit": "8e91badbca10f43e78ceeb1ad6daf87ee6e70522",
  "repo_url": "https://github.com/gmarczynski/odoo-web-progress",
  "model": "gpt-4-turbo-2024-04-09",
  "chunk_hashes": [
    "7e9ecb52ac65daa501fc"
  ],
  "responses": [
    {
      "content": "```yaml\nleads:\n  - headline: \"Unsafe Execution of User Input\"\n    analysis: |\n      The codebase incorrectly handles user input, allowing reletion to a command execution vulnerability. The system does not properly validate or escape user-generated values before passing them to server-side processing functions, especially in `jsonRpc`, `jsonpRpc`, `rpc`, and `get_file` functions in 'ajax.js'. This leads to a possible command or SQL injection if these unvalidated values are used to construct dynamic queries or commands. The flaw can also trigger improper file access if user input directs file paths.\n    cwe: CWE-89\n    function_names:\n      - jsonRpc\n      - jsonpRpc\n      - rpc\n      - get_file\n    filenames:\n      - web_progress/static/src/js/ajax.js\n    classification: \"very promising\"\n\n  - headline: \"Inappropriate Exposure of Progress Cancellation Functionalities\"\n    analysis: |\n      The application allows unauthorized or unauthenticated users to cancel ongoing operations/processes, as identified in both the RPC and the report controller (`report_download` method). This critical capability should be restricted to authenticated and authorized individuals, typically those who initiated the task or administrators. Without proper checks, an external actor or unauthorized user could disrupt system operations by sending a crafted request to cancel processes.\n    cwe: CWE-284\n    function_names:\n      - cancel_progress\n      - report_download\n    filenames:\n      - web_progress/models/web_progress.py\n      - web_progress/controllers/main.py\n    classification: \"very promising\"\n\n  - headline: \"Insufficient Access Control Leads to Unauthorized Actions\"\n    analysis: |\n      The function '_report_progress' in 'web_progress.py' allows logged users to report on progress without stringent verification of whether they possess sufficient privileges to post updates about the operation's progress. Additionally, the method to fetch user operations does not verify if the user requesting the information is permitted access to the progress details, potentially exposing sensitive operation progress data to unauthorized users.\n    cwe: CWE-863\n    function_names:\n      - _report_progress\n      - get_user_name\n    filenames:\n      - web_progress/models/web_progress.py\n    classification: \"very promising\"\n\n  - headline: \"Potential Denial of Service Via Progress Calculation\"\n    analysis: |\n      By not limiting the recursion in progress tracking and handling, an attacker can create deep or circular progress relationships which occupy an excessive amount of system resources. This can occur when '_get_total_progress' and '_report_progress_do_percent' deal with progress calculations recursively without proper bounding, increasing the load on the system potentially leading to a denial of service through resource exhaustion.\n    cwe: CWE-674\n    function_names:\n      - _get_progress_total\n      - _report_progress_do_percent\n    filenames:\n      - web_progress/models/web_progress.py\n    classification: \"slightly promising\"\n\n  - headline: \"Use of Outdated or Risky Cryptographic Algorithms\"\n    analysis: |\n      The cryptographic operations do not specify the use of strong, up-to-date algorithms, resulting in potential use of default or weaker cryptographic functions. This is particularly concerning where session identifiers or sensitive data communication regarding progress updates between client and server might be inadequately protected against attackers deciphering or tampering with the data.\n    cwe: CWE-327\n    function_names:\n      - pseudoUuid\n    filenames:\n      - web_progress/static/src/js/ajax.js\n    classification: \"slightly promising\"\n```",
      "date": "2024-06-09T12:19:58.576280",
      "usage": {
        "prompt_tokens": 18625,
        "completion_tokens": 709,
        "cost": 0.20752
      }
    }
  ],
  "leads": [
    {
      "headline": "Unsafe Execution of User Input",
      "analysis": "The codebase incorrectly handles user input, allowing reletion to a command execution vulnerability. The system does not properly validate or escape user-generated values before passing them to server-side processing functions, especially in jsonRpc, jsonpRpc, rpc, and get_file functions in 'ajax.js'. This leads to a possible command or SQL injection if these unvalidated values are used to construct dynamic queries or commands. The flaw can also trigger improper file access if user input directs file paths.\n",
      "classification": "very promising",
      "cwe": "CWE-89",
      "function_names": [
        "jsonRpc",
        "jsonpRpc",
        "rpc"
      ],
      "filenames": [
        "web_progress/static/src/js/ajax.js"
      ]
    },
    {
      "headline": "Inappropriate Exposure of Progress Cancellation Functionalities",
      "analysis": "The application allows unauthorized or unauthenticated users to cancel ongoing operations/processes, as identified in both the RPC and the report controller (report_download method). This critical capability should be restricted to authenticated and authorized individuals, typically those who initiated the task or administrators. Without proper checks, an external actor or unauthorized user could disrupt system operations by sending a crafted request to cancel processes.\n",
      "classification": "very promising",
      "cwe": "CWE-284",
      "function_names": [
        "cancel_progress",
        "report_download"
      ],
      "filenames": [
        "web_progress/models/web_progress.py",
        "web_progress/controllers/main.py"
      ]
    },
    {
      "headline": "Insufficient Access Control Leads to Unauthorized Actions",
      "analysis": "The function '_report_progress' in 'web_progress.py' allows logged users to report on progress without stringent verification of whether they possess sufficient privileges to post updates about the operation's progress. Additionally, the method to fetch user operations does not verify if the user requesting the information is permitted access to the progress details, potentially exposing sensitive operation progress data to unauthorized users.\n",
      "classification": "very promising",
      "cwe": "CWE-863",
      "function_names": [
        "_report_progress",
        "get_user_name"
      ],
      "filenames": [
        "web_progress/models/web_progress.py"
      ]
    },
    {
      "headline": "Potential Denial of Service Via Progress Calculation",
      "analysis": "By not limiting the recursion in progress tracking and handling, an attacker can create deep or circular progress relationships which occupy an excessive amount of system resources. This can occur when '_get_total_progress' and '_report_progress_do_percent' deal with progress calculations recursively without proper bounding, increasing the load on the system potentially leading to a denial of service through resource exhaustion.\n",
      "classification": "slightly promising",
      "cwe": "CWE-674",
      "function_names": [
        "_get_progress_total",
        "_report_progress_do_percent"
      ],
      "filenames": [
        "web_progress/models/web_progress.py"
      ]
    },
    {
      "headline": "Use of Outdated or Risky Cryptographic Algorithms",
      "analysis": "The cryptographic operations do not specify the use of strong, up-to-date algorithms, resulting in potential use of default or weaker cryptographic functions. This is particularly concerning where session identifiers or sensitive data communication regarding progress updates between client and server might be inadequately protected against attackers deciphering or tampering with the data.\n",
      "classification": "slightly promising",
      "cwe": "CWE-327",
      "function_names": [
        "pseudoUuid"
      ],
      "filenames": [
        "web_progress/static/src/js/ajax.js"
      ]
    }
  ],
  "scores": [
    {
      "stats": {
        "fn": 1,
        "tp": 0,
        "fp": 3
      },
      "mapping": {},
      "vuln_dates": {
        "CVE-2023-40954": "2023-12-15T01:15:07"
      },
      "scoring_model": "gpt-4o-2024-05-13",
      "type": "llm",
      "instruction_template_hash": "8998f09cf57fca8a6e03"
    },
    {
      "stats": {
        "fn": 1,
        "tp": 0,
        "fp": 3
      },
      "mapping": {},
      "vuln_dates": {
        "CVE-2023-40954": "2023-12-15T01:15:07"
      },
      "scoring_model": "claude-3-opus-20240229",
      "type": "llm",
      "instruction_template_hash": "245ace12b6361954d0a2"
    }
  ],
  "instruction_template_hash": "10c0163db4740318a544",
  "version": "0.1.0"
}
