{
  "commit": "12ee0af9da502cb47f30ab3ec134ba839c5478a3",
  "repo_url": "https://github.com/venemo/node-lmdb",
  "model": "claude-3-opus-20240229",
  "chunk_hashes": [
    "324f309a8c448d9fa1a0"
  ],
  "responses": [
    {
      "content": "Here are the potential security vulnerabilities I found in the node-lmdb codebase:\n\n```yaml\nleads:\n  - headline: Improper Input Validation in key types\n    analysis: |\n      The library allows specifying the key type (string, binary, uint32) for a database. However, it does not properly validate that the user-provided keys match the specified type when performing database operations. This could allow an attacker to bypass intended key type restrictions and potentially trigger unexpected behavior or crashes by providing keys of the wrong type.\n    cwe: CWE-20\n    function_names:\n      - argToKey\n      - cursorArgToKey\n    filenames:\n      - src/misc.cpp\n      - src/cursor.cpp\n    classification: very promising\n\n  - headline: Out-of-bounds Read when deleting with cursor  \n    analysis: |\n      In the mdb_cursor_del function, the cursor position is not checked before performing a delete operation. If the cursor is positioned on an invalid entry, such as the first or last entry, and a delete is attempted, it could cause an out-of-bounds read of database pages leading to information disclosure or a crash.\n    cwe: CWE-125  \n    function_names:\n      - mdb_cursor_del\n    filenames:\n      - src/txn.cpp\n    classification: slightly promising\n\n  - headline: Potential DoS via excessive iterations in batch writes\n    analysis: | \n      The mdb_env_batchwrite function allows performing a batch of write operations. However, the number of write operations is controlled by user input without any upper bounds checking. An attacker could provide an extremely large number of write operations, causing the function to iterate excessively and consume high CPU, potentially leading to a Denial-of-Service condition.\n    cwe: CWE-834\n    function_names:\n      - batchWrite\n    filenames: \n      - src/env.cpp  \n    classification: slightly promising\n\n  - headline: Uncontrolled Resource Consumption in unconstrained key and data sizes\n    analysis: |\n      Many of the database write functions allow providing arbitrary key and data sizes without enforcing upper size limits. An attacker could provide very large keys and data values to quickly exhaust the available database size and memory, causing a resource exhaustion and Denial-of-Service. Limiting key and data sizes to reasonable maximum values is recommended.\n    cwe: CWE-400\n    function_names:\n      - mdb_put\n      - putString\n      - putBinary\n    filenames:\n      - src/txn.cpp  \n    classification: slightly promising\n```\n\nThe analysis identifies a few potential vulnerabilities related to improper input validation, out-of-bounds reads, uncontrolled resource consumption, and denial of service risks. However, most of these require an attacker to have direct access to the LMDB API calls. Following secure coding best practices like input validation, bounds checking, and resource limits can help mitigate these risks.",
      "date": "2024-06-13T17:30:15.348203",
      "usage": {
        "prompt_tokens": 119218,
        "completion_tokens": 687,
        "cost": 1.839795
      }
    }
  ],
  "leads": [
    {
      "headline": "Improper Input Validation in key types",
      "analysis": "The library allows specifying the key type (string, binary, uint32) for a database. However, it does not properly validate that the user-provided keys match the specified type when performing database operations. This could allow an attacker to bypass intended key type restrictions and potentially trigger unexpected behavior or crashes by providing keys of the wrong type.\n",
      "classification": "very promising",
      "cwe": "CWE-20",
      "function_names": [
        "argToKey",
        "cursorArgToKey"
      ],
      "filenames": [
        "src/misc.cpp",
        "src/cursor.cpp"
      ]
    },
    {
      "headline": "Out-of-bounds Read when deleting with cursor",
      "analysis": "In the mdb_cursor_del function, the cursor position is not checked before performing a delete operation. If the cursor is positioned on an invalid entry, such as the first or last entry, and a delete is attempted, it could cause an out-of-bounds read of database pages leading to information disclosure or a crash.\n",
      "classification": "slightly promising",
      "cwe": "CWE-125",
      "function_names": [
        "mdb_cursor_del"
      ],
      "filenames": [
        "src/txn.cpp"
      ]
    },
    {
      "headline": "Potential DoS via excessive iterations in batch writes",
      "analysis": "The mdb_env_batchwrite function allows performing a batch of write operations. However, the number of write operations is controlled by user input without any upper bounds checking. An attacker could provide an extremely large number of write operations, causing the function to iterate excessively and consume high CPU, potentially leading to a Denial-of-Service condition.\n",
      "classification": "slightly promising",
      "cwe": "CWE-834",
      "function_names": [
        "batchWrite"
      ],
      "filenames": [
        "src/env.cpp"
      ]
    },
    {
      "headline": "Uncontrolled Resource Consumption in unconstrained key and data sizes",
      "analysis": "Many of the database write functions allow providing arbitrary key and data sizes without enforcing upper size limits. An attacker could provide very large keys and data values to quickly exhaust the available database size and memory, causing a resource exhaustion and Denial-of-Service. Limiting key and data sizes to reasonable maximum values is recommended.\n",
      "classification": "slightly promising",
      "cwe": "CWE-400",
      "function_names": [
        "mdb_put",
        "putString",
        "putBinary"
      ],
      "filenames": [
        "src/txn.cpp"
      ]
    }
  ],
  "scores": [
    {
      "stats": {
        "fn": 1,
        "tp": 0,
        "fp": 1
      },
      "mapping": {},
      "vuln_dates": {
        "CVE-2022-21164": "2022-03-16T16:15:10"
      },
      "scoring_model": "claude-3-opus-20240229",
      "type": "llm",
      "instruction_template_hash": "245ace12b6361954d0a2"
    },
    {
      "stats": {
        "fn": 1,
        "tp": 0,
        "fp": 1
      },
      "mapping": {},
      "vuln_dates": {
        "CVE-2022-21164": "2022-03-16T16:15:10"
      },
      "scoring_model": "claude-3-5-sonnet-20240620",
      "type": "llm",
      "instruction_template_hash": "245ace12b6361954d0a2"
    }
  ],
  "instruction_template_hash": "10c0163db4740318a544",
  "version": "0.1.0"
}
