{
  "commit": "2e2df20219f4e5aa557bac6f0a0031a40b5d422b",
  "repo_url": "https://github.com/jenkinsci/maven-release-cascade-plugin",
  "model": "claude-3-sonnet-20240229",
  "chunk_hashes": [
    "adfef682080fb05d99f5"
  ],
  "responses": [
    {
      "content": "Based on the provided code, here are the potential security vulnerabilities I identified, along with their corresponding CWE IDs and details:\n\n```yaml\nleads:\n  - headline: Potential Path Traversal Vulnerability\n    analysis: |\n      The code in the `PluginScm.java` file handles file paths and directories when interacting with\n      the Git version control system. If user input is not properly sanitized, it could lead to a\n      path traversal vulnerability (CWE-22) where an attacker can access or modify files outside of\n      the intended directory.\n    cwe: CWE-22\n    function_names:\n      - PluginScm.scmUpdate\n      - PluginScm.scmCommit\n      - PluginScm.scmCheckout\n    filenames:\n      - src/main/java/com/barchart/jenkins/cascade/PluginScm.java\n    classification: very promising\n\n  - headline: Potential Code Injection Vulnerability\n    analysis: |\n      The `LayoutLogic.java` file contains code that constructs dynamic file paths and executes\n      external programs using the `ProcessBuilder` class. If user input is not properly sanitized,\n      it could lead to a code injection vulnerability (CWE-94) where an attacker can inject and\n      execute arbitrary code on the system.\n    cwe: CWE-94\n    function_names:\n      - LayoutLogic.memberName\n      - LayoutLogic.processMemberUpdate\n      - design.process.ProcessUtil.executeProcess\n    filenames:\n      - src/main/java/com/barchart/jenkins/cascade/LayoutLogic.java\n      - src/test/java/design/process/ProcessUtil.java\n    classification: very promising\n\n  - headline: Potential Insecure Deserialization Vulnerability\n    analysis: |\n      The `SerialClone.java` file contains code that deserializes objects from byte streams. If\n      the deserialization process is not properly secured, it could lead to an insecure\n      deserialization vulnerability (CWE-502) where an attacker can execute arbitrary code by\n      providing a malicious serialized object.\n    cwe: CWE-502\n    function_names:\n      - SerialClone.cloneX\n    filenames:\n      - src/test/java/bench/SerialClone.java\n    classification: slightly promising\n\n  - headline: Potential Insecure Transport Layer Protection\n    analysis: |\n      The code interacts with Git repositories and potentially transmits sensitive data over\n      the network. If the communication channel is not properly secured, it could lead to\n      a lack of transport layer protection vulnerability (CWE-319) where an attacker can intercept\n      and tamper with the transmitted data.\n    cwe: CWE-319\n    function_names:\n      - PluginScm.scmCheckin\n      - PluginScm.scmUpdate\n      - PluginScmGit.doPush\n    filenames:\n      - src/main/java/com/barchart/jenkins/cascade/PluginScm.java\n      - src/main/java/com/barchart/jenkins/cascade/PluginScmGit.java\n    classification: slightly promising\n```\n\nThe provided codebase appears to be a Jenkins plugin for managing Maven projects and their release cycles. The vulnerabilities identified include potential path traversal, code injection, insecure deserialization, and lack of transport layer protection.\n\nIt's important to note that the classification of these vulnerabilities as \"very promising\" or \"slightly promising\" is based on a high-level analysis of the code. A more thorough review and testing would be necessary to confirm the existence and severity of these vulnerabilities.",
      "date": "2024-06-12T18:52:50.797875",
      "usage": {
        "prompt_tokens": 77611,
        "completion_tokens": 885,
        "cost": 0.246108
      }
    }
  ],
  "leads": [
    {
      "headline": "Potential Path Traversal Vulnerability",
      "analysis": "The code in the PluginScm.java file handles file paths and directories when interacting with\nthe Git version control system. If user input is not properly sanitized, it could lead to a\npath traversal vulnerability (CWE-22) where an attacker can access or modify files outside of\nthe intended directory.\n",
      "classification": "very promising",
      "cwe": "CWE-22",
      "function_names": [
        "PluginScm.scmUpdate",
        "PluginScm.scmCommit",
        "PluginScm.scmCheckout"
      ],
      "filenames": [
        "src/main/java/com/barchart/jenkins/cascade/PluginScm.java"
      ]
    },
    {
      "headline": "Potential Code Injection Vulnerability",
      "analysis": "The LayoutLogic.java file contains code that constructs dynamic file paths and executes\nexternal programs using the ProcessBuilder class. If user input is not properly sanitized,\nit could lead to a code injection vulnerability (CWE-94) where an attacker can inject and\nexecute arbitrary code on the system.\n",
      "classification": "very promising",
      "cwe": "CWE-94",
      "function_names": [
        "LayoutLogic.memberName",
        "LayoutLogic.processMemberUpdate",
        "design.process.ProcessUtil.executeProcess"
      ],
      "filenames": [
        "src/main/java/com/barchart/jenkins/cascade/LayoutLogic.java",
        "src/test/java/design/process/ProcessUtil.java"
      ]
    },
    {
      "headline": "Potential Insecure Deserialization Vulnerability",
      "analysis": "The SerialClone.java file contains code that deserializes objects from byte streams. If\nthe deserialization process is not properly secured, it could lead to an insecure\ndeserialization vulnerability (CWE-502) where an attacker can execute arbitrary code by\nproviding a malicious serialized object.\n",
      "classification": "slightly promising",
      "cwe": "CWE-502",
      "function_names": [
        "SerialClone.cloneX"
      ],
      "filenames": [
        "src/test/java/bench/SerialClone.java"
      ]
    },
    {
      "headline": "Potential Insecure Transport Layer Protection",
      "analysis": "The code interacts with Git repositories and potentially transmits sensitive data over\nthe network. If the communication channel is not properly secured, it could lead to\na lack of transport layer protection vulnerability (CWE-319) where an attacker can intercept\nand tamper with the transmitted data.\n",
      "classification": "slightly promising",
      "cwe": "CWE-319",
      "function_names": [
        "PluginScm.scmCheckin",
        "PluginScm.scmUpdate",
        "PluginScmGit.doPush"
      ],
      "filenames": [
        "src/main/java/com/barchart/jenkins/cascade/PluginScm.java",
        "src/main/java/com/barchart/jenkins/cascade/PluginScmGit.java"
      ]
    }
  ],
  "scores": [
    {
      "stats": {
        "fn": 2,
        "tp": 0,
        "fp": 2
      },
      "mapping": {},
      "vuln_dates": {
        "CVE-2020-2295": "2020-10-08T13:15:11",
        "CVE-2020-2294": "2020-10-08T13:15:11"
      },
      "scoring_model": "claude-3-opus-20240229",
      "type": "llm",
      "instruction_template_hash": "245ace12b6361954d0a2"
    }
  ],
  "instruction_template_hash": "10c0163db4740318a544",
  "version": "0.1.0"
}
