{
  "commit": "ba8c701292e4720b4e10210b266be5666d098fb6",
  "repo_url": "https://github.com/ijl/orjson",
  "model": "gpt-4o-2024-05-13",
  "chunk_hashes": [
    "0dfeca17dec9640b0b88"
  ],
  "responses": [
    {
      "content": "```yaml\nleads:\n  - headline: \"Possible Circular Reference in Dictionaries\"\n    analysis: |\n      The code in `test/test_circular.py` could result in a circular reference when dictionaries reference themselves, which can lead to Recursive Injection or Memory Consumption issues.\n    cwe: CWE-674\n    function_names:\n      - test_circular_dict\n      - test_circular_dict_sort_keys\n      - test_circular_dict_non_str_keys\n    filenames:\n      - test/test_circular.py\n    classification: slightly promising\n\n  - headline: \"Use of Undocumented Feature in Flask WSGI\"\n    analysis: |\n      The `orjson.Fragment` used within the Flask application's route in `integration/wsgi.py` directly manipulates JSON fragments, which might bypass normal serialization checks and introduce security risks such as JSON injection.\n    cwe: CWE-502\n    function_names: []\n    filenames:\n      - integration/wsgi.py\n    classification: very promising\n\n  - headline: \"Insecure Deployment Configuration\"\n    analysis: |\n      The `integration/wsgi.py` example does not set critical security headers which can lead to various attacks such as Cross-Site Request Forgery (CSRF), Clickjacking, Content Type sniffing, etc.\n    cwe: CWE-311\n    function_names: []\n    filenames:\n      - integration/wsgi.py\n    classification: very promising\n\n  - headline: \"Missing Error Handling in Fragment Parsing\"\n    analysis: |\n      The fragment parsing in `test/test_fragment.py` lacks robust error handling, potentially leading to unchecked exceptions and older versions of `orjson` could allow injection vulnerabilities via crafted fragments.\n    cwe: CWE-754\n    function_names:\n      - test_fragment_fragment_str_invalid\n      - test_fragment_fragment_bytes_invalid\n    filenames:\n      - test/test_fragment.py\n    classification: slightly promising\n\n  - headline: \"Unrestricted Deserialization of Arbitrary Data\"\n    analysis: |\n      The presence of tests for various invalid JSONs in `test/test_jsonchecker.py` suggests there might be vectors for deserialization attacks if input data is not properly sanitized and validated.\n    cwe: CWE-502\n    function_names: []\n    filenames:\n      - test/test_jsonchecker.py\n    classification: slightly promising\n\n  - headline: \"Handling of Non-String Dictionary Keys\"\n    analysis: |\n      The test cases in `test/test_non_str_keys.py` highlight the handling of dictionaries with non-string keys, which could lead to issues if these keys are not properly validated and coerced to stable formats.\n    cwe: CWE-841\n    function_names:\n      - test_dict_keys_non_str_keys\n      - test_dict_keys_int\n      - test_dict_keys_strict\n    filenames:\n      - test/test_non_str_keys.py\n    classification: slightly promising\n\n  - headline: \"Unhandled Edge Cases in JSON String Handling\"\n    analysis: |\n      The test cases in `test/test_string.py` may not cover all edge cases, potentially leaving vulnerabilities for invalid JSON strings, especially when dealing with untrusted input.\n    cwe: CWE-74\n    function_names:\n      - test_bad_string\n    filenames:\n      - test/test_string.py\n    classification: slightly promising\n\n  - headline: \"Insecure Handling of Large JSON Objects\"\n    analysis: |\n      Test cases like `test_large_dict.py` indicate that decoding large JSON files could result in significant resource consumption or buffer overflow if not properly managed.\n    cwe: CWE-400\n    function_names: []\n    filenames:\n      - test/test_large_dict.py\n    classification: slightly promising\n```",
      "date": "2024-06-09T12:33:43.743198",
      "usage": {
        "prompt_tokens": 72558,
        "completion_tokens": 744,
        "cost": 0.37395
      }
    }
  ],
  "leads": [
    {
      "headline": "Possible Circular Reference in Dictionaries",
      "analysis": "The code in test/test_circular.py could result in a circular reference when dictionaries reference themselves, which can lead to Recursive Injection or Memory Consumption issues.\n",
      "classification": "slightly promising",
      "cwe": "CWE-674",
      "function_names": [
        "test_circular_dict",
        "test_circular_dict_sort_keys",
        "test_circular_dict_non_str_keys"
      ],
      "filenames": [
        "test/test_circular.py"
      ]
    },
    {
      "headline": "Use of Undocumented Feature in Flask WSGI",
      "analysis": "The orjson.Fragment used within the Flask application's route in integration/wsgi.py directly manipulates JSON fragments, which might bypass normal serialization checks and introduce security risks such as JSON injection.\n",
      "classification": "very promising",
      "cwe": "CWE-502",
      "function_names": [],
      "filenames": [
        "integration/wsgi.py"
      ]
    },
    {
      "headline": "Insecure Deployment Configuration",
      "analysis": "The integration/wsgi.py example does not set critical security headers which can lead to various attacks such as Cross-Site Request Forgery (CSRF), Clickjacking, Content Type sniffing, etc.\n",
      "classification": "very promising",
      "cwe": "CWE-311",
      "function_names": [],
      "filenames": [
        "integration/wsgi.py"
      ]
    },
    {
      "headline": "Missing Error Handling in Fragment Parsing",
      "analysis": "The fragment parsing in test/test_fragment.py lacks robust error handling, potentially leading to unchecked exceptions and older versions of orjson could allow injection vulnerabilities via crafted fragments.\n",
      "classification": "slightly promising",
      "cwe": "CWE-754",
      "function_names": [
        "test_fragment_fragment_str_invalid",
        "test_fragment_fragment_bytes_invalid"
      ],
      "filenames": [
        "test/test_fragment.py"
      ]
    },
    {
      "headline": "Unrestricted Deserialization of Arbitrary Data",
      "analysis": "The presence of tests for various invalid JSONs in test/test_jsonchecker.py suggests there might be vectors for deserialization attacks if input data is not properly sanitized and validated.\n",
      "classification": "slightly promising",
      "cwe": "CWE-502",
      "function_names": [],
      "filenames": [
        "test/test_jsonchecker.py"
      ]
    },
    {
      "headline": "Handling of Non-String Dictionary Keys",
      "analysis": "The test cases in test/test_non_str_keys.py highlight the handling of dictionaries with non-string keys, which could lead to issues if these keys are not properly validated and coerced to stable formats.\n",
      "classification": "slightly promising",
      "cwe": "CWE-841",
      "function_names": [
        "test_dict_keys_non_str_keys",
        "test_dict_keys_int",
        "test_dict_keys_strict"
      ],
      "filenames": [
        "test/test_non_str_keys.py"
      ]
    },
    {
      "headline": "Unhandled Edge Cases in JSON String Handling",
      "analysis": "The test cases in test/test_string.py may not cover all edge cases, potentially leaving vulnerabilities for invalid JSON strings, especially when dealing with untrusted input.\n",
      "classification": "slightly promising",
      "cwe": "CWE-74",
      "function_names": [
        "test_bad_string"
      ],
      "filenames": [
        "test/test_string.py"
      ]
    },
    {
      "headline": "Insecure Handling of Large JSON Objects",
      "analysis": "Test cases like test_large_dict.py indicate that decoding large JSON files could result in significant resource consumption or buffer overflow if not properly managed.\n",
      "classification": "slightly promising",
      "cwe": "CWE-400",
      "function_names": [],
      "filenames": [
        "test/test_large_dict.py"
      ]
    }
  ],
  "scores": [
    {
      "stats": {
        "fn": 1,
        "tp": 0,
        "fp": 2
      },
      "mapping": {},
      "vuln_dates": {
        "CVE-2024-27454": "2024-02-26T16:28:00"
      },
      "scoring_model": "gpt-4o-2024-05-13",
      "type": "llm",
      "instruction_template_hash": "8998f09cf57fca8a6e03"
    },
    {
      "stats": {
        "fn": 1,
        "tp": 0,
        "fp": 2
      },
      "mapping": {},
      "vuln_dates": {
        "CVE-2024-27454": "2024-02-26T16:28:00"
      },
      "scoring_model": "claude-3-opus-20240229",
      "type": "llm",
      "instruction_template_hash": "245ace12b6361954d0a2"
    }
  ],
  "instruction_template_hash": "10c0163db4740318a544",
  "version": "0.1.0"
}
