{
  "commit": "01b947e0058c79a77901a2c3afdb0cbfd4cf9427",
  "repo_url": "https://github.com/jenkinsci/eagle-tester-plugin",
  "model": "claude-3-sonnet-20240229",
  "chunk_hashes": [
    "10c0c29d7ba0f12451e3"
  ],
  "responses": [
    {
      "content": "```yaml\nleads:\n  - headline: Potential path traversal vulnerability\n    analysis: |\n      The `getExternalFilePath` method in the `DeviceUtils` class constructs a file path using user-supplied input (`relativeFilePath`). If this input is not sanitized, an attacker could potentially traverse the filesystem and access or modify unintended files.\n    cwe: CWE-22\n    function_names:\n      - com.mobileenerlytics.eagle.tester.common.util.DeviceUtils.getExternalFilePath\n    filenames:\n      - src/main/java/com/mobileenerlytics/eagle/tester/common/util/DeviceUtils.java\n    classification: very promising\n\n  - headline: Potential command injection vulnerability\n    analysis: |\n      The `runAdb` method in the `DeviceUtils` class executes system commands by constructing a command string from user-supplied input (`device` and `cmd`). If this input is not sanitized, an attacker could potentially inject arbitrary system commands.\n    cwe: CWE-78\n    function_names:\n      - com.mobileenerlytics.eagle.tester.common.util.DeviceUtils.runAdb\n    filenames:\n      - src/main/java/com/mobileenerlytics/eagle/tester/common/util/DeviceUtils.java\n    classification: very promising\n\n  - headline: Potential cleartext transmission of sensitive information\n    analysis: |\n      The `NetUtils` class transmits sensitive information (username and password) over an unencrypted HTTP connection when authenticating with the Eagle server. This could allow an attacker to intercept and obtain the credentials.\n    cwe: CWE-319\n    function_names:\n      - com.mobileenerlytics.eagle.tester.common.util.NetUtils.formAuthenticate\n      - com.mobileenerlytics.eagle.tester.common.util.NetUtils.setAuthHeader\n    filenames:\n      - src/main/java/com/mobileenerlytics/eagle/tester/common/util/NetUtils.java\n    classification: very promising\n\n  - headline: Potential hard-coded credentials\n    analysis: |\n      The `LicenseVerifier` class appears to use a hard-coded password (`ycndajxc`) for decrypting the public key used for license verification. Hard-coded credentials are a security risk as they can be easily discovered and exploited.\n    cwe: CWE-798\n    function_names:\n      - com.mobileenerlytics.eagle.tester.common.util.LicenseVerifier.getPassword\n    filenames:\n      - src/main/java/com/mobileenerlytics/eagle/tester/common/util/LicenseVerifier.java\n    classification: very promising\n\n  - headline: Potential unrestricted file upload vulnerability\n    analysis: |\n      The `LargeFileUploadTest` class uploads a large file to the Eagle server without any apparent validation or restrictions on the file type or content. This could allow an attacker to upload and execute arbitrary code on the server.\n    cwe: CWE-434\n    function_names:\n      - com.mobileenerlytics.eagle.tester.common.util.LargeFileUploadTest.uploadTest\n    filenames:\n      - src/test/java/com/mobileenerlytics/eagle/tester/common/util/LargeFileUploadTest.java\n    classification: very promising\n\n  - headline: Potential buffer overflow vulnerability\n    analysis: |\n      The `LocalOperation` class appears to create a large file (`traces.zip`) without bounds checking, which could potentially lead to a buffer overflow condition. However, more context would be needed to confirm this vulnerability.\n    cwe: CWE-120\n    function_names:\n      - com.mobileenerlytics.eagle.tester.LocalOperation.after\n    filenames:\n      - src/main/java/com/mobileenerlytics/eagle/tester/LocalOperation.java\n    classification: slightly promising\n\n  - headline: Potential use of insecure cryptographic algorithm\n    analysis: |\n      The `LicenseVerifier` class uses the Base64 encoding algorithm, which is not a secure cryptographic algorithm for encryption or hashing. While Base64 is often used for encoding binary data, it does not provide any security guarantees and should not be used for cryptographic purposes.\n    cwe: CWE-327\n    function_names:\n      - com.mobileenerlytics.eagle.tester.common.util.LicenseVerifier.EagleLicenseProvider.getLicenseData\n    filenames:\n      - src/main/java/com/mobileenerlytics/eagle/tester/common/util/LicenseVerifier.java\n    classification: slightly promising\n```",
      "date": "2024-06-12T18:22:07.447474",
      "usage": {
        "prompt_tokens": 13058,
        "completion_tokens": 1141,
        "cost": 0.056289
      }
    }
  ],
  "leads": [
    {
      "headline": "Potential path traversal vulnerability",
      "analysis": "The getExternalFilePath method in the DeviceUtils class constructs a file path using user-supplied input (relativeFilePath). If this input is not sanitized, an attacker could potentially traverse the filesystem and access or modify unintended files.\n",
      "classification": "very promising",
      "cwe": "CWE-22",
      "function_names": [
        "com.mobileenerlytics.eagle.tester.common.util.DeviceUtils.getExternalFilePath"
      ],
      "filenames": [
        "src/main/java/com/mobileenerlytics/eagle/tester/common/util/DeviceUtils.java"
      ]
    },
    {
      "headline": "Potential command injection vulnerability",
      "analysis": "The runAdb method in the DeviceUtils class executes system commands by constructing a command string from user-supplied input (device and cmd). If this input is not sanitized, an attacker could potentially inject arbitrary system commands.\n",
      "classification": "very promising",
      "cwe": "CWE-78",
      "function_names": [
        "com.mobileenerlytics.eagle.tester.common.util.DeviceUtils.runAdb"
      ],
      "filenames": [
        "src/main/java/com/mobileenerlytics/eagle/tester/common/util/DeviceUtils.java"
      ]
    },
    {
      "headline": "Potential cleartext transmission of sensitive information",
      "analysis": "The NetUtils class transmits sensitive information (username and password) over an unencrypted HTTP connection when authenticating with the Eagle server. This could allow an attacker to intercept and obtain the credentials.\n",
      "classification": "very promising",
      "cwe": "CWE-319",
      "function_names": [
        "com.mobileenerlytics.eagle.tester.common.util.NetUtils.formAuthenticate",
        "com.mobileenerlytics.eagle.tester.common.util.NetUtils.setAuthHeader"
      ],
      "filenames": [
        "src/main/java/com/mobileenerlytics/eagle/tester/common/util/NetUtils.java"
      ]
    },
    {
      "headline": "Potential hard-coded credentials",
      "analysis": "The LicenseVerifier class appears to use a hard-coded password (ycndajxc) for decrypting the public key used for license verification. Hard-coded credentials are a security risk as they can be easily discovered and exploited.\n",
      "classification": "very promising",
      "cwe": "CWE-798",
      "function_names": [
        "com.mobileenerlytics.eagle.tester.common.util.LicenseVerifier.getPassword"
      ],
      "filenames": [
        "src/main/java/com/mobileenerlytics/eagle/tester/common/util/LicenseVerifier.java"
      ]
    },
    {
      "headline": "Potential unrestricted file upload vulnerability",
      "analysis": "The LargeFileUploadTest class uploads a large file to the Eagle server without any apparent validation or restrictions on the file type or content. This could allow an attacker to upload and execute arbitrary code on the server.\n",
      "classification": "very promising",
      "cwe": "CWE-434",
      "function_names": [
        "com.mobileenerlytics.eagle.tester.common.util.LargeFileUploadTest.uploadTest"
      ],
      "filenames": [
        "src/test/java/com/mobileenerlytics/eagle/tester/common/util/LargeFileUploadTest.java"
      ]
    },
    {
      "headline": "Potential buffer overflow vulnerability",
      "analysis": "The LocalOperation class appears to create a large file (traces.zip) without bounds checking, which could potentially lead to a buffer overflow condition. However, more context would be needed to confirm this vulnerability.\n",
      "classification": "slightly promising",
      "cwe": "CWE-120",
      "function_names": [
        "com.mobileenerlytics.eagle.tester.LocalOperation.after"
      ],
      "filenames": [
        "src/main/java/com/mobileenerlytics/eagle/tester/LocalOperation.java"
      ]
    },
    {
      "headline": "Potential use of insecure cryptographic algorithm",
      "analysis": "The LicenseVerifier class uses the Base64 encoding algorithm, which is not a secure cryptographic algorithm for encryption or hashing. While Base64 is often used for encoding binary data, it does not provide any security guarantees and should not be used for cryptographic purposes.\n",
      "classification": "slightly promising",
      "cwe": "CWE-327",
      "function_names": [
        "com.mobileenerlytics.eagle.tester.common.util.LicenseVerifier.EagleLicenseProvider.getLicenseData"
      ],
      "filenames": [
        "src/main/java/com/mobileenerlytics/eagle/tester/common/util/LicenseVerifier.java"
      ]
    }
  ],
  "scores": [
    {
      "stats": {
        "fn": 1,
        "tp": 0,
        "fp": 5
      },
      "mapping": {},
      "vuln_dates": {
        "CVE-2020-2129": "2020-02-12T15:15:14"
      },
      "scoring_model": "claude-3-opus-20240229",
      "type": "llm",
      "instruction_template_hash": "245ace12b6361954d0a2"
    },
    {
      "stats": {
        "fn": 1,
        "tp": 0,
        "fp": 5
      },
      "mapping": {},
      "vuln_dates": {
        "CVE-2020-2129": "2020-02-12T15:15:14"
      },
      "scoring_model": "claude-3-5-sonnet-20240620",
      "type": "llm",
      "instruction_template_hash": "245ace12b6361954d0a2"
    }
  ],
  "instruction_template_hash": "10c0163db4740318a544",
  "version": "0.1.0"
}
