{
  "commit": "1e87e80ace692a43d4563b2c85f1963f1d8aac52",
  "repo_url": "https://github.com/driverdan/node-xmlhttprequest",
  "model": "gpt-4-turbo-2024-04-09",
  "chunk_hashes": [
    "e92c580432d198eff7f3"
  ],
  "responses": [
    {
      "content": "```yaml\nleads:\n  - headline: Insecure HTTP Method Allowed\n    analysis: |\n      The application allows the use of the HTTP method GET for transferring data over a non-secure connection. This could expose sensitive data or allow unauthorized access to API endpoints that should not be publicly accessible.\n    cwe: CWE-287\n    function_names:\n      - open\n    filenames:\n      - lib/XMLHttpRequest.js\n    classification: very promising\n\n  - headline: HTTP Response Splitting via Access Control Exposure\n    analysis: |\n      The server's response can potentially be manipulated by modifying the headers or the response body, since the code lacks proper sanitization or validation of header inputs before they are sent within HTTP responses. This can allow attackers to perform HTTP response splitting or header injection attacks.\n    cwe: CWE-644\n    function_names:\n      - setRequestHeader\n      - getResponseHeader\n    filenames:\n      - lib/XMLHttpRequest.js\n    classification: very promising\n\n  - headline: Local File Inclusion via Improper Input Validation\n    analysis: |\n      The application does not properly validate user input for the file scheme URLs, allowing an attacker to access or execute files on the server by providing malicious paths.\n    cwe: CWE-22\n    function_names:\n      - open\n      - send\n    filenames:\n      - lib/XMLHttpRequest.js\n    classification: very promising\n\n  - headline: Unrestricted Header Manipulation Due to Skip of Validation\n    analysis: |\n      By manipulating headers that should be forbidden or restricted, attackers might modify how the application behaves, introducing vulnerabilities such as user tracking or cache poisoning.\n    cwe: CWE-444\n    function_names:\n      - setRequestHeader\n      - open\n    filenames:\n      - lib/XMLHttpRequest.js\n    classification: slightly promising\n\n  - headline: Denial of Service via Infinite Loop\n    analysis: |\n      The server can enter into an infinite loop if a specific condition is met in response handling, which a malicious user could exploit to cause a denial of service.\n    cwe: CWE-835\n    function_names:\n      - send\n    filenames:\n      - lib/XMLHttpRequest.js\n    classification: slightly promising\n\n  - headline: Exposing Sensitive Error Information to an Unauthorized Actor\n    analysis: |\n      Error handling exposes detailed stack traces to users. This information leakage can help an attacker gain a deeper understanding of the backend infrastructure and design of the application.\n    cwe: CWE-209\n    function_names:\n      - handleError\n    filenames:\n      - lib/XMLHttpRequest.js\n    classification: slightly promising\n\n  - headline: Missing XML External Entity (XXE) Handling\n    analysis: |\n      The application does not restrict processing of XML data, allowing external entities processing which could potentially lead to an XXE attack. This vulnerability particularly arises due to the lack of disabling external  entity references within XML inputs accepted by the server.\n    cwe: CWE-611\n    function_errs:\n      - send\n    filenames:\n      - example/demo.js\n    classification: not promising\n```",
      "date": "2024-06-12T16:05:44.347832",
      "usage": {
        "prompt_tokens": 9375,
        "completion_tokens": 631,
        "cost": 0.11268
      }
    }
  ],
  "leads": [
    {
      "headline": "Insecure HTTP Method Allowed",
      "analysis": "The application allows the use of the HTTP method GET for transferring data over a non-secure connection. This could expose sensitive data or allow unauthorized access to API endpoints that should not be publicly accessible.\n",
      "classification": "very promising",
      "cwe": "CWE-287",
      "function_names": [
        "open"
      ],
      "filenames": [
        "lib/XMLHttpRequest.js"
      ]
    },
    {
      "headline": "HTTP Response Splitting via Access Control Exposure",
      "analysis": "The server's response can potentially be manipulated by modifying the headers or the response body, since the code lacks proper sanitization or validation of header inputs before they are sent within HTTP responses. This can allow attackers to perform HTTP response splitting or header injection attacks.\n",
      "classification": "very promising",
      "cwe": "CWE-644",
      "function_names": [
        "setRequestHeader",
        "getResponseHeader"
      ],
      "filenames": [
        "lib/XMLHttpRequest.js"
      ]
    },
    {
      "headline": "Local File Inclusion via Improper Input Validation",
      "analysis": "The application does not properly validate user input for the file scheme URLs, allowing an attacker to access or execute files on the server by providing malicious paths.\n",
      "classification": "very promising",
      "cwe": "CWE-22",
      "function_names": [
        "open",
        "send"
      ],
      "filenames": [
        "lib/XMLHttpRequest.js"
      ]
    },
    {
      "headline": "Unrestricted Header Manipulation Due to Skip of Validation",
      "analysis": "By manipulating headers that should be forbidden or restricted, attackers might modify how the application behaves, introducing vulnerabilities such as user tracking or cache poisoning.\n",
      "classification": "slightly promising",
      "cwe": "CWE-444",
      "function_names": [
        "setRequestHeader",
        "open"
      ],
      "filenames": [
        "lib/XMLHttpRequest.js"
      ]
    },
    {
      "headline": "Denial of Service via Infinite Loop",
      "analysis": "The server can enter into an infinite loop if a specific condition is met in response handling, which a malicious user could exploit to cause a denial of service.\n",
      "classification": "slightly promising",
      "cwe": "CWE-835",
      "function_names": [
        "send"
      ],
      "filenames": [
        "lib/XMLHttpRequest.js"
      ]
    },
    {
      "headline": "Exposing Sensitive Error Information to an Unauthorized Actor",
      "analysis": "Error handling exposes detailed stack traces to users. This information leakage can help an attacker gain a deeper understanding of the backend infrastructure and design of the application.\n",
      "classification": "slightly promising",
      "cwe": "CWE-209",
      "function_names": [
        "handleError"
      ],
      "filenames": [
        "lib/XMLHttpRequest.js"
      ]
    },
    {
      "headline": "Missing XML External Entity (XXE) Handling",
      "analysis": "The application does not restrict processing of XML data, allowing external entities processing which could potentially lead to an XXE attack. This vulnerability particularly arises due to the lack of disabling external  entity references within XML inputs accepted by the server.\n",
      "classification": "not promising",
      "cwe": "CWE-611",
      "function_names": [],
      "filenames": [
        "example/demo.js"
      ]
    }
  ],
  "scores": [
    {
      "stats": {
        "fn": 1,
        "tp": 0,
        "fp": 3
      },
      "mapping": {},
      "vuln_dates": {
        "CVE-2020-28502": "2021-03-05T18:15:12"
      },
      "scoring_model": "claude-3-opus-20240229",
      "type": "llm",
      "instruction_template_hash": "245ace12b6361954d0a2"
    }
  ],
  "instruction_template_hash": "10c0163db4740318a544",
  "version": "0.1.0"
}
