{
  "commit": "0cfcf1c03821244cb1dfa090194017a8e52a3db3",
  "repo_url": "https://github.com/ehco1996/django-sspanel",
  "model": "gpt-4-turbo-2024-04-09",
  "chunk_hashes": [
    "842a866c3e086584774e"
  ],
  "responses": [
    {
      "content": "```yaml\nleads:\n  - headline: \"Insufficient Session Expiration\"\n    analysis: |\n      The application appears to lack a session expiration mechanism. Long-lived sessions increase the risk of session hijacking, as the extended timing window may allow an attacker to reuse or forge the session token.\n    cwe: CWE-613\n    function_names:\n      - __init__\n    filenames:\n      - \"apps/mw.py\"\n    classification: very promising\n\n  - headline: \"Weak Password Storage Mechanism\"\n    analysis: |\n      The configurations potentially allow weak password storage with simple hashing mechanisms or plaintext storage, insufficient to protect credentials from being disclosed.\n    cwe: CWE-916\n    function_names:\n      - add_new_user\n    filenames:\n      - \"apps/sspanel/models.py\"\n    classification: very promising\n\n  - headline: \"Insecure Direct Object References\"\n    analysis: |\n      The application improperly checks authorization before exporting reports, leading to a scenario where an attacker could access data or perform actions not intended for their user level.\n    cwe: CWE-639\n    function_names:\n      - export_node_traffic\n    filenames:\n      - \"apps/api/views.py\"\n    classification: very promising\n\n  - headline: \"Storage of Sensitive Information in Plaintext\"\n    analysis: |\n      The configuration settings indicate that sensitive information, including encryption keys and database credentials, might be stored in plaintext within the application's configuration files.\n    cwe: CWE-312\n    function_names:\n      - get\n    filenames:\n      - \"configs/default/db.py\"\n    classification: very promising\n  \n  - headline: \"Injection Vulnerability in Account Settings Update\"\n    analysis: |\n      User input from the account settings update functionality is not sufficiently sanitized, allowing an attacker to inject malicious content, potentially leading to command injection.\n    cwe: CWE-77\n    function_names:\n      - update_ss_config_from_dict\n    filenames:\n      - \"apps/sspanel/models.py\"\n    classification: slightly promising\n\n  - headline: \"Potential Command Injection via Shell Command Construction\"\n    analysis: |\n      The application constructs shell commands using user-controllable input without adequate validation, potentially allowing an attacker to execute arbitrary commands on the server.\n    cwe: CWE-78\n    function_names:\n      - wait_for\n    filenames:\n      - \"wait-for-it.sh\"\n    classification: very promising\n\n  - headline: \"Unchecked Return Value Leading to Potential Denial of Service\"\n    analysis: |\n      The system does not properly check the return values after making external API calls, which might lead to denial of service if the API call fails silently and the application proceeds as if it was successful.\n    cwe: CWE-252\n    function_names:\n      - sync_user_traffic_task\n    filenames:\n      - \"apps/celery.py\"\n    classification: slightly promising\n\n  - headline: \"Hard-coded Credentials in Source Code\"\n    analysis: |\n      The source code contains hard-coded credentials used for database access, which could easily lead to unauthorized access if the codebase is exposed or mishandled.\n    cwe: CWE-798\n    function_names:\n      - __init__\n    filenames:\n      - \"configs/default/db.py\"\n    classification: very promising\n\n  - headline: \"SQL Injection Vulnerability\"\n    analysis: |\n      The application constructs SQL queries directly using user-supplied input without proper sanitation, leading to potential manipulation of the underlying database through SQL injection attacks.\n    cwe: CWE-89\n    function_names:\n      - get_user_by_email\n    filenames:\n      - \"apps/sspanel/backends.py\"\n    classification: very promising\n\n  - headline: \"Insecure Deserialization of User-supplied Data\"\n    analysis: |\n      The application deserializes user-supplied data without sufficient validation, allowing an attacker to execute arbitrary code or commands on the server.\n    cwe: CWE-502\n    function_names:\n      - handle_json_post\n    filenames:\n      - \"apps/api/views.py\"\n    classification: very promising\n```",
      "date": "2024-06-12T16:11:57.399411",
      "usage": {
        "prompt_tokens": 95693,
        "completion_tokens": 828,
        "cost": 0.98177
      }
    }
  ],
  "leads": [
    {
      "headline": "Insufficient Session Expiration",
      "analysis": "The application appears to lack a session expiration mechanism. Long-lived sessions increase the risk of session hijacking, as the extended timing window may allow an attacker to reuse or forge the session token.\n",
      "classification": "very promising",
      "cwe": "CWE-613",
      "function_names": [
        "__init__"
      ],
      "filenames": [
        "apps/mw.py"
      ]
    },
    {
      "headline": "Weak Password Storage Mechanism",
      "analysis": "The configurations potentially allow weak password storage with simple hashing mechanisms or plaintext storage, insufficient to protect credentials from being disclosed.\n",
      "classification": "very promising",
      "cwe": "CWE-916",
      "function_names": [
        "add_new_user"
      ],
      "filenames": [
        "apps/sspanel/models.py"
      ]
    },
    {
      "headline": "Insecure Direct Object References",
      "analysis": "The application improperly checks authorization before exporting reports, leading to a scenario where an attacker could access data or perform actions not intended for their user level.\n",
      "classification": "very promising",
      "cwe": "CWE-639",
      "function_names": [
        "export_node_traffic"
      ],
      "filenames": [
        "apps/api/views.py"
      ]
    },
    {
      "headline": "Storage of Sensitive Information in Plaintext",
      "analysis": "The configuration settings indicate that sensitive information, including encryption keys and database credentials, might be stored in plaintext within the application's configuration files.\n",
      "classification": "very promising",
      "cwe": "CWE-312",
      "function_names": [
        "get"
      ],
      "filenames": [
        "configs/default/db.py"
      ]
    },
    {
      "headline": "Injection Vulnerability in Account Settings Update",
      "analysis": "User input from the account settings update functionality is not sufficiently sanitized, allowing an attacker to inject malicious content, potentially leading to command injection.\n",
      "classification": "slightly promising",
      "cwe": "CWE-77",
      "function_names": [
        "update_ss_config_from_dict"
      ],
      "filenames": [
        "apps/sspanel/models.py"
      ]
    },
    {
      "headline": "Potential Command Injection via Shell Command Construction",
      "analysis": "The application constructs shell commands using user-controllable input without adequate validation, potentially allowing an attacker to execute arbitrary commands on the server.\n",
      "classification": "very promising",
      "cwe": "CWE-78",
      "function_names": [
        "wait_for"
      ],
      "filenames": [
        "wait-for-it.sh"
      ]
    },
    {
      "headline": "Unchecked Return Value Leading to Potential Denial of Service",
      "analysis": "The system does not properly check the return values after making external API calls, which might lead to denial of service if the API call fails silently and the application proceeds as if it was successful.\n",
      "classification": "slightly promising",
      "cwe": "CWE-252",
      "function_names": [
        "sync_user_traffic_task"
      ],
      "filenames": [
        "apps/celery.py"
      ]
    },
    {
      "headline": "Hard-coded Credentials in Source Code",
      "analysis": "The source code contains hard-coded credentials used for database access, which could easily lead to unauthorized access if the codebase is exposed or mishandled.\n",
      "classification": "very promising",
      "cwe": "CWE-798",
      "function_names": [
        "__init__"
      ],
      "filenames": [
        "configs/default/db.py"
      ]
    },
    {
      "headline": "SQL Injection Vulnerability",
      "analysis": "The application constructs SQL queries directly using user-supplied input without proper sanitation, leading to potential manipulation of the underlying database through SQL injection attacks.\n",
      "classification": "very promising",
      "cwe": "CWE-89",
      "function_names": [
        "get_user_by_email"
      ],
      "filenames": [
        "apps/sspanel/backends.py"
      ]
    },
    {
      "headline": "Insecure Deserialization of User-supplied Data",
      "analysis": "The application deserializes user-supplied data without sufficient validation, allowing an attacker to execute arbitrary code or commands on the server.\n",
      "classification": "very promising",
      "cwe": "CWE-502",
      "function_names": [
        "handle_json_post"
      ],
      "filenames": [
        "apps/api/views.py"
      ]
    }
  ],
  "scores": [
    {
      "stats": {
        "fn": 1,
        "tp": 0,
        "fp": 8
      },
      "mapping": {},
      "vuln_dates": {
        "CVE-2023-38941": "2023-08-04T00:15:13"
      },
      "scoring_model": "claude-3-opus-20240229",
      "type": "llm",
      "instruction_template_hash": "245ace12b6361954d0a2"
    },
    {
      "stats": {
        "fn": 1,
        "tp": 0,
        "fp": 8
      },
      "mapping": {},
      "vuln_dates": {
        "CVE-2023-38941": "2023-08-04T00:15:13"
      },
      "scoring_model": "claude-3-5-sonnet-20240620",
      "type": "llm",
      "instruction_template_hash": "245ace12b6361954d0a2"
    }
  ],
  "instruction_template_hash": "10c0163db4740318a544",
  "version": "0.1.0"
}
