{
  "commit": "154a0a274acc5408442349af8b3f5bb3c3bc3c3e",
  "repo_url": "https://github.com/mubarakalmehairbi/toui",
  "model": "gpt-4-turbo-2024-04-09",
  "chunk_hashes": [
    "fff3d7970702c63b4874"
  ],
  "responses": [
    {
      "content": "```yaml\nleads:\n  - headline: Inadequate input validation on user inputs\n    analysis: |\n      The application is prone to unauthorized activities or logic abuse due to the lack of proper validation mechanisms on inputs. This vulnerability could be exploited by an attacker to inject malicious data, execute unintended actions, or access sensitive data. The application uses user inputs in multiple operations such as saving and retrieving data, user signup, and login, but does not validate or sanitize the inputs sufficiently.\n    cwe: CWE-20\n    function_names:\n      - signup_user\n      - signin_user\n      - saveData\n    filenames:\n      - tests/full_app.py\n      - toui/apps.py\n      - examples/example_5_user_variables.py\n    classification: very promising\n\n  - headline: Use of Insecure File Upload Functionality\n    analysis: |\n      The application allows file uploads without proper validation mechanisms in place, which could lead to unauthorized file uploads, execution of malicious scripts, or overwriting of sensitive files on the server. This is particularly concerning as the application does not check for file types, sizes, or any other content validation, making it prone to various forms of attacks like uploading executable files or large files that could exhaust server resources.\n    cwe: CWE-434\n    function_names:\n      - upload_file\n    filenames:\n      - tests/full_app.py\n    classification: very promising\n\n  - headline: Exposure of sensitive file system information via error messages\n    analysis: |\n      The application could potentially expose sensitive information about the filesystem through detailed error messages. This occurs when file manipulation operations (like file upload or download) encounter errors, and the application does not sufficiently sanitize or suppress the output of these error messages. An attacker can exploit this vulnerability to gain more information about the server's file system structure and potentially identify other exploitable vulnerabilities.\n    cwe: CWE-209\n    function_names:\n      - upload_file\n      - _download\n    filenames:\n      - toui/apps.py\n      - tests/full_app.py\n    classification: slightly promising\n\n  - headline: Usage of hard-coded secret keys in application configuration\n    analysis: |\n      The application uses hard-coded secret keys within its source code, which presents a high security risk as it makes the application susceptible to attacks if the codebase is exposed or accessed by unauthorized individuals. This is particularly concerning because the same key could be used across different installations, making it easier for attackers to forge session cookies or carry out other session-related attacks.\n    cwise: CWE-798\n    function_names:\n      - __init__\n    filenames:\n      - toui/apps.py\n    classification: slightly promising\n\n  - headline: Authentication Bypass Using Alternative Path or Channel\n    analysis: |\n      The system implements authentication controls, but an alternative path exists that undermines these security mechanisms. This could allow an attacker to bypass authentication procedures and gain unauthorized access to the application using alternative means, such as indirect interactions that do not require authentication or inconsistent application logic.\n    cwe: CWE-288\n    function_names:\n      - signup_user\n      - signin_user\n      - add_user_database\n    filenames:\n      - toui/apps.py\n    classification: very promising\n```",
      "date": "2024-06-13T10:18:44.390501",
      "usage": {
        "prompt_tokens": 29273,
        "completion_tokens": 658,
        "cost": 0.31247
      }
    }
  ],
  "leads": [
    {
      "headline": "Inadequate input validation on user inputs",
      "analysis": "The application is prone to unauthorized activities or logic abuse due to the lack of proper validation mechanisms on inputs. This vulnerability could be exploited by an attacker to inject malicious data, execute unintended actions, or access sensitive data. The application uses user inputs in multiple operations such as saving and retrieving data, user signup, and login, but does not validate or sanitize the inputs sufficiently.\n",
      "classification": "very promising",
      "cwe": "CWE-20",
      "function_names": [
        "signup_user",
        "signin_user",
        "saveData"
      ],
      "filenames": [
        "tests/full_app.py",
        "toui/apps.py",
        "examples/example_5_user_variables.py"
      ]
    },
    {
      "headline": "Use of Insecure File Upload Functionality",
      "analysis": "The application allows file uploads without proper validation mechanisms in place, which could lead to unauthorized file uploads, execution of malicious scripts, or overwriting of sensitive files on the server. This is particularly concerning as the application does not check for file types, sizes, or any other content validation, making it prone to various forms of attacks like uploading executable files or large files that could exhaust server resources.\n",
      "classification": "very promising",
      "cwe": "CWE-434",
      "function_names": [
        "upload_file"
      ],
      "filenames": [
        "tests/full_app.py"
      ]
    },
    {
      "headline": "Exposure of sensitive file system information via error messages",
      "analysis": "The application could potentially expose sensitive information about the filesystem through detailed error messages. This occurs when file manipulation operations (like file upload or download) encounter errors, and the application does not sufficiently sanitize or suppress the output of these error messages. An attacker can exploit this vulnerability to gain more information about the server's file system structure and potentially identify other exploitable vulnerabilities.\n",
      "classification": "slightly promising",
      "cwe": "CWE-209",
      "function_names": [
        "upload_file",
        "_download"
      ],
      "filenames": [
        "toui/apps.py",
        "tests/full_app.py"
      ]
    },
    {
      "headline": "Usage of hard-coded secret keys in application configuration",
      "analysis": "The application uses hard-coded secret keys within its source code, which presents a high security risk as it makes the application susceptible to attacks if the codebase is exposed or accessed by unauthorized individuals. This is particularly concerning because the same key could be used across different installations, making it easier for attackers to forge session cookies or carry out other session-related attacks.\n",
      "classification": "slightly promising",
      "cwe": null,
      "function_names": [
        "__init__"
      ],
      "filenames": [
        "toui/apps.py"
      ]
    },
    {
      "headline": "Authentication Bypass Using Alternative Path or Channel",
      "analysis": "The system implements authentication controls, but an alternative path exists that undermines these security mechanisms. This could allow an attacker to bypass authentication procedures and gain unauthorized access to the application using alternative means, such as indirect interactions that do not require authentication or inconsistent application logic.\n",
      "classification": "very promising",
      "cwe": "CWE-288",
      "function_names": [
        "signup_user",
        "signin_user",
        "add_user_database"
      ],
      "filenames": [
        "toui/apps.py"
      ]
    }
  ],
  "scores": [
    {
      "stats": {
        "fn": 1,
        "tp": 0,
        "fp": 3
      },
      "mapping": {},
      "vuln_dates": {
        "CVE-2023-33175": "2023-05-30T05:15:11"
      },
      "scoring_model": "claude-3-opus-20240229",
      "type": "llm",
      "instruction_template_hash": "245ace12b6361954d0a2"
    }
  ],
  "instruction_template_hash": "10c0163db4740318a544",
  "version": "0.1.0"
}
