{
  "commit": "2643a56144df948b0094b247b8f9d31c5b870e52",
  "repo_url": "https://github.com/jenkinsci/gitea-plugin",
  "model": "claude-3-opus-20240229",
  "chunk_hashes": [
    "f79e605f1be2ec6dab12"
  ],
  "responses": [
    {
      "content": "Here are the potential security vulnerabilities I identified in the provided codebase:\n\n```yaml\nleads:\n  - headline: Potential command injection in src/images/make-inkscape.sh\n    analysis: |\n      The shell script src/images/make-inkscape.sh executes inkscape commands using unsanitized inputs from file paths.\n      If any of the SVG files processed have malicious names containing shell metacharacters, they could lead to arbitrary command execution.\n    cwe: CWE-78\n    function_names: \n      - make-inkscape.sh\n    filenames:\n      - src/images/make-inkscape.sh\n    classification: very promising\n  \n  - headline: Potential SSRF/credential disclosure in GiteaServer\n    analysis: |\n      The GiteaServer class allows specifying an aliasUrl that is used in webhook events without strict validation.\n      If an attacker can control the aliasUrl, they may be able to make Jenkins connect to an attacker-controlled server and potentially steal credentials.\n      The doCheckAliasUrl validation does not seem to prevent URLs like http://localhost or http://127.0.0.1.\n    cwe: CWE-918\n    function_names:\n      - GiteaServer\n      - doCheckAliasUrl\n    filenames:\n      - src/main/java/org/jenkinsci/plugin/gitea/servers/GiteaServer.java\n    classification: slightly promising\n  \n  - headline: Potential credentials disclosure in GiteaSCMBuilder\n    analysis: |\n      The GiteaSCMBuilder class logs the repository clone URL which may contain sensitive credentials.\n      If the server URL contains a username/password or access token, it would get logged in cleartext.\n      The comment mentions wanting to redact credentials but it doesn't appear to actually do it currently.\n    cwe: CWE-522\n    function_names:\n      - GiteaSCMBuilder\n    filenames:\n      - src/main/java/org/jenkinsci/plugin/gitea/GiteaSCMBuilder.java  \n    classification: slightly promising\n\n  - headline: Potential XSS in avatar URLs\n    analysis: | \n      Various classes like GiteaBrowser and GiteaAvatar display avatar image URLs from Gitea without sanitization.\n      If an attacker can control the avatar URL for a user/organization/repository, they could potentially inject a malicious JavaScript URL.\n      However, exploitation would require a vulnerability in browsers or plugins to execute JavaScript from an img src URL.\n    cwe: CWE-79\n    function_names:\n      - GiteaBrowser\n      - GiteaAvatar\n    filenames:\n      - src/main/java/org/jenkinsci/plugin/gitea/GiteaBrowser.java\n      - src/main/java/org/jenkinsci/plugin/gitea/GiteaAvatar.java\n    classification: not promising\n```\n\nThe make-inkscape.sh command injection looks like the most concerning issue. The others are more speculative. Let me know if you need any clarification or have additional questions!",
      "date": "2024-06-12T18:29:10.697740",
      "usage": {
        "prompt_tokens": 165353,
        "completion_tokens": 728,
        "cost": 2.534895
      }
    }
  ],
  "leads": [
    {
      "headline": "Potential command injection in src/images/make-inkscape.sh",
      "analysis": "The shell script src/images/make-inkscape.sh executes inkscape commands using unsanitized inputs from file paths.\nIf any of the SVG files processed have malicious names containing shell metacharacters, they could lead to arbitrary command execution.\n",
      "classification": "very promising",
      "cwe": "CWE-78",
      "function_names": [
        "make-inkscape.sh"
      ],
      "filenames": [
        "src/images/make-inkscape.sh"
      ]
    },
    {
      "headline": "Potential SSRF/credential disclosure in GiteaServer",
      "analysis": "The GiteaServer class allows specifying an aliasUrl that is used in webhook events without strict validation.\nIf an attacker can control the aliasUrl, they may be able to make Jenkins connect to an attacker-controlled server and potentially steal credentials.\nThe doCheckAliasUrl validation does not seem to prevent URLs like http://localhost or http://127.0.0.1.\n",
      "classification": "slightly promising",
      "cwe": "CWE-918",
      "function_names": [
        "GiteaServer",
        "doCheckAliasUrl"
      ],
      "filenames": [
        "src/main/java/org/jenkinsci/plugin/gitea/servers/GiteaServer.java"
      ]
    },
    {
      "headline": "Potential credentials disclosure in GiteaSCMBuilder",
      "analysis": "The GiteaSCMBuilder class logs the repository clone URL which may contain sensitive credentials.\nIf the server URL contains a username/password or access token, it would get logged in cleartext.\nThe comment mentions wanting to redact credentials but it doesn't appear to actually do it currently.\n",
      "classification": "slightly promising",
      "cwe": "CWE-522",
      "function_names": [
        "GiteaSCMBuilder"
      ],
      "filenames": [
        "src/main/java/org/jenkinsci/plugin/gitea/GiteaSCMBuilder.java"
      ]
    },
    {
      "headline": "Potential XSS in avatar URLs",
      "analysis": "Various classes like GiteaBrowser and GiteaAvatar display avatar image URLs from Gitea without sanitization.\nIf an attacker can control the avatar URL for a user/organization/repository, they could potentially inject a malicious JavaScript URL.\nHowever, exploitation would require a vulnerability in browsers or plugins to execute JavaScript from an img src URL.\n",
      "classification": "not promising",
      "cwe": "CWE-79",
      "function_names": [
        "GiteaBrowser",
        "GiteaAvatar"
      ],
      "filenames": [
        "src/main/java/org/jenkinsci/plugin/gitea/GiteaBrowser.java",
        "src/main/java/org/jenkinsci/plugin/gitea/GiteaAvatar.java"
      ]
    }
  ],
  "scores": [
    {
      "stats": {
        "fn": 1,
        "tp": 0,
        "fp": 1
      },
      "mapping": {},
      "vuln_dates": {
        "CVE-2022-46685": "2022-12-12T09:15:13"
      },
      "scoring_model": "claude-3-opus-20240229",
      "type": "llm",
      "instruction_template_hash": "245ace12b6361954d0a2"
    }
  ],
  "instruction_template_hash": "10c0163db4740318a544",
  "version": "0.1.0"
}
