{
  "commit": "493dc3d7c85f39c44e879941df9d5682865da109",
  "repo_url": "https://github.com/onsdigital/ras-collection-instrument",
  "model": "gpt-4o-2024-05-13",
  "chunk_hashes": [
    "a4309143678bbc515b9b"
  ],
  "responses": [
    {
      "content": "```yaml\nleads:\n  - headline: \"Hardcoded Credentials\"\n    analysis: |\n      Within the config.py file, security-critical attributes like `SECURITY_USER_NAME` and `SECURITY_USER_PASSWORD` are hardcoded in multiple places, including in `DevelopmentConfig` and `TestingConfig`. This exposes plaintext credentials both in the source code and potentially in version control.\n    cwe: CWE-798\n    function_names: []\n    filenames:\n      - \"config.py\"\n    classification: very promising\n\n  - headline: \"SQL Injection Vulnerability\"\n    analysis: |\n      The method `_create_seft_file` in the `CollectionInstrument` class initializes a SQL query to insert a new SEFT instrument without validating or sanitizing the contents of the `file` parameter. If an attacker devises a malicious file name that includes SQL code, it could lead to SQL injection, allowing unauthorized database access or manipulation.\n    cwe: CWE-89\n    function_names:\n      - \"_create_seft_file\"\n    filenames:\n      - \"application/controllers/collection_instrument.py\"\n    classification: very promising\n\n  - headline: \"Missing CSRF Protection\"\n    analysis: |\n      The Flask application does not implement Cross-Site Request Forgery (CSRF) protection. None of the routes/checks implement a CSRF token system. This could allow attackers to tempt users to execute unwanted actions on authenticated web application sessions.\n    cwe: CWE-352\n    function_names: []\n    filenames: \n      - \"application/views/survey_responses_view.py\"\n      - \"application/views/collection_instrument_view.py\"\n    classification: very promising\n\n  - headline: \"Improper Input Validation\"\n    analysis: |\n      Multiple points in the code assume the validity of UUIDs without proper validation (e.g., method `upload_instrument_with_no_collection_exercise` in `CollectionInstrument` class). These points are a security risk where invalid inputs could potentially exploit system weaknesses.\n    cwe: CWE-20\n    function_names:\n      - \"upload_instrument_with_no_collection_exercise\"\n      - \"link_instrument_to_exercise\"\n    filenames:\n      - \"application/controllers/collection_instrument.py\"\n    classification: slightly promising\n\n  - headline: \"Plaintext Storage of Sensitive Data\"\n    analysis: |\n      The Config class in `config.py` and its subclasses read sensitive information (like `JSON_SECRET_KEYS` and `ONS_CRYPTOKEY`) from environment variables and assume plaintext storage. Better practices would involve encrypted storage and decoding only when necessary.\n    cwe: CWE-312\n    function_names: []\n    filenames:\n      - \"config.py\"\n    classification: very promising\n\n  - headline: \"Insecure Random Number Generation\"\n    analysis: |\n      There is potential for the random number generator in the `survey_response.py` method `add_survey_response` (`uuid.uuid4()`) to be insecure if the python module has a known weakness or if it isn't seeded securely.\n    cwe: CWE-338\n    function_names:\n      - \"add_survey_response\"\n    filenames:\n      - \"application/controllers/survey_response.py\"\n    classification: slightly promising\n\n  - headline: \"Improper Usage of Debug Mode\"\n    analysis: |\n      The `DevelopmentConfig` class sets `DEBUG` mode to `True`, which may potentially expose sensitive information in debugging output. Leaving debug mode enabled in a production environment can be a security risk.\n    cwe: CWE-209\n    function_names: []\n    filenames:\n      - \"config.py\"\n    classification: very promising\n```",
      "date": "2024-06-14T15:04:14.106461",
      "usage": {
        "prompt_tokens": 33784,
        "completion_tokens": 738,
        "cost": 0.17999
      }
    }
  ],
  "leads": [
    {
      "headline": "Hardcoded Credentials",
      "analysis": "Within the config.py file, security-critical attributes like SECURITY_USER_NAME and SECURITY_USER_PASSWORD are hardcoded in multiple places, including in DevelopmentConfig and TestingConfig. This exposes plaintext credentials both in the source code and potentially in version control.\n",
      "classification": "very promising",
      "cwe": "CWE-798",
      "function_names": [],
      "filenames": [
        "config.py"
      ]
    },
    {
      "headline": "SQL Injection Vulnerability",
      "analysis": "The method _create_seft_file in the CollectionInstrument class initializes a SQL query to insert a new SEFT instrument without validating or sanitizing the contents of the file parameter. If an attacker devises a malicious file name that includes SQL code, it could lead to SQL injection, allowing unauthorized database access or manipulation.\n",
      "classification": "very promising",
      "cwe": "CWE-89",
      "function_names": [
        "_create_seft_file"
      ],
      "filenames": [
        "application/controllers/collection_instrument.py"
      ]
    },
    {
      "headline": "Missing CSRF Protection",
      "analysis": "The Flask application does not implement Cross-Site Request Forgery (CSRF) protection. None of the routes/checks implement a CSRF token system. This could allow attackers to tempt users to execute unwanted actions on authenticated web application sessions.\n",
      "classification": "very promising",
      "cwe": "CWE-352",
      "function_names": [],
      "filenames": [
        "application/views/survey_responses_view.py",
        "application/views/collection_instrument_view.py"
      ]
    },
    {
      "headline": "Improper Input Validation",
      "analysis": "Multiple points in the code assume the validity of UUIDs without proper validation (e.g., method upload_instrument_with_no_collection_exercise in CollectionInstrument class). These points are a security risk where invalid inputs could potentially exploit system weaknesses.\n",
      "classification": "slightly promising",
      "cwe": "CWE-20",
      "function_names": [
        "upload_instrument_with_no_collection_exercise",
        "link_instrument_to_exercise"
      ],
      "filenames": [
        "application/controllers/collection_instrument.py"
      ]
    },
    {
      "headline": "Plaintext Storage of Sensitive Data",
      "analysis": "The Config class in config.py and its subclasses read sensitive information (like JSON_SECRET_KEYS and ONS_CRYPTOKEY) from environment variables and assume plaintext storage. Better practices would involve encrypted storage and decoding only when necessary.\n",
      "classification": "very promising",
      "cwe": "CWE-312",
      "function_names": [],
      "filenames": [
        "config.py"
      ]
    },
    {
      "headline": "Insecure Random Number Generation",
      "analysis": "There is potential for the random number generator in the survey_response.py method add_survey_response (uuid.uuid4()) to be insecure if the python module has a known weakness or if it isn't seeded securely.\n",
      "classification": "slightly promising",
      "cwe": "CWE-338",
      "function_names": [
        "add_survey_response"
      ],
      "filenames": [
        "application/controllers/survey_response.py"
      ]
    },
    {
      "headline": "Improper Usage of Debug Mode",
      "analysis": "The DevelopmentConfig class sets DEBUG mode to True, which may potentially expose sensitive information in debugging output. Leaving debug mode enabled in a production environment can be a security risk.\n",
      "classification": "very promising",
      "cwe": "CWE-209",
      "function_names": [],
      "filenames": [
        "config.py"
      ]
    }
  ],
  "scores": [
    {
      "stats": {
        "fn": 1,
        "tp": 0,
        "fp": 5
      },
      "mapping": {},
      "vuln_dates": {
        "CVE-2020-36762": "2023-07-18T15:15:11"
      },
      "scoring_model": "claude-3-opus-20240229",
      "type": "llm",
      "instruction_template_hash": "245ace12b6361954d0a2"
    },
    {
      "stats": {
        "fn": 1,
        "tp": 0,
        "fp": 5
      },
      "mapping": {},
      "vuln_dates": {
        "CVE-2020-36762": "2023-07-18T15:15:11"
      },
      "scoring_model": "claude-3-5-sonnet-20240620",
      "type": "llm",
      "instruction_template_hash": "245ace12b6361954d0a2"
    }
  ],
  "instruction_template_hash": "10c0163db4740318a544",
  "version": "0.1.0"
}
