{
  "commit": "3ddead1584c9e9055b0f04850bf93cff4d7a60f2",
  "repo_url": "https://github.com/alexcrichton/bzip2-rs",
  "model": "gpt-4-turbo-2024-04-09",
  "chunk_hashes": [
    "f4dca8b59ab22e85a46f"
  ],
  "responses": [
    {
      "content": "```yaml\nleads:\n  - headline: \"Inadequate Input Validation in bzip2\"\n    analysis: |\n      The bzip2 codebase lacks proper input validation for command-line arguments, memory allocation sizes, and file operations. Without thorough validation, unexpected or malicious input can cause the program to behave in unintended ways, potentially leading to crashes or other undefined behavior. This issue is compounded by the use of directly accessing array indices based on input values and performing file operations without rigorous error checking.\n    cwe: CWE-20\n    function_names:\n      - main\n      - bzReadGetUnused\n      - bsGetBit\n    filenames:\n      - \"bzip2-sys/bzip2-1.0.8/bzip2recover.c\"\n      - \"bzip2-sys/bzip2-1.0.8/bzlib.c\"\n      - \"bzip2-sys/bzip2-1.0.8/randtable.c\"\n    classification: \"very promising\"\n  - headline: \"Unsafe Memory Management in Decompression Routines\"\n    analysis: |\n      The decompression logic within bzip2, particularly in handling the Burrows-Wheeler transform and Huffman coding, does not sufficiently account for malformed or crafted input leading to buffer overflows. This occurs due to reliance on external input to dictate memory operations without adequate boundary checks. Specifically, when reconstructing the Huffman tree and during the inverse transform, unchecked memory operations are performed that could be exploited to execute arbitrary code or crash the system.\n    cwe: CWE-119\n    function_names:\n      - BZ2_decompress\n      - unRLE_obuf_to_output_SMALL\n      - unRLE_obuf_to_output_FAST\n    filenames:\n      - \"bzip2-sys/bzip2-1.0.8/decompress.c\"\n    classification: \"very promising\"\n  - headline: \"Out-of-Bounds Write in Compression Algorithm\"\n    analysis: |\n      The block sorting and Huffman coding implementation writes data beyond the allocated buffer when processing specially crafted inputs. This vulnerability is triggered during the final stages of compression, where boundary checks are insufficient or missing for buffer operations. This flaw can lead to data corruption, denial of service, or potentially remote code execution if exploited by an attacker.\n    cwe: CWE-787\n    function_names:\n      - BZ2_compressBlock\n      - BZ2_bsInitWrite\n      - mainQSort3\n    filenames:\n      - \"bzip2-sys/bzip2-1.0.8/compress.c\"\n      - \"bzip2-sys/bzip2-1.0.8/blocksort.c\"\n    classification: \"very promising\"\n```",
      "date": "2024-06-14T12:49:30.868867",
      "usage": {
        "prompt_tokens": 111036,
        "completion_tokens": 556,
        "cost": 1.12704
      }
    }
  ],
  "leads": [
    {
      "headline": "Inadequate Input Validation in bzip2",
      "analysis": "The bzip2 codebase lacks proper input validation for command-line arguments, memory allocation sizes, and file operations. Without thorough validation, unexpected or malicious input can cause the program to behave in unintended ways, potentially leading to crashes or other undefined behavior. This issue is compounded by the use of directly accessing array indices based on input values and performing file operations without rigorous error checking.\n",
      "classification": "very promising",
      "cwe": "CWE-20",
      "function_names": [
        "main",
        "bzReadGetUnused",
        "bsGetBit"
      ],
      "filenames": [
        "bzip2-sys/bzip2-1.0.8/bzip2recover.c",
        "bzip2-sys/bzip2-1.0.8/bzlib.c",
        "bzip2-sys/bzip2-1.0.8/randtable.c"
      ]
    },
    {
      "headline": "Unsafe Memory Management in Decompression Routines",
      "analysis": "The decompression logic within bzip2, particularly in handling the Burrows-Wheeler transform and Huffman coding, does not sufficiently account for malformed or crafted input leading to buffer overflows. This occurs due to reliance on external input to dictate memory operations without adequate boundary checks. Specifically, when reconstructing the Huffman tree and during the inverse transform, unchecked memory operations are performed that could be exploited to execute arbitrary code or crash the system.\n",
      "classification": "very promising",
      "cwe": "CWE-119",
      "function_names": [
        "BZ2_decompress",
        "unRLE_obuf_to_output_SMALL",
        "unRLE_obuf_to_output_FAST"
      ],
      "filenames": [
        "bzip2-sys/bzip2-1.0.8/decompress.c"
      ]
    },
    {
      "headline": "Out-of-Bounds Write in Compression Algorithm",
      "analysis": "The block sorting and Huffman coding implementation writes data beyond the allocated buffer when processing specially crafted inputs. This vulnerability is triggered during the final stages of compression, where boundary checks are insufficient or missing for buffer operations. This flaw can lead to data corruption, denial of service, or potentially remote code execution if exploited by an attacker.\n",
      "classification": "very promising",
      "cwe": "CWE-787",
      "function_names": [
        "BZ2_compressBlock",
        "BZ2_bsInitWrite",
        "mainQSort3"
      ],
      "filenames": [
        "bzip2-sys/bzip2-1.0.8/compress.c",
        "bzip2-sys/bzip2-1.0.8/blocksort.c"
      ]
    }
  ],
  "scores": [
    {
      "stats": {
        "fn": 1,
        "tp": 0,
        "fp": 3
      },
      "mapping": {},
      "vuln_dates": {
        "CVE-2023-22895": "2023-01-10T01:15:10"
      },
      "scoring_model": "claude-3-opus-20240229",
      "type": "llm",
      "instruction_template_hash": "245ace12b6361954d0a2"
    }
  ],
  "instruction_template_hash": "10c0163db4740318a544",
  "version": "0.1.0"
}
