{
  "commit": "090405ff1174d510c853b95030041f4659492a44",
  "repo_url": "https://github.com/jenkinsci/dynatrace-plugin",
  "model": "gpt-4-turbo-2024-04-09",
  "chunk_hashes": [
    "b15691fb054fb23bc923"
  ],
  "responses": [
    {
      "content": "```yaml\nleads:\n  - headline: \"Improper handling of API session keys\"\n    analysis: |\n      The code of the application handles API session keys insecurely by storing them in plain text instead of securing them. This could potentially expose sensitive information to unauthorized parties.\n    cwe: CWE-522\n    function_names:\n      - updateBuildVariables\n      - setupBuildVariables\n    filenames:\n      - src/main/java/com/dynatrace/jenkins/dashboard/utils/Utils.java\n      - src/main/java/com/dynatrace/jenkins/dashboard/TABuildWrapper.java\n    classification: \"very promising\"\n\n  - headline: \"Weak cryptography algorithms used\"\n    analysis: |\n      The application uses outdated or weak cryptographic algorithms, which might be vulnerable to attacks and could compromise the integrity and confidentiality of data.\n    cwe: CWE-327\n    function_names: []\n    filenames:\n      - src/main/java/com/dynatrace/jenkins/dashboard/utils/Utils.java\n    classification: \"very promising\"\n\n  - headline: \"Insecure storage of sensitive information\"\n    analysis: |\n      Sensitive details such as passwords, usernames, and API keys are stored insecurely, potentially making them accessible to attackers.\n    cwe: CWE-922\n    function_names:\n      - persistReportDetails\n    filenames:\n      - src/main/java/com/dynatrace/jenkins/dashboard/utils/TAReportDetailsFileUtils.java\n    classification: \"very promising\"\n\n  - headline: \"Insecure direct object references\"\n    analysis: |\n      The application is using direct object references without proper authorization checks, leading to potential unauthorized access to sensitive data.\n    cwe: CWE-639\n    function_names:\n      - getExportStoredSessionRequestURI\n    filenames:\n      - src/main/java/com/dynatrace/jenkins/dashboard/rest/ServerRestURIManager.java\n    classification: \"very promising\"\n\n  - headline: \"Information exposure through an error message\"\n    analysis: |\n      Detailed error messages reveal information that could be useful to an attacker for conducting further attacks, such as internal file paths or database details.\n    cwe: CWE-209\n    function_names:\n      - setBuild\n      - onLoad\n    filenames:\n      - src/main/java/com/dynatrace/jenkins/dashboard/TAReportingBuildAction_2_0_0.java\n    classification: \"slightly promising\"\n```\nThese leads should help security researchers start developing proofs of concept for potential vulnerabilities within the application. Each lead has details about the security concern, the type of vulnerability (CWE reference), and where in the code the issue appears, assisting in quickly locating and addressing these security flaws.",
      "date": "2024-06-12T18:21:04.272973",
      "usage": {
        "prompt_tokens": 73563,
        "completion_tokens": 545,
        "cost": 0.75198
      }
    }
  ],
  "leads": [
    {
      "headline": "Improper handling of API session keys",
      "analysis": "The code of the application handles API session keys insecurely by storing them in plain text instead of securing them. This could potentially expose sensitive information to unauthorized parties.\n",
      "classification": "very promising",
      "cwe": "CWE-522",
      "function_names": [
        "updateBuildVariables",
        "setupBuildVariables"
      ],
      "filenames": [
        "src/main/java/com/dynatrace/jenkins/dashboard/utils/Utils.java",
        "src/main/java/com/dynatrace/jenkins/dashboard/TABuildWrapper.java"
      ]
    },
    {
      "headline": "Weak cryptography algorithms used",
      "analysis": "The application uses outdated or weak cryptographic algorithms, which might be vulnerable to attacks and could compromise the integrity and confidentiality of data.\n",
      "classification": "very promising",
      "cwe": "CWE-327",
      "function_names": [],
      "filenames": [
        "src/main/java/com/dynatrace/jenkins/dashboard/utils/Utils.java"
      ]
    },
    {
      "headline": "Insecure storage of sensitive information",
      "analysis": "Sensitive details such as passwords, usernames, and API keys are stored insecurely, potentially making them accessible to attackers.\n",
      "classification": "very promising",
      "cwe": "CWE-922",
      "function_names": [
        "persistReportDetails"
      ],
      "filenames": [
        "src/main/java/com/dynatrace/jenkins/dashboard/utils/TAReportDetailsFileUtils.java"
      ]
    },
    {
      "headline": "Insecure direct object references",
      "analysis": "The application is using direct object references without proper authorization checks, leading to potential unauthorized access to sensitive data.\n",
      "classification": "very promising",
      "cwe": "CWE-639",
      "function_names": [
        "getExportStoredSessionRequestURI"
      ],
      "filenames": [
        "src/main/java/com/dynatrace/jenkins/dashboard/rest/ServerRestURIManager.java"
      ]
    },
    {
      "headline": "Information exposure through an error message",
      "analysis": "Detailed error messages reveal information that could be useful to an attacker for conducting further attacks, such as internal file paths or database details.\n",
      "classification": "slightly promising",
      "cwe": "CWE-209",
      "function_names": [
        "setBuild",
        "onLoad"
      ],
      "filenames": [
        "src/main/java/com/dynatrace/jenkins/dashboard/TAReportingBuildAction_2_0_0.java"
      ]
    }
  ],
  "scores": [
    {
      "stats": {
        "fn": 2,
        "tp": 1,
        "fp": 3
      },
      "mapping": {
        "2": "CVE-2019-10461"
      },
      "vuln_dates": {
        "CVE-2019-10463": "2019-10-23T13:15:10",
        "CVE-2019-10461": "2019-10-23T13:15:10",
        "CVE-2019-10462": "2019-10-23T13:15:10"
      },
      "scoring_model": "claude-3-opus-20240229",
      "type": "llm",
      "instruction_template_hash": "245ace12b6361954d0a2"
    },
    {
      "stats": {
        "fn": 2,
        "tp": 1,
        "fp": 2
      },
      "mapping": {
        "0": "CVE-2019-10461",
        "2": "CVE-2019-10461"
      },
      "vuln_dates": {
        "CVE-2019-10463": "2019-10-23T13:15:10",
        "CVE-2019-10461": "2019-10-23T13:15:10",
        "CVE-2019-10462": "2019-10-23T13:15:10"
      },
      "scoring_model": "claude-3-5-sonnet-20240620",
      "type": "llm",
      "instruction_template_hash": "245ace12b6361954d0a2"
    }
  ],
  "instruction_template_hash": "10c0163db4740318a544",
  "version": "0.1.0"
}
