{
  "commit": "ca25f6388005288aae7ed4978f37e7f1b02fc5e1",
  "repo_url": "https://github.com/ubertidavide/fastbots",
  "model": "claude-3-haiku-20240307",
  "chunk_hashes": [
    "fbf7a2b5b5e2583d9963"
  ],
  "responses": [
    {
      "content": "Here is the YAML output for the security vulnerabilities identified in the provided codebase:\n\n```yaml\nleads:\n  - headline: Improper Input Validation\n    analysis: |\n      The code does not properly validate the user-controlled input in the `send_keys()` method call on the `search_element` in the `SearchPage.forward()` method. This can lead to potential injection vulnerabilities, such as command injection or code injection, if the user provides malicious input.\n    cwe: CWE-20\n    function_names:\n      - forward\n    filenames:\n      - main.py\n    classification: slightly promising\n  - headline: Hardcoded Credentials\n    analysis: |\n      The code uses hardcoded credentials in the form of the `BOT_USER_AGENT` constant, which could be exposed and used by attackers to impersonate the bot. This can lead to authentication bypass or privilege escalation vulnerabilities.\n    cwe: CWE-798\n    function_names: []\n    filenames:\n      - fastbots/config.py\n    classification: slightly promising\n  - headline: Improper Authentication\n    analysis: |\n      The code does not appear to have any form of authentication implemented, which could allow unauthorized access to the functionality provided by the bot. This can lead to privilege escalation and other security issues.\n    cwe: CWE-306\n    function_names: []\n    filenames:\n      - main.py\n    classification: slightly promising\n  - headline: Improper Input Sanitization\n    analysis: |\n      The code does not properly sanitize or validate the user-controlled input in the `send_keys()` method call on the `search_element` in the `SearchPage.forward()` method. This can lead to potential injection vulnerabilities, such as cross-site scripting (XSS) or SQL injection, if the user provides malicious input.\n    cwe: CWE-79\n    function_names:\n      - forward\n    filenames:\n      - main.py\n    classification: slightly promising\n  - headline: Insecure Session Management\n    analysis: |\n      The code does not appear to have any mechanism for managing or expiring user sessions, which could allow attackers to hijack active sessions and gain unauthorized access to the system.\n    cwe: CWE-613\n    function_names: []\n    filenames:\n      - main.py\n    classification: slightly promising\n  - headline: Insecure Cookie Storage\n    analysis: |\n      The code stores cookies in a file on the local file system, which could allow attackers to access and potentially tamper with the stored cookies if they have access to the file system.\n    cwe: CWE-312\n    function_names:\n      - save_cookies\n      - load_cookies\n    filenames:\n      - fastbots/bot.py\n    classification: slightly promising\n  - headline: Insecure File Storage\n    analysis: |\n      The code saves HTML pages and screenshots to the local file system, which could allow attackers to access and potentially tamper with the stored files if they have access to the file system.\n    cwe: CWE-552\n    function_names:\n      - save_html\n      - save_screenshot\n    filenames:\n      - fastbots/bot.py\n    classification: slightly promising\n```\n\nThe identified security vulnerabilities in the provided codebase include:\n\n1. **Improper Input Validation**: The code does not properly validate user-controlled input in the `send_keys()` method call, which can lead to potential injection vulnerabilities.\n2. **Hardcoded Credentials**: The code uses hardcoded credentials in the form of the `BOT_USER_AGENT` constant, which could be exposed and used by attackers to impersonate the bot.\n3. **Improper Authentication**: The code does not appear to have any form of authentication implemented, which could allow unauthorized access to the functionality provided by the bot.\n4. **Improper Input Sanitization**: The code does not properly sanitize or validate user-controlled input in the `send_keys()` method call, which can lead to potential injection vulnerabilities.\n5. **Insecure Session Management**: The code does not appear to have any mechanism for managing or expiring user sessions, which could allow attackers to hijack active sessions and gain unauthorized access.\n6. **Insecure Cookie Storage**: The code stores cookies in a file on the local file system, which could allow attackers to access and potentially tamper with the stored cookies.\n7. **Insecure File Storage**: The code saves HTML pages and screenshots to the local file system, which could allow attackers to access and potentially tamper with the stored files.",
      "date": "2024-06-09T15:16:49.429287",
      "usage": {
        "prompt_tokens": 11832,
        "completion_tokens": 1079,
        "cost": 0.00430675
      }
    }
  ],
  "leads": [
    {
      "headline": "Improper Input Validation",
      "analysis": "The code does not properly validate the user-controlled input in the send_keys() method call on the search_element in the SearchPage.forward() method. This can lead to potential injection vulnerabilities, such as command injection or code injection, if the user provides malicious input.\n",
      "classification": "slightly promising",
      "cwe": "CWE-20",
      "function_names": [
        "forward"
      ],
      "filenames": [
        "main.py"
      ]
    },
    {
      "headline": "Hardcoded Credentials",
      "analysis": "The code uses hardcoded credentials in the form of the BOT_USER_AGENT constant, which could be exposed and used by attackers to impersonate the bot. This can lead to authentication bypass or privilege escalation vulnerabilities.\n",
      "classification": "slightly promising",
      "cwe": "CWE-798",
      "function_names": [],
      "filenames": [
        "fastbots/config.py"
      ]
    },
    {
      "headline": "Improper Authentication",
      "analysis": "The code does not appear to have any form of authentication implemented, which could allow unauthorized access to the functionality provided by the bot. This can lead to privilege escalation and other security issues.\n",
      "classification": "slightly promising",
      "cwe": "CWE-306",
      "function_names": [],
      "filenames": [
        "main.py"
      ]
    },
    {
      "headline": "Improper Input Sanitization",
      "analysis": "The code does not properly sanitize or validate the user-controlled input in the send_keys() method call on the search_element in the SearchPage.forward() method. This can lead to potential injection vulnerabilities, such as cross-site scripting (XSS) or SQL injection, if the user provides malicious input.\n",
      "classification": "slightly promising",
      "cwe": "CWE-79",
      "function_names": [
        "forward"
      ],
      "filenames": [
        "main.py"
      ]
    },
    {
      "headline": "Insecure Session Management",
      "analysis": "The code does not appear to have any mechanism for managing or expiring user sessions, which could allow attackers to hijack active sessions and gain unauthorized access to the system.\n",
      "classification": "slightly promising",
      "cwe": "CWE-613",
      "function_names": [],
      "filenames": [
        "main.py"
      ]
    },
    {
      "headline": "Insecure Cookie Storage",
      "analysis": "The code stores cookies in a file on the local file system, which could allow attackers to access and potentially tamper with the stored cookies if they have access to the file system.\n",
      "classification": "slightly promising",
      "cwe": "CWE-312",
      "function_names": [
        "save_cookies",
        "load_cookies"
      ],
      "filenames": [
        "fastbots/bot.py"
      ]
    },
    {
      "headline": "Insecure File Storage",
      "analysis": "The code saves HTML pages and screenshots to the local file system, which could allow attackers to access and potentially tamper with the stored files if they have access to the file system.\n",
      "classification": "slightly promising",
      "cwe": "CWE-552",
      "function_names": [
        "save_html",
        "save_screenshot"
      ],
      "filenames": [
        "fastbots/bot.py"
      ]
    }
  ],
  "scores": [
    {
      "stats": {
        "fn": 1,
        "tp": 0,
        "fp": 0
      },
      "mapping": {},
      "vuln_dates": {
        "CVE-2023-48699": "2023-11-21T23:15:08"
      },
      "scoring_model": "gpt-4o-2024-05-13",
      "type": "llm",
      "instruction_template_hash": "8998f09cf57fca8a6e03"
    }
  ],
  "instruction_template_hash": "10c0163db4740318a544",
  "version": "0.1.0"
}
