{
  "commit": "12b8a90ff8fda65e2b76a0327954e0128c2336b2",
  "repo_url": "https://github.com/democritus-project/d8s-utility",
  "model": "claude-3-sonnet-20240229",
  "chunk_hashes": [
    "4ea89dc1cbabe2cbb8ae"
  ],
  "responses": [
    {
      "content": "```yaml\nleads:\n  - headline: Potential security vulnerability with the eval() function\n    analysis: |\n      The code in the `d8s_utility/utility.py` file uses the `exec` function in several places,\n      which executes arbitrary Python code dynamically. This can potentially be a security risk if\n      the code being executed is not properly sanitized or validated. An attacker could potentially\n      inject malicious code through user input or other sources, which would then be executed by\n      the `exec` function, leading to code execution vulnerabilities.\n    cwe: CWE-94\n    function_names:\n      - subprocess_run\n      - ignore_errors\n    filenames:\n      - d8s_utility/utility.py\n    classification: slightly promising\n\n  - headline: Potential security vulnerability with string formatting\n    analysis: |\n      The code in the `d8s_utility/utility.py` file uses string formatting with user-supplied input,\n      which could potentially lead to injection vulnerabilities if the input is not properly sanitized.\n      An attacker could potentially inject malicious code or commands through the formatted strings,\n      leading to code execution or command injection vulnerabilities.\n    cwe: CWE-20\n    function_names:\n      - request_or_read\n      - validate_keyword_arg_value\n      - validate_arg_value\n    filenames:\n      - d8s_utility/utility.py\n    classification: slightly promising\n\n  - headline: Potential security vulnerability with file operations\n    analysis: |\n      The code in the `d8s_utility/utility.py` file performs file operations, such as reading and writing files,\n      using user-supplied input. If the input is not properly validated or sanitized, an attacker could potentially\n      provide malicious file paths that could lead to directory traversal or other file system-related vulnerabilities.\n    cwe: CWE-22\n    function_names:\n      - request_or_read_first_arg\n      - _update_test_with_error\n      - _update_test\n    filenames:\n      - conftest.py\n      - d8s_utility/utility.py\n    classification: slightly promising\n\n  - headline: Potential security vulnerability with deserialization\n    analysis: |\n      The code in the `conftest.py` file performs deserialization of data from various sources, such as user input\n      or external files. If the deserialized data is not properly validated or sanitized, an attacker could potentially\n      inject malicious payloads that could lead to code execution or other vulnerabilities.\n    cwe: CWE-502\n    function_names:\n      - _update_test\n      - _update_test_with_error\n    filenames:\n      - conftest.py\n    classification: slightly promising\n\n  - headline: Potential security vulnerability with subprocess execution\n    analysis: |\n      The code in the `d8s_utility/utility.py` file executes subprocesses using user-supplied input. If the input\n      is not properly validated or sanitized, an attacker could potentially inject malicious commands that could\n      lead to code execution or command injection vulnerabilities.\n    cwe: CWE-78\n    function_names:\n      - subprocess_run\n    filenames:\n      - d8s_utility/utility.py\n    classification: slightly promising\n\n  - headline: Potential security vulnerability with network operations\n    analysis: |\n      The code in the `d8s_utility/utility.py` file performs network operations, such as making HTTP requests,\n      using user-supplied input. If the input is not properly validated or sanitized, an attacker could potentially\n      inject malicious URLs or other data that could lead to server-side request forgery (SSRF) or other web-related\n      vulnerabilities.\n    cwe: CWE-918\n    function_names:\n      - request_or_read\n      - request_or_read_first_arg\n    filenames:\n      - d8s_utility/utility.py\n    classification: slightly promising\n\n  # Add more leads as needed\n\n```\n\nThe analysis above identifies several potential security vulnerabilities in the codebase, primarily related to the use of user-supplied input and dynamically executed code. The main concerns include:\n\n1. **Use of eval() and exec() functions**: The code uses the `exec` function to execute arbitrary Python code dynamically, which can potentially lead to code execution vulnerabilities if the executed code is not properly sanitized or validated.\n\n2. **String formatting vulnerabilities**: The code performs string formatting using user-supplied input, which could potentially lead to injection vulnerabilities if the input is not properly sanitized.\n\n3. **File operation vulnerabilities**: The code performs file operations, such as reading and writing files, using user-supplied input. If the input is not properly validated or sanitized, an attacker could potentially exploit directory traversal or other file system-related vulnerabilities.\n\n4. **Deserialization vulnerabilities**: The code deserializes data from various sources, such as user input or external files. If the deserialized data is not properly validated or sanitized, an attacker could potentially inject malicious payloads that could lead to code execution or other vulnerabilities.\n\n5. **Subprocess execution vulnerabilities**: The code executes subprocesses using user-supplied input. If the input is not properly validated or sanitized, an attacker could potentially inject malicious commands that could lead to code execution or command injection vulnerabilities.\n\n6. **Network operation vulnerabilities**: The code performs network operations, such as making HTTP requests, using user-supplied input. If the input is not properly validated or sanitized, an attacker could potentially inject malicious URLs or other data that could lead to server-side request forgery (SSRF) or other web-related vulnerabilities.\n\nIt's important to note that the classification of these leads as \"slightly promising\" or \"not promising\" is subjective and depends on factors such as the specific use case, the context in which the code is used, and the security requirements of the application.\n\nTo mitigate these potential vulnerabilities, it's recommended to implement proper input validation and sanitization techniques, such as using safe libraries for handling user input, performing strict input validation, and following secure coding practices. Additionally, it's advisable to review the code thoroughly and consider conducting security testing, such as penetration testing or code audits, to identify and address any potential vulnerabilities.",
      "date": "2024-06-12T15:59:59.963469",
      "usage": {
        "prompt_tokens": 12075,
        "completion_tokens": 1452,
        "cost": 0.058005
      }
    }
  ],
  "leads": [
    {
      "headline": "Potential security vulnerability with the eval() function",
      "analysis": "The code in the d8s_utility/utility.py file uses the exec function in several places,\nwhich executes arbitrary Python code dynamically. This can potentially be a security risk if\nthe code being executed is not properly sanitized or validated. An attacker could potentially\ninject malicious code through user input or other sources, which would then be executed by\nthe exec function, leading to code execution vulnerabilities.\n",
      "classification": "slightly promising",
      "cwe": "CWE-94",
      "function_names": [
        "subprocess_run",
        "ignore_errors"
      ],
      "filenames": [
        "d8s_utility/utility.py"
      ]
    },
    {
      "headline": "Potential security vulnerability with string formatting",
      "analysis": "The code in the d8s_utility/utility.py file uses string formatting with user-supplied input,\nwhich could potentially lead to injection vulnerabilities if the input is not properly sanitized.\nAn attacker could potentially inject malicious code or commands through the formatted strings,\nleading to code execution or command injection vulnerabilities.\n",
      "classification": "slightly promising",
      "cwe": "CWE-20",
      "function_names": [
        "request_or_read",
        "validate_keyword_arg_value",
        "validate_arg_value"
      ],
      "filenames": [
        "d8s_utility/utility.py"
      ]
    },
    {
      "headline": "Potential security vulnerability with file operations",
      "analysis": "The code in the d8s_utility/utility.py file performs file operations, such as reading and writing files,\nusing user-supplied input. If the input is not properly validated or sanitized, an attacker could potentially\nprovide malicious file paths that could lead to directory traversal or other file system-related vulnerabilities.\n",
      "classification": "slightly promising",
      "cwe": "CWE-22",
      "function_names": [
        "request_or_read_first_arg",
        "_update_test_with_error",
        "_update_test"
      ],
      "filenames": [
        "conftest.py",
        "d8s_utility/utility.py"
      ]
    },
    {
      "headline": "Potential security vulnerability with deserialization",
      "analysis": "The code in the conftest.py file performs deserialization of data from various sources, such as user input\nor external files. If the deserialized data is not properly validated or sanitized, an attacker could potentially\ninject malicious payloads that could lead to code execution or other vulnerabilities.\n",
      "classification": "slightly promising",
      "cwe": "CWE-502",
      "function_names": [
        "_update_test",
        "_update_test_with_error"
      ],
      "filenames": [
        "conftest.py"
      ]
    },
    {
      "headline": "Potential security vulnerability with subprocess execution",
      "analysis": "The code in the d8s_utility/utility.py file executes subprocesses using user-supplied input. If the input\nis not properly validated or sanitized, an attacker could potentially inject malicious commands that could\nlead to code execution or command injection vulnerabilities.\n",
      "classification": "slightly promising",
      "cwe": "CWE-78",
      "function_names": [
        "subprocess_run"
      ],
      "filenames": [
        "d8s_utility/utility.py"
      ]
    },
    {
      "headline": "Potential security vulnerability with network operations",
      "analysis": "The code in the d8s_utility/utility.py file performs network operations, such as making HTTP requests,\nusing user-supplied input. If the input is not properly validated or sanitized, an attacker could potentially\ninject malicious URLs or other data that could lead to server-side request forgery (SSRF) or other web-related\nvulnerabilities.\n",
      "classification": "slightly promising",
      "cwe": "CWE-918",
      "function_names": [
        "request_or_read",
        "request_or_read_first_arg"
      ],
      "filenames": [
        "d8s_utility/utility.py"
      ]
    }
  ],
  "scores": [
    {
      "stats": {
        "fn": 3,
        "tp": 0,
        "fp": 0
      },
      "mapping": {},
      "vuln_dates": {
        "CVE-2022-40430": "2022-09-19T16:15:12",
        "CVE-2022-41386": "2022-10-11T22:15:11",
        "CVE-2022-41381": "2022-10-11T22:15:11"
      },
      "scoring_model": "claude-3-opus-20240229",
      "type": "llm",
      "instruction_template_hash": "245ace12b6361954d0a2"
    }
  ],
  "instruction_template_hash": "10c0163db4740318a544",
  "version": "0.1.0"
}
