{
  "commit": "2423fee143459247c6b961beffed4c13b31c2a3b",
  "repo_url": "https://github.com/weaveworks/vscode-gitops-tools",
  "model": "gpt-4-turbo-2024-04-09",
  "chunk_hashes": [
    "52539c216eaa060bbac4"
  ],
  "responses": [
    {
      "content": "```yaml\nleads:\n  - headline: Improper handling of untrusted input for VSCode context setting\n    analysis: |\n      The function `setVSCodeContext` which is used across various parts of the system appears to request and manipulate VSCode context settings without properly validating the type or origin of the provided context values. This could lead to incorrect operation or potential security vulnerabilities if the context is manipulated with crafted values.\n    cwe: CWE-20\n    function_names:\n      - setVSCodeContext\n    filenames:\n      - src/commands/fluxCheck.ts\n      - src/commands/enableDisableGitOps.ts\n      - src/commands/deleteSource.ts\n      - src/views/treeViews.ts\n      - src/views/dataProviders/clusterDataProvider.ts\n    classification: slightly promising\n  - headline: Insecure storage of sensitive information\n    analysis: |\n      The extension stores sensitive information such as Azure Metadata which includes subscription ID, resource names, and similar Azure-specific details directly within the global state without apparent encryption or secure handling mechanisms. This might allow other extensions or unauthorized parties to access this information.\n    cwe: CWE-922\n    function_names:\n      - getAzureMetadata\n      - askUserForAzureMetadata\n    filenames:\n      - src/azure/azureTools.ts\n      - src/azure/getAzureMetadata.ts\n    classification: slightly promising\n  - headline: Excessive permissions and potential overexposure of resources in cluster interaction\n    analysis: |\n      The Azure integration functions (like `createSourceGit`, `enableGitOps`, `disableGitops`) interact with the Kubernetes API and possibly Azure resources with a high level of access, without clear separation or restriction of permissions. This might give the extension more control over the system than necessary, expanding the attack surface.\n    cwe: CWE-276\n    function_names:\n      - createSourceGit\n      - enableGitOps\n      - disableGitOps\n    filenames:\n      - src/azure/azureTools.ts\n    classification: slightly promising\n  - headline: Potential command injection in shell execution\n    analysis: |\n      Input from potentially untrusted sources is used to construct shell commands across multiple places within the extension ('downloadFile', 'unzipFile', 'moveFile') without sufficient sanitization and validation. This could lead to command injection if the inputs are crafted maliciously.\n    cwe: CWE-77\n    function_name:\n      - shell.exec\n    filenames:\n      - src/utils/fsUtils.ts\n    classification: very promising\n  - headline: Lack of user input validation for Git operations\n    analysis: |\n      User inputs used in constructing Git commands like cloning or pulling repositories ('createGitRepository', `pullGitRepository`) are taken directly without sufficient input sanitization. If manipulated, these inputs could potentially lead to operational discrepancies or security issues in interaction with the Git repositories.\n    cwe: CWE-20\n    function_names:\n      - pullGitRepository\n      - createGitRepository\n    filenames:\n      - src/commands/pullGitRepository.ts\n      - src/commands/createGitRepository.ts\n    classification: slightly promising\n```",
      "date": "2024-06-13T18:05:58.461771",
      "usage": {
        "prompt_tokens": 81472,
        "completion_tokens": 644,
        "cost": 0.83404
      }
    }
  ],
  "leads": [
    {
      "headline": "Improper handling of untrusted input for VSCode context setting",
      "analysis": "The function setVSCodeContext which is used across various parts of the system appears to request and manipulate VSCode context settings without properly validating the type or origin of the provided context values. This could lead to incorrect operation or potential security vulnerabilities if the context is manipulated with crafted values.\n",
      "classification": "slightly promising",
      "cwe": "CWE-20",
      "function_names": [
        "setVSCodeContext"
      ],
      "filenames": [
        "src/commands/fluxCheck.ts",
        "src/commands/enableDisableGitOps.ts",
        "src/commands/deleteSource.ts"
      ]
    },
    {
      "headline": "Insecure storage of sensitive information",
      "analysis": "The extension stores sensitive information such as Azure Metadata which includes subscription ID, resource names, and similar Azure-specific details directly within the global state without apparent encryption or secure handling mechanisms. This might allow other extensions or unauthorized parties to access this information.\n",
      "classification": "slightly promising",
      "cwe": "CWE-922",
      "function_names": [
        "getAzureMetadata",
        "askUserForAzureMetadata"
      ],
      "filenames": [
        "src/azure/azureTools.ts",
        "src/azure/getAzureMetadata.ts"
      ]
    },
    {
      "headline": "Excessive permissions and potential overexposure of resources in cluster interaction",
      "analysis": "The Azure integration functions (like createSourceGit, enableGitOps, disableGitops) interact with the Kubernetes API and possibly Azure resources with a high level of access, without clear separation or restriction of permissions. This might give the extension more control over the system than necessary, expanding the attack surface.\n",
      "classification": "slightly promising",
      "cwe": "CWE-276",
      "function_names": [
        "createSourceGit",
        "enableGitOps",
        "disableGitOps"
      ],
      "filenames": [
        "src/azure/azureTools.ts"
      ]
    },
    {
      "headline": "Potential command injection in shell execution",
      "analysis": "Input from potentially untrusted sources is used to construct shell commands across multiple places within the extension ('downloadFile', 'unzipFile', 'moveFile') without sufficient sanitization and validation. This could lead to command injection if the inputs are crafted maliciously.\n",
      "classification": "very promising",
      "cwe": "CWE-77",
      "function_names": [],
      "filenames": [
        "src/utils/fsUtils.ts"
      ]
    },
    {
      "headline": "Lack of user input validation for Git operations",
      "analysis": "User inputs used in constructing Git commands like cloning or pulling repositories ('createGitRepository', pullGitRepository) are taken directly without sufficient input sanitization. If manipulated, these inputs could potentially lead to operational discrepancies or security issues in interaction with the Git repositories.\n",
      "classification": "slightly promising",
      "cwe": "CWE-20",
      "function_names": [
        "pullGitRepository",
        "createGitRepository"
      ],
      "filenames": [
        "src/commands/pullGitRepository.ts",
        "src/commands/createGitRepository.ts"
      ]
    }
  ],
  "scores": [
    {
      "stats": {
        "fn": 1,
        "tp": 0,
        "fp": 1
      },
      "mapping": {},
      "vuln_dates": {
        "CVE-2022-35976": "2022-08-18T19:15:14"
      },
      "scoring_model": "claude-3-opus-20240229",
      "type": "llm",
      "instruction_template_hash": "245ace12b6361954d0a2"
    },
    {
      "stats": {
        "fn": 1,
        "tp": 0,
        "fp": 1
      },
      "mapping": {},
      "vuln_dates": {
        "CVE-2022-35976": "2022-08-18T19:15:14"
      },
      "scoring_model": "claude-3-5-sonnet-20240620",
      "type": "llm",
      "instruction_template_hash": "245ace12b6361954d0a2"
    }
  ],
  "instruction_template_hash": "10c0163db4740318a544",
  "version": "0.1.0"
}
