{
  "commit": "1d0f791efad16f0baa9b6a34779395d51aec26fb",
  "repo_url": "https://github.com/jenkinsci/apprenda-plugin",
  "model": "gpt-4-turbo-2024-04-09",
  "chunk_hashes": [
    "01f3019ab605e80f3464"
  ],
  "responses": [
    {
      "content": "```yaml\nleads:\n  - headline: Sensitive Data Exposure through Error Messages\n    analysis: |\n      The ApprendaClient class within the ApprendaClient.java file may expose sensitive information through error messages under certain conditions, notably during failed authentication. The detailed error messages, including stack traces and exceptions, are printed and can disclose sensitive configuration details or system information to unauthorized users.\n    cwe: CWE-209\n    function_names:\n      - authenticate\n    filenames:\n      - src/main/java/com/apprenda/jenkins/plugins/apprenda/ApprendaClient.java\n    classification: slightly promising\n\n  - headline: Man-in-the-middle (MITM) attack due to SSL/TLS verification bypass\n    analysis: |\n      The ApprendaRestUtility class contains a method getClient which will conditionally disable SSL/TLS certificate verification if the bypassSSL parameter is true. While this option may be intended for development or testing scenarios, its inclusion in production code can lead to severe vulnerabilities, including the possibility of man-in-the-middle attacks where an attacker can intercept or alter the data in transit.\n    cwe: CWE-295\n    function_names:\n      - getClient\n    filenames:\n      - src/main/java/utils/ApprendaRestUtility.java\n    classification: very promising\n\n  - headline: Hardcoded credential use with bypassSSL flag\n    analysis: |\n      The ApprendaCredentials class contains a 'bypassSSL' parameter that, when set, indicates the system should connect without SSL verification. This parameter, coupled with other sensitive details like tenant, username, and password within the same class, raises concerns about hardcoded security decisions that can lead to broader security vulnerabilities.\n    cwe: CWE-798\n    function_names:\n      - ApprendaCredentials\n    filenames:\n      - src/main/java/com/apprenda/jenkins/plugins/apprenda/ApprendaCredentials.java\n    classification: slightly promising\n\n  - headline: Potential Remote Code Execution via Arbitrary File Upload\n    analysis: |\n      The createApp and patchApp methods within ApprendaClient.java potentially allow arbitrary file uploads without sufficient validation of the incoming file's content or origin. With certain configurations, these methods could be exploited by an attacker to upload malicious files, potentially leading to remote code execution if the uploaded files are executed by the server.\n    cwe: CWE-434\n    function_names:\n      - createApp\n      - patchApp\n    filenames:\n      - src/main/java/com/apprenda/jenkins/plugins/apprenda/ApprendaClient.java\n    classification: slightly promising\n\n  - headline: Insufficient Logging and Monitoring of Failed Authentication Attempts\n    analysis: |\n      Within the ApprendaClient class, the authenticate method is used to manage user authentication. However, there does not appear to be sufficient logging or monitoring of authentication attempts, which could aid an attacker in performing brute force attacks without being detected.\n    cwe: CWE-307\n    function_names:\n      - authenticate\n    filenames:\n      - src/main/java/com/apprenda/jenkins/plugins/apprenda/ApprendaClient.java\n    classification: not promising\n```",
      "date": "2024-06-12T17:38:45.527879",
      "usage": {
        "prompt_tokens": 12133,
        "completion_tokens": 637,
        "cost": 0.14044
      }
    }
  ],
  "leads": [
    {
      "headline": "Sensitive Data Exposure through Error Messages",
      "analysis": "The ApprendaClient class within the ApprendaClient.java file may expose sensitive information through error messages under certain conditions, notably during failed authentication. The detailed error messages, including stack traces and exceptions, are printed and can disclose sensitive configuration details or system information to unauthorized users.\n",
      "classification": "slightly promising",
      "cwe": "CWE-209",
      "function_names": [
        "authenticate"
      ],
      "filenames": [
        "src/main/java/com/apprenda/jenkins/plugins/apprenda/ApprendaClient.java"
      ]
    },
    {
      "headline": "Man-in-the-middle (MITM) attack due to SSL/TLS verification bypass",
      "analysis": "The ApprendaRestUtility class contains a method getClient which will conditionally disable SSL/TLS certificate verification if the bypassSSL parameter is true. While this option may be intended for development or testing scenarios, its inclusion in production code can lead to severe vulnerabilities, including the possibility of man-in-the-middle attacks where an attacker can intercept or alter the data in transit.\n",
      "classification": "very promising",
      "cwe": "CWE-295",
      "function_names": [
        "getClient"
      ],
      "filenames": [
        "src/main/java/utils/ApprendaRestUtility.java"
      ]
    },
    {
      "headline": "Hardcoded credential use with bypassSSL flag",
      "analysis": "The ApprendaCredentials class contains a 'bypassSSL' parameter that, when set, indicates the system should connect without SSL verification. This parameter, coupled with other sensitive details like tenant, username, and password within the same class, raises concerns about hardcoded security decisions that can lead to broader security vulnerabilities.\n",
      "classification": "slightly promising",
      "cwe": "CWE-798",
      "function_names": [
        "ApprendaCredentials"
      ],
      "filenames": [
        "src/main/java/com/apprenda/jenkins/plugins/apprenda/ApprendaCredentials.java"
      ]
    },
    {
      "headline": "Potential Remote Code Execution via Arbitrary File Upload",
      "analysis": "The createApp and patchApp methods within ApprendaClient.java potentially allow arbitrary file uploads without sufficient validation of the incoming file's content or origin. With certain configurations, these methods could be exploited by an attacker to upload malicious files, potentially leading to remote code execution if the uploaded files are executed by the server.\n",
      "classification": "slightly promising",
      "cwe": "CWE-434",
      "function_names": [
        "createApp",
        "patchApp"
      ],
      "filenames": [
        "src/main/java/com/apprenda/jenkins/plugins/apprenda/ApprendaClient.java"
      ]
    },
    {
      "headline": "Insufficient Logging and Monitoring of Failed Authentication Attempts",
      "analysis": "Within the ApprendaClient class, the authenticate method is used to manage user authentication. However, there does not appear to be sufficient logging or monitoring of authentication attempts, which could aid an attacker in performing brute force attacks without being detected.\n",
      "classification": "not promising",
      "cwe": "CWE-307",
      "function_names": [
        "authenticate"
      ],
      "filenames": [
        "src/main/java/com/apprenda/jenkins/plugins/apprenda/ApprendaClient.java"
      ]
    }
  ],
  "scores": [
    {
      "stats": {
        "fn": 1,
        "tp": 0,
        "fp": 1
      },
      "mapping": {},
      "vuln_dates": {
        "CVE-2022-41251": "2022-09-21T16:15:11"
      },
      "scoring_model": "claude-3-opus-20240229",
      "type": "llm",
      "instruction_template_hash": "245ace12b6361954d0a2"
    }
  ],
  "instruction_template_hash": "10c0163db4740318a544",
  "version": "0.1.0"
}
