{
  "commit": "28da581611a0256a3962aa534c77a90ebd936752",
  "repo_url": "https://github.com/davesteele/gnome-gmail",
  "model": "gpt-4o-2024-05-13",
  "chunk_hashes": [
    "1d1b32501ef6de6df145"
  ],
  "responses": [
    {
      "content": "```yaml\nleads:\n  - headline: \"Embedded Credentials in Source Code\"\n    analysis: |\n      The `GMOauth` class contains hardcoded client ID and client secret for OAuth2 authentication. This allows attackers with access to the source code to discover these credentials and potentially misuse the OAuth2 mechanism or craft their attacks. The hardcoded credentials were found in the `__init__` method of the `GMOauth` class.\n    cwe: CWE-798\n    function_names:\n      - \"__init__\"\n    filenames:\n      - \"gnomegmail.py\"\n    classification: very promising\n  \n  - headline: \"Command Injection via Subprocess Call\"\n    analysis: |\n      In the `browser` function, the command `cmd = \"xdg-settings get default-web-browser\"` is executed using `subprocess.check_output(cmd.split(), universal_newlines=True)`. An attacker controlling the `cmd` variable could potentially execute arbitrary commands on the system with the privileges of the running script.\n    cwe: CWE-78\n    function_names:\n      - \"browser\"\n    filenames:\n      - \"gnomegmail.py\"\n    classification: very promising\n\n  - headline: \"HTTP Server Misconfiguration Leading to Information Leak\"\n    analysis: |\n      The script sets up a simple HTTP server using `HTTPServer` and `BaseHTTPRequestHandler`. However, it does not perform sufficient validation on incoming and outgoing requests. An attacker could exploit this to steal OAuth authentication codes or engage in other attacks.\n    cwe: CWE-918\n    function_names:\n      - \"get_code\"\n    filenames:\n      - \"gnomegmail.py\"\n    classification: very promising\n\n  - headline: \"Insecure Use of os.open for File Descriptors\"\n    analysis: |\n      The `nullfd` context manager uses `os.open(os.devnull, os.O_RDWR)` to open file descriptors without secure practices. This could lead to vulnerabilities associated with file descriptor leakage or redirection.\n    cwe: CWE-404\n    function_names:\n      - \"nullfd\"\n    filenames:\n      - \"gnomegmail.py\"\n    classification: slightly promising\n\n  - headline: \"Insufficient Encoding of E-Mail Contents\"\n    analysis: |\n      In the `GMailAPI` class, method `body2html`, there is insufficient proper escaping or encoding of user-supplied content before embedding it into the HTML body of the email. This could potentially lead to XSS attacks where user input is displayed.\n    cwe: CWE-79\n    function_names:\n      - \"body2html\"\n    filenames:\n      - \"gnomegmail.py\"\n    classification: very promising\n\n  - headline: \"Cleartext Transmission of Sensitive Information\"\n    analysis: |\n      The refresh token and access token are transmitted in cleartext when communicating with the Google OAuth2 API and GMail API using HTTP. Although SSL/TLS might be used at the transport layer, the code does not enforce or check this explicitly.\n    cwe: CWE-319\n    function_names:\n      - \"get_token_dict\"\n      - \"get_access_from_refresh\"\n      - \"upload_mail\"\n      - \"send_mail\"\n    filenames:\n      - \"gnomegmail.py\"\n    classification: very promising\n\n  - headline: \"Potential Improper Synchronization Leading to Race Conditions\"\n    analysis: |\n      The usage of GTK main iteration in `get_code`, especially in the context of waiting for and processing OAuth codes, might expose it to potential race conditions due to the handling of GTK events and potential window interactions.\n    cwe: CWE-362\n    function_names:\n      - \"get_code\"\n    filenames:\n      - \"gnomegmail.py\"\n    classification: slightly promising\n```",
      "date": "2024-06-12T15:54:56.275111",
      "usage": {
        "prompt_tokens": 15060,
        "completion_tokens": 764,
        "cost": 0.08676
      }
    }
  ],
  "leads": [
    {
      "headline": "Embedded Credentials in Source Code",
      "analysis": "The GMOauth class contains hardcoded client ID and client secret for OAuth2 authentication. This allows attackers with access to the source code to discover these credentials and potentially misuse the OAuth2 mechanism or craft their attacks. The hardcoded credentials were found in the __init__ method of the GMOauth class.\n",
      "classification": "very promising",
      "cwe": "CWE-798",
      "function_names": [
        "__init__"
      ],
      "filenames": [
        "gnomegmail.py"
      ]
    },
    {
      "headline": "Command Injection via Subprocess Call",
      "analysis": "In the browser function, the command cmd = \"xdg-settings get default-web-browser\" is executed using subprocess.check_output(cmd.split(), universal_newlines=True). An attacker controlling the cmd variable could potentially execute arbitrary commands on the system with the privileges of the running script.\n",
      "classification": "very promising",
      "cwe": "CWE-78",
      "function_names": [
        "browser"
      ],
      "filenames": [
        "gnomegmail.py"
      ]
    },
    {
      "headline": "HTTP Server Misconfiguration Leading to Information Leak",
      "analysis": "The script sets up a simple HTTP server using HTTPServer and BaseHTTPRequestHandler. However, it does not perform sufficient validation on incoming and outgoing requests. An attacker could exploit this to steal OAuth authentication codes or engage in other attacks.\n",
      "classification": "very promising",
      "cwe": "CWE-918",
      "function_names": [
        "get_code"
      ],
      "filenames": [
        "gnomegmail.py"
      ]
    },
    {
      "headline": "Insecure Use of os.open for File Descriptors",
      "analysis": "The nullfd context manager uses os.open(os.devnull, os.O_RDWR) to open file descriptors without secure practices. This could lead to vulnerabilities associated with file descriptor leakage or redirection.\n",
      "classification": "slightly promising",
      "cwe": "CWE-404",
      "function_names": [
        "nullfd"
      ],
      "filenames": [
        "gnomegmail.py"
      ]
    },
    {
      "headline": "Insufficient Encoding of E-Mail Contents",
      "analysis": "In the GMailAPI class, method body2html, there is insufficient proper escaping or encoding of user-supplied content before embedding it into the HTML body of the email. This could potentially lead to XSS attacks where user input is displayed.\n",
      "classification": "very promising",
      "cwe": "CWE-79",
      "function_names": [
        "body2html"
      ],
      "filenames": [
        "gnomegmail.py"
      ]
    },
    {
      "headline": "Cleartext Transmission of Sensitive Information",
      "analysis": "The refresh token and access token are transmitted in cleartext when communicating with the Google OAuth2 API and GMail API using HTTP. Although SSL/TLS might be used at the transport layer, the code does not enforce or check this explicitly.\n",
      "classification": "very promising",
      "cwe": "CWE-319",
      "function_names": [
        "get_token_dict",
        "get_access_from_refresh",
        "upload_mail"
      ],
      "filenames": [
        "gnomegmail.py"
      ]
    },
    {
      "headline": "Potential Improper Synchronization Leading to Race Conditions",
      "analysis": "The usage of GTK main iteration in get_code, especially in the context of waiting for and processing OAuth codes, might expose it to potential race conditions due to the handling of GTK events and potential window interactions.\n",
      "classification": "slightly promising",
      "cwe": "CWE-362",
      "function_names": [
        "get_code"
      ],
      "filenames": [
        "gnomegmail.py"
      ]
    }
  ],
  "scores": [
    {
      "stats": {
        "fn": 1,
        "tp": 0,
        "fp": 5
      },
      "mapping": {},
      "vuln_dates": {
        "CVE-2020-24904": "2023-08-11T14:15:10"
      },
      "scoring_model": "claude-3-opus-20240229",
      "type": "llm",
      "instruction_template_hash": "245ace12b6361954d0a2"
    },
    {
      "stats": {
        "fn": 1,
        "tp": 0,
        "fp": 5
      },
      "mapping": {},
      "vuln_dates": {
        "CVE-2020-24904": "2023-08-11T14:15:10"
      },
      "scoring_model": "claude-3-5-sonnet-20240620",
      "type": "llm",
      "instruction_template_hash": "245ace12b6361954d0a2"
    }
  ],
  "instruction_template_hash": "10c0163db4740318a544",
  "version": "0.1.0"
}
