{
  "commit": "02fb07f6b4885c599e84077078e095a1007dae61",
  "repo_url": "https://github.com/0xjacky/nginx-ui",
  "model": "claude-3-sonnet-20240229",
  "chunk_hashes": [
    "4c41606ae6c6e0ce5048"
  ],
  "responses": [
    {
      "content": "```yaml\nleads:\n  - headline: 'Potential command injection vulnerability'\n    analysis: |\n      The `install.sh` script uses the `curl` command without properly sanitizing user input from the `--proxy` and `--reverse-proxy` options. An attacker could potentially inject malicious code into the command by passing a crafted string containing shell metacharacters (e.g., `--proxy \"http://example.com/$(rm -rf /)\"`) to execute arbitrary commands on the system.\n    cwe: CWE-78\n    function_names:\n      - 'judgment_parameters'\n    filenames:\n      - 'install.sh'\n    classification: slightly promising\n\n  - headline: 'Potential arbitrary file upload vulnerability'\n    analysis: |\n      The `frontend/api/domain.ts` file has a function `add_auto_cert` that could potentially allow an attacker to upload arbitrary files to the server by sending a crafted request with a malicious filename. This could lead to remote code execution or other attacks if the uploaded file is not properly validated and handled.\n    cwe: CWE-434\n    function_names:\n      - 'add_auto_cert'\n    filenames:\n      - 'frontend/api/domain.ts'\n    classification: slightly promising\n\n  - headline: 'Potential code injection vulnerability'\n    analysis: |\n      The `frontend/vite.config.ts` file configures the Vite development server to proxy requests to a remote server (`https://nginx.jackyu.cn/`). If the remote server is compromised or returns malicious code, it could potentially lead to code injection attacks when developing the application.\n    cwe: CWE-94\n    function_names: []\n    filenames:\n      - 'frontend/vite.config.ts'\n    classification: slightly promising\n\n  - headline: 'Potential cross-site scripting (XSS) vulnerability'\n    analysis: |\n      The `frontend/index.html` file renders the page title using server-side data (`<title><%- title %></title>`). If the `title` value is not properly sanitized, it could potentially lead to a cross-site scripting (XSS) vulnerability, allowing an attacker to inject malicious scripts into the page.\n    cwe: CWE-79\n    function_names: []\n    filenames:\n      - 'frontend/index.html'\n    classification: slightly promising\n\n  - headline: 'Potential insecure deserialization vulnerability'\n    analysis: |\n      The codebase uses JSON Web Tokens (JWT) for authentication (`frontend/lib/http/index.ts`). If the JWT secret is compromised or if the JWT implementation has vulnerabilities, it could potentially lead to insecure deserialization attacks, allowing an attacker to forge or tamper with JWT tokens.\n    cwe: CWE-502\n    function_names: []\n    filenames:\n      - 'frontend/lib/http/index.ts'\n    classification: slightly promising\n\n  - headline: 'Potential information disclosure vulnerability'\n    analysis: |\n      The `frontend/views/system/About.vue` file exposes information about the development mode and potentially other sensitive information. An attacker could potentially use this information to gain insights into the application's configuration and potentially identify other vulnerabilities.\n    cwe: CWE-200\n    function_names: []\n    filenames:\n      - 'frontend/views/system/About.vue'\n    classification: slightly promising\n\n  - headline: 'Potential hardcoded credentials vulnerability'\n    analysis: |\n      The `frontend/api/auth.ts` file contains hardcoded credentials (`root` and `password`) for the demo environment. While this is likely intended for demonstration purposes, hardcoded credentials in production environments could potentially lead to unauthorized access if the credentials are not changed or properly secured.\n    cwe: CWE-798\n    function_names: []\n    filenames:\n      - 'frontend/api/auth.ts'\n    classification: not promising\n\n  - headline: 'Potential insecure communication vulnerability'\n    analysis: |\n      The `frontend/lib/websocket/index.ts` file uses WebSockets for communication. If the WebSocket connection is not properly secured (e.g., using HTTPS), it could potentially lead to eavesdropping or man-in-the-middle attacks, compromising the confidentiality and integrity of the data transmitted.\n    cwe: CWE-319\n    function_names: []\n    filenames:\n      - 'frontend/lib/websocket/index.ts'\n    classification: slightly promising\n\n  - headline: 'Potential denial of service vulnerability'\n    analysis: |\n      The `frontend/views/domain/ngx_conf/LocationEditor.vue` file allows the user to add arbitrary locations to the Nginx configuration. If the input is not properly validated, an attacker could potentially add a large number of locations or crafted locations to cause a denial of service condition or other unintended behavior.\n    cwe: CWE-400\n    function_names:\n      - 'addLocation'\n    filenames:\n      - 'frontend/views/domain/ngx_conf/LocationEditor.vue'\n    classification: slightly promising\n```\n\nThe analysis covers various potential security vulnerabilities in the provided codebase, including command injection, arbitrary file upload, code injection, cross-site scripting (XSS), insecure deserialization, information disclosure, hardcoded credentials, insecure communication, and denial of service vulnerabilities.\n\nPlease note that a more thorough analysis, including reviewing the server-side code and performing dynamic analysis, would be required to confirm the existence and severity of these potential vulnerabilities. Additionally, the classification of the vulnerabilities as \"slightly promising\" or \"not promising\" is subjective and may vary based on the specific context and risk assessment criteria.",
      "date": "2024-06-08T19:09:58.226114",
      "usage": {
        "prompt_tokens": 26642,
        "completion_tokens": 1358,
        "cost": 0.100296
      }
    }
  ],
  "leads": [
    {
      "headline": "Potential command injection vulnerability",
      "analysis": "The install.sh script uses the curl command without properly sanitizing user input from the --proxy and --reverse-proxy options. An attacker could potentially inject malicious code into the command by passing a crafted string containing shell metacharacters (e.g., --proxy \"http://example.com/$(rm -rf /)\") to execute arbitrary commands on the system.\n",
      "classification": "slightly promising",
      "cwe": "CWE-78",
      "function_names": [
        "judgment_parameters"
      ],
      "filenames": [
        "install.sh"
      ]
    },
    {
      "headline": "Potential arbitrary file upload vulnerability",
      "analysis": "The frontend/api/domain.ts file has a function add_auto_cert that could potentially allow an attacker to upload arbitrary files to the server by sending a crafted request with a malicious filename. This could lead to remote code execution or other attacks if the uploaded file is not properly validated and handled.\n",
      "classification": "slightly promising",
      "cwe": "CWE-434",
      "function_names": [
        "add_auto_cert"
      ],
      "filenames": [
        "frontend/api/domain.ts"
      ]
    },
    {
      "headline": "Potential code injection vulnerability",
      "analysis": "The frontend/vite.config.ts file configures the Vite development server to proxy requests to a remote server (https://nginx.jackyu.cn/). If the remote server is compromised or returns malicious code, it could potentially lead to code injection attacks when developing the application.\n",
      "classification": "slightly promising",
      "cwe": "CWE-94",
      "function_names": [],
      "filenames": [
        "frontend/vite.config.ts"
      ]
    },
    {
      "headline": "Potential cross-site scripting (XSS) vulnerability",
      "analysis": "The frontend/index.html file renders the page title using server-side data (<title><%- title %></title>). If the title value is not properly sanitized, it could potentially lead to a cross-site scripting (XSS) vulnerability, allowing an attacker to inject malicious scripts into the page.\n",
      "classification": "slightly promising",
      "cwe": "CWE-79",
      "function_names": [],
      "filenames": [
        "frontend/index.html"
      ]
    },
    {
      "headline": "Potential insecure deserialization vulnerability",
      "analysis": "The codebase uses JSON Web Tokens (JWT) for authentication (frontend/lib/http/index.ts). If the JWT secret is compromised or if the JWT implementation has vulnerabilities, it could potentially lead to insecure deserialization attacks, allowing an attacker to forge or tamper with JWT tokens.\n",
      "classification": "slightly promising",
      "cwe": "CWE-502",
      "function_names": [],
      "filenames": [
        "frontend/lib/http/index.ts"
      ]
    },
    {
      "headline": "Potential information disclosure vulnerability",
      "analysis": "The frontend/views/system/About.vue file exposes information about the development mode and potentially other sensitive information. An attacker could potentially use this information to gain insights into the application's configuration and potentially identify other vulnerabilities.\n",
      "classification": "slightly promising",
      "cwe": "CWE-200",
      "function_names": [],
      "filenames": [
        "frontend/views/system/About.vue"
      ]
    },
    {
      "headline": "Potential hardcoded credentials vulnerability",
      "analysis": "The frontend/api/auth.ts file contains hardcoded credentials (root and password) for the demo environment. While this is likely intended for demonstration purposes, hardcoded credentials in production environments could potentially lead to unauthorized access if the credentials are not changed or properly secured.\n",
      "classification": "not promising",
      "cwe": "CWE-798",
      "function_names": [],
      "filenames": [
        "frontend/api/auth.ts"
      ]
    },
    {
      "headline": "Potential insecure communication vulnerability",
      "analysis": "The frontend/lib/websocket/index.ts file uses WebSockets for communication. If the WebSocket connection is not properly secured (e.g., using HTTPS), it could potentially lead to eavesdropping or man-in-the-middle attacks, compromising the confidentiality and integrity of the data transmitted.\n",
      "classification": "slightly promising",
      "cwe": "CWE-319",
      "function_names": [],
      "filenames": [
        "frontend/lib/websocket/index.ts"
      ]
    },
    {
      "headline": "Potential denial of service vulnerability",
      "analysis": "The frontend/views/domain/ngx_conf/LocationEditor.vue file allows the user to add arbitrary locations to the Nginx configuration. If the input is not properly validated, an attacker could potentially add a large number of locations or crafted locations to cause a denial of service condition or other unintended behavior.\n",
      "classification": "slightly promising",
      "cwe": "CWE-400",
      "function_names": [
        "addLocation"
      ],
      "filenames": [
        "frontend/views/domain/ngx_conf/LocationEditor.vue"
      ]
    }
  ],
  "scores": [
    {
      "stats": {
        "fn": 4,
        "tp": 0,
        "fp": 0
      },
      "mapping": {},
      "vuln_dates": {
        "CVE-2024-23827": "2024-01-29T16:15:09",
        "CVE-2024-22198": "2024-01-11T20:15:45",
        "CVE-2024-22197": "2024-01-11T18:15:45",
        "CVE-2024-22196": "2024-01-11T20:15:44"
      },
      "scoring_model": "gpt-4o-2024-05-13",
      "type": "llm",
      "instruction_template_hash": "8998f09cf57fca8a6e03"
    },
    {
      "stats": {
        "fn": 4,
        "tp": 0,
        "fp": 0
      },
      "mapping": {},
      "vuln_dates": {
        "CVE-2024-23827": "2024-01-29T16:15:09",
        "CVE-2024-22198": "2024-01-11T20:15:45",
        "CVE-2024-22197": "2024-01-11T18:15:45",
        "CVE-2024-22196": "2024-01-11T20:15:44"
      },
      "scoring_model": "claude-3-opus-20240229",
      "type": "llm",
      "instruction_template_hash": "245ace12b6361954d0a2"
    },
    {
      "stats": {
        "fn": 4,
        "tp": 0,
        "fp": 0
      },
      "mapping": {},
      "vuln_dates": {
        "CVE-2024-23827": "2024-01-29T16:15:09",
        "CVE-2024-22198": "2024-01-11T20:15:45",
        "CVE-2024-22197": "2024-01-11T18:15:45",
        "CVE-2024-22196": "2024-01-11T20:15:44"
      },
      "scoring_model": "claude-3-5-sonnet-20240620",
      "type": "llm",
      "instruction_template_hash": "245ace12b6361954d0a2"
    }
  ],
  "instruction_template_hash": "6d88c94b8282011ae3db",
  "version": "0.1.0"
}
