{
  "commit": "27ed36c03297713d2cfa79431cdc8105602e80c2",
  "repo_url": "https://github.com/libimobiledevice/libplist",
  "model": "gpt-4o-2024-05-13",
  "chunk_hashes": [
    "4862f657edc6d17c409e"
  ],
  "responses": [
    {
      "content": "```yaml\nleads:\n  - headline: \"Potential Memory Leak in Duplicate Nodes\"\n    analysis: |\n      The function node_attach in libcnary/node.c allows attaching a node to multiple parents by creating a\n      deep copy of the node. If the original node is attached to multiple parents, the deep copies can lead to memory leaks if not properly\n      freed. This issue was observed in the function write_dict in src/bplist.c when handling dictionary nodes.\n    cwe: CWE-401\n    function_names:\n      - node_attach\n      - write_dict\n    filenames:\n      - libcnary/node.c\n      - src/bplist.c\n    classification: very promising\n  \n  - headline: \"Potential Buffer Overflow in plist_dict_set_item\"\n    analysis: |\n      In the function plist_dict_set_item in src/plist.c, the value set within the dictionary is replaced without\n      checking the size of the incoming value. This could potentially lead to a buffer overflow if the value's size exceeds the \n      allocated buffer size in the dictionary.\n    cwe: CWE-120\n    function_names:\n      - plist_dict_set_item\n    filenames:\n      - src/plist.c\n    classification: very promising\n  \n  - headline: \"Improper Input Validation in Multiple Functions\"\n    analysis: |\n      Multiple functions across the codebase do not validate input parameters properly, which could lead to different issues such as\n      buffer overflow, integer overflow, or null pointer dereference. Specifically, functions such as plist_array_get_item, plist_dict_get_item, \n      and plist_get_type_and_value lack proper validation of incoming parameters.\n    cwe: CWE-20\n    function_names:\n      - plist_array_get_item\n      - plist_dict_get_item\n      - plist_get_type_and_value\n    filenames:\n      - src/plist.c\n    classification: very promising\n\n  - headline: \"Potential Use of Uninitialized Resource\"\n    analysis: |\n      The function plist_get_data initializes a plist_data_t structure with calloc but does not cover all potential failure cases while\n      accessing its fields. This issue could lead to the use of uninitialized memory, causing unpredictable behavior.\n    cwe: CWE-908\n    function_names:\n      - plist_get_data\n    filenames:\n      - src/plist.c\n    classification: very promising\n    \n  - headline: \"Double-Free Vulnerability in plist_free_node\"\n    analysis: |\n      The function plist_free_node deallocates memory for node and its data. However, if the same node is referenced in multiple places,\n      releasing memory of a node could lead to double-free errors, causing undefined behavior and potential security risks.\n    cwe: CWE-415\n    function_names:\n      - plist_free_node\n    filenames:\n      - src/plist.c\n    classification: very promising\n  \n  - headline: \"Unchecked Return Value in array_get_size\"\n    analysis: |\n      The function array_get_size does not check the return values of lower-level functions like plist_array_get_size. If the size is \n      not validated, incorrect size values could propagate to higher-level logic, leading to erroneous behavior or security vulnerabilities.\n    cwe: CWE-252\n    function_names:\n      - array_get_size\n    filenames:\n      - src/Array.cpp\n    classification: slightly promising\n\n  - headline: \"Weak Password Recovery Mechanism\"\n    analysis: |\n      In src/Array.cpp, function Append might be used in contexts where an existing dictionary or array structure is altered. There's no \n      visible logic handling the authentication of changes or protecting recovery mechanisms, potentially leading to weakened security in \n      scenarios involving password recovery or sensitive data changes.\n    cwe: CWE-640\n    function_names:\n      - Append\n    filenames:\n      - src/Array.cpp\n    classification: slightly promising\n\n  - headline: \"Missing Authentication for Critical Function\"\n    analysis: |\n      The autogen.sh script carries out critical system setups. There are no checks in place to validate the authenticity or integrity of \n      components before performing operations, making it vulnerable to unauthorized manipulations.\n    cwe: CWE-306\n    function_names: []\n    filenames:\n      - autogen.sh\n    classification: very promising\n```",
      "date": "2024-06-13T09:42:50.434842",
      "usage": {
        "prompt_tokens": 55481,
        "completion_tokens": 868,
        "cost": 0.290425
      }
    }
  ],
  "leads": [
    {
      "headline": "Potential Memory Leak in Duplicate Nodes",
      "analysis": "The function node_attach in libcnary/node.c allows attaching a node to multiple parents by creating a\ndeep copy of the node. If the original node is attached to multiple parents, the deep copies can lead to memory leaks if not properly\nfreed. This issue was observed in the function write_dict in src/bplist.c when handling dictionary nodes.\n",
      "classification": "very promising",
      "cwe": "CWE-401",
      "function_names": [
        "node_attach",
        "write_dict"
      ],
      "filenames": [
        "libcnary/node.c",
        "src/bplist.c"
      ]
    },
    {
      "headline": "Potential Buffer Overflow in plist_dict_set_item",
      "analysis": "In the function plist_dict_set_item in src/plist.c, the value set within the dictionary is replaced without\nchecking the size of the incoming value. This could potentially lead to a buffer overflow if the value's size exceeds the \nallocated buffer size in the dictionary.\n",
      "classification": "very promising",
      "cwe": "CWE-120",
      "function_names": [
        "plist_dict_set_item"
      ],
      "filenames": [
        "src/plist.c"
      ]
    },
    {
      "headline": "Improper Input Validation in Multiple Functions",
      "analysis": "Multiple functions across the codebase do not validate input parameters properly, which could lead to different issues such as\nbuffer overflow, integer overflow, or null pointer dereference. Specifically, functions such as plist_array_get_item, plist_dict_get_item, \nand plist_get_type_and_value lack proper validation of incoming parameters.\n",
      "classification": "very promising",
      "cwe": "CWE-20",
      "function_names": [
        "plist_array_get_item",
        "plist_dict_get_item",
        "plist_get_type_and_value"
      ],
      "filenames": [
        "src/plist.c"
      ]
    },
    {
      "headline": "Potential Use of Uninitialized Resource",
      "analysis": "The function plist_get_data initializes a plist_data_t structure with calloc but does not cover all potential failure cases while\naccessing its fields. This issue could lead to the use of uninitialized memory, causing unpredictable behavior.\n",
      "classification": "very promising",
      "cwe": "CWE-908",
      "function_names": [
        "plist_get_data"
      ],
      "filenames": [
        "src/plist.c"
      ]
    },
    {
      "headline": "Double-Free Vulnerability in plist_free_node",
      "analysis": "The function plist_free_node deallocates memory for node and its data. However, if the same node is referenced in multiple places,\nreleasing memory of a node could lead to double-free errors, causing undefined behavior and potential security risks.\n",
      "classification": "very promising",
      "cwe": "CWE-415",
      "function_names": [
        "plist_free_node"
      ],
      "filenames": [
        "src/plist.c"
      ]
    },
    {
      "headline": "Unchecked Return Value in array_get_size",
      "analysis": "The function array_get_size does not check the return values of lower-level functions like plist_array_get_size. If the size is \nnot validated, incorrect size values could propagate to higher-level logic, leading to erroneous behavior or security vulnerabilities.\n",
      "classification": "slightly promising",
      "cwe": "CWE-252",
      "function_names": [
        "array_get_size"
      ],
      "filenames": [
        "src/Array.cpp"
      ]
    },
    {
      "headline": "Weak Password Recovery Mechanism",
      "analysis": "In src/Array.cpp, function Append might be used in contexts where an existing dictionary or array structure is altered. There's no \nvisible logic handling the authentication of changes or protecting recovery mechanisms, potentially leading to weakened security in \nscenarios involving password recovery or sensitive data changes.\n",
      "classification": "slightly promising",
      "cwe": "CWE-640",
      "function_names": [
        "Append"
      ],
      "filenames": [
        "src/Array.cpp"
      ]
    },
    {
      "headline": "Missing Authentication for Critical Function",
      "analysis": "The autogen.sh script carries out critical system setups. There are no checks in place to validate the authenticity or integrity of \ncomponents before performing operations, making it vulnerable to unauthorized manipulations.\n",
      "classification": "very promising",
      "cwe": "CWE-306",
      "function_names": [],
      "filenames": [
        "autogen.sh"
      ]
    }
  ],
  "scores": [
    {
      "stats": {
        "fn": 7,
        "tp": 0,
        "fp": 6
      },
      "mapping": {},
      "vuln_dates": {
        "CVE-2017-7982": "2017-04-20T14:59:00",
        "CVE-2017-6439": "2017-03-15T14:59:01",
        "CVE-2017-6440": "2017-03-15T14:59:01",
        "CVE-2017-6438": "2017-03-15T14:59:01",
        "CVE-2017-6437": "2017-03-15T14:59:01",
        "CVE-2017-6435": "2017-03-15T14:59:00",
        "CVE-2017-6436": "2017-03-15T14:59:00"
      },
      "scoring_model": "claude-3-opus-20240229",
      "type": "llm",
      "instruction_template_hash": "245ace12b6361954d0a2"
    },
    {
      "stats": {
        "fn": 7,
        "tp": 0,
        "fp": 6
      },
      "mapping": {},
      "vuln_dates": {
        "CVE-2017-7982": "2017-04-20T14:59:00",
        "CVE-2017-6439": "2017-03-15T14:59:01",
        "CVE-2017-6440": "2017-03-15T14:59:01",
        "CVE-2017-6438": "2017-03-15T14:59:01",
        "CVE-2017-6437": "2017-03-15T14:59:01",
        "CVE-2017-6435": "2017-03-15T14:59:00",
        "CVE-2017-6436": "2017-03-15T14:59:00"
      },
      "scoring_model": "claude-3-5-sonnet-20240620",
      "type": "llm",
      "instruction_template_hash": "245ace12b6361954d0a2"
    }
  ],
  "instruction_template_hash": "10c0163db4740318a544",
  "version": "0.1.0"
}
