{
  "commit": "26c21082e943f29d24356984a2f3eaae6a104b34",
  "repo_url": "https://github.com/vinsdragonis/project-nexus",
  "model": "claude-3-5-sonnet-20240620",
  "chunk_hashes": [
    "0bb029b7d6ac136f787c"
  ],
  "responses": [
    {
      "content": "```yaml\nleads:\n  - headline: Improper Authorization in User Update and Delete\n    analysis: |\n      In the users.js file, the routes for updating and deleting a user only check if the userId in the request body matches the id in the URL parameter. This allows any authenticated user to potentially update or delete any other user's account by simply providing the correct userId in the request body. There is no verification that the authenticated user actually owns the account they are trying to modify. This could lead to unauthorized access and modification of user accounts.\n    cwe: CWE-285\n    function_names:\n      - router.put\n      - router.delete\n    filenames:\n      - api/routes/users.js\n    classification: very promising\n\n  - headline: Missing Error Handling in Login Route\n    analysis: |\n      In the auth.js file, the login route has a try-catch block, but the catch block is empty. This means that any errors occurring during the login process are silently ignored. This could lead to unexpected behavior and make debugging difficult. Additionally, it may expose information about the system to potential attackers if errors are not properly handled and logged.\n    cwe: CWE-755\n    function_names:\n      - router.post\n    filenames:\n      - api/routes/auth.js\n    classification: slightly promising\n\n  - headline: Potential NoSQL Injection in User Lookup\n    analysis: |\n      In the auth.js file, the login route uses direct user input to query the database without any sanitization. The line `const user = await User.findOne({ username: req.body.username });` takes the username directly from the request body. If an attacker sends a specially crafted object instead of a string for the username, it could lead to a NoSQL injection attack, potentially allowing unauthorized access to user accounts.\n    cwe: CWE-943\n    function_names:\n      - router.post\n    filenames:\n      - api/routes/auth.js\n    classification: very promising\n\n  - headline: Insecure File Upload Configuration\n    analysis: |\n      In the index.js file, the file upload configuration allows the client to specify the filename of the uploaded file without any validation or sanitization. The line `cb(null, req.body.name);` in the filename function of multer storage configuration uses the name provided in the request body directly. This could allow an attacker to overwrite existing files or upload files with malicious extensions, potentially leading to arbitrary code execution on the server.\n    cwe: CWE-434\n    function_names:\n      - multer.diskStorage\n    filenames:\n      - api/index.js\n    classification: very promising\n\n  - headline: Missing Input Validation in Post Creation\n    analysis: |\n      In the posts.js file, the route for creating a new post (`router.post(\"/\")`) does not perform any input validation before saving the post to the database. It directly uses the request body to create a new Post object. This could allow an attacker to inject malicious data into the database or create posts with invalid or malformed data, potentially leading to application errors or data integrity issues.\n    cwe: CWE-20\n    function_names:\n      - router.post\n    filenames:\n      - api/routes/posts.js\n    classification: slightly promising\n```",
      "date": "2024-07-08T09:12:20.306721",
      "usage": {
        "prompt_tokens": 8032,
        "completion_tokens": 754,
        "cost": 0.035406
      }
    }
  ],
  "leads": [
    {
      "headline": "Improper Authorization in User Update and Delete",
      "analysis": "In the users.js file, the routes for updating and deleting a user only check if the userId in the request body matches the id in the URL parameter. This allows any authenticated user to potentially update or delete any other user's account by simply providing the correct userId in the request body. There is no verification that the authenticated user actually owns the account they are trying to modify. This could lead to unauthorized access and modification of user accounts.\n",
      "classification": "very promising",
      "cwe": "CWE-285",
      "function_names": [
        "router.put",
        "router.delete"
      ],
      "filenames": [
        "api/routes/users.js"
      ]
    },
    {
      "headline": "Missing Error Handling in Login Route",
      "analysis": "In the auth.js file, the login route has a try-catch block, but the catch block is empty. This means that any errors occurring during the login process are silently ignored. This could lead to unexpected behavior and make debugging difficult. Additionally, it may expose information about the system to potential attackers if errors are not properly handled and logged.\n",
      "classification": "slightly promising",
      "cwe": "CWE-755",
      "function_names": [
        "router.post"
      ],
      "filenames": [
        "api/routes/auth.js"
      ]
    },
    {
      "headline": "Potential NoSQL Injection in User Lookup",
      "analysis": "In the auth.js file, the login route uses direct user input to query the database without any sanitization. The line const user = await User.findOne({ username: req.body.username }); takes the username directly from the request body. If an attacker sends a specially crafted object instead of a string for the username, it could lead to a NoSQL injection attack, potentially allowing unauthorized access to user accounts.\n",
      "classification": "very promising",
      "cwe": "CWE-943",
      "function_names": [
        "router.post"
      ],
      "filenames": [
        "api/routes/auth.js"
      ]
    },
    {
      "headline": "Insecure File Upload Configuration",
      "analysis": "In the index.js file, the file upload configuration allows the client to specify the filename of the uploaded file without any validation or sanitization. The line cb(null, req.body.name); in the filename function of multer storage configuration uses the name provided in the request body directly. This could allow an attacker to overwrite existing files or upload files with malicious extensions, potentially leading to arbitrary code execution on the server.\n",
      "classification": "very promising",
      "cwe": "CWE-434",
      "function_names": [
        "multer.diskStorage"
      ],
      "filenames": [
        "api/index.js"
      ]
    },
    {
      "headline": "Missing Input Validation in Post Creation",
      "analysis": "In the posts.js file, the route for creating a new post (router.post(\"/\")) does not perform any input validation before saving the post to the database. It directly uses the request body to create a new Post object. This could allow an attacker to inject malicious data into the database or create posts with invalid or malformed data, potentially leading to application errors or data integrity issues.\n",
      "classification": "slightly promising",
      "cwe": "CWE-20",
      "function_names": [
        "router.post"
      ],
      "filenames": [
        "api/routes/posts.js"
      ]
    }
  ],
  "scores": [
    {
      "stats": {
        "fn": 1,
        "tp": 0,
        "fp": 3
      },
      "mapping": {},
      "vuln_dates": {
        "CVE-2022-36030": "2022-08-20T00:15:42"
      },
      "scoring_model": "claude-3-5-sonnet-20240620",
      "type": "llm",
      "instruction_template_hash": "245ace12b6361954d0a2"
    }
  ],
  "instruction_template_hash": "10c0163db4740318a544",
  "version": "0.1.0"
}
