{
  "commit": "1a2935c398a286929d6731245f021514c942af7f",
  "repo_url": "https://github.com/jenkinsci/jira-ext-plugin",
  "model": "gpt-4o-2024-05-13",
  "chunk_hashes": [
    "4e1f1f0f3e2ff6bab640"
  ],
  "responses": [
    {
      "content": "```yaml\nleads:\n  - headline: \"Hard-coded Credentials in Test Setup\"\n    analysis: |\n      The `jiraBaseUrl`, `username`, and `password` are hardcoded directly within the test setup methods and configurations in multiple places within the test files. This is an insecure practice because it exposes sensitive information within the source code, which can be extracted if the code repository is compromised.\n    cwe: CWE-798\n    function_names:\n      - setup\n      - testSaveConfig\n    filenames:\n      - src/test/java/org/jenkinsci/plugins/jiraext/ConfigTest.java\n      - src/test/java/org/jenkinsci/plugins/jiraext/svc/impl/JiraClientFactoryImplTest.java\n    classification: very promising\n\n  - headline: \"Weak Hard-coded Credentials in Test Setup\"\n    analysis: |\n      The test configuration includes hard-coded credentials like `ChangeMe!` and `username` which are weak. This practice, even in test environments, sets a bad precedent and may lead to similar practices in production code, making it easier for attackers to predict and crack credentials.\n    cwe: CWE-521\n    function_names:\n      - setup\n    filenames:\n      - src/test/java/org/jenkinsci/plugins/jiraext/svc/impl/JiraClientFactoryImplTest.java\n    classification: very promising\n\n  - headline: \"Hard-coded Credentials in HardCodedJiraClientFactoryImpl\"\n    analysis: |\n      The `HardCodedJiraClientFactoryImpl` class contains hard-coded credentials, which are intended for development use by the comment. However, including these directly in the source code is dangerous as they can be inadvertently moved to production or misused, compromising the security of the Jira system.\n    cwe: CWE-798\n    function_names:\n      - newJiraClient\n    filenames:\n      - src/main/java/org/jenkinsci/plugins/jiraext/svc/impl/HardCodedJiraClientFactoryImpl.java\n    classification: very promising\n\n  - headline: \"Potential Insecure Storage of Sensitive Information in Config\"\n    analysis: |\n      The `Config` class is storing sensitive information such as `username`, `password`, and `jiraBaseUrl` in plain text within its properties. This poses a risk of exposing sensitive information in case of unauthorized access to the Jenkins instance or the serialized files.\n    cwe: CWE-922\n    function_names:\n      - getDescriptor\n      - configure\n    filenames:\n      - src/main/java/org/jenkinsci/plugins/jiraext/Config.java\n    classification: very promising\n\n  - headline: \"Clear-text Transmission of Sensitive Information\"\n    analysis: |\n      The configuration does not mention whether the credentials (`username` and `password`) are encrypted before being transmitted over the network. If these credentials are transmitted in clear text, it could lead to interception by unauthorized actors.\n    cwe: CWE-319\n    function_names:\n      - newJiraClient\n    filenames:\n      - src/main/java/org/jenkinsci/plugins/jiraext/svc/impl/JiraClientFactoryImpl.java\n      - src/main/java/org/jenkinsci/plugins/jiraext/svc/impl/JiraClientSvcImpl.java\n    classification: slightly promising\n\n  - headline: \"Missing Authorization Checks\"\n    analysis: |\n      The code handling Jira interactions does not include sufficient authorization checks to verify if the user has necessary permissions to perform operations like adding comments, labels or transitioning issues. Absence of such checks can be exploited by unauthorized users to perform restricted actions.\n    cwe: CWE-862\n    function_names: \n      - addCommentToTicket\n      - addLabelToTicket\n      - changeWorkflowOfTicket\n      - updateStringField\n      - addLabelToField\n    filenames:\n      - src/main/java/org/jenkinsci/plugins/jiraext/svc/impl/JiraClientSvcImpl.java\n    classification: very promising\n```",
      "date": "2024-06-12T18:43:04.565993",
      "usage": {
        "prompt_tokens": 39843,
        "completion_tokens": 818,
        "cost": 0.211485
      }
    }
  ],
  "leads": [
    {
      "headline": "Hard-coded Credentials in Test Setup",
      "analysis": "The jiraBaseUrl, username, and password are hardcoded directly within the test setup methods and configurations in multiple places within the test files. This is an insecure practice because it exposes sensitive information within the source code, which can be extracted if the code repository is compromised.\n",
      "classification": "very promising",
      "cwe": "CWE-798",
      "function_names": [
        "setup",
        "testSaveConfig"
      ],
      "filenames": [
        "src/test/java/org/jenkinsci/plugins/jiraext/ConfigTest.java",
        "src/test/java/org/jenkinsci/plugins/jiraext/svc/impl/JiraClientFactoryImplTest.java"
      ]
    },
    {
      "headline": "Weak Hard-coded Credentials in Test Setup",
      "analysis": "The test configuration includes hard-coded credentials like ChangeMe! and username which are weak. This practice, even in test environments, sets a bad precedent and may lead to similar practices in production code, making it easier for attackers to predict and crack credentials.\n",
      "classification": "very promising",
      "cwe": "CWE-521",
      "function_names": [
        "setup"
      ],
      "filenames": [
        "src/test/java/org/jenkinsci/plugins/jiraext/svc/impl/JiraClientFactoryImplTest.java"
      ]
    },
    {
      "headline": "Hard-coded Credentials in HardCodedJiraClientFactoryImpl",
      "analysis": "The HardCodedJiraClientFactoryImpl class contains hard-coded credentials, which are intended for development use by the comment. However, including these directly in the source code is dangerous as they can be inadvertently moved to production or misused, compromising the security of the Jira system.\n",
      "classification": "very promising",
      "cwe": "CWE-798",
      "function_names": [
        "newJiraClient"
      ],
      "filenames": [
        "src/main/java/org/jenkinsci/plugins/jiraext/svc/impl/HardCodedJiraClientFactoryImpl.java"
      ]
    },
    {
      "headline": "Potential Insecure Storage of Sensitive Information in Config",
      "analysis": "The Config class is storing sensitive information such as username, password, and jiraBaseUrl in plain text within its properties. This poses a risk of exposing sensitive information in case of unauthorized access to the Jenkins instance or the serialized files.\n",
      "classification": "very promising",
      "cwe": "CWE-922",
      "function_names": [
        "getDescriptor",
        "configure"
      ],
      "filenames": [
        "src/main/java/org/jenkinsci/plugins/jiraext/Config.java"
      ]
    },
    {
      "headline": "Clear-text Transmission of Sensitive Information",
      "analysis": "The configuration does not mention whether the credentials (username and password) are encrypted before being transmitted over the network. If these credentials are transmitted in clear text, it could lead to interception by unauthorized actors.\n",
      "classification": "slightly promising",
      "cwe": "CWE-319",
      "function_names": [
        "newJiraClient"
      ],
      "filenames": [
        "src/main/java/org/jenkinsci/plugins/jiraext/svc/impl/JiraClientFactoryImpl.java",
        "src/main/java/org/jenkinsci/plugins/jiraext/svc/impl/JiraClientSvcImpl.java"
      ]
    },
    {
      "headline": "Missing Authorization Checks",
      "analysis": "The code handling Jira interactions does not include sufficient authorization checks to verify if the user has necessary permissions to perform operations like adding comments, labels or transitioning issues. Absence of such checks can be exploited by unauthorized users to perform restricted actions.\n",
      "classification": "very promising",
      "cwe": "CWE-862",
      "function_names": [
        "addCommentToTicket",
        "addLabelToTicket",
        "changeWorkflowOfTicket"
      ],
      "filenames": [
        "src/main/java/org/jenkinsci/plugins/jiraext/svc/impl/JiraClientSvcImpl.java"
      ]
    }
  ],
  "scores": [
    {
      "stats": {
        "fn": 0,
        "tp": 1,
        "fp": 3
      },
      "mapping": {
        "2": "CVE-2019-10302",
        "3": "CVE-2019-10302"
      },
      "vuln_dates": {
        "CVE-2019-10302": "2019-04-18T17:29:00"
      },
      "scoring_model": "claude-3-opus-20240229",
      "type": "llm",
      "instruction_template_hash": "245ace12b6361954d0a2"
    },
    {
      "stats": {
        "fn": 0,
        "tp": 1,
        "fp": 3
      },
      "mapping": {
        "2": "CVE-2019-10302",
        "3": "CVE-2019-10302"
      },
      "vuln_dates": {
        "CVE-2019-10302": "2019-04-18T17:29:00"
      },
      "scoring_model": "claude-3-5-sonnet-20240620",
      "type": "llm",
      "instruction_template_hash": "245ace12b6361954d0a2"
    }
  ],
  "instruction_template_hash": "10c0163db4740318a544",
  "version": "0.1.0"
}
