{
  "commit": "3ddead1584c9e9055b0f04850bf93cff4d7a60f2",
  "repo_url": "https://github.com/alexcrichton/bzip2-rs",
  "model": "claude-3-haiku-20240307",
  "chunk_hashes": [
    "f4dca8b59ab22e85a46f"
  ],
  "responses": [
    {
      "content": "Here is the YAML output equivalent to the type LeadList, according to the provided Pydantic definitions:\n\n```yaml\nleads:\n  - headline: Improper Neutralization of Formula Elements in a CSV File\n    analysis: |\n      The code appears to contain a vulnerability related to the improper neutralization of formula elements in a CSV file. This could allow an attacker to inject malicious formulas into the CSV file, which could then be executed when the file is opened or processed.\n    cwe: CWE-1236\n    function_names:\n      - compress\n      - compressStream\n      - sendMTFValues\n    filenames:\n      - bzip2-sys/bzip2-1.0.8/compress.c\n    classification: slightly promising\n  - headline: Improper Neutralization of Special Elements used in an Expression Language Statement ('Expression Language Injection')\n    analysis: |\n      The code appears to contain a vulnerability related to the improper neutralization of special elements used in an Expression Language Statement. This could allow an attacker to inject malicious expression language code into the compressed data stream, which could then be executed when the data is decompressed.\n    cwe: CWE-917\n    function_names:\n      - BZ2_bzCompress\n      - sendMTFValues\n    filenames:\n      - bzip2-sys/bzip2-1.0.8/compress.c\n    classification: slightly promising\n  - headline: Improper Restriction of Operations within the Bounds of a Memory Buffer\n    analysis: |\n      The code appears to contain vulnerabilities related to improper restriction of operations within the bounds of a memory buffer. This could lead to buffer overflow or out-of-bounds read/write vulnerabilities, which could potentially be exploited by an attacker.\n    cwe: CWE-119\n    function_names:\n      - BZ2_bzCompress\n      - sendMTFValues\n    filenames:\n      - bzip2-sys/bzip2-1.0.8/compress.c\n    classification: slightly promising\n  - headline: Insufficient Entropy\n    analysis: |\n      The code appears to use a random number generator to introduce randomness into the compressed data stream. However, the implementation of the random number generator may not be providing sufficient entropy, which could make the compressed data stream more predictable and vulnerable to attacks.\n    cwe: CWE-331\n    function_names:\n      - BZ2_bzCompress\n      - sendMTFValues\n    filenames:\n      - bzip2-sys/bzip2-1.0.8/compress.c\n    classification: slightly promising\n  - headline: Improper Encoding or Escaping of Output\n    analysis: |\n      The code appears to be responsible for generating the compressed data stream, which may not be properly encoded or escaped. This could lead to vulnerabilities where the compressed data stream contains malicious content that could be executed or interpreted in an unintended way.\n    cwe: CWE-116\n    function_names:\n      - BZ2_bzCompress\n      - sendMTFValues\n    filenames:\n      - bzip2-sys/bzip2-1.0.8/compress.c\n    classification: slightly promising\n  - headline: Improper Neutralization of Special Elements used in an OS Command ('OS Command Injection')\n    analysis: |\n      The code appears to be responsible for generating the compressed data stream, which could potentially contain malicious OS command elements. This could lead to OS command injection vulnerabilities if the compressed data is later executed or processed in an unsafe manner.\n    cwe: CWE-78\n    function_names:\n      - BZ2_bzCompress\n      - sendMTFValues\n    filenames:\n      - bzip2-sys/bzip2-1.0.8/compress.c\n    classification: slightly promising\n  - headline: Improper Neutralization of Input During Web Page Generation ('Cross-site Scripting')\n    analysis: |\n      The code appears to be responsible for generating the compressed data stream, which could potentially contain malicious cross-site scripting (XSS) elements. This could lead to XSS vulnerabilities if the compressed data is later processed and displayed in a web application or other context where user-supplied content is not properly sanitized.\n    cwe: CWE-79\n    function_names:\n      - BZ2_bzCompress\n      - sendMTFValues\n    filenames:\n      - bzip2-sys/bzip2-1.0.8/compress.c\n    classification: slightly promising\n  - headline: Improper Neutralization of Special Elements used in an SQL Command ('SQL Injection')\n    analysis: |\n      The code appears to be responsible for generating the compressed data stream, which could potentially contain malicious SQL injection elements. This could lead to SQL injection vulnerabilities if the compressed data is later processed and used in an SQL query or other database operation without proper sanitization.\n    cwe: CWE-89\n    function_names:\n      - BZ2_bzCompress\n      - sendMTFValues\n    filenames:\n      - bzip2-sys/bzip2-1.0.8/compress.c\n    classification: slightly promising\n  - headline: Improper Restriction of Operations within the Bounds of a Memory Buffer\n    analysis: |\n      The code appears to contain vulnerabilities related to improper restriction of operations within the bounds of a memory buffer. This could lead to buffer overflow or out-of-bounds read/write vulnerabilities, which could potentially be exploited by an attacker.\n    cwe: CWE-119\n    function_names:\n      - unRLE_obuf_to_output_FAST\n      - unRLE_obuf_to_output_SMALL\n    filenames:\n      - bzip2-sys/bzip2-1.0.8/decompress.c\n    classification: slightly promising\n  - headline: Improper Neutralization of Special Elements used in an Expression Language Statement ('Expression Language Injection')\n    analysis: |\n      The code appears to contain a vulnerability related to the improper neutralization of special elements used in an Expression Language Statement. This could allow an attacker to inject malicious expression language code into the decompressed data stream, which could then be executed when the data is processed.\n    cwe: CWE-917\n    function_names:\n      - BZ2_decompress\n    filenames:\n      - bzip2-sys/bzip2-1.0.8/decompress.c\n    classification: slightly promising\n  - headline: Improper Neutralization of Input During Web Page Generation ('Cross-site Scripting')\n    analysis: |\n      The code appears to be responsible for decompressing the compressed data stream, which could potentially contain malicious cross-site scripting (XSS) elements. This could lead to XSS vulnerabilities if the decompressed data is later processed and displayed in a web application or other context where user-supplied content is not properly sanitized.\n    cwe: CWE-79\n    function_names:\n      - BZ2_decompress\n    filenames:\n      - bzip2-sys/bzip2-1.0.8/decompress.c\n    classification: slightly promising\n  - headline: Improper Neutralization of Special Elements used in an OS Command ('OS Command Injection')\n    analysis: |\n      The code appears to be responsible for decompressing the compressed data stream, which could potentially contain malicious OS command elements. This could lead to OS command injection vulnerabilities if the decompressed data is later executed or processed in an unsafe manner.\n    cwe: CWE-78\n    function_names:\n      - BZ2_decompress\n    filenames:\n      - bzip2-sys/bzip2-1.0.8/decompress.c\n    classification: slightly promising\n  - headline: Improper Neutralization of Special Elements used in an SQL Command ('SQL Injection')\n    analysis: |\n      The code appears to be responsible for decompressing the compressed data stream, which could potentially contain malicious SQL injection elements. This could lead to SQL injection vulnerabilities if the decompressed data is later processed and used in an SQL query or other database operation without proper sanitization.\n    cwe: CWE-89\n    function_names:\n      - BZ2_decompress\n    filenames:\n      - bzip2-sys/bzip2-1.0.8/decompress.c\n    classification: slightly promising\n  - headline: Improper Restriction of Power Consumption\n    analysis: |\n      The code appears to be responsible for decompressing the compressed data stream, which could potentially lead to excessive power consumption or denial-of-service attacks if the decompression process is not properly restricted or throttled.\n    cwe: CWE-920\n    function_names:\n      - BZ2_decompress\n    filenames:\n      - bzip2-sys/bzip2-1.0.8/decompress.c\n    classification: slightly promising\n  - headline: Improper Restriction of Dynamically-Managed Code Resources\n    analysis: |\n      The code appears to be responsible for processing and decompressing the compressed data stream, which could potentially lead to vulnerabilities related to the improper restriction or handling of dynamically-managed code resources, such as unsafe reflection or deserialization vulnerabilities.\n    cwe: CWE-913\n    function_names:\n      - BZ2_decompress\n    filenames:\n      - bzip2-sys/bzip2-1.0.8/decompress.c\n    classification: slightly promising\n\n```",
      "date": "2024-06-14T12:48:51.258943",
      "usage": {
        "prompt_tokens": 134625,
        "completion_tokens": 2234,
        "cost": 0.03644875
      }
    }
  ],
  "leads": [
    {
      "headline": "Improper Neutralization of Formula Elements in a CSV File",
      "analysis": "The code appears to contain a vulnerability related to the improper neutralization of formula elements in a CSV file. This could allow an attacker to inject malicious formulas into the CSV file, which could then be executed when the file is opened or processed.\n",
      "classification": "slightly promising",
      "cwe": "CWE-1236",
      "function_names": [
        "compress",
        "compressStream",
        "sendMTFValues"
      ],
      "filenames": [
        "bzip2-sys/bzip2-1.0.8/compress.c"
      ]
    },
    {
      "headline": "Improper Neutralization of Special Elements used in an Expression Language Statement ('Expression Language Injection')",
      "analysis": "The code appears to contain a vulnerability related to the improper neutralization of special elements used in an Expression Language Statement. This could allow an attacker to inject malicious expression language code into the compressed data stream, which could then be executed when the data is decompressed.\n",
      "classification": "slightly promising",
      "cwe": "CWE-917",
      "function_names": [
        "BZ2_bzCompress",
        "sendMTFValues"
      ],
      "filenames": [
        "bzip2-sys/bzip2-1.0.8/compress.c"
      ]
    },
    {
      "headline": "Improper Restriction of Operations within the Bounds of a Memory Buffer",
      "analysis": "The code appears to contain vulnerabilities related to improper restriction of operations within the bounds of a memory buffer. This could lead to buffer overflow or out-of-bounds read/write vulnerabilities, which could potentially be exploited by an attacker.\n",
      "classification": "slightly promising",
      "cwe": "CWE-119",
      "function_names": [
        "BZ2_bzCompress",
        "sendMTFValues"
      ],
      "filenames": [
        "bzip2-sys/bzip2-1.0.8/compress.c"
      ]
    },
    {
      "headline": "Insufficient Entropy",
      "analysis": "The code appears to use a random number generator to introduce randomness into the compressed data stream. However, the implementation of the random number generator may not be providing sufficient entropy, which could make the compressed data stream more predictable and vulnerable to attacks.\n",
      "classification": "slightly promising",
      "cwe": "CWE-331",
      "function_names": [
        "BZ2_bzCompress",
        "sendMTFValues"
      ],
      "filenames": [
        "bzip2-sys/bzip2-1.0.8/compress.c"
      ]
    },
    {
      "headline": "Improper Encoding or Escaping of Output",
      "analysis": "The code appears to be responsible for generating the compressed data stream, which may not be properly encoded or escaped. This could lead to vulnerabilities where the compressed data stream contains malicious content that could be executed or interpreted in an unintended way.\n",
      "classification": "slightly promising",
      "cwe": "CWE-116",
      "function_names": [
        "BZ2_bzCompress",
        "sendMTFValues"
      ],
      "filenames": [
        "bzip2-sys/bzip2-1.0.8/compress.c"
      ]
    },
    {
      "headline": "Improper Neutralization of Special Elements used in an OS Command ('OS Command Injection')",
      "analysis": "The code appears to be responsible for generating the compressed data stream, which could potentially contain malicious OS command elements. This could lead to OS command injection vulnerabilities if the compressed data is later executed or processed in an unsafe manner.\n",
      "classification": "slightly promising",
      "cwe": "CWE-78",
      "function_names": [
        "BZ2_bzCompress",
        "sendMTFValues"
      ],
      "filenames": [
        "bzip2-sys/bzip2-1.0.8/compress.c"
      ]
    },
    {
      "headline": "Improper Neutralization of Input During Web Page Generation ('Cross-site Scripting')",
      "analysis": "The code appears to be responsible for generating the compressed data stream, which could potentially contain malicious cross-site scripting (XSS) elements. This could lead to XSS vulnerabilities if the compressed data is later processed and displayed in a web application or other context where user-supplied content is not properly sanitized.\n",
      "classification": "slightly promising",
      "cwe": "CWE-79",
      "function_names": [
        "BZ2_bzCompress",
        "sendMTFValues"
      ],
      "filenames": [
        "bzip2-sys/bzip2-1.0.8/compress.c"
      ]
    },
    {
      "headline": "Improper Neutralization of Special Elements used in an SQL Command ('SQL Injection')",
      "analysis": "The code appears to be responsible for generating the compressed data stream, which could potentially contain malicious SQL injection elements. This could lead to SQL injection vulnerabilities if the compressed data is later processed and used in an SQL query or other database operation without proper sanitization.\n",
      "classification": "slightly promising",
      "cwe": "CWE-89",
      "function_names": [
        "BZ2_bzCompress",
        "sendMTFValues"
      ],
      "filenames": [
        "bzip2-sys/bzip2-1.0.8/compress.c"
      ]
    },
    {
      "headline": "Improper Restriction of Operations within the Bounds of a Memory Buffer",
      "analysis": "The code appears to contain vulnerabilities related to improper restriction of operations within the bounds of a memory buffer. This could lead to buffer overflow or out-of-bounds read/write vulnerabilities, which could potentially be exploited by an attacker.\n",
      "classification": "slightly promising",
      "cwe": "CWE-119",
      "function_names": [
        "unRLE_obuf_to_output_FAST",
        "unRLE_obuf_to_output_SMALL"
      ],
      "filenames": [
        "bzip2-sys/bzip2-1.0.8/decompress.c"
      ]
    },
    {
      "headline": "Improper Neutralization of Special Elements used in an Expression Language Statement ('Expression Language Injection')",
      "analysis": "The code appears to contain a vulnerability related to the improper neutralization of special elements used in an Expression Language Statement. This could allow an attacker to inject malicious expression language code into the decompressed data stream, which could then be executed when the data is processed.\n",
      "classification": "slightly promising",
      "cwe": "CWE-917",
      "function_names": [
        "BZ2_decompress"
      ],
      "filenames": [
        "bzip2-sys/bzip2-1.0.8/decompress.c"
      ]
    },
    {
      "headline": "Improper Neutralization of Input During Web Page Generation ('Cross-site Scripting')",
      "analysis": "The code appears to be responsible for decompressing the compressed data stream, which could potentially contain malicious cross-site scripting (XSS) elements. This could lead to XSS vulnerabilities if the decompressed data is later processed and displayed in a web application or other context where user-supplied content is not properly sanitized.\n",
      "classification": "slightly promising",
      "cwe": "CWE-79",
      "function_names": [
        "BZ2_decompress"
      ],
      "filenames": [
        "bzip2-sys/bzip2-1.0.8/decompress.c"
      ]
    },
    {
      "headline": "Improper Neutralization of Special Elements used in an OS Command ('OS Command Injection')",
      "analysis": "The code appears to be responsible for decompressing the compressed data stream, which could potentially contain malicious OS command elements. This could lead to OS command injection vulnerabilities if the decompressed data is later executed or processed in an unsafe manner.\n",
      "classification": "slightly promising",
      "cwe": "CWE-78",
      "function_names": [
        "BZ2_decompress"
      ],
      "filenames": [
        "bzip2-sys/bzip2-1.0.8/decompress.c"
      ]
    },
    {
      "headline": "Improper Neutralization of Special Elements used in an SQL Command ('SQL Injection')",
      "analysis": "The code appears to be responsible for decompressing the compressed data stream, which could potentially contain malicious SQL injection elements. This could lead to SQL injection vulnerabilities if the decompressed data is later processed and used in an SQL query or other database operation without proper sanitization.\n",
      "classification": "slightly promising",
      "cwe": "CWE-89",
      "function_names": [
        "BZ2_decompress"
      ],
      "filenames": [
        "bzip2-sys/bzip2-1.0.8/decompress.c"
      ]
    },
    {
      "headline": "Improper Restriction of Power Consumption",
      "analysis": "The code appears to be responsible for decompressing the compressed data stream, which could potentially lead to excessive power consumption or denial-of-service attacks if the decompression process is not properly restricted or throttled.\n",
      "classification": "slightly promising",
      "cwe": "CWE-920",
      "function_names": [
        "BZ2_decompress"
      ],
      "filenames": [
        "bzip2-sys/bzip2-1.0.8/decompress.c"
      ]
    },
    {
      "headline": "Improper Restriction of Dynamically-Managed Code Resources",
      "analysis": "The code appears to be responsible for processing and decompressing the compressed data stream, which could potentially lead to vulnerabilities related to the improper restriction or handling of dynamically-managed code resources, such as unsafe reflection or deserialization vulnerabilities.\n",
      "classification": "slightly promising",
      "cwe": "CWE-913",
      "function_names": [
        "BZ2_decompress"
      ],
      "filenames": [
        "bzip2-sys/bzip2-1.0.8/decompress.c"
      ]
    }
  ],
  "scores": [
    {
      "stats": {
        "fn": 1,
        "tp": 0,
        "fp": 0
      },
      "mapping": {},
      "vuln_dates": {
        "CVE-2023-22895": "2023-01-10T01:15:10"
      },
      "scoring_model": "claude-3-opus-20240229",
      "type": "llm",
      "instruction_template_hash": "245ace12b6361954d0a2"
    },
    {
      "stats": {
        "fn": 1,
        "tp": 0,
        "fp": 0
      },
      "mapping": {},
      "vuln_dates": {
        "CVE-2023-22895": "2023-01-10T01:15:10"
      },
      "scoring_model": "claude-3-5-sonnet-20240620",
      "type": "llm",
      "instruction_template_hash": "245ace12b6361954d0a2"
    }
  ],
  "instruction_template_hash": "10c0163db4740318a544",
  "version": "0.1.0"
}
