{
  "commit": "00a5bad4afe6ef6d89200a05513ed15aa862bc6c",
  "repo_url": "https://github.com/adobe/git-server",
  "model": "claude-3-sonnet-20240229",
  "chunk_hashes": [
    "3bcd335fbe65e1ca1dcc"
  ],
  "responses": [
    {
      "content": "```yaml\nleads:\n  - headline: Potential path traversal vulnerability in raw file access\n    analysis: |\n      The `rawHandler` middleware in `lib/rawHandler.js` handles requests for raw file content\n      from a Git repository. The file path is constructed from URL parameters without sufficient\n      validation, which could allow an attacker to access arbitrary files on the server's file system\n      outside of the repository directory by using path traversal techniques (e.g. `../../../etc/passwd`).\n    cwe: CWE-22\n    function_names:\n      - createMiddleware\n    filenames:\n      - lib/rawHandler.js\n    classification: very promising\n\n  - headline: Potential command injection vulnerability in Git smart transfer protocol handler\n    analysis: |\n      The `xferHandler` middleware in `lib/xferHandler.js` handles Git smart transfer protocol\n      requests by spawning a child process with the `git` command and user-supplied arguments.\n      If the user input (e.g. repository name) is not properly sanitized, an attacker could potentially\n      inject arbitrary command arguments, leading to command injection and code execution on the server.\n    cwe: CWE-77\n    function_names:\n      - createMiddleware\n    filenames:\n      - lib/xferHandler.js\n    classification: very promising\n\n  - headline: Potential directory traversal vulnerability in HTML handlers\n    analysis: |\n      The `htmlHandler` middleware in `lib/htmlHandler.js` generates HTML views for files and\n      directories within a Git repository. The file path is constructed from URL parameters without\n      sufficient validation, which could potentially allow an attacker to access arbitrary files or\n      directories on the server's file system outside of the repository directory by using path\n      traversal techniques.\n    cwe: CWE-22\n    function_names:\n      - createMiddleware\n    filenames:\n      - lib/htmlHandler.js\n    classification: very promising\n\n  - headline: Potential server-side request forgery (SSRF) vulnerability in GitHub API request handlers\n    analysis: |\n      The various GitHub API request handlers in `lib/commitHandler.js`, `lib/contentHandler.js`,\n      `lib/blobHandler.js`, and `lib/treeHandler.js` generate URLs based on user input (e.g. repository\n      name, file path, commit SHA). If this user input is not properly sanitized, an attacker could\n      potentially cause the server to make arbitrary requests to internal or external systems, leading\n      to a server-side request forgery (SSRF) vulnerability.\n    cwe: CWE-918\n    function_names: []\n    filenames:\n      - lib/commitHandler.js\n      - lib/contentHandler.js\n      - lib/blobHandler.js\n      - lib/treeHandler.js\n    classification: slightly promising\n\n  - headline: Potential unrestricted file upload vulnerability in GitHub archive handler\n    analysis: |\n      The `archiveHandler` middleware in `lib/archiveHandler.js` generates ZIP or TAR archives\n      of Git repositories, including the working directory contents. If an attacker can create\n      or modify files in the working directory (e.g. by pushing malicious code), these files\n      could be included in the generated archive, potentially leading to unrestricted file upload\n      vulnerabilities in systems that process these archives without proper validation.\n    cwe: CWE-434\n    function_names:\n      - createMiddleware\n    filenames:\n      - lib/archiveHandler.js\n    classification: slightly promising\n\n  - headline: Potential use of hardcoded credentials in configuration file\n    analysis: |\n      The configuration file `config.js` may contain hardcoded credentials or other sensitive\n      information, such as private keys or database passwords. If these credentials are checked\n      into version control or otherwise exposed, they could be exploited by attackers to gain\n      unauthorized access to the system or other related systems.\n    cwe: CWE-798\n    function_names: []\n    filenames:\n      - config.js\n    classification: slightly promising\n\n  - headline: Lack of proper error handling and input validation\n    analysis: |\n      Several handlers throughout the codebase (e.g. `rawHandler`, `blobHandler`, `treeHandler`,\n      `commitHandler`, `contentHandler`) appear to lack proper error handling and input validation.\n      Errors and exceptions are often logged but not properly handled, and user input is\n      not consistently validated, which could potentially lead to various vulnerabilities such as\n      denial of service, information exposure, or code execution.\n    cwe: CWE-20\n    function_names: []\n    filenames:\n      - lib/rawHandler.js\n      - lib/blobHandler.js\n      - lib/treeHandler.js\n      - lib/commitHandler.js\n      - lib/contentHandler.js\n    classification: slightly promising\n\n  - headline: Potential improper authentication vulnerability\n    analysis: |\n      The codebase does not appear to implement any authentication mechanism for accessing Git\n      repositories or GitHub API endpoints. While this may be intentional for a publicly accessible\n      Git server, it could potentially lead to unauthorized access or modification of sensitive\n      data if the server is not properly secured or isolated from other systems.\n    cwe: CWE-306\n    function_names: []\n    filenames: []\n    classification: slightly promising\n\n  - headline: Potential insecure use of cryptographic algorithm in Git commit log handling\n    analysis: |\n      The `email2avatarUrl` function in `lib/commitHandler.js` generates Gravatar URLs based on\n      email addresses using the MD5 hash algorithm. MD5 is a cryptographically broken hash function\n      and should not be used for security-related purposes due to its vulnerabilities to collision\n      attacks and preimage attacks.\n    cwe: CWE-327\n    function_names:\n      - email2avatarUrl\n    filenames:\n      - lib/commitHandler.js\n    classification: slightly promising\n```\n\nThe codebase appears to be a Git server implementation that supports various Git operations and GitHub API endpoints. While the codebase is relatively small, it handles user input in several places, which could potentially lead to various vulnerabilities if the input is not properly validated or sanitized.\n\nThe most promising leads are related to path traversal vulnerabilities in the raw file access handler (`rawHandler`) and the HTML handlers (`htmlHandler`), as well as a potential command injection vulnerability in the Git smart transfer protocol handler (`xferHandler`). These vulnerabilities could allow an attacker to access arbitrary files or execute arbitrary commands on the server, respectively.\n\nOther potential vulnerabilities include server-side request forgery (SSRF) in the GitHub API request handlers, unrestricted file upload in the GitHub archive handler (`archiveHandler`), use of hardcoded credentials in the configuration file, lack of proper error handling and input validation throughout the codebase, and potential improper authentication issues.\n\nIt's worth noting that some of these vulnerabilities, such as the use of hardcoded credentials or lack of authentication, may be intentional design choices for a publicly accessible Git server. However, they should still be carefully reviewed and addressed if the server is intended to be used in a more secure environment or to handle sensitive data.\n\nAdditionally, the use of the insecure MD5 hash algorithm in the `commitHandler` for generating Gravatar URLs is a minor issue, but it highlights the importance of using secure cryptographic primitives in any security-related operations.\n\nOverall, while the codebase appears to be relatively simple, it contains several potential security vulnerabilities that should be addressed to ensure the security and integrity of the Git server and the data it handles.",
      "date": "2024-06-12T14:41:49.502890",
      "usage": {
        "prompt_tokens": 35155,
        "completion_tokens": 1758,
        "cost": 0.131835
      }
    }
  ],
  "leads": [
    {
      "headline": "Potential path traversal vulnerability in raw file access",
      "analysis": "The rawHandler middleware in lib/rawHandler.js handles requests for raw file content\nfrom a Git repository. The file path is constructed from URL parameters without sufficient\nvalidation, which could allow an attacker to access arbitrary files on the server's file system\noutside of the repository directory by using path traversal techniques (e.g. ../../../etc/passwd).\n",
      "classification": "very promising",
      "cwe": "CWE-22",
      "function_names": [
        "createMiddleware"
      ],
      "filenames": [
        "lib/rawHandler.js"
      ]
    },
    {
      "headline": "Potential command injection vulnerability in Git smart transfer protocol handler",
      "analysis": "The xferHandler middleware in lib/xferHandler.js handles Git smart transfer protocol\nrequests by spawning a child process with the git command and user-supplied arguments.\nIf the user input (e.g. repository name) is not properly sanitized, an attacker could potentially\ninject arbitrary command arguments, leading to command injection and code execution on the server.\n",
      "classification": "very promising",
      "cwe": "CWE-77",
      "function_names": [
        "createMiddleware"
      ],
      "filenames": [
        "lib/xferHandler.js"
      ]
    },
    {
      "headline": "Potential directory traversal vulnerability in HTML handlers",
      "analysis": "The htmlHandler middleware in lib/htmlHandler.js generates HTML views for files and\ndirectories within a Git repository. The file path is constructed from URL parameters without\nsufficient validation, which could potentially allow an attacker to access arbitrary files or\ndirectories on the server's file system outside of the repository directory by using path\ntraversal techniques.\n",
      "classification": "very promising",
      "cwe": "CWE-22",
      "function_names": [
        "createMiddleware"
      ],
      "filenames": [
        "lib/htmlHandler.js"
      ]
    },
    {
      "headline": "Potential server-side request forgery (SSRF) vulnerability in GitHub API request handlers",
      "analysis": "The various GitHub API request handlers in lib/commitHandler.js, lib/contentHandler.js,\nlib/blobHandler.js, and lib/treeHandler.js generate URLs based on user input (e.g. repository\nname, file path, commit SHA). If this user input is not properly sanitized, an attacker could\npotentially cause the server to make arbitrary requests to internal or external systems, leading\nto a server-side request forgery (SSRF) vulnerability.\n",
      "classification": "slightly promising",
      "cwe": "CWE-918",
      "function_names": [],
      "filenames": [
        "lib/commitHandler.js",
        "lib/contentHandler.js",
        "lib/blobHandler.js"
      ]
    },
    {
      "headline": "Potential unrestricted file upload vulnerability in GitHub archive handler",
      "analysis": "The archiveHandler middleware in lib/archiveHandler.js generates ZIP or TAR archives\nof Git repositories, including the working directory contents. If an attacker can create\nor modify files in the working directory (e.g. by pushing malicious code), these files\ncould be included in the generated archive, potentially leading to unrestricted file upload\nvulnerabilities in systems that process these archives without proper validation.\n",
      "classification": "slightly promising",
      "cwe": "CWE-434",
      "function_names": [
        "createMiddleware"
      ],
      "filenames": [
        "lib/archiveHandler.js"
      ]
    },
    {
      "headline": "Potential use of hardcoded credentials in configuration file",
      "analysis": "The configuration file config.js may contain hardcoded credentials or other sensitive\ninformation, such as private keys or database passwords. If these credentials are checked\ninto version control or otherwise exposed, they could be exploited by attackers to gain\nunauthorized access to the system or other related systems.\n",
      "classification": "slightly promising",
      "cwe": "CWE-798",
      "function_names": [],
      "filenames": [
        "config.js"
      ]
    },
    {
      "headline": "Lack of proper error handling and input validation",
      "analysis": "Several handlers throughout the codebase (e.g. rawHandler, blobHandler, treeHandler,\ncommitHandler, contentHandler) appear to lack proper error handling and input validation.\nErrors and exceptions are often logged but not properly handled, and user input is\nnot consistently validated, which could potentially lead to various vulnerabilities such as\ndenial of service, information exposure, or code execution.\n",
      "classification": "slightly promising",
      "cwe": "CWE-20",
      "function_names": [],
      "filenames": [
        "lib/rawHandler.js",
        "lib/blobHandler.js",
        "lib/treeHandler.js"
      ]
    },
    {
      "headline": "Potential improper authentication vulnerability",
      "analysis": "The codebase does not appear to implement any authentication mechanism for accessing Git\nrepositories or GitHub API endpoints. While this may be intentional for a publicly accessible\nGit server, it could potentially lead to unauthorized access or modification of sensitive\ndata if the server is not properly secured or isolated from other systems.\n",
      "classification": "slightly promising",
      "cwe": "CWE-306",
      "function_names": [],
      "filenames": []
    },
    {
      "headline": "Potential insecure use of cryptographic algorithm in Git commit log handling",
      "analysis": "The email2avatarUrl function in lib/commitHandler.js generates Gravatar URLs based on\nemail addresses using the MD5 hash algorithm. MD5 is a cryptographically broken hash function\nand should not be used for security-related purposes due to its vulnerabilities to collision\nattacks and preimage attacks.\n",
      "classification": "slightly promising",
      "cwe": "CWE-327",
      "function_names": [
        "email2avatarUrl"
      ],
      "filenames": [
        "lib/commitHandler.js"
      ]
    }
  ],
  "scores": [
    {
      "stats": {
        "fn": 0,
        "tp": 1,
        "fp": 1
      },
      "mapping": {
        "0": "CVE-2020-9708",
        "2": "CVE-2020-9708"
      },
      "vuln_dates": {
        "CVE-2020-9708": "2020-08-14T17:15:14"
      },
      "scoring_model": "claude-3-opus-20240229",
      "type": "llm",
      "instruction_template_hash": "245ace12b6361954d0a2"
    }
  ],
  "instruction_template_hash": "10c0163db4740318a544",
  "version": "0.1.0"
}
