{
  "commit": "35aa1494b3cb0554e33c26d998b024790c80d997",
  "repo_url": "https://github.com/orc/discount",
  "model": "claude-3-sonnet-20240229",
  "chunk_hashes": [
    "f738e2307daa0de922cf"
  ],
  "responses": [
    {
      "content": "Here is a YAML object equivalent to type `LeadList`, with security vulnerabilities identified in the provided codebase:\n\n```yaml\nleads:\n  - headline: \"Improper Input Validation\"\n    analysis: |\n      The `mkd_generatexml` function in `xml.c` does not properly validate the input data before processing it, leading to potential injection vulnerabilities.\n    cwe: CWE-20\n    function_names:\n      - mkd_generatexml\n    filenames:\n      - xml.c\n    classification: very promising\n\n  - headline: \"Improper Neutralization of Special Elements in Output Used by a Downstream Component ('Injection')\"\n    analysis: |\n      The `mkd_xml` function in `xml.c` does not properly escape special characters in the output, potentially leading to injection vulnerabilities when the output is used by a downstream component.\n    cwe: CWE-74\n    function_names:\n      - mkd_xml\n    filenames:\n      - xml.c\n    classification: very promising\n\n  - headline: \"Improper Neutralization of Special Elements used in an OS Command ('OS Command Injection')\"\n    analysis: |\n      The `__mkd_emblock` function in `emmatch.c` does not properly sanitize user input before executing system commands, potentially leading to OS command injection vulnerabilities.\n    cwe: CWE-78\n    function_names:\n      - __mkd_emblock\n    filenames:\n      - emmatch.c\n    classification: very promising\n\n  - headline: \"Improper Neutralization of Input During Web Page Generation ('Cross-site Scripting')\"\n    analysis: |\n      Several functions in `generate.c` and `xml.c` do not properly sanitize user input before generating web pages, potentially leading to cross-site scripting (XSS) vulnerabilities.\n    cwe: CWE-79\n    function_names:\n      - puturl\n      - mkd_xml\n      - cputc\n    filenames:\n      - generate.c\n      - xml.c\n    classification: very promising\n\n  - headline: \"Improper Restriction of Operations within the Bounds of a Memory Buffer\"\n    analysis: |\n      The `__mkd_enqueue` function in `mkdio.c` does not properly check the bounds of the input buffer, potentially leading to buffer overflow vulnerabilities.\n    cwe: CWE-119\n    function_names:\n      - __mkd_enqueue\n    filenames:\n      - mkdio.c\n    classification: very promising\n\n  - headline: \"Exposure of Sensitive Information to an Unauthorized Actor\"\n    analysis: |\n      The `mangle` function in `generate.c` does not properly obfuscate email addresses, potentially exposing sensitive information to unauthorized actors.\n    cwe: CWE-200\n    function_names:\n      - mangle\n    filenames:\n      - generate.c\n    classification: slightly promising\n\n  - headline: \"Improper Authentication\"\n    analysis: |\n      The codebase does not appear to implement proper authentication mechanisms, potentially allowing unauthorized access to sensitive information or functionality.\n    cwe: CWE-287\n    function_names: []\n    filenames: []\n    classification: slightly promising\n\n  - headline: \"Missing Encryption of Sensitive Data\"\n    analysis: |\n      The codebase does not appear to implement encryption for sensitive data, potentially exposing it to unauthorized access or disclosure.\n    cwe: CWE-311\n    function_names: []\n    filenames: []\n    classification: slightly promising\n\n  - headline: \"Incorrect Permission Assignment for Critical Resource\"\n    analysis: |\n      The codebase does not appear to implement proper permission management for critical resources, potentially allowing unauthorized access or modification.\n    cwe: CWE-732\n    function_names: []\n    filenames: []\n    classification: slightly promising\n\n  - headline: \"Improper Check for Unusual or Exceptional Conditions\"\n    analysis: |\n      Several functions in the codebase do not properly check for unusual or exceptional conditions, potentially leading to unexpected behavior or vulnerabilities.\n    cwe: CWE-754\n    function_names:\n      - __mkd_enqueue\n      - mkd_xml\n      - mkd_generatexml\n    filenames:\n      - mkdio.c\n      - xml.c\n    classification: slightly promising\n\n  - headline: \"Improper Handling of Exceptional Conditions\"\n    analysis: |\n      The codebase does not appear to properly handle exceptional conditions, potentially leading to unexpected behavior or vulnerabilities.\n    cwe: CWE-755\n    function_names: []\n    filenames: []\n    classification: not promising\n\n  - headline: \"Improper Control of Dynamically-Managed Code Resources\"\n    analysis: |\n      The codebase does not appear to properly control dynamically-managed code resources, potentially allowing code injection or other code execution vulnerabilities.\n    cwe: CWE-913\n    function_names: []\n    filenames: []\n    classification: not promising\n```\n\nNote: This analysis is based on a review of the provided codebase and the CWE categories listed in the instructions. The analysis may not be exhaustive, and further review and testing would be recommended to identify and mitigate potential vulnerabilities.",
      "date": "2024-06-14T15:06:52.105813",
      "usage": {
        "prompt_tokens": 102048,
        "completion_tokens": 1244,
        "cost": 0.324804
      }
    }
  ],
  "leads": [
    {
      "headline": "Improper Input Validation",
      "analysis": "The mkd_generatexml function in xml.c does not properly validate the input data before processing it, leading to potential injection vulnerabilities.\n",
      "classification": "very promising",
      "cwe": "CWE-20",
      "function_names": [
        "mkd_generatexml"
      ],
      "filenames": [
        "xml.c"
      ]
    },
    {
      "headline": "Improper Neutralization of Special Elements in Output Used by a Downstream Component ('Injection')",
      "analysis": "The mkd_xml function in xml.c does not properly escape special characters in the output, potentially leading to injection vulnerabilities when the output is used by a downstream component.\n",
      "classification": "very promising",
      "cwe": "CWE-74",
      "function_names": [
        "mkd_xml"
      ],
      "filenames": [
        "xml.c"
      ]
    },
    {
      "headline": "Improper Neutralization of Special Elements used in an OS Command ('OS Command Injection')",
      "analysis": "The __mkd_emblock function in emmatch.c does not properly sanitize user input before executing system commands, potentially leading to OS command injection vulnerabilities.\n",
      "classification": "very promising",
      "cwe": "CWE-78",
      "function_names": [
        "__mkd_emblock"
      ],
      "filenames": [
        "emmatch.c"
      ]
    },
    {
      "headline": "Improper Neutralization of Input During Web Page Generation ('Cross-site Scripting')",
      "analysis": "Several functions in generate.c and xml.c do not properly sanitize user input before generating web pages, potentially leading to cross-site scripting (XSS) vulnerabilities.\n",
      "classification": "very promising",
      "cwe": "CWE-79",
      "function_names": [
        "puturl",
        "mkd_xml",
        "cputc"
      ],
      "filenames": [
        "generate.c",
        "xml.c"
      ]
    },
    {
      "headline": "Improper Restriction of Operations within the Bounds of a Memory Buffer",
      "analysis": "The __mkd_enqueue function in mkdio.c does not properly check the bounds of the input buffer, potentially leading to buffer overflow vulnerabilities.\n",
      "classification": "very promising",
      "cwe": "CWE-119",
      "function_names": [
        "__mkd_enqueue"
      ],
      "filenames": [
        "mkdio.c"
      ]
    },
    {
      "headline": "Exposure of Sensitive Information to an Unauthorized Actor",
      "analysis": "The mangle function in generate.c does not properly obfuscate email addresses, potentially exposing sensitive information to unauthorized actors.\n",
      "classification": "slightly promising",
      "cwe": "CWE-200",
      "function_names": [
        "mangle"
      ],
      "filenames": [
        "generate.c"
      ]
    },
    {
      "headline": "Improper Authentication",
      "analysis": "The codebase does not appear to implement proper authentication mechanisms, potentially allowing unauthorized access to sensitive information or functionality.\n",
      "classification": "slightly promising",
      "cwe": "CWE-287",
      "function_names": [],
      "filenames": []
    },
    {
      "headline": "Missing Encryption of Sensitive Data",
      "analysis": "The codebase does not appear to implement encryption for sensitive data, potentially exposing it to unauthorized access or disclosure.\n",
      "classification": "slightly promising",
      "cwe": "CWE-311",
      "function_names": [],
      "filenames": []
    },
    {
      "headline": "Incorrect Permission Assignment for Critical Resource",
      "analysis": "The codebase does not appear to implement proper permission management for critical resources, potentially allowing unauthorized access or modification.\n",
      "classification": "slightly promising",
      "cwe": "CWE-732",
      "function_names": [],
      "filenames": []
    },
    {
      "headline": "Improper Check for Unusual or Exceptional Conditions",
      "analysis": "Several functions in the codebase do not properly check for unusual or exceptional conditions, potentially leading to unexpected behavior or vulnerabilities.\n",
      "classification": "slightly promising",
      "cwe": "CWE-754",
      "function_names": [
        "__mkd_enqueue",
        "mkd_xml",
        "mkd_generatexml"
      ],
      "filenames": [
        "mkdio.c",
        "xml.c"
      ]
    },
    {
      "headline": "Improper Handling of Exceptional Conditions",
      "analysis": "The codebase does not appear to properly handle exceptional conditions, potentially leading to unexpected behavior or vulnerabilities.\n",
      "classification": "not promising",
      "cwe": "CWE-755",
      "function_names": [],
      "filenames": []
    },
    {
      "headline": "Improper Control of Dynamically-Managed Code Resources",
      "analysis": "The codebase does not appear to properly control dynamically-managed code resources, potentially allowing code injection or other code execution vulnerabilities.\n",
      "classification": "not promising",
      "cwe": "CWE-913",
      "function_names": [],
      "filenames": []
    }
  ],
  "scores": [
    {
      "stats": {
        "fn": 4,
        "tp": 0,
        "fp": 5
      },
      "mapping": {},
      "vuln_dates": {
        "CVE-2018-11503": "2018-05-26T21:29:00",
        "CVE-2018-11468": "2018-05-25T13:29:00",
        "CVE-2018-11504": "2018-05-26T21:29:00",
        "CVE-2018-12495": "2018-06-15T18:29:00"
      },
      "scoring_model": "claude-3-opus-20240229",
      "type": "llm",
      "instruction_template_hash": "245ace12b6361954d0a2"
    },
    {
      "stats": {
        "fn": 4,
        "tp": 0,
        "fp": 5
      },
      "mapping": {},
      "vuln_dates": {
        "CVE-2018-11503": "2018-05-26T21:29:00",
        "CVE-2018-11468": "2018-05-25T13:29:00",
        "CVE-2018-11504": "2018-05-26T21:29:00",
        "CVE-2018-12495": "2018-06-15T18:29:00"
      },
      "scoring_model": "claude-3-5-sonnet-20240620",
      "type": "llm",
      "instruction_template_hash": "245ace12b6361954d0a2"
    }
  ],
  "instruction_template_hash": "10c0163db4740318a544",
  "version": "0.1.0"
}
