{
  "commit": "415cca36afbf1e6f977716f2cd564cfb4a5b8de8",
  "repo_url": "https://github.com/jenkinsci/cobertura-plugin",
  "model": "gpt-4o-2024-05-13",
  "chunk_hashes": [
    "cf75c27fd65b98fa0702"
  ],
  "responses": [
    {
      "content": "```yaml\nleads:\n  - headline: \"Potential Null Pointer Dereference in CoberturaBuildAction\"\n    analysis: |\n      The method `build.getAction(CoberturaBuildAction.class)` is called within `CoberturaCoverageRecordAction` without checking if it returns null, potentially leading to a `NullPointerException`. This can be exploited if an attacker can manipulate input to cause this method to return null.\n    cwe: CWE-476\n    function_names:\n      - \"CoberturaBuildAction.onLoad\"\n      - \"CoberturaBuildAction.onAttached\"\n    filenames:\n      - \"src/main/java/hudson/plugins/cobertura/CoberturaCoverageRecordAction.java\"\n    classification: slightly promising\n\n  - headline: \"Possible Reflected XSS in Jenkins Plugin Handling\"\n    analysis: |\n      Within various methods in the Cobertura plugin, e.g., `doGraph` and `getDynamic`, there isn't sufficient output escaping. This opens up the code to potential Cross-Site Scripting (XSS) attacks if malicious input is sent to these endpoints.\n    cwe: CWE-79\n    function_names:\n      - \"CoverageResult.doGraph\"\n      - \"CoverageResult.getDynamic\"\n    filenames:\n      - \"src/main/java/hudson/plugins/cobertura/targets/CoverageResult.java\"\n    classification: very promising\n\n  - headline: \"Directory Traversal in Cobertura Coverage Parsing\"\n    analysis: |\n      The report file handling logic in `ParseReportCallable` does not adequately sanitize input paths, making it susceptible to directory traversal attacks. This may allow attackers to read arbitrary files on the server.\n    cwe: CWE-22\n    function_names:\n      - \"CoberturaPublisher$ParseReportCallable.invoke\"\n    filenames:\n      - \"src/main/java/hudson/plugins/cobertura/CoberturaPublisher.java\"\n    classification: very promising\n\n  - headline: \"Improper Validation of Input to External Tools\"\n    analysis: |\n      In several instances, paths and other inputs are passed to external tools without proper validation or escaping, which could lead to command injection vulnerabilities.\n    cwe: CWE-78\n    function_names:\n      - \"SourceCodePainter.paintSourceCode\"\n      - \"CoberturaPublisher.perform\"\n    filenames:\n      - \"src/main/java/hudson/plugins/cobertura/renderers/SourceCodePainter.java\"\n      - \"src/main/java/hudson/plugins/cobertura/CoberturaPublisher.java\"\n    classification: very promising\n\n  - headline: \"Resource Exhaustion and Denial of Service via Heavy Parsing\"\n    analysis: |\n      The `CoberturaCoverageParser.parse` method can lead to heavy memory and CPU usage if an attacker provides a specially crafted XML file, which may result in Denial of Service (DoS). This is further exacerbated by the lack of input size restrictions.\n    cwe: CWE-400\n    function_names:\n      - \"CoberturaCoverageParser.parse\"\n    filenames:\n      - \"src/main/java/hudson/plugins/cobertura/CoberturaCoverageParser.java\"\n    classification: slightly promising\n```",
      "date": "2024-06-14T14:09:05.400071",
      "usage": {
        "prompt_tokens": 53981,
        "completion_tokens": 636,
        "cost": 0.279445
      }
    }
  ],
  "leads": [
    {
      "headline": "Potential Null Pointer Dereference in CoberturaBuildAction",
      "analysis": "The method build.getAction(CoberturaBuildAction.class) is called within CoberturaCoverageRecordAction without checking if it returns null, potentially leading to a NullPointerException. This can be exploited if an attacker can manipulate input to cause this method to return null.\n",
      "classification": "slightly promising",
      "cwe": "CWE-476",
      "function_names": [
        "CoberturaBuildAction.onLoad",
        "CoberturaBuildAction.onAttached"
      ],
      "filenames": [
        "src/main/java/hudson/plugins/cobertura/CoberturaCoverageRecordAction.java"
      ]
    },
    {
      "headline": "Possible Reflected XSS in Jenkins Plugin Handling",
      "analysis": "Within various methods in the Cobertura plugin, e.g., doGraph and getDynamic, there isn't sufficient output escaping. This opens up the code to potential Cross-Site Scripting (XSS) attacks if malicious input is sent to these endpoints.\n",
      "classification": "very promising",
      "cwe": "CWE-79",
      "function_names": [
        "CoverageResult.doGraph",
        "CoverageResult.getDynamic"
      ],
      "filenames": [
        "src/main/java/hudson/plugins/cobertura/targets/CoverageResult.java"
      ]
    },
    {
      "headline": "Directory Traversal in Cobertura Coverage Parsing",
      "analysis": "The report file handling logic in ParseReportCallable does not adequately sanitize input paths, making it susceptible to directory traversal attacks. This may allow attackers to read arbitrary files on the server.\n",
      "classification": "very promising",
      "cwe": "CWE-22",
      "function_names": [
        "CoberturaPublisher$ParseReportCallable.invoke"
      ],
      "filenames": [
        "src/main/java/hudson/plugins/cobertura/CoberturaPublisher.java"
      ]
    },
    {
      "headline": "Improper Validation of Input to External Tools",
      "analysis": "In several instances, paths and other inputs are passed to external tools without proper validation or escaping, which could lead to command injection vulnerabilities.\n",
      "classification": "very promising",
      "cwe": "CWE-78",
      "function_names": [
        "SourceCodePainter.paintSourceCode",
        "CoberturaPublisher.perform"
      ],
      "filenames": [
        "src/main/java/hudson/plugins/cobertura/renderers/SourceCodePainter.java",
        "src/main/java/hudson/plugins/cobertura/CoberturaPublisher.java"
      ]
    },
    {
      "headline": "Resource Exhaustion and Denial of Service via Heavy Parsing",
      "analysis": "The CoberturaCoverageParser.parse method can lead to heavy memory and CPU usage if an attacker provides a specially crafted XML file, which may result in Denial of Service (DoS). This is further exacerbated by the lack of input size restrictions.\n",
      "classification": "slightly promising",
      "cwe": "CWE-400",
      "function_names": [
        "CoberturaCoverageParser.parse"
      ],
      "filenames": [
        "src/main/java/hudson/plugins/cobertura/CoberturaCoverageParser.java"
      ]
    }
  ],
  "scores": [
    {
      "stats": {
        "fn": 2,
        "tp": 0,
        "fp": 3
      },
      "mapping": {},
      "vuln_dates": {
        "CVE-2020-2139": "2020-03-09T16:15:13",
        "CVE-2020-2138": "2020-03-09T16:15:12"
      },
      "scoring_model": "claude-3-opus-20240229",
      "type": "llm",
      "instruction_template_hash": "245ace12b6361954d0a2"
    },
    {
      "stats": {
        "fn": 1,
        "tp": 1,
        "fp": 2
      },
      "mapping": {
        "1": "CVE-2020-2139"
      },
      "vuln_dates": {
        "CVE-2020-2139": "2020-03-09T16:15:13",
        "CVE-2020-2138": "2020-03-09T16:15:12"
      },
      "scoring_model": "claude-3-5-sonnet-20240620",
      "type": "llm",
      "instruction_template_hash": "245ace12b6361954d0a2"
    }
  ],
  "instruction_template_hash": "10c0163db4740318a544",
  "version": "0.1.0"
}
