{
  "commit": "3095cff7d99e99e42183cc3f65d1f2938fbf08f5",
  "repo_url": "https://github.com/jc21/nginx-proxy-manager",
  "model": "claude-3-sonnet-20240229",
  "chunk_hashes": [
    "3b319fa950e488bd408d"
  ],
  "responses": [
    {
      "content": "```yaml\nleads:\n  - headline: Improper Neutralization of Special Elements used in an OS Command ('OS Command Injection')\n    analysis: |\n      The codebase contains a potential OS command injection vulnerability in the `internalAccessList.build` method of the `src/backend/internal/access-list.js` file. This function uses the `exec` method to execute the `htpasswd` command, which is a utility for creating and updating password files. However, the `username` and `password` arguments passed to the `htpasswd` command are not properly sanitized, allowing arbitrary command injection when malicious input is provided.\n    cwe: CWE-78\n    function_names:\n      - internalAccessList.build\n    filenames:\n      - src/backend/internal/access-list.js\n    classification: very promising\n\n  - headline: Improper Neutralization of Input During Web Page Generation ('Cross-site Scripting')\n    analysis: |\n      The codebase contains a potential cross-site scripting (XSS) vulnerability in the `index.html` file located in the `rootfs/var/www/html` directory. The HTML code in this file includes user-supplied data without proper sanitization or encoding, which could allow an attacker to inject malicious scripts that will be executed in the user's browser when the page is rendered.\n    cwe: CWE-79\n    function_names: []\n    filenames:\n      - rootfs/var/www/html/index.html\n    classification: very promising\n\n  - headline: Use of Insufficiently Random Values\n    analysis: |\n      The codebase uses the `crypto.randomBytes` function from the Node.js `crypto` module to generate a random value for the JSON Web Token (JWT) `jti` (JWT ID) claim in the `src/backend/models/token.js` file. However, the use of `crypto.randomBytes` without proper entropy sources can potentially lead to the generation of predictable values, which could compromise the security of the JWT tokens.\n    cwe: CWE-330\n    function_names:\n      - Token.create\n    filenames:\n      - src/backend/models/token.js\n    classification: slightly promising\n\n  - headline: Use of Hard-coded Credentials\n    analysis: |\n      The codebase contains hard-coded credentials in the `src/backend/setup.js` file. During the initial setup, an admin user with the email `admin@example.com` and password `changeme` is created. These hard-coded credentials can pose a security risk if they are not changed after the initial setup or if the application is deployed in a production environment without modifying these values.\n    cwe: CWE-798\n    function_names: []\n    filenames:\n      - src/backend/setup.js\n    classification: very promising\n\n  - headline: Improper Restriction of Operations within the Bounds of a Memory Buffer\n    analysis: |\n      The codebase uses the `fs.writeFile` and `fs.readFile` functions from the Node.js `fs` module to read and write files in various parts of the application, such as in the `internalAccessList.build` method of the `src/backend/internal/access-list.js` file and the `internalCertificate.writeCustomCert` method of the `src/backend/internal/certificate.js` file. These functions can potentially lead to buffer overflow vulnerabilities if the input data exceeds the available buffer size or if the file paths are not properly validated.\n    cwe: CWE-119\n    function_names:\n      - internalAccessList.build\n      - internalCertificate.writeCustomCert\n    filenames:\n      - src/backend/internal/access-list.js\n      - src/backend/internal/certificate.js\n    classification: slightly promising\n\n  - headline: Inclusion of Functionality from Untrusted Control Sphere\n    analysis: |\n      The codebase includes functionality from untrusted sources in the `src/backend/importer.js` file. This file imports data from a previous version of the application (`/config` directory) during the initial setup. If the imported data contains malicious content, it could potentially lead to security vulnerabilities or unintended behavior in the application.\n    cwe: CWE-829\n    function_names:\n      - importAccessLists\n      - importHosts\n    filenames:\n      - src/backend/importer.js\n    classification: slightly promising\n\n  - headline: Improper Restriction of XML External Entity Reference\n    analysis: |\n      The codebase does not appear to have any functionality related to parsing or processing XML documents. Therefore, the risk of an XML External Entity (XXE) vulnerability is unlikely to be present in this codebase.\n    cwe: CWE-611\n    function_names: []\n    filenames: []\n    classification: not promising\n```\n\nThe analysis covers several potential security vulnerabilities in the codebase, including OS command injection, cross-site scripting (XSS), use of insufficiently random values, hard-coded credentials, buffer overflows, and inclusion of functionality from untrusted sources. The most promising leads are related to OS command injection, XSS, and hard-coded credentials, which can have severe security implications if exploited.\n\nIt's important to note that some vulnerabilities, like buffer overflows and use of insufficiently random values, were classified as \"slightly promising\" due to the lack of specific details or context in the provided codebase. Further investigation and code review may be required to assess the actual risk and impact of these potential vulnerabilities.\n\nAdditionally, the analysis found no evidence of an XML External Entity (XXE) vulnerability, as the codebase does not appear to handle XML processing.\n\nOverall, the most critical vulnerabilities identified in the codebase should be addressed promptly to mitigate the potential security risks.",
      "date": "2024-06-12T17:28:09.361428",
      "usage": {
        "prompt_tokens": 133920,
        "completion_tokens": 1349,
        "cost": 0.421995
      }
    }
  ],
  "leads": [
    {
      "headline": "Improper Neutralization of Special Elements used in an OS Command ('OS Command Injection')",
      "analysis": "The codebase contains a potential OS command injection vulnerability in the internalAccessList.build method of the src/backend/internal/access-list.js file. This function uses the exec method to execute the htpasswd command, which is a utility for creating and updating password files. However, the username and password arguments passed to the htpasswd command are not properly sanitized, allowing arbitrary command injection when malicious input is provided.\n",
      "classification": "very promising",
      "cwe": "CWE-78",
      "function_names": [
        "internalAccessList.build"
      ],
      "filenames": [
        "src/backend/internal/access-list.js"
      ]
    },
    {
      "headline": "Improper Neutralization of Input During Web Page Generation ('Cross-site Scripting')",
      "analysis": "The codebase contains a potential cross-site scripting (XSS) vulnerability in the index.html file located in the rootfs/var/www/html directory. The HTML code in this file includes user-supplied data without proper sanitization or encoding, which could allow an attacker to inject malicious scripts that will be executed in the user's browser when the page is rendered.\n",
      "classification": "very promising",
      "cwe": "CWE-79",
      "function_names": [],
      "filenames": [
        "rootfs/var/www/html/index.html"
      ]
    },
    {
      "headline": "Use of Insufficiently Random Values",
      "analysis": "The codebase uses the crypto.randomBytes function from the Node.js crypto module to generate a random value for the JSON Web Token (JWT) jti (JWT ID) claim in the src/backend/models/token.js file. However, the use of crypto.randomBytes without proper entropy sources can potentially lead to the generation of predictable values, which could compromise the security of the JWT tokens.\n",
      "classification": "slightly promising",
      "cwe": "CWE-330",
      "function_names": [
        "Token.create"
      ],
      "filenames": [
        "src/backend/models/token.js"
      ]
    },
    {
      "headline": "Use of Hard-coded Credentials",
      "analysis": "The codebase contains hard-coded credentials in the src/backend/setup.js file. During the initial setup, an admin user with the email admin@example.com and password changeme is created. These hard-coded credentials can pose a security risk if they are not changed after the initial setup or if the application is deployed in a production environment without modifying these values.\n",
      "classification": "very promising",
      "cwe": "CWE-798",
      "function_names": [],
      "filenames": [
        "src/backend/setup.js"
      ]
    },
    {
      "headline": "Improper Restriction of Operations within the Bounds of a Memory Buffer",
      "analysis": "The codebase uses the fs.writeFile and fs.readFile functions from the Node.js fs module to read and write files in various parts of the application, such as in the internalAccessList.build method of the src/backend/internal/access-list.js file and the internalCertificate.writeCustomCert method of the src/backend/internal/certificate.js file. These functions can potentially lead to buffer overflow vulnerabilities if the input data exceeds the available buffer size or if the file paths are not properly validated.\n",
      "classification": "slightly promising",
      "cwe": "CWE-119",
      "function_names": [
        "internalAccessList.build",
        "internalCertificate.writeCustomCert"
      ],
      "filenames": [
        "src/backend/internal/access-list.js",
        "src/backend/internal/certificate.js"
      ]
    },
    {
      "headline": "Inclusion of Functionality from Untrusted Control Sphere",
      "analysis": "The codebase includes functionality from untrusted sources in the src/backend/importer.js file. This file imports data from a previous version of the application (/config directory) during the initial setup. If the imported data contains malicious content, it could potentially lead to security vulnerabilities or unintended behavior in the application.\n",
      "classification": "slightly promising",
      "cwe": "CWE-829",
      "function_names": [
        "importAccessLists",
        "importHosts"
      ],
      "filenames": [
        "src/backend/importer.js"
      ]
    },
    {
      "headline": "Improper Restriction of XML External Entity Reference",
      "analysis": "The codebase does not appear to have any functionality related to parsing or processing XML documents. Therefore, the risk of an XML External Entity (XXE) vulnerability is unlikely to be present in this codebase.\n",
      "classification": "not promising",
      "cwe": "CWE-611",
      "function_names": [],
      "filenames": []
    }
  ],
  "scores": [
    {
      "stats": {
        "fn": 1,
        "tp": 0,
        "fp": 3
      },
      "mapping": {},
      "vuln_dates": {
        "CVE-2019-15517": "2019-08-23T15:15:10"
      },
      "scoring_model": "claude-3-opus-20240229",
      "type": "llm",
      "instruction_template_hash": "245ace12b6361954d0a2"
    }
  ],
  "instruction_template_hash": "10c0163db4740318a544",
  "version": "0.1.0"
}
