{
  "commit": "3722c6c61e0808dcefeb1d633172dee833533901",
  "repo_url": "https://gitlab.com/libidn/libidn2",
  "model": "claude-3-haiku-20240307",
  "chunk_hashes": [
    "db4af47a3909eba4e53a"
  ],
  "responses": [
    {
      "content": "Based on the codebase provided, here is a YAML object equivalent to the LeadList type defined in the Pydantic definitions:\n\n```yaml\nleads:\n  - headline: IDNA2008 lookup string conversion on domain name with invalid character\n    analysis: |\n      The \"check-combining-property.pl\" script contains a vulnerability where it does not properly handle code points with a combining class of 0 and a non-Mc/Mn category. This can lead to the script terminating unexpectedly when processing such input.\n    cwe: CWE-20\n    function_names:\n      - die\n    filenames:\n      - check-combining-property.pl\n    classification: very promising\n\n  - headline: Potential buffer overflow in Punycode decoder\n    analysis: |\n      The Punycode decoder in the \"punycode.c\" file does not properly validate the input length, which could lead to a buffer overflow vulnerability if an attacker provides crafted input.\n    cwe: CWE-120\n    function_names:\n      - punycode_decode\n    filenames:\n      - punycode.c\n    classification: very promising\n\n  - headline: Potential Uninitialized Memory Use in IDNA2008 processing\n    analysis: |\n      The \"lookup.c\" file contains a vulnerability where the output parameter in the \"idn2_lookup_u8\" and \"idn2_register_u8\" functions may not be properly initialized, leading to the use of uninitialized memory.\n    cwe: CWE-824\n    function_names:\n      - idn2_lookup_u8\n      - idn2_register_u8\n    filenames:\n      - lookup.c\n    classification: very promising\n\n  - headline: Potential information disclosure in error message\n    analysis: |\n      The \"error.c\" file contains a vulnerability where the \"idn2_strerror\" function may disclose sensitive information in the error message, such as the location of the libidn2 library.\n    cwe: CWE-209\n    function_names:\n      - idn2_strerror\n    filenames:\n      - error.c\n    classification: slightly promising\n\n  - headline: Potential insecure randomness in IDNA2008 processing\n    analysis: |\n      The \"punycode.c\" file contains a vulnerability where the Punycode encoder and decoder do not use a secure random number generator, which could lead to predictable outputs and potential security issues.\n    cwe: CWE-330\n    function_names:\n      - punycode_encode\n      - punycode_decode\n    filenames:\n      - punycode.c\n    classification: slightly promising\n\n  - headline: Potential Uncontrolled Resource Consumption in IDNA2008 processing\n    analysis: |\n      The \"lookup.c\" and \"register.c\" files contain vulnerabilities where the output buffer size is not properly validated, which could lead to excessive memory allocation and potential denial-of-service attacks.\n    cwe: CWE-400\n    function_names:\n      - idn2_lookup_u8\n      - idn2_register_u8\n    filenames:\n      - lookup.c\n      - register.c\n    classification: slightly promising\n\n  - headline: Potential Incorrect Authorization in IDNA2008 processing\n    analysis: |\n      The \"register.c\" file contains a vulnerability where the \"idn2_register_u8\" function does not properly validate the input A-label, which could lead to incorrect registration of domain names.\n    cwe: CWE-863\n    function_names:\n      - idn2_register_u8\n    filenames:\n      - register.c\n    classification: slightly promising\n\n  - headline: Potential Uncontrolled Resource Shutdown in IDNA2008 processing\n    analysis: |\n      The \"free.c\" file contains a vulnerability where the \"idn2_free\" function is not properly implemented, which could lead to resource leaks or other issues when deallocating memory.\n    cwe: CWE-404\n    function_names:\n      - idn2_free\n    filenames:\n      - free.c\n    classification: not promising\n```\n\nThe above YAML object identifies the following security vulnerabilities in the provided codebase:\n\n1. A vulnerability in the \"check-combining-property.pl\" script that can lead to unexpected termination when processing input with certain code point characteristics.\n2. A potential buffer overflow vulnerability in the Punycode decoder in the \"punycode.c\" file.\n3. A vulnerability in the \"lookup.c\" and \"register.c\" files where the output parameters may not be properly initialized, leading to the use of uninitialized memory.\n4. A potential information disclosure vulnerability in the \"error.c\" file where the error message may disclose sensitive information.\n5. A vulnerability in the \"punycode.c\" file where the Punycode encoder and decoder do not use a secure random number generator.\n6. Vulnerabilities in the \"lookup.c\" and \"register.c\" files where the output buffer size is not properly validated, leading to potential denial-of-service attacks.\n7. A vulnerability in the \"register.c\" file where the input A-label is not properly validated, leading to potential incorrect registration of domain names.\n8. A vulnerability in the \"free.c\" file where the \"idn2_free\" function is not properly implemented, leading to potential resource leaks or other issues.",
      "date": "2024-07-08T09:36:58.935516",
      "usage": {
        "prompt_tokens": 112169,
        "completion_tokens": 1280,
        "cost": 0.02964225
      }
    }
  ],
  "leads": [
    {
      "headline": "IDNA2008 lookup string conversion on domain name with invalid character",
      "analysis": "The \"check-combining-property.pl\" script contains a vulnerability where it does not properly handle code points with a combining class of 0 and a non-Mc/Mn category. This can lead to the script terminating unexpectedly when processing such input.\n",
      "classification": "very promising",
      "cwe": "CWE-20",
      "function_names": [
        "die"
      ],
      "filenames": [
        "check-combining-property.pl"
      ]
    },
    {
      "headline": "Potential buffer overflow in Punycode decoder",
      "analysis": "The Punycode decoder in the \"punycode.c\" file does not properly validate the input length, which could lead to a buffer overflow vulnerability if an attacker provides crafted input.\n",
      "classification": "very promising",
      "cwe": "CWE-120",
      "function_names": [
        "punycode_decode"
      ],
      "filenames": [
        "punycode.c"
      ]
    },
    {
      "headline": "Potential Uninitialized Memory Use in IDNA2008 processing",
      "analysis": "The \"lookup.c\" file contains a vulnerability where the output parameter in the \"idn2_lookup_u8\" and \"idn2_register_u8\" functions may not be properly initialized, leading to the use of uninitialized memory.\n",
      "classification": "very promising",
      "cwe": "CWE-824",
      "function_names": [
        "idn2_lookup_u8",
        "idn2_register_u8"
      ],
      "filenames": [
        "lookup.c"
      ]
    },
    {
      "headline": "Potential information disclosure in error message",
      "analysis": "The \"error.c\" file contains a vulnerability where the \"idn2_strerror\" function may disclose sensitive information in the error message, such as the location of the libidn2 library.\n",
      "classification": "slightly promising",
      "cwe": "CWE-209",
      "function_names": [
        "idn2_strerror"
      ],
      "filenames": [
        "error.c"
      ]
    },
    {
      "headline": "Potential insecure randomness in IDNA2008 processing",
      "analysis": "The \"punycode.c\" file contains a vulnerability where the Punycode encoder and decoder do not use a secure random number generator, which could lead to predictable outputs and potential security issues.\n",
      "classification": "slightly promising",
      "cwe": "CWE-330",
      "function_names": [
        "punycode_encode",
        "punycode_decode"
      ],
      "filenames": [
        "punycode.c"
      ]
    },
    {
      "headline": "Potential Uncontrolled Resource Consumption in IDNA2008 processing",
      "analysis": "The \"lookup.c\" and \"register.c\" files contain vulnerabilities where the output buffer size is not properly validated, which could lead to excessive memory allocation and potential denial-of-service attacks.\n",
      "classification": "slightly promising",
      "cwe": "CWE-400",
      "function_names": [
        "idn2_lookup_u8",
        "idn2_register_u8"
      ],
      "filenames": [
        "lookup.c",
        "register.c"
      ]
    },
    {
      "headline": "Potential Incorrect Authorization in IDNA2008 processing",
      "analysis": "The \"register.c\" file contains a vulnerability where the \"idn2_register_u8\" function does not properly validate the input A-label, which could lead to incorrect registration of domain names.\n",
      "classification": "slightly promising",
      "cwe": "CWE-863",
      "function_names": [
        "idn2_register_u8"
      ],
      "filenames": [
        "register.c"
      ]
    },
    {
      "headline": "Potential Uncontrolled Resource Shutdown in IDNA2008 processing",
      "analysis": "The \"free.c\" file contains a vulnerability where the \"idn2_free\" function is not properly implemented, which could lead to resource leaks or other issues when deallocating memory.\n",
      "classification": "not promising",
      "cwe": "CWE-404",
      "function_names": [
        "idn2_free"
      ],
      "filenames": [
        "free.c"
      ]
    }
  ],
  "scores": [
    {
      "stats": {
        "fn": 1,
        "tp": 1,
        "fp": 2
      },
      "mapping": {
        "1": "CVE-2017-14062"
      },
      "vuln_dates": {
        "CVE-2017-14061": "2017-08-31T16:29:00",
        "CVE-2017-14062": "2017-08-31T16:29:00"
      },
      "scoring_model": "claude-3-5-sonnet-20240620",
      "type": "llm",
      "instruction_template_hash": "245ace12b6361954d0a2"
    }
  ],
  "instruction_template_hash": "10c0163db4740318a544",
  "version": "0.1.0"
}
