{
  "commit": "116171d7ce46f7b790ad6e382587fee21586b0e0",
  "repo_url": "https://github.com/juniper/jsnapy",
  "model": "gpt-4o-2024-05-13",
  "chunk_hashes": [
    "01e4321c015ffa0a7cf0"
  ],
  "responses": [
    {
      "content": "```yaml\nleads:\n  - headline: Unsafe realpath Handling\n    analysis: |\n      The `setup_logging_path` function in `setup.py` uses `os.path.exists` and `open` to check and read configuration files. This could allow an attacker to supply malicious paths to either read or escalate permissions via a race condition, leading to potential privilege escalation or denial of service.\n    cwe: CWE-362\n    function_names:\n      - setup_logging_path\n    filenames:\n      - setup.py\n    classification: very promising\n\n  - headline: Insufficient Input Validation and Error Handling\n    analysis: |\n      Several functions, such as `generate_reply`, inadequately handle inputs and errors. This can potentially lead to security vulnerabilities, particularly in the context of parsing or generating XML or YAML configurations. Functions like `insert_data`, `get_xml_using_snapname`, etc., rely on inputs that need stronger validation.\n    cwe: CWE-20\n    function_names:\n      - generate_reply\n      - insert_data\n      - get_xml_using_snapname\n    filenames:\n      - lib/jnpr/jsnapy/snap.py\n      - lib/jnpr/jsnapy/sqlite_store.py\n      - lib/jnpr/jsnapy/sqlite_get.py\n    classification: very promising\n    \n  - headline: OS Command Injection\n    analysis: |\n      In `run_cmd` method within `Parser` class, the usage of subprocess or dev.rpc.cli might lead to command injection if the command arguments are derived from unsafe sources without sufficient sanitization.\n    cwe: CWE-78\n    function_names:\n      - run_cmd\n    filenames:\n      - lib/jnpr/jsnapy/snap.py\n    classification: very promising\n\n  - headline: Parameter Manipulation in SnapAdmin Class\n    analysis: |\n      The `SnapAdmin` class methods such as `login`, `connect`, and `get_test` incorporate user-supplied data for sensitive operations without comprehensive validation, making them vulnerable to parameter manipulation or similar attacks.\n    cwe: CWE-20\n    function_names:\n      - login\n      - connect\n      - get_test\n    filenames:\n      - lib/jnpr/jsnapy/jsnapy.py\n    classification: very promising\n\n  - headline: Unchecked Return Value\n    analysis: |\n      Functions like `command_exists` do not check the return values of critical functions, which could lead to unexpected states or discrepancies in control flow.\n    cwe: CWE-252\n    function_names:\n      - command_exists\n    filenames:\n      - lib/jnpr/jsnapy/jsnapy.py\n    classification: slightly promising\n    \n  - headline: Potential SQL Injection in SQLite Operations\n    analysis: |\n      The usage of sqlite3 without parameterized queries in functions like `get_xml_using_snapname`, `insert_data` can open doors for SQL injection if any dynamic input is concatenated into SQL statements without proper sanitization.\n    cwe: CWE-89\n    function_names:\n      - get_xml_using_snapname\n      - insert_data\n    filenames:\n      - lib/jnpr/jsnapy/sqlite_store.py\n      - lib/jnpr/jsnapy/sqlite_get.py\n    classification: very promising\n\n  - headline: Unsanitized Logging of Errors\n    analysis: |\n      Logging sensitive or unsanitized data such as user credentials, errors, or paths without proper sanitation in various functions like `login`, `check_arguments` can inadvertently expose sensitive information.\n    cwe: CWE-532\n    function_names:\n      - login\n      - check_arguments\n    filenames:\n      - lib/jnpr/jsnapy/jsnapy.py\n    classification: very promising\n\n  - headline: Improper SSL/TLS Verification\n    analysis: |\n      The connection setup in `connect` method of `SnapAdmin` class needs explicit SSL/TLS verification. Absence of stringent validation can lead to MITM (Man-In-The-Middle) attacks.\n    cwe: CWE-295\n    function_names:\n      - connect\n    filenames:\n      - lib/jnpr/jsnapy/jsnapy.py\n    classification: very promising\n```",
      "date": "2024-06-13T09:06:50.439320",
      "usage": {
        "prompt_tokens": 110286,
        "completion_tokens": 863,
        "cost": 0.564375
      }
    }
  ],
  "leads": [
    {
      "headline": "Unsafe realpath Handling",
      "analysis": "The setup_logging_path function in setup.py uses os.path.exists and open to check and read configuration files. This could allow an attacker to supply malicious paths to either read or escalate permissions via a race condition, leading to potential privilege escalation or denial of service.\n",
      "classification": "very promising",
      "cwe": "CWE-362",
      "function_names": [
        "setup_logging_path"
      ],
      "filenames": [
        "setup.py"
      ]
    },
    {
      "headline": "Insufficient Input Validation and Error Handling",
      "analysis": "Several functions, such as generate_reply, inadequately handle inputs and errors. This can potentially lead to security vulnerabilities, particularly in the context of parsing or generating XML or YAML configurations. Functions like insert_data, get_xml_using_snapname, etc., rely on inputs that need stronger validation.\n",
      "classification": "very promising",
      "cwe": "CWE-20",
      "function_names": [
        "generate_reply",
        "insert_data",
        "get_xml_using_snapname"
      ],
      "filenames": [
        "lib/jnpr/jsnapy/snap.py",
        "lib/jnpr/jsnapy/sqlite_store.py",
        "lib/jnpr/jsnapy/sqlite_get.py"
      ]
    },
    {
      "headline": "OS Command Injection",
      "analysis": "In run_cmd method within Parser class, the usage of subprocess or dev.rpc.cli might lead to command injection if the command arguments are derived from unsafe sources without sufficient sanitization.\n",
      "classification": "very promising",
      "cwe": "CWE-78",
      "function_names": [
        "run_cmd"
      ],
      "filenames": [
        "lib/jnpr/jsnapy/snap.py"
      ]
    },
    {
      "headline": "Parameter Manipulation in SnapAdmin Class",
      "analysis": "The SnapAdmin class methods such as login, connect, and get_test incorporate user-supplied data for sensitive operations without comprehensive validation, making them vulnerable to parameter manipulation or similar attacks.\n",
      "classification": "very promising",
      "cwe": "CWE-20",
      "function_names": [
        "login",
        "connect",
        "get_test"
      ],
      "filenames": [
        "lib/jnpr/jsnapy/jsnapy.py"
      ]
    },
    {
      "headline": "Unchecked Return Value",
      "analysis": "Functions like command_exists do not check the return values of critical functions, which could lead to unexpected states or discrepancies in control flow.\n",
      "classification": "slightly promising",
      "cwe": "CWE-252",
      "function_names": [
        "command_exists"
      ],
      "filenames": [
        "lib/jnpr/jsnapy/jsnapy.py"
      ]
    },
    {
      "headline": "Potential SQL Injection in SQLite Operations",
      "analysis": "The usage of sqlite3 without parameterized queries in functions like get_xml_using_snapname, insert_data can open doors for SQL injection if any dynamic input is concatenated into SQL statements without proper sanitization.\n",
      "classification": "very promising",
      "cwe": "CWE-89",
      "function_names": [
        "get_xml_using_snapname",
        "insert_data"
      ],
      "filenames": [
        "lib/jnpr/jsnapy/sqlite_store.py",
        "lib/jnpr/jsnapy/sqlite_get.py"
      ]
    },
    {
      "headline": "Unsanitized Logging of Errors",
      "analysis": "Logging sensitive or unsanitized data such as user credentials, errors, or paths without proper sanitation in various functions like login, check_arguments can inadvertently expose sensitive information.\n",
      "classification": "very promising",
      "cwe": "CWE-532",
      "function_names": [
        "login",
        "check_arguments"
      ],
      "filenames": [
        "lib/jnpr/jsnapy/jsnapy.py"
      ]
    },
    {
      "headline": "Improper SSL/TLS Verification",
      "analysis": "The connection setup in connect method of SnapAdmin class needs explicit SSL/TLS verification. Absence of stringent validation can lead to MITM (Man-In-The-Middle) attacks.\n",
      "classification": "very promising",
      "cwe": "CWE-295",
      "function_names": [
        "connect"
      ],
      "filenames": [
        "lib/jnpr/jsnapy/jsnapy.py"
      ]
    }
  ],
  "scores": [
    {
      "stats": {
        "fn": 1,
        "tp": 0,
        "fp": 7
      },
      "mapping": {},
      "vuln_dates": {
        "CVE-2018-0023": "2018-04-11T19:29:00"
      },
      "scoring_model": "claude-3-opus-20240229",
      "type": "llm",
      "instruction_template_hash": "245ace12b6361954d0a2"
    },
    {
      "stats": {
        "fn": 1,
        "tp": 0,
        "fp": 7
      },
      "mapping": {},
      "vuln_dates": {
        "CVE-2018-0023": "2018-04-11T19:29:00"
      },
      "scoring_model": "claude-3-5-sonnet-20240620",
      "type": "llm",
      "instruction_template_hash": "245ace12b6361954d0a2"
    }
  ],
  "instruction_template_hash": "10c0163db4740318a544",
  "version": "0.1.0"
}
