{
  "commit": "03cb17a60ccad88599ccb5a3c231021bdda7f31a",
  "repo_url": "https://github.com/objective-see/lulu",
  "model": "claude-3-haiku-20240307",
  "chunk_hashes": [
    "17944e37c8d57b1e5ce5"
  ],
  "responses": [
    {
      "content": "Here is the YAML output identifying the security vulnerabilities in the provided codebase:\n\n```yaml\nleads:\n  - headline: Improper Neutralization of Special Elements used in an OS Command ('OS Command Injection')\n    analysis: |\n      The `VirusTotal` class contains a `postRequest` method that makes a POST request to the VirusTotal API using user-provided URL and POST data. If the URL and/or POST data are not properly sanitized, an attacker could potentially inject malicious OS commands that would be executed on the server-side, leading to a remote code execution vulnerability.\n    cwe: CWE-78\n    function_names:\n      - postRequest\n    filenames:\n      - loginItem/loginItem/VirusTotal.h\n      - loginItem/loginItem/VirusTotal.m\n    classification: slightly promising\n\n  - headline: Improper Neutralization of Special Elements used in an SQL Command ('SQL Injection')\n    analysis: |\n      The `AppReceipt` class appears to parse and extract data from the app receipt, which may contain user-provided input. If the input is not properly validated and sanitized, an attacker could potentially inject malicious SQL commands, leading to a SQL injection vulnerability.\n    cwe: CWE-89\n    function_names:\n      - init\n    filenames:\n      - loginItem/loginItem/AppReceipt.h\n      - loginItem/loginItem/AppReceipt.m\n    classification: slightly promising\n\n  - headline: Improper Neutralization of Input During Web Page Generation ('Cross-site Scripting')\n    analysis: |\n      The `VirusTotalViewController` class contains a `message` property that may display user-provided input. If this input is not properly sanitized before being displayed in the UI, an attacker could potentially inject malicious HTML/JavaScript, leading to a cross-site scripting (XSS) vulnerability.\n    cwe: CWE-79\n    function_names:\n      - None\n    filenames:\n      - loginItem/loginItem/VirusTotalViewController.h\n      - loginItem/loginItem/VirusTotalViewController.m\n    classification: slightly promising\n\n  - headline: Improper Neutralization of Special Elements used in an OS Command ('OS Command Injection')\n    analysis: |\n      The `configure.sh` script contains logic to install and uninstall the LuLu application. The script uses the `system_profiler` and `kextcache` commands, which may be vulnerable to OS command injection if the input parameters are not properly sanitized.\n    cwe: CWE-78\n    function_names:\n      - None\n    filenames:\n      - configure/Configure/Script/configure.sh\n    classification: slightly promising\n\n  - headline: Improper Neutralization of Input During Web Page Generation ('Cross-site Scripting')\n    analysis: |\n      The `HyperlinkTextField` class is used throughout the codebase to display user-provided input. If the input is not properly sanitized before being displayed, an attacker could potentially inject malicious HTML/JavaScript, leading to a cross-site scripting (XSS) vulnerability.\n    cwe: CWE-79\n    function_names:\n      - None\n    filenames:\n      - loginItem/loginItem/3rdParty/HyperlinkTextField.h\n      - mainApp/mainApp/3rdParty/HyperlinkTextField.h\n    classification: slightly promising\n\n  - headline: Improper Neutralization of Special Elements used in a Command ('Command Injection')\n    analysis: |\n      The `execTask` function in the `utilities.h` file executes external processes with user-provided arguments. If the arguments are not properly sanitized, an attacker could potentially inject malicious commands, leading to a command injection vulnerability.\n    cwe: CWE-77\n    function_names:\n      - execTask\n    filenames:\n      - shared/utilities.h\n    classification: slightly promising\n\n  - headline: Improper Neutralization of Special Elements used in an SQL Command ('SQL Injection')\n    analysis: |\n      The `AppReceipt` class appears to parse and extract data from the app receipt, which may contain user-provided input. If the input is not properly validated and sanitized, an attacker could potentially inject malicious SQL commands, leading to a SQL injection vulnerability.\n    cwe: CWE-89\n    function_names:\n      - init\n    filenames:\n      - loginItem/loginItem/AppReceipt.h\n      - loginItem/loginItem/AppReceipt.m\n    classification: slightly promising\n\n  - headline: Improper Neutralization of Special Elements used in an Expression Language Statement ('Expression Language Injection')\n    analysis: |\n      The `HyperlinkTextField` class is used throughout the codebase to display user-provided input. If the input is not properly sanitized before being displayed, an attacker could potentially inject malicious Expression Language (EL) statements, leading to an Expression Language Injection vulnerability.\n    cwe: CWE-917\n    function_names:\n      - None\n    filenames:\n      - loginItem/loginItem/3rdParty/HyperlinkTextField.h\n      - mainApp/mainApp/3rdParty/HyperlinkTextField.h\n    classification: slightly promising\n\n  - headline: Improper Neutralization of Input During Web Page Generation ('Cross-site Scripting')\n    analysis: |\n      The `AlertWindowController` class displays various user-provided input, such as process names, arguments, and IP addresses. If this input is not properly sanitized before being displayed in the UI, an attacker could potentially inject malicious HTML/JavaScript, leading to a cross-site scripting (XSS) vulnerability.\n    cwe: CWE-79\n    function_names:\n      - None\n    filenames:\n      - loginItem/loginItem/AlertWindowController.h\n      - loginItem/loginItem/AlertWindowController.m\n    classification: slightly promising\n\n  - headline: Improper Neutralization of Input During Web Page Generation ('Cross-site Scripting')\n    analysis: |\n      The `HelperInterface` class is used to communicate with the installer helper application. If the input received from the helper application is not properly sanitized before being displayed in the UI, an attacker could potentially inject malicious HTML/JavaScript, leading to a cross-site scripting (XSS) vulnerability.\n    cwe: CWE-79\n    function_names:\n      - None\n    filenames:\n      - configure/Helper/HelperInterface.h\n    classification: slightly promising\n\n  - headline: Improper Neutralization of Input During Web Page Generation ('Cross-site Scripting')\n    analysis: |\n      The `ErrorWindowController` class displays various user-provided error messages and information. If this input is not properly sanitized before being displayed in the UI, an attacker could potentially inject malicious HTML/JavaScript, leading to a cross-site scripting (XSS) vulnerability.\n    cwe: CWE-79\n    function_names:\n      - None\n    filenames:\n      - configure/Configure/ErrorWindowController.h\n      - configure/Configure/ErrorWindowController.m\n    classification: slightly promising\n\n  - headline: Improper Neutralization of Input During Web Page Generation ('Cross-site Scripting')\n    analysis: |\n      The `AboutWindowController` class displays various user-provided information, such as the version and patrons. If this input is not properly sanitized before being displayed in the UI, an attacker could potentially inject malicious HTML/JavaScript, leading to a cross-site scripting (XSS) vulnerability.\n    cwe: CWE-79\n    function_names:\n      - None\n    filenames:\n      - configure/Configure/AboutWindowController.h\n      - configure/Configure/AboutWindowController.m\n    classification: slightly promising\n\n  - headline: Improper Neutralization of Special Elements used in an OS Command ('OS Command Injection')\n    analysis: |\n      The `execTask` function in the `utilities.h` file executes external processes with user-provided arguments. If the arguments are not properly sanitized, an attacker could potentially inject malicious commands, leading to a command injection vulnerability.\n    cwe: CWE-78\n    function_names:\n      - execTask\n    filenames:\n      - shared/utilities.h\n    classification: slightly promising\n\n  - headline: Improper Neutralization of Special Elements used in an XML Document ('XML Injection')\n    analysis: |\n      The `AppReceipt` class appears to parse and extract data from the app receipt, which may contain user-provided input. If the input is not properly validated and sanitized, an attacker could potentially inject malicious XML elements, leading to an XML injection vulnerability.\n    cwe: CWE-91\n    function_names:\n      - init\n    filenames:\n      - loginItem/loginItem/AppReceipt.h\n      - loginItem/loginItem/AppReceipt.m\n    classification: slightly promising\n```",
      "date": "2024-06-13T10:43:14.789028",
      "usage": {
        "prompt_tokens": 44527,
        "completion_tokens": 2113,
        "cost": 0.013773
      }
    }
  ],
  "leads": [
    {
      "headline": "Improper Neutralization of Special Elements used in an OS Command ('OS Command Injection')",
      "analysis": "The VirusTotal class contains a postRequest method that makes a POST request to the VirusTotal API using user-provided URL and POST data. If the URL and/or POST data are not properly sanitized, an attacker could potentially inject malicious OS commands that would be executed on the server-side, leading to a remote code execution vulnerability.\n",
      "classification": "slightly promising",
      "cwe": "CWE-78",
      "function_names": [
        "postRequest"
      ],
      "filenames": [
        "loginItem/loginItem/VirusTotal.h",
        "loginItem/loginItem/VirusTotal.m"
      ]
    },
    {
      "headline": "Improper Neutralization of Special Elements used in an SQL Command ('SQL Injection')",
      "analysis": "The AppReceipt class appears to parse and extract data from the app receipt, which may contain user-provided input. If the input is not properly validated and sanitized, an attacker could potentially inject malicious SQL commands, leading to a SQL injection vulnerability.\n",
      "classification": "slightly promising",
      "cwe": "CWE-89",
      "function_names": [
        "init"
      ],
      "filenames": [
        "loginItem/loginItem/AppReceipt.h",
        "loginItem/loginItem/AppReceipt.m"
      ]
    },
    {
      "headline": "Improper Neutralization of Input During Web Page Generation ('Cross-site Scripting')",
      "analysis": "The VirusTotalViewController class contains a message property that may display user-provided input. If this input is not properly sanitized before being displayed in the UI, an attacker could potentially inject malicious HTML/JavaScript, leading to a cross-site scripting (XSS) vulnerability.\n",
      "classification": "slightly promising",
      "cwe": "CWE-79",
      "function_names": [
        "None"
      ],
      "filenames": [
        "loginItem/loginItem/VirusTotalViewController.h",
        "loginItem/loginItem/VirusTotalViewController.m"
      ]
    },
    {
      "headline": "Improper Neutralization of Special Elements used in an OS Command ('OS Command Injection')",
      "analysis": "The configure.sh script contains logic to install and uninstall the LuLu application. The script uses the system_profiler and kextcache commands, which may be vulnerable to OS command injection if the input parameters are not properly sanitized.\n",
      "classification": "slightly promising",
      "cwe": "CWE-78",
      "function_names": [
        "None"
      ],
      "filenames": [
        "configure/Configure/Script/configure.sh"
      ]
    },
    {
      "headline": "Improper Neutralization of Input During Web Page Generation ('Cross-site Scripting')",
      "analysis": "The HyperlinkTextField class is used throughout the codebase to display user-provided input. If the input is not properly sanitized before being displayed, an attacker could potentially inject malicious HTML/JavaScript, leading to a cross-site scripting (XSS) vulnerability.\n",
      "classification": "slightly promising",
      "cwe": "CWE-79",
      "function_names": [
        "None"
      ],
      "filenames": [
        "loginItem/loginItem/3rdParty/HyperlinkTextField.h",
        "mainApp/mainApp/3rdParty/HyperlinkTextField.h"
      ]
    },
    {
      "headline": "Improper Neutralization of Special Elements used in a Command ('Command Injection')",
      "analysis": "The execTask function in the utilities.h file executes external processes with user-provided arguments. If the arguments are not properly sanitized, an attacker could potentially inject malicious commands, leading to a command injection vulnerability.\n",
      "classification": "slightly promising",
      "cwe": "CWE-77",
      "function_names": [
        "execTask"
      ],
      "filenames": [
        "shared/utilities.h"
      ]
    },
    {
      "headline": "Improper Neutralization of Special Elements used in an SQL Command ('SQL Injection')",
      "analysis": "The AppReceipt class appears to parse and extract data from the app receipt, which may contain user-provided input. If the input is not properly validated and sanitized, an attacker could potentially inject malicious SQL commands, leading to a SQL injection vulnerability.\n",
      "classification": "slightly promising",
      "cwe": "CWE-89",
      "function_names": [
        "init"
      ],
      "filenames": [
        "loginItem/loginItem/AppReceipt.h",
        "loginItem/loginItem/AppReceipt.m"
      ]
    },
    {
      "headline": "Improper Neutralization of Special Elements used in an Expression Language Statement ('Expression Language Injection')",
      "analysis": "The HyperlinkTextField class is used throughout the codebase to display user-provided input. If the input is not properly sanitized before being displayed, an attacker could potentially inject malicious Expression Language (EL) statements, leading to an Expression Language Injection vulnerability.\n",
      "classification": "slightly promising",
      "cwe": "CWE-917",
      "function_names": [
        "None"
      ],
      "filenames": [
        "loginItem/loginItem/3rdParty/HyperlinkTextField.h",
        "mainApp/mainApp/3rdParty/HyperlinkTextField.h"
      ]
    },
    {
      "headline": "Improper Neutralization of Input During Web Page Generation ('Cross-site Scripting')",
      "analysis": "The AlertWindowController class displays various user-provided input, such as process names, arguments, and IP addresses. If this input is not properly sanitized before being displayed in the UI, an attacker could potentially inject malicious HTML/JavaScript, leading to a cross-site scripting (XSS) vulnerability.\n",
      "classification": "slightly promising",
      "cwe": "CWE-79",
      "function_names": [
        "None"
      ],
      "filenames": [
        "loginItem/loginItem/AlertWindowController.h",
        "loginItem/loginItem/AlertWindowController.m"
      ]
    },
    {
      "headline": "Improper Neutralization of Input During Web Page Generation ('Cross-site Scripting')",
      "analysis": "The HelperInterface class is used to communicate with the installer helper application. If the input received from the helper application is not properly sanitized before being displayed in the UI, an attacker could potentially inject malicious HTML/JavaScript, leading to a cross-site scripting (XSS) vulnerability.\n",
      "classification": "slightly promising",
      "cwe": "CWE-79",
      "function_names": [
        "None"
      ],
      "filenames": [
        "configure/Helper/HelperInterface.h"
      ]
    },
    {
      "headline": "Improper Neutralization of Input During Web Page Generation ('Cross-site Scripting')",
      "analysis": "The ErrorWindowController class displays various user-provided error messages and information. If this input is not properly sanitized before being displayed in the UI, an attacker could potentially inject malicious HTML/JavaScript, leading to a cross-site scripting (XSS) vulnerability.\n",
      "classification": "slightly promising",
      "cwe": "CWE-79",
      "function_names": [
        "None"
      ],
      "filenames": [
        "configure/Configure/ErrorWindowController.h",
        "configure/Configure/ErrorWindowController.m"
      ]
    },
    {
      "headline": "Improper Neutralization of Input During Web Page Generation ('Cross-site Scripting')",
      "analysis": "The AboutWindowController class displays various user-provided information, such as the version and patrons. If this input is not properly sanitized before being displayed in the UI, an attacker could potentially inject malicious HTML/JavaScript, leading to a cross-site scripting (XSS) vulnerability.\n",
      "classification": "slightly promising",
      "cwe": "CWE-79",
      "function_names": [
        "None"
      ],
      "filenames": [
        "configure/Configure/AboutWindowController.h",
        "configure/Configure/AboutWindowController.m"
      ]
    },
    {
      "headline": "Improper Neutralization of Special Elements used in an OS Command ('OS Command Injection')",
      "analysis": "The execTask function in the utilities.h file executes external processes with user-provided arguments. If the arguments are not properly sanitized, an attacker could potentially inject malicious commands, leading to a command injection vulnerability.\n",
      "classification": "slightly promising",
      "cwe": "CWE-78",
      "function_names": [
        "execTask"
      ],
      "filenames": [
        "shared/utilities.h"
      ]
    },
    {
      "headline": "Improper Neutralization of Special Elements used in an XML Document ('XML Injection')",
      "analysis": "The AppReceipt class appears to parse and extract data from the app receipt, which may contain user-provided input. If the input is not properly validated and sanitized, an attacker could potentially inject malicious XML elements, leading to an XML injection vulnerability.\n",
      "classification": "slightly promising",
      "cwe": "CWE-91",
      "function_names": [
        "init"
      ],
      "filenames": [
        "loginItem/loginItem/AppReceipt.h",
        "loginItem/loginItem/AppReceipt.m"
      ]
    }
  ],
  "scores": [
    {
      "stats": {
        "fn": 1,
        "tp": 0,
        "fp": 0
      },
      "mapping": {},
      "vuln_dates": {
        "CVE-2018-10404": "2018-06-13T22:29:00"
      },
      "scoring_model": "claude-3-opus-20240229",
      "type": "llm",
      "instruction_template_hash": "245ace12b6361954d0a2"
    }
  ],
  "instruction_template_hash": "10c0163db4740318a544",
  "version": "0.1.0"
}
