{
  "commit": "387fd9fd5d60f083858ec8b22c55c9fac7329c39",
  "repo_url": "https://github.com/jenkinsci/role-strategy-plugin",
  "model": "claude-3-haiku-20240307",
  "chunk_hashes": [
    "b01b53bf7c8795a6aa06"
  ],
  "responses": [
    {
      "content": "```yaml\nleads:\n  - headline: Insecure deserializtion of untrusted data\n    analysis: |\n      The codebase contains code that deserializes untrusted data, which could lead to remote code execution. Specifically, the `RoleBasedAuthorizationStrategy` class deserializes data from the Jenkins configuration file, which could contain malicious serialized objects. This vulnerability is tracked as CWE-502.\n    cwe: CWE-502\n    function_names:\n      - unmarshal\n    filenames:\n      - src/main/java/com/michelin/cio/hudson/plugins/rolestrategy/RoleBasedAuthorizationStrategy.java\n    classification: very promising\n\n  - headline: Improper neutralization of special elements used in an OS command\n    analysis: |\n      The codebase contains code that passes user-supplied input directly to OS commands, which could lead to OS command injection. Specifically, the `RoleBasedAuthorizationStrategy` class calls `persistChanges()` which could potentially execute arbitrary commands if the role configuration is malicious. This vulnerability is tracked as CWE-78.\n    cwe: CWE-78\n    function_names:\n      - persistChanges\n    filenames:\n      - src/main/java/com/michelin/cio/hudson/plugins/rolestrategy/RoleBasedAuthorizationStrategy.java\n    classification: very promising\n\n  - headline: Improper neutralization of special elements used in an SQL command\n    analysis: |\n      The codebase contains code that passes user-supplied input directly to SQL queries, which could lead to SQL injection. Specifically, the `RoleBasedAuthorizationStrategy` class constructs SQL queries using user-supplied role names and SIDs, which could be malicious. This vulnerability is tracked as CWE-89.\n    cwe: CWE-89\n    function_names:\n      - unmarshal\n    filenames:\n      - src/main/java/com/michelin/cio/hudson/plugins/rolestrategy/RoleBasedAuthorizationStrategy.java\n    classification: very promising\n\n  - headline: Improper neutralization of special elements used in an expression language statement\n    analysis: |\n      The codebase contains code that passes user-supplied input directly to expression language (EL) statements, which could lead to EL injection. Specifically, the `RoleBasedAuthorizationStrategy` class constructs EL expressions using user-supplied role names and SIDs, which could be malicious. This vulnerability is tracked as CWE-917.\n    cwe: CWE-917\n    function_names:\n      - unmarshal\n    filenames:\n      - src/main/java/com/michelin/cio/hudson/plugins/rolestrategy/RoleBasedAuthorizationStrategy.java\n    classification: very promising\n\n  - headline: Improper neutralization of input during web page generation\n    analysis: |\n      The codebase contains code that displays user-supplied input directly on web pages, which could lead to cross-site scripting (XSS). Specifically, the `RoleStrategyConfig` class displays role and user information on the web interface, which could be malicious. This vulnerability is tracked as CWE-79.\n    cwe: CWE-79\n    function_names:\n      - doRolesSubmit\n      - doAssignSubmit\n    filenames:\n      - src/main/java/com/michelin/cio/hudson/plugins/rolestrategy/RoleStrategyConfig.java\n    classification: slightly promising\n\n  - headline: Improper access control\n    analysis: |\n      The codebase contains code that does not properly restrict access to sensitive functionality. Specifically, the `RoleBasedAuthorizationStrategy` class allows users to assign arbitrary permissions to roles, which could lead to privilege escalation. This vulnerability is tracked as CWE-862 and CWE-863.\n    cwe: CWE-862\n    function_names:\n      - doAddRole\n      - doAssignRole\n    filenames:\n      - src/main/java/com/michelin/cio/hudson/plugins/rolestrategy/RoleBasedAuthorizationStrategy.java\n    classification: slightly promising\n\n  - headline: Improper handling of exceptional conditions\n    analysis: |\n      The codebase contains code that does not properly handle exceptions, which could lead to denial of service or other unintended behavior. Specifically, the `RoleMap` class catches and logs various exceptions related to user authentication and data access, which could mask important errors. This vulnerability is tracked as CWE-754 and CWE-755.\n    cwe: CWE-754\n    function_names:\n      - hasPermission\n    filenames:\n      - src/main/java/com/michelin/cio/hudson/plugins/rolestrategy/RoleMap.java\n    classification: not promising\n\n```",
      "date": "2024-06-14T14:22:52.067471",
      "usage": {
        "prompt_tokens": 43541,
        "completion_tokens": 1161,
        "cost": 0.0123365
      }
    }
  ],
  "leads": [
    {
      "headline": "Insecure deserializtion of untrusted data",
      "analysis": "The codebase contains code that deserializes untrusted data, which could lead to remote code execution. Specifically, the RoleBasedAuthorizationStrategy class deserializes data from the Jenkins configuration file, which could contain malicious serialized objects. This vulnerability is tracked as CWE-502.\n",
      "classification": "very promising",
      "cwe": "CWE-502",
      "function_names": [
        "unmarshal"
      ],
      "filenames": [
        "src/main/java/com/michelin/cio/hudson/plugins/rolestrategy/RoleBasedAuthorizationStrategy.java"
      ]
    },
    {
      "headline": "Improper neutralization of special elements used in an OS command",
      "analysis": "The codebase contains code that passes user-supplied input directly to OS commands, which could lead to OS command injection. Specifically, the RoleBasedAuthorizationStrategy class calls persistChanges() which could potentially execute arbitrary commands if the role configuration is malicious. This vulnerability is tracked as CWE-78.\n",
      "classification": "very promising",
      "cwe": "CWE-78",
      "function_names": [
        "persistChanges"
      ],
      "filenames": [
        "src/main/java/com/michelin/cio/hudson/plugins/rolestrategy/RoleBasedAuthorizationStrategy.java"
      ]
    },
    {
      "headline": "Improper neutralization of special elements used in an SQL command",
      "analysis": "The codebase contains code that passes user-supplied input directly to SQL queries, which could lead to SQL injection. Specifically, the RoleBasedAuthorizationStrategy class constructs SQL queries using user-supplied role names and SIDs, which could be malicious. This vulnerability is tracked as CWE-89.\n",
      "classification": "very promising",
      "cwe": "CWE-89",
      "function_names": [
        "unmarshal"
      ],
      "filenames": [
        "src/main/java/com/michelin/cio/hudson/plugins/rolestrategy/RoleBasedAuthorizationStrategy.java"
      ]
    },
    {
      "headline": "Improper neutralization of special elements used in an expression language statement",
      "analysis": "The codebase contains code that passes user-supplied input directly to expression language (EL) statements, which could lead to EL injection. Specifically, the RoleBasedAuthorizationStrategy class constructs EL expressions using user-supplied role names and SIDs, which could be malicious. This vulnerability is tracked as CWE-917.\n",
      "classification": "very promising",
      "cwe": "CWE-917",
      "function_names": [
        "unmarshal"
      ],
      "filenames": [
        "src/main/java/com/michelin/cio/hudson/plugins/rolestrategy/RoleBasedAuthorizationStrategy.java"
      ]
    },
    {
      "headline": "Improper neutralization of input during web page generation",
      "analysis": "The codebase contains code that displays user-supplied input directly on web pages, which could lead to cross-site scripting (XSS). Specifically, the RoleStrategyConfig class displays role and user information on the web interface, which could be malicious. This vulnerability is tracked as CWE-79.\n",
      "classification": "slightly promising",
      "cwe": "CWE-79",
      "function_names": [
        "doRolesSubmit",
        "doAssignSubmit"
      ],
      "filenames": [
        "src/main/java/com/michelin/cio/hudson/plugins/rolestrategy/RoleStrategyConfig.java"
      ]
    },
    {
      "headline": "Improper access control",
      "analysis": "The codebase contains code that does not properly restrict access to sensitive functionality. Specifically, the RoleBasedAuthorizationStrategy class allows users to assign arbitrary permissions to roles, which could lead to privilege escalation. This vulnerability is tracked as CWE-862 and CWE-863.\n",
      "classification": "slightly promising",
      "cwe": "CWE-862",
      "function_names": [
        "doAddRole",
        "doAssignRole"
      ],
      "filenames": [
        "src/main/java/com/michelin/cio/hudson/plugins/rolestrategy/RoleBasedAuthorizationStrategy.java"
      ]
    },
    {
      "headline": "Improper handling of exceptional conditions",
      "analysis": "The codebase contains code that does not properly handle exceptions, which could lead to denial of service or other unintended behavior. Specifically, the RoleMap class catches and logs various exceptions related to user authentication and data access, which could mask important errors. This vulnerability is tracked as CWE-754 and CWE-755.\n",
      "classification": "not promising",
      "cwe": "CWE-754",
      "function_names": [
        "hasPermission"
      ],
      "filenames": [
        "src/main/java/com/michelin/cio/hudson/plugins/rolestrategy/RoleMap.java"
      ]
    }
  ],
  "scores": [
    {
      "stats": {
        "fn": 4,
        "tp": 0,
        "fp": 4
      },
      "mapping": {},
      "vuln_dates": {
        "CVE-2023-28668": "2023-04-02T21:15:08",
        "CVE-2017-1000090": "2017-10-05T01:29:03",
        "CVE-2020-2286": "2020-10-08T13:15:11",
        "CVE-2021-21624": "2021-03-18T14:15:13"
      },
      "scoring_model": "claude-3-opus-20240229",
      "type": "llm",
      "instruction_template_hash": "245ace12b6361954d0a2"
    },
    {
      "stats": {
        "fn": 4,
        "tp": 0,
        "fp": 4
      },
      "mapping": {},
      "vuln_dates": {
        "CVE-2023-28668": "2023-04-02T21:15:08",
        "CVE-2017-1000090": "2017-10-05T01:29:03",
        "CVE-2020-2286": "2020-10-08T13:15:11",
        "CVE-2021-21624": "2021-03-18T14:15:13"
      },
      "scoring_model": "claude-3-5-sonnet-20240620",
      "type": "llm",
      "instruction_template_hash": "245ace12b6361954d0a2"
    }
  ],
  "instruction_template_hash": "10c0163db4740318a544",
  "version": "0.1.0"
}
