{
  "commit": "cb607485dc370ae66889f8a495ae1aa10caa9a8d",
  "repo_url": "https://github.com/exfatprogs/exfatprogs",
  "model": "gpt-4o-2024-05-13",
  "chunk_hashes": [
    "b20edd266cf3e502e779"
  ],
  "responses": [
    {
      "content": "```yaml\nleads:\n  - headline: \"Potential Command Injection in autogen.sh\"\n    analysis: |\n      The `autogen.sh` script uses `autoreconf` without validating or sanitizing its input.\n      Since `autoreconf` is being invoked directly via the shell, this can lead to command injection if an attacker can influence the input in some way.\n      The shell script doesn't ensure that the inputs are valid or expected, making it possible to provide malicious input.\n    cwe: CWE-78\n    function_names: []\n    filenames:\n      - \"autogen.sh\"\n    classification: \"slightly promising\"\n  \n  - headline: \"Possible Shell Injection in fsck/test_fsck.sh\"\n    analysis: |\n      The `test_fsck.sh` script contains several dynamic invocations of commands without proper input validation.\n      Specifically, various variables like `DEV_FILE` and `FSCK_OPTS` are derived from external inputs or untrusted sources and used directly in command invocations.\n      This opens the possibility of shell injection attacks if these inputs are manipulated by an attacker.\n    cwe: CWE-78\n    function_names: []\n    filenames:\n      - \"tests/test_fsck.sh\"\n    classification: \"very promising\"\n\n  - headline: \"Buffer overflow vulnerability in mkfs/upcase.c\"\n    analysis: |\n      The `exfat_create_upcase_table` function in upcase.c reads from `upcase_table` and writes to a file descriptor without any bounds checking.\n      This could potentially lead to a buffer overflow if there are more characters read than expected.\n      This can cause crashes or allow remote code execution if exploited correctly.\n    cwe: CWE-120\n    function_names:\n      - \"exfat_create_upcase_table\"\n    filenames:\n      - \"mkfs/upcase.c\"\n    classification: \"slightly promising\"\n\n  - headline: \"Format string vulnerability in mkfs/mkfs.c\"\n    analysis: |\n      In the mkfs.c file, the `exfat_info` and `exfat_err` functions are utilized repeatedly with potential format string vulnerabilities.\n      If any of these strings can be influenced by an attacker, it can lead to arbitrary code execution by manipulating the format strings.\n      This affects the functions for creating, writing, and logging about the filesystem generation process.\n    cwe: CWE-134\n    function_names:\n      - \"exfat_info\"\n      - \"exfat_err\"\n      - \"make_exfat\"\n    filenames:\n      - \"mkfs/mkfs.c\"\n    classification: \"very promising\"\n  \n  - headline: \"Instantiation of uninitialized data structures in fsck/fsck.c\"\n    analysis: |\n      The code in fsck.c has several instances where data structures are used without proper initialization.\n      This can lead to unpredictable behaviors, including exposing uninitialized memory content or causing program crashes.\n      Functions involving manipulation of these data structures may inadvertently leak or corrupt memory.\n    cwe: CWE-908\n    function_names:\n      - \"main\"\n      - \"read_children\"\n    filenames:\n      - \"fsck/fsck.c\"\n    classification: \"slightly promising\"\n    \n  - headline: \"Possible Race Condition in fsck/repair.c\"\n    analysis: |\n      The repair process in repair.c likely performs multiple file operations that can introduce race conditions.\n      Without adequate synchronization, these could lead to data corruption or unexpected behavior during concurrent execution.\n      Specific critical sections of the code that manipulate shared resources concurrently need to be protected with proper locking mechanisms.\n    cwe: CWE-362\n    function_names:\n      - \"write_bitmap\"\n      - \"exfat_repair_ask\"\n    filenames:\n      - \"fsck/repair.c\"\n    classification: \"slightly promising\"\n```\n",
      "date": "2024-06-09T11:45:53.589573",
      "usage": {
        "prompt_tokens": 93780,
        "completion_tokens": 773,
        "cost": 0.480495
      }
    }
  ],
  "leads": [
    {
      "headline": "Potential Command Injection in autogen.sh",
      "analysis": "The autogen.sh script uses autoreconf without validating or sanitizing its input.\nSince autoreconf is being invoked directly via the shell, this can lead to command injection if an attacker can influence the input in some way.\nThe shell script doesn't ensure that the inputs are valid or expected, making it possible to provide malicious input.\n",
      "classification": "slightly promising",
      "cwe": "CWE-78",
      "function_names": [],
      "filenames": [
        "autogen.sh"
      ]
    },
    {
      "headline": "Possible Shell Injection in fsck/test_fsck.sh",
      "analysis": "The test_fsck.sh script contains several dynamic invocations of commands without proper input validation.\nSpecifically, various variables like DEV_FILE and FSCK_OPTS are derived from external inputs or untrusted sources and used directly in command invocations.\nThis opens the possibility of shell injection attacks if these inputs are manipulated by an attacker.\n",
      "classification": "very promising",
      "cwe": "CWE-78",
      "function_names": [],
      "filenames": [
        "tests/test_fsck.sh"
      ]
    },
    {
      "headline": "Buffer overflow vulnerability in mkfs/upcase.c",
      "analysis": "The exfat_create_upcase_table function in upcase.c reads from upcase_table and writes to a file descriptor without any bounds checking.\nThis could potentially lead to a buffer overflow if there are more characters read than expected.\nThis can cause crashes or allow remote code execution if exploited correctly.\n",
      "classification": "slightly promising",
      "cwe": "CWE-120",
      "function_names": [
        "exfat_create_upcase_table"
      ],
      "filenames": [
        "mkfs/upcase.c"
      ]
    },
    {
      "headline": "Format string vulnerability in mkfs/mkfs.c",
      "analysis": "In the mkfs.c file, the exfat_info and exfat_err functions are utilized repeatedly with potential format string vulnerabilities.\nIf any of these strings can be influenced by an attacker, it can lead to arbitrary code execution by manipulating the format strings.\nThis affects the functions for creating, writing, and logging about the filesystem generation process.\n",
      "classification": "very promising",
      "cwe": "CWE-134",
      "function_names": [
        "exfat_info",
        "exfat_err",
        "make_exfat"
      ],
      "filenames": [
        "mkfs/mkfs.c"
      ]
    },
    {
      "headline": "Instantiation of uninitialized data structures in fsck/fsck.c",
      "analysis": "The code in fsck.c has several instances where data structures are used without proper initialization.\nThis can lead to unpredictable behaviors, including exposing uninitialized memory content or causing program crashes.\nFunctions involving manipulation of these data structures may inadvertently leak or corrupt memory.\n",
      "classification": "slightly promising",
      "cwe": "CWE-908",
      "function_names": [
        "main",
        "read_children"
      ],
      "filenames": [
        "fsck/fsck.c"
      ]
    },
    {
      "headline": "Possible Race Condition in fsck/repair.c",
      "analysis": "The repair process in repair.c likely performs multiple file operations that can introduce race conditions.\nWithout adequate synchronization, these could lead to data corruption or unexpected behavior during concurrent execution.\nSpecific critical sections of the code that manipulate shared resources concurrently need to be protected with proper locking mechanisms.\n",
      "classification": "slightly promising",
      "cwe": "CWE-362",
      "function_names": [
        "write_bitmap",
        "exfat_repair_ask"
      ],
      "filenames": [
        "fsck/repair.c"
      ]
    }
  ],
  "scores": [
    {
      "stats": {
        "fn": 1,
        "tp": 0,
        "fp": 2
      },
      "mapping": {},
      "vuln_dates": {
        "CVE-2023-45897": "2023-10-28T21:15:07"
      },
      "scoring_model": "gpt-4o-2024-05-13",
      "type": "llm",
      "instruction_template_hash": "8998f09cf57fca8a6e03"
    }
  ],
  "instruction_template_hash": "10c0163db4740318a544",
  "version": "0.1.0"
}
