{
  "commit": "189e23de5ba65e540f3c56f636474e33699fc310",
  "repo_url": "https://github.com/ovirt/ovirt-ansible",
  "model": "gpt-4o-2024-05-13",
  "chunk_hashes": [
    "7987d56f857d1a717fea"
  ],
  "responses": [
    {
      "content": "```yaml\nleads:\n  - headline: \"Inadequate validation of input parameters in bash scripts\"\n    analysis: |\n      The bash scripts `automation/build-artifacts.sh`, `automation/check-merged.sh`, and `automation/check-patch.sh` use user input without proper validation. This can lead to several types of security vulnerabilities like injection attacks, where an attacker can manipulate the input parameters to execute arbitrary commands, affecting the system's integrity and availability.\n    cwe: CWE-20\n    function_names: []\n    filenames:\n      - automation/build-artifacts.sh\n      - automation/check-merged.sh\n      - automation/check-patch.sh\n    classification: very promising\n\n  - headline: \"Improper Handling of Errors in Python Scripts\"\n    analysis: |\n      The Python scripts (e.g., `roles/ovirt-cluster-upgrade/library/ovirt_api_facts_internal_25.py` and others) handle exceptions using broad `except Exception as e` clauses. This can mask underlying errors and make it hard to diagnose issues, allowing potential security vulnerabilities to go unnoticed. More specific exception handling and proper logging should be implemented.\n    cwe: CWE-755\n    function_names:\n      - main\n    filenames:\n      - roles/ovirt-cluster-upgrade/library/ovirt_api_facts_internal_25.py\n      - roles/ovirt-cluster-upgrade/library/ovirt_clusters_internal_24.py\n      - roles/ovirt-cluster-upgrade/library/ovirt_scheduling_policies_facts_internal_24.py\n      - roles/ovirt-vm-infra/library/ovirt_vms_24.py\n      - roles/ovirt-storages/library/ovirt_storage_connections_internal_24.py\n    classification: slightly promising\n  \n  - headline: \"Hard-coded Authentication Credentials\"\n    analysis: |\n      The script `roles/ovirt-cluster-upgrade/library/ovirt_hosts_internal_24.py` uses predefined default usernames and passwords. Hard-coded credentials pose a severe security risk as they can easily be extracted, leading to unauthorized access to the system.\n    cwe: CWE-798\n    function_names:\n      - HostsModule.build_entity\n    filenames:\n      - roles/ovirt-cluster-upgrade/library/ovirt_hosts_internal_24.py\n    classification: very promising\n\n  - headline: \"Insufficient Input Sanitization in Ansible modules\"\n    analysis: |\n      The various Ansible modules defined in the scripts (e.g., `roles/ovirt-cluster-upgrade/library/ovirt_api_facts_internal_25.py`, `roles/ovirt-cluster-upgrade/library/ovirt_hosts_internal_24.py`) do not sufficiently sanitize input parameters. This could lead to injection vulnerabilities which allow an attacker to manipulate input data to execute arbitrary commands.\n    cwe: CWE-74\n    function_names:\n      - main\n    filenames:\n      - roles/ovirt-cluster-upgrade/library/ovirt_api_facts_internal_25.py\n      - roles/ovirt-cluster-upgrade/library/ovirt_hosts_internal_24.py\n      - roles/ovirt-cluster-upgrade/library/ovirt_clusters_internal_24.py\n    classification: very promising\n  \n  - headline: \"Exposure of Sensitive Information through Exception Messages\"\n    analysis: |\n      The exception handling in scripts such as `roles/ovirt-cluster-upgrade/library/ovirt_api_facts_internal_25.py` use `module.fail_json(msg=str(e), exception=traceback.format_exc())`, which can reveal sensitive information about the environment and runtime configuration. This exposed information can be exploited by an attacker to learn more about the system.\n    cwe: CWE-209\n    function_names:\n      - main\n    filenames:\n      - roles/ovirt-cluster-upgrade/library/ovirt_api_facts_internal_25.py\n      - roles/ovirt-cluster-upgrade/library/ovirt_hosts_internal_24.py\n      - roles/ovirt-cluster-upgrade/library/ovirt_clusters_internal_24.py\n      - roles/ovirt-vm-infra/library/ovirt_vms_24.py\n      - roles/ovirt-storages/library/ovirt_storage_connections_internal_24.py\n    classification: slightly promising\n  \n  - headline: \"Potential Command Injection via Shell Invocation in Python Scripts\"\n    analysis: |\n      In the `roles/ovirt-cluster-upgrade/library/ovirt_hosts_internal_24.py` module, functions that invoke shell commands do not sanitize the input thoroughly. This could allow an attacker to manipulate input parameters to execute malicious commands, leading to a complete system compromise.\n    cwe: CWE-78\n    function_names:\n      - HostsModule.action\n      - HostsModule.control_state\n      - HostsModule.pre_remove\n      - HostsModule.post_update\n    filenames:\n      - roles/ovirt-cluster-upgrade/library/ovirt_hosts_internal_24.py\n    classification: very promising\n```",
      "date": "2024-06-13T10:57:25.081883",
      "usage": {
        "prompt_tokens": 33666,
        "completion_tokens": 1028,
        "cost": 0.18375
      }
    }
  ],
  "leads": [
    {
      "headline": "Inadequate validation of input parameters in bash scripts",
      "analysis": "The bash scripts automation/build-artifacts.sh, automation/check-merged.sh, and automation/check-patch.sh use user input without proper validation. This can lead to several types of security vulnerabilities like injection attacks, where an attacker can manipulate the input parameters to execute arbitrary commands, affecting the system's integrity and availability.\n",
      "classification": "very promising",
      "cwe": "CWE-20",
      "function_names": [],
      "filenames": [
        "automation/build-artifacts.sh",
        "automation/check-merged.sh",
        "automation/check-patch.sh"
      ]
    },
    {
      "headline": "Improper Handling of Errors in Python Scripts",
      "analysis": "The Python scripts (e.g., roles/ovirt-cluster-upgrade/library/ovirt_api_facts_internal_25.py and others) handle exceptions using broad except Exception as e clauses. This can mask underlying errors and make it hard to diagnose issues, allowing potential security vulnerabilities to go unnoticed. More specific exception handling and proper logging should be implemented.\n",
      "classification": "slightly promising",
      "cwe": "CWE-755",
      "function_names": [
        "main"
      ],
      "filenames": [
        "roles/ovirt-cluster-upgrade/library/ovirt_api_facts_internal_25.py",
        "roles/ovirt-cluster-upgrade/library/ovirt_clusters_internal_24.py",
        "roles/ovirt-cluster-upgrade/library/ovirt_scheduling_policies_facts_internal_24.py"
      ]
    },
    {
      "headline": "Hard-coded Authentication Credentials",
      "analysis": "The script roles/ovirt-cluster-upgrade/library/ovirt_hosts_internal_24.py uses predefined default usernames and passwords. Hard-coded credentials pose a severe security risk as they can easily be extracted, leading to unauthorized access to the system.\n",
      "classification": "very promising",
      "cwe": "CWE-798",
      "function_names": [
        "HostsModule.build_entity"
      ],
      "filenames": [
        "roles/ovirt-cluster-upgrade/library/ovirt_hosts_internal_24.py"
      ]
    },
    {
      "headline": "Insufficient Input Sanitization in Ansible modules",
      "analysis": "The various Ansible modules defined in the scripts (e.g., roles/ovirt-cluster-upgrade/library/ovirt_api_facts_internal_25.py, roles/ovirt-cluster-upgrade/library/ovirt_hosts_internal_24.py) do not sufficiently sanitize input parameters. This could lead to injection vulnerabilities which allow an attacker to manipulate input data to execute arbitrary commands.\n",
      "classification": "very promising",
      "cwe": "CWE-74",
      "function_names": [
        "main"
      ],
      "filenames": [
        "roles/ovirt-cluster-upgrade/library/ovirt_api_facts_internal_25.py",
        "roles/ovirt-cluster-upgrade/library/ovirt_hosts_internal_24.py",
        "roles/ovirt-cluster-upgrade/library/ovirt_clusters_internal_24.py"
      ]
    },
    {
      "headline": "Exposure of Sensitive Information through Exception Messages",
      "analysis": "The exception handling in scripts such as roles/ovirt-cluster-upgrade/library/ovirt_api_facts_internal_25.py use module.fail_json(msg=str(e), exception=traceback.format_exc()), which can reveal sensitive information about the environment and runtime configuration. This exposed information can be exploited by an attacker to learn more about the system.\n",
      "classification": "slightly promising",
      "cwe": "CWE-209",
      "function_names": [
        "main"
      ],
      "filenames": [
        "roles/ovirt-cluster-upgrade/library/ovirt_api_facts_internal_25.py",
        "roles/ovirt-cluster-upgrade/library/ovirt_hosts_internal_24.py",
        "roles/ovirt-cluster-upgrade/library/ovirt_clusters_internal_24.py"
      ]
    },
    {
      "headline": "Potential Command Injection via Shell Invocation in Python Scripts",
      "analysis": "In the roles/ovirt-cluster-upgrade/library/ovirt_hosts_internal_24.py module, functions that invoke shell commands do not sanitize the input thoroughly. This could allow an attacker to manipulate input parameters to execute malicious commands, leading to a complete system compromise.\n",
      "classification": "very promising",
      "cwe": "CWE-78",
      "function_names": [
        "HostsModule.action",
        "HostsModule.control_state",
        "HostsModule.pre_remove"
      ],
      "filenames": [
        "roles/ovirt-cluster-upgrade/library/ovirt_hosts_internal_24.py"
      ]
    }
  ],
  "scores": [
    {
      "stats": {
        "fn": 1,
        "tp": 0,
        "fp": 4
      },
      "mapping": {},
      "vuln_dates": {
        "CVE-2018-1117": "2018-06-20T01:29:02"
      },
      "scoring_model": "claude-3-opus-20240229",
      "type": "llm",
      "instruction_template_hash": "245ace12b6361954d0a2"
    },
    {
      "stats": {
        "fn": 1,
        "tp": 0,
        "fp": 4
      },
      "mapping": {},
      "vuln_dates": {
        "CVE-2018-1117": "2018-06-20T01:29:02"
      },
      "scoring_model": "claude-3-5-sonnet-20240620",
      "type": "llm",
      "instruction_template_hash": "245ace12b6361954d0a2"
    }
  ],
  "instruction_template_hash": "10c0163db4740318a544",
  "version": "0.1.0"
}
