{
  "commit": "24b3fd3309d1057dd87af3a568def0db01dbaade",
  "repo_url": "https://github.com/validatorjs/validator.js",
  "model": "claude-3-opus-20240229",
  "chunk_hashes": [
    "7fbab1fa9eef83356392"
  ],
  "responses": [
    {
      "content": "Here are the potential security vulnerabilities I identified in the provided codebase:\n\n```yaml\nleads:\n  - headline: Possible code injection in rtrim function\n    analysis: |\n      The rtrim function uses a regular expression that is constructed from user input (the chars parameter). \n      If chars contains special regex characters like '(', '[', etc., it could allow an attacker to inject arbitrary regular expressions.\n      This could potentially be abused for regex denial of service attacks.\n    cwe: CWE-94\n    function_names:\n      - rtrim\n    filenames:\n      - src/lib/rtrim.js  \n    classification: slightly promising\n\n  - headline: Possible code injection in whitelist function\n    analysis: |\n      Similar to rtrim, the whitelist function constructs a regular expression from the user-provided chars parameter.\n      Special characters in chars could allow an attacker to inject arbitrary regular expressions. \n    cwe: CWE-94 \n    function_names:\n      - whitelist\n    filenames:\n      - src/lib/whitelist.js\n    classification: slightly promising\n\n  - headline: Uncontrolled resource consumption in isCreditCard \n    analysis: |\n      The isCreditCard function performs Luhn checksum validation by iterating over the entire credit card number string.\n      For very large inputs, this could lead to excessive CPU consumption. However, credit card numbers are relatively short,\n      so the risk is low.\n    cwe: CWE-400\n    function_names:\n      - isCreditCard\n    filenames:\n      - src/lib/isCreditCard.js\n    classification: not promising\n  \n  - headline: Lack of input validation could lead to uncontrolled resource consumption\n    analysis: |\n      Many of the validator functions iterate over the entire input string without checking its length first.\n      If an attacker provides very long strings, it could potentially lead to uncontrolled CPU consumption.\n      However, most of these operate on a single string at a time, limiting the potential impact.\n    cwe: CWE-400 \n    function_names:\n      - isEmail\n      - isAlpha\n      - isAlphanumeric\n      - isNumeric\n    filenames:\n      - src/lib/isEmail.js\n      - src/lib/isAlpha.js\n      - src/lib/isAlphanumeric.js  \n      - src/lib/isNumeric.js\n    classification: not promising\n\n```",
      "date": "2024-06-13T17:26:27.115993",
      "usage": {
        "prompt_tokens": 77454,
        "completion_tokens": 580,
        "cost": 1.20531
      }
    }
  ],
  "leads": [
    {
      "headline": "Possible code injection in rtrim function",
      "analysis": "The rtrim function uses a regular expression that is constructed from user input (the chars parameter). \nIf chars contains special regex characters like '(', '[', etc., it could allow an attacker to inject arbitrary regular expressions.\nThis could potentially be abused for regex denial of service attacks.\n",
      "classification": "slightly promising",
      "cwe": "CWE-94",
      "function_names": [
        "rtrim"
      ],
      "filenames": [
        "src/lib/rtrim.js"
      ]
    },
    {
      "headline": "Possible code injection in whitelist function",
      "analysis": "Similar to rtrim, the whitelist function constructs a regular expression from the user-provided chars parameter.\nSpecial characters in chars could allow an attacker to inject arbitrary regular expressions. \n",
      "classification": "slightly promising",
      "cwe": "CWE-94",
      "function_names": [
        "whitelist"
      ],
      "filenames": [
        "src/lib/whitelist.js"
      ]
    },
    {
      "headline": "Uncontrolled resource consumption in isCreditCard",
      "analysis": "The isCreditCard function performs Luhn checksum validation by iterating over the entire credit card number string.\nFor very large inputs, this could lead to excessive CPU consumption. However, credit card numbers are relatively short,\nso the risk is low.\n",
      "classification": "not promising",
      "cwe": "CWE-400",
      "function_names": [
        "isCreditCard"
      ],
      "filenames": [
        "src/lib/isCreditCard.js"
      ]
    },
    {
      "headline": "Lack of input validation could lead to uncontrolled resource consumption",
      "analysis": "Many of the validator functions iterate over the entire input string without checking its length first.\nIf an attacker provides very long strings, it could potentially lead to uncontrolled CPU consumption.\nHowever, most of these operate on a single string at a time, limiting the potential impact.\n",
      "classification": "not promising",
      "cwe": "CWE-400",
      "function_names": [
        "isEmail",
        "isAlpha",
        "isAlphanumeric"
      ],
      "filenames": [
        "src/lib/isEmail.js",
        "src/lib/isAlpha.js",
        "src/lib/isAlphanumeric.js"
      ]
    }
  ],
  "scores": [
    {
      "stats": {
        "fn": 1,
        "tp": 0,
        "fp": 0
      },
      "mapping": {},
      "vuln_dates": {
        "CVE-2021-3765": "2021-11-02T07:15:07"
      },
      "scoring_model": "claude-3-opus-20240229",
      "type": "llm",
      "instruction_template_hash": "245ace12b6361954d0a2"
    }
  ],
  "instruction_template_hash": "10c0163db4740318a544",
  "version": "0.1.0"
}
