{
  "commit": "3f5082e6319faaafc1ee60aa8b115be90696d6be",
  "repo_url": "https://github.com/curiosity-org/gipsy",
  "model": "claude-3-opus-20240229",
  "chunk_hashes": [
    "7760f4ccec12c2c8c1b6"
  ],
  "responses": [
    {
      "content": "Here are the security vulnerabilities I identified in the provided codebase:\n\n```yaml\nleads:\n  - headline: Arbitrary code execution in eval command\n    analysis: |\n      The _eval command in the Admin cog (plugins/admin/bot/main.py) allows a user with the \"bot_admin\" permission to execute arbitrary Python code. \n      This is very dangerous as it gives full control of the bot and server to those admins. The command tries to restrict access with the is_bot_admin check, but any compromise of an admin account could allow an attacker to exploit this to gain full control.\n    cwe: CWE-94\n    function_names:\n      - _eval\n    filenames:\n      - plugins/admin/bot/main.py\n    classification: very promising\n  \n  - headline: Potential XSS in web based commands \n    analysis: |\n      Several commands like rss_web and request_web in the Rss cog (plugins/rss/bot/main.py) allow fetching and displaying of arbitrary web pages and RSS feeds.\n      If the fetched page contains malicious JavaScript, it could potentially execute in the context of Discord users when the page content is sent to channels. \n      The risk depends on how the page content is sanitized and rendered by Discord.\n    cwe: CWE-79\n    function_names:\n      - rss_web\n      - request_web \n    filenames:\n      - plugins/rss/bot/main.py\n    classification: slightly promising\n\n  - headline: Lack of access control on config options\n    analysis: |\n      The Sconfig cog (bot/utils/sconfig.py) handles loading and saving of server specific configuration options. \n      However, there doesn't seem to be any granular access control on who can modify which options. Any user with the \"manage_guild\" permission can change any of the options.\n      Some options control powerful features like logging channel, Modlog events, etc. and should have tighter access control.\n    cwe: CWE-732\n    filenames:\n      - bot/utils/sconfig.py \n    classification: slightly promising\n\n  - headline: Missing Discord permissions check\n    analysis: |   \n      In a few places, the bot tries to execute moderative actions like kicking, banning, and adding/removing roles without first checking if it has the required Discord permissions.\n      For example, the mod_warn function (plugins/moderation/bot/main.py) DMs a user without checking permissions. \n      If the bot lacks DM permissions, this will crash with an Forbidden exception. Similar issues exist in a few other mod functions, and the on_member_join handler in plugins/welcome/bot/main.py.\n    cwe: CWE-285\n    function_names:\n      - mod_warn\n      - give_remove_roles\n    filenames:\n      - plugins/moderation/bot/main.py\n      - plugins/welcome/bot/main.py\n    classification: slightly promising\n```\n\nSome lower severity issues that I noticed but didn't include above:\n\n- The config files use string interpolation with user input when loading JSON, which could allow code injection if a user can control the config file. However this requires an attacker to already have write access to the bot's files.\n\n- The role rewards feature allows any user with \"manage_guild\" permissions to add/remove roles, which could be abused. Roles with sensitive permissions should be restricted.\n\n- Several functions build SQL queries using string interpolation instead of parameterization, potentially allowing SQL injection if user input ever gets mixed into the SQL. However, it looks like only bot/user IDs are currently interpolated.\n\nLet me know if you have any other questions! I'm happy to clarify or expand on any of the points above.",
      "date": "2024-06-14T13:10:57.156787",
      "usage": {
        "prompt_tokens": 131174,
        "completion_tokens": 868,
        "cost": 2.03271
      }
    }
  ],
  "leads": [
    {
      "headline": "Arbitrary code execution in eval command",
      "analysis": "The _eval command in the Admin cog (plugins/admin/bot/main.py) allows a user with the \"bot_admin\" permission to execute arbitrary Python code. \nThis is very dangerous as it gives full control of the bot and server to those admins. The command tries to restrict access with the is_bot_admin check, but any compromise of an admin account could allow an attacker to exploit this to gain full control.\n",
      "classification": "very promising",
      "cwe": "CWE-94",
      "function_names": [
        "_eval"
      ],
      "filenames": [
        "plugins/admin/bot/main.py"
      ]
    },
    {
      "headline": "Potential XSS in web based commands",
      "analysis": "Several commands like rss_web and request_web in the Rss cog (plugins/rss/bot/main.py) allow fetching and displaying of arbitrary web pages and RSS feeds.\nIf the fetched page contains malicious JavaScript, it could potentially execute in the context of Discord users when the page content is sent to channels. \nThe risk depends on how the page content is sanitized and rendered by Discord.\n",
      "classification": "slightly promising",
      "cwe": "CWE-79",
      "function_names": [
        "rss_web",
        "request_web"
      ],
      "filenames": [
        "plugins/rss/bot/main.py"
      ]
    },
    {
      "headline": "Lack of access control on config options",
      "analysis": "The Sconfig cog (bot/utils/sconfig.py) handles loading and saving of server specific configuration options. \nHowever, there doesn't seem to be any granular access control on who can modify which options. Any user with the \"manage_guild\" permission can change any of the options.\nSome options control powerful features like logging channel, Modlog events, etc. and should have tighter access control.\n",
      "classification": "slightly promising",
      "cwe": "CWE-732",
      "function_names": [],
      "filenames": [
        "bot/utils/sconfig.py"
      ]
    },
    {
      "headline": "Missing Discord permissions check",
      "analysis": "In a few places, the bot tries to execute moderative actions like kicking, banning, and adding/removing roles without first checking if it has the required Discord permissions.\nFor example, the mod_warn function (plugins/moderation/bot/main.py) DMs a user without checking permissions. \nIf the bot lacks DM permissions, this will crash with an Forbidden exception. Similar issues exist in a few other mod functions, and the on_member_join handler in plugins/welcome/bot/main.py.\n",
      "classification": "slightly promising",
      "cwe": "CWE-285",
      "function_names": [
        "mod_warn",
        "give_remove_roles"
      ],
      "filenames": [
        "plugins/moderation/bot/main.py",
        "plugins/welcome/bot/main.py"
      ]
    }
  ],
  "scores": [
    {
      "stats": {
        "fn": 1,
        "tp": 0,
        "fp": 1
      },
      "mapping": {},
      "vuln_dates": {
        "CVE-2023-30621": "2023-04-21T21:15:08"
      },
      "scoring_model": "claude-3-opus-20240229",
      "type": "llm",
      "instruction_template_hash": "245ace12b6361954d0a2"
    }
  ],
  "instruction_template_hash": "10c0163db4740318a544",
  "version": "0.1.0"
}
