{
  "commit": "26703f4dd9798a493149b5a45517afc7bde6eb1c",
  "repo_url": "https://github.com/mansuf/mangadex-downloader",
  "model": "gpt-4o-2024-05-13",
  "chunk_hashes": [
    "7ca2164ca97959219b37"
  ],
  "responses": [
    {
      "content": "```yaml\nleads:\n  - headline: \"Command Injection in compile.py\"\n    analysis: |\n      The script compile.py uses the `subprocess.run` function to execute the `pyinstaller` command, including user-provided input in the `output_one_folder` variable without proper sanitization. This can be exploited to execute arbitrary commands on the system.\n    cwe: CWE-77\n    function_names:\n      - run\n    filenames:\n      - compile.py\n    classification: very promising\n\n  - headline: \"Uncontrolled Resource Consumption in network.py\"\n    analysis: |\n      The `ModifiedSession` class in network.py allows setting a throttle delay based on headers from the server. This could potentially be used by an attacker to cause Denial of Service (DoS) by flooding the server with requests that create resource contention.\n    cwe: CWE-400\n    function_names:\n      - _request\n    filenames:\n      - mangadex_downloader/network.py\n    classification: slightly promising\n\n  - headline: \"Session Fixation Vulnerability in network.py\"\n    analysis: |\n      The `requestsMangaDexSession` class in network.py caches session tokens without proper validation of their integrity, allowing potential session fixation attacks where an attacker could gain unauthorized access using a fixed session identifier.\n    cwe: CWE-384\n    function_names:\n      - login_from_cache\n    filenames:\n      - mangadex_downloader/network.py\n    classification: very promising\n\n  - headline: \"Untrusted Input in Config Loading\"\n    analysis: |\n      The config.py reads local configuration files and the base_path can be influenced by an environment variable (`MANGADEXDL_CONFIG_PATH`). Unsanitized values from these environment variables could be exploited to read arbitrary files.\n    cwe: CWE-20\n    function_names:\n      - _Config.__init__\n    filenames:\n      - mangadex_downloader/config.py\n    classification: slightly promising\n\n  - headline: \"Insecure Temporary File Handling\"\n    analysis: |\n      The `update.py` script uses temporary files for downloading updates without ensuring they are created in a secure manner. This may open up opportunities for symlink attacks, where an attacker could replace the temporary file with a symlink to another sensitive file.\n    cwe: CWE-377\n    function_names:\n      - update_app\n    filenames:\n      - mangadex_downloader/update.py\n    classification: very promising\n\n  - headline: \"CSRF Vulnerability in exchange.py\"\n    analysis: |\n      The exchange endpoints do not protect against CSRF attacks. An adversary could trick an authenticated user into making unintended requests to the server, leveraging their authentication state.\n    cwe: CWE-352\n    function_names:\n      - all functions related to exchange endpoints\n    filenames:\n      - mangadex_downloader/exchange.py\n    classification: slightly promising\n```",
      "date": "2024-06-13T09:57:51.380803",
      "usage": {
        "prompt_tokens": 66786,
        "completion_tokens": 593,
        "cost": 0.342825
      }
    }
  ],
  "leads": [
    {
      "headline": "Command Injection in compile.py",
      "analysis": "The script compile.py uses the subprocess.run function to execute the pyinstaller command, including user-provided input in the output_one_folder variable without proper sanitization. This can be exploited to execute arbitrary commands on the system.\n",
      "classification": "very promising",
      "cwe": "CWE-77",
      "function_names": [
        "run"
      ],
      "filenames": [
        "compile.py"
      ]
    },
    {
      "headline": "Uncontrolled Resource Consumption in network.py",
      "analysis": "The ModifiedSession class in network.py allows setting a throttle delay based on headers from the server. This could potentially be used by an attacker to cause Denial of Service (DoS) by flooding the server with requests that create resource contention.\n",
      "classification": "slightly promising",
      "cwe": "CWE-400",
      "function_names": [
        "_request"
      ],
      "filenames": [
        "mangadex_downloader/network.py"
      ]
    },
    {
      "headline": "Session Fixation Vulnerability in network.py",
      "analysis": "The requestsMangaDexSession class in network.py caches session tokens without proper validation of their integrity, allowing potential session fixation attacks where an attacker could gain unauthorized access using a fixed session identifier.\n",
      "classification": "very promising",
      "cwe": "CWE-384",
      "function_names": [
        "login_from_cache"
      ],
      "filenames": [
        "mangadex_downloader/network.py"
      ]
    },
    {
      "headline": "Untrusted Input in Config Loading",
      "analysis": "The config.py reads local configuration files and the base_path can be influenced by an environment variable (MANGADEXDL_CONFIG_PATH). Unsanitized values from these environment variables could be exploited to read arbitrary files.\n",
      "classification": "slightly promising",
      "cwe": "CWE-20",
      "function_names": [
        "_Config.__init__"
      ],
      "filenames": [
        "mangadex_downloader/config.py"
      ]
    },
    {
      "headline": "Insecure Temporary File Handling",
      "analysis": "The update.py script uses temporary files for downloading updates without ensuring they are created in a secure manner. This may open up opportunities for symlink attacks, where an attacker could replace the temporary file with a symlink to another sensitive file.\n",
      "classification": "very promising",
      "cwe": "CWE-377",
      "function_names": [
        "update_app"
      ],
      "filenames": [
        "mangadex_downloader/update.py"
      ]
    },
    {
      "headline": "CSRF Vulnerability in exchange.py",
      "analysis": "The exchange endpoints do not protect against CSRF attacks. An adversary could trick an authenticated user into making unintended requests to the server, leveraging their authentication state.\n",
      "classification": "slightly promising",
      "cwe": "CWE-352",
      "function_names": [
        "all functions related to exchange endpoints"
      ],
      "filenames": [
        "mangadex_downloader/exchange.py"
      ]
    }
  ],
  "scores": [
    {
      "stats": {
        "fn": 1,
        "tp": 0,
        "fp": 3
      },
      "mapping": {},
      "vuln_dates": {
        "CVE-2022-36082": "2022-09-07T22:15:08"
      },
      "scoring_model": "claude-3-opus-20240229",
      "type": "llm",
      "instruction_template_hash": "245ace12b6361954d0a2"
    },
    {
      "stats": {
        "fn": 1,
        "tp": 0,
        "fp": 3
      },
      "mapping": {},
      "vuln_dates": {
        "CVE-2022-36082": "2022-09-07T22:15:08"
      },
      "scoring_model": "claude-3-5-sonnet-20240620",
      "type": "llm",
      "instruction_template_hash": "245ace12b6361954d0a2"
    }
  ],
  "instruction_template_hash": "10c0163db4740318a544",
  "version": "0.1.0"
}
