{
  "commit": "16b0f7cde604550f10d4c3c0c61f2653be3c2a0a",
  "repo_url": "https://github.com/archivy/archivy",
  "model": "claude-3-opus-20240229",
  "chunk_hashes": [
    "78d31df9c8d12825cabd"
  ],
  "responses": [
    {
      "content": "Here are the potential security vulnerabilities I found in the provided codebase:\n\n```yaml\nleads:\n  - headline: Potential XSS in dataobj parsing\n    analysis: |\n      The templates/dataobjs/show.html file renders dataobj content directly without escaping it first.\n      This could allow an attacker to inject malicious scripts if they can control the dataobj content.\n      For example, adding a dataobj with <script>alert(1)</script> would execute that JavaScript when viewing the dataobj page.\n    cwe: CWE-79\n    function_names:\n      - show_dataobj\n    filenames:\n      - archivy/routes.py\n      - archivy/templates/dataobjs/show.html  \n    classification: very promising\n\n  - headline: Potential XSS in search results\n    analysis: |\n      The search results in templates/home.html and templates/tags/show.html render matches directly from\n      the search index without escaping them first. If an attacker can inject scripts into dataobj content,\n      those could get indexed by the search engine and then executed when viewing search results.\n    cwe: CWE-79  \n    function_names:\n      - index\n      - show_tag\n    filenames:\n      - archivy/routes.py\n      - archivy/templates/home.html\n      - archivy/templates/tags/show.html\n    classification: very promising\n\n  - headline: Potential command injection in click_web\n    analysis: |\n      The archivy/click_web/resources/cmd_exec.py module executes archivy CLI commands based on \n      user supplied form data. It attempts to omit certain sensitive commands, but the check is \n      incomplete (e.g. doesn't prevent \"shell\" with arguments). A malicious user may be able to \n      execute arbitrary commands on the server by crafting the form parameters.\n    cwe: CWE-78\n    function_names:\n      - exec\n    filenames:\n      - archivy/click_web/resources/cmd_exec.py  \n    classification: very promising\n\n  - headline: Potential arbitrary file write via images\n    analysis: |\n      The save_image function in data.py saves user uploaded images to the configured images directory.\n      The filename is derived from the uploaded filename. An attacker could potentially overwrite sensitive \n      files by uploading an image with a crafted filename containing path traversals (../).\n      The allowed extensions check doesn't fully sanitize filenames.\n    cwe: CWE-22 \n    function_names:\n      - save_image\n    filenames: \n      - archivy/data.py\n    classification: slightly promising\n\n  - headline: Potential redirect via bookmarklet feature\n    analysis: |\n      The bookmarklet page allows redirecting to a user-supplied URL via window.location in JavaScript.\n      An attacker may be able to abuse this to redirect users to malicious sites, though the impact is limited\n      since it requires the user to drag the malicious bookmarklet to their bookmarks bar first.\n    cwe: CWE-601\n    filenames:\n      - archivy/templates/bookmarklet.html\n    function_names: []  \n    classification: slightly promising\n```\n\nIn summary:\n- There are multiple potential XSS issues from rendering user-controlled dataobj content without escaping\n- The click_web feature executes user-supplied commands and has an insufficient allowlist \n- User-uploaded images are saved with filenames that are not fully sanitized and could allow path traversal\n- The bookmarklet page does an open redirect, though exploitability is limited\n\nThe first three, especially the XSS and command injection, would be the most critical to investigate and fix.\nAdditional manual testing and review of how user data flows through the system would help identify the full scope.\nAdding strong input validation and contextual output encoding are important remediation steps.\n\nLet me know if you need any clarification or have additional questions! I'm happy to discuss potential mitigations in more detail.",
      "date": "2024-06-12T14:54:10.626507",
      "usage": {
        "prompt_tokens": 176550,
        "completion_tokens": 940,
        "cost": 2.71875
      }
    }
  ],
  "leads": [
    {
      "headline": "Potential XSS in dataobj parsing",
      "analysis": "The templates/dataobjs/show.html file renders dataobj content directly without escaping it first.\nThis could allow an attacker to inject malicious scripts if they can control the dataobj content.\nFor example, adding a dataobj with <script>alert(1)</script> would execute that JavaScript when viewing the dataobj page.\n",
      "classification": "very promising",
      "cwe": "CWE-79",
      "function_names": [
        "show_dataobj"
      ],
      "filenames": [
        "archivy/routes.py",
        "archivy/templates/dataobjs/show.html"
      ]
    },
    {
      "headline": "Potential XSS in search results",
      "analysis": "The search results in templates/home.html and templates/tags/show.html render matches directly from\nthe search index without escaping them first. If an attacker can inject scripts into dataobj content,\nthose could get indexed by the search engine and then executed when viewing search results.\n",
      "classification": "very promising",
      "cwe": "CWE-79",
      "function_names": [
        "index",
        "show_tag"
      ],
      "filenames": [
        "archivy/routes.py",
        "archivy/templates/home.html",
        "archivy/templates/tags/show.html"
      ]
    },
    {
      "headline": "Potential command injection in click_web",
      "analysis": "The archivy/click_web/resources/cmd_exec.py module executes archivy CLI commands based on \nuser supplied form data. It attempts to omit certain sensitive commands, but the check is \nincomplete (e.g. doesn't prevent \"shell\" with arguments). A malicious user may be able to \nexecute arbitrary commands on the server by crafting the form parameters.\n",
      "classification": "very promising",
      "cwe": "CWE-78",
      "function_names": [
        "exec"
      ],
      "filenames": [
        "archivy/click_web/resources/cmd_exec.py"
      ]
    },
    {
      "headline": "Potential arbitrary file write via images",
      "analysis": "The save_image function in data.py saves user uploaded images to the configured images directory.\nThe filename is derived from the uploaded filename. An attacker could potentially overwrite sensitive \nfiles by uploading an image with a crafted filename containing path traversals (../).\nThe allowed extensions check doesn't fully sanitize filenames.\n",
      "classification": "slightly promising",
      "cwe": "CWE-22",
      "function_names": [
        "save_image"
      ],
      "filenames": [
        "archivy/data.py"
      ]
    },
    {
      "headline": "Potential redirect via bookmarklet feature",
      "analysis": "The bookmarklet page allows redirecting to a user-supplied URL via window.location in JavaScript.\nAn attacker may be able to abuse this to redirect users to malicious sites, though the impact is limited\nsince it requires the user to drag the malicious bookmarklet to their bookmarks bar first.\n",
      "classification": "slightly promising",
      "cwe": "CWE-601",
      "function_names": [],
      "filenames": [
        "archivy/templates/bookmarklet.html"
      ]
    }
  ],
  "scores": [
    {
      "stats": {
        "fn": 2,
        "tp": 0,
        "fp": 3
      },
      "mapping": {},
      "vuln_dates": {
        "CVE-2022-0697": "2022-03-06T23:15:09",
        "CVE-2021-4162": "2021-12-25T12:15:17"
      },
      "scoring_model": "claude-3-opus-20240229",
      "type": "llm",
      "instruction_template_hash": "245ace12b6361954d0a2"
    }
  ],
  "instruction_template_hash": "10c0163db4740318a544",
  "version": "0.1.0"
}
