{
  "commit": "2006f3e1a71645886d1bd2eeb1d39f9c19f6fe33",
  "repo_url": "https://github.com/getgridea/gridea",
  "model": "claude-3-5-sonnet-20240620",
  "chunk_hashes": [
    "136cfa74e16543c79b15"
  ],
  "responses": [
    {
      "content": "```yaml\nleads:\n  - headline: Potential command injection vulnerability in renderer.ts\n    analysis: |\n      The renderer.ts file contains code that executes git commands using user-supplied input. Specifically, the remoteUrl variable is constructed using user-provided values for username, token, and repository. This remoteUrl is then passed directly to git commands like git.addRemote() and git.raw(). If an attacker can control any of those input values, they may be able to inject arbitrary commands that will be executed on the system. For example, they could potentially inject shell metacharacters to execute additional commands.\n    cwe: CWE-78\n    function_names:\n      - remoteDetect\n      - firstPush  \n    filenames:\n      - src/server/renderer.ts\n    classification: very promising\n\n  - headline: Potential path traversal vulnerability in posts.ts\n    analysis: |\n      The posts.ts file contains code that writes files using user-supplied filenames. Specifically, the savePostToFile() method writes markdown files to disk using the post.fileName value in the path. If an attacker can control the fileName, they may be able to write files to arbitrary locations on the filesystem by using path traversal sequences like \"../\". This could potentially allow overwriting critical files or adding malicious files to sensitive locations.\n    cwe: CWE-22\n    function_names: \n      - savePostToFile\n    filenames:\n      - src/server/posts.ts  \n    classification: very promising\n\n  - headline: Insecure use of eval() in theme style override\n    analysis: |\n      The style-override.js files for multiple themes contain code that generates CSS by concatenating strings, including user-supplied values. This generated CSS string is then likely eval()'d or injected into the page in some way to apply the styles. If an attacker can control any of the style parameters, they may be able to inject malicious JavaScript that would be executed in the context of the application. This could lead to XSS or other client-side attacks.\n    cwe: CWE-95\n    function_names:\n      - generateOverride\n    filenames:\n      - public/default-files/themes/notes/style-override.js\n      - public/default-files/themes/paper/style-override.js\n      - public/default-files/themes/simple/style-override.js\n      - public/default-files/themes/fly/style-override.js\n    classification: very promising\n\n  - headline: Potential XSS vulnerability in post rendering\n    analysis: |\n      The renderer.ts file contains code that renders user-supplied markdown content into HTML. This rendered HTML is then inserted into the page template. If the markdown rendering is not properly sanitizing the input, an attacker may be able to inject malicious HTML or JavaScript into the rendered page, leading to XSS attacks. The specific markdown rendering library and configuration should be carefully audited to ensure proper sanitization is in place.\n    cwe: CWE-79\n    function_names:\n      - renderPostDetail\n    filenames: \n      - src/server/renderer.ts\n    classification: slightly promising\n\n  - headline: Potential information disclosure in error handling\n    analysis: |\n      The app.ts file contains error handling code that may expose sensitive information. Specifically, in the catch block of the checkDir method, the full error object is logged to the console. Depending on the nature of the error, this could potentially expose filesystem paths, API keys, or other sensitive data in error messages or stack traces. In a production environment, errors should be carefully sanitized before logging or exposing to users.\n    cwe: CWE-209\n    function_names:\n      - checkDir\n    filenames:\n      - src/server/app.ts\n    classification: slightly promising\n```",
      "date": "2024-07-08T06:23:01.787646",
      "usage": {
        "prompt_tokens": 31283,
        "completion_tokens": 874,
        "cost": 0.106959
      }
    }
  ],
  "leads": [
    {
      "headline": "Potential command injection vulnerability in renderer.ts",
      "analysis": "The renderer.ts file contains code that executes git commands using user-supplied input. Specifically, the remoteUrl variable is constructed using user-provided values for username, token, and repository. This remoteUrl is then passed directly to git commands like git.addRemote() and git.raw(). If an attacker can control any of those input values, they may be able to inject arbitrary commands that will be executed on the system. For example, they could potentially inject shell metacharacters to execute additional commands.\n",
      "classification": "very promising",
      "cwe": "CWE-78",
      "function_names": [
        "remoteDetect",
        "firstPush"
      ],
      "filenames": [
        "src/server/renderer.ts"
      ]
    },
    {
      "headline": "Potential path traversal vulnerability in posts.ts",
      "analysis": "The posts.ts file contains code that writes files using user-supplied filenames. Specifically, the savePostToFile() method writes markdown files to disk using the post.fileName value in the path. If an attacker can control the fileName, they may be able to write files to arbitrary locations on the filesystem by using path traversal sequences like \"../\". This could potentially allow overwriting critical files or adding malicious files to sensitive locations.\n",
      "classification": "very promising",
      "cwe": "CWE-22",
      "function_names": [
        "savePostToFile"
      ],
      "filenames": [
        "src/server/posts.ts"
      ]
    },
    {
      "headline": "Insecure use of eval() in theme style override",
      "analysis": "The style-override.js files for multiple themes contain code that generates CSS by concatenating strings, including user-supplied values. This generated CSS string is then likely eval()'d or injected into the page in some way to apply the styles. If an attacker can control any of the style parameters, they may be able to inject malicious JavaScript that would be executed in the context of the application. This could lead to XSS or other client-side attacks.\n",
      "classification": "very promising",
      "cwe": "CWE-95",
      "function_names": [
        "generateOverride"
      ],
      "filenames": [
        "public/default-files/themes/notes/style-override.js",
        "public/default-files/themes/paper/style-override.js",
        "public/default-files/themes/simple/style-override.js"
      ]
    },
    {
      "headline": "Potential XSS vulnerability in post rendering",
      "analysis": "The renderer.ts file contains code that renders user-supplied markdown content into HTML. This rendered HTML is then inserted into the page template. If the markdown rendering is not properly sanitizing the input, an attacker may be able to inject malicious HTML or JavaScript into the rendered page, leading to XSS attacks. The specific markdown rendering library and configuration should be carefully audited to ensure proper sanitization is in place.\n",
      "classification": "slightly promising",
      "cwe": "CWE-79",
      "function_names": [
        "renderPostDetail"
      ],
      "filenames": [
        "src/server/renderer.ts"
      ]
    },
    {
      "headline": "Potential information disclosure in error handling",
      "analysis": "The app.ts file contains error handling code that may expose sensitive information. Specifically, in the catch block of the checkDir method, the full error object is logged to the console. Depending on the nature of the error, this could potentially expose filesystem paths, API keys, or other sensitive data in error messages or stack traces. In a production environment, errors should be carefully sanitized before logging or exposing to users.\n",
      "classification": "slightly promising",
      "cwe": "CWE-209",
      "function_names": [
        "checkDir"
      ],
      "filenames": [
        "src/server/app.ts"
      ]
    }
  ],
  "scores": [
    {
      "stats": {
        "fn": 2,
        "tp": 0,
        "fp": 3
      },
      "mapping": {},
      "vuln_dates": {
        "CVE-2019-12047": "2019-05-13T15:29:03",
        "CVE-2022-40274": "2022-09-30T17:15:13"
      },
      "scoring_model": "claude-3-5-sonnet-20240620",
      "type": "llm",
      "instruction_template_hash": "245ace12b6361954d0a2"
    }
  ],
  "instruction_template_hash": "10c0163db4740318a544",
  "version": "0.1.0"
}
