{
  "commit": "08d9891531457590a5fac8b447863d38aa4f0e3c",
  "repo_url": "https://github.com/jenkinsci/aws-codebuild-plugin",
  "model": "gpt-4o-2024-05-13",
  "chunk_hashes": [
    "80e878d42205ad5b7a72"
  ],
  "responses": [
    {
      "content": "```yaml\nleads:\n  - headline: \"Potential Throttling Issue\"\n    analysis: |\n      The `getClientConfiguration` method in the `AWSClientFactory` class uses a retry policy that retries requests on throttling errors multiple times. However, this might not be effective if the AWS service continues to throttle the requests, potentially leading to poor application performance or hitting service limits.\n    cwe: CWE-770\n    function_names:\n      - getClientConfiguration\n    filenames:\n      - src/main/java/AWSClientFactory.java\n    classification: slightly promising\n\n  - headline: \"Hard-coded/Improper Logging\"\n    analysis: |\n      The `LoggingHelper` class does not provide any log level configuration and directly writes to the console or Jenkins task listener which may expose sensitive information.\n    cwe: CWE-532\n    function_names:\n      - log\n    filenames:\n      - src/main/java/LoggingHelper.java\n    classification: slightly promising\n\n  - headline: \"Improper Bucket Versioning Check\"\n    analysis: |\n      The method `checkBucketIsVersioned` in `Validation` class only checks if the S3 bucket versioning status is explicitly 'ENABLED'. If S3 versioning is in 'Suspended' state, it will not detect this, leading to potential use of unversioned buckets.\n    cwe: CWE-20\n    function_names:\n      - checkBucketIsVersioned\n    filenames:\n      - src/main/java/Validation.java\n    classification: slightly promising\n\n  - headline: \"Lack of Validation for User Inputs\"\n    analysis: |\n      The `AWSClientFactory` constructor takes several parameters including `proxyHost`, `proxyPort` and `region` without adequate validation, which could lead to invalid or harmful inputs being accepted.\n    cwe: CWE-20\n    function_names:\n      - AWSClientFactory (constructor)\n    filenames:\n      - src/main/java/AWSClientFactory.java\n    classification: very promising\n\n  - headline: \"Potential Exposure of Sensitive AWS Credentials\"\n    analysis: |\n      The `CodeBuildCredentials` class stores AWS credentials as strings, and exposes getters for these credentials without any encryption or access control.\n    cwe: CWE-522\n    function_names:\n      - getCredentials\n    filenames:\n      - src/main/java/CodeBuildCredentials.java\n    classification: very promising\n\n  - headline: \"Potential Information Leakage via Exception Messages\"\n    analysis: |\n      Several methods throughout the codebase catch generic `Exception` types and include the exception messages in responses. This might lead to sensitive information being exposed via exception messages.\n    cwe: CWE-209\n    function_names:\n      - perform\n      - pollForLogs\n      - retrieveArtifactAndSourceInfo\n    filenames:\n      - src/main/java/CodeBuilder.java\n      - src/main/java/CloudWatchMonitor.java\n    classification: slightly promising\n\n  - headline: \"Improper Handling of Environment Variables\"\n    analysis: |\n      The `CodeBuilder` class directly uses environment variables without validating or sanitizing them, potentially allowing injection of malicious data or commands.\n    cwe: CWE-20\n    function_names:\n      - getParameterized\n    filenames:\n      - src/main/java/CodeBuilder.java\n    classification: very promising\n\n  - headline: \"Potentially Insecure Random Value Usage\"\n    analysis: |\n      The usage of `ThreadLocalRandom` for generating jitter in sleep times in `getSleepTime` method doesn't provide sufficient randomness for secure operations.\n    cwe: CWE-338\n    function_names:\n      - getSleepTime\n    filenames:\n      - src/main/java/CodeBuilder.java\n    classification: slightly promising\n\n  - headline: \"XML External Entity (XXE) Vulnerability in XML Parsing\"\n    analysis: |\n      The `CloudWatchMonitor` and `S3DataManager` class might be susceptible to XXE attacks if they process XML data without securely configuring XML parsers.\n    cwe: CWE-611\n    function_names:\n      - Some methods appear to interact with XML data indirectly.\n    filenames:\n      - src/main/java/CloudWatchMonitor.java\n      - src/main/java/S3DataManager.java\n    classification: very promising\n```",
      "date": "2024-06-12T17:55:30.307308",
      "usage": {
        "prompt_tokens": 55369,
        "completion_tokens": 872,
        "cost": 0.289925
      }
    }
  ],
  "leads": [
    {
      "headline": "Potential Throttling Issue",
      "analysis": "The getClientConfiguration method in the AWSClientFactory class uses a retry policy that retries requests on throttling errors multiple times. However, this might not be effective if the AWS service continues to throttle the requests, potentially leading to poor application performance or hitting service limits.\n",
      "classification": "slightly promising",
      "cwe": "CWE-770",
      "function_names": [
        "getClientConfiguration"
      ],
      "filenames": [
        "src/main/java/AWSClientFactory.java"
      ]
    },
    {
      "headline": "Hard-coded/Improper Logging",
      "analysis": "The LoggingHelper class does not provide any log level configuration and directly writes to the console or Jenkins task listener which may expose sensitive information.\n",
      "classification": "slightly promising",
      "cwe": "CWE-532",
      "function_names": [
        "log"
      ],
      "filenames": [
        "src/main/java/LoggingHelper.java"
      ]
    },
    {
      "headline": "Improper Bucket Versioning Check",
      "analysis": "The method checkBucketIsVersioned in Validation class only checks if the S3 bucket versioning status is explicitly 'ENABLED'. If S3 versioning is in 'Suspended' state, it will not detect this, leading to potential use of unversioned buckets.\n",
      "classification": "slightly promising",
      "cwe": "CWE-20",
      "function_names": [
        "checkBucketIsVersioned"
      ],
      "filenames": [
        "src/main/java/Validation.java"
      ]
    },
    {
      "headline": "Lack of Validation for User Inputs",
      "analysis": "The AWSClientFactory constructor takes several parameters including proxyHost, proxyPort and region without adequate validation, which could lead to invalid or harmful inputs being accepted.\n",
      "classification": "very promising",
      "cwe": "CWE-20",
      "function_names": [
        "AWSClientFactory (constructor)"
      ],
      "filenames": [
        "src/main/java/AWSClientFactory.java"
      ]
    },
    {
      "headline": "Potential Exposure of Sensitive AWS Credentials",
      "analysis": "The CodeBuildCredentials class stores AWS credentials as strings, and exposes getters for these credentials without any encryption or access control.\n",
      "classification": "very promising",
      "cwe": "CWE-522",
      "function_names": [
        "getCredentials"
      ],
      "filenames": [
        "src/main/java/CodeBuildCredentials.java"
      ]
    },
    {
      "headline": "Potential Information Leakage via Exception Messages",
      "analysis": "Several methods throughout the codebase catch generic Exception types and include the exception messages in responses. This might lead to sensitive information being exposed via exception messages.\n",
      "classification": "slightly promising",
      "cwe": "CWE-209",
      "function_names": [
        "perform",
        "pollForLogs",
        "retrieveArtifactAndSourceInfo"
      ],
      "filenames": [
        "src/main/java/CodeBuilder.java",
        "src/main/java/CloudWatchMonitor.java"
      ]
    },
    {
      "headline": "Improper Handling of Environment Variables",
      "analysis": "The CodeBuilder class directly uses environment variables without validating or sanitizing them, potentially allowing injection of malicious data or commands.\n",
      "classification": "very promising",
      "cwe": "CWE-20",
      "function_names": [
        "getParameterized"
      ],
      "filenames": [
        "src/main/java/CodeBuilder.java"
      ]
    },
    {
      "headline": "Potentially Insecure Random Value Usage",
      "analysis": "The usage of ThreadLocalRandom for generating jitter in sleep times in getSleepTime method doesn't provide sufficient randomness for secure operations.\n",
      "classification": "slightly promising",
      "cwe": "CWE-338",
      "function_names": [
        "getSleepTime"
      ],
      "filenames": [
        "src/main/java/CodeBuilder.java"
      ]
    },
    {
      "headline": "XML External Entity (XXE) Vulnerability in XML Parsing",
      "analysis": "The CloudWatchMonitor and S3DataManager class might be susceptible to XXE attacks if they process XML data without securely configuring XML parsers.\n",
      "classification": "very promising",
      "cwe": "CWE-611",
      "function_names": [
        "Some methods appear to interact with XML data indirectly."
      ],
      "filenames": [
        "src/main/java/CloudWatchMonitor.java",
        "src/main/java/S3DataManager.java"
      ]
    }
  ],
  "scores": [
    {
      "stats": {
        "fn": 1,
        "tp": 0,
        "fp": 4
      },
      "mapping": {},
      "vuln_dates": {
        "CVE-2018-1000404": "2018-07-09T13:29:00"
      },
      "scoring_model": "claude-3-opus-20240229",
      "type": "llm",
      "instruction_template_hash": "245ace12b6361954d0a2"
    }
  ],
  "instruction_template_hash": "10c0163db4740318a544",
  "version": "0.1.0"
}
