{
  "commit": "49c6003f3259be3105995a8034510061c64dff16",
  "repo_url": "https://github.com/starkbank/ecdsa-node",
  "model": "claude-3-5-sonnet-20240620",
  "chunk_hashes": [
    "2d1479fc1b59536285bb"
  ],
  "responses": [
    {
      "content": "```yaml\nleads:\n  - headline: Potential Insecure Random Number Generation\n    analysis: |\n      The random number generation in the secureRandomNumber function relies on the crypto.randomBytes() method. While this is generally considered cryptographically secure, its implementation may vary across different Node.js versions and platforms. There's a potential risk if the underlying random number generator is not truly cryptographically secure on all systems. This could potentially weaken the security of operations that rely on this randomness, such as key generation or signing.\n    cwe: CWE-338\n    function_names:\n      - secureRandomNumber\n    filenames:\n      - ellipticcurve/utils/integer.js\n    classification: slightly promising\n\n  - headline: Possible Integer Overflow in Bit Manipulation\n    analysis: |\n      In the calculateParameters and secureRandomNumber functions, there are several bitwise operations performed on BigInt values. While BigInt helps avoid some integer overflow issues, complex bit manipulations can still potentially lead to unexpected behavior if not carefully implemented. If an overflow occurs, it could potentially be exploited to generate predictable or weak keys/signatures.\n    cwe: CWE-190\n    function_names:\n      - calculateParameters\n      - secureRandomNumber\n    filenames:\n      - ellipticcurve/utils/integer.js\n    classification: slightly promising\n\n  - headline: Potential for Timing Attacks in Modular Arithmetic\n    analysis: |\n      The modulo function implementation may not be constant-time. In cryptographic operations, non-constant time operations can leak information through timing side channels. An attacker could potentially exploit timing differences in the modular arithmetic operations to gain information about secret values used in the ECDSA operations.\n    cwe: CWE-208\n    function_names:\n      - modulo\n    filenames:\n      - ellipticcurve/utils/integer.js\n    classification: slightly promising\n\n  - headline: Lack of Input Validation in fromPem Function\n    analysis: |\n      The fromPem function in der.js does not perform thorough input validation on the PEM-encoded data it receives. It assumes the input is well-formed and does not check for malformed input. This could potentially lead to unexpected behavior or crashes if given maliciously crafted input, though exploitation would likely be limited to denial of service.\n    cwe: CWE-20\n    function_names:\n      - fromPem\n    filenames:\n      - ellipticcurve/utils/der.js\n    classification: slightly promising\n\n  - headline: Potential for Unhandled Exceptions in DER Encoding/Decoding\n    analysis: |\n      Several functions in der.js, such as removeInteger, removeObject, etc., throw errors without proper exception handling. If these errors are not caught and handled properly by the calling code, it could lead to unexpected termination of the program. While not directly exploitable, it could be used as part of a larger attack to cause denial of service.\n    cwe: CWE-755\n    function_names:\n      - removeInteger\n      - removeObject\n      - removeBitString\n      - removeOctetString\n    filenames:\n      - ellipticcurve/utils/der.js\n    classification: slightly promising\n```",
      "date": "2024-07-08T08:44:58.366344",
      "usage": {
        "prompt_tokens": 16662,
        "completion_tokens": 756,
        "cost": 0.061326
      }
    }
  ],
  "leads": [
    {
      "headline": "Potential Insecure Random Number Generation",
      "analysis": "The random number generation in the secureRandomNumber function relies on the crypto.randomBytes() method. While this is generally considered cryptographically secure, its implementation may vary across different Node.js versions and platforms. There's a potential risk if the underlying random number generator is not truly cryptographically secure on all systems. This could potentially weaken the security of operations that rely on this randomness, such as key generation or signing.\n",
      "classification": "slightly promising",
      "cwe": "CWE-338",
      "function_names": [
        "secureRandomNumber"
      ],
      "filenames": [
        "ellipticcurve/utils/integer.js"
      ]
    },
    {
      "headline": "Possible Integer Overflow in Bit Manipulation",
      "analysis": "In the calculateParameters and secureRandomNumber functions, there are several bitwise operations performed on BigInt values. While BigInt helps avoid some integer overflow issues, complex bit manipulations can still potentially lead to unexpected behavior if not carefully implemented. If an overflow occurs, it could potentially be exploited to generate predictable or weak keys/signatures.\n",
      "classification": "slightly promising",
      "cwe": "CWE-190",
      "function_names": [
        "calculateParameters",
        "secureRandomNumber"
      ],
      "filenames": [
        "ellipticcurve/utils/integer.js"
      ]
    },
    {
      "headline": "Potential for Timing Attacks in Modular Arithmetic",
      "analysis": "The modulo function implementation may not be constant-time. In cryptographic operations, non-constant time operations can leak information through timing side channels. An attacker could potentially exploit timing differences in the modular arithmetic operations to gain information about secret values used in the ECDSA operations.\n",
      "classification": "slightly promising",
      "cwe": "CWE-208",
      "function_names": [
        "modulo"
      ],
      "filenames": [
        "ellipticcurve/utils/integer.js"
      ]
    },
    {
      "headline": "Lack of Input Validation in fromPem Function",
      "analysis": "The fromPem function in der.js does not perform thorough input validation on the PEM-encoded data it receives. It assumes the input is well-formed and does not check for malformed input. This could potentially lead to unexpected behavior or crashes if given maliciously crafted input, though exploitation would likely be limited to denial of service.\n",
      "classification": "slightly promising",
      "cwe": "CWE-20",
      "function_names": [
        "fromPem"
      ],
      "filenames": [
        "ellipticcurve/utils/der.js"
      ]
    },
    {
      "headline": "Potential for Unhandled Exceptions in DER Encoding/Decoding",
      "analysis": "Several functions in der.js, such as removeInteger, removeObject, etc., throw errors without proper exception handling. If these errors are not caught and handled properly by the calling code, it could lead to unexpected termination of the program. While not directly exploitable, it could be used as part of a larger attack to cause denial of service.\n",
      "classification": "slightly promising",
      "cwe": "CWE-755",
      "function_names": [
        "removeInteger",
        "removeObject",
        "removeBitString"
      ],
      "filenames": [
        "ellipticcurve/utils/der.js"
      ]
    }
  ],
  "scores": [
    {
      "stats": {
        "fn": 1,
        "tp": 0,
        "fp": 0
      },
      "mapping": {},
      "vuln_dates": {
        "CVE-2021-43571": "2021-11-09T22:15:07"
      },
      "scoring_model": "claude-3-5-sonnet-20240620",
      "type": "llm",
      "instruction_template_hash": "245ace12b6361954d0a2"
    }
  ],
  "instruction_template_hash": "10c0163db4740318a544",
  "version": "0.1.0"
}
