{
  "commit": "154a0a274acc5408442349af8b3f5bb3c3bc3c3e",
  "repo_url": "https://github.com/mubarakalmehairbi/toui",
  "model": "gpt-4o-2024-05-13",
  "chunk_hashes": [
    "fff3d7970702c63b4874"
  ],
  "responses": [
    {
      "content": "```yaml\nleads:\n  - headline: \"Insecure file upload handling\"\n    analysis: |\n      The `upload_file` function in `full_app.py` does not validate file names or handle potential path traversal attacks. Specifically, it uses the `os.path.exists` function with the uploaded file's name directly, which can be exploited to overwrite existing files on the server or write files to unintended directories by including special characters in the filename.\n    cwe: CWE-22\n    function_names:\n      - upload_file\n    filenames:\n      - tests/full_app.py\n    classification: very promising\n\n  - headline: \"Command injection vulnerability\"\n    analysis: |\n      The `DesktopApp` class in `apps.py` runs a Flask server by directly calling `os.system`. This can be exploited if any part of the application's input is used unsanitized in the command, potentially leading to command injection.\n    cwe: CWE-78\n    function_names:\n      - _run_server\n    filenames:\n      - toui/apps.py\n    classification: very promising\n\n  - headline: \"Sensitive data exposed in logs\"\n    analysis: |\n      The `error` function in `_helpers.py` logs the entire traceback, which can include sensitive information such as file paths, user data, or internal APIs, especially if the error originated from a web request or a user action.\n    cwe: CWE-532\n    function_names:\n      - error\n    filenames:\n      - toui/_helpers.py\n    classification: very promising\n\n  - headline: \"Weak encryption configuration\"\n    analysis: |\n      The `__init__` method of both `Website` and `DesktopApp` classes in `apps.py` generates a random secret key using `os.urandom` if none is provided. While it ensures a secret key is set, there's no mechanism to ensure the generated key is appropriately robust, nor does it guide users on securely managing this key.\n    cwe: CWE-330\n    function_names:\n      - __init__\n    filenames:\n      - toui/apps.py\n    classification: slightly promising\n\n  - headline: \"Race condition in file handling\"\n    analysis: |\n      The file upload handling in `full_app.py` opens a file for writing without properly securing access across concurrent uploads. This can lead to race conditions where multiple uploads with the same filename overlap.\n    cwe: CWE-362\n    function_names:\n      - upload_file\n    filenames:\n      - tests/full_app.py\n    classification: slightly promising\n\n  - headline: \"Potential for cross-site scripting (XSS)\"\n    analysis: |\n      The `upload_file` function in `full_app.py` does not sanitize user input when setting the content of elements. This can be exploited to inject scripts into the resulting page, causing cross-site scripting (XSS) attacks.\n    cwe: CWE-79\n    function_names:\n      - upload_file\n    filenames:\n      - tests/full_app.py\n    classification: slightly promising\n  \n  - headline: \"Improper validation of user input\"\n    analysis: |\n      In `signin_user` and `signup_user`, user input for username and password is not properly validated. This can lead to injection attacks (e.g., SQL injection) if these values are used directly in queries or other contexts without sanitization.\n    cwe: CWE-20\n    function_names:\n      - signup_user\n      - signin_user\n    filenames:\n      - toui/apps.py\n    classification: slightly promising\n```",
      "date": "2024-06-13T10:18:27.194789",
      "usage": {
        "prompt_tokens": 29562,
        "completion_tokens": 723,
        "cost": 0.158655
      }
    }
  ],
  "leads": [
    {
      "headline": "Insecure file upload handling",
      "analysis": "The upload_file function in full_app.py does not validate file names or handle potential path traversal attacks. Specifically, it uses the os.path.exists function with the uploaded file's name directly, which can be exploited to overwrite existing files on the server or write files to unintended directories by including special characters in the filename.\n",
      "classification": "very promising",
      "cwe": "CWE-22",
      "function_names": [
        "upload_file"
      ],
      "filenames": [
        "tests/full_app.py"
      ]
    },
    {
      "headline": "Command injection vulnerability",
      "analysis": "The DesktopApp class in apps.py runs a Flask server by directly calling os.system. This can be exploited if any part of the application's input is used unsanitized in the command, potentially leading to command injection.\n",
      "classification": "very promising",
      "cwe": "CWE-78",
      "function_names": [
        "_run_server"
      ],
      "filenames": [
        "toui/apps.py"
      ]
    },
    {
      "headline": "Sensitive data exposed in logs",
      "analysis": "The error function in _helpers.py logs the entire traceback, which can include sensitive information such as file paths, user data, or internal APIs, especially if the error originated from a web request or a user action.\n",
      "classification": "very promising",
      "cwe": "CWE-532",
      "function_names": [
        "error"
      ],
      "filenames": [
        "toui/_helpers.py"
      ]
    },
    {
      "headline": "Weak encryption configuration",
      "analysis": "The __init__ method of both Website and DesktopApp classes in apps.py generates a random secret key using os.urandom if none is provided. While it ensures a secret key is set, there's no mechanism to ensure the generated key is appropriately robust, nor does it guide users on securely managing this key.\n",
      "classification": "slightly promising",
      "cwe": "CWE-330",
      "function_names": [
        "__init__"
      ],
      "filenames": [
        "toui/apps.py"
      ]
    },
    {
      "headline": "Race condition in file handling",
      "analysis": "The file upload handling in full_app.py opens a file for writing without properly securing access across concurrent uploads. This can lead to race conditions where multiple uploads with the same filename overlap.\n",
      "classification": "slightly promising",
      "cwe": "CWE-362",
      "function_names": [
        "upload_file"
      ],
      "filenames": [
        "tests/full_app.py"
      ]
    },
    {
      "headline": "Potential for cross-site scripting (XSS)",
      "analysis": "The upload_file function in full_app.py does not sanitize user input when setting the content of elements. This can be exploited to inject scripts into the resulting page, causing cross-site scripting (XSS) attacks.\n",
      "classification": "slightly promising",
      "cwe": "CWE-79",
      "function_names": [
        "upload_file"
      ],
      "filenames": [
        "tests/full_app.py"
      ]
    },
    {
      "headline": "Improper validation of user input",
      "analysis": "In signin_user and signup_user, user input for username and password is not properly validated. This can lead to injection attacks (e.g., SQL injection) if these values are used directly in queries or other contexts without sanitization.\n",
      "classification": "slightly promising",
      "cwe": "CWE-20",
      "function_names": [
        "signup_user",
        "signin_user"
      ],
      "filenames": [
        "toui/apps.py"
      ]
    }
  ],
  "scores": [
    {
      "stats": {
        "fn": 1,
        "tp": 0,
        "fp": 3
      },
      "mapping": {},
      "vuln_dates": {
        "CVE-2023-33175": "2023-05-30T05:15:11"
      },
      "scoring_model": "claude-3-opus-20240229",
      "type": "llm",
      "instruction_template_hash": "245ace12b6361954d0a2"
    },
    {
      "stats": {
        "fn": 1,
        "tp": 0,
        "fp": 3
      },
      "mapping": {},
      "vuln_dates": {
        "CVE-2023-33175": "2023-05-30T05:15:11"
      },
      "scoring_model": "claude-3-5-sonnet-20240620",
      "type": "llm",
      "instruction_template_hash": "245ace12b6361954d0a2"
    }
  ],
  "instruction_template_hash": "10c0163db4740318a544",
  "version": "0.1.0"
}
