{
  "commit": "493ff934c1ef3f9164f500e2c25da94f9fc6e492",
  "repo_url": "https://github.com/jenkinsci/mongodb-plugin",
  "model": "claude-3-haiku-20240307",
  "chunk_hashes": [
    "e0cc3104d44024e87e4b"
  ],
  "responses": [
    {
      "content": "```yaml\nleads:\n  - headline: Improper Neutralization of Special Elements in Output Used by a Downstream Component ('Injection')\n    analysis: |\n      The codebase contains several instances of improper input validation and neutralization, leading to potential injection vulnerabilities. For example, the `doCheckPort()` and `doCheckStartTimeout()` methods in the `MongoBuildWrapper.DescriptorImpl` class do not properly validate user input, allowing for the injection of arbitrary values. Additionally, the `setupCmd()` method in the `MongoBuildWrapper` class does not properly sanitize the `parameters` input, which could lead to command injection vulnerabilities.\n    cwe: CWE-74\n    function_names:\n      - doCheckPort\n      - doCheckStartTimeout\n      - setupCmd\n    filenames:\n      - src/main/java/org/jenkinsci/plugins/mongodb/MongoBuildWrapper.java\n    classification: slightly promising\n\n  - headline: Improper Restriction of Operations within the Bounds of a Memory Buffer\n    analysis: |\n      The codebase does not appear to have any instances of buffer overflow or out-of-bounds read/write vulnerabilities. The code seems to handle memory management and buffer operations correctly.\n    cwe: CWE-119\n    function_names: []\n    filenames: []\n    classification: not promising\n\n  - headline: Exposure of Sensitive Information to an Unauthorized Actor\n    analysis: |\n      The codebase contains several instances where sensitive information, such as error messages and log entries, may be exposed to unauthorized actors. For example, the `MongoDB_InvalidStartTimeout()` and `MongoDB_InvalidPortNumber()` error messages in the `Messages` class could potentially leak information about the internal workings of the application.\n    cwe: CWE-200\n    function_names:\n      - doCheckStartTimeout\n      - doCheckPort\n    filenames:\n      - src/main/java/org/jenkinsci/plugins/mongodb/MongoBuildWrapper.java\n    classification: slightly promising\n\n  - headline: Improper Privilege Management\n    analysis: |\n      The codebase does not appear to have any instances of improper privilege management. The code does not seem to perform any privileged operations or make use of sensitive system resources.\n    cwe: CWE-269\n    function_names: []\n    filenames: []\n    classification: not promising\n\n  - headline: Incorrect Authorization\n    analysis: |\n      The codebase does not appear to have any instances of incorrect authorization vulnerabilities. The code does not seem to perform any authorization checks or access control logic.\n    cwe: CWE-863\n    function_names: []\n    filenames: []\n    classification: not promising\n\n  - headline: Improper Control of Dynamically-Managed Code Resources\n    analysis: |\n      The codebase contains several instances where untrusted user input is used to control the execution of dynamic code resources. For example, the `setupCmd()` method in the `MongoBuildWrapper` class concatenates user-supplied parameters to the MongoDB command-line arguments, which could lead to code injection vulnerabilities.\n    cwe: CWE-913\n    function_names:\n      - setupCmd\n    filenames:\n      - src/main/java/org/jenkinsci/plugins/mongodb/MongoBuildWrapper.java\n    classification: very promising\n```",
      "date": "2024-06-14T14:21:21.941531",
      "usage": {
        "prompt_tokens": 14657,
        "completion_tokens": 786,
        "cost": 0.00464675
      }
    }
  ],
  "leads": [
    {
      "headline": "Improper Neutralization of Special Elements in Output Used by a Downstream Component ('Injection')",
      "analysis": "The codebase contains several instances of improper input validation and neutralization, leading to potential injection vulnerabilities. For example, the doCheckPort() and doCheckStartTimeout() methods in the MongoBuildWrapper.DescriptorImpl class do not properly validate user input, allowing for the injection of arbitrary values. Additionally, the setupCmd() method in the MongoBuildWrapper class does not properly sanitize the parameters input, which could lead to command injection vulnerabilities.\n",
      "classification": "slightly promising",
      "cwe": "CWE-74",
      "function_names": [
        "doCheckPort",
        "doCheckStartTimeout",
        "setupCmd"
      ],
      "filenames": [
        "src/main/java/org/jenkinsci/plugins/mongodb/MongoBuildWrapper.java"
      ]
    },
    {
      "headline": "Improper Restriction of Operations within the Bounds of a Memory Buffer",
      "analysis": "The codebase does not appear to have any instances of buffer overflow or out-of-bounds read/write vulnerabilities. The code seems to handle memory management and buffer operations correctly.\n",
      "classification": "not promising",
      "cwe": "CWE-119",
      "function_names": [],
      "filenames": []
    },
    {
      "headline": "Exposure of Sensitive Information to an Unauthorized Actor",
      "analysis": "The codebase contains several instances where sensitive information, such as error messages and log entries, may be exposed to unauthorized actors. For example, the MongoDB_InvalidStartTimeout() and MongoDB_InvalidPortNumber() error messages in the Messages class could potentially leak information about the internal workings of the application.\n",
      "classification": "slightly promising",
      "cwe": "CWE-200",
      "function_names": [
        "doCheckStartTimeout",
        "doCheckPort"
      ],
      "filenames": [
        "src/main/java/org/jenkinsci/plugins/mongodb/MongoBuildWrapper.java"
      ]
    },
    {
      "headline": "Improper Privilege Management",
      "analysis": "The codebase does not appear to have any instances of improper privilege management. The code does not seem to perform any privileged operations or make use of sensitive system resources.\n",
      "classification": "not promising",
      "cwe": "CWE-269",
      "function_names": [],
      "filenames": []
    },
    {
      "headline": "Incorrect Authorization",
      "analysis": "The codebase does not appear to have any instances of incorrect authorization vulnerabilities. The code does not seem to perform any authorization checks or access control logic.\n",
      "classification": "not promising",
      "cwe": "CWE-863",
      "function_names": [],
      "filenames": []
    },
    {
      "headline": "Improper Control of Dynamically-Managed Code Resources",
      "analysis": "The codebase contains several instances where untrusted user input is used to control the execution of dynamic code resources. For example, the setupCmd() method in the MongoBuildWrapper class concatenates user-supplied parameters to the MongoDB command-line arguments, which could lead to code injection vulnerabilities.\n",
      "classification": "very promising",
      "cwe": "CWE-913",
      "function_names": [
        "setupCmd"
      ],
      "filenames": [
        "src/main/java/org/jenkinsci/plugins/mongodb/MongoBuildWrapper.java"
      ]
    }
  ],
  "scores": [
    {
      "stats": {
        "fn": 2,
        "tp": 0,
        "fp": 1
      },
      "mapping": {},
      "vuln_dates": {
        "CVE-2020-2268": "2020-09-16T14:15:14",
        "CVE-2020-2267": "2020-09-16T14:15:14"
      },
      "scoring_model": "claude-3-opus-20240229",
      "type": "llm",
      "instruction_template_hash": "245ace12b6361954d0a2"
    }
  ],
  "instruction_template_hash": "10c0163db4740318a544",
  "version": "0.1.0"
}
