{
  "commit": "2790acd4de4b615e5353d69c09ca0f2f44b1654f",
  "repo_url": "https://github.com/perl-catalyst/catalyst-plugin-session",
  "model": "claude-3-haiku-20240307",
  "chunk_hashes": [
    "e04a0a93573b0df9d523"
  ],
  "responses": [
    {
      "content": "Here is the YAML output equivalent to the type LeadList, based on the provided Pydantic definitions:\n\n```yaml\nleads:\n  - headline: Improper Validation of Specified Quantity in Input (CWE-1284)\n    analysis: |\n      The code appears to lack proper validation of the specified quantity in the input. This could allow an attacker to provide a malformed input that could lead to unexpected behavior or even vulnerabilities. A Proof of Concept (PoC) exploit could be developed to demonstrate how an attacker can leverage this issue to, for example, cause a buffer overflow or other types of memory corruption vulnerabilities.\n    cwe: CWE-1284\n    function_names:\n      - get_session_data\n      - store_session_data\n      - delete_session_data\n    filenames:\n      - lib/Catalyst/Plugin/Session/Store.pm\n    classification: slightly promising\n\n  - headline: Improper Neutralization of Special Elements in Output Used by a Downstream Component ('Injection') (CWE-74)\n    analysis: |\n      The code appears to lack proper sanitization of user input, which could allow an attacker to inject malicious content. This could lead to vulnerabilities such as Command Injection (CWE-77), OS Command Injection (CWE-78), SQL Injection (CWE-89), or XML Injection (CWE-91). A PoC exploit could demonstrate how an attacker can leverage this issue to execute arbitrary commands, access sensitive data, or perform other malicious actions.\n    cwe: CWE-74\n    function_names:\n      - get_session_data\n      - store_session_data\n      - delete_session_data\n    filenames:\n      - lib/Catalyst/Plugin/Session/Store.pm\n    classification: very promising\n\n  - headline: Improper Restriction of Operations within the Bounds of a Memory Buffer (CWE-119)\n    analysis: |\n      The code appears to lack proper bounds checking when handling session data, which could lead to memory corruption vulnerabilities such as Buffer Overflow (CWE-120), Out-of-bounds Read (CWE-125), or Out-of-bounds Write (CWE-787). A PoC exploit could demonstrate how an attacker can leverage this issue to execute arbitrary code or cause other types of security breaches.\n    cwe: CWE-119\n    function_names:\n      - get_session_data\n      - store_session_data\n      - delete_session_data\n    filenames:\n      - lib/Catalyst/Plugin/Session/Store.pm\n    classification: very promising\n\n  - headline: Exposure of Sensitive Information to an Unauthorized Actor (CWE-200)\n    analysis: |\n      The code appears to lack proper protection of sensitive information, such as session data. This could lead to the exposure of sensitive data to unauthorized parties. A PoC exploit could demonstrate how an attacker can extract sensitive information from the application, such as session IDs, user credentials, or other confidential data.\n    cwe: CWE-200\n    function_names:\n      - get_session_data\n      - store_session_data\n      - delete_session_data\n    filenames:\n      - lib/Catalyst/Plugin/Session/Store.pm\n    classification: slightly promising\n\n  - headline: Improper Privilege Management (CWE-269)\n    analysis: |\n      The code appears to lack proper management of user privileges, which could allow an attacker to gain unauthorized access to sensitive resources or perform actions that they should not be able to. A PoC exploit could demonstrate how an attacker can bypass security controls and perform actions that should be restricted.\n    cwe: CWE-269\n    function_names:\n      - get_session_id\n      - set_session_id\n      - delete_session_id\n    filenames:\n      - lib/Catalyst/Plugin/Session/State.pm\n    classification: not promising\n```",
      "date": "2024-06-13T11:01:48.459244",
      "usage": {
        "prompt_tokens": 27478,
        "completion_tokens": 922,
        "cost": 0.008022
      }
    }
  ],
  "leads": [
    {
      "headline": "Improper Validation of Specified Quantity in Input (CWE-1284)",
      "analysis": "The code appears to lack proper validation of the specified quantity in the input. This could allow an attacker to provide a malformed input that could lead to unexpected behavior or even vulnerabilities. A Proof of Concept (PoC) exploit could be developed to demonstrate how an attacker can leverage this issue to, for example, cause a buffer overflow or other types of memory corruption vulnerabilities.\n",
      "classification": "slightly promising",
      "cwe": "CWE-1284",
      "function_names": [
        "get_session_data",
        "store_session_data",
        "delete_session_data"
      ],
      "filenames": [
        "lib/Catalyst/Plugin/Session/Store.pm"
      ]
    },
    {
      "headline": "Improper Neutralization of Special Elements in Output Used by a Downstream Component ('Injection') (CWE-74)",
      "analysis": "The code appears to lack proper sanitization of user input, which could allow an attacker to inject malicious content. This could lead to vulnerabilities such as Command Injection (CWE-77), OS Command Injection (CWE-78), SQL Injection (CWE-89), or XML Injection (CWE-91). A PoC exploit could demonstrate how an attacker can leverage this issue to execute arbitrary commands, access sensitive data, or perform other malicious actions.\n",
      "classification": "very promising",
      "cwe": "CWE-74",
      "function_names": [
        "get_session_data",
        "store_session_data",
        "delete_session_data"
      ],
      "filenames": [
        "lib/Catalyst/Plugin/Session/Store.pm"
      ]
    },
    {
      "headline": "Improper Restriction of Operations within the Bounds of a Memory Buffer (CWE-119)",
      "analysis": "The code appears to lack proper bounds checking when handling session data, which could lead to memory corruption vulnerabilities such as Buffer Overflow (CWE-120), Out-of-bounds Read (CWE-125), or Out-of-bounds Write (CWE-787). A PoC exploit could demonstrate how an attacker can leverage this issue to execute arbitrary code or cause other types of security breaches.\n",
      "classification": "very promising",
      "cwe": "CWE-119",
      "function_names": [
        "get_session_data",
        "store_session_data",
        "delete_session_data"
      ],
      "filenames": [
        "lib/Catalyst/Plugin/Session/Store.pm"
      ]
    },
    {
      "headline": "Exposure of Sensitive Information to an Unauthorized Actor (CWE-200)",
      "analysis": "The code appears to lack proper protection of sensitive information, such as session data. This could lead to the exposure of sensitive data to unauthorized parties. A PoC exploit could demonstrate how an attacker can extract sensitive information from the application, such as session IDs, user credentials, or other confidential data.\n",
      "classification": "slightly promising",
      "cwe": "CWE-200",
      "function_names": [
        "get_session_data",
        "store_session_data",
        "delete_session_data"
      ],
      "filenames": [
        "lib/Catalyst/Plugin/Session/Store.pm"
      ]
    },
    {
      "headline": "Improper Privilege Management (CWE-269)",
      "analysis": "The code appears to lack proper management of user privileges, which could allow an attacker to gain unauthorized access to sensitive resources or perform actions that they should not be able to. A PoC exploit could demonstrate how an attacker can bypass security controls and perform actions that should be restricted.\n",
      "classification": "not promising",
      "cwe": "CWE-269",
      "function_names": [
        "get_session_id",
        "set_session_id",
        "delete_session_id"
      ],
      "filenames": [
        "lib/Catalyst/Plugin/Session/State.pm"
      ]
    }
  ],
  "scores": [
    {
      "stats": {
        "fn": 1,
        "tp": 0,
        "fp": 2
      },
      "mapping": {},
      "vuln_dates": {
        "CVE-2018-25052": "2022-12-28T12:15:08"
      },
      "scoring_model": "claude-3-opus-20240229",
      "type": "llm",
      "instruction_template_hash": "245ace12b6361954d0a2"
    }
  ],
  "instruction_template_hash": "10c0163db4740318a544",
  "version": "0.1.0"
}
