{
  "commit": "409c30c0d2d357f3fbc3abd7a80d5c111a738aa2",
  "repo_url": "https://github.com/tadashi-aikawa/owlmixin",
  "model": "gpt-4o-2024-05-13",
  "chunk_hashes": [
    "7e44a5a941e5eae71fc9"
  ],
  "responses": [
    {
      "content": "```yaml\nleads:\n  - headline: Hardcoded Credentials in release.sh\n    analysis: |\n      The `release.sh` script contains hardcoded credentials (`-u tadashi-aikawa`). Hardcoding sensitive information such as usernames or passwords directly in the code is a dangerous practice because it exposes these credentials to anyone who has access to the codebase. In this case, the username is exposed, but if this practice extends to passwords or tokens, it could lead to unauthorized access.\n    cwe: CWE-798\n    function_names: []\n    filenames:\n      - release.sh\n    classification: very promising\n\n  - headline: Environment Variable Injection in release.sh\n    analysis: |\n      The `release.sh` script uses `RELEASE_VERSION` and `PYPI_PASSWORD` environment variables without proper validation or sanitization. This can lead to security issues if an attacker can influence these environment variables. For example, an attacker could inject arbitrary commands or malicious inputs through these variables, leading to command injection or other unintended behaviors.\n    cwe: CWE-20\n    function_names: []\n    filenames:\n      - release.sh\n    classification: slightly promising\n\n  - headline: Unchecked Error Handling in setup.py\n    analysis: |\n      The `setup.py` script does not perform adequate error handling when performing file operations. For instance, calling `open('owlmixin/__init__.py').read()` without checking if the file exists or if there are read permissions could lead to crashes or undefined behaviors. This lack of error handling creates points where the application could fail unpredictably, leading to denial of service or other issues.\n    cwe: CWE-754\n    function_names:\n      - setup\n    filenames:\n      - setup.py\n    classification: slightly promising\n\n  - headline: Unsafe Usage of Regular Expressions in setup.py\n    analysis: |\n      The `setup.py` script uses a regular expression to extract the version from a file. Regular expressions can be exploited for Denial of Service (DoS) attacks if not properly constructed or if unexpected large input is processed. The complexity and performance of evaluating certain patterns can be manipulated in a way that consumes significant CPU resources, leading to DoS.\n    cwe: CWE-1333\n    function_names:\n      - setup\n      - re.search\n    filenames:\n      - setup.py\n    classification: slightly promising\n\n  - headline: Insecure Import from URL in tests/test_OwlMixin.py\n    analysis: |\n      The `tests/test_OwlMixin.py` script uses a mock to override the `load_json_url` function. If this function is improperly sandboxed or sanitized, it can accept and execute data from URLs. Downloading and executing data directly from remote locations without proper validation can lead to execution of malicious code, allowing attackers to inject harmful payloads.\n    cwe: CWE-494\n    function_names:\n      - load_json_url\n    filenames:\n      - tests/test_OwlMixin.py\n      - owlmixin/util.py\n    classification: very promising\n\n  - headline: Unsafe Deserialization in util.py\n    analysis: |\n      The `util.py` script uses `json.loads` and `yaml.load` for deserialization. Deserializing untrusted data can lead to security vulnerabilities if the incoming data contains structures that can execute code or manipulate objects in an unintended way. YAML is particularly prone to this as it allows for more complex data structures which can be exploited.\n    cwe: CWE-502\n    function_names:\n      - load_json\n      - load_json_url\n      - load_jsonf\n      - load_yaml\n      - load_yamlf\n    filenames:\n      - owlmixin/util.py\n    classification: very promising\n```",
      "date": "2024-07-08T08:53:00.154676",
      "usage": {
        "prompt_tokens": 33871,
        "completion_tokens": 764,
        "cost": 0.180815
      }
    }
  ],
  "leads": [
    {
      "headline": "Hardcoded Credentials in release.sh",
      "analysis": "The release.sh script contains hardcoded credentials (-u tadashi-aikawa). Hardcoding sensitive information such as usernames or passwords directly in the code is a dangerous practice because it exposes these credentials to anyone who has access to the codebase. In this case, the username is exposed, but if this practice extends to passwords or tokens, it could lead to unauthorized access.\n",
      "classification": "very promising",
      "cwe": "CWE-798",
      "function_names": [],
      "filenames": [
        "release.sh"
      ]
    },
    {
      "headline": "Environment Variable Injection in release.sh",
      "analysis": "The release.sh script uses RELEASE_VERSION and PYPI_PASSWORD environment variables without proper validation or sanitization. This can lead to security issues if an attacker can influence these environment variables. For example, an attacker could inject arbitrary commands or malicious inputs through these variables, leading to command injection or other unintended behaviors.\n",
      "classification": "slightly promising",
      "cwe": "CWE-20",
      "function_names": [],
      "filenames": [
        "release.sh"
      ]
    },
    {
      "headline": "Unchecked Error Handling in setup.py",
      "analysis": "The setup.py script does not perform adequate error handling when performing file operations. For instance, calling open('owlmixin/__init__.py').read() without checking if the file exists or if there are read permissions could lead to crashes or undefined behaviors. This lack of error handling creates points where the application could fail unpredictably, leading to denial of service or other issues.\n",
      "classification": "slightly promising",
      "cwe": "CWE-754",
      "function_names": [
        "setup"
      ],
      "filenames": [
        "setup.py"
      ]
    },
    {
      "headline": "Unsafe Usage of Regular Expressions in setup.py",
      "analysis": "The setup.py script uses a regular expression to extract the version from a file. Regular expressions can be exploited for Denial of Service (DoS) attacks if not properly constructed or if unexpected large input is processed. The complexity and performance of evaluating certain patterns can be manipulated in a way that consumes significant CPU resources, leading to DoS.\n",
      "classification": "slightly promising",
      "cwe": "CWE-1333",
      "function_names": [
        "setup",
        "re.search"
      ],
      "filenames": [
        "setup.py"
      ]
    },
    {
      "headline": "Insecure Import from URL in tests/test_OwlMixin.py",
      "analysis": "The tests/test_OwlMixin.py script uses a mock to override the load_json_url function. If this function is improperly sandboxed or sanitized, it can accept and execute data from URLs. Downloading and executing data directly from remote locations without proper validation can lead to execution of malicious code, allowing attackers to inject harmful payloads.\n",
      "classification": "very promising",
      "cwe": "CWE-494",
      "function_names": [
        "load_json_url"
      ],
      "filenames": [
        "tests/test_OwlMixin.py",
        "owlmixin/util.py"
      ]
    },
    {
      "headline": "Unsafe Deserialization in util.py",
      "analysis": "The util.py script uses json.loads and yaml.load for deserialization. Deserializing untrusted data can lead to security vulnerabilities if the incoming data contains structures that can execute code or manipulate objects in an unintended way. YAML is particularly prone to this as it allows for more complex data structures which can be exploited.\n",
      "classification": "very promising",
      "cwe": "CWE-502",
      "function_names": [
        "load_json",
        "load_json_url",
        "load_jsonf"
      ],
      "filenames": [
        "owlmixin/util.py"
      ]
    }
  ],
  "scores": [
    {
      "stats": {
        "fn": 0,
        "tp": 1,
        "fp": 2
      },
      "mapping": {
        "2": "CVE-2017-16618"
      },
      "vuln_dates": {
        "CVE-2017-16618": "2017-11-08T03:29:00"
      },
      "scoring_model": "claude-3-5-sonnet-20240620",
      "type": "llm",
      "instruction_template_hash": "245ace12b6361954d0a2"
    }
  ],
  "instruction_template_hash": "10c0163db4740318a544",
  "version": "0.1.0"
}
