{
  "commit": "2def3797d882d02bfba1e5c9fb54ea667045530e",
  "repo_url": "https://github.com/holgerhees/cloudsync",
  "model": "claude-3-5-sonnet-20240620",
  "chunk_hashes": [
    "02a0104255e683ef3d8a"
  ],
  "responses": [
    {
      "content": "```yaml\nleads:\n  - headline: Unsafe deserialization in RemoteDropboxOptions\n    analysis: |\n      The RemoteDropboxOptions class uses Properties.load() to load configuration from a file. This can lead to remote code execution if an attacker can control the contents of the config file. The load() method deserializes the file contents, potentially instantiating arbitrary classes. An attacker could craft a malicious config file to execute code when it's loaded.\n    cwe: CWE-502\n    function_names:\n      - RemoteDropboxOptions\n    filenames:\n      - src/main/java/cloudsync/connector/RemoteDropboxOptions.java\n    classification: very promising\n\n  - headline: Insecure temporary file creation\n    analysis: |\n      The encryptedBinary method in the Crypt class creates temporary files using File.createTempFile(). This uses predictable file names and locations, which could allow an attacker to access or manipulate these sensitive temporary files. The code does not appear to use secure random file names or restrict permissions on the temporary files.\n    cwe: CWE-377\n    function_names:\n      - encryptedBinary\n    filenames:\n      - src/main/java/cloudsync/helper/Crypt.java \n    classification: very promising\n\n  - headline: Use of weak cryptography\n    analysis: |\n      The Crypt class uses PGP encryption with AES-256. While AES-256 itself is considered secure, the implementation uses PBE (Password Based Encryption) which can be vulnerable to brute force attacks if a weak password is used. The code does not appear to use key stretching or other techniques to strengthen the password-based key derivation.\n    cwe: CWE-326\n    function_names:\n      - encryptData\n      - decryptData\n    filenames:\n      - src/main/java/cloudsync/helper/Crypt.java\n    classification: slightly promising\n\n  - headline: Potential path traversal in file operations\n    analysis: |\n      The LocalFilesystemConnector class constructs file paths using user-supplied input without proper sanitization. For example, the upload method directly appends the item.getPath() to localPath. An attacker could potentially craft a malicious path to access files outside the intended directory.\n    cwe: CWE-22\n    function_names:\n      - upload\n    filenames:\n      - src/main/java/cloudsync/connector/LocalFilesystemConnector.java\n    classification: slightly promising\n\n  - headline: Insufficient input validation \n    analysis: |\n      The CmdOptions class parses command line arguments without sufficient validation. For example, it directly uses values from cmd.getOptionValue() without checking for null or sanitizing the input. This could potentially lead to injection attacks or unexpected behavior if malicious command line arguments are provided.\n    cwe: CWE-20\n    function_names:\n      - parse\n    filenames:  \n      - src/main/java/cloudsync/helper/CmdOptions.java\n    classification: slightly promising\n```",
      "date": "2024-07-08T06:31:53.739628",
      "usage": {
        "prompt_tokens": 59744,
        "completion_tokens": 722,
        "cost": 0.190062
      }
    }
  ],
  "leads": [
    {
      "headline": "Unsafe deserialization in RemoteDropboxOptions",
      "analysis": "The RemoteDropboxOptions class uses Properties.load() to load configuration from a file. This can lead to remote code execution if an attacker can control the contents of the config file. The load() method deserializes the file contents, potentially instantiating arbitrary classes. An attacker could craft a malicious config file to execute code when it's loaded.\n",
      "classification": "very promising",
      "cwe": "CWE-502",
      "function_names": [
        "RemoteDropboxOptions"
      ],
      "filenames": [
        "src/main/java/cloudsync/connector/RemoteDropboxOptions.java"
      ]
    },
    {
      "headline": "Insecure temporary file creation",
      "analysis": "The encryptedBinary method in the Crypt class creates temporary files using File.createTempFile(). This uses predictable file names and locations, which could allow an attacker to access or manipulate these sensitive temporary files. The code does not appear to use secure random file names or restrict permissions on the temporary files.\n",
      "classification": "very promising",
      "cwe": "CWE-377",
      "function_names": [
        "encryptedBinary"
      ],
      "filenames": [
        "src/main/java/cloudsync/helper/Crypt.java"
      ]
    },
    {
      "headline": "Use of weak cryptography",
      "analysis": "The Crypt class uses PGP encryption with AES-256. While AES-256 itself is considered secure, the implementation uses PBE (Password Based Encryption) which can be vulnerable to brute force attacks if a weak password is used. The code does not appear to use key stretching or other techniques to strengthen the password-based key derivation.\n",
      "classification": "slightly promising",
      "cwe": "CWE-326",
      "function_names": [
        "encryptData",
        "decryptData"
      ],
      "filenames": [
        "src/main/java/cloudsync/helper/Crypt.java"
      ]
    },
    {
      "headline": "Potential path traversal in file operations",
      "analysis": "The LocalFilesystemConnector class constructs file paths using user-supplied input without proper sanitization. For example, the upload method directly appends the item.getPath() to localPath. An attacker could potentially craft a malicious path to access files outside the intended directory.\n",
      "classification": "slightly promising",
      "cwe": "CWE-22",
      "function_names": [
        "upload"
      ],
      "filenames": [
        "src/main/java/cloudsync/connector/LocalFilesystemConnector.java"
      ]
    },
    {
      "headline": "Insufficient input validation",
      "analysis": "The CmdOptions class parses command line arguments without sufficient validation. For example, it directly uses values from cmd.getOptionValue() without checking for null or sanitizing the input. This could potentially lead to injection attacks or unexpected behavior if malicious command line arguments are provided.\n",
      "classification": "slightly promising",
      "cwe": "CWE-20",
      "function_names": [
        "parse"
      ],
      "filenames": [
        "src/main/java/cloudsync/helper/CmdOptions.java"
      ]
    }
  ],
  "scores": [
    {
      "stats": {
        "fn": 1,
        "tp": 0,
        "fp": 2
      },
      "mapping": {},
      "vuln_dates": {
        "CVE-2022-4773": "2022-12-28T00:15:15"
      },
      "scoring_model": "claude-3-5-sonnet-20240620",
      "type": "llm",
      "instruction_template_hash": "245ace12b6361954d0a2"
    }
  ],
  "instruction_template_hash": "10c0163db4740318a544",
  "version": "0.1.0"
}
