{
  "commit": "b537cab466329b1b077e0e5e3c14edad2b7142f7",
  "repo_url": "https://github.com/cure53/dompurify",
  "model": "gpt-4o-2024-05-13",
  "chunk_hashes": [
    "7e2a30b651c874584040"
  ],
  "responses": [
    {
      "content": "```yaml\nleads:\n  - headline: Potential vulnerability with node.js and rollup plugins in rollup.config.js\n    analysis: |\n      The rollup configuration file uses dangerous plugins like \"uglify.\" Using UglifyJS without thoroughly sanitizing input might result in vulnerabilities like code injection.\n    cwe: CWE-94\n    function_names: []\n    filenames:\n      - rollup.config.js\n    classification: slightly promising\n    \n  - headline: Prototype pollution via clone function in src/utils.js\n    analysis: |\n      The function \"clone\" in src/utils.js has potential risks for prototype pollution because it shallowly copies properties from the source object without properly validating or filtering them. An attacker could inject properties into the prototype chain of JavaScript objects, potentially escalating privileges or disrupting application operations.\n    cwe: CWE-1321\n    function_names:\n      - clone\n    filenames:\n      - src/utils.js\n    classification: very promising\n    \n  - headline: Bypass restriction for script execution via src/purify.js hooks\n    analysis: |\n      The hooks in src/purify.js, like beforeSanitizeElements or uponSanitizeAttribute, can be used bypass the script sanitization by injecting malicious scripts or altering the sanitization logic.\n    cwe: CWE-502\n    function_names:\n      - DOMPurify.addHook\n    filenames:\n      - src/purify.js\n    classification: very promising\n    \n  - headline: Insecure handling of input inside DOMPurify for inline event handlers\n    analysis: |\n      Input sanitization is done to filter out malicious content. However, inline event handlers (like `onclick`, `onerror`, etc.) might still pose a risk if not properly managed. Malicious scripts can be executed if an attacker manages to pass sanitized inputs that include these event handlers.\n    cwe: CWE-79\n    function_names:\n      - _sanitizeAttributes\n      - addCSSRules\n      - DOMPurify.sanitize\n    filenames:\n      - src/purify.js\n    classification: very promising\n    \n  - headline: Missing or improper validation for HTML attributes in multiple files\n    analysis: |\n      In src/purify.js, functions such as \"_isValidAttribute\" do not comprehensively sanitize all HTML attributes. Safeguards might be inadequate against certain attacks involving `src`, `href`, etc.\n    cwe: CWE-74\n    function_names:\n      - _isValidAttribute\n    filenames:\n      - src/purify.js\n    classification: slightly promising\n    \n  - headline: Improper error handling in sanitization functions\n    analysis: |\n      The sanitization functions might not handle errors properly, leading to unexpected scenarios where malicious code bypasses security checks. Errors during sanitization (such as DOM parsing errors) are suppressed rather than explicitly managed.\n    cwe: CWE-755\n    function_names:\n      - _forceRemove\n      - _removeAttribute\n    filenames:\n      - src/purify.js\n    classification: slightly promising\n    \n  - headline: Potential input validation issues in src/purify.js hooks\n    analysis: |\n      Hooks such as `uponSanitizeElement` and `beforeSanitizeAttributes` allow users to manipulate the DOM elements during sanitization. These hooks may introduce vulnerabilities if the input is not properly validated by the hook functions.\n    cwe: CWE-20\n    function_names:\n      - _executeHook\n    filenames:\n      - src/purify.js\n    classification: slightly promising\n```",
      "date": "2024-06-09T10:15:12.200390",
      "usage": {
        "prompt_tokens": 115887,
        "completion_tokens": 721,
        "cost": 0.59025
      }
    }
  ],
  "leads": [
    {
      "headline": "Potential vulnerability with node.js and rollup plugins in rollup.config.js",
      "analysis": "The rollup configuration file uses dangerous plugins like \"uglify.\" Using UglifyJS without thoroughly sanitizing input might result in vulnerabilities like code injection.\n",
      "classification": "slightly promising",
      "cwe": "CWE-94",
      "function_names": [],
      "filenames": [
        "rollup.config.js"
      ]
    },
    {
      "headline": "Prototype pollution via clone function in src/utils.js",
      "analysis": "The function \"clone\" in src/utils.js has potential risks for prototype pollution because it shallowly copies properties from the source object without properly validating or filtering them. An attacker could inject properties into the prototype chain of JavaScript objects, potentially escalating privileges or disrupting application operations.\n",
      "classification": "very promising",
      "cwe": "CWE-1321",
      "function_names": [
        "clone"
      ],
      "filenames": [
        "src/utils.js"
      ]
    },
    {
      "headline": "Bypass restriction for script execution via src/purify.js hooks",
      "analysis": "The hooks in src/purify.js, like beforeSanitizeElements or uponSanitizeAttribute, can be used bypass the script sanitization by injecting malicious scripts or altering the sanitization logic.\n",
      "classification": "very promising",
      "cwe": "CWE-502",
      "function_names": [
        "DOMPurify.addHook"
      ],
      "filenames": [
        "src/purify.js"
      ]
    },
    {
      "headline": "Insecure handling of input inside DOMPurify for inline event handlers",
      "analysis": "Input sanitization is done to filter out malicious content. However, inline event handlers (like onclick, onerror, etc.) might still pose a risk if not properly managed. Malicious scripts can be executed if an attacker manages to pass sanitized inputs that include these event handlers.\n",
      "classification": "very promising",
      "cwe": "CWE-79",
      "function_names": [
        "_sanitizeAttributes",
        "addCSSRules",
        "DOMPurify.sanitize"
      ],
      "filenames": [
        "src/purify.js"
      ]
    },
    {
      "headline": "Missing or improper validation for HTML attributes in multiple files",
      "analysis": "In src/purify.js, functions such as \"_isValidAttribute\" do not comprehensively sanitize all HTML attributes. Safeguards might be inadequate against certain attacks involving src, href, etc.\n",
      "classification": "slightly promising",
      "cwe": "CWE-74",
      "function_names": [
        "_isValidAttribute"
      ],
      "filenames": [
        "src/purify.js"
      ]
    },
    {
      "headline": "Improper error handling in sanitization functions",
      "analysis": "The sanitization functions might not handle errors properly, leading to unexpected scenarios where malicious code bypasses security checks. Errors during sanitization (such as DOM parsing errors) are suppressed rather than explicitly managed.\n",
      "classification": "slightly promising",
      "cwe": "CWE-755",
      "function_names": [
        "_forceRemove",
        "_removeAttribute"
      ],
      "filenames": [
        "src/purify.js"
      ]
    },
    {
      "headline": "Potential input validation issues in src/purify.js hooks",
      "analysis": "Hooks such as uponSanitizeElement and beforeSanitizeAttributes allow users to manipulate the DOM elements during sanitization. These hooks may introduce vulnerabilities if the input is not properly validated by the hook functions.\n",
      "classification": "slightly promising",
      "cwe": "CWE-20",
      "function_names": [
        "_executeHook"
      ],
      "filenames": [
        "src/purify.js"
      ]
    }
  ],
  "scores": [
    {
      "stats": {
        "fn": 4,
        "tp": 0,
        "fp": 3
      },
      "mapping": {},
      "vuln_dates": {
        "CVE-2019-25155": "2023-11-07T03:09:22",
        "CVE-2020-26870": "2020-10-07T16:15:18",
        "CVE-2019-20374": "2020-01-09T23:15:10",
        "CVE-2019-16728": "2019-09-24T05:15:11"
      },
      "scoring_model": "gpt-4o-2024-05-13",
      "type": "llm",
      "instruction_template_hash": "8998f09cf57fca8a6e03"
    }
  ],
  "instruction_template_hash": "10c0163db4740318a544",
  "version": "0.1.0"
}
