{
  "commit": "16ed41b22c2739838ec7cb0e6ba26d52f4c8db3e",
  "repo_url": "https://github.com/nanohttpd/nanohttpd",
  "model": "gpt-4o-2024-05-13",
  "chunk_hashes": [
    "897b7a93d10e0b1c6258"
  ],
  "responses": [
    {
      "content": "```yaml\nleads:\n  - headline: Missing file existence check in the HTTP Server's static file handler.\n    analysis: |\n      In the method `fileToInputStream`, the code does not handle the case where the file does not exist or is inaccessible. If the provided file path does not exist, it could lead to an unhandled `FileNotFoundException`. \n    cwe: CWE-252\n    function_names:\n      - fileToInputStream\n    filenames:\n      - nanolets/src/main/java/fi/iki/elonen/router/RouterNanoHTTPD.java\n    classification: slightly promising\n\n  - headline: Logical flaw in URL pattern normalization leading to potential duplicate route replacements.\n    analysis: |\n      In the method `normalizeUri`, there is an issue with how trailing and leading slashes are trimmed. This may lead to different URLs being considered the same, which can cause one route to unintentionally replace another.\n\n      Example: \"/user\" and \"/user/\" will be considered identical, and adding a rule for \"/user\" can overwrite the existing one for \"/user/\".\n    cwe: CWE-697\n    function_names:\n      - normalizeUri\n    filenames:\n      - nanolets/src/main/java/fi/iki/elonen/router/RouterNanoHTTPD.java\n    classification: slightly promising\n\n  - headline: Insecure handling of user input that can lead to arbitrary file read vulnerability.\n    analysis: |\n      The `StaticPageHandler` class does not sanitize the input URL properly. It directly uses the URL path to access the filesystem. This can lead to directory traversal vulnerabilities where an attacker may retrieve sensitive files from the server.\n\n      Example: accessing `/browse/..%2F..%2Fetc%2Fpasswd`\n    cwe: CWE-22\n    function_names:\n      - StaticPageHandler.get\n    filenames:\n      - nanolets/src/main/java/fi/iki/elonen/router/RouterNanoHTTPD.java\n    classification: very promising\n\n  - headline: Execution of external programs leading to potential command injection.\n    analysis: |\n      In `NanoHTTPD.java` class, the method `safeClose` has checks similar to executing external programs. Without proper validations and sanitizations, such constructs may lead to command injection allowing arbitrary command execution.\n      \n      Example: Improper closing of socket connections might be influenced by external provided inputs.\n    cwe: CWE-78\n    function_names:\n      - safeClose\n    filenames:\n      - core/src/main/java/fi/iki/elonen/NanoHTTPD.java\n    classification: very promising\n\n  - headline: Lack of validation for user-uploaded filenames might lead to file overwrite attacks.\n    analysis: |\n      In `TestNanoFileUpLoad` class, the handling of file uploads does not sanitize or validate filenames. This allows an attacker to upload a file with a specific name and possibly overwrite critical files on the server.\n\n      Example: Uploading a file named `../../../../etc/password`\n    cwe: CWE-434\n    function_names:\n      - executeUpload\n    filenames:\n      - fileupload/src/test/java/fi/iki/elonen/TestNanoFileUpLoad.java\n    classification: very promising\n\n  - headline: Weak SSL Configuration leading to potential MITM attacks.\n    analysis: |\n      In `HttpSSLServerTest` and `ServerSocketFactoryTest`, the SSL server socket configurations, particularly the supported SSL protocols and ciphers, are not explicitly set. This could lead to the use of weak SSL versions or ciphers making them vulnerable to MITM attacks.\n\n      Example: Default SSLServerSocketFactory usage without enforcing stronger configurations.\n    cwe: CWE-295\n    function_names:\n      - createServerSocket\n    filenames:\n      - core/src/test/java/fi/iki/elonen/HttpSSLServerTest.java\n      - core/src/test/java/fi/iki/elonen/ServerSocketFactoryTest.java\n    classification: slightly promising\n```",
      "date": "2024-06-13T10:21:39.947431",
      "usage": {
        "prompt_tokens": 100718,
        "completion_tokens": 813,
        "cost": 0.515785
      }
    }
  ],
  "leads": [
    {
      "headline": "Missing file existence check in the HTTP Server's static file handler.",
      "analysis": "In the method fileToInputStream, the code does not handle the case where the file does not exist or is inaccessible. If the provided file path does not exist, it could lead to an unhandled FileNotFoundException. \n",
      "classification": "slightly promising",
      "cwe": "CWE-252",
      "function_names": [
        "fileToInputStream"
      ],
      "filenames": [
        "nanolets/src/main/java/fi/iki/elonen/router/RouterNanoHTTPD.java"
      ]
    },
    {
      "headline": "Logical flaw in URL pattern normalization leading to potential duplicate route replacements.",
      "analysis": "In the method normalizeUri, there is an issue with how trailing and leading slashes are trimmed. This may lead to different URLs being considered the same, which can cause one route to unintentionally replace another.\n\nExample: \"/user\" and \"/user/\" will be considered identical, and adding a rule for \"/user\" can overwrite the existing one for \"/user/\".\n",
      "classification": "slightly promising",
      "cwe": "CWE-697",
      "function_names": [
        "normalizeUri"
      ],
      "filenames": [
        "nanolets/src/main/java/fi/iki/elonen/router/RouterNanoHTTPD.java"
      ]
    },
    {
      "headline": "Insecure handling of user input that can lead to arbitrary file read vulnerability.",
      "analysis": "The StaticPageHandler class does not sanitize the input URL properly. It directly uses the URL path to access the filesystem. This can lead to directory traversal vulnerabilities where an attacker may retrieve sensitive files from the server.\n\nExample: accessing /browse/..%2F..%2Fetc%2Fpasswd\n",
      "classification": "very promising",
      "cwe": "CWE-22",
      "function_names": [
        "StaticPageHandler.get"
      ],
      "filenames": [
        "nanolets/src/main/java/fi/iki/elonen/router/RouterNanoHTTPD.java"
      ]
    },
    {
      "headline": "Execution of external programs leading to potential command injection.",
      "analysis": "In NanoHTTPD.java class, the method safeClose has checks similar to executing external programs. Without proper validations and sanitizations, such constructs may lead to command injection allowing arbitrary command execution.\n\nExample: Improper closing of socket connections might be influenced by external provided inputs.\n",
      "classification": "very promising",
      "cwe": "CWE-78",
      "function_names": [
        "safeClose"
      ],
      "filenames": [
        "core/src/main/java/fi/iki/elonen/NanoHTTPD.java"
      ]
    },
    {
      "headline": "Lack of validation for user-uploaded filenames might lead to file overwrite attacks.",
      "analysis": "In TestNanoFileUpLoad class, the handling of file uploads does not sanitize or validate filenames. This allows an attacker to upload a file with a specific name and possibly overwrite critical files on the server.\n\nExample: Uploading a file named ../../../../etc/password\n",
      "classification": "very promising",
      "cwe": "CWE-434",
      "function_names": [
        "executeUpload"
      ],
      "filenames": [
        "fileupload/src/test/java/fi/iki/elonen/TestNanoFileUpLoad.java"
      ]
    },
    {
      "headline": "Weak SSL Configuration leading to potential MITM attacks.",
      "analysis": "In HttpSSLServerTest and ServerSocketFactoryTest, the SSL server socket configurations, particularly the supported SSL protocols and ciphers, are not explicitly set. This could lead to the use of weak SSL versions or ciphers making them vulnerable to MITM attacks.\n\nExample: Default SSLServerSocketFactory usage without enforcing stronger configurations.\n",
      "classification": "slightly promising",
      "cwe": "CWE-295",
      "function_names": [
        "createServerSocket"
      ],
      "filenames": [
        "core/src/test/java/fi/iki/elonen/HttpSSLServerTest.java",
        "core/src/test/java/fi/iki/elonen/ServerSocketFactoryTest.java"
      ]
    }
  ],
  "scores": [
    {
      "stats": {
        "fn": 1,
        "tp": 1,
        "fp": 2
      },
      "mapping": {
        "0": "CVE-2020-13697"
      },
      "vuln_dates": {
        "CVE-2022-21230": "2022-05-01T16:15:08",
        "CVE-2020-13697": "2021-02-23T08:15:11"
      },
      "scoring_model": "claude-3-opus-20240229",
      "type": "llm",
      "instruction_template_hash": "245ace12b6361954d0a2"
    }
  ],
  "instruction_template_hash": "10c0163db4740318a544",
  "version": "0.1.0"
}
