{
  "commit": "d17da850f1c0083de65e458937b8c6b2fbddaa3b",
  "repo_url": "https://github.com/mikebrady/nqptp",
  "model": "gpt-4o-2024-05-13",
  "chunk_hashes": [
    "27a9fb8e6703eeab5e4d"
  ],
  "responses": [
    {
      "content": "```yaml\nleads:\n  - headline: Potential buffer overflow in `hex_string` function\n    analysis: |\n      The `hex_string` function allocates a static buffer `hexcharbuffer` of size 16384 bytes to store the hexadecimal representation of input data. It does not perform any bounds checking on either `buf_len` or ensure that it does not write beyond the `hexcharbuffer`.\n      \n      A buffer overflow may occur if `buf_len` is larger than 8192, since at this point `snprintf` would start writing beyond the allocated buffer size, leading to corruption of memory and potential exploitation.\n      \n      While the function is only used locally, if an attacker can craft inputs to exploit this, it could lead to arbitrary code execution.\n    cwe: CWE-787\n    function_names:\n      - hex_string\n    filenames:\n      - nqptp-message-handlers.c\n    classification: very promising\n\n  - headline: Missing return value checks for critical functions\n    analysis: |\n      There are several instances where the return values of critical functions such as `pthread_mutex_lock` and `pthread_mutex_unlock` are not checked for errors. For instance, in the `update_master_clock_info` function, these function calls are made without verifying successful execution.\n      \n      Failure to handle errors returned by these functions may result in undefined behavior, especially in concurrent environments, which could lead to data corruption or crashes.\n    cwe: CWE-252\n    function_names:\n      - update_master_clock_info\n      - handle_control_port_messages\n      - main\n    filenames:\n      - nqptp-clock-sources.c\n      - nqptp-message-handlers.c\n      - nqptp.c\n    classification: very promising\n\n  - headline: Potential race condition due to shared memory usage\n    analysis: |\n      Shared memory is utilized extensively throughout the codebase, particularly with client records and clock source updates. Functions like `update_master_clock_info` manage shared resources with mutexes, but insufficient synchronization or failure to acquire mutexes appropriately can lead to race conditions.\n      \n      If multiple threads or processes attempt to read/write shared memory concurrently without proper locking, this could result in data races, leading to inconsistent state or even crashes.\n    cwe: CWE-362\n    function_names:\n      - update_master_clock_info\n      - handle_control_port_messages\n    filenames:\n      - nqptp-clock-sources.c\n      - nqptp-message-handlers.c\n    classification: slightly promising\n\n  - headline: Insecure memory usage in `get_device_id`\n    analysis: |\n      In the `get_device_id` function, there is potential insecure handling of memory with the use of local buffer `id`. The function initializes a fixed-size buffer, clears it to zero, and then attempts to read the device ID into it. There is no verification to ensure that the buffer is sufficiently large to hold the MAC address.\n      \n      If the `max_length` provided is smaller than the expected address length, this may lead to buffer overflows, potentially corrupting memory and allowing exploitation.\n    cwe: CWE-120\n    function_names:\n      - get_device_id\n    filenames:\n      - nqptp-utilities.c\n    classification: very promising\n\n  - headline: Hard-coded file permissions in `goodbye` function\n    analysis: |\n      In the `goodbye` function, when creating shared memory or closing files, the code sets file permissions, but does not consider the implications of using fixed permissions (`0666`). This grants read and write access to all users, potentially leading to unauthorized access or modification of sensitive data.\n      \n      It is crucial to use more restrictive permissions and consider the principle of least privilege to mitigate the risk of unauthorized access.\n    cwe: CWE-276\n    function_names:\n      - goodbye\n    filenames:\n      - nqptp.c\n    classification: slightly promising\n\n  - headline: Insufficient checks on return values in `open_sockets_at_port`\n    analysis: |\n      In the `open_sockets_at_port` function, various system calls (like `socket`, `bind`, `setsockopt`, etc.) are made, but their return values are not always checked properly. Failure to adequately check these return values may result in undetected errors, thereby leading to unexpected behavior or insecurity.\n      \n      Specifically, if `socket` or `bind` fails and this is not handled, network communication could be compromised.\n    cwe: CWE-252\n    function_names:\n      - open_sockets_at_port\n    filenames:\n      - nqptp-utilities.c\n    classification: very promising\n\n  - headline: Potential integer overflow in time calculations\n    analysis: |\n      The code makes extensive use of 64-bit integer arithmetic for time calculations. However, there is a lack of checks for potential overflows or wraparounds. For example, the function `timespec_to_ns` converts timespec to nanoseconds using multiplication which could overflow if input values are unexpectedly large.\n      \n      Any overflow in time calculations can lead to incorrect time values, which in time-sensitive applications like PTP (Precision Time Protocol) can be catastrophic, leading to loss of synchronization or erroneous time data.\n    cwe: CWE-190\n    function_names:\n      - timespec_to_ns\n      - get_time_now\n      - broadcasting_task\n    filenames:\n      - general-utilities.c\n      - nqptp.c\n    classification: slightly promising\n```",
      "date": "2024-06-09T13:34:58.199630",
      "usage": {
        "prompt_tokens": 26920,
        "completion_tokens": 1125,
        "cost": 0.151475
      }
    }
  ],
  "leads": [
    {
      "headline": "Potential buffer overflow in hex_string function",
      "analysis": "The hex_string function allocates a static buffer hexcharbuffer of size 16384 bytes to store the hexadecimal representation of input data. It does not perform any bounds checking on either buf_len or ensure that it does not write beyond the hexcharbuffer.\n\nA buffer overflow may occur if buf_len is larger than 8192, since at this point snprintf would start writing beyond the allocated buffer size, leading to corruption of memory and potential exploitation.\n\nWhile the function is only used locally, if an attacker can craft inputs to exploit this, it could lead to arbitrary code execution.\n",
      "classification": "very promising",
      "cwe": "CWE-787",
      "function_names": [
        "hex_string"
      ],
      "filenames": [
        "nqptp-message-handlers.c"
      ]
    },
    {
      "headline": "Missing return value checks for critical functions",
      "analysis": "There are several instances where the return values of critical functions such as pthread_mutex_lock and pthread_mutex_unlock are not checked for errors. For instance, in the update_master_clock_info function, these function calls are made without verifying successful execution.\n\nFailure to handle errors returned by these functions may result in undefined behavior, especially in concurrent environments, which could lead to data corruption or crashes.\n",
      "classification": "very promising",
      "cwe": "CWE-252",
      "function_names": [
        "update_master_clock_info",
        "handle_control_port_messages",
        "main"
      ],
      "filenames": [
        "nqptp-clock-sources.c",
        "nqptp-message-handlers.c",
        "nqptp.c"
      ]
    },
    {
      "headline": "Potential race condition due to shared memory usage",
      "analysis": "Shared memory is utilized extensively throughout the codebase, particularly with client records and clock source updates. Functions like update_master_clock_info manage shared resources with mutexes, but insufficient synchronization or failure to acquire mutexes appropriately can lead to race conditions.\n\nIf multiple threads or processes attempt to read/write shared memory concurrently without proper locking, this could result in data races, leading to inconsistent state or even crashes.\n",
      "classification": "slightly promising",
      "cwe": "CWE-362",
      "function_names": [
        "update_master_clock_info",
        "handle_control_port_messages"
      ],
      "filenames": [
        "nqptp-clock-sources.c",
        "nqptp-message-handlers.c"
      ]
    },
    {
      "headline": "Insecure memory usage in get_device_id",
      "analysis": "In the get_device_id function, there is potential insecure handling of memory with the use of local buffer id. The function initializes a fixed-size buffer, clears it to zero, and then attempts to read the device ID into it. There is no verification to ensure that the buffer is sufficiently large to hold the MAC address.\n\nIf the max_length provided is smaller than the expected address length, this may lead to buffer overflows, potentially corrupting memory and allowing exploitation.\n",
      "classification": "very promising",
      "cwe": "CWE-120",
      "function_names": [
        "get_device_id"
      ],
      "filenames": [
        "nqptp-utilities.c"
      ]
    },
    {
      "headline": "Hard-coded file permissions in goodbye function",
      "analysis": "In the goodbye function, when creating shared memory or closing files, the code sets file permissions, but does not consider the implications of using fixed permissions (0666). This grants read and write access to all users, potentially leading to unauthorized access or modification of sensitive data.\n\nIt is crucial to use more restrictive permissions and consider the principle of least privilege to mitigate the risk of unauthorized access.\n",
      "classification": "slightly promising",
      "cwe": "CWE-276",
      "function_names": [
        "goodbye"
      ],
      "filenames": [
        "nqptp.c"
      ]
    },
    {
      "headline": "Insufficient checks on return values in open_sockets_at_port",
      "analysis": "In the open_sockets_at_port function, various system calls (like socket, bind, setsockopt, etc.) are made, but their return values are not always checked properly. Failure to adequately check these return values may result in undetected errors, thereby leading to unexpected behavior or insecurity.\n\nSpecifically, if socket or bind fails and this is not handled, network communication could be compromised.\n",
      "classification": "very promising",
      "cwe": "CWE-252",
      "function_names": [
        "open_sockets_at_port"
      ],
      "filenames": [
        "nqptp-utilities.c"
      ]
    },
    {
      "headline": "Potential integer overflow in time calculations",
      "analysis": "The code makes extensive use of 64-bit integer arithmetic for time calculations. However, there is a lack of checks for potential overflows or wraparounds. For example, the function timespec_to_ns converts timespec to nanoseconds using multiplication which could overflow if input values are unexpectedly large.\n\nAny overflow in time calculations can lead to incorrect time values, which in time-sensitive applications like PTP (Precision Time Protocol) can be catastrophic, leading to loss of synchronization or erroneous time data.\n",
      "classification": "slightly promising",
      "cwe": "CWE-190",
      "function_names": [
        "timespec_to_ns",
        "get_time_now",
        "broadcasting_task"
      ],
      "filenames": [
        "general-utilities.c",
        "nqptp.c"
      ]
    }
  ],
  "scores": [
    {
      "stats": {
        "fn": 1,
        "tp": 0,
        "fp": 4
      },
      "mapping": {},
      "vuln_dates": {
        "CVE-2023-43771": "2023-09-22T06:15:10"
      },
      "scoring_model": "gpt-4o-2024-05-13",
      "type": "llm",
      "instruction_template_hash": "8998f09cf57fca8a6e03"
    }
  ],
  "instruction_template_hash": "10c0163db4740318a544",
  "version": "0.1.0"
}
