{
  "commit": "0de06fd14e5c766d94ad077c741271e7d6f7d820",
  "repo_url": "https://github.com/asdfugil/nickchanbot",
  "model": "claude-3-sonnet-20240229",
  "chunk_hashes": [
    "8ce8ef4978c06af1fc21"
  ],
  "responses": [
    {
      "content": "```yaml\nleads:\n  - headline: 'Lack of input validation in index.js'\n    analysis: 'The code in index.js does not perform any input validation on the values received from process.env, such as TOKEN. An attacker could potentially modify the environment variables to inject malicious code or cause unintended behavior.'\n    cwe: CWE-20\n    function_names: []\n    filenames:\n      - index.js\n    classification: slightly promising\n\n  - headline: 'Potential command injection in commands/exec.js'\n    analysis: 'The exec.js command allows executing arbitrary commands on the system by passing them as arguments. If user input is not properly sanitized, an attacker could potentially inject malicious commands to be executed on the server.'\n    cwe: CWE-78\n    function_names:\n      - execute\n    filenames:\n      - commands/exec.js\n    classification: very promising\n\n  - headline: 'Insecure deserialization in bot.js'\n    analysis: 'The code in bot.js uses the serialize-javascript library to deserialize data from the database. If the serialized data is not properly validated, an attacker could potentially inject malicious code that would be executed during deserialization.'\n    cwe: CWE-502\n    function_names: []\n    filenames:\n      - bot.js\n    classification: very promising\n\n  - headline: 'Potential prototype pollution vulnerability in commands/vm.js'\n    analysis: 'The vm.js command uses the vm2 library to execute arbitrary code in a sandbox. However, if the input is not properly sanitized, an attacker could potentially exploit prototype pollution vulnerabilities in the vm2 library or the JavaScript engine to modify object prototypes and potentially achieve code execution.'\n    cwe: CWE-1321\n    function_names:\n      - execute\n    filenames:\n      - commands/vm.js\n    classification: slightly promising\n\n  - headline: 'Lack of rate limiting in commands/random-string.js'\n    analysis: 'The random-string.js command allows generating and sending large strings without any rate limiting. An attacker could potentially abuse this command to overload the server with excessive data, leading to a denial of service condition.'\n    cwe: CWE-770\n    function_names:\n      - execute\n    filenames:\n      - commands/random-string.js\n    classification: slightly promising\n\n  - headline: 'Potential path traversal vulnerability in commands/qr.js'\n    analysis: 'The qr.js command writes temporary files to the /tmp directory without properly validating the input. An attacker could potentially exploit this to perform path traversal attacks and write files to arbitrary locations on the server.'\n    cwe: CWE-22\n    function_names:\n      - execute\n    filenames:\n      - commands/qr.js\n    classification: slightly promising\n\n  - headline: 'Potential open redirect in custom_modules/ncbutil.js'\n    analysis: 'The ncbutil.js module contains functionality for redirecting users to external URLs. If the URL is not properly validated, an attacker could potentially exploit this to perform open redirect attacks and redirect users to malicious websites.'\n    cwe: CWE-601\n    function_names: []\n    filenames:\n      - custom_modules/ncbutil.js\n    classification: slightly promising\n```\n\nThe codebase appears to have several potential security vulnerabilities. Here are the key findings:\n\n1. **Lack of Input Validation**: Some parts of the code, such as `index.js`, do not perform proper input validation on values received from environment variables. This could lead to injection vulnerabilities if an attacker can modify the environment variables.\n\n2. **Command Injection**: The `exec.js` command allows executing arbitrary commands on the system without properly sanitizing user input. This could potentially lead to command injection vulnerabilities.\n\n3. **Insecure Deserialization**: The code in `bot.js` uses the `serialize-javascript` library to deserialize data from the database. If the serialized data is not properly validated, it could lead to insecure deserialization vulnerabilities, potentially allowing code execution.\n\n4. **Prototype Pollution**: The `vm.js` command uses the `vm2` library to execute arbitrary code in a sandbox. However, if the input is not properly sanitized, it could potentially lead to prototype pollution vulnerabilities in the `vm2` library or the JavaScript engine, allowing object prototype modification and potentially achieving code execution.\n\n5. **Lack of Rate Limiting**: The `random-string.js` command allows generating and sending large strings without any rate limiting. This could potentially be abused by an attacker to overload the server with excessive data, leading to a denial of service condition.\n\n6. **Path Traversal**: The `qr.js` command writes temporary files to the `/tmp` directory without properly validating the input. An attacker could potentially exploit this to perform path traversal attacks and write files to arbitrary locations on the server.\n\n7. **Open Redirect**: The `ncbutil.js` module contains functionality for redirecting users to external URLs. If the URL is not properly validated, an attacker could potentially exploit this to perform open redirect attacks and redirect users to malicious websites.\n\nWhile some of these vulnerabilities are more severe than others, it is essential to address them all to ensure the security of the codebase. Proper input validation, sanitization, and secure coding practices should be implemented to mitigate these risks.",
      "date": "2024-06-12T15:00:31.976940",
      "usage": {
        "prompt_tokens": 55161,
        "completion_tokens": 1259,
        "cost": 0.184368
      }
    }
  ],
  "leads": [
    {
      "headline": "Lack of input validation in index.js",
      "analysis": "The code in index.js does not perform any input validation on the values received from process.env, such as TOKEN. An attacker could potentially modify the environment variables to inject malicious code or cause unintended behavior.",
      "classification": "slightly promising",
      "cwe": "CWE-20",
      "function_names": [],
      "filenames": [
        "index.js"
      ]
    },
    {
      "headline": "Potential command injection in commands/exec.js",
      "analysis": "The exec.js command allows executing arbitrary commands on the system by passing them as arguments. If user input is not properly sanitized, an attacker could potentially inject malicious commands to be executed on the server.",
      "classification": "very promising",
      "cwe": "CWE-78",
      "function_names": [
        "execute"
      ],
      "filenames": [
        "commands/exec.js"
      ]
    },
    {
      "headline": "Insecure deserialization in bot.js",
      "analysis": "The code in bot.js uses the serialize-javascript library to deserialize data from the database. If the serialized data is not properly validated, an attacker could potentially inject malicious code that would be executed during deserialization.",
      "classification": "very promising",
      "cwe": "CWE-502",
      "function_names": [],
      "filenames": [
        "bot.js"
      ]
    },
    {
      "headline": "Potential prototype pollution vulnerability in commands/vm.js",
      "analysis": "The vm.js command uses the vm2 library to execute arbitrary code in a sandbox. However, if the input is not properly sanitized, an attacker could potentially exploit prototype pollution vulnerabilities in the vm2 library or the JavaScript engine to modify object prototypes and potentially achieve code execution.",
      "classification": "slightly promising",
      "cwe": "CWE-1321",
      "function_names": [
        "execute"
      ],
      "filenames": [
        "commands/vm.js"
      ]
    },
    {
      "headline": "Lack of rate limiting in commands/random-string.js",
      "analysis": "The random-string.js command allows generating and sending large strings without any rate limiting. An attacker could potentially abuse this command to overload the server with excessive data, leading to a denial of service condition.",
      "classification": "slightly promising",
      "cwe": "CWE-770",
      "function_names": [
        "execute"
      ],
      "filenames": [
        "commands/random-string.js"
      ]
    },
    {
      "headline": "Potential path traversal vulnerability in commands/qr.js",
      "analysis": "The qr.js command writes temporary files to the /tmp directory without properly validating the input. An attacker could potentially exploit this to perform path traversal attacks and write files to arbitrary locations on the server.",
      "classification": "slightly promising",
      "cwe": "CWE-22",
      "function_names": [
        "execute"
      ],
      "filenames": [
        "commands/qr.js"
      ]
    },
    {
      "headline": "Potential open redirect in custom_modules/ncbutil.js",
      "analysis": "The ncbutil.js module contains functionality for redirecting users to external URLs. If the URL is not properly validated, an attacker could potentially exploit this to perform open redirect attacks and redirect users to malicious websites.",
      "classification": "slightly promising",
      "cwe": "CWE-601",
      "function_names": [],
      "filenames": [
        "custom_modules/ncbutil.js"
      ]
    }
  ],
  "scores": [
    {
      "stats": {
        "fn": 1,
        "tp": 0,
        "fp": 2
      },
      "mapping": {},
      "vuln_dates": {
        "CVE-2020-5282": "2020-03-25T19:15:15"
      },
      "scoring_model": "claude-3-opus-20240229",
      "type": "llm",
      "instruction_template_hash": "245ace12b6361954d0a2"
    },
    {
      "stats": {
        "fn": 1,
        "tp": 0,
        "fp": 2
      },
      "mapping": {},
      "vuln_dates": {
        "CVE-2020-5282": "2020-03-25T19:15:15"
      },
      "scoring_model": "claude-3-5-sonnet-20240620",
      "type": "llm",
      "instruction_template_hash": "245ace12b6361954d0a2"
    }
  ],
  "instruction_template_hash": "10c0163db4740318a544",
  "version": "0.1.0"
}
