{
  "commit": "1adf0f0a2f81fe4ee72982f64cd63d5edb996a2c",
  "repo_url": "https://github.com/jenkinsci/ccm-plugin",
  "model": "claude-3-haiku-20240307",
  "chunk_hashes": [
    "aa5b02783e87f3b75db3"
  ],
  "responses": [
    {
      "content": "Based on the code provided, here are the identified security vulnerabilities:\n\n```yaml\nleads:\n  - headline: Improper Input Validation\n    analysis: |\n      The code does not properly validate user input, which could lead to vulnerabilities such as command injection or code injection. This is a common issue in many software applications.\n    cwe: CWE-20\n    function_names:\n      - parse\n      - calculateMetricPriority\n    filenames:\n      - hudson/plugins/ccm/parser/CcmParser.java\n    classification: very promising\n  - headline: Exposure of Sensitive Information\n    analysis: |\n      The code exposes detailed information about the software, such as the names of functions and files, which could be useful for an attacker. This can lead to increased attack surface and make it easier for an attacker to find vulnerabilities.\n    cwe: CWE-200\n    function_names:\n      - getDisplayName\n      - getTrendName\n    filenames:\n      - hudson/plugins/ccm/CcmProjectAction.java\n    classification: slightly promising\n  - headline: Insecure Deserialization\n    analysis: |\n      The code uses deserialization, which can be vulnerable to attacks if the input is not properly validated. Insecure deserialization can lead to remote code execution or other types of attacks.\n    cwe: CWE-502\n    function_names:\n      - parseCCMXmlFile\n    filenames:\n      - hudson/plugins/ccm/parser/CcmParser.java\n    classification: very promising\n  - headline: Incorrect Permission Assignment\n    analysis: |\n      The code does not properly manage permissions, which could lead to unauthorized access or privilege escalation. This is a common issue in many software applications.\n    cwe: CWE-732\n    function_names:\n      - perform\n    filenames:\n      - hudson/plugins/ccm/CcmPublisher.java\n    classification: slightly promising\n```\n\nThe identified vulnerabilities include:\n\n1. Improper Input Validation (CWE-20): The `parse()` and `calculateMetricPriority()` functions in `CcmParser.java` do not properly validate user input, which could lead to vulnerabilities such as command injection or code injection.\n\n2. Exposure of Sensitive Information (CWE-200): The `getDisplayName()` and `getTrendName()` functions in `CcmProjectAction.java` expose detailed information about the software, which could be useful for an attacker.\n\n3. Insecure Deserialization (CWE-502): The `parseCCMXmlFile()` function in `CcmParser.java` uses deserialization, which can be vulnerable to attacks if the input is not properly validated.\n\n4. Incorrect Permission Assignment (CWE-732): The `perform()` function in `CcmPublisher.java` does not properly manage permissions, which could lead to unauthorized access or privilege escalation.\n\nIt's important to address these vulnerabilities to improve the security of the software. Recommendations for mitigating these issues include:\n\n1. Implement proper input validation to prevent injection attacks.\n2. Minimize the exposure of sensitive information to reduce the attack surface.\n3. Avoid using deserialization or use a safe deserialization library to prevent remote code execution attacks.\n4. Implement proper access control and permission management to prevent unauthorized access and privilege escalation.",
      "date": "2024-06-12T18:02:19.112944",
      "usage": {
        "prompt_tokens": 26609,
        "completion_tokens": 795,
        "cost": 0.007646
      }
    }
  ],
  "leads": [
    {
      "headline": "Improper Input Validation",
      "analysis": "The code does not properly validate user input, which could lead to vulnerabilities such as command injection or code injection. This is a common issue in many software applications.\n",
      "classification": "very promising",
      "cwe": "CWE-20",
      "function_names": [
        "parse",
        "calculateMetricPriority"
      ],
      "filenames": [
        "hudson/plugins/ccm/parser/CcmParser.java"
      ]
    },
    {
      "headline": "Exposure of Sensitive Information",
      "analysis": "The code exposes detailed information about the software, such as the names of functions and files, which could be useful for an attacker. This can lead to increased attack surface and make it easier for an attacker to find vulnerabilities.\n",
      "classification": "slightly promising",
      "cwe": "CWE-200",
      "function_names": [
        "getDisplayName",
        "getTrendName"
      ],
      "filenames": [
        "hudson/plugins/ccm/CcmProjectAction.java"
      ]
    },
    {
      "headline": "Insecure Deserialization",
      "analysis": "The code uses deserialization, which can be vulnerable to attacks if the input is not properly validated. Insecure deserialization can lead to remote code execution or other types of attacks.\n",
      "classification": "very promising",
      "cwe": "CWE-502",
      "function_names": [
        "parseCCMXmlFile"
      ],
      "filenames": [
        "hudson/plugins/ccm/parser/CcmParser.java"
      ]
    },
    {
      "headline": "Incorrect Permission Assignment",
      "analysis": "The code does not properly manage permissions, which could lead to unauthorized access or privilege escalation. This is a common issue in many software applications.\n",
      "classification": "slightly promising",
      "cwe": "CWE-732",
      "function_names": [
        "perform"
      ],
      "filenames": [
        "hudson/plugins/ccm/CcmPublisher.java"
      ]
    }
  ],
  "scores": [
    {
      "stats": {
        "fn": 1,
        "tp": 0,
        "fp": 2
      },
      "mapping": {},
      "vuln_dates": {
        "CVE-2018-1000054": "2018-02-09T23:29:01"
      },
      "scoring_model": "claude-3-opus-20240229",
      "type": "llm",
      "instruction_template_hash": "245ace12b6361954d0a2"
    }
  ],
  "instruction_template_hash": "10c0163db4740318a544",
  "version": "0.1.0"
}
