{
  "commit": "343e9be13460fbaee976b03133ed32cff3c6c856",
  "repo_url": "https://github.com/jenkinsci/autocomplete-parameter-plugin",
  "model": "gpt-4o-2024-05-13",
  "chunk_hashes": [
    "36e05c53d15cacd26e32"
  ],
  "responses": [
    {
      "content": "```yaml\nleads:\n  - headline: \"Uninitialized Variables in ExpirableCache\"\n    analysis: |\n      The `ExpirableCache` class does not initialize the `expirationTime` and `data` maps in its constructor, which can lead to `NullPointerException` if methods are called on an instance before proper initialization.\n    cwe: CWE-909\n    function_names:\n      - ExpirableCache\n    filenames:\n      - src/main/java/wirelabs/commons/ExpirableCache.java\n    classification: very promising\n\n  - headline: \"Potential Denial of Service in RemoteDataProvider\"\n    analysis: |\n      The `RemoteDataProvider` class performs remote HTTP requests in real-time without any rate limiting or retry mechanisms. This can lead to service disruptions if the remote server is slow or unresponsive, causing a denial of service.\n    cwe: CWE-400\n    function_names:\n      - filter\n      - getData\n    filenames:\n      - src/main/java/org/jenkinsci/plugins/autocompleteparameter/providers/RemoteDataProvider.java\n    classification: very promising\n  \n  - headline: \"Hard-coded Credentials in CredentialsUtils\"\n    analysis: |\n      The `CredentialsUtils` class hard-codes the method of encoding credentials for basic authentication instead of using a more secure approach such as dynamically retrieving encoding mechanisms or encrypting the credentials.\n    cwe: CWE-798\n    function_names:\n      - addAuth\n    filenames:\n      - src/main/java/wirelabs/commons/CredentialsUtils.java\n    classification: slightly promising\n\n  - headline: \"Command Execution in Parameter-Groovy-Editor.js\"\n    analysis: |\n      The `parameter-groovy-editor.js` file includes functionality to run scripts which may allow an attacker to inject and execute arbitrary code if the input is not properly sanitized or validated.\n    cwe: CWE-94\n    function_names:\n      - initEditor\n    filenames:\n      - src/main/js/parameter-groovy-editor.js\n    classification: very promising\n  \n  - headline: \"Exposure of Sensitive Information in RequestBuilder\"\n    analysis: |\n      In the `RequestBuilder` class, sensitive information such as URLs and credentials might be logged or exposed if the `signatureContent` is improperly handled or transmitted.\n    cwe: CWE-209\n    function_names:\n      - doRequest\n    filenames:\n      - src/main/java/wirelabs/commons/RequestBuilder.java\n    classification: slightly promising\n  \n  - headline: \"Improper Synchronization in ExpirableCacheTest\"\n    analysis: |\n      The `ExpirableCacheTest` class uses `Thread.sleep` for synchronization which is not a reliable method for proper synchronization, potentially leading to race conditions.\n    cwe: CWE-362\n    function_names:\n      - happyDay\n    filenames:\n      - src/test/java/wirelabs/commons/ExpirableCacheTest.java\n    classification: slightly promising\n\n  - headline: \"Improper Validation in InlineJsonDataProvider\"\n    analysis: |\n      The `InlineJsonDataProvider` class does not perform sufficient validation of the JSON data, which could lead to invalid data being processed and used within the application.\n    cwe: CWE-20\n    function_names:\n      - getData\n    filenames:\n      - src/main/java/org/jenkinsci/plugins/autocompleteparameter/providers/InlineJsonDataProvider.java\n    classification: slightly promising\n```",
      "date": "2024-06-12T17:53:52.937875",
      "usage": {
        "prompt_tokens": 33966,
        "completion_tokens": 701,
        "cost": 0.180345
      }
    }
  ],
  "leads": [
    {
      "headline": "Uninitialized Variables in ExpirableCache",
      "analysis": "The ExpirableCache class does not initialize the expirationTime and data maps in its constructor, which can lead to NullPointerException if methods are called on an instance before proper initialization.\n",
      "classification": "very promising",
      "cwe": "CWE-909",
      "function_names": [
        "ExpirableCache"
      ],
      "filenames": [
        "src/main/java/wirelabs/commons/ExpirableCache.java"
      ]
    },
    {
      "headline": "Potential Denial of Service in RemoteDataProvider",
      "analysis": "The RemoteDataProvider class performs remote HTTP requests in real-time without any rate limiting or retry mechanisms. This can lead to service disruptions if the remote server is slow or unresponsive, causing a denial of service.\n",
      "classification": "very promising",
      "cwe": "CWE-400",
      "function_names": [
        "filter",
        "getData"
      ],
      "filenames": [
        "src/main/java/org/jenkinsci/plugins/autocompleteparameter/providers/RemoteDataProvider.java"
      ]
    },
    {
      "headline": "Hard-coded Credentials in CredentialsUtils",
      "analysis": "The CredentialsUtils class hard-codes the method of encoding credentials for basic authentication instead of using a more secure approach such as dynamically retrieving encoding mechanisms or encrypting the credentials.\n",
      "classification": "slightly promising",
      "cwe": "CWE-798",
      "function_names": [
        "addAuth"
      ],
      "filenames": [
        "src/main/java/wirelabs/commons/CredentialsUtils.java"
      ]
    },
    {
      "headline": "Command Execution in Parameter-Groovy-Editor.js",
      "analysis": "The parameter-groovy-editor.js file includes functionality to run scripts which may allow an attacker to inject and execute arbitrary code if the input is not properly sanitized or validated.\n",
      "classification": "very promising",
      "cwe": "CWE-94",
      "function_names": [
        "initEditor"
      ],
      "filenames": [
        "src/main/js/parameter-groovy-editor.js"
      ]
    },
    {
      "headline": "Exposure of Sensitive Information in RequestBuilder",
      "analysis": "In the RequestBuilder class, sensitive information such as URLs and credentials might be logged or exposed if the signatureContent is improperly handled or transmitted.\n",
      "classification": "slightly promising",
      "cwe": "CWE-209",
      "function_names": [
        "doRequest"
      ],
      "filenames": [
        "src/main/java/wirelabs/commons/RequestBuilder.java"
      ]
    },
    {
      "headline": "Improper Synchronization in ExpirableCacheTest",
      "analysis": "The ExpirableCacheTest class uses Thread.sleep for synchronization which is not a reliable method for proper synchronization, potentially leading to race conditions.\n",
      "classification": "slightly promising",
      "cwe": "CWE-362",
      "function_names": [
        "happyDay"
      ],
      "filenames": [
        "src/test/java/wirelabs/commons/ExpirableCacheTest.java"
      ]
    },
    {
      "headline": "Improper Validation in InlineJsonDataProvider",
      "analysis": "The InlineJsonDataProvider class does not perform sufficient validation of the JSON data, which could lead to invalid data being processed and used within the application.\n",
      "classification": "slightly promising",
      "cwe": "CWE-20",
      "function_names": [
        "getData"
      ],
      "filenames": [
        "src/main/java/org/jenkinsci/plugins/autocompleteparameter/providers/InlineJsonDataProvider.java"
      ]
    }
  ],
  "scores": [
    {
      "stats": {
        "fn": 3,
        "tp": 0,
        "fp": 3
      },
      "mapping": {},
      "vuln_dates": {
        "CVE-2022-30961": "2022-05-17T15:15:10",
        "CVE-2022-30969": "2022-05-17T15:15:11",
        "CVE-2022-30970": "2022-05-17T15:15:11"
      },
      "scoring_model": "claude-3-opus-20240229",
      "type": "llm",
      "instruction_template_hash": "245ace12b6361954d0a2"
    },
    {
      "stats": {
        "fn": 3,
        "tp": 0,
        "fp": 3
      },
      "mapping": {},
      "vuln_dates": {
        "CVE-2022-30961": "2022-05-17T15:15:10",
        "CVE-2022-30969": "2022-05-17T15:15:11",
        "CVE-2022-30970": "2022-05-17T15:15:11"
      },
      "scoring_model": "claude-3-5-sonnet-20240620",
      "type": "llm",
      "instruction_template_hash": "245ace12b6361954d0a2"
    }
  ],
  "instruction_template_hash": "10c0163db4740318a544",
  "version": "0.1.0"
}
