{
  "commit": "4084ea18f96d9a953315f5555fca45f26639b8be",
  "repo_url": "https://github.com/cyanomiko/dcnnt-py",
  "model": "claude-3-5-sonnet-20240620",
  "chunk_hashes": [
    "ae7b8d1efa8980c63a92"
  ],
  "responses": [
    {
      "content": "```yaml\nleads:\n  - headline: Insecure use of AES encryption\n    analysis: |\n      The encryption functions in dcnnt/common/__init__.py use AES in GCM mode, which is generally secure. However, the nonce is included in the ciphertext without any randomization or uniqueness guarantees. Reusing a nonce with the same key in GCM mode can completely break the encryption. The code should use a cryptographically secure random number generator to create a unique nonce for each encryption operation.\n    cwe: CWE-323\n    function_names:\n      - encrypt\n      - decrypt  \n    filenames:\n      - dcnnt/common/__init__.py\n    classification: very promising\n\n  - headline: Use of weak key derivation function\n    analysis: |\n      The derive_key function in dcnnt/common/__init__.py uses a simple SHA256 hash to derive encryption keys from passwords. This is vulnerable to fast brute-force attacks. A secure key derivation function like PBKDF2, bcrypt, or Argon2 should be used instead to make brute-force attacks more computationally expensive.\n    cwe: CWE-916\n    function_names:\n      - derive_key\n    filenames:\n      - dcnnt/common/__init__.py\n    classification: very promising\n\n  - headline: Potential command injection vulnerability\n    analysis: |\n      The OpenerPlugin class in dcnnt/plugins/opener.py executes shell commands using user-controlled input without proper sanitization. The 'path' and 'url' variables are inserted directly into shell commands, allowing potential command injection attacks if an attacker can control these values. Proper input sanitization or using secure APIs instead of shell commands is necessary to prevent this vulnerability.\n    cwe: CWE-78\n    function_names:\n      - handle_open_file\n      - handle_open_link\n    filenames:\n      - dcnnt/plugins/opener.py\n    classification: very promising\n\n  - headline: Potential path traversal vulnerability\n    analysis: |\n      The FileTransferPlugin class in dcnnt/plugins/file_transfer.py allows downloading files based on an index provided by the client. There does not appear to be any validation that the resulting file path is within an allowed directory. This could potentially allow an attacker to read arbitrary files on the system through path traversal. Proper path validation and sanitization should be implemented.\n    cwe: CWE-22\n    function_names:\n      - handle_download\n    filenames:\n      - dcnnt/plugins/file_transfer.py\n    classification: slightly promising\n\n  - headline: Use of hardcoded credentials\n    analysis: |\n      The DConnectApp class in dcnnt/app.py generates a default password using a simple random string generation method. This password is then stored in the configuration file. Using hardcoded or default credentials can lead to unauthorized access if an attacker gains access to the configuration file or guesses the password generation method.\n    cwe: CWE-798\n    function_names:\n      - init_conf\n    filenames:\n      - dcnnt/app.py\n    classification: slightly promising\n```",
      "date": "2024-07-07T20:53:44.741482",
      "usage": {
        "prompt_tokens": 30039,
        "completion_tokens": 739,
        "cost": 0.101202
      }
    }
  ],
  "leads": [
    {
      "headline": "Insecure use of AES encryption",
      "analysis": "The encryption functions in dcnnt/common/__init__.py use AES in GCM mode, which is generally secure. However, the nonce is included in the ciphertext without any randomization or uniqueness guarantees. Reusing a nonce with the same key in GCM mode can completely break the encryption. The code should use a cryptographically secure random number generator to create a unique nonce for each encryption operation.\n",
      "classification": "very promising",
      "cwe": "CWE-323",
      "function_names": [
        "encrypt",
        "decrypt"
      ],
      "filenames": [
        "dcnnt/common/__init__.py"
      ]
    },
    {
      "headline": "Use of weak key derivation function",
      "analysis": "The derive_key function in dcnnt/common/__init__.py uses a simple SHA256 hash to derive encryption keys from passwords. This is vulnerable to fast brute-force attacks. A secure key derivation function like PBKDF2, bcrypt, or Argon2 should be used instead to make brute-force attacks more computationally expensive.\n",
      "classification": "very promising",
      "cwe": "CWE-916",
      "function_names": [
        "derive_key"
      ],
      "filenames": [
        "dcnnt/common/__init__.py"
      ]
    },
    {
      "headline": "Potential command injection vulnerability",
      "analysis": "The OpenerPlugin class in dcnnt/plugins/opener.py executes shell commands using user-controlled input without proper sanitization. The 'path' and 'url' variables are inserted directly into shell commands, allowing potential command injection attacks if an attacker can control these values. Proper input sanitization or using secure APIs instead of shell commands is necessary to prevent this vulnerability.\n",
      "classification": "very promising",
      "cwe": "CWE-78",
      "function_names": [
        "handle_open_file",
        "handle_open_link"
      ],
      "filenames": [
        "dcnnt/plugins/opener.py"
      ]
    },
    {
      "headline": "Potential path traversal vulnerability",
      "analysis": "The FileTransferPlugin class in dcnnt/plugins/file_transfer.py allows downloading files based on an index provided by the client. There does not appear to be any validation that the resulting file path is within an allowed directory. This could potentially allow an attacker to read arbitrary files on the system through path traversal. Proper path validation and sanitization should be implemented.\n",
      "classification": "slightly promising",
      "cwe": "CWE-22",
      "function_names": [
        "handle_download"
      ],
      "filenames": [
        "dcnnt/plugins/file_transfer.py"
      ]
    },
    {
      "headline": "Use of hardcoded credentials",
      "analysis": "The DConnectApp class in dcnnt/app.py generates a default password using a simple random string generation method. This password is then stored in the configuration file. Using hardcoded or default credentials can lead to unauthorized access if an attacker gains access to the configuration file or guesses the password generation method.\n",
      "classification": "slightly promising",
      "cwe": "CWE-798",
      "function_names": [
        "init_conf"
      ],
      "filenames": [
        "dcnnt/app.py"
      ]
    }
  ],
  "scores": [
    {
      "stats": {
        "fn": 1,
        "tp": 0,
        "fp": 3
      },
      "mapping": {},
      "vuln_dates": {
        "CVE-2023-1000": "2024-04-27T09:15:08"
      },
      "scoring_model": "claude-3-5-sonnet-20240620",
      "type": "llm",
      "instruction_template_hash": "245ace12b6361954d0a2"
    }
  ],
  "instruction_template_hash": "10c0163db4740318a544",
  "version": "0.1.0"
}
