{
  "commit": "f3b1b183df3bd9f2163349314d04306eafeb1320",
  "repo_url": "https://github.com/peppermint-lab/peppermint",
  "model": "gpt-4o-2024-05-13",
  "chunk_hashes": [
    "93263371cc4b2406fd63"
  ],
  "responses": [
    {
      "content": "```yaml\nleads:\n  - headline: \"SQL Injection in CreateClient\"\n    analysis: |\n      The createClient function sends user input (number, contactName, name, email) directly to the /api/v1/admin/client/create without validation or sanitization. This can lead to SQL injection if the server-side code that processes this data isn't secure.\n    cwe: CWE-89\n    function_names:\n      - createClient\n    filenames:\n      - components/CreateClientModal/index.js\n    classification: very promising\n  - headline: \"Insecure Password Storage\"\n    analysis: |\n      Passwords are hashed with bcrypt but the salt rounds are not specified, which might lead to a lower security hashing. It is important to use a sufficient number of rounds to ensure password security.\n    cwe: CWE-916\n    function_names: []\n    filenames:\n      - pages/api/auth/[...nextauth].js\n    classification: slightly promising\n  - headline: \"Cross-Site Scripting (XSS) in Client Notes\"\n    analysis: |\n      User-provided input (value) is passed to the MDEditor component in the ClientNotesModal without any sanitization. This can lead to stored XSS attacks if the rendered markdown isn't properly sanitized.\n    cwe: CWE-79\n    function_names:\n      - ClientNotesModal\n    filenames:\n      - components/ClientNotesModal/index.js\n    classification: very promising\n  - headline: \"Incorrect Deployment of Server-Side Request Forgery (SSRF) Protection\"\n    analysis: |\n      In multiple webhook implementations, URLs are directly fetched using user-provided input (url). This can lead to SSRF attacks if the URLs are not validated or if requests are not limited.\n    cwe: CWE-918\n    function_names:\n      - createWebhook\n    filenames:\n      - pages/api/v1/admin/webhooks/create.js\n    classification: very promising\n  - headline: \"Hardcoded Secrets in NextAuth Configuration\"\n    analysis: |\n      The NextAuth secret is hardcoded as 'yudjXHbqE5VH4LkwZ4srgsdL2EZrjp' in the options object. Hardcoded secrets compromise the security of the application since they can be easily extracted and used maliciously.\n    cwe: CWE-798\n    function_names: []\n    filenames:\n      - pages/api/auth/[...nextauth].js\n    classification: very promising\n  - headline: \"Command Injection in TransferTicket\"\n    analysis: |\n      Comments indicate placeholders for commands in the ticket transfer function, which if directly executed with user input can lead to command injection attacks.\n    cwe: CWE-77\n    function_names:\n      - TransferTicket\n    filenames:\n      - components/TransferTicket/index.js\n    classification: very promising\n  - headline: \"Race Condition in User Session Management\"\n    analysis: |\n      There could be a race condition in updating the user session where multiple simultaneous requests may lead to an inconsistent state. This isn't directly evident but should be considered.\n    cwe: CWE-362\n    function_names: []\n    filenames:\n      - pages/api/auth/[...nextauth].js\n    classification: slightly promising\n  - headline: \"Improper Error Handling in User Registration\"\n    analysis: |\n      Error objects are caught and a generic error message is returned without logging the actual error. This leads to the inability to investigate issues promptly.\n    cwe: CWE-755\n    function_names: []\n    filenames:\n      - pages/api/v1/admin/user/create.js\n    classification: slightly promising\n```",
      "date": "2024-06-09T14:02:27.794262",
      "usage": {
        "prompt_tokens": 60536,
        "completion_tokens": 743,
        "cost": 0.313825
      }
    }
  ],
  "leads": [
    {
      "headline": "SQL Injection in CreateClient",
      "analysis": "The createClient function sends user input (number, contactName, name, email) directly to the /api/v1/admin/client/create without validation or sanitization. This can lead to SQL injection if the server-side code that processes this data isn't secure.\n",
      "classification": "very promising",
      "cwe": "CWE-89",
      "function_names": [
        "createClient"
      ],
      "filenames": [
        "components/CreateClientModal/index.js"
      ]
    },
    {
      "headline": "Insecure Password Storage",
      "analysis": "Passwords are hashed with bcrypt but the salt rounds are not specified, which might lead to a lower security hashing. It is important to use a sufficient number of rounds to ensure password security.\n",
      "classification": "slightly promising",
      "cwe": "CWE-916",
      "function_names": [],
      "filenames": [
        "pages/api/auth/[...nextauth].js"
      ]
    },
    {
      "headline": "Cross-Site Scripting (XSS) in Client Notes",
      "analysis": "User-provided input (value) is passed to the MDEditor component in the ClientNotesModal without any sanitization. This can lead to stored XSS attacks if the rendered markdown isn't properly sanitized.\n",
      "classification": "very promising",
      "cwe": "CWE-79",
      "function_names": [
        "ClientNotesModal"
      ],
      "filenames": [
        "components/ClientNotesModal/index.js"
      ]
    },
    {
      "headline": "Incorrect Deployment of Server-Side Request Forgery (SSRF) Protection",
      "analysis": "In multiple webhook implementations, URLs are directly fetched using user-provided input (url). This can lead to SSRF attacks if the URLs are not validated or if requests are not limited.\n",
      "classification": "very promising",
      "cwe": "CWE-918",
      "function_names": [
        "createWebhook"
      ],
      "filenames": [
        "pages/api/v1/admin/webhooks/create.js"
      ]
    },
    {
      "headline": "Hardcoded Secrets in NextAuth Configuration",
      "analysis": "The NextAuth secret is hardcoded as 'yudjXHbqE5VH4LkwZ4srgsdL2EZrjp' in the options object. Hardcoded secrets compromise the security of the application since they can be easily extracted and used maliciously.\n",
      "classification": "very promising",
      "cwe": "CWE-798",
      "function_names": [],
      "filenames": [
        "pages/api/auth/[...nextauth].js"
      ]
    },
    {
      "headline": "Command Injection in TransferTicket",
      "analysis": "Comments indicate placeholders for commands in the ticket transfer function, which if directly executed with user input can lead to command injection attacks.\n",
      "classification": "very promising",
      "cwe": "CWE-77",
      "function_names": [
        "TransferTicket"
      ],
      "filenames": [
        "components/TransferTicket/index.js"
      ]
    },
    {
      "headline": "Race Condition in User Session Management",
      "analysis": "There could be a race condition in updating the user session where multiple simultaneous requests may lead to an inconsistent state. This isn't directly evident but should be considered.\n",
      "classification": "slightly promising",
      "cwe": "CWE-362",
      "function_names": [],
      "filenames": [
        "pages/api/auth/[...nextauth].js"
      ]
    },
    {
      "headline": "Improper Error Handling in User Registration",
      "analysis": "Error objects are caught and a generic error message is returned without logging the actual error. This leads to the inability to investigate issues promptly.\n",
      "classification": "slightly promising",
      "cwe": "CWE-755",
      "function_names": [],
      "filenames": [
        "pages/api/v1/admin/user/create.js"
      ]
    }
  ],
  "scores": [
    {
      "stats": {
        "fn": 4,
        "tp": 0,
        "fp": 5
      },
      "mapping": {},
      "vuln_dates": {
        "CVE-2023-42328": "2023-09-18T16:15:45",
        "CVE-2023-26984": "2023-03-29T18:15:07",
        "CVE-2023-46864": "2023-10-30T00:15:39",
        "CVE-2023-46863": "2023-10-30T00:15:39"
      },
      "scoring_model": "gpt-4o-2024-05-13",
      "type": "llm",
      "instruction_template_hash": "8998f09cf57fca8a6e03"
    },
    {
      "stats": {
        "fn": 4,
        "tp": 0,
        "fp": 5
      },
      "mapping": {},
      "vuln_dates": {
        "CVE-2023-42328": "2023-09-18T16:15:45",
        "CVE-2023-26984": "2023-03-29T18:15:07",
        "CVE-2023-46864": "2023-10-30T00:15:39",
        "CVE-2023-46863": "2023-10-30T00:15:39"
      },
      "scoring_model": "claude-3-opus-20240229",
      "type": "llm",
      "instruction_template_hash": "245ace12b6361954d0a2"
    }
  ],
  "instruction_template_hash": "10c0163db4740318a544",
  "version": "0.1.0"
}
