{
  "commit": "99eb6766d20df0c3cbacc14d7de29ac9b3616788",
  "repo_url": "https://github.com/brefphp/bref",
  "model": "gpt-4o-2024-05-13",
  "chunk_hashes": [
    "f21aff3ed4d3f7e07eac"
  ],
  "responses": [
    {
      "content": "```yaml\nleads:\n  - headline: Potential Directory Traversal Vulnerability\n    analysis: |\n      The function `includeBrefLayers` in `plugin/serverless.ts` uses user-provided `layerName` to resolve file paths. This can lead to a directory traversal vulnerability if an attacker can control `layerName` to escape the intended directory and access unintended files.\n    cwe: CWE-22\n    function_names:\n      - includeBrefLayers\n    filenames:\n      - plugin/serverless.ts\n    classification: very promising\n\n  - headline: Improper Input Validation for Layer ARN\n    analysis: |\n      In the function `getConsoleLayerArn` in `plugin/run-console.js`, the layer ARN is assembled using values from a JSON file without proper validation. If the JSON data or `region` value is compromised, it could lead to invalid ARNs affecting the functionality.\n    cwe: CWE-20\n    function_names:\n      - getConsoleLayerArn\n    filenames:\n      - plugin/run-console.js\n    classification: slightly promising\n\n  - headline: Potential Command Injection in runLocal\n    analysis: |\n      The `runLocal` function in `plugin/local.js` uses `spawnSync` with user-controlled input without proper sanitization. This opens the possibility for an attacker to provide malicious input that could lead to command injection.\n    cwe: CWE-78\n    function_names:\n      - runLocal\n    filenames:\n      - plugin/local.js\n    classification: very promising\n\n  - headline: Lack of Error Handling in Telemetry Function\n    analysis: |\n      The `telemetry` function in `plugin/serverless.ts` sends data over the network without adequate error handling. A network failure or malformed payload could cause the function to fail silently, potentially losing important telemetry data.\n    cwe: CWE-754\n    function_names:\n      - telemetry\n    filenames:\n      - plugin/serverless.ts\n    classification: slightly promising\n\n  - headline: Information Exposure via Telemetry Data\n    analysis: |\n      The `telemetry` function in `plugin/serverless.ts` includes detailed user environment information in the payload sent over the network. This could inadvertently expose sensitive user information if not properly secured.\n    cwe: CWE-200\n    function_names:\n      - telemetry\n    filenames:\n      - plugin/serverless.ts\n    classification: slightly promising\n\n  - headline: Insufficient Synchronization in GuzzleServer\n    analysis: |\n      The `GuzzleServer` class in `tests/server.js` lacks proper synchronization mechanisms. The simultaneous addition of responses and modification of shared state could cause race conditions.\n    cwe: CWE-362\n    function_names:\n      - controlRequest\n      - receivedRequest\n    filenames:\n      - tests/server.js\n    classification: very promising\n\n  - headline: Unauthenticated File Access in Serverless Plugin\n    analysis: |\n      The `ServerlessPlugin` class in `index.js` reads sensitive files like `layers.json` without validating the caller's permissions or authenticity. This could allow unauthorized users to access sensitive data or modify plugin behavior.\n    cwe: CWE-668\n    function_names:\n      - constructor\n    filenames:\n      - index.js\n    classification: slightly promising\n```",
      "date": "2024-06-09T09:18:06.372140",
      "usage": {
        "prompt_tokens": 14814,
        "completion_tokens": 667,
        "cost": 0.084075
      }
    }
  ],
  "leads": [
    {
      "headline": "Potential Directory Traversal Vulnerability",
      "analysis": "The function includeBrefLayers in plugin/serverless.ts uses user-provided layerName to resolve file paths. This can lead to a directory traversal vulnerability if an attacker can control layerName to escape the intended directory and access unintended files.\n",
      "classification": "very promising",
      "cwe": "CWE-22",
      "function_names": [
        "includeBrefLayers"
      ],
      "filenames": [
        "plugin/serverless.ts"
      ]
    },
    {
      "headline": "Improper Input Validation for Layer ARN",
      "analysis": "In the function getConsoleLayerArn in plugin/run-console.js, the layer ARN is assembled using values from a JSON file without proper validation. If the JSON data or region value is compromised, it could lead to invalid ARNs affecting the functionality.\n",
      "classification": "slightly promising",
      "cwe": "CWE-20",
      "function_names": [
        "getConsoleLayerArn"
      ],
      "filenames": [
        "plugin/run-console.js"
      ]
    },
    {
      "headline": "Potential Command Injection in runLocal",
      "analysis": "The runLocal function in plugin/local.js uses spawnSync with user-controlled input without proper sanitization. This opens the possibility for an attacker to provide malicious input that could lead to command injection.\n",
      "classification": "very promising",
      "cwe": "CWE-78",
      "function_names": [
        "runLocal"
      ],
      "filenames": [
        "plugin/local.js"
      ]
    },
    {
      "headline": "Lack of Error Handling in Telemetry Function",
      "analysis": "The telemetry function in plugin/serverless.ts sends data over the network without adequate error handling. A network failure or malformed payload could cause the function to fail silently, potentially losing important telemetry data.\n",
      "classification": "slightly promising",
      "cwe": "CWE-754",
      "function_names": [
        "telemetry"
      ],
      "filenames": [
        "plugin/serverless.ts"
      ]
    },
    {
      "headline": "Information Exposure via Telemetry Data",
      "analysis": "The telemetry function in plugin/serverless.ts includes detailed user environment information in the payload sent over the network. This could inadvertently expose sensitive user information if not properly secured.\n",
      "classification": "slightly promising",
      "cwe": "CWE-200",
      "function_names": [
        "telemetry"
      ],
      "filenames": [
        "plugin/serverless.ts"
      ]
    },
    {
      "headline": "Insufficient Synchronization in GuzzleServer",
      "analysis": "The GuzzleServer class in tests/server.js lacks proper synchronization mechanisms. The simultaneous addition of responses and modification of shared state could cause race conditions.\n",
      "classification": "very promising",
      "cwe": "CWE-362",
      "function_names": [
        "controlRequest",
        "receivedRequest"
      ],
      "filenames": [
        "tests/server.js"
      ]
    },
    {
      "headline": "Unauthenticated File Access in Serverless Plugin",
      "analysis": "The ServerlessPlugin class in index.js reads sensitive files like layers.json without validating the caller's permissions or authenticity. This could allow unauthorized users to access sensitive data or modify plugin behavior.\n",
      "classification": "slightly promising",
      "cwe": "CWE-668",
      "function_names": [
        "constructor"
      ],
      "filenames": [
        "index.js"
      ]
    }
  ],
  "scores": [
    {
      "stats": {
        "fn": 4,
        "tp": 0,
        "fp": 3
      },
      "mapping": {},
      "vuln_dates": {
        "CVE-2024-24752": "2024-02-01T16:17:14",
        "CVE-2024-24753": "2024-02-01T16:17:14",
        "CVE-2024-24754": "2024-02-01T16:17:14",
        "CVE-2024-29186": "2024-03-22T17:15:08"
      },
      "scoring_model": "gpt-4o-2024-05-13",
      "type": "llm",
      "instruction_template_hash": "8998f09cf57fca8a6e03"
    },
    {
      "stats": {
        "fn": 4,
        "tp": 0,
        "fp": 3
      },
      "mapping": {},
      "vuln_dates": {
        "CVE-2024-24752": "2024-02-01T16:17:14",
        "CVE-2024-24753": "2024-02-01T16:17:14",
        "CVE-2024-24754": "2024-02-01T16:17:14",
        "CVE-2024-29186": "2024-03-22T17:15:08"
      },
      "scoring_model": "claude-3-opus-20240229",
      "type": "llm",
      "instruction_template_hash": "245ace12b6361954d0a2"
    }
  ],
  "instruction_template_hash": "10c0163db4740318a544",
  "version": "0.1.0"
}
