{
  "commit": "3e1b59c8d95c1be8ad536088a389a3f36dec15a2",
  "repo_url": "https://github.com/aiven-open/journalpump",
  "model": "gpt-4o-2024-05-13",
  "chunk_hashes": [
    "d4a5785f40ad2352b38c"
  ],
  "responses": [
    {
      "content": "```yaml\nleads:\n  - headline: Multiple Senders Fail Gracefully\n    analysis: |\n      The JournalReader class handles multiple senders, some of which may fail during initialization due to incorrect configurations or other issues. The _init_kafka method is primarily responsible for initializing Kafka senders and managing connection properties. The handling involves retry mechanisms, backoff strategies, and the ability to gracefully handle exceptions without crashing the reader.\n    cwe: CWE-754\n    function_names:\n      - _init_kafka\n      - get_sender_class\n      - mark_disconnected\n    filenames:\n      - journalpump/journalpump.py\n      - journalpump/senders/__init__.py\n    classification: slightly promising\n\n  - headline: AWS CloudWatch Sender Initialization Exception Handling\n    analysis: |\n      The AWSCloudWatchSender class, during its initialization, handles common client errors, including AccessDeniedException. If it detects this particular error, it retries the initialization multiple times before eventually raising a SenderInitializationError. This behavior is crucial for maintaining robust error handling and service continuity.\n    cwe: CWE-754\n    function_names:\n      - _init_logs\n      - AWSCloudWatchSender.__init__\n    filenames:\n      - journalpump/senders/aws_cloudwatch.py\n    classification: very promising\n\n  - headline: Invalid Memory Access Handling in Senders\n    analysis: |\n      The _send method in various sender classes (like WebSocket and Kafka) include mechanisms to handle broad exceptions during message sending operations. This allows the senders to maintain stability and attempt reconnections or retries, preventing unexpected crashes due to unforeseen issues in network communication or message serialization.\n    cwe: CWE-119\n    function_names:\n      - _send\n      - send_messages\n    filenames:\n      - journalpump/senders/kafka.py\n      - journalpump/senders/base.py\n    classification: very promising\n\n  - headline: Use of Broad Exception Handling\n    analysis: |\n      The utilization of broad exception handling patterns is prevalent in the codebase, especially in the sender and reader classes. This can obscure the specific causes of exceptions, making debugging and maintenance more difficult. Improving exception granularity can enhance code reliability and support easier error tracing.\n    cwe: CWE-705\n    function_names:\n      - send_messages\n      - _send\n      - __init__\n    filenames:\n      - journalpump/senders/kafka.py\n      - journalpump/util.py\n    classification: slightly promising\n\n  - headline: Insecure Log Handling\n    analysis: |\n      The use of logging with sensitive information needs careful evaluation to ensure no critical data gets exposed inadvertently. This becomes critical while handling exceptions, errors, and debug information in different sender implementations.\n    cwe: CWE-532\n    function_names:\n      - log\n      - send_messages\n      - _send\n    filenames:\n      - journalpump/senders/base.py\n      - journalpump/journalpump.py\n    classification: very promising\n```",
      "date": "2024-06-08T22:08:57.790289",
      "usage": {
        "prompt_tokens": 55002,
        "completion_tokens": 612,
        "cost": 0.28419
      }
    }
  ],
  "leads": [
    {
      "headline": "Multiple Senders Fail Gracefully",
      "analysis": "The JournalReader class handles multiple senders, some of which may fail during initialization due to incorrect configurations or other issues. The _init_kafka method is primarily responsible for initializing Kafka senders and managing connection properties. The handling involves retry mechanisms, backoff strategies, and the ability to gracefully handle exceptions without crashing the reader.\n",
      "classification": "slightly promising",
      "cwe": "CWE-754",
      "function_names": [
        "_init_kafka",
        "get_sender_class",
        "mark_disconnected"
      ],
      "filenames": [
        "journalpump/journalpump.py",
        "journalpump/senders/__init__.py"
      ]
    },
    {
      "headline": "AWS CloudWatch Sender Initialization Exception Handling",
      "analysis": "The AWSCloudWatchSender class, during its initialization, handles common client errors, including AccessDeniedException. If it detects this particular error, it retries the initialization multiple times before eventually raising a SenderInitializationError. This behavior is crucial for maintaining robust error handling and service continuity.\n",
      "classification": "very promising",
      "cwe": "CWE-754",
      "function_names": [
        "_init_logs",
        "AWSCloudWatchSender.__init__"
      ],
      "filenames": [
        "journalpump/senders/aws_cloudwatch.py"
      ]
    },
    {
      "headline": "Invalid Memory Access Handling in Senders",
      "analysis": "The _send method in various sender classes (like WebSocket and Kafka) include mechanisms to handle broad exceptions during message sending operations. This allows the senders to maintain stability and attempt reconnections or retries, preventing unexpected crashes due to unforeseen issues in network communication or message serialization.\n",
      "classification": "very promising",
      "cwe": "CWE-119",
      "function_names": [
        "_send",
        "send_messages"
      ],
      "filenames": [
        "journalpump/senders/kafka.py",
        "journalpump/senders/base.py"
      ]
    },
    {
      "headline": "Use of Broad Exception Handling",
      "analysis": "The utilization of broad exception handling patterns is prevalent in the codebase, especially in the sender and reader classes. This can obscure the specific causes of exceptions, making debugging and maintenance more difficult. Improving exception granularity can enhance code reliability and support easier error tracing.\n",
      "classification": "slightly promising",
      "cwe": "CWE-705",
      "function_names": [
        "send_messages",
        "_send",
        "__init__"
      ],
      "filenames": [
        "journalpump/senders/kafka.py",
        "journalpump/util.py"
      ]
    },
    {
      "headline": "Insecure Log Handling",
      "analysis": "The use of logging with sensitive information needs careful evaluation to ensure no critical data gets exposed inadvertently. This becomes critical while handling exceptions, errors, and debug information in different sender implementations.\n",
      "classification": "very promising",
      "cwe": "CWE-532",
      "function_names": [
        "log",
        "send_messages",
        "_send"
      ],
      "filenames": [
        "journalpump/senders/base.py",
        "journalpump/journalpump.py"
      ]
    }
  ],
  "scores": [
    {
      "stats": {
        "fn": 0,
        "tp": 1,
        "fp": 2
      },
      "mapping": {
        "2": "CVE-2023-51390"
      },
      "vuln_dates": {
        "CVE-2023-51390": "2023-12-21T00:15:26"
      },
      "scoring_model": "gpt-4o-2024-05-13",
      "type": "llm",
      "instruction_template_hash": "8998f09cf57fca8a6e03"
    }
  ],
  "instruction_template_hash": "10c0163db4740318a544",
  "version": "0.1.0"
}
