{
  "commit": "3a0699d2a90544a0f8928c40947b119e9491c2fa",
  "repo_url": "https://github.com/senchalabs/connect",
  "model": "claude-3-5-sonnet-20240620",
  "chunk_hashes": [
    "1fe5273731f7746154fc"
  ],
  "responses": [
    {
      "content": "Here are the main security vulnerabilities I identified in the Connect codebase:\n\n1. Prototype Pollution in cookieParser middleware\n\n```yaml\nleads:\n  - headline: Prototype pollution vulnerability in cookieParser middleware\n    analysis: |\n      The cookieParser middleware uses the utils.parseJSONCookies function to parse JSON-encoded cookie values. This function uses JSON.parse without any sanitization, which can lead to prototype pollution if an attacker can control the cookie values. An attacker could potentially pollute Object.prototype by setting a malicious __proto__ property in a cookie value.\n    cwe: CWE-1321\n    function_names:\n      - cookieParser\n      - parseJSONCookies  \n    filenames:\n      - lib/middleware/cookieParser.js\n      - lib/utils.js\n    classification: very promising\n\n  - headline: Path traversal vulnerability in static file serving middleware\n    analysis: |\n      The static file serving middleware does not properly sanitize file paths, allowing potential path traversal attacks. It uses the normalize() function on user-provided paths, but this is not sufficient to prevent all path traversal vectors. An attacker could potentially access files outside the intended directory by using sequences like \"../\".\n    cwe: CWE-22\n    function_names:\n      - staticMiddleware\n    filenames:\n      - lib/middleware/static.js\n    classification: very promising\n\n  - headline: Insecure random token generation in CSRF protection\n    analysis: |\n      The CSRF protection middleware uses Math.random() to generate CSRF tokens. This is not a cryptographically secure random number generator and could potentially be predicted by attackers. This may allow bypassing of CSRF protections if an attacker can guess valid tokens.\n    cwe: CWE-338  \n    function_names:\n      - generateSalt\n    filenames:\n      - lib/middleware/csrf.js\n    classification: slightly promising\n\n  - headline: Possible XSS in directory listing functionality\n    analysis: |\n      The directory listing functionality does not properly encode user-controlled filenames before inserting them into the HTML response. This could potentially allow XSS attacks if a malicious filename containing JavaScript is encountered and rendered in the directory listing.\n    cwe: CWE-79\n    function_names: []\n    filenames:\n      - lib/middleware/directory.js\n    classification: slightly promising\n\n  - headline: Unbounded memory usage in MemoryStore session storage\n    analysis: |\n      The MemoryStore used for session storage does not limit the number of sessions or the size of session data. This could potentially lead to denial of service through memory exhaustion if an attacker creates many sessions with large amounts of data.\n    cwe: CWE-400\n    function_names:\n      - MemoryStore\n    filenames:\n      - lib/middleware/session/memory.js  \n    classification: slightly promising\n```\n\nThese represent the most critical security issues I identified in my review of the Connect codebase. The prototype pollution and path traversal vulnerabilities are particularly concerning and should be addressed as high priorities. The other issues are still important but may have a lower severity or exploitability.",
      "date": "2024-07-08T08:30:31.353692",
      "usage": {
        "prompt_tokens": 125120,
        "completion_tokens": 728,
        "cost": 0.38628
      }
    }
  ],
  "leads": [
    {
      "headline": "Prototype pollution vulnerability in cookieParser middleware",
      "analysis": "The cookieParser middleware uses the utils.parseJSONCookies function to parse JSON-encoded cookie values. This function uses JSON.parse without any sanitization, which can lead to prototype pollution if an attacker can control the cookie values. An attacker could potentially pollute Object.prototype by setting a malicious __proto__ property in a cookie value.\n",
      "classification": "very promising",
      "cwe": "CWE-1321",
      "function_names": [
        "cookieParser",
        "parseJSONCookies"
      ],
      "filenames": [
        "lib/middleware/cookieParser.js",
        "lib/utils.js"
      ]
    },
    {
      "headline": "Path traversal vulnerability in static file serving middleware",
      "analysis": "The static file serving middleware does not properly sanitize file paths, allowing potential path traversal attacks. It uses the normalize() function on user-provided paths, but this is not sufficient to prevent all path traversal vectors. An attacker could potentially access files outside the intended directory by using sequences like \"../\".\n",
      "classification": "very promising",
      "cwe": "CWE-22",
      "function_names": [
        "staticMiddleware"
      ],
      "filenames": [
        "lib/middleware/static.js"
      ]
    },
    {
      "headline": "Insecure random token generation in CSRF protection",
      "analysis": "The CSRF protection middleware uses Math.random() to generate CSRF tokens. This is not a cryptographically secure random number generator and could potentially be predicted by attackers. This may allow bypassing of CSRF protections if an attacker can guess valid tokens.\n",
      "classification": "slightly promising",
      "cwe": "CWE-338",
      "function_names": [
        "generateSalt"
      ],
      "filenames": [
        "lib/middleware/csrf.js"
      ]
    },
    {
      "headline": "Possible XSS in directory listing functionality",
      "analysis": "The directory listing functionality does not properly encode user-controlled filenames before inserting them into the HTML response. This could potentially allow XSS attacks if a malicious filename containing JavaScript is encountered and rendered in the directory listing.\n",
      "classification": "slightly promising",
      "cwe": "CWE-79",
      "function_names": [],
      "filenames": [
        "lib/middleware/directory.js"
      ]
    },
    {
      "headline": "Unbounded memory usage in MemoryStore session storage",
      "analysis": "The MemoryStore used for session storage does not limit the number of sessions or the size of session data. This could potentially lead to denial of service through memory exhaustion if an attacker creates many sessions with large amounts of data.\n",
      "classification": "slightly promising",
      "cwe": "CWE-400",
      "function_names": [
        "MemoryStore"
      ],
      "filenames": [
        "lib/middleware/session/memory.js"
      ]
    }
  ],
  "scores": [
    {
      "stats": {
        "fn": 1,
        "tp": 0,
        "fp": 2
      },
      "mapping": {},
      "vuln_dates": {
        "CVE-2018-3717": "2018-06-07T02:29:08"
      },
      "scoring_model": "claude-3-5-sonnet-20240620",
      "type": "llm",
      "instruction_template_hash": "245ace12b6361954d0a2"
    }
  ],
  "instruction_template_hash": "10c0163db4740318a544",
  "version": "0.1.0"
}
