{
  "commit": "e110ffd335ba4181c2e298e3d30ce8b6b51bfcd6",
  "repo_url": "https://github.com/michaeldaum/spreadsheet-parsexlsx",
  "model": "gpt-4o-2024-05-13",
  "chunk_hashes": [
    "0a3a532ab61ef0da5dcc"
  ],
  "responses": [
    {
      "content": "```yaml\nleads:\n  - headline: \"Possible Command Injection via Decryption Password Parameter\"\n    analysis: |\n      The code in `Spreadsheet::ParseXLSX::Decryptor` and `Spreadsheet::ParseXLSX::Decryptor::Standard` handles decrypted passwords, but there is no validation or sanitization of the input password. An attacker could potentially exploit this by providing a malicious string as a password, leading to command injection.\n    cwe: CWE-78\n    function_names:\n      - \"Spreadsheet::ParseXLSX::Decryptor::Standard::_generateDecryptionKey\"\n      - \"Spreadsheet::ParseXLSX::Decryptor::Standard::verifyPassword\"\n      - \"Spreadsheet::ParseXLSX::Decryptor::open\"\n    filenames:\n      - \"lib/Spreadsheet/ParseXLSX/Decryptor.pm\"\n      - \"lib/Spreadsheet/ParseXLSX/Decryptor/Standard.pm\"\n    classification: very promising\n\n  - headline: \"Improper XML Handling Leading to XML External Entity (XXE) Injection\"\n    analysis: |\n      The code uses `XML::Twig` to parse XML files without enabling the appropriate protections against XML External Entity (XXE) injection. If an attacker can control the XML input, they could exploit this vulnerability to read arbitrary files from the filesystem or initiate network requests.\n    cwe: CWE-611\n    function_names:\n      - \"_parse_xml\"\n      - \"_parse_sheet\"\n      - \"_extract_files\"\n    filenames:\n      - \"lib/Spreadsheet/ParseXLSX.pm\"\n    classification: very promising\n\n  - headline: \"Insecure Temporary File Creation\"\n    analysis: |\n      The use of `File::Temp` to create temporary files without proper security options may lead to a situation where an attacker can exploit the race condition between the file creation and its usage. This could lead to data exposure or corruption.\n    cwe: CWE-377\n    function_names:\n      - \"Spreadsheet::ParseXLSX::Decryptor::_getCompoundData\"\n      - \"Spreadsheet::ParseXLSX::Decryptor::_standardDecryption\"\n      - \"Spreadsheet::ParseXLSX::Decryptor::_agileDecryption\"\n    filenames:\n      - \"lib/Spreadsheet/ParseXLSX/Decryptor.pm\"\n    classification: very promising\n\n  - headline: \"Memory Management Issue: Large Files Leading to Out of Memory\"\n    analysis: |\n      The module uses `XML::Twig` which can lead to high memory consumption when processing large files. This can cause the application to crash or become unresponsive, which constitutes a denial of service attack.\n    cwe: CWE-400\n    function_names:\n      - \"_new_twig\"\n    filenames:\n      - \"lib/Spreadsheet/ParseXLSX.pm\"\n    classification: slightly promising\n\n  - headline: \"Lack of Proper Error Handling\"\n    analysis: |\n      The code contains several instances where potential error conditions are not properly handled. For example, checking for the success of file operations and calling `die` on failure without cleaning up resources can lead to incomplete operations or data corruption.\n    cwe: CWE-754\n    function_names:\n      - \"Spreadsheet::ParseXLSX::parse\"\n      - '_parse_xml'\n      - '_zip_file_member'\n    filenames:\n      - \"lib/Spreadsheet/ParseXLSX.pm\"\n    classification: slightly promising\n```",
      "date": "2024-06-09T13:32:13.536605",
      "usage": {
        "prompt_tokens": 30782,
        "completion_tokens": 703,
        "cost": 0.164455
      }
    }
  ],
  "leads": [
    {
      "headline": "Possible Command Injection via Decryption Password Parameter",
      "analysis": "The code in Spreadsheet::ParseXLSX::Decryptor and Spreadsheet::ParseXLSX::Decryptor::Standard handles decrypted passwords, but there is no validation or sanitization of the input password. An attacker could potentially exploit this by providing a malicious string as a password, leading to command injection.\n",
      "classification": "very promising",
      "cwe": "CWE-78",
      "function_names": [
        "Spreadsheet::ParseXLSX::Decryptor::Standard::_generateDecryptionKey",
        "Spreadsheet::ParseXLSX::Decryptor::Standard::verifyPassword",
        "Spreadsheet::ParseXLSX::Decryptor::open"
      ],
      "filenames": [
        "lib/Spreadsheet/ParseXLSX/Decryptor.pm",
        "lib/Spreadsheet/ParseXLSX/Decryptor/Standard.pm"
      ]
    },
    {
      "headline": "Improper XML Handling Leading to XML External Entity (XXE) Injection",
      "analysis": "The code uses XML::Twig to parse XML files without enabling the appropriate protections against XML External Entity (XXE) injection. If an attacker can control the XML input, they could exploit this vulnerability to read arbitrary files from the filesystem or initiate network requests.\n",
      "classification": "very promising",
      "cwe": "CWE-611",
      "function_names": [
        "_parse_xml",
        "_parse_sheet",
        "_extract_files"
      ],
      "filenames": [
        "lib/Spreadsheet/ParseXLSX.pm"
      ]
    },
    {
      "headline": "Insecure Temporary File Creation",
      "analysis": "The use of File::Temp to create temporary files without proper security options may lead to a situation where an attacker can exploit the race condition between the file creation and its usage. This could lead to data exposure or corruption.\n",
      "classification": "very promising",
      "cwe": "CWE-377",
      "function_names": [
        "Spreadsheet::ParseXLSX::Decryptor::_getCompoundData",
        "Spreadsheet::ParseXLSX::Decryptor::_standardDecryption",
        "Spreadsheet::ParseXLSX::Decryptor::_agileDecryption"
      ],
      "filenames": [
        "lib/Spreadsheet/ParseXLSX/Decryptor.pm"
      ]
    },
    {
      "headline": "Memory Management Issue: Large Files Leading to Out of Memory",
      "analysis": "The module uses XML::Twig which can lead to high memory consumption when processing large files. This can cause the application to crash or become unresponsive, which constitutes a denial of service attack.\n",
      "classification": "slightly promising",
      "cwe": "CWE-400",
      "function_names": [
        "_new_twig"
      ],
      "filenames": [
        "lib/Spreadsheet/ParseXLSX.pm"
      ]
    },
    {
      "headline": "Lack of Proper Error Handling",
      "analysis": "The code contains several instances where potential error conditions are not properly handled. For example, checking for the success of file operations and calling die on failure without cleaning up resources can lead to incomplete operations or data corruption.\n",
      "classification": "slightly promising",
      "cwe": "CWE-754",
      "function_names": [
        "Spreadsheet::ParseXLSX::parse",
        "_parse_xml",
        "_zip_file_member"
      ],
      "filenames": [
        "lib/Spreadsheet/ParseXLSX.pm"
      ]
    }
  ],
  "scores": [
    {
      "stats": {
        "fn": 0,
        "tp": 1,
        "fp": 2
      },
      "mapping": {
        "1": "CVE-2024-23525"
      },
      "vuln_dates": {
        "CVE-2024-23525": "2024-01-18T00:15:38"
      },
      "scoring_model": "gpt-4o-2024-05-13",
      "type": "llm",
      "instruction_template_hash": "8998f09cf57fca8a6e03"
    },
    {
      "stats": {
        "fn": 0,
        "tp": 1,
        "fp": 2
      },
      "mapping": {
        "1": "CVE-2024-23525"
      },
      "vuln_dates": {
        "CVE-2024-23525": "2024-01-18T00:15:38"
      },
      "scoring_model": "claude-3-opus-20240229",
      "type": "llm",
      "instruction_template_hash": "245ace12b6361954d0a2"
    },
    {
      "stats": {
        "fn": 0,
        "tp": 1,
        "fp": 2
      },
      "mapping": {
        "1": "CVE-2024-23525"
      },
      "vuln_dates": {
        "CVE-2024-23525": "2024-01-18T00:15:38"
      },
      "scoring_model": "claude-3-5-sonnet-20240620",
      "type": "llm",
      "instruction_template_hash": "245ace12b6361954d0a2"
    }
  ],
  "instruction_template_hash": "10c0163db4740318a544",
  "version": "0.1.0"
}
