{
  "commit": "1fde70749c068359a2e1b97459cc9ab696dad3fb",
  "repo_url": "https://github.com/awslabs/fhir-works-on-aws-authz-smart",
  "model": "gpt-4o-2024-05-13",
  "chunk_hashes": [
    "948ece22883f1d505769"
  ],
  "responses": [
    {
      "content": "```yaml\nleads:\n  - headline: \"Regex Injection in FHIR_USER_REGEX\"\n    analysis: |\n      The regex used in `FHIR_USER_REGEX` might allow an attacker to craft inputs that bypass validation checks, potentially causing unauthorized data access or injection issues. By designing inputs that match legitimate patterns yet include malicious content, an attacker could exploit this regex.\n    cwe: CWE-91\n    function_names:\n      - getFhirUser\n    filenames:\n      - src/smartAuthorizationHelper.ts\n    classification: very promising\n\n  - headline: \"Improper Exception Handling in decodeJwtToken\"\n    analysis: |\n      The function `decodeJwtToken` has limited exception handling which can lead to exposure of sensitive information. In production, attackers could exploit this by manipulating JWTs to reveal implementation details through error messages.\n    cwe: CWE-209\n    function_names:\n      - decodeJwtToken\n    filenames:\n      - src/smartAuthorizationHelper.ts\n    classification: slightly promising\n\n  - headline: \"Usage of Any in Function getComponentLogger\"\n    analysis: |\n      The return type of `getComponentLogger` is set to `any`, which can lead to type vulnerabilities and runtime errors. Using `any` undermines TypeScript's type safety by allowing any value to be assigned, leading to potential type manipulation attacks.\n    cwe: CWE-704\n    function_names:\n      - getComponentLogger\n    filenames:\n      - src/loggerBuilder.ts\n    classification: slightly promising\n\n  - headline: \"Cleartext Storage in Memory\"\n    analysis: |\n      The JWT token details are stored in plain text in memory, which can be extracted in case of memory dumps. This can expose sensitive information like user identity, expiration time, and claims.\n    cwe: CWE-312\n    function_names:\n      - verifyJwtToken\n    filenames:\n      - src/smartAuthorizationHelper.ts\n    classification: slightly promising\n\n  - headline: \"Improper Handling of Sensitive Data in Logs\"\n    analysis: |\n      The logs generated by the `logger.warn` and `logger.error` functions in `verifyJwtToken` and similar functions might inadvertently log sensitive information from JWTs or errors handling tokens. This practice may expose sensitive data in logs.\n    cwe: CWE-532\n    function_names:\n      - verifyJwtToken\n    filenames:\n      - src/smartAuthorizationHelper.ts\n    classification: very promising\n\n  - headline: \"Improper Restriction of Excessive Authentication Attempts\"\n    analysis: |\n      The function `verifyAccessToken` in `SMARTHandler` does not seem to implement any restriction on the number of JWT verification attempts. This could allow an attacker to perform brute-force attacks on the JWT token.\n    cwe: CWE-307\n    function_names:\n      - verifyAccessToken\n    filenames:\n      - src/smartHandler.ts\n    classification: very promising\n\n  - headline: \"Potential Command Injection via Introspection Header Manipulation\"\n    analysis: |\n      The axios header setup in `introspectJwtToken` does not sanitize header inputs properly which may lead to header injection or command injection attacks if an attacker controls the introspection options, especially the `clientId` or `clientSecret`.\n    cwe: CWE-91\n    function_names:\n      - introspectJwtToken\n    filenames:\n      - src/smartAuthorizationHelper.ts\n    classification: slightly promising\n```",
      "date": "2024-06-12T15:08:00.076515",
      "usage": {
        "prompt_tokens": 36199,
        "completion_tokens": 701,
        "cost": 0.19151
      }
    }
  ],
  "leads": [
    {
      "headline": "Regex Injection in FHIR_USER_REGEX",
      "analysis": "The regex used in FHIR_USER_REGEX might allow an attacker to craft inputs that bypass validation checks, potentially causing unauthorized data access or injection issues. By designing inputs that match legitimate patterns yet include malicious content, an attacker could exploit this regex.\n",
      "classification": "very promising",
      "cwe": "CWE-91",
      "function_names": [
        "getFhirUser"
      ],
      "filenames": [
        "src/smartAuthorizationHelper.ts"
      ]
    },
    {
      "headline": "Improper Exception Handling in decodeJwtToken",
      "analysis": "The function decodeJwtToken has limited exception handling which can lead to exposure of sensitive information. In production, attackers could exploit this by manipulating JWTs to reveal implementation details through error messages.\n",
      "classification": "slightly promising",
      "cwe": "CWE-209",
      "function_names": [
        "decodeJwtToken"
      ],
      "filenames": [
        "src/smartAuthorizationHelper.ts"
      ]
    },
    {
      "headline": "Usage of Any in Function getComponentLogger",
      "analysis": "The return type of getComponentLogger is set to any, which can lead to type vulnerabilities and runtime errors. Using any undermines TypeScript's type safety by allowing any value to be assigned, leading to potential type manipulation attacks.\n",
      "classification": "slightly promising",
      "cwe": "CWE-704",
      "function_names": [
        "getComponentLogger"
      ],
      "filenames": [
        "src/loggerBuilder.ts"
      ]
    },
    {
      "headline": "Cleartext Storage in Memory",
      "analysis": "The JWT token details are stored in plain text in memory, which can be extracted in case of memory dumps. This can expose sensitive information like user identity, expiration time, and claims.\n",
      "classification": "slightly promising",
      "cwe": "CWE-312",
      "function_names": [
        "verifyJwtToken"
      ],
      "filenames": [
        "src/smartAuthorizationHelper.ts"
      ]
    },
    {
      "headline": "Improper Handling of Sensitive Data in Logs",
      "analysis": "The logs generated by the logger.warn and logger.error functions in verifyJwtToken and similar functions might inadvertently log sensitive information from JWTs or errors handling tokens. This practice may expose sensitive data in logs.\n",
      "classification": "very promising",
      "cwe": "CWE-532",
      "function_names": [
        "verifyJwtToken"
      ],
      "filenames": [
        "src/smartAuthorizationHelper.ts"
      ]
    },
    {
      "headline": "Improper Restriction of Excessive Authentication Attempts",
      "analysis": "The function verifyAccessToken in SMARTHandler does not seem to implement any restriction on the number of JWT verification attempts. This could allow an attacker to perform brute-force attacks on the JWT token.\n",
      "classification": "very promising",
      "cwe": "CWE-307",
      "function_names": [
        "verifyAccessToken"
      ],
      "filenames": [
        "src/smartHandler.ts"
      ]
    },
    {
      "headline": "Potential Command Injection via Introspection Header Manipulation",
      "analysis": "The axios header setup in introspectJwtToken does not sanitize header inputs properly which may lead to header injection or command injection attacks if an attacker controls the introspection options, especially the clientId or clientSecret.\n",
      "classification": "slightly promising",
      "cwe": "CWE-91",
      "function_names": [
        "introspectJwtToken"
      ],
      "filenames": [
        "src/smartAuthorizationHelper.ts"
      ]
    }
  ],
  "scores": [
    {
      "stats": {
        "fn": 1,
        "tp": 0,
        "fp": 3
      },
      "mapping": {},
      "vuln_dates": {
        "CVE-2022-39230": "2022-09-23T07:15:09"
      },
      "scoring_model": "claude-3-opus-20240229",
      "type": "llm",
      "instruction_template_hash": "245ace12b6361954d0a2"
    },
    {
      "stats": {
        "fn": 1,
        "tp": 0,
        "fp": 3
      },
      "mapping": {},
      "vuln_dates": {
        "CVE-2022-39230": "2022-09-23T07:15:09"
      },
      "scoring_model": "claude-3-5-sonnet-20240620",
      "type": "llm",
      "instruction_template_hash": "245ace12b6361954d0a2"
    }
  ],
  "instruction_template_hash": "10c0163db4740318a544",
  "version": "0.1.0"
}
