{
  "commit": "232a58021af8dd3eea9ff0e4482cc2f6138ac7ad",
  "repo_url": "https://github.com/relekang/django-nopassword",
  "model": "claude-3-haiku-20240307",
  "chunk_hashes": [
    "244e4376c9b85073f708"
  ],
  "responses": [
    {
      "content": "```yaml\nleads:\n  - headline: Improper Input Validation\n    analysis: |\n      The codebase contains several instances of improper input validation, which can lead to vulnerabilities such as SQL Injection, Command Injection, and Cross-Site Scripting (XSS). These issues are present in the forms and views, particularly in the handling of user input.\n    cwe: CWE-20\n    function_names:\n      - clean_username\n      - save\n      - clean_code\n    filenames:\n      - nopassword/forms.py\n      - nopassword/rest/views.py\n    classification: very promising\n  - headline: Improper Handling of Exceptional Conditions\n    analysis: |\n      The codebase does not properly handle exceptional conditions, such as when a user provides an invalid login code or when a user is inactive. This can lead to information disclosure and denial of service vulnerabilities.\n    cwe: CWE-754\n    function_names:\n      - clean_code\n      - form_valid\n    filenames:\n      - nopassword/forms.py\n      - nopassword/rest/views.py\n    classification: slightly promising\n  - headline: Cleartext Storage and Transmission of Sensitive Information\n    analysis: |\n      The codebase stores and transmits login codes in cleartext, which can lead to the exposure of sensitive information. This includes the transmission of the login code via email and SMS.\n    cwe: CWE-312\n    function_names:\n      - send_login_code\n    filenames:\n      - nopassword/backends/email.py\n      - nopassword/backends/sms.py\n    classification: very promising\n  - headline: Improper Encoding or Escaping of Output\n    analysis: |\n      The codebase does not properly encode or escape output, which can lead to Cross-Site Scripting (XSS) vulnerabilities. This is particularly evident in the rendering of the login code in the email and SMS templates.\n    cwe: CWE-116\n    function_names:\n      - send_login_code\n    filenames:\n      - nopassword/backends/email.py\n      - nopassword/backends/sms.py\n    classification: slightly promising\n  - headline: Improper Neutralization of Input During Web Page Generation\n    analysis: |\n      The codebase does not properly neutralize user input, which can lead to Cross-Site Scripting (XSS) vulnerabilities. This is particularly evident in the handling of the 'next' parameter in the login forms and views.\n    cwe: CWE-79\n    function_names:\n      - save\n      - get_redirect_url\n    filenames:\n      - nopassword/forms.py\n      - nopassword/views.py\n    classification: very promising\n\n```",
      "date": "2024-06-13T11:24:37.012491",
      "usage": {
        "prompt_tokens": 18143,
        "completion_tokens": 661,
        "cost": 0.005362
      }
    }
  ],
  "leads": [
    {
      "headline": "Improper Input Validation",
      "analysis": "The codebase contains several instances of improper input validation, which can lead to vulnerabilities such as SQL Injection, Command Injection, and Cross-Site Scripting (XSS). These issues are present in the forms and views, particularly in the handling of user input.\n",
      "classification": "very promising",
      "cwe": "CWE-20",
      "function_names": [
        "clean_username",
        "save",
        "clean_code"
      ],
      "filenames": [
        "nopassword/forms.py",
        "nopassword/rest/views.py"
      ]
    },
    {
      "headline": "Improper Handling of Exceptional Conditions",
      "analysis": "The codebase does not properly handle exceptional conditions, such as when a user provides an invalid login code or when a user is inactive. This can lead to information disclosure and denial of service vulnerabilities.\n",
      "classification": "slightly promising",
      "cwe": "CWE-754",
      "function_names": [
        "clean_code",
        "form_valid"
      ],
      "filenames": [
        "nopassword/forms.py",
        "nopassword/rest/views.py"
      ]
    },
    {
      "headline": "Cleartext Storage and Transmission of Sensitive Information",
      "analysis": "The codebase stores and transmits login codes in cleartext, which can lead to the exposure of sensitive information. This includes the transmission of the login code via email and SMS.\n",
      "classification": "very promising",
      "cwe": "CWE-312",
      "function_names": [
        "send_login_code"
      ],
      "filenames": [
        "nopassword/backends/email.py",
        "nopassword/backends/sms.py"
      ]
    },
    {
      "headline": "Improper Encoding or Escaping of Output",
      "analysis": "The codebase does not properly encode or escape output, which can lead to Cross-Site Scripting (XSS) vulnerabilities. This is particularly evident in the rendering of the login code in the email and SMS templates.\n",
      "classification": "slightly promising",
      "cwe": "CWE-116",
      "function_names": [
        "send_login_code"
      ],
      "filenames": [
        "nopassword/backends/email.py",
        "nopassword/backends/sms.py"
      ]
    },
    {
      "headline": "Improper Neutralization of Input During Web Page Generation",
      "analysis": "The codebase does not properly neutralize user input, which can lead to Cross-Site Scripting (XSS) vulnerabilities. This is particularly evident in the handling of the 'next' parameter in the login forms and views.\n",
      "classification": "very promising",
      "cwe": "CWE-79",
      "function_names": [
        "save",
        "get_redirect_url"
      ],
      "filenames": [
        "nopassword/forms.py",
        "nopassword/views.py"
      ]
    }
  ],
  "scores": [
    {
      "stats": {
        "fn": 0,
        "tp": 1,
        "fp": 2
      },
      "mapping": {
        "1": "CVE-2019-10682"
      },
      "vuln_dates": {
        "CVE-2019-10682": "2020-03-18T15:15:11"
      },
      "scoring_model": "claude-3-opus-20240229",
      "type": "llm",
      "instruction_template_hash": "245ace12b6361954d0a2"
    },
    {
      "stats": {
        "fn": 0,
        "tp": 1,
        "fp": 2
      },
      "mapping": {
        "1": "CVE-2019-10682"
      },
      "vuln_dates": {
        "CVE-2019-10682": "2020-03-18T15:15:11"
      },
      "scoring_model": "claude-3-5-sonnet-20240620",
      "type": "llm",
      "instruction_template_hash": "245ace12b6361954d0a2"
    }
  ],
  "instruction_template_hash": "10c0163db4740318a544",
  "version": "0.1.0"
}
