{
  "commit": "0cf9a6b441ca91dad3c0fcb3fd0e07180b28f0c8",
  "repo_url": "https://github.com/bluesmoon/node-geoip",
  "model": "gpt-4-turbo-2024-04-09",
  "chunk_hashes": [
    "41cdf414050b1b0c27f7"
  ],
  "responses": [
    {
      "content": "```yaml\nleads:\n  - headline: Exposure of sensitive information through overly verbose error messages in geolocation lookup\n    analysis: |\n      The geo-location lookup functionality in `lib/geoip.js` might return verbose error messages if an IP address fails to be processed or is out of range. This could reveal underlying implementation details or configurations about the IP lookup mechanism to unauthorized users.\n    cwe: CWE-209\n    function_names:\n      - lookup4\n      - lookup6\n    filenames:\n      - lib/geoip.js\n    classification: slightly promising\n\n  - headline: Use of hardcoded credentials and sensitive information in code\n    analysis: |\n      The module `scripts/updatedb.js` contains hard-coded user agent strings and URLs within its code base, which can potentially expose sensitive information or settings crucial to the operation of the script. Additionally, these hardcoded values could facilitate targeted attacks if the user agent or URLs contain known vulnerabilities or are specifically black-listed by services.\n    cwe: CWE-798\n    function_names:\n      - fetch\n    filenames:\n      - scripts/updatedb.js\n    classification: slightly promising\n\n  - headline: Insufficient validation of CSV data could allow for injection and incorrect processing in geolocation update scripts\n    analysis: |\n      The function `CSVtoArray` used in `scripts/updatedb.js` does not properly validate the format of the CSV before processing, potentially allowing malformed or malicious data to be processed, leading to data integrity issues or cross-layer attacks if not handled correctly.\n    cwe: CWE-20\n    function_names:\n      - CSVtoArray\n    filenames:\n      - scripts/updatedb.js\n    classification: slightly promising\n\n  - headline: Potential directory traversal in filesystem operations\n    analysis: |\n      The function `extract` in `scripts/updatedb.js` lacks validation on paths derived from ZIP file entries, which could allow directory traversal if a ZIP file with specially crafted entries is processed. This might lead unauthorized access to filesystem resources.\n    cwe: CWE-22\n    function_names:\n      - extract\n    filenames:\n      - scripts/updatedb.js\n    classification: slightly promising\n\n  - headline: Race condition in update handling of geolocation data\n    analysis: |\n      The implementation of data updates in `lib/geoip.js` starts and stops watchers on geolocation data files but does not implement proper locking mechanisms. This could lead to race conditions where concurrent updates cause data corruption or inconsistent reads.\n    cwe: CWE-362\n    function_names:\n      - startWatchingDataUpdate\n      - stopWatchingDataUpdate\n    filenames:\n      - lib/geoip.js\n    classification: very promising\n\n  - headline: Missing proper handling of exceptional conditions\n    analysis: |\n      The scripts and libraries such as `lib/geoip.js` and `scripts/updatedb.js` do not have proper exception or error handling for file operations and network requests, which might result in unexpected software behavior or crashes on encountering errors.\n    cwe: CWE-755\n    function_names:\n      - preload\n      - fetch\n    filenames:\n      - lib/geoip.js\n      - scripts/updatedb.js\n    classification: slightly promising\n```",
      "date": "2024-06-12T15:15:08.641138",
      "usage": {
        "prompt_tokens": 12064,
        "completion_tokens": 662,
        "cost": 0.1405
      }
    }
  ],
  "leads": [
    {
      "headline": "Exposure of sensitive information through overly verbose error messages in geolocation lookup",
      "analysis": "The geo-location lookup functionality in lib/geoip.js might return verbose error messages if an IP address fails to be processed or is out of range. This could reveal underlying implementation details or configurations about the IP lookup mechanism to unauthorized users.\n",
      "classification": "slightly promising",
      "cwe": "CWE-209",
      "function_names": [
        "lookup4",
        "lookup6"
      ],
      "filenames": [
        "lib/geoip.js"
      ]
    },
    {
      "headline": "Use of hardcoded credentials and sensitive information in code",
      "analysis": "The module scripts/updatedb.js contains hard-coded user agent strings and URLs within its code base, which can potentially expose sensitive information or settings crucial to the operation of the script. Additionally, these hardcoded values could facilitate targeted attacks if the user agent or URLs contain known vulnerabilities or are specifically black-listed by services.\n",
      "classification": "slightly promising",
      "cwe": "CWE-798",
      "function_names": [
        "fetch"
      ],
      "filenames": [
        "scripts/updatedb.js"
      ]
    },
    {
      "headline": "Insufficient validation of CSV data could allow for injection and incorrect processing in geolocation update scripts",
      "analysis": "The function CSVtoArray used in scripts/updatedb.js does not properly validate the format of the CSV before processing, potentially allowing malformed or malicious data to be processed, leading to data integrity issues or cross-layer attacks if not handled correctly.\n",
      "classification": "slightly promising",
      "cwe": "CWE-20",
      "function_names": [
        "CSVtoArray"
      ],
      "filenames": [
        "scripts/updatedb.js"
      ]
    },
    {
      "headline": "Potential directory traversal in filesystem operations",
      "analysis": "The function extract in scripts/updatedb.js lacks validation on paths derived from ZIP file entries, which could allow directory traversal if a ZIP file with specially crafted entries is processed. This might lead unauthorized access to filesystem resources.\n",
      "classification": "slightly promising",
      "cwe": "CWE-22",
      "function_names": [
        "extract"
      ],
      "filenames": [
        "scripts/updatedb.js"
      ]
    },
    {
      "headline": "Race condition in update handling of geolocation data",
      "analysis": "The implementation of data updates in lib/geoip.js starts and stops watchers on geolocation data files but does not implement proper locking mechanisms. This could lead to race conditions where concurrent updates cause data corruption or inconsistent reads.\n",
      "classification": "very promising",
      "cwe": "CWE-362",
      "function_names": [
        "startWatchingDataUpdate",
        "stopWatchingDataUpdate"
      ],
      "filenames": [
        "lib/geoip.js"
      ]
    },
    {
      "headline": "Missing proper handling of exceptional conditions",
      "analysis": "The scripts and libraries such as lib/geoip.js and scripts/updatedb.js do not have proper exception or error handling for file operations and network requests, which might result in unexpected software behavior or crashes on encountering errors.\n",
      "classification": "slightly promising",
      "cwe": "CWE-755",
      "function_names": [
        "preload",
        "fetch"
      ],
      "filenames": [
        "lib/geoip.js",
        "scripts/updatedb.js"
      ]
    }
  ],
  "scores": [
    {
      "stats": {
        "fn": 1,
        "tp": 0,
        "fp": 1
      },
      "mapping": {},
      "vuln_dates": {
        "CVE-2016-10680": "2018-05-29T20:29:01"
      },
      "scoring_model": "claude-3-opus-20240229",
      "type": "llm",
      "instruction_template_hash": "245ace12b6361954d0a2"
    }
  ],
  "instruction_template_hash": "10c0163db4740318a544",
  "version": "0.1.0"
}
