{
  "commit": "45be0f99c7065f345ad76fd9767dae1c19cd01d5",
  "repo_url": "https://github.com/redon-tech/roblox-purchasing-hub",
  "model": "gpt-4-turbo-2024-04-09",
  "chunk_hashes": [
    "c1d9834b7ece9e000d10"
  ],
  "responses": [
    {
      "content": "```yaml\nleads:\n  - headline: Insufficient Input Validation and Error Handling in Product System\n    analysis: |\n      The `createproduct`, `updateproduct`, `deleteproduct`, `giveproduct`, and `revokeproduct` functions in the `api.py` file lack comprehensive input validation, allowing potentially malformed or malicious data to be passed through, leading to database entry corruptions or unintended behavior. This lack of validation combines with insufficient error handling in the functions and routes exposed via the API, such as failing to respond appropriately to invalid requests, which could allow users to bypass intended product or user attribute management logic.\n    cwe: CWE-20\n    function_names:\n      - createproduct\n      - updateproduct\n      - deleteproduct\n      - giveproduct\n      - revokeproduct\n    filenames:\n      - /lib/utils/api.py\n    classification: very promising\n\n  - headline: Insensitive Log Message and Information Exposure in Database Operations\n    analysis: |\n      Some database operations in `api.py` seem to log informational or error messages that could contain sensitive data about the database queries or their parameters. These issues might expose sensitive information such as user IDs and product details that could lead to security implications like information leakage or potential unauthorized database actions identification.\n    cwe: CWE-532\n    function_names:\n      - createproduct\n    filenames:\n      - /lib/utils/api.py\n    classification: slightly promising\n\n  - headline: Weak Authentication and Authorization Implementations in API Routes\n    analysis: |\n      Basic API key authentication used in various routes within the `website.py` cog is insufficient for secure operations. This could be brute-forced or bypassed, potentially allowing unauthorized users to interact with sensitive API functions such as creating, updating, or deleting products. Similarly, the lack of robust authorization checks to validate that the requesting user can perform certain actions heightens the risk of privilege escalation.\n    cwe: CWE-287\n    function_names:\n      - create_product\n      - update_product\n      - delete_product\n    filenames:\n      - /lib/cogs/website.py\n    classification: very promising\n\n  - headline: Lack of Resource Throttling Leading to Uncontrolled Resource Consumption\n    analysis: |\n      The application's API lacks measures to throttle incoming requests effectively. This oversight can allow an attacker to send a large number of requests in a short period, potentially resulting in a denial-of-service condition by overwhelming the application's servers or depleting the system's resources.\n    cwe: CWE-770\n    function_names:\n      - create_product\n      - update_product\n      - delete_product\n    filenames:\n      - /lib/cogs/website.py\n    classification: slightly promising\n\n  - headline: Sensitive Data Exposure Through Insecure Data Transport\n    analysis: |\n      The application does not enforce or implement transport layer security consistently for all data being transmitted, especially seen through the interactions with external services and between the client and server. This makes sensitive information such as API keys, user information, and product details susceptible to interception by unauthorized parties during transmission.\n    cwe: CWE-319\n    function_names:\n      - app.route\n    filenames:\n      - /lib/cogs/website.py\n    classification: slightly promising\n\n  - headline: Actual Implementation Mismatch and Desynchronization in Product Functionality\n    analysis: |\n      The `products.py` cog includes misaligned functionalities, where options for updating and deleting products exist without proper preliminary checks or subsequent validations. This condition can lead to race conditions and stale state information, which if exploited, can impact database integrity and user experience.\n    cwe: CWE-367\n    function_names:\n      - updateproduct\n      - deleteproduct\n    filenames:\n      - /lib/cogs/product.py\n    classification: slightly promising\n```",
      "date": "2024-06-14T15:25:17.051939",
      "usage": {
        "prompt_tokens": 14224,
        "completion_tokens": 777,
        "cost": 0.16555
      }
    }
  ],
  "leads": [
    {
      "headline": "Insufficient Input Validation and Error Handling in Product System",
      "analysis": "The createproduct, updateproduct, deleteproduct, giveproduct, and revokeproduct functions in the api.py file lack comprehensive input validation, allowing potentially malformed or malicious data to be passed through, leading to database entry corruptions or unintended behavior. This lack of validation combines with insufficient error handling in the functions and routes exposed via the API, such as failing to respond appropriately to invalid requests, which could allow users to bypass intended product or user attribute management logic.\n",
      "classification": "very promising",
      "cwe": "CWE-20",
      "function_names": [
        "createproduct",
        "updateproduct",
        "deleteproduct"
      ],
      "filenames": [
        "/lib/utils/api.py"
      ]
    },
    {
      "headline": "Insensitive Log Message and Information Exposure in Database Operations",
      "analysis": "Some database operations in api.py seem to log informational or error messages that could contain sensitive data about the database queries or their parameters. These issues might expose sensitive information such as user IDs and product details that could lead to security implications like information leakage or potential unauthorized database actions identification.\n",
      "classification": "slightly promising",
      "cwe": "CWE-532",
      "function_names": [
        "createproduct"
      ],
      "filenames": [
        "/lib/utils/api.py"
      ]
    },
    {
      "headline": "Weak Authentication and Authorization Implementations in API Routes",
      "analysis": "Basic API key authentication used in various routes within the website.py cog is insufficient for secure operations. This could be brute-forced or bypassed, potentially allowing unauthorized users to interact with sensitive API functions such as creating, updating, or deleting products. Similarly, the lack of robust authorization checks to validate that the requesting user can perform certain actions heightens the risk of privilege escalation.\n",
      "classification": "very promising",
      "cwe": "CWE-287",
      "function_names": [
        "create_product",
        "update_product",
        "delete_product"
      ],
      "filenames": [
        "/lib/cogs/website.py"
      ]
    },
    {
      "headline": "Lack of Resource Throttling Leading to Uncontrolled Resource Consumption",
      "analysis": "The application's API lacks measures to throttle incoming requests effectively. This oversight can allow an attacker to send a large number of requests in a short period, potentially resulting in a denial-of-service condition by overwhelming the application's servers or depleting the system's resources.\n",
      "classification": "slightly promising",
      "cwe": "CWE-770",
      "function_names": [
        "create_product",
        "update_product",
        "delete_product"
      ],
      "filenames": [
        "/lib/cogs/website.py"
      ]
    },
    {
      "headline": "Sensitive Data Exposure Through Insecure Data Transport",
      "analysis": "The application does not enforce or implement transport layer security consistently for all data being transmitted, especially seen through the interactions with external services and between the client and server. This makes sensitive information such as API keys, user information, and product details susceptible to interception by unauthorized parties during transmission.\n",
      "classification": "slightly promising",
      "cwe": "CWE-319",
      "function_names": [
        "app.route"
      ],
      "filenames": [
        "/lib/cogs/website.py"
      ]
    },
    {
      "headline": "Actual Implementation Mismatch and Desynchronization in Product Functionality",
      "analysis": "The products.py cog includes misaligned functionalities, where options for updating and deleting products exist without proper preliminary checks or subsequent validations. This condition can lead to race conditions and stale state information, which if exploited, can impact database integrity and user experience.\n",
      "classification": "slightly promising",
      "cwe": "CWE-367",
      "function_names": [
        "updateproduct",
        "deleteproduct"
      ],
      "filenames": [
        "/lib/cogs/product.py"
      ]
    }
  ],
  "scores": [
    {
      "stats": {
        "fn": 0,
        "tp": 1,
        "fp": 1
      },
      "mapping": {
        "1": "CVE-2021-41191"
      },
      "vuln_dates": {
        "CVE-2021-41191": "2021-10-27T21:15:08"
      },
      "scoring_model": "claude-3-opus-20240229",
      "type": "llm",
      "instruction_template_hash": "245ace12b6361954d0a2"
    },
    {
      "stats": {
        "fn": 0,
        "tp": 1,
        "fp": 1
      },
      "mapping": {
        "1": "CVE-2021-41191"
      },
      "vuln_dates": {
        "CVE-2021-41191": "2021-10-27T21:15:08"
      },
      "scoring_model": "claude-3-5-sonnet-20240620",
      "type": "llm",
      "instruction_template_hash": "245ace12b6361954d0a2"
    }
  ],
  "instruction_template_hash": "10c0163db4740318a544",
  "version": "0.1.0"
}
