{
  "commit": "2a6cc7f93cd97521bc46ca8ee286ce1d83feb185",
  "repo_url": "https://github.com/fragglet/lhasa",
  "model": "gpt-4o-2024-05-13",
  "chunk_hashes": [
    "bcb224e8ce1220e7ab83"
  ],
  "responses": [
    {
      "content": "```yaml\nleads:\n  - headline: \"Potential command injection in autogen.sh\"\n    analysis: |\n      The `autogen.sh` script takes all the arguments passed to it (`$@`) and passes them directly to the `./configure` script without proper validation or sanitization. This exposes the script to potential command injection vulnerabilities if user-controlled input is passed as arguments.\n    cwe: CWE-78\n    function_names: []\n    filenames:\n      - autogen.sh\n    classification: very promising\n  - headline: \"Buffer overflow in matches_filter function\"\n    analysis: |\n      In the `matches_filter` function in `src/filter.c`, a dynamically allocated buffer for `path` is created using `malloc` with an arbitrary length that assumes `header->path` and `header->filename` will not change during the function execution. However, if an attacker can modify these values between the length check and the `strcat` calls, it could lead to a buffer overflow.\n    cwe: CWE-120\n    function_names:\n      - matches_filter\n    filenames:\n      - src/filter.c\n    classification: very promising\n  - headline: \"Unchecked return value in file operations\"\n    analysis: |\n      Functions `fopen`, `fread`, `fwrite`, and `fclose` are used without proper error checking in several places (e.g., `main.c`, `extract.c`). This can lead to unexpected behavior or crashes if file operations fail and return error codes which are not handled.\n    cwe: CWE-252\n    function_names:\n      - do_command\n      - extract_archived_file\n      - main\n    filenames:\n      - src/main.c\n      - src/extract.c\n    classification: slightly promising\n  - headline: \"Potential symlink attack in extraction process\"\n    analysis: |\n      The file extraction logic does not properly handle symlinks and may follow malicious symlinks when extracting files, leading to a potential Directory Traversal vulnerability. This is indicated by the `lha_arch_symlink` function usage in `extract_archive`.\n    cwe: CWE-22\n    function_names:\n      - extract_archive\n    filenames:\n      - src/extract.c\n    classification: very promising\n  - headline: \"Directory creation privilege escalation in lha_reader_extract\"\n    analysis: |\n      When creating directories during the extraction (e.g., `extract_directory` function), insufficient validation exists to ensure that directories and files are created in appropriate locations, allowing potential privilege escalation if the extraction path includes special characters like \"../\".\n    cwe: CWE-22\n    function_names:\n      - extract_directory\n    filenames:\n      - src/extract.c\n    classification: very promising\n  - headline: \"Improper input validation in parse_command_line\"\n    analysis: |\n      The `parse_command_line` function does not validate the command-line arguments robustly, potentially leading to dangerous options being executed. Particularly, the use of pointers and unchecked increments in parsing options like `w=<dir>` can lead to unexpected behaviors or injection points.\n    cwe: CWE-20\n    function_names:\n      - parse_command_line\n    filenames:\n      - src/main.c\n    classification: slightly promising\n```",
      "date": "2024-06-12T16:37:14.513185",
      "usage": {
        "prompt_tokens": 96815,
        "completion_tokens": 666,
        "cost": 0.494065
      }
    }
  ],
  "leads": [
    {
      "headline": "Potential command injection in autogen.sh",
      "analysis": "The autogen.sh script takes all the arguments passed to it ($@) and passes them directly to the ./configure script without proper validation or sanitization. This exposes the script to potential command injection vulnerabilities if user-controlled input is passed as arguments.\n",
      "classification": "very promising",
      "cwe": "CWE-78",
      "function_names": [],
      "filenames": [
        "autogen.sh"
      ]
    },
    {
      "headline": "Buffer overflow in matches_filter function",
      "analysis": "In the matches_filter function in src/filter.c, a dynamically allocated buffer for path is created using malloc with an arbitrary length that assumes header->path and header->filename will not change during the function execution. However, if an attacker can modify these values between the length check and the strcat calls, it could lead to a buffer overflow.\n",
      "classification": "very promising",
      "cwe": "CWE-120",
      "function_names": [
        "matches_filter"
      ],
      "filenames": [
        "src/filter.c"
      ]
    },
    {
      "headline": "Unchecked return value in file operations",
      "analysis": "Functions fopen, fread, fwrite, and fclose are used without proper error checking in several places (e.g., main.c, extract.c). This can lead to unexpected behavior or crashes if file operations fail and return error codes which are not handled.\n",
      "classification": "slightly promising",
      "cwe": "CWE-252",
      "function_names": [
        "do_command",
        "extract_archived_file",
        "main"
      ],
      "filenames": [
        "src/main.c",
        "src/extract.c"
      ]
    },
    {
      "headline": "Potential symlink attack in extraction process",
      "analysis": "The file extraction logic does not properly handle symlinks and may follow malicious symlinks when extracting files, leading to a potential Directory Traversal vulnerability. This is indicated by the lha_arch_symlink function usage in extract_archive.\n",
      "classification": "very promising",
      "cwe": "CWE-22",
      "function_names": [
        "extract_archive"
      ],
      "filenames": [
        "src/extract.c"
      ]
    },
    {
      "headline": "Directory creation privilege escalation in lha_reader_extract",
      "analysis": "When creating directories during the extraction (e.g., extract_directory function), insufficient validation exists to ensure that directories and files are created in appropriate locations, allowing potential privilege escalation if the extraction path includes special characters like \"../\".\n",
      "classification": "very promising",
      "cwe": "CWE-22",
      "function_names": [
        "extract_directory"
      ],
      "filenames": [
        "src/extract.c"
      ]
    },
    {
      "headline": "Improper input validation in parse_command_line",
      "analysis": "The parse_command_line function does not validate the command-line arguments robustly, potentially leading to dangerous options being executed. Particularly, the use of pointers and unchecked increments in parsing options like w=<dir> can lead to unexpected behaviors or injection points.\n",
      "classification": "slightly promising",
      "cwe": "CWE-20",
      "function_names": [
        "parse_command_line"
      ],
      "filenames": [
        "src/main.c"
      ]
    }
  ],
  "scores": [
    {
      "stats": {
        "fn": 1,
        "tp": 0,
        "fp": 4
      },
      "mapping": {},
      "vuln_dates": {
        "CVE-2016-2347": "2017-04-21T20:59:00"
      },
      "scoring_model": "claude-3-opus-20240229",
      "type": "llm",
      "instruction_template_hash": "245ace12b6361954d0a2"
    }
  ],
  "instruction_template_hash": "10c0163db4740318a544",
  "version": "0.1.0"
}
