{
  "commit": "48063aeb0dd2065a8af7c976d6650d49980949a4",
  "repo_url": "https://github.com/snowflakedb/snowflake-hive-metastore-connector",
  "model": "claude-3-haiku-20240307",
  "chunk_hashes": [
    "cf53e68c6375f8df4e66"
  ],
  "responses": [
    {
      "content": "Here is the YAML output:\n\n```yaml\nleads:\n  - headline: Improper Input Validation\n    analysis: |\n      The codebase contains several instances of improper input validation, which can lead to vulnerabilities such as:\n      \n      1. CWE-1284 Improper Validation of Specified Quantity in Input: The code does not properly validate the quantity of input data, which can lead to buffer overflow and other types of input-related vulnerabilities.\n      \n      2. CWE-129 Improper Validation of Array Index: The code does not properly validate the index of an array, which can lead to out-of-bounds read/write vulnerabilities.\n    cwe: CWE-20\n    function_names:\n      - TestUtil.initializeMockTable\n      - TestUtil.mockSnowflakeStageWithLocation\n    filenames:\n      - src/test/java/TestUtil.java\n      - src/test/java/CreateTableTest.java\n    classification: very promising\n\n  - headline: Injection\n    analysis: |\n      The codebase contains several instances of injection vulnerabilities, which can lead to vulnerabilities such as:\n      \n      1. CWE-77 Improper Neutralization of Special Elements used in a Command ('Command Injection'): The code does not properly neutralize user input that is used in a Snowflake SQL command, which can lead to command injection.\n      \n      2. CWE-89 Improper Neutralization of Special Elements used in an SQL Command ('SQL Injection'): The code does not properly neutralize user input that is used in an SQL command, which can lead to SQL injection.\n    cwe: CWE-74\n    function_names:\n      - SnowflakeClient.executeStatement\n      - SnowflakeClient.executeStatements\n    filenames:\n      - src/main/java/net/snowflake/hivemetastoreconnector/core/SnowflakeClient.java\n    classification: very promising\n\n  - headline: Exposure of Sensitive Information\n    analysis: |\n      The codebase contains several instances of exposing sensitive information, which can lead to vulnerabilities such as:\n      \n      1. CWE-209 Generation of Error Message Containing Sensitive Information: The code can generate error messages that contain sensitive information, such as Snowflake credentials, which can be exposed to an attacker.\n      \n      2. CWE-532 Insertion of Sensitive Information into Log File: The code can log sensitive information, such as Snowflake credentials, to log files, which can be accessed by an attacker.\n    cwe: CWE-200\n    function_names:\n      - SnowflakeClient.getConnection\n      - SnowflakeClient.executeStatement\n    filenames:\n      - src/main/java/net/snowflake/hivemetastoreconnector/core/SnowflakeClient.java\n    classification: slightly promising\n\n  - headline: Missing Encryption of Sensitive Data\n    analysis: |\n      The codebase contains instances of storing and transmitting sensitive data without encryption, which can lead to vulnerabilities such as:\n      \n      1. CWE-312 Cleartext Storage of Sensitive Information: The code stores Snowflake credentials, such as passwords and private keys, in cleartext, which can be accessed by an attacker.\n      \n      2. CWE-319 Cleartext Transmission of Sensitive Information: The code transmits Snowflake credentials, such as passwords and private keys, in cleartext, which can be intercepted by an attacker.\n    cwe: CWE-311\n    function_names:\n      - SnowflakeClient.getConnection\n    filenames:\n      - src/main/java/net/snowflake/hivemetastoreconnector/core/SnowflakeClient.java\n    classification: very promising\n\n  - headline: Improper Restriction of Operations within the Bounds of a Memory Buffer\n    analysis: |\n      The codebase contains instances of improper restriction of operations within the bounds of a memory buffer, which can lead to vulnerabilities such as:\n      \n      1. CWE-120 Buffer Copy without Checking Size of Input ('Classic Buffer Overflow'): The code copies data from user input into a fixed-size buffer without checking the size of the input, which can lead to buffer overflow vulnerabilities.\n      \n      2. CWE-125 Out-of-bounds Read: The code reads from a buffer outside of its bounds, which can lead to information disclosure vulnerabilities.\n    cwe: CWE-119\n    function_names:\n      - TestUtil.initializeMockTable\n      - TestUtil.mockSnowflakeStageWithLocation\n    filenames:\n      - src/test/java/TestUtil.java\n      - src/test/java/CreateTableTest.java\n    classification: very promising\n\n  - headline: Improper Certificate Validation\n    analysis: |\n      The codebase contains instances of improper certificate validation, which can lead to vulnerabilities such as:\n      \n      1. CWE-295 Improper Certificate Validation: The code does not properly validate the certificates used for connecting to Snowflake, which can lead to man-in-the-middle attacks and other types of vulnerabilities.\n    cwe: CWE-287\n    function_names:\n      - SnowflakeClient.getConnection\n    filenames:\n      - src/main/java/net/snowflake/hivemetastoreconnector/core/SnowflakeClient.java\n    classification: slightly promising\n\n  - headline: Improper Synchronization\n    analysis: |\n      The codebase contains instances of improper synchronization, which can lead to vulnerabilities such as:\n      \n      1. CWE-362 Concurrent Execution using Shared Resource with Improper Synchronization ('Race Condition'): The code does not properly synchronize the access to shared resources, which can lead to race conditions and other types of concurrency vulnerabilities.\n    cwe: CWE-362\n    function_names:\n      - Scheduler.doWork\n    filenames:\n      - src/main/java/net/snowflake/hivemetastoreconnector/core/Scheduler.java\n    classification: slightly promising\n\n  - headline: Improper Resource Shutdown or Release\n    analysis: |\n      The codebase contains instances of improper resource shutdown or release, which can lead to vulnerabilities such as:\n      \n      1. CWE-401 Missing Release of Memory after Effective Lifetime: The code does not properly release memory resources, which can lead to memory leaks and other types of resource exhaustion vulnerabilities.\n      \n      2. CWE-772 Missing Release of Resource after Effective Lifetime: The code does not properly release other types of resources, such as database connections or file handles, which can lead to resource exhaustion vulnerabilities.\n    cwe: CWE-404\n    function_names:\n      - SnowflakeClient.getConnection\n      - SnowflakeClient.executeStatement\n    filenames:\n      - src/main/java/net/snowflake/hivemetastoreconnector/core/SnowflakeClient.java\n    classification: slightly promising\n\n  - headline: Externally Controlled Reference to a Resource in Another Sphere\n    analysis: |\n      The codebase contains instances of externally controlled references to resources in another sphere, which can lead to vulnerabilities such as:\n      \n      1. CWE-601 URL Redirection to Untrusted Site ('Open Redirect'): The code does not properly validate the URL used for redirection, which can lead to open redirect vulnerabilities.\n      \n      2. CWE-918 Server-Side Request Forgery (SSRF): The code does not properly validate the URL used for making requests to external resources, which can lead to SSRF vulnerabilities.\n    cwe: CWE-610\n    function_names:\n      - HiveToSnowflakeType.toSnowflakeURL\n    filenames:\n      - src/main/java/net/snowflake/hivemetastoreconnector/util/HiveToSnowflakeType.java\n    classification: slightly promising\n\n  - headline: Improper Removal of Sensitive Information Before Storage or Transfer\n    analysis: |\n      The codebase contains instances of improper removal of sensitive information before storage or transfer, which can lead to vulnerabilities such as:\n      \n      1. CWE-212 Improper Removal of Sensitive Information Before Storage or Transfer: The code does not properly remove sensitive information, such as Snowflake credentials, before storing or transferring the data, which can lead to information disclosure vulnerabilities.\n    cwe: CWE-669\n    function_names:\n      - SnowflakeClient.getConnection\n    filenames:\n      - src/main/java/net/snowflake/hivemetastoreconnector/core/SnowflakeClient.java\n    classification: slightly promising\n\n  - headline: Incorrect Comparison\n    analysis: |\n      The codebase contains instances of incorrect comparison, which can lead to vulnerabilities such as:\n      \n      1. CWE-697 Incorrect Comparison: The code does not properly compare values, which can lead to logic errors and other types of vulnerabilities.\n    cwe: CWE-697\n    function_names:\n      - HiveToSnowflakeSchema.getSnowflakeSchemaFromHiveSchema\n    filenames:\n      - src/main/java/net/snowflake/hivemetastoreconnector/util/HiveToSnowflakeSchema.java\n    classification: slightly promising\n\n  - headline: Incorrect Type Conversion or Cast\n    analysis: |\n      The codebase contains instances of incorrect type conversion or cast, which can lead to vulnerabilities such as:\n      \n      1. CWE-704 Incorrect Type Conversion or Cast: The code does not properly convert or cast types, which can lead to logic errors and other types of vulnerabilities.\n    cwe: CWE-704\n    function_names:\n      - HiveToSnowflakeType.toSnowflakeColumnDataType\n    filenames:\n      - src/main/java/net/snowflake/hivemetastoreconnector/util/HiveToSnowflakeType.java\n    classification: slightly promising\n\n  - headline: Improper Check for Unusual or Exceptional Conditions\n    analysis: |\n      The codebase contains instances of improper check for unusual or exceptional conditions, which can lead to vulnerabilities such as:\n      \n      1. CWE-252 Unchecked Return Value: The code does not properly check the return values of function calls, which can lead to logic errors and other types of vulnerabilities.\n      \n      2. CWE-476 NULL Pointer Dereference: The code does not properly check for null pointers, which can lead to crashes and other types of vulnerabilities.\n    cwe: CWE-754\n    function_names:\n      - SnowflakeClient.getConnection\n      - SnowflakeClient.executeStatement\n    filenames:\n      - src/main/java/net/snowflake/hivemetastoreconnector/core/SnowflakeClient.java\n    classification: slightly promising\n\n  - headline: Missing Authorization\n    analysis: |\n      The codebase contains instances of missing authorization, which can lead to vulnerabilities such as:\n      \n      1. CWE-862 Missing Authorization: The code does not properly authorize users or processes, which can lead to unauthorized access to resources.\n    cwe: CWE-862\n    function_names:\n      - SnowflakeClient.getConnection\n      - SnowflakeClient.executeStatement\n    filenames:\n      - src/main/java/net/snowflake/hivemetastoreconnector/core/SnowflakeClient.java\n    classification: slightly promising\n\n  - headline: Improper Control of Dynamically-Managed Code Resources\n    analysis: |\n      The codebase contains instances of improper control of dynamically-managed code resources, which can lead to vulnerabilities such as:\n      \n      1. CWE-502 Deserialization of Untrusted Data: The code deserializes data from untrusted sources, which can lead to remote code execution vulnerabilities.\n    cwe: CWE-913\n    function_names:\n      - CommandGenerator.getCommand\n    filenames:\n      - src/main/java/net/snowflake/hivemetastoreconnector/core/CommandGenerator.java\n    classification: slightly promising\n\n```",
      "date": "2024-06-09T14:51:12.548444",
      "usage": {
        "prompt_tokens": 72270,
        "completion_tokens": 2965,
        "cost": 0.02177375
      }
    }
  ],
  "leads": [
    {
      "headline": "Improper Input Validation",
      "analysis": "The codebase contains several instances of improper input validation, which can lead to vulnerabilities such as:\n\n1. CWE-1284 Improper Validation of Specified Quantity in Input: The code does not properly validate the quantity of input data, which can lead to buffer overflow and other types of input-related vulnerabilities.\n\n2. CWE-129 Improper Validation of Array Index: The code does not properly validate the index of an array, which can lead to out-of-bounds read/write vulnerabilities.\n",
      "classification": "very promising",
      "cwe": "CWE-20",
      "function_names": [
        "TestUtil.initializeMockTable",
        "TestUtil.mockSnowflakeStageWithLocation"
      ],
      "filenames": [
        "src/test/java/TestUtil.java",
        "src/test/java/CreateTableTest.java"
      ]
    },
    {
      "headline": "Injection",
      "analysis": "The codebase contains several instances of injection vulnerabilities, which can lead to vulnerabilities such as:\n\n1. CWE-77 Improper Neutralization of Special Elements used in a Command ('Command Injection'): The code does not properly neutralize user input that is used in a Snowflake SQL command, which can lead to command injection.\n\n2. CWE-89 Improper Neutralization of Special Elements used in an SQL Command ('SQL Injection'): The code does not properly neutralize user input that is used in an SQL command, which can lead to SQL injection.\n",
      "classification": "very promising",
      "cwe": "CWE-74",
      "function_names": [
        "SnowflakeClient.executeStatement",
        "SnowflakeClient.executeStatements"
      ],
      "filenames": [
        "src/main/java/net/snowflake/hivemetastoreconnector/core/SnowflakeClient.java"
      ]
    },
    {
      "headline": "Exposure of Sensitive Information",
      "analysis": "The codebase contains several instances of exposing sensitive information, which can lead to vulnerabilities such as:\n\n1. CWE-209 Generation of Error Message Containing Sensitive Information: The code can generate error messages that contain sensitive information, such as Snowflake credentials, which can be exposed to an attacker.\n\n2. CWE-532 Insertion of Sensitive Information into Log File: The code can log sensitive information, such as Snowflake credentials, to log files, which can be accessed by an attacker.\n",
      "classification": "slightly promising",
      "cwe": "CWE-200",
      "function_names": [
        "SnowflakeClient.getConnection",
        "SnowflakeClient.executeStatement"
      ],
      "filenames": [
        "src/main/java/net/snowflake/hivemetastoreconnector/core/SnowflakeClient.java"
      ]
    },
    {
      "headline": "Missing Encryption of Sensitive Data",
      "analysis": "The codebase contains instances of storing and transmitting sensitive data without encryption, which can lead to vulnerabilities such as:\n\n1. CWE-312 Cleartext Storage of Sensitive Information: The code stores Snowflake credentials, such as passwords and private keys, in cleartext, which can be accessed by an attacker.\n\n2. CWE-319 Cleartext Transmission of Sensitive Information: The code transmits Snowflake credentials, such as passwords and private keys, in cleartext, which can be intercepted by an attacker.\n",
      "classification": "very promising",
      "cwe": "CWE-311",
      "function_names": [
        "SnowflakeClient.getConnection"
      ],
      "filenames": [
        "src/main/java/net/snowflake/hivemetastoreconnector/core/SnowflakeClient.java"
      ]
    },
    {
      "headline": "Improper Restriction of Operations within the Bounds of a Memory Buffer",
      "analysis": "The codebase contains instances of improper restriction of operations within the bounds of a memory buffer, which can lead to vulnerabilities such as:\n\n1. CWE-120 Buffer Copy without Checking Size of Input ('Classic Buffer Overflow'): The code copies data from user input into a fixed-size buffer without checking the size of the input, which can lead to buffer overflow vulnerabilities.\n\n2. CWE-125 Out-of-bounds Read: The code reads from a buffer outside of its bounds, which can lead to information disclosure vulnerabilities.\n",
      "classification": "very promising",
      "cwe": "CWE-119",
      "function_names": [
        "TestUtil.initializeMockTable",
        "TestUtil.mockSnowflakeStageWithLocation"
      ],
      "filenames": [
        "src/test/java/TestUtil.java",
        "src/test/java/CreateTableTest.java"
      ]
    },
    {
      "headline": "Improper Certificate Validation",
      "analysis": "The codebase contains instances of improper certificate validation, which can lead to vulnerabilities such as:\n\n1. CWE-295 Improper Certificate Validation: The code does not properly validate the certificates used for connecting to Snowflake, which can lead to man-in-the-middle attacks and other types of vulnerabilities.\n",
      "classification": "slightly promising",
      "cwe": "CWE-287",
      "function_names": [
        "SnowflakeClient.getConnection"
      ],
      "filenames": [
        "src/main/java/net/snowflake/hivemetastoreconnector/core/SnowflakeClient.java"
      ]
    },
    {
      "headline": "Improper Synchronization",
      "analysis": "The codebase contains instances of improper synchronization, which can lead to vulnerabilities such as:\n\n1. CWE-362 Concurrent Execution using Shared Resource with Improper Synchronization ('Race Condition'): The code does not properly synchronize the access to shared resources, which can lead to race conditions and other types of concurrency vulnerabilities.\n",
      "classification": "slightly promising",
      "cwe": "CWE-362",
      "function_names": [
        "Scheduler.doWork"
      ],
      "filenames": [
        "src/main/java/net/snowflake/hivemetastoreconnector/core/Scheduler.java"
      ]
    },
    {
      "headline": "Improper Resource Shutdown or Release",
      "analysis": "The codebase contains instances of improper resource shutdown or release, which can lead to vulnerabilities such as:\n\n1. CWE-401 Missing Release of Memory after Effective Lifetime: The code does not properly release memory resources, which can lead to memory leaks and other types of resource exhaustion vulnerabilities.\n\n2. CWE-772 Missing Release of Resource after Effective Lifetime: The code does not properly release other types of resources, such as database connections or file handles, which can lead to resource exhaustion vulnerabilities.\n",
      "classification": "slightly promising",
      "cwe": "CWE-404",
      "function_names": [
        "SnowflakeClient.getConnection",
        "SnowflakeClient.executeStatement"
      ],
      "filenames": [
        "src/main/java/net/snowflake/hivemetastoreconnector/core/SnowflakeClient.java"
      ]
    },
    {
      "headline": "Externally Controlled Reference to a Resource in Another Sphere",
      "analysis": "The codebase contains instances of externally controlled references to resources in another sphere, which can lead to vulnerabilities such as:\n\n1. CWE-601 URL Redirection to Untrusted Site ('Open Redirect'): The code does not properly validate the URL used for redirection, which can lead to open redirect vulnerabilities.\n\n2. CWE-918 Server-Side Request Forgery (SSRF): The code does not properly validate the URL used for making requests to external resources, which can lead to SSRF vulnerabilities.\n",
      "classification": "slightly promising",
      "cwe": "CWE-610",
      "function_names": [
        "HiveToSnowflakeType.toSnowflakeURL"
      ],
      "filenames": [
        "src/main/java/net/snowflake/hivemetastoreconnector/util/HiveToSnowflakeType.java"
      ]
    },
    {
      "headline": "Improper Removal of Sensitive Information Before Storage or Transfer",
      "analysis": "The codebase contains instances of improper removal of sensitive information before storage or transfer, which can lead to vulnerabilities such as:\n\n1. CWE-212 Improper Removal of Sensitive Information Before Storage or Transfer: The code does not properly remove sensitive information, such as Snowflake credentials, before storing or transferring the data, which can lead to information disclosure vulnerabilities.\n",
      "classification": "slightly promising",
      "cwe": "CWE-669",
      "function_names": [
        "SnowflakeClient.getConnection"
      ],
      "filenames": [
        "src/main/java/net/snowflake/hivemetastoreconnector/core/SnowflakeClient.java"
      ]
    },
    {
      "headline": "Incorrect Comparison",
      "analysis": "The codebase contains instances of incorrect comparison, which can lead to vulnerabilities such as:\n\n1. CWE-697 Incorrect Comparison: The code does not properly compare values, which can lead to logic errors and other types of vulnerabilities.\n",
      "classification": "slightly promising",
      "cwe": "CWE-697",
      "function_names": [
        "HiveToSnowflakeSchema.getSnowflakeSchemaFromHiveSchema"
      ],
      "filenames": [
        "src/main/java/net/snowflake/hivemetastoreconnector/util/HiveToSnowflakeSchema.java"
      ]
    },
    {
      "headline": "Incorrect Type Conversion or Cast",
      "analysis": "The codebase contains instances of incorrect type conversion or cast, which can lead to vulnerabilities such as:\n\n1. CWE-704 Incorrect Type Conversion or Cast: The code does not properly convert or cast types, which can lead to logic errors and other types of vulnerabilities.\n",
      "classification": "slightly promising",
      "cwe": "CWE-704",
      "function_names": [
        "HiveToSnowflakeType.toSnowflakeColumnDataType"
      ],
      "filenames": [
        "src/main/java/net/snowflake/hivemetastoreconnector/util/HiveToSnowflakeType.java"
      ]
    },
    {
      "headline": "Improper Check for Unusual or Exceptional Conditions",
      "analysis": "The codebase contains instances of improper check for unusual or exceptional conditions, which can lead to vulnerabilities such as:\n\n1. CWE-252 Unchecked Return Value: The code does not properly check the return values of function calls, which can lead to logic errors and other types of vulnerabilities.\n\n2. CWE-476 NULL Pointer Dereference: The code does not properly check for null pointers, which can lead to crashes and other types of vulnerabilities.\n",
      "classification": "slightly promising",
      "cwe": "CWE-754",
      "function_names": [
        "SnowflakeClient.getConnection",
        "SnowflakeClient.executeStatement"
      ],
      "filenames": [
        "src/main/java/net/snowflake/hivemetastoreconnector/core/SnowflakeClient.java"
      ]
    },
    {
      "headline": "Missing Authorization",
      "analysis": "The codebase contains instances of missing authorization, which can lead to vulnerabilities such as:\n\n1. CWE-862 Missing Authorization: The code does not properly authorize users or processes, which can lead to unauthorized access to resources.\n",
      "classification": "slightly promising",
      "cwe": "CWE-862",
      "function_names": [
        "SnowflakeClient.getConnection",
        "SnowflakeClient.executeStatement"
      ],
      "filenames": [
        "src/main/java/net/snowflake/hivemetastoreconnector/core/SnowflakeClient.java"
      ]
    },
    {
      "headline": "Improper Control of Dynamically-Managed Code Resources",
      "analysis": "The codebase contains instances of improper control of dynamically-managed code resources, which can lead to vulnerabilities such as:\n\n1. CWE-502 Deserialization of Untrusted Data: The code deserializes data from untrusted sources, which can lead to remote code execution vulnerabilities.\n",
      "classification": "slightly promising",
      "cwe": "CWE-913",
      "function_names": [
        "CommandGenerator.getCommand"
      ],
      "filenames": [
        "src/main/java/net/snowflake/hivemetastoreconnector/core/CommandGenerator.java"
      ]
    }
  ],
  "scores": [
    {
      "stats": {
        "fn": 1,
        "tp": 0,
        "fp": 4
      },
      "mapping": {},
      "vuln_dates": {
        "CVE-2024-28851": "2024-03-15T19:15:07"
      },
      "scoring_model": "gpt-4o-2024-05-13",
      "type": "llm",
      "instruction_template_hash": "8998f09cf57fca8a6e03"
    },
    {
      "stats": {
        "fn": 1,
        "tp": 0,
        "fp": 4
      },
      "mapping": {},
      "vuln_dates": {
        "CVE-2024-28851": "2024-03-15T19:15:07"
      },
      "scoring_model": "claude-3-opus-20240229",
      "type": "llm",
      "instruction_template_hash": "245ace12b6361954d0a2"
    },
    {
      "stats": {
        "fn": 1,
        "tp": 0,
        "fp": 4
      },
      "mapping": {},
      "vuln_dates": {
        "CVE-2024-28851": "2024-03-15T19:15:07"
      },
      "scoring_model": "claude-3-5-sonnet-20240620",
      "type": "llm",
      "instruction_template_hash": "245ace12b6361954d0a2"
    }
  ],
  "instruction_template_hash": "10c0163db4740318a544",
  "version": "0.1.0"
}
