{
  "commit": "48acf4365a6575d7c5fdae329b6383c20ad5eddb",
  "repo_url": "https://github.com/ros2/sros2",
  "model": "gpt-4o-2024-05-13",
  "chunk_hashes": [
    "799dfdedaa0016076b17"
  ],
  "responses": [
    {
      "content": "```yaml\nleads: \n  - headline: \"Unchecked Return Value when creating keystore\"\n    analysis: |\n      Function `create_keystore` in `sros2/api/__init__.py` returns without checking if the `os.makedirs`\n      or `shutil.copyfile` functions successfully execute. If the directory creation or file copy fails\n      for any reason, this could lead to improper initialization without any error, causing potential\n      security issues later if invalid paths are used or expected files are missing.\n    cwe: \"CWE-252\"\n    function_names:\n      - \"create_keystore\"\n    filenames: \n      - \"sros2/sros2/api/__init__.py\"\n    classification: \"very promising\"\n\n  - headline: \"Environment variable usage without validation\"\n    analysis: |\n      The function `create_governance_file` in `sros2/api/__init__.py` uses the domain ID directly from the \n      environment variable 'ROS_DOMAIN_ID' without validation. This could be manipulated by an attacker\n      setting an invalid or harmful value in the environment variable, leading to unexpected behavior.\n    cwe: \"CWE-20\"\n    function_names:\n      - \"create_governance_file\"\n    filenames: \n      - \"sros2/sros2/api/__init__.py\"\n    classification: \"slightly promising\"\n\n  - headline: \"Potential race condition in setting environment variables\"\n    analysis: |\n      In `sros2/__init__.py`, environment variable `XML_CATALOG_FILES` is set conditionally. Another thread \n      might change the environment variable concurrently, leading to inconsistent state or vulnerabilities \n      due to race condition.\n    cwe: \"CWE-362\"\n    function_names: []\n    filenames: \n      - \"sros2/sros2/__init__.py\"\n    classification: \"slightly promising\"\n\n  - headline: \"Possible Directory Traversal in API functions\"\n    analysis: |\n      Functions like `create_permission` and `create_key` in `sros2/sros2/api/__init__.py` do not sanitize the \n      `identity` parameter or related paths provided. Without proper sanitization, an attacker could exploit \n      directory traversal to write arbitrary paths, potentially overwriting sensitive files or placing \n      malicious files in unexpected locations.\n    cwe: \"CWE-22\"\n    function_names:\n      - \"create_permission\"\n      - \"create_key\"\n    filenames: \n      - \"sros2/sros2/api/__init__.py\"\n    classification: \"very promising\"\n\n  - headline: \"Missing release of resources in tests\"\n    analysis: |\n      Tests in files `test_generate_policy.py` and others create ROS nodes without ensuring \n      their proper destruction before shutting down the context. This improper resource management \n      can lead to resource leaks and irregular test behavior across different test runs.\n    cwe: \"CWE-401\"\n    function_names: []\n    filenames: \n      - \"sros2/test/sros2/commands/security/verbs/test_generate_policy.py\"\n    classification: \"not promising\"\n\n  - headline: \"Insufficient entropy in cryptographic keys\"\n    analysis: |\n      The `_build_key_and_cert` function generates cryptographic keys using the default backend without \n      explicitly ensuring a strong source of entropy. In dynamic environments, this could lead to \n      predictability in cryptographic operations.\n    cwe: \"CWE-331\"\n    function_names:\n      - \"_build_key_and_cert\"\n    filenames: \n      - \"sros2/sros2/api/__init__.py\"\n    classification: \"slightly promising\"\n```",
      "date": "2024-06-14T15:28:58.316127",
      "usage": {
        "prompt_tokens": 18453,
        "completion_tokens": 753,
        "cost": 0.10356
      }
    }
  ],
  "leads": [
    {
      "headline": "Unchecked Return Value when creating keystore",
      "analysis": "Function create_keystore in sros2/api/__init__.py returns without checking if the os.makedirs\nor shutil.copyfile functions successfully execute. If the directory creation or file copy fails\nfor any reason, this could lead to improper initialization without any error, causing potential\nsecurity issues later if invalid paths are used or expected files are missing.\n",
      "classification": "very promising",
      "cwe": "CWE-252",
      "function_names": [
        "create_keystore"
      ],
      "filenames": [
        "sros2/sros2/api/__init__.py"
      ]
    },
    {
      "headline": "Environment variable usage without validation",
      "analysis": "The function create_governance_file in sros2/api/__init__.py uses the domain ID directly from the \nenvironment variable 'ROS_DOMAIN_ID' without validation. This could be manipulated by an attacker\nsetting an invalid or harmful value in the environment variable, leading to unexpected behavior.\n",
      "classification": "slightly promising",
      "cwe": "CWE-20",
      "function_names": [
        "create_governance_file"
      ],
      "filenames": [
        "sros2/sros2/api/__init__.py"
      ]
    },
    {
      "headline": "Potential race condition in setting environment variables",
      "analysis": "In sros2/__init__.py, environment variable XML_CATALOG_FILES is set conditionally. Another thread \nmight change the environment variable concurrently, leading to inconsistent state or vulnerabilities \ndue to race condition.\n",
      "classification": "slightly promising",
      "cwe": "CWE-362",
      "function_names": [],
      "filenames": [
        "sros2/sros2/__init__.py"
      ]
    },
    {
      "headline": "Possible Directory Traversal in API functions",
      "analysis": "Functions like create_permission and create_key in sros2/sros2/api/__init__.py do not sanitize the \nidentity parameter or related paths provided. Without proper sanitization, an attacker could exploit \ndirectory traversal to write arbitrary paths, potentially overwriting sensitive files or placing \nmalicious files in unexpected locations.\n",
      "classification": "very promising",
      "cwe": "CWE-22",
      "function_names": [
        "create_permission",
        "create_key"
      ],
      "filenames": [
        "sros2/sros2/api/__init__.py"
      ]
    },
    {
      "headline": "Missing release of resources in tests",
      "analysis": "Tests in files test_generate_policy.py and others create ROS nodes without ensuring \ntheir proper destruction before shutting down the context. This improper resource management \ncan lead to resource leaks and irregular test behavior across different test runs.\n",
      "classification": "not promising",
      "cwe": "CWE-401",
      "function_names": [],
      "filenames": [
        "sros2/test/sros2/commands/security/verbs/test_generate_policy.py"
      ]
    },
    {
      "headline": "Insufficient entropy in cryptographic keys",
      "analysis": "The _build_key_and_cert function generates cryptographic keys using the default backend without \nexplicitly ensuring a strong source of entropy. In dynamic environments, this could lead to \npredictability in cryptographic operations.\n",
      "classification": "slightly promising",
      "cwe": "CWE-331",
      "function_names": [
        "_build_key_and_cert"
      ],
      "filenames": [
        "sros2/sros2/api/__init__.py"
      ]
    }
  ],
  "scores": [
    {
      "stats": {
        "fn": 2,
        "tp": 0,
        "fp": 2
      },
      "mapping": {},
      "vuln_dates": {
        "CVE-2019-19625": "2019-12-06T16:15:11",
        "CVE-2019-19627": "2019-12-06T16:15:11"
      },
      "scoring_model": "claude-3-opus-20240229",
      "type": "llm",
      "instruction_template_hash": "245ace12b6361954d0a2"
    },
    {
      "stats": {
        "fn": 2,
        "tp": 0,
        "fp": 2
      },
      "mapping": {},
      "vuln_dates": {
        "CVE-2019-19625": "2019-12-06T16:15:11",
        "CVE-2019-19627": "2019-12-06T16:15:11"
      },
      "scoring_model": "claude-3-5-sonnet-20240620",
      "type": "llm",
      "instruction_template_hash": "245ace12b6361954d0a2"
    }
  ],
  "instruction_template_hash": "10c0163db4740318a544",
  "version": "0.1.0"
}
