{
  "commit": "3b3bc471642440e83f33d32c6dad971deffa1401",
  "repo_url": "https://github.com/troglobit/ssdp-responder",
  "model": "claude-3-sonnet-20240229",
  "chunk_hashes": [
    "d8e30a590c02a0883650"
  ],
  "responses": [
    {
      "content": "```yaml\nleads:\n  - headline: Improper restriction of multicast group membership\n    analysis: |\n      The code uses the `IP_ADD_MEMBERSHIP` socket option to join the multicast group, but it does not check whether the join was successful or whether the membership was already added. If the membership is added multiple times without being dropped, it can lead to a resource leak and potentially cause issues with multicast traffic handling.\n    cwe: CWE-20\n    function_names:\n      - open_socket\n      - multicast_join\n    filenames:\n      - ssdpd.c\n    classification: very promising\n\n  - headline: Integer underflow in announcement interval parsing\n    analysis: |\n      The code parses the announcement interval from the command line arguments using `atoi`, but it does not validate the result against integer underflow. If the input string represents a very large negative number, it can cause an integer underflow, leading to an unexpectedly small announcement interval or even a wraparound to a large positive value.\n    cwe: CWE-191\n    function_names:\n      - main\n    filenames:\n      - ssdpd.c\n    classification: slightly promising\n\n  - headline: Buffer overflow in web server response\n    analysis: |\n      The web server code constructs the response buffer by concatenating several strings without properly checking the buffer size or performing bounds checking. If the combined length of the strings exceeds the buffer size, it can lead to a buffer overflow vulnerability.\n    cwe: CWE-120\n    function_names:\n      - respond\n    filenames:\n      - web.c\n    classification: very promising\n\n  - headline: Potential use of hard-coded credentials\n    analysis: |\n      The code includes default values for the server string and the manufacturer URL, which could potentially contain hard-coded credentials or sensitive information. If these values are not properly sanitized or replaced with appropriate values during deployment, it could lead to the exposure of sensitive information.\n    cwe: CWE-798\n    function_names: []\n    filenames:\n      - ssdpd.c\n      - web.c\n    classification: slightly promising\n\n  - headline: Lack of input validation for interface names\n    analysis: |\n      The code reads interface names from command line arguments and uses them for filtering and binding sockets. However, it does not validate the input interface names, potentially allowing an attacker to pass crafted input that could lead to unexpected behavior or vulnerabilities.\n    cwe: CWE-20\n    function_names:\n      - ssdp_init\n      - filter_iface\n    filenames:\n      - ssdpd.c\n    classification: slightly promising\n\n  - headline: Potential time-of-check, time-of-use (TOCTOU) race condition\n    analysis: |\n      The code performs a check to determine if a socket needs to be added or removed based on the interface addresses. However, there is a window between checking the interface addresses and registering or closing the socket, during which the interface state could change. This could lead to a time-of-check, time-of-use (TOCTOU) race condition vulnerability.\n    cwe: CWE-367\n    function_names:\n      - ssdp_init\n    filenames:\n      - ssdpd.c\n    classification: slightly promising\n```\n\nThe analysis covers several potential security vulnerabilities in the codebase, including improper restriction of multicast group membership, integer underflow, buffer overflow, use of hard-coded credentials, lack of input validation, and a potential time-of-check, time-of-use (TOCTOU) race condition.\n\nThe most promising leads are:\n\n1. **Improper restriction of multicast group membership**: This vulnerability could lead to resource leaks and issues with multicast traffic handling if the multicast group membership is added multiple times without being dropped.\n\n2. **Buffer overflow in web server response**: The web server code constructs the response buffer without proper bounds checking, which could lead to a buffer overflow vulnerability if the combined length of the strings exceeds the buffer size.\n\nOther slightly promising leads include integer underflow in announcement interval parsing, potential use of hard-coded credentials, lack of input validation for interface names, and a potential TOCTOU race condition.\n\nIt's important to note that a more comprehensive code review and testing would be necessary to confirm the existence and exploitability of these potential vulnerabilities.",
      "date": "2024-07-08T09:00:20.559351",
      "usage": {
        "prompt_tokens": 22093,
        "completion_tokens": 998,
        "cost": 0.081249
      }
    }
  ],
  "leads": [
    {
      "headline": "Improper restriction of multicast group membership",
      "analysis": "The code uses the IP_ADD_MEMBERSHIP socket option to join the multicast group, but it does not check whether the join was successful or whether the membership was already added. If the membership is added multiple times without being dropped, it can lead to a resource leak and potentially cause issues with multicast traffic handling.\n",
      "classification": "very promising",
      "cwe": "CWE-20",
      "function_names": [
        "open_socket",
        "multicast_join"
      ],
      "filenames": [
        "ssdpd.c"
      ]
    },
    {
      "headline": "Integer underflow in announcement interval parsing",
      "analysis": "The code parses the announcement interval from the command line arguments using atoi, but it does not validate the result against integer underflow. If the input string represents a very large negative number, it can cause an integer underflow, leading to an unexpectedly small announcement interval or even a wraparound to a large positive value.\n",
      "classification": "slightly promising",
      "cwe": "CWE-191",
      "function_names": [
        "main"
      ],
      "filenames": [
        "ssdpd.c"
      ]
    },
    {
      "headline": "Buffer overflow in web server response",
      "analysis": "The web server code constructs the response buffer by concatenating several strings without properly checking the buffer size or performing bounds checking. If the combined length of the strings exceeds the buffer size, it can lead to a buffer overflow vulnerability.\n",
      "classification": "very promising",
      "cwe": "CWE-120",
      "function_names": [
        "respond"
      ],
      "filenames": [
        "web.c"
      ]
    },
    {
      "headline": "Potential use of hard-coded credentials",
      "analysis": "The code includes default values for the server string and the manufacturer URL, which could potentially contain hard-coded credentials or sensitive information. If these values are not properly sanitized or replaced with appropriate values during deployment, it could lead to the exposure of sensitive information.\n",
      "classification": "slightly promising",
      "cwe": "CWE-798",
      "function_names": [],
      "filenames": [
        "ssdpd.c",
        "web.c"
      ]
    },
    {
      "headline": "Lack of input validation for interface names",
      "analysis": "The code reads interface names from command line arguments and uses them for filtering and binding sockets. However, it does not validate the input interface names, potentially allowing an attacker to pass crafted input that could lead to unexpected behavior or vulnerabilities.\n",
      "classification": "slightly promising",
      "cwe": "CWE-20",
      "function_names": [
        "ssdp_init",
        "filter_iface"
      ],
      "filenames": [
        "ssdpd.c"
      ]
    },
    {
      "headline": "Potential time-of-check, time-of-use (TOCTOU) race condition",
      "analysis": "The code performs a check to determine if a socket needs to be added or removed based on the interface addresses. However, there is a window between checking the interface addresses and registering or closing the socket, during which the interface state could change. This could lead to a time-of-check, time-of-use (TOCTOU) race condition vulnerability.\n",
      "classification": "slightly promising",
      "cwe": "CWE-367",
      "function_names": [
        "ssdp_init"
      ],
      "filenames": [
        "ssdpd.c"
      ]
    }
  ],
  "scores": [
    {
      "stats": {
        "fn": 1,
        "tp": 0,
        "fp": 2
      },
      "mapping": {},
      "vuln_dates": {
        "CVE-2019-14323": "2019-07-28T13:15:10"
      },
      "scoring_model": "claude-3-5-sonnet-20240620",
      "type": "llm",
      "instruction_template_hash": "245ace12b6361954d0a2"
    }
  ],
  "instruction_template_hash": "10c0163db4740318a544",
  "version": "0.1.0"
}
