{
  "commit": "31517f6677e3578e6f7eeb0da658a37c0fc84345",
  "repo_url": "https://github.com/jenkinsci/jclouds-plugin",
  "model": "gpt-4o-2024-05-13",
  "chunk_hashes": [
    "df3fd9329747d6f168ab"
  ],
  "responses": [
    {
      "content": "```yaml\nleads:\n  - headline: XSS vulnerability in HTTP response\n    analysis: |\n      In JCloudsCloudTest.java, the input for configuring a cloud profile is not properly sanitized before being rendered in the HTML response. This can allow an attacker to inject malicious scripts which can execute in the context of other users viewing the response.\n    cwe: CWE-79\n    function_names:\n      - testConfigurationUI\n    filenames:\n      - jclouds-plugin/src/test/java/jenkins/plugins/jclouds/compute/JCloudsCloudTest.java\n    classification: very promising\n\n  - headline: Hard-coded sensitive credentials in test file\n    analysis: |\n      The file SSHPublicKeyExtractorTest.java contains a hard-coded RSA private key and DSA private key. These sensitive credentials should not be included in the test file as they pose a security risk if used in production-like environments.\n    cwe: CWE-798\n    function_names: []\n    filenames:\n      - jclouds-plugin/src/test/java/jenkins/plugins/jclouds/internal/SSHPublicKeyExtractorTest.java\n    classification: slightly promising\n\n  - headline: Insecure temporary file creation\n    analysis: |\n      In BlobStorePublisher.java, the method \"upload\" temporarily stores data locally before uploading it to the blobstore. If not handled securely, this might lead to exposure of the data.\n    cwe: CWE-377\n    function_names:\n      - upload\n    filenames:\n      - jclouds-plugin/src/main/java/jenkins/plugins/jclouds/blobstore/BlobStorePublisher.java\n    classification: very promising\n\n  - headline: Insecure handling of multithreaded input streams\n    analysis: |\n      In the class RetryOnExceptionSupplier.java, multiple retries for creating nodes might lead to race conditions due to improper synchronization mechanisms used. This can cause unpredictable states in the node creation process.\n    cwe: CWE-362\n    function_names:\n      - call\n    filenames:\n      - jclouds-plugin/src/main/java/jenkins/plugins/jclouds/compute/internal/RetryOnExceptionSupplier.java\n    classification: very promising\n\n  - headline: Potential resource exhaustion due to missing limits\n    analysis: |\n      In the method setFinal in JCloudsSlaveTemplate.java, there is a loop which tries to use reflection to set final variables. This loop does not have any restriction on the number of retries, which can potentially be a resource exhaustion vulnerability.\n    cwe: CWE-770\n    function_names:\n      - setFinal\n    filenames:\n      - jclouds-plugin/src/main/java/jenkins/plugins/jclouds/compute/JCloudsSlaveTemplate.java\n    classification: slightly promising\n```",
      "date": "2024-06-12T18:41:20.657020",
      "usage": {
        "prompt_tokens": 78576,
        "completion_tokens": 561,
        "cost": 0.401295
      }
    }
  ],
  "leads": [
    {
      "headline": "XSS vulnerability in HTTP response",
      "analysis": "In JCloudsCloudTest.java, the input for configuring a cloud profile is not properly sanitized before being rendered in the HTML response. This can allow an attacker to inject malicious scripts which can execute in the context of other users viewing the response.\n",
      "classification": "very promising",
      "cwe": "CWE-79",
      "function_names": [
        "testConfigurationUI"
      ],
      "filenames": [
        "jclouds-plugin/src/test/java/jenkins/plugins/jclouds/compute/JCloudsCloudTest.java"
      ]
    },
    {
      "headline": "Hard-coded sensitive credentials in test file",
      "analysis": "The file SSHPublicKeyExtractorTest.java contains a hard-coded RSA private key and DSA private key. These sensitive credentials should not be included in the test file as they pose a security risk if used in production-like environments.\n",
      "classification": "slightly promising",
      "cwe": "CWE-798",
      "function_names": [],
      "filenames": [
        "jclouds-plugin/src/test/java/jenkins/plugins/jclouds/internal/SSHPublicKeyExtractorTest.java"
      ]
    },
    {
      "headline": "Insecure temporary file creation",
      "analysis": "In BlobStorePublisher.java, the method \"upload\" temporarily stores data locally before uploading it to the blobstore. If not handled securely, this might lead to exposure of the data.\n",
      "classification": "very promising",
      "cwe": "CWE-377",
      "function_names": [
        "upload"
      ],
      "filenames": [
        "jclouds-plugin/src/main/java/jenkins/plugins/jclouds/blobstore/BlobStorePublisher.java"
      ]
    },
    {
      "headline": "Insecure handling of multithreaded input streams",
      "analysis": "In the class RetryOnExceptionSupplier.java, multiple retries for creating nodes might lead to race conditions due to improper synchronization mechanisms used. This can cause unpredictable states in the node creation process.\n",
      "classification": "very promising",
      "cwe": "CWE-362",
      "function_names": [
        "call"
      ],
      "filenames": [
        "jclouds-plugin/src/main/java/jenkins/plugins/jclouds/compute/internal/RetryOnExceptionSupplier.java"
      ]
    },
    {
      "headline": "Potential resource exhaustion due to missing limits",
      "analysis": "In the method setFinal in JCloudsSlaveTemplate.java, there is a loop which tries to use reflection to set final variables. This loop does not have any restriction on the number of retries, which can potentially be a resource exhaustion vulnerability.\n",
      "classification": "slightly promising",
      "cwe": "CWE-770",
      "function_names": [
        "setFinal"
      ],
      "filenames": [
        "jclouds-plugin/src/main/java/jenkins/plugins/jclouds/compute/JCloudsSlaveTemplate.java"
      ]
    }
  ],
  "scores": [
    {
      "stats": {
        "fn": 2,
        "tp": 0,
        "fp": 3
      },
      "mapping": {},
      "vuln_dates": {
        "CVE-2019-10369": "2019-08-07T15:15:12",
        "CVE-2019-10368": "2019-08-07T15:15:12"
      },
      "scoring_model": "claude-3-opus-20240229",
      "type": "llm",
      "instruction_template_hash": "245ace12b6361954d0a2"
    }
  ],
  "instruction_template_hash": "10c0163db4740318a544",
  "version": "0.1.0"
}
