{
  "commit": "177ab3715b3c1070432258f91886373acb3ca2de",
  "repo_url": "https://github.com/ssshooter/mind-elixir-core",
  "model": "gpt-4o-2024-05-13",
  "chunk_hashes": [
    "8af17bf551d116405d76"
  ],
  "responses": [
    {
      "content": "```yaml\nleads:\n  - headline: \"Command Injection in Jest Configuration\"\n    analysis: |\n      The Jest configuration file allows for dynamic module loading via the \"moduleNameMapper\" property. The \"moduleNameMapper\" maps regular expressions to module paths, which can lead to command injection if user input is improperly sanitized. An attacker could manipulate input paths that are used by Jest to load modules, executing arbitrary commands or code.\n    cwe: CWE-78\n    function_names: []\n    filenames:\n      - \"jest.config.js\"\n    classification: very promising\n\n  - headline: \"Unsafe Serialization in Babel Configuration\"\n    analysis: |\n      The Babel configuration uses JSON-like serialization for presets and plugins, which may not be sanitized correctly. Unsafe user inputs could lead to injection of arbitrary code or alteration of Babel configurations, potentially leading to code execution or logic manipulation.\n    cwe: CWE-502\n    function_names: []\n    filenames:\n      - \"babel.config.js\"\n    classification: slightly promising\n\n  - headline: \"Use of Insecure Dependencies in Webpack Configuration\"\n    analysis: |\n      The Webpack configuration includes several dependencies that are subject to inclusion from untrusted sources. Notably, \"uglifyjs-webpack-plugin\" and \"webpack-bundle-analyzer\" are included without specifying precise versions, which may lead to pulling in unpatched versions vulnerable to various attacks.\n    cwe: CWE-829\n    function_names: []\n    filenames:\n      - \"webpack.config.js\"\n    classification: slightly promising\n\n  - headline: \"Cross-Site Scripting (XSS) in HTML Template\"\n    analysis: |\n      The HTML template (`index.html`) contains a possible vector for Cross-Site Scripting (XSS) attacks. There\u2019s no default sanitization for user inputs that might be included in the HTML, making it vulnerable if those inputs are displayed back to the user.\n    cwe: CWE-79\n    function_names: []\n    filenames:\n      - \"src/index.html\"\n    classification: very promising\n\n  - headline: \"Potential Insecure Handling of Sensitive Data in Mind Map Data Exports\"\n    analysis: |\n      The capabilities to export mind map data to JSON or HTML format in `src/interact.js` may be misused to expose sensitive data. Proper validation and verification mechanisms are necessary to ensure that no unauthorized data is included in the exports.\n    cwe: CWE-200\n    function_names:\n      - \"getAllDataString\"\n      - \"getAllDataMd\"\n    filenames:\n      - \"src/interact.js\"\n    classification: slightly promising\n\n  - headline: \"Improper Input Validation in Node Operations\"\n    analysis: |\n      Functions for node manipulation (`insertSibling`, `addChild`) in `src/nodeOperation.js` do not appear to sanitize or validate inputs rigorously. This could allow unintended nodes to be added, manipulated, or deleted, leading to potential application logic vulnerabilities.\n    cwe: CWE-20\n    function_names:\n      - \"insertSibling\"\n      - \"addChild\"\n    filenames:\n      - \"src/nodeOperation.js\"\n    classification: slightly promising\n\n  - headline: \"Prototype Pollution in Plugin Loader\"\n    analysis: |\n      The plugin loader supports adding various plugins to the core application. Without proper sanitation, it is possible for an attacker to manipulate the data structure or inject malicious properties into object prototypes.\n    cwe: CWE-1321\n    function_names: []\n    filenames:\n      - \"src/plugin/nodeMenu.js\"\n      - \"src/plugin/toolBar.js\"\n    classification: slightly promising\n\n  - headline: \"Server-Side Request Forgery (SSRF) in Export Functions\"\n    analysis: |\n      The functions designed to export data to SVG or PNG (`exportSvg`, `exportPng`) within the `painter` module could be exploited to perform SSRF attacks if user-controlled URLs are not properly sanitized. This could lead to unauthorized access to internal services.\n    cwe: CWE-918\n    function_names:\n      - \"exportSvg\"\n      - \"exportPng\"\n    filenames:\n      - \"painter/index.js\"\n    classification: very promising\n```",
      "date": "2024-06-13T12:00:30.549839",
      "usage": {
        "prompt_tokens": 82582,
        "completion_tokens": 853,
        "cost": 0.425705
      }
    }
  ],
  "leads": [
    {
      "headline": "Command Injection in Jest Configuration",
      "analysis": "The Jest configuration file allows for dynamic module loading via the \"moduleNameMapper\" property. The \"moduleNameMapper\" maps regular expressions to module paths, which can lead to command injection if user input is improperly sanitized. An attacker could manipulate input paths that are used by Jest to load modules, executing arbitrary commands or code.\n",
      "classification": "very promising",
      "cwe": "CWE-78",
      "function_names": [],
      "filenames": [
        "jest.config.js"
      ]
    },
    {
      "headline": "Unsafe Serialization in Babel Configuration",
      "analysis": "The Babel configuration uses JSON-like serialization for presets and plugins, which may not be sanitized correctly. Unsafe user inputs could lead to injection of arbitrary code or alteration of Babel configurations, potentially leading to code execution or logic manipulation.\n",
      "classification": "slightly promising",
      "cwe": "CWE-502",
      "function_names": [],
      "filenames": [
        "babel.config.js"
      ]
    },
    {
      "headline": "Use of Insecure Dependencies in Webpack Configuration",
      "analysis": "The Webpack configuration includes several dependencies that are subject to inclusion from untrusted sources. Notably, \"uglifyjs-webpack-plugin\" and \"webpack-bundle-analyzer\" are included without specifying precise versions, which may lead to pulling in unpatched versions vulnerable to various attacks.\n",
      "classification": "slightly promising",
      "cwe": "CWE-829",
      "function_names": [],
      "filenames": [
        "webpack.config.js"
      ]
    },
    {
      "headline": "Cross-Site Scripting (XSS) in HTML Template",
      "analysis": "The HTML template (index.html) contains a possible vector for Cross-Site Scripting (XSS) attacks. There\u2019s no default sanitization for user inputs that might be included in the HTML, making it vulnerable if those inputs are displayed back to the user.\n",
      "classification": "very promising",
      "cwe": "CWE-79",
      "function_names": [],
      "filenames": [
        "src/index.html"
      ]
    },
    {
      "headline": "Potential Insecure Handling of Sensitive Data in Mind Map Data Exports",
      "analysis": "The capabilities to export mind map data to JSON or HTML format in src/interact.js may be misused to expose sensitive data. Proper validation and verification mechanisms are necessary to ensure that no unauthorized data is included in the exports.\n",
      "classification": "slightly promising",
      "cwe": "CWE-200",
      "function_names": [
        "getAllDataString",
        "getAllDataMd"
      ],
      "filenames": [
        "src/interact.js"
      ]
    },
    {
      "headline": "Improper Input Validation in Node Operations",
      "analysis": "Functions for node manipulation (insertSibling, addChild) in src/nodeOperation.js do not appear to sanitize or validate inputs rigorously. This could allow unintended nodes to be added, manipulated, or deleted, leading to potential application logic vulnerabilities.\n",
      "classification": "slightly promising",
      "cwe": "CWE-20",
      "function_names": [
        "insertSibling",
        "addChild"
      ],
      "filenames": [
        "src/nodeOperation.js"
      ]
    },
    {
      "headline": "Prototype Pollution in Plugin Loader",
      "analysis": "The plugin loader supports adding various plugins to the core application. Without proper sanitation, it is possible for an attacker to manipulate the data structure or inject malicious properties into object prototypes.\n",
      "classification": "slightly promising",
      "cwe": "CWE-1321",
      "function_names": [],
      "filenames": [
        "src/plugin/nodeMenu.js",
        "src/plugin/toolBar.js"
      ]
    },
    {
      "headline": "Server-Side Request Forgery (SSRF) in Export Functions",
      "analysis": "The functions designed to export data to SVG or PNG (exportSvg, exportPng) within the painter module could be exploited to perform SSRF attacks if user-controlled URLs are not properly sanitized. This could lead to unauthorized access to internal services.\n",
      "classification": "very promising",
      "cwe": "CWE-918",
      "function_names": [
        "exportSvg",
        "exportPng"
      ],
      "filenames": [
        "painter/index.js"
      ]
    }
  ],
  "scores": [
    {
      "stats": {
        "fn": 1,
        "tp": 0,
        "fp": 3
      },
      "mapping": {},
      "vuln_dates": {
        "CVE-2021-32851": "2023-02-20T22:15:11"
      },
      "scoring_model": "claude-3-opus-20240229",
      "type": "llm",
      "instruction_template_hash": "245ace12b6361954d0a2"
    }
  ],
  "instruction_template_hash": "10c0163db4740318a544",
  "version": "0.1.0"
}
