{
  "commit": "04d180e11a8502855d051b2b6ba18fc88026e8e2",
  "repo_url": "https://github.com/yuezk/globalprotect-openconnect",
  "model": "gpt-4-turbo-2024-04-09",
  "chunk_hashes": [
    "2a5eeddc75fbf26f5a51"
  ],
  "responses": [
    {
      "content": "```yaml\nleads:\n  - headline: Insecure use of 'eval' in CDPCommandManager::sendCommand resulting in potential code injection\n    analysis: |\n      The method sendCommand in the CDPCommandManager class uses QVariantMap which gets converted directly to JSON strings\n      and sent over a web socket. This approach does not properly validate or escape the content, which could lead to code injection\n      if malicious data is crafted in such a way that it escapes the current data context and is executed as code.\n    cwe: CWE-94\n    function_names:\n      - sendCommand\n      - sendCommend\n    filenames:\n      - /GPClient/cdpcommandmanager.cpp\n    classification: very promising\n\n  - headline: Lack of SSL/TLS certificate validation\n    analysis: |\n      The method gpclient::helper::createRequest in gphelper.cpp configures the SSL settings to not verify peers, with the \n      configuration directive QSslConfiguration::setPeerVerifyMode set to QSslSocket::VerifyNone. This means it accepts any \n      SSL/TLS certificate provided by the server during the SSL handshake, without validating whether the certificate is \n      trusted, expired, or revoked. This exposes users to man-in-the-middle attacks.\n    cwe: CWE-295\n    function_traits:\n      - createRequest\n    filenames:\n      - GPClient/gphelper.cpp\n    classification: very promising\n\n  - headline: Possible shell command injection via system calls in script files\n    analysis: |\n      Several shell scripts such as release.sh make use of external input within system commands\n      without adequate sanitization. For instance, in release.sh, the captured version from the VERSION file is directly \n      used within git commit and git tag commands, potentially allowing the execution of arbitrary OS commands.\n    cwe: CWE-78\n    function_names: []\n    filenames: \n      - scripts/release.sh\n      - scripts/prepare-packaging.sh\n    classification: slightly promising\n\n  - headline: Exposure of sensitive log information\n    analysis: |\n      The GPService's onProcessStdout method logs detailed output that includes potentially sensitive information regarding the VPN connection,\n      which might contain host addresses, usernames, or cookies depending on the verbosity of the OpenConnect tool output being logged. This sensitive\n      data could be discovered by unauthorized users if the log output is not properly controlled or if logs are inadequately secured.\n    cwe: CWE-532\n    function_names:\n      - onProcessStdout\n    filenames:\n      - GPService/gpservice.cpp\n    classification: slightly promising\n\n  - headline: Use of Uninitialized Resource in the GPClient's user settings handling\n    analysis: |\n      In GPClient::setupSettings and other methods in GPClient, there's direct dependency on the settings retrieved from QSettings, without prior checks to\n      ensure they have been initialized or set up properly. If the settings keys or paths are incorrectly configured, or if external modifications lead to\n      corrupted or missing settings, the software might exhibit erratic behavior or crashes due to reliance on these uninitialized settings.\n    cwe: CWE-908\n    function_names:\n      - setupSettings\n      - onSettingsAccepted\n      - onSettingsButtonClicked\n    filenames:\n      - GPClient/gpclient.cpp\n    classification: not promising\n```",
      "date": "2024-06-14T11:02:26.833476",
      "usage": {
        "prompt_tokens": 30975,
        "completion_tokens": 687,
        "cost": 0.33036
      }
    }
  ],
  "leads": [
    {
      "headline": "Insecure use of 'eval' in CDPCommandManager::sendCommand resulting in potential code injection",
      "analysis": "The method sendCommand in the CDPCommandManager class uses QVariantMap which gets converted directly to JSON strings\nand sent over a web socket. This approach does not properly validate or escape the content, which could lead to code injection\nif malicious data is crafted in such a way that it escapes the current data context and is executed as code.\n",
      "classification": "very promising",
      "cwe": "CWE-94",
      "function_names": [
        "sendCommand",
        "sendCommend"
      ],
      "filenames": [
        "/GPClient/cdpcommandmanager.cpp"
      ]
    },
    {
      "headline": "Lack of SSL/TLS certificate validation",
      "analysis": "The method gpclient::helper::createRequest in gphelper.cpp configures the SSL settings to not verify peers, with the \nconfiguration directive QSslConfiguration::setPeerVerifyMode set to QSslSocket::VerifyNone. This means it accepts any \nSSL/TLS certificate provided by the server during the SSL handshake, without validating whether the certificate is \ntrusted, expired, or revoked. This exposes users to man-in-the-middle attacks.\n",
      "classification": "very promising",
      "cwe": "CWE-295",
      "function_names": [],
      "filenames": [
        "GPClient/gphelper.cpp"
      ]
    },
    {
      "headline": "Possible shell command injection via system calls in script files",
      "analysis": "Several shell scripts such as release.sh make use of external input within system commands\nwithout adequate sanitization. For instance, in release.sh, the captured version from the VERSION file is directly \nused within git commit and git tag commands, potentially allowing the execution of arbitrary OS commands.\n",
      "classification": "slightly promising",
      "cwe": "CWE-78",
      "function_names": [],
      "filenames": [
        "scripts/release.sh",
        "scripts/prepare-packaging.sh"
      ]
    },
    {
      "headline": "Exposure of sensitive log information",
      "analysis": "The GPService's onProcessStdout method logs detailed output that includes potentially sensitive information regarding the VPN connection,\nwhich might contain host addresses, usernames, or cookies depending on the verbosity of the OpenConnect tool output being logged. This sensitive\ndata could be discovered by unauthorized users if the log output is not properly controlled or if logs are inadequately secured.\n",
      "classification": "slightly promising",
      "cwe": "CWE-532",
      "function_names": [
        "onProcessStdout"
      ],
      "filenames": [
        "GPService/gpservice.cpp"
      ]
    },
    {
      "headline": "Use of Uninitialized Resource in the GPClient's user settings handling",
      "analysis": "In GPClient::setupSettings and other methods in GPClient, there's direct dependency on the settings retrieved from QSettings, without prior checks to\nensure they have been initialized or set up properly. If the settings keys or paths are incorrectly configured, or if external modifications lead to\ncorrupted or missing settings, the software might exhibit erratic behavior or crashes due to reliance on these uninitialized settings.\n",
      "classification": "not promising",
      "cwe": "CWE-908",
      "function_names": [
        "setupSettings",
        "onSettingsAccepted",
        "onSettingsButtonClicked"
      ],
      "filenames": [
        "GPClient/gpclient.cpp"
      ]
    }
  ],
  "scores": [
    {
      "stats": {
        "fn": 1,
        "tp": 0,
        "fp": 2
      },
      "mapping": {},
      "vuln_dates": {
        "CVE-2021-45809": "2022-03-22T11:15:07"
      },
      "scoring_model": "claude-3-opus-20240229",
      "type": "llm",
      "instruction_template_hash": "245ace12b6361954d0a2"
    }
  ],
  "instruction_template_hash": "10c0163db4740318a544",
  "version": "0.1.0"
}
