{
  "commit": "3095cff7d99e99e42183cc3f65d1f2938fbf08f5",
  "repo_url": "https://github.com/jc21/nginx-proxy-manager",
  "model": "gpt-4-turbo-2024-04-09",
  "chunk_hashes": [
    "3b319fa950e488bd408d"
  ],
  "responses": [
    {
      "content": "```yaml\nleads:\n  - headline: \"Improper Input Validation for Environment Variables\"\n    analysis: |\n      The codebase contains various instances where environment variables such as NODE_ENV are used directly without proper validation. This might lead to security vulnerabilities where an attacker can exploit these variables, potentially causing the application to execute in an unintended mode. For example, setting NODE_ENV to a different environment could expose sensitive information if the application changes its behavior based on the presumed environment (development, production, etc.).\n    cwe: CWE-20\n    function_names:\n      - appStart\n      - initTimer\n    filenames:\n      - src/frontend/js/app/main.js\n      - src/backend/internal/nginx.js\n    classification: \"very promising\"\n\n  - headline: \"Exposure of Sensitive Information to an Unauthorized Actor\"\n    analysis: |\n      The application logs sensitive data in various circumstances which can lead to exposure of sensitive information such as the internal state, environment variables, or configurations. This is evident from the use cases where debugging and error logging are implemented, potentially leaking information that should not be accessible.\n    cwe: CWE-532\n    function_names:\n      - fetch\n      - bootstrapTimer\n      - refreshTokenTimer\n    filenames:\n      - src/frontend/js/app/api.js\n      - src/frontend/js/app/main.js\n    classification: \"very promising\"\n\n  - headline: \"Missing Authentication for Critical Function\"\n    analysis: |\n      Certain critical operations such as managing settings and configurations do not explicitly require authentication checks, especially when performed via APIs. This could allow an unauthenticated user to perform actions that would typically require admin privileges. For instance, update operations in settings and issuance of tokens don't explicitly verify whether the API call was made by a legitimate and authenticated user.\n    cwe: CWE-306\n    function_names:\n      - Tokens.login\n      - update\n    filenames:\n      - src/frontend/js/app/api.js\n      - src/frontend/js/app/settings/main.js\n    classification: \"slightly promising\"\n\n  - headline: \"Insecure Storage of Sensitive Information\"\n    analysis: |\n      Sensitive data such as user settings, configurations, and SSL certificates are stored without sufficient encryption, exposing them to potential disclosure. While the application incorporates token-based security, the physical storage of sensitive data in plain formats (as seen in models and configuration JSONs) can be easily accessed or modified by unauthorized parties.\n    cwe: CWE-922\n    function_names:\n      - setStorageTokens\n      - showModalDialog\n    filenames:\n      - src/frontend/js/app/tokens.js\n      - src/frontend/js/app/ui/main.js\n    classification: \"very promising\"\n```",
      "date": "2024-06-12T17:28:05.089668",
      "usage": {
        "prompt_tokens": 100772,
        "completion_tokens": 545,
        "cost": 1.02407
      }
    }
  ],
  "leads": [
    {
      "headline": "Improper Input Validation for Environment Variables",
      "analysis": "The codebase contains various instances where environment variables such as NODE_ENV are used directly without proper validation. This might lead to security vulnerabilities where an attacker can exploit these variables, potentially causing the application to execute in an unintended mode. For example, setting NODE_ENV to a different environment could expose sensitive information if the application changes its behavior based on the presumed environment (development, production, etc.).\n",
      "classification": "very promising",
      "cwe": "CWE-20",
      "function_names": [
        "appStart",
        "initTimer"
      ],
      "filenames": [
        "src/frontend/js/app/main.js",
        "src/backend/internal/nginx.js"
      ]
    },
    {
      "headline": "Exposure of Sensitive Information to an Unauthorized Actor",
      "analysis": "The application logs sensitive data in various circumstances which can lead to exposure of sensitive information such as the internal state, environment variables, or configurations. This is evident from the use cases where debugging and error logging are implemented, potentially leaking information that should not be accessible.\n",
      "classification": "very promising",
      "cwe": "CWE-532",
      "function_names": [
        "fetch",
        "bootstrapTimer",
        "refreshTokenTimer"
      ],
      "filenames": [
        "src/frontend/js/app/api.js",
        "src/frontend/js/app/main.js"
      ]
    },
    {
      "headline": "Missing Authentication for Critical Function",
      "analysis": "Certain critical operations such as managing settings and configurations do not explicitly require authentication checks, especially when performed via APIs. This could allow an unauthenticated user to perform actions that would typically require admin privileges. For instance, update operations in settings and issuance of tokens don't explicitly verify whether the API call was made by a legitimate and authenticated user.\n",
      "classification": "slightly promising",
      "cwe": "CWE-306",
      "function_names": [
        "Tokens.login",
        "update"
      ],
      "filenames": [
        "src/frontend/js/app/api.js",
        "src/frontend/js/app/settings/main.js"
      ]
    },
    {
      "headline": "Insecure Storage of Sensitive Information",
      "analysis": "Sensitive data such as user settings, configurations, and SSL certificates are stored without sufficient encryption, exposing them to potential disclosure. While the application incorporates token-based security, the physical storage of sensitive data in plain formats (as seen in models and configuration JSONs) can be easily accessed or modified by unauthorized parties.\n",
      "classification": "very promising",
      "cwe": "CWE-922",
      "function_names": [
        "setStorageTokens",
        "showModalDialog"
      ],
      "filenames": [
        "src/frontend/js/app/tokens.js",
        "src/frontend/js/app/ui/main.js"
      ]
    }
  ],
  "scores": [
    {
      "stats": {
        "fn": 1,
        "tp": 0,
        "fp": 3
      },
      "mapping": {},
      "vuln_dates": {
        "CVE-2019-15517": "2019-08-23T15:15:10"
      },
      "scoring_model": "claude-3-opus-20240229",
      "type": "llm",
      "instruction_template_hash": "245ace12b6361954d0a2"
    },
    {
      "stats": {
        "fn": 1,
        "tp": 0,
        "fp": 3
      },
      "mapping": {},
      "vuln_dates": {
        "CVE-2019-15517": "2019-08-23T15:15:10"
      },
      "scoring_model": "claude-3-5-sonnet-20240620",
      "type": "llm",
      "instruction_template_hash": "245ace12b6361954d0a2"
    }
  ],
  "instruction_template_hash": "10c0163db4740318a544",
  "version": "0.1.0"
}
