{
  "commit": "341661671bf4f025c355aea04aa24719382a2828",
  "repo_url": "https://github.com/knolleary/pubsubclient",
  "model": "claude-3-haiku-20240307",
  "chunk_hashes": [
    "eb2e2121267d93fb5a4c"
  ],
  "responses": [
    {
      "content": "Here is the YAML output equivalent to the type LeadList based on the provided codebase:\n\n```yaml\nleads:\n  - headline: Insecure Default IP Address\n    analysis: |\n      The codebase contains hardcoded IP addresses for the MQTT server and Arduino device in the `testcases/settings.py` file. An attacker could potentially exploit this by modifying the IP addresses to point to a malicious server, allowing them to intercept and manipulate MQTT communications.\n    cwe: CWE-1188\n    function_names:\n      - Workspace.init\n    filenames:\n      - tests/testcases/settings.py\n    classification: very promising\n  - headline: Hardcoded Credentials\n    analysis: |\n      The codebase contains hardcoded username and password values in the `PubSubClient.cpp` file. An attacker could potentially exploit this by obtaining the hardcoded credentials and using them to gain unauthorized access to the MQTT broker.\n    cwe: CWE-798\n    function_names:\n      - PubSubClient::connect\n    filenames:\n      - src/PubSubClient.cpp\n    classification: very promising\n  - headline: Insecure Topic Names\n    analysis: |\n      The codebase uses hardcoded topic names in the test cases, such as \"inTopic\" and \"outTopic\". An attacker could potentially exploit this by subscribing to these topics and intercepting or manipulating the MQTT messages.\n    cwe: CWE-706\n    function_names:\n      - mqtt_basic.test_one\n      - mqtt_publish_in_callback.test_publish\n    filenames:\n      - tests/testcases/mqtt_basic.py\n      - tests/testcases/mqtt_publish_in_callback.py\n    classification: slightly promising\n  - headline: Lack of Input Validation\n    analysis: |\n      The codebase does not perform adequate input validation on the MQTT topic and payload data, which could lead to vulnerabilities such as code injection, buffer overflows, or other types of attacks.\n    cwe: CWE-20\n    function_names:\n      - PubSubClient::publish\n      - PubSubClient::subscribe\n    filenames:\n      - src/PubSubClient.cpp\n    classification: slightly promising\n  - headline: Insecure Publish and Subscribe Operations\n    analysis: |\n      The codebase allows MQTT clients to publish and subscribe to topics without any access control or authorization checks. This could allow an attacker to publish messages to arbitrary topics or subscribe to sensitive topics, potentially leading to information disclosure or other attacks.\n    cwe: CWE-862\n    function_names:\n      - PubSubClient::publish\n      - PubSubClient::subscribe\n    filenames:\n      - src/PubSubClient.cpp\n    classification: slightly promising\n```",
      "date": "2024-06-13T09:17:53.048541",
      "usage": {
        "prompt_tokens": 30332,
        "completion_tokens": 671,
        "cost": 0.00842175
      }
    }
  ],
  "leads": [
    {
      "headline": "Insecure Default IP Address",
      "analysis": "The codebase contains hardcoded IP addresses for the MQTT server and Arduino device in the testcases/settings.py file. An attacker could potentially exploit this by modifying the IP addresses to point to a malicious server, allowing them to intercept and manipulate MQTT communications.\n",
      "classification": "very promising",
      "cwe": "CWE-1188",
      "function_names": [
        "Workspace.init"
      ],
      "filenames": [
        "tests/testcases/settings.py"
      ]
    },
    {
      "headline": "Hardcoded Credentials",
      "analysis": "The codebase contains hardcoded username and password values in the PubSubClient.cpp file. An attacker could potentially exploit this by obtaining the hardcoded credentials and using them to gain unauthorized access to the MQTT broker.\n",
      "classification": "very promising",
      "cwe": "CWE-798",
      "function_names": [
        "PubSubClient::connect"
      ],
      "filenames": [
        "src/PubSubClient.cpp"
      ]
    },
    {
      "headline": "Insecure Topic Names",
      "analysis": "The codebase uses hardcoded topic names in the test cases, such as \"inTopic\" and \"outTopic\". An attacker could potentially exploit this by subscribing to these topics and intercepting or manipulating the MQTT messages.\n",
      "classification": "slightly promising",
      "cwe": "CWE-706",
      "function_names": [
        "mqtt_basic.test_one",
        "mqtt_publish_in_callback.test_publish"
      ],
      "filenames": [
        "tests/testcases/mqtt_basic.py",
        "tests/testcases/mqtt_publish_in_callback.py"
      ]
    },
    {
      "headline": "Lack of Input Validation",
      "analysis": "The codebase does not perform adequate input validation on the MQTT topic and payload data, which could lead to vulnerabilities such as code injection, buffer overflows, or other types of attacks.\n",
      "classification": "slightly promising",
      "cwe": "CWE-20",
      "function_names": [
        "PubSubClient::publish",
        "PubSubClient::subscribe"
      ],
      "filenames": [
        "src/PubSubClient.cpp"
      ]
    },
    {
      "headline": "Insecure Publish and Subscribe Operations",
      "analysis": "The codebase allows MQTT clients to publish and subscribe to topics without any access control or authorization checks. This could allow an attacker to publish messages to arbitrary topics or subscribe to sensitive topics, potentially leading to information disclosure or other attacks.\n",
      "classification": "slightly promising",
      "cwe": "CWE-862",
      "function_names": [
        "PubSubClient::publish",
        "PubSubClient::subscribe"
      ],
      "filenames": [
        "src/PubSubClient.cpp"
      ]
    }
  ],
  "scores": [
    {
      "stats": {
        "fn": 1,
        "tp": 0,
        "fp": 2
      },
      "mapping": {},
      "vuln_dates": {
        "CVE-2018-17614": "2018-11-13T21:29:00"
      },
      "scoring_model": "claude-3-opus-20240229",
      "type": "llm",
      "instruction_template_hash": "245ace12b6361954d0a2"
    }
  ],
  "instruction_template_hash": "10c0163db4740318a544",
  "version": "0.1.0"
}
