{
  "commit": "390a6c9eefa59917108cb60acd73dde51b0843f0",
  "repo_url": "https://github.com/ubernostrum/django-registration",
  "model": "claude-3-haiku-20240307",
  "chunk_hashes": [
    "5ef39cf15e70f9760b8d"
  ],
  "responses": [
    {
      "content": "Here is the YAML object equivalent to type LeadList, with the identified security vulnerabilities:\n\n```yaml\nleads:\n  - headline: Improper Input Validation\n    analysis: |\n      The codebase contains multiple instances of improper input validation, which can lead to vulnerabilities such as buffer overflow, integer overflow/wraparound, and other types of injection attacks. Specific instances include:\n      - CWE-129 Improper Validation of Array Index: The codebase may not properly validate input values used as array indices, leading to out-of-bounds read/write vulnerabilities.\n      - CWE-20 Improper Input Validation: The codebase may not properly validate user input before using it, leading to various injection vulnerabilities.\n    cwe: CWE-20\n    function_names:\n      - register\n      - activate\n    filenames:\n      - src/django_registration/forms.py\n      - src/django_registration/validators.py\n      - tests/test_forms.py\n    classification: slightly promising\n\n  - headline: Injection Vulnerabilities\n    analysis: |\n      The codebase contains multiple instances of injection vulnerabilities, including:\n      - CWE-89 SQL Injection: The codebase may not properly sanitize user input used in SQL queries, leading to SQL injection attacks.\n      - CWE-94 Code Injection: The codebase may not properly sanitize user input used in dynamic code execution, leading to code injection attacks.\n      - CWE-79 Cross-Site Scripting (XSS): The codebase may not properly sanitize user input used in HTML output, leading to XSS attacks.\n    cwe: CWE-74\n    function_names:\n      - register\n      - activate\n    filenames:\n      - src/django_registration/forms.py\n      - src/django_registration/validators.py\n      - tests/test_forms.py\n    classification: very promising\n\n  - headline: Insecure Cryptographic Practices\n    analysis: |\n      The codebase may use insecure cryptographic algorithms or practices, such as:\n      - CWE-327 Use of a Broken or Risky Cryptographic Algorithm: The codebase may use cryptographic algorithms that are known to be weak or insecure.\n      - CWE-326 Inadequate Encryption Strength: The codebase may use cryptographic algorithms with insufficient key lengths or other parameters, leading to attacks.\n      - CWE-311 Missing Encryption of Sensitive Data: The codebase may transmit or store sensitive data without proper encryption.\n    cwe: CWE-326\n    function_names:\n      - get_activation_key\n      - validate_key\n    filenames:\n      - src/django_registration/backends/activation/views.py\n    classification: slightly promising\n\n  - headline: Insecure Configuration\n    analysis: |\n      The codebase may contain insecure configuration settings, such as:\n      - CWE-732 Incorrect Permission Assignment for Critical Resource: The codebase may not properly set permissions on critical resources, leading to unauthorized access.\n      - CWE-668 Exposure of Resource to Wrong Sphere: The codebase may expose resources to the wrong sphere, leading to unauthorized access or information disclosure.\n    cwe: CWE-732\n    function_names:\n      - register\n      - activate\n    filenames:\n      - src/django_registration/views.py\n      - src/django_registration/backends/activation/views.py\n    classification: slightly promising\n\n  - headline: Improper Handling of Exceptional Conditions\n    analysis: |\n      The codebase may not properly handle exceptional conditions, leading to vulnerabilities such as:\n      - CWE-754 Improper Check for Unusual or Exceptional Conditions: The codebase may not properly check for and handle unusual or exceptional conditions, leading to vulnerabilities.\n      - CWE-755 Improper Handling of Exceptional Conditions: The codebase may not properly handle exceptional conditions, leading to vulnerabilities.\n    cwe: CWE-754\n    function_names:\n      - activate\n    filenames:\n      - src/django_registration/backends/activation/views.py\n    classification: slightly promising\n```",
      "date": "2024-07-08T09:06:49.812659",
      "usage": {
        "prompt_tokens": 25310,
        "completion_tokens": 998,
        "cost": 0.007575
      }
    }
  ],
  "leads": [
    {
      "headline": "Improper Input Validation",
      "analysis": "The codebase contains multiple instances of improper input validation, which can lead to vulnerabilities such as buffer overflow, integer overflow/wraparound, and other types of injection attacks. Specific instances include:\n- CWE-129 Improper Validation of Array Index: The codebase may not properly validate input values used as array indices, leading to out-of-bounds read/write vulnerabilities.\n- CWE-20 Improper Input Validation: The codebase may not properly validate user input before using it, leading to various injection vulnerabilities.\n",
      "classification": "slightly promising",
      "cwe": "CWE-20",
      "function_names": [
        "register",
        "activate"
      ],
      "filenames": [
        "src/django_registration/forms.py",
        "src/django_registration/validators.py",
        "tests/test_forms.py"
      ]
    },
    {
      "headline": "Injection Vulnerabilities",
      "analysis": "The codebase contains multiple instances of injection vulnerabilities, including:\n- CWE-89 SQL Injection: The codebase may not properly sanitize user input used in SQL queries, leading to SQL injection attacks.\n- CWE-94 Code Injection: The codebase may not properly sanitize user input used in dynamic code execution, leading to code injection attacks.\n- CWE-79 Cross-Site Scripting (XSS): The codebase may not properly sanitize user input used in HTML output, leading to XSS attacks.\n",
      "classification": "very promising",
      "cwe": "CWE-74",
      "function_names": [
        "register",
        "activate"
      ],
      "filenames": [
        "src/django_registration/forms.py",
        "src/django_registration/validators.py",
        "tests/test_forms.py"
      ]
    },
    {
      "headline": "Insecure Cryptographic Practices",
      "analysis": "The codebase may use insecure cryptographic algorithms or practices, such as:\n- CWE-327 Use of a Broken or Risky Cryptographic Algorithm: The codebase may use cryptographic algorithms that are known to be weak or insecure.\n- CWE-326 Inadequate Encryption Strength: The codebase may use cryptographic algorithms with insufficient key lengths or other parameters, leading to attacks.\n- CWE-311 Missing Encryption of Sensitive Data: The codebase may transmit or store sensitive data without proper encryption.\n",
      "classification": "slightly promising",
      "cwe": "CWE-326",
      "function_names": [
        "get_activation_key",
        "validate_key"
      ],
      "filenames": [
        "src/django_registration/backends/activation/views.py"
      ]
    },
    {
      "headline": "Insecure Configuration",
      "analysis": "The codebase may contain insecure configuration settings, such as:\n- CWE-732 Incorrect Permission Assignment for Critical Resource: The codebase may not properly set permissions on critical resources, leading to unauthorized access.\n- CWE-668 Exposure of Resource to Wrong Sphere: The codebase may expose resources to the wrong sphere, leading to unauthorized access or information disclosure.\n",
      "classification": "slightly promising",
      "cwe": "CWE-732",
      "function_names": [
        "register",
        "activate"
      ],
      "filenames": [
        "src/django_registration/views.py",
        "src/django_registration/backends/activation/views.py"
      ]
    },
    {
      "headline": "Improper Handling of Exceptional Conditions",
      "analysis": "The codebase may not properly handle exceptional conditions, leading to vulnerabilities such as:\n- CWE-754 Improper Check for Unusual or Exceptional Conditions: The codebase may not properly check for and handle unusual or exceptional conditions, leading to vulnerabilities.\n- CWE-755 Improper Handling of Exceptional Conditions: The codebase may not properly handle exceptional conditions, leading to vulnerabilities.\n",
      "classification": "slightly promising",
      "cwe": "CWE-754",
      "function_names": [
        "activate"
      ],
      "filenames": [
        "src/django_registration/backends/activation/views.py"
      ]
    }
  ],
  "scores": [
    {
      "stats": {
        "fn": 1,
        "tp": 0,
        "fp": 1
      },
      "mapping": {},
      "vuln_dates": {
        "CVE-2021-21416": "2021-04-01T22:15:11"
      },
      "scoring_model": "claude-3-5-sonnet-20240620",
      "type": "llm",
      "instruction_template_hash": "245ace12b6361954d0a2"
    }
  ],
  "instruction_template_hash": "10c0163db4740318a544",
  "version": "0.1.0"
}
