{
  "commit": "154a0a274acc5408442349af8b3f5bb3c3bc3c3e",
  "repo_url": "https://github.com/mubarakalmehairbi/toui",
  "model": "claude-3-5-sonnet-20240620",
  "chunk_hashes": [
    "fff3d7970702c63b4874"
  ],
  "responses": [
    {
      "content": "```yaml\nleads:\n  - headline: Insecure storage of sensitive information\n    analysis: |\n      The secret key for the Flask application is hardcoded directly in the source code in multiple places. For example, in example_1_simple_website.py, the secret key is set to \"some text\". This is insecure as it exposes the secret key in plaintext in the source code. The secret key should be stored securely, such as in an environment variable, and retrieved at runtime.\n    cwe: CWE-798\n    function_names:\n      - Website.__init__\n    filenames:\n      - examples/example_1_simple_website.py\n      - examples/example_3_updating_page.py\n      - examples/example_4_function_with_arg.py\n      - examples/example_5_user_variables.py\n    classification: slightly promising\n\n  - headline: Potential XSS vulnerability in user input handling\n    analysis: |\n      In example_3_updating_page.py and example_5_user_variables.py, user input is retrieved from HTML elements and directly inserted back into the page without any sanitization or encoding. This could allow an attacker to inject malicious scripts that would be executed in the victim's browser. Proper input validation, sanitization and output encoding should be implemented to prevent XSS attacks.\n    cwe: CWE-79\n    function_names:\n      - addValues\n      - loadData  \n    filenames:\n      - examples/example_3_updating_page.py\n      - examples/example_5_user_variables.py\n    classification: slightly promising\n\n  - headline: Insecure direct object references\n    analysis: |\n      The app.get_user_page() method in multiple examples allows retrieving the current user's page object directly. If not properly restricted, this could potentially allow unauthorized access to other users' pages. The method should implement proper access controls to ensure a user can only access their own page data.\n    cwe: CWE-639\n    function_names:\n      - Website.get_user_page\n    filenames:\n      - toui/apps.py\n    classification: slightly promising\n\n  - headline: Potential information exposure through error messages\n    analysis: |\n      The error handling in the _communicate method of the _App class prints full exception details, which could potentially expose sensitive information about the application's internal workings to an attacker. Error messages visible to users should be sanitized to avoid leaking implementation details.\n    cwe: CWE-209\n    function_names:\n      - _App._communicate\n    filenames:\n      - toui/apps.py  \n    classification: slightly promising\n\n  - headline: Use of a broken or risky cryptographic algorithm\n    analysis: |\n      The app uses os.urandom() to generate a random secret key if one is not provided. While better than a hardcoded key, os.urandom() is not cryptographically secure and should not be used for generating secret keys. A proper cryptographic key generation function should be used instead.\n    cwe: CWE-327\n    function_names:\n      - _App.__init__\n    filenames:\n      - toui/apps.py\n    classification: slightly promising\n```",
      "date": "2024-07-08T07:53:18.120314",
      "usage": {
        "prompt_tokens": 37182,
        "completion_tokens": 746,
        "cost": 0.122736
      }
    }
  ],
  "leads": [
    {
      "headline": "Insecure storage of sensitive information",
      "analysis": "The secret key for the Flask application is hardcoded directly in the source code in multiple places. For example, in example_1_simple_website.py, the secret key is set to \"some text\". This is insecure as it exposes the secret key in plaintext in the source code. The secret key should be stored securely, such as in an environment variable, and retrieved at runtime.\n",
      "classification": "slightly promising",
      "cwe": "CWE-798",
      "function_names": [
        "Website.__init__"
      ],
      "filenames": [
        "examples/example_1_simple_website.py",
        "examples/example_3_updating_page.py",
        "examples/example_4_function_with_arg.py"
      ]
    },
    {
      "headline": "Potential XSS vulnerability in user input handling",
      "analysis": "In example_3_updating_page.py and example_5_user_variables.py, user input is retrieved from HTML elements and directly inserted back into the page without any sanitization or encoding. This could allow an attacker to inject malicious scripts that would be executed in the victim's browser. Proper input validation, sanitization and output encoding should be implemented to prevent XSS attacks.\n",
      "classification": "slightly promising",
      "cwe": "CWE-79",
      "function_names": [
        "addValues",
        "loadData"
      ],
      "filenames": [
        "examples/example_3_updating_page.py",
        "examples/example_5_user_variables.py"
      ]
    },
    {
      "headline": "Insecure direct object references",
      "analysis": "The app.get_user_page() method in multiple examples allows retrieving the current user's page object directly. If not properly restricted, this could potentially allow unauthorized access to other users' pages. The method should implement proper access controls to ensure a user can only access their own page data.\n",
      "classification": "slightly promising",
      "cwe": "CWE-639",
      "function_names": [
        "Website.get_user_page"
      ],
      "filenames": [
        "toui/apps.py"
      ]
    },
    {
      "headline": "Potential information exposure through error messages",
      "analysis": "The error handling in the _communicate method of the _App class prints full exception details, which could potentially expose sensitive information about the application's internal workings to an attacker. Error messages visible to users should be sanitized to avoid leaking implementation details.\n",
      "classification": "slightly promising",
      "cwe": "CWE-209",
      "function_names": [
        "_App._communicate"
      ],
      "filenames": [
        "toui/apps.py"
      ]
    },
    {
      "headline": "Use of a broken or risky cryptographic algorithm",
      "analysis": "The app uses os.urandom() to generate a random secret key if one is not provided. While better than a hardcoded key, os.urandom() is not cryptographically secure and should not be used for generating secret keys. A proper cryptographic key generation function should be used instead.\n",
      "classification": "slightly promising",
      "cwe": "CWE-327",
      "function_names": [
        "_App.__init__"
      ],
      "filenames": [
        "toui/apps.py"
      ]
    }
  ],
  "scores": [
    {
      "stats": {
        "fn": 1,
        "tp": 0,
        "fp": 0
      },
      "mapping": {},
      "vuln_dates": {
        "CVE-2023-33175": "2023-05-30T05:15:11"
      },
      "scoring_model": "claude-3-5-sonnet-20240620",
      "type": "llm",
      "instruction_template_hash": "245ace12b6361954d0a2"
    }
  ],
  "instruction_template_hash": "10c0163db4740318a544",
  "version": "0.1.0"
}
