{
  "commit": "836922e884c27f1295012589749514f2682d25c8",
  "repo_url": "https://github.com/xwikisas/application-licensing",
  "model": "gpt-4o-2024-05-13",
  "chunk_hashes": [
    "045d5ba1ed042b53ed37"
  ],
  "responses": [
    {
      "content": "```yaml\nleads:\n  - headline: Potential Unhandled Exception in DefaultLicenseValidator\n    analysis: |\n      In the `DefaultLicenseValidator` class, the `checkUserCount` method invokes `userCounter.getUserCount()`, expecting no exceptions. If `userCounter.getUserCount()` throws an exception, it implies the license is invalid. An attacker could exploit this scenario by causing denials of service or using it to bypass license checks.\n    cwe: CWE-754\n    function_names:\n      - checkUserCount\n    filenames:\n      - application-licensing-licensor/application-licensing-licensor-api/src/main/java/com/xwiki/licensing/internal/DefaultLicenseValidator.java\n    classification: very promising\n\n  - headline: Potential SQL Injection in getUserCount\n    analysis: |\n      The `UserCounter` class constructs an SQL query dynamically in the `getUserCountOnWiki` method using string concatenation. If not properly sanitized, attackers could exploit this to perform SQL injection attacks.\n    cwe: CWE-89\n    function_names:\n      - getUserCountOnWiki\n    filenames:\n      - application-licensing-licensor/application-licensing-licensor-api/src/main/java/com/xwiki/licensing/internal/UserCounter.java\n    classification: very promising\n\n  - headline: Hard-coded Cryptographic Keys\n    analysis: |\n      In `SignedLicenseTestUtils.java`, the cryptographic keys (DSA private and public keys) are hard-coded. This poses a significant security risk as an attacker could exploit this information to compromise the security of the application.\n    cwe: CWE-798\n    function_names:\n      - getSigningKeyPair\n    filenames:\n      - application-licensing-common/application-licensing-common-api/src/test/java/com/xwiki/licensing/test/internal/DefaultSignedLicenseTestUtils.java\n    classification: very promising\n\n  - headline: Permissions Not Verified in LicensingScriptService\n    analysis: |\n      The `LicenseScriptService` class has methods that interact with the filesystem and don't adequately check permissions or validate input paths before accessing them. This could enable unauthorized information disclosure or filesystem manipulation.\n    cwe: CWE-269\n    function_names:\n      - getFileLicenseStore\n    filenames:\n      - application-licensing-common/application-licensing-common-api/src/main/java/com/xwiki/licensing/script/LicenseScriptService.java\n    classification: very promising\n\n  - headline: Potential Data Exposure in LicenseConverter\n    analysis: |\n      Data that may be sensitive (e.g., license information) is logged when conversion exceptions occur in `LicenseConverter`. If the log level includes debug information in a production environment, it can expose sensitive data.\n    cwe: CWE-532\n    function_names:\n      - convertToType\n    filenames:\n      - application-licensing-common/application-licensing-common-api/src/main/java/com/xwiki/licensing/internal/LicenseConverter.java\n    classification: slightly promising\n\n  - headline: Weak Exception Handling in TrialLicenseGenerator\n    analysis: |\n      The `TrialLicenseGenerator` class catches generic `Exception` types in several places (e.g., updateLicenses and generateTrialLicense methods). This pattern may hide specific errors, making debugging difficult and potentially allowing minor issues to escalate.\n    cwe: CWE-397\n    function_names:\n      - updateLicenses\n      - generateTrialLicense\n    filenames:\n      - application-licensing-licensor/application-licensing-licensor-api/src/main/java/com/xwiki/licensing/internal/TrialLicenseGenerator.java\n    classification: slightly promising\n\n  - headline: Overly Broad Catch in LicensingInitializer\n    analysis: |\n      The `initializeLicensingSystem` method in `LicensingInitializer` catches `Exception` and ignores potential sub-issues. Overly broad catches can obscure genuine issues and weaken fault tolerance.\n    cwe: CWE-397\n    function_names:\n      - initializeLicensingSystem\n    filenames:\n      - application-licensing-licensor/application-licensing-licensor-api/src/main/java/com/xwiki/licensing/internal/enforcer/LicensingInitializer.java\n    classification: slightly promising\n\n  - headline: Insecure Configuration Handling\n    analysis: |\n      The `DefaultLicensingConfiguration` class relies heavily on user-provided paths and URLs for its operations. If these inputs are not validated correctly, this could lead to insecure configurations.\n    cwe: CWE-20\n    function_names:\n      - getLocalStorePath\n      - getAutoUpgradeAllowList\n    filenames:\n      - application-licensing-licensor/application-licensing-licensor-api/src/main/java/com/xwiki/licensing/internal/DefaultLicensingConfiguration.java\n    classification: slightly promising\n```",
      "date": "2024-06-09T15:32:29.619062",
      "usage": {
        "prompt_tokens": 113143,
        "completion_tokens": 974,
        "cost": 0.580325
      }
    }
  ],
  "leads": [
    {
      "headline": "Potential Unhandled Exception in DefaultLicenseValidator",
      "analysis": "In the DefaultLicenseValidator class, the checkUserCount method invokes userCounter.getUserCount(), expecting no exceptions. If userCounter.getUserCount() throws an exception, it implies the license is invalid. An attacker could exploit this scenario by causing denials of service or using it to bypass license checks.\n",
      "classification": "very promising",
      "cwe": "CWE-754",
      "function_names": [
        "checkUserCount"
      ],
      "filenames": [
        "application-licensing-licensor/application-licensing-licensor-api/src/main/java/com/xwiki/licensing/internal/DefaultLicenseValidator.java"
      ]
    },
    {
      "headline": "Potential SQL Injection in getUserCount",
      "analysis": "The UserCounter class constructs an SQL query dynamically in the getUserCountOnWiki method using string concatenation. If not properly sanitized, attackers could exploit this to perform SQL injection attacks.\n",
      "classification": "very promising",
      "cwe": "CWE-89",
      "function_names": [
        "getUserCountOnWiki"
      ],
      "filenames": [
        "application-licensing-licensor/application-licensing-licensor-api/src/main/java/com/xwiki/licensing/internal/UserCounter.java"
      ]
    },
    {
      "headline": "Hard-coded Cryptographic Keys",
      "analysis": "In SignedLicenseTestUtils.java, the cryptographic keys (DSA private and public keys) are hard-coded. This poses a significant security risk as an attacker could exploit this information to compromise the security of the application.\n",
      "classification": "very promising",
      "cwe": "CWE-798",
      "function_names": [
        "getSigningKeyPair"
      ],
      "filenames": [
        "application-licensing-common/application-licensing-common-api/src/test/java/com/xwiki/licensing/test/internal/DefaultSignedLicenseTestUtils.java"
      ]
    },
    {
      "headline": "Permissions Not Verified in LicensingScriptService",
      "analysis": "The LicenseScriptService class has methods that interact with the filesystem and don't adequately check permissions or validate input paths before accessing them. This could enable unauthorized information disclosure or filesystem manipulation.\n",
      "classification": "very promising",
      "cwe": "CWE-269",
      "function_names": [
        "getFileLicenseStore"
      ],
      "filenames": [
        "application-licensing-common/application-licensing-common-api/src/main/java/com/xwiki/licensing/script/LicenseScriptService.java"
      ]
    },
    {
      "headline": "Potential Data Exposure in LicenseConverter",
      "analysis": "Data that may be sensitive (e.g., license information) is logged when conversion exceptions occur in LicenseConverter. If the log level includes debug information in a production environment, it can expose sensitive data.\n",
      "classification": "slightly promising",
      "cwe": "CWE-532",
      "function_names": [
        "convertToType"
      ],
      "filenames": [
        "application-licensing-common/application-licensing-common-api/src/main/java/com/xwiki/licensing/internal/LicenseConverter.java"
      ]
    },
    {
      "headline": "Weak Exception Handling in TrialLicenseGenerator",
      "analysis": "The TrialLicenseGenerator class catches generic Exception types in several places (e.g., updateLicenses and generateTrialLicense methods). This pattern may hide specific errors, making debugging difficult and potentially allowing minor issues to escalate.\n",
      "classification": "slightly promising",
      "cwe": "CWE-397",
      "function_names": [
        "updateLicenses",
        "generateTrialLicense"
      ],
      "filenames": [
        "application-licensing-licensor/application-licensing-licensor-api/src/main/java/com/xwiki/licensing/internal/TrialLicenseGenerator.java"
      ]
    },
    {
      "headline": "Overly Broad Catch in LicensingInitializer",
      "analysis": "The initializeLicensingSystem method in LicensingInitializer catches Exception and ignores potential sub-issues. Overly broad catches can obscure genuine issues and weaken fault tolerance.\n",
      "classification": "slightly promising",
      "cwe": "CWE-397",
      "function_names": [
        "initializeLicensingSystem"
      ],
      "filenames": [
        "application-licensing-licensor/application-licensing-licensor-api/src/main/java/com/xwiki/licensing/internal/enforcer/LicensingInitializer.java"
      ]
    },
    {
      "headline": "Insecure Configuration Handling",
      "analysis": "The DefaultLicensingConfiguration class relies heavily on user-provided paths and URLs for its operations. If these inputs are not validated correctly, this could lead to insecure configurations.\n",
      "classification": "slightly promising",
      "cwe": "CWE-20",
      "function_names": [
        "getLocalStorePath",
        "getAutoUpgradeAllowList"
      ],
      "filenames": [
        "application-licensing-licensor/application-licensing-licensor-api/src/main/java/com/xwiki/licensing/internal/DefaultLicensingConfiguration.java"
      ]
    }
  ],
  "scores": [
    {
      "stats": {
        "fn": 1,
        "tp": 0,
        "fp": 4
      },
      "mapping": {},
      "vuln_dates": {
        "CVE-2024-26138": "2024-02-21T17:15:10"
      },
      "scoring_model": "gpt-4o-2024-05-13",
      "type": "llm",
      "instruction_template_hash": "8998f09cf57fca8a6e03"
    },
    {
      "stats": {
        "fn": 1,
        "tp": 0,
        "fp": 4
      },
      "mapping": {},
      "vuln_dates": {
        "CVE-2024-26138": "2024-02-21T17:15:10"
      },
      "scoring_model": "claude-3-opus-20240229",
      "type": "llm",
      "instruction_template_hash": "245ace12b6361954d0a2"
    },
    {
      "stats": {
        "fn": 1,
        "tp": 0,
        "fp": 4
      },
      "mapping": {},
      "vuln_dates": {
        "CVE-2024-26138": "2024-02-21T17:15:10"
      },
      "scoring_model": "claude-3-5-sonnet-20240620",
      "type": "llm",
      "instruction_template_hash": "245ace12b6361954d0a2"
    }
  ],
  "instruction_template_hash": "10c0163db4740318a544",
  "version": "0.1.0"
}
