{
  "commit": "eb4ddd0503114577a9b523d6e416ce41c8d1dc92",
  "repo_url": "https://github.com/plannigan/hyper-bump-it",
  "model": "gpt-4o-2024-05-13",
  "chunk_hashes": [
    "898182f9c7014cde33d5"
  ],
  "responses": [
    {
      "content": "```yaml\nleads:\n  - headline: Missing Encryption for Sensitive Data in Config File\n    analysis: |\n      Sensitive data, such as the current version information, is stored in configuration files in plaintext. This can potentially expose sensitive information if the configuration file is accessed by unauthorized users.\n    cwe: CWE-311\n    function_names:\n      - read_config\n    filenames:\n      - hyper_bump_it/_hyper_bump_it/config/file.py\n      - hyper_bump_it/_hyper_bump_it/config/application.py\n    classification: very promising\n  \n  - headline: Arbitrary Code Execution via Dynamic Imports\n    analysis: |\n      The application dynamically imports modules and executes functions specified in the configuration files, which could be manipulated by an attacker to execute arbitrary code.\n    cwe: CWE-94\n    function_names:\n      - None\n    filenames:\n      - hyper_bump_it/_hyper_bump_it/config/application.py\n    classification: very promising\n\n  - headline: Security Misconfiguration of File Permissions\n    analysis: |\n      The codebase does not adequately set file permissions when creating or modifying configuration files. This could lead to sensitive configuration files being readable by unauthorized users.\n    cwe: CWE-276\n    function_names:\n      - _write_config\n      - perform_change\n    filenames:\n      - hyper_bump_it/_hyper_bump_it/cli/init.py\n      - hyper_bump_it/_hyper_bump_it/files.py\n    classification: very promising\n\n  - headline: Unauthorized Access to Git Repositories\n    analysis: |\n      The codebase does not enforce authentication and authorization checks when interacting with Git repositories, potentially allowing unauthorized users to make changes to the repositories.\n    cwe: CWE-287\n    function_names:\n      - get_vetted_repo\n    filenames:\n      - hyper_bump_it/_hyper_bump_it/vcs.py\n    classification: slightly promising\n\n  - headline: Improper Input Validation in CLI Argument Parsing\n    analysis: |\n      The CLI argument parsing does not enforce sufficient input validation, leaving the application vulnerable to injection attacks.\n    cwe: CWE-20\n    function_names:\n      - _create_option_factory\n      - _check_action\n    filenames:\n      - hyper_bump_it/_hyper_bump_it/cli/common.py\n      - hyper_bump_it/_hyper_bump_it/config/file.py\n    classification: very promising\n```",
      "date": "2024-06-09T14:09:41.440930",
      "usage": {
        "prompt_tokens": 85438,
        "completion_tokens": 493,
        "cost": 0.434585
      }
    }
  ],
  "leads": [
    {
      "headline": "Missing Encryption for Sensitive Data in Config File",
      "analysis": "Sensitive data, such as the current version information, is stored in configuration files in plaintext. This can potentially expose sensitive information if the configuration file is accessed by unauthorized users.\n",
      "classification": "very promising",
      "cwe": "CWE-311",
      "function_names": [
        "read_config"
      ],
      "filenames": [
        "hyper_bump_it/_hyper_bump_it/config/file.py",
        "hyper_bump_it/_hyper_bump_it/config/application.py"
      ]
    },
    {
      "headline": "Arbitrary Code Execution via Dynamic Imports",
      "analysis": "The application dynamically imports modules and executes functions specified in the configuration files, which could be manipulated by an attacker to execute arbitrary code.\n",
      "classification": "very promising",
      "cwe": "CWE-94",
      "function_names": [
        "None"
      ],
      "filenames": [
        "hyper_bump_it/_hyper_bump_it/config/application.py"
      ]
    },
    {
      "headline": "Security Misconfiguration of File Permissions",
      "analysis": "The codebase does not adequately set file permissions when creating or modifying configuration files. This could lead to sensitive configuration files being readable by unauthorized users.\n",
      "classification": "very promising",
      "cwe": "CWE-276",
      "function_names": [
        "_write_config",
        "perform_change"
      ],
      "filenames": [
        "hyper_bump_it/_hyper_bump_it/cli/init.py",
        "hyper_bump_it/_hyper_bump_it/files.py"
      ]
    },
    {
      "headline": "Unauthorized Access to Git Repositories",
      "analysis": "The codebase does not enforce authentication and authorization checks when interacting with Git repositories, potentially allowing unauthorized users to make changes to the repositories.\n",
      "classification": "slightly promising",
      "cwe": "CWE-287",
      "function_names": [
        "get_vetted_repo"
      ],
      "filenames": [
        "hyper_bump_it/_hyper_bump_it/vcs.py"
      ]
    },
    {
      "headline": "Improper Input Validation in CLI Argument Parsing",
      "analysis": "The CLI argument parsing does not enforce sufficient input validation, leaving the application vulnerable to injection attacks.\n",
      "classification": "very promising",
      "cwe": "CWE-20",
      "function_names": [
        "_create_option_factory",
        "_check_action"
      ],
      "filenames": [
        "hyper_bump_it/_hyper_bump_it/cli/common.py",
        "hyper_bump_it/_hyper_bump_it/config/file.py"
      ]
    }
  ],
  "scores": [
    {
      "stats": {
        "fn": 1,
        "tp": 0,
        "fp": 4
      },
      "mapping": {},
      "vuln_dates": {
        "CVE-2023-41057": "2023-09-04T18:15:09"
      },
      "scoring_model": "gpt-4o-2024-05-13",
      "type": "llm",
      "instruction_template_hash": "8998f09cf57fca8a6e03"
    },
    {
      "stats": {
        "fn": 1,
        "tp": 0,
        "fp": 4
      },
      "mapping": {},
      "vuln_dates": {
        "CVE-2023-41057": "2023-09-04T18:15:09"
      },
      "scoring_model": "claude-3-opus-20240229",
      "type": "llm",
      "instruction_template_hash": "245ace12b6361954d0a2"
    }
  ],
  "instruction_template_hash": "10c0163db4740318a544",
  "version": "0.1.0"
}
