{
  "commit": "3eaad67a5f5b63dab58fa4d34d8c67b614be6e7b",
  "repo_url": "https://github.com/akashrajpurohit/clipper",
  "model": "claude-3-5-sonnet-20240620",
  "chunk_hashes": [
    "007a01e341e2d801a62f"
  ],
  "responses": [
    {
      "content": "```yaml\nleads:\n  - headline: Command Injection Vulnerability in System Shell Execution\n    analysis: |\n      The main.js file contains a potential command injection vulnerability in the electron.remote.shell.openExternal() call. This function executes system shell commands, and if user input is passed to it unsanitized, it could allow arbitrary command execution. The vulnerability occurs because the URL being opened is constructed using user-supplied data (the el.getAttribute(\"href\") value) without any validation or sanitization. An attacker could craft a malicious URL to inject additional shell commands that would be executed on the user's system.\n    cwe: CWE-78\n    function_names:\n      - handleFooterClick\n    filenames:\n      - renderer.js\n    classification: very promising\n\n  - headline: Unsafe Use of eval() with User-Supplied Data\n    analysis: |\n      The renderer.js file uses the eval() function to execute JavaScript code constructed from user input. Specifically, the code constructs a string containing user-supplied data from localStorage and passes it to eval(). This is extremely dangerous as it allows arbitrary JavaScript execution. An attacker could store malicious JavaScript in localStorage which would then be executed, potentially leading to XSS attacks, data theft, or other malicious actions.\n    cwe: CWE-94  \n    function_names:\n      - componentWillMount\n    filenames:\n      - renderer.js\n    classification: very promising\n\n  - headline: Potential Cross-Site Scripting (XSS) Vulnerability \n    analysis: |\n      The renderer.js file contains several instances where user-supplied content is inserted into the DOM without proper sanitization. For example, the renderRow() function directly inserts user-supplied text into the DOM using innerHTML. If this text contains malicious script tags or other JavaScript code, it could be executed, leading to XSS attacks. Similar issues exist in other functions that construct HTML dynamically. Proper encoding/escaping should be used when inserting user data into HTML contexts.\n    cwe: CWE-79\n    function_names:\n      - renderRow\n      - renderTable  \n    filenames:\n      - renderer.js\n    classification: very promising\n\n  - headline: Use of Insecure Cryptographic Algorithm\n    analysis: |\n      The preload.js file uses the MD5 hashing algorithm, which is considered cryptographically broken and unsuitable for security purposes. MD5 is vulnerable to collision attacks and should not be used for any security-critical applications. A more secure hashing algorithm like SHA-256 should be used instead. While the specific usage here is unclear without more context, using MD5 in any security-related capacity is a potential vulnerability.\n    cwe: CWE-327\n    function_names: []\n    filenames:\n      - preload.js  \n    classification: slightly promising\n\n  - headline: Potential Information Exposure Through Error Messages\n    analysis: |\n      The main.js file contains error handling that may expose sensitive information. For example, in the catch block of the try-catch statement, the full error object is logged to the console. This could potentially include sensitive data or internal system information that should not be exposed to users or potential attackers. Error messages displayed to users should be sanitized to remove any potentially sensitive information.\n    cwe: CWE-209\n    function_names: []\n    filenames:\n      - main.js\n    classification: slightly promising\n```",
      "date": "2024-07-08T05:33:38.968565",
      "usage": {
        "prompt_tokens": 138012,
        "completion_tokens": 779,
        "cost": 0.425721
      }
    }
  ],
  "leads": [
    {
      "headline": "Command Injection Vulnerability in System Shell Execution",
      "analysis": "The main.js file contains a potential command injection vulnerability in the electron.remote.shell.openExternal() call. This function executes system shell commands, and if user input is passed to it unsanitized, it could allow arbitrary command execution. The vulnerability occurs because the URL being opened is constructed using user-supplied data (the el.getAttribute(\"href\") value) without any validation or sanitization. An attacker could craft a malicious URL to inject additional shell commands that would be executed on the user's system.\n",
      "classification": "very promising",
      "cwe": "CWE-78",
      "function_names": [
        "handleFooterClick"
      ],
      "filenames": [
        "renderer.js"
      ]
    },
    {
      "headline": "Unsafe Use of eval() with User-Supplied Data",
      "analysis": "The renderer.js file uses the eval() function to execute JavaScript code constructed from user input. Specifically, the code constructs a string containing user-supplied data from localStorage and passes it to eval(). This is extremely dangerous as it allows arbitrary JavaScript execution. An attacker could store malicious JavaScript in localStorage which would then be executed, potentially leading to XSS attacks, data theft, or other malicious actions.\n",
      "classification": "very promising",
      "cwe": "CWE-94",
      "function_names": [
        "componentWillMount"
      ],
      "filenames": [
        "renderer.js"
      ]
    },
    {
      "headline": "Potential Cross-Site Scripting (XSS) Vulnerability",
      "analysis": "The renderer.js file contains several instances where user-supplied content is inserted into the DOM without proper sanitization. For example, the renderRow() function directly inserts user-supplied text into the DOM using innerHTML. If this text contains malicious script tags or other JavaScript code, it could be executed, leading to XSS attacks. Similar issues exist in other functions that construct HTML dynamically. Proper encoding/escaping should be used when inserting user data into HTML contexts.\n",
      "classification": "very promising",
      "cwe": "CWE-79",
      "function_names": [
        "renderRow",
        "renderTable"
      ],
      "filenames": [
        "renderer.js"
      ]
    },
    {
      "headline": "Use of Insecure Cryptographic Algorithm",
      "analysis": "The preload.js file uses the MD5 hashing algorithm, which is considered cryptographically broken and unsuitable for security purposes. MD5 is vulnerable to collision attacks and should not be used for any security-critical applications. A more secure hashing algorithm like SHA-256 should be used instead. While the specific usage here is unclear without more context, using MD5 in any security-related capacity is a potential vulnerability.\n",
      "classification": "slightly promising",
      "cwe": "CWE-327",
      "function_names": [],
      "filenames": [
        "preload.js"
      ]
    },
    {
      "headline": "Potential Information Exposure Through Error Messages",
      "analysis": "The main.js file contains error handling that may expose sensitive information. For example, in the catch block of the try-catch statement, the full error object is logged to the console. This could potentially include sensitive data or internal system information that should not be exposed to users or potential attackers. Error messages displayed to users should be sanitized to remove any potentially sensitive information.\n",
      "classification": "slightly promising",
      "cwe": "CWE-209",
      "function_names": [],
      "filenames": [
        "main.js"
      ]
    }
  ],
  "scores": [
    {
      "stats": {
        "fn": 0,
        "tp": 1,
        "fp": 2
      },
      "mapping": {
        "0": "CVE-2021-28134"
      },
      "vuln_dates": {
        "CVE-2021-28134": "2021-03-11T00:15:12"
      },
      "scoring_model": "claude-3-5-sonnet-20240620",
      "type": "llm",
      "instruction_template_hash": "245ace12b6361954d0a2"
    }
  ],
  "instruction_template_hash": "10c0163db4740318a544",
  "version": "0.1.0"
}
