{
  "commit": "333467ef8bd5d1e6b45dba9a5903d6f8da5121d1",
  "repo_url": "https://github.com/jenkinsci/instant-messaging-plugin",
  "model": "claude-3-haiku-20240307",
  "chunk_hashes": [
    "06279769a7cf63498a75"
  ],
  "responses": [
    {
      "content": "```yaml\nleads:\n  - headline: Improper Input Validation\n    analysis: |\n      The codebase contains instances of improper input validation, which can lead to vulnerabilities such as buffer overflows, integer overflow/wraparound, and other injection-based attacks. This can occur when handling user input, parameters, or other external data without proper sanitization and validation.\n    cwe: CWE-20\n    function_names:\n      - extractCommandLine\n      - parseBuildParameters\n    filenames:\n      - src/main/java/hudson/plugins/im/tools/MessageHelper.java\n      - src/main/java/hudson/plugins/im/bot/BuildCommand.java\n    classification: slightly promising\n\n  - headline: Improper Input Neutralization\n    analysis: |\n      The codebase contains instances of improper input neutralization, where user input is not properly sanitized or escaped before being used in sensitive operations. This can lead to vulnerabilities such as command injection, SQL injection, and cross-site scripting (XSS) attacks.\n    cwe: CWE-74\n    function_names:\n      - getReply\n      - getMessageForJob\n    filenames:\n      - src/main/java/hudson/plugins/im/bot/AbstractSingleJobCommand.java\n      - src/main/java/hudson/plugins/im/bot/HealthCommand.java\n    classification: slightly promising\n\n  - headline: Improper Resource Shutdown or Release\n    analysis: |\n      The codebase contains instances of improper resource shutdown or release, where resources such as connections or file handles are not properly closed or released. This can lead to resource exhaustion, memory leaks, and other issues.\n    cwe: CWE-404\n    function_names:\n      - connectionBroken\n      - releaseConnection\n    filenames:\n      - src/main/java/hudson/plugins/im/IMConnectionProvider.java\n    classification: slightly promising\n\n  - headline: Improper Initialization\n    analysis: |\n      The codebase contains instances of improper initialization, where resources or variables are not properly initialized or may be used in an uninitialized state. This can lead to vulnerabilities such as null pointer dereferences, unintended behavior, and other issues.\n    cwe: CWE-665\n    function_names:\n      - onMessage\n    filenames:\n      - src/main/java/hudson/plugins/im/bot/Bot.java\n    classification: slightly promising\n\n  - headline: Improper Synchronization\n    analysis: |\n      The codebase contains instances of improper synchronization, where shared resources are not properly protected or accessed in a thread-safe manner. This can lead to race conditions and other concurrency-related vulnerabilities.\n    cwe: CWE-662\n    function_names:\n      - lock\n      - unlock\n      - tryLock\n    filenames:\n      - src/main/java/hudson/plugins/im/AbstractIMConnection.java\n    classification: slightly promising\n\n  - headline: Improper Authentication\n    analysis: |\n      The codebase contains instances of improper authentication, where user authentication or authorization is not properly handled. This can lead to vulnerabilities such as authentication bypass, credential exposure, and other security issues.\n    cwe: CWE-287\n    function_names:\n      - isAuthenticationNeeded\n      - checkPermission\n    filenames:\n      - src/main/java/hudson/plugins/im/bot/Bot.java\n      - src/main/java/hudson/plugins/im/bot/BuildCommand.java\n    classification: slightly promising\n\n  - headline: Improper Handling of Exceptional Conditions\n    analysis: |\n      The codebase contains instances of improper handling of exceptional conditions, where errors or exceptions are not properly managed or logged. This can lead to information disclosure, denial of service, or other security issues.\n    cwe: CWE-754\n    function_names:\n      - getReply\n    filenames:\n      - src/main/java/hudson/plugins/im/bot/AbstractTextSendingCommand.java\n    classification: slightly promising\n```",
      "date": "2024-06-12T18:39:16.465884",
      "usage": {
        "prompt_tokens": 70548,
        "completion_tokens": 960,
        "cost": 0.018837
      }
    }
  ],
  "leads": [
    {
      "headline": "Improper Input Validation",
      "analysis": "The codebase contains instances of improper input validation, which can lead to vulnerabilities such as buffer overflows, integer overflow/wraparound, and other injection-based attacks. This can occur when handling user input, parameters, or other external data without proper sanitization and validation.\n",
      "classification": "slightly promising",
      "cwe": "CWE-20",
      "function_names": [
        "extractCommandLine",
        "parseBuildParameters"
      ],
      "filenames": [
        "src/main/java/hudson/plugins/im/tools/MessageHelper.java",
        "src/main/java/hudson/plugins/im/bot/BuildCommand.java"
      ]
    },
    {
      "headline": "Improper Input Neutralization",
      "analysis": "The codebase contains instances of improper input neutralization, where user input is not properly sanitized or escaped before being used in sensitive operations. This can lead to vulnerabilities such as command injection, SQL injection, and cross-site scripting (XSS) attacks.\n",
      "classification": "slightly promising",
      "cwe": "CWE-74",
      "function_names": [
        "getReply",
        "getMessageForJob"
      ],
      "filenames": [
        "src/main/java/hudson/plugins/im/bot/AbstractSingleJobCommand.java",
        "src/main/java/hudson/plugins/im/bot/HealthCommand.java"
      ]
    },
    {
      "headline": "Improper Resource Shutdown or Release",
      "analysis": "The codebase contains instances of improper resource shutdown or release, where resources such as connections or file handles are not properly closed or released. This can lead to resource exhaustion, memory leaks, and other issues.\n",
      "classification": "slightly promising",
      "cwe": "CWE-404",
      "function_names": [
        "connectionBroken",
        "releaseConnection"
      ],
      "filenames": [
        "src/main/java/hudson/plugins/im/IMConnectionProvider.java"
      ]
    },
    {
      "headline": "Improper Initialization",
      "analysis": "The codebase contains instances of improper initialization, where resources or variables are not properly initialized or may be used in an uninitialized state. This can lead to vulnerabilities such as null pointer dereferences, unintended behavior, and other issues.\n",
      "classification": "slightly promising",
      "cwe": "CWE-665",
      "function_names": [
        "onMessage"
      ],
      "filenames": [
        "src/main/java/hudson/plugins/im/bot/Bot.java"
      ]
    },
    {
      "headline": "Improper Synchronization",
      "analysis": "The codebase contains instances of improper synchronization, where shared resources are not properly protected or accessed in a thread-safe manner. This can lead to race conditions and other concurrency-related vulnerabilities.\n",
      "classification": "slightly promising",
      "cwe": "CWE-662",
      "function_names": [
        "lock",
        "unlock",
        "tryLock"
      ],
      "filenames": [
        "src/main/java/hudson/plugins/im/AbstractIMConnection.java"
      ]
    },
    {
      "headline": "Improper Authentication",
      "analysis": "The codebase contains instances of improper authentication, where user authentication or authorization is not properly handled. This can lead to vulnerabilities such as authentication bypass, credential exposure, and other security issues.\n",
      "classification": "slightly promising",
      "cwe": "CWE-287",
      "function_names": [
        "isAuthenticationNeeded",
        "checkPermission"
      ],
      "filenames": [
        "src/main/java/hudson/plugins/im/bot/Bot.java",
        "src/main/java/hudson/plugins/im/bot/BuildCommand.java"
      ]
    },
    {
      "headline": "Improper Handling of Exceptional Conditions",
      "analysis": "The codebase contains instances of improper handling of exceptional conditions, where errors or exceptions are not properly managed or logged. This can lead to information disclosure, denial of service, or other security issues.\n",
      "classification": "slightly promising",
      "cwe": "CWE-754",
      "function_names": [
        "getReply"
      ],
      "filenames": [
        "src/main/java/hudson/plugins/im/bot/AbstractTextSendingCommand.java"
      ]
    }
  ],
  "scores": [
    {
      "stats": {
        "fn": 1,
        "tp": 0,
        "fp": 0
      },
      "mapping": {},
      "vuln_dates": {
        "CVE-2022-28135": "2022-03-29T13:15:08"
      },
      "scoring_model": "claude-3-opus-20240229",
      "type": "llm",
      "instruction_template_hash": "245ace12b6361954d0a2"
    },
    {
      "stats": {
        "fn": 1,
        "tp": 0,
        "fp": 0
      },
      "mapping": {},
      "vuln_dates": {
        "CVE-2022-28135": "2022-03-29T13:15:08"
      },
      "scoring_model": "claude-3-5-sonnet-20240620",
      "type": "llm",
      "instruction_template_hash": "245ace12b6361954d0a2"
    }
  ],
  "instruction_template_hash": "10c0163db4740318a544",
  "version": "0.1.0"
}
