{
  "commit": "2b3eb35a9f2ad00afd09e26e4e2a988baac4dbaf",
  "repo_url": "https://github.com/matanui159/replaysorcery",
  "model": "claude-3-haiku-20240307",
  "chunk_hashes": [
    "666dff3c73c0fe01a546"
  ],
  "responses": [
    {
      "content": "Based on the provided codebase, here are the security vulnerabilities identified:\n\n```yaml\nleads:\n  - headline: Improper Input Validation\n    analysis: |\n      The codebase contains several instances of improper input validation, which can lead to vulnerabilities such as buffer overflow, integer overflow, and directory traversal. These issues can be found in the following functions:\n\n      1. rsFormatv() in src/util.c\n      2. rsOutputCreate() in src/output.c\n      3. rsOptionsSetv() in src/util.c\n    cwe: CWE-20\n    function_names:\n      - rsFormatv\n      - rsOutputCreate\n      - rsOptionsSetv\n    filenames:\n      - src/util.c\n      - src/output.c\n    classification: very promising\n\n  - headline: Improper Neutralization of Special Elements in Output Used by a Downstream Component ('Injection')\n    analysis: |\n      The codebase uses user-supplied input in several places without proper sanitization, which can lead to injection vulnerabilities. These issues can be found in the following functions:\n\n      1. rsFormat() in src/util.c\n      2. rsOptionsSet() in src/util.c\n      3. rsOptionsSetv() in src/util.c\n    cwe: CWE-74\n    function_names:\n      - rsFormat\n      - rsOptionsSet\n      - rsOptionsSetv\n    filenames:\n      - src/util.c\n    classification: very promising\n\n  - headline: Incorrect Resource Transfer Between Spheres\n    analysis: |\n      The codebase allows the user to specify the output file path, which can lead to directory traversal and other vulnerabilities. This issue can be found in the rsOutputCreate() function in src/output.c.\n    cwe: CWE-669\n    function_names:\n      - rsOutputCreate\n    filenames:\n      - src/output.c\n    classification: slightly promising\n\n  - headline: Incorrect Type Conversion or Cast\n    analysis: |\n      The codebase performs type conversions and casts without proper validation, which can lead to unexpected behavior and potential vulnerabilities. These issues can be found in the following functions:\n\n      1. rsFormatv() in src/util.c\n      2. rsXDisplayOpen() in src/util.c\n    cwe: CWE-704\n    function_names:\n      - rsFormatv\n      - rsXDisplayOpen\n    filenames:\n      - src/util.c\n    classification: slightly promising\n\n  - headline: Improper Handling of Exceptional Conditions\n    analysis: |\n      The codebase does not handle all error conditions properly, which can lead to unexpected behavior and potential vulnerabilities. This issue can be found in several functions, such as rsOutputClose() in src/output.c and rsControlWantsSave() in src/control/dbgctrl.c.\n    cwe: CWE-755\n    function_names:\n      - rsOutputClose\n      - rsControlWantsSave\n    filenames:\n      - src/output.c\n      - src/control/dbgctrl.c\n    classification: slightly promising\n```",
      "date": "2024-06-13T09:59:24.265349",
      "usage": {
        "prompt_tokens": 49355,
        "completion_tokens": 746,
        "cost": 0.01327125
      }
    }
  ],
  "leads": [
    {
      "headline": "Improper Input Validation",
      "analysis": "The codebase contains several instances of improper input validation, which can lead to vulnerabilities such as buffer overflow, integer overflow, and directory traversal. These issues can be found in the following functions:\n\n1. rsFormatv() in src/util.c\n2. rsOutputCreate() in src/output.c\n3. rsOptionsSetv() in src/util.c\n",
      "classification": "very promising",
      "cwe": "CWE-20",
      "function_names": [
        "rsFormatv",
        "rsOutputCreate",
        "rsOptionsSetv"
      ],
      "filenames": [
        "src/util.c",
        "src/output.c"
      ]
    },
    {
      "headline": "Improper Neutralization of Special Elements in Output Used by a Downstream Component ('Injection')",
      "analysis": "The codebase uses user-supplied input in several places without proper sanitization, which can lead to injection vulnerabilities. These issues can be found in the following functions:\n\n1. rsFormat() in src/util.c\n2. rsOptionsSet() in src/util.c\n3. rsOptionsSetv() in src/util.c\n",
      "classification": "very promising",
      "cwe": "CWE-74",
      "function_names": [
        "rsFormat",
        "rsOptionsSet",
        "rsOptionsSetv"
      ],
      "filenames": [
        "src/util.c"
      ]
    },
    {
      "headline": "Incorrect Resource Transfer Between Spheres",
      "analysis": "The codebase allows the user to specify the output file path, which can lead to directory traversal and other vulnerabilities. This issue can be found in the rsOutputCreate() function in src/output.c.\n",
      "classification": "slightly promising",
      "cwe": "CWE-669",
      "function_names": [
        "rsOutputCreate"
      ],
      "filenames": [
        "src/output.c"
      ]
    },
    {
      "headline": "Incorrect Type Conversion or Cast",
      "analysis": "The codebase performs type conversions and casts without proper validation, which can lead to unexpected behavior and potential vulnerabilities. These issues can be found in the following functions:\n\n1. rsFormatv() in src/util.c\n2. rsXDisplayOpen() in src/util.c\n",
      "classification": "slightly promising",
      "cwe": "CWE-704",
      "function_names": [
        "rsFormatv",
        "rsXDisplayOpen"
      ],
      "filenames": [
        "src/util.c"
      ]
    },
    {
      "headline": "Improper Handling of Exceptional Conditions",
      "analysis": "The codebase does not handle all error conditions properly, which can lead to unexpected behavior and potential vulnerabilities. This issue can be found in several functions, such as rsOutputClose() in src/output.c and rsControlWantsSave() in src/control/dbgctrl.c.\n",
      "classification": "slightly promising",
      "cwe": "CWE-755",
      "function_names": [
        "rsOutputClose",
        "rsControlWantsSave"
      ],
      "filenames": [
        "src/output.c",
        "src/control/dbgctrl.c"
      ]
    }
  ],
  "scores": [
    {
      "stats": {
        "fn": 2,
        "tp": 0,
        "fp": 2
      },
      "mapping": {},
      "vuln_dates": {
        "CVE-2021-26936": "2021-02-10T18:15:13",
        "CVE-2021-36983": "2021-07-30T14:15:18"
      },
      "scoring_model": "claude-3-opus-20240229",
      "type": "llm",
      "instruction_template_hash": "245ace12b6361954d0a2"
    },
    {
      "stats": {
        "fn": 2,
        "tp": 0,
        "fp": 2
      },
      "mapping": {},
      "vuln_dates": {
        "CVE-2021-26936": "2021-02-10T18:15:13",
        "CVE-2021-36983": "2021-07-30T14:15:18"
      },
      "scoring_model": "claude-3-5-sonnet-20240620",
      "type": "llm",
      "instruction_template_hash": "245ace12b6361954d0a2"
    }
  ],
  "instruction_template_hash": "10c0163db4740318a544",
  "version": "0.1.0"
}
