{
  "commit": "42e2a59b208e6c6660d81de0c70103403249bb55",
  "repo_url": "https://github.com/lota/phamm",
  "model": "claude-3-5-sonnet-20240620",
  "chunk_hashes": [
    "68dabb7abca19016d795"
  ],
  "responses": [
    {
      "content": "Here's a YAML analysis of potential security vulnerabilities in the provided codebase:\n\n```yaml\nleads:\n  - headline: Potential command injection vulnerability in make-mail.sh\n    analysis: |\n      The make-mail.sh script uses user-controlled input from mailq directly in shell commands without proper sanitization. An attacker could potentially inject malicious commands by manipulating mailq output. The script should validate and sanitize any user-controlled data before using it in commands.\n    cwe: CWE-78\n    function_names:\n      - mailq\n    filenames:\n      - tools/make-mail.sh\n    classification: slightly promising\n\n  - headline: Hardcoded credentials in multiple scripts\n    analysis: |\n      Several scripts contain hardcoded LDAP credentials, including usernames and passwords. This could allow an attacker who gains access to the scripts to directly access the LDAP server. Credentials should be stored securely and retrieved at runtime, not hardcoded in scripts.\n    cwe: CWE-798\n    function_names: []\n    filenames:\n      - tools/backup-basedn.sh\n      - tools/handle_vacation.sh\n      - tools/greylist_recipients_whitelists_ldap.pl\n    classification: very promising\n\n  - headline: Potential SQL injection in LDAP queries\n    analysis: |\n      The phamm-useradd.pl script constructs LDAP queries using unsanitized user input. While LDAP injection is less common than SQL injection, it's still possible an attacker could manipulate the LDAP query by injecting special characters. User input should be properly escaped before being used in LDAP queries.\n    cwe: CWE-89\n    function_names:\n      - get_user_dn2\n    filenames:\n      - tools/phamm-useradd.pl  \n    classification: slightly promising\n\n  - headline: Insecure temporary file creation\n    analysis: |\n      The handle_vacation.sh script uses the tempfile command to create temporary files without specifying a secure directory or permissions. This could potentially allow an attacker to predict the filename and access sensitive data. Temporary files should be created securely with unpredictable names in a protected directory.\n    cwe: CWE-377\n    function_names: []\n    filenames:\n      - tools/handle_vacation.sh\n    classification: slightly promising\n\n  - headline: Use of weak cryptographic algorithms\n    analysis: |\n      The phamm-useradd.pl script uses the Crypt::SmbHash module which likely implements outdated hashing algorithms like LM or NTLM. These are considered cryptographically weak. Modern, secure hashing algorithms should be used instead for password storage.\n    cwe: CWE-327\n    function_names:\n      - ntlmgen\n    filenames:  \n      - tools/phamm-useradd.pl\n    classification: slightly promising\n```\n\nThis analysis identifies some of the most critical potential security issues in the codebase, focusing on common vulnerabilities like injection flaws, credential exposure, and cryptographic weaknesses. Further in-depth analysis would be needed to confirm the exploitability of these issues.",
      "date": "2024-07-08T07:44:25.020933",
      "usage": {
        "prompt_tokens": 42929,
        "completion_tokens": 737,
        "cost": 0.139842
      }
    }
  ],
  "leads": [
    {
      "headline": "Potential command injection vulnerability in make-mail.sh",
      "analysis": "The make-mail.sh script uses user-controlled input from mailq directly in shell commands without proper sanitization. An attacker could potentially inject malicious commands by manipulating mailq output. The script should validate and sanitize any user-controlled data before using it in commands.\n",
      "classification": "slightly promising",
      "cwe": "CWE-78",
      "function_names": [
        "mailq"
      ],
      "filenames": [
        "tools/make-mail.sh"
      ]
    },
    {
      "headline": "Hardcoded credentials in multiple scripts",
      "analysis": "Several scripts contain hardcoded LDAP credentials, including usernames and passwords. This could allow an attacker who gains access to the scripts to directly access the LDAP server. Credentials should be stored securely and retrieved at runtime, not hardcoded in scripts.\n",
      "classification": "very promising",
      "cwe": "CWE-798",
      "function_names": [],
      "filenames": [
        "tools/backup-basedn.sh",
        "tools/handle_vacation.sh",
        "tools/greylist_recipients_whitelists_ldap.pl"
      ]
    },
    {
      "headline": "Potential SQL injection in LDAP queries",
      "analysis": "The phamm-useradd.pl script constructs LDAP queries using unsanitized user input. While LDAP injection is less common than SQL injection, it's still possible an attacker could manipulate the LDAP query by injecting special characters. User input should be properly escaped before being used in LDAP queries.\n",
      "classification": "slightly promising",
      "cwe": "CWE-89",
      "function_names": [
        "get_user_dn2"
      ],
      "filenames": [
        "tools/phamm-useradd.pl"
      ]
    },
    {
      "headline": "Insecure temporary file creation",
      "analysis": "The handle_vacation.sh script uses the tempfile command to create temporary files without specifying a secure directory or permissions. This could potentially allow an attacker to predict the filename and access sensitive data. Temporary files should be created securely with unpredictable names in a protected directory.\n",
      "classification": "slightly promising",
      "cwe": "CWE-377",
      "function_names": [],
      "filenames": [
        "tools/handle_vacation.sh"
      ]
    },
    {
      "headline": "Use of weak cryptographic algorithms",
      "analysis": "The phamm-useradd.pl script uses the Crypt::SmbHash module which likely implements outdated hashing algorithms like LM or NTLM. These are considered cryptographically weak. Modern, secure hashing algorithms should be used instead for password storage.\n",
      "classification": "slightly promising",
      "cwe": "CWE-327",
      "function_names": [
        "ntlmgen"
      ],
      "filenames": [
        "tools/phamm-useradd.pl"
      ]
    }
  ],
  "scores": [
    {
      "stats": {
        "fn": 1,
        "tp": 0,
        "fp": 1
      },
      "mapping": {},
      "vuln_dates": {
        "CVE-2018-20806": "2019-03-17T23:32:51"
      },
      "scoring_model": "claude-3-5-sonnet-20240620",
      "type": "llm",
      "instruction_template_hash": "245ace12b6361954d0a2"
    }
  ],
  "instruction_template_hash": "10c0163db4740318a544",
  "version": "0.1.0"
}
