{
  "commit": "153efaaf47601b8372cc10852d881273d40eca1c",
  "repo_url": "https://github.com/validformbuilder/validformbuilder",
  "model": "claude-3-haiku-20240307",
  "chunk_hashes": [
    "50d300c7515a22154f9f"
  ],
  "responses": [
    {
      "content": "Here is the YAML output with the identified security vulnerabilities in the codebase:\n\n```yaml\nleads:\n  - headline: Improper Neutralization of Special Elements in Output Used by a Downstream Component ('Injection')\n    analysis: |\n      The codebase contains several instances of improper neutralization of user input, which can lead to injection vulnerabilities. Specifically, the `ValidForm.prototype.showAlerts()` function concatenates user-supplied error messages directly into the DOM, without properly sanitizing or escaping the input. This can allow an attacker to inject malicious scripts or HTML into the page, leading to cross-site scripting (XSS) vulnerabilities.\n    cwe: CWE-79\n    function_names:\n      - showAlerts\n    filenames:\n      - js/validform.js\n    classification: very promising\n\n  - headline: Improper Neutralization of Argument Delimiters in a Command ('Argument Injection')\n    analysis: |\n      The codebase contains an instance of improper neutralization of user input used in a command, which can lead to argument injection vulnerabilities. Specifically, the `ValidForm.prototype.attachDynamicConditions()` function concatenates user-supplied field names into a condition object, without properly sanitizing or escaping the input. This can allow an attacker to inject malicious arguments into the condition, potentially leading to command injection vulnerabilities.\n    cwe: CWE-88\n    function_names:\n      - attachDynamicConditions\n    filenames:\n      - js/validform.js\n    classification: very promising\n\n  - headline: Improper Neutralization of Input During Web Page Generation ('Cross-site Scripting')\n    analysis: |\n      The codebase contains several instances of improper neutralization of user input used in web page generation, which can lead to cross-site scripting (XSS) vulnerabilities. Specifically, the `ValidForm.prototype.showAlerts()` function concatenates user-supplied error messages directly into the DOM, without properly sanitizing or escaping the input. This can allow an attacker to inject malicious scripts or HTML into the page, leading to XSS vulnerabilities.\n    cwe: CWE-79\n    function_names:\n      - showAlerts\n    filenames:\n      - js/validform.js\n    classification: very promising\n\n  - headline: Improper Neutralization of Input During Dynamic Web Page Generation ('Reflected XSS')\n    analysis: |\n      The codebase contains instances of improper neutralization of user input used in dynamic web page generation, which can lead to reflected cross-site scripting (XSS) vulnerabilities. Specifically, the `ValidForm.prototype.dynamicDuplication()` function updates various element IDs and names based on user-supplied field names, without properly sanitizing or escaping the input. This can allow an attacker to inject malicious scripts or HTML into the page, leading to reflected XSS vulnerabilities.\n    cwe: CWE-79\n    function_names:\n      - dynamicDuplication\n    filenames:\n      - js/validform.js\n    classification: very promising\n\n  - headline: Improper Restriction of XML External Entity Reference ('XXE')\n    analysis: |\n      The codebase does not appear to contain any functionality related to parsing XML or processing external entities. Therefore, there is no apparent vulnerability to XML external entity (XXE) attacks.\n    cwe: CWE-611\n    function_names: []\n    filenames: []\n    classification: not promising\n\n  - headline: Improper Sanitization of Special Elements used in an Expression Language Statement ('Expression Language Injection')\n    analysis: |\n      The codebase does not appear to contain any functionality related to processing expression language statements. Therefore, there is no apparent vulnerability to expression language injection attacks.\n    cwe: CWE-917\n    function_names: []\n    filenames: []\n    classification: not promising\n\n  - headline: Improper Neutralization of Special Elements used in an SQL Command ('SQL Injection')\n    analysis: |\n      The codebase does not appear to contain any functionality related to constructing or executing SQL queries. Therefore, there is no apparent vulnerability to SQL injection attacks.\n    cwe: CWE-89\n    function_names: []\n    filenames: []\n    classification: not promising\n\n  - headline: Improper Neutralization of Argument Delimiters in a Command ('OS Command Injection')\n    analysis: |\n      The codebase does not appear to contain any functionality related to executing OS commands or passing user input to such commands. Therefore, there is no apparent vulnerability to OS command injection attacks.\n    cwe: CWE-78\n    function_names: []\n    filenames: []\n    classification: not promising\n```",
      "date": "2024-06-13T17:27:12.094399",
      "usage": {
        "prompt_tokens": 28378,
        "completion_tokens": 1106,
        "cost": 0.008477
      }
    }
  ],
  "leads": [
    {
      "headline": "Improper Neutralization of Special Elements in Output Used by a Downstream Component ('Injection')",
      "analysis": "The codebase contains several instances of improper neutralization of user input, which can lead to injection vulnerabilities. Specifically, the ValidForm.prototype.showAlerts() function concatenates user-supplied error messages directly into the DOM, without properly sanitizing or escaping the input. This can allow an attacker to inject malicious scripts or HTML into the page, leading to cross-site scripting (XSS) vulnerabilities.\n",
      "classification": "very promising",
      "cwe": "CWE-79",
      "function_names": [
        "showAlerts"
      ],
      "filenames": [
        "js/validform.js"
      ]
    },
    {
      "headline": "Improper Neutralization of Argument Delimiters in a Command ('Argument Injection')",
      "analysis": "The codebase contains an instance of improper neutralization of user input used in a command, which can lead to argument injection vulnerabilities. Specifically, the ValidForm.prototype.attachDynamicConditions() function concatenates user-supplied field names into a condition object, without properly sanitizing or escaping the input. This can allow an attacker to inject malicious arguments into the condition, potentially leading to command injection vulnerabilities.\n",
      "classification": "very promising",
      "cwe": "CWE-88",
      "function_names": [
        "attachDynamicConditions"
      ],
      "filenames": [
        "js/validform.js"
      ]
    },
    {
      "headline": "Improper Neutralization of Input During Web Page Generation ('Cross-site Scripting')",
      "analysis": "The codebase contains several instances of improper neutralization of user input used in web page generation, which can lead to cross-site scripting (XSS) vulnerabilities. Specifically, the ValidForm.prototype.showAlerts() function concatenates user-supplied error messages directly into the DOM, without properly sanitizing or escaping the input. This can allow an attacker to inject malicious scripts or HTML into the page, leading to XSS vulnerabilities.\n",
      "classification": "very promising",
      "cwe": "CWE-79",
      "function_names": [
        "showAlerts"
      ],
      "filenames": [
        "js/validform.js"
      ]
    },
    {
      "headline": "Improper Neutralization of Input During Dynamic Web Page Generation ('Reflected XSS')",
      "analysis": "The codebase contains instances of improper neutralization of user input used in dynamic web page generation, which can lead to reflected cross-site scripting (XSS) vulnerabilities. Specifically, the ValidForm.prototype.dynamicDuplication() function updates various element IDs and names based on user-supplied field names, without properly sanitizing or escaping the input. This can allow an attacker to inject malicious scripts or HTML into the page, leading to reflected XSS vulnerabilities.\n",
      "classification": "very promising",
      "cwe": "CWE-79",
      "function_names": [
        "dynamicDuplication"
      ],
      "filenames": [
        "js/validform.js"
      ]
    },
    {
      "headline": "Improper Restriction of XML External Entity Reference ('XXE')",
      "analysis": "The codebase does not appear to contain any functionality related to parsing XML or processing external entities. Therefore, there is no apparent vulnerability to XML external entity (XXE) attacks.\n",
      "classification": "not promising",
      "cwe": "CWE-611",
      "function_names": [],
      "filenames": []
    },
    {
      "headline": "Improper Sanitization of Special Elements used in an Expression Language Statement ('Expression Language Injection')",
      "analysis": "The codebase does not appear to contain any functionality related to processing expression language statements. Therefore, there is no apparent vulnerability to expression language injection attacks.\n",
      "classification": "not promising",
      "cwe": "CWE-917",
      "function_names": [],
      "filenames": []
    },
    {
      "headline": "Improper Neutralization of Special Elements used in an SQL Command ('SQL Injection')",
      "analysis": "The codebase does not appear to contain any functionality related to constructing or executing SQL queries. Therefore, there is no apparent vulnerability to SQL injection attacks.\n",
      "classification": "not promising",
      "cwe": "CWE-89",
      "function_names": [],
      "filenames": []
    },
    {
      "headline": "Improper Neutralization of Argument Delimiters in a Command ('OS Command Injection')",
      "analysis": "The codebase does not appear to contain any functionality related to executing OS commands or passing user input to such commands. Therefore, there is no apparent vulnerability to OS command injection attacks.\n",
      "classification": "not promising",
      "cwe": "CWE-78",
      "function_names": [],
      "filenames": []
    }
  ],
  "scores": [
    {
      "stats": {
        "fn": 1,
        "tp": 0,
        "fp": 4
      },
      "mapping": {},
      "vuln_dates": {
        "CVE-2018-1000059": "2018-02-09T23:29:02"
      },
      "scoring_model": "claude-3-opus-20240229",
      "type": "llm",
      "instruction_template_hash": "245ace12b6361954d0a2"
    }
  ],
  "instruction_template_hash": "10c0163db4740318a544",
  "version": "0.1.0"
}
