{
  "commit": "31412f8402beec26edfca4c530a44aa09b385666",
  "repo_url": "https://github.com/dom96/jester",
  "model": "claude-3-haiku-20240307",
  "chunk_hashes": [
    "cacb07f836d9fb72286c"
  ],
  "responses": [
    {
      "content": "```yaml\nleads:\n  - headline: Improper Validation of Specified Quantity in Input (CWE-1284)\n    analysis: |\n      The code in the `todo.markdown` file contains a TODO item that suggests checking file permissions for static files. This indicates a potential vulnerability related to improper validation of the specified quantity in the input, which could lead to unauthorized access to files or directories.\n    cwe: CWE-1284\n    function_names: []\n    filenames:\n      - todo.markdown\n    classification: slightly promising\n\n  - headline: Improper Neutralization of Special Elements used in an OS Command ('OS Command Injection') (CWE-78)\n    analysis: |\n      The code in the `todo.markdown` file contains a TODO item that suggests implementing the ability to trigger another route. This could potentially lead to OS command injection vulnerability if the implementation is not done securely.\n    cwe: CWE-78\n    function_names: []\n    filenames:\n      - todo.markdown\n    classification: slightly promising\n\n  - headline: Improper Initialization (CWE-665)\n    analysis: |\n      The code in the `todo.markdown` file contains a TODO item that suggests checking file permissions for static files. This could indicate a potential issue with improper initialization of resources, such as not properly setting file permissions or ownership.\n    cwe: CWE-665\n    function_names: []\n    filenames:\n      - todo.markdown\n    classification: slightly promising\n\n  - headline: Uncontrolled Resource Consumption (CWE-400)\n    analysis: |\n      The code in the `todo.markdown` file contains a TODO item that suggests implementing better and more adjustable logging. This could indicate a potential issue with uncontrolled resource consumption, such as not properly limiting the amount of log data or the rate at which it is generated.\n    cwe: CWE-400\n    function_names: []\n    filenames:\n      - todo.markdown\n    classification: slightly promising\n\n  - headline: Improper Neutralization of Input During Web Page Generation ('Cross-site Scripting') (CWE-79)\n    analysis: |\n      The code in the `readme.markdown` file suggests using the `htmlgen` module, which could potentially lead to cross-site scripting (XSS) vulnerabilities if the input is not properly sanitized before being included in the generated HTML.\n    cwe: CWE-79\n    function_names:\n      - generateHTMLPage\n    filenames:\n      - readme.markdown\n    classification: slightly promising\n\n  - headline: Improper Handling of Exceptional Conditions (CWE-755)\n    analysis: |\n      The code in the `todo.markdown` file contains a TODO item that suggests implementing better error handling and response handling, such as the ability to override default 404/503 messages. This could indicate a potential issue with improper handling of exceptional conditions.\n    cwe: CWE-755\n    function_names: []\n    filenames:\n      - todo.markdown\n    classification: slightly promising\n\n  - headline: Improper Neutralization of Formula Elements in a CSV File (CWE-1236)\n    analysis: |\n      The code in the `todo.markdown` file contains a TODO item that suggests implementing the ability to handle PUT/PATCH/DELETE/OPTIONS HTTP methods. If these methods are not properly implemented or validated, they could potentially lead to formula injection vulnerabilities in CSV files.\n    cwe: CWE-1236\n    function_names: []\n    filenames:\n      - todo.markdown\n    classification: slightly promising\n\n  - headline: Improper Neutralization of Argument Delimiters in a Command ('Argument Injection') (CWE-88)\n    analysis: |\n      The code in the `todo.markdown` file contains a TODO item that suggests implementing the ability to trigger another route. If this functionality is not properly implemented or validated, it could potentially lead to argument injection vulnerabilities.\n    cwe: CWE-88\n    function_names: []\n    filenames:\n      - todo.markdown\n    classification: slightly promising\n\n  - headline: Improper Neutralization of Special Elements used in an Expression Language Statement ('Expression Language Injection') (CWE-917)\n    analysis: |\n      The code in the `readme.markdown` file suggests using the `htmlgen` module, which could potentially lead to expression language injection vulnerabilities if the input is not properly sanitized before being included in the generated HTML.\n    cwe: CWE-917\n    function_names:\n      - generateHTMLPage\n    filenames:\n      - readme.markdown\n    classification: slightly promising\n\n  - headline: Improper Neutralization of Special Elements used in an SQL Command ('SQL Injection') (CWE-89)\n    analysis: |\n      The code in the `todo.markdown` file contains a TODO item that suggests implementing the ability to handle PUT/PATCH/DELETE/OPTIONS HTTP methods. If these methods are not properly implemented or validated, they could potentially lead to SQL injection vulnerabilities.\n    cwe: CWE-89\n    function_names: []\n    filenames:\n      - todo.markdown\n    classification: slightly promising\n\n  - headline: Improper Neutralization of Special Elements used in a Command ('Command Injection') (CWE-77)\n    analysis: |\n      The code in the `todo.markdown` file contains a TODO item that suggests implementing the ability to trigger another route. If this functionality is not properly implemented or validated, it could potentially lead to command injection vulnerabilities.\n    cwe: CWE-77\n    function_names: []\n    filenames:\n      - todo.markdown\n    classification: slightly promising\n\n  - headline: Improper Neutralization of Input During Web Page Generation ('Cross-site Scripting') (CWE-79)\n    analysis: |\n      The code in the `readme.markdown` file suggests using the `htmlgen` module, which could potentially lead to cross-site scripting (XSS) vulnerabilities if the input is not properly sanitized before being included in the generated HTML.\n    cwe: CWE-79\n    function_names:\n      - generateHTMLPage\n    filenames:\n      - readme.markdown\n    classification: slightly promising\n\n  - headline: Improper Neutralization of Special Elements used in an Expression Language Statement ('Expression Language Injection') (CWE-917)\n    analysis: |\n      The code in the `readme.markdown` file suggests using the `htmlgen` module, which could potentially lead to expression language injection vulnerabilities if the input is not properly sanitized before being included in the generated HTML.\n    cwe: CWE-917\n    function_names:\n      - generateHTMLPage\n    filenames:\n      - readme.markdown\n    classification: slightly promising\n\n  - headline: Improper Neutralization of Special Elements used in an OS Command ('OS Command Injection') (CWE-78)\n    analysis: |\n      The code in the `todo.markdown` file contains a TODO item that suggests implementing the ability to trigger another route. If this functionality is not properly implemented or validated, it could potentially lead to OS command injection vulnerabilities.\n    cwe: CWE-78\n    function_names: []\n    filenames:\n      - todo.markdown\n    classification: slightly promising\n\n  - headline: Improper Neutralization of Special Elements used in an Expression Language Statement ('Expression Language Injection') (CWE-917)\n    analysis: |\n      The code in the `readme.markdown` file suggests using the `htmlgen` module, which could potentially lead to expression language injection vulnerabilities if the input is not properly sanitized before being included in the generated HTML.\n    cwe: CWE-917\n    function_names:\n      - generateHTMLPage\n    filenames:\n      - readme.markdown\n    classification: slightly promising\n\n  - headline: Improper Neutralization of Special Elements used in an SQL Command ('SQL Injection') (CWE-89)\n    analysis: |\n      The code in the `todo.markdown` file contains a TODO item that suggests implementing the ability to handle PUT/PATCH/DELETE/OPTIONS HTTP methods. If these methods are not properly implemented or validated, they could potentially lead to SQL injection vulnerabilities.\n    cwe: CWE-89\n    function_names: []\n    filenames:\n      - todo.markdown\n    classification: slightly promising\n\n  - headline: Improper Neutralization of Special Elements used in a Command ('Command Injection') (CWE-77)\n    analysis: |\n      The code in the `todo.markdown` file contains a TODO item that suggests implementing the ability to trigger another route. If this functionality is not properly implemented or validated, it could potentially lead to command injection vulnerabilities.\n    cwe: CWE-77\n    function_names: []\n    filenames:\n      - todo.markdown\n    classification: slightly promising\n\n  - headline: Improper Neutralization of Input During Web Page Generation ('Cross-site Scripting') (CWE-79)\n    analysis: |\n      The code in the `readme.markdown` file suggests using the `htmlgen` module, which could potentially lead to cross-site scripting (XSS) vulnerabilities if the input is not properly sanitized before being included in the generated HTML.\n    cwe: CWE-79\n    function_names:\n      - generateHTMLPage\n    filenames:\n      - readme.markdown\n    classification: slightly promising\n\n  - headline: Improper Neutralization of Formula Elements in a CSV File (CWE-1236)\n    analysis: |\n      The code in the `todo.markdown` file contains a TODO item that suggests implementing the ability to handle PUT/PATCH/DELETE/OPTIONS HTTP methods. If these methods are not properly implemented or validated, they could potentially lead to formula injection vulnerabilities in CSV files.\n    cwe: CWE-1236\n    function_names: []\n    filenames:\n      - todo.markdown\n    classification: slightly promising\n\n```",
      "date": "2024-06-09T11:32:57.971780",
      "usage": {
        "prompt_tokens": 5157,
        "completion_tokens": 2310,
        "cost": 0.00417675
      }
    }
  ],
  "leads": [
    {
      "headline": "Improper Validation of Specified Quantity in Input (CWE-1284)",
      "analysis": "The code in the todo.markdown file contains a TODO item that suggests checking file permissions for static files. This indicates a potential vulnerability related to improper validation of the specified quantity in the input, which could lead to unauthorized access to files or directories.\n",
      "classification": "slightly promising",
      "cwe": "CWE-1284",
      "function_names": [],
      "filenames": [
        "todo.markdown"
      ]
    },
    {
      "headline": "Improper Neutralization of Special Elements used in an OS Command ('OS Command Injection') (CWE-78)",
      "analysis": "The code in the todo.markdown file contains a TODO item that suggests implementing the ability to trigger another route. This could potentially lead to OS command injection vulnerability if the implementation is not done securely.\n",
      "classification": "slightly promising",
      "cwe": "CWE-78",
      "function_names": [],
      "filenames": [
        "todo.markdown"
      ]
    },
    {
      "headline": "Improper Initialization (CWE-665)",
      "analysis": "The code in the todo.markdown file contains a TODO item that suggests checking file permissions for static files. This could indicate a potential issue with improper initialization of resources, such as not properly setting file permissions or ownership.\n",
      "classification": "slightly promising",
      "cwe": "CWE-665",
      "function_names": [],
      "filenames": [
        "todo.markdown"
      ]
    },
    {
      "headline": "Uncontrolled Resource Consumption (CWE-400)",
      "analysis": "The code in the todo.markdown file contains a TODO item that suggests implementing better and more adjustable logging. This could indicate a potential issue with uncontrolled resource consumption, such as not properly limiting the amount of log data or the rate at which it is generated.\n",
      "classification": "slightly promising",
      "cwe": "CWE-400",
      "function_names": [],
      "filenames": [
        "todo.markdown"
      ]
    },
    {
      "headline": "Improper Neutralization of Input During Web Page Generation ('Cross-site Scripting') (CWE-79)",
      "analysis": "The code in the readme.markdown file suggests using the htmlgen module, which could potentially lead to cross-site scripting (XSS) vulnerabilities if the input is not properly sanitized before being included in the generated HTML.\n",
      "classification": "slightly promising",
      "cwe": "CWE-79",
      "function_names": [
        "generateHTMLPage"
      ],
      "filenames": [
        "readme.markdown"
      ]
    },
    {
      "headline": "Improper Handling of Exceptional Conditions (CWE-755)",
      "analysis": "The code in the todo.markdown file contains a TODO item that suggests implementing better error handling and response handling, such as the ability to override default 404/503 messages. This could indicate a potential issue with improper handling of exceptional conditions.\n",
      "classification": "slightly promising",
      "cwe": "CWE-755",
      "function_names": [],
      "filenames": [
        "todo.markdown"
      ]
    },
    {
      "headline": "Improper Neutralization of Formula Elements in a CSV File (CWE-1236)",
      "analysis": "The code in the todo.markdown file contains a TODO item that suggests implementing the ability to handle PUT/PATCH/DELETE/OPTIONS HTTP methods. If these methods are not properly implemented or validated, they could potentially lead to formula injection vulnerabilities in CSV files.\n",
      "classification": "slightly promising",
      "cwe": "CWE-1236",
      "function_names": [],
      "filenames": [
        "todo.markdown"
      ]
    },
    {
      "headline": "Improper Neutralization of Argument Delimiters in a Command ('Argument Injection') (CWE-88)",
      "analysis": "The code in the todo.markdown file contains a TODO item that suggests implementing the ability to trigger another route. If this functionality is not properly implemented or validated, it could potentially lead to argument injection vulnerabilities.\n",
      "classification": "slightly promising",
      "cwe": "CWE-88",
      "function_names": [],
      "filenames": [
        "todo.markdown"
      ]
    },
    {
      "headline": "Improper Neutralization of Special Elements used in an Expression Language Statement ('Expression Language Injection') (CWE-917)",
      "analysis": "The code in the readme.markdown file suggests using the htmlgen module, which could potentially lead to expression language injection vulnerabilities if the input is not properly sanitized before being included in the generated HTML.\n",
      "classification": "slightly promising",
      "cwe": "CWE-917",
      "function_names": [
        "generateHTMLPage"
      ],
      "filenames": [
        "readme.markdown"
      ]
    },
    {
      "headline": "Improper Neutralization of Special Elements used in an SQL Command ('SQL Injection') (CWE-89)",
      "analysis": "The code in the todo.markdown file contains a TODO item that suggests implementing the ability to handle PUT/PATCH/DELETE/OPTIONS HTTP methods. If these methods are not properly implemented or validated, they could potentially lead to SQL injection vulnerabilities.\n",
      "classification": "slightly promising",
      "cwe": "CWE-89",
      "function_names": [],
      "filenames": [
        "todo.markdown"
      ]
    },
    {
      "headline": "Improper Neutralization of Special Elements used in a Command ('Command Injection') (CWE-77)",
      "analysis": "The code in the todo.markdown file contains a TODO item that suggests implementing the ability to trigger another route. If this functionality is not properly implemented or validated, it could potentially lead to command injection vulnerabilities.\n",
      "classification": "slightly promising",
      "cwe": "CWE-77",
      "function_names": [],
      "filenames": [
        "todo.markdown"
      ]
    },
    {
      "headline": "Improper Neutralization of Input During Web Page Generation ('Cross-site Scripting') (CWE-79)",
      "analysis": "The code in the readme.markdown file suggests using the htmlgen module, which could potentially lead to cross-site scripting (XSS) vulnerabilities if the input is not properly sanitized before being included in the generated HTML.\n",
      "classification": "slightly promising",
      "cwe": "CWE-79",
      "function_names": [
        "generateHTMLPage"
      ],
      "filenames": [
        "readme.markdown"
      ]
    },
    {
      "headline": "Improper Neutralization of Special Elements used in an Expression Language Statement ('Expression Language Injection') (CWE-917)",
      "analysis": "The code in the readme.markdown file suggests using the htmlgen module, which could potentially lead to expression language injection vulnerabilities if the input is not properly sanitized before being included in the generated HTML.\n",
      "classification": "slightly promising",
      "cwe": "CWE-917",
      "function_names": [
        "generateHTMLPage"
      ],
      "filenames": [
        "readme.markdown"
      ]
    },
    {
      "headline": "Improper Neutralization of Special Elements used in an OS Command ('OS Command Injection') (CWE-78)",
      "analysis": "The code in the todo.markdown file contains a TODO item that suggests implementing the ability to trigger another route. If this functionality is not properly implemented or validated, it could potentially lead to OS command injection vulnerabilities.\n",
      "classification": "slightly promising",
      "cwe": "CWE-78",
      "function_names": [],
      "filenames": [
        "todo.markdown"
      ]
    },
    {
      "headline": "Improper Neutralization of Special Elements used in an Expression Language Statement ('Expression Language Injection') (CWE-917)",
      "analysis": "The code in the readme.markdown file suggests using the htmlgen module, which could potentially lead to expression language injection vulnerabilities if the input is not properly sanitized before being included in the generated HTML.\n",
      "classification": "slightly promising",
      "cwe": "CWE-917",
      "function_names": [
        "generateHTMLPage"
      ],
      "filenames": [
        "readme.markdown"
      ]
    },
    {
      "headline": "Improper Neutralization of Special Elements used in an SQL Command ('SQL Injection') (CWE-89)",
      "analysis": "The code in the todo.markdown file contains a TODO item that suggests implementing the ability to handle PUT/PATCH/DELETE/OPTIONS HTTP methods. If these methods are not properly implemented or validated, they could potentially lead to SQL injection vulnerabilities.\n",
      "classification": "slightly promising",
      "cwe": "CWE-89",
      "function_names": [],
      "filenames": [
        "todo.markdown"
      ]
    },
    {
      "headline": "Improper Neutralization of Special Elements used in a Command ('Command Injection') (CWE-77)",
      "analysis": "The code in the todo.markdown file contains a TODO item that suggests implementing the ability to trigger another route. If this functionality is not properly implemented or validated, it could potentially lead to command injection vulnerabilities.\n",
      "classification": "slightly promising",
      "cwe": "CWE-77",
      "function_names": [],
      "filenames": [
        "todo.markdown"
      ]
    },
    {
      "headline": "Improper Neutralization of Input During Web Page Generation ('Cross-site Scripting') (CWE-79)",
      "analysis": "The code in the readme.markdown file suggests using the htmlgen module, which could potentially lead to cross-site scripting (XSS) vulnerabilities if the input is not properly sanitized before being included in the generated HTML.\n",
      "classification": "slightly promising",
      "cwe": "CWE-79",
      "function_names": [
        "generateHTMLPage"
      ],
      "filenames": [
        "readme.markdown"
      ]
    },
    {
      "headline": "Improper Neutralization of Formula Elements in a CSV File (CWE-1236)",
      "analysis": "The code in the todo.markdown file contains a TODO item that suggests implementing the ability to handle PUT/PATCH/DELETE/OPTIONS HTTP methods. If these methods are not properly implemented or validated, they could potentially lead to formula injection vulnerabilities in CSV files.\n",
      "classification": "slightly promising",
      "cwe": "CWE-1236",
      "function_names": [],
      "filenames": [
        "todo.markdown"
      ]
    }
  ],
  "scores": [
    {
      "stats": {
        "fn": 2,
        "tp": 0,
        "fp": 0
      },
      "mapping": {},
      "vuln_dates": {
        "CVE-2023-50693": "2024-01-19T20:15:11",
        "CVE-2018-13034": "2018-07-09T18:29:00"
      },
      "scoring_model": "gpt-4o-2024-05-13",
      "type": "llm",
      "instruction_template_hash": "8998f09cf57fca8a6e03"
    }
  ],
  "instruction_template_hash": "10c0163db4740318a544",
  "version": "0.1.0"
}
