{
  "commit": "18f65d0fe9762f6ac2faac3e67459e89b0818ab7",
  "repo_url": "https://github.com/neocotic/convert-svg",
  "model": "claude-3-haiku-20240307",
  "chunk_hashes": [
    "57ff9ce86bbc04b7b13e"
  ],
  "responses": [
    {
      "content": "Here is the YAML output with the identified security vulnerabilities:\n\n```yaml\nleads:\n  - headline: Improper Input Validation\n    analysis: |\n      The codebase does not sufficiently validate user input, which could lead to vulnerabilities such as injection attacks (e.g. command injection, SQL injection, XML injection) or other input-related issues. Specifically, the code does not properly sanitize or validate the SVG input before processing it, which could allow an attacker to inject malicious content that could be executed or cause unintended behavior.\n    cwe: CWE-20\n    function_names: \n      - convert\n      - convertFile\n    filenames:\n      - packages/convert-svg-core/src/Converter.js\n    classification: very promising\n  - headline: Exposure of Sensitive Information\n    analysis: |\n      The codebase may expose sensitive information, such as file paths or URLs, in error messages or log files. This could allow an attacker to gather information about the system and potentially exploit other vulnerabilities. The code should be reviewed to ensure that sensitive information is properly sanitized or removed before being displayed or logged.\n    cwe: CWE-200\n    function_names:\n      - error\n      - output\n    filenames:\n      - packages/convert-svg-core/src/CLI.js\n    classification: slightly promising\n  - headline: Improper Privilege Management\n    analysis: |\n      The codebase does not properly manage privileges, which could allow an attacker to gain unauthorized access or perform actions that they should not be able to. The code should be reviewed to ensure that permissions and access controls are properly implemented and enforced.\n    cwe: CWE-269\n    function_names:\n      - convertFile\n    filenames:\n      - packages/convert-svg-core/src/Converter.js\n    classification: slightly promising\n  - headline: Insufficient Randomness\n    analysis: |\n      The codebase may not be using a sufficiently random source of entropy for security-critical operations, such as the generation of temporary files. This could make the system more vulnerable to attacks such as directory traversal or path manipulation. The code should be reviewed to ensure that a strong source of randomness is used for any security-critical operations.\n    cwe: CWE-330\n    function_names:\n      - getTempFile\n    filenames:\n      - packages/convert-svg-core/src/Converter.js\n    classification: slightly promising\n  - headline: Improper Resource Shutdown or Release\n    analysis: |\n      The codebase may not properly release or shut down resources, such as the headless Chromium instance or temporary files, which could lead to resource exhaustion or other issues. The code should be reviewed to ensure that all resources are properly cleaned up, even in error conditions or when the Converter is destroyed.\n    cwe: CWE-404\n    function_names:\n      - destroy\n    filenames:\n      - packages/convert-svg-core/src/Converter.js\n    classification: slightly promising\n  - headline: Incorrect Type Conversion or Cast\n    analysis: |\n      The codebase may not properly handle type conversions or casts, which could lead to unexpected behavior or security vulnerabilities. For example, the code should ensure that all numeric values are properly validated and converted to the expected data types before being used.\n    cwe: CWE-704\n    function_names:\n      - parseAPIOptions\n    filenames:\n      - packages/convert-svg-core/src/Converter.js\n    classification: slightly promising\n  - headline: Improper Limitation of a Pathname to a Restricted Directory\n    analysis: |\n      The codebase may not properly restrict file paths to a specific directory, which could allow an attacker to access files outside of the intended directory. This could be a vulnerability if the code is processing user-provided file paths or URLs.\n    cwe: CWE-22\n    function_names:\n      - parseAPIOptions\n    filenames:\n      - packages/convert-svg-core/src/Converter.js\n    classification: slightly promising\n  - headline: Improper Check for Unusual or Exceptional Conditions\n    analysis: |\n      The codebase may not properly handle or check for unusual or exceptional conditions, which could lead to unexpected behavior or security vulnerabilities. For example, the code should ensure that it properly handles errors or exceptions that may occur during the conversion process.\n    cwe: CWE-754\n    function_names:\n      - convert\n      - convertFile\n    filenames:\n      - packages/convert-svg-core/src/Converter.js\n      - packages/convert-svg-core/src/API.js\n    classification: slightly promising\n```\n\nThe identified security vulnerabilities in the codebase include:\n\n1. **Improper Input Validation (CWE-20)**: The codebase does not sufficiently validate user input, which could lead to vulnerabilities such as injection attacks.\n2. **Exposure of Sensitive Information (CWE-200)**: The codebase may expose sensitive information, such as file paths or URLs, in error messages or log files.\n3. **Improper Privilege Management (CWE-269)**: The codebase does not properly manage privileges, which could allow an attacker to gain unauthorized access or perform actions that they should not be able to.\n4. **Insufficient Randomness (CWE-330)**: The codebase may not be using a sufficiently random source of entropy for security-critical operations, such as the generation of temporary files.\n5. **Improper Resource Shutdown or Release (CWE-404)**: The codebase may not properly release or shut down resources, such as the headless Chromium instance or temporary files.\n6. **Incorrect Type Conversion or Cast (CWE-704)**: The codebase may not properly handle type conversions or casts, which could lead to unexpected behavior or security vulnerabilities.\n7. **Improper Limitation of a Pathname to a Restricted Directory (CWE-22)**: The codebase may not properly restrict file paths to a specific directory, which could allow an attacker to access files outside of the intended directory.\n8. **Improper Check for Unusual or Exceptional Conditions (CWE-754)**: The codebase may not properly handle or check for unusual or exceptional conditions, which could lead to unexpected behavior or security vulnerabilities.",
      "date": "2024-06-13T10:24:18.979982",
      "usage": {
        "prompt_tokens": 28273,
        "completion_tokens": 1474,
        "cost": 0.00891075
      }
    }
  ],
  "leads": [
    {
      "headline": "Improper Input Validation",
      "analysis": "The codebase does not sufficiently validate user input, which could lead to vulnerabilities such as injection attacks (e.g. command injection, SQL injection, XML injection) or other input-related issues. Specifically, the code does not properly sanitize or validate the SVG input before processing it, which could allow an attacker to inject malicious content that could be executed or cause unintended behavior.\n",
      "classification": "very promising",
      "cwe": "CWE-20",
      "function_names": [
        "convert",
        "convertFile"
      ],
      "filenames": [
        "packages/convert-svg-core/src/Converter.js"
      ]
    },
    {
      "headline": "Exposure of Sensitive Information",
      "analysis": "The codebase may expose sensitive information, such as file paths or URLs, in error messages or log files. This could allow an attacker to gather information about the system and potentially exploit other vulnerabilities. The code should be reviewed to ensure that sensitive information is properly sanitized or removed before being displayed or logged.\n",
      "classification": "slightly promising",
      "cwe": "CWE-200",
      "function_names": [
        "error",
        "output"
      ],
      "filenames": [
        "packages/convert-svg-core/src/CLI.js"
      ]
    },
    {
      "headline": "Improper Privilege Management",
      "analysis": "The codebase does not properly manage privileges, which could allow an attacker to gain unauthorized access or perform actions that they should not be able to. The code should be reviewed to ensure that permissions and access controls are properly implemented and enforced.\n",
      "classification": "slightly promising",
      "cwe": "CWE-269",
      "function_names": [
        "convertFile"
      ],
      "filenames": [
        "packages/convert-svg-core/src/Converter.js"
      ]
    },
    {
      "headline": "Insufficient Randomness",
      "analysis": "The codebase may not be using a sufficiently random source of entropy for security-critical operations, such as the generation of temporary files. This could make the system more vulnerable to attacks such as directory traversal or path manipulation. The code should be reviewed to ensure that a strong source of randomness is used for any security-critical operations.\n",
      "classification": "slightly promising",
      "cwe": "CWE-330",
      "function_names": [
        "getTempFile"
      ],
      "filenames": [
        "packages/convert-svg-core/src/Converter.js"
      ]
    },
    {
      "headline": "Improper Resource Shutdown or Release",
      "analysis": "The codebase may not properly release or shut down resources, such as the headless Chromium instance or temporary files, which could lead to resource exhaustion or other issues. The code should be reviewed to ensure that all resources are properly cleaned up, even in error conditions or when the Converter is destroyed.\n",
      "classification": "slightly promising",
      "cwe": "CWE-404",
      "function_names": [
        "destroy"
      ],
      "filenames": [
        "packages/convert-svg-core/src/Converter.js"
      ]
    },
    {
      "headline": "Incorrect Type Conversion or Cast",
      "analysis": "The codebase may not properly handle type conversions or casts, which could lead to unexpected behavior or security vulnerabilities. For example, the code should ensure that all numeric values are properly validated and converted to the expected data types before being used.\n",
      "classification": "slightly promising",
      "cwe": "CWE-704",
      "function_names": [
        "parseAPIOptions"
      ],
      "filenames": [
        "packages/convert-svg-core/src/Converter.js"
      ]
    },
    {
      "headline": "Improper Limitation of a Pathname to a Restricted Directory",
      "analysis": "The codebase may not properly restrict file paths to a specific directory, which could allow an attacker to access files outside of the intended directory. This could be a vulnerability if the code is processing user-provided file paths or URLs.\n",
      "classification": "slightly promising",
      "cwe": "CWE-22",
      "function_names": [
        "parseAPIOptions"
      ],
      "filenames": [
        "packages/convert-svg-core/src/Converter.js"
      ]
    },
    {
      "headline": "Improper Check for Unusual or Exceptional Conditions",
      "analysis": "The codebase may not properly handle or check for unusual or exceptional conditions, which could lead to unexpected behavior or security vulnerabilities. For example, the code should ensure that it properly handles errors or exceptions that may occur during the conversion process.\n",
      "classification": "slightly promising",
      "cwe": "CWE-754",
      "function_names": [
        "convert",
        "convertFile"
      ],
      "filenames": [
        "packages/convert-svg-core/src/Converter.js",
        "packages/convert-svg-core/src/API.js"
      ]
    }
  ],
  "scores": [
    {
      "stats": {
        "fn": 3,
        "tp": 0,
        "fp": 1
      },
      "mapping": {},
      "vuln_dates": {
        "CVE-2022-25759": "2022-07-22T20:15:09",
        "CVE-2022-24278": "2022-06-10T20:15:07",
        "CVE-2022-24429": "2022-06-10T20:15:08"
      },
      "scoring_model": "claude-3-opus-20240229",
      "type": "llm",
      "instruction_template_hash": "245ace12b6361954d0a2"
    },
    {
      "stats": {
        "fn": 2,
        "tp": 1,
        "fp": 0
      },
      "mapping": {
        "0": "CVE-2022-25759"
      },
      "vuln_dates": {
        "CVE-2022-25759": "2022-07-22T20:15:09",
        "CVE-2022-24278": "2022-06-10T20:15:07",
        "CVE-2022-24429": "2022-06-10T20:15:08"
      },
      "scoring_model": "claude-3-5-sonnet-20240620",
      "type": "llm",
      "instruction_template_hash": "245ace12b6361954d0a2"
    }
  ],
  "instruction_template_hash": "10c0163db4740318a544",
  "version": "0.1.0"
}
