{
  "commit": "48063aeb0dd2065a8af7c976d6650d49980949a4",
  "repo_url": "https://github.com/snowflakedb/snowflake-hive-metastore-connector",
  "model": "gpt-4o-2024-05-13",
  "chunk_hashes": [
    "cf53e68c6375f8df4e66"
  ],
  "responses": [
    {
      "content": "```yaml\nleads:\n  - headline: \"Environment Variable Injection in deploy.sh\"\n    analysis: |\n      The script `deploy.sh` directly uses environment variables without validation or sanitization. This allows potential attackers to inject malicious values. For instance, the variables `SONATYPE_USER`, `SONATYPE_PWD`, `GPG_KEY_ID`, and `GPG_KEY_PASSPHRASE` are used directly, which could lead to arbitrary code execution or bypass security mechanisms if compromised.\n    cwe: CWE-78\n    function_names: []\n    filenames:\n      - deploy.sh\n    classification: very promising\n  \n  - headline: \"Hard-coded Credentials in TestUtil.java\"\n    analysis: |\n      In `TestUtil.java`, AWS access keys are hard-coded in the code, specifically for mocking HMSHandler and configurations. Hard-coded keys (`accessKeyId` and `awsSecretKey`) exposed in the code can be extracted and used by attackers to access AWS services, making this a significant risk.\n    cwe: CWE-798\n    function_names:\n      - initializeMockHMSHandler\n    filenames:\n      - src/test/java/TestUtil.java\n    classification: very promising\n  \n  - headline: \"Sensitive Information in Logs in DropTableTest.java\"\n    analysis: |\n      The code in `DropTableTest.java` directly utilizes potentially sensitive information such as database names and table names without masking them. This could result in exposure of these details in logs, which could be exploited if logs are accessed by unauthorized users.\n    cwe: CWE-532\n    function_names:\n      - basicDropTableGenerateCommandTest\n    filenames:\n      - src/test/java/DropTableTest.java\n    classification: slightly promising\n\n  - headline: \"Missing Input Validation in AddPartition.java\"\n    analysis: |\n      In the `AddPartition` class, there's improper validation of partition details. The functions don't validate the partition keys or values adequately before processing, which can lead to injection attacks or data corruption.\n    cwe: CWE-20\n    function_names:\n      - generatePartitionDetails\n    filenames:\n      - src/main/java/net/snowflake/hivemetastoreconnector/commands/AddPartition.java\n    classification: slightly promising\n  \n  - headline: \"Unsafe Use of Apache Hive Configuration in CreateExternalTable.java\"\n    analysis: |\n      The method `generateLocationWithCommand` in `CreateExternalTable.java` constructs locations and commands using the Hive configuration directly. If the configuration contains untrusted values, this could lead to path traversal attacks or command injections.\n    cwe: CWE-74\n    function_names:\n      - generateLocationWithCommand\n    filenames:\n      - src/main/java/net/snowflake/hivemetastoreconnector/commands/CreateExternalTable.java\n    classification: very promising\n\n  - headline: \"SQL Injection in SnowflakeClient.java\"\n    analysis: |\n      In `SnowflakeClient`, SQL queries are constructed using string concatenation with unsanitized input. This can lead to SQL Injection vulnerabilities, allowing attackers to execute arbitrary SQL commands.\n    cwe: CWE-89\n    function_names:\n      - executeStatements\n    filenames:\n      - src/main/java/net/snowflake/hivemetastoreconnector/core/SnowflakeClient.java\n    classification: very promising\n  \n  - headline: \"Lack of Encryption for Sensitive Data in SnowflakeConf.java\"\n    analysis: |\n      The `SnowflakeConf` class stores sensitive data such as usernames, passwords, and private keys in plaintext. Lack of encryption mechanisms for these sensitive properties can expose them to attackers if the configuration file is accessed.\n    cwe: CWE-311\n    function_names: []\n    filenames:\n      - src/main/java/net/snowflake/hivemetastoreconnector/SnowflakeConf.java\n    classification: slightly promising\n  \n  - headline: \"Improper Authentication Handling in Scheduler.java\"\n    analysis: |\n      The `Scheduler` class does not implement proper synchronization mechanisms when accessing shared resources, which could lead to race conditions. This might allow attackers to manipulate the state or behavior of scheduled actions.\n    cwe: CWE-362\n    function_names:\n      - enqueueMessage\n      - doWork\n    filenames:\n      - src/main/java/net/snowflake/hivemetastoreconnector/core/Scheduler.java\n    classification: slightly promising\n```",
      "date": "2024-06-09T14:51:05.771147",
      "usage": {
        "prompt_tokens": 53707,
        "completion_tokens": 884,
        "cost": 0.281795
      }
    }
  ],
  "leads": [
    {
      "headline": "Environment Variable Injection in deploy.sh",
      "analysis": "The script deploy.sh directly uses environment variables without validation or sanitization. This allows potential attackers to inject malicious values. For instance, the variables SONATYPE_USER, SONATYPE_PWD, GPG_KEY_ID, and GPG_KEY_PASSPHRASE are used directly, which could lead to arbitrary code execution or bypass security mechanisms if compromised.\n",
      "classification": "very promising",
      "cwe": "CWE-78",
      "function_names": [],
      "filenames": [
        "deploy.sh"
      ]
    },
    {
      "headline": "Hard-coded Credentials in TestUtil.java",
      "analysis": "In TestUtil.java, AWS access keys are hard-coded in the code, specifically for mocking HMSHandler and configurations. Hard-coded keys (accessKeyId and awsSecretKey) exposed in the code can be extracted and used by attackers to access AWS services, making this a significant risk.\n",
      "classification": "very promising",
      "cwe": "CWE-798",
      "function_names": [
        "initializeMockHMSHandler"
      ],
      "filenames": [
        "src/test/java/TestUtil.java"
      ]
    },
    {
      "headline": "Sensitive Information in Logs in DropTableTest.java",
      "analysis": "The code in DropTableTest.java directly utilizes potentially sensitive information such as database names and table names without masking them. This could result in exposure of these details in logs, which could be exploited if logs are accessed by unauthorized users.\n",
      "classification": "slightly promising",
      "cwe": "CWE-532",
      "function_names": [
        "basicDropTableGenerateCommandTest"
      ],
      "filenames": [
        "src/test/java/DropTableTest.java"
      ]
    },
    {
      "headline": "Missing Input Validation in AddPartition.java",
      "analysis": "In the AddPartition class, there's improper validation of partition details. The functions don't validate the partition keys or values adequately before processing, which can lead to injection attacks or data corruption.\n",
      "classification": "slightly promising",
      "cwe": "CWE-20",
      "function_names": [
        "generatePartitionDetails"
      ],
      "filenames": [
        "src/main/java/net/snowflake/hivemetastoreconnector/commands/AddPartition.java"
      ]
    },
    {
      "headline": "Unsafe Use of Apache Hive Configuration in CreateExternalTable.java",
      "analysis": "The method generateLocationWithCommand in CreateExternalTable.java constructs locations and commands using the Hive configuration directly. If the configuration contains untrusted values, this could lead to path traversal attacks or command injections.\n",
      "classification": "very promising",
      "cwe": "CWE-74",
      "function_names": [
        "generateLocationWithCommand"
      ],
      "filenames": [
        "src/main/java/net/snowflake/hivemetastoreconnector/commands/CreateExternalTable.java"
      ]
    },
    {
      "headline": "SQL Injection in SnowflakeClient.java",
      "analysis": "In SnowflakeClient, SQL queries are constructed using string concatenation with unsanitized input. This can lead to SQL Injection vulnerabilities, allowing attackers to execute arbitrary SQL commands.\n",
      "classification": "very promising",
      "cwe": "CWE-89",
      "function_names": [
        "executeStatements"
      ],
      "filenames": [
        "src/main/java/net/snowflake/hivemetastoreconnector/core/SnowflakeClient.java"
      ]
    },
    {
      "headline": "Lack of Encryption for Sensitive Data in SnowflakeConf.java",
      "analysis": "The SnowflakeConf class stores sensitive data such as usernames, passwords, and private keys in plaintext. Lack of encryption mechanisms for these sensitive properties can expose them to attackers if the configuration file is accessed.\n",
      "classification": "slightly promising",
      "cwe": "CWE-311",
      "function_names": [],
      "filenames": [
        "src/main/java/net/snowflake/hivemetastoreconnector/SnowflakeConf.java"
      ]
    },
    {
      "headline": "Improper Authentication Handling in Scheduler.java",
      "analysis": "The Scheduler class does not implement proper synchronization mechanisms when accessing shared resources, which could lead to race conditions. This might allow attackers to manipulate the state or behavior of scheduled actions.\n",
      "classification": "slightly promising",
      "cwe": "CWE-362",
      "function_names": [
        "enqueueMessage",
        "doWork"
      ],
      "filenames": [
        "src/main/java/net/snowflake/hivemetastoreconnector/core/Scheduler.java"
      ]
    }
  ],
  "scores": [
    {
      "stats": {
        "fn": 1,
        "tp": 0,
        "fp": 4
      },
      "mapping": {},
      "vuln_dates": {
        "CVE-2024-28851": "2024-03-15T19:15:07"
      },
      "scoring_model": "gpt-4o-2024-05-13",
      "type": "llm",
      "instruction_template_hash": "8998f09cf57fca8a6e03"
    },
    {
      "stats": {
        "fn": 1,
        "tp": 0,
        "fp": 4
      },
      "mapping": {},
      "vuln_dates": {
        "CVE-2024-28851": "2024-03-15T19:15:07"
      },
      "scoring_model": "claude-3-opus-20240229",
      "type": "llm",
      "instruction_template_hash": "245ace12b6361954d0a2"
    }
  ],
  "instruction_template_hash": "10c0163db4740318a544",
  "version": "0.1.0"
}
