{
  "commit": "021d4453e2b5f175069e81988ebaa116ab5ed7ba",
  "repo_url": "https://github.com/abhilash1985/predictapp",
  "model": "claude-3-haiku-20240307",
  "chunk_hashes": [
    "377a91a16b313cd485cd"
  ],
  "responses": [
    {
      "content": "```yaml\nleads:\n  - headline: Improper Neutralization of Special Elements used in an OS Command ('OS Command Injection')\n    analysis: |\n      The codebase does not appear to contain any instances of OS command injection vulnerabilities. The code appears to be primarily focused on front-end functionality and does not contain any server-side code that executes external commands.\n    cwe: CWE-78\n    function_names: []\n    filenames: []\n    classification: not promising\n\n  - headline: Improper Neutralization of Special Elements used in an SQL Command ('SQL Injection')\n    analysis: |\n      The codebase does not appear to contain any instances of SQL injection vulnerabilities. The code appears to be primarily focused on front-end functionality and does not contain any server-side code that interacts with a database.\n    cwe: CWE-89\n    function_names: []\n    filenames: []\n    classification: not promising\n\n  - headline: Improper Neutralization of Input During Web Page Generation ('Cross-site Scripting')\n    analysis: |\n      The codebase does not appear to contain any instances of cross-site scripting (XSS) vulnerabilities. The code appears to be primarily focused on front-end functionality and does not contain any server-side code that renders user-supplied input.\n    cwe: CWE-79\n    function_names: []\n    filenames: []\n    classification: not promising\n\n  - headline: Improper Encoding or Escaping of Output\n    analysis: |\n      While the codebase does not appear to contain any obvious instances of output encoding vulnerabilities, it's worth reviewing the code that generates or displays any user-supplied data to ensure proper output encoding is in place. This can be a common issue in web applications.\n    cwe: CWE-116\n    function_names:\n      - application.js\n    filenames:\n      - app/assets/javascripts/application.js\n    classification: slightly promising\n\n  - headline: Improper Restriction of Excessive Authentication Attempts\n    analysis: |\n      The codebase does not appear to contain any functionality related to authentication. Without any such functionality, there is no risk of excessive authentication attempts vulnerabilities.\n    cwe: CWE-307\n    function_names: []\n    filenames: []\n    classification: not promising\n\n  - headline: Uncontrolled Resource Consumption\n    analysis: |\n      The codebase does not appear to contain any server-side functionality that could lead to resource exhaustion vulnerabilities. The code seems focused on front-end functionality and does not make any intensive resource requests.\n    cwe: CWE-400\n    function_names: []\n    filenames: []\n    classification: not promising\n\n  - headline: Improper Synchronization\n    analysis: |\n      The codebase does not appear to contain any complex concurrency-related functionality that could lead to synchronization issues. The code seems focused on front-end functionality and does not involve any shared resources.\n    cwe: CWE-662\n    function_names: []\n    filenames: []\n    classification: not promising\n\n  - headline: Incorrect Calculation\n    analysis: |\n      The codebase does not appear to contain any complex mathematical calculations or operations that could lead to numerical issues such as integer overflow or division by zero. The code seems focused on front-end functionality and does not involve any critical calculations.\n    cwe: CWE-682\n    function_names: []\n    filenames: []\n    classification: not promising\n\n  - headline: Improper Control of Dynamically-Managed Code Resources\n    analysis: |\n      The codebase does not appear to contain any functionality related to dynamic code execution or manipulation. The code seems focused on front-end functionality and does not involve any dynamic code resources.\n    cwe: CWE-913\n    function_names: []\n    filenames: []\n    classification: not promising\n```",
      "date": "2024-06-12T14:38:02.583163",
      "usage": {
        "prompt_tokens": 18709,
        "completion_tokens": 902,
        "cost": 0.00580475
      }
    }
  ],
  "leads": [
    {
      "headline": "Improper Neutralization of Special Elements used in an OS Command ('OS Command Injection')",
      "analysis": "The codebase does not appear to contain any instances of OS command injection vulnerabilities. The code appears to be primarily focused on front-end functionality and does not contain any server-side code that executes external commands.\n",
      "classification": "not promising",
      "cwe": "CWE-78",
      "function_names": [],
      "filenames": []
    },
    {
      "headline": "Improper Neutralization of Special Elements used in an SQL Command ('SQL Injection')",
      "analysis": "The codebase does not appear to contain any instances of SQL injection vulnerabilities. The code appears to be primarily focused on front-end functionality and does not contain any server-side code that interacts with a database.\n",
      "classification": "not promising",
      "cwe": "CWE-89",
      "function_names": [],
      "filenames": []
    },
    {
      "headline": "Improper Neutralization of Input During Web Page Generation ('Cross-site Scripting')",
      "analysis": "The codebase does not appear to contain any instances of cross-site scripting (XSS) vulnerabilities. The code appears to be primarily focused on front-end functionality and does not contain any server-side code that renders user-supplied input.\n",
      "classification": "not promising",
      "cwe": "CWE-79",
      "function_names": [],
      "filenames": []
    },
    {
      "headline": "Improper Encoding or Escaping of Output",
      "analysis": "While the codebase does not appear to contain any obvious instances of output encoding vulnerabilities, it's worth reviewing the code that generates or displays any user-supplied data to ensure proper output encoding is in place. This can be a common issue in web applications.\n",
      "classification": "slightly promising",
      "cwe": "CWE-116",
      "function_names": [
        "application.js"
      ],
      "filenames": [
        "app/assets/javascripts/application.js"
      ]
    },
    {
      "headline": "Improper Restriction of Excessive Authentication Attempts",
      "analysis": "The codebase does not appear to contain any functionality related to authentication. Without any such functionality, there is no risk of excessive authentication attempts vulnerabilities.\n",
      "classification": "not promising",
      "cwe": "CWE-307",
      "function_names": [],
      "filenames": []
    },
    {
      "headline": "Uncontrolled Resource Consumption",
      "analysis": "The codebase does not appear to contain any server-side functionality that could lead to resource exhaustion vulnerabilities. The code seems focused on front-end functionality and does not make any intensive resource requests.\n",
      "classification": "not promising",
      "cwe": "CWE-400",
      "function_names": [],
      "filenames": []
    },
    {
      "headline": "Improper Synchronization",
      "analysis": "The codebase does not appear to contain any complex concurrency-related functionality that could lead to synchronization issues. The code seems focused on front-end functionality and does not involve any shared resources.\n",
      "classification": "not promising",
      "cwe": "CWE-662",
      "function_names": [],
      "filenames": []
    },
    {
      "headline": "Incorrect Calculation",
      "analysis": "The codebase does not appear to contain any complex mathematical calculations or operations that could lead to numerical issues such as integer overflow or division by zero. The code seems focused on front-end functionality and does not involve any critical calculations.\n",
      "classification": "not promising",
      "cwe": "CWE-682",
      "function_names": [],
      "filenames": []
    },
    {
      "headline": "Improper Control of Dynamically-Managed Code Resources",
      "analysis": "The codebase does not appear to contain any functionality related to dynamic code execution or manipulation. The code seems focused on front-end functionality and does not involve any dynamic code resources.\n",
      "classification": "not promising",
      "cwe": "CWE-913",
      "function_names": [],
      "filenames": []
    }
  ],
  "scores": [
    {
      "stats": {
        "fn": 1,
        "tp": 0,
        "fp": 0
      },
      "mapping": {},
      "vuln_dates": {
        "CVE-2022-4890": "2023-01-16T13:15:10"
      },
      "scoring_model": "claude-3-opus-20240229",
      "type": "llm",
      "instruction_template_hash": "245ace12b6361954d0a2"
    }
  ],
  "instruction_template_hash": "10c0163db4740318a544",
  "version": "0.1.0"
}
