{
  "commit": "0a833ea632922dfd4f54c54985460903903f1c37",
  "repo_url": "https://github.com/jenkinsci/testlink-plugin",
  "model": "claude-3-opus-20240229",
  "chunk_hashes": [
    "f0501d105e2d27d1f174"
  ],
  "responses": [
    {
      "content": "Here are the security vulnerabilities I identified in the provided codebase:\n\n```yaml\nleads:\n  - headline: Unsafe deserialization in JUnitSuiteNameResultSeeker\n    analysis: |\n      The addAliases method in the TestLinkBuilderDescriptor class registers several classes for deserialization with the XStream library. Deserializing untrusted user input can lead to remote code execution.\n    cwe: CWE-502\n    function_names:\n      - TestLinkBuilderDescriptor.addAliases\n    filenames: \n      - src/main/java/hudson/plugins/testlink/TestLinkBuilderDescriptor.java\n    classification: very promising\n\n  - headline: Unchecked file path usage in various classes\n    analysis: | \n      Several classes like JUnitMethodNameResultSeeker use the includePattern field provided by users to find test result files. If this path is not validated, it could allow reading arbitrary files on the Jenkins master. For example, passing something like /etc/passwd as the includePattern.\n    cwe: CWE-22\n    function_names:\n      - JUnitMethodNameResultSeeker.seek\n      - AbstractTestNGResultSeeker.scan\n    filenames:\n      - src/main/java/hudson/plugins/testlink/result/JUnitMethodNameResultSeeker.java  \n      - src/main/java/hudson/plugins/testlink/result/AbstractTestNGResultSeeker.java\n    classification: very promising\n\n  - headline: Improper authorization in various classes\n    analysis: |\n      Many of the \"Seeker\" classes invoke build.getWorkspace().act() to perform file operations on the Jenkins agent workspace. However, they do not perform any authorization checks to ensure the user triggering the build has permissions to access those files.\n    cwe: CWE-862\n    function_names:\n      - JUnitMethodNameResultSeeker.seek\n      - TestNGMethodNameResultSeeker.seek\n    filenames:\n      - src/main/java/hudson/plugins/testlink/result/JUnitMethodNameResultSeeker.java\n      - src/main/java/hudson/plugins/testlink/result/TestNGMethodNameResultSeeker.java  \n    classification: very promising\n\n  - headline: Potential XSS via build name \n    analysis: |\n      The build name is included in some HTML fragments without escaping. If an attacker can control the build name, they may be able to inject scripts. However, build names are usually restricted.\n    cwe: CWE-79\n    function_names:\n      - TestLinkHelper.createReportSummary  \n    filenames:\n      - src/main/java/hudson/plugins/testlink/util/TestLinkHelper.java\n    classification: slightly promising\n\n  - headline: CSRF via URLs exposed by actions\n    analysis: |  \n      The TestLinkProjectAction and TestLinkBuildAction expose some URLs that do not have CSRF protection. Attackers may be able to make unauthorized changes by tricking users into clicking malicious links.\n    cwe: CWE-352\n    function_names:\n      - TestLinkProjectAction.doIndex\n      - TestLinkProjectAction.doGraph\n    filenames:  \n      - src/main/java/hudson/plugins/testlink/TestLinkProjectAction.java\n    classification: slightly promising\n```\n\nIn summary, the most serious issues are unsafe deserialization which can enable remote code execution, and unchecked file paths which may allow reading sensitive files. There are also some authorization and XSS risks to investigate further. I recommend focusing on fixing the deserialization and file path vulnerabilities first.",
      "date": "2024-06-12T19:27:06.446502",
      "usage": {
        "prompt_tokens": 114544,
        "completion_tokens": 865,
        "cost": 1.783035
      }
    }
  ],
  "leads": [
    {
      "headline": "Unsafe deserialization in JUnitSuiteNameResultSeeker",
      "analysis": "The addAliases method in the TestLinkBuilderDescriptor class registers several classes for deserialization with the XStream library. Deserializing untrusted user input can lead to remote code execution.\n",
      "classification": "very promising",
      "cwe": "CWE-502",
      "function_names": [
        "TestLinkBuilderDescriptor.addAliases"
      ],
      "filenames": [
        "src/main/java/hudson/plugins/testlink/TestLinkBuilderDescriptor.java"
      ]
    },
    {
      "headline": "Unchecked file path usage in various classes",
      "analysis": "Several classes like JUnitMethodNameResultSeeker use the includePattern field provided by users to find test result files. If this path is not validated, it could allow reading arbitrary files on the Jenkins master. For example, passing something like /etc/passwd as the includePattern.\n",
      "classification": "very promising",
      "cwe": "CWE-22",
      "function_names": [
        "JUnitMethodNameResultSeeker.seek",
        "AbstractTestNGResultSeeker.scan"
      ],
      "filenames": [
        "src/main/java/hudson/plugins/testlink/result/JUnitMethodNameResultSeeker.java",
        "src/main/java/hudson/plugins/testlink/result/AbstractTestNGResultSeeker.java"
      ]
    },
    {
      "headline": "Improper authorization in various classes",
      "analysis": "Many of the \"Seeker\" classes invoke build.getWorkspace().act() to perform file operations on the Jenkins agent workspace. However, they do not perform any authorization checks to ensure the user triggering the build has permissions to access those files.\n",
      "classification": "very promising",
      "cwe": "CWE-862",
      "function_names": [
        "JUnitMethodNameResultSeeker.seek",
        "TestNGMethodNameResultSeeker.seek"
      ],
      "filenames": [
        "src/main/java/hudson/plugins/testlink/result/JUnitMethodNameResultSeeker.java",
        "src/main/java/hudson/plugins/testlink/result/TestNGMethodNameResultSeeker.java"
      ]
    },
    {
      "headline": "Potential XSS via build name",
      "analysis": "The build name is included in some HTML fragments without escaping. If an attacker can control the build name, they may be able to inject scripts. However, build names are usually restricted.\n",
      "classification": "slightly promising",
      "cwe": "CWE-79",
      "function_names": [
        "TestLinkHelper.createReportSummary"
      ],
      "filenames": [
        "src/main/java/hudson/plugins/testlink/util/TestLinkHelper.java"
      ]
    },
    {
      "headline": "CSRF via URLs exposed by actions",
      "analysis": "The TestLinkProjectAction and TestLinkBuildAction expose some URLs that do not have CSRF protection. Attackers may be able to make unauthorized changes by tricking users into clicking malicious links.\n",
      "classification": "slightly promising",
      "cwe": "CWE-352",
      "function_names": [
        "TestLinkProjectAction.doIndex",
        "TestLinkProjectAction.doGraph"
      ],
      "filenames": [
        "src/main/java/hudson/plugins/testlink/TestLinkProjectAction.java"
      ]
    }
  ],
  "scores": [
    {
      "stats": {
        "fn": 2,
        "tp": 0,
        "fp": 3
      },
      "mapping": {},
      "vuln_dates": {
        "CVE-2019-10378": "2019-08-07T15:15:13",
        "CVE-2018-1000113": "2018-03-13T13:29:00"
      },
      "scoring_model": "claude-3-opus-20240229",
      "type": "llm",
      "instruction_template_hash": "245ace12b6361954d0a2"
    }
  ],
  "instruction_template_hash": "10c0163db4740318a544",
  "version": "0.1.0"
}
