{
  "commit": "2f98656940ee16d8a083128fdd3e5274086905e5",
  "repo_url": "https://github.com/jenkinsci/websphere-deployer-plugin",
  "model": "claude-3-haiku-20240307",
  "chunk_hashes": [
    "01428c9cca38e8c643e7"
  ],
  "responses": [
    {
      "content": "Here is the YAML output equivalent to the type LeadList, based on the provided Pydantic definitions:\n\n```yaml\nleads:\n  - headline: Improper Neutralization of Input During Web Page Generation ('Cross-site Scripting')\n    analysis: |\n      The code does not properly sanitize user-provided input before using it in dynamically generated web pages. This can allow an attacker to inject malicious scripts into the web application, which would be executed in the context of the victim's browser session. The vulnerability exists in multiple places where user input is used, such as in the deployment artifacts, virtual host, and context path configuration.\n    cwe: CWE-79\n    function_names:\n      - createArtifact\n      - getContext\n      - getVirtualHost\n    filenames:\n      - src/main/java/org/jenkinsci/plugins/websphere/services/deployment/Artifact.java\n      - src/main/java/org/jenkinsci/plugins/websphere_deployer/WebSphereDeployerPlugin.java\n    classification: very promising\n  - headline: Improper Input Validation\n    analysis: |\n      The code does not properly validate user-provided input, such as the IP address, port, and other configuration settings. This can lead to a variety of issues, including command injection, path traversal, and other vulnerabilities. The lack of input validation is present throughout the codebase, including in the connection handling and deployment logic.\n    cwe: CWE-20\n    function_names:\n      - connect\n      - gatherArtifactPaths\n      - createArtifact\n    filenames:\n      - src/main/java/org/jenkinsci/plugins/websphere/services/deployment/AbstractDeploymentService.java\n      - src/main/java/org/jenkinsci/plugins/websphere_deployer/WebSphereDeployerPlugin.java\n      - src/main/java/org/jenkinsci/plugins/websphere_deployer/LibertyDeployerPlugin.java\n    classification: very promising\n  - headline: Improper Neutralization of Argument Delimiters in a Command ('Argument Injection')\n    analysis: |\n      The code does not properly sanitize user-provided input before using it in system commands or arguments. This can allow an attacker to inject malicious arguments, leading to command injection vulnerabilities. The issue is present in the deployment and connection handling logic, where user-controlled values are used in system calls without proper validation.\n    cwe: CWE-88\n    function_names:\n      - connect\n      - deployArtifact\n      - uninstallArtifact\n    filenames:\n      - src/main/java/org/jenkinsci/plugins/websphere/services/deployment/AbstractDeploymentService.java\n      - src/main/java/org/jenkinsci/plugins/websphere_deployer/WebSphereDeployerPlugin.java\n      - src/main/java/org/jenkinsci/plugins/websphere_deployer/LibertyDeployerPlugin.java\n    classification: very promising\n  - headline: Improper Neutralization of Special Elements used in an OS Command ('OS Command Injection')\n    analysis: |\n      The code does not properly sanitize user-provided input before using it in OS commands. This can allow an attacker to inject malicious commands, leading to remote code execution vulnerabilities. The issue is present in the deployment and connection handling logic, where user-controlled values are used in system calls without proper validation.\n    cwe: CWE-78\n    function_names:\n      - connect\n      - deployArtifact\n      - uninstallArtifact\n    filenames:\n      - src/main/java/org/jenkinsci/plugins/websphere/services/deployment/AbstractDeploymentService.java\n      - src/main/java/org/jenkinsci/plugins/websphere_deployer/WebSphereDeployerPlugin.java\n      - src/main/java/org/jenkinsci/plugins/websphere_deployer/LibertyDeployerPlugin.java\n    classification: very promising\n  - headline: Improper Restriction of XML External Entity Reference\n    analysis: |\n      The code does not properly validate or restrict the use of XML External Entities (XXE) in the generated application.xml files. This can allow an attacker to read local files, perform SSRF attacks, or execute arbitrary code on the server. The issue is present in the `getApplicationXML` method, where a static XML template is used without properly sanitizing user-provided input.\n    cwe: CWE-611\n    function_names:\n      - getApplicationXML\n    filenames:\n      - src/main/java/org/jenkinsci/plugins/websphere/services/deployment/WebSphereDeploymentService.java\n    classification: very promising\n  - headline: Improper Privilege Management\n    analysis: |\n      The code does not properly manage privileges and access controls. For example, the `WebSphereSecurity` class allows users to specify the credentials used to connect to the WebSphere server, including the username, password, and SSL certificate information. This can lead to privilege escalation vulnerabilities if these credentials are not properly secured or validated.\n    cwe: CWE-269\n    function_names:\n      - connect\n      - preInitializeService\n    filenames:\n      - src/main/java/org/jenkinsci/plugins/websphere_deployer/WebSphereSecurity.java\n      - src/main/java/org/jenkinsci/plugins/websphere_deployer/WebSphereDeployerPlugin.java\n    classification: very promising\n  - headline: Incorrect Authorization\n    analysis: |\n      The code does not properly validate the authorization of the user performing the deployment actions. This can lead to unauthorized access and privilege escalation vulnerabilities. The issue is present in the deployment logic, where user-provided credentials are used without proper validation or access controls.\n    cwe: CWE-863\n    function_names:\n      - connect\n      - preInitializeService\n    filenames:\n      - src/main/java/org/jenkinsci/plugins/websphere_deployer/WebSphereSecurity.java\n      - src/main/java/org/jenkinsci/plugins/websphere_deployer/WebSphereDeployerPlugin.java\n    classification: very promising\n  - headline: Improper Removal of Sensitive Information Before Storage or Transfer\n    analysis: |\n      The code does not properly remove sensitive information, such as passwords and SSL certificate details, before storing or transferring them. This can lead to information disclosure vulnerabilities, where an attacker can gain access to these sensitive details. The issue is present in the `WebSphereSecurity` class, where the credentials are stored in plaintext or weakly hashed.\n    cwe: CWE-212\n    function_names:\n      - getPassword\n      - getClientKeyPassword\n      - getClientTrustPassword\n    filenames:\n      - src/main/java/org/jenkinsci/plugins/websphere_deployer/WebSphereSecurity.java\n    classification: very promising\n\n```",
      "date": "2024-06-12T19:31:35.341572",
      "usage": {
        "prompt_tokens": 34783,
        "completion_tokens": 1675,
        "cost": 0.0107895
      }
    }
  ],
  "leads": [
    {
      "headline": "Improper Neutralization of Input During Web Page Generation ('Cross-site Scripting')",
      "analysis": "The code does not properly sanitize user-provided input before using it in dynamically generated web pages. This can allow an attacker to inject malicious scripts into the web application, which would be executed in the context of the victim's browser session. The vulnerability exists in multiple places where user input is used, such as in the deployment artifacts, virtual host, and context path configuration.\n",
      "classification": "very promising",
      "cwe": "CWE-79",
      "function_names": [
        "createArtifact",
        "getContext",
        "getVirtualHost"
      ],
      "filenames": [
        "src/main/java/org/jenkinsci/plugins/websphere/services/deployment/Artifact.java",
        "src/main/java/org/jenkinsci/plugins/websphere_deployer/WebSphereDeployerPlugin.java"
      ]
    },
    {
      "headline": "Improper Input Validation",
      "analysis": "The code does not properly validate user-provided input, such as the IP address, port, and other configuration settings. This can lead to a variety of issues, including command injection, path traversal, and other vulnerabilities. The lack of input validation is present throughout the codebase, including in the connection handling and deployment logic.\n",
      "classification": "very promising",
      "cwe": "CWE-20",
      "function_names": [
        "connect",
        "gatherArtifactPaths",
        "createArtifact"
      ],
      "filenames": [
        "src/main/java/org/jenkinsci/plugins/websphere/services/deployment/AbstractDeploymentService.java",
        "src/main/java/org/jenkinsci/plugins/websphere_deployer/WebSphereDeployerPlugin.java",
        "src/main/java/org/jenkinsci/plugins/websphere_deployer/LibertyDeployerPlugin.java"
      ]
    },
    {
      "headline": "Improper Neutralization of Argument Delimiters in a Command ('Argument Injection')",
      "analysis": "The code does not properly sanitize user-provided input before using it in system commands or arguments. This can allow an attacker to inject malicious arguments, leading to command injection vulnerabilities. The issue is present in the deployment and connection handling logic, where user-controlled values are used in system calls without proper validation.\n",
      "classification": "very promising",
      "cwe": "CWE-88",
      "function_names": [
        "connect",
        "deployArtifact",
        "uninstallArtifact"
      ],
      "filenames": [
        "src/main/java/org/jenkinsci/plugins/websphere/services/deployment/AbstractDeploymentService.java",
        "src/main/java/org/jenkinsci/plugins/websphere_deployer/WebSphereDeployerPlugin.java",
        "src/main/java/org/jenkinsci/plugins/websphere_deployer/LibertyDeployerPlugin.java"
      ]
    },
    {
      "headline": "Improper Neutralization of Special Elements used in an OS Command ('OS Command Injection')",
      "analysis": "The code does not properly sanitize user-provided input before using it in OS commands. This can allow an attacker to inject malicious commands, leading to remote code execution vulnerabilities. The issue is present in the deployment and connection handling logic, where user-controlled values are used in system calls without proper validation.\n",
      "classification": "very promising",
      "cwe": "CWE-78",
      "function_names": [
        "connect",
        "deployArtifact",
        "uninstallArtifact"
      ],
      "filenames": [
        "src/main/java/org/jenkinsci/plugins/websphere/services/deployment/AbstractDeploymentService.java",
        "src/main/java/org/jenkinsci/plugins/websphere_deployer/WebSphereDeployerPlugin.java",
        "src/main/java/org/jenkinsci/plugins/websphere_deployer/LibertyDeployerPlugin.java"
      ]
    },
    {
      "headline": "Improper Restriction of XML External Entity Reference",
      "analysis": "The code does not properly validate or restrict the use of XML External Entities (XXE) in the generated application.xml files. This can allow an attacker to read local files, perform SSRF attacks, or execute arbitrary code on the server. The issue is present in the getApplicationXML method, where a static XML template is used without properly sanitizing user-provided input.\n",
      "classification": "very promising",
      "cwe": "CWE-611",
      "function_names": [
        "getApplicationXML"
      ],
      "filenames": [
        "src/main/java/org/jenkinsci/plugins/websphere/services/deployment/WebSphereDeploymentService.java"
      ]
    },
    {
      "headline": "Improper Privilege Management",
      "analysis": "The code does not properly manage privileges and access controls. For example, the WebSphereSecurity class allows users to specify the credentials used to connect to the WebSphere server, including the username, password, and SSL certificate information. This can lead to privilege escalation vulnerabilities if these credentials are not properly secured or validated.\n",
      "classification": "very promising",
      "cwe": "CWE-269",
      "function_names": [
        "connect",
        "preInitializeService"
      ],
      "filenames": [
        "src/main/java/org/jenkinsci/plugins/websphere_deployer/WebSphereSecurity.java",
        "src/main/java/org/jenkinsci/plugins/websphere_deployer/WebSphereDeployerPlugin.java"
      ]
    },
    {
      "headline": "Incorrect Authorization",
      "analysis": "The code does not properly validate the authorization of the user performing the deployment actions. This can lead to unauthorized access and privilege escalation vulnerabilities. The issue is present in the deployment logic, where user-provided credentials are used without proper validation or access controls.\n",
      "classification": "very promising",
      "cwe": "CWE-863",
      "function_names": [
        "connect",
        "preInitializeService"
      ],
      "filenames": [
        "src/main/java/org/jenkinsci/plugins/websphere_deployer/WebSphereSecurity.java",
        "src/main/java/org/jenkinsci/plugins/websphere_deployer/WebSphereDeployerPlugin.java"
      ]
    },
    {
      "headline": "Improper Removal of Sensitive Information Before Storage or Transfer",
      "analysis": "The code does not properly remove sensitive information, such as passwords and SSL certificate details, before storing or transferring them. This can lead to information disclosure vulnerabilities, where an attacker can gain access to these sensitive details. The issue is present in the WebSphereSecurity class, where the credentials are stored in plaintext or weakly hashed.\n",
      "classification": "very promising",
      "cwe": "CWE-212",
      "function_names": [
        "getPassword",
        "getClientKeyPassword",
        "getClientTrustPassword"
      ],
      "filenames": [
        "src/main/java/org/jenkinsci/plugins/websphere_deployer/WebSphereSecurity.java"
      ]
    }
  ],
  "scores": [
    {
      "stats": {
        "fn": 3,
        "tp": 1,
        "fp": 7
      },
      "mapping": {
        "4": "CVE-2020-2108"
      },
      "vuln_dates": {
        "CVE-2020-2108": "2020-01-29T16:15:12",
        "CVE-2019-16560": "2019-12-17T15:15:18",
        "CVE-2019-16561": "2019-12-17T15:15:18",
        "CVE-2019-16559": "2019-12-17T15:15:18"
      },
      "scoring_model": "claude-3-opus-20240229",
      "type": "llm",
      "instruction_template_hash": "245ace12b6361954d0a2"
    },
    {
      "stats": {
        "fn": 2,
        "tp": 2,
        "fp": 6
      },
      "mapping": {
        "4": "CVE-2020-2108",
        "6": "CVE-2019-16559"
      },
      "vuln_dates": {
        "CVE-2020-2108": "2020-01-29T16:15:12",
        "CVE-2019-16560": "2019-12-17T15:15:18",
        "CVE-2019-16561": "2019-12-17T15:15:18",
        "CVE-2019-16559": "2019-12-17T15:15:18"
      },
      "scoring_model": "claude-3-5-sonnet-20240620",
      "type": "llm",
      "instruction_template_hash": "245ace12b6361954d0a2"
    }
  ],
  "instruction_template_hash": "10c0163db4740318a544",
  "version": "0.1.0"
}
