{
  "commit": "39c4a78634966f9fb965ab1060f70eac41c52966",
  "repo_url": "https://github.com/turbowarp/desktop",
  "model": "gpt-4-turbo-2024-04-09",
  "chunk_hashes": [
    "0e73bcbe6a8a8501ff90"
  ],
  "responses": [
    {
      "content": "```yaml\nleads:\n  - headline: \"Insecure Environment Variable Handling\"\n    analysis: |\n      In the 'webpack.main.js' file, the `process.env.TW_ENABLE_UPDATE_CHECKER` environment variable is used indirectly to enable or disable the update checking feature without proper validation or sanitization. This design could be leveraged by attackers to inject unintended values or modify the behavior of the application, potentially leading to a security misconfiguration scenario.\n    cwe: CWE-807\n    function_names:\n      - \"merge_smart\"\n    filenames:\n      - \"/webpack.main.js\"\n    classification: \"very promising\"\n\n  - headline: \"Potential Information Exposure Through Browser Interface\"\n    analysis: |\n      The 'src/renderer/gui/load-initial-project.js' script initiates communication with external services (e.g., Scratch API, external URLs for project data) directly from the client's side. This method of handling external data might expose internal implementation details about the handling of external resources and pose risks of unauthorized access to sensitive project information.\n    cwe: CWE-200\n    function_names:\n      - \"loadInitialProject\"\n    filenames:\n      - \"/src/renderer/gui/load-initial-project.js\"\n    classification: \"slightly promising\"\n\n  - headline: \"Lack of Authentication for Critical Function\"\n    analysis: |\n      The application allows reading files from the system through the 'ipcMain.handle' handlers defined in 'src/main/index.js', which listen for file access events from the renderer process without enforcing any strict authentication or authorization checks. This could allow local users to exploit the functionality to access or manipulate files which they typically should not access.\n    cwe: CWE-284\n    function_names:\n      - \"export-project/start\"\n    filenames:\n      - \"/src/main/index.js\"\n    classification: \"very promising\"\n\n  - headline: \"Command Injection Through External Input\"\n    analysis: |\n      In 'src/main/index.js', there is a function that can receive command line parameters, which are employed to dynamically generate executable actions without adequate input validation. This particular handling could lead to potential command injection if unsanitized external input is passed through the environment variables or direct user input.\n    cwe: CWE-77\n    function_names:\n      - \"parseArgs\"\n    filenames:\n      - \"/src/main/index.js\"\n    classification: \"slightly promising\"\n\n  - headline: \"Path Traversal via Unvalidated Input\"\n    analysis: |\n      The application supports fetching files based on input paths provided via IPC messages without sufficient path validation ('src/main/index.js'). Malicious inputs can be constructed to traverse the file system to unauthorized directories, leading to unauthorized information disclosure or manipulation.\n    cwe: CWE-22\n    function_names:\n      - \"ipcMain.handle\"\n    filenames:\n      - \"/src/main/index.js\"\n    classification: \"very promising\"\n\n  - headline: \"Insecure Permission Assignment for Critical Resource\"\n    analysis: |\n      The 'deb/download-binaries.py' script downloads binary files and saves them without properly setting or verifying the permissions of the downloaded files. This can result in files with overly permissive or incorrect permissions, potentially allowing unauthorized users to modify or execute these files.\n    cwe: CWE-732\n    function_names:\n      - \"download_as\"\n    filenames:\n      - \"/debian/download-binaries.py\"\n    classification: \"slightly promising\"\n```",
      "date": "2024-07-08T09:03:37.319573",
      "usage": {
        "prompt_tokens": 57366,
        "completion_tokens": 686,
        "cost": 0.59424
      }
    }
  ],
  "leads": [
    {
      "headline": "Insecure Environment Variable Handling",
      "analysis": "In the 'webpack.main.js' file, the process.env.TW_ENABLE_UPDATE_CHECKER environment variable is used indirectly to enable or disable the update checking feature without proper validation or sanitization. This design could be leveraged by attackers to inject unintended values or modify the behavior of the application, potentially leading to a security misconfiguration scenario.\n",
      "classification": "very promising",
      "cwe": "CWE-807",
      "function_names": [
        "merge_smart"
      ],
      "filenames": [
        "/webpack.main.js"
      ]
    },
    {
      "headline": "Potential Information Exposure Through Browser Interface",
      "analysis": "The 'src/renderer/gui/load-initial-project.js' script initiates communication with external services (e.g., Scratch API, external URLs for project data) directly from the client's side. This method of handling external data might expose internal implementation details about the handling of external resources and pose risks of unauthorized access to sensitive project information.\n",
      "classification": "slightly promising",
      "cwe": "CWE-200",
      "function_names": [
        "loadInitialProject"
      ],
      "filenames": [
        "/src/renderer/gui/load-initial-project.js"
      ]
    },
    {
      "headline": "Lack of Authentication for Critical Function",
      "analysis": "The application allows reading files from the system through the 'ipcMain.handle' handlers defined in 'src/main/index.js', which listen for file access events from the renderer process without enforcing any strict authentication or authorization checks. This could allow local users to exploit the functionality to access or manipulate files which they typically should not access.\n",
      "classification": "very promising",
      "cwe": "CWE-284",
      "function_names": [
        "export-project/start"
      ],
      "filenames": [
        "/src/main/index.js"
      ]
    },
    {
      "headline": "Command Injection Through External Input",
      "analysis": "In 'src/main/index.js', there is a function that can receive command line parameters, which are employed to dynamically generate executable actions without adequate input validation. This particular handling could lead to potential command injection if unsanitized external input is passed through the environment variables or direct user input.\n",
      "classification": "slightly promising",
      "cwe": "CWE-77",
      "function_names": [
        "parseArgs"
      ],
      "filenames": [
        "/src/main/index.js"
      ]
    },
    {
      "headline": "Path Traversal via Unvalidated Input",
      "analysis": "The application supports fetching files based on input paths provided via IPC messages without sufficient path validation ('src/main/index.js'). Malicious inputs can be constructed to traverse the file system to unauthorized directories, leading to unauthorized information disclosure or manipulation.\n",
      "classification": "very promising",
      "cwe": "CWE-22",
      "function_names": [
        "ipcMain.handle"
      ],
      "filenames": [
        "/src/main/index.js"
      ]
    },
    {
      "headline": "Insecure Permission Assignment for Critical Resource",
      "analysis": "The 'deb/download-binaries.py' script downloads binary files and saves them without properly setting or verifying the permissions of the downloaded files. This can result in files with overly permissive or incorrect permissions, potentially allowing unauthorized users to modify or execute these files.\n",
      "classification": "slightly promising",
      "cwe": "CWE-732",
      "function_names": [
        "download_as"
      ],
      "filenames": [
        "/debian/download-binaries.py"
      ]
    }
  ],
  "scores": [
    {
      "stats": {
        "fn": 0,
        "tp": 1,
        "fp": 2
      },
      "mapping": {
        "2": "CVE-2023-40168"
      },
      "vuln_dates": {
        "CVE-2023-40168": "2023-08-17T20:15:11"
      },
      "scoring_model": "claude-3-5-sonnet-20240620",
      "type": "llm",
      "instruction_template_hash": "245ace12b6361954d0a2"
    }
  ],
  "instruction_template_hash": "10c0163db4740318a544",
  "version": "0.1.0"
}
