{
  "commit": "2b8554bbe810c36ce960d3f4836584bc40b6ba53",
  "repo_url": "https://github.com/silverwind/droppy",
  "model": "gemini/gemini-1.5-pro",
  "chunk_hashes": [
    "e25061a190c92eef714d"
  ],
  "responses": [
    {
      "content": "```yaml\nleads:\n  - headline: Directory Traversal in Archive Download\n    analysis: |\n      The function `streamArchive` in `server/server.js` constructs a zip archive from a directory specified by the client via the URL.\n      The path provided by the client is only sanitized through `utils.isPathSane`, which only rejects paths containing `..` as part of a URL (i.e. `?~~/../`).\n      However, if a client requests the archive through a normal path (i.e `?_//directory`), `utils.isPathSane` is not used,\n      and the application passes the path to `readdirp` unsanitized, allowing an attacker to escape the intended directory and access other files on the server.\n    cwe: CWE-22\n    function_names:\n      - streamArchive\n    filenames:\n      - server/server.js\n    classification: very promising\n  - headline: Path Traversal in handleFileRequest\n    analysis: |\n      The function `handleFileRequest` in `server/server.js` takes a path from the URL and serves a file at that path.\n      The path is only sanitized for certain URL prefixes using `utils.isPathSane`, but not for paths starting with \"?_/\".\n      This allows an attacker to request files outside the intended directory using a URL such as `?_//etc/passwd`,\n      bypassing the intended sanitization and potentially accessing sensitive files on the server.\n    cwe: CWE-22\n    function_names:\n      - handleFileRequest\n    filenames:\n      - server/server.js\n    classification: very promising\n  - headline: Cross-Site Scripting in Share Link Box\n    analysis: |\n      The function `showLink` in `client/client.js` takes a share link hash and constructs a URL from it.\n      This URL is then displayed to the user in the share link box. The share link hash is not sanitized before being inserted into the HTML,\n      which means that if an attacker can control the share link hash, they can inject arbitrary HTML and JavaScript into the page.\n      This could allow them to steal user cookies or perform other malicious actions.\n    cwe: CWE-79\n    function_names:\n      - showLink\n    filenames:\n      - client/client.js\n    classification: slightly promising\n  - headline: Cross-Site Scripting in Audio Bar Title\n    analysis: |\n      The function `onNewAudio` in `client/client.js` takes the filename from the audio player's source URL,\n      decodes it, and sets it as the text of the audio bar's title element. The filename is not sanitized before being inserted into the HTML,\n      which means that if an attacker can control the filename, they can inject arbitrary HTML and JavaScript into the page.\n      This could allow them to steal user cookies or perform other malicious actions.\n    cwe: CWE-79\n    function_names:\n      - onNewAudio\n    filenames:\n      - client/client.js\n    classification: slightly promising\n  - headline: Possible privilege escalation via user creation\n    analysis: |\n      The function handling the '/adduser' endpoint does not seem to have any mechanism for verifying the identity of the user making the request.\n      An attacker could potentially send a crafted request to this endpoint to create a privileged user account without proper authentication,\n      effectively gaining administrative control over the application.\n    cwe: CWE-269\n    function_names:\n      - handlePOST\n    filenames:\n      - server/server.js\n    classification: slightly promising\n  - headline: Sensitive Information Exposure Through Error Messages\n    analysis: |\n      The `log.error` function in `server/log.js` logs detailed error stack traces without any filtering.\n      These stack traces may contain sensitive information like file paths, internal function names, or even snippets of source code.\n      An attacker could potentially trigger an error condition and observe the resulting log output to gain insights into the application's internals.\n    cwe: CWE-209\n    function_names:\n      - error\n    filenames:\n      - server/log.js\n    classification: not promising\n```",
      "date": "2024-06-13T11:44:01.143863",
      "usage": {
        "prompt_tokens": 53567,
        "completion_tokens": 846,
        "cost": 0.035065625
      }
    }
  ],
  "leads": [
    {
      "headline": "Directory Traversal in Archive Download",
      "analysis": "The function streamArchive in server/server.js constructs a zip archive from a directory specified by the client via the URL.\nThe path provided by the client is only sanitized through utils.isPathSane, which only rejects paths containing .. as part of a URL (i.e. ?~~/../).\nHowever, if a client requests the archive through a normal path (i.e ?_//directory), utils.isPathSane is not used,\nand the application passes the path to readdirp unsanitized, allowing an attacker to escape the intended directory and access other files on the server.\n",
      "classification": "very promising",
      "cwe": "CWE-22",
      "function_names": [
        "streamArchive"
      ],
      "filenames": [
        "server/server.js"
      ]
    },
    {
      "headline": "Path Traversal in handleFileRequest",
      "analysis": "The function handleFileRequest in server/server.js takes a path from the URL and serves a file at that path.\nThe path is only sanitized for certain URL prefixes using utils.isPathSane, but not for paths starting with \"?_/\".\nThis allows an attacker to request files outside the intended directory using a URL such as ?_//etc/passwd,\nbypassing the intended sanitization and potentially accessing sensitive files on the server.\n",
      "classification": "very promising",
      "cwe": "CWE-22",
      "function_names": [
        "handleFileRequest"
      ],
      "filenames": [
        "server/server.js"
      ]
    },
    {
      "headline": "Cross-Site Scripting in Share Link Box",
      "analysis": "The function showLink in client/client.js takes a share link hash and constructs a URL from it.\nThis URL is then displayed to the user in the share link box. The share link hash is not sanitized before being inserted into the HTML,\nwhich means that if an attacker can control the share link hash, they can inject arbitrary HTML and JavaScript into the page.\nThis could allow them to steal user cookies or perform other malicious actions.\n",
      "classification": "slightly promising",
      "cwe": "CWE-79",
      "function_names": [
        "showLink"
      ],
      "filenames": [
        "client/client.js"
      ]
    },
    {
      "headline": "Cross-Site Scripting in Audio Bar Title",
      "analysis": "The function onNewAudio in client/client.js takes the filename from the audio player's source URL,\ndecodes it, and sets it as the text of the audio bar's title element. The filename is not sanitized before being inserted into the HTML,\nwhich means that if an attacker can control the filename, they can inject arbitrary HTML and JavaScript into the page.\nThis could allow them to steal user cookies or perform other malicious actions.\n",
      "classification": "slightly promising",
      "cwe": "CWE-79",
      "function_names": [
        "onNewAudio"
      ],
      "filenames": [
        "client/client.js"
      ]
    },
    {
      "headline": "Possible privilege escalation via user creation",
      "analysis": "The function handling the '/adduser' endpoint does not seem to have any mechanism for verifying the identity of the user making the request.\nAn attacker could potentially send a crafted request to this endpoint to create a privileged user account without proper authentication,\neffectively gaining administrative control over the application.\n",
      "classification": "slightly promising",
      "cwe": "CWE-269",
      "function_names": [
        "handlePOST"
      ],
      "filenames": [
        "server/server.js"
      ]
    },
    {
      "headline": "Sensitive Information Exposure Through Error Messages",
      "analysis": "The log.error function in server/log.js logs detailed error stack traces without any filtering.\nThese stack traces may contain sensitive information like file paths, internal function names, or even snippets of source code.\nAn attacker could potentially trigger an error condition and observe the resulting log output to gain insights into the application's internals.\n",
      "classification": "not promising",
      "cwe": "CWE-209",
      "function_names": [
        "error"
      ],
      "filenames": [
        "server/log.js"
      ]
    }
  ],
  "scores": [
    {
      "stats": {
        "fn": 1,
        "tp": 0,
        "fp": 2
      },
      "mapping": {},
      "vuln_dates": {
        "CVE-2016-10529": "2018-05-31T20:29:00"
      },
      "scoring_model": "claude-3-opus-20240229",
      "type": "llm",
      "instruction_template_hash": "245ace12b6361954d0a2"
    }
  ],
  "instruction_template_hash": "10c0163db4740318a544",
  "version": "0.1.0"
}
