{
  "commit": "fb4d24de6bcf1235f0fe876dfa76e43e7eb42fd8",
  "repo_url": "https://github.com/crafatar/crafatar",
  "model": "claude-3-5-sonnet-20240620",
  "chunk_hashes": [
    "619aadb705f27179078c"
  ],
  "responses": [
    {
      "content": "```yaml\nleads:\n  - headline: Insecure handling of user input in avatar requests\n    analysis: |\n      The avatar route handler does not properly sanitize or validate the user-supplied size parameter. It only checks if the size is within a min/max range, but does not verify that it is a valid integer. An attacker could potentially supply a non-integer value or extremely large integer to cause unexpected behavior or resource exhaustion.\n    cwe: CWE-20\n    function_names:\n      - module.exports\n    filenames:\n      - lib/routes/avatars.js\n    classification: slightly promising\n\n  - headline: Potential path traversal vulnerability in asset requests\n    analysis: |\n      The asset_request function constructs a file path using user-supplied input (req.url.path_list) without proper sanitization. This could potentially allow an attacker to access files outside the intended directory via path traversal techniques.\n    cwe: CWE-22 \n    function_names:\n      - asset_request\n    filenames:\n      - lib/server.js\n    classification: slightly promising\n\n  - headline: Improper error handling exposes sensitive information\n    analysis: |\n      When debug mode is enabled, full error stack traces are returned to the client in HTTP responses. This could potentially expose sensitive system information to attackers.\n    cwe: CWE-209\n    function_names:\n      - requestHandler\n    filenames:\n      - lib/server.js\n    classification: slightly promising\n\n  - headline: Unvalidated URL redirect\n    analysis: |\n      The handle_default function in multiple route handlers performs redirects to user-supplied URLs without proper validation. An attacker could potentially exploit this to perform open redirects to malicious sites.\n    cwe: CWE-601\n    function_names:\n      - handle_default\n    filenames:\n      - lib/routes/avatars.js\n      - lib/routes/skins.js\n      - lib/routes/renders.js\n    classification: slightly promising\n\n  - headline: Potential denial of service via unbounded resource consumption\n    analysis: |\n      The server does not implement proper rate limiting or resource constraints on image processing operations. An attacker could potentially overwhelm the server by issuing many simultaneous requests for resource-intensive operations like skin rendering.\n    cwe: CWE-400\n    function_names: []\n    filenames:\n      - lib/server.js\n    classification: slightly promising\n```",
      "date": "2024-07-07T20:52:36.491632",
      "usage": {
        "prompt_tokens": 35373,
        "completion_tokens": 567,
        "cost": 0.114624
      }
    }
  ],
  "leads": [
    {
      "headline": "Insecure handling of user input in avatar requests",
      "analysis": "The avatar route handler does not properly sanitize or validate the user-supplied size parameter. It only checks if the size is within a min/max range, but does not verify that it is a valid integer. An attacker could potentially supply a non-integer value or extremely large integer to cause unexpected behavior or resource exhaustion.\n",
      "classification": "slightly promising",
      "cwe": "CWE-20",
      "function_names": [
        "module.exports"
      ],
      "filenames": [
        "lib/routes/avatars.js"
      ]
    },
    {
      "headline": "Potential path traversal vulnerability in asset requests",
      "analysis": "The asset_request function constructs a file path using user-supplied input (req.url.path_list) without proper sanitization. This could potentially allow an attacker to access files outside the intended directory via path traversal techniques.\n",
      "classification": "slightly promising",
      "cwe": "CWE-22",
      "function_names": [
        "asset_request"
      ],
      "filenames": [
        "lib/server.js"
      ]
    },
    {
      "headline": "Improper error handling exposes sensitive information",
      "analysis": "When debug mode is enabled, full error stack traces are returned to the client in HTTP responses. This could potentially expose sensitive system information to attackers.\n",
      "classification": "slightly promising",
      "cwe": "CWE-209",
      "function_names": [
        "requestHandler"
      ],
      "filenames": [
        "lib/server.js"
      ]
    },
    {
      "headline": "Unvalidated URL redirect",
      "analysis": "The handle_default function in multiple route handlers performs redirects to user-supplied URLs without proper validation. An attacker could potentially exploit this to perform open redirects to malicious sites.\n",
      "classification": "slightly promising",
      "cwe": "CWE-601",
      "function_names": [
        "handle_default"
      ],
      "filenames": [
        "lib/routes/avatars.js",
        "lib/routes/skins.js",
        "lib/routes/renders.js"
      ]
    },
    {
      "headline": "Potential denial of service via unbounded resource consumption",
      "analysis": "The server does not implement proper rate limiting or resource constraints on image processing operations. An attacker could potentially overwhelm the server by issuing many simultaneous requests for resource-intensive operations like skin rendering.\n",
      "classification": "slightly promising",
      "cwe": "CWE-400",
      "function_names": [],
      "filenames": [
        "lib/server.js"
      ]
    }
  ],
  "scores": [
    {
      "stats": {
        "fn": 1,
        "tp": 0,
        "fp": 0
      },
      "mapping": {},
      "vuln_dates": {
        "CVE-2024-24756": "2024-02-01T23:15:11"
      },
      "scoring_model": "claude-3-5-sonnet-20240620",
      "type": "llm",
      "instruction_template_hash": "245ace12b6361954d0a2"
    }
  ],
  "instruction_template_hash": "10c0163db4740318a544",
  "version": "0.1.0"
}
