{
  "commit": "3e1b59c8d95c1be8ad536088a389a3f36dec15a2",
  "repo_url": "https://github.com/aiven-open/journalpump",
  "model": "gemini/gemini-1.5-pro",
  "chunk_hashes": [
    "d4a5785f40ad2352b38c"
  ],
  "responses": [
    {
      "content": "```yaml\nleads:\n  - headline: Potential directory traversal in JournalReader\n    analysis: |\n      The `get_reader` function in `journalpump/journalpump.py` accepts a `path` argument from the configuration.\n      This path is then directly passed to the `PumpReader` constructor. \n      There is no sanitization or validation performed on this path, meaning that a malicious user could potentially supply a path that would allow them to read arbitrary files on the system.\n      However, the `PumpReader` constructor ultimately calls into the `sd-journal` library, which is likely to perform some path validation of its own.\n    cwe: CWE-22\n    function_names:\n      - get_reader\n    filenames:\n      - journalpump/journalpump.py\n    classification: slightly promising\n  - headline: Potential denial of service in StatsClient\n    analysis: |\n      The `_send` function in `journalpump/statsd.py` does not appear to handle the possibility of `socket.sendto` raising an exception.\n      If an exception is raised, the function simply logs the error and continues. \n      A malicious user could potentially exploit this to cause a denial of service by sending a large number of invalid statsd packets, causing the `StatsClient` to repeatedly log errors and potentially consume excessive resources.\n    cwe: CWE-754\n    function_names:\n      - _send\n    filenames:\n      - journalpump/statsd.py\n    classification: not promising\n  - headline: Uncontrolled Recursion in AWS CloudWatch sender retry logic\n    analysis: |\n      The AWS CloudWatch sender in `journalpump/senders/aws_cloudwatch.py` has a retry loop in the `_init_logs` function.\n      This loop retries the initialization of the AWS CloudWatch client if it encounters a `ClientError`.\n      However, this loop does not have any mechanism to prevent uncontrolled recursion if the `ClientError` persists.\n      This could lead to a stack overflow if the error condition continues indefinitely.\n    cwe: CWE-674\n    function_names:\n      - _init_logs\n    filenames:\n      - journalpump/senders/aws_cloudwatch.py\n    classification: not promising\n  - headline: Missing Certificate Validation in LogplexSender\n    analysis: |\n      The `send_messages` function in `journalpump/senders/logplex.py` makes a POST request to the Logplex endpoint using `requests.Session.post`.\n      The `verify` argument to this function is set to `False`. \n      This means that the sender will not verify the SSL certificate of the Logplex endpoint, making it vulnerable to man-in-the-middle attacks.\n    cwe: CWE-295\n    function_names:\n      - send_messages\n    filenames:\n      - journalpump/senders/logplex.py\n    classification: very promising\n  - headline: Excessive Iteration in LogSender\n    analysis: |\n      The `run` function in `journalpump/senders/base.py` contains a loop that calls `get_and_send_messages`.\n      The `get_and_send_messages` function retrieves messages from the buffer and sends them to the destination.\n      However, if an exception occurs during the send process, the loop calls `_backoff` and then continues iterating without checking whether the exception condition has been resolved.\n      This could result in excessive iteration and potentially lead to performance issues if the exception persists. \n    cwe: CWE-834\n    function_names:\n      - run\n      - get_and_send_messages\n    filenames:\n      - journalpump/senders/base.py\n    classification: not promising\n```",
      "date": "2024-06-12T11:37:10.721760",
      "usage": {
        "prompt_tokens": 54889,
        "completion_tokens": 747,
        "cost": 0.199955
      }
    }
  ],
  "leads": [
    {
      "headline": "Potential directory traversal in JournalReader",
      "analysis": "The get_reader function in journalpump/journalpump.py accepts a path argument from the configuration.\nThis path is then directly passed to the PumpReader constructor. \nThere is no sanitization or validation performed on this path, meaning that a malicious user could potentially supply a path that would allow them to read arbitrary files on the system.\nHowever, the PumpReader constructor ultimately calls into the sd-journal library, which is likely to perform some path validation of its own.\n",
      "classification": "slightly promising",
      "cwe": "CWE-22",
      "function_names": [
        "get_reader"
      ],
      "filenames": [
        "journalpump/journalpump.py"
      ]
    },
    {
      "headline": "Potential denial of service in StatsClient",
      "analysis": "The _send function in journalpump/statsd.py does not appear to handle the possibility of socket.sendto raising an exception.\nIf an exception is raised, the function simply logs the error and continues. \nA malicious user could potentially exploit this to cause a denial of service by sending a large number of invalid statsd packets, causing the StatsClient to repeatedly log errors and potentially consume excessive resources.\n",
      "classification": "not promising",
      "cwe": "CWE-754",
      "function_names": [
        "_send"
      ],
      "filenames": [
        "journalpump/statsd.py"
      ]
    },
    {
      "headline": "Uncontrolled Recursion in AWS CloudWatch sender retry logic",
      "analysis": "The AWS CloudWatch sender in journalpump/senders/aws_cloudwatch.py has a retry loop in the _init_logs function.\nThis loop retries the initialization of the AWS CloudWatch client if it encounters a ClientError.\nHowever, this loop does not have any mechanism to prevent uncontrolled recursion if the ClientError persists.\nThis could lead to a stack overflow if the error condition continues indefinitely.\n",
      "classification": "not promising",
      "cwe": "CWE-674",
      "function_names": [
        "_init_logs"
      ],
      "filenames": [
        "journalpump/senders/aws_cloudwatch.py"
      ]
    },
    {
      "headline": "Missing Certificate Validation in LogplexSender",
      "analysis": "The send_messages function in journalpump/senders/logplex.py makes a POST request to the Logplex endpoint using requests.Session.post.\nThe verify argument to this function is set to False. \nThis means that the sender will not verify the SSL certificate of the Logplex endpoint, making it vulnerable to man-in-the-middle attacks.\n",
      "classification": "very promising",
      "cwe": "CWE-295",
      "function_names": [
        "send_messages"
      ],
      "filenames": [
        "journalpump/senders/logplex.py"
      ]
    },
    {
      "headline": "Excessive Iteration in LogSender",
      "analysis": "The run function in journalpump/senders/base.py contains a loop that calls get_and_send_messages.\nThe get_and_send_messages function retrieves messages from the buffer and sends them to the destination.\nHowever, if an exception occurs during the send process, the loop calls _backoff and then continues iterating without checking whether the exception condition has been resolved.\nThis could result in excessive iteration and potentially lead to performance issues if the exception persists. \n",
      "classification": "not promising",
      "cwe": "CWE-834",
      "function_names": [
        "run",
        "get_and_send_messages"
      ],
      "filenames": [
        "journalpump/senders/base.py"
      ]
    }
  ],
  "scores": [
    {
      "stats": {
        "fn": 1,
        "tp": 0,
        "fp": 1
      },
      "mapping": {},
      "vuln_dates": {
        "CVE-2023-51390": "2023-12-21T00:15:26"
      },
      "scoring_model": "claude-3-opus-20240229",
      "type": "llm",
      "instruction_template_hash": "245ace12b6361954d0a2"
    },
    {
      "stats": {
        "fn": 1,
        "tp": 0,
        "fp": 1
      },
      "mapping": {},
      "vuln_dates": {
        "CVE-2023-51390": "2023-12-21T00:15:26"
      },
      "scoring_model": "claude-3-5-sonnet-20240620",
      "type": "llm",
      "instruction_template_hash": "245ace12b6361954d0a2"
    }
  ],
  "instruction_template_hash": "10c0163db4740318a544",
  "version": "0.1.0"
}
