{
  "commit": "76aab0ca2ff0580adf1afa92131c93799f19bbb6",
  "repo_url": "https://github.com/agl/jbig2enc",
  "model": "gpt-4o-2024-05-13",
  "chunk_hashes": [
    "3d8b7427b0062625ef2a"
  ],
  "responses": [
    {
      "content": "```yaml\nleads:\n  - headline: \"Arbitrary File Read in pdf.py\"\n    analysis: |\n      In the `main` function of `pdf.py`, the program uses the `file` function to open a filename without validating the input properly. This allows an attacker to specify arbitrary filenames, potentially leading to arbitrary file reads.\n    cwe: CWE-20\n    function_names:\n      - main\n    filenames:\n      - pdf.py\n    classification: very promising\n  - headline: \"Command Injection in autogen.sh\"\n    analysis: |\n      In the `autogen.sh` script, several system commands (like `aclocal`, `libtoolize`, `automake`, etc.) are run without sanitizing their inputs. If any environment variables or inputs are controlled by an attacker, they could execute arbitrary commands.\n    cwe: CWE-77\n    function_names: []\n    filenames:\n      - autogen.sh\n    classification: very promising\n  - headline: \"Improper Validation of Array Index in jbig2enc.h and jbig2arith.h\"\n    analysis: |\n      The usage of arrays in the header files `jbig2enc.h` and `jbig2arith.h` without proper checks may lead to buffer overflows if indices are not properly validated. This could cause out-of-bounds reads or writes, leading to potential serious vulnerabilities.\n    cwe: CWE-129\n    function_names: []\n    filenames:\n      - src/jbig2enc.h\n      - src/jbig2arith.h\n    classification: slightly promising\n  - headline: \"Heap-based Buffer Overflow in jbig2.cc\"\n    analysis: |\n      In `jbig2.cc`, when handling the context for arithmetic encoding, there's potential for buffer overflow due to improper size checks when handling large data sizes. Specifically, the `context` buffer is susceptible to overflow if not properly managed.\n    cwe: CWE-787\n    function_names:\n      - jbig2enc_init\n    filenames:\n      - src/jbig2.cc\n    classification: very promising\n  - headline: \"Insecure Temporary File Creation in autogen.sh\"\n    analysis: |\n      The shell script `autogen.sh` potentially creates files and directories in insecure manners, leading to race conditions and possible symlink attacks. Proper secure methods for temporary files should be employed.\n    cwe: CWE-362\n    function_names: []\n    filenames:\n      - autogen.sh\n    classification: slightly promising\n  - headline: \"Insufficient Entropy in jbig2comparator.h\"\n    analysis: |\n      The file `jbig2comparator.h` has logic that relies on randomness without sufficient entropy. This could weaken the security of the application. The function `jbig2enc_are_equivalent` does not properly seed the random number generator.\n    cwe: CWE-331\n    function_names:\n      - jbig2enc_are_equivalent\n    filenames:\n      - src/jbig2comparator.h\n    classification: not promising\n  - headline: \"Improper Null Termination in jbig2sym.cc\"\n    analysis: |\n      In `jbig2sym.cc`, some strings are not properly null-terminated, which can lead to buffer over-reads or undefined behavior when handled by string functions.\n    cwe: CWE-170\n    function_names:\n      - jbig2enc_symboltable\n    filenames:\n      - src/jbig2sym.cc\n    classification: slightly promising\n  - headline: \"Race Condition in jbig2enc.cc\"\n    analysis: |\n      In `jbig2enc.cc`, concurrent access to shared resources is not properly synchronized, leading to potential race conditions. This occurs in scenarios where multiple threads or processes might modify shared data without proper locking mechanisms.\n    cwe: CWE-362\n    function_names:\n      - jbig2_add_page\n    filenames:\n      - src/jbig2enc.cc\n    classification: slightly promising\n```\n",
      "date": "2024-06-08T21:59:07.210121",
      "usage": {
        "prompt_tokens": 40212,
        "completion_tokens": 821,
        "cost": 0.213375
      }
    }
  ],
  "leads": [
    {
      "headline": "Arbitrary File Read in pdf.py",
      "analysis": "In the main function of pdf.py, the program uses the file function to open a filename without validating the input properly. This allows an attacker to specify arbitrary filenames, potentially leading to arbitrary file reads.\n",
      "classification": "very promising",
      "cwe": "CWE-20",
      "function_names": [
        "main"
      ],
      "filenames": [
        "pdf.py"
      ]
    },
    {
      "headline": "Command Injection in autogen.sh",
      "analysis": "In the autogen.sh script, several system commands (like aclocal, libtoolize, automake, etc.) are run without sanitizing their inputs. If any environment variables or inputs are controlled by an attacker, they could execute arbitrary commands.\n",
      "classification": "very promising",
      "cwe": "CWE-77",
      "function_names": [],
      "filenames": [
        "autogen.sh"
      ]
    },
    {
      "headline": "Improper Validation of Array Index in jbig2enc.h and jbig2arith.h",
      "analysis": "The usage of arrays in the header files jbig2enc.h and jbig2arith.h without proper checks may lead to buffer overflows if indices are not properly validated. This could cause out-of-bounds reads or writes, leading to potential serious vulnerabilities.\n",
      "classification": "slightly promising",
      "cwe": "CWE-129",
      "function_names": [],
      "filenames": [
        "src/jbig2enc.h",
        "src/jbig2arith.h"
      ]
    },
    {
      "headline": "Heap-based Buffer Overflow in jbig2.cc",
      "analysis": "In jbig2.cc, when handling the context for arithmetic encoding, there's potential for buffer overflow due to improper size checks when handling large data sizes. Specifically, the context buffer is susceptible to overflow if not properly managed.\n",
      "classification": "very promising",
      "cwe": "CWE-787",
      "function_names": [
        "jbig2enc_init"
      ],
      "filenames": [
        "src/jbig2.cc"
      ]
    },
    {
      "headline": "Insecure Temporary File Creation in autogen.sh",
      "analysis": "The shell script autogen.sh potentially creates files and directories in insecure manners, leading to race conditions and possible symlink attacks. Proper secure methods for temporary files should be employed.\n",
      "classification": "slightly promising",
      "cwe": "CWE-362",
      "function_names": [],
      "filenames": [
        "autogen.sh"
      ]
    },
    {
      "headline": "Insufficient Entropy in jbig2comparator.h",
      "analysis": "The file jbig2comparator.h has logic that relies on randomness without sufficient entropy. This could weaken the security of the application. The function jbig2enc_are_equivalent does not properly seed the random number generator.\n",
      "classification": "not promising",
      "cwe": "CWE-331",
      "function_names": [
        "jbig2enc_are_equivalent"
      ],
      "filenames": [
        "src/jbig2comparator.h"
      ]
    },
    {
      "headline": "Improper Null Termination in jbig2sym.cc",
      "analysis": "In jbig2sym.cc, some strings are not properly null-terminated, which can lead to buffer over-reads or undefined behavior when handled by string functions.\n",
      "classification": "slightly promising",
      "cwe": "CWE-170",
      "function_names": [
        "jbig2enc_symboltable"
      ],
      "filenames": [
        "src/jbig2sym.cc"
      ]
    },
    {
      "headline": "Race Condition in jbig2enc.cc",
      "analysis": "In jbig2enc.cc, concurrent access to shared resources is not properly synchronized, leading to potential race conditions. This occurs in scenarios where multiple threads or processes might modify shared data without proper locking mechanisms.\n",
      "classification": "slightly promising",
      "cwe": "CWE-362",
      "function_names": [
        "jbig2_add_page"
      ],
      "filenames": [
        "src/jbig2enc.cc"
      ]
    }
  ],
  "scores": [
    {
      "stats": {
        "fn": 3,
        "tp": 0,
        "fp": 3
      },
      "mapping": {},
      "vuln_dates": {
        "CVE-2023-46362": "2023-11-08T21:15:08",
        "CVE-2023-46363": "2023-11-08T21:15:08",
        "CVE-2018-11230": "2018-05-17T12:29:00"
      },
      "scoring_model": "gpt-4o-2024-05-13",
      "type": "llm",
      "instruction_template_hash": "8998f09cf57fca8a6e03"
    },
    {
      "stats": {
        "fn": 3,
        "tp": 0,
        "fp": 3
      },
      "mapping": {},
      "vuln_dates": {
        "CVE-2023-46362": "2023-11-08T21:15:08",
        "CVE-2023-46363": "2023-11-08T21:15:08",
        "CVE-2018-11230": "2018-05-17T12:29:00"
      },
      "scoring_model": "claude-3-opus-20240229",
      "type": "llm",
      "instruction_template_hash": "245ace12b6361954d0a2"
    },
    {
      "stats": {
        "fn": 3,
        "tp": 0,
        "fp": 3
      },
      "mapping": {},
      "vuln_dates": {
        "CVE-2023-46362": "2023-11-08T21:15:08",
        "CVE-2023-46363": "2023-11-08T21:15:08",
        "CVE-2018-11230": "2018-05-17T12:29:00"
      },
      "scoring_model": "claude-3-5-sonnet-20240620",
      "type": "llm",
      "instruction_template_hash": "245ace12b6361954d0a2"
    }
  ],
  "instruction_template_hash": "10c0163db4740318a544",
  "version": "0.1.0"
}
