{
  "commit": "28cd0593cd01363332fff976a12b984648983929",
  "repo_url": "https://github.com/roehling/postsrsd",
  "model": "claude-3-5-sonnet-20240620",
  "chunk_hashes": [
    "db3cee37e227ddc04af5"
  ],
  "responses": [
    {
      "content": "```yaml\nleads:\n  - headline: Insecure use of random() function for generating addresses\n    analysis: |\n      The generate_random_address() function uses the random() function to generate random addresses for testing. However, random() is not cryptographically secure and can produce predictable output. An attacker could potentially predict the randomly generated addresses, which could lead to vulnerabilities if these addresses are used for anything security-sensitive. A cryptographically secure random number generator like /dev/urandom should be used instead for generating random data for security purposes.\n    cwe: CWE-338\n    function_names:\n      - generate_random_address\n    filenames:\n      - tests.c\n    classification: slightly promising\n\n  - headline: Potential buffer overflow in url_encode function\n    analysis: |\n      The url_encode function in srs2.c does not properly check buffer limits when encoding special characters. If the input contains many characters that need to be percent-encoded, it's possible to write beyond the end of the output buffer. This could lead to a buffer overflow vulnerability. The function should ensure it never writes beyond the specified output buffer length, even in the worst case where every input character needs to be encoded.\n    cwe: CWE-120\n    function_names:\n      - url_encode\n    filenames:\n      - srs2.c\n    classification: very promising\n\n  - headline: Potential buffer overflow in srs_compile_shortcut function\n    analysis: |\n      The srs_compile_shortcut function in srs2.c calculates a required buffer length and compares it to the provided buffer length, but then uses sprintf to write to the buffer without any length limiting. If the calculated length is incorrect, this could lead to a buffer overflow. A length-limiting string function like snprintf should be used instead to ensure the write cannot exceed the buffer size.\n    cwe: CWE-120\n    function_names:\n      - srs_compile_shortcut\n    filenames:\n      - srs2.c\n    classification: very promising\n\n  - headline: Use of deprecated and unsafe strcpy function\n    analysis: |\n      The code uses the strcpy function in multiple places, such as in srs_forward_alloc. strcpy is considered unsafe as it does not perform any bounds checking and can lead to buffer overflows if the destination buffer is not large enough to hold the source string. It should be replaced with safer alternatives like strncpy or strlcpy that limit the number of characters copied.\n    cwe: CWE-120\n    function_names:\n      - srs_forward_alloc\n    filenames:\n      - srs2.c\n    classification: slightly promising\n\n  - headline: Potential integer overflow in srs_forward_alloc\n    analysis: |\n      In the srs_forward_alloc function, the buffer length is calculated by adding several integer values. If these values are large, it could lead to an integer overflow, resulting in a buffer that is too small being allocated. This could then lead to a buffer overflow when writing to the buffer. The code should use safe integer arithmetic to prevent potential overflows.\n    cwe: CWE-190\n    function_names:\n      - srs_forward_alloc\n    filenames:\n      - srs2.c\n    classification: slightly promising\n\n  - headline: Unsafe use of alloca for dynamic memory allocation\n    analysis: |\n      The code uses alloca in several places to allocate memory on the stack. While not inherently unsafe, alloca can lead to stack overflow if used with large or unbounded sizes. It's especially risky in recursive functions. Consider using safer alternatives like malloc for dynamic memory allocation, especially for larger or variable-sized allocations.\n    cwe: CWE-787\n    function_names:\n      - srs_hash_create\n      - srs_forward\n    filenames:\n      - srs2.c\n    classification: slightly promising\n\n  - headline: Potential command injection vulnerability in postsrsd\n    analysis: |\n      The postsrsd.c file appears to handle user input for email addresses and domain names. While there is some input validation and sanitization, it may not be comprehensive. If any of this user-controlled data is used to construct system commands without proper escaping, it could lead to command injection vulnerabilities. A thorough review of how user input is handled and used throughout the application is necessary to ensure all potential injection points are properly secured.\n    cwe: CWE-78\n    function_names: []\n    filenames:\n      - postsrsd.c\n    classification: slightly promising\n```",
      "date": "2024-07-08T08:26:28.126407",
      "usage": {
        "prompt_tokens": 26420,
        "completion_tokens": 1046,
        "cost": 0.09495
      }
    }
  ],
  "leads": [
    {
      "headline": "Insecure use of random() function for generating addresses",
      "analysis": "The generate_random_address() function uses the random() function to generate random addresses for testing. However, random() is not cryptographically secure and can produce predictable output. An attacker could potentially predict the randomly generated addresses, which could lead to vulnerabilities if these addresses are used for anything security-sensitive. A cryptographically secure random number generator like /dev/urandom should be used instead for generating random data for security purposes.\n",
      "classification": "slightly promising",
      "cwe": "CWE-338",
      "function_names": [
        "generate_random_address"
      ],
      "filenames": [
        "tests.c"
      ]
    },
    {
      "headline": "Potential buffer overflow in url_encode function",
      "analysis": "The url_encode function in srs2.c does not properly check buffer limits when encoding special characters. If the input contains many characters that need to be percent-encoded, it's possible to write beyond the end of the output buffer. This could lead to a buffer overflow vulnerability. The function should ensure it never writes beyond the specified output buffer length, even in the worst case where every input character needs to be encoded.\n",
      "classification": "very promising",
      "cwe": "CWE-120",
      "function_names": [
        "url_encode"
      ],
      "filenames": [
        "srs2.c"
      ]
    },
    {
      "headline": "Potential buffer overflow in srs_compile_shortcut function",
      "analysis": "The srs_compile_shortcut function in srs2.c calculates a required buffer length and compares it to the provided buffer length, but then uses sprintf to write to the buffer without any length limiting. If the calculated length is incorrect, this could lead to a buffer overflow. A length-limiting string function like snprintf should be used instead to ensure the write cannot exceed the buffer size.\n",
      "classification": "very promising",
      "cwe": "CWE-120",
      "function_names": [
        "srs_compile_shortcut"
      ],
      "filenames": [
        "srs2.c"
      ]
    },
    {
      "headline": "Use of deprecated and unsafe strcpy function",
      "analysis": "The code uses the strcpy function in multiple places, such as in srs_forward_alloc. strcpy is considered unsafe as it does not perform any bounds checking and can lead to buffer overflows if the destination buffer is not large enough to hold the source string. It should be replaced with safer alternatives like strncpy or strlcpy that limit the number of characters copied.\n",
      "classification": "slightly promising",
      "cwe": "CWE-120",
      "function_names": [
        "srs_forward_alloc"
      ],
      "filenames": [
        "srs2.c"
      ]
    },
    {
      "headline": "Potential integer overflow in srs_forward_alloc",
      "analysis": "In the srs_forward_alloc function, the buffer length is calculated by adding several integer values. If these values are large, it could lead to an integer overflow, resulting in a buffer that is too small being allocated. This could then lead to a buffer overflow when writing to the buffer. The code should use safe integer arithmetic to prevent potential overflows.\n",
      "classification": "slightly promising",
      "cwe": "CWE-190",
      "function_names": [
        "srs_forward_alloc"
      ],
      "filenames": [
        "srs2.c"
      ]
    },
    {
      "headline": "Unsafe use of alloca for dynamic memory allocation",
      "analysis": "The code uses alloca in several places to allocate memory on the stack. While not inherently unsafe, alloca can lead to stack overflow if used with large or unbounded sizes. It's especially risky in recursive functions. Consider using safer alternatives like malloc for dynamic memory allocation, especially for larger or variable-sized allocations.\n",
      "classification": "slightly promising",
      "cwe": "CWE-787",
      "function_names": [
        "srs_hash_create",
        "srs_forward"
      ],
      "filenames": [
        "srs2.c"
      ]
    },
    {
      "headline": "Potential command injection vulnerability in postsrsd",
      "analysis": "The postsrsd.c file appears to handle user input for email addresses and domain names. While there is some input validation and sanitization, it may not be comprehensive. If any of this user-controlled data is used to construct system commands without proper escaping, it could lead to command injection vulnerabilities. A thorough review of how user input is handled and used throughout the application is necessary to ensure all potential injection points are properly secured.\n",
      "classification": "slightly promising",
      "cwe": "CWE-78",
      "function_names": [],
      "filenames": [
        "postsrsd.c"
      ]
    }
  ],
  "scores": [
    {
      "stats": {
        "fn": 2,
        "tp": 0,
        "fp": 2
      },
      "mapping": {},
      "vuln_dates": {
        "CVE-2020-35573": "2020-12-20T05:15:09",
        "CVE-2021-35525": "2021-06-28T18:15:08"
      },
      "scoring_model": "claude-3-5-sonnet-20240620",
      "type": "llm",
      "instruction_template_hash": "245ace12b6361954d0a2"
    }
  ],
  "instruction_template_hash": "10c0163db4740318a544",
  "version": "0.1.0"
}
