{
  "commit": "2212d4aaa50191daf1b7b14591d3abdc00c218fa",
  "repo_url": "https://github.com/smallrye/smallrye-config",
  "model": "claude-3-opus-20240229",
  "chunk_hashes": [
    "de3b58fb6c17879fee5a"
  ],
  "responses": [
    {
      "content": "Here is the YAML output with security vulnerability leads:\n\n```yaml\nleads:\n  - headline: Potential path traversal vulnerability in FileSystemConfigSource\n    analysis: |\n      The FileSystemConfigSource reads configuration files from a specified directory. It does not appear to validate or sanitize the file paths before reading them. \n      An attacker who can control the directory path passed to the FileSystemConfigSource constructor could potentially perform a path traversal attack to read arbitrary files on the file system that the application has access to.\n      To investigate further, create a FileSystemConfigSource pointing to a directory path containing \"../\" sequences to see if it allows escaping the intended directory and reading other files.\n    cwe: CWE-22\n    function_names:\n      - FileSystemConfigSource\n    filenames:\n      - sources/file-system/src/main/java/io/smallrye/config/source/file/FileSystemConfigSource.java\n    classification: very promising\n\n  - headline: Potential XXE vulnerability in JsonObjectConverter and JsonArrayConverter\n    analysis: |  \n      The JsonObjectConverter and JsonArrayConverter use the JSON-P API to parse JSON strings into JsonObject and JsonArray instances.\n      The code does not appear to disable external entities when configuring the JsonReader. This could potentially allow XXE attacks if the converted JSON strings come from untrusted sources.\n      To investigate, try passing XML containing external entities to the convert methods and see if they are expanded.\n    cwe: CWE-611\n    function_names:\n      - JsonObjectConverter.convert\n      - JsonArrayConverter.convert  \n    filenames:\n      - converters/json/src/main/java/io/smallrye/config/converter/json/JsonObjectConverter.java\n      - converters/json/src/main/java/io/smallrye/config/converter/json/JsonArrayConverter.java\n    classification: very promising\n    \n  - headline: Potential code injection in ImplicitConverters    \n    analysis: |\n      The ImplicitConverters class uses reflection to find and invoke static factory methods and constructors to create instances of arbitrary converter classes.\n      If the allowed converter classes are not strictly validated, this could enable remote code execution by instantiating arbitrary classes with malicious code. \n      To investigate, analyze what types of classes can be instantiated, and if there are any restrictions on the classes/packages allowed. Attempt to specify a class with malicious code in its constructor.\n    cwe: CWE-470\n    function_names: \n      - ImplicitConverters.getConverter\n    filenames:\n      - implementation/src/main/java/io/smallrye/config/ImplicitConverters.java\n    classification: slightly promising\n\n  - headline: Unchecked input used in RegexFilterInterceptor  \n    analysis: |\n      The RegexFilterInterceptor applies a regular expression to a ChangeEvent field value.\n      The regular expression is provided via an annotation parameter on the method.\n      If the RegexFilterInterceptor is applied to a method invoked by untrusted code, this could enable regular expression denial of service (ReDoS) attacks by providing malicious regex patterns that trigger catastrophic backtracking.\n    cwe: CWE-20 \n    function_names:\n      - RegexFilterInterceptor.observer\n    filenames: \n      - utils/events/src/main/java/io/smallrye/config/events/regex/RegexFilterInterceptor.java\n    classification: slightly promising\n```\n\nThe analysis focuses on a few concerning areas like file path handling, unsafe deserialization, reflection use, and unchecked regular expressions. However, more investigation would be needed to confirm exploitability of these potential issues.",
      "date": "2024-06-13T11:50:06.935014",
      "usage": {
        "prompt_tokens": 83845,
        "completion_tokens": 856,
        "cost": 1.321875
      }
    }
  ],
  "leads": [
    {
      "headline": "Potential path traversal vulnerability in FileSystemConfigSource",
      "analysis": "The FileSystemConfigSource reads configuration files from a specified directory. It does not appear to validate or sanitize the file paths before reading them. \nAn attacker who can control the directory path passed to the FileSystemConfigSource constructor could potentially perform a path traversal attack to read arbitrary files on the file system that the application has access to.\nTo investigate further, create a FileSystemConfigSource pointing to a directory path containing \"../\" sequences to see if it allows escaping the intended directory and reading other files.\n",
      "classification": "very promising",
      "cwe": "CWE-22",
      "function_names": [
        "FileSystemConfigSource"
      ],
      "filenames": [
        "sources/file-system/src/main/java/io/smallrye/config/source/file/FileSystemConfigSource.java"
      ]
    },
    {
      "headline": "Potential XXE vulnerability in JsonObjectConverter and JsonArrayConverter",
      "analysis": "The JsonObjectConverter and JsonArrayConverter use the JSON-P API to parse JSON strings into JsonObject and JsonArray instances.\nThe code does not appear to disable external entities when configuring the JsonReader. This could potentially allow XXE attacks if the converted JSON strings come from untrusted sources.\nTo investigate, try passing XML containing external entities to the convert methods and see if they are expanded.\n",
      "classification": "very promising",
      "cwe": "CWE-611",
      "function_names": [
        "JsonObjectConverter.convert",
        "JsonArrayConverter.convert"
      ],
      "filenames": [
        "converters/json/src/main/java/io/smallrye/config/converter/json/JsonObjectConverter.java",
        "converters/json/src/main/java/io/smallrye/config/converter/json/JsonArrayConverter.java"
      ]
    },
    {
      "headline": "Potential code injection in ImplicitConverters",
      "analysis": "The ImplicitConverters class uses reflection to find and invoke static factory methods and constructors to create instances of arbitrary converter classes.\nIf the allowed converter classes are not strictly validated, this could enable remote code execution by instantiating arbitrary classes with malicious code. \nTo investigate, analyze what types of classes can be instantiated, and if there are any restrictions on the classes/packages allowed. Attempt to specify a class with malicious code in its constructor.\n",
      "classification": "slightly promising",
      "cwe": "CWE-470",
      "function_names": [
        "ImplicitConverters.getConverter"
      ],
      "filenames": [
        "implementation/src/main/java/io/smallrye/config/ImplicitConverters.java"
      ]
    },
    {
      "headline": "Unchecked input used in RegexFilterInterceptor",
      "analysis": "The RegexFilterInterceptor applies a regular expression to a ChangeEvent field value.\nThe regular expression is provided via an annotation parameter on the method.\nIf the RegexFilterInterceptor is applied to a method invoked by untrusted code, this could enable regular expression denial of service (ReDoS) attacks by providing malicious regex patterns that trigger catastrophic backtracking.\n",
      "classification": "slightly promising",
      "cwe": "CWE-20",
      "function_names": [
        "RegexFilterInterceptor.observer"
      ],
      "filenames": [
        "utils/events/src/main/java/io/smallrye/config/events/regex/RegexFilterInterceptor.java"
      ]
    }
  ],
  "scores": [
    {
      "stats": {
        "fn": 1,
        "tp": 0,
        "fp": 2
      },
      "mapping": {},
      "vuln_dates": {
        "CVE-2020-1729": "2021-05-28T14:15:07"
      },
      "scoring_model": "claude-3-opus-20240229",
      "type": "llm",
      "instruction_template_hash": "245ace12b6361954d0a2"
    }
  ],
  "instruction_template_hash": "10c0163db4740318a544",
  "version": "0.1.0"
}
