{
  "commit": "44938b49c27407db9a03ec47824f126363e183b6",
  "repo_url": "https://github.com/jitsi/jitsi-meet-electron",
  "model": "claude-3-sonnet-20240229",
  "chunk_hashes": [
    "673647caae3c668516d8"
  ],
  "responses": [
    {
      "content": "```yaml\nleads:\n  - headline: Potential Link Following vulnerability\n    analysis: |\n      The `getExternalApiURL` function in `app/features/utils/functions.js` constructs the URL to the external API script by concatenating the server URL provided by the user with the path `/external_api.js`. This could potentially lead to a Link Following vulnerability if the provided server URL contains path traversal sequences like `../` that allow accessing files outside of the intended directory.\n    cwe: CWE-59\n    function_names:\n      - getExternalApiURL\n    filenames:\n      - app/features/utils/functions.js\n    classification: slightly promising\n\n  - headline: Potential Path Traversal vulnerability\n    analysis: |\n      The `getExternalApiURL` function in `app/features/utils/functions.js` constructs the URL to the external API script by concatenating the server URL provided by the user with the path `/external_api.js`. This could potentially lead to a Path Traversal vulnerability if the provided server URL contains path traversal sequences like `../` that allow accessing files outside of the intended directory.\n    cwe: CWE-22\n    function_names:\n      - getExternalApiURL\n    filenames:\n      - app/features/utils/functions.js\n    classification: slightly promising\n\n  - headline: Potential Server-Side Request Forgery (SSRF) vulnerability\n    analysis: |\n      The `getExternalApiURL` function in `app/features/utils/functions.js` constructs the URL to the external API script based on a user-provided server URL. This could potentially lead to a Server-Side Request Forgery (SSRF) vulnerability if the user-provided server URL points to an internal or otherwise restricted resource.\n    cwe: CWE-918\n    function_names:\n      - getExternalApiURL\n    filenames:\n      - app/features/utils/functions.js\n    classification: slightly promising\n\n  - headline: Potential Session Fixation vulnerability\n    analysis: |\n      The `createJitsiMeetWindow` function in `main.js` does not appear to generate a new session ID or invalidate the existing session when a new window is created. This could potentially lead to a Session Fixation vulnerability, which allows an attacker to hijack a user's session.\n    cwe: CWE-384\n    function_names:\n      - createJitsiMeetWindow\n    filenames:\n      - main.js\n    classification: slightly promising\n\n  - headline: Potential Null Pointer Dereference vulnerability\n    analysis: |\n      The `_onIframeLoad` function in `app/features/conference/components/Conference.js` does not appear to check if `this._loadTimer` is null before calling `clearTimeout`. This could potentially lead to a Null Pointer Dereference vulnerability if `this._loadTimer` is null.\n    cwe: CWE-476\n    function_names:\n      - _onIframeLoad\n    filenames:\n      - app/features/conference/components/Conference.js\n    classification: slightly promising\n\n  - headline: Potential Improper Neutralization of Special Elements Used in an OS Command vulnerability\n    analysis: |\n      The `patches/app-builder-lib+22.7.0.patch` file modifies the `exec` command used by the `app-builder-lib` package to include the `--no-sandbox` flag. This could potentially lead to an Improper Neutralization of Special Elements Used in an OS Command vulnerability if the `exec` command is constructed using untrusted input, allowing an attacker to inject arbitrary commands.\n    cwe: CWE-78\n    function_names: []\n    filenames:\n      - patches/app-builder-lib+22.7.0.patch\n    classification: slightly promising\n\n  - headline: Potential Cross-Site Request Forgery (CSRF) vulnerability\n    analysis: |\n      The application does not appear to implement any Cross-Site Request Forgery (CSRF) protection mechanisms. This could potentially lead to a CSRF vulnerability, allowing an attacker to perform unauthorized actions on behalf of a user.\n    cwe: CWE-352\n    function_names: []\n    filenames: []\n    classification: slightly promising\n\n  - headline: Potential Improper Restriction of Excessive Authentication Attempts vulnerability\n    analysis: |\n      The application does not appear to implement any mechanisms to restrict excessive authentication attempts. This could potentially lead to an Improper Restriction of Excessive Authentication Attempts vulnerability, allowing an attacker to perform brute-force attacks on user accounts.\n    cwe: CWE-307\n    function_names: []\n    filenames: []\n    classification: slightly promising\n\n  - headline: Potential Improper Neutralization of Input During Web Page Generation ('Cross-site Scripting') vulnerability\n    analysis: |\n      The application appears to render user-provided data in the React components without proper sanitization or encoding. This could potentially lead to an Improper Neutralization of Input During Web Page Generation ('Cross-site Scripting') vulnerability, allowing an attacker to inject malicious scripts into the application's web pages.\n    cwe: CWE-79\n    function_names: []\n    filenames: []\n    classification: slightly promising\n\n  - headline: Potential Use of Hard-coded Credentials vulnerability\n    analysis: |\n      The application appears to use hard-coded default values for server URLs and other configuration settings. This could potentially lead to a Use of Hard-coded Credentials vulnerability if these default values are used in production environments without being changed.\n    cwe: CWE-798\n    function_names: []\n    filenames:\n      - app/features/config/index.js\n    classification: slightly promising\n```",
      "date": "2024-06-14T14:30:19.088058",
      "usage": {
        "prompt_tokens": 37651,
        "completion_tokens": 1331,
        "cost": 0.132918
      }
    }
  ],
  "leads": [
    {
      "headline": "Potential Link Following vulnerability",
      "analysis": "The getExternalApiURL function in app/features/utils/functions.js constructs the URL to the external API script by concatenating the server URL provided by the user with the path /external_api.js. This could potentially lead to a Link Following vulnerability if the provided server URL contains path traversal sequences like ../ that allow accessing files outside of the intended directory.\n",
      "classification": "slightly promising",
      "cwe": "CWE-59",
      "function_names": [
        "getExternalApiURL"
      ],
      "filenames": [
        "app/features/utils/functions.js"
      ]
    },
    {
      "headline": "Potential Path Traversal vulnerability",
      "analysis": "The getExternalApiURL function in app/features/utils/functions.js constructs the URL to the external API script by concatenating the server URL provided by the user with the path /external_api.js. This could potentially lead to a Path Traversal vulnerability if the provided server URL contains path traversal sequences like ../ that allow accessing files outside of the intended directory.\n",
      "classification": "slightly promising",
      "cwe": "CWE-22",
      "function_names": [
        "getExternalApiURL"
      ],
      "filenames": [
        "app/features/utils/functions.js"
      ]
    },
    {
      "headline": "Potential Server-Side Request Forgery (SSRF) vulnerability",
      "analysis": "The getExternalApiURL function in app/features/utils/functions.js constructs the URL to the external API script based on a user-provided server URL. This could potentially lead to a Server-Side Request Forgery (SSRF) vulnerability if the user-provided server URL points to an internal or otherwise restricted resource.\n",
      "classification": "slightly promising",
      "cwe": "CWE-918",
      "function_names": [
        "getExternalApiURL"
      ],
      "filenames": [
        "app/features/utils/functions.js"
      ]
    },
    {
      "headline": "Potential Session Fixation vulnerability",
      "analysis": "The createJitsiMeetWindow function in main.js does not appear to generate a new session ID or invalidate the existing session when a new window is created. This could potentially lead to a Session Fixation vulnerability, which allows an attacker to hijack a user's session.\n",
      "classification": "slightly promising",
      "cwe": "CWE-384",
      "function_names": [
        "createJitsiMeetWindow"
      ],
      "filenames": [
        "main.js"
      ]
    },
    {
      "headline": "Potential Null Pointer Dereference vulnerability",
      "analysis": "The _onIframeLoad function in app/features/conference/components/Conference.js does not appear to check if this._loadTimer is null before calling clearTimeout. This could potentially lead to a Null Pointer Dereference vulnerability if this._loadTimer is null.\n",
      "classification": "slightly promising",
      "cwe": "CWE-476",
      "function_names": [
        "_onIframeLoad"
      ],
      "filenames": [
        "app/features/conference/components/Conference.js"
      ]
    },
    {
      "headline": "Potential Improper Neutralization of Special Elements Used in an OS Command vulnerability",
      "analysis": "The patches/app-builder-lib+22.7.0.patch file modifies the exec command used by the app-builder-lib package to include the --no-sandbox flag. This could potentially lead to an Improper Neutralization of Special Elements Used in an OS Command vulnerability if the exec command is constructed using untrusted input, allowing an attacker to inject arbitrary commands.\n",
      "classification": "slightly promising",
      "cwe": "CWE-78",
      "function_names": [],
      "filenames": [
        "patches/app-builder-lib+22.7.0.patch"
      ]
    },
    {
      "headline": "Potential Cross-Site Request Forgery (CSRF) vulnerability",
      "analysis": "The application does not appear to implement any Cross-Site Request Forgery (CSRF) protection mechanisms. This could potentially lead to a CSRF vulnerability, allowing an attacker to perform unauthorized actions on behalf of a user.\n",
      "classification": "slightly promising",
      "cwe": "CWE-352",
      "function_names": [],
      "filenames": []
    },
    {
      "headline": "Potential Improper Restriction of Excessive Authentication Attempts vulnerability",
      "analysis": "The application does not appear to implement any mechanisms to restrict excessive authentication attempts. This could potentially lead to an Improper Restriction of Excessive Authentication Attempts vulnerability, allowing an attacker to perform brute-force attacks on user accounts.\n",
      "classification": "slightly promising",
      "cwe": "CWE-307",
      "function_names": [],
      "filenames": []
    },
    {
      "headline": "Potential Improper Neutralization of Input During Web Page Generation ('Cross-site Scripting') vulnerability",
      "analysis": "The application appears to render user-provided data in the React components without proper sanitization or encoding. This could potentially lead to an Improper Neutralization of Input During Web Page Generation ('Cross-site Scripting') vulnerability, allowing an attacker to inject malicious scripts into the application's web pages.\n",
      "classification": "slightly promising",
      "cwe": "CWE-79",
      "function_names": [],
      "filenames": []
    },
    {
      "headline": "Potential Use of Hard-coded Credentials vulnerability",
      "analysis": "The application appears to use hard-coded default values for server URLs and other configuration settings. This could potentially lead to a Use of Hard-coded Credentials vulnerability if these default values are used in production environments without being changed.\n",
      "classification": "slightly promising",
      "cwe": "CWE-798",
      "function_names": [],
      "filenames": [
        "app/features/config/index.js"
      ]
    }
  ],
  "scores": [
    {
      "stats": {
        "fn": 1,
        "tp": 0,
        "fp": 0
      },
      "mapping": {},
      "vuln_dates": {
        "CVE-2020-25019": "2020-08-29T17:15:11"
      },
      "scoring_model": "claude-3-opus-20240229",
      "type": "llm",
      "instruction_template_hash": "245ace12b6361954d0a2"
    },
    {
      "stats": {
        "fn": 1,
        "tp": 0,
        "fp": 0
      },
      "mapping": {},
      "vuln_dates": {
        "CVE-2020-25019": "2020-08-29T17:15:11"
      },
      "scoring_model": "claude-3-5-sonnet-20240620",
      "type": "llm",
      "instruction_template_hash": "245ace12b6361954d0a2"
    }
  ],
  "instruction_template_hash": "10c0163db4740318a544",
  "version": "0.1.0"
}
