{
  "commit": "2cd9997382a9d29e97806fce9086f83409cb077e",
  "repo_url": "https://github.com/jenkinsci/mantis-plugin",
  "model": "gpt-4o-2024-05-13",
  "chunk_hashes": [
    "e56a63e502f475750918"
  ],
  "responses": [
    {
      "content": "```yaml\nleads:\n  - headline: \"Sensitive Information in Log Files\"\n    analysis: |\n      The `doCheckLogin` method in `MantisProjectProperty.java` writes the `password` parameter to log files. This can expose sensitive information if logs are accessed by unauthorized parties. Developers need to mask or avoid logging sensitive data to prevent such exposure.\n    cwe: CWE-532\n    function_names:\n      - \"doCheckLogin\"\n    filenames:\n      - \"src/main/java/hudson/plugins/mantis/MantisProjectProperty.java\"\n    classification: very promising\n\n  - headline: \"Use of Hard-coded Credentials\"\n    analysis: |\n      The code in `MantisSiteTest.java` and other files contains hard-coded usernames and passwords (`jenkinsci`, `test`, `dummy`). This allows attackers to bypass authentication. These credentials should be managed securely and not hard-coded in the source files.\n    cwe: CWE-798\n    function_names:\n    filenames:\n      - \"src/test/java/hudson/plugins/mantis/MantisSiteTest.java\"\n      - \"src/test/java/hudson/plugins/mantis/MantisProjectPropertyConfigSubmitTest.java\"\n    classification: very promising\n\n  - headline: \"Cleartext Storage of Sensitive Information\"\n    analysis: |\n      The code uses `String` to store passwords in `MantisSite.java`. Storing sensitive data in cleartext can be risky. Developers should use a secure method of storing such information, such as encrypted storage with secure key management.\n    cwe: CWE-312\n    function_names:\n      - \"MantisSite\"\n    filenames:\n      - \"src/main/java/hudson/plugins/mantis/MantisSite.java\"\n    classification: very promising\n\n  - headline: \"Incomplete Initialization\"\n    analysis: |\n      The constructor of the `MantisSite` class initializes some fields but does not consistently manage the initialization of all fields, leading to possible null references or incomplete states of the object, which could cause runtime issues or security flaws.\n    cwe: CWE-665\n    function_names:\n      - \"MantisSite\"\n    filenames:\n      - \"src/main/java/hudson/plugins/mantis/MantisSite.java\"\n    classification: slightly promising\n\n  - headline: \"Insufficient Logging of Critical Actions\"\n    analysis: |\n      Methods such as `addIssue`, `updateIssue` in the `MantisSite` class do not have sufficient logging for critical actions. Lack of detailed logging can hinder incident response and forensic analysis.\n    cwe: CWE-117\n    function_names:\n      - \"addIssue\"\n      - \"updateIssue\"\n    filenames:\n      - \"src/main/java/hudson/plugins/mantis/MantisSite.java\"\n    classification: slightly promising\n\n  - headline: \"Improper Handling of Exceptional Conditions\"\n    analysis: |\n      The `perform` method in `MantisIssueUpdater.java` catches InterruptedException and IOException but only logs a generic failure message without sufficient context. Proper exception handling is required to diagnose the issue accurately.\n    cwe: CWE-755\n    function_names:\n      - \"perform\"\n    filenames:\n      - \"src/main/java/hudson/plugins/mantis/MantisIssueUpdater.java\"\n    classification: slightly promising\n\n  - headline: \"Command Injection Vulnerability\"\n    analysis: |\n      The `createSession` method in `AbstractMantisSession.java` constructs a command string with user-controlled input. If this string is not properly sanitized, an attacker can inject malicious commands. Always validate and sanitize all input.\n    cwe: CWE-78\n    function_names:\n      - \"createSession\"\n    filenames:\n      - \"src/main/java/hudson/plugins/mantis/soap/AbstractMantisSession.java\"\n    classification: very promising\n```",
      "date": "2024-06-12T18:49:25.069920",
      "usage": {
        "prompt_tokens": 24263,
        "completion_tokens": 777,
        "cost": 0.13297
      }
    }
  ],
  "leads": [
    {
      "headline": "Sensitive Information in Log Files",
      "analysis": "The doCheckLogin method in MantisProjectProperty.java writes the password parameter to log files. This can expose sensitive information if logs are accessed by unauthorized parties. Developers need to mask or avoid logging sensitive data to prevent such exposure.\n",
      "classification": "very promising",
      "cwe": "CWE-532",
      "function_names": [
        "doCheckLogin"
      ],
      "filenames": [
        "src/main/java/hudson/plugins/mantis/MantisProjectProperty.java"
      ]
    },
    {
      "headline": "Cleartext Storage of Sensitive Information",
      "analysis": "The code uses String to store passwords in MantisSite.java. Storing sensitive data in cleartext can be risky. Developers should use a secure method of storing such information, such as encrypted storage with secure key management.\n",
      "classification": "very promising",
      "cwe": "CWE-312",
      "function_names": [
        "MantisSite"
      ],
      "filenames": [
        "src/main/java/hudson/plugins/mantis/MantisSite.java"
      ]
    },
    {
      "headline": "Incomplete Initialization",
      "analysis": "The constructor of the MantisSite class initializes some fields but does not consistently manage the initialization of all fields, leading to possible null references or incomplete states of the object, which could cause runtime issues or security flaws.\n",
      "classification": "slightly promising",
      "cwe": "CWE-665",
      "function_names": [
        "MantisSite"
      ],
      "filenames": [
        "src/main/java/hudson/plugins/mantis/MantisSite.java"
      ]
    },
    {
      "headline": "Insufficient Logging of Critical Actions",
      "analysis": "Methods such as addIssue, updateIssue in the MantisSite class do not have sufficient logging for critical actions. Lack of detailed logging can hinder incident response and forensic analysis.\n",
      "classification": "slightly promising",
      "cwe": "CWE-117",
      "function_names": [
        "addIssue",
        "updateIssue"
      ],
      "filenames": [
        "src/main/java/hudson/plugins/mantis/MantisSite.java"
      ]
    },
    {
      "headline": "Improper Handling of Exceptional Conditions",
      "analysis": "The perform method in MantisIssueUpdater.java catches InterruptedException and IOException but only logs a generic failure message without sufficient context. Proper exception handling is required to diagnose the issue accurately.\n",
      "classification": "slightly promising",
      "cwe": "CWE-755",
      "function_names": [
        "perform"
      ],
      "filenames": [
        "src/main/java/hudson/plugins/mantis/MantisIssueUpdater.java"
      ]
    },
    {
      "headline": "Command Injection Vulnerability",
      "analysis": "The createSession method in AbstractMantisSession.java constructs a command string with user-controlled input. If this string is not properly sanitized, an attacker can inject malicious commands. Always validate and sanitize all input.\n",
      "classification": "very promising",
      "cwe": "CWE-78",
      "function_names": [
        "createSession"
      ],
      "filenames": [
        "src/main/java/hudson/plugins/mantis/soap/AbstractMantisSession.java"
      ]
    }
  ],
  "scores": [
    {
      "stats": {
        "fn": 1,
        "tp": 0,
        "fp": 3
      },
      "mapping": {},
      "vuln_dates": {
        "CVE-2019-16569": "2019-12-17T15:15:22"
      },
      "scoring_model": "claude-3-opus-20240229",
      "type": "llm",
      "instruction_template_hash": "245ace12b6361954d0a2"
    },
    {
      "stats": {
        "fn": 1,
        "tp": 0,
        "fp": 3
      },
      "mapping": {},
      "vuln_dates": {
        "CVE-2019-16569": "2019-12-17T15:15:22"
      },
      "scoring_model": "claude-3-5-sonnet-20240620",
      "type": "llm",
      "instruction_template_hash": "245ace12b6361954d0a2"
    }
  ],
  "instruction_template_hash": "10c0163db4740318a544",
  "version": "0.1.0"
}
