{
  "commit": "22f1f794d438e5cb234dbc161f8f9abfd5c3f04b",
  "repo_url": "https://github.com/jenkinsci/ontrack-plugin",
  "model": "claude-3-haiku-20240307",
  "chunk_hashes": [
    "b13cdf6dc5f1739f3d9b"
  ],
  "responses": [
    {
      "content": "Here is the YAML output for the security vulnerabilities in the codebase:\n\n```yaml\nleads:\n  - headline: Improper Input Validation\n    analysis: |\n      The codebase contains several instances of improper input validation, which could lead to vulnerabilities such as CWE-1284 Improper Validation of Specified Quantity in Input and CWE-129 Improper Validation of Array Index. This could allow an attacker to provide malformed input and potentially execute arbitrary code or access sensitive information.\n    cwe: CWE-20\n    function_names:\n      - runDSL\n      - createValue\n    filenames:\n      - src/main/java/net/nemerosa/ontrack/jenkins/AbstractOntrackParameterDefinition.java\n      - src/main/java/net/nemerosa/ontrack/jenkins/OntrackSingleParameterDefinition.java\n      - src/main/java/net/nemerosa/ontrack/jenkins/steps/OntrackValidateStep.java\n    classification: slightly promising\n\n  - headline: Improper Neutralization of Special Elements in Output Used by a Downstream Component ('Injection')\n    analysis: |\n      The codebase contains several instances of improper neutralization of special elements in the output, which could lead to injection vulnerabilities such as CWE-77 Improper Neutralization of Special Elements used in a Command ('Command Injection'), CWE-79 Improper Neutralization of Input During Web Page Generation ('Cross-site Scripting'), and CWE-89 Improper Neutralization of Special Elements used in an SQL Command ('SQL Injection'). This could allow an attacker to inject malicious code or commands into the application, potentially leading to arbitrary code execution or data exposure.\n    cwe: CWE-74\n    function_names:\n      - expand\n      - getParameter\n      - readScript\n    filenames:\n      - src/main/java/net/nemerosa/ontrack/jenkins/OntrackPluginSupport.java\n    classification: very promising\n\n  - headline: Incorrect Resource Transfer Between Spheres\n    analysis: |\n      The codebase contains several instances of incorrect resource transfer between spheres, which could lead to vulnerabilities such as CWE-212 Improper Removal of Sensitive Information Before Storage or Transfer and CWE-829 Inclusion of Functionality from Untrusted Control Sphere. This could allow an attacker to access or manipulate sensitive information or include untrusted functionality in the application, potentially leading to data exposure or further compromise.\n    cwe: CWE-669\n    function_names:\n      - createOntrackLinks\n    filenames:\n      - src/main/java/net/nemerosa/ontrack/jenkins/OntrackPluginSupport.java\n    classification: slightly promising\n\n  - headline: Improper Handling of Exceptional Conditions\n    analysis: |\n      The codebase contains several instances of improper handling of exceptional conditions, which could lead to vulnerabilities such as CWE-252 Unchecked Return Value, CWE-273 Improper Check for Dropped Privileges, and CWE-476 NULL Pointer Dereference. This could allow an attacker to trigger unhandled exceptions and potentially execute arbitrary code or access sensitive information.\n    cwe: CWE-754\n    function_names:\n      - perform\n      - run\n    filenames:\n      - src/main/java/net/nemerosa/ontrack/jenkins/OntrackDSLNotifier.java\n      - src/main/java/net/nemerosa/ontrack/jenkins/OntrackDSLStep.java\n    classification: very promising\n\n  - headline: Improper Control of Dynamically-Managed Code Resources\n    analysis: |\n      The codebase contains several instances of improper control of dynamically-managed code resources, which could lead to vulnerabilities such as CWE-470 Use of Externally-Controlled Input to Select Classes or Code ('Unsafe Reflection') and CWE-502 Deserialization of Untrusted Data. This could allow an attacker to load and execute arbitrary code or manipulate the application's behavior by providing malformed input.\n    cwe: CWE-913\n    function_names:\n      - run\n      - createDSLRunner\n    filenames:\n      - src/main/java/net/nemerosa/ontrack/jenkins/dsl/OntrackDSLRunner.java\n    classification: very promising\n```",
      "date": "2024-06-12T18:56:17.919138",
      "usage": {
        "prompt_tokens": 76941,
        "completion_tokens": 1064,
        "cost": 0.02056525
      }
    }
  ],
  "leads": [
    {
      "headline": "Improper Input Validation",
      "analysis": "The codebase contains several instances of improper input validation, which could lead to vulnerabilities such as CWE-1284 Improper Validation of Specified Quantity in Input and CWE-129 Improper Validation of Array Index. This could allow an attacker to provide malformed input and potentially execute arbitrary code or access sensitive information.\n",
      "classification": "slightly promising",
      "cwe": "CWE-20",
      "function_names": [
        "runDSL",
        "createValue"
      ],
      "filenames": [
        "src/main/java/net/nemerosa/ontrack/jenkins/AbstractOntrackParameterDefinition.java",
        "src/main/java/net/nemerosa/ontrack/jenkins/OntrackSingleParameterDefinition.java",
        "src/main/java/net/nemerosa/ontrack/jenkins/steps/OntrackValidateStep.java"
      ]
    },
    {
      "headline": "Improper Neutralization of Special Elements in Output Used by a Downstream Component ('Injection')",
      "analysis": "The codebase contains several instances of improper neutralization of special elements in the output, which could lead to injection vulnerabilities such as CWE-77 Improper Neutralization of Special Elements used in a Command ('Command Injection'), CWE-79 Improper Neutralization of Input During Web Page Generation ('Cross-site Scripting'), and CWE-89 Improper Neutralization of Special Elements used in an SQL Command ('SQL Injection'). This could allow an attacker to inject malicious code or commands into the application, potentially leading to arbitrary code execution or data exposure.\n",
      "classification": "very promising",
      "cwe": "CWE-74",
      "function_names": [
        "expand",
        "getParameter",
        "readScript"
      ],
      "filenames": [
        "src/main/java/net/nemerosa/ontrack/jenkins/OntrackPluginSupport.java"
      ]
    },
    {
      "headline": "Incorrect Resource Transfer Between Spheres",
      "analysis": "The codebase contains several instances of incorrect resource transfer between spheres, which could lead to vulnerabilities such as CWE-212 Improper Removal of Sensitive Information Before Storage or Transfer and CWE-829 Inclusion of Functionality from Untrusted Control Sphere. This could allow an attacker to access or manipulate sensitive information or include untrusted functionality in the application, potentially leading to data exposure or further compromise.\n",
      "classification": "slightly promising",
      "cwe": "CWE-669",
      "function_names": [
        "createOntrackLinks"
      ],
      "filenames": [
        "src/main/java/net/nemerosa/ontrack/jenkins/OntrackPluginSupport.java"
      ]
    },
    {
      "headline": "Improper Handling of Exceptional Conditions",
      "analysis": "The codebase contains several instances of improper handling of exceptional conditions, which could lead to vulnerabilities such as CWE-252 Unchecked Return Value, CWE-273 Improper Check for Dropped Privileges, and CWE-476 NULL Pointer Dereference. This could allow an attacker to trigger unhandled exceptions and potentially execute arbitrary code or access sensitive information.\n",
      "classification": "very promising",
      "cwe": "CWE-754",
      "function_names": [
        "perform",
        "run"
      ],
      "filenames": [
        "src/main/java/net/nemerosa/ontrack/jenkins/OntrackDSLNotifier.java",
        "src/main/java/net/nemerosa/ontrack/jenkins/OntrackDSLStep.java"
      ]
    },
    {
      "headline": "Improper Control of Dynamically-Managed Code Resources",
      "analysis": "The codebase contains several instances of improper control of dynamically-managed code resources, which could lead to vulnerabilities such as CWE-470 Use of Externally-Controlled Input to Select Classes or Code ('Unsafe Reflection') and CWE-502 Deserialization of Untrusted Data. This could allow an attacker to load and execute arbitrary code or manipulate the application's behavior by providing malformed input.\n",
      "classification": "very promising",
      "cwe": "CWE-913",
      "function_names": [
        "run",
        "createDSLRunner"
      ],
      "filenames": [
        "src/main/java/net/nemerosa/ontrack/jenkins/dsl/OntrackDSLRunner.java"
      ]
    }
  ],
  "scores": [
    {
      "stats": {
        "fn": 1,
        "tp": 1,
        "fp": 1
      },
      "mapping": {
        "0": "CVE-2019-10306",
        "2": "CVE-2019-10306"
      },
      "vuln_dates": {
        "CVE-2019-10306": "2019-04-18T17:29:00",
        "CVE-2022-34192": "2022-06-23T17:15:16"
      },
      "scoring_model": "claude-3-opus-20240229",
      "type": "llm",
      "instruction_template_hash": "245ace12b6361954d0a2"
    },
    {
      "stats": {
        "fn": 0,
        "tp": 2,
        "fp": 0
      },
      "mapping": {
        "0": "CVE-2022-34192",
        "1": "CVE-2019-10306",
        "2": "CVE-2019-10306"
      },
      "vuln_dates": {
        "CVE-2019-10306": "2019-04-18T17:29:00",
        "CVE-2022-34192": "2022-06-23T17:15:16"
      },
      "scoring_model": "claude-3-5-sonnet-20240620",
      "type": "llm",
      "instruction_template_hash": "245ace12b6361954d0a2"
    }
  ],
  "instruction_template_hash": "10c0163db4740318a544",
  "version": "0.1.0"
}
