{
  "commit": "005668dd56ff9cc6cc295f7ef73891a591cfbd15",
  "repo_url": "https://github.com/jens-maus/hm_email",
  "model": "gpt-4-turbo-2024-04-09",
  "chunk_hashes": [
    "8e2e4261a78150af613f"
  ],
  "responses": [
    {
      "content": "```yaml\nleads:\n  - headline: \"Insecure Use of Shell Commands\"\n    analysis: |\n      The script `generate_img.sh` uses shell commands to copy configuration and other sensitive files to a temporary directory for archiving. This could lead to command injection if unsanitized inputs are added into the shell-command formation. The design uses fixed commands but may not handle unexpected input changes securely.\n    cwe: CWE-78\n    function_names: []\n    filenames:\n      - generate_img.sh\n    classification: \"very promising\"\n\n  - headline: \"Exposure of Sensitive Information in Log Files\"\n    analysis: |\n      The script `generate_img.sh` copies sensitive configuration files (`account.conf`, `msmtp.conf`) into a temporary directory and eventually into a tar archive. If these log files are accessible by unauthorized users, it would be a severe security risk as they potentially contain sensitive information, including configuration details and credentials.\n    cwe: CWE-532\n    function_names: []\n    filenames:\n      - generate_img.sh\n    classification: \"very promising\"\n\n  - headline: \"Hard-coded Command Execution in TCL Script\"\n    analysis: |\n      The TCL script in `userscript.tcl` involves hard-coded command execution paths which could potentially be manipulated to execute arbitrary commands, particularly if user input affects command execution paths or parameters indirectly. Though not directly from the user inputs seen in the script, the environment or extended TCL scripts could influence these behaviors.\n    cwe: CWE-78\n    function_names: []\n    filenames:\n      - userscript.tcl\n    classification: \"slightly promising\"\n\n  - headline: \"Use of Insecure TCL Load Operation\"\n    analysis: |\n      The use of `load tclrega.so` within `userscript.tcl` combined with the way variables are handled and executed could potentially expose the system to arbitrary code execution if the `tclrega.so` module or the registry objects being accessed are compromised or mishandled.\n    cwe: CWE-94\n    function_names: []\n    filenames:\n      - userscript.tcl\n    classification: \"slightly promising\"\n\n  - headline: \"Improper Neutralization of Input During Web Page Generation\"\n    analysis: |\n      The HTML page at `www/anleitung.html` shows contents dynamically based on user interactions or predefined variables, with generated elements potentially being susceptible to cross-site scripting (XSS) if user-provided data isn't properly sanitized.\n    cwe: CWE-79\n    function_sell: []\n    filenames:\n      - www/anleitung.html\n    classification: \"not promising\"\n\n  - headline: \"Exposure of Sensitive Email Configuration Data\"\n    analysis: |\n      Email configurations, including plaintext SMTP server details and login credentials in email.js, are vulnerable to exposure through improper handling or if debug endpoints (like save.cgi or testmail.cgi) are misconfigured or unconstrained.\n    cwe: CWE-200\n    function_names:\n      - Account.apply\n    filenames:\n      - email.js\n    classification: \"very promising\"\n\n  - headline: \"Improper Access Control for Email Handler Scripts\"\n    analysis: |\n      The CGI scripts within the email system `save.cgi`, `testmail.cgi`, accessible through POST or GET requests, could be exploited to send emails or modify configurations if access control is not properly enforced.\n    cwe: CWE-284\n    function_names: []\n    filenames:\n      - save.cgi\n      - testmail.cgi\n    classification: \"very promising\"\n\n  - headline: \"Use of Hard-coded Credentials in Web Application\"\n    analysis: |\n      If `email.js` JavaScript file uses potentially hard-coded credentials or tokens in AJAX post requests for authenticating or authorizing actions, this could allow attackers to reuse these credentials if they are intercepted or leaked through XSS vulnerabilities or other methods.\n    cwe: CWE-798\n    function_names:\n      - Account.apply\n    filenames:\n      - email.js\n    inst: \"slightly promising\"\n```",
      "date": "2024-06-12T19:36:54.288210",
      "usage": {
        "prompt_tokens": 11693,
        "completion_tokens": 818,
        "cost": 0.14147
      }
    }
  ],
  "leads": [
    {
      "headline": "Insecure Use of Shell Commands",
      "analysis": "The script generate_img.sh uses shell commands to copy configuration and other sensitive files to a temporary directory for archiving. This could lead to command injection if unsanitized inputs are added into the shell-command formation. The design uses fixed commands but may not handle unexpected input changes securely.\n",
      "classification": "very promising",
      "cwe": "CWE-78",
      "function_names": [],
      "filenames": [
        "generate_img.sh"
      ]
    },
    {
      "headline": "Exposure of Sensitive Information in Log Files",
      "analysis": "The script generate_img.sh copies sensitive configuration files (account.conf, msmtp.conf) into a temporary directory and eventually into a tar archive. If these log files are accessible by unauthorized users, it would be a severe security risk as they potentially contain sensitive information, including configuration details and credentials.\n",
      "classification": "very promising",
      "cwe": "CWE-532",
      "function_names": [],
      "filenames": [
        "generate_img.sh"
      ]
    },
    {
      "headline": "Hard-coded Command Execution in TCL Script",
      "analysis": "The TCL script in userscript.tcl involves hard-coded command execution paths which could potentially be manipulated to execute arbitrary commands, particularly if user input affects command execution paths or parameters indirectly. Though not directly from the user inputs seen in the script, the environment or extended TCL scripts could influence these behaviors.\n",
      "classification": "slightly promising",
      "cwe": "CWE-78",
      "function_names": [],
      "filenames": [
        "userscript.tcl"
      ]
    },
    {
      "headline": "Use of Insecure TCL Load Operation",
      "analysis": "The use of load tclrega.so within userscript.tcl combined with the way variables are handled and executed could potentially expose the system to arbitrary code execution if the tclrega.so module or the registry objects being accessed are compromised or mishandled.\n",
      "classification": "slightly promising",
      "cwe": "CWE-94",
      "function_names": [],
      "filenames": [
        "userscript.tcl"
      ]
    },
    {
      "headline": "Improper Neutralization of Input During Web Page Generation",
      "analysis": "The HTML page at www/anleitung.html shows contents dynamically based on user interactions or predefined variables, with generated elements potentially being susceptible to cross-site scripting (XSS) if user-provided data isn't properly sanitized.\n",
      "classification": "not promising",
      "cwe": "CWE-79",
      "function_names": [],
      "filenames": [
        "www/anleitung.html"
      ]
    },
    {
      "headline": "Exposure of Sensitive Email Configuration Data",
      "analysis": "Email configurations, including plaintext SMTP server details and login credentials in email.js, are vulnerable to exposure through improper handling or if debug endpoints (like save.cgi or testmail.cgi) are misconfigured or unconstrained.\n",
      "classification": "very promising",
      "cwe": "CWE-200",
      "function_names": [
        "Account.apply"
      ],
      "filenames": [
        "email.js"
      ]
    },
    {
      "headline": "Improper Access Control for Email Handler Scripts",
      "analysis": "The CGI scripts within the email system save.cgi, testmail.cgi, accessible through POST or GET requests, could be exploited to send emails or modify configurations if access control is not properly enforced.\n",
      "classification": "very promising",
      "cwe": "CWE-284",
      "function_names": [],
      "filenames": [
        "save.cgi",
        "testmail.cgi"
      ]
    }
  ],
  "scores": [
    {
      "stats": {
        "fn": 0,
        "tp": 1,
        "fp": 3
      },
      "mapping": {
        "3": "CVE-2019-18938"
      },
      "vuln_dates": {
        "CVE-2019-18938": "2019-11-14T19:15:13"
      },
      "scoring_model": "claude-3-opus-20240229",
      "type": "llm",
      "instruction_template_hash": "245ace12b6361954d0a2"
    }
  ],
  "instruction_template_hash": "10c0163db4740318a544",
  "version": "0.1.0"
}
