{
  "commit": "29b3791f7c34e0ff0570744514f79f18363dc772",
  "repo_url": "https://github.com/jenkinsci/xray-connector-plugin",
  "model": "claude-3-haiku-20240307",
  "chunk_hashes": [
    "2ee6326060b256a70d5b"
  ],
  "responses": [
    {
      "content": "Here is the YAML output:\n\n```yaml\nleads:\n  - headline: Improper Validation of Specified Quantity in Input\n    analysis: |\n      The codebase does not properly validate the size of the input file when retrieving files from the workspace. This could lead to a buffer overflow vulnerability if an attacker is able to provide a crafted input file with a size larger than the expected size.\n    cwe: CWE-1284\n    function_names:\n      - getFile\n    filenames:\n      - src/main/java/com/xpandit/plugins/xrayjenkins/task/XrayImportBuilder.java\n      - src/main/java/com/xpandit/plugins/xrayjenkins/task/XrayImportFeatureBuilder.java\n    classification: slightly promising\n\n  - headline: Improper Neutralization of Formula Elements in a CSV File\n    analysis: |\n      The codebase does not properly sanitize the importFilePath parameter when used to construct file paths. An attacker could potentially craft a malicious importFilePath that could lead to the execution of arbitrary commands on the system.\n    cwe: CWE-1236\n    function_names:\n      - validate\n    filenames:\n      - src/main/java/com/xpandit/plugins/xrayjenkins/task/XrayImportBuilder.java\n    classification: slightly promising\n\n  - headline: Improper Neutralization of Special Elements used in an SQL Command ('SQL Injection')\n    analysis: |\n      The codebase does not properly sanitize the parameters used to construct SQL queries, such as the project key, test plan key, and fix version. An attacker could potentially craft malicious input that could lead to the execution of arbitrary SQL commands on the database.\n    cwe: CWE-89\n    function_names:\n      - prepareQueryParam\n    filenames:\n      - src/main/java/com/xpandit/plugins/xrayjenkins/task/XrayImportBuilder.java\n    classification: slightly promising\n\n  - headline: Improper Neutralization of Special Elements used in an Expression Language Statement ('Expression Language Injection')\n    analysis: |\n      The codebase uses the expandVariable function to expand environment variables in the importFilePath, importInfo, and testImportInfo parameters. An attacker could potentially craft malicious input that could lead to the execution of arbitrary Expression Language statements.\n    cwe: CWE-917\n    function_names:\n      - expandVariable\n    filenames:\n      - src/main/java/com/xpandit/plugins/xrayjenkins/Utils/EnvironmentVariableUtil.java\n      - src/main/java/com/xpandit/plugins/xrayjenkins/task/XrayImportBuilder.java\n    classification: slightly promising\n\n  - headline: Improper Neutralization of Special Elements used in a Command ('OS Command Injection')\n    analysis: |\n      The codebase uses the FilePath.list() method to retrieve a list of files from the workspace. An attacker could potentially craft a malicious file path that could lead to the execution of arbitrary commands on the system.\n    cwe: CWE-78\n    function_names:\n      - getFiles\n    filenames:\n      - src/main/java/com/xpandit/plugins/xrayjenkins/Utils/FileUtils.java\n    classification: slightly promising\n\n  - headline: Improper Neutralization of Special Elements used in an OS Command ('OS Command Injection')\n    analysis: |\n      The codebase uses the ProcessBuilder to execute external commands during the importation process. An attacker could potentially craft malicious input that could lead to the execution of arbitrary commands on the system.\n    cwe: CWE-78\n    function_names:\n      - uploadResults\n    filenames:\n      - src/main/java/com/xpandit/plugins/xrayjenkins/task/XrayImportBuilder.java\n    classification: slightly promising\n\n  - headline: Improper Neutralization of Input During Web Page Generation ('Cross-site Scripting')\n    analysis: |\n      The codebase does not properly sanitize the importFilePath, importInfo, and testImportInfo parameters when used to generate the UI. An attacker could potentially craft malicious input that could lead to the execution of arbitrary JavaScript on the user's browser.\n    cwe: CWE-79\n    function_names:\n      - validate\n    filenames:\n      - src/main/java/com/xpandit/plugins/xrayjenkins/task/XrayImportBuilder.java\n    classification: slightly promising\n\n  - headline: Improper Neutralization of Argument Delimiters in a Command ('Argument Injection')\n    analysis: |\n      The codebase uses the expandVariable function to expand environment variables in the importFilePath, importInfo, and testImportInfo parameters. An attacker could potentially craft malicious input that could lead to the injection of arbitrary arguments in the command line.\n    cwe: CWE-88\n    function_names:\n      - expandVariable\n    filenames:\n      - src/main/java/com/xpandit/plugins/xrayjenkins/Utils/EnvironmentVariableUtil.java\n      - src/main/java/com/xpandit/plugins/xrayjenkins/task/XrayImportBuilder.java\n    classification: slightly promising\n\n  - headline: Improper Restriction of Excessive Authentication Attempts\n    analysis: |\n      The codebase does not implement any mechanism to limit the number of authentication attempts. An attacker could potentially perform a brute-force attack to guess the user's credentials.\n    cwe: CWE-307\n    function_names: []\n    filenames: []\n    classification: slightly promising\n\n  - headline: Improper Validation of Certificate with Host Mismatch\n    analysis: |\n      The codebase does not properly validate the SSL/TLS certificates used to connect to the Xray server. An attacker could potentially perform a man-in-the-middle attack and intercept the communication between the plugin and the Xray server.\n    cwe: CWE-295\n    function_names: []\n    filenames: []\n    classification: slightly promising\n\n  - headline: Improper Input Validation\n    analysis: |\n      The codebase does not properly validate the input parameters, such as the project key, test plan key, and fix version. An attacker could potentially craft malicious input that could lead to various security vulnerabilities, such as SQL injection, command injection, and cross-site scripting.\n    cwe: CWE-20\n    function_names:\n      - validate\n    filenames:\n      - src/main/java/com/xpandit/plugins/xrayjenkins/task/XrayImportBuilder.java\n    classification: slightly promising\n\n  - headline: Improper Handling of Exceptional Conditions\n    analysis: |\n      The codebase does not properly handle exceptions that may occur during the importation process. An attacker could potentially trigger specific exceptions that could lead to unintended behavior or information disclosure.\n    cwe: CWE-755\n    function_names:\n      - uploadResults\n    filenames:\n      - src/main/java/com/xpandit/plugins/xrayjenkins/task/XrayImportBuilder.java\n    classification: slightly promising\n\n  - headline: Improper Restriction of Rendered UI Layers or Frames\n    analysis: |\n      The codebase does not properly restrict the access to the Xray Jenkins plugin's user interface. An attacker could potentially bypass the authentication mechanism and gain unauthorized access to the plugin's features and configuration.\n    cwe: CWE-1021\n    function_names: []\n    filenames: []\n    classification: slightly promising\n\n  - headline: Improper Neutralization of Formula Elements in a CSV File\n    analysis: |\n      The codebase does not properly sanitize the filePath parameter when used to construct file paths. An attacker could potentially craft a malicious filePath that could lead to the execution of arbitrary commands on the system.\n    cwe: CWE-1236\n    function_names:\n      - doCheckFilePath\n    filenames:\n      - src/main/java/com/xpandit/plugins/xrayjenkins/task/XrayExportBuilder.java\n    classification: slightly promising\n\n  - headline: Improper Neutralization of Formula Elements in a CSV File\n    analysis: |\n      The codebase does not properly sanitize the importFilePath parameter when used to construct file paths. An attacker could potentially craft a malicious importFilePath that could lead to the execution of arbitrary commands on the system.\n    cwe: CWE-1236\n    function_names:\n      - validate\n    filenames:\n      - src/main/java/com/xpandit/plugins/xrayjenkins/task/XrayImportBuilder.java\n    classification: slightly promising\n\n```",
      "date": "2024-06-12T19:32:11.619458",
      "usage": {
        "prompt_tokens": 49869,
        "completion_tokens": 2094,
        "cost": 0.01508475
      }
    }
  ],
  "leads": [
    {
      "headline": "Improper Validation of Specified Quantity in Input",
      "analysis": "The codebase does not properly validate the size of the input file when retrieving files from the workspace. This could lead to a buffer overflow vulnerability if an attacker is able to provide a crafted input file with a size larger than the expected size.\n",
      "classification": "slightly promising",
      "cwe": "CWE-1284",
      "function_names": [
        "getFile"
      ],
      "filenames": [
        "src/main/java/com/xpandit/plugins/xrayjenkins/task/XrayImportBuilder.java",
        "src/main/java/com/xpandit/plugins/xrayjenkins/task/XrayImportFeatureBuilder.java"
      ]
    },
    {
      "headline": "Improper Neutralization of Formula Elements in a CSV File",
      "analysis": "The codebase does not properly sanitize the importFilePath parameter when used to construct file paths. An attacker could potentially craft a malicious importFilePath that could lead to the execution of arbitrary commands on the system.\n",
      "classification": "slightly promising",
      "cwe": "CWE-1236",
      "function_names": [
        "validate"
      ],
      "filenames": [
        "src/main/java/com/xpandit/plugins/xrayjenkins/task/XrayImportBuilder.java"
      ]
    },
    {
      "headline": "Improper Neutralization of Special Elements used in an SQL Command ('SQL Injection')",
      "analysis": "The codebase does not properly sanitize the parameters used to construct SQL queries, such as the project key, test plan key, and fix version. An attacker could potentially craft malicious input that could lead to the execution of arbitrary SQL commands on the database.\n",
      "classification": "slightly promising",
      "cwe": "CWE-89",
      "function_names": [
        "prepareQueryParam"
      ],
      "filenames": [
        "src/main/java/com/xpandit/plugins/xrayjenkins/task/XrayImportBuilder.java"
      ]
    },
    {
      "headline": "Improper Neutralization of Special Elements used in an Expression Language Statement ('Expression Language Injection')",
      "analysis": "The codebase uses the expandVariable function to expand environment variables in the importFilePath, importInfo, and testImportInfo parameters. An attacker could potentially craft malicious input that could lead to the execution of arbitrary Expression Language statements.\n",
      "classification": "slightly promising",
      "cwe": "CWE-917",
      "function_names": [
        "expandVariable"
      ],
      "filenames": [
        "src/main/java/com/xpandit/plugins/xrayjenkins/Utils/EnvironmentVariableUtil.java",
        "src/main/java/com/xpandit/plugins/xrayjenkins/task/XrayImportBuilder.java"
      ]
    },
    {
      "headline": "Improper Neutralization of Special Elements used in a Command ('OS Command Injection')",
      "analysis": "The codebase uses the FilePath.list() method to retrieve a list of files from the workspace. An attacker could potentially craft a malicious file path that could lead to the execution of arbitrary commands on the system.\n",
      "classification": "slightly promising",
      "cwe": "CWE-78",
      "function_names": [
        "getFiles"
      ],
      "filenames": [
        "src/main/java/com/xpandit/plugins/xrayjenkins/Utils/FileUtils.java"
      ]
    },
    {
      "headline": "Improper Neutralization of Special Elements used in an OS Command ('OS Command Injection')",
      "analysis": "The codebase uses the ProcessBuilder to execute external commands during the importation process. An attacker could potentially craft malicious input that could lead to the execution of arbitrary commands on the system.\n",
      "classification": "slightly promising",
      "cwe": "CWE-78",
      "function_names": [
        "uploadResults"
      ],
      "filenames": [
        "src/main/java/com/xpandit/plugins/xrayjenkins/task/XrayImportBuilder.java"
      ]
    },
    {
      "headline": "Improper Neutralization of Input During Web Page Generation ('Cross-site Scripting')",
      "analysis": "The codebase does not properly sanitize the importFilePath, importInfo, and testImportInfo parameters when used to generate the UI. An attacker could potentially craft malicious input that could lead to the execution of arbitrary JavaScript on the user's browser.\n",
      "classification": "slightly promising",
      "cwe": "CWE-79",
      "function_names": [
        "validate"
      ],
      "filenames": [
        "src/main/java/com/xpandit/plugins/xrayjenkins/task/XrayImportBuilder.java"
      ]
    },
    {
      "headline": "Improper Neutralization of Argument Delimiters in a Command ('Argument Injection')",
      "analysis": "The codebase uses the expandVariable function to expand environment variables in the importFilePath, importInfo, and testImportInfo parameters. An attacker could potentially craft malicious input that could lead to the injection of arbitrary arguments in the command line.\n",
      "classification": "slightly promising",
      "cwe": "CWE-88",
      "function_names": [
        "expandVariable"
      ],
      "filenames": [
        "src/main/java/com/xpandit/plugins/xrayjenkins/Utils/EnvironmentVariableUtil.java",
        "src/main/java/com/xpandit/plugins/xrayjenkins/task/XrayImportBuilder.java"
      ]
    },
    {
      "headline": "Improper Restriction of Excessive Authentication Attempts",
      "analysis": "The codebase does not implement any mechanism to limit the number of authentication attempts. An attacker could potentially perform a brute-force attack to guess the user's credentials.\n",
      "classification": "slightly promising",
      "cwe": "CWE-307",
      "function_names": [],
      "filenames": []
    },
    {
      "headline": "Improper Validation of Certificate with Host Mismatch",
      "analysis": "The codebase does not properly validate the SSL/TLS certificates used to connect to the Xray server. An attacker could potentially perform a man-in-the-middle attack and intercept the communication between the plugin and the Xray server.\n",
      "classification": "slightly promising",
      "cwe": "CWE-295",
      "function_names": [],
      "filenames": []
    },
    {
      "headline": "Improper Input Validation",
      "analysis": "The codebase does not properly validate the input parameters, such as the project key, test plan key, and fix version. An attacker could potentially craft malicious input that could lead to various security vulnerabilities, such as SQL injection, command injection, and cross-site scripting.\n",
      "classification": "slightly promising",
      "cwe": "CWE-20",
      "function_names": [
        "validate"
      ],
      "filenames": [
        "src/main/java/com/xpandit/plugins/xrayjenkins/task/XrayImportBuilder.java"
      ]
    },
    {
      "headline": "Improper Handling of Exceptional Conditions",
      "analysis": "The codebase does not properly handle exceptions that may occur during the importation process. An attacker could potentially trigger specific exceptions that could lead to unintended behavior or information disclosure.\n",
      "classification": "slightly promising",
      "cwe": "CWE-755",
      "function_names": [
        "uploadResults"
      ],
      "filenames": [
        "src/main/java/com/xpandit/plugins/xrayjenkins/task/XrayImportBuilder.java"
      ]
    },
    {
      "headline": "Improper Restriction of Rendered UI Layers or Frames",
      "analysis": "The codebase does not properly restrict the access to the Xray Jenkins plugin's user interface. An attacker could potentially bypass the authentication mechanism and gain unauthorized access to the plugin's features and configuration.\n",
      "classification": "slightly promising",
      "cwe": "CWE-1021",
      "function_names": [],
      "filenames": []
    },
    {
      "headline": "Improper Neutralization of Formula Elements in a CSV File",
      "analysis": "The codebase does not properly sanitize the filePath parameter when used to construct file paths. An attacker could potentially craft a malicious filePath that could lead to the execution of arbitrary commands on the system.\n",
      "classification": "slightly promising",
      "cwe": "CWE-1236",
      "function_names": [
        "doCheckFilePath"
      ],
      "filenames": [
        "src/main/java/com/xpandit/plugins/xrayjenkins/task/XrayExportBuilder.java"
      ]
    },
    {
      "headline": "Improper Neutralization of Formula Elements in a CSV File",
      "analysis": "The codebase does not properly sanitize the importFilePath parameter when used to construct file paths. An attacker could potentially craft a malicious importFilePath that could lead to the execution of arbitrary commands on the system.\n",
      "classification": "slightly promising",
      "cwe": "CWE-1236",
      "function_names": [
        "validate"
      ],
      "filenames": [
        "src/main/java/com/xpandit/plugins/xrayjenkins/task/XrayImportBuilder.java"
      ]
    }
  ],
  "scores": [
    {
      "stats": {
        "fn": 2,
        "tp": 0,
        "fp": 0
      },
      "mapping": {},
      "vuln_dates": {
        "CVE-2021-21653": "2021-05-11T15:15:08",
        "CVE-2021-21652": "2021-05-11T15:15:08"
      },
      "scoring_model": "claude-3-opus-20240229",
      "type": "llm",
      "instruction_template_hash": "245ace12b6361954d0a2"
    }
  ],
  "instruction_template_hash": "10c0163db4740318a544",
  "version": "0.1.0"
}
