{
  "commit": "3b08ab1e7404dc00dfb3050d6f34821ae300b59c",
  "repo_url": "https://github.com/sindresorhus/file-type",
  "model": "gpt-4o-2024-05-13",
  "chunk_hashes": [
    "f7006f63078151916eb2"
  ],
  "responses": [
    {
      "content": "```yaml\nleads:\n  - headline: \"Potential Command Injection in 'util.js'\"\n    analysis: |\n      The `tarHeaderChecksumMatches` function parses potentially untrusted buffer data and subsequently uses this data in arithmetic operations and comparisons without sanitization. \n      \n      Such direct use of untrusted input might be exploited if an attacker can control the buffer content. Any buffer-related vulnerabilities or unchecked operations like the one at `buffer.toString` combined with `parseInt` for checksum calculation might be repurposed for command injection or even corrupting the memory since it involves parsing binary data into strings then computing hashes.\n    cwe: CWE-78\n    function_names:\n      - tarHeaderChecksumMatches\n    filenames:\n      - util.js\n    classification: slightly promising\n  - headline: \"Improper Input Validation in core.js\"\n    analysis: |\n      In the `core.js` file, the function `fromBuffer` does not validate the input type rigorously enough. The function `fromBuffer` is expected to accept a Buffer, Uint8Array, or ArrayBuffer, but the check does not consider modified or extended types that might subvert this through type coercion or Prototype Pollution. \n\n      This could lead to potentially malformed data being processed, which might be exploited to trigger further issues in downstream functions reading or manipulating the structure of these buffers.\n    cwe: CWE-20\n    function_names:\n      - fromBuffer\n    filenames:\n      - core.js\n    classification: slightly promising\n  - headline: \"Insecure Incomplete Data Deserialization in core.js\"\n    analysis: |\n      In the `core.js` function `_fromTokenizer`, tokens read from the tokenizer are directly used without additional validation. Specifically, reading file header elements such as PNGs could be altered to include malformed or malicious data segments leading check functions astray.\n\n      This can be especially dangerous since token-based parsing is common in various attack vectors like SQL injection, especially when the `tokenizer.readBuffer` function is involved in handling user-uploaded data.\n    cwe: CWE-502\n    function_names:\n      - _fromTokenizer\n    filenames:\n      - core.js\n    classification: very promising\n  - headline: \"Deserialization of Untrusted Data in index.js\"\n    analysis: |\n      The `fromFile` function in `index.js` potentially allows deserialization of untrusted data without sufficient validation. While the tokenizer approach enables efficient parsing, it does not inherently safeguard against manipulated data objects designed for exploitative purposes.\n\n      Given the reliance on the file format assumptions and the decode mechanisms employed, malicious actors can insert specially crafted file metadata leading to unexpected behaviors or runtime exceptions.\n    cwe: CWE-502\n    function_names:\n      - fromFile\n    filenames:\n      - index.js\n    classification: very promising\n  - headline: \"Improper Error Handling in test.js\"\n    analysis: |\n      The `test.js` file performs multiple file operations, including reading files and streams without adequately handling potential I/O exceptions. Functions like `fs.readFileSync` and `fs.createReadStream` are used extensively, assuming the presence and correctness of test files. \n\n      Neglecting appropriate catch mechanisms or fallback routines may cause the entire test suite to fail abruptly, exposing internal state details, useful to orchestrate Denial-of-Service (DoS) attacks or leakage of debugging information.\n    cwe: CWE-755\n    function_names:\n      - testFromFile\n      - testFromBuffer\n    filenames:\n      - test.js\n    classification: slightly promising\n```",
      "date": "2024-07-08T08:34:28.146541",
      "usage": {
        "prompt_tokens": 26073,
        "completion_tokens": 730,
        "cost": 0.141315
      }
    }
  ],
  "leads": [
    {
      "headline": "Potential Command Injection in 'util.js'",
      "analysis": "The tarHeaderChecksumMatches function parses potentially untrusted buffer data and subsequently uses this data in arithmetic operations and comparisons without sanitization. \n\nSuch direct use of untrusted input might be exploited if an attacker can control the buffer content. Any buffer-related vulnerabilities or unchecked operations like the one at buffer.toString combined with parseInt for checksum calculation might be repurposed for command injection or even corrupting the memory since it involves parsing binary data into strings then computing hashes.\n",
      "classification": "slightly promising",
      "cwe": "CWE-78",
      "function_names": [
        "tarHeaderChecksumMatches"
      ],
      "filenames": [
        "util.js"
      ]
    },
    {
      "headline": "Improper Input Validation in core.js",
      "analysis": "In the core.js file, the function fromBuffer does not validate the input type rigorously enough. The function fromBuffer is expected to accept a Buffer, Uint8Array, or ArrayBuffer, but the check does not consider modified or extended types that might subvert this through type coercion or Prototype Pollution. \n\nThis could lead to potentially malformed data being processed, which might be exploited to trigger further issues in downstream functions reading or manipulating the structure of these buffers.\n",
      "classification": "slightly promising",
      "cwe": "CWE-20",
      "function_names": [
        "fromBuffer"
      ],
      "filenames": [
        "core.js"
      ]
    },
    {
      "headline": "Insecure Incomplete Data Deserialization in core.js",
      "analysis": "In the core.js function _fromTokenizer, tokens read from the tokenizer are directly used without additional validation. Specifically, reading file header elements such as PNGs could be altered to include malformed or malicious data segments leading check functions astray.\n\nThis can be especially dangerous since token-based parsing is common in various attack vectors like SQL injection, especially when the tokenizer.readBuffer function is involved in handling user-uploaded data.\n",
      "classification": "very promising",
      "cwe": "CWE-502",
      "function_names": [
        "_fromTokenizer"
      ],
      "filenames": [
        "core.js"
      ]
    },
    {
      "headline": "Deserialization of Untrusted Data in index.js",
      "analysis": "The fromFile function in index.js potentially allows deserialization of untrusted data without sufficient validation. While the tokenizer approach enables efficient parsing, it does not inherently safeguard against manipulated data objects designed for exploitative purposes.\n\nGiven the reliance on the file format assumptions and the decode mechanisms employed, malicious actors can insert specially crafted file metadata leading to unexpected behaviors or runtime exceptions.\n",
      "classification": "very promising",
      "cwe": "CWE-502",
      "function_names": [
        "fromFile"
      ],
      "filenames": [
        "index.js"
      ]
    },
    {
      "headline": "Improper Error Handling in test.js",
      "analysis": "The test.js file performs multiple file operations, including reading files and streams without adequately handling potential I/O exceptions. Functions like fs.readFileSync and fs.createReadStream are used extensively, assuming the presence and correctness of test files. \n\nNeglecting appropriate catch mechanisms or fallback routines may cause the entire test suite to fail abruptly, exposing internal state details, useful to orchestrate Denial-of-Service (DoS) attacks or leakage of debugging information.\n",
      "classification": "slightly promising",
      "cwe": "CWE-755",
      "function_names": [
        "testFromFile",
        "testFromBuffer"
      ],
      "filenames": [
        "test.js"
      ]
    }
  ],
  "scores": [
    {
      "stats": {
        "fn": 1,
        "tp": 0,
        "fp": 2
      },
      "mapping": {},
      "vuln_dates": {
        "CVE-2022-36313": "2022-07-21T16:15:09"
      },
      "scoring_model": "claude-3-5-sonnet-20240620",
      "type": "llm",
      "instruction_template_hash": "245ace12b6361954d0a2"
    }
  ],
  "instruction_template_hash": "10c0163db4740318a544",
  "version": "0.1.0"
}
