{
  "commit": "2b536fa46428bc7929aec8cb789f544337375593",
  "repo_url": "https://github.com/jettison-json/jettison",
  "model": "gpt-4o-2024-05-13",
  "chunk_hashes": [
    "0d29a4b7408ce5aac947"
  ],
  "responses": [
    {
      "content": "```yaml\nleads:\n  - headline: \"Improper XML Handling - External Entity Injection\"\n    analysis: |\n      The code uses XML parsers without proper configuration to prevent XML External Entity (XXE) attacks. Specifically, the DocumentBuilderFactory is not configured to disable entity resolution, making the application vulnerable to XXE if it processes untrusted XML input.\n    cwe: CWE-611\n    function_names: []\n    filenames:\n      - src/test/java/org/codehaus/jettison/DOMTest.java\n      - src/test/java/org/codehaus/jettison/badgerfish/BadgerFishDOMTest.java\n      - src/test/java/org/codehaus/jettison/badgerfish/BadgerFishXMLStreamReaderTest.java\n    classification: very promising\n\n  - headline: \"Improper Handling of Null Values\"\n    analysis: |\n      There are several instances where the code checks for or processes null values inappropriately. For instance, methods like `getString` in the `JSONObject` class convert explicit nulls into the string \"null\", which can lead to unexpected behavior and potential security vulnerabilities if untrusted JSON data is processed.\n    cwe: CWE-476\n    function_names: []\n    filenames:\n      - src/main/java/org/codehaus/jettison/json/JSONObject.java\n      - src/test/java/org/codehaus/jettison/json/JSONObjectTest.java\n      - src/test/java/org/codehaus/jettison/mapped/MappedXMLInputFactoryTest.java\n    classification: slightly promising\n\n  - headline: \"Improper Exception Handling\"\n    analysis: |\n      The codebase contains multiple instances of swallowing generic exceptions (e.g., `Exception`, `IOException`). This practice can mask the root cause of errors and make it more difficult to diagnose security issues. Specific exceptions should be caught and handled appropriately to ensure the application behaves securely.\n    cwe: CWE-397\n    function_names: []\n    filenames:\n      - src/main/java/org/codehaus/jettison/mapped/MappedXMLStreamWriter.java\n      - src/main/java/org/codehaus/jettison/mapped/SimpleConverter.java\n      - src/main/java/org/codehaus/jettison/json/JSONException.java\n    classification: slightly promising\n\n  - headline: \"Improper Type Handling - Mixed Content\"\n    analysis: |\n      The MappedXMLStreamReader uses a valueKey of \"$\" to handle mixed content. This can introduce issues when documents have mixed text and child elements, potentially leading to data loss or incorrect interpretation. Proper handling of mixed content should be ensured.\n    cwe: CWE-116\n    function_names: []\n    filenames:\n      - src/main/java/org/codehaus/jettison/mapped/MappedXMLStreamReader.java\n      - src/test/java/org/codehaus/jettison/mapped/MappedXMLStreamReaderTest.java\n    classification: slightly promising\n\n  - headline: \"Potential Resource Handling Issues\"\n    analysis: |\n      The code opens resources (e.g., streams and readers) without always properly ensuring they are closed. This can lead to resource leaks, which may be leveraged for Denial of Service (DoS) attacks.\n    cwe: CWE-404\n    function_names: []\n    filenames:\n      - src/main/java/org/codehaus/jettison/AbstractDOMDocumentParser.java\n      - src/main/java/org/codehaus/jettison/AbstractXMLOutputFactory.java\n      - src/test/java/org/codehaus/jettison/badgerfish/RoundTripTest.java\n    classification: slightly promising\n\n  - headline: \"Potential JSON Injection Risk\"\n    analysis: |\n      The code constructs JSON objects from strings without properly sanitizing the input. This can lead to injection vulnerabilities if user-controlled input is directly included in the constructed JSON objects.\n    cwe: CWE-94\n    function_names: []\n    filenames:\n      - src/main/java/org/codehaus/jettison/json/JSONObject.java\n      - src/test/java/org/codehaus/jettison/json/JSONObjectTest.java\n      - src/test/java/org/codehaus/jettison/mapped/MappedXMLStreamReaderTest.java\n    classification: slightly promising\n```",
      "date": "2024-06-12T19:37:55.112928",
      "usage": {
        "prompt_tokens": 90006,
        "completion_tokens": 851,
        "cost": 0.462795
      }
    }
  ],
  "leads": [
    {
      "headline": "Improper XML Handling - External Entity Injection",
      "analysis": "The code uses XML parsers without proper configuration to prevent XML External Entity (XXE) attacks. Specifically, the DocumentBuilderFactory is not configured to disable entity resolution, making the application vulnerable to XXE if it processes untrusted XML input.\n",
      "classification": "very promising",
      "cwe": "CWE-611",
      "function_names": [],
      "filenames": [
        "src/test/java/org/codehaus/jettison/DOMTest.java",
        "src/test/java/org/codehaus/jettison/badgerfish/BadgerFishDOMTest.java",
        "src/test/java/org/codehaus/jettison/badgerfish/BadgerFishXMLStreamReaderTest.java"
      ]
    },
    {
      "headline": "Improper Handling of Null Values",
      "analysis": "There are several instances where the code checks for or processes null values inappropriately. For instance, methods like getString in the JSONObject class convert explicit nulls into the string \"null\", which can lead to unexpected behavior and potential security vulnerabilities if untrusted JSON data is processed.\n",
      "classification": "slightly promising",
      "cwe": "CWE-476",
      "function_names": [],
      "filenames": [
        "src/main/java/org/codehaus/jettison/json/JSONObject.java",
        "src/test/java/org/codehaus/jettison/json/JSONObjectTest.java",
        "src/test/java/org/codehaus/jettison/mapped/MappedXMLInputFactoryTest.java"
      ]
    },
    {
      "headline": "Improper Exception Handling",
      "analysis": "The codebase contains multiple instances of swallowing generic exceptions (e.g., Exception, IOException). This practice can mask the root cause of errors and make it more difficult to diagnose security issues. Specific exceptions should be caught and handled appropriately to ensure the application behaves securely.\n",
      "classification": "slightly promising",
      "cwe": "CWE-397",
      "function_names": [],
      "filenames": [
        "src/main/java/org/codehaus/jettison/mapped/MappedXMLStreamWriter.java",
        "src/main/java/org/codehaus/jettison/mapped/SimpleConverter.java",
        "src/main/java/org/codehaus/jettison/json/JSONException.java"
      ]
    },
    {
      "headline": "Improper Type Handling - Mixed Content",
      "analysis": "The MappedXMLStreamReader uses a valueKey of \"$\" to handle mixed content. This can introduce issues when documents have mixed text and child elements, potentially leading to data loss or incorrect interpretation. Proper handling of mixed content should be ensured.\n",
      "classification": "slightly promising",
      "cwe": "CWE-116",
      "function_names": [],
      "filenames": [
        "src/main/java/org/codehaus/jettison/mapped/MappedXMLStreamReader.java",
        "src/test/java/org/codehaus/jettison/mapped/MappedXMLStreamReaderTest.java"
      ]
    },
    {
      "headline": "Potential Resource Handling Issues",
      "analysis": "The code opens resources (e.g., streams and readers) without always properly ensuring they are closed. This can lead to resource leaks, which may be leveraged for Denial of Service (DoS) attacks.\n",
      "classification": "slightly promising",
      "cwe": "CWE-404",
      "function_names": [],
      "filenames": [
        "src/main/java/org/codehaus/jettison/AbstractDOMDocumentParser.java",
        "src/main/java/org/codehaus/jettison/AbstractXMLOutputFactory.java",
        "src/test/java/org/codehaus/jettison/badgerfish/RoundTripTest.java"
      ]
    },
    {
      "headline": "Potential JSON Injection Risk",
      "analysis": "The code constructs JSON objects from strings without properly sanitizing the input. This can lead to injection vulnerabilities if user-controlled input is directly included in the constructed JSON objects.\n",
      "classification": "slightly promising",
      "cwe": "CWE-94",
      "function_names": [],
      "filenames": [
        "src/main/java/org/codehaus/jettison/json/JSONObject.java",
        "src/test/java/org/codehaus/jettison/json/JSONObjectTest.java",
        "src/test/java/org/codehaus/jettison/mapped/MappedXMLStreamReaderTest.java"
      ]
    }
  ],
  "scores": [
    {
      "stats": {
        "fn": 5,
        "tp": 0,
        "fp": 1
      },
      "mapping": {},
      "vuln_dates": {
        "CVE-2023-1436": "2023-03-22T06:15:09",
        "CVE-2022-45693": "2022-12-13T15:15:11",
        "CVE-2022-45685": "2022-12-13T15:15:11",
        "CVE-2022-40149": "2022-09-16T10:15:09",
        "CVE-2022-40150": "2022-09-16T10:15:09"
      },
      "scoring_model": "claude-3-opus-20240229",
      "type": "llm",
      "instruction_template_hash": "245ace12b6361954d0a2"
    }
  ],
  "instruction_template_hash": "10c0163db4740318a544",
  "version": "0.1.0"
}
