{
  "commit": "2212d4aaa50191daf1b7b14591d3abdc00c218fa",
  "repo_url": "https://github.com/smallrye/smallrye-config",
  "model": "claude-3-haiku-20240307",
  "chunk_hashes": [
    "de3b58fb6c17879fee5a"
  ],
  "responses": [
    {
      "content": "Here is the YAML output for the provided codebase:\n\n```yaml\nleads:\n  - headline: Improper Input Validation\n    analysis: |\n      The codebase contains multiple instances of improper input validation, which could lead to various security vulnerabilities such as buffer overflow, integer overflow, and injection attacks.\n    cwe: CWE-20\n    function_names:\n      - getValue\n      - convert\n      - detectChangesAndFire\n    filenames:\n      - sources/implementation/src/main/java/io/smallrye/config/SmallRyeConfig.java\n      - sources/implementation/src/main/java/io/smallrye/config/PropertiesConfigSource.java\n      - sources/implementation/src/main/java/io/smallrye/config/ChangeEventNotifier.java\n    classification: very promising\n\n  - headline: Improper Neutralization of Special Elements used in an Expression Language Statement ('Expression Language Injection')\n    analysis: |\n      The codebase uses JSON objects and arrays, which could be vulnerable to injection attacks if the input is not properly validated and neutralized.\n    cwe: CWE-917\n    function_names:\n      - convert\n    filenames:\n      - converters/json/src/main/java/io/smallrye/config/converter/json/JsonArrayConverter.java\n      - converters/json/src/main/java/io/smallrye/config/converter/json/JsonObjectConverter.java\n    classification: slightly promising\n\n  - headline: Improper Neutralization of Special Elements used in an OS Command ('OS Command Injection')\n    analysis: |\n      The codebase uses the System.getenv() method to retrieve environment variables, which could be vulnerable to command injection attacks if the input is not properly validated and neutralized.\n    cwe: CWE-78\n    function_names:\n      - getValue\n    filenames:\n      - sources/implementation/src/main/java/io/smallrye/config/EnvConfigSource.java\n    classification: slightly promising\n\n  - headline: Improper Initialization\n    analysis: |\n      The codebase initializes several objects and resources, such as the ConfigSourceMap and the ChangeEventNotifier, which could be vulnerable to improper initialization if the input is not properly validated and neutralized.\n    cwe: CWE-665\n    function_names:\n      - init\n    filenames:\n      - utils/cdi-provider/src/main/java/io/smallrye/config/util/injection/ConfigSourceProvider.java\n      - utils/events/src/main/java/io/smallrye/config/events/ChangeEventNotifier.java\n    classification: slightly promising\n\n  - headline: Improper Restriction of XML External Entity Reference\n    analysis: |\n      The codebase uses the JSON-P library to parse JSON strings, which could be vulnerable to XML External Entity (XXE) attacks if the input is not properly validated and neutralized.\n    cwe: CWE-611\n    function_names:\n      - convert\n    filenames:\n      - converters/json/src/main/java/io/smallrye/config/converter/json/JsonArrayConverter.java\n      - converters/json/src/main/java/io/smallrye/config/converter/json/JsonObjectConverter.java\n    classification: slightly promising\n\n  - headline: Improper Handling of Exceptional Conditions\n    analysis: |\n      The codebase handles various exceptions, such as NoSuchElementException and IllegalArgumentException, which could lead to unexpected behavior or information disclosure if not properly handled.\n    cwe: CWE-755\n    function_names:\n      - getValue\n      - convert\n    filenames:\n      - sources/implementation/src/main/java/io/smallrye/config/SmallRyeConfig.java\n      - sources/implementation/src/main/java/io/smallrye/config/Converters.java\n    classification: slightly promising\n\n  - headline: Incorrect Calculation of Buffer Size\n    analysis: |\n      The codebase uses various string manipulation and array manipulation functions, which could be vulnerable to buffer overflow attacks if the input is not properly validated and the buffer size is not correctly calculated.\n    cwe: CWE-131\n    function_names:\n      - copy\n      - convert\n    filenames:\n      - sources/implementation/src/main/java/io/smallrye/config/Converters.java\n    classification: slightly promising\n```",
      "date": "2024-06-13T11:48:53.000159",
      "usage": {
        "prompt_tokens": 83845,
        "completion_tokens": 1056,
        "cost": 0.02228125
      }
    }
  ],
  "leads": [
    {
      "headline": "Improper Input Validation",
      "analysis": "The codebase contains multiple instances of improper input validation, which could lead to various security vulnerabilities such as buffer overflow, integer overflow, and injection attacks.\n",
      "classification": "very promising",
      "cwe": "CWE-20",
      "function_names": [
        "getValue",
        "convert",
        "detectChangesAndFire"
      ],
      "filenames": [
        "sources/implementation/src/main/java/io/smallrye/config/SmallRyeConfig.java",
        "sources/implementation/src/main/java/io/smallrye/config/PropertiesConfigSource.java",
        "sources/implementation/src/main/java/io/smallrye/config/ChangeEventNotifier.java"
      ]
    },
    {
      "headline": "Improper Neutralization of Special Elements used in an Expression Language Statement ('Expression Language Injection')",
      "analysis": "The codebase uses JSON objects and arrays, which could be vulnerable to injection attacks if the input is not properly validated and neutralized.\n",
      "classification": "slightly promising",
      "cwe": "CWE-917",
      "function_names": [
        "convert"
      ],
      "filenames": [
        "converters/json/src/main/java/io/smallrye/config/converter/json/JsonArrayConverter.java",
        "converters/json/src/main/java/io/smallrye/config/converter/json/JsonObjectConverter.java"
      ]
    },
    {
      "headline": "Improper Neutralization of Special Elements used in an OS Command ('OS Command Injection')",
      "analysis": "The codebase uses the System.getenv() method to retrieve environment variables, which could be vulnerable to command injection attacks if the input is not properly validated and neutralized.\n",
      "classification": "slightly promising",
      "cwe": "CWE-78",
      "function_names": [
        "getValue"
      ],
      "filenames": [
        "sources/implementation/src/main/java/io/smallrye/config/EnvConfigSource.java"
      ]
    },
    {
      "headline": "Improper Initialization",
      "analysis": "The codebase initializes several objects and resources, such as the ConfigSourceMap and the ChangeEventNotifier, which could be vulnerable to improper initialization if the input is not properly validated and neutralized.\n",
      "classification": "slightly promising",
      "cwe": "CWE-665",
      "function_names": [
        "init"
      ],
      "filenames": [
        "utils/cdi-provider/src/main/java/io/smallrye/config/util/injection/ConfigSourceProvider.java",
        "utils/events/src/main/java/io/smallrye/config/events/ChangeEventNotifier.java"
      ]
    },
    {
      "headline": "Improper Restriction of XML External Entity Reference",
      "analysis": "The codebase uses the JSON-P library to parse JSON strings, which could be vulnerable to XML External Entity (XXE) attacks if the input is not properly validated and neutralized.\n",
      "classification": "slightly promising",
      "cwe": "CWE-611",
      "function_names": [
        "convert"
      ],
      "filenames": [
        "converters/json/src/main/java/io/smallrye/config/converter/json/JsonArrayConverter.java",
        "converters/json/src/main/java/io/smallrye/config/converter/json/JsonObjectConverter.java"
      ]
    },
    {
      "headline": "Improper Handling of Exceptional Conditions",
      "analysis": "The codebase handles various exceptions, such as NoSuchElementException and IllegalArgumentException, which could lead to unexpected behavior or information disclosure if not properly handled.\n",
      "classification": "slightly promising",
      "cwe": "CWE-755",
      "function_names": [
        "getValue",
        "convert"
      ],
      "filenames": [
        "sources/implementation/src/main/java/io/smallrye/config/SmallRyeConfig.java",
        "sources/implementation/src/main/java/io/smallrye/config/Converters.java"
      ]
    },
    {
      "headline": "Incorrect Calculation of Buffer Size",
      "analysis": "The codebase uses various string manipulation and array manipulation functions, which could be vulnerable to buffer overflow attacks if the input is not properly validated and the buffer size is not correctly calculated.\n",
      "classification": "slightly promising",
      "cwe": "CWE-131",
      "function_names": [
        "copy",
        "convert"
      ],
      "filenames": [
        "sources/implementation/src/main/java/io/smallrye/config/Converters.java"
      ]
    }
  ],
  "scores": [
    {
      "stats": {
        "fn": 1,
        "tp": 0,
        "fp": 1
      },
      "mapping": {},
      "vuln_dates": {
        "CVE-2020-1729": "2021-05-28T14:15:07"
      },
      "scoring_model": "claude-3-opus-20240229",
      "type": "llm",
      "instruction_template_hash": "245ace12b6361954d0a2"
    },
    {
      "stats": {
        "fn": 1,
        "tp": 0,
        "fp": 1
      },
      "mapping": {},
      "vuln_dates": {
        "CVE-2020-1729": "2021-05-28T14:15:07"
      },
      "scoring_model": "claude-3-5-sonnet-20240620",
      "type": "llm",
      "instruction_template_hash": "245ace12b6361954d0a2"
    }
  ],
  "instruction_template_hash": "10c0163db4740318a544",
  "version": "0.1.0"
}
