{
  "commit": "6c57dea2d9beb1577ae4d80f6eaf03aad4ef3857",
  "repo_url": "https://github.com/tmccombs/tls-listener",
  "model": "gpt-4o-2024-05-13",
  "chunk_hashes": [
    "5b3813c68d4561a79848"
  ],
  "responses": [
    {
      "content": "```yaml\nleads:\n  - headline: Insecure SSL/TLS Settings\n    analysis: |\n      The TLS context is configured using `ssl.PROTOCOL_TLS_CLIENT`, which defaults to the latest protocol version. However, options like `ssl.OP_NO_TLSv1` or `ssl.OP_NO_TLSv1_1` are not set, potentially allowing insecure older versions of TLS if a downgrade attack occurs. This could enable an attacker to exploit vulnerabilities in older TLS versions.\n    cwe: CWE-326\n    function_names:\n      - tls_conn\n      - ExampleHttpsConnection.connect\n      - ExampleHttpsHandler.__init__\n    filenames:\n      - examples/test_examples.py\n    classification: very promising\n\n  - headline: Hardcoded Credentials\n    analysis: |\n      The `DOMAIN` and `HOST` variables are hardcoded, and if they represent sensitive environments, they might expose confidential information. Using hardcoded values for such credentials can lead to unauthorized access or leaked sensitive information.\n    cwe: CWE-798\n    function_names: []\n    filenames:\n      - examples/test_examples.py\n    classification: slightly promising\n\n  - headline: Potential Command Injection\n    analysis: |\n      The `subprocess.run` and `subprocess.Popen` methods are used to execute shell commands. While the current usage appears safe, dynamic or unvalidated input could lead to command injection vulnerabilities where an attacker might execute arbitrary commands.\n    cwe: CWE-78\n    function_names:\n      - build_examples\n      - run_example\n    filenames:\n      - examples/test_examples.py\n    classification: very promising\n\n  - headline: Leakage of File Descriptors\n    analysis: |\n      In the `run_example` context manager, the process is terminated but file descriptors might not be correctly handled in all cases, potentially leaking file descriptors. This can cause resource exhaustion or unintentional data exposure.\n    cwe: CWE-404\n    function_names:\n      - run_example\n    filenames:\n      - examples/test_examples.py\n    classification: slightly promising\n\n  - headline: Incomplete Error Handling\n    analysis: |\n      The code relies on direct assertions and subprocess return values without extensive exception handling. This can lead to unhandled exceptions and crashes, especially under unexpected conditions or malicious input.\n    cwe: CWE-754\n    function_names:\n      - echo_test\n      - http_test\n      - bad_connection_test\n    filenames:\n      - examples/test_examples.py\n    classification: not promising\n```",
      "date": "2024-06-09T15:10:02.190165",
      "usage": {
        "prompt_tokens": 3292,
        "completion_tokens": 508,
        "cost": 0.02408
      }
    }
  ],
  "leads": [
    {
      "headline": "Insecure SSL/TLS Settings",
      "analysis": "The TLS context is configured using ssl.PROTOCOL_TLS_CLIENT, which defaults to the latest protocol version. However, options like ssl.OP_NO_TLSv1 or ssl.OP_NO_TLSv1_1 are not set, potentially allowing insecure older versions of TLS if a downgrade attack occurs. This could enable an attacker to exploit vulnerabilities in older TLS versions.\n",
      "classification": "very promising",
      "cwe": "CWE-326",
      "function_names": [
        "tls_conn",
        "ExampleHttpsConnection.connect",
        "ExampleHttpsHandler.__init__"
      ],
      "filenames": [
        "examples/test_examples.py"
      ]
    },
    {
      "headline": "Hardcoded Credentials",
      "analysis": "The DOMAIN and HOST variables are hardcoded, and if they represent sensitive environments, they might expose confidential information. Using hardcoded values for such credentials can lead to unauthorized access or leaked sensitive information.\n",
      "classification": "slightly promising",
      "cwe": "CWE-798",
      "function_names": [],
      "filenames": [
        "examples/test_examples.py"
      ]
    },
    {
      "headline": "Potential Command Injection",
      "analysis": "The subprocess.run and subprocess.Popen methods are used to execute shell commands. While the current usage appears safe, dynamic or unvalidated input could lead to command injection vulnerabilities where an attacker might execute arbitrary commands.\n",
      "classification": "very promising",
      "cwe": "CWE-78",
      "function_names": [
        "build_examples",
        "run_example"
      ],
      "filenames": [
        "examples/test_examples.py"
      ]
    },
    {
      "headline": "Leakage of File Descriptors",
      "analysis": "In the run_example context manager, the process is terminated but file descriptors might not be correctly handled in all cases, potentially leaking file descriptors. This can cause resource exhaustion or unintentional data exposure.\n",
      "classification": "slightly promising",
      "cwe": "CWE-404",
      "function_names": [
        "run_example"
      ],
      "filenames": [
        "examples/test_examples.py"
      ]
    },
    {
      "headline": "Incomplete Error Handling",
      "analysis": "The code relies on direct assertions and subprocess return values without extensive exception handling. This can lead to unhandled exceptions and crashes, especially under unexpected conditions or malicious input.\n",
      "classification": "not promising",
      "cwe": "CWE-754",
      "function_names": [
        "echo_test",
        "http_test",
        "bad_connection_test"
      ],
      "filenames": [
        "examples/test_examples.py"
      ]
    }
  ],
  "scores": [
    {
      "stats": {
        "fn": 1,
        "tp": 0,
        "fp": 2
      },
      "mapping": {},
      "vuln_dates": {
        "CVE-2024-28854": "2024-03-15T19:15:07"
      },
      "scoring_model": "gpt-4o-2024-05-13",
      "type": "llm",
      "instruction_template_hash": "8998f09cf57fca8a6e03"
    }
  ],
  "instruction_template_hash": "10c0163db4740318a544",
  "version": "0.1.0"
}
