{
  "commit": "1115251555e88c9069027a63f5e38a377d5f1b89",
  "repo_url": "https://github.com/tinyproxy/tinyproxy",
  "model": "gpt-4-turbo-2024-04-09",
  "chunk_hashes": [
    "26fd6194d1af7bf58372"
  ],
  "responses": [
    {
      "content": "```yaml\nleads:\n  - headline: \"Use of Uninitialized Resource in buffer management.\"\n    analysis: |\n      A potential vulnerability exists in the `buffer.c` implementation where buffer operations might attempt to manage resources that have not been correctly initialized or have been left in an inconsistent state. This could occur when handling abrupt disconnections or unexpected data received over the network.\n    cwe: CWE-908\n    function_names:\n      - new_buffer\n      - delete_buffer\n      - add_to_buffer\n    filenames:\n      - src/buffer.c\n    classification: \"slightly promising\"\n\n  - headline: \"Inadequate Validation of Input in URL processing.\"\n    analysis: |\n      The function `process_request` in reqs.c does not sufficiently validate the URL input, which could be exploited to perform directory traversal or bypass security filters aimed to limit URL access based on path or protocol.\n    cwe: CWE-20\n    function_names:\n      - process_request\n    filenames:\n      - src/reqs.c\n    classification: \"very promising\"\n\n  - headline: \"Improper Handling of Exceptional Conditions (Error States).\"\n    analysis: |\n      When encountering issues like failure to bind a socket or to listen on a port, the application logs the error but does not effectively manage the progression of state afterward, potentially leaving the application in a non-secure or unpredictable state.\n    cwe: CWE-754\n    function_names:\n      - bind_socket\n      - listen_sock\n    filenames:\n      - src/sock.c\n    classification: \"slightly promising\"\n\n  - headline: \"Memory Leak Potential in Error Handling.\"\n    analysis: |\n      In the logging function (`write_message` in log.c), there's potential for a memory leak where allocated buffers may not be properly freed upon error conditions, leading to memory exhaustion.\n    cwe: CWE-401\n    function_names:\n      - write_message\n    filenames:\n      - src/log.c\n    classification: \"slightly promising\"\n\n  - headline: \"Lack of Resource Release on Error Path.\"\n    analysis: |\n      In the `establish_http_connection` function, there is a missing resource release (file descriptors, memory) on an error path which could lead to resource exhaustion.\n    cwe: CWE-404\n    function_names:\n      - establish_http_connection\n      - connect_to_upstream\n    filenames:\n      - src/reqs.c\n    classification: \"not promising\"\n\n  - headline: \"Race Condition in Logging Function.\"\n    analysis: |\n      The logger setup allows for a potential race condition where the log file could be manipulated between checking its state and opening it for writing, allowing an attacker to force the application to write logs to an unauthorized location.\n    cwe: CWE-367\n    function_names:\n      - setup_logging\n    filenames:\n      - src/log.c\n    classification: \"slightly promising\"\n```",
      "date": "2024-06-13T17:18:07.542887",
      "usage": {
        "prompt_tokens": 82026,
        "completion_tokens": 596,
        "cost": 0.83814
      }
    }
  ],
  "leads": [
    {
      "headline": "Use of Uninitialized Resource in buffer management.",
      "analysis": "A potential vulnerability exists in the buffer.c implementation where buffer operations might attempt to manage resources that have not been correctly initialized or have been left in an inconsistent state. This could occur when handling abrupt disconnections or unexpected data received over the network.\n",
      "classification": "slightly promising",
      "cwe": "CWE-908",
      "function_names": [
        "new_buffer",
        "delete_buffer",
        "add_to_buffer"
      ],
      "filenames": [
        "src/buffer.c"
      ]
    },
    {
      "headline": "Inadequate Validation of Input in URL processing.",
      "analysis": "The function process_request in reqs.c does not sufficiently validate the URL input, which could be exploited to perform directory traversal or bypass security filters aimed to limit URL access based on path or protocol.\n",
      "classification": "very promising",
      "cwe": "CWE-20",
      "function_names": [
        "process_request"
      ],
      "filenames": [
        "src/reqs.c"
      ]
    },
    {
      "headline": "Improper Handling of Exceptional Conditions (Error States).",
      "analysis": "When encountering issues like failure to bind a socket or to listen on a port, the application logs the error but does not effectively manage the progression of state afterward, potentially leaving the application in a non-secure or unpredictable state.\n",
      "classification": "slightly promising",
      "cwe": "CWE-754",
      "function_names": [
        "bind_socket",
        "listen_sock"
      ],
      "filenames": [
        "src/sock.c"
      ]
    },
    {
      "headline": "Memory Leak Potential in Error Handling.",
      "analysis": "In the logging function (write_message in log.c), there's potential for a memory leak where allocated buffers may not be properly freed upon error conditions, leading to memory exhaustion.\n",
      "classification": "slightly promising",
      "cwe": "CWE-401",
      "function_names": [
        "write_message"
      ],
      "filenames": [
        "src/log.c"
      ]
    },
    {
      "headline": "Lack of Resource Release on Error Path.",
      "analysis": "In the establish_http_connection function, there is a missing resource release (file descriptors, memory) on an error path which could lead to resource exhaustion.\n",
      "classification": "not promising",
      "cwe": "CWE-404",
      "function_names": [
        "establish_http_connection",
        "connect_to_upstream"
      ],
      "filenames": [
        "src/reqs.c"
      ]
    },
    {
      "headline": "Race Condition in Logging Function.",
      "analysis": "The logger setup allows for a potential race condition where the log file could be manipulated between checking its state and opening it for writing, allowing an attacker to force the application to write logs to an unauthorized location.\n",
      "classification": "slightly promising",
      "cwe": "CWE-367",
      "function_names": [
        "setup_logging"
      ],
      "filenames": [
        "src/log.c"
      ]
    }
  ],
  "scores": [
    {
      "stats": {
        "fn": 1,
        "tp": 0,
        "fp": 1
      },
      "mapping": {},
      "vuln_dates": {
        "CVE-2017-11747": "2017-07-30T16:29:00"
      },
      "scoring_model": "claude-3-opus-20240229",
      "type": "llm",
      "instruction_template_hash": "245ace12b6361954d0a2"
    }
  ],
  "instruction_template_hash": "10c0163db4740318a544",
  "version": "0.1.0"
}
