{
  "commit": "224cc6a28ddfcf4d1a184a25d10833cf153e3bda",
  "repo_url": "https://github.com/electron/packager",
  "model": "gpt-4o-2024-05-13",
  "chunk_hashes": [
    "96f81faedc910c4eed17"
  ],
  "responses": [
    {
      "content": "```yaml\nleads:\n  - headline: Insecure temp directory creation\n    analysis: |\n      The `packageUniversalMac` function creates a temporary directory with `fs.mkdtemp` but does not set restrictive permissions. This can potentially allow an attacker to access or manipulate files in the temporary directory.\n    cwe: CWE-379\n    function_names:\n      - packageUniversalMac\n    filenames:\n      - src/universal.ts\n    classification: slightly promising\n\n  - headline: Use of predictable temporary directory names\n    analysis: |\n      The function `testSymlink` creates a temporary directory with a predictable name (`symlink-test-${comboOpts.platform}-${comboOpts.arch}`) by using `fs.mkdtemp`. Predictable temporary directory names can lead to race conditions and potential data theft or manipulation.\n    cwe: CWE-377\n    function_names:\n      - testSymlink\n    filenames:\n      - src/packager.ts\n    classification: slightly promising\n\n  - headline: Failure to securely handle sensitive information in code signing\n    analysis: |\n      The code involves adding signing identities to the macOS keychain, which are handled in potentially insecure scripts without proper validation and handling. The script `import-testing-cert-ci.sh` imports keychain certificates and uses predefined passwords without any encryption or secure storage.\n    cwe: CWE-522\n    function_names: []\n    filenames:\n      - test/ci/codesign/import-testing-cert-ci.sh\n    classification: very promising\n\n  - headline: Command injection risk in certificate generation\n    analysis: |\n      The script `generate-identity.sh` uses `openssl` commands to generate certificates without sanitizing inputs. This can lead to command injection if any of the inputs are controlled by an attacker.\n    cwe: CWE-78\n    function_names: []\n    filenames:\n      - test/ci/codesign/generate-identity.sh\n    classification: very promising\n\n  - headline: Insecure handling of keys and certificates\n    analysis: |\n      The script `generate-identity.sh` imports private keys and certificates into the macOS keychain without ensuring that the environment is secure. This can lead to potential key and certificate exposure, especially in shared or less secure environments.\n    cwe: CWE-522\n    function_names: []\n    filenames:\n      - test/ci/codesign/generate-identity.sh\n    classification: very promising\n\n  - headline: Safe Code execution flag not used in package.json parsing\n    analysis: |\n      The `getMetadataFromPackageJSON` function uses an unchecked `require` to load the package.json file. This could be exploited by crafting a malicious package.json file that executes arbitrary code during the requiring process.\n    cwe: CWE-94\n    function_names:\n      - getMetadataFromPackageJSON\n    filenames:\n      - src/infer.ts\n    classification: slightly promising\n\n  - headline: Use of cryptographically weak random numbers\n    analysis: |\n      The `generateFinalBasename` function is meant to produce unique file names but does not ensure strong entropy. Using only hyphens and platform/architecture info may lead to predictable file names.\n    cwe: CWE-331\n    function_names:\n      - generateFinalBasename\n    filenames:\n      - src/common.ts\n    classification: slightly promising\n\n  - headline: External input not sanitized\n    analysis: |\n      The `parseArgs` function in `cli.ts` does not sanitize or validate the inputs before parsing them, leading to potential injection attacks and unexpected behavior if the untrusted input is received.\n    cwe: CWE-78\n    function_names:\n      - parseArgs\n    filenames:\n      - src/cli.ts\n    classification: very promising\n```",
      "date": "2024-06-09T11:39:06.752913",
      "usage": {
        "prompt_tokens": 53363,
        "completion_tokens": 768,
        "cost": 0.278335
      }
    }
  ],
  "leads": [
    {
      "headline": "Insecure temp directory creation",
      "analysis": "The packageUniversalMac function creates a temporary directory with fs.mkdtemp but does not set restrictive permissions. This can potentially allow an attacker to access or manipulate files in the temporary directory.\n",
      "classification": "slightly promising",
      "cwe": "CWE-379",
      "function_names": [
        "packageUniversalMac"
      ],
      "filenames": [
        "src/universal.ts"
      ]
    },
    {
      "headline": "Use of predictable temporary directory names",
      "analysis": "The function testSymlink creates a temporary directory with a predictable name (symlink-test-${comboOpts.platform}-${comboOpts.arch}) by using fs.mkdtemp. Predictable temporary directory names can lead to race conditions and potential data theft or manipulation.\n",
      "classification": "slightly promising",
      "cwe": "CWE-377",
      "function_names": [
        "testSymlink"
      ],
      "filenames": [
        "src/packager.ts"
      ]
    },
    {
      "headline": "Failure to securely handle sensitive information in code signing",
      "analysis": "The code involves adding signing identities to the macOS keychain, which are handled in potentially insecure scripts without proper validation and handling. The script import-testing-cert-ci.sh imports keychain certificates and uses predefined passwords without any encryption or secure storage.\n",
      "classification": "very promising",
      "cwe": "CWE-522",
      "function_names": [],
      "filenames": [
        "test/ci/codesign/import-testing-cert-ci.sh"
      ]
    },
    {
      "headline": "Command injection risk in certificate generation",
      "analysis": "The script generate-identity.sh uses openssl commands to generate certificates without sanitizing inputs. This can lead to command injection if any of the inputs are controlled by an attacker.\n",
      "classification": "very promising",
      "cwe": "CWE-78",
      "function_names": [],
      "filenames": [
        "test/ci/codesign/generate-identity.sh"
      ]
    },
    {
      "headline": "Insecure handling of keys and certificates",
      "analysis": "The script generate-identity.sh imports private keys and certificates into the macOS keychain without ensuring that the environment is secure. This can lead to potential key and certificate exposure, especially in shared or less secure environments.\n",
      "classification": "very promising",
      "cwe": "CWE-522",
      "function_names": [],
      "filenames": [
        "test/ci/codesign/generate-identity.sh"
      ]
    },
    {
      "headline": "Safe Code execution flag not used in package.json parsing",
      "analysis": "The getMetadataFromPackageJSON function uses an unchecked require to load the package.json file. This could be exploited by crafting a malicious package.json file that executes arbitrary code during the requiring process.\n",
      "classification": "slightly promising",
      "cwe": "CWE-94",
      "function_names": [
        "getMetadataFromPackageJSON"
      ],
      "filenames": [
        "src/infer.ts"
      ]
    },
    {
      "headline": "Use of cryptographically weak random numbers",
      "analysis": "The generateFinalBasename function is meant to produce unique file names but does not ensure strong entropy. Using only hyphens and platform/architecture info may lead to predictable file names.\n",
      "classification": "slightly promising",
      "cwe": "CWE-331",
      "function_names": [
        "generateFinalBasename"
      ],
      "filenames": [
        "src/common.ts"
      ]
    },
    {
      "headline": "External input not sanitized",
      "analysis": "The parseArgs function in cli.ts does not sanitize or validate the inputs before parsing them, leading to potential injection attacks and unexpected behavior if the untrusted input is received.\n",
      "classification": "very promising",
      "cwe": "CWE-78",
      "function_names": [
        "parseArgs"
      ],
      "filenames": [
        "src/cli.ts"
      ]
    }
  ],
  "scores": [
    {
      "stats": {
        "fn": 1,
        "tp": 0,
        "fp": 4
      },
      "mapping": {},
      "vuln_dates": {
        "CVE-2024-29900": "2024-03-29T16:15:08"
      },
      "scoring_model": "gpt-4o-2024-05-13",
      "type": "llm",
      "instruction_template_hash": "8998f09cf57fca8a6e03"
    }
  ],
  "instruction_template_hash": "10c0163db4740318a544",
  "version": "0.1.0"
}
