{
  "commit": "2d8b10e0ef35cddbc7607c46f2e9006a01e33b36",
  "repo_url": "https://github.com/jenkinsci/saltstack-plugin",
  "model": "claude-3-sonnet-20240229",
  "chunk_hashes": [
    "007e736542ccc3067654"
  ],
  "responses": [
    {
      "content": "```yaml\nleads:\n  - headline: Lack of input validation in Utils.validatePillar\n    analysis: |\n      The `Utils.validatePillar` method does not properly validate the input string before attempting to parse it as JSON. This could potentially lead to various types of injection vulnerabilities, depending on how the parsed JSON object is used within the application.\n    cwe: CWE-1284\n    function_names:\n      - Utils.validatePillar\n    filenames:\n      - src/main/java/com/waytta/Utils.java\n    classification: very promising\n      \n  - headline: Lack of output encoding in Utils.writeFile\n    analysis: |\n      The `Utils.writeFile` method writes the given string directly to a file without any encoding or sanitization. If the string contains user-supplied data or untrusted input, this could potentially lead to various types of injection vulnerabilities or data exposure.\n    cwe: CWE-838\n    function_names:\n      - Utils.writeFile\n    filenames:\n      - src/main/java/com/waytta/Utils.java\n    classification: very promising\n      \n  - headline: Use of user-supplied input in file paths\n    analysis: |\n      Several methods in the codebase accept user-supplied input (e.g., target, function, arguments) and use them to construct file paths or URLs without proper validation or sanitization. This could potentially lead to path traversal or other file system-related vulnerabilities.\n    cwe: CWE-22\n    function_names:\n      - HttpCallable.call\n      - SaltAPIBuilder.prepareSaltFunction\n    filenames:\n      - src/main/java/com/waytta/HttpCallable.java\n      - src/main/java/com/waytta/SaltAPIBuilder.java\n    classification: very promising\n      \n  - headline: Potential hardcoded credentials in test code\n    analysis: |\n      The `SaltAPIBuilderTest` class contains hardcoded credential values (e.g., usernames, passwords) used for testing purposes. While these values may be intended for testing only, hardcoded credentials in production code can lead to unauthorized access if discovered by an attacker.\n    cwe: CWE-798\n    function_names: []\n    filenames:\n      - src/test/java/com/waytta/SaltAPIBuilderTest.java\n    classification: slightly promising\n      \n  - headline: Lack of input validation in Builds.addArgumentsToSaltFunction\n    analysis: |\n      The `Builds.addArgumentsToSaltFunction` method does not properly validate the input string `myarguments` before splitting it and using its parts to construct a JSON object. This could potentially lead to various types of injection vulnerabilities, depending on how the constructed JSON object is used within the application.\n    cwe: CWE-1284\n    function_names:\n      - Builds.addArgumentsToSaltFunction\n    filenames:\n      - src/main/java/com/waytta/Builds.java\n    classification: very promising\n      \n  - headline: Potential race condition in Builds.checkBlockingBuild\n    analysis: |\n      The `Builds.checkBlockingBuild` method performs a series of HTTP requests and checks for minion responses within a specific timeout period. If the timing and coordination of these operations are not properly handled, it could potentially lead to race conditions or other concurrency-related vulnerabilities.\n    cwe: CWE-362\n    function_names:\n      - Builds.checkBlockingBuild\n    filenames:\n      - src/main/java/com/waytta/Builds.java\n    classification: slightly promising\n```",
      "date": "2024-06-12T19:08:08.745896",
      "usage": {
        "prompt_tokens": 30668,
        "completion_tokens": 858,
        "cost": 0.104874
      }
    }
  ],
  "leads": [
    {
      "headline": "Lack of input validation in Utils.validatePillar",
      "analysis": "The Utils.validatePillar method does not properly validate the input string before attempting to parse it as JSON. This could potentially lead to various types of injection vulnerabilities, depending on how the parsed JSON object is used within the application.\n",
      "classification": "very promising",
      "cwe": "CWE-1284",
      "function_names": [
        "Utils.validatePillar"
      ],
      "filenames": [
        "src/main/java/com/waytta/Utils.java"
      ]
    },
    {
      "headline": "Lack of output encoding in Utils.writeFile",
      "analysis": "The Utils.writeFile method writes the given string directly to a file without any encoding or sanitization. If the string contains user-supplied data or untrusted input, this could potentially lead to various types of injection vulnerabilities or data exposure.\n",
      "classification": "very promising",
      "cwe": "CWE-838",
      "function_names": [
        "Utils.writeFile"
      ],
      "filenames": [
        "src/main/java/com/waytta/Utils.java"
      ]
    },
    {
      "headline": "Use of user-supplied input in file paths",
      "analysis": "Several methods in the codebase accept user-supplied input (e.g., target, function, arguments) and use them to construct file paths or URLs without proper validation or sanitization. This could potentially lead to path traversal or other file system-related vulnerabilities.\n",
      "classification": "very promising",
      "cwe": "CWE-22",
      "function_names": [
        "HttpCallable.call",
        "SaltAPIBuilder.prepareSaltFunction"
      ],
      "filenames": [
        "src/main/java/com/waytta/HttpCallable.java",
        "src/main/java/com/waytta/SaltAPIBuilder.java"
      ]
    },
    {
      "headline": "Potential hardcoded credentials in test code",
      "analysis": "The SaltAPIBuilderTest class contains hardcoded credential values (e.g., usernames, passwords) used for testing purposes. While these values may be intended for testing only, hardcoded credentials in production code can lead to unauthorized access if discovered by an attacker.\n",
      "classification": "slightly promising",
      "cwe": "CWE-798",
      "function_names": [],
      "filenames": [
        "src/test/java/com/waytta/SaltAPIBuilderTest.java"
      ]
    },
    {
      "headline": "Lack of input validation in Builds.addArgumentsToSaltFunction",
      "analysis": "The Builds.addArgumentsToSaltFunction method does not properly validate the input string myarguments before splitting it and using its parts to construct a JSON object. This could potentially lead to various types of injection vulnerabilities, depending on how the constructed JSON object is used within the application.\n",
      "classification": "very promising",
      "cwe": "CWE-1284",
      "function_names": [
        "Builds.addArgumentsToSaltFunction"
      ],
      "filenames": [
        "src/main/java/com/waytta/Builds.java"
      ]
    },
    {
      "headline": "Potential race condition in Builds.checkBlockingBuild",
      "analysis": "The Builds.checkBlockingBuild method performs a series of HTTP requests and checks for minion responses within a specific timeout period. If the timing and coordination of these operations are not properly handled, it could potentially lead to race conditions or other concurrency-related vulnerabilities.\n",
      "classification": "slightly promising",
      "cwe": "CWE-362",
      "function_names": [
        "Builds.checkBlockingBuild"
      ],
      "filenames": [
        "src/main/java/com/waytta/Builds.java"
      ]
    }
  ],
  "scores": [
    {
      "stats": {
        "fn": 1,
        "tp": 0,
        "fp": 4
      },
      "mapping": {},
      "vuln_dates": {
        "CVE-2018-1999027": "2018-08-01T13:29:00"
      },
      "scoring_model": "claude-3-opus-20240229",
      "type": "llm",
      "instruction_template_hash": "245ace12b6361954d0a2"
    },
    {
      "stats": {
        "fn": 1,
        "tp": 0,
        "fp": 4
      },
      "mapping": {},
      "vuln_dates": {
        "CVE-2018-1999027": "2018-08-01T13:29:00"
      },
      "scoring_model": "claude-3-5-sonnet-20240620",
      "type": "llm",
      "instruction_template_hash": "245ace12b6361954d0a2"
    }
  ],
  "instruction_template_hash": "10c0163db4740318a544",
  "version": "0.1.0"
}
