{
  "commit": "4ad36ac736b95ce617fa0dfb708a8a73618e3340",
  "repo_url": "https://github.com/nickzren/alsdb",
  "model": "gpt-4o-2024-05-13",
  "chunk_hashes": [
    "618d3f14538df0d8a296"
  ],
  "responses": [
    {
      "content": "```yaml\nleads:\n  - headline: \"Potential Command Injection in Input Handling\"\n    analysis: |\n      The `Input::init` method handles user input without proper sanitization and directly uses it in SQL queries. This can lead to command injection attacks. For example, in the `initRegionListByGeneName` function, the SQL query is constructed using string concatenation with the user-provided gene name.\n    cwe: CWE-77\n    function_names:\n      - init\n      - initRegionListByGeneName\n    filenames:\n      - src/main/java/igm/alsdb/model/Input.java\n    classification: very promising\n    \n  - headline: \"Potential SQL Injection in DBManager::executeQuery\"\n    analysis: |\n      The `DBManager::executeQuery` method executes SQL queries built via string concatenation with user inputs, exposing the codebase to SQL injection risks. For instance, the `Output::initVariant` method constructs SQL queries directly using user-provided data (Input.idStr).\n    cwe: CWE-89\n    function_names:\n      - executeQuery\n      - initVariant\n    filenames:\n      - src/main/java/igm/alsdb/util/DBManager.java\n      - src/main/java/igm/alsdb/model/Output.java\n    classification: very promising\n\n  - headline: \"Logging Credentials in DBManager Class\"\n    analysis: |\n      Database credentials are hardcoded in the `DBManager` class. This practice can expose sensitive information, leading to potential unauthorized database access if the codebase is leaked or accessed by unauthorized personnel.\n    cwe: CWE-798\n    function_names:\n      - init\n    filenames:\n      - src/main/java/igm/alsdb/util/DBManager.java\n    classification: very promising\n\n  - headline: \"Debug and Sensitive Information Exposure in Logs\"\n    analysis: |\n      The debug logging throughout the codebase (e.g., in `Input::init` method) may inadvertently leak sensitive information. Logging detailed internal state and sensitive data can aid attackers in understanding your system architecture and finding potential weaknesses.\n    cwe: CWE-532\n    function_names:\n      - init\n      - buildHeaders\n    filenames:\n      - src/main/java/igm/alsdb/model/Input.java\n      - src/main/webapp/js/jquery.tablesorter.js\n    classification: slightly promising\n\n  - headline: \"Potential Cross-Site Scripting (XSS) in Search Import\"\n    analysis: |\n      User inputs are incorporated into SQL queries or dynamically generated content without proper sanitization or escaping. It could lead to cross-site scripting (XSS) if the outputs are reflected back to the front end without proper encoding or escaping.\n    cwe: CWE-79\n    function_names:\n      - processRequest\n    filenames:\n      - src/main/java/igm/alsdb/controller/Search.java\n    classification: slightly promising\n    \n  - headline: \"Insecure Direct Object Reference (IDOR) in File Handling\"\n    analysis: |\n      The `Download::generateFile` method constructs file paths using user inputs directly, which might allow attackers to manipulate file paths and access unauthorized files if proper precautionary checks are not in place.\n    cwe: CWE-22\n    function_names:\n      - generateFile\n    filenames:\n      - src/main/java/igm/alsdb/model/Download.java\n    classification: very promising\n```",
      "date": "2024-06-14T14:56:24.429907",
      "usage": {
        "prompt_tokens": 56022,
        "completion_tokens": 697,
        "cost": 0.290565
      }
    }
  ],
  "leads": [
    {
      "headline": "Potential Command Injection in Input Handling",
      "analysis": "The Input::init method handles user input without proper sanitization and directly uses it in SQL queries. This can lead to command injection attacks. For example, in the initRegionListByGeneName function, the SQL query is constructed using string concatenation with the user-provided gene name.\n",
      "classification": "very promising",
      "cwe": "CWE-77",
      "function_names": [
        "init",
        "initRegionListByGeneName"
      ],
      "filenames": [
        "src/main/java/igm/alsdb/model/Input.java"
      ]
    },
    {
      "headline": "Potential SQL Injection in DBManager::executeQuery",
      "analysis": "The DBManager::executeQuery method executes SQL queries built via string concatenation with user inputs, exposing the codebase to SQL injection risks. For instance, the Output::initVariant method constructs SQL queries directly using user-provided data (Input.idStr).\n",
      "classification": "very promising",
      "cwe": "CWE-89",
      "function_names": [
        "executeQuery",
        "initVariant"
      ],
      "filenames": [
        "src/main/java/igm/alsdb/util/DBManager.java",
        "src/main/java/igm/alsdb/model/Output.java"
      ]
    },
    {
      "headline": "Logging Credentials in DBManager Class",
      "analysis": "Database credentials are hardcoded in the DBManager class. This practice can expose sensitive information, leading to potential unauthorized database access if the codebase is leaked or accessed by unauthorized personnel.\n",
      "classification": "very promising",
      "cwe": "CWE-798",
      "function_names": [
        "init"
      ],
      "filenames": [
        "src/main/java/igm/alsdb/util/DBManager.java"
      ]
    },
    {
      "headline": "Debug and Sensitive Information Exposure in Logs",
      "analysis": "The debug logging throughout the codebase (e.g., in Input::init method) may inadvertently leak sensitive information. Logging detailed internal state and sensitive data can aid attackers in understanding your system architecture and finding potential weaknesses.\n",
      "classification": "slightly promising",
      "cwe": "CWE-532",
      "function_names": [
        "init",
        "buildHeaders"
      ],
      "filenames": [
        "src/main/java/igm/alsdb/model/Input.java",
        "src/main/webapp/js/jquery.tablesorter.js"
      ]
    },
    {
      "headline": "Potential Cross-Site Scripting (XSS) in Search Import",
      "analysis": "User inputs are incorporated into SQL queries or dynamically generated content without proper sanitization or escaping. It could lead to cross-site scripting (XSS) if the outputs are reflected back to the front end without proper encoding or escaping.\n",
      "classification": "slightly promising",
      "cwe": "CWE-79",
      "function_names": [
        "processRequest"
      ],
      "filenames": [
        "src/main/java/igm/alsdb/controller/Search.java"
      ]
    },
    {
      "headline": "Insecure Direct Object Reference (IDOR) in File Handling",
      "analysis": "The Download::generateFile method constructs file paths using user inputs directly, which might allow attackers to manipulate file paths and access unauthorized files if proper precautionary checks are not in place.\n",
      "classification": "very promising",
      "cwe": "CWE-22",
      "function_names": [
        "generateFile"
      ],
      "filenames": [
        "src/main/java/igm/alsdb/model/Download.java"
      ]
    }
  ],
  "scores": [
    {
      "stats": {
        "fn": 0,
        "tp": 1,
        "fp": 3
      },
      "mapping": {
        "1": "CVE-2016-15021"
      },
      "vuln_dates": {
        "CVE-2016-15021": "2023-01-17T16:15:16"
      },
      "scoring_model": "claude-3-opus-20240229",
      "type": "llm",
      "instruction_template_hash": "245ace12b6361954d0a2"
    },
    {
      "stats": {
        "fn": 0,
        "tp": 1,
        "fp": 2
      },
      "mapping": {
        "0": "CVE-2016-15021",
        "1": "CVE-2016-15021"
      },
      "vuln_dates": {
        "CVE-2016-15021": "2023-01-17T16:15:16"
      },
      "scoring_model": "claude-3-5-sonnet-20240620",
      "type": "llm",
      "instruction_template_hash": "245ace12b6361954d0a2"
    }
  ],
  "instruction_template_hash": "10c0163db4740318a544",
  "version": "0.1.0"
}
