{
  "commit": "235a1945749f88f040354596f7adff353ff72522",
  "repo_url": "https://github.com/jenkinsci/fabric-beta-publisher-plugin",
  "model": "claude-3-sonnet-20240229",
  "chunk_hashes": [
    "905b991a16ff1dbb5f26"
  ],
  "responses": [
    {
      "content": "```yaml\nleads:\n  - headline: Unvalidated potential source code inclusion from input parameters\n    analysis: |\n      The FabricBetaPublisher class takes several input parameters from the user that are then used to construct command line arguments for the external \"crashlytics-devtools.jar\" tool. Some of these parameters, such as `releaseNotesParameter`, `testersEmails`, and `testersGroup`, are directly concatenated into the command without any validation or sanitization.\n\n      If an attacker can control the values of these parameters, they may be able to inject arbitrary commands to be executed by the \"crashlytics-devtools.jar\" tool, potentially leading to remote code execution on the Jenkins master.\n    cwe: CWE-94\n    function_names:\n      - FabricBetaPublisher.buildCrashlyticsCommand\n    filenames:\n      - src/main/java/fabric/beta/publisher/FabricBetaPublisher.java\n    classification: very promising\n\n  - headline: Unvalidated open redirect with `organization` parameter\n    analysis: |\n      The AppRelease class constructs URLs of the form `https://fabric.io/{organization}/android/apps/{package}/beta/releases/{id}` based on the `organization` parameter provided to the FabricBetaPublisher class. This URL is then saved as an environment variable for the build.\n\n      If an attacker can control the `organization` parameter, they may be able to cause the URL to redirect to an attacker-controlled site, potentially leading to phishing or other attacks.\n    cwe: CWE-601\n    function_names:\n      - AppRelease.buildLink\n    filenames:\n      - src/main/java/fabric/beta/publisher/AppRelease.java\n    classification: slightly promising\n\n  - headline: Blind trust of APK file metadata\n    analysis: |\n      The AppRelease class reads metadata from the \"crashlytics-build.properties\" file inside the provided APK file, and uses this metadata to construct URLs and other information for the release. However, there is no validation that the APK file actually comes from a trusted source.\n\n      If an attacker can supply a malicious APK file, they may be able to control the metadata used by the plugin, potentially leading to unexpected behavior or security vulnerabilities.\n    cwe: CWE-494\n    function_names:\n      - AppRelease.from\n    filenames:\n      - src/main/java/fabric/beta/publisher/AppRelease.java\n    classification: slightly promising\n\n  - headline: Unvalidated creation of temporary files\n    analysis: |\n      The FileUtils class creates temporary files and directories in various locations without sanitizing the file names or ensuring that the files are created in a secure directory with appropriate permissions.\n\n      If an attacker can influence the file names or locations, they may be able to perform path traversal attacks or gain unauthorized access to files or directories.\n    cwe: CWE-22\n    function_names:\n      - FileUtils.getManifestFile\n      - FileUtils.createTemporaryUploadFile\n      - FileUtils.createTempDirectory\n    filenames:\n      - src/main/java/fabric/beta/publisher/FileUtils.java\n    classification: slightly promising\n\n  - headline: Insecure deserialization of untrusted data\n    analysis: |\n      The FabricBetaPublisher class deserializes the build changelog set (`ChangeLogSet`) and uses it to construct release notes for the APK upload. However, there is no validation that the changelog set comes from a trusted source, and it is not clear how the changelog set is serialized or transmitted.\n\n      If an attacker can control the serialized form of the changelog set, they may be able to execute arbitrary code or perform other attacks by exploiting insecure deserialization vulnerabilities.\n    cwe: CWE-502\n    function_names:\n      - FabricBetaPublisher.perform\n    filenames:\n      - src/main/java/fabric/beta/publisher/FabricBetaPublisher.java\n    classification: slightly promising\n\n  - headline: Lack of authentication for critical functionality\n    analysis: |\n      The FabricBetaPublisher class allows any user with access to the Jenkins master to upload APK files to the Fabric Beta service, without requiring authentication or authorization checks.\n\n      An attacker who gains access to the Jenkins master (e.g., through a separate vulnerability) may be able to upload malicious or unauthorized APK files to the Fabric Beta service, potentially leading to data leaks or other security issues.\n    cwe: CWE-306\n    function_names: []\n    filenames:\n      - src/main/java/fabric/beta/publisher/FabricBetaPublisher.java\n    classification: slightly promising\n\n  - headline: Potential command injection from system properties\n    analysis: |\n      The FabricBetaPublisher class constructs a command to execute the \"crashlytics-devtools.jar\" tool, and includes various system properties (e.g., `http.proxyHost`, `https.proxyPort`) as command line arguments without any validation or sanitization.\n\n      If an attacker can control these system properties (e.g., by modifying the Jenkins system configuration or environment variables), they may be able to inject arbitrary commands to be executed by the \"crashlytics-devtools.jar\" tool, potentially leading to remote code execution on the Jenkins master.\n    cwe: CWE-78\n    function_names:\n      - FabricBetaPublisher.buildCrashlyticsCommand\n    filenames:\n      - src/main/java/fabric/beta/publisher/FabricBetaPublisher.java\n    classification: slightly promising\n\n  - headline: Potential path traversal vulnerability in APK file handling\n    analysis: |\n      The FabricBetaPublisher class allows users to specify the path to the APK file(s) to be uploaded, either as a single path or as an Ant-style glob pattern. However, there does not appear to be any validation or sanitization of these paths to prevent path traversal attacks.\n\n      If an attacker can control the `apkPath` parameter, they may be able to access or modify files outside of the intended directory structure on the Jenkins master or the build workspace.\n    cwe: CWE-22\n    function_names:\n      - FabricBetaPublisher.getApkFilePaths\n    filenames:\n      - src/main/java/fabric/beta/publisher/FabricBetaPublisher.java\n    classification: slightly promising\n\n  - headline: Potential information disclosure from error messages\n    analysis: |\n      The FabricApi class logs error messages directly to the Jenkins build log, including potentially sensitive information such as HTTP request and response details, network error messages, and other internal details.\n\n      If an attacker can trigger specific error conditions or exceptions, they may be able to extract sensitive information from these error messages, potentially leading to further attacks or information disclosure.\n    cwe: CWE-209\n    function_names:\n      - FabricApi.interceptor\n    filenames:\n      - src/main/java/fabric/beta/publisher/FabricApi.java\n    classification: slightly promising\n```",
      "date": "2024-06-12T18:24:33.859566",
      "usage": {
        "prompt_tokens": 11766,
        "completion_tokens": 1683,
        "cost": 0.060543
      }
    }
  ],
  "leads": [
    {
      "headline": "Unvalidated potential source code inclusion from input parameters",
      "analysis": "The FabricBetaPublisher class takes several input parameters from the user that are then used to construct command line arguments for the external \"crashlytics-devtools.jar\" tool. Some of these parameters, such as releaseNotesParameter, testersEmails, and testersGroup, are directly concatenated into the command without any validation or sanitization.\n\nIf an attacker can control the values of these parameters, they may be able to inject arbitrary commands to be executed by the \"crashlytics-devtools.jar\" tool, potentially leading to remote code execution on the Jenkins master.\n",
      "classification": "very promising",
      "cwe": "CWE-94",
      "function_names": [
        "FabricBetaPublisher.buildCrashlyticsCommand"
      ],
      "filenames": [
        "src/main/java/fabric/beta/publisher/FabricBetaPublisher.java"
      ]
    },
    {
      "headline": "Unvalidated open redirect with organization parameter",
      "analysis": "The AppRelease class constructs URLs of the form https://fabric.io/{organization}/android/apps/{package}/beta/releases/{id} based on the organization parameter provided to the FabricBetaPublisher class. This URL is then saved as an environment variable for the build.\n\nIf an attacker can control the organization parameter, they may be able to cause the URL to redirect to an attacker-controlled site, potentially leading to phishing or other attacks.\n",
      "classification": "slightly promising",
      "cwe": "CWE-601",
      "function_names": [
        "AppRelease.buildLink"
      ],
      "filenames": [
        "src/main/java/fabric/beta/publisher/AppRelease.java"
      ]
    },
    {
      "headline": "Blind trust of APK file metadata",
      "analysis": "The AppRelease class reads metadata from the \"crashlytics-build.properties\" file inside the provided APK file, and uses this metadata to construct URLs and other information for the release. However, there is no validation that the APK file actually comes from a trusted source.\n\nIf an attacker can supply a malicious APK file, they may be able to control the metadata used by the plugin, potentially leading to unexpected behavior or security vulnerabilities.\n",
      "classification": "slightly promising",
      "cwe": "CWE-494",
      "function_names": [
        "AppRelease.from"
      ],
      "filenames": [
        "src/main/java/fabric/beta/publisher/AppRelease.java"
      ]
    },
    {
      "headline": "Unvalidated creation of temporary files",
      "analysis": "The FileUtils class creates temporary files and directories in various locations without sanitizing the file names or ensuring that the files are created in a secure directory with appropriate permissions.\n\nIf an attacker can influence the file names or locations, they may be able to perform path traversal attacks or gain unauthorized access to files or directories.\n",
      "classification": "slightly promising",
      "cwe": "CWE-22",
      "function_names": [
        "FileUtils.getManifestFile",
        "FileUtils.createTemporaryUploadFile",
        "FileUtils.createTempDirectory"
      ],
      "filenames": [
        "src/main/java/fabric/beta/publisher/FileUtils.java"
      ]
    },
    {
      "headline": "Insecure deserialization of untrusted data",
      "analysis": "The FabricBetaPublisher class deserializes the build changelog set (ChangeLogSet) and uses it to construct release notes for the APK upload. However, there is no validation that the changelog set comes from a trusted source, and it is not clear how the changelog set is serialized or transmitted.\n\nIf an attacker can control the serialized form of the changelog set, they may be able to execute arbitrary code or perform other attacks by exploiting insecure deserialization vulnerabilities.\n",
      "classification": "slightly promising",
      "cwe": "CWE-502",
      "function_names": [
        "FabricBetaPublisher.perform"
      ],
      "filenames": [
        "src/main/java/fabric/beta/publisher/FabricBetaPublisher.java"
      ]
    },
    {
      "headline": "Lack of authentication for critical functionality",
      "analysis": "The FabricBetaPublisher class allows any user with access to the Jenkins master to upload APK files to the Fabric Beta service, without requiring authentication or authorization checks.\n\nAn attacker who gains access to the Jenkins master (e.g., through a separate vulnerability) may be able to upload malicious or unauthorized APK files to the Fabric Beta service, potentially leading to data leaks or other security issues.\n",
      "classification": "slightly promising",
      "cwe": "CWE-306",
      "function_names": [],
      "filenames": [
        "src/main/java/fabric/beta/publisher/FabricBetaPublisher.java"
      ]
    },
    {
      "headline": "Potential command injection from system properties",
      "analysis": "The FabricBetaPublisher class constructs a command to execute the \"crashlytics-devtools.jar\" tool, and includes various system properties (e.g., http.proxyHost, https.proxyPort) as command line arguments without any validation or sanitization.\n\nIf an attacker can control these system properties (e.g., by modifying the Jenkins system configuration or environment variables), they may be able to inject arbitrary commands to be executed by the \"crashlytics-devtools.jar\" tool, potentially leading to remote code execution on the Jenkins master.\n",
      "classification": "slightly promising",
      "cwe": "CWE-78",
      "function_names": [
        "FabricBetaPublisher.buildCrashlyticsCommand"
      ],
      "filenames": [
        "src/main/java/fabric/beta/publisher/FabricBetaPublisher.java"
      ]
    },
    {
      "headline": "Potential path traversal vulnerability in APK file handling",
      "analysis": "The FabricBetaPublisher class allows users to specify the path to the APK file(s) to be uploaded, either as a single path or as an Ant-style glob pattern. However, there does not appear to be any validation or sanitization of these paths to prevent path traversal attacks.\n\nIf an attacker can control the apkPath parameter, they may be able to access or modify files outside of the intended directory structure on the Jenkins master or the build workspace.\n",
      "classification": "slightly promising",
      "cwe": "CWE-22",
      "function_names": [
        "FabricBetaPublisher.getApkFilePaths"
      ],
      "filenames": [
        "src/main/java/fabric/beta/publisher/FabricBetaPublisher.java"
      ]
    },
    {
      "headline": "Potential information disclosure from error messages",
      "analysis": "The FabricApi class logs error messages directly to the Jenkins build log, including potentially sensitive information such as HTTP request and response details, network error messages, and other internal details.\n\nIf an attacker can trigger specific error conditions or exceptions, they may be able to extract sensitive information from these error messages, potentially leading to further attacks or information disclosure.\n",
      "classification": "slightly promising",
      "cwe": "CWE-209",
      "function_names": [
        "FabricApi.interceptor"
      ],
      "filenames": [
        "src/main/java/fabric/beta/publisher/FabricApi.java"
      ]
    }
  ],
  "scores": [
    {
      "stats": {
        "fn": 1,
        "tp": 0,
        "fp": 1
      },
      "mapping": {},
      "vuln_dates": {
        "CVE-2019-1003088": "2019-04-04T16:29:01"
      },
      "scoring_model": "claude-3-opus-20240229",
      "type": "llm",
      "instruction_template_hash": "245ace12b6361954d0a2"
    }
  ],
  "instruction_template_hash": "10c0163db4740318a544",
  "version": "0.1.0"
}
