{
  "commit": "1c517ffafcf8907b159146ae51d897cd3bcddbfe",
  "repo_url": "https://github.com/datadog/guarddog",
  "model": "claude-3-5-sonnet-20240620",
  "chunk_hashes": [
    "4c404fd2d4b50c07f486"
  ],
  "responses": [
    {
      "content": "```yaml\nleads:\n  - headline: Command injection vulnerability in cli.py\n    analysis: |\n      The cli.py file contains a command injection vulnerability in the 'verify' function. It uses the 'path' argument directly in a command execution without proper sanitization. An attacker could craft a malicious path value to execute arbitrary commands. For example, passing \"; rm -rf /\" as the path could delete files on the system.\n    cwe: CWE-78\n    function_names:\n      - verify\n    filenames:\n      - guarddog/cli.py\n    classification: very promising\n\n  - headline: Potential remote code execution in package_scanner.py\n    analysis: |\n      The package_scanner.py file contains a potential remote code execution vulnerability in the download_package method. It downloads and extracts package files from PyPI without proper validation or sandboxing. An attacker could potentially upload a malicious package to PyPI that when downloaded and extracted by this function could execute arbitrary code.\n    cwe: CWE-94\n    function_names:\n      - download_package\n      - download_compressed  \n    filenames:\n      - guarddog/scanners/package_scanner.py\n    classification: slightly promising\n\n  - headline: Insecure deserialization of JSON data\n    analysis: |\n      The package_info.py file retrieves and deserializes JSON data from PyPI without proper validation. An attacker controlling a malicious PyPI server could potentially return maliciously crafted JSON that when deserialized could lead to arbitrary code execution. The json.loads() call should be replaced with a safer alternative that does not execute arbitrary code during deserialization.\n    cwe: CWE-502\n    function_names:\n      - get_package_info\n    filenames:  \n      - guarddog/utils/package_info.py\n    classification: slightly promising\n\n  - headline: Potential directory traversal in file operations\n    analysis: |\n      The analyzer.py file performs file operations using user-controlled input without properly sanitizing file paths. This could potentially allow an attacker to read or write files outside the intended directory via directory traversal. The code should validate and sanitize file paths before using them in operations.\n    cwe: CWE-22\n    function_names:\n      - analyze_sourcecode\n    filenames:\n      - guarddog/analyzer/analyzer.py  \n    classification: slightly promising\n\n  - headline: Use of hard-coded credentials\n    analysis: |\n      The project_scanner.py file contains hard-coded GitHub credentials used for authentication. Hard-coding credentials is insecure as it exposes sensitive information in source code. These credentials should be moved to a secure external configuration or environment variables.\n    cwe: CWE-798\n    function_names:\n      - _authenticate_by_access_token\n    filenames:\n      - guarddog/scanners/project_scanner.py\n    classification: slightly promising\n```",
      "date": "2024-07-08T05:59:33.838529",
      "usage": {
        "prompt_tokens": 31967,
        "completion_tokens": 672,
        "cost": 0.105981
      }
    }
  ],
  "leads": [
    {
      "headline": "Command injection vulnerability in cli.py",
      "analysis": "The cli.py file contains a command injection vulnerability in the 'verify' function. It uses the 'path' argument directly in a command execution without proper sanitization. An attacker could craft a malicious path value to execute arbitrary commands. For example, passing \"; rm -rf /\" as the path could delete files on the system.\n",
      "classification": "very promising",
      "cwe": "CWE-78",
      "function_names": [
        "verify"
      ],
      "filenames": [
        "guarddog/cli.py"
      ]
    },
    {
      "headline": "Potential remote code execution in package_scanner.py",
      "analysis": "The package_scanner.py file contains a potential remote code execution vulnerability in the download_package method. It downloads and extracts package files from PyPI without proper validation or sandboxing. An attacker could potentially upload a malicious package to PyPI that when downloaded and extracted by this function could execute arbitrary code.\n",
      "classification": "slightly promising",
      "cwe": "CWE-94",
      "function_names": [
        "download_package",
        "download_compressed"
      ],
      "filenames": [
        "guarddog/scanners/package_scanner.py"
      ]
    },
    {
      "headline": "Insecure deserialization of JSON data",
      "analysis": "The package_info.py file retrieves and deserializes JSON data from PyPI without proper validation. An attacker controlling a malicious PyPI server could potentially return maliciously crafted JSON that when deserialized could lead to arbitrary code execution. The json.loads() call should be replaced with a safer alternative that does not execute arbitrary code during deserialization.\n",
      "classification": "slightly promising",
      "cwe": "CWE-502",
      "function_names": [
        "get_package_info"
      ],
      "filenames": [
        "guarddog/utils/package_info.py"
      ]
    },
    {
      "headline": "Potential directory traversal in file operations",
      "analysis": "The analyzer.py file performs file operations using user-controlled input without properly sanitizing file paths. This could potentially allow an attacker to read or write files outside the intended directory via directory traversal. The code should validate and sanitize file paths before using them in operations.\n",
      "classification": "slightly promising",
      "cwe": "CWE-22",
      "function_names": [
        "analyze_sourcecode"
      ],
      "filenames": [
        "guarddog/analyzer/analyzer.py"
      ]
    },
    {
      "headline": "Use of hard-coded credentials",
      "analysis": "The project_scanner.py file contains hard-coded GitHub credentials used for authentication. Hard-coding credentials is insecure as it exposes sensitive information in source code. These credentials should be moved to a secure external configuration or environment variables.\n",
      "classification": "slightly promising",
      "cwe": "CWE-798",
      "function_names": [
        "_authenticate_by_access_token"
      ],
      "filenames": [
        "guarddog/scanners/project_scanner.py"
      ]
    }
  ],
  "scores": [
    {
      "stats": {
        "fn": 2,
        "tp": 0,
        "fp": 1
      },
      "mapping": {},
      "vuln_dates": {
        "CVE-2022-23530": "2022-12-16T23:15:09",
        "CVE-2022-23531": "2022-12-17T00:15:08"
      },
      "scoring_model": "claude-3-5-sonnet-20240620",
      "type": "llm",
      "instruction_template_hash": "245ace12b6361954d0a2"
    }
  ],
  "instruction_template_hash": "10c0163db4740318a544",
  "version": "0.1.0"
}
