{
  "commit": "3897b11ea4213bc44945369f758b8dbe592a6558",
  "repo_url": "https://github.com/nautobot/nautobot-plugin-device-onboarding",
  "model": "claude-3-haiku-20240307",
  "chunk_hashes": [
    "684f1e0abcf4d04dec18"
  ],
  "responses": [
    {
      "content": "Here is the YAML output for the security vulnerabilities in the codebase:\n\n```yaml\nleads:\n  - headline: Sensitive Data Exposure\n    analysis: |\n      The codebase contains code that exposes sensitive information, such as user credentials, to unauthorized actors. This could allow attackers to gain access to system resources and potentially compromise the entire system.\n    cwe: CWE-200\n    function_names:\n      - OnboardingTaskForm.save\n    filenames:\n      - nautobot_device_onboarding/forms.py\n    classification: very promising\n\n  - headline: Improper Neutralization of Input During Web Page Generation\n    analysis: |\n      The codebase contains code that does not properly sanitize user input, which could allow attackers to inject malicious code into the system. This could lead to cross-site scripting (XSS) vulnerabilities and allow attackers to steal sensitive information or perform other malicious actions.\n    cwe: CWE-79\n    function_names:\n      - DeviceContent.right_page\n    filenames:\n      - nautobot_device_onboarding/template_content.py\n    classification: slightly promising\n\n  - headline: Improper Neutralization of Special Elements used in an OS Command\n    analysis: |\n      The codebase contains code that executes OS commands without properly sanitizing user input. This could allow attackers to inject malicious commands into the system and potentially gain unauthorized access or perform other malicious actions.\n    cwe: CWE-78\n    function_names:\n      - run_command\n    filenames:\n      - nautobot_device_onboarding/tasks.py\n    classification: very promising\n\n  - headline: Improper Neutralization of Special Elements used in an SQL Command\n    analysis: |\n      The codebase contains code that executes SQL queries without properly sanitizing user input. This could allow attackers to inject malicious SQL statements into the system and potentially gain unauthorized access to sensitive data or perform other malicious actions.\n    cwe: CWE-89\n    function_names:\n      - object_match\n    filenames:\n      - nautobot_device_onboarding/nautobot_keeper.py\n    classification: slightly promising\n\n  - headline: Insecure Storage of Sensitive Information\n    analysis: |\n      The codebase contains code that stores sensitive information, such as user credentials, in an insecure manner. This could allow attackers to gain access to this information and potentially compromise the entire system.\n    cwe: CWE-922\n    function_names:\n      - OnboardingTaskForm.save\n    filenames:\n      - nautobot_device_onboarding/forms.py\n    classification: very promising\n\n  - headline: Improper Neutralization of Formula Elements in a CSV File\n    analysis: |\n      The codebase contains code that generates CSV files without properly sanitizing user input. This could allow attackers to inject malicious formula elements into the CSV file, which could be executed by the system and potentially lead to unauthorized access or other malicious actions.\n    cwe: CWE-1236\n    function_names:\n      - generate_packages\n    filenames:\n      - nautobot_device_onboarding/tasks.py\n    classification: slightly promising\n```",
      "date": "2024-06-09T13:41:13.117131",
      "usage": {
        "prompt_tokens": 51128,
        "completion_tokens": 762,
        "cost": 0.0137345
      }
    }
  ],
  "leads": [
    {
      "headline": "Sensitive Data Exposure",
      "analysis": "The codebase contains code that exposes sensitive information, such as user credentials, to unauthorized actors. This could allow attackers to gain access to system resources and potentially compromise the entire system.\n",
      "classification": "very promising",
      "cwe": "CWE-200",
      "function_names": [
        "OnboardingTaskForm.save"
      ],
      "filenames": [
        "nautobot_device_onboarding/forms.py"
      ]
    },
    {
      "headline": "Improper Neutralization of Input During Web Page Generation",
      "analysis": "The codebase contains code that does not properly sanitize user input, which could allow attackers to inject malicious code into the system. This could lead to cross-site scripting (XSS) vulnerabilities and allow attackers to steal sensitive information or perform other malicious actions.\n",
      "classification": "slightly promising",
      "cwe": "CWE-79",
      "function_names": [
        "DeviceContent.right_page"
      ],
      "filenames": [
        "nautobot_device_onboarding/template_content.py"
      ]
    },
    {
      "headline": "Improper Neutralization of Special Elements used in an OS Command",
      "analysis": "The codebase contains code that executes OS commands without properly sanitizing user input. This could allow attackers to inject malicious commands into the system and potentially gain unauthorized access or perform other malicious actions.\n",
      "classification": "very promising",
      "cwe": "CWE-78",
      "function_names": [
        "run_command"
      ],
      "filenames": [
        "nautobot_device_onboarding/tasks.py"
      ]
    },
    {
      "headline": "Improper Neutralization of Special Elements used in an SQL Command",
      "analysis": "The codebase contains code that executes SQL queries without properly sanitizing user input. This could allow attackers to inject malicious SQL statements into the system and potentially gain unauthorized access to sensitive data or perform other malicious actions.\n",
      "classification": "slightly promising",
      "cwe": "CWE-89",
      "function_names": [
        "object_match"
      ],
      "filenames": [
        "nautobot_device_onboarding/nautobot_keeper.py"
      ]
    },
    {
      "headline": "Insecure Storage of Sensitive Information",
      "analysis": "The codebase contains code that stores sensitive information, such as user credentials, in an insecure manner. This could allow attackers to gain access to this information and potentially compromise the entire system.\n",
      "classification": "very promising",
      "cwe": "CWE-922",
      "function_names": [
        "OnboardingTaskForm.save"
      ],
      "filenames": [
        "nautobot_device_onboarding/forms.py"
      ]
    },
    {
      "headline": "Improper Neutralization of Formula Elements in a CSV File",
      "analysis": "The codebase contains code that generates CSV files without properly sanitizing user input. This could allow attackers to inject malicious formula elements into the CSV file, which could be executed by the system and potentially lead to unauthorized access or other malicious actions.\n",
      "classification": "slightly promising",
      "cwe": "CWE-1236",
      "function_names": [
        "generate_packages"
      ],
      "filenames": [
        "nautobot_device_onboarding/tasks.py"
      ]
    }
  ],
  "scores": [
    {
      "stats": {
        "fn": 0,
        "tp": 1,
        "fp": 1
      },
      "mapping": {
        "0": "CVE-2023-48700",
        "2": "CVE-2023-48700"
      },
      "vuln_dates": {
        "CVE-2023-48700": "2023-11-21T23:15:08"
      },
      "scoring_model": "gpt-4o-2024-05-13",
      "type": "llm",
      "instruction_template_hash": "8998f09cf57fca8a6e03"
    }
  ],
  "instruction_template_hash": "10c0163db4740318a544",
  "version": "0.1.0"
}
