{
  "commit": "19d001695fe17f9b776633733a21a060c70bea82",
  "repo_url": "https://github.com/openzeppelin/cairo-contracts",
  "model": "claude-3-5-sonnet-20240620",
  "chunk_hashes": [
    "fb06edd579d2663c9ce2"
  ],
  "responses": [
    {
      "content": "```yaml\nleads:\n  - headline: Insufficient access control on mint function\n    analysis: |\n      The mint function in the ERC721_Mintable_Burnable contract lacks proper access control. It only checks that the caller is the owner, but does not use the Ownable contract's onlyOwner modifier. This means that if the owner account is compromised, an attacker could mint an unlimited number of tokens. A more secure approach would be to use the onlyOwner modifier from the Ownable contract.\n    cwe: CWE-284\n    function_names:\n      - mint\n    filenames:\n      - src/openzeppelin/token/erc721/ERC721_Mintable_Burnable.cairo\n    classification: slightly promising\n\n  - headline: Possible integer overflow in tokenByIndex\n    analysis: |\n      The tokenByIndex function in the ERC721Enumerable contract does not check for integer overflow when incrementing the index. If the total supply of tokens reaches the maximum uint256 value, incrementing it further could cause an overflow and unexpected behavior. While this is unlikely in practice due to gas limits, it is still a potential vulnerability that should be addressed.\n    cwe: CWE-190\n    function_names:\n      - tokenByIndex\n    filenames:\n      - src/openzeppelin/token/erc721/enumerable/ERC721_Enumerable.cairo\n    classification: slightly promising\n\n  - headline: Lack of check for zero address in setApprovalForAll\n    analysis: |\n      The setApprovalForAll function in the ERC721 contract does not check if the operator address is the zero address. Setting the zero address as an operator could lead to tokens being unintentionally burned or lost. It's a good practice to explicitly check for and reject the zero address in such operations.\n    cwe: CWE-20\n    function_names:\n      - setApprovalForAll\n    filenames:\n      - src/openzeppelin/token/erc721/ERC721.cairo\n    classification: slightly promising\n\n  - headline: Potential reentrancy in safeTransferFrom\n    analysis: |\n      The safeTransferFrom function in the ERC721 contract makes an external call to the recipient's onERC721Received function before updating the token ownership. This pattern could potentially allow for reentrancy attacks if the recipient contract is malicious. While the contract does use checks-effects-interactions pattern in general, this specific function might benefit from additional safeguards.\n    cwe: CWE-841\n    function_names:\n      - safeTransferFrom\n    filenames:\n      - src/openzeppelin/token/erc721/ERC721.cairo\n    classification: slightly promising\n\n  - headline: Lack of event emission in setTokenURI\n    analysis: |\n      The setTokenURI function in the ERC721_Mintable_Burnable contract updates the token URI without emitting an event. This makes it difficult for off-chain applications to track changes to token metadata. While not a security vulnerability per se, it's a deviation from best practices and could lead to synchronization issues for dapps relying on this data.\n    cwe: CWE-223\n    function_names:\n      - setTokenURI\n    filenames:\n      - src/openzeppelin/token/erc721/ERC721_Mintable_Burnable.cairo\n    classification: not promising\n```",
      "date": "2024-07-08T08:09:07.608853",
      "usage": {
        "prompt_tokens": 52545,
        "completion_tokens": 799,
        "cost": 0.16962
      }
    }
  ],
  "leads": [
    {
      "headline": "Insufficient access control on mint function",
      "analysis": "The mint function in the ERC721_Mintable_Burnable contract lacks proper access control. It only checks that the caller is the owner, but does not use the Ownable contract's onlyOwner modifier. This means that if the owner account is compromised, an attacker could mint an unlimited number of tokens. A more secure approach would be to use the onlyOwner modifier from the Ownable contract.\n",
      "classification": "slightly promising",
      "cwe": "CWE-284",
      "function_names": [
        "mint"
      ],
      "filenames": [
        "src/openzeppelin/token/erc721/ERC721_Mintable_Burnable.cairo"
      ]
    },
    {
      "headline": "Possible integer overflow in tokenByIndex",
      "analysis": "The tokenByIndex function in the ERC721Enumerable contract does not check for integer overflow when incrementing the index. If the total supply of tokens reaches the maximum uint256 value, incrementing it further could cause an overflow and unexpected behavior. While this is unlikely in practice due to gas limits, it is still a potential vulnerability that should be addressed.\n",
      "classification": "slightly promising",
      "cwe": "CWE-190",
      "function_names": [
        "tokenByIndex"
      ],
      "filenames": [
        "src/openzeppelin/token/erc721/enumerable/ERC721_Enumerable.cairo"
      ]
    },
    {
      "headline": "Lack of check for zero address in setApprovalForAll",
      "analysis": "The setApprovalForAll function in the ERC721 contract does not check if the operator address is the zero address. Setting the zero address as an operator could lead to tokens being unintentionally burned or lost. It's a good practice to explicitly check for and reject the zero address in such operations.\n",
      "classification": "slightly promising",
      "cwe": "CWE-20",
      "function_names": [
        "setApprovalForAll"
      ],
      "filenames": [
        "src/openzeppelin/token/erc721/ERC721.cairo"
      ]
    },
    {
      "headline": "Potential reentrancy in safeTransferFrom",
      "analysis": "The safeTransferFrom function in the ERC721 contract makes an external call to the recipient's onERC721Received function before updating the token ownership. This pattern could potentially allow for reentrancy attacks if the recipient contract is malicious. While the contract does use checks-effects-interactions pattern in general, this specific function might benefit from additional safeguards.\n",
      "classification": "slightly promising",
      "cwe": "CWE-841",
      "function_names": [
        "safeTransferFrom"
      ],
      "filenames": [
        "src/openzeppelin/token/erc721/ERC721.cairo"
      ]
    },
    {
      "headline": "Lack of event emission in setTokenURI",
      "analysis": "The setTokenURI function in the ERC721_Mintable_Burnable contract updates the token URI without emitting an event. This makes it difficult for off-chain applications to track changes to token metadata. While not a security vulnerability per se, it's a deviation from best practices and could lead to synchronization issues for dapps relying on this data.\n",
      "classification": "not promising",
      "cwe": "CWE-223",
      "function_names": [
        "setTokenURI"
      ],
      "filenames": [
        "src/openzeppelin/token/erc721/ERC721_Mintable_Burnable.cairo"
      ]
    }
  ],
  "scores": [
    {
      "stats": {
        "fn": 1,
        "tp": 0,
        "fp": 0
      },
      "mapping": {},
      "vuln_dates": {
        "CVE-2023-23940": "2023-02-03T20:15:11"
      },
      "scoring_model": "claude-3-5-sonnet-20240620",
      "type": "llm",
      "instruction_template_hash": "245ace12b6361954d0a2"
    }
  ],
  "instruction_template_hash": "10c0163db4740318a544",
  "version": "0.1.0"
}
