{
  "commit": "d90c9e0733fa9af68bd8ea0b1cf023cf482163ef",
  "repo_url": "https://github.com/sap/cloud-pysec",
  "model": "claude-3-sonnet-20240229",
  "chunk_hashes": [
    "2d20a677bda812c751ff"
  ],
  "responses": [
    {
      "content": "```yaml\nleads:\n  - headline: Insecure Deserialization of Untrusted Data\n    analysis: |\n      The codebase contains functionality for deserializing untrusted data, which can lead to arbitrary code execution if the deserialized data contains malicious objects. This vulnerability is known as \"Insecure Deserialization\" and is tracked under CWE-502.\n    cwe: CWE-502\n    function_names:\n      - sap.xssec.jwt_validation_facade.JwtValidationFacade.decode\n      - sap.xssec.jwt_validation_facade.JwtValidationFacade.get_unverified_header\n    filenames:\n      - sap/xssec/jwt_validation_facade.py\n    classification: very promising\n\n  - headline: Use of Broken or Risky Cryptographic Algorithm\n    analysis: |\n      The codebase uses the HS256 (HMAC with SHA-256) algorithm for JWT signature verification. This algorithm is symmetric, which means the same key is used for signing and verifying the JWT. Using a symmetric key algorithm for JWT verification is considered insecure because it requires sharing the secret key with the verifier, increasing the risk of key compromise. The recommended practice is to use an asymmetric algorithm like RS256 (RSA with SHA-256) for JWT signature verification.\n    cwe: CWE-327\n    function_names:\n      - sap.xssec.jwt_validation_facade.ALGORITHMS\n    filenames:\n      - sap/xssec/jwt_validation_facade.py\n    classification: very promising\n\n  - headline: Improper Restriction of XML External Entity Reference\n    analysis: |\n      The codebase contains functionality for parsing XML data from untrusted sources, which can lead to XML External Entity (XXE) injection attacks if not properly handled. This vulnerability is tracked under CWE-611.\n    cwe: CWE-611\n    function_names: []\n    filenames: []\n    classification: slightly promising\n\n  - headline: Use of Insecure Random Values\n    analysis: |\n      The codebase does not appear to include any functionality for generating or using random values, which are essential for cryptographic operations like key generation, nonces, and initialization vectors. If random values are not generated securely, it can lead to vulnerabilities like predictable encryption keys (CWE-330, CWE-331, CWE-335, CWE-338).\n    cwe: CWE-330\n    function_names: []\n    filenames: []\n    classification: slightly promising\n\n  - headline: Improper Certificate Validation\n    analysis: |\n      The codebase does not appear to include any functionality for validating X.509 certificates used for mutual TLS (mTLS) authentication. Improper validation of certificates can lead to authentication bypass vulnerabilities (CWE-295).\n    cwe: CWE-295\n    function_names: []\n    filenames: []\n    classification: slightly promising\n\n  - headline: Missing Authentication for Critical Function\n    analysis: |\n      The codebase does not appear to include any functionality for authenticating requests to critical functions or resources. Missing authentication can lead to unauthorized access to sensitive data or functionality (CWE-306).\n    cwe: CWE-306\n    function_names: []\n    filenames: []\n    classification: slightly promising\n\n  - headline: Use of Hard-coded Credentials\n    analysis: |\n      The codebase does not appear to include any hard-coded credentials, which can lead to unauthorized access if the credentials are discovered (CWE-798).\n    cwe: CWE-798\n    function_names: []\n    filenames: []\n    classification: not promising\n\n  - headline: Improper Neutralization of Input During Web Page Generation\n    analysis: |\n      The codebase does not appear to include any functionality for generating web pages or handling user input that could be used for Cross-Site Scripting (XSS) attacks (CWE-79).\n    cwe: CWE-79\n    function_names: []\n    filenames: []\n    classification: not promising\n\n  - headline: Insufficient Verification of Data Authenticity\n    analysis: |\n      The codebase does not appear to include any functionality for verifying the authenticity of data, which can lead to vulnerabilities like Insecure Direct Object References (CWE-639), Cross-Site Request Forgery (CWE-352), and Improper Verification of Cryptographic Signature (CWE-347).\n    cwe: CWE-345\n    function_names: []\n    filenames: []\n    classification: slightly promising\n```\n\nThe analysis covers various security vulnerabilities that could potentially exist in the provided codebase. The most promising lead is the \"Insecure Deserialization of Untrusted Data\" vulnerability, which is tracked under CWE-502. This vulnerability can lead to arbitrary code execution if the deserialized data contains malicious objects.\n\nAnother significant lead is the \"Use of Broken or Risky Cryptographic Algorithm\" vulnerability, which is tracked under CWE-327. The codebase appears to use the HS256 (HMAC with SHA-256) algorithm for JWT signature verification, which is considered insecure because it requires sharing the secret key with the verifier.\n\nThe analysis also highlights other potential vulnerabilities like \"Improper Restriction of XML External Entity Reference\" (CWE-611), \"Use of Insecure Random Values\" (CWE-330), \"Improper Certificate Validation\" (CWE-295), \"Missing Authentication for Critical Function\" (CWE-306), and \"Insufficient Verification of Data Authenticity\" (CWE-345).\n\nOn the other hand, the analysis indicates that the codebase does not appear to include hard-coded credentials (CWE-798) or functionality for generating web pages or handling user input that could lead to Cross-Site Scripting (XSS) attacks (CWE-79).\n\nIt's important to note that the analysis is based solely on the provided codebase and may not be exhaustive. Further manual review and testing may be necessary to identify and mitigate any potential vulnerabilities.",
      "date": "2024-06-09T14:43:39.775985",
      "usage": {
        "prompt_tokens": 53789,
        "completion_tokens": 1446,
        "cost": 0.183057
      }
    }
  ],
  "leads": [
    {
      "headline": "Insecure Deserialization of Untrusted Data",
      "analysis": "The codebase contains functionality for deserializing untrusted data, which can lead to arbitrary code execution if the deserialized data contains malicious objects. This vulnerability is known as \"Insecure Deserialization\" and is tracked under CWE-502.\n",
      "classification": "very promising",
      "cwe": "CWE-502",
      "function_names": [
        "sap.xssec.jwt_validation_facade.JwtValidationFacade.decode",
        "sap.xssec.jwt_validation_facade.JwtValidationFacade.get_unverified_header"
      ],
      "filenames": [
        "sap/xssec/jwt_validation_facade.py"
      ]
    },
    {
      "headline": "Use of Broken or Risky Cryptographic Algorithm",
      "analysis": "The codebase uses the HS256 (HMAC with SHA-256) algorithm for JWT signature verification. This algorithm is symmetric, which means the same key is used for signing and verifying the JWT. Using a symmetric key algorithm for JWT verification is considered insecure because it requires sharing the secret key with the verifier, increasing the risk of key compromise. The recommended practice is to use an asymmetric algorithm like RS256 (RSA with SHA-256) for JWT signature verification.\n",
      "classification": "very promising",
      "cwe": "CWE-327",
      "function_names": [
        "sap.xssec.jwt_validation_facade.ALGORITHMS"
      ],
      "filenames": [
        "sap/xssec/jwt_validation_facade.py"
      ]
    },
    {
      "headline": "Improper Restriction of XML External Entity Reference",
      "analysis": "The codebase contains functionality for parsing XML data from untrusted sources, which can lead to XML External Entity (XXE) injection attacks if not properly handled. This vulnerability is tracked under CWE-611.\n",
      "classification": "slightly promising",
      "cwe": "CWE-611",
      "function_names": [],
      "filenames": []
    },
    {
      "headline": "Use of Insecure Random Values",
      "analysis": "The codebase does not appear to include any functionality for generating or using random values, which are essential for cryptographic operations like key generation, nonces, and initialization vectors. If random values are not generated securely, it can lead to vulnerabilities like predictable encryption keys (CWE-330, CWE-331, CWE-335, CWE-338).\n",
      "classification": "slightly promising",
      "cwe": "CWE-330",
      "function_names": [],
      "filenames": []
    },
    {
      "headline": "Improper Certificate Validation",
      "analysis": "The codebase does not appear to include any functionality for validating X.509 certificates used for mutual TLS (mTLS) authentication. Improper validation of certificates can lead to authentication bypass vulnerabilities (CWE-295).\n",
      "classification": "slightly promising",
      "cwe": "CWE-295",
      "function_names": [],
      "filenames": []
    },
    {
      "headline": "Missing Authentication for Critical Function",
      "analysis": "The codebase does not appear to include any functionality for authenticating requests to critical functions or resources. Missing authentication can lead to unauthorized access to sensitive data or functionality (CWE-306).\n",
      "classification": "slightly promising",
      "cwe": "CWE-306",
      "function_names": [],
      "filenames": []
    },
    {
      "headline": "Use of Hard-coded Credentials",
      "analysis": "The codebase does not appear to include any hard-coded credentials, which can lead to unauthorized access if the credentials are discovered (CWE-798).\n",
      "classification": "not promising",
      "cwe": "CWE-798",
      "function_names": [],
      "filenames": []
    },
    {
      "headline": "Improper Neutralization of Input During Web Page Generation",
      "analysis": "The codebase does not appear to include any functionality for generating web pages or handling user input that could be used for Cross-Site Scripting (XSS) attacks (CWE-79).\n",
      "classification": "not promising",
      "cwe": "CWE-79",
      "function_names": [],
      "filenames": []
    },
    {
      "headline": "Insufficient Verification of Data Authenticity",
      "analysis": "The codebase does not appear to include any functionality for verifying the authenticity of data, which can lead to vulnerabilities like Insecure Direct Object References (CWE-639), Cross-Site Request Forgery (CWE-352), and Improper Verification of Cryptographic Signature (CWE-347).\n",
      "classification": "slightly promising",
      "cwe": "CWE-345",
      "function_names": [],
      "filenames": []
    }
  ],
  "scores": [
    {
      "stats": {
        "fn": 1,
        "tp": 0,
        "fp": 2
      },
      "mapping": {},
      "vuln_dates": {
        "CVE-2023-50423": "2023-12-12T02:15:08"
      },
      "scoring_model": "gpt-4o-2024-05-13",
      "type": "llm",
      "instruction_template_hash": "8998f09cf57fca8a6e03"
    },
    {
      "stats": {
        "fn": 0,
        "tp": 1,
        "fp": 1
      },
      "mapping": {
        "0": "CVE-2023-50423"
      },
      "vuln_dates": {
        "CVE-2023-50423": "2023-12-12T02:15:08"
      },
      "scoring_model": "claude-3-opus-20240229",
      "type": "llm",
      "instruction_template_hash": "245ace12b6361954d0a2"
    }
  ],
  "instruction_template_hash": "10c0163db4740318a544",
  "version": "0.1.0"
}
