{
  "commit": "48fe028f3ea4b3e7544f03bce21ed6c93320abd4",
  "repo_url": "https://github.com/mayankmetha/rucky",
  "model": "gemini/gemini-1.5-pro",
  "chunk_hashes": [
    "e4f0e4e8d0741e6f0983"
  ],
  "responses": [
    {
      "content": "```yaml\nleads:\n  - headline: Insecure Storage of Sensitive Information (Private Key and IV)\n    analysis: |\n      The `EditorActivity` class stores the encrypted private key and initialization vector (IV) in SharedPreferences using the `config.setKeyStore1` and `config.setKeyStore2` methods. SharedPreferences is not a secure storage mechanism, as it can be accessed by other apps on the device. This exposes the encrypted private key and IV to potential attackers, who could then decrypt the stored data.\n    cwe: CWE-922\n    function_names:\n      - getKey\n    filenames:\n      - app/src/main/java/com/mayank/rucky/activity/EditorActivity.java\n    classification: slightly promising\n  - headline: Authentication Bypass by Spoofing\n    analysis: |\n      The `USBReceiver` class allows execution of arbitrary commands as root when a USB device is connected, without any authentication or authorization checks. An attacker could potentially create a malicious USB device that, when connected, would trigger the execution of malicious commands on the device.\n    cwe: CWE-290\n    function_names:\n      - onReceive\n    filenames:\n      - app/src/main/java/com/mayank/rucky/receiver/USBReceiver.java\n    classification: slightly promising\n  - headline: Time-of-check Time-of-use (TOCTOU) Race Condition in Root Check\n    analysis: |\n      The `getRoot` method in `USBReceiver` performs a check for root access and then stores a `DataOutputStream` object in a static variable. This creates a potential race condition where an attacker could connect a USB device between the root check and the storage of the `DataOutputStream` object. As a result, the attacker could gain access to the `DataOutputStream` object and execute arbitrary commands as root.\n    cwe: CWE-367\n    function_names:\n      - getRoot\n      - onReceive\n    filenames:\n      - app/src/main/java/com/mayank/rucky/receiver/USBReceiver.java\n    classification: slightly promising\n  - headline: Arbitrary Command Execution via Network Socket\n    analysis: |\n      The `NetSocketReceiver` class allows execution of arbitrary commands from a network socket without any authentication or authorization checks. An attacker who can connect to the specified network socket could send arbitrary commands to the device and execute them with the privileges of the app.\n    cwe: CWE-862\n    function_names:\n      - onReceive\n    filenames:\n      - app/src/main/java/com/mayank/rucky/receiver/NetSocketReceiver.java\n    classification: slightly promising\n  - headline: Insecure File Deletion\n    analysis: |\n      The `hidDelete` and `ide` methods in `EditorActivity` and `HidActivity` use `file.delete()` to delete files. This method is not guaranteed to securely delete the file contents, as the data may still be recoverable from the storage media. An attacker could potentially recover deleted files and gain access to sensitive information.\n    cwe: CWE-212\n    function_names:\n      - hidDelete\n      - ide\n    filenames:\n      - app/src/main/java/com/mayank/rucky/activity/EditorActivity.java\n      - app/src/main/java/com/mayank/rucky/activity/HidActivity.java\n    classification: not promising\n  - headline: Unvalidated Redirect in WebView\n    analysis: |\n      The `shouldOverrideUrlLoading` method in `BrowserActivity` loads any URL without validation. An attacker could potentially redirect the user to a malicious website by sending a specially crafted link.\n    cwe: CWE-601\n    function_names:\n      - shouldOverrideUrlLoading\n    filenames:\n      - app/src/main/java/com/mayank/rucky/activity/BrowserActivity.java\n    classification: not promising\n```",
      "date": "2024-06-14T14:47:58.093557",
      "usage": {
        "prompt_tokens": 37082,
        "completion_tokens": 781,
        "cost": 0.024640625000000003
      }
    }
  ],
  "leads": [
    {
      "headline": "Insecure Storage of Sensitive Information (Private Key and IV)",
      "analysis": "The EditorActivity class stores the encrypted private key and initialization vector (IV) in SharedPreferences using the config.setKeyStore1 and config.setKeyStore2 methods. SharedPreferences is not a secure storage mechanism, as it can be accessed by other apps on the device. This exposes the encrypted private key and IV to potential attackers, who could then decrypt the stored data.\n",
      "classification": "slightly promising",
      "cwe": "CWE-922",
      "function_names": [
        "getKey"
      ],
      "filenames": [
        "app/src/main/java/com/mayank/rucky/activity/EditorActivity.java"
      ]
    },
    {
      "headline": "Authentication Bypass by Spoofing",
      "analysis": "The USBReceiver class allows execution of arbitrary commands as root when a USB device is connected, without any authentication or authorization checks. An attacker could potentially create a malicious USB device that, when connected, would trigger the execution of malicious commands on the device.\n",
      "classification": "slightly promising",
      "cwe": "CWE-290",
      "function_names": [
        "onReceive"
      ],
      "filenames": [
        "app/src/main/java/com/mayank/rucky/receiver/USBReceiver.java"
      ]
    },
    {
      "headline": "Time-of-check Time-of-use (TOCTOU) Race Condition in Root Check",
      "analysis": "The getRoot method in USBReceiver performs a check for root access and then stores a DataOutputStream object in a static variable. This creates a potential race condition where an attacker could connect a USB device between the root check and the storage of the DataOutputStream object. As a result, the attacker could gain access to the DataOutputStream object and execute arbitrary commands as root.\n",
      "classification": "slightly promising",
      "cwe": "CWE-367",
      "function_names": [
        "getRoot",
        "onReceive"
      ],
      "filenames": [
        "app/src/main/java/com/mayank/rucky/receiver/USBReceiver.java"
      ]
    },
    {
      "headline": "Arbitrary Command Execution via Network Socket",
      "analysis": "The NetSocketReceiver class allows execution of arbitrary commands from a network socket without any authentication or authorization checks. An attacker who can connect to the specified network socket could send arbitrary commands to the device and execute them with the privileges of the app.\n",
      "classification": "slightly promising",
      "cwe": "CWE-862",
      "function_names": [
        "onReceive"
      ],
      "filenames": [
        "app/src/main/java/com/mayank/rucky/receiver/NetSocketReceiver.java"
      ]
    },
    {
      "headline": "Insecure File Deletion",
      "analysis": "The hidDelete and ide methods in EditorActivity and HidActivity use file.delete() to delete files. This method is not guaranteed to securely delete the file contents, as the data may still be recoverable from the storage media. An attacker could potentially recover deleted files and gain access to sensitive information.\n",
      "classification": "not promising",
      "cwe": "CWE-212",
      "function_names": [
        "hidDelete",
        "ide"
      ],
      "filenames": [
        "app/src/main/java/com/mayank/rucky/activity/EditorActivity.java",
        "app/src/main/java/com/mayank/rucky/activity/HidActivity.java"
      ]
    },
    {
      "headline": "Unvalidated Redirect in WebView",
      "analysis": "The shouldOverrideUrlLoading method in BrowserActivity loads any URL without validation. An attacker could potentially redirect the user to a malicious website by sending a specially crafted link.\n",
      "classification": "not promising",
      "cwe": "CWE-601",
      "function_names": [
        "shouldOverrideUrlLoading"
      ],
      "filenames": [
        "app/src/main/java/com/mayank/rucky/activity/BrowserActivity.java"
      ]
    }
  ],
  "scores": [
    {
      "stats": {
        "fn": 1,
        "tp": 0,
        "fp": 0
      },
      "mapping": {},
      "vuln_dates": {
        "CVE-2021-41096": "2021-09-27T20:15:07"
      },
      "scoring_model": "claude-3-opus-20240229",
      "type": "llm",
      "instruction_template_hash": "245ace12b6361954d0a2"
    },
    {
      "stats": {
        "fn": 1,
        "tp": 0,
        "fp": 0
      },
      "mapping": {},
      "vuln_dates": {
        "CVE-2021-41096": "2021-09-27T20:15:07"
      },
      "scoring_model": "claude-3-5-sonnet-20240620",
      "type": "llm",
      "instruction_template_hash": "245ace12b6361954d0a2"
    }
  ],
  "instruction_template_hash": "10c0163db4740318a544",
  "version": "0.1.0"
}
