{
  "commit": "2bad9ec73d6ae5ede21df61faad6c254438a2e21",
  "repo_url": "https://github.com/stargate-rewritten/stargate-bukkit",
  "model": "claude-3-sonnet-20240229",
  "chunk_hashes": [
    "c8bfb18261a619f4a661"
  ],
  "responses": [
    {
      "content": "Certainly! Here are the security vulnerabilities I found in the provided codebase, along with their details in the required YAML format:\n\n```yaml\nleads:\n  - headline: Possible Command Injection\n    analysis: The `Gate.loadGate` method reads gate configuration from a file using a `Scanner` object, which could potentially allow an attacker to inject arbitrary commands if the file contents are not sanitized properly. The `scanner.nextLine()` method reads the entire line, including any special characters or commands, which could lead to command injection if the input is not validated or sanitized.\n    cwe: CWE-77\n    function_names:\n      - net.TheDgtl.Stargate.Gate.loadGate\n    filenames:\n      - src/net/TheDgtl/Stargate/Gate.java\n    classification: very promising\n\n  - headline: Potential Path Traversal\n    analysis: The `Portal.loadAllGates` method reads gate data from files in a directory specified by a user-controlled input (`Stargate.getSaveLocation()`). If the input is not properly sanitized, an attacker could potentially traverse the file system and access arbitrary files outside the intended directory.\n    cwe: CWE-22\n    function_names:\n      - net.TheDgtl.Stargate.Portal.loadAllGates\n    filenames:\n      - src/net/TheDgtl/Stargate/Portal.java\n    classification: very promising\n\n  - headline: Use of Insecure Random Number Generator\n    analysis: The `Portal.cycleDestination` method uses the `Random` class to generate a random index for the `destinations` list. However, the `Random` class is considered a weak pseudo-random number generator and should not be used for security-sensitive applications. An attacker could potentially predict or manipulate the generated random numbers, leading to security vulnerabilities.\n    cwe: CWE-338\n    function_names:\n      - net.TheDgtl.Stargate.Portal.cycleDestination\n    filenames:\n      - src/net/TheDgtl/Stargate/Portal.java\n    classification: slightly promising\n\n  - headline: Potential Command Injection\n    analysis: The `Stargate.onCommand` method uses the `Runtime.exec` method to execute system commands. If the command input is not properly sanitized, an attacker could potentially inject arbitrary commands, leading to command injection vulnerabilities.\n    cwe: CWE-77\n    function_names:\n      - net.TheDgtl.Stargate.Stargate.onCommand\n    filenames:\n      - src/net/TheDgtl/Stargate/Stargate.java\n    classification: very promising\n\n  - headline: Use of Insecure Cryptographic Algorithm\n    analysis: The `EconomyHandler` class appears to be using the `Random` class to generate random values, which is not a secure method for generating cryptographic keys or other security-sensitive data. The use of insecure cryptographic algorithms or weak random number generators can lead to security vulnerabilities.\n    cwe: CWE-327\n    function_names:\n      - net.TheDgtl.Stargate.EconomyHandler.chargePlayer\n    filenames:\n      - src/net/TheDgtl/Stargate/EconomyHandler.java\n    classification: slightly promising\n\n  - headline: Potential Path Traversal\n    analysis: The `LangLoader.load` method reads language files from a directory specified by a user-controlled input (`datFolder`). If the input is not properly sanitized, an attacker could potentially traverse the file system and access arbitrary files outside the intended directory.\n    cwe: CWE-22\n    function_names:\n      - net.TheDgtl.Stargate.LangLoader.load\n    filenames:\n      - src/net/TheDgtl/Stargate/LangLoader.java\n    classification: very promising\n```\n\nPlease note that these are potential vulnerabilities identified based on the provided code. Further analysis and testing would be required to confirm the exploitability and impact of these vulnerabilities in the actual application context.",
      "date": "2024-06-13T12:02:15.601536",
      "usage": {
        "prompt_tokens": 48665,
        "completion_tokens": 961,
        "cost": 0.16041
      }
    }
  ],
  "leads": [
    {
      "headline": "Possible Command Injection",
      "analysis": "The Gate.loadGate method reads gate configuration from a file using a Scanner object, which could potentially allow an attacker to inject arbitrary commands if the file contents are not sanitized properly. The scanner.nextLine() method reads the entire line, including any special characters or commands, which could lead to command injection if the input is not validated or sanitized.",
      "classification": "very promising",
      "cwe": "CWE-77",
      "function_names": [
        "net.TheDgtl.Stargate.Gate.loadGate"
      ],
      "filenames": [
        "src/net/TheDgtl/Stargate/Gate.java"
      ]
    },
    {
      "headline": "Potential Path Traversal",
      "analysis": "The Portal.loadAllGates method reads gate data from files in a directory specified by a user-controlled input (Stargate.getSaveLocation()). If the input is not properly sanitized, an attacker could potentially traverse the file system and access arbitrary files outside the intended directory.",
      "classification": "very promising",
      "cwe": "CWE-22",
      "function_names": [
        "net.TheDgtl.Stargate.Portal.loadAllGates"
      ],
      "filenames": [
        "src/net/TheDgtl/Stargate/Portal.java"
      ]
    },
    {
      "headline": "Use of Insecure Random Number Generator",
      "analysis": "The Portal.cycleDestination method uses the Random class to generate a random index for the destinations list. However, the Random class is considered a weak pseudo-random number generator and should not be used for security-sensitive applications. An attacker could potentially predict or manipulate the generated random numbers, leading to security vulnerabilities.",
      "classification": "slightly promising",
      "cwe": "CWE-338",
      "function_names": [
        "net.TheDgtl.Stargate.Portal.cycleDestination"
      ],
      "filenames": [
        "src/net/TheDgtl/Stargate/Portal.java"
      ]
    },
    {
      "headline": "Potential Command Injection",
      "analysis": "The Stargate.onCommand method uses the Runtime.exec method to execute system commands. If the command input is not properly sanitized, an attacker could potentially inject arbitrary commands, leading to command injection vulnerabilities.",
      "classification": "very promising",
      "cwe": "CWE-77",
      "function_names": [
        "net.TheDgtl.Stargate.Stargate.onCommand"
      ],
      "filenames": [
        "src/net/TheDgtl/Stargate/Stargate.java"
      ]
    },
    {
      "headline": "Use of Insecure Cryptographic Algorithm",
      "analysis": "The EconomyHandler class appears to be using the Random class to generate random values, which is not a secure method for generating cryptographic keys or other security-sensitive data. The use of insecure cryptographic algorithms or weak random number generators can lead to security vulnerabilities.",
      "classification": "slightly promising",
      "cwe": "CWE-327",
      "function_names": [
        "net.TheDgtl.Stargate.EconomyHandler.chargePlayer"
      ],
      "filenames": [
        "src/net/TheDgtl/Stargate/EconomyHandler.java"
      ]
    },
    {
      "headline": "Potential Path Traversal",
      "analysis": "The LangLoader.load method reads language files from a directory specified by a user-controlled input (datFolder). If the input is not properly sanitized, an attacker could potentially traverse the file system and access arbitrary files outside the intended directory.",
      "classification": "very promising",
      "cwe": "CWE-22",
      "function_names": [
        "net.TheDgtl.Stargate.LangLoader.load"
      ],
      "filenames": [
        "src/net/TheDgtl/Stargate/LangLoader.java"
      ]
    }
  ],
  "scores": [
    {
      "stats": {
        "fn": 1,
        "tp": 0,
        "fp": 4
      },
      "mapping": {},
      "vuln_dates": {
        "CVE-2021-43819": "2023-04-19T18:15:07"
      },
      "scoring_model": "claude-3-opus-20240229",
      "type": "llm",
      "instruction_template_hash": "245ace12b6361954d0a2"
    }
  ],
  "instruction_template_hash": "10c0163db4740318a544",
  "version": "0.1.0"
}
