{
  "commit": "085bb77ca3b493eb28c9ea0930e2e39c5a7bb72d",
  "repo_url": "https://github.com/tankywoo/simiki",
  "model": "claude-3-sonnet-20240229",
  "chunk_hashes": [
    "8b62a295714d576b3f09"
  ],
  "responses": [
    {
      "content": "```yaml\nleads:\n  - headline: Failure to sanitize user input leads to code injection\n    analysis: |\n      The code does not properly sanitize user input when generating new wiki pages, leaving it vulnerable to code injection attacks. An attacker could craft a malicious filename containing code that would be executed on the server when creating the new file.\n    cwe: CWE-94\n    function_names:\n      - create_new_wiki\n    filenames:\n      - simiki/cli.py\n    classification: very promising\n\n  - headline: Use of insecure defaults in deployed configuration\n    analysis: |\n      The default configuration in simiki/config.py sets the 'debug' option to True, which could potentially expose sensitive information to attackers if this default is deployed to a production system.\n    cwe: CWE-1188\n    function_names: []\n    filenames:\n      - simiki/config.py\n    classification: very promising\n\n  - headline: Potential remote code execution via unsafe YAML load\n    analysis: |\n      The code uses the yaml.load() function to parse configuration files, which can be unsafe if the YAML input is not properly validated. An attacker could potentially construct a malicious YAML file that causes arbitrary code execution on the server.\n    cwe: CWE-94\n    function_names: \n      - parse_config\n    filenames:\n      - simiki/config.py\n    classification: slightly promising\n\n  - headline: Use of hardcoded credentials in fabfile\n    analysis: |\n      The fabfile.py script contains functionality to deploy the wiki via FTP, with the ability to hardcode FTP passwords in the configuration. This could potentially expose credentials if this file is committed to a public repository.\n    cwe: CWE-798\n    function_names:\n      - deploy_ftp\n    filenames:\n      - simiki/conf_templates/fabfile.py \n    classification: slightly promising\n      \n  - headline: Improper input validation for filenames\n    analysis: |\n      The code does not properly validate filenames when creating new wiki pages, which could allow path traversal attacks if an attacker is able to control the filename.\n    cwe: CWE-22\n    function_names:\n      - create_new_wiki\n    filenames:  \n      - simiki/cli.py\n    classification: slightly promising\n      \n  - headline: Potential unquoted path vulnerabilities \n    analysis: |\n      The simiki.utils.copytree function concatenates paths in an unsafe way that could be vulnerable to unquoted path attacks if the inputs are not properly sanitized.\n    cwe: CWE-428\n    function_names:\n      - copytree\n    filenames:\n      - simiki/utils.py\n    classification: slightly promising\n```\n\nThe codebase has several security vulnerabilities:\n\n1. **Code injection (CWE-94)**: The `create_new_wiki` function in cli.py does not sanitize user input when creating new wiki pages, allowing an attacker to potentially inject malicious code.\n\n2. **Insecure defaults (CWE-1188)**: The default configuration in config.py sets 'debug' to True, which could expose sensitive information if deployed to production environments. \n\n3. **Unsafe YAML loading (CWE-94)**: The `parse_config` function in config.py uses `yaml.load` which is unsafe if the YAML input is not properly validated, potentially enabling code execution.\n\n4. **Hardcoded credentials (CWE-798)**: The `deploy_ftp` function in fabfile.py allows hardcoding FTP passwords, which could expose credentials.\n\n5. **Path traversal (CWE-22)**: Insufficient validation of filenames in `create_new_wiki` could enable path traversal attacks.\n\n6. **Unquoted paths (CWE-428)**: The `copytree` function in utils.py concatenates paths unsafely, potentially enabling unquoted path vulnerabilities.\n\nThe most promising vulnerability is the code injection in `create_new_wiki`, as it could enable remote code execution. The insecure defaults and unsafe YAML loading are also very concerning from a security perspective. The other vulnerabilities, while valid, are slightly less severe.",
      "date": "2024-06-13T17:12:27.566337",
      "usage": {
        "prompt_tokens": 38174,
        "completion_tokens": 988,
        "cost": 0.129342
      }
    }
  ],
  "leads": [
    {
      "headline": "Failure to sanitize user input leads to code injection",
      "analysis": "The code does not properly sanitize user input when generating new wiki pages, leaving it vulnerable to code injection attacks. An attacker could craft a malicious filename containing code that would be executed on the server when creating the new file.\n",
      "classification": "very promising",
      "cwe": "CWE-94",
      "function_names": [
        "create_new_wiki"
      ],
      "filenames": [
        "simiki/cli.py"
      ]
    },
    {
      "headline": "Use of insecure defaults in deployed configuration",
      "analysis": "The default configuration in simiki/config.py sets the 'debug' option to True, which could potentially expose sensitive information to attackers if this default is deployed to a production system.\n",
      "classification": "very promising",
      "cwe": "CWE-1188",
      "function_names": [],
      "filenames": [
        "simiki/config.py"
      ]
    },
    {
      "headline": "Potential remote code execution via unsafe YAML load",
      "analysis": "The code uses the yaml.load() function to parse configuration files, which can be unsafe if the YAML input is not properly validated. An attacker could potentially construct a malicious YAML file that causes arbitrary code execution on the server.\n",
      "classification": "slightly promising",
      "cwe": "CWE-94",
      "function_names": [
        "parse_config"
      ],
      "filenames": [
        "simiki/config.py"
      ]
    },
    {
      "headline": "Use of hardcoded credentials in fabfile",
      "analysis": "The fabfile.py script contains functionality to deploy the wiki via FTP, with the ability to hardcode FTP passwords in the configuration. This could potentially expose credentials if this file is committed to a public repository.\n",
      "classification": "slightly promising",
      "cwe": "CWE-798",
      "function_names": [
        "deploy_ftp"
      ],
      "filenames": [
        "simiki/conf_templates/fabfile.py"
      ]
    },
    {
      "headline": "Improper input validation for filenames",
      "analysis": "The code does not properly validate filenames when creating new wiki pages, which could allow path traversal attacks if an attacker is able to control the filename.\n",
      "classification": "slightly promising",
      "cwe": "CWE-22",
      "function_names": [
        "create_new_wiki"
      ],
      "filenames": [
        "simiki/cli.py"
      ]
    },
    {
      "headline": "Potential unquoted path vulnerabilities",
      "analysis": "The simiki.utils.copytree function concatenates paths in an unsafe way that could be vulnerable to unquoted path attacks if the inputs are not properly sanitized.\n",
      "classification": "slightly promising",
      "cwe": "CWE-428",
      "function_names": [
        "copytree"
      ],
      "filenames": [
        "simiki/utils.py"
      ]
    }
  ],
  "scores": [
    {
      "stats": {
        "fn": 2,
        "tp": 0,
        "fp": 2
      },
      "mapping": {},
      "vuln_dates": {
        "CVE-2020-19001": "2021-08-27T19:15:07",
        "CVE-2020-19000": "2021-08-27T19:15:07"
      },
      "scoring_model": "claude-3-opus-20240229",
      "type": "llm",
      "instruction_template_hash": "245ace12b6361954d0a2"
    }
  ],
  "instruction_template_hash": "10c0163db4740318a544",
  "version": "0.1.0"
}
