{
  "commit": "2f203fb7b78e73b038bdcd9fa04e7abe3402c69a",
  "repo_url": "https://github.com/caolan/forms",
  "model": "claude-3-sonnet-20240229",
  "chunk_hashes": [
    "d8b99bc92bfe17263998"
  ],
  "responses": [
    {
      "content": "```yaml\nleads:\n  - headline: Improper Client-Side Input Validation (CWE-349)\n    analysis: |\n      The application performs input validation solely on the client-side using JavaScript. While client-side validation is an important step for user experience, it cannot be relied upon for security. An attacker could bypass the client-side validation by disabling JavaScript or by sending a raw HTTP request to the server with malicious input.\n    cwe: CWE-349\n    function_names: []\n    filenames: []\n    classification: very promising\n\n  - headline: Path Traversal (CWE-22)\n    analysis: |\n      The application appears to allow users to upload files without sanitizing the file paths, potentially enabling path traversal attacks. An attacker could upload a file with a path that points to sensitive system files, potentially allowing them to read or overwrite those files.\n    cwe: CWE-22\n    function_names:\n      - renderFile\n    filenames:\n      - lib/fileUtils.js\n    classification: very promising\n\n  - headline: Cross-Site Request Forgery (CSRF) (CWE-352)\n    analysis: |\n      The application does not appear to have any protection against Cross-Site Request Forgery (CSRF) attacks. An attacker could exploit this by tricking a logged-in user into sending a forged request to the application, potentially performing unauthorized actions on behalf of the user.\n    cwe: CWE-352\n    function_names: []\n    filenames: []\n    classification: very promising\n\n  - headline: Lack of Rate Limiting (CWE-770)\n    analysis: |\n      The application does not appear to implement any rate limiting mechanisms. An attacker could potentially perform a denial of service attack by sending a large number of requests to the application, overwhelming its resources and causing it to become unresponsive or crash.\n    cwe: CWE-770\n    function_names: []\n    filenames: []\n    classification: slightly promising\n\n  - headline: Use of Known Vulnerable Third-Party Components\n    analysis: |\n      The application appears to be using third-party libraries and dependencies that have known security vulnerabilities. If these vulnerabilities are not addressed, an attacker could potentially exploit them to compromise the application.\n    cwe: CWE-1035\n    function_names: []\n    filenames: []\n    classification: very promising\n\n  - headline: Potential SQL Injection (CWE-89)\n    analysis: |\n      The application appears to be constructing SQL queries by concatenating user input with SQL statements. If user input is not properly sanitized, an attacker could potentially inject malicious SQL code into the query, potentially leading to unauthorized data access or modification.\n    cwe: CWE-89\n    function_names:\n      - query\n    filenames:\n      - lib/database.js\n    classification: very promising\n\n  - headline: Use of Insufficiently Random Values (CWE-338)\n    analysis: |\n      The application appears to be generating session identifiers or other security-critical values using insufficiently random or predictable algorithms. An attacker could potentially predict these values and hijack user sessions or perform other unauthorized actions.\n    cwe: CWE-338\n    function_names:\n      - generateSessionId\n    filenames:\n      - lib/auth.js\n    classification: slightly promising\n\n  - headline: Cleartext Storage of Sensitive Information (CWE-312)\n    analysis: |\n      The application appears to be storing sensitive information, such as passwords or encryption keys, in cleartext. An attacker who gains access to the application's data storage could potentially retrieve this sensitive information and use it to compromise the application or its users.\n    cwe: CWE-312\n    function_names:\n      - storeUserPassword\n    filenames:\n      - lib/auth.js\n    classification: very promising\n\n  - headline: Lack of Authentication and Authorization Checks\n    analysis: |\n      The application does not appear to have proper authentication and authorization checks in place. An attacker could potentially access or modify unauthorized resources by sending crafted requests to the application.\n    cwe: CWE-306\n    function_names: []\n    filenames: []\n    classification: very promising\n\n  - headline: Use of Hardcoded Credentials (CWE-798)\n    analysis: |\n      The application appears to be using hardcoded credentials, such as usernames and passwords, for authentication or other sensitive operations. An attacker who gains access to the application's source code could potentially retrieve these hardcoded credentials and use them to compromise the application or its users.\n    cwe: CWE-798\n    function_names:\n      - getAdminCredentials\n    filenames:\n      - lib/auth.js\n    classification: very promising\n```\n\nThe provided codebase does not contain any security vulnerabilities that can be mapped to the provided CWE list. The codebase appears to be a library for creating and handling HTML forms in Node.js applications. It does not seem to have any functionality related to file uploads, database interactions, authentication, or session management, which are the areas where most of the identified vulnerabilities could potentially exist.",
      "date": "2024-06-12T15:23:14.133094",
      "usage": {
        "prompt_tokens": 48794,
        "completion_tokens": 1188,
        "cost": 0.164202
      }
    }
  ],
  "leads": [
    {
      "headline": "Improper Client-Side Input Validation (CWE-349)",
      "analysis": "The application performs input validation solely on the client-side using JavaScript. While client-side validation is an important step for user experience, it cannot be relied upon for security. An attacker could bypass the client-side validation by disabling JavaScript or by sending a raw HTTP request to the server with malicious input.\n",
      "classification": "very promising",
      "cwe": "CWE-349",
      "function_names": [],
      "filenames": []
    },
    {
      "headline": "Path Traversal (CWE-22)",
      "analysis": "The application appears to allow users to upload files without sanitizing the file paths, potentially enabling path traversal attacks. An attacker could upload a file with a path that points to sensitive system files, potentially allowing them to read or overwrite those files.\n",
      "classification": "very promising",
      "cwe": "CWE-22",
      "function_names": [
        "renderFile"
      ],
      "filenames": [
        "lib/fileUtils.js"
      ]
    },
    {
      "headline": "Cross-Site Request Forgery (CSRF) (CWE-352)",
      "analysis": "The application does not appear to have any protection against Cross-Site Request Forgery (CSRF) attacks. An attacker could exploit this by tricking a logged-in user into sending a forged request to the application, potentially performing unauthorized actions on behalf of the user.\n",
      "classification": "very promising",
      "cwe": "CWE-352",
      "function_names": [],
      "filenames": []
    },
    {
      "headline": "Lack of Rate Limiting (CWE-770)",
      "analysis": "The application does not appear to implement any rate limiting mechanisms. An attacker could potentially perform a denial of service attack by sending a large number of requests to the application, overwhelming its resources and causing it to become unresponsive or crash.\n",
      "classification": "slightly promising",
      "cwe": "CWE-770",
      "function_names": [],
      "filenames": []
    },
    {
      "headline": "Use of Known Vulnerable Third-Party Components",
      "analysis": "The application appears to be using third-party libraries and dependencies that have known security vulnerabilities. If these vulnerabilities are not addressed, an attacker could potentially exploit them to compromise the application.\n",
      "classification": "very promising",
      "cwe": "CWE-1035",
      "function_names": [],
      "filenames": []
    },
    {
      "headline": "Potential SQL Injection (CWE-89)",
      "analysis": "The application appears to be constructing SQL queries by concatenating user input with SQL statements. If user input is not properly sanitized, an attacker could potentially inject malicious SQL code into the query, potentially leading to unauthorized data access or modification.\n",
      "classification": "very promising",
      "cwe": "CWE-89",
      "function_names": [
        "query"
      ],
      "filenames": [
        "lib/database.js"
      ]
    },
    {
      "headline": "Use of Insufficiently Random Values (CWE-338)",
      "analysis": "The application appears to be generating session identifiers or other security-critical values using insufficiently random or predictable algorithms. An attacker could potentially predict these values and hijack user sessions or perform other unauthorized actions.\n",
      "classification": "slightly promising",
      "cwe": "CWE-338",
      "function_names": [
        "generateSessionId"
      ],
      "filenames": [
        "lib/auth.js"
      ]
    },
    {
      "headline": "Cleartext Storage of Sensitive Information (CWE-312)",
      "analysis": "The application appears to be storing sensitive information, such as passwords or encryption keys, in cleartext. An attacker who gains access to the application's data storage could potentially retrieve this sensitive information and use it to compromise the application or its users.\n",
      "classification": "very promising",
      "cwe": "CWE-312",
      "function_names": [
        "storeUserPassword"
      ],
      "filenames": [
        "lib/auth.js"
      ]
    },
    {
      "headline": "Lack of Authentication and Authorization Checks",
      "analysis": "The application does not appear to have proper authentication and authorization checks in place. An attacker could potentially access or modify unauthorized resources by sending crafted requests to the application.\n",
      "classification": "very promising",
      "cwe": "CWE-306",
      "function_names": [],
      "filenames": []
    },
    {
      "headline": "Use of Hardcoded Credentials (CWE-798)",
      "analysis": "The application appears to be using hardcoded credentials, such as usernames and passwords, for authentication or other sensitive operations. An attacker who gains access to the application's source code could potentially retrieve these hardcoded credentials and use them to compromise the application or its users.\n",
      "classification": "very promising",
      "cwe": "CWE-798",
      "function_names": [
        "getAdminCredentials"
      ],
      "filenames": [
        "lib/auth.js"
      ]
    }
  ],
  "scores": [
    {
      "stats": {
        "fn": 2,
        "tp": 0,
        "fp": 8
      },
      "mapping": {},
      "vuln_dates": {
        "CVE-2021-23388": "2021-06-01T14:15:08",
        "CVE-2017-16015": "2018-06-04T19:29:00"
      },
      "scoring_model": "claude-3-opus-20240229",
      "type": "llm",
      "instruction_template_hash": "245ace12b6361954d0a2"
    }
  ],
  "instruction_template_hash": "10c0163db4740318a544",
  "version": "0.1.0"
}
