{
  "commit": "1f77a34b7ae04b16efb17fdbaaa0f8e7ad48c33a",
  "repo_url": "https://github.com/jenkinsci/codefresh-plugin",
  "model": "gpt-4-turbo-2024-04-09",
  "chunk_hashes": [
    "ae85d3b83f14a1748b7b"
  ],
  "responses": [
    {
      "content": "```yaml\nleads:\n  - headline: Exposure of sensitive token through source code in test configurations\n    analysis: |\n      The exposed sensitive token in the commented code within CFPipelineBuilderTest.java is a security threat as it provides direct access to the system with specified credentials. This hardcoded token can be used by malicious actors if the code is exposed publicly through version control systems or other means.\n    cwe: CWE-798\n    function_names:\n      - first\n    filenames:\n      - src/test/java/org/jenkinsci/plugins/codefresh/CFPipelineBuilderTest.java\n    classification: very promising\n\n  - headline: Use of Insecure HTTP protocol in API connections, risking the interception of data\n    analysis: |\n      The CFApi.java file facilitates connections to the Codefresh API using both HTTP and HTTPS based on configuration but defaults to insecure HTTP when HTTPS configuration fails or is not enforced, permitting Man-in-the-Middle (MITM) attacks where an attacker could intercept or tamper with data going to and from the API.\n    cwe: CWE-319\n    function_names:\n      - getConnection\n    filenames:\n      - src/main/java/org/jenkinsci/plugins/codefresh/CFApi.java\n    classification: slightly promising\n\n  - headline: Inadequate exception handling in API responses\n    analysis: |\n      The CFApi.java file contains methods such as getConnection and launchComposition where IOExceptions are caught but the system continues to execute potentially leading to undefined system states or further processing with incomplete or compromised data integrity.\n    cwe: CWE-390\n    function_names:\n      - launchComposition\n      - getConnection\n    filenames:\n      - src/main/java/org/jenkinsci/plugins/codefresh/CFApi.java\n    classification: slightly promising\n\n  - headline: Use of hardcoded credentials as part of configuration testing\n    analysis: |\n      In the CFGlobalConfig.java, there is functionality to test the connection to an external system using hardcoded or user-provided credentials directly within the application logic, making the system rigid and insecure, as credentials are more susceptible to being leaked or mishandled.\n    cwe: CWE-259\n    function_names:\n      - doTestConnection\n    filenames:\n      - src/main/java/org/jenkinsci/plugins/codefresh/CFGlobalConfig.java\n    classification: slightly promising\n\n  - headline: Insufficient validation of untrusted input leading to unauthorized API calls\n    analysis: |\n      The CFApi.java class methods such as getProcess and startBuild do not properly validate the integrity and authenticity of inputs before making critical API calls, potentially allowing attackers to inject or manipulate API calls.\n    cwe: CWE-345\n    function_names:\n      - getProcess\n      - startBuild\n    filenames:\n      - src/main/java/org/jenkinsci/plugins/codefresh/CFApi.java\n    classification: very promising\n\n  - headline: Lack of encryption in data transmission and storage\n    analysis: |\n      The plugin configuration allows data to be transmitted over channels without enforcing encryption, visible in the lack of compulsory HTTPS usage in CFApi.java and the storage of sensitive information like tokens in potentially unencrypted forms within the CFGlobalConfig.java.\n    cwe: CWE-311\n    function_names:\n      - getConnection\n    filenames:\n      - src/main/java/org/jenkinsci/plugins/codefresh/CFApi.java\n      - src/main/java/org/jenkinsci/plugins/codefresh/CFGlobalConfig.java\n    classification: slightly promising\n\n  - headline: Improper handling of URL redirection potential exposing to phishing attacks\n    analysis: |\n      The classes handling external API calls and webhook interactions can be manipulated to redirect users or services to malicious destinations, deducting from missing URL validation logic.\n    cwe: CWE-601\n    function_names:\n      - getConnection\n    filenames:\n      - src/main/java/org/jenkinsci/plugins/codefresh/CFApi.java\n    classification: slightly promising\n```",
      "date": "2024-06-12T18:04:42.674790",
      "usage": {
        "prompt_tokens": 17925,
        "completion_tokens": 802,
        "cost": 0.20331
      }
    }
  ],
  "leads": [
    {
      "headline": "Exposure of sensitive token through source code in test configurations",
      "analysis": "The exposed sensitive token in the commented code within CFPipelineBuilderTest.java is a security threat as it provides direct access to the system with specified credentials. This hardcoded token can be used by malicious actors if the code is exposed publicly through version control systems or other means.\n",
      "classification": "very promising",
      "cwe": "CWE-798",
      "function_names": [
        "first"
      ],
      "filenames": [
        "src/test/java/org/jenkinsci/plugins/codefresh/CFPipelineBuilderTest.java"
      ]
    },
    {
      "headline": "Use of Insecure HTTP protocol in API connections, risking the interception of data",
      "analysis": "The CFApi.java file facilitates connections to the Codefresh API using both HTTP and HTTPS based on configuration but defaults to insecure HTTP when HTTPS configuration fails or is not enforced, permitting Man-in-the-Middle (MITM) attacks where an attacker could intercept or tamper with data going to and from the API.\n",
      "classification": "slightly promising",
      "cwe": "CWE-319",
      "function_names": [
        "getConnection"
      ],
      "filenames": [
        "src/main/java/org/jenkinsci/plugins/codefresh/CFApi.java"
      ]
    },
    {
      "headline": "Inadequate exception handling in API responses",
      "analysis": "The CFApi.java file contains methods such as getConnection and launchComposition where IOExceptions are caught but the system continues to execute potentially leading to undefined system states or further processing with incomplete or compromised data integrity.\n",
      "classification": "slightly promising",
      "cwe": "CWE-390",
      "function_names": [
        "launchComposition",
        "getConnection"
      ],
      "filenames": [
        "src/main/java/org/jenkinsci/plugins/codefresh/CFApi.java"
      ]
    },
    {
      "headline": "Use of hardcoded credentials as part of configuration testing",
      "analysis": "In the CFGlobalConfig.java, there is functionality to test the connection to an external system using hardcoded or user-provided credentials directly within the application logic, making the system rigid and insecure, as credentials are more susceptible to being leaked or mishandled.\n",
      "classification": "slightly promising",
      "cwe": "CWE-259",
      "function_names": [
        "doTestConnection"
      ],
      "filenames": [
        "src/main/java/org/jenkinsci/plugins/codefresh/CFGlobalConfig.java"
      ]
    },
    {
      "headline": "Insufficient validation of untrusted input leading to unauthorized API calls",
      "analysis": "The CFApi.java class methods such as getProcess and startBuild do not properly validate the integrity and authenticity of inputs before making critical API calls, potentially allowing attackers to inject or manipulate API calls.\n",
      "classification": "very promising",
      "cwe": "CWE-345",
      "function_names": [
        "getProcess",
        "startBuild"
      ],
      "filenames": [
        "src/main/java/org/jenkinsci/plugins/codefresh/CFApi.java"
      ]
    },
    {
      "headline": "Lack of encryption in data transmission and storage",
      "analysis": "The plugin configuration allows data to be transmitted over channels without enforcing encryption, visible in the lack of compulsory HTTPS usage in CFApi.java and the storage of sensitive information like tokens in potentially unencrypted forms within the CFGlobalConfig.java.\n",
      "classification": "slightly promising",
      "cwe": "CWE-311",
      "function_names": [
        "getConnection"
      ],
      "filenames": [
        "src/main/java/org/jenkinsci/plugins/codefresh/CFApi.java",
        "src/main/java/org/jenkinsci/plugins/codefresh/CFGlobalConfig.java"
      ]
    },
    {
      "headline": "Improper handling of URL redirection potential exposing to phishing attacks",
      "analysis": "The classes handling external API calls and webhook interactions can be manipulated to redirect users or services to malicious destinations, deducting from missing URL validation logic.\n",
      "classification": "slightly promising",
      "cwe": "CWE-601",
      "function_names": [
        "getConnection"
      ],
      "filenames": [
        "src/main/java/org/jenkinsci/plugins/codefresh/CFApi.java"
      ]
    }
  ],
  "scores": [
    {
      "stats": {
        "fn": 1,
        "tp": 0,
        "fp": 2
      },
      "mapping": {},
      "vuln_dates": {
        "CVE-2019-10381": "2019-08-07T15:15:13"
      },
      "scoring_model": "claude-3-opus-20240229",
      "type": "llm",
      "instruction_template_hash": "245ace12b6361954d0a2"
    },
    {
      "stats": {
        "fn": 1,
        "tp": 0,
        "fp": 2
      },
      "mapping": {},
      "vuln_dates": {
        "CVE-2019-10381": "2019-08-07T15:15:13"
      },
      "scoring_model": "claude-3-5-sonnet-20240620",
      "type": "llm",
      "instruction_template_hash": "245ace12b6361954d0a2"
    }
  ],
  "instruction_template_hash": "10c0163db4740318a544",
  "version": "0.1.0"
}
