{
  "commit": "d1cf36c67c2aa0e76882a08a5cd878b3306e0671",
  "repo_url": "https://github.com/vantage6/vantage6-ui",
  "model": "gpt-4o-2024-05-13",
  "chunk_hashes": [
    "ed70b5454075361027ed"
  ],
  "responses": [
    {
      "content": "```yaml\nleads:\n  - headline: Missing Authorization\n    analysis: |\n      The application lacks proper authorization checks in several components, potentially allowing unauthorized users to access restricted areas and perform actions they shouldn't be able to.\n    cwe: CWE-862\n    function_names:\n      - canActivate\n    filenames:\n      - src/app/auth/access-guard.guard.ts\n    classification: very promising\n\n  - headline: Weak Password Requirements\n    analysis: |\n      The application's password requirements are weak, which could allow attackers to use easily guessable passwords for gaining unauthorized access.\n    cwe: CWE-521\n    function_names:\n      - savePassword\n    filenames:\n      - src/app/components/edit/user-edit/change-password/change-password.component.ts\n    classification: very promising\n\n  - headline: Insufficient Authentication\n    analysis: |\n      The authentication mechanism doesn't employ sufficient measures to validate user identities robustly, which might allow attackers to authenticate without proper credentials.\n    cwe: CWE-287\n    function_names:\n      - login\n    filenames:\n      - src/app/components/login/login/login.component.ts\n    classification: very promising\n\n  - headline: Insufficient Input Validation\n    analysis: |\n      Several parts of the application rely on user-supplied input without proper validation, which could lead to various vulnerabilities like injection attacks or malformed data processing.\n    cwe: CWE-20\n    function_names:\n      - save\n    filenames:\n      - src/app/services/api/user-api.service.ts\n    classification: very promising\n\n  - headline: Cross-Site Request Forgery (CSRF)\n    analysis: |\n      The application does not implement mechanisms to protect against CSRF attacks, allowing attackers to execute actions on behalf of authenticated users without their consent.\n    cwe: CWE-352\n    function_names:\n      - tokenStorageService\n    filenames:\n      - src/app/services/common/token-storage.service.ts\n    classification: slightly promising\n\n  - headline: Cleartext Transmission of Sensitive Information\n    analysis: |\n      Sensitive information such as passwords or tokens are being transmitted in clear text, which can be intercepted by attackers to gain unauthorized access.\n    cwe: CWE-319\n    function_names:\n      - change_password\n    filenames:\n      - src/app/services/api/user-api.service.ts\n    classification: very promising\n\n  - headline: Missing Encryption of Sensitive Data\n    analysis: |\n      The application stores sensitive data without encryption, thereby exposing it to unauthorized access in case of a data breach.\n    cwe: CWE-311\n    function_names:\n      - saveToken\n    filenames:\n      - src/app/services/common/token-storage.service.ts\n    classification: very promising\n\n  - headline: Server-Side Request Forgery (SSRF)\n    analysis: |\n      The application processes URLs in a way that could be exploited to access unauthorized internal resources.\n    cwe: CWE-918\n    function_names:\n      - save\n    filenames:\n      - src/app/services/api/task-api.service.ts\n    classification: slightly promising\n```",
      "date": "2024-06-09T15:22:13.375588",
      "usage": {
        "prompt_tokens": 114340,
        "completion_tokens": 619,
        "cost": 0.580985
      }
    }
  ],
  "leads": [
    {
      "headline": "Missing Authorization",
      "analysis": "The application lacks proper authorization checks in several components, potentially allowing unauthorized users to access restricted areas and perform actions they shouldn't be able to.\n",
      "classification": "very promising",
      "cwe": "CWE-862",
      "function_names": [
        "canActivate"
      ],
      "filenames": [
        "src/app/auth/access-guard.guard.ts"
      ]
    },
    {
      "headline": "Weak Password Requirements",
      "analysis": "The application's password requirements are weak, which could allow attackers to use easily guessable passwords for gaining unauthorized access.\n",
      "classification": "very promising",
      "cwe": "CWE-521",
      "function_names": [
        "savePassword"
      ],
      "filenames": [
        "src/app/components/edit/user-edit/change-password/change-password.component.ts"
      ]
    },
    {
      "headline": "Insufficient Authentication",
      "analysis": "The authentication mechanism doesn't employ sufficient measures to validate user identities robustly, which might allow attackers to authenticate without proper credentials.\n",
      "classification": "very promising",
      "cwe": "CWE-287",
      "function_names": [
        "login"
      ],
      "filenames": [
        "src/app/components/login/login/login.component.ts"
      ]
    },
    {
      "headline": "Insufficient Input Validation",
      "analysis": "Several parts of the application rely on user-supplied input without proper validation, which could lead to various vulnerabilities like injection attacks or malformed data processing.\n",
      "classification": "very promising",
      "cwe": "CWE-20",
      "function_names": [
        "save"
      ],
      "filenames": [
        "src/app/services/api/user-api.service.ts"
      ]
    },
    {
      "headline": "Cross-Site Request Forgery (CSRF)",
      "analysis": "The application does not implement mechanisms to protect against CSRF attacks, allowing attackers to execute actions on behalf of authenticated users without their consent.\n",
      "classification": "slightly promising",
      "cwe": "CWE-352",
      "function_names": [
        "tokenStorageService"
      ],
      "filenames": [
        "src/app/services/common/token-storage.service.ts"
      ]
    },
    {
      "headline": "Cleartext Transmission of Sensitive Information",
      "analysis": "Sensitive information such as passwords or tokens are being transmitted in clear text, which can be intercepted by attackers to gain unauthorized access.\n",
      "classification": "very promising",
      "cwe": "CWE-319",
      "function_names": [
        "change_password"
      ],
      "filenames": [
        "src/app/services/api/user-api.service.ts"
      ]
    },
    {
      "headline": "Missing Encryption of Sensitive Data",
      "analysis": "The application stores sensitive data without encryption, thereby exposing it to unauthorized access in case of a data breach.\n",
      "classification": "very promising",
      "cwe": "CWE-311",
      "function_names": [
        "saveToken"
      ],
      "filenames": [
        "src/app/services/common/token-storage.service.ts"
      ]
    },
    {
      "headline": "Server-Side Request Forgery (SSRF)",
      "analysis": "The application processes URLs in a way that could be exploited to access unauthorized internal resources.\n",
      "classification": "slightly promising",
      "cwe": "CWE-918",
      "function_names": [
        "save"
      ],
      "filenames": [
        "src/app/services/api/task-api.service.ts"
      ]
    }
  ],
  "scores": [
    {
      "stats": {
        "fn": 2,
        "tp": 0,
        "fp": 6
      },
      "mapping": {},
      "vuln_dates": {
        "CVE-2024-24562": "2024-03-14T19:15:49",
        "CVE-2024-22200": "2024-01-30T16:15:48"
      },
      "scoring_model": "gpt-4o-2024-05-13",
      "type": "llm",
      "instruction_template_hash": "8998f09cf57fca8a6e03"
    }
  ],
  "instruction_template_hash": "10c0163db4740318a544",
  "version": "0.1.0"
}
