{
  "commit": "1d6bfcdcce157c8daa42d0a056d4f3ee871c447a",
  "repo_url": "https://github.com/waysact/webpack-subresource-integrity",
  "model": "claude-3-sonnet-20240229",
  "chunk_hashes": [
    "db0daa848845e0e64e51"
  ],
  "responses": [
    {
      "content": "```yaml\nleads:\n  - headline: Incorrect Validation of Array Index (CWE-129)\n    analysis: |\n      The `addIfNotExist` function in `util.js` does not validate the input `item` against the type of elements stored in the `set`. If `set` is a `Set` of non-primitive types (e.g., objects or arrays), and `item` is a primitive value, the `set.has(item)` check may incorrectly return `false` due to the way JavaScript compares objects. This could lead to adding duplicate primitive values to the `set`.\n    cwe: CWE-129\n    function_names:\n      - addIfNotExist\n    filenames:\n      - util.js\n    classification: slightly promising\n\n  - headline: Improper Restriction of Operations within the Bounds of a Memory Buffer (CWE-119)\n    analysis: |\n      The `computeIntegrity` function in `util.js` uses the `update` method of the `crypto.Hash` class with the `source` string as input. However, the function does not validate the length of the `source` string or perform any bounds checking. If the `source` string is excessively large, it could potentially lead to a buffer overflow or out-of-bounds write when updating the hash object.\n    cwe: CWE-119\n    function_names:\n      - computeIntegrity\n    filenames:\n      - util.js\n    classification: slightly promising\n\n  - headline: Use of Externally-Controlled Input to Select Classes or Code (CWE-470)\n    analysis: |\n      The `findChunks` function in `util.js` uses the `chunk.groupsIterable` property to determine which code path to execute. However, this property is controlled by the input data (`chunk` object), which could be considered external input. An attacker could potentially manipulate the `chunk` object to execute unintended code paths or cause unexpected behavior.\n    cwe: CWE-470\n    function_names:\n      - findChunks\n    filenames:\n      - util.js\n    classification: slightly promising\n\n  - headline: Improper Handling of Exceptional Conditions (CWE-755)\n    analysis: |\n      The `getIntegrityChecksumForAsset` function in `util.js` does not handle cases where `assets[normalizedKey]` is undefined or does not have an `integrity` property. This could lead to unexpected behavior or errors when the function is called with invalid input.\n    cwe: CWE-755\n    function_names:\n      - getIntegrityChecksumForAsset\n    filenames:\n      - util.js\n    classification: slightly promising\n\n  - headline: Incorrect Permission Assignment for Critical Resource (CWE-732)\n    analysis: |\n      The `WebIntegrityJsonpMainTemplatePlugin` class in `jmtp.js` modifies the `script` and `link` elements in the HTML output, potentially introducing a security vulnerability if the elements are not properly sanitized or validated. The `addAttribute` method directly assigns the `integrity` and `crossOrigin` attributes to the elements, which could allow an attacker to inject malicious code or execute unintended actions.\n    cwe: CWE-732\n    function_names:\n      - addAttribute\n    filenames:\n      - jmtp.js\n    classification: very promising\n\n  - headline: Improper Initialization of Resource (CWE-909)\n    analysis: |\n      The `SubresourceIntegrityPlugin` class in `index.js` initializes the `emittedMessages` property as an empty object. However, this object is used as a set to track emitted messages. Using an object as a set can lead to unexpected behavior or collisions when keys with different string representations but the same hash value are added.\n    cwe: CWE-909\n    function_names: []\n    filenames:\n      - index.js\n    classification: slightly promising\n\n  - headline: Incorrect Restriction of Excessive Authentication Attempts (CWE-307)\n    analysis: |\n      The `karmaMiddleware.create` override in `karma.conf.js` does not impose any restrictions on the number of requests or attempts made by a client. This could potentially allow an attacker to launch a brute-force attack or cause a denial of service by sending an excessive number of requests.\n    cwe: CWE-307\n    function_names:\n      - karmaMiddleware.create\n    filenames:\n      - karma.conf.js\n    classification: slightly promising\n```",
      "date": "2024-06-13T18:04:30.748972",
      "usage": {
        "prompt_tokens": 31848,
        "completion_tokens": 1072,
        "cost": 0.111624
      }
    }
  ],
  "leads": [
    {
      "headline": "Incorrect Validation of Array Index (CWE-129)",
      "analysis": "The addIfNotExist function in util.js does not validate the input item against the type of elements stored in the set. If set is a Set of non-primitive types (e.g., objects or arrays), and item is a primitive value, the set.has(item) check may incorrectly return false due to the way JavaScript compares objects. This could lead to adding duplicate primitive values to the set.\n",
      "classification": "slightly promising",
      "cwe": "CWE-129",
      "function_names": [
        "addIfNotExist"
      ],
      "filenames": [
        "util.js"
      ]
    },
    {
      "headline": "Improper Restriction of Operations within the Bounds of a Memory Buffer (CWE-119)",
      "analysis": "The computeIntegrity function in util.js uses the update method of the crypto.Hash class with the source string as input. However, the function does not validate the length of the source string or perform any bounds checking. If the source string is excessively large, it could potentially lead to a buffer overflow or out-of-bounds write when updating the hash object.\n",
      "classification": "slightly promising",
      "cwe": "CWE-119",
      "function_names": [
        "computeIntegrity"
      ],
      "filenames": [
        "util.js"
      ]
    },
    {
      "headline": "Use of Externally-Controlled Input to Select Classes or Code (CWE-470)",
      "analysis": "The findChunks function in util.js uses the chunk.groupsIterable property to determine which code path to execute. However, this property is controlled by the input data (chunk object), which could be considered external input. An attacker could potentially manipulate the chunk object to execute unintended code paths or cause unexpected behavior.\n",
      "classification": "slightly promising",
      "cwe": "CWE-470",
      "function_names": [
        "findChunks"
      ],
      "filenames": [
        "util.js"
      ]
    },
    {
      "headline": "Improper Handling of Exceptional Conditions (CWE-755)",
      "analysis": "The getIntegrityChecksumForAsset function in util.js does not handle cases where assets[normalizedKey] is undefined or does not have an integrity property. This could lead to unexpected behavior or errors when the function is called with invalid input.\n",
      "classification": "slightly promising",
      "cwe": "CWE-755",
      "function_names": [
        "getIntegrityChecksumForAsset"
      ],
      "filenames": [
        "util.js"
      ]
    },
    {
      "headline": "Incorrect Permission Assignment for Critical Resource (CWE-732)",
      "analysis": "The WebIntegrityJsonpMainTemplatePlugin class in jmtp.js modifies the script and link elements in the HTML output, potentially introducing a security vulnerability if the elements are not properly sanitized or validated. The addAttribute method directly assigns the integrity and crossOrigin attributes to the elements, which could allow an attacker to inject malicious code or execute unintended actions.\n",
      "classification": "very promising",
      "cwe": "CWE-732",
      "function_names": [
        "addAttribute"
      ],
      "filenames": [
        "jmtp.js"
      ]
    },
    {
      "headline": "Improper Initialization of Resource (CWE-909)",
      "analysis": "The SubresourceIntegrityPlugin class in index.js initializes the emittedMessages property as an empty object. However, this object is used as a set to track emitted messages. Using an object as a set can lead to unexpected behavior or collisions when keys with different string representations but the same hash value are added.\n",
      "classification": "slightly promising",
      "cwe": "CWE-909",
      "function_names": [],
      "filenames": [
        "index.js"
      ]
    },
    {
      "headline": "Incorrect Restriction of Excessive Authentication Attempts (CWE-307)",
      "analysis": "The karmaMiddleware.create override in karma.conf.js does not impose any restrictions on the number of requests or attempts made by a client. This could potentially allow an attacker to launch a brute-force attack or cause a denial of service by sending an excessive number of requests.\n",
      "classification": "slightly promising",
      "cwe": "CWE-307",
      "function_names": [
        "karmaMiddleware.create"
      ],
      "filenames": [
        "karma.conf.js"
      ]
    }
  ],
  "scores": [
    {
      "stats": {
        "fn": 1,
        "tp": 0,
        "fp": 1
      },
      "mapping": {},
      "vuln_dates": {
        "CVE-2020-15262": "2020-10-19T20:15:12"
      },
      "scoring_model": "claude-3-opus-20240229",
      "type": "llm",
      "instruction_template_hash": "245ace12b6361954d0a2"
    }
  ],
  "instruction_template_hash": "10c0163db4740318a544",
  "version": "0.1.0"
}
