{
  "commit": "ba3cadefbc2b5e6b102cad2d39f40dcb378428ea",
  "repo_url": "https://github.com/nc3-lu/testingplatform",
  "model": "claude-3-5-sonnet-20240620",
  "chunk_hashes": [
    "c92a485dc8918e493c75"
  ],
  "responses": [
    {
      "content": "```yaml\nleads:\n  - headline: Path traversal vulnerability in file upload functionality\n    analysis: |\n      The get_upload_path function in models.py uses user-supplied input (filename) directly in constructing the file path, without proper sanitization. An attacker could potentially supply a filename containing \"../\" sequences to traverse directories and write files outside of the intended upload directory. This could allow unauthorized access to sensitive files or execution of malicious code.\n    cwe: CWE-22\n    function_names:\n      - get_upload_path\n    filenames:\n      - onekey/models.py\n    classification: very promising\n\n  - headline: Potential SQL injection in ORM query\n    analysis: |\n      The FirmwareAnalysisRequest.objects.order_by(\"id\").last() query in the save method of FirmwareAnalysisRequest model uses a string parameter that could potentially be user-controlled. While Django's ORM generally provides protection against SQL injection, if this value were to come from user input without proper sanitization, it could lead to SQL injection vulnerabilities.\n    cwe: CWE-89 \n    function_names:\n      - save\n    filenames:\n      - onekey/models.py\n    classification: slightly promising\n\n  - headline: Insecure direct object reference in download_report view\n    analysis: |\n      The download_report view retrieves a FirmwareAnalysisRequest object directly using a user-supplied report_uuid without verifying if the current user has permission to access that report. An attacker could potentially access or download reports belonging to other users by guessing or enumerating report UUIDs.\n    cwe: CWE-639\n    function_names:\n      - download_report\n    filenames:\n      - onekey/views.py\n    classification: very promising\n\n  - headline: Potential command injection in ping function\n    analysis: |\n      The ping function in automation/tasks.py uses subprocess.Popen to execute the ping command with user-supplied input as an argument. If the 'host' parameter is not properly sanitized before being passed to the command, it could allow command injection attacks where an attacker injects additional shell commands to be executed.\n    cwe: CWE-78\n    function_names:\n      - ping\n    filenames:\n      - automation/tasks.py  \n    classification: very promising\n\n  - headline: Insecure use of pickle for session serialization\n    analysis: |\n      The code uses Django's default session backend, which uses pickle for serialization. Pickle is not secure against maliciously constructed data and can lead to arbitrary code execution if an attacker is able to modify the session data. Consider using a more secure serialization method like JSON.\n    cwe: CWE-502\n    function_names: []\n    filenames:\n      - testing_platform/settings.py\n    classification: slightly promising\n\n  - headline: Potential open redirect vulnerability\n    analysis: |\n      The download_report view in onekey/views.py performs a redirect to a URL obtained from the database without validation. If an attacker could manipulate this stored URL, they could potentially cause a redirect to a malicious site. Always validate and sanitize URLs before redirecting to them, especially if they come from user input or the database.\n    cwe: CWE-601\n    function_names:\n      - download_report\n    filenames:\n      - onekey/views.py\n    classification: very promising\n```",
      "date": "2024-07-08T04:43:24.512591",
      "usage": {
        "prompt_tokens": 125622,
        "completion_tokens": 790,
        "cost": 0.388716
      }
    }
  ],
  "leads": [
    {
      "headline": "Path traversal vulnerability in file upload functionality",
      "analysis": "The get_upload_path function in models.py uses user-supplied input (filename) directly in constructing the file path, without proper sanitization. An attacker could potentially supply a filename containing \"../\" sequences to traverse directories and write files outside of the intended upload directory. This could allow unauthorized access to sensitive files or execution of malicious code.\n",
      "classification": "very promising",
      "cwe": "CWE-22",
      "function_names": [
        "get_upload_path"
      ],
      "filenames": [
        "onekey/models.py"
      ]
    },
    {
      "headline": "Potential SQL injection in ORM query",
      "analysis": "The FirmwareAnalysisRequest.objects.order_by(\"id\").last() query in the save method of FirmwareAnalysisRequest model uses a string parameter that could potentially be user-controlled. While Django's ORM generally provides protection against SQL injection, if this value were to come from user input without proper sanitization, it could lead to SQL injection vulnerabilities.\n",
      "classification": "slightly promising",
      "cwe": "CWE-89",
      "function_names": [
        "save"
      ],
      "filenames": [
        "onekey/models.py"
      ]
    },
    {
      "headline": "Insecure direct object reference in download_report view",
      "analysis": "The download_report view retrieves a FirmwareAnalysisRequest object directly using a user-supplied report_uuid without verifying if the current user has permission to access that report. An attacker could potentially access or download reports belonging to other users by guessing or enumerating report UUIDs.\n",
      "classification": "very promising",
      "cwe": "CWE-639",
      "function_names": [
        "download_report"
      ],
      "filenames": [
        "onekey/views.py"
      ]
    },
    {
      "headline": "Potential command injection in ping function",
      "analysis": "The ping function in automation/tasks.py uses subprocess.Popen to execute the ping command with user-supplied input as an argument. If the 'host' parameter is not properly sanitized before being passed to the command, it could allow command injection attacks where an attacker injects additional shell commands to be executed.\n",
      "classification": "very promising",
      "cwe": "CWE-78",
      "function_names": [
        "ping"
      ],
      "filenames": [
        "automation/tasks.py"
      ]
    },
    {
      "headline": "Insecure use of pickle for session serialization",
      "analysis": "The code uses Django's default session backend, which uses pickle for serialization. Pickle is not secure against maliciously constructed data and can lead to arbitrary code execution if an attacker is able to modify the session data. Consider using a more secure serialization method like JSON.\n",
      "classification": "slightly promising",
      "cwe": "CWE-502",
      "function_names": [],
      "filenames": [
        "testing_platform/settings.py"
      ]
    },
    {
      "headline": "Potential open redirect vulnerability",
      "analysis": "The download_report view in onekey/views.py performs a redirect to a URL obtained from the database without validation. If an attacker could manipulate this stored URL, they could potentially cause a redirect to a malicious site. Always validate and sanitize URLs before redirecting to them, especially if they come from user input or the database.\n",
      "classification": "very promising",
      "cwe": "CWE-601",
      "function_names": [
        "download_report"
      ],
      "filenames": [
        "onekey/views.py"
      ]
    }
  ],
  "scores": [
    {
      "stats": {
        "fn": 1,
        "tp": 0,
        "fp": 4
      },
      "mapping": {},
      "vuln_dates": {
        "CVE-2023-48310": "2023-11-20T23:15:06"
      },
      "scoring_model": "claude-3-5-sonnet-20240620",
      "type": "llm",
      "instruction_template_hash": "245ace12b6361954d0a2"
    }
  ],
  "instruction_template_hash": "10c0163db4740318a544",
  "version": "0.1.0"
}
