{
  "commit": "128ee9800c048d89c334f901a9671608e1218e4e",
  "repo_url": "https://github.com/jenkinsci/kubernetes-credentials-provider-plugin",
  "model": "claude-3-sonnet-20240229",
  "chunk_hashes": [
    "eb071721e4140fed5b0d"
  ],
  "responses": [
    {
      "content": "Here is a YAML representation of the security leads found in the provided codebase, with analysis and CWE mapping:\n\n```yaml\nleads:\n  - headline: Potential Untrusted Data Used in Path Operation\n    analysis: |\n      The `SecretUtils.getKeyName` method retrieves a key name from a Kubernetes Secret, potentially allowing for path traversal vulnerabilities if the key name is derived from untrusted data (e.g., user input). While the current implementation does not directly use external input, it may be possible for an attacker to inject malicious data into the Secret's annotations, leading to path traversal attacks.\n    cwe: CWE-22\n    function_names:\n      - com.cloudbees.jenkins.plugins.kubernetes_credentials_provider.SecretUtils.getKeyName\n    filenames:\n      - src/main/java/com/cloudbees/jenkins/plugins/kubernetes_credentials_provider/SecretUtils.java\n    classification: slightly promising\n\n  - headline: Potential Exposure of Sensitive Information\n    analysis: |\n      The `SecretUtils` class contains methods that handle the decoding and retrieval of sensitive data from Kubernetes Secrets, such as passwords, private keys, and access tokens. While the methods themselves do not directly expose sensitive information, improper usage or handling of the retrieved data could lead to information exposure vulnerabilities.\n    cwe: CWE-200\n    function_names:\n      - com.cloudbees.jenkins.plugins.kubernetes_credentials_provider.SecretUtils.base64DecodeToString\n      - com.cloudbees.jenkins.plugins.kubernetes_credentials_provider.SecretUtils.base64Decode\n      - com.cloudbees.jenkins.plugins.kubernetes_credentials_provider.SecretUtils.getNonNullSecretData\n      - com.cloudbees.jenkins.plugins.kubernetes_credentials_provider.SecretUtils.getOptionalSecretData\n    filenames:\n      - src/main/java/com/cloudbees/jenkins/plugins/kubernetes_credentials_provider/SecretUtils.java\n    classification: slightly promising\n\n  - headline: Potential Insecure Deserialization\n    analysis: |\n      The `KubernetesCredentialProvider` class deserializes Kubernetes Secrets using the `io.fabric8.kubernetes.client.utils.Serialization` utility. While the Fabric8 Kubernetes client library is widely used and maintained, deserialization of untrusted data can potentially lead to remote code execution vulnerabilities if not handled properly.\n    cwe: CWE-502\n    function_names:\n      - com.cloudbees.jenkins.plugins.kubernetes_credentials_provider.KubernetesCredentialProvider.startWatchingForSecrets\n    filenames:\n      - src/main/java/com/cloudbees/jenkins/plugins/kubernetes_credentials_provider/KubernetesCredentialProvider.java\n    classification: slightly promising\n\n  - headline: Potential Improper Input Validation\n    analysis: |\n      The `LabelSelectorExpressions` class parses Kubernetes label selector expressions, which could potentially be derived from untrusted input. While the current implementation does not directly use external input, improper validation of these expressions could lead to injection vulnerabilities or denial of service conditions.\n    cwe: CWE-20\n    function_names:\n      - com.cloudbees.jenkins.plugins.kubernetes_credentials_provider.LabelSelectorExpressions.parse\n    filenames:\n      - src/main/java/com/cloudbees/jenkins/plugins/kubernetes_credentials_provider/LabelSelectorExpressions.java\n    classification: slightly promising\n\n  - headline: Potential Improper Authentication\n    analysis: |\n      The `KubernetesCredentialProvider` class interacts with the Kubernetes API using the `io.fabric8.kubernetes.client.DefaultKubernetesClient`. While the client library handles authentication and authorization, improper configuration or credential management could potentially lead to authentication bypass vulnerabilities.\n    cwe: CWE-287\n    function_names:\n      - com.cloudbees.jenkins.plugins.kubernetes_credentials_provider.KubernetesCredentialProvider.getKubernetesClient\n    filenames:\n      - src/main/java/com/cloudbees/jenkins/plugins/kubernetes_credentials_provider/KubernetesCredentialProvider.java\n    classification: slightly promising\n```\n\nThis analysis covers potential security vulnerabilities related to path traversal, information exposure, insecure deserialization, improper input validation, and improper authentication. While the codebase does not exhibit any obvious or critical vulnerabilities, there are areas where additional validation, input sanitization, and secure coding practices could be implemented to mitigate potential risks.",
      "date": "2024-06-12T18:45:09.680465",
      "usage": {
        "prompt_tokens": 71647,
        "completion_tokens": 1102,
        "cost": 0.231471
      }
    }
  ],
  "leads": [
    {
      "headline": "Potential Untrusted Data Used in Path Operation",
      "analysis": "The SecretUtils.getKeyName method retrieves a key name from a Kubernetes Secret, potentially allowing for path traversal vulnerabilities if the key name is derived from untrusted data (e.g., user input). While the current implementation does not directly use external input, it may be possible for an attacker to inject malicious data into the Secret's annotations, leading to path traversal attacks.\n",
      "classification": "slightly promising",
      "cwe": "CWE-22",
      "function_names": [
        "com.cloudbees.jenkins.plugins.kubernetes_credentials_provider.SecretUtils.getKeyName"
      ],
      "filenames": [
        "src/main/java/com/cloudbees/jenkins/plugins/kubernetes_credentials_provider/SecretUtils.java"
      ]
    },
    {
      "headline": "Potential Exposure of Sensitive Information",
      "analysis": "The SecretUtils class contains methods that handle the decoding and retrieval of sensitive data from Kubernetes Secrets, such as passwords, private keys, and access tokens. While the methods themselves do not directly expose sensitive information, improper usage or handling of the retrieved data could lead to information exposure vulnerabilities.\n",
      "classification": "slightly promising",
      "cwe": "CWE-200",
      "function_names": [
        "com.cloudbees.jenkins.plugins.kubernetes_credentials_provider.SecretUtils.base64DecodeToString",
        "com.cloudbees.jenkins.plugins.kubernetes_credentials_provider.SecretUtils.base64Decode",
        "com.cloudbees.jenkins.plugins.kubernetes_credentials_provider.SecretUtils.getNonNullSecretData"
      ],
      "filenames": [
        "src/main/java/com/cloudbees/jenkins/plugins/kubernetes_credentials_provider/SecretUtils.java"
      ]
    },
    {
      "headline": "Potential Insecure Deserialization",
      "analysis": "The KubernetesCredentialProvider class deserializes Kubernetes Secrets using the io.fabric8.kubernetes.client.utils.Serialization utility. While the Fabric8 Kubernetes client library is widely used and maintained, deserialization of untrusted data can potentially lead to remote code execution vulnerabilities if not handled properly.\n",
      "classification": "slightly promising",
      "cwe": "CWE-502",
      "function_names": [
        "com.cloudbees.jenkins.plugins.kubernetes_credentials_provider.KubernetesCredentialProvider.startWatchingForSecrets"
      ],
      "filenames": [
        "src/main/java/com/cloudbees/jenkins/plugins/kubernetes_credentials_provider/KubernetesCredentialProvider.java"
      ]
    },
    {
      "headline": "Potential Improper Input Validation",
      "analysis": "The LabelSelectorExpressions class parses Kubernetes label selector expressions, which could potentially be derived from untrusted input. While the current implementation does not directly use external input, improper validation of these expressions could lead to injection vulnerabilities or denial of service conditions.\n",
      "classification": "slightly promising",
      "cwe": "CWE-20",
      "function_names": [
        "com.cloudbees.jenkins.plugins.kubernetes_credentials_provider.LabelSelectorExpressions.parse"
      ],
      "filenames": [
        "src/main/java/com/cloudbees/jenkins/plugins/kubernetes_credentials_provider/LabelSelectorExpressions.java"
      ]
    },
    {
      "headline": "Potential Improper Authentication",
      "analysis": "The KubernetesCredentialProvider class interacts with the Kubernetes API using the io.fabric8.kubernetes.client.DefaultKubernetesClient. While the client library handles authentication and authorization, improper configuration or credential management could potentially lead to authentication bypass vulnerabilities.\n",
      "classification": "slightly promising",
      "cwe": "CWE-287",
      "function_names": [
        "com.cloudbees.jenkins.plugins.kubernetes_credentials_provider.KubernetesCredentialProvider.getKubernetesClient"
      ],
      "filenames": [
        "src/main/java/com/cloudbees/jenkins/plugins/kubernetes_credentials_provider/KubernetesCredentialProvider.java"
      ]
    }
  ],
  "scores": [
    {
      "stats": {
        "fn": 1,
        "tp": 0,
        "fp": 0
      },
      "mapping": {},
      "vuln_dates": {
        "CVE-2023-24425": "2023-01-26T21:18:16"
      },
      "scoring_model": "claude-3-opus-20240229",
      "type": "llm",
      "instruction_template_hash": "245ace12b6361954d0a2"
    }
  ],
  "instruction_template_hash": "10c0163db4740318a544",
  "version": "0.1.0"
}
