{
  "commit": "45be0f99c7065f345ad76fd9767dae1c19cd01d5",
  "repo_url": "https://github.com/redon-tech/roblox-purchasing-hub",
  "model": "claude-3-sonnet-20240229",
  "chunk_hashes": [
    "c1d9834b7ece9e000d10"
  ],
  "responses": [
    {
      "content": "```yaml\nleads:\n  - headline: Improper authorization in giveproduct and revokeproduct commands\n    analysis: |\n      The `giveproduct` and `revokeproduct` commands in `/lib/cogs/user.py` allow any user with the `manage_guild` permission to give or revoke products for any user. This could potentially allow a malicious guild moderator to grant or revoke products without authorization. The commands should validate that the target user is a member of the guild, and implement additional access controls to prevent unauthorized modifications.\n    cwe: CWE-862\n    function_names:\n      - giveproduct\n      - revokeproduct\n    filenames:\n      - BOT/lib/cogs/user.py\n    classification: very promising\n  \n  - headline: Potential command injection in createproduct command\n    analysis: |\n      The `createproduct` command in `/lib/cogs/product.py` constructs a POST request to the Roblox API using user-provided input for the `name`, `description`, and `price` parameters. If these inputs are not properly sanitized, it could potentially lead to command injection vulnerabilities. The inputs should be validated and sanitized before being used in the API request.\n    cwe: CWE-74\n    function_names:\n      - createproduct\n    filenames:\n      - BOT/lib/cogs/product.py\n    classification: very promising\n\n  - headline: Potential file upload vulnerabilities in createproduct command\n    analysis: |\n      The `createproduct` command in `/lib/cogs/product.py` allows users to upload attachments as part of the product creation process. If the attachment content is not properly validated, it could potentially lead to file upload vulnerabilities such as arbitrary file uploads or code execution. The uploaded attachments should be validated for allowed file types, content, and size.\n    cwe: CWE-434\n    function_names:\n      - createproduct\n    filenames:\n      - BOT/lib/cogs/product.py\n    classification: very promising\n\n  - headline: Use of insecure default permissions\n    analysis: |\n      The bot appears to be running on a publicly accessible server (`0.0.0.0`). This could potentially expose the bot and its functionality to unauthorized access. The server should be configured to only allow access from trusted sources, and additional authentication and authorization mechanisms should be implemented to prevent unauthorized access.\n    cwe: CWE-276\n    function_names: []\n    filenames:\n      - BOT/lib/cogs/website.py\n    classification: very promising\n\n  - headline: Potential race condition in product update\n    analysis: |\n      The `WhatUpdateView` view in `/lib/cogs/product.py` allows users to edit product details by sending messages with the new values. However, there does not appear to be any synchronization mechanism in place to prevent race conditions if multiple users attempt to update the same product concurrently. This could potentially lead to data corruption or inconsistent updates. Appropriate locking or synchronization mechanisms should be implemented to ensure atomic updates.\n    cwe: CWE-362\n    function_names: []\n    filenames:\n      - BOT/lib/cogs/product.py\n    classification: slightly promising\n\n  - headline: Potential directory traversal vulnerability\n    analysis: |\n      The bot appears to use hard-coded file paths for loading configuration and other files. If these file paths are not properly validated, it could potentially lead to directory traversal vulnerabilities allowing access to arbitrary files on the system. All file paths should be properly validated and sanitized to prevent directory traversal attacks.\n    cwe: CWE-22\n    function_names: []\n    filenames:\n      - BOT/lib/bot/__init__.py\n      - BOT/lib/utils/util.py\n      - BOT/lib/utils/database.py\n    classification: slightly promising\n\n  - headline: Use of the next() function\n    analysis: |\n      The codebase appears to use the `next()` function in several places, which could potentially lead to issues if the input is not properly sanitized. While this is not a direct security vulnerability, improper use of `next()` could potentially lead to unexpected behavior or crashes, which could be leveraged as part of a denial-of-service attack. The usage of `next()` should be reviewed and input should be properly validated and sanitized.\n    cwe: CWE-754\n    function_names: []\n    filenames:\n      - BOT/lib/cogs/product.py\n      - BOT/lib/cogs/user.py\n    classification: not promising\n```",
      "date": "2024-06-14T15:24:56.859847",
      "usage": {
        "prompt_tokens": 18920,
        "completion_tokens": 1076,
        "cost": 0.0729
      }
    }
  ],
  "leads": [
    {
      "headline": "Improper authorization in giveproduct and revokeproduct commands",
      "analysis": "The giveproduct and revokeproduct commands in /lib/cogs/user.py allow any user with the manage_guild permission to give or revoke products for any user. This could potentially allow a malicious guild moderator to grant or revoke products without authorization. The commands should validate that the target user is a member of the guild, and implement additional access controls to prevent unauthorized modifications.\n",
      "classification": "very promising",
      "cwe": "CWE-862",
      "function_names": [
        "giveproduct",
        "revokeproduct"
      ],
      "filenames": [
        "BOT/lib/cogs/user.py"
      ]
    },
    {
      "headline": "Potential command injection in createproduct command",
      "analysis": "The createproduct command in /lib/cogs/product.py constructs a POST request to the Roblox API using user-provided input for the name, description, and price parameters. If these inputs are not properly sanitized, it could potentially lead to command injection vulnerabilities. The inputs should be validated and sanitized before being used in the API request.\n",
      "classification": "very promising",
      "cwe": "CWE-74",
      "function_names": [
        "createproduct"
      ],
      "filenames": [
        "BOT/lib/cogs/product.py"
      ]
    },
    {
      "headline": "Potential file upload vulnerabilities in createproduct command",
      "analysis": "The createproduct command in /lib/cogs/product.py allows users to upload attachments as part of the product creation process. If the attachment content is not properly validated, it could potentially lead to file upload vulnerabilities such as arbitrary file uploads or code execution. The uploaded attachments should be validated for allowed file types, content, and size.\n",
      "classification": "very promising",
      "cwe": "CWE-434",
      "function_names": [
        "createproduct"
      ],
      "filenames": [
        "BOT/lib/cogs/product.py"
      ]
    },
    {
      "headline": "Use of insecure default permissions",
      "analysis": "The bot appears to be running on a publicly accessible server (0.0.0.0). This could potentially expose the bot and its functionality to unauthorized access. The server should be configured to only allow access from trusted sources, and additional authentication and authorization mechanisms should be implemented to prevent unauthorized access.\n",
      "classification": "very promising",
      "cwe": "CWE-276",
      "function_names": [],
      "filenames": [
        "BOT/lib/cogs/website.py"
      ]
    },
    {
      "headline": "Potential race condition in product update",
      "analysis": "The WhatUpdateView view in /lib/cogs/product.py allows users to edit product details by sending messages with the new values. However, there does not appear to be any synchronization mechanism in place to prevent race conditions if multiple users attempt to update the same product concurrently. This could potentially lead to data corruption or inconsistent updates. Appropriate locking or synchronization mechanisms should be implemented to ensure atomic updates.\n",
      "classification": "slightly promising",
      "cwe": "CWE-362",
      "function_names": [],
      "filenames": [
        "BOT/lib/cogs/product.py"
      ]
    },
    {
      "headline": "Potential directory traversal vulnerability",
      "analysis": "The bot appears to use hard-coded file paths for loading configuration and other files. If these file paths are not properly validated, it could potentially lead to directory traversal vulnerabilities allowing access to arbitrary files on the system. All file paths should be properly validated and sanitized to prevent directory traversal attacks.\n",
      "classification": "slightly promising",
      "cwe": "CWE-22",
      "function_names": [],
      "filenames": [
        "BOT/lib/bot/__init__.py",
        "BOT/lib/utils/util.py",
        "BOT/lib/utils/database.py"
      ]
    },
    {
      "headline": "Use of the next() function",
      "analysis": "The codebase appears to use the next() function in several places, which could potentially lead to issues if the input is not properly sanitized. While this is not a direct security vulnerability, improper use of next() could potentially lead to unexpected behavior or crashes, which could be leveraged as part of a denial-of-service attack. The usage of next() should be reviewed and input should be properly validated and sanitized.\n",
      "classification": "not promising",
      "cwe": "CWE-754",
      "function_names": [],
      "filenames": [
        "BOT/lib/cogs/product.py",
        "BOT/lib/cogs/user.py"
      ]
    }
  ],
  "scores": [
    {
      "stats": {
        "fn": 1,
        "tp": 0,
        "fp": 4
      },
      "mapping": {},
      "vuln_dates": {
        "CVE-2021-41191": "2021-10-27T21:15:08"
      },
      "scoring_model": "claude-3-opus-20240229",
      "type": "llm",
      "instruction_template_hash": "245ace12b6361954d0a2"
    }
  ],
  "instruction_template_hash": "10c0163db4740318a544",
  "version": "0.1.0"
}
