{
  "commit": "20ce28ba0c25d8062323f82b4b9bcbbfbc5142d1",
  "repo_url": "https://github.com/pandora-analysis/pandora",
  "model": "gemini/gemini-1.5-pro",
  "chunk_hashes": [
    "248429ec84c3819aa582"
  ],
  "responses": [
    {
      "content": "```yaml\nleads:\n  - headline: Open Redirect in Unoserver\n    analysis: |\n      The `unoserver_launcher.py` script uses the `UnoServer` class from the `unoserver` library to launch an Unoconv server. \n      The `UnoServer` class does not properly sanitize URLs provided to it, allowing an attacker to specify a malicious redirect URL when making a request to the server. \n      This can be exploited by sending a specially crafted request to the Unoconv server that includes a redirect URL pointing to a malicious website. \n      When a user clicks on the link generated by the server, they will be redirected to the malicious website.\n    cwe: CWE-601\n    function_names:\n      - _launch_unoserver\n    filenames:\n      - bin/unoserver_launcher.py\n    classification: very promising\n  - headline: Password Hardcoded in website/web/__init__.py\n    analysis: |\n      The website's initialization script (`website/web/__init__.py`) contains a hardcoded password (`get_config('generic', 'sample_password')`) used to encrypt downloaded zip files. \n      An attacker with access to the codebase could easily retrieve this password and decrypt any zip files downloaded from the platform. \n      This exposes sensitive user data as downloaded zip files are supposed to be protected by a user-defined password.\n    cwe: CWE-798\n    function_names: \n      - api_task_download\n    filenames:\n      - website/web/__init__.py\n    classification: very promising\n  - headline: Lack of Input Validation in HybridAnalysis Worker\n    analysis: |\n      The HybridAnalysis worker in `pandora/workers/hybridanalysis.py` does not validate user-supplied input for the `apiurl` parameter.\n      An attacker could provide a malicious URL for this parameter, potentially leading to Server-Side Request Forgery (SSRF) or other vulnerabilities.\n      Exploiting this would require compromising the configuration file used by the worker, but could allow the attacker to make requests to internal services or arbitrary URLs from the Pandora server.\n    cwe: CWE-918\n    function_names:\n      - __init__\n    filenames:\n      - pandora/workers/hybridanalysis.py\n    classification: slightly promising\n  - headline: Lack of Input Validation in Lookyloo Worker\n    analysis: |\n      The Lookyloo worker in `pandora/workers/lookyloo.py` does not validate user-supplied input for various parameters like `apiurl`, `referer`, `user_agent`, `http_headers`, `cookies`, and `proxy`. \n      An attacker could provide malicious values for these parameters, potentially leading to SSRF or other vulnerabilities. \n      Exploiting this would require compromising the configuration file used by the worker, but could allow the attacker to make requests to internal services or arbitrary URLs from the Pandora server.\n    cwe: CWE-918\n    function_names:\n      - __init__\n    filenames:\n      - pandora/workers/lookyloo.py\n    classification: slightly promising\n  - headline: Unrestricted File Upload in /submit\n    analysis: |\n      The file upload endpoint at `/submit` lacks validation on the uploaded file type. This could allow an attacker to upload arbitrary files, potentially leading to code execution or other vulnerabilities if Pandora processes the uploaded files without proper security measures. \n      Exploitation would depend on the specific file types processed by Pandora and the security measures in place for each file type.\n    cwe: CWE-434\n    function_names:\n      - post\n    filenames:\n      - website/web/generic_api.py\n    classification: slightly promising\n  - headline: Potential for Denial of Service in Extractor Worker\n    analysis: |\n      The Extractor worker in `pandora/workers/extractor.py` has several checks for maximum file sizes and number of files within archives, but exceeding these limits could still lead to denial of service. \n      An attacker could submit a specially crafted archive containing a very large number of files or very large files, potentially consuming excessive resources on the Pandora server and impacting its availability.\n    cwe: CWE-400\n    function_names:\n      - analyse\n      - _extract_iso\n      - _extract_zip\n    filenames:\n      - pandora/workers/extractor.py\n    classification: not promising\n  - headline: Potential for Cross-Site Scripting (XSS) in website/web/__init__.py\n    analysis: |\n      The script `website/web/__init__.py` directly embeds user-supplied data from task details (e.g., filenames, error messages) into HTML templates.\n      While textract is used for content extraction, there's no indication of output encoding or sanitization before rendering it on the web interface.\n      If user-supplied data contains malicious JavaScript code, it could be executed in the context of a user's browser when viewing task details.\n    cwe: CWE-79\n    function_names: \n      - api_analysis\n    filenames:\n      - website/web/__init__.py\n    classification: not promising\n```",
      "date": "2024-06-13T10:59:38.989733",
      "usage": {
        "prompt_tokens": 86845,
        "completion_tokens": 1048,
        "cost": 0.3149615
      }
    }
  ],
  "leads": [
    {
      "headline": "Open Redirect in Unoserver",
      "analysis": "The unoserver_launcher.py script uses the UnoServer class from the unoserver library to launch an Unoconv server. \nThe UnoServer class does not properly sanitize URLs provided to it, allowing an attacker to specify a malicious redirect URL when making a request to the server. \nThis can be exploited by sending a specially crafted request to the Unoconv server that includes a redirect URL pointing to a malicious website. \nWhen a user clicks on the link generated by the server, they will be redirected to the malicious website.\n",
      "classification": "very promising",
      "cwe": "CWE-601",
      "function_names": [
        "_launch_unoserver"
      ],
      "filenames": [
        "bin/unoserver_launcher.py"
      ]
    },
    {
      "headline": "Password Hardcoded in website/web/__init__.py",
      "analysis": "The website's initialization script (website/web/__init__.py) contains a hardcoded password (get_config('generic', 'sample_password')) used to encrypt downloaded zip files. \nAn attacker with access to the codebase could easily retrieve this password and decrypt any zip files downloaded from the platform. \nThis exposes sensitive user data as downloaded zip files are supposed to be protected by a user-defined password.\n",
      "classification": "very promising",
      "cwe": "CWE-798",
      "function_names": [
        "api_task_download"
      ],
      "filenames": [
        "website/web/__init__.py"
      ]
    },
    {
      "headline": "Lack of Input Validation in HybridAnalysis Worker",
      "analysis": "The HybridAnalysis worker in pandora/workers/hybridanalysis.py does not validate user-supplied input for the apiurl parameter.\nAn attacker could provide a malicious URL for this parameter, potentially leading to Server-Side Request Forgery (SSRF) or other vulnerabilities.\nExploiting this would require compromising the configuration file used by the worker, but could allow the attacker to make requests to internal services or arbitrary URLs from the Pandora server.\n",
      "classification": "slightly promising",
      "cwe": "CWE-918",
      "function_names": [
        "__init__"
      ],
      "filenames": [
        "pandora/workers/hybridanalysis.py"
      ]
    },
    {
      "headline": "Lack of Input Validation in Lookyloo Worker",
      "analysis": "The Lookyloo worker in pandora/workers/lookyloo.py does not validate user-supplied input for various parameters like apiurl, referer, user_agent, http_headers, cookies, and proxy. \nAn attacker could provide malicious values for these parameters, potentially leading to SSRF or other vulnerabilities. \nExploiting this would require compromising the configuration file used by the worker, but could allow the attacker to make requests to internal services or arbitrary URLs from the Pandora server.\n",
      "classification": "slightly promising",
      "cwe": "CWE-918",
      "function_names": [
        "__init__"
      ],
      "filenames": [
        "pandora/workers/lookyloo.py"
      ]
    },
    {
      "headline": "Unrestricted File Upload in /submit",
      "analysis": "The file upload endpoint at /submit lacks validation on the uploaded file type. This could allow an attacker to upload arbitrary files, potentially leading to code execution or other vulnerabilities if Pandora processes the uploaded files without proper security measures. \nExploitation would depend on the specific file types processed by Pandora and the security measures in place for each file type.\n",
      "classification": "slightly promising",
      "cwe": "CWE-434",
      "function_names": [
        "post"
      ],
      "filenames": [
        "website/web/generic_api.py"
      ]
    },
    {
      "headline": "Potential for Denial of Service in Extractor Worker",
      "analysis": "The Extractor worker in pandora/workers/extractor.py has several checks for maximum file sizes and number of files within archives, but exceeding these limits could still lead to denial of service. \nAn attacker could submit a specially crafted archive containing a very large number of files or very large files, potentially consuming excessive resources on the Pandora server and impacting its availability.\n",
      "classification": "not promising",
      "cwe": "CWE-400",
      "function_names": [
        "analyse",
        "_extract_iso",
        "_extract_zip"
      ],
      "filenames": [
        "pandora/workers/extractor.py"
      ]
    },
    {
      "headline": "Potential for Cross-Site Scripting (XSS) in website/web/__init__.py",
      "analysis": "The script website/web/__init__.py directly embeds user-supplied data from task details (e.g., filenames, error messages) into HTML templates.\nWhile textract is used for content extraction, there's no indication of output encoding or sanitization before rendering it on the web interface.\nIf user-supplied data contains malicious JavaScript code, it could be executed in the context of a user's browser when viewing task details.\n",
      "classification": "not promising",
      "cwe": "CWE-79",
      "function_names": [
        "api_analysis"
      ],
      "filenames": [
        "website/web/__init__.py"
      ]
    }
  ],
  "scores": [
    {
      "stats": {
        "fn": 1,
        "tp": 0,
        "fp": 2
      },
      "mapping": {},
      "vuln_dates": {
        "CVE-2023-22898": "2023-01-10T02:15:09"
      },
      "scoring_model": "claude-3-opus-20240229",
      "type": "llm",
      "instruction_template_hash": "245ace12b6361954d0a2"
    },
    {
      "stats": {
        "fn": 1,
        "tp": 0,
        "fp": 2
      },
      "mapping": {},
      "vuln_dates": {
        "CVE-2023-22898": "2023-01-10T02:15:09"
      },
      "scoring_model": "claude-3-5-sonnet-20240620",
      "type": "llm",
      "instruction_template_hash": "245ace12b6361954d0a2"
    }
  ],
  "instruction_template_hash": "10c0163db4740318a544",
  "version": "0.1.0"
}
