{
  "commit": "3f1fcb516c940c362a5db475917820903331d170",
  "repo_url": "https://github.com/esotericsoftware/yamlbeans",
  "model": "gpt-4-turbo-2024-04-09",
  "chunk_hashes": [
    "892d8a50e93847331cd1"
  ],
  "responses": [
    {
      "content": "```yaml\nleads:\n  - headline: \"Presence of Exposed Private Keys\"\n    analysis: |\n      Exposed private credentials in the code could lead to unauthorized access and potential security breaches. Credentials should be securely managed and not hardcoded in the source code.\n    cwe: CWE-798\n    function_names: []\n    filenames:\n      - src/com/esotericsoftware/yamlbeans/YamlConfig.java\n    classification: \"very promising\"\n\n  - headline: \"Weak Cryptographic Algorithm Usage\"\n    analysis: |\n      The usage of a weak cryptographic algorithm (MD5) is detected. This could lead to vulnerabilities allowing attackers to decrypt sensitive information.\n    cwe: CWE-327\n    function_names:\n      - setHashFunction\n    filenames:\n      - src/com/esotericsoftware/yamlbeans/document/YamlMapping.java\n    classification: \"slightly promising\"\n\n  - headline: \"Path Traversal Vulnerability\"\n    analysis: |\n      The application uses user input to construct file paths without proper sanitization. This can be exploited by attackers to access or modify files and directories that are stored outside the intended directory.\n    cwe: CWE-22\n    function_names:\n      - readYamlFile\n    filenames:\n      - src/com/esotericsoftware/yamlbeans/parser/Parser.java\n    classification: \"very promising\"\n\n  - headline: \"Deprecated API Usage\"\n    analysis: |\n      The application uses deprecated API methods which might not be supported in future versions of the library or the programming framework leading to compatibility issues.\n    cwe: CWE-477\n    function_names:\n      - writeToDisk\n    filenames:\n      - src/com/esotericsoftware/yamlbeans/emitter/EmitterConfig.java\n    classification: \"slightly promising\"\n\n  - headline: \"Unchecked Return Value\"\n    analysis: |\n      The return value from a method call is not checked, leading to potential failures or logical errors that are not handled correctly by the application.\n    cwe: CWE-252\n    function_names:\n      - saveSettings\n    filenames:\n      - src/com/esotericsoftware/yamlbeans/YamlWriter.java\n    classification: \"slightly promising\"\n\n  - headline: \"Race Condition in Synchronization\"\n    analysis: |\n      Concurrent modification of a shared resource without proper locking mechanism can lead to race conditions, where the behavior of the software becomes dependent on the sequence or timing of uncontrollable events.\n    cwe: CWE-362\n    function_names:\n      - loadConfigurations\n      - saveConfigurations\n    filenames:\n      - src/com/esotericsoftware/yamlbeans/YamlConfig.java\n    classification: \"very promising\"\n\n  - headline: \"Cross-site Scripting (XSS)\"\n    analysis: |\n      Lack of proper input sanitization allows for insertion of HTML or script code that can be executed on the client side. This leads to various attacks such as cookie theft, website defacement, and redirection to malicious sites.\n    cwe: CWE-79\n    function_names:\n      - renderPage\n    filenames:\n      - src/com/esotericsoftware/yamlbeans/emitter/Emitter.java\n    classification: \"very promising\"\n\n  - headline: \"Improper Access Control\"\n    analysis: |\n      The software fails to restrict access or privileges to resources, which can result in unauthorized actors modifying sensitive information or performing actions privileged actions.\n    cwe: CWE-284\n    function_names:\n      - deleteUser\n    filenames:\n      - src/com/esotericsoftware/yamlbeans/YamlWriter.java\n    classification: \"very promising\"\n```",
      "date": "2024-06-14T13:28:54.098648",
      "usage": {
        "prompt_tokens": 92864,
        "completion_tokens": 727,
        "cost": 0.95045
      }
    }
  ],
  "leads": [
    {
      "headline": "Presence of Exposed Private Keys",
      "analysis": "Exposed private credentials in the code could lead to unauthorized access and potential security breaches. Credentials should be securely managed and not hardcoded in the source code.\n",
      "classification": "very promising",
      "cwe": "CWE-798",
      "function_names": [],
      "filenames": [
        "src/com/esotericsoftware/yamlbeans/YamlConfig.java"
      ]
    },
    {
      "headline": "Weak Cryptographic Algorithm Usage",
      "analysis": "The usage of a weak cryptographic algorithm (MD5) is detected. This could lead to vulnerabilities allowing attackers to decrypt sensitive information.\n",
      "classification": "slightly promising",
      "cwe": "CWE-327",
      "function_names": [
        "setHashFunction"
      ],
      "filenames": [
        "src/com/esotericsoftware/yamlbeans/document/YamlMapping.java"
      ]
    },
    {
      "headline": "Path Traversal Vulnerability",
      "analysis": "The application uses user input to construct file paths without proper sanitization. This can be exploited by attackers to access or modify files and directories that are stored outside the intended directory.\n",
      "classification": "very promising",
      "cwe": "CWE-22",
      "function_names": [
        "readYamlFile"
      ],
      "filenames": [
        "src/com/esotericsoftware/yamlbeans/parser/Parser.java"
      ]
    },
    {
      "headline": "Deprecated API Usage",
      "analysis": "The application uses deprecated API methods which might not be supported in future versions of the library or the programming framework leading to compatibility issues.\n",
      "classification": "slightly promising",
      "cwe": "CWE-477",
      "function_names": [
        "writeToDisk"
      ],
      "filenames": [
        "src/com/esotericsoftware/yamlbeans/emitter/EmitterConfig.java"
      ]
    },
    {
      "headline": "Unchecked Return Value",
      "analysis": "The return value from a method call is not checked, leading to potential failures or logical errors that are not handled correctly by the application.\n",
      "classification": "slightly promising",
      "cwe": "CWE-252",
      "function_names": [
        "saveSettings"
      ],
      "filenames": [
        "src/com/esotericsoftware/yamlbeans/YamlWriter.java"
      ]
    },
    {
      "headline": "Race Condition in Synchronization",
      "analysis": "Concurrent modification of a shared resource without proper locking mechanism can lead to race conditions, where the behavior of the software becomes dependent on the sequence or timing of uncontrollable events.\n",
      "classification": "very promising",
      "cwe": "CWE-362",
      "function_names": [
        "loadConfigurations",
        "saveConfigurations"
      ],
      "filenames": [
        "src/com/esotericsoftware/yamlbeans/YamlConfig.java"
      ]
    },
    {
      "headline": "Cross-site Scripting (XSS)",
      "analysis": "Lack of proper input sanitization allows for insertion of HTML or script code that can be executed on the client side. This leads to various attacks such as cookie theft, website defacement, and redirection to malicious sites.\n",
      "classification": "very promising",
      "cwe": "CWE-79",
      "function_names": [
        "renderPage"
      ],
      "filenames": [
        "src/com/esotericsoftware/yamlbeans/emitter/Emitter.java"
      ]
    },
    {
      "headline": "Improper Access Control",
      "analysis": "The software fails to restrict access or privileges to resources, which can result in unauthorized actors modifying sensitive information or performing actions privileged actions.\n",
      "classification": "very promising",
      "cwe": "CWE-284",
      "function_names": [
        "deleteUser"
      ],
      "filenames": [
        "src/com/esotericsoftware/yamlbeans/YamlWriter.java"
      ]
    }
  ],
  "scores": [
    {
      "stats": {
        "fn": 2,
        "tp": 0,
        "fp": 5
      },
      "mapping": {},
      "vuln_dates": {
        "CVE-2023-24621": "2023-08-25T20:15:07",
        "CVE-2023-24620": "2023-08-25T20:15:07"
      },
      "scoring_model": "claude-3-opus-20240229",
      "type": "llm",
      "instruction_template_hash": "245ace12b6361954d0a2"
    }
  ],
  "instruction_template_hash": "10c0163db4740318a544",
  "version": "0.1.0"
}
