{
  "commit": "0d2b85edf9519854e9bc968019f5c10c2d9d166a",
  "repo_url": "https://github.com/jenkinsci/ssh-slaves-plugin",
  "model": "gpt-4-turbo-2024-04-09",
  "chunk_hashes": [
    "7deebc03f7ca59c28ed4"
  ],
  "responses": [
    {
      "content": "```yaml\nleads:\n  - headline: Insecure storage and transmission of sensitive data\n    analysis: |\n      The codebases use insecure methods of transmitting and storing sensitive data, such as credentials. This could allow an attacker to intercept or access sensitive information.\n    cwe: CWE-311\n    function_names:\n      - launch\n      - lookupSystemCredentials\n    filenames:\n      - src/main/java/hudson/plugins/sshslaves/SSHLauncher.java\n    classification: very promising\n\n  - headline: Improper authentication handling\n    analysis: |\n      There is a lack of robust error handling and security checks around authentication processes, potentially allowing attackers to bypass authentication mechanisms.\n    cwe: CWE-287\n    function_names:\n      - openConnection\n    filenames:\n      - src/main/java/hudson/plugins/sshslaves/SSHLauncher.java\n    classification: slightly promising\n\n  - headline: Hard-coded credentials found\n    analysis: |\n      The code contains methods that could permit the use of hardcoded credentials or default passwords, which can be exploited by malicious users to gain unauthorized access.\n    cwe: CWE-798\n    function_names:\n      - SSHConnector\n      - SSHLauncher\n    filenames:\n      - src/main/java/hudson/plugins/sshslaves/SSHConnector.java\n      - src/main/java/hudson/plugins/sshslaves/SSHLauncher.java\n    classification: slightly promising\n\n  - headline: Use of deprecated and potentially insecure methods\n    analysis: |\n      Several methods are marked as deprecated and may rely on outdated or less secure protocols. Continuing to use these methods may pose security risks.\n    cwe: CWE-327\n    function_names:\n      - SSHLauncher\n      - launch\n    filenames:\n      - src/main/java/hudson/plugins/sshslaves/SSHLauncher.java\n    classification: slightly promising\n\n  - headline: Insecure file permissions and operations\n    analysis: |\n      File operations such as 'chmod' and 'delete' use weak permission handling that could be exploited to perform unauthorized actions on files.\n    cwe: CWE-732\n    function_names:\n      - createFile\n      - chmod\n    filenames:\n      - src/main/java/hudson/plugins/sshslaves/SFTPClient.java\n    classification: slightly promising\n\n  - headline: Insufficient error handling in remote command execution\n    analysis: |\n      The remote command execution functions do not sufficiently handle errors, potentially allowing execution of unintended commands or unauthorized actions.\n    cwe: CWE-755\n    function_names:\n      - launchChannel\n      - makeCommandLine\n    filenames:\n      - src/main/java/hudson/plugins/sshslaves/RemoteLauncher.java\n    classification: not promising\n\n  - headline: Excessive reliance on external control of system properties\n    analysis: |\n      The application excessively trusts external input to control key properties and behavior, making it susceptible to malicious modifications.\n    cwe: CWE-915\n    function_names:\n      - RemoteLauncher\n    filenames:\n      - src/main/java/hudson/plugins/sshslaves/RemoteLauncher.java\n    classification: not promising\n```",
      "date": "2024-06-12T19:21:20.145535",
      "usage": {
        "prompt_tokens": 25784,
        "completion_tokens": 636,
        "cost": 0.27692
      }
    }
  ],
  "leads": [
    {
      "headline": "Insecure storage and transmission of sensitive data",
      "analysis": "The codebases use insecure methods of transmitting and storing sensitive data, such as credentials. This could allow an attacker to intercept or access sensitive information.\n",
      "classification": "very promising",
      "cwe": "CWE-311",
      "function_names": [
        "launch",
        "lookupSystemCredentials"
      ],
      "filenames": [
        "src/main/java/hudson/plugins/sshslaves/SSHLauncher.java"
      ]
    },
    {
      "headline": "Improper authentication handling",
      "analysis": "There is a lack of robust error handling and security checks around authentication processes, potentially allowing attackers to bypass authentication mechanisms.\n",
      "classification": "slightly promising",
      "cwe": "CWE-287",
      "function_names": [
        "openConnection"
      ],
      "filenames": [
        "src/main/java/hudson/plugins/sshslaves/SSHLauncher.java"
      ]
    },
    {
      "headline": "Hard-coded credentials found",
      "analysis": "The code contains methods that could permit the use of hardcoded credentials or default passwords, which can be exploited by malicious users to gain unauthorized access.\n",
      "classification": "slightly promising",
      "cwe": "CWE-798",
      "function_names": [
        "SSHConnector",
        "SSHLauncher"
      ],
      "filenames": [
        "src/main/java/hudson/plugins/sshslaves/SSHConnector.java",
        "src/main/java/hudson/plugins/sshslaves/SSHLauncher.java"
      ]
    },
    {
      "headline": "Use of deprecated and potentially insecure methods",
      "analysis": "Several methods are marked as deprecated and may rely on outdated or less secure protocols. Continuing to use these methods may pose security risks.\n",
      "classification": "slightly promising",
      "cwe": "CWE-327",
      "function_names": [
        "SSHLauncher",
        "launch"
      ],
      "filenames": [
        "src/main/java/hudson/plugins/sshslaves/SSHLauncher.java"
      ]
    },
    {
      "headline": "Insecure file permissions and operations",
      "analysis": "File operations such as 'chmod' and 'delete' use weak permission handling that could be exploited to perform unauthorized actions on files.\n",
      "classification": "slightly promising",
      "cwe": "CWE-732",
      "function_names": [
        "createFile",
        "chmod"
      ],
      "filenames": [
        "src/main/java/hudson/plugins/sshslaves/SFTPClient.java"
      ]
    },
    {
      "headline": "Insufficient error handling in remote command execution",
      "analysis": "The remote command execution functions do not sufficiently handle errors, potentially allowing execution of unintended commands or unauthorized actions.\n",
      "classification": "not promising",
      "cwe": "CWE-755",
      "function_names": [
        "launchChannel",
        "makeCommandLine"
      ],
      "filenames": [
        "src/main/java/hudson/plugins/sshslaves/RemoteLauncher.java"
      ]
    },
    {
      "headline": "Excessive reliance on external control of system properties",
      "analysis": "The application excessively trusts external input to control key properties and behavior, making it susceptible to malicious modifications.\n",
      "classification": "not promising",
      "cwe": "CWE-915",
      "function_names": [
        "RemoteLauncher"
      ],
      "filenames": [
        "src/main/java/hudson/plugins/sshslaves/RemoteLauncher.java"
      ]
    }
  ],
  "scores": [
    {
      "stats": {
        "fn": 1,
        "tp": 0,
        "fp": 1
      },
      "mapping": {},
      "vuln_dates": {
        "CVE-2017-2648": "2018-07-27T20:29:00"
      },
      "scoring_model": "claude-3-opus-20240229",
      "type": "llm",
      "instruction_template_hash": "245ace12b6361954d0a2"
    }
  ],
  "instruction_template_hash": "10c0163db4740318a544",
  "version": "0.1.0"
}
