{
  "commit": "dc7dd0003d39adcd0ca15a592e7e14a7c4af216f",
  "repo_url": "https://github.com/plone/plone.rest",
  "model": "gpt-4o-2024-05-13",
  "chunk_hashes": [
    "3b7c364d133447d5aa4d"
  ],
  "responses": [
    {
      "content": "```yaml\nleads:\n  - headline: \"Hard-coded Credentials in setup.py\"\n    analysis: |\n      The setup.py file defines a static author email address \"plone-developers@lists.sourceforge.net\". If this email address is used for sensitive communications or operations without further validation, it might lead to Unauthorized Access.\n    cwe: CWE-798\n    function_names: []\n    filenames:\n      - \"setup.py\"\n    classification: slightly promising\n\n  - headline: \"Command Injection in setup.py\"\n    analysis: |\n      The read function in setup.py uses the open function to read files, combining os.path functions to determine the file path. This can potentially be exploited through command injection if the arguments passed to read() are not properly sanitized.\n    cwe: CWE-78\n    function_names:\n      - read\n    filenames:\n      - \"setup.py\"\n    classification: slightly promising\n\n  - headline: \"Use of HTTP in ErrorHandling for generating error URLs\"\n    analysis: |\n      In the file src/plone/rest/errors.py, there's a hard-coded use of \"http://\" in the HTTPError generation. This can lead to insecure transmission of error reporting data if it involves sensitive information.\n    cwe: CWE-319\n    function_names:\n      - __call__\n    filenames:\n      - \"src/plone/rest/errors.py\"\n    classification: slightly promising\n\n  - headline: \"Uncontrolled Resource Consumption in tests\"\n    analysis: |\n      The tests defined in the src/plone/rest/tests/ directory create several objects, resources, and make looping calls to test various scenarios. This can potentially lead to uncontrolled resource consumption, especially due to the absence of cleanup routines post testing.\n    cwe: CWE-400\n    function_names: []\n    filenames:\n      - \"src/plone/rest/tests/test_redirects.py\"\n      - \"src/plone/rest/tests/test_dexterity.py\"\n    classification: slightly promising\n\n  - headline: \"Improper Handling of Case Sensitivity in CORSPolicy\"\n    analysis: |\n      The CORSPolicy checks for allowed origins and methods in case-insensitive comparisons in a potential improper manner. This could lead to bypassing the policy unintentionally for certain case variants.\n    cwe: CWE-178\n    function_names:\n      - process_simple_request\n      - process_preflight_request\n    filenames:\n      - \"src/plone/rest/cors.py\"\n    classification: slightly promising\n\n  - headline: \"Insufficient Authentication Checks in RESTTraverse\"\n    analysis: |\n      The RESTTraverse class does not perform robust authentication checks post traversal, leading to a scenario where unauthorized access to REST services could be possible without proper validation.\n    cwe: CWE-287\n    function_names:\n      - publishTraverse\n    filenames:\n      - \"src/plone/rest/traverse.py\"\n    classification: slightly promising\n\n  - headline: \"Potential Information Disclosure via Verbose Error Messages\"\n    analysis: |\n      The error handling routines might capture and display verbose error messages, which include stack traces and internal object states that could potentially disclose information useful to an attacker.\n    cwe: CWE-209\n    function_names:\n      - render_exception\n      - render_traceback\n    filenames:\n      - \"src/plone/rest/errors.py\"\n    classification: slightly promising\n```",
      "date": "2024-06-09T14:12:24.013243",
      "usage": {
        "prompt_tokens": 25501,
        "completion_tokens": 676,
        "cost": 0.137645
      }
    }
  ],
  "leads": [
    {
      "headline": "Hard-coded Credentials in setup.py",
      "analysis": "The setup.py file defines a static author email address \"plone-developers@lists.sourceforge.net\". If this email address is used for sensitive communications or operations without further validation, it might lead to Unauthorized Access.\n",
      "classification": "slightly promising",
      "cwe": "CWE-798",
      "function_names": [],
      "filenames": [
        "setup.py"
      ]
    },
    {
      "headline": "Command Injection in setup.py",
      "analysis": "The read function in setup.py uses the open function to read files, combining os.path functions to determine the file path. This can potentially be exploited through command injection if the arguments passed to read() are not properly sanitized.\n",
      "classification": "slightly promising",
      "cwe": "CWE-78",
      "function_names": [
        "read"
      ],
      "filenames": [
        "setup.py"
      ]
    },
    {
      "headline": "Use of HTTP in ErrorHandling for generating error URLs",
      "analysis": "In the file src/plone/rest/errors.py, there's a hard-coded use of \"http://\" in the HTTPError generation. This can lead to insecure transmission of error reporting data if it involves sensitive information.\n",
      "classification": "slightly promising",
      "cwe": "CWE-319",
      "function_names": [
        "__call__"
      ],
      "filenames": [
        "src/plone/rest/errors.py"
      ]
    },
    {
      "headline": "Uncontrolled Resource Consumption in tests",
      "analysis": "The tests defined in the src/plone/rest/tests/ directory create several objects, resources, and make looping calls to test various scenarios. This can potentially lead to uncontrolled resource consumption, especially due to the absence of cleanup routines post testing.\n",
      "classification": "slightly promising",
      "cwe": "CWE-400",
      "function_names": [],
      "filenames": [
        "src/plone/rest/tests/test_redirects.py",
        "src/plone/rest/tests/test_dexterity.py"
      ]
    },
    {
      "headline": "Improper Handling of Case Sensitivity in CORSPolicy",
      "analysis": "The CORSPolicy checks for allowed origins and methods in case-insensitive comparisons in a potential improper manner. This could lead to bypassing the policy unintentionally for certain case variants.\n",
      "classification": "slightly promising",
      "cwe": "CWE-178",
      "function_names": [
        "process_simple_request",
        "process_preflight_request"
      ],
      "filenames": [
        "src/plone/rest/cors.py"
      ]
    },
    {
      "headline": "Insufficient Authentication Checks in RESTTraverse",
      "analysis": "The RESTTraverse class does not perform robust authentication checks post traversal, leading to a scenario where unauthorized access to REST services could be possible without proper validation.\n",
      "classification": "slightly promising",
      "cwe": "CWE-287",
      "function_names": [
        "publishTraverse"
      ],
      "filenames": [
        "src/plone/rest/traverse.py"
      ]
    },
    {
      "headline": "Potential Information Disclosure via Verbose Error Messages",
      "analysis": "The error handling routines might capture and display verbose error messages, which include stack traces and internal object states that could potentially disclose information useful to an attacker.\n",
      "classification": "slightly promising",
      "cwe": "CWE-209",
      "function_names": [
        "render_exception",
        "render_traceback"
      ],
      "filenames": [
        "src/plone/rest/errors.py"
      ]
    }
  ],
  "scores": [
    {
      "stats": {
        "fn": 1,
        "tp": 0,
        "fp": 0
      },
      "mapping": {},
      "vuln_dates": {
        "CVE-2023-42457": "2023-09-21T15:15:10"
      },
      "scoring_model": "gpt-4o-2024-05-13",
      "type": "llm",
      "instruction_template_hash": "8998f09cf57fca8a6e03"
    }
  ],
  "instruction_template_hash": "10c0163db4740318a544",
  "version": "0.1.0"
}
