{
  "commit": "25791512d219b284bd62bb068cae85d8e68bd05b",
  "repo_url": "https://github.com/micromatch/braces",
  "model": "gpt-4o-2024-05-13",
  "chunk_hashes": [
    "0db3451c0d8e1d7b49ec"
  ],
  "responses": [
    {
      "content": "```yaml\nleads:\n  - headline: \"Command injection in bash test functions\"\n    analysis: |\n      The bash functions in the test files can potentially execute arbitrary commands that are derived from user-controlled input. Specifically, functions such as `bash` within `test/bash-expanded-sets.js`, `test/bash-spec.js`, `test/bash-compiled-ranges.js`, `test/bash-compiled-sets.js`, `test/braces.expand.js`, and `test/bash-expanded-ranges.js` use `cp.spawnSync(bashPath(), ['-c', \\`echo ${input}\\`])`. If `input` is not properly sanitized, this could lead to command injection.\n    cwe: CWE-78\n    function_names:\n      - bash\n      - equal\n    filenames:\n      - test/bash-expanded-sets.js\n      - test/bash-spec.js\n      - test/bash-compiled-ranges.js\n      - test/bash-compiled-sets.js\n      - test/braces.expand.js\n      - test/bash-expanded-ranges.js\n    classification: very promising\n\n  - headline: \"Potential Regular Expression Denial of Service (ReDoS)\"\n    analysis: |\n      The functions that compile regular expressions using user-controlled input, specifically the `compile` function in `lib/compile.js` and `expand` function in `lib/expand.js`, may be vulnerable to Regular Expression Denial of Service (ReDoS) when processing patterns with large repetitions or complex nested structures. If a user can control the regex patterns passed to these functions, they can craft patterns that cause extensive backtracking, leading to high CPU consumption and potential denial of service.\n    cwe: CWE-1333\n    function_names:\n      - compile\n      - expand\n    filenames:\n      - lib/compile.js\n      - lib/expand.js\n    classification: slightly promising\n\n  - headline: \"Improper Input Validation in Range Handling\"\n    analysis: |\n      The handling of numeric and character ranges within the `expand` and `fill` functions can lead to uncontrolled resource consumption. Specifically, handling large ranges without limiting their size could lead to excessive memory usage, which could crash the application or degrade its performance.\n    cwe: CWE-770\n    function_names:\n      - expand\n    filenames:\n      - lib/expand.js\n    classification: very promising\n\n  - headline: \"Improper Validation of Input Length\"\n    analysis: |\n      The `parse` function in `lib/parse.js` and other files where user input is parsed has some validation to check the length of input strings. However, it does not comprehensively handle all potential edge cases, especially with complex nested structures and escape sequences, which could lead to buffer overflow or denial of service.\n    cwe: CWE-20\n    function_names:\n      - parse\n    filenames:\n      - lib/parse.js\n    classification: slightly promising\n```",
      "date": "2024-06-09T13:33:48.648247",
      "usage": {
        "prompt_tokens": 55946,
        "completion_tokens": 596,
        "cost": 0.28867
      }
    }
  ],
  "leads": [
    {
      "headline": "Command injection in bash test functions",
      "analysis": "The bash functions in the test files can potentially execute arbitrary commands that are derived from user-controlled input. Specifically, functions such as bash within test/bash-expanded-sets.js, test/bash-spec.js, test/bash-compiled-ranges.js, test/bash-compiled-sets.js, test/braces.expand.js, and test/bash-expanded-ranges.js use cp.spawnSync(bashPath(), ['-c', \\echo ${input}\\]). If input is not properly sanitized, this could lead to command injection.\n",
      "classification": "very promising",
      "cwe": "CWE-78",
      "function_names": [
        "bash",
        "equal"
      ],
      "filenames": [
        "test/bash-expanded-sets.js",
        "test/bash-spec.js",
        "test/bash-compiled-ranges.js"
      ]
    },
    {
      "headline": "Potential Regular Expression Denial of Service (ReDoS)",
      "analysis": "The functions that compile regular expressions using user-controlled input, specifically the compile function in lib/compile.js and expand function in lib/expand.js, may be vulnerable to Regular Expression Denial of Service (ReDoS) when processing patterns with large repetitions or complex nested structures. If a user can control the regex patterns passed to these functions, they can craft patterns that cause extensive backtracking, leading to high CPU consumption and potential denial of service.\n",
      "classification": "slightly promising",
      "cwe": "CWE-1333",
      "function_names": [
        "compile",
        "expand"
      ],
      "filenames": [
        "lib/compile.js",
        "lib/expand.js"
      ]
    },
    {
      "headline": "Improper Input Validation in Range Handling",
      "analysis": "The handling of numeric and character ranges within the expand and fill functions can lead to uncontrolled resource consumption. Specifically, handling large ranges without limiting their size could lead to excessive memory usage, which could crash the application or degrade its performance.\n",
      "classification": "very promising",
      "cwe": "CWE-770",
      "function_names": [
        "expand"
      ],
      "filenames": [
        "lib/expand.js"
      ]
    },
    {
      "headline": "Improper Validation of Input Length",
      "analysis": "The parse function in lib/parse.js and other files where user input is parsed has some validation to check the length of input strings. However, it does not comprehensively handle all potential edge cases, especially with complex nested structures and escape sequences, which could lead to buffer overflow or denial of service.\n",
      "classification": "slightly promising",
      "cwe": "CWE-20",
      "function_names": [
        "parse"
      ],
      "filenames": [
        "lib/parse.js"
      ]
    }
  ],
  "scores": [
    {
      "stats": {
        "fn": 1,
        "tp": 0,
        "fp": 2
      },
      "mapping": {},
      "vuln_dates": {
        "CVE-2024-4068": "2024-05-14T15:42:48"
      },
      "scoring_model": "gpt-4o-2024-05-13",
      "type": "llm",
      "instruction_template_hash": "8998f09cf57fca8a6e03"
    }
  ],
  "instruction_template_hash": "10c0163db4740318a544",
  "version": "0.1.0"
}
