{
  "commit": "228f357af22643dd8be7464c39e04e009af2d2ee",
  "repo_url": "https://github.com/maxtortime/setupbox",
  "model": "claude-3-opus-20240229",
  "chunk_hashes": [
    "12299c1340cd2175c350"
  ],
  "responses": [
    {
      "content": "Here is the YAML output with leads on potential security vulnerabilities in the provided codebase:\n\n```yaml\nleads:\n  - headline: Possible command injection in svn_wrapper.do_command\n    analysis: |\n      The do_command method in svn_wrapper.py constructs a shell command by concatenating user-controlled input (username, password, parameters) into the command string without proper validation or escaping. This could allow an attacker to inject arbitrary commands.\n    cwe: CWE-78\n    function_names:\n      - svn_wrapper.do_command\n    filenames:\n      - setupbox/svn_wrapper.py\n    classification: very promising\n  \n  - headline: Insecure password storage \n    analysis: |\n      The user's password is stored in plaintext in the user.json file created by client_init.py. Passwords should never be stored in plaintext. A secure password hashing algorithm like bcrypt, PBKDF2, or Argon2 should be used instead.\n    cwe: CWE-256 \n    function_names:\n      - client_init\n    filenames:\n      - setupbox/client_init.py\n    classification: very promising\n\n  - headline: Missing access control when modifying files\n    analysis: |\n      The add, rm, and commit operations in transaction_manager.py allow modifying arbitrary files without proper access controls. A malicious user could potentially overwrite or delete sensitive files on the server. Access should be restricted to intended directories only.\n    cwe: CWE-284\n    function_names: \n      - add\n      - rm\n      - commit\n    filenames:\n      - setupbox/transaction_manager.py\n    classification: very promising\n\n  - headline: Use of hard-coded credentials\n    analysis: |\n      Hard-coded credentials for the email server are present in config.py. If these credentials are exposed, an attacker could use them to gain unauthorized access to the email account. Credentials should be stored securely in environment variables or secret management systems.\n    cwe: CWE-798\n    function_names: []\n    filenames:\n      - web_server/config.py\n    classification: slightly promising\n\n  - headline: Potential XXE in vcs database\n    analysis: |\n      The VCS class seems to be interacting with a sqlite database to store version control data. If untrusted data is allowed in the msg field and later processed as XML somewhere, it could lead to XML external entity (XXE) injection. User input should be sanitized before storing in the database.\n    cwe: CWE-611\n    function_names:\n      - VCS.insert\n    filenames:  \n      - setupbox/vcs.py\n    classification: slightly promising\n\n```\n\nThis includes leads on command injection, insecure password storage, missing access controls, hard-coded credentials, and potential XXE. The analysis provides details on each vulnerability and the relevant CWE. Let me know if you need any clarification or have additional questions!",
      "date": "2024-06-13T10:03:49.683813",
      "usage": {
        "prompt_tokens": 20150,
        "completion_tokens": 694,
        "cost": 0.3543
      }
    }
  ],
  "leads": [
    {
      "headline": "Possible command injection in svn_wrapper.do_command",
      "analysis": "The do_command method in svn_wrapper.py constructs a shell command by concatenating user-controlled input (username, password, parameters) into the command string without proper validation or escaping. This could allow an attacker to inject arbitrary commands.\n",
      "classification": "very promising",
      "cwe": "CWE-78",
      "function_names": [
        "svn_wrapper.do_command"
      ],
      "filenames": [
        "setupbox/svn_wrapper.py"
      ]
    },
    {
      "headline": "Insecure password storage",
      "analysis": "The user's password is stored in plaintext in the user.json file created by client_init.py. Passwords should never be stored in plaintext. A secure password hashing algorithm like bcrypt, PBKDF2, or Argon2 should be used instead.\n",
      "classification": "very promising",
      "cwe": "CWE-256",
      "function_names": [
        "client_init"
      ],
      "filenames": [
        "setupbox/client_init.py"
      ]
    },
    {
      "headline": "Missing access control when modifying files",
      "analysis": "The add, rm, and commit operations in transaction_manager.py allow modifying arbitrary files without proper access controls. A malicious user could potentially overwrite or delete sensitive files on the server. Access should be restricted to intended directories only.\n",
      "classification": "very promising",
      "cwe": "CWE-284",
      "function_names": [
        "add",
        "rm",
        "commit"
      ],
      "filenames": [
        "setupbox/transaction_manager.py"
      ]
    },
    {
      "headline": "Use of hard-coded credentials",
      "analysis": "Hard-coded credentials for the email server are present in config.py. If these credentials are exposed, an attacker could use them to gain unauthorized access to the email account. Credentials should be stored securely in environment variables or secret management systems.\n",
      "classification": "slightly promising",
      "cwe": "CWE-798",
      "function_names": [],
      "filenames": [
        "web_server/config.py"
      ]
    },
    {
      "headline": "Potential XXE in vcs database",
      "analysis": "The VCS class seems to be interacting with a sqlite database to store version control data. If untrusted data is allowed in the msg field and later processed as XML somewhere, it could lead to XML external entity (XXE) injection. User input should be sanitized before storing in the database.\n",
      "classification": "slightly promising",
      "cwe": "CWE-611",
      "function_names": [
        "VCS.insert"
      ],
      "filenames": [
        "setupbox/vcs.py"
      ]
    }
  ],
  "scores": [
    {
      "stats": {
        "fn": 1,
        "tp": 0,
        "fp": 3
      },
      "mapping": {},
      "vuln_dates": {
        "CVE-2022-31543": "2022-07-11T01:15:09"
      },
      "scoring_model": "claude-3-opus-20240229",
      "type": "llm",
      "instruction_template_hash": "245ace12b6361954d0a2"
    }
  ],
  "instruction_template_hash": "10c0163db4740318a544",
  "version": "0.1.0"
}
