{
  "commit": "68c82e4be33f52a6fc4444fd28539e11d47d0602",
  "repo_url": "https://gitlab.com/edneville/please",
  "model": "claude-3-5-sonnet-20240620",
  "chunk_hashes": [
    "0104976b512e93f2b055"
  ],
  "responses": [
    {
      "content": "```yaml\nleads:\n  - headline: Command injection vulnerability in please command\n    analysis: |\n      The please command appears to execute user-supplied input directly as shell commands without proper sanitization. For example, in test_1/test.sh, user input is passed directly to please:\n      \n      echo '/usr/bin/please -r ree /bin/echo worked' | su - ed\n      \n      This allows arbitrary command execution if a user can control the input after the -r flag. An attacker could exploit this to run malicious commands with elevated privileges.\n    cwe: CWE-78\n    function_names: []\n    filenames:\n      - bintest/test_1/test.sh\n    classification: very promising\n\n  - headline: Potential path traversal vulnerability in pleaseedit command  \n    analysis: |\n      The pleaseedit command appears to allow editing arbitrary files specified by the user without sufficient path validation. For example, in test_4_default/test.sh:\n      \n      echo \"abc 192.168.1.1\" | pleaseedit /etc/test\n      \n      This could potentially be exploited to edit files outside of intended directories if proper path canonicalization and validation is not performed. An attacker may be able to edit sensitive system files.\n    cwe: CWE-22\n    function_names: []\n    filenames:\n      - bintest/test_4_default/test.sh\n    classification: slightly promising\n\n  - headline: Insecure file permissions set on edited files\n    analysis: |\n      The pleaseedit command appears to set insecure permissions on edited files in some cases. For example, in test_10_file_exists/test.sh, files are created with 0777 permissions:\n      \n      chmod \"$mode\" \"/tmp/file_${mode}\"\n      \n      This could allow unauthorized access to sensitive file contents if an attacker gains access to the system.\n    cwe: CWE-732\n    function_names: []\n    filenames: \n      - bintest/test_10_file_exists/test.sh\n    classification: slightly promising\n\n  - headline: Potential information disclosure via error messages\n    analysis: |\n      Error messages from the please command may reveal sensitive system information. For example, in test_9_regex_error_line/test.sh:\n      \n      please -l | grep 'Error parsing /etc/please.ini: ed_all:4'\n      \n      Detailed error messages could provide attackers with information about the system configuration and structure.\n    cwe: CWE-209\n    function_names: []\n    filenames:\n      - bintest/test_9_regex_error_line/test.sh  \n    classification: slightly promising\n\n  - headline: Potential for privilege escalation via insecure environment variables\n    analysis: |\n      The please command appears to allow specifying environment variables that are passed to executed commands. For example, in test_6_environment_set/test.sh:\n      \n      please -a PATH env | grep PATH=/foo/bar\n      \n      If not properly restricted, this could allow privilege escalation by manipulating environment variables like LD_PRELOAD.\n    cwe: CWE-269\n    function_names: []\n    filenames:\n      - bintest/test_6_environment_set/test.sh\n    classification: slightly promising\n```",
      "date": "2024-07-08T05:29:41.055578",
      "usage": {
        "prompt_tokens": 13446,
        "completion_tokens": 777,
        "cost": 0.051993
      }
    }
  ],
  "leads": [
    {
      "headline": "Command injection vulnerability in please command",
      "analysis": "The please command appears to execute user-supplied input directly as shell commands without proper sanitization. For example, in test_1/test.sh, user input is passed directly to please:\n\necho '/usr/bin/please -r ree /bin/echo worked' | su - ed\n\nThis allows arbitrary command execution if a user can control the input after the -r flag. An attacker could exploit this to run malicious commands with elevated privileges.\n",
      "classification": "very promising",
      "cwe": "CWE-78",
      "function_names": [],
      "filenames": [
        "bintest/test_1/test.sh"
      ]
    },
    {
      "headline": "Potential path traversal vulnerability in pleaseedit command",
      "analysis": "The pleaseedit command appears to allow editing arbitrary files specified by the user without sufficient path validation. For example, in test_4_default/test.sh:\n\necho \"abc 192.168.1.1\" | pleaseedit /etc/test\n\nThis could potentially be exploited to edit files outside of intended directories if proper path canonicalization and validation is not performed. An attacker may be able to edit sensitive system files.\n",
      "classification": "slightly promising",
      "cwe": "CWE-22",
      "function_names": [],
      "filenames": [
        "bintest/test_4_default/test.sh"
      ]
    },
    {
      "headline": "Insecure file permissions set on edited files",
      "analysis": "The pleaseedit command appears to set insecure permissions on edited files in some cases. For example, in test_10_file_exists/test.sh, files are created with 0777 permissions:\n\nchmod \"$mode\" \"/tmp/file_${mode}\"\n\nThis could allow unauthorized access to sensitive file contents if an attacker gains access to the system.\n",
      "classification": "slightly promising",
      "cwe": "CWE-732",
      "function_names": [],
      "filenames": [
        "bintest/test_10_file_exists/test.sh"
      ]
    },
    {
      "headline": "Potential information disclosure via error messages",
      "analysis": "Error messages from the please command may reveal sensitive system information. For example, in test_9_regex_error_line/test.sh:\n\nplease -l | grep 'Error parsing /etc/please.ini: ed_all:4'\n\nDetailed error messages could provide attackers with information about the system configuration and structure.\n",
      "classification": "slightly promising",
      "cwe": "CWE-209",
      "function_names": [],
      "filenames": [
        "bintest/test_9_regex_error_line/test.sh"
      ]
    },
    {
      "headline": "Potential for privilege escalation via insecure environment variables",
      "analysis": "The please command appears to allow specifying environment variables that are passed to executed commands. For example, in test_6_environment_set/test.sh:\n\nplease -a PATH env | grep PATH=/foo/bar\n\nIf not properly restricted, this could allow privilege escalation by manipulating environment variables like LD_PRELOAD.\n",
      "classification": "slightly promising",
      "cwe": "CWE-269",
      "function_names": [],
      "filenames": [
        "bintest/test_6_environment_set/test.sh"
      ]
    }
  ],
  "scores": [
    {
      "stats": {
        "fn": 1,
        "tp": 0,
        "fp": 1
      },
      "mapping": {},
      "vuln_dates": {
        "CVE-2023-46277": "2023-10-20T05:15:08"
      },
      "scoring_model": "claude-3-5-sonnet-20240620",
      "type": "llm",
      "instruction_template_hash": "245ace12b6361954d0a2"
    }
  ],
  "instruction_template_hash": "10c0163db4740318a544",
  "version": "0.1.0"
}
