{
  "commit": "72c017717800c17ff7aee66506bf3976783c5efd",
  "repo_url": "https://github.com/redon-tech/redon-hub",
  "model": "claude-3-sonnet-20240229",
  "chunk_hashes": [
    "1d8ca55377e8cd7bf003"
  ],
  "responses": [
    {
      "content": "```yaml\nleads:\n  - headline: Reflected Cross-Site Scripting (XSS)\n    analysis: The codebase contains a reflected Cross-Site Scripting (XSS) vulnerability. This vulnerability occurs when user input is not properly sanitized or encoded before being included in the server's response. An attacker can inject malicious scripts through crafted input, which will be executed by the victim's browser. This could lead to session hijacking, website defacement, or other attacks.\n    cwe: CWE-79\n    function_names:\n      - user_transfer_autocomplete\n      - user_admin_give_autocomplete\n      - user_admin_revoke_autocomplete\n      - get_product_info_command_autocomplete\n      - get_product_stats_info_command_autocomplete\n      - update_product_command_autocomplete\n      - get_tag_info_command_autocomplete\n      - update_tag_command_autocomplete\n    filenames:\n      - bot/cogs/user.py\n      - bot/cogs/product.py\n      - bot/cogs/tag.py\n    classification: very promising\n\n  - headline: Use of Hard-coded Credentials\n    analysis: The codebase contains hard-coded credentials, specifically the API key for the Redon Hub API. Hard-coding sensitive information like API keys or passwords in the codebase is a security risk, as it can be easily discovered by attackers if the source code is exposed. If an attacker obtains the API key, they can gain unauthorized access to the API and potentially compromise the system.\n    cwe: CWE-798\n    function_names: []\n    filenames:\n      - bot/cogs/api_v1.py\n    classification: very promising\n\n  - headline: Improper Access Control\n    analysis: The codebase contains an improper access control vulnerability related to the migrate command. The `migrate` command can be invoked by any user, but it should only be accessible to authorized users (owners). If an unauthorized user can execute this command, they could potentially migrate data from other providers, leading to data tampering or unauthorized access.\n    cwe: CWE-862\n    function_names:\n      - migrate\n    filenames:\n      - bot/cogs/migrate.py\n    classification: very promising\n\n  - headline: Improper Handling of Exceptional Conditions\n    analysis: The codebase does not consistently handle exceptional conditions or errors. In several places, exceptions are caught, but the error is not properly logged or handled. This could lead to unexpected behavior or errors going unnoticed, making it difficult to diagnose and fix issues in the application.\n    cwe: CWE-755\n    function_names: []\n    filenames:\n      - bot/cogs/user.py\n      - bot/cogs/product.py\n      - bot/cogs/tag.py\n      - bot/cogs/migrate.py\n      - bot/cogs/api_v1.py\n      - bot/data/prisma/user.py\n      - bot/data/prisma/product.py\n      - bot/data/prisma/tag.py\n    classification: slightly promising\n\n  - headline: Improper Input Validation\n    analysis: The codebase does not consistently validate user input, which could lead to various security vulnerabilities. For example, the `get_product_by_name` function could be vulnerable to SQL injection if the product name is not properly sanitized before being used in a database query.\n    cwe: CWE-20\n    function_names: []\n    filenames:\n      - bot/data/prisma/product.py\n    classification: slightly promising\n\n  - headline: Incorrect Calculation of Buffer Size\n    analysis: In the `promptChooseAttachments` function, there is a potential for an incorrect calculation of buffer size. The function appends user input (attachments) to a list without checking its size. If an attacker can provide an excessive amount of input, it could lead to a buffer overflow or other memory-related vulnerabilities.\n    cwe: CWE-131\n    function_names:\n      - promptChooseAttachments\n    filenames:\n      - bot/cogs/product.py\n    classification: slightly promising\n```\n\nThe analysis identifies several security vulnerabilities in the provided codebase, with varying levels of severity and potential impact. Here's a summary of the findings:\n\n1. **Reflected Cross-Site Scripting (XSS)**: Multiple functions that handle user input (e.g., `user_transfer_autocomplete`, `get_product_info_command_autocomplete`) do not properly sanitize or encode the input before including it in the server's response. This could lead to reflected XSS vulnerabilities, allowing an attacker to inject malicious scripts.\n\n2. **Use of Hard-coded Credentials**: The API key for the Redon Hub API is hard-coded in the codebase (`bot/cogs/api_v1.py`). Hard-coding sensitive information like API keys or passwords is a security risk, as it can be easily discovered if the source code is exposed.\n\n3. **Improper Access Control**: The `migrate` command in `bot/cogs/migrate.py` can be invoked by any user, but it should only be accessible to authorized users (owners). This could lead to unauthorized data migration or tampering.\n\n4. **Improper Handling of Exceptional Conditions**: The codebase does not consistently handle exceptional conditions or errors. Exceptions are caught, but errors are not properly logged or handled in several places, making it difficult to diagnose and fix issues.\n\n5. **Improper Input Validation**: User input is not consistently validated, which could lead to various security vulnerabilities. For example, the `get_product_by_name` function in `bot/data/prisma/product.py` could be vulnerable to SQL injection if the product name is not properly sanitized.\n\n6. **Incorrect Calculation of Buffer Size**: In the `promptChooseAttachments` function (`bot/cogs/product.py`), user input (attachments) is appended to a list without checking its size. If an attacker can provide an excessive amount of input, it could lead to a buffer overflow or other memory-related vulnerabilities.\n\nThe analysis classifies the reflected XSS, use of hard-coded credentials, improper access control, and improper handling of exceptional conditions as \"very promising\" vulnerabilities, meaning they have a high potential for exploitation and should be addressed promptly. The improper input validation and incorrect calculation of buffer size are classified as \"slightly promising\" vulnerabilities, indicating a lower risk but still requiring attention.\n\nIt's important to note that while the analysis provides an overview of potential vulnerabilities, a thorough manual review and testing of the codebase is recommended to identify and mitigate any additional security risks.",
      "date": "2024-06-09T14:31:01.882847",
      "usage": {
        "prompt_tokens": 39462,
        "completion_tokens": 1558,
        "cost": 0.141756
      }
    }
  ],
  "leads": [
    {
      "headline": "Reflected Cross-Site Scripting (XSS)",
      "analysis": "The codebase contains a reflected Cross-Site Scripting (XSS) vulnerability. This vulnerability occurs when user input is not properly sanitized or encoded before being included in the server's response. An attacker can inject malicious scripts through crafted input, which will be executed by the victim's browser. This could lead to session hijacking, website defacement, or other attacks.",
      "classification": "very promising",
      "cwe": "CWE-79",
      "function_names": [
        "user_transfer_autocomplete",
        "user_admin_give_autocomplete",
        "user_admin_revoke_autocomplete"
      ],
      "filenames": [
        "bot/cogs/user.py",
        "bot/cogs/product.py",
        "bot/cogs/tag.py"
      ]
    },
    {
      "headline": "Use of Hard-coded Credentials",
      "analysis": "The codebase contains hard-coded credentials, specifically the API key for the Redon Hub API. Hard-coding sensitive information like API keys or passwords in the codebase is a security risk, as it can be easily discovered by attackers if the source code is exposed. If an attacker obtains the API key, they can gain unauthorized access to the API and potentially compromise the system.",
      "classification": "very promising",
      "cwe": "CWE-798",
      "function_names": [],
      "filenames": [
        "bot/cogs/api_v1.py"
      ]
    },
    {
      "headline": "Improper Access Control",
      "analysis": "The codebase contains an improper access control vulnerability related to the migrate command. The migrate command can be invoked by any user, but it should only be accessible to authorized users (owners). If an unauthorized user can execute this command, they could potentially migrate data from other providers, leading to data tampering or unauthorized access.",
      "classification": "very promising",
      "cwe": "CWE-862",
      "function_names": [
        "migrate"
      ],
      "filenames": [
        "bot/cogs/migrate.py"
      ]
    },
    {
      "headline": "Improper Handling of Exceptional Conditions",
      "analysis": "The codebase does not consistently handle exceptional conditions or errors. In several places, exceptions are caught, but the error is not properly logged or handled. This could lead to unexpected behavior or errors going unnoticed, making it difficult to diagnose and fix issues in the application.",
      "classification": "slightly promising",
      "cwe": "CWE-755",
      "function_names": [],
      "filenames": [
        "bot/cogs/user.py",
        "bot/cogs/product.py",
        "bot/cogs/tag.py"
      ]
    },
    {
      "headline": "Improper Input Validation",
      "analysis": "The codebase does not consistently validate user input, which could lead to various security vulnerabilities. For example, the get_product_by_name function could be vulnerable to SQL injection if the product name is not properly sanitized before being used in a database query.",
      "classification": "slightly promising",
      "cwe": "CWE-20",
      "function_names": [],
      "filenames": [
        "bot/data/prisma/product.py"
      ]
    },
    {
      "headline": "Incorrect Calculation of Buffer Size",
      "analysis": "In the promptChooseAttachments function, there is a potential for an incorrect calculation of buffer size. The function appends user input (attachments) to a list without checking its size. If an attacker can provide an excessive amount of input, it could lead to a buffer overflow or other memory-related vulnerabilities.",
      "classification": "slightly promising",
      "cwe": "CWE-131",
      "function_names": [
        "promptChooseAttachments"
      ],
      "filenames": [
        "bot/cogs/product.py"
      ]
    }
  ],
  "scores": [
    {
      "stats": {
        "fn": 0,
        "tp": 1,
        "fp": 2
      },
      "mapping": {
        "2": "CVE-2024-31442"
      },
      "vuln_dates": {
        "CVE-2024-31442": "2024-04-08T16:15:07"
      },
      "scoring_model": "gpt-4o-2024-05-13",
      "type": "llm",
      "instruction_template_hash": "8998f09cf57fca8a6e03"
    }
  ],
  "instruction_template_hash": "10c0163db4740318a544",
  "version": "0.1.0"
}
