{
  "commit": "234b545cb11f9a570a7823767018ccdf419d6897",
  "repo_url": "https://github.com/jenkinsci/tikal-multijob-plugin",
  "model": "claude-3-haiku-20240307",
  "chunk_hashes": [
    "302ad03f57154554a870"
  ],
  "responses": [
    {
      "content": "Here is the YAML object equivalent to type LeadList, according to the provided Pydantic definitions:\n\n```yaml\nleads:\n  - headline: Buffer Copy without Checking Size of Input ('Classic Buffer Overflow')\n    analysis: |\n      The codebase contains a vulnerability related to improper restriction of operations within the bounds of a memory buffer, specifically a classic buffer overflow. This vulnerability can lead to unexpected program behavior, such as crashes or potential execution of arbitrary code.\n    cwe: CWE-120\n    function_names:\n      - createMultiJobProject\n    filenames:\n      - src/test/java/com/tikal/jenkins/plugins/multijob/test/MultiJobProjectTestCase.java\n    classification: very promising\n\n  - headline: Improper Neutralization of Special Elements used in an OS Command ('OS Command Injection')\n    analysis: |\n      The codebase contains a vulnerability related to improper neutralization of special elements used in an OS command, which can lead to OS command injection. This vulnerability can allow an attacker to execute arbitrary commands on the system, potentially gaining unauthorized access or performing malicious actions.\n    cwe: CWE-78\n    function_names:\n      - doIndex\n    filenames:\n      - src/main/java/com/tikal/jenkins/plugins/multijob/MultiJobResumeBuild.java\n    classification: very promising\n\n  - headline: Improper Restriction of Operations within the Bounds of a Memory Buffer\n    analysis: |\n      The codebase contains a vulnerability related to improper restriction of operations within the bounds of a memory buffer. This vulnerability can lead to various memory-related issues, such as buffer overflows, out-of-bounds reads, or out-of-bounds writes, potentially causing crashes, data corruption, or even execution of arbitrary code.\n    cwe: CWE-119\n    function_names:\n      - prepareActions\n      - injectEnvVars\n    filenames:\n      - src/main/java/com/tikal/jenkins/plugins/multijob/MultiJobBuilder.java\n    classification: very promising\n\n  - headline: Improper Neutralization of Special Elements used in an Expression Language Statement ('Expression Language Injection')\n    analysis: |\n      The codebase contains a vulnerability related to improper neutralization of special elements used in an expression language statement, which can lead to expression language injection. This vulnerability can allow an attacker to execute arbitrary code or access sensitive information within the application.\n    cwe: CWE-917\n    function_names:\n      - evalCondition\n    filenames:\n      - src/main/java/com/tikal/jenkins/plugins/multijob/MultiJobBuilder.java\n    classification: very promising\n\n  - headline: Improper Neutralization of Input During Web Page Generation ('Cross-site Scripting')\n    analysis: |\n      The codebase contains a vulnerability related to improper neutralization of input during web page generation, which can lead to cross-site scripting (XSS) attacks. This vulnerability can allow an attacker to inject malicious scripts into the application's web pages, potentially stealing sensitive information or performing unauthorized actions on behalf of the user.\n    cwe: CWE-79\n    function_names:\n      - getBuildParams\n    filenames:\n      - src/main/java/com/tikal/jenkins/plugins/multijob/MultiJobBuild.java\n    classification: slightly promising\n\n  - headline: Improper Restriction of XML External Entity Reference\n    analysis: |\n      The codebase contains a vulnerability related to improper restriction of XML external entity references, which can lead to XML external entity (XXE) injection attacks. This vulnerability can allow an attacker to access sensitive information, perform denial-of-service attacks, or even execute arbitrary code on the server.\n    cwe: CWE-611\n    function_names:\n      - readResolve\n    filenames:\n      - src/main/java/com/tikal/jenkins/plugins/multijob/PhaseJobsConfig.java\n    classification: slightly promising\n```",
      "date": "2024-06-12T19:27:30.327461",
      "usage": {
        "prompt_tokens": 55837,
        "completion_tokens": 937,
        "cost": 0.0151305
      }
    }
  ],
  "leads": [
    {
      "headline": "Buffer Copy without Checking Size of Input ('Classic Buffer Overflow')",
      "analysis": "The codebase contains a vulnerability related to improper restriction of operations within the bounds of a memory buffer, specifically a classic buffer overflow. This vulnerability can lead to unexpected program behavior, such as crashes or potential execution of arbitrary code.\n",
      "classification": "very promising",
      "cwe": "CWE-120",
      "function_names": [
        "createMultiJobProject"
      ],
      "filenames": [
        "src/test/java/com/tikal/jenkins/plugins/multijob/test/MultiJobProjectTestCase.java"
      ]
    },
    {
      "headline": "Improper Neutralization of Special Elements used in an OS Command ('OS Command Injection')",
      "analysis": "The codebase contains a vulnerability related to improper neutralization of special elements used in an OS command, which can lead to OS command injection. This vulnerability can allow an attacker to execute arbitrary commands on the system, potentially gaining unauthorized access or performing malicious actions.\n",
      "classification": "very promising",
      "cwe": "CWE-78",
      "function_names": [
        "doIndex"
      ],
      "filenames": [
        "src/main/java/com/tikal/jenkins/plugins/multijob/MultiJobResumeBuild.java"
      ]
    },
    {
      "headline": "Improper Restriction of Operations within the Bounds of a Memory Buffer",
      "analysis": "The codebase contains a vulnerability related to improper restriction of operations within the bounds of a memory buffer. This vulnerability can lead to various memory-related issues, such as buffer overflows, out-of-bounds reads, or out-of-bounds writes, potentially causing crashes, data corruption, or even execution of arbitrary code.\n",
      "classification": "very promising",
      "cwe": "CWE-119",
      "function_names": [
        "prepareActions",
        "injectEnvVars"
      ],
      "filenames": [
        "src/main/java/com/tikal/jenkins/plugins/multijob/MultiJobBuilder.java"
      ]
    },
    {
      "headline": "Improper Neutralization of Special Elements used in an Expression Language Statement ('Expression Language Injection')",
      "analysis": "The codebase contains a vulnerability related to improper neutralization of special elements used in an expression language statement, which can lead to expression language injection. This vulnerability can allow an attacker to execute arbitrary code or access sensitive information within the application.\n",
      "classification": "very promising",
      "cwe": "CWE-917",
      "function_names": [
        "evalCondition"
      ],
      "filenames": [
        "src/main/java/com/tikal/jenkins/plugins/multijob/MultiJobBuilder.java"
      ]
    },
    {
      "headline": "Improper Neutralization of Input During Web Page Generation ('Cross-site Scripting')",
      "analysis": "The codebase contains a vulnerability related to improper neutralization of input during web page generation, which can lead to cross-site scripting (XSS) attacks. This vulnerability can allow an attacker to inject malicious scripts into the application's web pages, potentially stealing sensitive information or performing unauthorized actions on behalf of the user.\n",
      "classification": "slightly promising",
      "cwe": "CWE-79",
      "function_names": [
        "getBuildParams"
      ],
      "filenames": [
        "src/main/java/com/tikal/jenkins/plugins/multijob/MultiJobBuild.java"
      ]
    },
    {
      "headline": "Improper Restriction of XML External Entity Reference",
      "analysis": "The codebase contains a vulnerability related to improper restriction of XML external entity references, which can lead to XML external entity (XXE) injection attacks. This vulnerability can allow an attacker to access sensitive information, perform denial-of-service attacks, or even execute arbitrary code on the server.\n",
      "classification": "slightly promising",
      "cwe": "CWE-611",
      "function_names": [
        "readResolve"
      ],
      "filenames": [
        "src/main/java/com/tikal/jenkins/plugins/multijob/PhaseJobsConfig.java"
      ]
    }
  ],
  "scores": [
    {
      "stats": {
        "fn": 1,
        "tp": 0,
        "fp": 4
      },
      "mapping": {},
      "vuln_dates": {
        "CVE-2017-1000390": "2018-01-26T02:29:00"
      },
      "scoring_model": "claude-3-opus-20240229",
      "type": "llm",
      "instruction_template_hash": "245ace12b6361954d0a2"
    },
    {
      "stats": {
        "fn": 1,
        "tp": 0,
        "fp": 4
      },
      "mapping": {},
      "vuln_dates": {
        "CVE-2017-1000390": "2018-01-26T02:29:00"
      },
      "scoring_model": "claude-3-5-sonnet-20240620",
      "type": "llm",
      "instruction_template_hash": "245ace12b6361954d0a2"
    }
  ],
  "instruction_template_hash": "10c0163db4740318a544",
  "version": "0.1.0"
}
