{
  "commit": "3ddead1584c9e9055b0f04850bf93cff4d7a60f2",
  "repo_url": "https://github.com/alexcrichton/bzip2-rs",
  "model": "gpt-4o-2024-05-13",
  "chunk_hashes": [
    "f4dca8b59ab22e85a46f"
  ],
  "responses": [
    {
      "content": "```yaml\nleads:\n  - headline: Possible Command Injection via Unsanitized Input in compressStream Function\n    analysis: |\n      The compressStream function reads data from an input stream and writes it to a compressed output stream. However, user input is directly used in the command execution without proper sanitization, which poses a potential command injection exploit opportunity. This vulnerability allows an attacker to manipulate the input data and execute arbitrary commands on the system.\n    cwe: CWE-78\n    function_names:\n      - compressStream\n    filenames:\n      - bzip2-sys/bzip2-1.0.8/bzip2.c\n    classification: very promising\n\n  - headline: Use of Uninitialized Memory in BZ_STREAM_END Condition\n    analysis: |\n      In the BZ2_decompress function, there is a condition that relies on the value of state_out_pos and numZ. If these values are uninitialized, it can lead to undefined behavior or memory corruption. This scenario may be particularly exploitable in environments where memory content can be influenced by an attacker.\n    cwe: CWE-824\n    function_names:\n      - BZ2_decompress\n    filenames:\n      - bzip2-sys/bzip2-1.0.8/decompress.c\n    classification: very promising\n\n  - headline: Potential Buffer Overflow in ADD_CHAR_TO_BLOCK Macro\n    analysis: |\n      The ADD_CHAR_TO_BLOCK macro does not perform proper bounds checking before writing data to the block buffer. This can potentially lead to buffer overflows, especially if an attacker can control the state variables used within the macro. Buffer overflow vulnerabilities may lead to arbitrary code execution.\n    cwe: CWE-120\n    function_names:\n      - ADD_CHAR_TO_BLOCK\n    filenames:\n      - bzip2-sys/bzip2-1.0.8/bzip2.c\n    classification: very promising\n\n  - headline: Improper Synchronization in Fallback Sorting Algorithm\n    analysis: |\n      The fallbackQSort3 function uses shared resources without proper synchronization mechanisms, which can lead to race conditions. This vulnerability can be exploited in multi-threaded environments where concurrent access to shared variables without locks or atomic operations may result in unpredictable behavior or crashes.\n    cwe: CWE-362\n    function_names:\n      - fallbackQSort3\n    filenames:\n      - bzip2-sys/bzip2-1.0.8/blocksort.c\n    classification: slightly promising\n\n  - headline: Inadequate Error Handling in bzStream Functions\n    analysis: |\n      The various bzStream functions (e.g., BZ2_bzRead, BZ2_bzWrite) do not adequately handle error conditions, such as out-of-memory scenarios. They often rely on default malloc and free functions without checking the return values, which could lead to null pointer dereferences and potential crashes.\n    cwe: CWE-252\n    function_names:\n      - BZ2_bzRead\n      - BZ2_bzWrite\n    filenames:\n      - bzip2-sys/bzip2-1.0.8/bzlib.c\n    classification: very promising\n\n  - headline: Insufficient Entropy in Random Number Generator\n    analysis: |\n      The randtable.c file contains a static table for random number generation which is easily predictable and does not provide sufficient entropy. This can weaken the randomness needed for security operations, making the system more susceptible to brute force attacks.\n    cwe: CWE-331\n    function_names:\n      - (no specific functions, issue is with the static table)\n    filenames:\n      - bzip2-sys/bzip2-1.0.8/randtable.c\n    classification: slightly promising\n```",
      "date": "2024-06-14T12:49:08.448091",
      "usage": {
        "prompt_tokens": 111122,
        "completion_tokens": 769,
        "cost": 0.567145
      }
    }
  ],
  "leads": [
    {
      "headline": "Possible Command Injection via Unsanitized Input in compressStream Function",
      "analysis": "The compressStream function reads data from an input stream and writes it to a compressed output stream. However, user input is directly used in the command execution without proper sanitization, which poses a potential command injection exploit opportunity. This vulnerability allows an attacker to manipulate the input data and execute arbitrary commands on the system.\n",
      "classification": "very promising",
      "cwe": "CWE-78",
      "function_names": [
        "compressStream"
      ],
      "filenames": [
        "bzip2-sys/bzip2-1.0.8/bzip2.c"
      ]
    },
    {
      "headline": "Use of Uninitialized Memory in BZ_STREAM_END Condition",
      "analysis": "In the BZ2_decompress function, there is a condition that relies on the value of state_out_pos and numZ. If these values are uninitialized, it can lead to undefined behavior or memory corruption. This scenario may be particularly exploitable in environments where memory content can be influenced by an attacker.\n",
      "classification": "very promising",
      "cwe": "CWE-824",
      "function_names": [
        "BZ2_decompress"
      ],
      "filenames": [
        "bzip2-sys/bzip2-1.0.8/decompress.c"
      ]
    },
    {
      "headline": "Potential Buffer Overflow in ADD_CHAR_TO_BLOCK Macro",
      "analysis": "The ADD_CHAR_TO_BLOCK macro does not perform proper bounds checking before writing data to the block buffer. This can potentially lead to buffer overflows, especially if an attacker can control the state variables used within the macro. Buffer overflow vulnerabilities may lead to arbitrary code execution.\n",
      "classification": "very promising",
      "cwe": "CWE-120",
      "function_names": [
        "ADD_CHAR_TO_BLOCK"
      ],
      "filenames": [
        "bzip2-sys/bzip2-1.0.8/bzip2.c"
      ]
    },
    {
      "headline": "Improper Synchronization in Fallback Sorting Algorithm",
      "analysis": "The fallbackQSort3 function uses shared resources without proper synchronization mechanisms, which can lead to race conditions. This vulnerability can be exploited in multi-threaded environments where concurrent access to shared variables without locks or atomic operations may result in unpredictable behavior or crashes.\n",
      "classification": "slightly promising",
      "cwe": "CWE-362",
      "function_names": [
        "fallbackQSort3"
      ],
      "filenames": [
        "bzip2-sys/bzip2-1.0.8/blocksort.c"
      ]
    },
    {
      "headline": "Inadequate Error Handling in bzStream Functions",
      "analysis": "The various bzStream functions (e.g., BZ2_bzRead, BZ2_bzWrite) do not adequately handle error conditions, such as out-of-memory scenarios. They often rely on default malloc and free functions without checking the return values, which could lead to null pointer dereferences and potential crashes.\n",
      "classification": "very promising",
      "cwe": "CWE-252",
      "function_names": [
        "BZ2_bzRead",
        "BZ2_bzWrite"
      ],
      "filenames": [
        "bzip2-sys/bzip2-1.0.8/bzlib.c"
      ]
    },
    {
      "headline": "Insufficient Entropy in Random Number Generator",
      "analysis": "The randtable.c file contains a static table for random number generation which is easily predictable and does not provide sufficient entropy. This can weaken the randomness needed for security operations, making the system more susceptible to brute force attacks.\n",
      "classification": "slightly promising",
      "cwe": "CWE-331",
      "function_names": [
        "(no specific functions, issue is with the static table)"
      ],
      "filenames": [
        "bzip2-sys/bzip2-1.0.8/randtable.c"
      ]
    }
  ],
  "scores": [
    {
      "stats": {
        "fn": 1,
        "tp": 0,
        "fp": 4
      },
      "mapping": {},
      "vuln_dates": {
        "CVE-2023-22895": "2023-01-10T01:15:10"
      },
      "scoring_model": "claude-3-opus-20240229",
      "type": "llm",
      "instruction_template_hash": "245ace12b6361954d0a2"
    }
  ],
  "instruction_template_hash": "10c0163db4740318a544",
  "version": "0.1.0"
}
