{
  "commit": "350f0f09188727c297bf53dfa9c1a221e37ab826",
  "repo_url": "https://github.com/lambda-science/impatient",
  "model": "gpt-4o-2024-05-13",
  "chunk_hashes": [
    "2a701117956cd0820d5b"
  ],
  "responses": [
    {
      "content": "```yaml\nleads:\n  - headline: \"Default admin credentials are hard-coded\"\n    analysis: |\n      The application's configuration in `config.py` contains hard-coded default admin credentials. Hard-coding admin credentials is a critical security flaw as it can be exploited by attackers to gain unauthorized access to the system. The default credentials include both the admin username and password.\n    cwe: CWE-798\n    function_names:\n      - create_admin\n    filenames:\n      - impatient.py\n      - config.py\n    classification: very promising\n\n  - headline: \"Use of weak cryptographic settings\"\n    analysis: |\n      The application uses JWT tokens for password reset functionality in `models.py`. However, the secret key for encoding the JWT token is a simple string, and there are no secure generation or storage mechanisms for this key. Additionally, the algorithm \"HS256\" is used, which is still considered secure but could be replaced with a more resilient algorithm.\n    cwe: CWE-327\n    function_names:\n      - get_reset_password_token\n    filenames:\n      - app/models.py\n      - config.py\n    classification: slightly promising\n\n  - headline: \"Sensitive information exposed in logs\"\n    analysis: |\n      The application's logging configuration in `__init__.py`, particularly in non-debug and non-testing environments, includes sending logs with potentially sensitive information to an SMTP handler and file handler without sanitization, which could leak sensitive data through logs.\n    cwe: CWE-532\n    function_names:\n      - create_app\n    filenames:\n      - app/__init__.py\n    classification: slightly promising\n\n  - headline: \"Cleartext storage of sensitive information\"\n    analysis: |\n      Passwords are stored as cleartext in the configuration file `config.py` and potentially within environment variables passed to Docker containers, which makes them susceptible to exposure.\n    cwe: CWE-312\n    function_names: []\n    filenames:\n      - config.py\n      - docker/run_sample.sh\n    classification: very promising\n\n  - headline: \"Server-side request forgery (SSRF)\"\n    analysis: |\n      The `app/dashapp/use_ml_image_segmentation_classifier.py` script decodes a base64-encoded classifier file and then loads it using `pickle.load`. This approach can be exploited with a specially crafted payload, leading to SSRF attacks and remote code execution.\n    cwe: CWE-918\n    function_names:\n      - use_img_classifier\n    filenames:\n      - app/dashapp/use_ml_image_segmentation_classifier.py\n    classification: slightly promising\n\n  - headline: \"Unrestricted file upload leading to potential RCE\"\n    analysis: |\n      The routes `docreate_img` in `imgupload/routes.py` and `ocr_pdf` in `historeport/routes.py` allow file uploads without proper validation of the file types, leading to possible malicious file uploads which can be used for Remote Code Execution (RCE).\n    cwe: CWE-434\n    function_names:\n      - create_img\n      - ocr_pdf\n    filenames:\n      - app/imgupload/routes.py\n      - app/historeport/routes.py\n    classification: very promising\n\n  - headline: \"Improper validation of uploaded files\"\n    analysis: |\n      File uploads in `imgupload/routes.py` and `historeport/routes.py` do not implement thorough validation or sanitization checks, allowing an attacker to possibly upload malicious files including scripts or binaries that can be executed.\n    cwe: CWE-20\n    function_names:\n      - create_img\n      - ocr_pdf\n    filenames:\n      - app/imgupload/routes.py\n      - app/historeport/routes.py\n    classification: very promising\n```",
      "date": "2024-06-13T09:29:21.757308",
      "usage": {
        "prompt_tokens": 60775,
        "completion_tokens": 765,
        "cost": 0.31535
      }
    }
  ],
  "leads": [
    {
      "headline": "Default admin credentials are hard-coded",
      "analysis": "The application's configuration in config.py contains hard-coded default admin credentials. Hard-coding admin credentials is a critical security flaw as it can be exploited by attackers to gain unauthorized access to the system. The default credentials include both the admin username and password.\n",
      "classification": "very promising",
      "cwe": "CWE-798",
      "function_names": [
        "create_admin"
      ],
      "filenames": [
        "impatient.py",
        "config.py"
      ]
    },
    {
      "headline": "Use of weak cryptographic settings",
      "analysis": "The application uses JWT tokens for password reset functionality in models.py. However, the secret key for encoding the JWT token is a simple string, and there are no secure generation or storage mechanisms for this key. Additionally, the algorithm \"HS256\" is used, which is still considered secure but could be replaced with a more resilient algorithm.\n",
      "classification": "slightly promising",
      "cwe": "CWE-327",
      "function_names": [
        "get_reset_password_token"
      ],
      "filenames": [
        "app/models.py",
        "config.py"
      ]
    },
    {
      "headline": "Sensitive information exposed in logs",
      "analysis": "The application's logging configuration in __init__.py, particularly in non-debug and non-testing environments, includes sending logs with potentially sensitive information to an SMTP handler and file handler without sanitization, which could leak sensitive data through logs.\n",
      "classification": "slightly promising",
      "cwe": "CWE-532",
      "function_names": [
        "create_app"
      ],
      "filenames": [
        "app/__init__.py"
      ]
    },
    {
      "headline": "Cleartext storage of sensitive information",
      "analysis": "Passwords are stored as cleartext in the configuration file config.py and potentially within environment variables passed to Docker containers, which makes them susceptible to exposure.\n",
      "classification": "very promising",
      "cwe": "CWE-312",
      "function_names": [],
      "filenames": [
        "config.py",
        "docker/run_sample.sh"
      ]
    },
    {
      "headline": "Server-side request forgery (SSRF)",
      "analysis": "The app/dashapp/use_ml_image_segmentation_classifier.py script decodes a base64-encoded classifier file and then loads it using pickle.load. This approach can be exploited with a specially crafted payload, leading to SSRF attacks and remote code execution.\n",
      "classification": "slightly promising",
      "cwe": "CWE-918",
      "function_names": [
        "use_img_classifier"
      ],
      "filenames": [
        "app/dashapp/use_ml_image_segmentation_classifier.py"
      ]
    },
    {
      "headline": "Unrestricted file upload leading to potential RCE",
      "analysis": "The routes docreate_img in imgupload/routes.py and ocr_pdf in historeport/routes.py allow file uploads without proper validation of the file types, leading to possible malicious file uploads which can be used for Remote Code Execution (RCE).\n",
      "classification": "very promising",
      "cwe": "CWE-434",
      "function_names": [
        "create_img",
        "ocr_pdf"
      ],
      "filenames": [
        "app/imgupload/routes.py",
        "app/historeport/routes.py"
      ]
    },
    {
      "headline": "Improper validation of uploaded files",
      "analysis": "File uploads in imgupload/routes.py and historeport/routes.py do not implement thorough validation or sanitization checks, allowing an attacker to possibly upload malicious files including scripts or binaries that can be executed.\n",
      "classification": "very promising",
      "cwe": "CWE-20",
      "function_names": [
        "create_img",
        "ocr_pdf"
      ],
      "filenames": [
        "app/imgupload/routes.py",
        "app/historeport/routes.py"
      ]
    }
  ],
  "scores": [
    {
      "stats": {
        "fn": 1,
        "tp": 0,
        "fp": 4
      },
      "mapping": {},
      "vuln_dates": {
        "CVE-2023-23637": "2023-01-17T21:15:17"
      },
      "scoring_model": "claude-3-opus-20240229",
      "type": "llm",
      "instruction_template_hash": "245ace12b6361954d0a2"
    }
  ],
  "instruction_template_hash": "10c0163db4740318a544",
  "version": "0.1.0"
}
