{
  "commit": "18264b470ed61a9ae9d41043624a0d4dda981235",
  "repo_url": "https://github.com/redisbloom/redisbloom",
  "model": "claude-3-sonnet-20240229",
  "chunk_hashes": [
    "cab23d546936ee1870e3"
  ],
  "responses": [
    {
      "content": "Based on the provided code, I have identified the following potential security vulnerabilities:\n\n```yaml\nleads:\n  - headline: Use of unsafe deserialization\n    analysis: |\n      The code uses deserialization of user-controlled data in the functions `SB_NewChainFromHeader` and `SBChain_LoadEncodedChunk`. If the deserialized data is not validated properly, it could lead to code execution or other attacks.\n    cwe: CWE-502\n    function_names:\n      - SB_NewChainFromHeader\n      - SBChain_LoadEncodedChunk\n    filenames:\n      - src/sb.c\n    classification: very promising\n\n  - headline: Use of insecure cryptographic algorithm\n    analysis: |\n      The code uses the MurmurHash2 hashing algorithm, which is not designed for cryptographic purposes and may be vulnerable to collisions and other attacks.\n    cwe: CWE-327\n    function_names:\n      - bloom_calc_hash\n      - bloom_calc_hash64\n    filenames:\n      - deps/bloom/bloom.c\n      - deps/murmur2/MurmurHash2.c\n    classification: slightly promising\n\n  - headline: Use of insufficiently random values\n    analysis: |\n      The `TopK_Add` function in the `topk.c` file uses the `rand` function, which is not designed for cryptographic purposes and may not provide sufficient randomness for security-critical applications.\n    cwe: CWE-330\n    function_names:\n      - TopK_Add\n    filenames:\n      - src/topk.c\n    classification: slightly promising\n\n  - headline: Use of uninitialized memory\n    analysis: |\n      The `SB_NewChainFromHeader` function in the `sb.c` file allocates memory for the `SBChain` struct and its members but does not initialize them, which could lead to undefined behavior or potentially expose sensitive data.\n    cwe: CWE-824\n    function_names:\n      - SB_NewChainFromHeader\n    filenames:\n      - src/sb.c\n    classification: slightly promising\n\n  - headline: Use of hardcoded credentials\n    analysis: |\n      The code does not appear to use any hardcoded credentials, but it is a good practice to avoid hardcoding credentials or other sensitive information in the code.\n    cwe: CWE-798\n    function_names: []\n    filenames: []\n    classification: not promising\n\n  - headline: Missing input validation\n    analysis: |\n      The code appears to perform some input validation, but a more thorough review is recommended to ensure that all input data is properly validated and sanitized before being used.\n    cwe: CWE-20\n    function_names: []\n    filenames: []\n    classification: slightly promising\n\n  - headline: Use of uncontrolled recursion\n    analysis: |\n      The code does not appear to use any uncontrolled recursion, but it is a good practice to avoid recursive functions that could potentially lead to stack overflows or other vulnerabilities.\n    cwe: CWE-674\n    function_names: []\n    filenames: []\n    classification: not promising\n```\n\nPlease note that this analysis is based on the provided code and may not be exhaustive. It is recommended to perform a more thorough code review and security testing to identify and mitigate potential vulnerabilities.",
      "date": "2024-06-09T14:30:20.105407",
      "usage": {
        "prompt_tokens": 135650,
        "completion_tokens": 801,
        "cost": 0.418965
      }
    }
  ],
  "leads": [
    {
      "headline": "Use of unsafe deserialization",
      "analysis": "The code uses deserialization of user-controlled data in the functions SB_NewChainFromHeader and SBChain_LoadEncodedChunk. If the deserialized data is not validated properly, it could lead to code execution or other attacks.\n",
      "classification": "very promising",
      "cwe": "CWE-502",
      "function_names": [
        "SB_NewChainFromHeader",
        "SBChain_LoadEncodedChunk"
      ],
      "filenames": [
        "src/sb.c"
      ]
    },
    {
      "headline": "Use of insecure cryptographic algorithm",
      "analysis": "The code uses the MurmurHash2 hashing algorithm, which is not designed for cryptographic purposes and may be vulnerable to collisions and other attacks.\n",
      "classification": "slightly promising",
      "cwe": "CWE-327",
      "function_names": [
        "bloom_calc_hash",
        "bloom_calc_hash64"
      ],
      "filenames": [
        "deps/bloom/bloom.c",
        "deps/murmur2/MurmurHash2.c"
      ]
    },
    {
      "headline": "Use of insufficiently random values",
      "analysis": "The TopK_Add function in the topk.c file uses the rand function, which is not designed for cryptographic purposes and may not provide sufficient randomness for security-critical applications.\n",
      "classification": "slightly promising",
      "cwe": "CWE-330",
      "function_names": [
        "TopK_Add"
      ],
      "filenames": [
        "src/topk.c"
      ]
    },
    {
      "headline": "Use of uninitialized memory",
      "analysis": "The SB_NewChainFromHeader function in the sb.c file allocates memory for the SBChain struct and its members but does not initialize them, which could lead to undefined behavior or potentially expose sensitive data.\n",
      "classification": "slightly promising",
      "cwe": "CWE-824",
      "function_names": [
        "SB_NewChainFromHeader"
      ],
      "filenames": [
        "src/sb.c"
      ]
    },
    {
      "headline": "Use of hardcoded credentials",
      "analysis": "The code does not appear to use any hardcoded credentials, but it is a good practice to avoid hardcoding credentials or other sensitive information in the code.\n",
      "classification": "not promising",
      "cwe": "CWE-798",
      "function_names": [],
      "filenames": []
    },
    {
      "headline": "Missing input validation",
      "analysis": "The code appears to perform some input validation, but a more thorough review is recommended to ensure that all input data is properly validated and sanitized before being used.\n",
      "classification": "slightly promising",
      "cwe": "CWE-20",
      "function_names": [],
      "filenames": []
    },
    {
      "headline": "Use of uncontrolled recursion",
      "analysis": "The code does not appear to use any uncontrolled recursion, but it is a good practice to avoid recursive functions that could potentially lead to stack overflows or other vulnerabilities.\n",
      "classification": "not promising",
      "cwe": "CWE-674",
      "function_names": [],
      "filenames": []
    }
  ],
  "scores": [
    {
      "stats": {
        "fn": 2,
        "tp": 0,
        "fp": 1
      },
      "mapping": {},
      "vuln_dates": {
        "CVE-2024-25115": "2024-04-09T18:15:08",
        "CVE-2024-25116": "2024-04-09T18:15:09"
      },
      "scoring_model": "gpt-4o-2024-05-13",
      "type": "llm",
      "instruction_template_hash": "8998f09cf57fca8a6e03"
    },
    {
      "stats": {
        "fn": 1,
        "tp": 1,
        "fp": 0
      },
      "mapping": {
        "0": "CVE-2024-25115"
      },
      "vuln_dates": {
        "CVE-2024-25115": "2024-04-09T18:15:08",
        "CVE-2024-25116": "2024-04-09T18:15:09"
      },
      "scoring_model": "claude-3-opus-20240229",
      "type": "llm",
      "instruction_template_hash": "245ace12b6361954d0a2"
    }
  ],
  "instruction_template_hash": "10c0163db4740318a544",
  "version": "0.1.0"
}
