{
  "commit": "2f1d6d333669589edef08ec68b508ee7efd25865",
  "repo_url": "https://github.com/jenkinsci/publish-over-cifs-plugin",
  "model": "claude-3-haiku-20240307",
  "chunk_hashes": [
    "001a71ad2bd060ed7735"
  ],
  "responses": [
    {
      "content": "Here is the YAML output for the security vulnerabilities found in the provided codebase:\n\n```yaml\nleads:\n  - headline: Cleartext Transmission of Sensitive Information\n    analysis: |\n      The code does not properly secure the transmission of sensitive information such as usernames and passwords over the network. This could allow an attacker to intercept and steal these credentials.\n    cwe: CWE-319\n    function_names:\n      - createSmbFile\n      - createUrlForSubDir\n    filenames:\n      - src/main/java/jenkins/plugins/publish_over_cifs/CifsClient.java\n      - src/main/java/jenkins/plugins/publish_over_cifs/CifsHostConfiguration.java\n    classification: very promising\n  - headline: Improper Neutralization of Special Elements used in an SQL Command ('SQL Injection')\n    analysis: |\n      The code does not properly sanitize user input, which could allow an attacker to inject malicious SQL commands and potentially gain unauthorized access to the underlying database.\n    cwe: CWE-89\n    function_names:\n      - listFiles\n      - delete\n      - exists\n      - canRead\n      - mkdirs\n    filenames:\n      - src/main/java/jenkins/plugins/publish_over_cifs/CifsHelper.java\n    classification: slightly promising\n  - headline: Improper Encoding or Escaping of Output\n    analysis: |\n      The `encode` method in the `CifsHostConfiguration` class does not properly encode all user input, which could lead to a vulnerability where special characters are not properly escaped and could be interpreted as part of a command or URL.\n    cwe: CWE-116\n    function_names:\n      - encode\n    filenames:\n      - src/main/java/jenkins/plugins/publish_over_cifs/CifsHostConfiguration.java\n    classification: slightly promising\n  - headline: Incorrect Conversion between Numeric Types\n    analysis: |\n      The code does not properly handle the conversion between numeric types, which could lead to integer overflow or underflow vulnerabilities.\n    cwe: CWE-681\n    function_names:\n      - toDigit\n    filenames:\n      - src/main/java/jenkins/plugins/publish_over_cifs/CifsHostConfiguration.java\n    classification: not promising\n```",
      "date": "2024-06-12T19:02:19.684240",
      "usage": {
        "prompt_tokens": 60032,
        "completion_tokens": 554,
        "cost": 0.0157005
      }
    }
  ],
  "leads": [
    {
      "headline": "Cleartext Transmission of Sensitive Information",
      "analysis": "The code does not properly secure the transmission of sensitive information such as usernames and passwords over the network. This could allow an attacker to intercept and steal these credentials.\n",
      "classification": "very promising",
      "cwe": "CWE-319",
      "function_names": [
        "createSmbFile",
        "createUrlForSubDir"
      ],
      "filenames": [
        "src/main/java/jenkins/plugins/publish_over_cifs/CifsClient.java",
        "src/main/java/jenkins/plugins/publish_over_cifs/CifsHostConfiguration.java"
      ]
    },
    {
      "headline": "Improper Neutralization of Special Elements used in an SQL Command ('SQL Injection')",
      "analysis": "The code does not properly sanitize user input, which could allow an attacker to inject malicious SQL commands and potentially gain unauthorized access to the underlying database.\n",
      "classification": "slightly promising",
      "cwe": "CWE-89",
      "function_names": [
        "listFiles",
        "delete",
        "exists"
      ],
      "filenames": [
        "src/main/java/jenkins/plugins/publish_over_cifs/CifsHelper.java"
      ]
    },
    {
      "headline": "Improper Encoding or Escaping of Output",
      "analysis": "The encode method in the CifsHostConfiguration class does not properly encode all user input, which could lead to a vulnerability where special characters are not properly escaped and could be interpreted as part of a command or URL.\n",
      "classification": "slightly promising",
      "cwe": "CWE-116",
      "function_names": [
        "encode"
      ],
      "filenames": [
        "src/main/java/jenkins/plugins/publish_over_cifs/CifsHostConfiguration.java"
      ]
    },
    {
      "headline": "Incorrect Conversion between Numeric Types",
      "analysis": "The code does not properly handle the conversion between numeric types, which could lead to integer overflow or underflow vulnerabilities.\n",
      "classification": "not promising",
      "cwe": "CWE-681",
      "function_names": [
        "toDigit"
      ],
      "filenames": [
        "src/main/java/jenkins/plugins/publish_over_cifs/CifsHostConfiguration.java"
      ]
    }
  ],
  "scores": [
    {
      "stats": {
        "fn": 1,
        "tp": 0,
        "fp": 1
      },
      "mapping": {},
      "vuln_dates": {
        "CVE-2018-1999038": "2018-08-01T13:29:00"
      },
      "scoring_model": "claude-3-opus-20240229",
      "type": "llm",
      "instruction_template_hash": "245ace12b6361954d0a2"
    },
    {
      "stats": {
        "fn": 1,
        "tp": 0,
        "fp": 1
      },
      "mapping": {},
      "vuln_dates": {
        "CVE-2018-1999038": "2018-08-01T13:29:00"
      },
      "scoring_model": "claude-3-5-sonnet-20240620",
      "type": "llm",
      "instruction_template_hash": "245ace12b6361954d0a2"
    }
  ],
  "instruction_template_hash": "10c0163db4740318a544",
  "version": "0.1.0"
}
