{
  "commit": "f229c1e8e0c5951213cf3652cfa32c2b7d10bbb8",
  "repo_url": "https://github.com/idurar/idurar-erp-crm",
  "model": "gpt-4o-2024-05-13",
  "chunk_hashes": [
    "a7346cd23da9c109d4d3"
  ],
  "responses": [
    {
      "content": "```yaml\nleads:\n  - headline: Insufficient Validation of Pathnames in Function 'icon'\n    analysis: |\n      The function `icon` in `helpers.js` uses `fs.readFileSync` to read files without proper validation of the `name` parameter. This allows an attacker to manipulate the file path, potentially reading any file on the server.\n    cwe: CWE-22\n    function_names:\n      - icon\n    filenames:\n      - helpers.js\n    classification: very promising\n\n  - headline: Improper Error Handling in File Read Function\n    analysis: |\n      The `image` function in `helpers.js` uses `fs.readFileSync` without proper error handling. If an attacker tries to read a file that doesn't exist, the lack of error handling can disclose sensitive information through error messages.\n    cwe: CWE-209\n    function_names:\n      - image\n    filenames:\n      - helpers.js\n    classification: slightly promising\n\n  - headline: Hardcoded API Keys in Email Sending Function\n    analysis: |\n      The function `sendViaApi` in `mailInvoiceController.js` uses the API key stored in `process.env.RESEND_API` directly. If the `RESEND_API` environment variable is improperly managed or exposed, this could lead to unauthorized access.\n    cwe: CWE-798\n    function_names:\n      - sendViaApi\n    filenames:\n      - controllers/erpControllers/mailInvoiceController.js\n    classification: very promising\n\n  - headline: Information Disclosure Through Detailed Error Messages in CRUD Operations\n    analysis: |\n      Multiple functions in `apiRest.js` disclose detailed error messages. Disclosing internal error structure can provide attackers with critical information about the application, facilitating other types of attacks.\n    cwe: CWE-209\n    function_names:\n      - create\n      - read\n      - update\n    filenames:\n      - controllers/corsControllers/apiRest.js\n    classification: slightly promising\n\n  - headline: Missing Authentication for Important Operations\n    analysis: |\n      The `read` function in `crudController.js` does not check for proper authentication before accessing the database. This allows unauthenticated users to perform read operations on sensitive data.\n    cwe: CWE-306\n    function_names:\n      - read\n    filenames:\n      - controllers/corsControllers/crudController.js\n    classification: very promising\n\n  - headline: No Rate Limiting for API Requests\n    analysis: |\n      The API endpoints in `erpAuthRouter.js` and other route files do not implement any rate limiting. This omission allows attackers to perform brute-force attacks or other types of denial-of-service attacks.\n    cwe: CWE-307\n    function_names:\n      - N/A\n    filenames:\n      - routes/erpRoutes/erpAuthRouter.js\n      - routes/erpRoutes/erpApiRouter.js\n    classification: very promising\n```",
      "date": "2024-06-09T12:32:12.693045",
      "usage": {
        "prompt_tokens": 61083,
        "completion_tokens": 596,
        "cost": 0.314355
      }
    }
  ],
  "leads": [
    {
      "headline": "Insufficient Validation of Pathnames in Function 'icon'",
      "analysis": "The function icon in helpers.js uses fs.readFileSync to read files without proper validation of the name parameter. This allows an attacker to manipulate the file path, potentially reading any file on the server.\n",
      "classification": "very promising",
      "cwe": "CWE-22",
      "function_names": [
        "icon"
      ],
      "filenames": [
        "helpers.js"
      ]
    },
    {
      "headline": "Improper Error Handling in File Read Function",
      "analysis": "The image function in helpers.js uses fs.readFileSync without proper error handling. If an attacker tries to read a file that doesn't exist, the lack of error handling can disclose sensitive information through error messages.\n",
      "classification": "slightly promising",
      "cwe": "CWE-209",
      "function_names": [
        "image"
      ],
      "filenames": [
        "helpers.js"
      ]
    },
    {
      "headline": "Hardcoded API Keys in Email Sending Function",
      "analysis": "The function sendViaApi in mailInvoiceController.js uses the API key stored in process.env.RESEND_API directly. If the RESEND_API environment variable is improperly managed or exposed, this could lead to unauthorized access.\n",
      "classification": "very promising",
      "cwe": "CWE-798",
      "function_names": [
        "sendViaApi"
      ],
      "filenames": [
        "controllers/erpControllers/mailInvoiceController.js"
      ]
    },
    {
      "headline": "Information Disclosure Through Detailed Error Messages in CRUD Operations",
      "analysis": "Multiple functions in apiRest.js disclose detailed error messages. Disclosing internal error structure can provide attackers with critical information about the application, facilitating other types of attacks.\n",
      "classification": "slightly promising",
      "cwe": "CWE-209",
      "function_names": [
        "create",
        "read",
        "update"
      ],
      "filenames": [
        "controllers/corsControllers/apiRest.js"
      ]
    },
    {
      "headline": "Missing Authentication for Important Operations",
      "analysis": "The read function in crudController.js does not check for proper authentication before accessing the database. This allows unauthenticated users to perform read operations on sensitive data.\n",
      "classification": "very promising",
      "cwe": "CWE-306",
      "function_names": [
        "read"
      ],
      "filenames": [
        "controllers/corsControllers/crudController.js"
      ]
    },
    {
      "headline": "No Rate Limiting for API Requests",
      "analysis": "The API endpoints in erpAuthRouter.js and other route files do not implement any rate limiting. This omission allows attackers to perform brute-force attacks or other types of denial-of-service attacks.\n",
      "classification": "very promising",
      "cwe": "CWE-307",
      "function_names": [
        "N/A"
      ],
      "filenames": [
        "routes/erpRoutes/erpAuthRouter.js",
        "routes/erpRoutes/erpApiRouter.js"
      ]
    }
  ],
  "scores": [
    {
      "stats": {
        "fn": 1,
        "tp": 0,
        "fp": 4
      },
      "mapping": {},
      "vuln_dates": {
        "CVE-2023-52265": "2023-12-30T23:15:42"
      },
      "scoring_model": "gpt-4o-2024-05-13",
      "type": "llm",
      "instruction_template_hash": "8998f09cf57fca8a6e03"
    },
    {
      "stats": {
        "fn": 1,
        "tp": 0,
        "fp": 4
      },
      "mapping": {},
      "vuln_dates": {
        "CVE-2023-52265": "2023-12-30T23:15:42"
      },
      "scoring_model": "claude-3-opus-20240229",
      "type": "llm",
      "instruction_template_hash": "245ace12b6361954d0a2"
    }
  ],
  "instruction_template_hash": "10c0163db4740318a544",
  "version": "0.1.0"
}
