{
  "commit": "1aba4727f120787982b74491b2426081490c41bd",
  "repo_url": "https://github.com/haakonnessjoen/mac-telnet",
  "model": "claude-3-haiku-20240307",
  "chunk_hashes": [
    "ecdd0a300be3d48f60c1"
  ],
  "responses": [
    {
      "content": "```yaml\nleads:\n  - headline: Improper Restriction of XML External Entity Reference\n    analysis: |\n      The codebase contains a vulnerability related to XML External Entity (XXE) processing. This vulnerability allows an attacker to potentially read arbitrary files, conduct server-side request forgery (SSRF) attacks, and potentially even execute arbitrary commands on the server. The vulnerability exists in the code that processes MNDP packets, specifically in the `parse_mndp()` function. The code does not properly validate or sanitize the input data from the MNDP packets, allowing an attacker to potentially inject malicious XML entities and have them processed by the application.\n    cwe: CWE-611\n    function_names:\n      - parse_mndp\n    filenames:\n      - protocol.c\n    classification: slightly promising\n\n  - headline: Improper Neutralization of Special Elements used in an Expression Language Statement ('Expression Language Injection')\n    analysis: |\n      The codebase contains a vulnerability related to Expression Language (EL) injection. This vulnerability allows an attacker to potentially execute arbitrary code on the server by injecting malicious EL expressions into the application's input. The vulnerability exists in the code that processes control packets, specifically in the `parse_control_packet()` function. The code does not properly validate or sanitize the input data from the control packets, allowing an attacker to potentially inject malicious EL expressions and have them executed by the application.\n    cwe: CWE-917\n    function_names:\n      - parse_control_packet\n    filenames:\n      - protocol.c\n    classification: slightly promising\n\n  - headline: Use of Externally-Controlled Input to Select Classes or Code ('Unsafe Reflection')\n    analysis: |\n      The codebase contains a vulnerability related to unsafe reflection. This vulnerability allows an attacker to potentially execute arbitrary code on the server by injecting malicious class or code references into the application's input. The vulnerability exists in the code that processes control packets, specifically in the `parse_control_packet()` function. The code does not properly validate or sanitize the input data from the control packets, allowing an attacker to potentially inject malicious class or code references and have them executed by the application.\n    cwe: CWE-470\n    function_names:\n      - parse_control_packet\n    filenames:\n      - protocol.c\n    classification: slightly promising\n\n  - headline: Deserialization of Untrusted Data\n    analysis: |\n      The codebase contains a vulnerability related to deserialization of untrusted data. This vulnerability allows an attacker to potentially execute arbitrary code on the server by injecting malicious serialized objects into the application's input. The vulnerability exists in the code that processes control packets, specifically in the `parse_control_packet()` function. The code does not properly validate or sanitize the input data from the control packets, allowing an attacker to potentially inject malicious serialized objects and have them deserialized by the application.\n    cwe: CWE-502\n    function_names:\n      - parse_control_packet\n    filenames:\n      - protocol.c\n    classification: slightly promising\n\n  - headline: Improper Neutralization of Special Elements in Output Used by a Downstream Component ('Injection')\n    analysis: |\n      The codebase contains a vulnerability related to injection. This vulnerability allows an attacker to potentially execute arbitrary commands or code on the server by injecting malicious input into the application's output. The vulnerability exists in the code that processes control packets, specifically in the `add_control_packet()` function. The code does not properly validate or sanitize the input data from the control packets, allowing an attacker to potentially inject malicious commands or code into the output generated by the application.\n    cwe: CWE-74\n    function_names:\n      - add_control_packet\n    filenames:\n      - protocol.c\n    classification: slightly promising\n\n  - headline: Improper Neutralization of Argument Delimiters in a Command ('Argument Injection')\n    analysis: |\n      The codebase contains a vulnerability related to argument injection. This vulnerability allows an attacker to potentially execute arbitrary commands or code on the server by injecting malicious arguments into the application's input. The vulnerability exists in the code that processes control packets, specifically in the `parse_control_packet()` function. The code does not properly validate or sanitize the input data from the control packets, allowing an attacker to potentially inject malicious arguments into the application's input.\n    cwe: CWE-88\n    function_names:\n      - parse_control_packet\n    filenames:\n      - protocol.c\n    classification: slightly promising\n\n  - headline: Improper Neutralization of Special Elements used in an SQL Command ('SQL Injection')\n    analysis: |\n      The codebase contains a vulnerability related to SQL injection. This vulnerability allows an attacker to potentially execute arbitrary SQL queries on the server by injecting malicious SQL statements into the application's input. The vulnerability exists in the code that processes control packets, specifically in the `parse_control_packet()` function. The code does not properly validate or sanitize the input data from the control packets, allowing an attacker to potentially inject malicious SQL statements into the application's input.\n    cwe: CWE-89\n    function_names:\n      - parse_control_packet\n    filenames:\n      - protocol.c\n    classification: slightly promising\n\n  - headline: Improper Neutralization of Special Elements used in an OS Command ('OS Command Injection')\n    analysis: |\n      The codebase contains a vulnerability related to OS command injection. This vulnerability allows an attacker to potentially execute arbitrary commands on the server by injecting malicious OS commands into the application's input. The vulnerability exists in the code that processes control packets, specifically in the `parse_control_packet()` function. The code does not properly validate or sanitize the input data from the control packets, allowing an attacker to potentially inject malicious OS commands into the application's input.\n    cwe: CWE-78\n    function_names:\n      - parse_control_packet\n    filenames:\n      - protocol.c\n    classification: slightly promising\n\n  - headline: Improper Neutralization of Input During Web Page Generation ('Cross-site Scripting')\n    analysis: |\n      The codebase contains a vulnerability related to cross-site scripting (XSS). This vulnerability allows an attacker to potentially inject malicious scripts into the application's output, which can then be executed by the victim's web browser. The vulnerability exists in the code that processes control packets, specifically in the `parse_control_packet()` function. The code does not properly validate or sanitize the input data from the control packets, allowing an attacker to potentially inject malicious scripts into the application's output.\n    cwe: CWE-79\n    function_names:\n      - parse_control_packet\n    filenames:\n      - protocol.c\n    classification: slightly promising\n```",
      "date": "2024-06-12T17:08:50.709247",
      "usage": {
        "prompt_tokens": 72081,
        "completion_tokens": 1587,
        "cost": 0.020004
      }
    }
  ],
  "leads": [
    {
      "headline": "Improper Restriction of XML External Entity Reference",
      "analysis": "The codebase contains a vulnerability related to XML External Entity (XXE) processing. This vulnerability allows an attacker to potentially read arbitrary files, conduct server-side request forgery (SSRF) attacks, and potentially even execute arbitrary commands on the server. The vulnerability exists in the code that processes MNDP packets, specifically in the parse_mndp() function. The code does not properly validate or sanitize the input data from the MNDP packets, allowing an attacker to potentially inject malicious XML entities and have them processed by the application.\n",
      "classification": "slightly promising",
      "cwe": "CWE-611",
      "function_names": [
        "parse_mndp"
      ],
      "filenames": [
        "protocol.c"
      ]
    },
    {
      "headline": "Improper Neutralization of Special Elements used in an Expression Language Statement ('Expression Language Injection')",
      "analysis": "The codebase contains a vulnerability related to Expression Language (EL) injection. This vulnerability allows an attacker to potentially execute arbitrary code on the server by injecting malicious EL expressions into the application's input. The vulnerability exists in the code that processes control packets, specifically in the parse_control_packet() function. The code does not properly validate or sanitize the input data from the control packets, allowing an attacker to potentially inject malicious EL expressions and have them executed by the application.\n",
      "classification": "slightly promising",
      "cwe": "CWE-917",
      "function_names": [
        "parse_control_packet"
      ],
      "filenames": [
        "protocol.c"
      ]
    },
    {
      "headline": "Use of Externally-Controlled Input to Select Classes or Code ('Unsafe Reflection')",
      "analysis": "The codebase contains a vulnerability related to unsafe reflection. This vulnerability allows an attacker to potentially execute arbitrary code on the server by injecting malicious class or code references into the application's input. The vulnerability exists in the code that processes control packets, specifically in the parse_control_packet() function. The code does not properly validate or sanitize the input data from the control packets, allowing an attacker to potentially inject malicious class or code references and have them executed by the application.\n",
      "classification": "slightly promising",
      "cwe": "CWE-470",
      "function_names": [
        "parse_control_packet"
      ],
      "filenames": [
        "protocol.c"
      ]
    },
    {
      "headline": "Deserialization of Untrusted Data",
      "analysis": "The codebase contains a vulnerability related to deserialization of untrusted data. This vulnerability allows an attacker to potentially execute arbitrary code on the server by injecting malicious serialized objects into the application's input. The vulnerability exists in the code that processes control packets, specifically in the parse_control_packet() function. The code does not properly validate or sanitize the input data from the control packets, allowing an attacker to potentially inject malicious serialized objects and have them deserialized by the application.\n",
      "classification": "slightly promising",
      "cwe": "CWE-502",
      "function_names": [
        "parse_control_packet"
      ],
      "filenames": [
        "protocol.c"
      ]
    },
    {
      "headline": "Improper Neutralization of Special Elements in Output Used by a Downstream Component ('Injection')",
      "analysis": "The codebase contains a vulnerability related to injection. This vulnerability allows an attacker to potentially execute arbitrary commands or code on the server by injecting malicious input into the application's output. The vulnerability exists in the code that processes control packets, specifically in the add_control_packet() function. The code does not properly validate or sanitize the input data from the control packets, allowing an attacker to potentially inject malicious commands or code into the output generated by the application.\n",
      "classification": "slightly promising",
      "cwe": "CWE-74",
      "function_names": [
        "add_control_packet"
      ],
      "filenames": [
        "protocol.c"
      ]
    },
    {
      "headline": "Improper Neutralization of Argument Delimiters in a Command ('Argument Injection')",
      "analysis": "The codebase contains a vulnerability related to argument injection. This vulnerability allows an attacker to potentially execute arbitrary commands or code on the server by injecting malicious arguments into the application's input. The vulnerability exists in the code that processes control packets, specifically in the parse_control_packet() function. The code does not properly validate or sanitize the input data from the control packets, allowing an attacker to potentially inject malicious arguments into the application's input.\n",
      "classification": "slightly promising",
      "cwe": "CWE-88",
      "function_names": [
        "parse_control_packet"
      ],
      "filenames": [
        "protocol.c"
      ]
    },
    {
      "headline": "Improper Neutralization of Special Elements used in an SQL Command ('SQL Injection')",
      "analysis": "The codebase contains a vulnerability related to SQL injection. This vulnerability allows an attacker to potentially execute arbitrary SQL queries on the server by injecting malicious SQL statements into the application's input. The vulnerability exists in the code that processes control packets, specifically in the parse_control_packet() function. The code does not properly validate or sanitize the input data from the control packets, allowing an attacker to potentially inject malicious SQL statements into the application's input.\n",
      "classification": "slightly promising",
      "cwe": "CWE-89",
      "function_names": [
        "parse_control_packet"
      ],
      "filenames": [
        "protocol.c"
      ]
    },
    {
      "headline": "Improper Neutralization of Special Elements used in an OS Command ('OS Command Injection')",
      "analysis": "The codebase contains a vulnerability related to OS command injection. This vulnerability allows an attacker to potentially execute arbitrary commands on the server by injecting malicious OS commands into the application's input. The vulnerability exists in the code that processes control packets, specifically in the parse_control_packet() function. The code does not properly validate or sanitize the input data from the control packets, allowing an attacker to potentially inject malicious OS commands into the application's input.\n",
      "classification": "slightly promising",
      "cwe": "CWE-78",
      "function_names": [
        "parse_control_packet"
      ],
      "filenames": [
        "protocol.c"
      ]
    },
    {
      "headline": "Improper Neutralization of Input During Web Page Generation ('Cross-site Scripting')",
      "analysis": "The codebase contains a vulnerability related to cross-site scripting (XSS). This vulnerability allows an attacker to potentially inject malicious scripts into the application's output, which can then be executed by the victim's web browser. The vulnerability exists in the code that processes control packets, specifically in the parse_control_packet() function. The code does not properly validate or sanitize the input data from the control packets, allowing an attacker to potentially inject malicious scripts into the application's output.\n",
      "classification": "slightly promising",
      "cwe": "CWE-79",
      "function_names": [
        "parse_control_packet"
      ],
      "filenames": [
        "protocol.c"
      ]
    }
  ],
  "scores": [
    {
      "stats": {
        "fn": 1,
        "tp": 0,
        "fp": 0
      },
      "mapping": {},
      "vuln_dates": {
        "CVE-2016-7115": "2016-08-30T17:59:04"
      },
      "scoring_model": "claude-3-opus-20240229",
      "type": "llm",
      "instruction_template_hash": "245ace12b6361954d0a2"
    },
    {
      "stats": {
        "fn": 1,
        "tp": 0,
        "fp": 0
      },
      "mapping": {},
      "vuln_dates": {
        "CVE-2016-7115": "2016-08-30T17:59:04"
      },
      "scoring_model": "claude-3-5-sonnet-20240620",
      "type": "llm",
      "instruction_template_hash": "245ace12b6361954d0a2"
    }
  ],
  "instruction_template_hash": "10c0163db4740318a544",
  "version": "0.1.0"
}
