{
  "commit": "38c1f60e935014edb927aa38888a957b6714b55a",
  "repo_url": "https://github.com/jenkinsci/kanboard-plugin",
  "model": "gpt-4o-2024-05-13",
  "chunk_hashes": [
    "d6a7f62cfe827527c3c0"
  ],
  "responses": [
    {
      "content": "```yaml\nleads:\n  - headline: \"Hard-coded Credentials in Utils.java\"\n    analysis: |\n      The `ApiAuthenticator` class in the `Utils.java` file constructs the authentication token by directly encoding the API token. This hard-coded configuration can expose sensitive information, making it easier for attackers to compromise the application. The issue resides in the `configure` method within the `ApiAuthenticator` class, where the `xApiAuthToken` is constructed and added to the HTTP connection header.\n    cwe: CWE-798\n    function_names:\n      - \"ApiAuthenticator.configure\"\n    filenames:\n      - \"src/main/java/org/mably/jenkins/plugins/kanboard/Utils.java\"\n    classification: \"very promising\"\n  - headline: \"Missing Release of Resource after Effective Lifetime\"\n    analysis: |\n      The method `fetchAttachments` in `KanboardTaskFetcher.java` fetches URL contents and writes the data into files but does not ensure the proper release of resources. There are cases where the `HttpURLConnection` may not get properly disconnected, leading to potential resource leaks.\n    cwe: CWE-772\n    function_names:\n      - \"KanboardTaskFetcher.fetchAttachments\"\n    filenames:\n      - \"src/main/java/org/mably/jenkins/plugins/kanboard/KanboardTaskFetcher.java\"\n    classification: \"slightly promising\"\n  - headline: \"Improper Input Validation\"\n    analysis: |\n      The method `getCSVStringValue` in `Utils.java` assumes that the input string is appropriately formatted and splits it based on commas. However, there is no input sanitizer to handle unexpected or malformed inputs, which can lead to unexpected behaviors or potential security issues.\n    cwe: CWE-20\n    function_names:\n      - \"Utils.getCSVStringValue\"\n    filenames:\n      - \"src/main/java/org/mably/jenkins/plugins/kanboard/Utils.java\"\n    classification: \"slightly promising\"\n  - headline: \"Potential Command Injection\"\n    analysis: |\n      In `KanboardTaskPublisher.java`, there is a method `perform` that sets up various task properties using input strings. These inputs are not adequately sanitized before being used in session requests, which could enable command injection attacks if an attacker controls the input.\n    cwe: CWE-78\n    function_names:\n      - \"KanboardTaskPublisher.perform\"\n    filenames:\n      - \"src/main/java/org/mably/jenkins/plugins/kanboard/KanboardTaskPublisher.java\"\n    classification: \"very promising\"\n  - headline: \"Exposure of Sensitive Information in Logs\"\n    analysis: |\n      Methods like `initJSONRPCSession` in `Utils.java`, where debug mode is enabled, could potentially log sensitive information such as API tokens or passwords. If the log files are accessible, they could expose sensitive information.\n    cwe: CWE-532\n    function_names:\n      - \"Utils.initJSONRPCSession\"\n    filenames:\n      - \"src/main/java/org/mably/jenkins/plugins/kanboard/Utils.java\"\n    classification: \"slightly promising\"\n  - headline: \"Use of Insecure Cryptographic Storage\"\n    analysis: |\n      Files are encoded and decoded using Base64 in methods such as `encodeFileToBase64Binary` and `decodeBase64ToBinaryFile` in `Utils.java`. Base64 is not a secure means of storing or transmitting data as it is easily reversible, hence sensitive data should be encrypted using secure algorithms.\n    cwe: CWE-922\n    function_names:\n      - \"Utils.encodeFileToBase64Binary\"\n      - \"Utils.decodeBase64ToBinaryFile\"\n    filenames:\n      - \"src/main/java/org/mably/jenkins/plugins/kanboard/Utils.java\"\n    classification: \"slightly promising\"\n  - headline: \"Missing Authentication for Critical Function\"\n    analysis: |\n      The `KanboardQueryTrigger` class lacks proper authentication checks before performing the task query, which could lead to unauthorized access and manipulation of data. It's crucial to ensure that only authenticated users can trigger and query tasks.\n    cwe: CWE-306\n    function_names:\n      - \"KanboardQueryTrigger.run\"\n      - \"KanboardQueryTrigger.queryTasks\"\n    filenames:\n      - \"src/main/java/org/mably/jenkins/plugins/kanboard/KanboardQueryTrigger.java\"\n    classification: \"very promising\"\n```",
      "date": "2024-06-14T14:18:57.038322",
      "usage": {
        "prompt_tokens": 23175,
        "completion_tokens": 900,
        "cost": 0.129375
      }
    }
  ],
  "leads": [
    {
      "headline": "Hard-coded Credentials in Utils.java",
      "analysis": "The ApiAuthenticator class in the Utils.java file constructs the authentication token by directly encoding the API token. This hard-coded configuration can expose sensitive information, making it easier for attackers to compromise the application. The issue resides in the configure method within the ApiAuthenticator class, where the xApiAuthToken is constructed and added to the HTTP connection header.\n",
      "classification": "very promising",
      "cwe": "CWE-798",
      "function_names": [
        "ApiAuthenticator.configure"
      ],
      "filenames": [
        "src/main/java/org/mably/jenkins/plugins/kanboard/Utils.java"
      ]
    },
    {
      "headline": "Missing Release of Resource after Effective Lifetime",
      "analysis": "The method fetchAttachments in KanboardTaskFetcher.java fetches URL contents and writes the data into files but does not ensure the proper release of resources. There are cases where the HttpURLConnection may not get properly disconnected, leading to potential resource leaks.\n",
      "classification": "slightly promising",
      "cwe": "CWE-772",
      "function_names": [
        "KanboardTaskFetcher.fetchAttachments"
      ],
      "filenames": [
        "src/main/java/org/mably/jenkins/plugins/kanboard/KanboardTaskFetcher.java"
      ]
    },
    {
      "headline": "Improper Input Validation",
      "analysis": "The method getCSVStringValue in Utils.java assumes that the input string is appropriately formatted and splits it based on commas. However, there is no input sanitizer to handle unexpected or malformed inputs, which can lead to unexpected behaviors or potential security issues.\n",
      "classification": "slightly promising",
      "cwe": "CWE-20",
      "function_names": [
        "Utils.getCSVStringValue"
      ],
      "filenames": [
        "src/main/java/org/mably/jenkins/plugins/kanboard/Utils.java"
      ]
    },
    {
      "headline": "Potential Command Injection",
      "analysis": "In KanboardTaskPublisher.java, there is a method perform that sets up various task properties using input strings. These inputs are not adequately sanitized before being used in session requests, which could enable command injection attacks if an attacker controls the input.\n",
      "classification": "very promising",
      "cwe": "CWE-78",
      "function_names": [
        "KanboardTaskPublisher.perform"
      ],
      "filenames": [
        "src/main/java/org/mably/jenkins/plugins/kanboard/KanboardTaskPublisher.java"
      ]
    },
    {
      "headline": "Exposure of Sensitive Information in Logs",
      "analysis": "Methods like initJSONRPCSession in Utils.java, where debug mode is enabled, could potentially log sensitive information such as API tokens or passwords. If the log files are accessible, they could expose sensitive information.\n",
      "classification": "slightly promising",
      "cwe": "CWE-532",
      "function_names": [
        "Utils.initJSONRPCSession"
      ],
      "filenames": [
        "src/main/java/org/mably/jenkins/plugins/kanboard/Utils.java"
      ]
    },
    {
      "headline": "Use of Insecure Cryptographic Storage",
      "analysis": "Files are encoded and decoded using Base64 in methods such as encodeFileToBase64Binary and decodeBase64ToBinaryFile in Utils.java. Base64 is not a secure means of storing or transmitting data as it is easily reversible, hence sensitive data should be encrypted using secure algorithms.\n",
      "classification": "slightly promising",
      "cwe": "CWE-922",
      "function_names": [
        "Utils.encodeFileToBase64Binary",
        "Utils.decodeBase64ToBinaryFile"
      ],
      "filenames": [
        "src/main/java/org/mably/jenkins/plugins/kanboard/Utils.java"
      ]
    },
    {
      "headline": "Missing Authentication for Critical Function",
      "analysis": "The KanboardQueryTrigger class lacks proper authentication checks before performing the task query, which could lead to unauthorized access and manipulation of data. It's crucial to ensure that only authenticated users can trigger and query tasks.\n",
      "classification": "very promising",
      "cwe": "CWE-306",
      "function_names": [
        "KanboardQueryTrigger.run",
        "KanboardQueryTrigger.queryTasks"
      ],
      "filenames": [
        "src/main/java/org/mably/jenkins/plugins/kanboard/KanboardQueryTrigger.java"
      ]
    }
  ],
  "scores": [
    {
      "stats": {
        "fn": 1,
        "tp": 0,
        "fp": 3
      },
      "mapping": {},
      "vuln_dates": {
        "CVE-2019-1003020": "2019-02-06T16:29:00"
      },
      "scoring_model": "claude-3-opus-20240229",
      "type": "llm",
      "instruction_template_hash": "245ace12b6361954d0a2"
    },
    {
      "stats": {
        "fn": 1,
        "tp": 0,
        "fp": 3
      },
      "mapping": {},
      "vuln_dates": {
        "CVE-2019-1003020": "2019-02-06T16:29:00"
      },
      "scoring_model": "claude-3-5-sonnet-20240620",
      "type": "llm",
      "instruction_template_hash": "245ace12b6361954d0a2"
    }
  ],
  "instruction_template_hash": "10c0163db4740318a544",
  "version": "0.1.0"
}
