{
  "commit": "01e9fbb37c0319d56070046182bdbb4f193b20d8",
  "repo_url": "https://github.com/forumone/wp-cfm",
  "model": "gpt-4-turbo-2024-04-09",
  "chunk_hashes": [
    "c9e6926a550ebc8905d7"
  ],
  "responses": [
    {
      "content": "```yaml\nleads:\n  - headline: Insecure direct object reference in admin functionality\n    analysis: |\n      The JavaScript code in assets/js/admin.js directly manipulates DOM elements based on user input without proper sanitization or authorization checks. This can lead to issues where malicious scripts could be injected or unintended actions could be triggered by manipulating the DOM elements directly from the browser console or through crafted payloads.\n    cwe: CWE-22\n    function_names:\n      - prettyTextDiff\n    filenames:\n      - assets/js/admin.js\n    classification: very promising\n\n  - headline: Command injection possibility in Grunt configuration\n    analysis: |\n      The Grunt configuration file 'Gruntfile.js' dynamically constructs shell commands based on input which includes composer bin paths. If the composer bin path or any part involved in command construction can be controlled by an attacker or ends up being tampered with by other malicious modifications or misconfigurations, it could lead to command injection vulnerabilities.\n    cwe: CWE-77\n    function_names:\n      - shell\n    filenames:\n      - Gruntfile.js\n    classification: very promising\n\n  - headline: Lack of input validation for multi-select jQuery plugin\n    analysis: |\n      The jQuery multi-select plugin in 'assets/js/multiselect/jquery.multiselect.js' does not validate or encode the input from the select options it constructs dynamically. This could potentially lead to cross-site scripting (XSS) if the option values contain executable code or markup injected by an attacker.\n    cwe: CWE-79\n    function_names:\n      - MultiSelect\n    filenames:\n      - assets/js/multiselect/jquery.multiselect.js\n    classification: very promising\n\n  - headline: Uncontrolled resource consumption due to recursive entity references\n    analysis: |\n      The code in the included third-party library 'assets/js/pretty-text-diff/diff_match_patch.js' appears to use recursive methods to compute differences without proper termination or depth handling. This could potentially lead to denial of service (DoS) via deeply nested recursive calls or extremely long input sequences that could exhaust system resources.\n    cwe: CWE-674\n    function_names:\n      - diff_match_patch\n    filenames:\n      - assets/js/pretty-text-diff/diff_match_patch.js\n    classification: very promising\n\n  - headline: Potential XPath injection in jQuery prettyTextDiff plugin\n    analysis: |\n      The 'assets/js/pretty-text-diff/jquery.pretty-text-diff.js' script processes differences in textual content. It involves the manipulation and placement of user-controlled data into HTML without escaping, potentially leading to injection flaws such as XPath injection if this input is processed further in XML or similar technologies.\n    cwe: CWE-91\n    function_names:\n      - prettyTextDiff\n    filenames:\n      - assets/js/pretty-text-diff/jquery.pretty-text-diff.js\n    classification: slightly promising\n\n  - headline: Server-side request forgery (SSRF) risk in Gruntfile network operations\n    analysis: |\n      In 'Gruntfile.js', the 'gitinfo' and 'checkrepo' tasks interact with external Git repositories. If the repository URLs or other Git parameters are externally influenced or not adequately validated, this could lead to SSRF where the Grunt tasks could be manipulated to interact with unintended servers or services.\n    cwe: CWE-918\n    function_names:\n      - gitinfo\n      - checkrepo\n    filenames:\n      - Gruntfile.js\n    classification: slightly promising\n```",
      "date": "2024-06-09T12:07:29.580857",
      "usage": {
        "prompt_tokens": 14826,
        "completion_tokens": 718,
        "cost": 0.1698
      }
    }
  ],
  "leads": [
    {
      "headline": "Insecure direct object reference in admin functionality",
      "analysis": "The JavaScript code in assets/js/admin.js directly manipulates DOM elements based on user input without proper sanitization or authorization checks. This can lead to issues where malicious scripts could be injected or unintended actions could be triggered by manipulating the DOM elements directly from the browser console or through crafted payloads.\n",
      "classification": "very promising",
      "cwe": "CWE-22",
      "function_names": [
        "prettyTextDiff"
      ],
      "filenames": [
        "assets/js/admin.js"
      ]
    },
    {
      "headline": "Command injection possibility in Grunt configuration",
      "analysis": "The Grunt configuration file 'Gruntfile.js' dynamically constructs shell commands based on input which includes composer bin paths. If the composer bin path or any part involved in command construction can be controlled by an attacker or ends up being tampered with by other malicious modifications or misconfigurations, it could lead to command injection vulnerabilities.\n",
      "classification": "very promising",
      "cwe": "CWE-77",
      "function_names": [
        "shell"
      ],
      "filenames": [
        "Gruntfile.js"
      ]
    },
    {
      "headline": "Lack of input validation for multi-select jQuery plugin",
      "analysis": "The jQuery multi-select plugin in 'assets/js/multiselect/jquery.multiselect.js' does not validate or encode the input from the select options it constructs dynamically. This could potentially lead to cross-site scripting (XSS) if the option values contain executable code or markup injected by an attacker.\n",
      "classification": "very promising",
      "cwe": "CWE-79",
      "function_names": [
        "MultiSelect"
      ],
      "filenames": [
        "assets/js/multiselect/jquery.multiselect.js"
      ]
    },
    {
      "headline": "Uncontrolled resource consumption due to recursive entity references",
      "analysis": "The code in the included third-party library 'assets/js/pretty-text-diff/diff_match_patch.js' appears to use recursive methods to compute differences without proper termination or depth handling. This could potentially lead to denial of service (DoS) via deeply nested recursive calls or extremely long input sequences that could exhaust system resources.\n",
      "classification": "very promising",
      "cwe": "CWE-674",
      "function_names": [
        "diff_match_patch"
      ],
      "filenames": [
        "assets/js/pretty-text-diff/diff_match_patch.js"
      ]
    },
    {
      "headline": "Potential XPath injection in jQuery prettyTextDiff plugin",
      "analysis": "The 'assets/js/pretty-text-diff/jquery.pretty-text-diff.js' script processes differences in textual content. It involves the manipulation and placement of user-controlled data into HTML without escaping, potentially leading to injection flaws such as XPath injection if this input is processed further in XML or similar technologies.\n",
      "classification": "slightly promising",
      "cwe": "CWE-91",
      "function_names": [
        "prettyTextDiff"
      ],
      "filenames": [
        "assets/js/pretty-text-diff/jquery.pretty-text-diff.js"
      ]
    },
    {
      "headline": "Server-side request forgery (SSRF) risk in Gruntfile network operations",
      "analysis": "In 'Gruntfile.js', the 'gitinfo' and 'checkrepo' tasks interact with external Git repositories. If the repository URLs or other Git parameters are externally influenced or not adequately validated, this could lead to SSRF where the Grunt tasks could be manipulated to interact with unintended servers or services.\n",
      "classification": "slightly promising",
      "cwe": "CWE-918",
      "function_names": [
        "gitinfo",
        "checkrepo"
      ],
      "filenames": [
        "Gruntfile.js"
      ]
    }
  ],
  "scores": [
    {
      "stats": {
        "fn": 1,
        "tp": 0,
        "fp": 4
      },
      "mapping": {},
      "vuln_dates": {
        "CVE-2024-24706": "2024-02-07T17:15:11"
      },
      "scoring_model": "gpt-4o-2024-05-13",
      "type": "llm",
      "instruction_template_hash": "8998f09cf57fca8a6e03"
    }
  ],
  "instruction_template_hash": "10c0163db4740318a544",
  "version": "0.1.0"
}
