{
  "commit": "432d7c60a1f64bfd1ad05683392cec36c6bc8455",
  "repo_url": "https://github.com/yubico/yubico-pam",
  "model": "claude-3-5-sonnet-20240620",
  "chunk_hashes": [
    "e4f2e5c1f2563f478811"
  ],
  "responses": [
    {
      "content": "Here's my analysis of the security vulnerabilities in the provided codebase:\n\n```yaml\nleads:\n  - headline: Buffer overflow in get_user_cfgfile_path function\n    analysis: |\n      The get_user_cfgfile_path function in util.c uses sprintf to construct a file path, which can lead to a buffer overflow if the inputs are too long. The buffer 'userfile' is allocated with a fixed size based on the lengths of the inputs, but sprintf is used without length checking. An attacker could provide overly long inputs to overflow the buffer.\n    cwe: CWE-120\n    function_names:\n      - get_user_cfgfile_path\n    filenames:\n      - util.c\n    classification: very promising\n\n  - headline: Potential command injection in ykpamcfg\n    analysis: |\n      The ykpamcfg utility takes user input for the output path (-p option) and uses it directly when creating directories and files. This could allow an attacker to inject malicious commands if special characters are not properly sanitized. The code does not appear to do sufficient input validation or sanitization on the path.\n    cwe: CWE-78\n    function_names:\n      - main\n    filenames:\n      - ykpamcfg.c\n    classification: slightly promising\n\n  - headline: Use of deprecated LDAP functions\n    analysis: |\n      The code uses deprecated LDAP functions like ldap_init and ldap_simple_bind_s. While not directly exploitable, using deprecated functions increases the risk of vulnerabilities and makes the code less secure overall. The comments indicate these will be updated soon, but currently pose a potential security risk.\n    cwe: CWE-477\n    function_names:\n      - authorize_user_token_ldap  \n    filenames:\n      - pam_yubico.c\n    classification: slightly promising\n\n  - headline: Potential for timing attacks in password comparison\n    analysis: |\n      The check_user_token function compares passwords using strcmp, which can be vulnerable to timing attacks. An attacker may be able to determine information about the correct password by measuring the time taken for comparisons. A constant-time comparison function should be used instead for cryptographic operations.\n    cwe: CWE-208\n    function_names: \n      - check_user_token\n    filenames:\n      - util.c  \n    classification: slightly promising\n\n  - headline: Lack of input validation on user-supplied data\n    analysis: |\n      Several functions like filter_printf take user-supplied input and use it directly in string formatting operations without proper validation. This could potentially lead to format string vulnerabilities if an attacker can control the format string. More rigorous input validation and sanitization should be implemented.\n    cwe: CWE-134\n    function_names:\n      - filter_printf\n    filenames:\n      - util.c\n    classification: slightly promising\n```\n\nThis analysis identifies several potential security vulnerabilities in the codebase, ranging from more serious issues like buffer overflows to less critical but still concerning issues like use of deprecated functions. The most promising vulnerability is the potential buffer overflow in get_user_cfgfile_path, which could allow arbitrary code execution if exploited. The other issues are less severe but still warrant attention to improve the overall security of the code.",
      "date": "2024-07-08T09:29:57.744411",
      "usage": {
        "prompt_tokens": 40333,
        "completion_tokens": 764,
        "cost": 0.132459
      }
    }
  ],
  "leads": [
    {
      "headline": "Buffer overflow in get_user_cfgfile_path function",
      "analysis": "The get_user_cfgfile_path function in util.c uses sprintf to construct a file path, which can lead to a buffer overflow if the inputs are too long. The buffer 'userfile' is allocated with a fixed size based on the lengths of the inputs, but sprintf is used without length checking. An attacker could provide overly long inputs to overflow the buffer.\n",
      "classification": "very promising",
      "cwe": "CWE-120",
      "function_names": [
        "get_user_cfgfile_path"
      ],
      "filenames": [
        "util.c"
      ]
    },
    {
      "headline": "Potential command injection in ykpamcfg",
      "analysis": "The ykpamcfg utility takes user input for the output path (-p option) and uses it directly when creating directories and files. This could allow an attacker to inject malicious commands if special characters are not properly sanitized. The code does not appear to do sufficient input validation or sanitization on the path.\n",
      "classification": "slightly promising",
      "cwe": "CWE-78",
      "function_names": [
        "main"
      ],
      "filenames": [
        "ykpamcfg.c"
      ]
    },
    {
      "headline": "Use of deprecated LDAP functions",
      "analysis": "The code uses deprecated LDAP functions like ldap_init and ldap_simple_bind_s. While not directly exploitable, using deprecated functions increases the risk of vulnerabilities and makes the code less secure overall. The comments indicate these will be updated soon, but currently pose a potential security risk.\n",
      "classification": "slightly promising",
      "cwe": "CWE-477",
      "function_names": [
        "authorize_user_token_ldap"
      ],
      "filenames": [
        "pam_yubico.c"
      ]
    },
    {
      "headline": "Potential for timing attacks in password comparison",
      "analysis": "The check_user_token function compares passwords using strcmp, which can be vulnerable to timing attacks. An attacker may be able to determine information about the correct password by measuring the time taken for comparisons. A constant-time comparison function should be used instead for cryptographic operations.\n",
      "classification": "slightly promising",
      "cwe": "CWE-208",
      "function_names": [
        "check_user_token"
      ],
      "filenames": [
        "util.c"
      ]
    },
    {
      "headline": "Lack of input validation on user-supplied data",
      "analysis": "Several functions like filter_printf take user-supplied input and use it directly in string formatting operations without proper validation. This could potentially lead to format string vulnerabilities if an attacker can control the format string. More rigorous input validation and sanitization should be implemented.\n",
      "classification": "slightly promising",
      "cwe": "CWE-134",
      "function_names": [
        "filter_printf"
      ],
      "filenames": [
        "util.c"
      ]
    }
  ],
  "scores": [
    {
      "stats": {
        "fn": 1,
        "tp": 0,
        "fp": 1
      },
      "mapping": {},
      "vuln_dates": {
        "CVE-2018-9275": "2018-04-04T18:29:02"
      },
      "scoring_model": "claude-3-5-sonnet-20240620",
      "type": "llm",
      "instruction_template_hash": "245ace12b6361954d0a2"
    }
  ],
  "instruction_template_hash": "10c0163db4740318a544",
  "version": "0.1.0"
}
