{
  "commit": "09485d682218f3d0c1b6f7acada4a48c2d362be0",
  "repo_url": "https://github.com/elric1/knc",
  "model": "claude-3-sonnet-20240229",
  "chunk_hashes": [
    "c94890c68989f19d4e24"
  ],
  "responses": [
    {
      "content": "```yaml\nleads:\n  - headline: Potential buffer overflow in knc_put_stream_gssbuf\n    analysis: |\n      The `knc_put_stream_gssbuf` function allocates memory using `calloc` based on the length of the input `gss_buffer_t` structure. However, it does not validate the length field before allocating memory, which could lead to a buffer overflow if an attacker provides a malicious length value.\n    cwe: CWE-119\n    function_names:\n      - knc_put_stream_gssbuf\n    filenames:\n      - lib/libknc.c\n    classification: very promising\n\n  - headline: Potential integer overflow in knc_put_stream_mmapbuf\n    analysis: |\n      The `knc_put_stream_mmapbuf` function allocates memory using `mmap` based on the input `len` parameter. However, it does not validate the `len` parameter before mapping memory, which could lead to an integer overflow if an attacker provides a large value for `len`.\n    cwe: CWE-190\n    function_names:\n      - knc_put_stream_mmapbuf\n    filenames:\n      - lib/libknc.c\n    classification: very promising\n\n  - headline: Potential buffer overflow in knc_get_stream_bit\n    analysis: |\n      The `knc_alloc_stream_bit` function allocates a fixed-size buffer based on a hardcoded constant `STREAM_BIT_ALLOC_UNIT`. However, it does not validate the input `len` parameter against the allocated buffer size, which could lead to a buffer overflow if `len` is larger than the allocated buffer size.\n    cwe: CWE-119\n    function_names:\n      - knc_alloc_stream_bit\n      - knc_get_istream\n    filenames:\n      - lib/libknc.c\n    classification: very promising\n\n  - headline: Potential integer overflow in knc_get_obufv\n    analysis: |\n      The `knc_get_obufv` function allocates memory for an array of `iovec` structures based on the input `count` parameter. However, it does not validate the `count` parameter against the maximum allowed value of `MAX_IOVCNT`, which could lead to an integer overflow if an attacker provides a large value for `count`.\n    cwe: CWE-190\n    function_names:\n      - knc_get_obufv\n    filenames:\n      - lib/libknc.c\n    classification: very promising\n\n  - headline: Potential buffer overflow in read_packet\n    analysis: |\n      The `read_packet` function allocates a temporary buffer `tmpbuf` based on the received length field `len`. However, it does not validate the `len` value against a maximum allowed value, which could lead to a buffer overflow if an attacker provides a malicious value for `len`.\n    cwe: CWE-119\n    function_names:\n      - read_packet\n    filenames:\n      - lib/libknc.c\n    classification: very promising\n\n  - headline: Potential buffer overflow in knc_errstring\n    analysis: |\n      The `knc_errstring` function allocates memory for a string buffer based on the length of the input status message. However, it does not validate the length of the status message against a maximum allowed value, which could lead to a buffer overflow if an attacker provides a malicious status message with a large length.\n    cwe: CWE-119\n    function_names:\n      - knc_errstring\n    filenames:\n      - lib/libknc.c\n    classification: very promising\n\n  - headline: Potential buffer overflow in emit_key_value\n    analysis: |\n      The `emit_key_value` function writes the input `key` and `value` strings to a buffer without validating the length of these strings against a maximum allowed value. This could lead to a buffer overflow if an attacker provides malicious input strings with large lengths.\n    cwe: CWE-119\n    function_names:\n      - emit_key_value\n    filenames:\n      - bin/knc.c\n    classification: very promising\n\n  - headline: Potential buffer overflow in putenv_knc_key_value\n    analysis: |\n      The `putenv_knc_key_value` function allocates memory for a string buffer based on the concatenated lengths of the input `key` and `value` strings. However, it does not validate the lengths of these strings against a maximum allowed value, which could lead to a buffer overflow if an attacker provides malicious input strings with large lengths.\n    cwe: CWE-119\n    function_names:\n      - putenv_knc_key_value\n    filenames:\n      - bin/knc.c\n    classification: very promising\n\n  - headline: Potential buffer overflow in gstd_get_display_name\n    analysis: |\n      The `gstd_get_display_name` function allocates memory for a string buffer based on the length of the input `gss_name_t` structure. However, it does not validate the length field against a maximum allowed value, which could lead to a buffer overflow if an attacker provides a malicious `gss_name_t` structure with a large length value.\n    cwe: CWE-119\n    function_names:\n      - gstd_get_display_name\n    filenames:\n      - bin/gssstdio.c\n    classification: very promising\n\n  - headline: Potential buffer overflow in gstd_get_export_name\n    analysis: |\n      The `gstd_get_export_name` function allocates memory for a string buffer based on the length of the input `gss_name_t` structure. However, it does not validate the length field against a maximum allowed value, which could lead to a buffer overflow if an attacker provides a malicious `gss_name_t` structure with a large length value.\n    cwe: CWE-119\n    function_names:\n      - gstd_get_export_name\n    filenames:\n      - bin/gssstdio.c\n    classification: very promising\n\n  - headline: Potential buffer overflow in gstd_get_mech\n    analysis: |\n      The `gstd_get_mech` function allocates memory for a string buffer based on the length of the input `gss_OID` structure. However, it does not validate the length field against a maximum allowed value, which could lead to a buffer overflow if an attacker provides a malicious `gss_OID` structure with a large length value.\n    cwe: CWE-119\n    function_names:\n      - gstd_get_mech\n    filenames:\n      - bin/gssstdio.c\n    classification: very promising\n\n  - headline: Potential buffer overflow in gstd_errstring\n    analysis: |\n      The `gstd_errstring` function allocates memory for a string buffer based on the length of the input status message. However, it does not validate the length of the status message against a maximum allowed value, which could lead to a buffer overflow if an attacker provides a malicious status message with a large length.\n    cwe: CWE-119\n    function_names:\n      - gstd_errstring\n    filenames:\n      - bin/gssstdio.c\n    classification: very promising\n\n  - headline: Potential use of a hardcoded credential in knc_initiate\n    analysis: |\n      The `knc_initiate` function uses a hardcoded Kerberos principal name when `princ` is NULL, which could potentially lead to a security vulnerability if the hardcoded principal name is compromised or has weak credentials.\n    cwe: CWE-798\n    function_names:\n      - knc_initiate\n    filenames:\n      - lib/libknc.c\n    classification: slightly promising\n\n  - headline: Potential insecure deserialization in knc_state_session\n    analysis: |\n      The `knc_state_session` function processes incoming data from the network without validating the data format or content. This could potentially lead to an insecure deserialization vulnerability if an attacker sends malicious data that is improperly handled or deserialized by the function.\n    cwe: CWE-502\n    function_names:\n      - knc_state_session\n    filenames:\n      - lib/libknc.c\n    classification: slightly promising\n\n  - headline: Potential command injection in knc_state_command\n    analysis: |\n      The `knc_state_command` function processes incoming commands from the network without validating the command format or content. This could potentially lead to a command injection vulnerability if an attacker sends malicious commands that are improperly handled or executed by the function.\n    cwe: CWE-77\n    function_names:\n      - knc_state_command\n    filenames:\n      - lib/libknc.c\n    classification: slightly promising\n\n  - headline: Potential file inclusion vulnerability in launch_program\n    analysis: |\n      The `launch_program` function executes a program specified by the input `argv` array without validating the program path or arguments. This could potentially lead to a file inclusion vulnerability if an attacker provides a malicious program path or arguments that are executed without proper validation.\n    cwe: CWE-829\n    function_names:\n      - launch_program\n    filenames:\n      - bin/knc.c\n    classification: slightly promising\n\n  - headline: Potential use of hardcoded credentials in gstd_initiate\n    analysis: |\n      The `gstd_initiate` function constructs a hardcoded Kerberos service principal name based on the input `hostname` and `service` parameters without validating or sanitizing these inputs. This could potentially lead to a security vulnerability if an attacker provides malicious input values that result in an insecure or compromised principal name.\n    cwe: CWE-798\n    function_names:\n      - gstd_initiate\n    filenames:\n      - bin/gssstdio.c\n    classification: slightly promising\n\n  - headline: Potential race condition in launch_program\n    analysis: |\n      The `launch_program` function forks a child process and creates a socket pair for communication with the child process. However, there is a potential race condition between the child process and the parent process, where the child process could execute the `exec` function before the parent process sets up the communication channels properly.\n    cwe: CWE-362\n    function_names:\n      - launch_program\n    filenames:\n      - bin/knc.c\n    classification: not promising\n\n  - headline: Potential missing input validation in connect_host_inner\n    analysis: |\n      The `connect_host_inner` function accepts the `domain` and `service` parameters without validating or sanitizing them, which could potentially lead to security vulnerabilities if an attacker provides malicious input values.\n    cwe: CWE-20\n    function_names:\n      - connect_host_inner\n    filenames:\n      - bin/knc.c\n    classification: not promising\n\n  - headline: Potential missing error handling in gss_release_buffer\n    analysis: |\n      The `gstd_close` function calls `gss_release_buffer` without checking the return value, which could potentially lead to missing important error information or unexpected behavior if the function fails.\n    cwe: CWE-252\n    function_names:\n      - gstd_close\n    filenames:\n      - bin/gssstdio.c\n    classification: not promising\n\n  - headline: Potential hardcoded socket option in socket_options\n    analysis: |\n      The `socket_options` function sets the `O_NOSIGPIPE` option unconditionally, which could potentially lead to unexpected behavior or security issues if this option is not appropriate or desired in certain scenarios.\n    cwe: CWE-665\n    function_names:\n      - socket_options\n    filenames:\n      - lib/libknc.c\n    classification: not promising\n\n  - headline: Potential improper error handling in launch_program\n    analysis: |\n      The `launch_program` function does not properly handle errors when `dup2` fails for `STDIN_FILENO`, `STDOUT_FILENO`, or `STDERR_FILENO`, which could potentially lead to unexpected behavior or security issues.\n    cwe: CWE-755\n    function_names:\n      - launch_program\n    filenames:\n      - bin/knc.c\n    classification: not promising\n```",
      "date": "2024-06-12T16:15:53.069393",
      "usage": {
        "prompt_tokens": 62232,
        "completion_tokens": 2978,
        "cost": 0.231366
      }
    }
  ],
  "leads": [
    {
      "headline": "Potential buffer overflow in knc_put_stream_gssbuf",
      "analysis": "The knc_put_stream_gssbuf function allocates memory using calloc based on the length of the input gss_buffer_t structure. However, it does not validate the length field before allocating memory, which could lead to a buffer overflow if an attacker provides a malicious length value.\n",
      "classification": "very promising",
      "cwe": "CWE-119",
      "function_names": [
        "knc_put_stream_gssbuf"
      ],
      "filenames": [
        "lib/libknc.c"
      ]
    },
    {
      "headline": "Potential integer overflow in knc_put_stream_mmapbuf",
      "analysis": "The knc_put_stream_mmapbuf function allocates memory using mmap based on the input len parameter. However, it does not validate the len parameter before mapping memory, which could lead to an integer overflow if an attacker provides a large value for len.\n",
      "classification": "very promising",
      "cwe": "CWE-190",
      "function_names": [
        "knc_put_stream_mmapbuf"
      ],
      "filenames": [
        "lib/libknc.c"
      ]
    },
    {
      "headline": "Potential buffer overflow in knc_get_stream_bit",
      "analysis": "The knc_alloc_stream_bit function allocates a fixed-size buffer based on a hardcoded constant STREAM_BIT_ALLOC_UNIT. However, it does not validate the input len parameter against the allocated buffer size, which could lead to a buffer overflow if len is larger than the allocated buffer size.\n",
      "classification": "very promising",
      "cwe": "CWE-119",
      "function_names": [
        "knc_alloc_stream_bit",
        "knc_get_istream"
      ],
      "filenames": [
        "lib/libknc.c"
      ]
    },
    {
      "headline": "Potential integer overflow in knc_get_obufv",
      "analysis": "The knc_get_obufv function allocates memory for an array of iovec structures based on the input count parameter. However, it does not validate the count parameter against the maximum allowed value of MAX_IOVCNT, which could lead to an integer overflow if an attacker provides a large value for count.\n",
      "classification": "very promising",
      "cwe": "CWE-190",
      "function_names": [
        "knc_get_obufv"
      ],
      "filenames": [
        "lib/libknc.c"
      ]
    },
    {
      "headline": "Potential buffer overflow in read_packet",
      "analysis": "The read_packet function allocates a temporary buffer tmpbuf based on the received length field len. However, it does not validate the len value against a maximum allowed value, which could lead to a buffer overflow if an attacker provides a malicious value for len.\n",
      "classification": "very promising",
      "cwe": "CWE-119",
      "function_names": [
        "read_packet"
      ],
      "filenames": [
        "lib/libknc.c"
      ]
    },
    {
      "headline": "Potential buffer overflow in knc_errstring",
      "analysis": "The knc_errstring function allocates memory for a string buffer based on the length of the input status message. However, it does not validate the length of the status message against a maximum allowed value, which could lead to a buffer overflow if an attacker provides a malicious status message with a large length.\n",
      "classification": "very promising",
      "cwe": "CWE-119",
      "function_names": [
        "knc_errstring"
      ],
      "filenames": [
        "lib/libknc.c"
      ]
    },
    {
      "headline": "Potential buffer overflow in emit_key_value",
      "analysis": "The emit_key_value function writes the input key and value strings to a buffer without validating the length of these strings against a maximum allowed value. This could lead to a buffer overflow if an attacker provides malicious input strings with large lengths.\n",
      "classification": "very promising",
      "cwe": "CWE-119",
      "function_names": [
        "emit_key_value"
      ],
      "filenames": [
        "bin/knc.c"
      ]
    },
    {
      "headline": "Potential buffer overflow in putenv_knc_key_value",
      "analysis": "The putenv_knc_key_value function allocates memory for a string buffer based on the concatenated lengths of the input key and value strings. However, it does not validate the lengths of these strings against a maximum allowed value, which could lead to a buffer overflow if an attacker provides malicious input strings with large lengths.\n",
      "classification": "very promising",
      "cwe": "CWE-119",
      "function_names": [
        "putenv_knc_key_value"
      ],
      "filenames": [
        "bin/knc.c"
      ]
    },
    {
      "headline": "Potential buffer overflow in gstd_get_display_name",
      "analysis": "The gstd_get_display_name function allocates memory for a string buffer based on the length of the input gss_name_t structure. However, it does not validate the length field against a maximum allowed value, which could lead to a buffer overflow if an attacker provides a malicious gss_name_t structure with a large length value.\n",
      "classification": "very promising",
      "cwe": "CWE-119",
      "function_names": [
        "gstd_get_display_name"
      ],
      "filenames": [
        "bin/gssstdio.c"
      ]
    },
    {
      "headline": "Potential buffer overflow in gstd_get_export_name",
      "analysis": "The gstd_get_export_name function allocates memory for a string buffer based on the length of the input gss_name_t structure. However, it does not validate the length field against a maximum allowed value, which could lead to a buffer overflow if an attacker provides a malicious gss_name_t structure with a large length value.\n",
      "classification": "very promising",
      "cwe": "CWE-119",
      "function_names": [
        "gstd_get_export_name"
      ],
      "filenames": [
        "bin/gssstdio.c"
      ]
    },
    {
      "headline": "Potential buffer overflow in gstd_get_mech",
      "analysis": "The gstd_get_mech function allocates memory for a string buffer based on the length of the input gss_OID structure. However, it does not validate the length field against a maximum allowed value, which could lead to a buffer overflow if an attacker provides a malicious gss_OID structure with a large length value.\n",
      "classification": "very promising",
      "cwe": "CWE-119",
      "function_names": [
        "gstd_get_mech"
      ],
      "filenames": [
        "bin/gssstdio.c"
      ]
    },
    {
      "headline": "Potential buffer overflow in gstd_errstring",
      "analysis": "The gstd_errstring function allocates memory for a string buffer based on the length of the input status message. However, it does not validate the length of the status message against a maximum allowed value, which could lead to a buffer overflow if an attacker provides a malicious status message with a large length.\n",
      "classification": "very promising",
      "cwe": "CWE-119",
      "function_names": [
        "gstd_errstring"
      ],
      "filenames": [
        "bin/gssstdio.c"
      ]
    },
    {
      "headline": "Potential use of a hardcoded credential in knc_initiate",
      "analysis": "The knc_initiate function uses a hardcoded Kerberos principal name when princ is NULL, which could potentially lead to a security vulnerability if the hardcoded principal name is compromised or has weak credentials.\n",
      "classification": "slightly promising",
      "cwe": "CWE-798",
      "function_names": [
        "knc_initiate"
      ],
      "filenames": [
        "lib/libknc.c"
      ]
    },
    {
      "headline": "Potential insecure deserialization in knc_state_session",
      "analysis": "The knc_state_session function processes incoming data from the network without validating the data format or content. This could potentially lead to an insecure deserialization vulnerability if an attacker sends malicious data that is improperly handled or deserialized by the function.\n",
      "classification": "slightly promising",
      "cwe": "CWE-502",
      "function_names": [
        "knc_state_session"
      ],
      "filenames": [
        "lib/libknc.c"
      ]
    },
    {
      "headline": "Potential command injection in knc_state_command",
      "analysis": "The knc_state_command function processes incoming commands from the network without validating the command format or content. This could potentially lead to a command injection vulnerability if an attacker sends malicious commands that are improperly handled or executed by the function.\n",
      "classification": "slightly promising",
      "cwe": "CWE-77",
      "function_names": [
        "knc_state_command"
      ],
      "filenames": [
        "lib/libknc.c"
      ]
    },
    {
      "headline": "Potential file inclusion vulnerability in launch_program",
      "analysis": "The launch_program function executes a program specified by the input argv array without validating the program path or arguments. This could potentially lead to a file inclusion vulnerability if an attacker provides a malicious program path or arguments that are executed without proper validation.\n",
      "classification": "slightly promising",
      "cwe": "CWE-829",
      "function_names": [
        "launch_program"
      ],
      "filenames": [
        "bin/knc.c"
      ]
    },
    {
      "headline": "Potential use of hardcoded credentials in gstd_initiate",
      "analysis": "The gstd_initiate function constructs a hardcoded Kerberos service principal name based on the input hostname and service parameters without validating or sanitizing these inputs. This could potentially lead to a security vulnerability if an attacker provides malicious input values that result in an insecure or compromised principal name.\n",
      "classification": "slightly promising",
      "cwe": "CWE-798",
      "function_names": [
        "gstd_initiate"
      ],
      "filenames": [
        "bin/gssstdio.c"
      ]
    },
    {
      "headline": "Potential race condition in launch_program",
      "analysis": "The launch_program function forks a child process and creates a socket pair for communication with the child process. However, there is a potential race condition between the child process and the parent process, where the child process could execute the exec function before the parent process sets up the communication channels properly.\n",
      "classification": "not promising",
      "cwe": "CWE-362",
      "function_names": [
        "launch_program"
      ],
      "filenames": [
        "bin/knc.c"
      ]
    },
    {
      "headline": "Potential missing input validation in connect_host_inner",
      "analysis": "The connect_host_inner function accepts the domain and service parameters without validating or sanitizing them, which could potentially lead to security vulnerabilities if an attacker provides malicious input values.\n",
      "classification": "not promising",
      "cwe": "CWE-20",
      "function_names": [
        "connect_host_inner"
      ],
      "filenames": [
        "bin/knc.c"
      ]
    },
    {
      "headline": "Potential missing error handling in gss_release_buffer",
      "analysis": "The gstd_close function calls gss_release_buffer without checking the return value, which could potentially lead to missing important error information or unexpected behavior if the function fails.\n",
      "classification": "not promising",
      "cwe": "CWE-252",
      "function_names": [
        "gstd_close"
      ],
      "filenames": [
        "bin/gssstdio.c"
      ]
    },
    {
      "headline": "Potential hardcoded socket option in socket_options",
      "analysis": "The socket_options function sets the O_NOSIGPIPE option unconditionally, which could potentially lead to unexpected behavior or security issues if this option is not appropriate or desired in certain scenarios.\n",
      "classification": "not promising",
      "cwe": "CWE-665",
      "function_names": [
        "socket_options"
      ],
      "filenames": [
        "lib/libknc.c"
      ]
    },
    {
      "headline": "Potential improper error handling in launch_program",
      "analysis": "The launch_program function does not properly handle errors when dup2 fails for STDIN_FILENO, STDOUT_FILENO, or STDERR_FILENO, which could potentially lead to unexpected behavior or security issues.\n",
      "classification": "not promising",
      "cwe": "CWE-755",
      "function_names": [
        "launch_program"
      ],
      "filenames": [
        "bin/knc.c"
      ]
    }
  ],
  "scores": [
    {
      "stats": {
        "fn": 1,
        "tp": 0,
        "fp": 12
      },
      "mapping": {},
      "vuln_dates": {
        "CVE-2017-9732": "2018-12-20T23:29:00"
      },
      "scoring_model": "claude-3-opus-20240229",
      "type": "llm",
      "instruction_template_hash": "245ace12b6361954d0a2"
    },
    {
      "stats": {
        "fn": 1,
        "tp": 0,
        "fp": 12
      },
      "mapping": {},
      "vuln_dates": {
        "CVE-2017-9732": "2018-12-20T23:29:00"
      },
      "scoring_model": "claude-3-5-sonnet-20240620",
      "type": "llm",
      "instruction_template_hash": "245ace12b6361954d0a2"
    }
  ],
  "instruction_template_hash": "10c0163db4740318a544",
  "version": "0.1.0"
}
