{
  "commit": "7c8e93e6fb2420fb6003c54a741e267c4f883bab",
  "repo_url": "https://github.com/pixee/java-security-toolkit",
  "model": "claude-3-5-sonnet-20240620",
  "chunk_hashes": [
    "02a412cc0ecfd4e6d948"
  ],
  "responses": [
    {
      "content": "```yaml\nleads:\n  - headline: Unsafe XML parsing in DocumentBuilderFactorySecurityTest\n    analysis: |\n      The test case 'xxe_works_in_dbf' in DocumentBuilderFactorySecurityTest demonstrates that XML external entity (XXE) processing is enabled by default in the DocumentBuilderFactory. This allows an attacker to read arbitrary files on the system by including external entities in malicious XML input. The test creates a DocumentBuilderFactory without any security hardening and successfully reads the contents of a secret file via XXE.\n    cwe: CWE-611\n    function_names:\n      - xxe_works_in_dbf\n    filenames:\n      - src/test/java/io/github/pixee/security/DocumentBuilderFactorySecurityTest.java\n    classification: very promising\n\n  - headline: Unsafe XML parsing in XMLInputFactorySecurityTest  \n    analysis: |\n      The test case 'xxe_works_in_xmlinputfactory' in XMLInputFactorySecurityTest shows that XML external entity (XXE) processing is enabled by default in XMLInputFactory. This allows an attacker to read arbitrary files on the system by including external entities in malicious XML input. The test creates an XMLInputFactory without any security hardening and successfully reads the contents of a secret file via XXE.\n    cwe: CWE-611\n    function_names:\n      - xxe_works_in_xmlinputfactory\n    filenames:\n      - src/test/java/io/github/pixee/security/XMLInputFactorySecurityTest.java  \n    classification: very promising\n\n  - headline: Unsafe deserialization in ObjectInputFiltersTest\n    analysis: |\n      The test case 'default_is_unprotected' in ObjectInputFiltersTest demonstrates that Java deserialization is unsafe by default. It successfully deserializes a DiskFileItem object, which is a known gadget that can be exploited for remote code execution. This shows that without proper filtering, an attacker could craft malicious serialized data to achieve code execution when deserialized.\n    cwe: CWE-502\n    function_names:\n      - default_is_unprotected\n    filenames:\n      - src/java11Test/java/io/github/pixee/security/ObjectInputFiltersTest.java\n    classification: very promising\n\n  - headline: Potential command injection in SystemCommandTest\n    analysis: |\n      The SystemCommandTest class contains several test cases that allow potentially dangerous system commands to be executed. For example, the 'it_allows_innocent_commands' test passes commands like \"ls /etc\" directly to Runtime.exec(). While the test is intended to verify \"innocent\" commands, it demonstrates a pattern that could be exploited for command injection if user input was passed to these methods without proper sanitization.\n    cwe: CWE-78\n    function_names:\n      - it_allows_innocent_commands\n    filenames:\n      - src/test/java/io/github/pixee/security/SystemCommandTest.java\n    classification: slightly promising\n\n  - headline: Unsafe reflection in ReflectionTest\n    analysis: |\n      The ReflectionTest class contains methods that load classes dynamically using Class.forName(). While some checks are in place, the 'it_loads_normal_classes' test demonstrates loading arbitrary classes specified by a string name. This pattern could potentially be exploited to load and instantiate malicious classes if an attacker can control the class name input.\n    cwe: CWE-470\n    function_names:\n      - it_loads_normal_classes\n    filenames:\n      - src/test/java/io/github/pixee/security/ReflectionTest.java\n    classification: slightly promising\n```",
      "date": "2024-07-08T04:53:41.559969",
      "usage": {
        "prompt_tokens": 44458,
        "completion_tokens": 875,
        "cost": 0.146499
      }
    }
  ],
  "leads": [
    {
      "headline": "Unsafe XML parsing in DocumentBuilderFactorySecurityTest",
      "analysis": "The test case 'xxe_works_in_dbf' in DocumentBuilderFactorySecurityTest demonstrates that XML external entity (XXE) processing is enabled by default in the DocumentBuilderFactory. This allows an attacker to read arbitrary files on the system by including external entities in malicious XML input. The test creates a DocumentBuilderFactory without any security hardening and successfully reads the contents of a secret file via XXE.\n",
      "classification": "very promising",
      "cwe": "CWE-611",
      "function_names": [
        "xxe_works_in_dbf"
      ],
      "filenames": [
        "src/test/java/io/github/pixee/security/DocumentBuilderFactorySecurityTest.java"
      ]
    },
    {
      "headline": "Unsafe XML parsing in XMLInputFactorySecurityTest",
      "analysis": "The test case 'xxe_works_in_xmlinputfactory' in XMLInputFactorySecurityTest shows that XML external entity (XXE) processing is enabled by default in XMLInputFactory. This allows an attacker to read arbitrary files on the system by including external entities in malicious XML input. The test creates an XMLInputFactory without any security hardening and successfully reads the contents of a secret file via XXE.\n",
      "classification": "very promising",
      "cwe": "CWE-611",
      "function_names": [
        "xxe_works_in_xmlinputfactory"
      ],
      "filenames": [
        "src/test/java/io/github/pixee/security/XMLInputFactorySecurityTest.java"
      ]
    },
    {
      "headline": "Unsafe deserialization in ObjectInputFiltersTest",
      "analysis": "The test case 'default_is_unprotected' in ObjectInputFiltersTest demonstrates that Java deserialization is unsafe by default. It successfully deserializes a DiskFileItem object, which is a known gadget that can be exploited for remote code execution. This shows that without proper filtering, an attacker could craft malicious serialized data to achieve code execution when deserialized.\n",
      "classification": "very promising",
      "cwe": "CWE-502",
      "function_names": [
        "default_is_unprotected"
      ],
      "filenames": [
        "src/java11Test/java/io/github/pixee/security/ObjectInputFiltersTest.java"
      ]
    },
    {
      "headline": "Potential command injection in SystemCommandTest",
      "analysis": "The SystemCommandTest class contains several test cases that allow potentially dangerous system commands to be executed. For example, the 'it_allows_innocent_commands' test passes commands like \"ls /etc\" directly to Runtime.exec(). While the test is intended to verify \"innocent\" commands, it demonstrates a pattern that could be exploited for command injection if user input was passed to these methods without proper sanitization.\n",
      "classification": "slightly promising",
      "cwe": "CWE-78",
      "function_names": [
        "it_allows_innocent_commands"
      ],
      "filenames": [
        "src/test/java/io/github/pixee/security/SystemCommandTest.java"
      ]
    },
    {
      "headline": "Unsafe reflection in ReflectionTest",
      "analysis": "The ReflectionTest class contains methods that load classes dynamically using Class.forName(). While some checks are in place, the 'it_loads_normal_classes' test demonstrates loading arbitrary classes specified by a string name. This pattern could potentially be exploited to load and instantiate malicious classes if an attacker can control the class name input.\n",
      "classification": "slightly promising",
      "cwe": "CWE-470",
      "function_names": [
        "it_loads_normal_classes"
      ],
      "filenames": [
        "src/test/java/io/github/pixee/security/ReflectionTest.java"
      ]
    }
  ],
  "scores": [
    {
      "stats": {
        "fn": 1,
        "tp": 0,
        "fp": 3
      },
      "mapping": {},
      "vuln_dates": {
        "CVE-2024-24569": "2024-02-01T19:15:08"
      },
      "scoring_model": "claude-3-5-sonnet-20240620",
      "type": "llm",
      "instruction_template_hash": "245ace12b6361954d0a2"
    }
  ],
  "instruction_template_hash": "10c0163db4740318a544",
  "version": "0.1.0"
}
