{
  "commit": "2db2bcd1a833c1a85258e27e02a5d68e078cd38d",
  "repo_url": "https://github.com/jenkinsci/zephyr-for-jira-test-management-plugin",
  "model": "claude-3-5-sonnet-20240620",
  "chunk_hashes": [
    "15546d6f7035e71a4329"
  ],
  "responses": [
    {
      "content": "```yaml\nleads:\n  - headline: Hardcoded credentials in ZephyrCloudInstance class\n    analysis: |\n      The ZephyrCloudInstance class contains fields for storing sensitive credentials like passwords and API keys as plain text strings. This could lead to exposure of these credentials if the object is serialized or logged. Storing credentials in plain text is a security risk and best practice is to use secure credential storage mechanisms.\n    cwe: CWE-798\n    function_names:\n      - setJiraCloudPassword\n      - setZephyrCloudAccessKey  \n      - setZephyrCloudSecretKey\n    filenames:\n      - src/main/java/com/thed/zephyr/jenkins/model/ZephyrCloudInstance.java\n    classification: very promising\n\n  - headline: Potential SQL injection in Project class\n    analysis: |\n      The getProjectIdByName method in the Project class builds a SQL query by directly concatenating the projectName parameter into the URL string. This could allow SQL injection if the projectName is not properly sanitized. The method should use parameterized queries or proper input validation/escaping to prevent SQL injection attacks.\n    cwe: CWE-89\n    function_names:\n      - getProjectIdByName\n    filenames:\n      - src/main/java/com/thed/zephyr/jenkins/utils/rest/Project.java  \n    classification: very promising\n\n  - headline: Insecure SSL/TLS configuration in RestClient\n    analysis: |\n      The createHttpClient method in RestClient disables SSL certificate validation by using TrustSelfSignedStrategy and ALLOW_ALL_HOSTNAME_VERIFIER. This allows connections to any SSL site, including those with invalid certificates, making the connection vulnerable to man-in-the-middle attacks. Proper SSL certificate validation should be implemented instead.\n    cwe: CWE-295\n    function_names:\n      - createHttpClient\n    filenames:\n      - src/main/java/com/thed/zephyr/jenkins/utils/rest/RestClient.java\n    classification: very promising\n\n  - headline: Hardcoded credentials in main method\n    analysis: |\n      The main method in the Cycle class contains hardcoded credentials for Jira and Zephyr Cloud. This is likely test/debug code, but if accidentally committed and pushed to a repository, it could expose sensitive credentials. Hardcoded credentials should be removed and replaced with a secure credential management system.\n    cwe: CWE-798  \n    function_names:\n      - main\n    filenames:\n      - src/main/java/com/thed/zephyr/jenkins/utils/rest/Cycle.java\n    classification: slightly promising\n\n  - headline: Insecure random number generation\n    analysis: |\n      The generateJWT method uses java.util.Date to generate timestamps, which relies on the system clock and is not cryptographically secure. For security-sensitive token generation, a cryptographically strong random number generator should be used instead.\n    cwe: CWE-338\n    function_names:\n      - generateJWT\n    filenames:\n      - src/main/java/com/thed/zephyr/jenkins/utils/rest/ServerInfo.java\n    classification: slightly promising\n```",
      "date": "2024-07-08T07:21:11.491158",
      "usage": {
        "prompt_tokens": 49555,
        "completion_tokens": 765,
        "cost": 0.16014
      }
    }
  ],
  "leads": [
    {
      "headline": "Hardcoded credentials in ZephyrCloudInstance class",
      "analysis": "The ZephyrCloudInstance class contains fields for storing sensitive credentials like passwords and API keys as plain text strings. This could lead to exposure of these credentials if the object is serialized or logged. Storing credentials in plain text is a security risk and best practice is to use secure credential storage mechanisms.\n",
      "classification": "very promising",
      "cwe": "CWE-798",
      "function_names": [
        "setJiraCloudPassword",
        "setZephyrCloudAccessKey",
        "setZephyrCloudSecretKey"
      ],
      "filenames": [
        "src/main/java/com/thed/zephyr/jenkins/model/ZephyrCloudInstance.java"
      ]
    },
    {
      "headline": "Potential SQL injection in Project class",
      "analysis": "The getProjectIdByName method in the Project class builds a SQL query by directly concatenating the projectName parameter into the URL string. This could allow SQL injection if the projectName is not properly sanitized. The method should use parameterized queries or proper input validation/escaping to prevent SQL injection attacks.\n",
      "classification": "very promising",
      "cwe": "CWE-89",
      "function_names": [
        "getProjectIdByName"
      ],
      "filenames": [
        "src/main/java/com/thed/zephyr/jenkins/utils/rest/Project.java"
      ]
    },
    {
      "headline": "Insecure SSL/TLS configuration in RestClient",
      "analysis": "The createHttpClient method in RestClient disables SSL certificate validation by using TrustSelfSignedStrategy and ALLOW_ALL_HOSTNAME_VERIFIER. This allows connections to any SSL site, including those with invalid certificates, making the connection vulnerable to man-in-the-middle attacks. Proper SSL certificate validation should be implemented instead.\n",
      "classification": "very promising",
      "cwe": "CWE-295",
      "function_names": [
        "createHttpClient"
      ],
      "filenames": [
        "src/main/java/com/thed/zephyr/jenkins/utils/rest/RestClient.java"
      ]
    },
    {
      "headline": "Hardcoded credentials in main method",
      "analysis": "The main method in the Cycle class contains hardcoded credentials for Jira and Zephyr Cloud. This is likely test/debug code, but if accidentally committed and pushed to a repository, it could expose sensitive credentials. Hardcoded credentials should be removed and replaced with a secure credential management system.\n",
      "classification": "slightly promising",
      "cwe": "CWE-798",
      "function_names": [
        "main"
      ],
      "filenames": [
        "src/main/java/com/thed/zephyr/jenkins/utils/rest/Cycle.java"
      ]
    },
    {
      "headline": "Insecure random number generation",
      "analysis": "The generateJWT method uses java.util.Date to generate timestamps, which relies on the system clock and is not cryptographically secure. For security-sensitive token generation, a cryptographically strong random number generator should be used instead.\n",
      "classification": "slightly promising",
      "cwe": "CWE-338",
      "function_names": [
        "generateJWT"
      ],
      "filenames": [
        "src/main/java/com/thed/zephyr/jenkins/utils/rest/ServerInfo.java"
      ]
    }
  ],
  "scores": [
    {
      "stats": {
        "fn": 2,
        "tp": 1,
        "fp": 2
      },
      "mapping": {
        "0": "CVE-2020-2154"
      },
      "vuln_dates": {
        "CVE-2020-2216": "2020-07-02T15:15:18",
        "CVE-2020-2215": "2020-07-02T15:15:18",
        "CVE-2020-2154": "2020-03-09T16:15:14"
      },
      "scoring_model": "claude-3-5-sonnet-20240620",
      "type": "llm",
      "instruction_template_hash": "245ace12b6361954d0a2"
    }
  ],
  "instruction_template_hash": "10c0163db4740318a544",
  "version": "0.1.0"
}
