{
  "commit": "3095cff7d99e99e42183cc3f65d1f2938fbf08f5",
  "repo_url": "https://github.com/jc21/nginx-proxy-manager",
  "model": "gemini/gemini-1.5-pro",
  "chunk_hashes": [
    "3b319fa950e488bd408d"
  ],
  "responses": [
    {
      "content": "```yaml\nleads:\n  - headline: Improper Neutralization of Input During Web Page Generation ('Cross-site Scripting') in src/backend/routes/main.js\n    analysis: |\n      The function that handles every route other than `/login`, in `src/backend/routes/main.js` takes a path from the URL parameters using `req.params.page = req.params['0']`, reads the contents of the file at `dist` + the provided path using `fs.readFile` and then returns the data read from the file without any sanitization in `res.contentType('text/html').end(data)`.\n      This could allow an attacker to inject malicious JavaScript code into the response by crafting a malicious URL that causes the application to read and return the contents of a file containing the attacker's code.\n    cwe: CWE-79\n    function_names:\n      - router.get\n    filenames:\n      - src/backend/routes/main.js\n    classification: very promising\n  - headline: Possible SSRF in src/backend/importer.js\n    analysis: |\n      The `importCertificate` function in `src/backend/importer.js` uses the result of `getCertificateVersion`, which relies on user input (directory names from `/etc/letsencrypt/archive`). The result of `getCertificateVersion` is then used to build a file path used in `fs.symlinkSync('../../archive/npm-' + certificate.id + '/' + name[1], name[0]);`. If the initial input is maliciously crafted, it is possible to get the application to create a symlink to an arbitrary file. Since the application runs as root, this could allow an attacker to read the content of arbitrary files.\n    cwe: CWE-918\n    function_names:\n      - importCertificate\n    filenames:\n      - src/backend/importer.js\n    classification: slightly promising\n  - headline: SQL Injection vulnerability in src/backend/importer.js\n    analysis: |\n      The function that handles import of LetsEncrypt certificates (`importCertificate`) in `src/backend/importer.js` takes a directory name from user input and uses it to update the content of a configuration file via two calls to `utils.exec` without sanitizing the input. \n      An attacker could craft a malicious directory name to execute arbitrary SQL commands via the `sed` command. For example, an attacker might name a directory ` '; DROP TABLE users; -- ` to try and remove the users table. \n    cwe: CWE-89\n    function_names:\n      - importCertificate\n    filenames:\n      - src/backend/importer.js\n    classification: very promising\n  - headline: OS Command Injection vulnerability in src/backend/internal/access-list.js\n    analysis: |\n      The function that builds `.htpasswd` files (`build`) in `src/backend/internal/access-list.js` takes a list of users and passwords from user input and then builds and executes a shell command that is passed to `utils.exec`. The shell command includes user input without any sanitization.\n      An attacker could craft a malicious username or password to inject arbitrary commands into the shell. For example, an attacker could supply a username of `user && rm -rf /` to cause the application to attempt to remove all files on the system. \n    cwe: CWE-78\n    function_names:\n      - build\n    filenames:\n      - src/backend/internal/access-list.js\n    classification: very promising\n  - headline: Hardcoded Credentials in src/backend/setup.js\n    analysis: |\n      The setup process in `src/backend/setup.js` hardcodes an administrator user with email `admin@example.com` and password `changeme`. \n      An attacker that can reach the setup process could potentially take over the application using these credentials.\n    cwe: CWE-798\n    function_names:\n      - module.exports\n    filenames:\n      - src/backend/setup.js\n    classification: very promising\n  - headline: Use of a Broken or Risky Cryptographic Algorithm in src/backend/setup.js and src/backend/models/auth.js\n    analysis: |\n      The user creation in `src/backend/setup.js` and the `Auth` class in `src/backend/models/auth.js` use `bcrypt` to store user passwords. While `bcrypt` is not inherently broken, it is slow to compute, and better alternatives such as `Argon2` exist. This makes the application slightly more vulnerable to brute-force attacks.\n    cwe: CWE-327\n    function_names:\n      - module.exports\n      - Auth.$beforeInsert\n      - Auth.$beforeUpdate\n    filenames:\n      - src/backend/setup.js\n      - src/backend/models/auth.js\n    classification: not promising\n  - headline: Weak Password Requirements in src/backend/models/auth.js\n    analysis: |\n      The `Auth` class in `src/backend/models/auth.js` does not enforce any particular password strength policy. It is therefore possible for users to choose weak, easy-to-guess passwords, making the application more vulnerable to brute-force attacks.\n    cwe: CWE-521\n    function_names:\n      - Auth.$beforeInsert\n      - Auth.$beforeUpdate\n    filenames:\n      - src/backend/models/auth.js\n    classification: not promising\n  - headline: Missing Authentication for Critical Function in src/backend/routes/api/tokens.js\n    analysis: |\n      The GET route for `/tokens` in `src/backend/routes/api/tokens.js` does not require authentication. This route can be used by unauthenticated users to get new access tokens if they can present a valid, unexpired token. An attacker could steal an unexpired token and use it to get a new, long-lived token to access the application. \n    cwe: CWE-306\n    function_names:\n      - router.route\n    filenames:\n      - src/backend/routes/api/tokens.js\n    classification: slightly promising\n  - headline: Missing Authentication for Critical Function in src/backend/internal/certificate.js\n    analysis: |\n      The `validate` function in `src/backend/internal/certificate.js` does not require authentication. An attacker could call this function to test arbitrary certificates and private keys. While this does not allow direct access to the application, it can be used by an attacker to test stolen certificates. \n    cwe: CWE-306\n    function_names:\n      - validate\n    filenames:\n      - src/backend/internal/certificate.js\n    classification: not promising\n  - headline: Possible privilege escalation during setup in src/backend/setup.js\n    analysis: |\n      While the application's setup process, in `src/backend/setup.js` checks for existing users, it does not implement a mechanism to prevent a user from triggering the setup process again. Since the setup process involves writing to configuration files, and since the application runs as root, a user might be able to escalate their privileges by forcing the application to write to an arbitrary file with arbitrary data.  \n    cwe: CWE-269\n    function_names:\n      - module.exports\n    filenames:\n      - src/backend/setup.js\n    classification: slightly promising\n```",
      "date": "2024-06-12T17:28:18.087186",
      "usage": {
        "prompt_tokens": 100765,
        "completion_tokens": 1431,
        "cost": 0.06566125
      }
    }
  ],
  "leads": [
    {
      "headline": "Improper Neutralization of Input During Web Page Generation ('Cross-site Scripting') in src/backend/routes/main.js",
      "analysis": "The function that handles every route other than /login, in src/backend/routes/main.js takes a path from the URL parameters using req.params.page = req.params['0'], reads the contents of the file at dist + the provided path using fs.readFile and then returns the data read from the file without any sanitization in res.contentType('text/html').end(data).\nThis could allow an attacker to inject malicious JavaScript code into the response by crafting a malicious URL that causes the application to read and return the contents of a file containing the attacker's code.\n",
      "classification": "very promising",
      "cwe": "CWE-79",
      "function_names": [
        "router.get"
      ],
      "filenames": [
        "src/backend/routes/main.js"
      ]
    },
    {
      "headline": "Possible SSRF in src/backend/importer.js",
      "analysis": "The importCertificate function in src/backend/importer.js uses the result of getCertificateVersion, which relies on user input (directory names from /etc/letsencrypt/archive). The result of getCertificateVersion is then used to build a file path used in fs.symlinkSync('../../archive/npm-' + certificate.id + '/' + name[1], name[0]);. If the initial input is maliciously crafted, it is possible to get the application to create a symlink to an arbitrary file. Since the application runs as root, this could allow an attacker to read the content of arbitrary files.\n",
      "classification": "slightly promising",
      "cwe": "CWE-918",
      "function_names": [
        "importCertificate"
      ],
      "filenames": [
        "src/backend/importer.js"
      ]
    },
    {
      "headline": "SQL Injection vulnerability in src/backend/importer.js",
      "analysis": "The function that handles import of LetsEncrypt certificates (importCertificate) in src/backend/importer.js takes a directory name from user input and uses it to update the content of a configuration file via two calls to utils.exec without sanitizing the input. \nAn attacker could craft a malicious directory name to execute arbitrary SQL commands via the sed command. For example, an attacker might name a directory  '; DROP TABLE users; --  to try and remove the users table. \n",
      "classification": "very promising",
      "cwe": "CWE-89",
      "function_names": [
        "importCertificate"
      ],
      "filenames": [
        "src/backend/importer.js"
      ]
    },
    {
      "headline": "OS Command Injection vulnerability in src/backend/internal/access-list.js",
      "analysis": "The function that builds .htpasswd files (build) in src/backend/internal/access-list.js takes a list of users and passwords from user input and then builds and executes a shell command that is passed to utils.exec. The shell command includes user input without any sanitization.\nAn attacker could craft a malicious username or password to inject arbitrary commands into the shell. For example, an attacker could supply a username of user && rm -rf / to cause the application to attempt to remove all files on the system. \n",
      "classification": "very promising",
      "cwe": "CWE-78",
      "function_names": [
        "build"
      ],
      "filenames": [
        "src/backend/internal/access-list.js"
      ]
    },
    {
      "headline": "Hardcoded Credentials in src/backend/setup.js",
      "analysis": "The setup process in src/backend/setup.js hardcodes an administrator user with email admin@example.com and password changeme. \nAn attacker that can reach the setup process could potentially take over the application using these credentials.\n",
      "classification": "very promising",
      "cwe": "CWE-798",
      "function_names": [
        "module.exports"
      ],
      "filenames": [
        "src/backend/setup.js"
      ]
    },
    {
      "headline": "Use of a Broken or Risky Cryptographic Algorithm in src/backend/setup.js and src/backend/models/auth.js",
      "analysis": "The user creation in src/backend/setup.js and the Auth class in src/backend/models/auth.js use bcrypt to store user passwords. While bcrypt is not inherently broken, it is slow to compute, and better alternatives such as Argon2 exist. This makes the application slightly more vulnerable to brute-force attacks.\n",
      "classification": "not promising",
      "cwe": "CWE-327",
      "function_names": [
        "module.exports",
        "Auth.$beforeInsert",
        "Auth.$beforeUpdate"
      ],
      "filenames": [
        "src/backend/setup.js",
        "src/backend/models/auth.js"
      ]
    },
    {
      "headline": "Weak Password Requirements in src/backend/models/auth.js",
      "analysis": "The Auth class in src/backend/models/auth.js does not enforce any particular password strength policy. It is therefore possible for users to choose weak, easy-to-guess passwords, making the application more vulnerable to brute-force attacks.\n",
      "classification": "not promising",
      "cwe": "CWE-521",
      "function_names": [
        "Auth.$beforeInsert",
        "Auth.$beforeUpdate"
      ],
      "filenames": [
        "src/backend/models/auth.js"
      ]
    },
    {
      "headline": "Missing Authentication for Critical Function in src/backend/routes/api/tokens.js",
      "analysis": "The GET route for /tokens in src/backend/routes/api/tokens.js does not require authentication. This route can be used by unauthenticated users to get new access tokens if they can present a valid, unexpired token. An attacker could steal an unexpired token and use it to get a new, long-lived token to access the application. \n",
      "classification": "slightly promising",
      "cwe": "CWE-306",
      "function_names": [
        "router.route"
      ],
      "filenames": [
        "src/backend/routes/api/tokens.js"
      ]
    },
    {
      "headline": "Missing Authentication for Critical Function in src/backend/internal/certificate.js",
      "analysis": "The validate function in src/backend/internal/certificate.js does not require authentication. An attacker could call this function to test arbitrary certificates and private keys. While this does not allow direct access to the application, it can be used by an attacker to test stolen certificates. \n",
      "classification": "not promising",
      "cwe": "CWE-306",
      "function_names": [
        "validate"
      ],
      "filenames": [
        "src/backend/internal/certificate.js"
      ]
    },
    {
      "headline": "Possible privilege escalation during setup in src/backend/setup.js",
      "analysis": "While the application's setup process, in src/backend/setup.js checks for existing users, it does not implement a mechanism to prevent a user from triggering the setup process again. Since the setup process involves writing to configuration files, and since the application runs as root, a user might be able to escalate their privileges by forcing the application to write to an arbitrary file with arbitrary data.  \n",
      "classification": "slightly promising",
      "cwe": "CWE-269",
      "function_names": [
        "module.exports"
      ],
      "filenames": [
        "src/backend/setup.js"
      ]
    }
  ],
  "scores": [
    {
      "stats": {
        "fn": 1,
        "tp": 0,
        "fp": 4
      },
      "mapping": {},
      "vuln_dates": {
        "CVE-2019-15517": "2019-08-23T15:15:10"
      },
      "scoring_model": "claude-3-opus-20240229",
      "type": "llm",
      "instruction_template_hash": "245ace12b6361954d0a2"
    },
    {
      "stats": {
        "fn": 1,
        "tp": 0,
        "fp": 4
      },
      "mapping": {},
      "vuln_dates": {
        "CVE-2019-15517": "2019-08-23T15:15:10"
      },
      "scoring_model": "claude-3-5-sonnet-20240620",
      "type": "llm",
      "instruction_template_hash": "245ace12b6361954d0a2"
    }
  ],
  "instruction_template_hash": "10c0163db4740318a544",
  "version": "0.1.0"
}
