{
  "commit": "4820ebf4c74a5d97f727ed995759902075571abc",
  "repo_url": "https://github.com/jberger/galileo",
  "model": "claude-3-haiku-20240307",
  "chunk_hashes": [
    "1db2fbea9896c5872e1b"
  ],
  "responses": [
    {
      "content": "Here is the YAML output for the codebase provided:\n\n```yaml\nleads:\n  - headline: Improper Input Validation\n    analysis: |\n      The codebase contains multiple vulnerabilities related to improper input validation. These vulnerabilities could allow an attacker to execute arbitrary code, access sensitive information, or perform other malicious actions.\n    cwe: CWE-20\n    function_names:\n      - _HashHTMLBlocks\n      - _StripLinkDefinitions\n    filenames:\n      - lib/Galileo.pm\n      - lib/Galileo/Page.pm\n      - lib/Galileo/User.pm\n      - lib/Galileo/Admin.pm\n    classification: very promising\n\n  - headline: Injection\n    analysis: |\n      The codebase contains vulnerabilities related to injection, such as SQL injection, command injection, and XML injection. These vulnerabilities could allow an attacker to execute arbitrary code, access sensitive information, or perform other malicious actions.\n    cwe: CWE-74\n    function_names:\n      - _HashHTMLBlocks\n      - _StripLinkDefinitions\n      - _EncodeAmpsAndAngles\n    filenames:\n      - lib/Galileo.pm\n      - lib/Galileo/Page.pm\n      - lib/Galileo/User.pm\n      - lib/Galileo/Admin.pm\n    classification: very promising\n\n  - headline: Improper Encoding or Escaping of Output\n    analysis: |\n      The codebase contains vulnerabilities related to improper encoding or escaping of output. These vulnerabilities could lead to cross-site scripting (XSS) attacks, where an attacker could inject malicious code into the application's output and have it executed by the user's browser.\n    cwe: CWE-116\n    function_names:\n      - _EncodeAmpsAndAngles\n    filenames:\n      - lib/Galileo.pm\n      - lib/Galileo/Page.pm\n      - lib/Galileo/User.pm\n      - lib/Galileo/Admin.pm\n    classification: very promising\n\n  - headline: Buffer Overflow\n    analysis: |\n      The codebase contains vulnerabilities related to buffer overflows. These vulnerabilities could allow an attacker to execute arbitrary code, access sensitive information, or perform other malicious actions.\n    cwe: CWE-119\n    function_names:\n      - _Detab\n    filenames:\n      - lib/Galileo.pm\n    classification: slightly promising\n\n  - headline: Exposure of Sensitive Information\n    analysis: |\n      The codebase contains vulnerabilities related to the exposure of sensitive information, such as error messages or log files. These vulnerabilities could allow an attacker to gather information about the application's internal workings, which could be used to launch further attacks.\n    cwe: CWE-200\n    function_names:\n      - _HashHTMLBlocks\n    filenames:\n      - lib/Galileo.pm\n      - lib/Galileo/Admin.pm\n    classification: slightly promising\n\n  - headline: Improper Authentication\n    analysis: |\n      The codebase contains vulnerabilities related to improper authentication, such as weak password requirements or use of hard-coded credentials. These vulnerabilities could allow an attacker to gain unauthorized access to the application.\n    cwe: CWE-287\n    function_names:\n      - get_user\n      - is_author\n      - is_admin\n    filenames:\n      - lib/Galileo.pm\n      - lib/Galileo/User.pm\n    classification: slightly promising\n\n  - headline: Cross-Site Request Forgery (CSRF)\n    analysis: |\n      The codebase may be vulnerable to CSRF attacks, which could allow an attacker to perform unauthorized actions on behalf of a legitimate user.\n    cwe: CWE-352\n    function_names: []\n    filenames: []\n    classification: not promising\n\n  - headline: Race Condition\n    analysis: |\n      The codebase may be vulnerable to race conditions, which could allow an attacker to perform unauthorized actions or access sensitive information.\n    cwe: CWE-362\n    function_names:\n      - handleModeChange\n      - handlePaste\n    filenames:\n      - lib/Galileo/User.pm\n    classification: slightly promising\n\n  - headline: Uncontrolled Resource Consumption\n    analysis: |\n      The codebase may be vulnerable to uncontrolled resource consumption, which could lead to denial-of-service attacks or other performance issues.\n    cwe: CWE-400\n    function_names: []\n    filenames: []\n    classification: not promising\n\n  - headline: Improper Resource Shutdown or Release\n    analysis: |\n      The codebase may be vulnerable to improper resource shutdown or release, which could lead to memory leaks or other performance issues.\n    cwe: CWE-404\n    function_names: []\n    filenames: []\n    classification: not promising\n\n  - headline: Interpretation Conflict\n    analysis: |\n      The codebase may be vulnerable to interpretation conflicts, which could allow an attacker to bypass security controls or perform other malicious actions.\n    cwe: CWE-436\n    function_names: []\n    filenames: []\n    classification: not promising\n\n  - headline: Improper Synchronization\n    analysis: |\n      The codebase may be vulnerable to issues with improper synchronization, which could lead to race conditions or other concurrency-related vulnerabilities.\n    cwe: CWE-662\n    function_names:\n      - handleModeChange\n      - handlePaste\n    filenames:\n      - lib/Galileo/User.pm\n    classification: slightly promising\n\n  - headline: Incorrect Resource Transfer Between Spheres\n    analysis: |\n      The codebase may be vulnerable to issues with incorrect resource transfer between spheres, which could lead to unauthorized access or other security problems.\n    cwe: CWE-669\n    function_names: []\n    filenames: []\n    classification: not promising\n\n  - headline: Incorrect Comparison\n    analysis: |\n      The codebase may be vulnerable to issues with incorrect comparison, which could lead to logic errors or other security problems.\n    cwe: CWE-697\n    function_names: []\n    filenames: []\n    classification: not promising\n\n  - headline: Incorrect Type Conversion or Cast\n    analysis: |\n      The codebase may be vulnerable to issues with incorrect type conversion or casting, which could lead to unexpected behavior or security problems.\n    cwe: CWE-704\n    function_names: []\n    filenames: []\n    classification: not promising\n\n  - headline: Incorrect Permission Assignment for Critical Resource\n    analysis: |\n      The codebase may be vulnerable to issues with incorrect permission assignment for critical resources, which could lead to unauthorized access or other security problems.\n    cwe: CWE-732\n    function_names: []\n    filenames: []\n    classification: not promising\n\n  - headline: Improper Check for Unusual or Exceptional Conditions\n    analysis: |\n      The codebase may be vulnerable to issues with improper checking for unusual or exceptional conditions, which could lead to undefined behavior or security problems.\n    cwe: CWE-754\n    function_names: []\n    filenames: []\n    classification: not promising\n\n  - headline: Improper Control of Dynamically-Managed Code Resources\n    analysis: |\n      The codebase may be vulnerable to issues with improper control of dynamically-managed code resources, which could lead to arbitrary code execution or other security problems.\n    cwe: CWE-913\n    function_names: []\n    filenames: []\n    classification: not promising\n\n  - headline: Insecure Storage of Sensitive Information\n    analysis: |\n      The codebase may be vulnerable to issues with insecure storage of sensitive information, which could lead to data breaches or other security problems.\n    cwe: CWE-922\n    function_names: []\n    filenames: []\n    classification: not promising\n```",
      "date": "2024-06-14T13:58:15.853917",
      "usage": {
        "prompt_tokens": 79085,
        "completion_tokens": 1901,
        "cost": 0.0221475
      }
    }
  ],
  "leads": [
    {
      "headline": "Improper Input Validation",
      "analysis": "The codebase contains multiple vulnerabilities related to improper input validation. These vulnerabilities could allow an attacker to execute arbitrary code, access sensitive information, or perform other malicious actions.\n",
      "classification": "very promising",
      "cwe": "CWE-20",
      "function_names": [
        "_HashHTMLBlocks",
        "_StripLinkDefinitions"
      ],
      "filenames": [
        "lib/Galileo.pm",
        "lib/Galileo/Page.pm",
        "lib/Galileo/User.pm"
      ]
    },
    {
      "headline": "Injection",
      "analysis": "The codebase contains vulnerabilities related to injection, such as SQL injection, command injection, and XML injection. These vulnerabilities could allow an attacker to execute arbitrary code, access sensitive information, or perform other malicious actions.\n",
      "classification": "very promising",
      "cwe": "CWE-74",
      "function_names": [
        "_HashHTMLBlocks",
        "_StripLinkDefinitions",
        "_EncodeAmpsAndAngles"
      ],
      "filenames": [
        "lib/Galileo.pm",
        "lib/Galileo/Page.pm",
        "lib/Galileo/User.pm"
      ]
    },
    {
      "headline": "Improper Encoding or Escaping of Output",
      "analysis": "The codebase contains vulnerabilities related to improper encoding or escaping of output. These vulnerabilities could lead to cross-site scripting (XSS) attacks, where an attacker could inject malicious code into the application's output and have it executed by the user's browser.\n",
      "classification": "very promising",
      "cwe": "CWE-116",
      "function_names": [
        "_EncodeAmpsAndAngles"
      ],
      "filenames": [
        "lib/Galileo.pm",
        "lib/Galileo/Page.pm",
        "lib/Galileo/User.pm"
      ]
    },
    {
      "headline": "Buffer Overflow",
      "analysis": "The codebase contains vulnerabilities related to buffer overflows. These vulnerabilities could allow an attacker to execute arbitrary code, access sensitive information, or perform other malicious actions.\n",
      "classification": "slightly promising",
      "cwe": "CWE-119",
      "function_names": [
        "_Detab"
      ],
      "filenames": [
        "lib/Galileo.pm"
      ]
    },
    {
      "headline": "Exposure of Sensitive Information",
      "analysis": "The codebase contains vulnerabilities related to the exposure of sensitive information, such as error messages or log files. These vulnerabilities could allow an attacker to gather information about the application's internal workings, which could be used to launch further attacks.\n",
      "classification": "slightly promising",
      "cwe": "CWE-200",
      "function_names": [
        "_HashHTMLBlocks"
      ],
      "filenames": [
        "lib/Galileo.pm",
        "lib/Galileo/Admin.pm"
      ]
    },
    {
      "headline": "Improper Authentication",
      "analysis": "The codebase contains vulnerabilities related to improper authentication, such as weak password requirements or use of hard-coded credentials. These vulnerabilities could allow an attacker to gain unauthorized access to the application.\n",
      "classification": "slightly promising",
      "cwe": "CWE-287",
      "function_names": [
        "get_user",
        "is_author",
        "is_admin"
      ],
      "filenames": [
        "lib/Galileo.pm",
        "lib/Galileo/User.pm"
      ]
    },
    {
      "headline": "Cross-Site Request Forgery (CSRF)",
      "analysis": "The codebase may be vulnerable to CSRF attacks, which could allow an attacker to perform unauthorized actions on behalf of a legitimate user.\n",
      "classification": "not promising",
      "cwe": "CWE-352",
      "function_names": [],
      "filenames": []
    },
    {
      "headline": "Race Condition",
      "analysis": "The codebase may be vulnerable to race conditions, which could allow an attacker to perform unauthorized actions or access sensitive information.\n",
      "classification": "slightly promising",
      "cwe": "CWE-362",
      "function_names": [
        "handleModeChange",
        "handlePaste"
      ],
      "filenames": [
        "lib/Galileo/User.pm"
      ]
    },
    {
      "headline": "Uncontrolled Resource Consumption",
      "analysis": "The codebase may be vulnerable to uncontrolled resource consumption, which could lead to denial-of-service attacks or other performance issues.\n",
      "classification": "not promising",
      "cwe": "CWE-400",
      "function_names": [],
      "filenames": []
    },
    {
      "headline": "Improper Resource Shutdown or Release",
      "analysis": "The codebase may be vulnerable to improper resource shutdown or release, which could lead to memory leaks or other performance issues.\n",
      "classification": "not promising",
      "cwe": "CWE-404",
      "function_names": [],
      "filenames": []
    },
    {
      "headline": "Interpretation Conflict",
      "analysis": "The codebase may be vulnerable to interpretation conflicts, which could allow an attacker to bypass security controls or perform other malicious actions.\n",
      "classification": "not promising",
      "cwe": "CWE-436",
      "function_names": [],
      "filenames": []
    },
    {
      "headline": "Improper Synchronization",
      "analysis": "The codebase may be vulnerable to issues with improper synchronization, which could lead to race conditions or other concurrency-related vulnerabilities.\n",
      "classification": "slightly promising",
      "cwe": "CWE-662",
      "function_names": [
        "handleModeChange",
        "handlePaste"
      ],
      "filenames": [
        "lib/Galileo/User.pm"
      ]
    },
    {
      "headline": "Incorrect Resource Transfer Between Spheres",
      "analysis": "The codebase may be vulnerable to issues with incorrect resource transfer between spheres, which could lead to unauthorized access or other security problems.\n",
      "classification": "not promising",
      "cwe": "CWE-669",
      "function_names": [],
      "filenames": []
    },
    {
      "headline": "Incorrect Comparison",
      "analysis": "The codebase may be vulnerable to issues with incorrect comparison, which could lead to logic errors or other security problems.\n",
      "classification": "not promising",
      "cwe": "CWE-697",
      "function_names": [],
      "filenames": []
    },
    {
      "headline": "Incorrect Type Conversion or Cast",
      "analysis": "The codebase may be vulnerable to issues with incorrect type conversion or casting, which could lead to unexpected behavior or security problems.\n",
      "classification": "not promising",
      "cwe": "CWE-704",
      "function_names": [],
      "filenames": []
    },
    {
      "headline": "Incorrect Permission Assignment for Critical Resource",
      "analysis": "The codebase may be vulnerable to issues with incorrect permission assignment for critical resources, which could lead to unauthorized access or other security problems.\n",
      "classification": "not promising",
      "cwe": "CWE-732",
      "function_names": [],
      "filenames": []
    },
    {
      "headline": "Improper Check for Unusual or Exceptional Conditions",
      "analysis": "The codebase may be vulnerable to issues with improper checking for unusual or exceptional conditions, which could lead to undefined behavior or security problems.\n",
      "classification": "not promising",
      "cwe": "CWE-754",
      "function_names": [],
      "filenames": []
    },
    {
      "headline": "Improper Control of Dynamically-Managed Code Resources",
      "analysis": "The codebase may be vulnerable to issues with improper control of dynamically-managed code resources, which could lead to arbitrary code execution or other security problems.\n",
      "classification": "not promising",
      "cwe": "CWE-913",
      "function_names": [],
      "filenames": []
    },
    {
      "headline": "Insecure Storage of Sensitive Information",
      "analysis": "The codebase may be vulnerable to issues with insecure storage of sensitive information, which could lead to data breaches or other security problems.\n",
      "classification": "not promising",
      "cwe": "CWE-922",
      "function_names": [],
      "filenames": []
    }
  ],
  "scores": [
    {
      "stats": {
        "fn": 1,
        "tp": 0,
        "fp": 3
      },
      "mapping": {},
      "vuln_dates": {
        "CVE-2019-7410": "2020-08-14T14:15:12"
      },
      "scoring_model": "claude-3-opus-20240229",
      "type": "llm",
      "instruction_template_hash": "245ace12b6361954d0a2"
    },
    {
      "stats": {
        "fn": 1,
        "tp": 0,
        "fp": 3
      },
      "mapping": {},
      "vuln_dates": {
        "CVE-2019-7410": "2020-08-14T14:15:12"
      },
      "scoring_model": "claude-3-5-sonnet-20240620",
      "type": "llm",
      "instruction_template_hash": "245ace12b6361954d0a2"
    }
  ],
  "instruction_template_hash": "10c0163db4740318a544",
  "version": "0.1.0"
}
