{
  "commit": "1dfe072dfb0f23d2feaa1d00d89f7455020788ff",
  "repo_url": "https://github.com/jenkinsci/pangolin-testrail-connector-plugin",
  "model": "gpt-4o-2024-05-13",
  "chunk_hashes": [
    "ade31e89abb696cbe263"
  ],
  "responses": [
    {
      "content": "```yaml\nleads:\n  - headline: \"Hardcoded TestRail password in code\"\n    analysis: |\n      The TestRail password is hardcoded in the code, which is a security risk as it exposes sensitive information. Specifically, the TestRail password is stored in plain text in multiple test cases. An attacker who gains access to the source code can easily retrieve the password and potentially access the associated TestRail account.\n    cwe: CWE-798\n    function_names: \n      - \"testCreateWithTestRailPasswordFromConfiguration\"\n      - \"testCreateWithTestRailPasswordFromGlobalConfig\"\n      - \"testCreateWithEmptyTestRailPassword\"\n    filenames:\n      - \"src/test/java/com/agiletestware/pangolin/BulkUpdateParametersFactoryTest.java\"\n    classification: very promising\n  \n  - headline: \"Hardcoded TestRail user in code\"\n    analysis: |\n      The TestRail username is hardcoded in the code, which exposes sensitive information. If an attacker gains access to the source code, they can retrieve the username and leverage it in combination with other vulnerabilities (e.g., a leaked password) to access the affected TestRail account.\n    cwe: CWE-798\n    function_names:\n      - \"testCreateWithTestRailUserNameFromConfiguration\"\n      - \"testCreateWithTestRailPasswordFromGlobalConfig\"\n      - \"testCreateWithEmptyTestRailPassword\"\n    filenames:\n      - \"src/test/java/com/agiletestware/pangolin/BulkUpdateParametersFactoryTest.java\"\n    classification: very promising\n\n  - headline: \"Hardcoded Pangolin URL in code\"\n    analysis: |\n      The Pangolin URL is hardcoded in the code, which can limit flexibility. If the Pangolin server address changes, every instance where the URL is hardcoded needs to be updated. This is mostly a maintainability issue, but can also lead to potential security risks if old addresses are used inadvertently.\n    cwe: CWE-611\n    function_names:\n      - \"createGlobalConfigMock\"\n      - \"doSaveConnectionPassTest\"\n    filenames: \n      - \"src/test/java/com/agiletestware/pangolin/BulkUpdateParametersFactoryTest.java\"\n      - \"src/test/java/com/agiletestware/pangolin/GlobalConfigTest.java\"\n    classification: slightly promising\n\n  - headline: \"Insufficient validation of URLs\"\n    analysis: |\n      The code lacks comprehensive validation for URLs, including the TestRail and Pangolin URLs. Without proper validation, it is easier for attackers to exploit these endpoints for various injection attacks or to redirect the application to malicious servers.\n    cwe: CWE-20\n    function_names:\n      - \"doCheckPangolinURL\"\n      - \"doCheckTestRailURL\"\n    filenames: \n      - \"src/main/java/com/agiletestware/pangolin/GlobalConfig.java\"\n    classification: very promising\n\n  - headline: \"Potential logging of sensitive information\"\n    analysis: |\n      The code may log sensitive information, including encrypted error messages or potentially even credentials. Logs can be a source of sensitive data leaks if not handled properly, especially in cases of exceptions.\n    cwe: CWE-532\n    function_names:\n      - \"perform\"\n      - \"doUpdate\"\n    filenames:\n      - \"src/main/java/com/agiletestware/pangolin/PangolinPublisher.java\"\n    classification: slightly promising\n```",
      "date": "2024-06-12T18:58:52.135078",
      "usage": {
        "prompt_tokens": 29933,
        "completion_tokens": 701,
        "cost": 0.16018
      }
    }
  ],
  "leads": [
    {
      "headline": "Hardcoded TestRail password in code",
      "analysis": "The TestRail password is hardcoded in the code, which is a security risk as it exposes sensitive information. Specifically, the TestRail password is stored in plain text in multiple test cases. An attacker who gains access to the source code can easily retrieve the password and potentially access the associated TestRail account.\n",
      "classification": "very promising",
      "cwe": "CWE-798",
      "function_names": [
        "testCreateWithTestRailPasswordFromConfiguration",
        "testCreateWithTestRailPasswordFromGlobalConfig",
        "testCreateWithEmptyTestRailPassword"
      ],
      "filenames": [
        "src/test/java/com/agiletestware/pangolin/BulkUpdateParametersFactoryTest.java"
      ]
    },
    {
      "headline": "Hardcoded TestRail user in code",
      "analysis": "The TestRail username is hardcoded in the code, which exposes sensitive information. If an attacker gains access to the source code, they can retrieve the username and leverage it in combination with other vulnerabilities (e.g., a leaked password) to access the affected TestRail account.\n",
      "classification": "very promising",
      "cwe": "CWE-798",
      "function_names": [
        "testCreateWithTestRailUserNameFromConfiguration",
        "testCreateWithTestRailPasswordFromGlobalConfig",
        "testCreateWithEmptyTestRailPassword"
      ],
      "filenames": [
        "src/test/java/com/agiletestware/pangolin/BulkUpdateParametersFactoryTest.java"
      ]
    },
    {
      "headline": "Hardcoded Pangolin URL in code",
      "analysis": "The Pangolin URL is hardcoded in the code, which can limit flexibility. If the Pangolin server address changes, every instance where the URL is hardcoded needs to be updated. This is mostly a maintainability issue, but can also lead to potential security risks if old addresses are used inadvertently.\n",
      "classification": "slightly promising",
      "cwe": "CWE-611",
      "function_names": [
        "createGlobalConfigMock",
        "doSaveConnectionPassTest"
      ],
      "filenames": [
        "src/test/java/com/agiletestware/pangolin/BulkUpdateParametersFactoryTest.java",
        "src/test/java/com/agiletestware/pangolin/GlobalConfigTest.java"
      ]
    },
    {
      "headline": "Insufficient validation of URLs",
      "analysis": "The code lacks comprehensive validation for URLs, including the TestRail and Pangolin URLs. Without proper validation, it is easier for attackers to exploit these endpoints for various injection attacks or to redirect the application to malicious servers.\n",
      "classification": "very promising",
      "cwe": "CWE-20",
      "function_names": [
        "doCheckPangolinURL",
        "doCheckTestRailURL"
      ],
      "filenames": [
        "src/main/java/com/agiletestware/pangolin/GlobalConfig.java"
      ]
    },
    {
      "headline": "Potential logging of sensitive information",
      "analysis": "The code may log sensitive information, including encrypted error messages or potentially even credentials. Logs can be a source of sensitive data leaks if not handled properly, especially in cases of exceptions.\n",
      "classification": "slightly promising",
      "cwe": "CWE-532",
      "function_names": [
        "perform",
        "doUpdate"
      ],
      "filenames": [
        "src/main/java/com/agiletestware/pangolin/PangolinPublisher.java"
      ]
    }
  ],
  "scores": [
    {
      "stats": {
        "fn": 1,
        "tp": 0,
        "fp": 3
      },
      "mapping": {},
      "vuln_dates": {
        "CVE-2018-1999032": "2018-08-01T13:29:00"
      },
      "scoring_model": "claude-3-opus-20240229",
      "type": "llm",
      "instruction_template_hash": "245ace12b6361954d0a2"
    },
    {
      "stats": {
        "fn": 0,
        "tp": 1,
        "fp": 2
      },
      "mapping": {
        "2": "CVE-2018-1999032"
      },
      "vuln_dates": {
        "CVE-2018-1999032": "2018-08-01T13:29:00"
      },
      "scoring_model": "claude-3-5-sonnet-20240620",
      "type": "llm",
      "instruction_template_hash": "245ace12b6361954d0a2"
    }
  ],
  "instruction_template_hash": "10c0163db4740318a544",
  "version": "0.1.0"
}
