{
  "commit": "2abfaedae070e3c81a8b17bffd7180362da8fe7c",
  "repo_url": "https://github.com/rancher/rancher",
  "model": "claude-3-opus-20240229",
  "chunk_hashes": [
    "19fd9e68bb30253670d4"
  ],
  "responses": [
    {
      "content": "Here is the YAML output identifying potential security vulnerabilities in the provided codebase:\n\n```yaml\nleads:\n  - headline: Arbitrary command execution through environment variable\n    analysis: |\n      In agent/run.sh, various environment variables like $http_proxy, $NO_PROXY, $CATTLE_ACCESS_KEY, etc. are passed as-is to the docker run command that launches the rancher-agent container. \n      Attacker-controlled values in these environment variables could allow arbitrary command execution when starting the agent container.\n    cwe: CWE-78\n    function_names:\n      - run\n    filenames:\n      - agent/run.sh\n    classification: very promising\n\n  - headline: Docker socket exposed to agent container  \n    analysis: |\n      The host's /var/run/docker.sock Unix socket is bind mounted into the rancher-agent container when running agent/run.sh.\n      This effectively allows the agent container to control the host's Docker daemon and execute arbitrary Docker commands on the host with root privileges.\n    cwe: CWE-284\n    function_names:\n      - launch_agent\n    filenames:\n      - agent/run.sh\n    classification: very promising\n\n  - headline: Arbitrary file write through LOG_DIR variable\n    analysis: |\n      The LOG_DIR variable in server/artifacts/cattle.sh is user controlled and used in the java command line to set the heap dump path. \n      By setting this to an arbitrary path, an attacker could overwrite sensitive files when the JVM crashes and dumps heap memory.\n    cwe: CWE-73\n    function_names:\n      - run  \n    filenames:\n      - server/artifacts/cattle.sh\n    classification: slightly promising\n\n  - headline: Credential disclosure through environment variables\n    analysis: |  \n      Sensitive credentials like CATTLE_ACCESS_KEY, CATTLE_SECRET_KEY, CATTLE_DB_CATTLE_PASSWORD are passed to containers through environment variables in agent/run.sh and server/artifacts/cattle.sh.\n      If an attacker can access the environment of these containers, they could obtain these credentials which may allow further system access.\n    cwe: CWE-522\n    function_names:\n      - launch_agent\n      - setup_mysql\n      - setup_graphite \n    filenames:\n      - agent/run.sh\n      - server/artifacts/cattle.sh\n    classification: slightly promising\n\n  - headline: Arbitrary URL fetch and execute  \n    analysis: |\n      The master() function in server/artifacts/cattle.sh fetches a properties file from a URL and pipes it to /usr/bin via the cattle-binary-pull command.\n      An attacker who can change the cattle-global.properties URL in this function could execute arbitrary code on the server by making it fetch and run a malicious script.\n    cwe: CWE-829\n    function_names:\n      - master\n    filenames:  \n      - server/artifacts/cattle.sh\n    classification: very promising\n  \n  - headline: Image tag poisoning\n    analysis: |\n      Several bash scripts like scripts/update-version.sh and agent-base/build-image.sh allow overriding the image repo/tag via environment variables.\n      If an attacker can control these variables, they could point the tag to an arbitrary malicious image which would get deployed on servers and agents.\n    cwe: CWE-494\n    function_names: []\n    filenames:\n      - scripts/update-version.sh  \n      - agent-base/build-image.sh\n    classification: slightly promising\n```",
      "date": "2024-06-13T11:19:02.339642",
      "usage": {
        "prompt_tokens": 14612,
        "completion_tokens": 829,
        "cost": 0.281355
      }
    }
  ],
  "leads": [
    {
      "headline": "Arbitrary command execution through environment variable",
      "analysis": "In agent/run.sh, various environment variables like $http_proxy, $NO_PROXY, $CATTLE_ACCESS_KEY, etc. are passed as-is to the docker run command that launches the rancher-agent container. \nAttacker-controlled values in these environment variables could allow arbitrary command execution when starting the agent container.\n",
      "classification": "very promising",
      "cwe": "CWE-78",
      "function_names": [
        "run"
      ],
      "filenames": [
        "agent/run.sh"
      ]
    },
    {
      "headline": "Docker socket exposed to agent container",
      "analysis": "The host's /var/run/docker.sock Unix socket is bind mounted into the rancher-agent container when running agent/run.sh.\nThis effectively allows the agent container to control the host's Docker daemon and execute arbitrary Docker commands on the host with root privileges.\n",
      "classification": "very promising",
      "cwe": "CWE-284",
      "function_names": [
        "launch_agent"
      ],
      "filenames": [
        "agent/run.sh"
      ]
    },
    {
      "headline": "Arbitrary file write through LOG_DIR variable",
      "analysis": "The LOG_DIR variable in server/artifacts/cattle.sh is user controlled and used in the java command line to set the heap dump path. \nBy setting this to an arbitrary path, an attacker could overwrite sensitive files when the JVM crashes and dumps heap memory.\n",
      "classification": "slightly promising",
      "cwe": "CWE-73",
      "function_names": [
        "run"
      ],
      "filenames": [
        "server/artifacts/cattle.sh"
      ]
    },
    {
      "headline": "Credential disclosure through environment variables",
      "analysis": "Sensitive credentials like CATTLE_ACCESS_KEY, CATTLE_SECRET_KEY, CATTLE_DB_CATTLE_PASSWORD are passed to containers through environment variables in agent/run.sh and server/artifacts/cattle.sh.\nIf an attacker can access the environment of these containers, they could obtain these credentials which may allow further system access.\n",
      "classification": "slightly promising",
      "cwe": "CWE-522",
      "function_names": [
        "launch_agent",
        "setup_mysql",
        "setup_graphite"
      ],
      "filenames": [
        "agent/run.sh",
        "server/artifacts/cattle.sh"
      ]
    },
    {
      "headline": "Arbitrary URL fetch and execute",
      "analysis": "The master() function in server/artifacts/cattle.sh fetches a properties file from a URL and pipes it to /usr/bin via the cattle-binary-pull command.\nAn attacker who can change the cattle-global.properties URL in this function could execute arbitrary code on the server by making it fetch and run a malicious script.\n",
      "classification": "very promising",
      "cwe": "CWE-829",
      "function_names": [
        "master"
      ],
      "filenames": [
        "server/artifacts/cattle.sh"
      ]
    },
    {
      "headline": "Image tag poisoning",
      "analysis": "Several bash scripts like scripts/update-version.sh and agent-base/build-image.sh allow overriding the image repo/tag via environment variables.\nIf an attacker can control these variables, they could point the tag to an arbitrary malicious image which would get deployed on servers and agents.\n",
      "classification": "slightly promising",
      "cwe": "CWE-494",
      "function_names": [],
      "filenames": [
        "scripts/update-version.sh",
        "agent-base/build-image.sh"
      ]
    }
  ],
  "scores": [
    {
      "stats": {
        "fn": 1,
        "tp": 0,
        "fp": 3
      },
      "mapping": {},
      "vuln_dates": {
        "CVE-2017-7297": "2017-03-29T00:59:00"
      },
      "scoring_model": "claude-3-opus-20240229",
      "type": "llm",
      "instruction_template_hash": "245ace12b6361954d0a2"
    }
  ],
  "instruction_template_hash": "10c0163db4740318a544",
  "version": "0.1.0"
}
