{
  "commit": "1fe15cd707fa05bd558d6bb5b6c489d483179ace",
  "repo_url": "https://github.com/trustedsec/trevorc2",
  "model": "claude-3-opus-20240229",
  "chunk_hashes": [
    "0ab784f42c75eada2d72"
  ],
  "responses": [
    {
      "content": "Here are the potential security vulnerabilities I identified in the provided codebase:\n\n```yaml\nleads:\n  - headline: Insecure deserialization\n    analysis: |\n      The trevorc2_client.java code uses Java's deserialization methods like readObject() to deserialize data received from the server. Deserialization of untrusted data can allow an attacker to execute arbitrary code or conduct other attacks if the deserialization process is not properly secured. An attacker could potentially send a malicious serialized object to execute code on the client.\n    cwe: CWE-502\n    function_names: \n      - main\n    filenames:\n      - trevorc2_client.java\n    classification: very promising\n    \n  - headline: Use of insecure cryptographic algorithms\n    analysis: |\n      The codebase uses AES in CBC mode with a static IV. Using a static IV is insecure and makes the encryption deterministic and susceptible to dictionary attacks. Additionally, SHA-256 is used to hash the encryption key which is not ideal. A standard key derivation function like PBKDF2 should be used instead.\n    cwe: CWE-327\n    function_names:\n      - encrypt\n      - decrypt\n    filenames:\n      - trevorc2_client.py\n      - trevorc2_server.py  \n      - trevorc2_client.java\n    classification: very promising\n\n  - headline: Potential command injection\n    analysis: |\n      The Python client code uses subprocess.Popen() to execute commands received from the C2 server. If the input is not properly sanitized, an attacker could potentially inject arbitrary commands to be executed on the client machine. Thorough input validation should be implemented.\n    cwe: CWE-78\n    function_names:\n      - main\n    filenames:\n      - trevorc2_client.py\n    classification: slightly promising\n\n  - headline: Sensitive data exposure \n    analysis: |\n      Sensitive data like executed commands and results are stored on the server's file system without proper protection. An attacker who gains access to the server could retrieve this sensitive data. Sensitive data should be properly encrypted both in transit and at rest.\n    cwe: CWE-200\n    function_names:\n      - SPQ.get \n    filenames:\n      - trevorc2_server.py\n    classification: slightly promising\n\n  - headline: Unvalidated redirects and forwards\n    analysis: | \n      The server clones a provided website URL without validating the URL. An attacker could supply a malicious URL that redirects users to a site that steals credentials or installs malware. The provided URL should be properly validated before being used.\n    cwe: CWE-601 \n    function_names:\n      - clone_site\n    filenames:\n      - trevorc2_server.py\n    classification: not promising\n\n```\n\nThe most concerning vulnerabilities are insecure deserialization which can allow remote code execution, use of insecure crypto with static IVs, and potential for command injection on the client. Sensitive data exposure and unvalidated redirects are lower severity but should also be addressed to harden the security of the application.",
      "date": "2024-06-13T17:19:29.774962",
      "usage": {
        "prompt_tokens": 14643,
        "completion_tokens": 745,
        "cost": 0.27552
      }
    }
  ],
  "leads": [
    {
      "headline": "Insecure deserialization",
      "analysis": "The trevorc2_client.java code uses Java's deserialization methods like readObject() to deserialize data received from the server. Deserialization of untrusted data can allow an attacker to execute arbitrary code or conduct other attacks if the deserialization process is not properly secured. An attacker could potentially send a malicious serialized object to execute code on the client.\n",
      "classification": "very promising",
      "cwe": "CWE-502",
      "function_names": [
        "main"
      ],
      "filenames": [
        "trevorc2_client.java"
      ]
    },
    {
      "headline": "Use of insecure cryptographic algorithms",
      "analysis": "The codebase uses AES in CBC mode with a static IV. Using a static IV is insecure and makes the encryption deterministic and susceptible to dictionary attacks. Additionally, SHA-256 is used to hash the encryption key which is not ideal. A standard key derivation function like PBKDF2 should be used instead.\n",
      "classification": "very promising",
      "cwe": "CWE-327",
      "function_names": [
        "encrypt",
        "decrypt"
      ],
      "filenames": [
        "trevorc2_client.py",
        "trevorc2_server.py",
        "trevorc2_client.java"
      ]
    },
    {
      "headline": "Potential command injection",
      "analysis": "The Python client code uses subprocess.Popen() to execute commands received from the C2 server. If the input is not properly sanitized, an attacker could potentially inject arbitrary commands to be executed on the client machine. Thorough input validation should be implemented.\n",
      "classification": "slightly promising",
      "cwe": "CWE-78",
      "function_names": [
        "main"
      ],
      "filenames": [
        "trevorc2_client.py"
      ]
    },
    {
      "headline": "Sensitive data exposure",
      "analysis": "Sensitive data like executed commands and results are stored on the server's file system without proper protection. An attacker who gains access to the server could retrieve this sensitive data. Sensitive data should be properly encrypted both in transit and at rest.\n",
      "classification": "slightly promising",
      "cwe": "CWE-200",
      "function_names": [
        "SPQ.get"
      ],
      "filenames": [
        "trevorc2_server.py"
      ]
    },
    {
      "headline": "Unvalidated redirects and forwards",
      "analysis": "The server clones a provided website URL without validating the URL. An attacker could supply a malicious URL that redirects users to a site that steals credentials or installs malware. The provided URL should be properly validated before being used.\n",
      "classification": "not promising",
      "cwe": "CWE-601",
      "function_names": [
        "clone_site"
      ],
      "filenames": [
        "trevorc2_server.py"
      ]
    }
  ],
  "scores": [
    {
      "stats": {
        "fn": 1,
        "tp": 0,
        "fp": 2
      },
      "mapping": {},
      "vuln_dates": {
        "CVE-2019-18850": "2019-12-04T13:15:10"
      },
      "scoring_model": "claude-3-opus-20240229",
      "type": "llm",
      "instruction_template_hash": "245ace12b6361954d0a2"
    },
    {
      "stats": {
        "fn": 1,
        "tp": 0,
        "fp": 2
      },
      "mapping": {},
      "vuln_dates": {
        "CVE-2019-18850": "2019-12-04T13:15:10"
      },
      "scoring_model": "claude-3-5-sonnet-20240620",
      "type": "llm",
      "instruction_template_hash": "245ace12b6361954d0a2"
    }
  ],
  "instruction_template_hash": "10c0163db4740318a544",
  "version": "0.1.0"
}
