{
  "commit": "08109dcdd686b48365912046e796bc993479808f",
  "repo_url": "https://github.com/node-swig/swig-templates",
  "model": "gpt-4o-2024-05-13",
  "chunk_hashes": [
    "ef3da246ab4c9b44796f"
  ],
  "responses": [
    {
      "content": "```yaml\nleads:\n  - headline: \"Potential Command Injection in swig.compileFile\"\n    analysis: |\n      The `compileFile` function loads a template file using an external method but does not sanitize the filename string. This opens the possibility of command injection if an attacker can control the filename. This vulnerability allows arbitrary command execution on the server where the application is running.\n    cwe: CWE-78\n    function_names:\n      - compileFile\n    filenames:\n      - lib/swig.js\n    classification: very promising\n\n  - headline: \"Potential Improper Neutralization of Input During Web Page Generation\"\n    analysis: |\n      Functions such as `compile` and `render` process user input directly for rendering templates. If these inputs are not properly sanitized or escaped, they are at risk of Cross-site Scripting (XSS) where an attacker injects malicious scripts to be executed in the context of another user.\n    cwe: CWE-79\n    function_names:\n      - compile\n      - render\n    filenames:\n      - lib/swig.js\n      - bin/swig.js\n    classification: very promising\n\n  - headline: \"Exposure of Sensitive Information During Compilation and Caching\"\n    analysis: |\n      During file compilation and caching in `swig.compileFile` and `swig.precompile`, detailed errors and stack traces can be potentially exposed to users, revealing sensitive information about the server environment, filesystem structure, and application code.\n    cwe: CWE-209\n    function_names:\n      - compileFile\n      - precompile\n    filenames:\n      - lib/swig.js\n    classification: slightly promising\n\n  - headline: \"Possible Race Condition in Cache Invalidation\"\n    analysis: |\n      The `invalidateCache` function clears the in-memory template cache, but this might not be thread-safe. Concurrent attempts to access and clear the cache may lead to race conditions, causing inconsistent reads or writes within the cache mechanism.\n    cwe: CWE-362\n    function_names:\n      - invalidateCache\n    filenames:\n      - lib/swig.js\n    classification: slightly promising\n\n  - headline: \"Insecure Usage of JavaScript's `eval` in swig CLI Tool\"\n    analysis: |\n      In `swig.js` CLI tool's run command, the `eval` function is used to execute compiled template functions. This is inherently dangerous as it executes code in the scope of the caller, which may lead to arbitrary code execution if an attacker can influence the inputs to `eval`.\n    cwe: CWE-94\n    function_names:\n      - eval\n    filenames:\n      - bin/swig.js\n    classification: very promising\n\n  - headline: \"Parallel Execution Might Cause Unintended Behavior in Loader's Synchronous Code\"\n    analysis: |\n      The file system loader in `lib/loaders/filesystem.js` synchronously loads files. In highly concurrent environments, such synchronous operations can block the event loop, leading to performance degradation or denial of service.\n    cwe: CWE-770\n    function_names:\n      - load\n    filenames:\n      - lib/loaders/filesystem.js\n    classification: slightly promising\n\n  - headline: \"Hardcoded Template Directory Path\"\n    analysis: |\n      The path resolution in the memory loader leverages hardcoded paths for resolving template paths. If the base path or template identifiers include user input without proper validation, it might lead to security issues such as path traversal attacks.\n    cwe: CWE-22\n    function_names:\n      - resolve\n    filenames:\n      - lib/loaders/memory.js\n    classification: very promising\n```",
      "date": "2024-06-13T10:33:35.406884",
      "usage": {
        "prompt_tokens": 70613,
        "completion_tokens": 743,
        "cost": 0.36421
      }
    }
  ],
  "leads": [
    {
      "headline": "Potential Command Injection in swig.compileFile",
      "analysis": "The compileFile function loads a template file using an external method but does not sanitize the filename string. This opens the possibility of command injection if an attacker can control the filename. This vulnerability allows arbitrary command execution on the server where the application is running.\n",
      "classification": "very promising",
      "cwe": "CWE-78",
      "function_names": [
        "compileFile"
      ],
      "filenames": [
        "lib/swig.js"
      ]
    },
    {
      "headline": "Potential Improper Neutralization of Input During Web Page Generation",
      "analysis": "Functions such as compile and render process user input directly for rendering templates. If these inputs are not properly sanitized or escaped, they are at risk of Cross-site Scripting (XSS) where an attacker injects malicious scripts to be executed in the context of another user.\n",
      "classification": "very promising",
      "cwe": "CWE-79",
      "function_names": [
        "compile",
        "render"
      ],
      "filenames": [
        "lib/swig.js",
        "bin/swig.js"
      ]
    },
    {
      "headline": "Exposure of Sensitive Information During Compilation and Caching",
      "analysis": "During file compilation and caching in swig.compileFile and swig.precompile, detailed errors and stack traces can be potentially exposed to users, revealing sensitive information about the server environment, filesystem structure, and application code.\n",
      "classification": "slightly promising",
      "cwe": "CWE-209",
      "function_names": [
        "compileFile",
        "precompile"
      ],
      "filenames": [
        "lib/swig.js"
      ]
    },
    {
      "headline": "Possible Race Condition in Cache Invalidation",
      "analysis": "The invalidateCache function clears the in-memory template cache, but this might not be thread-safe. Concurrent attempts to access and clear the cache may lead to race conditions, causing inconsistent reads or writes within the cache mechanism.\n",
      "classification": "slightly promising",
      "cwe": "CWE-362",
      "function_names": [
        "invalidateCache"
      ],
      "filenames": [
        "lib/swig.js"
      ]
    },
    {
      "headline": "Insecure Usage of JavaScript's eval in swig CLI Tool",
      "analysis": "In swig.js CLI tool's run command, the eval function is used to execute compiled template functions. This is inherently dangerous as it executes code in the scope of the caller, which may lead to arbitrary code execution if an attacker can influence the inputs to eval.\n",
      "classification": "very promising",
      "cwe": "CWE-94",
      "function_names": [
        "eval"
      ],
      "filenames": [
        "bin/swig.js"
      ]
    },
    {
      "headline": "Parallel Execution Might Cause Unintended Behavior in Loader's Synchronous Code",
      "analysis": "The file system loader in lib/loaders/filesystem.js synchronously loads files. In highly concurrent environments, such synchronous operations can block the event loop, leading to performance degradation or denial of service.\n",
      "classification": "slightly promising",
      "cwe": "CWE-770",
      "function_names": [
        "load"
      ],
      "filenames": [
        "lib/loaders/filesystem.js"
      ]
    },
    {
      "headline": "Hardcoded Template Directory Path",
      "analysis": "The path resolution in the memory loader leverages hardcoded paths for resolving template paths. If the base path or template identifiers include user input without proper validation, it might lead to security issues such as path traversal attacks.\n",
      "classification": "very promising",
      "cwe": "CWE-22",
      "function_names": [
        "resolve"
      ],
      "filenames": [
        "lib/loaders/memory.js"
      ]
    }
  ],
  "scores": [
    {
      "stats": {
        "fn": 1,
        "tp": 1,
        "fp": 3
      },
      "mapping": {
        "2": "CVE-2023-25344"
      },
      "vuln_dates": {
        "CVE-2023-25345": "2023-03-15T20:15:10",
        "CVE-2023-25344": "2023-03-15T20:15:10"
      },
      "scoring_model": "claude-3-opus-20240229",
      "type": "llm",
      "instruction_template_hash": "245ace12b6361954d0a2"
    }
  ],
  "instruction_template_hash": "10c0163db4740318a544",
  "version": "0.1.0"
}
