{
  "commit": "3ddead1584c9e9055b0f04850bf93cff4d7a60f2",
  "repo_url": "https://github.com/alexcrichton/bzip2-rs",
  "model": "claude-3-opus-20240229",
  "chunk_hashes": [
    "f4dca8b59ab22e85a46f"
  ],
  "responses": [
    {
      "content": "Here is the YAML output analyzing the bzip2 codebase for vulnerabilities:\n\n```yaml\nleads:\n  - headline: Potential integer overflow in BZ2_decompress\n    analysis: |\n      The BZ2_decompress function in decompress.c does not check for potential integer overflow when calculating the number of bytes to read. The GET_BITS macro reads a specified number of bits (nnn) from the input stream into an Int32 variable (vvv). \n      \n      If a large value is passed for nnn that causes vvv to overflow, it could lead to an out-of-bounds read or buffer overflow later when vvv is used to read data into a buffer. An attacker may be able to trigger this by providing a specially crafted compressed stream.\n    cwe: CWE-190\n    function_names:\n      - BZ2_decompress\n    filenames:\n      - decompress.c  \n    classification: very promising\n\n  - headline: Unchecked array index in BZ2_decompress   \n    analysis: |  \n      In the BZ2_decompress function in decompress.c, the GET_MTF_VAL macro retrieves values used to index into arrays (gLimit, gPerm, gBase).\n\n      The macro calculates an array index (zvec - gBase[zn]) but does not validate that the index is within the bounds of the arrays. Invalid index values could cause out-of-bounds reads or writes leading to data corruption or code execution.\n\n      The values used to calculate the index originate from the compressed stream. An attacker could potentially craft a malicious stream to exploit this vulnerability.\n    cwe: CWE-129\n    function_names:\n      - BZ2_decompress\n    filenames: \n      - decompress.c\n    classification: very promising\n\n  - headline: Missing check for NULL return from malloc\n    analysis: |\n      The default_bzalloc function in bzlib.c wraps malloc but does not check if malloc returns NULL on failure before returning the pointer.\n\n      The BZ2_bzReadOpen and BZ2_bzWriteOpen functions call default_bzalloc to allocate a bzFile struct. If the allocation fails and NULL is returned, it could lead to a null pointer dereference and crash.\n\n      This is an easily triggered denial of service (DOS) if an attacker can force malloc to fail, such as in low memory situations. It may also lead to code execution or other impacts if the returned NULL is dereferenced.\n    cwe: CWE-690\n    function_names:\n      - default_bzalloc\n      - BZ2_bzReadOpen\n      - BZ2_bzWriteOpen \n    filenames:\n      - bzlib.c\n    classification: slightly promising\n\n  - headline: Divide by zero possibility in BZ2_blockSort\n    analysis: |  \n      The BZ2_blockSort function in blocksort.c calculates memory requirements using the nblock variable.\n\n      If nblock is zero, it will cause a divide by zero later in the function when calculating \"workFactor = nblock * ((workFactor-1) / 3);\".\n\n      The value of nblock comes from the strm->avail_in variable which contains the number of bytes available in the input stream. A crafted compressed stream could set this to zero to trigger the divide by zero.\n    cwe: CWE-369  \n    function_names:\n      - BZ2_blockSort\n    filenames:\n      - blocksort.c\n    classification: slightly promising\n\n  - headline: Reliance on untrusted inputs in bzip2recover\n    analysis: |\n      The bzip2recover.c utility reconstructs files by iterating through a compressed stream looking for block boundaries. It writes recovered blocks out to files using the inFileName variable to generate output file names.\n\n      The inFileName variable comes directly from a command line argument. An attacker could potentially pass a crafted file name string to trigger path traversal or code injection when generating the output file names.\n\n      Proper input validation, character escaping, and use of secure string functions would mitigate this risk.\n    cwe: CWE-20\n    function_names: \n      - main  \n    filenames:\n      - bzip2recover.c\n    classification: slightly promising\n```\n\nThe analysis identified a few potential vulnerabilities in the bzip2 code base that warrant further investigation and could possibly be exploited:\n\n1. Integer overflow issues when parsing crafted compressed data streams \n2. Unchecked array indexing allowing out-of-bounds memory access\n3. Missing null pointer checks that could lead to crashes or RCE\n4. Potential divide-by-zero error with specially crafted input\n5. Insecure handling of untrusted input in the bzip2recover utility\n\nThe decompress.c and bzip2recover.c files seem to be the riskiest areas. Focus should be on the BZ2_decompress function for developing proof-of-concept exploits of the most promising leads related to parsing untrusted compressed data. Let me know if you need any other information!",
      "date": "2024-06-14T12:50:36.016967",
      "usage": {
        "prompt_tokens": 134625,
        "completion_tokens": 1178,
        "cost": 2.107725
      }
    }
  ],
  "leads": [
    {
      "headline": "Potential integer overflow in BZ2_decompress",
      "analysis": "The BZ2_decompress function in decompress.c does not check for potential integer overflow when calculating the number of bytes to read. The GET_BITS macro reads a specified number of bits (nnn) from the input stream into an Int32 variable (vvv). \n\nIf a large value is passed for nnn that causes vvv to overflow, it could lead to an out-of-bounds read or buffer overflow later when vvv is used to read data into a buffer. An attacker may be able to trigger this by providing a specially crafted compressed stream.\n",
      "classification": "very promising",
      "cwe": "CWE-190",
      "function_names": [
        "BZ2_decompress"
      ],
      "filenames": [
        "decompress.c"
      ]
    },
    {
      "headline": "Unchecked array index in BZ2_decompress",
      "analysis": "In the BZ2_decompress function in decompress.c, the GET_MTF_VAL macro retrieves values used to index into arrays (gLimit, gPerm, gBase).\n\nThe macro calculates an array index (zvec - gBase[zn]) but does not validate that the index is within the bounds of the arrays. Invalid index values could cause out-of-bounds reads or writes leading to data corruption or code execution.\n\nThe values used to calculate the index originate from the compressed stream. An attacker could potentially craft a malicious stream to exploit this vulnerability.\n",
      "classification": "very promising",
      "cwe": "CWE-129",
      "function_names": [
        "BZ2_decompress"
      ],
      "filenames": [
        "decompress.c"
      ]
    },
    {
      "headline": "Missing check for NULL return from malloc",
      "analysis": "The default_bzalloc function in bzlib.c wraps malloc but does not check if malloc returns NULL on failure before returning the pointer.\n\nThe BZ2_bzReadOpen and BZ2_bzWriteOpen functions call default_bzalloc to allocate a bzFile struct. If the allocation fails and NULL is returned, it could lead to a null pointer dereference and crash.\n\nThis is an easily triggered denial of service (DOS) if an attacker can force malloc to fail, such as in low memory situations. It may also lead to code execution or other impacts if the returned NULL is dereferenced.\n",
      "classification": "slightly promising",
      "cwe": "CWE-690",
      "function_names": [
        "default_bzalloc",
        "BZ2_bzReadOpen",
        "BZ2_bzWriteOpen"
      ],
      "filenames": [
        "bzlib.c"
      ]
    },
    {
      "headline": "Divide by zero possibility in BZ2_blockSort",
      "analysis": "The BZ2_blockSort function in blocksort.c calculates memory requirements using the nblock variable.\n\nIf nblock is zero, it will cause a divide by zero later in the function when calculating \"workFactor = nblock * ((workFactor-1) / 3);\".\n\nThe value of nblock comes from the strm->avail_in variable which contains the number of bytes available in the input stream. A crafted compressed stream could set this to zero to trigger the divide by zero.\n",
      "classification": "slightly promising",
      "cwe": "CWE-369",
      "function_names": [
        "BZ2_blockSort"
      ],
      "filenames": [
        "blocksort.c"
      ]
    },
    {
      "headline": "Reliance on untrusted inputs in bzip2recover",
      "analysis": "The bzip2recover.c utility reconstructs files by iterating through a compressed stream looking for block boundaries. It writes recovered blocks out to files using the inFileName variable to generate output file names.\n\nThe inFileName variable comes directly from a command line argument. An attacker could potentially pass a crafted file name string to trigger path traversal or code injection when generating the output file names.\n\nProper input validation, character escaping, and use of secure string functions would mitigate this risk.\n",
      "classification": "slightly promising",
      "cwe": "CWE-20",
      "function_names": [
        "main"
      ],
      "filenames": [
        "bzip2recover.c"
      ]
    }
  ],
  "scores": [
    {
      "stats": {
        "fn": 1,
        "tp": 0,
        "fp": 2
      },
      "mapping": {},
      "vuln_dates": {
        "CVE-2023-22895": "2023-01-10T01:15:10"
      },
      "scoring_model": "claude-3-opus-20240229",
      "type": "llm",
      "instruction_template_hash": "245ace12b6361954d0a2"
    }
  ],
  "instruction_template_hash": "10c0163db4740318a544",
  "version": "0.1.0"
}
