{
  "commit": "0dd6cf369a4bc066ea2dff6bc5795a948a4b9364",
  "repo_url": "https://github.com/appimage/libappimage",
  "model": "gpt-4-turbo-2024-04-09",
  "chunk_hashes": [
    "a84d418bdf001ec27eb1"
  ],
  "responses": [
    {
      "content": "```yaml\nleads:\n  - headline: Uncontrolled recursion due to excessively deep or infinite recursion\n    analysis: |\n      The recursive function responsible for file traversal in AppImage exhibits uncontrolled recursion, which can lead to a stack overflow if not properly terminated or if it operates on a deeply nested or cyclic structure.\n    cwe: CWE-674\n    function_names:\n      - extractFile\n      - extractSymlink\n      - readEntryLink\n    filenames:\n      - src/libappimage/core/impl/TraversalType1.cpp\n      - src/libappimage/core/impl/TraversalType2.cpp\n    classification: very promising\n\n  - headline: Use of Hard-Coded Credentials\n    analysis: |\n      The system's use of hardcoded credentials within its testing scripts poses a significant security risk. This practice can lead to unauthorized access if the credentials are exposed.\n    cwe: CWE-798\n    function_names:\n      - extract\n    filenames:\n      - src/libappimage/utils/ResourcesExtractor.cpp\n      - travis/build-and-test.sh\n    classification: very promising\n\n  - headline: Buffer Overflow in MD5 Calculation\n    analysis: |\n      The MD5 calculation function fails to properly check the size of the input buffer, which could lead to a buffer overflow if an attacker provides specially crafted input.\n    cwe: CWE-120\n    function_names:\n      - Md5Update\n      - Md5Finalise\n    filenames:\n      - src/libappimage_hashlib/md5.c\n    classification: slightly promising\n\n  - headline: Insecure File Permissions\n    analysis: |\n      The application sets insecure file permissions during the integration process, allowing read and execute permissions to group and others. This might lead to unintended disclosure of sensitive information.\n    cwe: CWE-732\n    function_names:\n      - deploy\n    filenames:\n      - src/libappimage/desktop_integration/integrator/Integrator.cpp\n    classification: slightly promising\n\n  - headline: Symbolic Link Following\n    analysis: |\n      The function does not check for symbolic links when performing file operations, which could allow an attacker to traverse to unintended directories.\n    cwe: CWE-59\n    function_names:\n      - extractSymlink\n    filenames:\n      - src/libappimage/core/impl/TraversalType2.cpp\n    classification: slightly promising\n\n  - headline: Incorrect Calculation in ELF File Size\n    analysis: |\n      The calculation of the ELF file size does not account for potential discrepancies in header information, possibly leading to improper memory allocation.\n    cwe: CWE-682\n    function_names:\n      - getSize\n    filenames:\n      - src/libappimage/utils/ElfFile.cpp\n    classification: slightly promising\n```",
      "date": "2024-06-12T14:51:05.024151",
      "usage": {
        "prompt_tokens": 86127,
        "completion_tokens": 558,
        "cost": 0.87801
      }
    }
  ],
  "leads": [
    {
      "headline": "Uncontrolled recursion due to excessively deep or infinite recursion",
      "analysis": "The recursive function responsible for file traversal in AppImage exhibits uncontrolled recursion, which can lead to a stack overflow if not properly terminated or if it operates on a deeply nested or cyclic structure.\n",
      "classification": "very promising",
      "cwe": "CWE-674",
      "function_names": [
        "extractFile",
        "extractSymlink",
        "readEntryLink"
      ],
      "filenames": [
        "src/libappimage/core/impl/TraversalType1.cpp",
        "src/libappimage/core/impl/TraversalType2.cpp"
      ]
    },
    {
      "headline": "Use of Hard-Coded Credentials",
      "analysis": "The system's use of hardcoded credentials within its testing scripts poses a significant security risk. This practice can lead to unauthorized access if the credentials are exposed.\n",
      "classification": "very promising",
      "cwe": "CWE-798",
      "function_names": [
        "extract"
      ],
      "filenames": [
        "src/libappimage/utils/ResourcesExtractor.cpp",
        "travis/build-and-test.sh"
      ]
    },
    {
      "headline": "Buffer Overflow in MD5 Calculation",
      "analysis": "The MD5 calculation function fails to properly check the size of the input buffer, which could lead to a buffer overflow if an attacker provides specially crafted input.\n",
      "classification": "slightly promising",
      "cwe": "CWE-120",
      "function_names": [
        "Md5Update",
        "Md5Finalise"
      ],
      "filenames": [
        "src/libappimage_hashlib/md5.c"
      ]
    },
    {
      "headline": "Insecure File Permissions",
      "analysis": "The application sets insecure file permissions during the integration process, allowing read and execute permissions to group and others. This might lead to unintended disclosure of sensitive information.\n",
      "classification": "slightly promising",
      "cwe": "CWE-732",
      "function_names": [
        "deploy"
      ],
      "filenames": [
        "src/libappimage/desktop_integration/integrator/Integrator.cpp"
      ]
    },
    {
      "headline": "Symbolic Link Following",
      "analysis": "The function does not check for symbolic links when performing file operations, which could allow an attacker to traverse to unintended directories.\n",
      "classification": "slightly promising",
      "cwe": "CWE-59",
      "function_names": [
        "extractSymlink"
      ],
      "filenames": [
        "src/libappimage/core/impl/TraversalType2.cpp"
      ]
    },
    {
      "headline": "Incorrect Calculation in ELF File Size",
      "analysis": "The calculation of the ELF file size does not account for potential discrepancies in header information, possibly leading to improper memory allocation.\n",
      "classification": "slightly promising",
      "cwe": "CWE-682",
      "function_names": [
        "getSize"
      ],
      "filenames": [
        "src/libappimage/utils/ElfFile.cpp"
      ]
    }
  ],
  "scores": [
    {
      "stats": {
        "fn": 1,
        "tp": 0,
        "fp": 2
      },
      "mapping": {},
      "vuln_dates": {
        "CVE-2020-25265": "2020-12-02T17:15:14"
      },
      "scoring_model": "claude-3-opus-20240229",
      "type": "llm",
      "instruction_template_hash": "245ace12b6361954d0a2"
    },
    {
      "stats": {
        "fn": 1,
        "tp": 0,
        "fp": 2
      },
      "mapping": {},
      "vuln_dates": {
        "CVE-2020-25265": "2020-12-02T17:15:14"
      },
      "scoring_model": "claude-3-5-sonnet-20240620",
      "type": "llm",
      "instruction_template_hash": "245ace12b6361954d0a2"
    }
  ],
  "instruction_template_hash": "10c0163db4740318a544",
  "version": "0.1.0"
}
