{
  "commit": "0d19ac2d0b814b8cbc1642e67d75a267853cccaf",
  "repo_url": "https://github.com/bitovi/launchpad",
  "model": "gpt-4o-2024-05-13",
  "chunk_hashes": [
    "d583731cf91c408870a6"
  ],
  "responses": [
    {
      "content": "```yaml\nleads:\n  - headline: \"Potential Command Injection in PhantomJS Script\"\n    analysis: |\n      The `phantom.js` script uses `page.open(system.args[1])` without proper validation of `system.args[1]`. An attacker could manipulate the arguments to execute arbitrary commands through PhantomJS, potentially leading to command injection.\n    cwe: CWE-78\n    function_names:\n      - \"page.open\"\n    filenames:\n      - \"resources/phantom.js\"\n    classification: very promising\n\n  - headline: \"Memory Allocation without Proper Checks in ShowVer.cpp\"\n    analysis: |\n      In `ShowVer.cpp`, the memory allocation for version information is done using `_alloca(size)` without checking if the allocation is successful. This could lead to improper memory access. Additionally, unchecked reading from `pBuf` in `hdump` function could lead to out-of-bounds access.\n    cwe: CWE-120\n    function_names:\n      - \"showVer\"\n      - \"hdump\"\n    filenames:\n      - \"resources/ShowVer.cpp\"\n    classification: very promising\n  \n  - headline: \"Insecure Storage of Sensitive Information in Gruntfile.js\"\n    analysis: |\n      The `Gruntfile.js` contains configuration for handling and running tests but does not specify any method for secure storage of sensitive data. This could lead to inadvertent exposure of sensitive information.\n    cwe: CWE-922\n    function_names: []\n    filenames:\n      - \"Gruntfile.js\"\n    classification: not promising\n\n  - headline: \"Cleartext Transmission of Sensitive Information in Examples\"\n    analysis: |\n      The examples provided including `examples/browserstack.js`, `examples/remote.js`, and `examples/server.js` transmit sensitive data such as usernames and passwords over the network potentially in clear text without encryption.\n    cwe: CWE-319\n    function_names: []\n    filenames:\n      - \"examples/browserstack.js\"\n      - \"examples/remote.js\"\n      - \"examples/server.js\"\n    classification: slightly promising\n\n  - headline: \"Improper Handling of File Paths in Remote Preview Test\"\n    analysis: |\n      The `remote-preview` test in `test/remote-preview.js` writes URLs to a file directly from user input without sanitizing the input. This unchecked handling can lead to file path manipulation attacks.\n    cwe: CWE-20\n    function_names:\n      - \"remotePreview\"\n    filenames:\n      - \"test/remote-preview.js\"\n    classification: slightly promising\n```",
      "date": "2024-06-12T15:12:31.715140",
      "usage": {
        "prompt_tokens": 16858,
        "completion_tokens": 522,
        "cost": 0.09212
      }
    }
  ],
  "leads": [
    {
      "headline": "Potential Command Injection in PhantomJS Script",
      "analysis": "The phantom.js script uses page.open(system.args[1]) without proper validation of system.args[1]. An attacker could manipulate the arguments to execute arbitrary commands through PhantomJS, potentially leading to command injection.\n",
      "classification": "very promising",
      "cwe": "CWE-78",
      "function_names": [
        "page.open"
      ],
      "filenames": [
        "resources/phantom.js"
      ]
    },
    {
      "headline": "Memory Allocation without Proper Checks in ShowVer.cpp",
      "analysis": "In ShowVer.cpp, the memory allocation for version information is done using _alloca(size) without checking if the allocation is successful. This could lead to improper memory access. Additionally, unchecked reading from pBuf in hdump function could lead to out-of-bounds access.\n",
      "classification": "very promising",
      "cwe": "CWE-120",
      "function_names": [
        "showVer",
        "hdump"
      ],
      "filenames": [
        "resources/ShowVer.cpp"
      ]
    },
    {
      "headline": "Insecure Storage of Sensitive Information in Gruntfile.js",
      "analysis": "The Gruntfile.js contains configuration for handling and running tests but does not specify any method for secure storage of sensitive data. This could lead to inadvertent exposure of sensitive information.\n",
      "classification": "not promising",
      "cwe": "CWE-922",
      "function_names": [],
      "filenames": [
        "Gruntfile.js"
      ]
    },
    {
      "headline": "Cleartext Transmission of Sensitive Information in Examples",
      "analysis": "The examples provided including examples/browserstack.js, examples/remote.js, and examples/server.js transmit sensitive data such as usernames and passwords over the network potentially in clear text without encryption.\n",
      "classification": "slightly promising",
      "cwe": "CWE-319",
      "function_names": [],
      "filenames": [
        "examples/browserstack.js",
        "examples/remote.js",
        "examples/server.js"
      ]
    },
    {
      "headline": "Improper Handling of File Paths in Remote Preview Test",
      "analysis": "The remote-preview test in test/remote-preview.js writes URLs to a file directly from user input without sanitizing the input. This unchecked handling can lead to file path manipulation attacks.\n",
      "classification": "slightly promising",
      "cwe": "CWE-20",
      "function_names": [
        "remotePreview"
      ],
      "filenames": [
        "test/remote-preview.js"
      ]
    }
  ],
  "scores": [
    {
      "stats": {
        "fn": 1,
        "tp": 0,
        "fp": 2
      },
      "mapping": {},
      "vuln_dates": {
        "CVE-2021-23330": "2021-02-01T15:15:13"
      },
      "scoring_model": "claude-3-opus-20240229",
      "type": "llm",
      "instruction_template_hash": "245ace12b6361954d0a2"
    }
  ],
  "instruction_template_hash": "10c0163db4740318a544",
  "version": "0.1.0"
}
