{
  "commit": "25d93b30da61650efa62060c8c2b732e0f655caf",
  "repo_url": "https://github.com/xwiki-contrib/oidc",
  "model": "claude-3-sonnet-20240229",
  "chunk_hashes": [
    "3184cdf5aaf8d6a31d04"
  ],
  "responses": [
    {
      "content": "```yaml\nleads:\n  - headline: Cross-Site Scripting (XSS) vulnerability in OIDCProviderConsentPage\n    analysis: |\n      The `OIDCProviderConsentPage` class contains a potential Cross-Site Scripting (XSS) vulnerability. The class accepts user input through the `consent_accept` and `consent_refuse` form parameters, which are then used to generate HTML responses. If these parameters are not properly sanitized, an attacker could inject malicious scripts into the response, leading to XSS attacks.\n    cwe: CWE-79\n    function_names:\n      - org.xwiki.contrib.oidc.test.po.OIDCProviderConsentPage.clickAccept\n      - org.xwiki.contrib.oidc.test.po.OIDCProviderConsentPage.clickRefuse\n    filenames:\n      - oidc-test/oidc-test-pageobjects/src/main/java/org/xwiki/contrib/oidc/test/po/OIDCProviderConsentPage.java\n    classification: very promising\n\n  - headline: Potential Improper Input Validation in OIDCAuthServiceImpl\n    analysis: |\n      The `OIDCAuthServiceImpl` class handles user authentication and appears to rely on form parameters or query parameters for various operations. If these parameters are not properly validated or sanitized, it could lead to various injection attacks or other security vulnerabilities.\n    cwe: CWE-20\n    function_names:\n      - org.xwiki.contrib.oidc.auth.OIDCAuthServiceImpl.checkAuth\n      - org.xwiki.contrib.oidc.auth.OIDCAuthServiceImpl.showLogin\n    filenames:\n      - oidc-authenticator/src/main/java/org/xwiki/contrib/oidc/auth/OIDCAuthServiceImpl.java\n    classification: slightly promising\n\n  - headline: Potential Information Exposure in OIDCManager\n    analysis: |\n      The `OIDCManager` class appears to handle sensitive information such as access tokens, private keys, and user data. If these data are not properly protected or sanitized before being displayed or transmitted, it could lead to information exposure vulnerabilities.\n    cwe: CWE-200\n    function_names:\n      - org.xwiki.contrib.oidc.provider.internal.OIDCManager.executeTemplate\n      - org.xwiki.contrib.oidc.provider.internal.OIDCManager.createdIdToken\n    filenames:\n      - oidc-provider/src/main/java/org/xwiki/contrib/oidc/provider/internal/OIDCManager.java\n    classification: slightly promising\n\n  - headline: Potential Insecure Cryptographic Algorithm Usage\n    analysis: |\n      The codebase appears to use cryptographic algorithms for authentication and encryption purposes. If these algorithms are not properly configured or if they rely on weak or outdated algorithms, it could lead to security vulnerabilities.\n    cwe: CWE-327\n    function_names:\n      - org.xwiki.contrib.oidc.provider.internal.OIDCManager.initialize\n      - org.xwiki.contrib.oidc.provider.internal.OIDCManager.createdIdToken\n    filenames:\n      - oidc-provider/src/main/java/org/xwiki/contrib/oidc/provider/internal/OIDCManager.java\n    classification: very promising\n\n  - headline: Potential Missing Authentication for Critical Function\n    analysis: |\n      Some critical functions in the codebase, such as user management and authentication, do not appear to have proper authentication checks in place. If these functions can be accessed or invoked without proper authentication, it could lead to unauthorized access and potential abuse.\n    cwe: CWE-306\n    function_names:\n      - org.xwiki.contrib.oidc.auth.internal.OIDCUserManager.updateUserInfo\n      - org.xwiki.contrib.oidc.auth.internal.OIDCUserManager.logout\n    filenames:\n      - oidc-authenticator/src/main/java/org/xwiki/contrib/oidc/auth/internal/OIDCUserManager.java\n    classification: very promising\n\n  - headline: Potential Security Misconfiguration\n    analysis: |\n      The codebase appears to rely on various configuration settings for security-related operations, such as authentication mechanisms, cryptographic algorithms, and access control. If these configurations are not properly set or validated, it could lead to security vulnerabilities.\n    cwe: CWE-1188\n    function_names:\n      - org.xwiki.contrib.oidc.auth.internal.OIDCClientConfiguration.getProperty\n      - org.xwiki.contrib.oidc.provider.internal.OIDCProviderConfiguration.getProperty\n    filenames:\n      - oidc-authenticator/src/main/java/org/xwiki/contrib/oidc/auth/internal/OIDCClientConfiguration.java\n      - oidc-provider/src/main/java/org/xwiki/contrib/oidc/provider/internal/OIDCProviderConfiguration.java\n    classification: slightly promising\n```\n\nThe analysis identifies several potential security vulnerabilities in the codebase, including:\n\n1. **Cross-Site Scripting (XSS)**: The `OIDCProviderConsentPage` class accepts user input without proper sanitization, leading to a potential XSS vulnerability.\n\n2. **Improper Input Validation**: The `OIDCAuthServiceImpl` class appears to rely on form parameters or query parameters without proper validation, potentially leading to injection attacks or other security vulnerabilities.\n\n3. **Information Exposure**: The `OIDCManager` class handles sensitive information such as access tokens, private keys, and user data, which could lead to information exposure vulnerabilities if not properly protected or sanitized.\n\n4. **Insecure Cryptographic Algorithm Usage**: The codebase appears to use cryptographic algorithms for authentication and encryption purposes, and if these algorithms are not properly configured or rely on weak or outdated algorithms, it could lead to security vulnerabilities.\n\n5. **Missing Authentication for Critical Functions**: Some critical functions, such as user management and authentication, do not appear to have proper authentication checks in place, potentially leading to unauthorized access and abuse.\n\n6. **Security Misconfiguration**: The codebase relies on various configuration settings for security-related operations, and if these configurations are not properly set or validated, it could lead to security vulnerabilities.\n\nThe analysis also provides the relevant CWE identifiers, affected function names, and file paths for each potential vulnerability, which can be used to prioritize and address the identified issues.",
      "date": "2024-06-14T10:55:02.331580",
      "usage": {
        "prompt_tokens": 84632,
        "completion_tokens": 1584,
        "cost": 0.277656
      }
    }
  ],
  "leads": [
    {
      "headline": "Cross-Site Scripting (XSS) vulnerability in OIDCProviderConsentPage",
      "analysis": "The OIDCProviderConsentPage class contains a potential Cross-Site Scripting (XSS) vulnerability. The class accepts user input through the consent_accept and consent_refuse form parameters, which are then used to generate HTML responses. If these parameters are not properly sanitized, an attacker could inject malicious scripts into the response, leading to XSS attacks.\n",
      "classification": "very promising",
      "cwe": "CWE-79",
      "function_names": [
        "org.xwiki.contrib.oidc.test.po.OIDCProviderConsentPage.clickAccept",
        "org.xwiki.contrib.oidc.test.po.OIDCProviderConsentPage.clickRefuse"
      ],
      "filenames": [
        "oidc-test/oidc-test-pageobjects/src/main/java/org/xwiki/contrib/oidc/test/po/OIDCProviderConsentPage.java"
      ]
    },
    {
      "headline": "Potential Improper Input Validation in OIDCAuthServiceImpl",
      "analysis": "The OIDCAuthServiceImpl class handles user authentication and appears to rely on form parameters or query parameters for various operations. If these parameters are not properly validated or sanitized, it could lead to various injection attacks or other security vulnerabilities.\n",
      "classification": "slightly promising",
      "cwe": "CWE-20",
      "function_names": [
        "org.xwiki.contrib.oidc.auth.OIDCAuthServiceImpl.checkAuth",
        "org.xwiki.contrib.oidc.auth.OIDCAuthServiceImpl.showLogin"
      ],
      "filenames": [
        "oidc-authenticator/src/main/java/org/xwiki/contrib/oidc/auth/OIDCAuthServiceImpl.java"
      ]
    },
    {
      "headline": "Potential Information Exposure in OIDCManager",
      "analysis": "The OIDCManager class appears to handle sensitive information such as access tokens, private keys, and user data. If these data are not properly protected or sanitized before being displayed or transmitted, it could lead to information exposure vulnerabilities.\n",
      "classification": "slightly promising",
      "cwe": "CWE-200",
      "function_names": [
        "org.xwiki.contrib.oidc.provider.internal.OIDCManager.executeTemplate",
        "org.xwiki.contrib.oidc.provider.internal.OIDCManager.createdIdToken"
      ],
      "filenames": [
        "oidc-provider/src/main/java/org/xwiki/contrib/oidc/provider/internal/OIDCManager.java"
      ]
    },
    {
      "headline": "Potential Insecure Cryptographic Algorithm Usage",
      "analysis": "The codebase appears to use cryptographic algorithms for authentication and encryption purposes. If these algorithms are not properly configured or if they rely on weak or outdated algorithms, it could lead to security vulnerabilities.\n",
      "classification": "very promising",
      "cwe": "CWE-327",
      "function_names": [
        "org.xwiki.contrib.oidc.provider.internal.OIDCManager.initialize",
        "org.xwiki.contrib.oidc.provider.internal.OIDCManager.createdIdToken"
      ],
      "filenames": [
        "oidc-provider/src/main/java/org/xwiki/contrib/oidc/provider/internal/OIDCManager.java"
      ]
    },
    {
      "headline": "Potential Missing Authentication for Critical Function",
      "analysis": "Some critical functions in the codebase, such as user management and authentication, do not appear to have proper authentication checks in place. If these functions can be accessed or invoked without proper authentication, it could lead to unauthorized access and potential abuse.\n",
      "classification": "very promising",
      "cwe": "CWE-306",
      "function_names": [
        "org.xwiki.contrib.oidc.auth.internal.OIDCUserManager.updateUserInfo",
        "org.xwiki.contrib.oidc.auth.internal.OIDCUserManager.logout"
      ],
      "filenames": [
        "oidc-authenticator/src/main/java/org/xwiki/contrib/oidc/auth/internal/OIDCUserManager.java"
      ]
    },
    {
      "headline": "Potential Security Misconfiguration",
      "analysis": "The codebase appears to rely on various configuration settings for security-related operations, such as authentication mechanisms, cryptographic algorithms, and access control. If these configurations are not properly set or validated, it could lead to security vulnerabilities.\n",
      "classification": "slightly promising",
      "cwe": "CWE-1188",
      "function_names": [
        "org.xwiki.contrib.oidc.auth.internal.OIDCClientConfiguration.getProperty",
        "org.xwiki.contrib.oidc.provider.internal.OIDCProviderConfiguration.getProperty"
      ],
      "filenames": [
        "oidc-authenticator/src/main/java/org/xwiki/contrib/oidc/auth/internal/OIDCClientConfiguration.java",
        "oidc-provider/src/main/java/org/xwiki/contrib/oidc/provider/internal/OIDCProviderConfiguration.java"
      ]
    }
  ],
  "scores": [
    {
      "stats": {
        "fn": 1,
        "tp": 0,
        "fp": 3
      },
      "mapping": {},
      "vuln_dates": {
        "CVE-2022-39387": "2022-11-04T19:15:10"
      },
      "scoring_model": "claude-3-opus-20240229",
      "type": "llm",
      "instruction_template_hash": "245ace12b6361954d0a2"
    },
    {
      "stats": {
        "fn": 1,
        "tp": 0,
        "fp": 3
      },
      "mapping": {},
      "vuln_dates": {
        "CVE-2022-39387": "2022-11-04T19:15:10"
      },
      "scoring_model": "claude-3-5-sonnet-20240620",
      "type": "llm",
      "instruction_template_hash": "245ace12b6361954d0a2"
    }
  ],
  "instruction_template_hash": "10c0163db4740318a544",
  "version": "0.1.0"
}
