{
  "commit": "39aaa2bb3cfba1101173b5706438a0d9d6d0b229",
  "repo_url": "https://github.com/mannyvergel/oils-js",
  "model": "gpt-4o-2024-05-13",
  "chunk_hashes": [
    "0acce186267f69b8566a"
  ],
  "responses": [
    {
      "content": "```yaml\nleads:\n  - headline: \"Potential Command Injection in Configuration Loader\"\n    analysis: |\n      The code loads configuration files based on paths constructed using user-controlled inputs (`this.conf.baseDir` and other directory paths). Specifically, the `require` statements in methods like `include` in `/core/Web.js` and `_getPluginFunction` in `/core/Web.js` can be manipulated if an attacker can control the configuration paths. By crafting a malicious configuration path, an attacker could inject arbitrary code that gets executed in the context of the application.\n    cwe: CWE-78\n    function_names:\n      - include\n      - _getPluginFunction\n    filenames:\n      - core/Web.js\n    classification: very promising\n\n  - headline: \"Insufficient Input Validation in Object Extension Mechanism\"\n    analysis: |\n      The `extend` function in `/core/Obj.js` does not perform sufficient validation on the properties being copied to the new prototype. This could lead to prototype pollution, where malicious properties can be injected into JavaScript objects, potentially bypassing security controls or corrupting the application state.\n    cwe: CWE-1321\n    function_names:\n      - extend\n    filenames:\n      - core/Obj.js\n    classification: slightly promising\n\n  - headline: \"Cleartext Transmission of Sensitive Data\"\n    analysis: |\n      The application defaults to using HTTP for communication unless explicitly configured to use HTTPS. This can result in the transmission of sensitive information such as cookies and credentials over unencrypted channels, making them susceptible to interception and tampering.\n    cwe: CWE-319\n    function_names:\n      - start\n    filenames:\n      - core/Web.js\n    classification: very promising\n\n  - headline: \"Potential Denial of Service due to Missing Error Handling\"\n    analysis: |\n      The `fs.readFile` method in `/core/loaders/lib/FsLoader.js` and `/core/utils/oilsUtils.js` does not have proper error handling. If a file read operation fails, especially due to high filesystem latency or non-existent files, the application could crash, leading to denial of service.\n    cwe: CWE-754\n    function_names:\n      - load\n      - serveStaticFile\n    filenames:\n      - core/loaders/lib/FsLoader.js\n      - core/utils/oilsUtils.js\n    classification: slightly promising\n\n  - headline: \"Improper Validation of Integrity Check Value\"\n    analysis: |\n      The process of extending schemas in the `includeModelObj` method combines schemas from different models without validating their integrity. This could lead to unexpected behavior if schemas are extended incorrectly, potentially allowing for injection attacks or data corruption.\n    cwe: CWE-354\n    function_names:\n      - includeModelObj\n    filenames:\n      - core/Web.js\n    classification: slightly promising\n```",
      "date": "2024-06-14T14:45:32.731692",
      "usage": {
        "prompt_tokens": 14336,
        "completion_tokens": 583,
        "cost": 0.080425
      }
    }
  ],
  "leads": [
    {
      "headline": "Potential Command Injection in Configuration Loader",
      "analysis": "The code loads configuration files based on paths constructed using user-controlled inputs (this.conf.baseDir and other directory paths). Specifically, the require statements in methods like include in /core/Web.js and _getPluginFunction in /core/Web.js can be manipulated if an attacker can control the configuration paths. By crafting a malicious configuration path, an attacker could inject arbitrary code that gets executed in the context of the application.\n",
      "classification": "very promising",
      "cwe": "CWE-78",
      "function_names": [
        "include",
        "_getPluginFunction"
      ],
      "filenames": [
        "core/Web.js"
      ]
    },
    {
      "headline": "Insufficient Input Validation in Object Extension Mechanism",
      "analysis": "The extend function in /core/Obj.js does not perform sufficient validation on the properties being copied to the new prototype. This could lead to prototype pollution, where malicious properties can be injected into JavaScript objects, potentially bypassing security controls or corrupting the application state.\n",
      "classification": "slightly promising",
      "cwe": "CWE-1321",
      "function_names": [
        "extend"
      ],
      "filenames": [
        "core/Obj.js"
      ]
    },
    {
      "headline": "Cleartext Transmission of Sensitive Data",
      "analysis": "The application defaults to using HTTP for communication unless explicitly configured to use HTTPS. This can result in the transmission of sensitive information such as cookies and credentials over unencrypted channels, making them susceptible to interception and tampering.\n",
      "classification": "very promising",
      "cwe": "CWE-319",
      "function_names": [
        "start"
      ],
      "filenames": [
        "core/Web.js"
      ]
    },
    {
      "headline": "Potential Denial of Service due to Missing Error Handling",
      "analysis": "The fs.readFile method in /core/loaders/lib/FsLoader.js and /core/utils/oilsUtils.js does not have proper error handling. If a file read operation fails, especially due to high filesystem latency or non-existent files, the application could crash, leading to denial of service.\n",
      "classification": "slightly promising",
      "cwe": "CWE-754",
      "function_names": [
        "load",
        "serveStaticFile"
      ],
      "filenames": [
        "core/loaders/lib/FsLoader.js",
        "core/utils/oilsUtils.js"
      ]
    },
    {
      "headline": "Improper Validation of Integrity Check Value",
      "analysis": "The process of extending schemas in the includeModelObj method combines schemas from different models without validating their integrity. This could lead to unexpected behavior if schemas are extended incorrectly, potentially allowing for injection attacks or data corruption.\n",
      "classification": "slightly promising",
      "cwe": "CWE-354",
      "function_names": [
        "includeModelObj"
      ],
      "filenames": [
        "core/Web.js"
      ]
    }
  ],
  "scores": [
    {
      "stats": {
        "fn": 1,
        "tp": 0,
        "fp": 2
      },
      "mapping": {},
      "vuln_dates": {
        "CVE-2021-4260": "2022-12-19T14:15:10"
      },
      "scoring_model": "claude-3-opus-20240229",
      "type": "llm",
      "instruction_template_hash": "245ace12b6361954d0a2"
    }
  ],
  "instruction_template_hash": "10c0163db4740318a544",
  "version": "0.1.0"
}
