{
  "commit": "3e1b59c8d95c1be8ad536088a389a3f36dec15a2",
  "repo_url": "https://github.com/aiven-open/journalpump",
  "model": "gpt-4-turbo-2024-04-09",
  "chunk_hashes": [
    "d4a5785f40ad2352b38c"
  ],
  "responses": [
    {
      "content": "```yaml\nleads:\n  - headline: \"Improper File Permission Assignment\"\n    analysis: |\n      The JournalPump code appears to be using the `os.chown` command in `test_journalpump_rotated_files_deletion` without proper checks on the implications of such operations. Changing file ownership indiscriminately could lead to unauthorized users gaining access to sensitive log files or the ability to perform actions as other system users, potentially leading to further system compromise.\n    cwe: CWE-732\n    function_names:\n      - \"test_journalpump_rotated_files_deletion\"\n    filenames:\n      - \"systest/test_rotation.py\"\n    classification: very promising\n  - headline: \"Unhandled Exception on WebSocket Server\"\n    analysis: |\n      In the `run` method of the `WebsocketMockServer` class, exceptions such as `websockets.exceptions.InvalidMessage` are caught, which may indicate unexpected or malicious WebSocket frames that the server doesn't handle. This could lead to denial of service if a client repeatedly sends unexpected frames, and the server keeps catching the exception without properly mitigating or logging the defect.\n    cwe: CWE-755\n    function vpn_names:\n      - \"run\"\n    filenames:\n      - \"test/test_websocket.py\"\n    classification: slightly promising\n  - headline: \"Sensitive Information Written to Log without Adequate Encryption\"\n    analysis: |\n      In the `test_journalpump_init` function, a dictionary containing sensitive fields like AWS credentials (aws_access_key_id and aws_secret_access_key) is declared openly. This data might be logged or printed elsewhere in debugging or error messages, posing risks of exposure.\n    cwe: CWE-532\n    function_names:\n      - \"test_journalpump_init\"\n    filenames:\n      - \"systest/test_rotation.py\"\n    classification: slightly promising\n  - headline: \"Potential Use of Insecure Temporary File Creation Method\"\n    analysis: |\n      The method `generate_logs.py` introduces potential vulnerability where the `tempfile.mkdtemp` is used to create temporary directories without securely setting permissions. This could permit local users to access or manipulate files in these directories.\n    cwe: CWE-379\n    function_names:\n      - \"__init__\"\n      - \"__enter__\"\n    filenames:\n      - \"scripts/generate_logs.py\"\n    classification: very promising\n  - headline: \"Subprocess Called Without Shell Argument Check\"\n    analysis: |\n      In multiple test cases, the module calls subprocess.Popen without validating external inputs used to construct shell commands. This could lead to shell injection if inputs are crafted maliciously by an attacker.\n    cwe: CWE-78\n    function_names:\n      - \"start\"\n      - \"test_rsyslogd_tcp_sender\"\n    filenames:\n      - \"systest/test_rsyslog.py\"\n    classification: slightly promising\n```",
      "date": "2024-06-08T22:09:32.189184",
      "usage": {
        "prompt_tokens": 54896,
        "completion_tokens": 588,
        "cost": 0.5666
      }
    }
  ],
  "leads": [
    {
      "headline": "Improper File Permission Assignment",
      "analysis": "The JournalPump code appears to be using the os.chown command in test_journalpump_rotated_files_deletion without proper checks on the implications of such operations. Changing file ownership indiscriminately could lead to unauthorized users gaining access to sensitive log files or the ability to perform actions as other system users, potentially leading to further system compromise.\n",
      "classification": "very promising",
      "cwe": "CWE-732",
      "function_names": [
        "test_journalpump_rotated_files_deletion"
      ],
      "filenames": [
        "systest/test_rotation.py"
      ]
    },
    {
      "headline": "Unhandled Exception on WebSocket Server",
      "analysis": "In the run method of the WebsocketMockServer class, exceptions such as websockets.exceptions.InvalidMessage are caught, which may indicate unexpected or malicious WebSocket frames that the server doesn't handle. This could lead to denial of service if a client repeatedly sends unexpected frames, and the server keeps catching the exception without properly mitigating or logging the defect.\n",
      "classification": "slightly promising",
      "cwe": "CWE-755",
      "function_names": [],
      "filenames": [
        "test/test_websocket.py"
      ]
    },
    {
      "headline": "Sensitive Information Written to Log without Adequate Encryption",
      "analysis": "In the test_journalpump_init function, a dictionary containing sensitive fields like AWS credentials (aws_access_key_id and aws_secret_access_key) is declared openly. This data might be logged or printed elsewhere in debugging or error messages, posing risks of exposure.\n",
      "classification": "slightly promising",
      "cwe": "CWE-532",
      "function_names": [
        "test_journalpump_init"
      ],
      "filenames": [
        "systest/test_rotation.py"
      ]
    },
    {
      "headline": "Potential Use of Insecure Temporary File Creation Method",
      "analysis": "The method generate_logs.py introduces potential vulnerability where the tempfile.mkdtemp is used to create temporary directories without securely setting permissions. This could permit local users to access or manipulate files in these directories.\n",
      "classification": "very promising",
      "cwe": "CWE-379",
      "function_names": [
        "__init__",
        "__enter__"
      ],
      "filenames": [
        "scripts/generate_logs.py"
      ]
    },
    {
      "headline": "Subprocess Called Without Shell Argument Check",
      "analysis": "In multiple test cases, the module calls subprocess.Popen without validating external inputs used to construct shell commands. This could lead to shell injection if inputs are crafted maliciously by an attacker.\n",
      "classification": "slightly promising",
      "cwe": "CWE-78",
      "function_names": [
        "start",
        "test_rsyslogd_tcp_sender"
      ],
      "filenames": [
        "systest/test_rsyslog.py"
      ]
    }
  ],
  "scores": [
    {
      "stats": {
        "fn": 1,
        "tp": 0,
        "fp": 2
      },
      "mapping": {},
      "vuln_dates": {
        "CVE-2023-51390": "2023-12-21T00:15:26"
      },
      "scoring_model": "gpt-4o-2024-05-13",
      "type": "llm",
      "instruction_template_hash": "8998f09cf57fca8a6e03"
    }
  ],
  "instruction_template_hash": "10c0163db4740318a544",
  "version": "0.1.0"
}
