{
  "commit": "015225affc1e207eb931fec055653a407c8c3688",
  "repo_url": "https://github.com/kubernetes-csi/csi-proxy",
  "model": "claude-3-5-sonnet-20240620",
  "chunk_hashes": [
    "f54fd1fd8bedcde459bf"
  ],
  "responses": [
    {
      "content": "```yaml\nleads:\n  - headline: Hardcoded credentials in scripts/sync-csi-proxy.sh\n    analysis: |\n      The script contains hardcoded credentials, specifically the username \"prow\" used for SSH access. Hardcoded credentials pose a security risk as they can be easily discovered if the code is exposed. Additionally, using a shared account like \"prow\" makes it difficult to audit individual actions.\n    cwe: CWE-798\n    function_names:\n      - main\n    filenames:\n      - scripts/sync-csi-proxy.sh\n    classification: very promising\n\n  - headline: Potential command injection in scripts/bump-version.sh\n    analysis: | \n      The script uses variables like $API_GROUP and $OLD_API_VERSION directly in commands without proper sanitization. This could allow command injection if an attacker can control those variables. For example, in the line \"sed -i s/$OLD_API_VERSION/$NEW_API_VERSION/g\", if $OLD_API_VERSION contains malicious shell metacharacters, it could lead to arbitrary command execution.\n    cwe: CWE-78\n    function_names:\n      - bump_client\n      - bump_server\n    filenames:\n      - scripts/bump-version.sh  \n    classification: very promising\n\n  - headline: Unsafe use of eval in scripts/utils.sh\n    analysis: |\n      The script uses eval to execute commands constructed from variables, for example: \"eval value=\"\\${${var}_${version}}\"\". This is dangerous as it allows arbitrary code execution if an attacker can control the contents of those variables. Eval should be avoided whenever possible as it's very difficult to use safely.\n    cwe: CWE-95\n    function_names:\n      - get_versioned_variable\n    filenames:\n      - scripts/utils.sh\n    classification: very promising\n\n  - headline: Potential path traversal in release-tools/boilerplate/boilerplate.py\n    analysis: |\n      The script constructs file paths using user-supplied input without proper sanitization. For example, it uses os.path.join(args.boilerplate_dir, \"boilerplate.*.txt\") to glob files. If an attacker can control args.boilerplate_dir, they may be able to read files outside the intended directory via path traversal.\n    cwe: CWE-22\n    function_names:\n      - get_refs\n    filenames:\n      - release-tools/boilerplate/boilerplate.py\n    classification: slightly promising\n\n  - headline: Use of MD5 hash in release-tools/verify-boilerplate.sh\n    analysis: |\n      The script appears to use MD5 hashing, based on the presence of md5sum commands. MD5 is cryptographically broken and should not be used for security purposes. While it's not clear if it's being used in a security context here, it's generally recommended to use more secure alternatives like SHA-256.\n    cwe: CWE-327\n    function_names: []\n    filenames:\n      - release-tools/verify-boilerplate.sh\n    classification: slightly promising\n```",
      "date": "2024-07-07T21:31:03.603736",
      "usage": {
        "prompt_tokens": 53763,
        "completion_tokens": 732,
        "cost": 0.172269
      }
    }
  ],
  "leads": [
    {
      "headline": "Hardcoded credentials in scripts/sync-csi-proxy.sh",
      "analysis": "The script contains hardcoded credentials, specifically the username \"prow\" used for SSH access. Hardcoded credentials pose a security risk as they can be easily discovered if the code is exposed. Additionally, using a shared account like \"prow\" makes it difficult to audit individual actions.\n",
      "classification": "very promising",
      "cwe": "CWE-798",
      "function_names": [
        "main"
      ],
      "filenames": [
        "scripts/sync-csi-proxy.sh"
      ]
    },
    {
      "headline": "Potential command injection in scripts/bump-version.sh",
      "analysis": "The script uses variables like $API_GROUP and $OLD_API_VERSION directly in commands without proper sanitization. This could allow command injection if an attacker can control those variables. For example, in the line \"sed -i s/$OLD_API_VERSION/$NEW_API_VERSION/g\", if $OLD_API_VERSION contains malicious shell metacharacters, it could lead to arbitrary command execution.\n",
      "classification": "very promising",
      "cwe": "CWE-78",
      "function_names": [
        "bump_client",
        "bump_server"
      ],
      "filenames": [
        "scripts/bump-version.sh"
      ]
    },
    {
      "headline": "Unsafe use of eval in scripts/utils.sh",
      "analysis": "The script uses eval to execute commands constructed from variables, for example: \"eval value=\"\\${${var}_${version}}\"\". This is dangerous as it allows arbitrary code execution if an attacker can control the contents of those variables. Eval should be avoided whenever possible as it's very difficult to use safely.\n",
      "classification": "very promising",
      "cwe": "CWE-95",
      "function_names": [
        "get_versioned_variable"
      ],
      "filenames": [
        "scripts/utils.sh"
      ]
    },
    {
      "headline": "Potential path traversal in release-tools/boilerplate/boilerplate.py",
      "analysis": "The script constructs file paths using user-supplied input without proper sanitization. For example, it uses os.path.join(args.boilerplate_dir, \"boilerplate.*.txt\") to glob files. If an attacker can control args.boilerplate_dir, they may be able to read files outside the intended directory via path traversal.\n",
      "classification": "slightly promising",
      "cwe": "CWE-22",
      "function_names": [
        "get_refs"
      ],
      "filenames": [
        "release-tools/boilerplate/boilerplate.py"
      ]
    },
    {
      "headline": "Use of MD5 hash in release-tools/verify-boilerplate.sh",
      "analysis": "The script appears to use MD5 hashing, based on the presence of md5sum commands. MD5 is cryptographically broken and should not be used for security purposes. While it's not clear if it's being used in a security context here, it's generally recommended to use more secure alternatives like SHA-256.\n",
      "classification": "slightly promising",
      "cwe": "CWE-327",
      "function_names": [],
      "filenames": [
        "release-tools/verify-boilerplate.sh"
      ]
    }
  ],
  "scores": [
    {
      "stats": {
        "fn": 1,
        "tp": 0,
        "fp": 3
      },
      "mapping": {},
      "vuln_dates": {
        "CVE-2023-3893": "2023-11-03T18:15:08"
      },
      "scoring_model": "claude-3-5-sonnet-20240620",
      "type": "llm",
      "instruction_template_hash": "245ace12b6361954d0a2"
    }
  ],
  "instruction_template_hash": "10c0163db4740318a544",
  "version": "0.1.0"
}
