{
  "commit": "2bad9ec73d6ae5ede21df61faad6c254438a2e21",
  "repo_url": "https://github.com/stargate-rewritten/stargate-bukkit",
  "model": "gpt-4o-2024-05-13",
  "chunk_hashes": [
    "c8bfb18261a619f4a661"
  ],
  "responses": [
    {
      "content": "```yaml\nleads:\n  - headline: \"Potential Command Injection in pmListener\"\n    analysis: |\n      The `pmListener` class handles plugin messages with the method `onPluginMessageReceived`. Specifically, it processes incoming messages on the \"BungeeCord\" channel and attempts to handle \"SGBungee\" packets. The method does not adequately verify the content of the message before parsing, which could lead to command injection if a malicious user can send crafted messages on the \"BungeeCord\" channel.\n    cwe: CWE-77\n    function_names:\n      - onPluginMessageReceived\n    filenames:\n      - src/net/TheDgtl/Stargate/pmListener.java\n    classification: very promising\n\n  - headline: \"Possible Arbitrary File Write in loadGates\"\n    analysis: |\n      In the Gate class, the loadGates method reads files from the file system and processes their content. If an attacker can influence the file names or content placed in the gate folder, this may lead to arbitrary file writes, especially since input is not validated. This could be exploited to write arbitrary data to the file system.\n    cwe: CWE-22\n    function_names:\n      - loadGates\n    filenames:\n      - src/net/TheDgtl/Stargate/Gate.java\n    classification: very promising\n\n  - headline: \"Exposure of Sensitive Information to Unauthorized Actor\"\n    analysis: |\n      The broadcasting of onPlayerMove and other events may display sensitive information, like internal portal network names or player actions, which can be leveraged by an attacker to gain insights into the portal network structure or player behavior.\n    cwe: CWE-200\n    function_names:\n      - onPlayerMove\n    filenames:\n      - src/net/TheDgtl/Stargate/Stargate.java\n    classification: slightly promising\n\n  - headline: \"Improper Input Validation in Blox Constructor\"\n    analysis: |\n      The constructor of the Blox class allows the instantiation of Blox objects using unvalidated strings (e.g., `new Blox(World world, String string)`). Malformed strings could lead to unexpected behavior or exceptions, particularly if the string does not conform to the expected format.\n    cwe: CWE-20\n    function_names:\n      - Blox (constructor)\n    filenames:\n      - src/net/TheDgtl/Stargate/Blox.java\n    classification: slightly promising\n\n  - headline: \"Improper Authentication in Portal Creation\"\n    analysis: |\n      The createPortal method uses input from SignChangeEvent to create a new portal without strict validation of user permissions and network access. This can allow unauthorized users to create portals in restricted networks if checks are bypassed.\n    cwe: CWE-287\n    function_names:\n      - createPortal\n    filenames:\n      - src/net/TheDgtl/Stargate/Portal.java\n    classification: very promising\n\n  - headline: \"Potential Null Pointer Dereference in getOwnerName Method\"\n    analysis: |\n      In the Portal class, the getOwnerName method is susceptible to a Null Pointer Dereference if the ownerUUID of a portal is null, leading to an exceptional termination if used without previous checks.\n    cwe: CWE-476\n    function_names:\n      - getOwnerName\n    filenames:\n      - src/net/TheDgtl/Stargate/Portal.java\n    classification: slightly promising\n\n  - headline: \"Improper Handling of Exceptional Conditions in EconomyHandler\"\n    analysis: |\n      Several methods within the EconomyHandler class do not thoroughly handle cases where the economy object is null, leading to potential Null Pointer Dereferences and unhandled exceptions in economic transactions.\n    cwe: CWE-755\n    function_names:\n      - chargePlayer\n      - getBalance\n    filenames:\n      - src/net/TheDgtl/Stargate/EconomyHandler.java\n    classification: slightly promising\n\n  - headline: \"Insecure Design: Lack of Authentication for Critical Functions\"\n    analysis: |\n      The Stargate class handles essential operations like portal creation and teleportation without rigorous authentication checks. Functions like openPortal and createPortal can be exploited by any player with minor permissions, potentially leading to unauthorized access and manipulation of the portal system.\n    cwe: CWE-306\n    function_names:\n      - openPortal\n      - createPortal\n    filenames:\n      - src/net/TheDgtl/Stargate/Stargate.java\n      - src/net/TheDgtl/Stargate/Portal.java\n    classification: very promising\n```",
      "date": "2024-06-13T12:02:12.650210",
      "usage": {
        "prompt_tokens": 38771,
        "completion_tokens": 931,
        "cost": 0.20782
      }
    }
  ],
  "leads": [
    {
      "headline": "Potential Command Injection in pmListener",
      "analysis": "The pmListener class handles plugin messages with the method onPluginMessageReceived. Specifically, it processes incoming messages on the \"BungeeCord\" channel and attempts to handle \"SGBungee\" packets. The method does not adequately verify the content of the message before parsing, which could lead to command injection if a malicious user can send crafted messages on the \"BungeeCord\" channel.\n",
      "classification": "very promising",
      "cwe": "CWE-77",
      "function_names": [
        "onPluginMessageReceived"
      ],
      "filenames": [
        "src/net/TheDgtl/Stargate/pmListener.java"
      ]
    },
    {
      "headline": "Possible Arbitrary File Write in loadGates",
      "analysis": "In the Gate class, the loadGates method reads files from the file system and processes their content. If an attacker can influence the file names or content placed in the gate folder, this may lead to arbitrary file writes, especially since input is not validated. This could be exploited to write arbitrary data to the file system.\n",
      "classification": "very promising",
      "cwe": "CWE-22",
      "function_names": [
        "loadGates"
      ],
      "filenames": [
        "src/net/TheDgtl/Stargate/Gate.java"
      ]
    },
    {
      "headline": "Exposure of Sensitive Information to Unauthorized Actor",
      "analysis": "The broadcasting of onPlayerMove and other events may display sensitive information, like internal portal network names or player actions, which can be leveraged by an attacker to gain insights into the portal network structure or player behavior.\n",
      "classification": "slightly promising",
      "cwe": "CWE-200",
      "function_names": [
        "onPlayerMove"
      ],
      "filenames": [
        "src/net/TheDgtl/Stargate/Stargate.java"
      ]
    },
    {
      "headline": "Improper Input Validation in Blox Constructor",
      "analysis": "The constructor of the Blox class allows the instantiation of Blox objects using unvalidated strings (e.g., new Blox(World world, String string)). Malformed strings could lead to unexpected behavior or exceptions, particularly if the string does not conform to the expected format.\n",
      "classification": "slightly promising",
      "cwe": "CWE-20",
      "function_names": [
        "Blox (constructor)"
      ],
      "filenames": [
        "src/net/TheDgtl/Stargate/Blox.java"
      ]
    },
    {
      "headline": "Improper Authentication in Portal Creation",
      "analysis": "The createPortal method uses input from SignChangeEvent to create a new portal without strict validation of user permissions and network access. This can allow unauthorized users to create portals in restricted networks if checks are bypassed.\n",
      "classification": "very promising",
      "cwe": "CWE-287",
      "function_names": [
        "createPortal"
      ],
      "filenames": [
        "src/net/TheDgtl/Stargate/Portal.java"
      ]
    },
    {
      "headline": "Potential Null Pointer Dereference in getOwnerName Method",
      "analysis": "In the Portal class, the getOwnerName method is susceptible to a Null Pointer Dereference if the ownerUUID of a portal is null, leading to an exceptional termination if used without previous checks.\n",
      "classification": "slightly promising",
      "cwe": "CWE-476",
      "function_names": [
        "getOwnerName"
      ],
      "filenames": [
        "src/net/TheDgtl/Stargate/Portal.java"
      ]
    },
    {
      "headline": "Improper Handling of Exceptional Conditions in EconomyHandler",
      "analysis": "Several methods within the EconomyHandler class do not thoroughly handle cases where the economy object is null, leading to potential Null Pointer Dereferences and unhandled exceptions in economic transactions.\n",
      "classification": "slightly promising",
      "cwe": "CWE-755",
      "function_names": [
        "chargePlayer",
        "getBalance"
      ],
      "filenames": [
        "src/net/TheDgtl/Stargate/EconomyHandler.java"
      ]
    },
    {
      "headline": "Insecure Design: Lack of Authentication for Critical Functions",
      "analysis": "The Stargate class handles essential operations like portal creation and teleportation without rigorous authentication checks. Functions like openPortal and createPortal can be exploited by any player with minor permissions, potentially leading to unauthorized access and manipulation of the portal system.\n",
      "classification": "very promising",
      "cwe": "CWE-306",
      "function_names": [
        "openPortal",
        "createPortal"
      ],
      "filenames": [
        "src/net/TheDgtl/Stargate/Stargate.java",
        "src/net/TheDgtl/Stargate/Portal.java"
      ]
    }
  ],
  "scores": [
    {
      "stats": {
        "fn": 1,
        "tp": 0,
        "fp": 4
      },
      "mapping": {},
      "vuln_dates": {
        "CVE-2021-43819": "2023-04-19T18:15:07"
      },
      "scoring_model": "claude-3-opus-20240229",
      "type": "llm",
      "instruction_template_hash": "245ace12b6361954d0a2"
    }
  ],
  "instruction_template_hash": "10c0163db4740318a544",
  "version": "0.1.0"
}
