{
  "commit": "000a21240da490d27d4032e26c5f6c42a8353fbc",
  "repo_url": "https://github.com/azuread/passport-azure-ad",
  "model": "claude-3-sonnet-20240229",
  "chunk_hashes": [
    "911674a43625de430612"
  ],
  "responses": [
    {
      "content": "Here are the potential security vulnerabilities in the codebase, formatted as a YAML object of type LeadList:\n\n```yaml\nleads:\n  - headline: Cross-Site Scripting (XSS) vulnerability\n    analysis: |\n      The code does not properly sanitize user input before rendering it in the response, allowing an attacker to inject malicious JavaScript that will execute in the victim's browser.\n    cwe: CWE-79\n    function_names:\n      - createTask\n    filenames:\n      - examples/server-oauth2/server.js\n    classification: very promising\n\n  - headline: Improper Authentication vulnerability\n    analysis: |\n      The application does not properly authenticate users before granting access to sensitive resources, allowing an attacker to potentially access or modify data without authorization.\n    cwe: CWE-306\n    function_names:\n      - authenticate\n    filenames:\n      - lib/passport-azure-ad/oidcstrategy.js\n    classification: very promising\n\n  - headline: Insecure Cryptographic Storage vulnerability\n    analysis: |\n      The application stores sensitive information, such as credentials or session tokens, in an insecure manner, potentially allowing an attacker to gain unauthorized access.\n    cwe: CWE-312\n    function_names:\n      - jwtVerify\n    filenames:\n      - lib/passport-azure-ad/tokenValidator.js\n    classification: slightly promising\n\n  - headline: Insecure Direct Object Reference vulnerability\n    analysis: |\n      The application uses user-supplied input to directly access objects in the system, potentially allowing an attacker to gain unauthorized access to sensitive data or functionality.\n    cwe: CWE-639\n    function_names:\n      - getProfile\n    filenames:\n      - lib/passport-azure-ad/samlutils.js\n    classification: slightly promising\n\n  - headline: Unvalidated Redirects and Forwards vulnerability\n    analysis: |\n      The application redirects users to a user-supplied URL without properly validating the destination, potentially allowing an attacker to redirect victims to a malicious site.\n    cwe: CWE-601\n    function_names:\n      - authenticate\n    filenames:\n      - lib/passport-azure-ad/oidcstrategy.js\n    classification: slightly promising\n```\n\nNote: This analysis is based on a review of the provided code and may not be exhaustive. It's recommended to perform additional security testing and code review to identify and mitigate potential vulnerabilities.",
      "date": "2024-06-12T15:09:45.035673",
      "usage": {
        "prompt_tokens": 65593,
        "completion_tokens": 579,
        "cost": 0.205464
      }
    }
  ],
  "leads": [
    {
      "headline": "Cross-Site Scripting (XSS) vulnerability",
      "analysis": "The code does not properly sanitize user input before rendering it in the response, allowing an attacker to inject malicious JavaScript that will execute in the victim's browser.\n",
      "classification": "very promising",
      "cwe": "CWE-79",
      "function_names": [
        "createTask"
      ],
      "filenames": [
        "examples/server-oauth2/server.js"
      ]
    },
    {
      "headline": "Improper Authentication vulnerability",
      "analysis": "The application does not properly authenticate users before granting access to sensitive resources, allowing an attacker to potentially access or modify data without authorization.\n",
      "classification": "very promising",
      "cwe": "CWE-306",
      "function_names": [
        "authenticate"
      ],
      "filenames": [
        "lib/passport-azure-ad/oidcstrategy.js"
      ]
    },
    {
      "headline": "Insecure Cryptographic Storage vulnerability",
      "analysis": "The application stores sensitive information, such as credentials or session tokens, in an insecure manner, potentially allowing an attacker to gain unauthorized access.\n",
      "classification": "slightly promising",
      "cwe": "CWE-312",
      "function_names": [
        "jwtVerify"
      ],
      "filenames": [
        "lib/passport-azure-ad/tokenValidator.js"
      ]
    },
    {
      "headline": "Insecure Direct Object Reference vulnerability",
      "analysis": "The application uses user-supplied input to directly access objects in the system, potentially allowing an attacker to gain unauthorized access to sensitive data or functionality.\n",
      "classification": "slightly promising",
      "cwe": "CWE-639",
      "function_names": [
        "getProfile"
      ],
      "filenames": [
        "lib/passport-azure-ad/samlutils.js"
      ]
    },
    {
      "headline": "Unvalidated Redirects and Forwards vulnerability",
      "analysis": "The application redirects users to a user-supplied URL without properly validating the destination, potentially allowing an attacker to redirect victims to a malicious site.\n",
      "classification": "slightly promising",
      "cwe": "CWE-601",
      "function_names": [
        "authenticate"
      ],
      "filenames": [
        "lib/passport-azure-ad/oidcstrategy.js"
      ]
    }
  ],
  "scores": [
    {
      "stats": {
        "fn": 1,
        "tp": 0,
        "fp": 2
      },
      "mapping": {},
      "vuln_dates": {
        "CVE-2016-7191": "2016-09-28T20:59:00"
      },
      "scoring_model": "claude-3-opus-20240229",
      "type": "llm",
      "instruction_template_hash": "245ace12b6361954d0a2"
    }
  ],
  "instruction_template_hash": "10c0163db4740318a544",
  "version": "0.1.0"
}
