{
  "commit": "1368b4ce35ba2139328b9bd731fe2ea1ae5d9d27",
  "repo_url": "https://github.com/pingidentity/ssam",
  "model": "claude-3-5-sonnet-20240620",
  "chunk_hashes": [
    "9d242986302f3ba4247b"
  ],
  "responses": [
    {
      "content": "Here's my analysis of the security vulnerabilities in the provided codebase:\n\n```yaml\nleads:\n  - headline: Potential XML external entity (XXE) vulnerability\n    analysis: |\n      The code uses XML parsing in multiple places, but does not explicitly disable external entity processing. This could potentially allow XXE attacks if untrusted XML input is processed. The XML parsing occurs in the LDAP SDK classes that are used throughout the application. An attacker could potentially exploit this by submitting maliciously crafted XML data that references external entities, leading to information disclosure, denial of service, or server-side request forgery.\n    cwe: CWE-611\n    function_names:\n      - ldapConnectionPool\n    filenames:\n      - src/main/java/com/unboundid/webapp/ssam/SSAMApplication.java\n    classification: slightly promising\n\n  - headline: Potential insecure randomness in password generation\n    analysis: |\n      The code uses SecureRandom to generate passwords, which is generally secure. However, it uses the default constructor which may use a weak seed on some platforms. A more secure approach would be to explicitly seed SecureRandom with entropy from /dev/urandom or use SecureRandom.getInstanceStrong(). An attacker could potentially predict generated passwords if the randomness is weak, allowing unauthorized access.\n    cwe: CWE-330\n    function_names:\n      - initialize\n    filenames:  \n      - src/main/java/com/unboundid/webapp/ssam/SSAMInstaller.java\n    classification: slightly promising\n\n  - headline: Potential LDAP injection vulnerability\n    analysis: |\n      The code constructs LDAP filters using user-supplied input without proper sanitization. For example, in the LDAPAuthenticationProvider class, the username is directly inserted into the search filter. This could allow an attacker to inject malicious LDAP queries. A successful attack could lead to unauthorized access, information disclosure, or manipulation of LDAP data.\n    cwe: CWE-90\n    function_names:\n      - authenticate\n    filenames:\n      - src/main/java/com/unboundid/webapp/ssam/LDAPAuthenticationProvider.java  \n    classification: very promising\n\n  - headline: Potential information leakage in error messages\n    analysis: |\n      The code returns detailed error messages in some cases, which could reveal sensitive information about the system to attackers. For example, in the SSAMController class, LDAP exceptions are directly returned in error responses. This information could be used by attackers to gather intelligence about the underlying LDAP structure and potentially craft more targeted attacks.\n    cwe: CWE-209\n    function_names:\n      - updatePassword\n      - createUser\n    filenames:\n      - src/main/java/com/unboundid/webapp/ssam/SSAMController.java\n    classification: slightly promising\n\n  - headline: Use of hardcoded credentials \n    analysis: |\n      The code contains hardcoded credentials in multiple places. For example, in the ssam-aws-setup.sh script, a hardcoded password is used. Hardcoded credentials are a security risk as they can be easily discovered by examining the source code or binary. An attacker who gains access to the code could use these credentials to gain unauthorized access to the system.\n    cwe: CWE-798\n    function_names: []\n    filenames:\n      - src/main/assembly/files/ssam-aws-setup.sh\n    classification: very promising\n```\n\nThis analysis identifies several potential security vulnerabilities in the codebase, ranging from slightly promising to very promising leads. The most critical issues appear to be the potential for LDAP injection and the use of hardcoded credentials. Other issues like potential XXE vulnerabilities and insecure randomness are also concerning but may require more specific circumstances to exploit. The information leakage in error messages is a common issue that could aid attackers in gathering intelligence about the system.",
      "date": "2024-07-08T08:15:17.741298",
      "usage": {
        "prompt_tokens": 71011,
        "completion_tokens": 913,
        "cost": 0.226728
      }
    }
  ],
  "leads": [
    {
      "headline": "Potential XML external entity (XXE) vulnerability",
      "analysis": "The code uses XML parsing in multiple places, but does not explicitly disable external entity processing. This could potentially allow XXE attacks if untrusted XML input is processed. The XML parsing occurs in the LDAP SDK classes that are used throughout the application. An attacker could potentially exploit this by submitting maliciously crafted XML data that references external entities, leading to information disclosure, denial of service, or server-side request forgery.\n",
      "classification": "slightly promising",
      "cwe": "CWE-611",
      "function_names": [
        "ldapConnectionPool"
      ],
      "filenames": [
        "src/main/java/com/unboundid/webapp/ssam/SSAMApplication.java"
      ]
    },
    {
      "headline": "Potential insecure randomness in password generation",
      "analysis": "The code uses SecureRandom to generate passwords, which is generally secure. However, it uses the default constructor which may use a weak seed on some platforms. A more secure approach would be to explicitly seed SecureRandom with entropy from /dev/urandom or use SecureRandom.getInstanceStrong(). An attacker could potentially predict generated passwords if the randomness is weak, allowing unauthorized access.\n",
      "classification": "slightly promising",
      "cwe": "CWE-330",
      "function_names": [
        "initialize"
      ],
      "filenames": [
        "src/main/java/com/unboundid/webapp/ssam/SSAMInstaller.java"
      ]
    },
    {
      "headline": "Potential LDAP injection vulnerability",
      "analysis": "The code constructs LDAP filters using user-supplied input without proper sanitization. For example, in the LDAPAuthenticationProvider class, the username is directly inserted into the search filter. This could allow an attacker to inject malicious LDAP queries. A successful attack could lead to unauthorized access, information disclosure, or manipulation of LDAP data.\n",
      "classification": "very promising",
      "cwe": "CWE-90",
      "function_names": [
        "authenticate"
      ],
      "filenames": [
        "src/main/java/com/unboundid/webapp/ssam/LDAPAuthenticationProvider.java"
      ]
    },
    {
      "headline": "Potential information leakage in error messages",
      "analysis": "The code returns detailed error messages in some cases, which could reveal sensitive information about the system to attackers. For example, in the SSAMController class, LDAP exceptions are directly returned in error responses. This information could be used by attackers to gather intelligence about the underlying LDAP structure and potentially craft more targeted attacks.\n",
      "classification": "slightly promising",
      "cwe": "CWE-209",
      "function_names": [
        "updatePassword",
        "createUser"
      ],
      "filenames": [
        "src/main/java/com/unboundid/webapp/ssam/SSAMController.java"
      ]
    },
    {
      "headline": "Use of hardcoded credentials",
      "analysis": "The code contains hardcoded credentials in multiple places. For example, in the ssam-aws-setup.sh script, a hardcoded password is used. Hardcoded credentials are a security risk as they can be easily discovered by examining the source code or binary. An attacker who gains access to the code could use these credentials to gain unauthorized access to the system.\n",
      "classification": "very promising",
      "cwe": "CWE-798",
      "function_names": [],
      "filenames": [
        "src/main/assembly/files/ssam-aws-setup.sh"
      ]
    }
  ],
  "scores": [
    {
      "stats": {
        "fn": 1,
        "tp": 0,
        "fp": 2
      },
      "mapping": {},
      "vuln_dates": {
        "CVE-2018-25084": "2023-04-10T18:15:07"
      },
      "scoring_model": "claude-3-5-sonnet-20240620",
      "type": "llm",
      "instruction_template_hash": "245ace12b6361954d0a2"
    }
  ],
  "instruction_template_hash": "10c0163db4740318a544",
  "version": "0.1.0"
}
