{
  "commit": "c15e2199d7199a311a2ae7039a317dcf64de336b",
  "repo_url": "https://github.com/rocklobster-in/contact-form-7",
  "model": "claude-3-haiku-20240307",
  "chunk_hashes": [
    "5d19f627e663911eeaff"
  ],
  "responses": [
    {
      "content": "```yaml\nleads:\n  - headline: Improper Validation of Specified Quantity in Input\n    analysis: |\n      The code appears to be vulnerable to CWE-1284 Improper Validation of Specified Quantity in Input. The code does not properly validate the input values for certain form fields, such as date, number, and range inputs. This could allow an attacker to provide invalid input that could lead to unexpected behavior or even crashes.\n    cwe: CWE-1284\n    function_names:\n      - initForm\n    filenames:\n      - includes/js/scripts.js\n    classification: very promising\n\n  - headline: Improper Neutralization of Formula Elements in a CSV File\n    analysis: |\n      The code appears to be vulnerable to CWE-1236 Improper Neutralization of Formula Elements in a CSV File. The code does not properly sanitize the values submitted in the contact form, which could allow an attacker to inject formulas or other malicious content into the exported CSV file.\n    cwe: CWE-1236\n    function_names:\n      - submit\n    filenames:\n      - includes/js/scripts.js\n    classification: very promising\n\n  - headline: Improper Neutralization of Special Elements used in a Command ('Command Injection')\n    analysis: |\n      The code appears to be vulnerable to CWE-77 Improper Neutralization of Special Elements used in a Command ('Command Injection'). The code does not properly sanitize the input values submitted in the contact form, which could allow an attacker to inject malicious commands that could be executed on the server.\n    cwe: CWE-77\n    function_names:\n      - submit\n    filenames:\n      - includes/js/scripts.js\n    classification: very promising\n\n  - headline: Improper Neutralization of Special Elements used in an OS Command ('OS Command Injection')\n    analysis: |\n      The code appears to be vulnerable to CWE-78 Improper Neutralization of Special Elements used in an OS Command ('OS Command Injection'). The code does not properly sanitize the input values submitted in the contact form, which could allow an attacker to inject malicious OS commands that could be executed on the server.\n    cwe: CWE-78\n    function_names:\n      - submit\n    filenames:\n      - includes/js/scripts.js\n    classification: very promising\n\n  - headline: Improper Neutralization of Input During Web Page Generation ('Cross-site Scripting')\n    analysis: |\n      The code appears to be vulnerable to CWE-79 Improper Neutralization of Input During Web Page Generation ('Cross-site Scripting'). The code does not properly sanitize the input values submitted in the contact form, which could allow an attacker to inject malicious scripts that could be executed in the victim's browser.\n    cwe: CWE-79\n    function_names:\n      - submit\n    filenames:\n      - includes/js/scripts.js\n    classification: very promising\n\n  - headline: Improper Neutralization of Argument Delimiters in a Command ('Argument Injection')\n    analysis: |\n      The code appears to be vulnerable to CWE-88 Improper Neutralization of Argument Delimiters in a Command ('Argument Injection'). The code does not properly sanitize the input values submitted in the contact form, which could allow an attacker to inject malicious arguments that could be executed in the server-side command.\n    cwe: CWE-88\n    function_names:\n      - submit\n    filenames:\n      - includes/js/scripts.js\n    classification: very promising\n\n  - headline: Improper Neutralization of Special Elements used in an SQL Command ('SQL Injection')\n    analysis: |\n      The code appears to be vulnerable to CWE-89 Improper Neutralization of Special Elements used in an SQL Command ('SQL Injection'). The code does not properly sanitize the input values submitted in the contact form, which could allow an attacker to inject malicious SQL commands that could be executed on the server's database.\n    cwe: CWE-89\n    function_names:\n      - submit\n    filenames:\n      - includes/js/scripts.js\n    classification: very promising\n\n  - headline: Improper Restriction of Operations within the Bounds of a Memory Buffer\n    analysis: |\n      The code appears to be vulnerable to various CWEs related to Improper Restriction of Operations within the Bounds of a Memory Buffer, such as CWE-120 Buffer Copy without Checking Size of Input ('Classic Buffer Overflow'), CWE-125 Out-of-bounds Read, and CWE-787 Out-of-bounds Write. The code does not properly validate the input values submitted in the contact form, which could lead to buffer overflow vulnerabilities.\n    cwe: CWE-120\n    function_names:\n      - initForm\n    filenames:\n      - includes/js/scripts.js\n    classification: very promising\n\n  - headline: Generation of Error Message Containing Sensitive Information\n    analysis: |\n      The code appears to be vulnerable to CWE-209 Generation of Error Message Containing Sensitive Information. The code does not properly handle errors and may display sensitive information in the error messages, which could be leveraged by an attacker to gain more information about the system.\n    cwe: CWE-209\n    function_names:\n      - submit\n    filenames:\n      - includes/js/scripts.js\n    classification: slightly promising\n\n  - headline: Incorrect Usage of Seeds in Pseudo-Random Number Generator (PRNG)\n    analysis: |\n      The code appears to be vulnerable to CWE-335 Incorrect Usage of Seeds in Pseudo-Random Number Generator (PRNG). The code generates a random ID for the contact form, but the implementation may not be secure, potentially allowing an attacker to predict or manipulate the generated IDs.\n    cwe: CWE-335\n    function_names:\n      - getId\n    filenames:\n      - includes/js/scripts.js\n    classification: slightly promising\n\n  - headline: Improper Validation of Integrity Check Value\n    analysis: |\n      The code appears to be vulnerable to CWE-354 Improper Validation of Integrity Check Value. The code does not properly validate the integrity of the data submitted in the contact form, which could allow an attacker to tamper with the data and bypass any integrity checks.\n    cwe: CWE-354\n    function_names:\n      - submit\n    filenames:\n      - includes/js/scripts.js\n    classification: slightly promising\n\n  - headline: Improper Restriction of Rendered UI Layers or Frames\n    analysis: |\n      The code appears to be vulnerable to CWE-1021 Improper Restriction of Rendered UI Layers or Frames. The code does not properly restrict the rendering of certain UI elements, which could allow an attacker to inject malicious content or bypass security controls.\n    cwe: CWE-1021\n    function_names:\n      - submit\n    filenames:\n      - includes/js/scripts.js\n    classification: slightly promising\n\n  - headline: Improper Removal of Sensitive Information Before Storage or Transfer\n    analysis: |\n      The code appears to be vulnerable to CWE-212 Improper Removal of Sensitive Information Before Storage or Transfer. The code does not properly sanitize or remove sensitive information from the contact form submissions, which could lead to the exposure of sensitive data.\n    cwe: CWE-212\n    function_names:\n      - submit\n    filenames:\n      - includes/js/scripts.js\n    classification: slightly promising\n\n  - headline: Incorrect Calculation of Buffer Size\n    analysis: |\n      The code appears to be vulnerable to CWE-131 Incorrect Calculation of Buffer Size. The code may not properly calculate the size of the buffer required to hold the input values submitted in the contact form, which could lead to buffer overflow vulnerabilities.\n    cwe: CWE-131\n    function_names:\n      - initForm\n    filenames:\n      - includes/js/scripts.js\n    classification: slightly promising\n\n  - headline: Improper Handling of Case Sensitivity\n    analysis: |\n      The code appears to be vulnerable to CWE-178 Improper Handling of Case Sensitivity. The code may not properly handle case sensitivity in certain input fields, which could lead to unexpected behavior or even security vulnerabilities.\n    cwe: CWE-178\n    function_names:\n      - normalize\n    filenames:\n      - admin/js/tag-generator.js\n    classification: slightly promising\n\n  - headline: Improper Preservation of Permissions\n    analysis: |\n      The code appears to be vulnerable to CWE-281 Improper Preservation of Permissions. The code may not properly handle the preservation of permissions for certain resources, which could lead to unauthorized access or privilege escalation.\n    cwe: CWE-281\n    function_names: []\n    filenames: []\n    classification: not promising\n\n  - headline: Unchecked Return Value\n    analysis: |\n      The code appears to be vulnerable to CWE-252 Unchecked Return Value. The code may not properly check the return values of certain function calls, which could lead to unexpected behavior or even security vulnerabilities.\n    cwe: CWE-252\n    function_names:\n      - submit\n    filenames:\n      - includes/js/scripts.js\n    classification: slightly promising\n\n```",
      "date": "2024-06-09T14:40:44.470115",
      "usage": {
        "prompt_tokens": 19403,
        "completion_tokens": 2215,
        "cost": 0.0076195
      }
    }
  ],
  "leads": [
    {
      "headline": "Improper Validation of Specified Quantity in Input",
      "analysis": "The code appears to be vulnerable to CWE-1284 Improper Validation of Specified Quantity in Input. The code does not properly validate the input values for certain form fields, such as date, number, and range inputs. This could allow an attacker to provide invalid input that could lead to unexpected behavior or even crashes.\n",
      "classification": "very promising",
      "cwe": "CWE-1284",
      "function_names": [
        "initForm"
      ],
      "filenames": [
        "includes/js/scripts.js"
      ]
    },
    {
      "headline": "Improper Neutralization of Formula Elements in a CSV File",
      "analysis": "The code appears to be vulnerable to CWE-1236 Improper Neutralization of Formula Elements in a CSV File. The code does not properly sanitize the values submitted in the contact form, which could allow an attacker to inject formulas or other malicious content into the exported CSV file.\n",
      "classification": "very promising",
      "cwe": "CWE-1236",
      "function_names": [
        "submit"
      ],
      "filenames": [
        "includes/js/scripts.js"
      ]
    },
    {
      "headline": "Improper Neutralization of Special Elements used in a Command ('Command Injection')",
      "analysis": "The code appears to be vulnerable to CWE-77 Improper Neutralization of Special Elements used in a Command ('Command Injection'). The code does not properly sanitize the input values submitted in the contact form, which could allow an attacker to inject malicious commands that could be executed on the server.\n",
      "classification": "very promising",
      "cwe": "CWE-77",
      "function_names": [
        "submit"
      ],
      "filenames": [
        "includes/js/scripts.js"
      ]
    },
    {
      "headline": "Improper Neutralization of Special Elements used in an OS Command ('OS Command Injection')",
      "analysis": "The code appears to be vulnerable to CWE-78 Improper Neutralization of Special Elements used in an OS Command ('OS Command Injection'). The code does not properly sanitize the input values submitted in the contact form, which could allow an attacker to inject malicious OS commands that could be executed on the server.\n",
      "classification": "very promising",
      "cwe": "CWE-78",
      "function_names": [
        "submit"
      ],
      "filenames": [
        "includes/js/scripts.js"
      ]
    },
    {
      "headline": "Improper Neutralization of Input During Web Page Generation ('Cross-site Scripting')",
      "analysis": "The code appears to be vulnerable to CWE-79 Improper Neutralization of Input During Web Page Generation ('Cross-site Scripting'). The code does not properly sanitize the input values submitted in the contact form, which could allow an attacker to inject malicious scripts that could be executed in the victim's browser.\n",
      "classification": "very promising",
      "cwe": "CWE-79",
      "function_names": [
        "submit"
      ],
      "filenames": [
        "includes/js/scripts.js"
      ]
    },
    {
      "headline": "Improper Neutralization of Argument Delimiters in a Command ('Argument Injection')",
      "analysis": "The code appears to be vulnerable to CWE-88 Improper Neutralization of Argument Delimiters in a Command ('Argument Injection'). The code does not properly sanitize the input values submitted in the contact form, which could allow an attacker to inject malicious arguments that could be executed in the server-side command.\n",
      "classification": "very promising",
      "cwe": "CWE-88",
      "function_names": [
        "submit"
      ],
      "filenames": [
        "includes/js/scripts.js"
      ]
    },
    {
      "headline": "Improper Neutralization of Special Elements used in an SQL Command ('SQL Injection')",
      "analysis": "The code appears to be vulnerable to CWE-89 Improper Neutralization of Special Elements used in an SQL Command ('SQL Injection'). The code does not properly sanitize the input values submitted in the contact form, which could allow an attacker to inject malicious SQL commands that could be executed on the server's database.\n",
      "classification": "very promising",
      "cwe": "CWE-89",
      "function_names": [
        "submit"
      ],
      "filenames": [
        "includes/js/scripts.js"
      ]
    },
    {
      "headline": "Improper Restriction of Operations within the Bounds of a Memory Buffer",
      "analysis": "The code appears to be vulnerable to various CWEs related to Improper Restriction of Operations within the Bounds of a Memory Buffer, such as CWE-120 Buffer Copy without Checking Size of Input ('Classic Buffer Overflow'), CWE-125 Out-of-bounds Read, and CWE-787 Out-of-bounds Write. The code does not properly validate the input values submitted in the contact form, which could lead to buffer overflow vulnerabilities.\n",
      "classification": "very promising",
      "cwe": "CWE-120",
      "function_names": [
        "initForm"
      ],
      "filenames": [
        "includes/js/scripts.js"
      ]
    },
    {
      "headline": "Generation of Error Message Containing Sensitive Information",
      "analysis": "The code appears to be vulnerable to CWE-209 Generation of Error Message Containing Sensitive Information. The code does not properly handle errors and may display sensitive information in the error messages, which could be leveraged by an attacker to gain more information about the system.\n",
      "classification": "slightly promising",
      "cwe": "CWE-209",
      "function_names": [
        "submit"
      ],
      "filenames": [
        "includes/js/scripts.js"
      ]
    },
    {
      "headline": "Incorrect Usage of Seeds in Pseudo-Random Number Generator (PRNG)",
      "analysis": "The code appears to be vulnerable to CWE-335 Incorrect Usage of Seeds in Pseudo-Random Number Generator (PRNG). The code generates a random ID for the contact form, but the implementation may not be secure, potentially allowing an attacker to predict or manipulate the generated IDs.\n",
      "classification": "slightly promising",
      "cwe": "CWE-335",
      "function_names": [
        "getId"
      ],
      "filenames": [
        "includes/js/scripts.js"
      ]
    },
    {
      "headline": "Improper Validation of Integrity Check Value",
      "analysis": "The code appears to be vulnerable to CWE-354 Improper Validation of Integrity Check Value. The code does not properly validate the integrity of the data submitted in the contact form, which could allow an attacker to tamper with the data and bypass any integrity checks.\n",
      "classification": "slightly promising",
      "cwe": "CWE-354",
      "function_names": [
        "submit"
      ],
      "filenames": [
        "includes/js/scripts.js"
      ]
    },
    {
      "headline": "Improper Restriction of Rendered UI Layers or Frames",
      "analysis": "The code appears to be vulnerable to CWE-1021 Improper Restriction of Rendered UI Layers or Frames. The code does not properly restrict the rendering of certain UI elements, which could allow an attacker to inject malicious content or bypass security controls.\n",
      "classification": "slightly promising",
      "cwe": "CWE-1021",
      "function_names": [
        "submit"
      ],
      "filenames": [
        "includes/js/scripts.js"
      ]
    },
    {
      "headline": "Improper Removal of Sensitive Information Before Storage or Transfer",
      "analysis": "The code appears to be vulnerable to CWE-212 Improper Removal of Sensitive Information Before Storage or Transfer. The code does not properly sanitize or remove sensitive information from the contact form submissions, which could lead to the exposure of sensitive data.\n",
      "classification": "slightly promising",
      "cwe": "CWE-212",
      "function_names": [
        "submit"
      ],
      "filenames": [
        "includes/js/scripts.js"
      ]
    },
    {
      "headline": "Incorrect Calculation of Buffer Size",
      "analysis": "The code appears to be vulnerable to CWE-131 Incorrect Calculation of Buffer Size. The code may not properly calculate the size of the buffer required to hold the input values submitted in the contact form, which could lead to buffer overflow vulnerabilities.\n",
      "classification": "slightly promising",
      "cwe": "CWE-131",
      "function_names": [
        "initForm"
      ],
      "filenames": [
        "includes/js/scripts.js"
      ]
    },
    {
      "headline": "Improper Handling of Case Sensitivity",
      "analysis": "The code appears to be vulnerable to CWE-178 Improper Handling of Case Sensitivity. The code may not properly handle case sensitivity in certain input fields, which could lead to unexpected behavior or even security vulnerabilities.\n",
      "classification": "slightly promising",
      "cwe": "CWE-178",
      "function_names": [
        "normalize"
      ],
      "filenames": [
        "admin/js/tag-generator.js"
      ]
    },
    {
      "headline": "Improper Preservation of Permissions",
      "analysis": "The code appears to be vulnerable to CWE-281 Improper Preservation of Permissions. The code may not properly handle the preservation of permissions for certain resources, which could lead to unauthorized access or privilege escalation.\n",
      "classification": "not promising",
      "cwe": "CWE-281",
      "function_names": [],
      "filenames": []
    },
    {
      "headline": "Unchecked Return Value",
      "analysis": "The code appears to be vulnerable to CWE-252 Unchecked Return Value. The code may not properly check the return values of certain function calls, which could lead to unexpected behavior or even security vulnerabilities.\n",
      "classification": "slightly promising",
      "cwe": "CWE-252",
      "function_names": [
        "submit"
      ],
      "filenames": [
        "includes/js/scripts.js"
      ]
    }
  ],
  "scores": [
    {
      "stats": {
        "fn": 2,
        "tp": 0,
        "fp": 8
      },
      "mapping": {},
      "vuln_dates": {
        "CVE-2023-6449": "2023-12-01T11:15:08",
        "CVE-2020-35489": "2020-12-17T19:15:14"
      },
      "scoring_model": "gpt-4o-2024-05-13",
      "type": "llm",
      "instruction_template_hash": "8998f09cf57fca8a6e03"
    },
    {
      "stats": {
        "fn": 2,
        "tp": 0,
        "fp": 8
      },
      "mapping": {},
      "vuln_dates": {
        "CVE-2023-6449": "2023-12-01T11:15:08",
        "CVE-2020-35489": "2020-12-17T19:15:14"
      },
      "scoring_model": "claude-3-opus-20240229",
      "type": "llm",
      "instruction_template_hash": "245ace12b6361954d0a2"
    },
    {
      "stats": {
        "fn": 2,
        "tp": 0,
        "fp": 8
      },
      "mapping": {},
      "vuln_dates": {
        "CVE-2023-6449": "2023-12-01T11:15:08",
        "CVE-2020-35489": "2020-12-17T19:15:14"
      },
      "scoring_model": "claude-3-5-sonnet-20240620",
      "type": "llm",
      "instruction_template_hash": "245ace12b6361954d0a2"
    }
  ],
  "instruction_template_hash": "10c0163db4740318a544",
  "version": "0.1.0"
}
