{
  "commit": "f452f13f118a5a1650cc0fae824695f90751f5bf",
  "repo_url": "https://github.com/jenkinsci/teams-webhook-trigger-plugin",
  "model": "gpt-4-turbo-2024-04-09",
  "chunk_hashes": [
    "382f11e78cd790292a08"
  ],
  "responses": [
    {
      "content": "```yaml\nleads:\n  - headline: Insecure cryptographic algorithm used\n    analysis: |\n      The HMAC verification relies on a choice between three cryptographic algorithms: HMAC-MD5, HMAC-SHA1, and HMAC-SHA256, a method defined in `WhitelistAlgorithm`. Given that both HMAC-MD5 and HMAC-SHA1 are known to have vulnerabilities and are considered cryptographically broken, their use might allow an attacker to spoof HMAC values if collision vulnerabilities are exploited.\n    cwe: CWE-327\n    function_names:\n      - hmacVerify\n    filenames:\n      - src/main/java/org/jenkinsci/plugins/teamstrigger/whitelist/HMACVerifier.java\n      - src/main/java/org/jenkinsci/plugins/teamstrigger/global/WhitelistAlgorithm.java\n    classification: slightly promising\n\n  - headline: Missing host header validation allows for web cache poisoning\n    analysis: |\n      In 'GenericWebHookRequestReceiver.java', the host header is not validated when constructing responses with headers inside `doInvoke`. This can allow an attacker to manipulate the host header sent in HTTP requests to the Jenkins instance, potentially poisoning web caches and conducting further attacks such as password reset poisoning or impacting the integrity of cached pages. \n    cwe: CWE-444\n    function_names:\n      - doInvoke\n    filenames:\n      - src/main/java/org/jenkinsci/plugins/teamstrigger/GenericWebHookRequestReceiver.java\n    classification: very promising\n\n  - headline: Token leakage through error messages\n    analysis: |\n      In the class 'WhitelistException', which is used in several parts of the application, detailed error messages include sensitive information about why certain whitelist verification processes fail. These detailed messages are then used in client-facing error responses, potentially leaking sensitive configuration details or token information which could help an attacker refine further attacks.\n    cwe: CWE-209\n    function_names:\n      - WhitelistException\n    filenames:\n      - src/main/java/org/jenkinsci/plugins/teamstrigger/whitelist/WhitelistException.java\n    classification: slightly promising\n\n  - headline: Server-Side Request Forgery (SSRF) in GenericWebHookRequestReceiver\n    analysis: |\n      The method `doInvoke` in `GenericWebHookRequestReceiver.java` processes incoming HTTP requests and forwards them after some processing. Since there is no restriction on the URLs that can be requested, an attacker could potentially cause the server to interact with arbitrary external systems. This could be exploited to interact with unexpected services via SSRF.\n    cwe: CWE-918\n    function_names:\n      - doInvoke\n    filenames:\n      - src/main/java/org/jenkinsci/plugins/teamstrigger/GenericWebHookRequestReceiver.java\n    classification: slightly promising\n\n  - headline: Lack of proper input validation in regular expression handling\n    analysis: |\n      In `Renderer.java`, user input is directly utilized to create regular expressions without adequate validation. This could lead to inefficient regular expressions that cause a Denial of Service (DoS) condition through excessive CPU utilization, commonly known as Regular Expression Denial of Service (ReDoS).\n    cwe: CWE-1333\n    function_names:\n      - isMatching\n      - renderText\n    filenames:\n      - src/main/java/org/jenkinsci/plugins/teamstrigger/Renderer.java\n    classification: slightly promising\n\n  - headline: Improper access control leads to unauthorized actions\n    analysis: |\n      In 'JobFinder.java', the method `findAllJobsWithTrigger` indirectly grants high privileges by allowing job triggers without proper authorization checks. This could potentially allow unauthorized users to trigger jobs if the security settings of Jenkins are misconfigured or if there are other failures in the access control logic, leading to unauthorized code execution or information disclosure.\n    cwe: CWE-284\n    function_names:\n      - findAllJobsWithTrigger\n    filenames:\n      - src/main/java/org/jenkinsci/plugins/teamstrigger/jobfinder/JobFinder.java\n    classification: slightly promising\n\n```",
      "date": "2024-06-09T12:54:57.551668",
      "usage": {
        "prompt_tokens": 39657,
        "completion_tokens": 817,
        "cost": 0.42108
      }
    }
  ],
  "leads": [
    {
      "headline": "Insecure cryptographic algorithm used",
      "analysis": "The HMAC verification relies on a choice between three cryptographic algorithms: HMAC-MD5, HMAC-SHA1, and HMAC-SHA256, a method defined in WhitelistAlgorithm. Given that both HMAC-MD5 and HMAC-SHA1 are known to have vulnerabilities and are considered cryptographically broken, their use might allow an attacker to spoof HMAC values if collision vulnerabilities are exploited.\n",
      "classification": "slightly promising",
      "cwe": "CWE-327",
      "function_names": [
        "hmacVerify"
      ],
      "filenames": [
        "src/main/java/org/jenkinsci/plugins/teamstrigger/whitelist/HMACVerifier.java",
        "src/main/java/org/jenkinsci/plugins/teamstrigger/global/WhitelistAlgorithm.java"
      ]
    },
    {
      "headline": "Missing host header validation allows for web cache poisoning",
      "analysis": "In 'GenericWebHookRequestReceiver.java', the host header is not validated when constructing responses with headers inside doInvoke. This can allow an attacker to manipulate the host header sent in HTTP requests to the Jenkins instance, potentially poisoning web caches and conducting further attacks such as password reset poisoning or impacting the integrity of cached pages. \n",
      "classification": "very promising",
      "cwe": "CWE-444",
      "function_names": [
        "doInvoke"
      ],
      "filenames": [
        "src/main/java/org/jenkinsci/plugins/teamstrigger/GenericWebHookRequestReceiver.java"
      ]
    },
    {
      "headline": "Token leakage through error messages",
      "analysis": "In the class 'WhitelistException', which is used in several parts of the application, detailed error messages include sensitive information about why certain whitelist verification processes fail. These detailed messages are then used in client-facing error responses, potentially leaking sensitive configuration details or token information which could help an attacker refine further attacks.\n",
      "classification": "slightly promising",
      "cwe": "CWE-209",
      "function_names": [
        "WhitelistException"
      ],
      "filenames": [
        "src/main/java/org/jenkinsci/plugins/teamstrigger/whitelist/WhitelistException.java"
      ]
    },
    {
      "headline": "Server-Side Request Forgery (SSRF) in GenericWebHookRequestReceiver",
      "analysis": "The method doInvoke in GenericWebHookRequestReceiver.java processes incoming HTTP requests and forwards them after some processing. Since there is no restriction on the URLs that can be requested, an attacker could potentially cause the server to interact with arbitrary external systems. This could be exploited to interact with unexpected services via SSRF.\n",
      "classification": "slightly promising",
      "cwe": "CWE-918",
      "function_names": [
        "doInvoke"
      ],
      "filenames": [
        "src/main/java/org/jenkinsci/plugins/teamstrigger/GenericWebHookRequestReceiver.java"
      ]
    },
    {
      "headline": "Lack of proper input validation in regular expression handling",
      "analysis": "In Renderer.java, user input is directly utilized to create regular expressions without adequate validation. This could lead to inefficient regular expressions that cause a Denial of Service (DoS) condition through excessive CPU utilization, commonly known as Regular Expression Denial of Service (ReDoS).\n",
      "classification": "slightly promising",
      "cwe": "CWE-1333",
      "function_names": [
        "isMatching",
        "renderText"
      ],
      "filenames": [
        "src/main/java/org/jenkinsci/plugins/teamstrigger/Renderer.java"
      ]
    },
    {
      "headline": "Improper access control leads to unauthorized actions",
      "analysis": "In 'JobFinder.java', the method findAllJobsWithTrigger indirectly grants high privileges by allowing job triggers without proper authorization checks. This could potentially allow unauthorized users to trigger jobs if the security settings of Jenkins are misconfigured or if there are other failures in the access control logic, leading to unauthorized code execution or information disclosure.\n",
      "classification": "slightly promising",
      "cwe": "CWE-284",
      "function_names": [
        "findAllJobsWithTrigger"
      ],
      "filenames": [
        "src/main/java/org/jenkinsci/plugins/teamstrigger/jobfinder/JobFinder.java"
      ]
    }
  ],
  "scores": [
    {
      "stats": {
        "fn": 1,
        "tp": 0,
        "fp": 1
      },
      "mapping": {},
      "vuln_dates": {
        "CVE-2023-46658": "2023-10-25T18:17:40"
      },
      "scoring_model": "gpt-4o-2024-05-13",
      "type": "llm",
      "instruction_template_hash": "8998f09cf57fca8a6e03"
    }
  ],
  "instruction_template_hash": "10c0163db4740318a544",
  "version": "0.1.0"
}
