{
  "commit": "44e2ed17df95ea510340984a6efa9f11169e675f",
  "repo_url": "https://github.com/jenkinsci/zap-pipeline-plugin",
  "model": "gpt-4o-2024-05-13",
  "chunk_hashes": [
    "beb9182b6a7f950195a7"
  ],
  "responses": [
    {
      "content": "```yaml\nleads:\n  - headline: \"Potential Improper Output Encoding in TaskListenerStub\"\n    analysis: |\n      The `getLogger` method in `TaskListenerStub` returns a `PrintStream` that prints directly to System.out. This can be a security concern in web applications, as it doesn't encode or sanitize output, potentially leading to XSS vulnerabilities when printing user input to logs or other outputs that could be rendered in the browser.\n    cwe: CWE-116\n    function_names:\n      - \"getLogger\"\n    filenames:\n      - \"src/test/java/com/vrondakis/zap/TaskListenerStub.java\"\n    classification: \"slightly promising\"\n\n  - headline: \"Potential Security Misconfiguration in ZapDriverImpl\"\n    analysis: |\n      The `startZapProcess` method in `ZapDriverImpl` includes command line options \\(cmd\\) for starting ZAP, but uses hardcoded, potentially insecure settings like disabling the API key via `api.disablekey=true` and allowing uncontrolled access via regex.\n    cwe: CWE-1188\n    function_names:\n      - \"startZapProcess\"\n    filenames:\n      - \"src/main/java/com/vrondakis/zap/ZapDriverImpl.java\"\n    classification: \"slightly promising\"\n\n  - headline: \"Potential Hardcoded Credentials in ZapDriverImpl\"\n    analysis: |\n      The `startZapProcess` method in `ZapDriverImpl` uses the flag `api.disablekey=true`, which could potentially disable API key checks allowing unauthorized access to the ZAP instance if not handled correctly.\n    cwe: CWE-798\n    function_names:\n      - \"startZapProcess\"\n    filenames:\n      - \"src/main/java/com/vrondakis/zap/ZapDriverImpl.java\"\n    classification: \"very promising\"\n\n  - headline: \"Cleartext Transmission of Sensitive Information in ZapDriverImpl\"\n    analysis: |\n      The `getZapReport` and `getZapReportXML` methods in `ZapDriverImpl` retrieve ZAP reports via HTTP, without encryption. This could expose sensitive data during transmission.\n    cwe: CWE-319\n    function_names:\n      - \"getZapReport\"\n      - \"getZapReportXML\"\n    filenames:\n      - \"src/main/java/com/vrondakis/zap/ZapDriverImpl.java\"\n    classification: \"slightly promising\"\n\n  - headline: \"Possible Insecure Randomness in ZapDriverController\"\n    analysis: |\n      The `zapDrivers` HashMap in `ZapDriverController` stores instances of `ZapDriver` using URLs as keys. If these URLs are derived from user inputs without validation, it could lead to collisions or predictability in chosen instances.\n    cwe: CWE-330\n    function_names:\n      - \"newDriver\"\n    filenames:\n      - \"src/main/java/com/vrondakis/zap/ZapDriverController.java\"\n    classification: \"slightly promising\"\n\n  - headline: \"Use of Insufficiently Protected Credentials in ZapDriverImpl\"\n    analysis: |\n      Methods in `ZapDriverImpl` such as `setZapHost`, `setZapPort`, and `setFailBuild` store potentially sensitive information in memory without encryption or protection mechanisms.\n    cwe: CWE-522\n    function_names:\n      - \"setZapHost\"\n      - \"setZapPort\"\n      - \"setFailBuild\"\n    filenames:\n      - \"src/main/java/com/vrondakis/zap/ZapDriverImpl.java\"\n    classification: \"slightly promising\"\n\n  - headline: \"Improper Validation of Integrity Check Value in ImportZapUrlsExecution\"\n    analysis: |\n      The `start` method in `ImportZapUrlsExecution` does not validate the contents of the URLs file being imported. Malicious URLs could affect the ZAP scan or the application being tested.\n    cwe: CWE-354\n    function_names:\n      - \"start\"\n    filenames:\n      - \"src/main/java/com/vrondakis/zap/workflow/ImportZapUrlsExecution.java\"\n    classification: \"very promising\"\n```",
      "date": "2024-06-14T14:29:02.991158",
      "usage": {
        "prompt_tokens": 32458,
        "completion_tokens": 837,
        "cost": 0.174845
      }
    }
  ],
  "leads": [
    {
      "headline": "Potential Improper Output Encoding in TaskListenerStub",
      "analysis": "The getLogger method in TaskListenerStub returns a PrintStream that prints directly to System.out. This can be a security concern in web applications, as it doesn't encode or sanitize output, potentially leading to XSS vulnerabilities when printing user input to logs or other outputs that could be rendered in the browser.\n",
      "classification": "slightly promising",
      "cwe": "CWE-116",
      "function_names": [
        "getLogger"
      ],
      "filenames": [
        "src/test/java/com/vrondakis/zap/TaskListenerStub.java"
      ]
    },
    {
      "headline": "Potential Security Misconfiguration in ZapDriverImpl",
      "analysis": "The startZapProcess method in ZapDriverImpl includes command line options \\(cmd\\) for starting ZAP, but uses hardcoded, potentially insecure settings like disabling the API key via api.disablekey=true and allowing uncontrolled access via regex.\n",
      "classification": "slightly promising",
      "cwe": "CWE-1188",
      "function_names": [
        "startZapProcess"
      ],
      "filenames": [
        "src/main/java/com/vrondakis/zap/ZapDriverImpl.java"
      ]
    },
    {
      "headline": "Potential Hardcoded Credentials in ZapDriverImpl",
      "analysis": "The startZapProcess method in ZapDriverImpl uses the flag api.disablekey=true, which could potentially disable API key checks allowing unauthorized access to the ZAP instance if not handled correctly.\n",
      "classification": "very promising",
      "cwe": "CWE-798",
      "function_names": [
        "startZapProcess"
      ],
      "filenames": [
        "src/main/java/com/vrondakis/zap/ZapDriverImpl.java"
      ]
    },
    {
      "headline": "Cleartext Transmission of Sensitive Information in ZapDriverImpl",
      "analysis": "The getZapReport and getZapReportXML methods in ZapDriverImpl retrieve ZAP reports via HTTP, without encryption. This could expose sensitive data during transmission.\n",
      "classification": "slightly promising",
      "cwe": "CWE-319",
      "function_names": [
        "getZapReport",
        "getZapReportXML"
      ],
      "filenames": [
        "src/main/java/com/vrondakis/zap/ZapDriverImpl.java"
      ]
    },
    {
      "headline": "Possible Insecure Randomness in ZapDriverController",
      "analysis": "The zapDrivers HashMap in ZapDriverController stores instances of ZapDriver using URLs as keys. If these URLs are derived from user inputs without validation, it could lead to collisions or predictability in chosen instances.\n",
      "classification": "slightly promising",
      "cwe": "CWE-330",
      "function_names": [
        "newDriver"
      ],
      "filenames": [
        "src/main/java/com/vrondakis/zap/ZapDriverController.java"
      ]
    },
    {
      "headline": "Use of Insufficiently Protected Credentials in ZapDriverImpl",
      "analysis": "Methods in ZapDriverImpl such as setZapHost, setZapPort, and setFailBuild store potentially sensitive information in memory without encryption or protection mechanisms.\n",
      "classification": "slightly promising",
      "cwe": "CWE-522",
      "function_names": [
        "setZapHost",
        "setZapPort",
        "setFailBuild"
      ],
      "filenames": [
        "src/main/java/com/vrondakis/zap/ZapDriverImpl.java"
      ]
    },
    {
      "headline": "Improper Validation of Integrity Check Value in ImportZapUrlsExecution",
      "analysis": "The start method in ImportZapUrlsExecution does not validate the contents of the URLs file being imported. Malicious URLs could affect the ZAP scan or the application being tested.\n",
      "classification": "very promising",
      "cwe": "CWE-354",
      "function_names": [
        "start"
      ],
      "filenames": [
        "src/main/java/com/vrondakis/zap/workflow/ImportZapUrlsExecution.java"
      ]
    }
  ],
  "scores": [
    {
      "stats": {
        "fn": 1,
        "tp": 0,
        "fp": 2
      },
      "mapping": {},
      "vuln_dates": {
        "CVE-2020-2214": "2020-07-02T15:15:18"
      },
      "scoring_model": "claude-3-opus-20240229",
      "type": "llm",
      "instruction_template_hash": "245ace12b6361954d0a2"
    },
    {
      "stats": {
        "fn": 1,
        "tp": 0,
        "fp": 2
      },
      "mapping": {},
      "vuln_dates": {
        "CVE-2020-2214": "2020-07-02T15:15:18"
      },
      "scoring_model": "claude-3-5-sonnet-20240620",
      "type": "llm",
      "instruction_template_hash": "245ace12b6361954d0a2"
    }
  ],
  "instruction_template_hash": "10c0163db4740318a544",
  "version": "0.1.0"
}
