{
  "commit": "202b40adccc6b22fb362a816bce7c159664e098c",
  "repo_url": "https://github.com/jenkinsci/build-pipeline-plugin",
  "model": "gpt-4o-2024-05-13",
  "chunk_hashes": [
    "8452987b2d95fd2def08"
  ],
  "responses": [
    {
      "content": "```yaml\nleads:\n  - headline: Improper Validation of Specific Quantities in Input \n    analysis: |\n      The method `calculatePercentage` in `PipelineBuildTest` class fails to validate whether the second parameter `estimatedDuration` is zero before performing a division. This allows for potential divide-by-zero errors that can cause unexpected crashes or behaviors when estimatedDuration is zero.\n    cwe: CWE-369\n    function_names:\n      - calculatePercentage\n    filenames:\n      - src/test/java/au/com/centrumsystems/hudson/plugin/buildpipeline/PipelineBuildTest.java\n    classification: very promising\n\n  - headline: Reliance on Cookies without Validation and Integrity Checking\n    analysis: |\n      In the `rerunBuild` method in the `BuildCardExtension` class, the retrigger logic reuses the Causes from a previous build without ensuring these causes are still valid or have not been tampered with. This reliance on previously captured data without validation can introduce vulnerabilities where an unauthorized or modified cause is used.\n    cwe: CWE-565\n    function_names:\n      - rerunBuild\n    filenames:\n      - src/main/java/au/com/centrumsystems/hudson/plugin/buildpipeline/extension/BuildCardExtension.java\n    classification: slightly promising\n\n  - headline: Cleartext Transmission of Sensitive Information\n    analysis: |\n      In the `getUnsensitiveParameters` method in the `BuildUtil` class, sensitive information (like passwords) is merely masked and removed from the map, but other parameters are returned in cleartext. Depending on where this map is used or transmitted, this could expose sensitive operational details.\n    cwe: CWE-319\n    function_names:\n      - getUnsensitiveParameters\n    filenames:\n      - src/main/java/au/com/centrumsystems/hudson/plugin/util/BuildUtil.java\n    classification: slightly promising\n\n  - headline: Insecure Handling of Sensitive Information in Logs\n    analysis: |\n      The `BuildPipelineTrigger.DescriptorImpl` logs sensitive information (downstream project names) during the onDelete and onRename operations without sanitization. This could lead to exposure of project configurations through logs.\n    cwe: CWE-532\n    function_names:\n      - onRenamed\n      - onDeleted\n    filenames:\n      - src/main/java/au/com/centrumsystems/hudson/plugin/buildpipeline/trigger/BuildPipelineTrigger.java\n    classification: very promising\n\n  - headline: Incorrect Permission Assignment for Critical Resource\n    analysis: |\n      The method `hasBuildPermission` in the `BuildPipelineView` class allows determining if there is a general build permission check by any user for triggering builds, rather than checking specific user permissions in Jenkins, potentially allowing unauthorized users to initiate build processes.\n    cwe: CWE-732\n    function_names:\n      - hasBuildPermission\n    filenames:\n      - src/main/java/au/com/centrumsystems/hudson/plugin/buildpipeline/BuildPipelineView.java\n    classification: very promising\n```",
      "date": "2024-06-12T17:59:51.511319",
      "usage": {
        "prompt_tokens": 93554,
        "completion_tokens": 622,
        "cost": 0.4771
      }
    }
  ],
  "leads": [
    {
      "headline": "Improper Validation of Specific Quantities in Input",
      "analysis": "The method calculatePercentage in PipelineBuildTest class fails to validate whether the second parameter estimatedDuration is zero before performing a division. This allows for potential divide-by-zero errors that can cause unexpected crashes or behaviors when estimatedDuration is zero.\n",
      "classification": "very promising",
      "cwe": "CWE-369",
      "function_names": [
        "calculatePercentage"
      ],
      "filenames": [
        "src/test/java/au/com/centrumsystems/hudson/plugin/buildpipeline/PipelineBuildTest.java"
      ]
    },
    {
      "headline": "Reliance on Cookies without Validation and Integrity Checking",
      "analysis": "In the rerunBuild method in the BuildCardExtension class, the retrigger logic reuses the Causes from a previous build without ensuring these causes are still valid or have not been tampered with. This reliance on previously captured data without validation can introduce vulnerabilities where an unauthorized or modified cause is used.\n",
      "classification": "slightly promising",
      "cwe": "CWE-565",
      "function_names": [
        "rerunBuild"
      ],
      "filenames": [
        "src/main/java/au/com/centrumsystems/hudson/plugin/buildpipeline/extension/BuildCardExtension.java"
      ]
    },
    {
      "headline": "Cleartext Transmission of Sensitive Information",
      "analysis": "In the getUnsensitiveParameters method in the BuildUtil class, sensitive information (like passwords) is merely masked and removed from the map, but other parameters are returned in cleartext. Depending on where this map is used or transmitted, this could expose sensitive operational details.\n",
      "classification": "slightly promising",
      "cwe": "CWE-319",
      "function_names": [
        "getUnsensitiveParameters"
      ],
      "filenames": [
        "src/main/java/au/com/centrumsystems/hudson/plugin/util/BuildUtil.java"
      ]
    },
    {
      "headline": "Insecure Handling of Sensitive Information in Logs",
      "analysis": "The BuildPipelineTrigger.DescriptorImpl logs sensitive information (downstream project names) during the onDelete and onRename operations without sanitization. This could lead to exposure of project configurations through logs.\n",
      "classification": "very promising",
      "cwe": "CWE-532",
      "function_names": [
        "onRenamed",
        "onDeleted"
      ],
      "filenames": [
        "src/main/java/au/com/centrumsystems/hudson/plugin/buildpipeline/trigger/BuildPipelineTrigger.java"
      ]
    },
    {
      "headline": "Incorrect Permission Assignment for Critical Resource",
      "analysis": "The method hasBuildPermission in the BuildPipelineView class allows determining if there is a general build permission check by any user for triggering builds, rather than checking specific user permissions in Jenkins, potentially allowing unauthorized users to initiate build processes.\n",
      "classification": "very promising",
      "cwe": "CWE-732",
      "function_names": [
        "hasBuildPermission"
      ],
      "filenames": [
        "src/main/java/au/com/centrumsystems/hudson/plugin/buildpipeline/BuildPipelineView.java"
      ]
    }
  ],
  "scores": [
    {
      "stats": {
        "fn": 1,
        "tp": 0,
        "fp": 3
      },
      "mapping": {},
      "vuln_dates": {
        "CVE-2019-10373": "2019-08-07T15:15:12"
      },
      "scoring_model": "claude-3-opus-20240229",
      "type": "llm",
      "instruction_template_hash": "245ace12b6361954d0a2"
    }
  ],
  "instruction_template_hash": "10c0163db4740318a544",
  "version": "0.1.0"
}
