{
  "commit": "24b3fd3309d1057dd87af3a568def0db01dbaade",
  "repo_url": "https://github.com/validatorjs/validator.js",
  "model": "gpt-4-turbo-2024-04-09",
  "chunk_hashes": [
    "7fbab1fa9eef83356392"
  ],
  "responses": [
    {
      "content": "```yaml\nleads:\n  - headline: \"Insecure Dependency Handling in build-browser.js\"\n    analysis: |\n      The code imports several external libraries/modules such as fs, rollup-plugin-babel, and others. The version of the babel preset (@babel/preset-env) is not pinned, leading to potential inclusion of unvetted updates. Lack of package lock or strict versioning threatens the integrity and reliability of the build process by allowing for the execution of non-validated code.\n    cwe: CWE-829\n    function_names: [\"rollup\"]\n    filenames:\n      - \"build-browser.js\"\n    classification: \"very promising\"\n\n  - headline: \"License File Exposure in build-browser.js\"\n    analysis: |\n      The source code reads the content of the LICENSE file and inserts it into the built JavaScript files as a comment. This file could contain sensitive metadata or comments unintended for public release, posing a risk if the file is not sanitized or if sensitive information is not removed before deployment.\n    cwe: CWE-200\n    function_names: []\n    filenames:\n      - \"build-browser.js\"\n    classification: \"slightly promising\"\n\n  - headline: \"Potential Path Traversal in src/lib/whitelist.js and src/lib/blacklist.js\"\n    analysis: |\n      The whitelist and blacklist functions do not properly sanitize inputs before processing, allowing for potential exploitation through malicious input that could manipulate the behavior of the regex used for validating inputs. This could lead to unauthorized access or denial of service if special characters are used to break out of the restricted patterns.\n    cwe: CWE-22\n    function_names: [\"whitelist\", \"blacklist\"]\n    filenames:\n      - \"src/lib/wholesale.js\"\n      - \"src/lib/blacklist.js\"\n    classification: \"very promising\"\n\n  - headline: \"Regex Denial of Service in isHSL in src/lib/isHSL.js\"\n    analysis: |\n      The function uses complex regular expressions that may be susceptible to regex denial of service (ReDoS) if given specially crafted inputs. This could potentially be exploited by an attacker to cause excessive CPU utilization, leading to slower processing and potential denial of service.\n    cwe: CWE-1333\n    function_names: [\"isHSL\"]\n    filenames:\n      - \"src/lib/isHSL.js\"\n    classification: \"very promising\"\n\n  - headline: \"Improper Neutralization of Input During Web Page Generation in src/lib/escape.js and src/lib/unescape.js\"\n    analysis: |\n      The escape and unescape functions manipulate strings meant for HTML content without adequately ensuring that inputs are sanitized against persistent XSS attacks, potentially allowing an attacker to inject executable scripts through the web interface.\n    cwe: CWE-79\n    function_names: [\"escape\", \"unescape\"]\n    filenames:\n      - \"src/lib/escape.js\"\n      - \"src/lib/unescape.js\"\n    classification: \"very promising\"\n```",
      "date": "2024-06-13T17:25:50.461310",
      "usage": {
        "prompt_tokens": 62107,
        "completion_tokens": 602,
        "cost": 0.63913
      }
    }
  ],
  "leads": [
    {
      "headline": "Insecure Dependency Handling in build-browser.js",
      "analysis": "The code imports several external libraries/modules such as fs, rollup-plugin-babel, and others. The version of the babel preset (@babel/preset-env) is not pinned, leading to potential inclusion of unvetted updates. Lack of package lock or strict versioning threatens the integrity and reliability of the build process by allowing for the execution of non-validated code.\n",
      "classification": "very promising",
      "cwe": "CWE-829",
      "function_names": [
        "rollup"
      ],
      "filenames": [
        "build-browser.js"
      ]
    },
    {
      "headline": "License File Exposure in build-browser.js",
      "analysis": "The source code reads the content of the LICENSE file and inserts it into the built JavaScript files as a comment. This file could contain sensitive metadata or comments unintended for public release, posing a risk if the file is not sanitized or if sensitive information is not removed before deployment.\n",
      "classification": "slightly promising",
      "cwe": "CWE-200",
      "function_names": [],
      "filenames": [
        "build-browser.js"
      ]
    },
    {
      "headline": "Potential Path Traversal in src/lib/whitelist.js and src/lib/blacklist.js",
      "analysis": "The whitelist and blacklist functions do not properly sanitize inputs before processing, allowing for potential exploitation through malicious input that could manipulate the behavior of the regex used for validating inputs. This could lead to unauthorized access or denial of service if special characters are used to break out of the restricted patterns.\n",
      "classification": "very promising",
      "cwe": "CWE-22",
      "function_names": [
        "whitelist",
        "blacklist"
      ],
      "filenames": [
        "src/lib/wholesale.js",
        "src/lib/blacklist.js"
      ]
    },
    {
      "headline": "Regex Denial of Service in isHSL in src/lib/isHSL.js",
      "analysis": "The function uses complex regular expressions that may be susceptible to regex denial of service (ReDoS) if given specially crafted inputs. This could potentially be exploited by an attacker to cause excessive CPU utilization, leading to slower processing and potential denial of service.\n",
      "classification": "very promising",
      "cwe": "CWE-1333",
      "function_names": [
        "isHSL"
      ],
      "filenames": [
        "src/lib/isHSL.js"
      ]
    },
    {
      "headline": "Improper Neutralization of Input During Web Page Generation in src/lib/escape.js and src/lib/unescape.js",
      "analysis": "The escape and unescape functions manipulate strings meant for HTML content without adequately ensuring that inputs are sanitized against persistent XSS attacks, potentially allowing an attacker to inject executable scripts through the web interface.\n",
      "classification": "very promising",
      "cwe": "CWE-79",
      "function_names": [
        "escape",
        "unescape"
      ],
      "filenames": [
        "src/lib/escape.js",
        "src/lib/unescape.js"
      ]
    }
  ],
  "scores": [
    {
      "stats": {
        "fn": 0,
        "tp": 1,
        "fp": 3
      },
      "mapping": {
        "2": "CVE-2021-3765"
      },
      "vuln_dates": {
        "CVE-2021-3765": "2021-11-02T07:15:07"
      },
      "scoring_model": "claude-3-opus-20240229",
      "type": "llm",
      "instruction_template_hash": "245ace12b6361954d0a2"
    }
  ],
  "instruction_template_hash": "10c0163db4740318a544",
  "version": "0.1.0"
}
