{
  "commit": "3f09a47887e25c5056a4e434d7558d4542bf049b",
  "repo_url": "https://github.com/dcit/perl-crypt-jwt",
  "model": "gpt-4o-2024-05-13",
  "chunk_hashes": [
    "9acc2d1641def2752823"
  ],
  "responses": [
    {
      "content": "```yaml\nleads:\n  - headline: Potential Allocation of Resources Without Limits\n    analysis: |\n      The `encode_jwt` function allows the generation of tokens with an uncapped size. Specifically, allowing uncompressed payloads in JSON could facilitate potential Denial of Service attacks through the generation of excessively large payloads, consuming significant memory.\n    cwe: CWE-770\n    function_names:\n      - encode_jwt\n    filenames:\n      - lib/Crypt/JWT.pm\n    classification: very promising\n\n  - headline: Insufficient Session Expiration\n    analysis: |\n      There is no clear indication of setting a maximum session expiration time within the JWT. If the 'exp' claim is missing, a JWT could potentially stay valid indefinitely. This might allow unauthorized access even long after a user's session should have expired.\n    cwe: CWE-613\n    function_names:\n      - decode_jwt\n    filenames:\n      - lib/Crypt/JWT.pm\n    classification: slightly promising\n\n  - headline: Potential Improper Check for Dropped Privileges\n    analysis: |\n      The `_prepare_*_key` functions do not sufficiently validate keys or check for compromised or revoked keys, raising potential risks if a compromised key is retained in memory or fails to be properly dropped.\n    cwe: CWE-273\n    function_names:\n      - _prepare_rsa_key\n      - _prepare_ecc_key\n      - _prepare_oct_key\n    filenames:\n      - lib/Crypt/JWT.pm\n    classification: slightly promising\n\n  - headline: Improper Verification of Cryptographic Signature\n    analysis: |\n      The functions utilize string comparisons for verifying cryptographic signatures, which might be vulnerable to timing attacks. Using constant-time string comparison would mitigate this issue, providing stronger assurance against attacks.\n    cwe: CWE-347\n    function_names:\n      - _verify_jws\n    filenames:\n      - lib/Crypt/JWT.pm\n    classification: slightly promising\n\n  - headline: Insufficient Entropy for JWT ID\n    analysis: |\n      JWT IDs (`jti`) are used for preventing replay attacks. However, it's crucial that the JWT ID is generated with sufficient entropy to prevent potential prediction attacks that might jeopardize the security.\n    cwe: CWE-331\n    function_names:\n      - _add_claims\n    filenames:\n      - lib/Crypt/JWT.pm\n    classification: slightly promising\n\n  - headline: Exposure of Sensitive Information to Unauthorized Actors\n    analysis: |\n      The error handling and logging mechanisms may expose sensitive information about the cryptographic operations, especially on failure. This information could be exploited by attackers for further vulnerabilities.\n    cwe: CWE-209\n    function_names:\n      - decode_jwt\n    filenames:\n      - lib/Crypt/JWT.pm\n    classification: slightly promising\n\n  - headline: Cleartext Transmission of Sensitive Information\n    analysis: |\n      The functions handling key and payload do not enforce secure transmission protocols or encryption of sensitive data within their constraints. This could lead to sensitive information being transferred in cleartext over unsecured channels.\n    cwe: CWE-319\n    function_names:\n      - _encrypt_jwe_payload\n      - _decrypt_jwe_payload\n    filenames:\n      - lib/Crypt/JWT.pm\n    classification: slightly promising\n\n  - headline: Hardcoded Passwords in the Codebase\n    analysis: |\n      There are instances where keyword arguments receive hardcoded passwords, especially within test suites. This practice poses significant risk if similar practices are used in the main codebase, potentially leading to hardcoded keys or credentials.\n    cwe: CWE-798\n    function_names:\n      - encode_jwt\n      - decode_jwt\n    filenames:\n      - t/jwt_params.t\n      - t/jwt_encode_decode.t\n    classification: slightly promising\n```",
      "date": "2024-06-14T13:15:47.800169",
      "usage": {
        "prompt_tokens": 95388,
        "completion_tokens": 789,
        "cost": 0.488775
      }
    }
  ],
  "leads": [
    {
      "headline": "Potential Allocation of Resources Without Limits",
      "analysis": "The encode_jwt function allows the generation of tokens with an uncapped size. Specifically, allowing uncompressed payloads in JSON could facilitate potential Denial of Service attacks through the generation of excessively large payloads, consuming significant memory.\n",
      "classification": "very promising",
      "cwe": "CWE-770",
      "function_names": [
        "encode_jwt"
      ],
      "filenames": [
        "lib/Crypt/JWT.pm"
      ]
    },
    {
      "headline": "Insufficient Session Expiration",
      "analysis": "There is no clear indication of setting a maximum session expiration time within the JWT. If the 'exp' claim is missing, a JWT could potentially stay valid indefinitely. This might allow unauthorized access even long after a user's session should have expired.\n",
      "classification": "slightly promising",
      "cwe": "CWE-613",
      "function_names": [
        "decode_jwt"
      ],
      "filenames": [
        "lib/Crypt/JWT.pm"
      ]
    },
    {
      "headline": "Potential Improper Check for Dropped Privileges",
      "analysis": "The _prepare_*_key functions do not sufficiently validate keys or check for compromised or revoked keys, raising potential risks if a compromised key is retained in memory or fails to be properly dropped.\n",
      "classification": "slightly promising",
      "cwe": "CWE-273",
      "function_names": [
        "_prepare_rsa_key",
        "_prepare_ecc_key",
        "_prepare_oct_key"
      ],
      "filenames": [
        "lib/Crypt/JWT.pm"
      ]
    },
    {
      "headline": "Improper Verification of Cryptographic Signature",
      "analysis": "The functions utilize string comparisons for verifying cryptographic signatures, which might be vulnerable to timing attacks. Using constant-time string comparison would mitigate this issue, providing stronger assurance against attacks.\n",
      "classification": "slightly promising",
      "cwe": "CWE-347",
      "function_names": [
        "_verify_jws"
      ],
      "filenames": [
        "lib/Crypt/JWT.pm"
      ]
    },
    {
      "headline": "Insufficient Entropy for JWT ID",
      "analysis": "JWT IDs (jti) are used for preventing replay attacks. However, it's crucial that the JWT ID is generated with sufficient entropy to prevent potential prediction attacks that might jeopardize the security.\n",
      "classification": "slightly promising",
      "cwe": "CWE-331",
      "function_names": [
        "_add_claims"
      ],
      "filenames": [
        "lib/Crypt/JWT.pm"
      ]
    },
    {
      "headline": "Exposure of Sensitive Information to Unauthorized Actors",
      "analysis": "The error handling and logging mechanisms may expose sensitive information about the cryptographic operations, especially on failure. This information could be exploited by attackers for further vulnerabilities.\n",
      "classification": "slightly promising",
      "cwe": "CWE-209",
      "function_names": [
        "decode_jwt"
      ],
      "filenames": [
        "lib/Crypt/JWT.pm"
      ]
    },
    {
      "headline": "Cleartext Transmission of Sensitive Information",
      "analysis": "The functions handling key and payload do not enforce secure transmission protocols or encryption of sensitive data within their constraints. This could lead to sensitive information being transferred in cleartext over unsecured channels.\n",
      "classification": "slightly promising",
      "cwe": "CWE-319",
      "function_names": [
        "_encrypt_jwe_payload",
        "_decrypt_jwe_payload"
      ],
      "filenames": [
        "lib/Crypt/JWT.pm"
      ]
    },
    {
      "headline": "Hardcoded Passwords in the Codebase",
      "analysis": "There are instances where keyword arguments receive hardcoded passwords, especially within test suites. This practice poses significant risk if similar practices are used in the main codebase, potentially leading to hardcoded keys or credentials.\n",
      "classification": "slightly promising",
      "cwe": "CWE-798",
      "function_names": [
        "encode_jwt",
        "decode_jwt"
      ],
      "filenames": [
        "t/jwt_params.t",
        "t/jwt_encode_decode.t"
      ]
    }
  ],
  "scores": [
    {
      "stats": {
        "fn": 1,
        "tp": 0,
        "fp": 1
      },
      "mapping": {},
      "vuln_dates": {
        "CVE-2019-1010263": "2019-07-17T21:15:10"
      },
      "scoring_model": "claude-3-opus-20240229",
      "type": "llm",
      "instruction_template_hash": "245ace12b6361954d0a2"
    }
  ],
  "instruction_template_hash": "10c0163db4740318a544",
  "version": "0.1.0"
}
