{
  "commit": "e4d8656441d93eb08d74a0b7cf1036a0de7473b5",
  "repo_url": "https://github.com/ansibleguy/webui",
  "model": "claude-3-5-sonnet-20240620",
  "chunk_hashes": [
    "3d13c554f24f52188519"
  ],
  "responses": [
    {
      "content": "```yaml\nleads:\n  - headline: Insecure use of SECRET_KEY\n    analysis: |\n      The SECRET_KEY is hardcoded in the source code in the run_dev.sh script. This key is used for cryptographic signing in Django and should be kept secret. Hardcoding it in source control exposes it to anyone with access to the code. An attacker could potentially use this to forge session cookies and authentication tokens.\n    cwe: CWE-798\n    function_names:\n      - run_shared.sh\n    filenames:\n      - scripts/run_dev.sh\n    classification: very promising\n\n  - headline: Potential SQL injection in database queries\n    analysis: |\n      The code uses raw SQL queries in several places without proper parameterization. For example, in the JobExecution model, the status_name_from_id method uses string formatting to insert values directly into SQL queries. This could allow SQL injection if the input is not properly sanitized. An attacker could potentially execute arbitrary SQL commands by manipulating the input.\n    cwe: CWE-89\n    function_names:\n      - status_name_from_id\n    filenames:\n      - src/ansibleguy-webui/aw/model/job.py\n    classification: very promising\n\n  - headline: Insufficient input validation on user-supplied data\n    analysis: |\n      The code does not appear to consistently validate or sanitize user input before using it in queries or commands. For example, the API endpoints often use request.data directly without validation. This could allow injection attacks or other malicious input. An attacker could potentially exploit this to execute unintended operations or access unauthorized data.\n    cwe: CWE-20\n    function_names:\n      - post\n      - put \n    filenames:\n      - src/ansibleguy-webui/aw/api_endpoints/job.py\n      - src/ansibleguy-webui/aw/api_endpoints/repository.py\n    classification: very promising\n\n  - headline: Insecure direct object references\n    analysis: |\n      The code uses object IDs directly in API endpoints without checking if the current user has permission to access that object. For example, in the APIJobItem class, it retrieves a job by ID without verifying the user's permissions first. This could allow unauthorized access to jobs or other resources. An attacker could potentially access or modify data they should not have access to by guessing or enumerating IDs.\n    cwe: CWE-639\n    function_names:\n      - get\n      - put\n      - delete  \n    filenames:\n      - src/ansibleguy-webui/aw/api_endpoints/job.py\n    classification: very promising\n\n  - headline: Potential command injection in subprocess calls\n    analysis: |\n      The code uses subprocess.Popen to execute shell commands in several places, sometimes with user-supplied input. For example, in the ExecuteRepository class, git commands are constructed using user-supplied data. If this input is not properly sanitized, it could lead to command injection vulnerabilities. An attacker could potentially execute arbitrary system commands by injecting malicious input.\n    cwe: CWE-78\n    function_names:\n      - _repo_process\n    filenames:\n      - src/ansibleguy-webui/aw/execute/repository.py  \n    classification: very promising\n```",
      "date": "2024-07-07T20:37:14.521186",
      "usage": {
        "prompt_tokens": 160744,
        "completion_tokens": 785,
        "cost": 0.494007
      }
    }
  ],
  "leads": [
    {
      "headline": "Insecure use of SECRET_KEY",
      "analysis": "The SECRET_KEY is hardcoded in the source code in the run_dev.sh script. This key is used for cryptographic signing in Django and should be kept secret. Hardcoding it in source control exposes it to anyone with access to the code. An attacker could potentially use this to forge session cookies and authentication tokens.\n",
      "classification": "very promising",
      "cwe": "CWE-798",
      "function_names": [
        "run_shared.sh"
      ],
      "filenames": [
        "scripts/run_dev.sh"
      ]
    },
    {
      "headline": "Potential SQL injection in database queries",
      "analysis": "The code uses raw SQL queries in several places without proper parameterization. For example, in the JobExecution model, the status_name_from_id method uses string formatting to insert values directly into SQL queries. This could allow SQL injection if the input is not properly sanitized. An attacker could potentially execute arbitrary SQL commands by manipulating the input.\n",
      "classification": "very promising",
      "cwe": "CWE-89",
      "function_names": [
        "status_name_from_id"
      ],
      "filenames": [
        "src/ansibleguy-webui/aw/model/job.py"
      ]
    },
    {
      "headline": "Insufficient input validation on user-supplied data",
      "analysis": "The code does not appear to consistently validate or sanitize user input before using it in queries or commands. For example, the API endpoints often use request.data directly without validation. This could allow injection attacks or other malicious input. An attacker could potentially exploit this to execute unintended operations or access unauthorized data.\n",
      "classification": "very promising",
      "cwe": "CWE-20",
      "function_names": [
        "post",
        "put"
      ],
      "filenames": [
        "src/ansibleguy-webui/aw/api_endpoints/job.py",
        "src/ansibleguy-webui/aw/api_endpoints/repository.py"
      ]
    },
    {
      "headline": "Insecure direct object references",
      "analysis": "The code uses object IDs directly in API endpoints without checking if the current user has permission to access that object. For example, in the APIJobItem class, it retrieves a job by ID without verifying the user's permissions first. This could allow unauthorized access to jobs or other resources. An attacker could potentially access or modify data they should not have access to by guessing or enumerating IDs.\n",
      "classification": "very promising",
      "cwe": "CWE-639",
      "function_names": [
        "get",
        "put",
        "delete"
      ],
      "filenames": [
        "src/ansibleguy-webui/aw/api_endpoints/job.py"
      ]
    },
    {
      "headline": "Potential command injection in subprocess calls",
      "analysis": "The code uses subprocess.Popen to execute shell commands in several places, sometimes with user-supplied input. For example, in the ExecuteRepository class, git commands are constructed using user-supplied data. If this input is not properly sanitized, it could lead to command injection vulnerabilities. An attacker could potentially execute arbitrary system commands by injecting malicious input.\n",
      "classification": "very promising",
      "cwe": "CWE-78",
      "function_names": [
        "_repo_process"
      ],
      "filenames": [
        "src/ansibleguy-webui/aw/execute/repository.py"
      ]
    }
  ],
  "scores": [
    {
      "stats": {
        "fn": 1,
        "tp": 0,
        "fp": 5
      },
      "mapping": {},
      "vuln_dates": {
        "CVE-2024-36110": "2024-05-28T19:15:11"
      },
      "scoring_model": "claude-3-5-sonnet-20240620",
      "type": "llm",
      "instruction_template_hash": "245ace12b6361954d0a2"
    }
  ],
  "instruction_template_hash": "10c0163db4740318a544",
  "version": "0.1.0"
}
