{
  "commit": "2abfaedae070e3c81a8b17bffd7180362da8fe7c",
  "repo_url": "https://github.com/rancher/rancher",
  "model": "claude-3-sonnet-20240229",
  "chunk_hashes": [
    "19fd9e68bb30253670d4"
  ],
  "responses": [
    {
      "content": "```yaml\nleads:\n  - headline: Potential SQL Injection vulnerability\n    analysis: |\n      The code in `register.py` constructs SQL queries by concatenating user-supplied input (the `key` argument) without proper sanitization or validation. This could allow an attacker to inject malicious SQL code and potentially gain unauthorized access to the database or expose sensitive information.\n    cwe: CWE-89\n    function_names:\n      - register.py (line not clearly mapped to a function)\n    filenames:\n      - agent/register.py\n    classification: very promising\n\n  - headline: Use of hard-coded credentials\n    analysis: |\n      The code in `register.py` uses hard-coded API credentials (`CATTLE_REGISTRATION_ACCESS_KEY` and `CATTLE_REGISTRATION_SECRET_KEY`) to authenticate with the Cattle API. Hard-coded credentials are a security risk as they cannot be easily changed or revoked if compromised.\n    cwe: CWE-798\n    function_names:\n      - register.py (line not clearly mapped to a function)\n    filenames:\n      - agent/register.py  \n    classification: very promising\n\n  - headline: Potential command injection vulnerability\n    analysis: |\n      The code in `ranchertests/test_cattles.py` constructs command strings by concatenating user input (the `mysql_cmd` fixture) without proper sanitization or validation. This could potentially allow an attacker to inject malicious commands and gain unauthorized access or execute arbitrary code on the system.\n    cwe: CWE-78\n    function_names:\n      - test_local_cattle_db_has_mysql_process\n    filenames:\n      - tests/server/ranchertests/test_cattles.py\n    classification: slightly promising\n\n  - headline: Insecure transmission of sensitive information (credentials)\n    analysis: |\n      The code in `register.py` sends API credentials (`CATTLE_REGISTRATION_ACCESS_KEY` and `CATTLE_REGISTRATION_SECRET_KEY`) as plaintext over the network when communicating with the Cattle API. This could potentially expose sensitive credentials to an attacker sniffing the network traffic.\n    cwe: CWE-319\n    function_names:\n      - register.py (line not clearly mapped to a function)\n    filenames:\n      - agent/register.py\n    classification: very promising\n      \n  - headline: Missing authentication for critical function\n    analysis: |\n      The code in `resolve_url.py` creates a new registration token without proper authentication checks. This could potentially allow an unauthorized user to generate and obtain a registration token, enabling them to register and gain unauthorized access to the system.\n    cwe: CWE-306\n    function_names:\n      - resolve_url.py (line not clearly mapped to a function)\n    filenames:\n      - agent/resolve_url.py\n    classification: very promising\n\n  - headline: Potential race condition vulnerability\n    analysis: |\n      The code in `artifacts/mysql.sh` uses `mysqladmin` to check the status of the MySQL server before starting or stopping it. However, there is no proper synchronization or locking mechanism in place, which could potentially lead to race conditions if multiple instances of the script are running concurrently.\n    cwe: CWE-362\n    function_names: []\n    filenames:\n      - server/artifacts/mysql.sh\n    classification: slightly promising\n```",
      "date": "2024-06-13T11:18:35.712581",
      "usage": {
        "prompt_tokens": 14612,
        "completion_tokens": 792,
        "cost": 0.055716
      }
    }
  ],
  "leads": [
    {
      "headline": "Potential SQL Injection vulnerability",
      "analysis": "The code in register.py constructs SQL queries by concatenating user-supplied input (the key argument) without proper sanitization or validation. This could allow an attacker to inject malicious SQL code and potentially gain unauthorized access to the database or expose sensitive information.\n",
      "classification": "very promising",
      "cwe": "CWE-89",
      "function_names": [
        "register.py (line not clearly mapped to a function)"
      ],
      "filenames": [
        "agent/register.py"
      ]
    },
    {
      "headline": "Use of hard-coded credentials",
      "analysis": "The code in register.py uses hard-coded API credentials (CATTLE_REGISTRATION_ACCESS_KEY and CATTLE_REGISTRATION_SECRET_KEY) to authenticate with the Cattle API. Hard-coded credentials are a security risk as they cannot be easily changed or revoked if compromised.\n",
      "classification": "very promising",
      "cwe": "CWE-798",
      "function_names": [
        "register.py (line not clearly mapped to a function)"
      ],
      "filenames": [
        "agent/register.py"
      ]
    },
    {
      "headline": "Potential command injection vulnerability",
      "analysis": "The code in ranchertests/test_cattles.py constructs command strings by concatenating user input (the mysql_cmd fixture) without proper sanitization or validation. This could potentially allow an attacker to inject malicious commands and gain unauthorized access or execute arbitrary code on the system.\n",
      "classification": "slightly promising",
      "cwe": "CWE-78",
      "function_names": [
        "test_local_cattle_db_has_mysql_process"
      ],
      "filenames": [
        "tests/server/ranchertests/test_cattles.py"
      ]
    },
    {
      "headline": "Insecure transmission of sensitive information (credentials)",
      "analysis": "The code in register.py sends API credentials (CATTLE_REGISTRATION_ACCESS_KEY and CATTLE_REGISTRATION_SECRET_KEY) as plaintext over the network when communicating with the Cattle API. This could potentially expose sensitive credentials to an attacker sniffing the network traffic.\n",
      "classification": "very promising",
      "cwe": "CWE-319",
      "function_names": [
        "register.py (line not clearly mapped to a function)"
      ],
      "filenames": [
        "agent/register.py"
      ]
    },
    {
      "headline": "Missing authentication for critical function",
      "analysis": "The code in resolve_url.py creates a new registration token without proper authentication checks. This could potentially allow an unauthorized user to generate and obtain a registration token, enabling them to register and gain unauthorized access to the system.\n",
      "classification": "very promising",
      "cwe": "CWE-306",
      "function_names": [
        "resolve_url.py (line not clearly mapped to a function)"
      ],
      "filenames": [
        "agent/resolve_url.py"
      ]
    },
    {
      "headline": "Potential race condition vulnerability",
      "analysis": "The code in artifacts/mysql.sh uses mysqladmin to check the status of the MySQL server before starting or stopping it. However, there is no proper synchronization or locking mechanism in place, which could potentially lead to race conditions if multiple instances of the script are running concurrently.\n",
      "classification": "slightly promising",
      "cwe": "CWE-362",
      "function_names": [],
      "filenames": [
        "server/artifacts/mysql.sh"
      ]
    }
  ],
  "scores": [
    {
      "stats": {
        "fn": 1,
        "tp": 0,
        "fp": 4
      },
      "mapping": {},
      "vuln_dates": {
        "CVE-2017-7297": "2017-03-29T00:59:00"
      },
      "scoring_model": "claude-3-opus-20240229",
      "type": "llm",
      "instruction_template_hash": "245ace12b6361954d0a2"
    }
  ],
  "instruction_template_hash": "10c0163db4740318a544",
  "version": "0.1.0"
}
