{
  "commit": "044b243f2f3ebe279dbcba535c3f0885d578eccf",
  "repo_url": "https://github.com/styria-digital/django-rest-framework-jwt",
  "model": "claude-3-haiku-20240307",
  "chunk_hashes": [
    "a68f7cba4042f3e023e2"
  ],
  "responses": [
    {
      "content": "Here is the YAML output identifying the security vulnerabilities in the codebase:\n\n```yaml\nleads:\n  - headline: Improper Input Validation\n    analysis: |\n      The codebase contains several instances of improper input validation, which could lead to vulnerabilities such as command injection, SQL injection, and cross-site scripting (XSS). These vulnerabilities are present in the authentication and verification endpoints, where user-provided data is not properly sanitized or validated before being used.\n    cwe: CWE-20\n    function_names:\n      - authenticate_credentials\n      - jwt_get_token_from_request\n    filenames:\n      - src/rest_framework_jwt/authentication.py\n      - src/rest_framework_jwt/serializers.py\n    classification: very promising\n\n  - headline: Improper Neutralization of Input During Web Page Generation ('Cross-site Scripting')\n    analysis: |\n      The codebase does not properly sanitize or encode user-provided data before rendering it in the response. This could lead to cross-site scripting (XSS) vulnerabilities, where an attacker could inject malicious scripts into the page and execute them in the victim's browser.\n    cwe: CWE-79\n    function_names:\n      - jwt_create_response_payload\n    filenames:\n      - src/rest_framework_jwt/utils.py\n    classification: very promising\n\n  - headline: Improper Certificate Validation\n    analysis: |\n      The codebase uses the JWT authentication mechanism, which relies on cryptographic certificates for verification. However, the implementation does not properly validate the certificates, which could lead to vulnerabilities where an attacker could impersonate a legitimate user or server.\n    cwe: CWE-295\n    function_names:\n      - jwt_decode_token\n    filenames:\n      - src/rest_framework_jwt/utils.py\n    classification: slightly promising\n\n  - headline: Weak Password Requirements\n    analysis: |\n      The codebase does not enforce strong password requirements for user accounts. This could lead to vulnerabilities where an attacker could easily guess or brute-force user credentials and gain unauthorized access to the system.\n    cwe: CWE-521\n    function_names: []\n    filenames: []\n    classification: slightly promising\n\n  - headline: Improper Handling of Exceptional Conditions\n    analysis: |\n      The codebase does not properly handle exceptional conditions, such as invalid tokens or inactive users. This could lead to vulnerabilities where an attacker could bypass authentication or cause the system to reveal sensitive information in error messages.\n    cwe: CWE-754\n    function_names:\n      - authenticate_credentials\n      - check_payload\n      - check_user\n    filenames:\n      - src/rest_framework_jwt/authentication.py\n      - src/rest_framework_jwt/utils.py\n    classification: very promising\n```",
      "date": "2024-06-13T12:08:52.430794",
      "usage": {
        "prompt_tokens": 24294,
        "completion_tokens": 672,
        "cost": 0.0069135
      }
    }
  ],
  "leads": [
    {
      "headline": "Improper Input Validation",
      "analysis": "The codebase contains several instances of improper input validation, which could lead to vulnerabilities such as command injection, SQL injection, and cross-site scripting (XSS). These vulnerabilities are present in the authentication and verification endpoints, where user-provided data is not properly sanitized or validated before being used.\n",
      "classification": "very promising",
      "cwe": "CWE-20",
      "function_names": [
        "authenticate_credentials",
        "jwt_get_token_from_request"
      ],
      "filenames": [
        "src/rest_framework_jwt/authentication.py",
        "src/rest_framework_jwt/serializers.py"
      ]
    },
    {
      "headline": "Improper Neutralization of Input During Web Page Generation ('Cross-site Scripting')",
      "analysis": "The codebase does not properly sanitize or encode user-provided data before rendering it in the response. This could lead to cross-site scripting (XSS) vulnerabilities, where an attacker could inject malicious scripts into the page and execute them in the victim's browser.\n",
      "classification": "very promising",
      "cwe": "CWE-79",
      "function_names": [
        "jwt_create_response_payload"
      ],
      "filenames": [
        "src/rest_framework_jwt/utils.py"
      ]
    },
    {
      "headline": "Improper Certificate Validation",
      "analysis": "The codebase uses the JWT authentication mechanism, which relies on cryptographic certificates for verification. However, the implementation does not properly validate the certificates, which could lead to vulnerabilities where an attacker could impersonate a legitimate user or server.\n",
      "classification": "slightly promising",
      "cwe": "CWE-295",
      "function_names": [
        "jwt_decode_token"
      ],
      "filenames": [
        "src/rest_framework_jwt/utils.py"
      ]
    },
    {
      "headline": "Weak Password Requirements",
      "analysis": "The codebase does not enforce strong password requirements for user accounts. This could lead to vulnerabilities where an attacker could easily guess or brute-force user credentials and gain unauthorized access to the system.\n",
      "classification": "slightly promising",
      "cwe": "CWE-521",
      "function_names": [],
      "filenames": []
    },
    {
      "headline": "Improper Handling of Exceptional Conditions",
      "analysis": "The codebase does not properly handle exceptional conditions, such as invalid tokens or inactive users. This could lead to vulnerabilities where an attacker could bypass authentication or cause the system to reveal sensitive information in error messages.\n",
      "classification": "very promising",
      "cwe": "CWE-754",
      "function_names": [
        "authenticate_credentials",
        "check_payload",
        "check_user"
      ],
      "filenames": [
        "src/rest_framework_jwt/authentication.py",
        "src/rest_framework_jwt/utils.py"
      ]
    }
  ],
  "scores": [
    {
      "stats": {
        "fn": 1,
        "tp": 0,
        "fp": 3
      },
      "mapping": {},
      "vuln_dates": {
        "CVE-2020-10594": "2020-03-15T22:15:14"
      },
      "scoring_model": "claude-3-opus-20240229",
      "type": "llm",
      "instruction_template_hash": "245ace12b6361954d0a2"
    }
  ],
  "instruction_template_hash": "10c0163db4740318a544",
  "version": "0.1.0"
}
