{
  "commit": "2b8554bbe810c36ce960d3f4836584bc40b6ba53",
  "repo_url": "https://github.com/silverwind/droppy",
  "model": "gpt-4-turbo-2024-04-09",
  "chunk_hashes": [
    "e25061a190c92eef714d"
  ],
  "responses": [
    {
      "content": "```yaml\nleads:\n  - headline: \"Improper Privilege Management\"\n    analysis: |\n      The code allows a form of privilege escalation where a user could swap files by dragging between views, and this leads to unauthorized access or modification of files. The specific logic for handling drag-and-drop operations doesn\u2019t appear to perform adequate privilege checks, potentially allowing a low-privileged user to perform actions as if they were a higher-privileged user.\n    cwe: CWE-269\n    function_names:\n      - bindDragEvents\n      - bindDropEvents\n    filenames:\n      - \"/client/client.js\"\n    classification: slightly promising\n\n  - headline: \"Improper Authentication Handling\"\n    analysis: |\n      The code uses a cookie-based session management system without adequately securing the cookie or ensuring its integrity. This might allow an attacker to forge session cookies or leverage session fixation techniques. There\u2019s also no mechanism to prevent brute-forcing of credentials, as observed in the POST handler for authentication in `client/client.js`.\n    cwe: CWE-287\n    function_names:\n      - initAuthPage\n    filenames:\n      - \"/client/client.js\"\n    classification: very promising\n\n  - headline: \"Potential XSS in Dynamic HTML Content\"\n    analysis: |\n      The application dynamically generates HTML content based on user interaction and server responses, particularly when rendering file listings or processing uploads. If untrusted input can influence the HTML output without proper sanitization, it could lead to a Cross-Site Scripting (XSS) attack.\n    cwe: CWE-79\n    function_names:\n      - loadContent\n      - openMedia\n    filenames:\n      - \"/client/client.js\"\n    classification: slightly promising\n\n  - headline: \"Potential Path Traversal in File Handling Operations\"\n    analysis: |\n      The functions involved in file operations such as views update or file uploads do not appear to have robust mechanisms against path traversal attacks. User input concatenated directly into file paths without adequate checks could lead to unauthorized file system access.\n    cwe: CWE-22\n    function_names:\n      - updateLocation\n      - handleFileRequest\n    filenames:\n      - \"/client/client.js\"\n    classification: slightly promising\n\n  - headline: \"Exposure of Sensitive Information Through Error Messages\"\n    analysis: |\n      The server setup and authentication procedures involve responses that include direct system paths or configuration details when errors occur, especially seen in the `auth.html` template. This could inadvertently expose sensitive information to an unauthorized actor, aiding them in crafting further attacks.\n    cwe: CWE-209\n    function_names: []\n    filenames:\n      - \"/client/html/auth.html\"\n    classification: not promising\n\n  - headline: \"Unrestricted File Upload leads to Server-Side Code Execution\"\n    analysis: |\n      The application implements a file upload feature but does not sufficiently restrict the types of files that can be uploaded. This could allow an attacker to upload executable files or scripts that could be run on the server, leading to server-side code execution.\n    cwe: CWE-434\n    function_names:\n      - upload\n    filenames:\n      - \"/client/client.js\"\n    classification: very promising\n\n  - headline: \"Insecure Storage of Sensitive Information in Log File\"\n    analysis: |\n      The logging function writes logs directly to disk without safeguarding sensitive information. The log files could potentially include user credentials or session tokens, thus exposing this information to anyone with access to these files.\n    cwe: CWE-532\n    function_names:\n      - showError\n      - log.error\n    filenames:\n      - \"/client/client.js\"\n    classification: not promising\n\n  - headline: \"Improper Handling of Exceptional Conditions\"\n    analysis: |\n      The JavaScript handling for user interactions and server responses lack proper error handling, which could result in uncaught exceptions or improper state management across the application. This could lead to denial of service or unpredictable application behavior under certain conditions.\n    cwe: CWE-755\n    function_locations:\n      - initAuthPage\n      - sendMessage\n    filenames:\n      - \"/client/client.js\"\n    classification: slightly promising\n```",
      "date": "2024-06-13T11:44:05.570581",
      "usage": {
        "prompt_tokens": 53574,
        "completion_tokens": 844,
        "cost": 0.56106
      }
    }
  ],
  "leads": [
    {
      "headline": "Improper Privilege Management",
      "analysis": "The code allows a form of privilege escalation where a user could swap files by dragging between views, and this leads to unauthorized access or modification of files. The specific logic for handling drag-and-drop operations doesn\u2019t appear to perform adequate privilege checks, potentially allowing a low-privileged user to perform actions as if they were a higher-privileged user.\n",
      "classification": "slightly promising",
      "cwe": "CWE-269",
      "function_names": [
        "bindDragEvents",
        "bindDropEvents"
      ],
      "filenames": [
        "/client/client.js"
      ]
    },
    {
      "headline": "Improper Authentication Handling",
      "analysis": "The code uses a cookie-based session management system without adequately securing the cookie or ensuring its integrity. This might allow an attacker to forge session cookies or leverage session fixation techniques. There\u2019s also no mechanism to prevent brute-forcing of credentials, as observed in the POST handler for authentication in client/client.js.\n",
      "classification": "very promising",
      "cwe": "CWE-287",
      "function_names": [
        "initAuthPage"
      ],
      "filenames": [
        "/client/client.js"
      ]
    },
    {
      "headline": "Potential XSS in Dynamic HTML Content",
      "analysis": "The application dynamically generates HTML content based on user interaction and server responses, particularly when rendering file listings or processing uploads. If untrusted input can influence the HTML output without proper sanitization, it could lead to a Cross-Site Scripting (XSS) attack.\n",
      "classification": "slightly promising",
      "cwe": "CWE-79",
      "function_names": [
        "loadContent",
        "openMedia"
      ],
      "filenames": [
        "/client/client.js"
      ]
    },
    {
      "headline": "Potential Path Traversal in File Handling Operations",
      "analysis": "The functions involved in file operations such as views update or file uploads do not appear to have robust mechanisms against path traversal attacks. User input concatenated directly into file paths without adequate checks could lead to unauthorized file system access.\n",
      "classification": "slightly promising",
      "cwe": "CWE-22",
      "function_names": [
        "updateLocation",
        "handleFileRequest"
      ],
      "filenames": [
        "/client/client.js"
      ]
    },
    {
      "headline": "Exposure of Sensitive Information Through Error Messages",
      "analysis": "The server setup and authentication procedures involve responses that include direct system paths or configuration details when errors occur, especially seen in the auth.html template. This could inadvertently expose sensitive information to an unauthorized actor, aiding them in crafting further attacks.\n",
      "classification": "not promising",
      "cwe": "CWE-209",
      "function_names": [],
      "filenames": [
        "/client/html/auth.html"
      ]
    },
    {
      "headline": "Unrestricted File Upload leads to Server-Side Code Execution",
      "analysis": "The application implements a file upload feature but does not sufficiently restrict the types of files that can be uploaded. This could allow an attacker to upload executable files or scripts that could be run on the server, leading to server-side code execution.\n",
      "classification": "very promising",
      "cwe": "CWE-434",
      "function_names": [
        "upload"
      ],
      "filenames": [
        "/client/client.js"
      ]
    },
    {
      "headline": "Insecure Storage of Sensitive Information in Log File",
      "analysis": "The logging function writes logs directly to disk without safeguarding sensitive information. The log files could potentially include user credentials or session tokens, thus exposing this information to anyone with access to these files.\n",
      "classification": "not promising",
      "cwe": "CWE-532",
      "function_names": [
        "showError",
        "log.error"
      ],
      "filenames": [
        "/client/client.js"
      ]
    },
    {
      "headline": "Improper Handling of Exceptional Conditions",
      "analysis": "The JavaScript handling for user interactions and server responses lack proper error handling, which could result in uncaught exceptions or improper state management across the application. This could lead to denial of service or unpredictable application behavior under certain conditions.\n",
      "classification": "slightly promising",
      "cwe": "CWE-755",
      "function_names": [],
      "filenames": [
        "/client/client.js"
      ]
    }
  ],
  "scores": [
    {
      "stats": {
        "fn": 1,
        "tp": 0,
        "fp": 2
      },
      "mapping": {},
      "vuln_dates": {
        "CVE-2016-10529": "2018-05-31T20:29:00"
      },
      "scoring_model": "claude-3-opus-20240229",
      "type": "llm",
      "instruction_template_hash": "245ace12b6361954d0a2"
    }
  ],
  "instruction_template_hash": "10c0163db4740318a544",
  "version": "0.1.0"
}
