{
  "commit": "1e1efc8eb75d75c1d97b86587b4a9d118d7add4f",
  "repo_url": "https://github.com/jenkinsci/bearychat-plugin",
  "model": "claude-3-haiku-20240307",
  "chunk_hashes": [
    "51de4048453dfa96f389"
  ],
  "responses": [
    {
      "content": "Here is the YAML output equivalent to the LeadList type, based on the provided codebase:\n\n```yaml\nleads:\n  - headline: Potential prototype pollution vulnerability\n    analysis: |\n      The codebase includes the use of the `Improperly Controlled Modification of Object Prototype Attributes ('Prototype Pollution')` vulnerability (CWE-1321). This can occur in the `BearyChatSendStep` class, where the `setBearyChatService` method is used to create a new `StandardBearyChatService` instance with user-controlled input for the `webhook` and `channel` parameters. An attacker could potentially modify the prototype of the `StandardBearyChatService` class or its dependencies, leading to arbitrary code execution or other security issues.\n    cwe: CWE-1321\n    function_names:\n      - BearyChatSendStep.BearyChatSendStepExecution.getBearyChatService\n    filenames:\n      - src/main/java/jenkins/plugins/bearychat/workflow/BearyChatSendStep.java\n    classification: very promising\n  - headline: Potential unsafe reflection vulnerability\n    analysis: |\n      The codebase includes the use of the `Use of Externally-Controlled Input to Select Classes or Code ('Unsafe Reflection')` vulnerability (CWE-470). This can occur in the `BearyChatSendStep` class, where the `Jenkins.getInstance()` method is used to retrieve the global configuration. An attacker could potentially provide crafted input to the `BearyChatSendStep` that could lead to the execution of arbitrary code through reflection.\n    cwe: CWE-470\n    function_names:\n      - BearyChatSendStep.BearyChatSendStepExecution.run\n    filenames:\n      - src/main/java/jenkins/plugins/bearychat/workflow/BearyChatSendStep.java\n    classification: very promising\n  - headline: Potential deserialization vulnerability\n    analysis: |\n      The codebase includes the use of the `Deserialization of Untrusted Data` vulnerability (CWE-502). This can occur in the `BearyChatSendStep` class, where the `getBearyChatService` method returns a `StandardBearyChatService` instance. An attacker could potentially provide crafted input to the `BearyChatSendStep` that could lead to the deserialization of untrusted data, potentially resulting in arbitrary code execution.\n    cwe: CWE-502\n    function_names:\n      - BearyChatSendStep.BearyChatSendStepExecution.getBearyChatService\n    filenames:\n      - src/main/java/jenkins/plugins/bearychat/workflow/BearyChatSendStep.java\n    classification: very promising\n  - headline: Potential open redirect vulnerability\n    analysis: |\n      The codebase includes the use of the `URL Redirection to Untrusted Site ('Open Redirect')` vulnerability (CWE-601). This can occur in the `MessageBuilder` class, where the `getJobURL` method is used to construct a URL for the Jenkins job. An attacker could potentially provide crafted input to the `BearyChatSendStep` that could lead to the redirection of users to a malicious website.\n    cwe: CWE-601\n    function_names:\n      - MessageBuilder.getJobURL\n    filenames:\n      - src/main/java/jenkins/plugins/bearychat/MessageBuilder.java\n    classification: slightly promising\n  - headline: Potential cross-site scripting (XSS) vulnerability\n    analysis: |\n      The codebase includes the use of the `Improper Neutralization of Input During Web Page Generation ('Cross-site Scripting')` vulnerability (CWE-79). This can occur in various parts of the codebase, where user-controlled input is not properly sanitized before being used in HTML or other dynamic content. An attacker could potentially provide crafted input to the `BearyChatSendStep` that could lead to the execution of malicious scripts in the user's browser.\n    cwe: CWE-79\n    function_names:\n      - Helper.escape\n      - MessageBuilder.getProject\n      - MessageBuilder.getJob\n      - MessageBuilder.getFiles\n    filenames:\n      - src/main/java/jenkins/plugins/bearychat/Helper.java\n      - src/main/java/jenkins/plugins/bearychat/MessageBuilder.java\n    classification: slightly promising\n  - headline: Potential command injection vulnerability\n    analysis: |\n      The codebase includes the use of the `Improper Neutralization of Special Elements used in an OS Command ('OS Command Injection')` vulnerability (CWE-78). This can occur in the `StandardBearyChatService` class, where the `getHttpClient` method is used to create an `HttpClient` instance. An attacker could potentially provide crafted input to the `BearyChatSendStep` that could lead to the execution of arbitrary OS commands.\n    cwe: CWE-78\n    function_names:\n      - StandardBearyChatService.getHttpClient\n    filenames:\n      - src/main/java/jenkins/plugins/bearychat/StandardBearyChatService.java\n    classification: slightly promising\n\n```",
      "date": "2024-06-12T17:57:35.770977",
      "usage": {
        "prompt_tokens": 21124,
        "completion_tokens": 1259,
        "cost": 0.00685475
      }
    }
  ],
  "leads": [
    {
      "headline": "Potential prototype pollution vulnerability",
      "analysis": "The codebase includes the use of the Improperly Controlled Modification of Object Prototype Attributes ('Prototype Pollution') vulnerability (CWE-1321). This can occur in the BearyChatSendStep class, where the setBearyChatService method is used to create a new StandardBearyChatService instance with user-controlled input for the webhook and channel parameters. An attacker could potentially modify the prototype of the StandardBearyChatService class or its dependencies, leading to arbitrary code execution or other security issues.\n",
      "classification": "very promising",
      "cwe": "CWE-1321",
      "function_names": [
        "BearyChatSendStep.BearyChatSendStepExecution.getBearyChatService"
      ],
      "filenames": [
        "src/main/java/jenkins/plugins/bearychat/workflow/BearyChatSendStep.java"
      ]
    },
    {
      "headline": "Potential unsafe reflection vulnerability",
      "analysis": "The codebase includes the use of the Use of Externally-Controlled Input to Select Classes or Code ('Unsafe Reflection') vulnerability (CWE-470). This can occur in the BearyChatSendStep class, where the Jenkins.getInstance() method is used to retrieve the global configuration. An attacker could potentially provide crafted input to the BearyChatSendStep that could lead to the execution of arbitrary code through reflection.\n",
      "classification": "very promising",
      "cwe": "CWE-470",
      "function_names": [
        "BearyChatSendStep.BearyChatSendStepExecution.run"
      ],
      "filenames": [
        "src/main/java/jenkins/plugins/bearychat/workflow/BearyChatSendStep.java"
      ]
    },
    {
      "headline": "Potential deserialization vulnerability",
      "analysis": "The codebase includes the use of the Deserialization of Untrusted Data vulnerability (CWE-502). This can occur in the BearyChatSendStep class, where the getBearyChatService method returns a StandardBearyChatService instance. An attacker could potentially provide crafted input to the BearyChatSendStep that could lead to the deserialization of untrusted data, potentially resulting in arbitrary code execution.\n",
      "classification": "very promising",
      "cwe": "CWE-502",
      "function_names": [
        "BearyChatSendStep.BearyChatSendStepExecution.getBearyChatService"
      ],
      "filenames": [
        "src/main/java/jenkins/plugins/bearychat/workflow/BearyChatSendStep.java"
      ]
    },
    {
      "headline": "Potential open redirect vulnerability",
      "analysis": "The codebase includes the use of the URL Redirection to Untrusted Site ('Open Redirect') vulnerability (CWE-601). This can occur in the MessageBuilder class, where the getJobURL method is used to construct a URL for the Jenkins job. An attacker could potentially provide crafted input to the BearyChatSendStep that could lead to the redirection of users to a malicious website.\n",
      "classification": "slightly promising",
      "cwe": "CWE-601",
      "function_names": [
        "MessageBuilder.getJobURL"
      ],
      "filenames": [
        "src/main/java/jenkins/plugins/bearychat/MessageBuilder.java"
      ]
    },
    {
      "headline": "Potential cross-site scripting (XSS) vulnerability",
      "analysis": "The codebase includes the use of the Improper Neutralization of Input During Web Page Generation ('Cross-site Scripting') vulnerability (CWE-79). This can occur in various parts of the codebase, where user-controlled input is not properly sanitized before being used in HTML or other dynamic content. An attacker could potentially provide crafted input to the BearyChatSendStep that could lead to the execution of malicious scripts in the user's browser.\n",
      "classification": "slightly promising",
      "cwe": "CWE-79",
      "function_names": [
        "Helper.escape",
        "MessageBuilder.getProject",
        "MessageBuilder.getJob"
      ],
      "filenames": [
        "src/main/java/jenkins/plugins/bearychat/Helper.java",
        "src/main/java/jenkins/plugins/bearychat/MessageBuilder.java"
      ]
    },
    {
      "headline": "Potential command injection vulnerability",
      "analysis": "The codebase includes the use of the Improper Neutralization of Special Elements used in an OS Command ('OS Command Injection') vulnerability (CWE-78). This can occur in the StandardBearyChatService class, where the getHttpClient method is used to create an HttpClient instance. An attacker could potentially provide crafted input to the BearyChatSendStep that could lead to the execution of arbitrary OS commands.\n",
      "classification": "slightly promising",
      "cwe": "CWE-78",
      "function_names": [
        "StandardBearyChatService.getHttpClient"
      ],
      "filenames": [
        "src/main/java/jenkins/plugins/bearychat/StandardBearyChatService.java"
      ]
    }
  ],
  "scores": [
    {
      "stats": {
        "fn": 2,
        "tp": 0,
        "fp": 3
      },
      "mapping": {},
      "vuln_dates": {
        "CVE-2023-24459": "2023-01-26T21:18:19",
        "CVE-2023-24458": "2023-01-26T21:18:19"
      },
      "scoring_model": "claude-3-opus-20240229",
      "type": "llm",
      "instruction_template_hash": "245ace12b6361954d0a2"
    },
    {
      "stats": {
        "fn": 2,
        "tp": 0,
        "fp": 3
      },
      "mapping": {},
      "vuln_dates": {
        "CVE-2023-24459": "2023-01-26T21:18:19",
        "CVE-2023-24458": "2023-01-26T21:18:19"
      },
      "scoring_model": "claude-3-5-sonnet-20240620",
      "type": "llm",
      "instruction_template_hash": "245ace12b6361954d0a2"
    }
  ],
  "instruction_template_hash": "10c0163db4740318a544",
  "version": "0.1.0"
}
