{
  "commit": "5647855a7ddd322e0e9ced1134e5ea6cc100904e",
  "repo_url": "https://github.com/libfuse/libfuse",
  "model": "gpt-4o-2024-05-13",
  "chunk_hashes": [
    "de47eb8b02e883407dc9"
  ],
  "responses": [
    {
      "content": "```yaml\nleads:\n  - headline: Potential Command Injection in makeconf.sh\n    analysis: |\n      The script `makeconf.sh` uses unvalidated, user-supplied path data in several external commands (e.g., echo, cd, ln -sf). These commands do not validate the input paths, which could allow an attacker to inject arbitrary commands if the script is executed in an environment where the paths contain malicious payloads. This type of vulnerability could potentially lead to an attacker gaining control over the execution flow of the script.\n    cwe: CWE-78\n    function_names: []\n    filenames:\n      - makeconf.sh\n    classification: very promising\n  - headline: Possible Overflow and Permissions Issues in example Code\n    analysis: |\n      The code in the `example/` directory, particularly in `null.c`, `fusexmp.c`, `fusexmp_fh.c`, and `hello.c`, does not perform sufficient input validation on file system paths or size parameters. Specifically, the use of hardcoded file permissions (e.g., 0644, 0444) and operations like `memcpy` may lead to buffer overflows or mismanaging file permissions if the application ever evolves to accept user-supplied inputs.\n    cwe: CWE-119\n    function_names: []\n    filenames:\n      - example/null.c\n      - example/fusexmp.c\n      - example/fusexmp_fh.c\n      - example/hello.c\n    classification: slightly promising\n  - headline: Potential EFSI and Improper Locking in Kernel Modules\n    analysis: |\n      The kernel module files in `kernel/` exhibit potential issues with improper error handling and synchronization. Calls to functions like `down_interruptible()` and `up_read()` in multiple locations (e.g., in `fuse_dev_cleanup()`, `fuse_release_conn()`) can lead to race conditions if not properly synchronized. Moreover, improper error handling in I/O operations (e.g., `request_send()`) can lead to kernel panic scenarios.\n    cwe: CWE-362\n    function_names:\n      - fuse_dev_cleanup\n      - fuse_release_conn\n    filenames:\n      - kernel/dev.c\n      - kernel/inode.c\n    classification: slightly promising\n  - headline: Insufficient Path Validation in Utility Code\n    analysis: |\n      Utility files such as `util/fusermount.c` contain instances where paths are directly used in file operations without sufficient validation or escaping. For instance, the `do_mount()` function constructs and mounts file paths based on inputs that are not adequately sanitized, which may lead to path traversal attacks.\n    cwe: CWE-22\n    function_names:\n      - do_mount\n    filenames:\n      - util/fusermount.c\n    classification: very promising\n```",
      "date": "2024-06-09T13:10:38.839928",
      "usage": {
        "prompt_tokens": 80701,
        "completion_tokens": 585,
        "cost": 0.41228
      }
    }
  ],
  "leads": [
    {
      "headline": "Potential Command Injection in makeconf.sh",
      "analysis": "The script makeconf.sh uses unvalidated, user-supplied path data in several external commands (e.g., echo, cd, ln -sf). These commands do not validate the input paths, which could allow an attacker to inject arbitrary commands if the script is executed in an environment where the paths contain malicious payloads. This type of vulnerability could potentially lead to an attacker gaining control over the execution flow of the script.\n",
      "classification": "very promising",
      "cwe": "CWE-78",
      "function_names": [],
      "filenames": [
        "makeconf.sh"
      ]
    },
    {
      "headline": "Possible Overflow and Permissions Issues in example Code",
      "analysis": "The code in the example/ directory, particularly in null.c, fusexmp.c, fusexmp_fh.c, and hello.c, does not perform sufficient input validation on file system paths or size parameters. Specifically, the use of hardcoded file permissions (e.g., 0644, 0444) and operations like memcpy may lead to buffer overflows or mismanaging file permissions if the application ever evolves to accept user-supplied inputs.\n",
      "classification": "slightly promising",
      "cwe": "CWE-119",
      "function_names": [],
      "filenames": [
        "example/null.c",
        "example/fusexmp.c",
        "example/fusexmp_fh.c"
      ]
    },
    {
      "headline": "Potential EFSI and Improper Locking in Kernel Modules",
      "analysis": "The kernel module files in kernel/ exhibit potential issues with improper error handling and synchronization. Calls to functions like down_interruptible() and up_read() in multiple locations (e.g., in fuse_dev_cleanup(), fuse_release_conn()) can lead to race conditions if not properly synchronized. Moreover, improper error handling in I/O operations (e.g., request_send()) can lead to kernel panic scenarios.\n",
      "classification": "slightly promising",
      "cwe": "CWE-362",
      "function_names": [
        "fuse_dev_cleanup",
        "fuse_release_conn"
      ],
      "filenames": [
        "kernel/dev.c",
        "kernel/inode.c"
      ]
    },
    {
      "headline": "Insufficient Path Validation in Utility Code",
      "analysis": "Utility files such as util/fusermount.c contain instances where paths are directly used in file operations without sufficient validation or escaping. For instance, the do_mount() function constructs and mounts file paths based on inputs that are not adequately sanitized, which may lead to path traversal attacks.\n",
      "classification": "very promising",
      "cwe": "CWE-22",
      "function_names": [
        "do_mount"
      ],
      "filenames": [
        "util/fusermount.c"
      ]
    }
  ],
  "scores": [
    {
      "stats": {
        "fn": 1,
        "tp": 0,
        "fp": 2
      },
      "mapping": {},
      "vuln_dates": {
        "CVE-2023-1108": "2023-09-14T15:15:08"
      },
      "scoring_model": "gpt-4o-2024-05-13",
      "type": "llm",
      "instruction_template_hash": "8998f09cf57fca8a6e03"
    }
  ],
  "instruction_template_hash": "10c0163db4740318a544",
  "version": "0.1.0"
}
