{
  "commit": "2bf377194efc6b4f13b6bc6cd9272b935f64793e",
  "repo_url": "https://github.com/semantic-release/semantic-release",
  "model": "claude-3-haiku-20240307",
  "chunk_hashes": [
    "3f366b9c0e28df3ca722"
  ],
  "responses": [
    {
      "content": "```yaml\nleads:\n  - headline: Improper Input Validation\n    analysis: |\n      The codebase contains vulnerabilities related to improper input validation, including:\n\n      1. CWE-1284 Improper Validation of Specified Quantity in Input\n      2. CWE-129 Improper Validation of Array Index\n\n      These vulnerabilities can allow an attacker to bypass input validation checks and potentially execute arbitrary code or access sensitive data.\n    cwe: CWE-20\n    function_names:\n      - getCommits\n      - gitGetCommits\n    filenames:\n      - lib/get-commits.js\n      - lib/git.js\n    classification: very promising\n\n  - headline: Injection Vulnerabilities\n    analysis: |\n      The codebase contains several injection vulnerabilities, including:\n\n      1. CWE-77 Improper Neutralization of Special Elements used in a Command ('Command Injection')\n      2. CWE-79 Improper Neutralization of Input During Web Page Generation ('Cross-site Scripting')\n      3. CWE-89 Improper Neutralization of Special Elements used in an SQL Command ('SQL Injection')\n\n      These vulnerabilities can allow an attacker to inject malicious code or commands into the application, potentially leading to remote code execution, data breaches, or other serious consequences.\n    cwe: CWE-74\n    function_names:\n      - getGitAuthUrl\n      - repoUrl\n    filenames:\n      - lib/get-git-auth-url.js\n      - lib/git.js\n    classification: very promising\n\n  - headline: Cleartext Transmission of Sensitive Information\n    analysis: |\n      The codebase contains a vulnerability related to the cleartext transmission of sensitive information, specifically CWE-319 Cleartext Transmission of Sensitive Information.\n\n      This vulnerability can allow an attacker to intercept and read sensitive information, such as authentication credentials or private data, during transmission between the application and the remote repository.\n    cwe: CWE-311\n    function_names:\n      - getGitAuthUrl\n    filenames:\n      - lib/get-git-auth-url.js\n    classification: slightly promising\n\n  - headline: Improper Restriction of Operations within the Bounds of a Memory Buffer\n    analysis: |\n      The codebase contains vulnerabilities related to improper restriction of operations within the bounds of a memory buffer, including:\n\n      1. CWE-120 Buffer Copy without Checking Size of Input ('Classic Buffer Overflow')\n      2. CWE-125 Out-of-bounds Read\n\n      These vulnerabilities can allow an attacker to overwrite or read from memory locations outside of the intended buffer, potentially leading to crashes, data corruption, or even remote code execution.\n    cwe: CWE-119\n    function_names:\n      - gitGetCommits\n      - getCommits\n    filenames:\n      - lib/get-commits.js\n      - lib/git.js\n    classification: slightly promising\n\n  - headline: Improper Authentication\n    analysis: |\n      The codebase contains several vulnerabilities related to improper authentication, including:\n\n      1. CWE-306 Missing Authentication for Critical Function\n      2. CWE-307 Improper Restriction of Excessive Authentication Attempts\n      3. CWE-522 Insufficiently Protected Credentials\n\n      These vulnerabilities can allow an attacker to bypass authentication mechanisms and gain unauthorized access to the application or its resources.\n    cwe: CWE-287\n    function_names:\n      - verifyAuth\n    filenames:\n      - lib/git.js\n    classification: slightly promising\n\n  - headline: Improper Synchronization\n    analysis: |\n      The codebase contains a vulnerability related to improper synchronization, specifically CWE-362 Concurrent Execution using Shared Resource with Improper Synchronization ('Race Condition').\n\n      This vulnerability can allow multiple concurrent processes to access and modify shared resources in an unpredictable manner, potentially leading to data inconsistencies or other unintended behavior.\n    cwe: CWE-362\n    function_names:\n      - gitGetCommits\n      - getCommits\n    filenames:\n      - lib/get-commits.js\n      - lib/git.js\n    classification: slightly promising\n\n  - headline: Improper Resource Shutdown or Release\n    analysis: |\n      The codebase contains vulnerabilities related to improper resource shutdown or release, including:\n\n      1. CWE-401 Missing Release of Memory after Effective Lifetime\n      2. CWE-772 Missing Release of Resource after Effective Lifetime\n\n      These vulnerabilities can lead to resource leaks, which can cause the application to consume an increasing amount of system resources over time, potentially leading to crashes or performance degradation.\n    cwe: CWE-404\n    function_names:\n      - gitGetCommits\n      - gitGetNote\n      - gitAddNote\n    filenames:\n      - lib/get-commits.js\n      - lib/git.js\n    classification: slightly promising\n```",
      "date": "2024-06-13T11:39:20.350246",
      "usage": {
        "prompt_tokens": 130511,
        "completion_tokens": 1191,
        "cost": 0.0341165
      }
    }
  ],
  "leads": [
    {
      "headline": "Improper Input Validation",
      "analysis": "The codebase contains vulnerabilities related to improper input validation, including:\n\n1. CWE-1284 Improper Validation of Specified Quantity in Input\n2. CWE-129 Improper Validation of Array Index\n\nThese vulnerabilities can allow an attacker to bypass input validation checks and potentially execute arbitrary code or access sensitive data.\n",
      "classification": "very promising",
      "cwe": "CWE-20",
      "function_names": [
        "getCommits",
        "gitGetCommits"
      ],
      "filenames": [
        "lib/get-commits.js",
        "lib/git.js"
      ]
    },
    {
      "headline": "Injection Vulnerabilities",
      "analysis": "The codebase contains several injection vulnerabilities, including:\n\n1. CWE-77 Improper Neutralization of Special Elements used in a Command ('Command Injection')\n2. CWE-79 Improper Neutralization of Input During Web Page Generation ('Cross-site Scripting')\n3. CWE-89 Improper Neutralization of Special Elements used in an SQL Command ('SQL Injection')\n\nThese vulnerabilities can allow an attacker to inject malicious code or commands into the application, potentially leading to remote code execution, data breaches, or other serious consequences.\n",
      "classification": "very promising",
      "cwe": "CWE-74",
      "function_names": [
        "getGitAuthUrl",
        "repoUrl"
      ],
      "filenames": [
        "lib/get-git-auth-url.js",
        "lib/git.js"
      ]
    },
    {
      "headline": "Cleartext Transmission of Sensitive Information",
      "analysis": "The codebase contains a vulnerability related to the cleartext transmission of sensitive information, specifically CWE-319 Cleartext Transmission of Sensitive Information.\n\nThis vulnerability can allow an attacker to intercept and read sensitive information, such as authentication credentials or private data, during transmission between the application and the remote repository.\n",
      "classification": "slightly promising",
      "cwe": "CWE-311",
      "function_names": [
        "getGitAuthUrl"
      ],
      "filenames": [
        "lib/get-git-auth-url.js"
      ]
    },
    {
      "headline": "Improper Restriction of Operations within the Bounds of a Memory Buffer",
      "analysis": "The codebase contains vulnerabilities related to improper restriction of operations within the bounds of a memory buffer, including:\n\n1. CWE-120 Buffer Copy without Checking Size of Input ('Classic Buffer Overflow')\n2. CWE-125 Out-of-bounds Read\n\nThese vulnerabilities can allow an attacker to overwrite or read from memory locations outside of the intended buffer, potentially leading to crashes, data corruption, or even remote code execution.\n",
      "classification": "slightly promising",
      "cwe": "CWE-119",
      "function_names": [
        "gitGetCommits",
        "getCommits"
      ],
      "filenames": [
        "lib/get-commits.js",
        "lib/git.js"
      ]
    },
    {
      "headline": "Improper Authentication",
      "analysis": "The codebase contains several vulnerabilities related to improper authentication, including:\n\n1. CWE-306 Missing Authentication for Critical Function\n2. CWE-307 Improper Restriction of Excessive Authentication Attempts\n3. CWE-522 Insufficiently Protected Credentials\n\nThese vulnerabilities can allow an attacker to bypass authentication mechanisms and gain unauthorized access to the application or its resources.\n",
      "classification": "slightly promising",
      "cwe": "CWE-287",
      "function_names": [
        "verifyAuth"
      ],
      "filenames": [
        "lib/git.js"
      ]
    },
    {
      "headline": "Improper Synchronization",
      "analysis": "The codebase contains a vulnerability related to improper synchronization, specifically CWE-362 Concurrent Execution using Shared Resource with Improper Synchronization ('Race Condition').\n\nThis vulnerability can allow multiple concurrent processes to access and modify shared resources in an unpredictable manner, potentially leading to data inconsistencies or other unintended behavior.\n",
      "classification": "slightly promising",
      "cwe": "CWE-362",
      "function_names": [
        "gitGetCommits",
        "getCommits"
      ],
      "filenames": [
        "lib/get-commits.js",
        "lib/git.js"
      ]
    },
    {
      "headline": "Improper Resource Shutdown or Release",
      "analysis": "The codebase contains vulnerabilities related to improper resource shutdown or release, including:\n\n1. CWE-401 Missing Release of Memory after Effective Lifetime\n2. CWE-772 Missing Release of Resource after Effective Lifetime\n\nThese vulnerabilities can lead to resource leaks, which can cause the application to consume an increasing amount of system resources over time, potentially leading to crashes or performance degradation.\n",
      "classification": "slightly promising",
      "cwe": "CWE-404",
      "function_names": [
        "gitGetCommits",
        "gitGetNote",
        "gitAddNote"
      ],
      "filenames": [
        "lib/get-commits.js",
        "lib/git.js"
      ]
    }
  ],
  "scores": [
    {
      "stats": {
        "fn": 2,
        "tp": 0,
        "fp": 2
      },
      "mapping": {},
      "vuln_dates": {
        "CVE-2020-26226": "2020-11-18T22:15:12",
        "CVE-2022-31051": "2022-06-09T20:15:08"
      },
      "scoring_model": "claude-3-opus-20240229",
      "type": "llm",
      "instruction_template_hash": "245ace12b6361954d0a2"
    },
    {
      "stats": {
        "fn": 2,
        "tp": 0,
        "fp": 2
      },
      "mapping": {},
      "vuln_dates": {
        "CVE-2020-26226": "2020-11-18T22:15:12",
        "CVE-2022-31051": "2022-06-09T20:15:08"
      },
      "scoring_model": "claude-3-5-sonnet-20240620",
      "type": "llm",
      "instruction_template_hash": "245ace12b6361954d0a2"
    }
  ],
  "instruction_template_hash": "10c0163db4740318a544",
  "version": "0.1.0"
}
