{
  "commit": "da953f20cca0f7b03fa56eaa65aba8d9a45afbe9",
  "repo_url": "https://github.com/saleor/auth-sdk",
  "model": "gpt-4o-2024-05-13",
  "chunk_hashes": [
    "37d05c897b4b2ccfb168"
  ],
  "responses": [
    {
      "content": "```yaml\nleads:\n  - headline: \"Potential Cleartext Storage of Sensitive Information in Cookies\"\n    analysis: |\n      In the `src/next/server.ts` file, the `setItem` method of the `StorageRepository` interface is setting cookies without enforcing the use of secure attributes explicitly (`httpOnly`, `sameSite`, and `secure`). This could lead to scenarios where sensitive information (like JWT tokens) is stored in a non-secure manner if the options provided by the user do not enforce these attributes, increasing the risk of stealing this information through vulnerabilities like Cross-Site Scripting (XSS).\n    cwe: CWE-311\n    function_names:\n      - tryGetExpFromJwt\n      - getNextServerCookiesStorage\n    filenames:\n      - src/next/server.ts\n    classification: very promising\n\n  - headline: \"Information Exposure Through Query result Logs\"\n    analysis: |\n      In `src/SaleorExternalAuth.ts`, the `makePOSTRequest` function logs errors received from query results to the console. This could potentially expose sensitive information to unauthorized individuals who have access to application logs, revealing internal workings and data related to the GraphQL operations.\n    cwe: CWE-209\n    function_names:\n      - makePOSTRequest\n    filenames:\n      - src/SaleorExternalAuth.ts\n    classification: slightly promising\n\n  - headline: \"Potential Risk of Command Injection in Fetch Mock Setup\"\n    analysis: |\n      In `test/SaleorExternalAuth.test.ts` and `test/SaleorAuthClient.test.ts`, the usage of `fetchMock.mockResponseOnce` and similar methods improperly validates the input fetched from potentially untrusted sources. This could lead to command injection vulnerabilities if an attacker manages to influence the input parameters being tested.\n    cwe: CWE-77\n    function_names:\n      - Not directly applicable\n    filenames:\n      - test/SaleorExternalAuth.test.ts\n      - test/SaleorAuthClient.test.ts\n    classification: slightly promising\n    \n  - headline: \"Weak Error Handling in Auth Token Refresh\"\n    analysis: |\n      In `SaleorAuthClient.ts`, the `handleRequestWithTokenRefresh` method does not have exhaustive error-handling mechanisms in place. If the token refresh request fails or returns errors, it simply sets the tokens to null and attempts to proceed, potentially compromising security by not handling edge cases or responding to error states adequately.\n    cwe: CWE-754\n    function_names:\n      - handleRequestWithTokenRefresh\n    filenames:\n      - src/SaleorAuthClient.ts\n    classification: very promising\n\n  - headline: \"Unsafe Token Decoding Implementation\"\n    analysis: |\n      The `decodeToken` function in `src/utils.ts` assumes the token is correctly formatted and base64 encoded without any validation or error handling. This can result in the application crashing if an invalid token is provided, creating a potential denial of service (DoS) scenario.\n    cwe: CWE-704\n    function_names:\n      - decodeToken\n    filenames:\n      - src/utils.ts\n    classification: very promising\n```",
      "date": "2024-06-09T14:42:47.842164",
      "usage": {
        "prompt_tokens": 12042,
        "completion_tokens": 640,
        "cost": 0.06981
      }
    }
  ],
  "leads": [
    {
      "headline": "Potential Cleartext Storage of Sensitive Information in Cookies",
      "analysis": "In the src/next/server.ts file, the setItem method of the StorageRepository interface is setting cookies without enforcing the use of secure attributes explicitly (httpOnly, sameSite, and secure). This could lead to scenarios where sensitive information (like JWT tokens) is stored in a non-secure manner if the options provided by the user do not enforce these attributes, increasing the risk of stealing this information through vulnerabilities like Cross-Site Scripting (XSS).\n",
      "classification": "very promising",
      "cwe": "CWE-311",
      "function_names": [
        "tryGetExpFromJwt",
        "getNextServerCookiesStorage"
      ],
      "filenames": [
        "src/next/server.ts"
      ]
    },
    {
      "headline": "Information Exposure Through Query result Logs",
      "analysis": "In src/SaleorExternalAuth.ts, the makePOSTRequest function logs errors received from query results to the console. This could potentially expose sensitive information to unauthorized individuals who have access to application logs, revealing internal workings and data related to the GraphQL operations.\n",
      "classification": "slightly promising",
      "cwe": "CWE-209",
      "function_names": [
        "makePOSTRequest"
      ],
      "filenames": [
        "src/SaleorExternalAuth.ts"
      ]
    },
    {
      "headline": "Potential Risk of Command Injection in Fetch Mock Setup",
      "analysis": "In test/SaleorExternalAuth.test.ts and test/SaleorAuthClient.test.ts, the usage of fetchMock.mockResponseOnce and similar methods improperly validates the input fetched from potentially untrusted sources. This could lead to command injection vulnerabilities if an attacker manages to influence the input parameters being tested.\n",
      "classification": "slightly promising",
      "cwe": "CWE-77",
      "function_names": [
        "Not directly applicable"
      ],
      "filenames": [
        "test/SaleorExternalAuth.test.ts",
        "test/SaleorAuthClient.test.ts"
      ]
    },
    {
      "headline": "Weak Error Handling in Auth Token Refresh",
      "analysis": "In SaleorAuthClient.ts, the handleRequestWithTokenRefresh method does not have exhaustive error-handling mechanisms in place. If the token refresh request fails or returns errors, it simply sets the tokens to null and attempts to proceed, potentially compromising security by not handling edge cases or responding to error states adequately.\n",
      "classification": "very promising",
      "cwe": "CWE-754",
      "function_names": [
        "handleRequestWithTokenRefresh"
      ],
      "filenames": [
        "src/SaleorAuthClient.ts"
      ]
    },
    {
      "headline": "Unsafe Token Decoding Implementation",
      "analysis": "The decodeToken function in src/utils.ts assumes the token is correctly formatted and base64 encoded without any validation or error handling. This can result in the application crashing if an invalid token is provided, creating a potential denial of service (DoS) scenario.\n",
      "classification": "very promising",
      "cwe": "CWE-704",
      "function_names": [
        "decodeToken"
      ],
      "filenames": [
        "src/utils.ts"
      ]
    }
  ],
  "scores": [
    {
      "stats": {
        "fn": 1,
        "tp": 0,
        "fp": 3
      },
      "mapping": {},
      "vuln_dates": {
        "CVE-2024-29036": "2024-03-20T21:15:31"
      },
      "scoring_model": "gpt-4o-2024-05-13",
      "type": "llm",
      "instruction_template_hash": "8998f09cf57fca8a6e03"
    }
  ],
  "instruction_template_hash": "10c0163db4740318a544",
  "version": "0.1.0"
}
