{
  "commit": "46f66a9e091f752ed74dade8101ea4f201a95b5e",
  "repo_url": "https://github.com/operatorequals/wormnest",
  "model": "claude-3-sonnet-20240229",
  "chunk_hashes": [
    "2ac50fb19139ae7e0977"
  ],
  "responses": [
    {
      "content": "```yaml\nleads:\n  - headline: Improper input validation\n    analysis: |\n      The application does not properly validate user input, allowing an attacker to potentially inject malicious data or code. This could lead to various types of injection vulnerabilities such as SQL injection, cross-site scripting (XSS), code injection, and others.\n    cwe: CWE-20\n    function_names:\n      - resolve_url\n    filenames:\n      - app.py\n    classification: very promising\n\n  - headline: Potential server-side request forgery (SSRF)\n    analysis: |\n      The application constructs URLs using user-supplied input and fetches resources from those URLs using the `urllib.request.urlopen` function. This could potentially allow an attacker to access internal resources or make requests to unintended destinations, leading to a server-side request forgery (SSRF) vulnerability.\n    cwe: CWE-918\n    function_names:\n      - load_defaults\n    filenames:\n      - app.py\n    classification: very promising\n\n  - headline: Inclusion of functionality from untrusted control sphere\n    analysis: |\n      The application dynamically loads and executes Python modules (hooks) specified in the `HOOK_SCRIPTS` environment variable. This could potentially allow an attacker to execute arbitrary code if they can control the contents of the environment variable or the files specified in it.\n    cwe: CWE-829\n    function_names:\n      - parse_config\n    filenames:\n      - wormnest/utils.py\n    classification: very promising\n\n  - headline: Potential directory traversal vulnerability\n    analysis: |\n      The application serves files from a directory specified in the `SRV_DIR` environment variable. If this directory is not properly sanitized or validated, an attacker could potentially access files outside of the intended directory, leading to a directory traversal vulnerability.\n    cwe: CWE-22\n    function_names:\n      - dir_listing\n    filenames:\n      - app.py\n    classification: slightly promising\n\n  - headline: Potential code injection vulnerability\n    analysis: |\n      The application uses the `os.system` function to execute a shell command when serving random data. If the command is not properly sanitized or validated, an attacker could potentially inject malicious code, leading to a code injection vulnerability.\n    cwe: CWE-78\n    function_names:\n      - serve_random\n    filenames:\n      - hooks/serve_random.py\n    classification: slightly promising\n\n  - headline: Potential open redirect vulnerability\n    analysis: |\n      The application redirects users to a URL specified in the `REDIRECT_URL` environment variable. If this URL is not properly validated or sanitized, an attacker could potentially redirect users to a malicious site, leading to an open redirect vulnerability.\n    cwe: CWE-601\n    function_names:\n      - redirect_away\n    filenames:\n      - app.py\n    classification: slightly promising\n\n  - headline: Potential exposure of sensitive information\n    analysis: |\n      The application logs request data, including user agent strings, IP addresses, and file contents, to a file named `wormnest_access.ndjson`. If this file is not properly protected or sanitized, it could potentially expose sensitive information to unauthorized parties.\n    cwe: CWE-200\n    function_names:\n      - req_log_hook\n    filenames:\n      - hooks/req_log_hook.py\n    classification: slightly promising\n```\n\nThe codebase contains several potential security vulnerabilities, including improper input validation, server-side request forgery (SSRF), inclusion of functionality from untrusted control spheres, directory traversal, code injection, open redirect, and exposure of sensitive information. The analysis section provides an explanation of how these vulnerabilities could be exploited, and the CWE IDs identify the root causes according to the Common Weakness Enumeration (CWE) list.",
      "date": "2024-06-14T15:05:04.319710",
      "usage": {
        "prompt_tokens": 14169,
        "completion_tokens": 909,
        "cost": 0.056142
      }
    }
  ],
  "leads": [
    {
      "headline": "Improper input validation",
      "analysis": "The application does not properly validate user input, allowing an attacker to potentially inject malicious data or code. This could lead to various types of injection vulnerabilities such as SQL injection, cross-site scripting (XSS), code injection, and others.\n",
      "classification": "very promising",
      "cwe": "CWE-20",
      "function_names": [
        "resolve_url"
      ],
      "filenames": [
        "app.py"
      ]
    },
    {
      "headline": "Potential server-side request forgery (SSRF)",
      "analysis": "The application constructs URLs using user-supplied input and fetches resources from those URLs using the urllib.request.urlopen function. This could potentially allow an attacker to access internal resources or make requests to unintended destinations, leading to a server-side request forgery (SSRF) vulnerability.\n",
      "classification": "very promising",
      "cwe": "CWE-918",
      "function_names": [
        "load_defaults"
      ],
      "filenames": [
        "app.py"
      ]
    },
    {
      "headline": "Inclusion of functionality from untrusted control sphere",
      "analysis": "The application dynamically loads and executes Python modules (hooks) specified in the HOOK_SCRIPTS environment variable. This could potentially allow an attacker to execute arbitrary code if they can control the contents of the environment variable or the files specified in it.\n",
      "classification": "very promising",
      "cwe": "CWE-829",
      "function_names": [
        "parse_config"
      ],
      "filenames": [
        "wormnest/utils.py"
      ]
    },
    {
      "headline": "Potential directory traversal vulnerability",
      "analysis": "The application serves files from a directory specified in the SRV_DIR environment variable. If this directory is not properly sanitized or validated, an attacker could potentially access files outside of the intended directory, leading to a directory traversal vulnerability.\n",
      "classification": "slightly promising",
      "cwe": "CWE-22",
      "function_names": [
        "dir_listing"
      ],
      "filenames": [
        "app.py"
      ]
    },
    {
      "headline": "Potential code injection vulnerability",
      "analysis": "The application uses the os.system function to execute a shell command when serving random data. If the command is not properly sanitized or validated, an attacker could potentially inject malicious code, leading to a code injection vulnerability.\n",
      "classification": "slightly promising",
      "cwe": "CWE-78",
      "function_names": [
        "serve_random"
      ],
      "filenames": [
        "hooks/serve_random.py"
      ]
    },
    {
      "headline": "Potential open redirect vulnerability",
      "analysis": "The application redirects users to a URL specified in the REDIRECT_URL environment variable. If this URL is not properly validated or sanitized, an attacker could potentially redirect users to a malicious site, leading to an open redirect vulnerability.\n",
      "classification": "slightly promising",
      "cwe": "CWE-601",
      "function_names": [
        "redirect_away"
      ],
      "filenames": [
        "app.py"
      ]
    },
    {
      "headline": "Potential exposure of sensitive information",
      "analysis": "The application logs request data, including user agent strings, IP addresses, and file contents, to a file named wormnest_access.ndjson. If this file is not properly protected or sanitized, it could potentially expose sensitive information to unauthorized parties.\n",
      "classification": "slightly promising",
      "cwe": "CWE-200",
      "function_names": [
        "req_log_hook"
      ],
      "filenames": [
        "hooks/req_log_hook.py"
      ]
    }
  ],
  "scores": [
    {
      "stats": {
        "fn": 1,
        "tp": 0,
        "fp": 3
      },
      "mapping": {},
      "vuln_dates": {
        "CVE-2022-31502": "2022-07-11T01:15:08"
      },
      "scoring_model": "claude-3-opus-20240229",
      "type": "llm",
      "instruction_template_hash": "245ace12b6361954d0a2"
    }
  ],
  "instruction_template_hash": "10c0163db4740318a544",
  "version": "0.1.0"
}
