{
  "commit": "aa63312d201d65ef46cede992ab13388ff79e679",
  "repo_url": "https://github.com/rjbs/email-mime",
  "model": "claude-3-haiku-20240307",
  "chunk_hashes": [
    "ad416f6aad9461fd1a46"
  ],
  "responses": [
    {
      "content": "Here is the YAML object equivalent to type LeadList, with the security vulnerabilities identified in the codebase:\n\n```yaml\nleads:\n  - headline: Insufficient Encryption Strength\n    analysis: |\n      The codebase uses weak or outdated encryption algorithms, which can be easily broken by attackers. This vulnerability allows an attacker to decrypt the contents of the message, potentially exposing sensitive information.\n    cwe: CWE-326\n    function_names: []\n    filenames:\n      - lib/Email/MIME.pm\n    classification: very promising\n\n  - headline: Improper Neutralization of Special Elements used in an OS Command ('OS Command Injection')\n    analysis: |\n      The codebase does not properly sanitize user input before using it in OS commands, which could allow an attacker to inject malicious commands and take control of the system.\n    cwe: CWE-78\n    function_names:\n      - Email::MIME::Creator::_construct_part\n    filenames:\n      - lib/Email/MIME/Creator.pm\n    classification: very promising\n\n  - headline: Improper Neutralization of Special Elements used in an Expression Language Statement ('Expression Language Injection')\n    analysis: |\n      The codebase uses user input in expression language statements without proper sanitization, which could allow an attacker to inject malicious code and gain unauthorized access.\n    cwe: CWE-917\n    function_names: []\n    filenames:\n      - lib/Email/MIME/Header.pm\n    classification: slightly promising\n\n  - headline: Improper Validation of Specified Quantity in Input\n    analysis: |\n      The codebase does not properly validate the length or quantity of user input, which could lead to buffer overflow or other vulnerabilities.\n    cwe: CWE-1284\n    function_names:\n      - Email::MIME::new\n      - Email::MIME::create\n    filenames:\n      - lib/Email/MIME.pm\n    classification: slightly promising\n\n  - headline: Improper Validation of Array Index\n    analysis: |\n      The codebase does not properly validate array indices, which could lead to out-of-bounds read or write vulnerabilities.\n    cwe: CWE-129\n    function_names:\n      - Email::MIME::parts_set\n      - Email::MIME::parts_add\n    filenames:\n      - lib/Email/MIME.pm\n    classification: slightly promising\n```",
      "date": "2024-06-09T14:35:43.158359",
      "usage": {
        "prompt_tokens": 34999,
        "completion_tokens": 576,
        "cost": 0.00946975
      }
    }
  ],
  "leads": [
    {
      "headline": "Insufficient Encryption Strength",
      "analysis": "The codebase uses weak or outdated encryption algorithms, which can be easily broken by attackers. This vulnerability allows an attacker to decrypt the contents of the message, potentially exposing sensitive information.\n",
      "classification": "very promising",
      "cwe": "CWE-326",
      "function_names": [],
      "filenames": [
        "lib/Email/MIME.pm"
      ]
    },
    {
      "headline": "Improper Neutralization of Special Elements used in an OS Command ('OS Command Injection')",
      "analysis": "The codebase does not properly sanitize user input before using it in OS commands, which could allow an attacker to inject malicious commands and take control of the system.\n",
      "classification": "very promising",
      "cwe": "CWE-78",
      "function_names": [
        "Email::MIME::Creator::_construct_part"
      ],
      "filenames": [
        "lib/Email/MIME/Creator.pm"
      ]
    },
    {
      "headline": "Improper Neutralization of Special Elements used in an Expression Language Statement ('Expression Language Injection')",
      "analysis": "The codebase uses user input in expression language statements without proper sanitization, which could allow an attacker to inject malicious code and gain unauthorized access.\n",
      "classification": "slightly promising",
      "cwe": "CWE-917",
      "function_names": [],
      "filenames": [
        "lib/Email/MIME/Header.pm"
      ]
    },
    {
      "headline": "Improper Validation of Specified Quantity in Input",
      "analysis": "The codebase does not properly validate the length or quantity of user input, which could lead to buffer overflow or other vulnerabilities.\n",
      "classification": "slightly promising",
      "cwe": "CWE-1284",
      "function_names": [
        "Email::MIME::new",
        "Email::MIME::create"
      ],
      "filenames": [
        "lib/Email/MIME.pm"
      ]
    },
    {
      "headline": "Improper Validation of Array Index",
      "analysis": "The codebase does not properly validate array indices, which could lead to out-of-bounds read or write vulnerabilities.\n",
      "classification": "slightly promising",
      "cwe": "CWE-129",
      "function_names": [
        "Email::MIME::parts_set",
        "Email::MIME::parts_add"
      ],
      "filenames": [
        "lib/Email/MIME.pm"
      ]
    }
  ],
  "scores": [
    {
      "stats": {
        "fn": 1,
        "tp": 0,
        "fp": 2
      },
      "mapping": {},
      "vuln_dates": {
        "CVE-2024-4140": "2024-05-02T20:15:07"
      },
      "scoring_model": "gpt-4o-2024-05-13",
      "type": "llm",
      "instruction_template_hash": "8998f09cf57fca8a6e03"
    }
  ],
  "instruction_template_hash": "10c0163db4740318a544",
  "version": "0.1.0"
}
