{
  "commit": "1b8ea5c4d14dd08ee21d69ce060f7cb01d216535",
  "repo_url": "https://github.com/fgribreau/node-request-retry",
  "model": "gpt-4-turbo-2024-04-09",
  "chunk_hashes": [
    "72936f5a615803dfbb45"
  ],
  "responses": [
    {
      "content": "```yaml\nleads:\n  - headline: Potential misuse of user-provided options leading to command execution or resource manipulation\n    analysis: |\n      The code does not consistently validate or sanitize the `options` object used throughout requests. This includes direct use in HTTP request components and external system calls, where manipulation by an attacker could lead to resource manipulation or command execution. Specifically, the top-level functions accept an `options` object which populates HTTP request properties without any checks, allowing an attacker to inject harmful values.\n    cwe: CWE-20\n    function_names:\n      - makeHelper\n      - Factory\n    filenames:\n      - /index.js\n    classification: very promising\n\n  - headline: Potential for retry attacks or denial of service through the retry strategy logic\n    analysis: |\n      The custom retry logic applied in `Request.prototype._tryUntilFail` could let an attacker purposefully trigger retries by causing controlled failures, potentially leading to service unavailability or resource exhaustion. An insufficient strategy for determining when to stop retrying could be exploited to cause repeated computation or network requests, leading to a denial of service.\n    cwe: CWE-400\n    function_names:\n      - _tryUntilFail\n    filenames:\n      - /index.js\n    classification: slightly promising\n\n  - headline: Inadequate exception management in promise handling\n    analysis: |\n      The `makePromise` and promise method registrars like `Request.prototype['then']` and `Request.prototype['catch']` suggest custom promise handling but do not contain adequate guards against promise construction errors or ensure promises are always correctly resolved/rejected. Mismanagement of these promise states could lead to unhandled exception scenarios in asynchronous operations.\n    cwe: CWE-754\n    function_names:\n      - makePromise\n      - Request.prototype['then']\n      - Request.prototype['catch']\n    filenames:\n      - /index.js\n    classification: slightly promising\n\n  - headline: Use of potentially unsafe regular expression in retry options\n    analysis: |\n      The implementation of delay strategies using a user-defined `delayStrategy` function in the retry mechanism allows for any custom logic including potentially unsafe or inefficient regex operations, which an attacker could exploit to trigger a Denial of Service via catastrophic backtracking or other expensive pattern evaluations.\n    cwe: CWE-1333\n    function_names:\n      - Request\n    filenames:\n      - /index.js\n    classification: slightly promising\n\n  - headline: Risk of HTTP request smuggling or unexpected HTTP behaviors via HTTP method injections\n    analysis: |\n      The application constructs HTTP requests based on user input without proper sanitization or validation, particularly where the method can be supplied or altered. This design could be exploited to alter the behavior of the server or intermediate proxies, potentially leading to HTTP request smuggling attacks.\n    cwe: CWE-444\n    function_names:\n      - makeHelper\n    filenames:\n      - /index.js\n    classification: very promising\n\n  - headline: Information leakage through error messages and logs\n    analysis: |\n      Error handling in multiple locations logs or exposes detailed information about the internal state or result of operations, which could aid an attacker in designing further attacks or gaining unauthorized knowledge about the system.\n    cwe: CWE-209\n    function_names:\n      - reply\n      - Request.prototype.abort\n    filenames:\n      - /index.js\n    classification: slightly promising\n```",
      "date": "2024-06-12T16:33:00.454274",
      "usage": {
        "prompt_tokens": 10670,
        "completion_tokens": 692,
        "cost": 0.12746
      }
    }
  ],
  "leads": [
    {
      "headline": "Potential misuse of user-provided options leading to command execution or resource manipulation",
      "analysis": "The code does not consistently validate or sanitize the options object used throughout requests. This includes direct use in HTTP request components and external system calls, where manipulation by an attacker could lead to resource manipulation or command execution. Specifically, the top-level functions accept an options object which populates HTTP request properties without any checks, allowing an attacker to inject harmful values.\n",
      "classification": "very promising",
      "cwe": "CWE-20",
      "function_names": [
        "makeHelper",
        "Factory"
      ],
      "filenames": [
        "/index.js"
      ]
    },
    {
      "headline": "Potential for retry attacks or denial of service through the retry strategy logic",
      "analysis": "The custom retry logic applied in Request.prototype._tryUntilFail could let an attacker purposefully trigger retries by causing controlled failures, potentially leading to service unavailability or resource exhaustion. An insufficient strategy for determining when to stop retrying could be exploited to cause repeated computation or network requests, leading to a denial of service.\n",
      "classification": "slightly promising",
      "cwe": "CWE-400",
      "function_names": [
        "_tryUntilFail"
      ],
      "filenames": [
        "/index.js"
      ]
    },
    {
      "headline": "Inadequate exception management in promise handling",
      "analysis": "The makePromise and promise method registrars like Request.prototype['then'] and Request.prototype['catch'] suggest custom promise handling but do not contain adequate guards against promise construction errors or ensure promises are always correctly resolved/rejected. Mismanagement of these promise states could lead to unhandled exception scenarios in asynchronous operations.\n",
      "classification": "slightly promising",
      "cwe": "CWE-754",
      "function_names": [
        "makePromise",
        "Request.prototype['then']",
        "Request.prototype['catch']"
      ],
      "filenames": [
        "/index.js"
      ]
    },
    {
      "headline": "Use of potentially unsafe regular expression in retry options",
      "analysis": "The implementation of delay strategies using a user-defined delayStrategy function in the retry mechanism allows for any custom logic including potentially unsafe or inefficient regex operations, which an attacker could exploit to trigger a Denial of Service via catastrophic backtracking or other expensive pattern evaluations.\n",
      "classification": "slightly promising",
      "cwe": "CWE-1333",
      "function_names": [
        "Request"
      ],
      "filenames": [
        "/index.js"
      ]
    },
    {
      "headline": "Risk of HTTP request smuggling or unexpected HTTP behaviors via HTTP method injections",
      "analysis": "The application constructs HTTP requests based on user input without proper sanitization or validation, particularly where the method can be supplied or altered. This design could be exploited to alter the behavior of the server or intermediate proxies, potentially leading to HTTP request smuggling attacks.\n",
      "classification": "very promising",
      "cwe": "CWE-444",
      "function_names": [
        "makeHelper"
      ],
      "filenames": [
        "/index.js"
      ]
    },
    {
      "headline": "Information leakage through error messages and logs",
      "analysis": "Error handling in multiple locations logs or exposes detailed information about the internal state or result of operations, which could aid an attacker in designing further attacks or gaining unauthorized knowledge about the system.\n",
      "classification": "slightly promising",
      "cwe": "CWE-209",
      "function_names": [
        "reply",
        "Request.prototype.abort"
      ],
      "filenames": [
        "/index.js"
      ]
    }
  ],
  "scores": [
    {
      "stats": {
        "fn": 1,
        "tp": 0,
        "fp": 2
      },
      "mapping": {},
      "vuln_dates": {
        "CVE-2022-0654": "2022-02-23T00:15:07"
      },
      "scoring_model": "claude-3-opus-20240229",
      "type": "llm",
      "instruction_template_hash": "245ace12b6361954d0a2"
    }
  ],
  "instruction_template_hash": "10c0163db4740318a544",
  "version": "0.1.0"
}
