{
  "commit": "1d92eac8dea8efd4a271c0dd6ff59b0ef1d4dc9e",
  "repo_url": "https://github.com/jenkinsci/aws-codedeploy-plugin",
  "model": "gpt-4o-2024-05-13",
  "chunk_hashes": [
    "9cf6724ae4758a1b9ed7"
  ],
  "responses": [
    {
      "content": "```yaml\nleads:\n  - headline: \"Use of Hard-coded AWS Credentials\"\n    analysis: |\n      The code contains hard-coded AWS access and secret keys in the AWSClients class, which is prone to exploitation if the source code is leaked. The presence of hard-coded credentials in the source code is a serious security flaw as it can allow unauthorized access to the AWS resources if the source code is accessed by malicious users.\n    cwe: CWE-798\n    function_names:\n      - fromBasicCredentials\n      - configure\n    filenames:\n      - src/main/java/com/amazonaws/codedeploy/AWSClients.java\n      - src/main/java/com/amazonaws/codedeploy/AWSCodeDeployPublisher.java\n    classification: very promising\n\n  - headline: \"Potential Server-Side Request Forgery (SSRF) in getAccountId\"\n    analysis: |\n      The getAccountId function in the AWSClients class makes a call to AWS IAM without validating or sanitizing the proxyHost and proxyPort inputs. This can be exploited by attackers to achieve Server-Side Request Forgery (SSRF), where requests are redirected to malicious third-party sites or internal services.\n    cwe: CWE-918\n    function_names:\n      - getAccountId\n    filenames:\n      - src/main/java/com/amazonaws/codedeploy/AWSClients.java\n    classification: very promising\n\n  - headline: \"Weak Encryption Configuration\"\n    analysis: |\n      The code defaults to using a temporary file to store sensitive information such as AWS keys and file contents without ensuring encryption strength. Storing sensitive information in a temporary file without proper encryption can lead to unauthorized access if the system is compromised.\n    cwe: CWE-311\n    function_names:\n      - createTestFile\n    filenames:\n      - src/main/java/com/amazonaws/codedeploy/AWSClients.java\n    classification: slightly promising\n\n  - headline: \"Exposure of Sensitive Information in Logs\"\n    analysis: |\n      The code logs sensitive information such as AWS bucket names and file paths in the log files without addressing the associated risks. If the logs get accessed by unauthorized users, it might expose sensitive information.\n    cwe: CWE-200\n    function_names:\n      - zipAndUpload\n      - perform\n      - doTestConnection\n    filenames:\n      - src/main/java/com/amazonaws/codedeploy/AWSCodeDeployPublisher.java\n    classification: slightly promising\n\n  - headline: \"Improper Input Validation\"\n    analysis: |\n      The parameter values for bucket names and paths are directly accepted without validation. This can lead to issues such as path traversal or injection attacks if malicious input is provided.\n    cwe: CWE-20\n    function_names:\n      - perform\n      - verifyCodeDeployApplication\n      - zipAndUpload\n    filenames:\n      - src/main/java/com/amazonaws/codedeploy/AWSCodeDeployPublisher.java\n    classification: very promising\n```",
      "date": "2024-06-12T17:56:48.070667",
      "usage": {
        "prompt_tokens": 11334,
        "completion_tokens": 609,
        "cost": 0.065805
      }
    }
  ],
  "leads": [
    {
      "headline": "Use of Hard-coded AWS Credentials",
      "analysis": "The code contains hard-coded AWS access and secret keys in the AWSClients class, which is prone to exploitation if the source code is leaked. The presence of hard-coded credentials in the source code is a serious security flaw as it can allow unauthorized access to the AWS resources if the source code is accessed by malicious users.\n",
      "classification": "very promising",
      "cwe": "CWE-798",
      "function_names": [
        "fromBasicCredentials",
        "configure"
      ],
      "filenames": [
        "src/main/java/com/amazonaws/codedeploy/AWSClients.java",
        "src/main/java/com/amazonaws/codedeploy/AWSCodeDeployPublisher.java"
      ]
    },
    {
      "headline": "Potential Server-Side Request Forgery (SSRF) in getAccountId",
      "analysis": "The getAccountId function in the AWSClients class makes a call to AWS IAM without validating or sanitizing the proxyHost and proxyPort inputs. This can be exploited by attackers to achieve Server-Side Request Forgery (SSRF), where requests are redirected to malicious third-party sites or internal services.\n",
      "classification": "very promising",
      "cwe": "CWE-918",
      "function_names": [
        "getAccountId"
      ],
      "filenames": [
        "src/main/java/com/amazonaws/codedeploy/AWSClients.java"
      ]
    },
    {
      "headline": "Weak Encryption Configuration",
      "analysis": "The code defaults to using a temporary file to store sensitive information such as AWS keys and file contents without ensuring encryption strength. Storing sensitive information in a temporary file without proper encryption can lead to unauthorized access if the system is compromised.\n",
      "classification": "slightly promising",
      "cwe": "CWE-311",
      "function_names": [
        "createTestFile"
      ],
      "filenames": [
        "src/main/java/com/amazonaws/codedeploy/AWSClients.java"
      ]
    },
    {
      "headline": "Exposure of Sensitive Information in Logs",
      "analysis": "The code logs sensitive information such as AWS bucket names and file paths in the log files without addressing the associated risks. If the logs get accessed by unauthorized users, it might expose sensitive information.\n",
      "classification": "slightly promising",
      "cwe": "CWE-200",
      "function_names": [
        "zipAndUpload",
        "perform",
        "doTestConnection"
      ],
      "filenames": [
        "src/main/java/com/amazonaws/codedeploy/AWSCodeDeployPublisher.java"
      ]
    },
    {
      "headline": "Improper Input Validation",
      "analysis": "The parameter values for bucket names and paths are directly accepted without validation. This can lead to issues such as path traversal or injection attacks if malicious input is provided.\n",
      "classification": "very promising",
      "cwe": "CWE-20",
      "function_names": [
        "perform",
        "verifyCodeDeployApplication",
        "zipAndUpload"
      ],
      "filenames": [
        "src/main/java/com/amazonaws/codedeploy/AWSCodeDeployPublisher.java"
      ]
    }
  ],
  "scores": [
    {
      "stats": {
        "fn": 1,
        "tp": 1,
        "fp": 2
      },
      "mapping": {
        "0": "CVE-2018-1000403"
      },
      "vuln_dates": {
        "CVE-2018-1000402": "2018-07-09T13:29:00",
        "CVE-2018-1000403": "2018-07-09T13:29:00"
      },
      "scoring_model": "claude-3-opus-20240229",
      "type": "llm",
      "instruction_template_hash": "245ace12b6361954d0a2"
    }
  ],
  "instruction_template_hash": "10c0163db4740318a544",
  "version": "0.1.0"
}
