{
  "commit": "0e89d18bc5966dd9e62e89426e9ea63b2e0e617d",
  "repo_url": "https://github.com/darrenofficial/dpaste",
  "model": "claude-3-sonnet-20240229",
  "chunk_hashes": [
    "2929f62b2791e8469a04"
  ],
  "responses": [
    {
      "content": "```yaml\nleads:\n  - headline: Potential open redirect vulnerability\n    analysis: |\n      In the `APIView` class in the `dpaste/views.py` file, the `_format_url` method constructs the response URL by concatenating the `base_url` with the `get_absolute_url` method of the `Snippet` object. The `get_absolute_url` method relies on the `snippet_id` value, which is not sanitized or validated. If an attacker can control the `snippet_id` value, they could potentially cause an open redirect to an arbitrary external site.\n    cwe: CWE-601\n    function_names:\n      - _format_url\n      - get_absolute_url\n    filenames:\n      - dpaste/views.py\n      - dpaste/models.py\n    classification: slightly promising\n\n  - headline: Potential XML External Entity (XXE) vulnerability\n    analysis: |\n      The `RestructuredTextHighlighter` class in the `dpaste/highlight.py` file uses the Python `docutils` library to render reStructuredText content. The `docutils` library is known to be vulnerable to XML External Entity (XXE) attacks when parsing untrusted input. If an attacker can control the content rendered by `RestructuredTextHighlighter`, they could potentially exploit this vulnerability to perform various attacks, such as disclosing sensitive information or conducting server-side request forgery (SSRF) attacks.\n    cwe: CWE-611\n    function_names:\n      - highlight\n    filenames:\n      - dpaste/highlight.py\n    classification: slightly promising\n\n  - headline: Potential command injection vulnerability\n    analysis: |\n      The `render_plain_text` method in the `SnippetRawView` class in the `dpaste/views.py` file constructs an HTTP response by directly inserting the `content` of the `Snippet` object into the response body without sanitization or escaping. If an attacker can control the `content` value, they could potentially inject malicious commands or code, leading to a command injection vulnerability.\n    cwe: CWE-78\n    function_names:\n      - render_plain_text\n    filenames:\n      - dpaste/views.py\n    classification: slightly promising\n\n  - headline: Potential cross-site scripting (XSS) vulnerability\n    analysis: |\n      The `highlight` method in the `SnippetDetailView` class in the `dpaste/views.py` file passes the `content` of the `Snippet` object to the `render` method of the `Highlighter` class without proper sanitization or escaping. If an attacker can control the `content` value, they could potentially inject malicious scripts, leading to a cross-site scripting (XSS) vulnerability.\n    cwe: CWE-79\n    function_names:\n      - highlight\n      - render\n    filenames:\n      - dpaste/views.py\n      - dpaste/highlight.py\n    classification: slightly promising\n\n  - headline: Potential insecure deserialization vulnerability\n    analysis: |\n      The `Snippet` model in the `dpaste/models.py` file contains a `parent` field that accepts a foreign key reference to another `Snippet` object. If the `Snippet` object is deserialized from untrusted data, an attacker could potentially manipulate the `parent` field to reference arbitrary objects or perform other malicious actions, leading to an insecure deserialization vulnerability.\n    cwe: CWE-502\n    function_names: []\n    filenames:\n      - dpaste/models.py\n    classification: slightly promising\n\n  - headline: Potential SQL injection vulnerability\n    analysis: |\n      The `SnippetDetailView` class in the `dpaste/views.py` file retrieves `Snippet` objects from the database using the `get_object_or_404` function, which internally constructs an SQL query based on the provided `snippet_id`. If the `snippet_id` value is not properly sanitized, an attacker could potentially inject malicious SQL code, leading to an SQL injection vulnerability.\n    cwe: CWE-89\n    function_names:\n      - get_object\n      - get_object_or_404\n    filenames:\n      - dpaste/views.py\n    classification: slightly promising\n\n  - headline: Potential server-side request forgery (SSRF) vulnerability\n    analysis: |\n      The `get_base_url` method in the `dpaste/apps.py` file constructs the base URL for the application by retrieving the current site domain from the Django Sites framework. However, the `get_current_site` function can potentially be abused by an attacker to make requests to arbitrary internal or external URLs, leading to a server-side request forgery (SSRF) vulnerability.\n    cwe: CWE-918\n    function_names:\n      - get_base_url\n      - get_current_site\n    filenames:\n      - dpaste/apps.py\n    classification: slightly promising\n\n  - headline: Potential cryptographic issue\n    analysis: |\n      The `generate_secret_id` function in the `dpaste/models.py` file generates a random secret ID for new snippets using the `SystemRandom` class from the Python `random` module. However, the `SystemRandom` class is not recommended for cryptographic purposes, as it may not provide sufficient entropy or security guarantees. An attacker could potentially predict or brute-force the generated secret IDs, leading to potential security vulnerabilities.\n    cwe: CWE-330\n    function_names:\n      - generate_secret_id\n    filenames:\n      - dpaste/models.py\n    classification: slightly promising\n\n  - headline: Potential insecure configuration vulnerability\n    analysis: |\n      The `dpaste/settings/base.py` file contains various security-related settings, such as `CSRF_COOKIE_SECURE`, `SECURE_PROXY_SSL_HEADER`, and `CSP_DEFAULT_SRC`. If these settings are not configured correctly, they could potentially lead to security vulnerabilities, such as cross-site scripting (XSS), cross-site request forgery (CSRF), or other attacks.\n    cwe: CWE-16\n    function_names: []\n    filenames:\n      - dpaste/settings/base.py\n    classification: slightly promising\n\n  - headline: Potential unvalidated redirect vulnerability\n    analysis: |\n      The `SnippetView` class in the `dpaste/views.py` file performs a redirect after a successful submission of a new snippet. However, the URL for the redirect is constructed from the `get_absolute_url` method of the `Snippet` object, which relies on the `snippet_id` value. If the `snippet_id` value is not properly validated, an attacker could potentially cause an unvalidated redirect to an arbitrary external site.\n    cwe: CWE-601\n    function_names:\n      - form_valid\n      - get_absolute_url\n    filenames:\n      - dpaste/views.py\n      - dpaste/models.py\n    classification: slightly promising\n\n  - headline: Potential secret key exposure vulnerability\n    analysis: |\n      The `dpaste/settings/base.py` file retrieves the `SECRET_KEY` value from the environment variable `SECRET_KEY` or uses a hardcoded default value if the environment variable is not set. Storing secret keys directly in the codebase or using insecure default values could potentially lead to the exposure of sensitive information and compromise the application's security.\n    cwe: CWE-312\n    function_names: []\n    filenames:\n      - dpaste/settings/base.py\n    classification: slightly promising\n```\n\nThe codebase seems to have several potential security vulnerabilities, ranging from injection vulnerabilities (XSS, SQL injection, command injection, open redirect, etc.) to insecure deserialization, cryptographic issues, and configuration vulnerabilities. Most of these vulnerabilities stem from the lack of proper input validation and sanitization, as well as the use of insecure or outdated libraries and practices.\n\nHere are some of the key vulnerabilities identified:\n\n1. **Open Redirect Vulnerability**: The `_format_url` method in the `APIView` class and the `get_absolute_url` method in the `SnippetView` class construct URLs without properly validating the `snippet_id` parameter, potentially allowing an attacker to redirect users to arbitrary external sites.\n\n2. **XML External Entity (XXE) Vulnerability**: The `RestructuredTextHighlighter` class uses the `docutils` library to render reStructuredText content, which is known to be vulnerable to XXE attacks when parsing untrusted input.\n\n3. **Command Injection Vulnerability**: The `render_plain_text` method in the `SnippetRawView` class constructs an HTTP response by directly inserting the `content` of the `Snippet` object without proper sanitization, potentially allowing command injection attacks.\n\n4. **Cross-Site Scripting (XSS) Vulnerability**: The `highlight` method in the `SnippetDetailView` class passes the `content` of the `Snippet` object to the `render` method without proper sanitization, potentially allowing XSS attacks.\n\n5. **Insecure Deserialization Vulnerability**: The `Snippet` model in the `dpaste/models.py` file deserializes data from untrusted sources, potentially allowing an attacker to manipulate the `parent` field and perform unauthorized actions.\n\n6. **SQL Injection Vulnerability**: The `SnippetDetailView` class retrieves `Snippet` objects from the database using the `snippet_id` parameter without proper sanitization, potentially allowing SQL injection attacks.\n\n7. **Server-Side Request Forgery (SSRF) Vulnerability**: The `get_base_url` method in the `dpaste/apps.py` file retrieves the current site domain from the Django Sites framework, which could potentially be abused by an attacker to make requests to arbitrary internal or external URLs.\n\n8. **Cryptographic Issue**: The `generate_secret_id` function in the `dpaste/models.py` file uses the `SystemRandom` class from the Python `random` module, which is not recommended for cryptographic purposes and could potentially lead to predictable or weak secret IDs.\n\n9. **Insecure Configuration Vulnerability**: The `dpaste/settings/base.py` file contains various security-related settings, such as `CSRF_COOKIE_SECURE`, `SECURE_PROXY_SSL_HEADER`, and `CSP_DEFAULT_SRC`, which could potentially lead to security vulnerabilities if not configured correctly.\n\n10. **Secret Key Exposure Vulnerability**: The `dpaste/settings/base.py` file retrieves the `SECRET_KEY` value from the environment variable or uses a hardcoded default value, potentially exposing sensitive information if the default value is used or the environment variable is not properly secured.\n\nTo mitigate these vulnerabilities, the codebase should be thoroughly reviewed, and proper input validation, sanitization, and escaping techniques should be implemented. Additionally, the use of secure and up-to-date libraries and best practices for cryptography, configuration, and secure coding should be adopted. Regular security audits and penetration testing can also help identify and address potential vulnerabilities.",
      "date": "2024-06-09T11:23:13.034534",
      "usage": {
        "prompt_tokens": 37064,
        "completion_tokens": 2626,
        "cost": 0.150582
      }
    }
  ],
  "leads": [
    {
      "headline": "Potential open redirect vulnerability",
      "analysis": "In the APIView class in the dpaste/views.py file, the _format_url method constructs the response URL by concatenating the base_url with the get_absolute_url method of the Snippet object. The get_absolute_url method relies on the snippet_id value, which is not sanitized or validated. If an attacker can control the snippet_id value, they could potentially cause an open redirect to an arbitrary external site.\n",
      "classification": "slightly promising",
      "cwe": "CWE-601",
      "function_names": [
        "_format_url",
        "get_absolute_url"
      ],
      "filenames": [
        "dpaste/views.py",
        "dpaste/models.py"
      ]
    },
    {
      "headline": "Potential XML External Entity (XXE) vulnerability",
      "analysis": "The RestructuredTextHighlighter class in the dpaste/highlight.py file uses the Python docutils library to render reStructuredText content. The docutils library is known to be vulnerable to XML External Entity (XXE) attacks when parsing untrusted input. If an attacker can control the content rendered by RestructuredTextHighlighter, they could potentially exploit this vulnerability to perform various attacks, such as disclosing sensitive information or conducting server-side request forgery (SSRF) attacks.\n",
      "classification": "slightly promising",
      "cwe": "CWE-611",
      "function_names": [
        "highlight"
      ],
      "filenames": [
        "dpaste/highlight.py"
      ]
    },
    {
      "headline": "Potential command injection vulnerability",
      "analysis": "The render_plain_text method in the SnippetRawView class in the dpaste/views.py file constructs an HTTP response by directly inserting the content of the Snippet object into the response body without sanitization or escaping. If an attacker can control the content value, they could potentially inject malicious commands or code, leading to a command injection vulnerability.\n",
      "classification": "slightly promising",
      "cwe": "CWE-78",
      "function_names": [
        "render_plain_text"
      ],
      "filenames": [
        "dpaste/views.py"
      ]
    },
    {
      "headline": "Potential cross-site scripting (XSS) vulnerability",
      "analysis": "The highlight method in the SnippetDetailView class in the dpaste/views.py file passes the content of the Snippet object to the render method of the Highlighter class without proper sanitization or escaping. If an attacker can control the content value, they could potentially inject malicious scripts, leading to a cross-site scripting (XSS) vulnerability.\n",
      "classification": "slightly promising",
      "cwe": "CWE-79",
      "function_names": [
        "highlight",
        "render"
      ],
      "filenames": [
        "dpaste/views.py",
        "dpaste/highlight.py"
      ]
    },
    {
      "headline": "Potential insecure deserialization vulnerability",
      "analysis": "The Snippet model in the dpaste/models.py file contains a parent field that accepts a foreign key reference to another Snippet object. If the Snippet object is deserialized from untrusted data, an attacker could potentially manipulate the parent field to reference arbitrary objects or perform other malicious actions, leading to an insecure deserialization vulnerability.\n",
      "classification": "slightly promising",
      "cwe": "CWE-502",
      "function_names": [],
      "filenames": [
        "dpaste/models.py"
      ]
    },
    {
      "headline": "Potential SQL injection vulnerability",
      "analysis": "The SnippetDetailView class in the dpaste/views.py file retrieves Snippet objects from the database using the get_object_or_404 function, which internally constructs an SQL query based on the provided snippet_id. If the snippet_id value is not properly sanitized, an attacker could potentially inject malicious SQL code, leading to an SQL injection vulnerability.\n",
      "classification": "slightly promising",
      "cwe": "CWE-89",
      "function_names": [
        "get_object",
        "get_object_or_404"
      ],
      "filenames": [
        "dpaste/views.py"
      ]
    },
    {
      "headline": "Potential server-side request forgery (SSRF) vulnerability",
      "analysis": "The get_base_url method in the dpaste/apps.py file constructs the base URL for the application by retrieving the current site domain from the Django Sites framework. However, the get_current_site function can potentially be abused by an attacker to make requests to arbitrary internal or external URLs, leading to a server-side request forgery (SSRF) vulnerability.\n",
      "classification": "slightly promising",
      "cwe": "CWE-918",
      "function_names": [
        "get_base_url",
        "get_current_site"
      ],
      "filenames": [
        "dpaste/apps.py"
      ]
    },
    {
      "headline": "Potential cryptographic issue",
      "analysis": "The generate_secret_id function in the dpaste/models.py file generates a random secret ID for new snippets using the SystemRandom class from the Python random module. However, the SystemRandom class is not recommended for cryptographic purposes, as it may not provide sufficient entropy or security guarantees. An attacker could potentially predict or brute-force the generated secret IDs, leading to potential security vulnerabilities.\n",
      "classification": "slightly promising",
      "cwe": "CWE-330",
      "function_names": [
        "generate_secret_id"
      ],
      "filenames": [
        "dpaste/models.py"
      ]
    },
    {
      "headline": "Potential insecure configuration vulnerability",
      "analysis": "The dpaste/settings/base.py file contains various security-related settings, such as CSRF_COOKIE_SECURE, SECURE_PROXY_SSL_HEADER, and CSP_DEFAULT_SRC. If these settings are not configured correctly, they could potentially lead to security vulnerabilities, such as cross-site scripting (XSS), cross-site request forgery (CSRF), or other attacks.\n",
      "classification": "slightly promising",
      "cwe": "CWE-16",
      "function_names": [],
      "filenames": [
        "dpaste/settings/base.py"
      ]
    },
    {
      "headline": "Potential unvalidated redirect vulnerability",
      "analysis": "The SnippetView class in the dpaste/views.py file performs a redirect after a successful submission of a new snippet. However, the URL for the redirect is constructed from the get_absolute_url method of the Snippet object, which relies on the snippet_id value. If the snippet_id value is not properly validated, an attacker could potentially cause an unvalidated redirect to an arbitrary external site.\n",
      "classification": "slightly promising",
      "cwe": "CWE-601",
      "function_names": [
        "form_valid",
        "get_absolute_url"
      ],
      "filenames": [
        "dpaste/views.py",
        "dpaste/models.py"
      ]
    },
    {
      "headline": "Potential secret key exposure vulnerability",
      "analysis": "The dpaste/settings/base.py file retrieves the SECRET_KEY value from the environment variable SECRET_KEY or uses a hardcoded default value if the environment variable is not set. Storing secret keys directly in the codebase or using insecure default values could potentially lead to the exposure of sensitive information and compromise the application's security.\n",
      "classification": "slightly promising",
      "cwe": "CWE-312",
      "function_names": [],
      "filenames": [
        "dpaste/settings/base.py"
      ]
    }
  ],
  "scores": [
    {
      "stats": {
        "fn": 1,
        "tp": 0,
        "fp": 0
      },
      "mapping": {},
      "vuln_dates": {
        "CVE-2023-49277": "2023-12-01T21:15:08"
      },
      "scoring_model": "gpt-4o-2024-05-13",
      "type": "llm",
      "instruction_template_hash": "8998f09cf57fca8a6e03"
    },
    {
      "stats": {
        "fn": 1,
        "tp": 0,
        "fp": 0
      },
      "mapping": {},
      "vuln_dates": {
        "CVE-2023-49277": "2023-12-01T21:15:08"
      },
      "scoring_model": "claude-3-opus-20240229",
      "type": "llm",
      "instruction_template_hash": "245ace12b6361954d0a2"
    },
    {
      "stats": {
        "fn": 1,
        "tp": 0,
        "fp": 0
      },
      "mapping": {},
      "vuln_dates": {
        "CVE-2023-49277": "2023-12-01T21:15:08"
      },
      "scoring_model": "claude-3-5-sonnet-20240620",
      "type": "llm",
      "instruction_template_hash": "245ace12b6361954d0a2"
    }
  ],
  "instruction_template_hash": "10c0163db4740318a544",
  "version": "0.1.0"
}
