{
  "commit": "120ad4f6356f50e861acc15f826132c4c9d0e7e3",
  "repo_url": "https://github.com/oamg/convert2rhel",
  "model": "gpt-4o-2024-05-13",
  "chunk_hashes": [
    "82103e68f56c14c6e8fe"
  ],
  "responses": [
    {
      "content": "```yaml\nleads:\n  - headline: Missing error checking for file operations\n    analysis: |\n      Multiple instances of file operations (like file reading and writing) lack error handling. This can lead to unexpected crashes or undefined behavior if the files are missing or unreadable.\n    cwe: CWE-252\n    function_names:\n      - read\n      - store_content_to_file\n    filenames:\n      - convert2rhel/__init__.py\n      - convert2rhel/utils.py\n    classification: very promising\n\n  - headline: Absence of permission checks for critical operations\n    analysis: |\n      Various critical operations such as restarting the system or modifying configuration files do not have proper permissions checks. This can lead to unauthorized use and potential system compromise.\n    cwe: CWE-284\n    function_names:\n      - restart_system\n      - remove_pkgs\n    filenames:\n      - convert2rhel/utils.py\n      - convert2rhel/pkghandler.py\n    classification: very promising\n\n  - headline: Inadequate validation of input arguments\n    analysis: |\n      Many functions accept arguments without sufficient validation, which could be exploited by an attacker to inject malicious inputs, potentially leading to arbitrary code execution or data manipulation.\n    cwe: CWE-20\n    function_names:\n      - call_yum_cmd\n      - ensure_compatibility_of_kmods\n      - download_pkg\n    filenames:\n      - convert2rhel/pkghandler.py\n      - convert2rhel/checks.py\n      - convert2rhel/utils.py\n    classification: very promising\n\n  - headline: Use of hard-coded credentials in the codebase\n    analysis: |\n      Hard-coded credentials are present in several parts of the codebase, which could be easily extracted by an attacker with access to the source code, leading to unauthorized access to system resources.\n    cwe: CWE-798\n    function_names:\n    filenames:\n      - convert2rhel/tests/integration/method/satellite.py\n    classification: very promising\n\n  - headline: Data exposure through logging\n    analysis: |\n      Sensitive data such as passwords are logged without proper masking. An attacker with access to the logs can retrieve these sensitive details, leading to potential unauthorized access.\n    cwe: CWE-532\n    function_names:\n      - call_registration_cmd\n    filenames:\n      - convert2rhel/subscription.py\n    classification: very promising\n\n  - headline: Command injection via unsanitized user input\n    analysis: |\n      There are instances where user inputs are directly included in command-line executions without proper sanitization. This could allow an attacker to inject malicious commands.\n    cwe: CWE-78\n    function_names:\n      - run_subprocess\n      - run_cmd_in_pty\n    filenames:\n      - convert2rhel/utils.py\n    classification: very promising\n\n  - headline: Improper configuration file permissions\n    analysis: |\n      Configuration files are created/modified without setting secure file permissions, which may allow unauthorized users to read or modify configuration settings.\n    cwe: CWE-276\n    function_names:\n    filenames:\n      - convert2rhel/pkghandler.py\n      - convert2rhel/redhatrelease.py\n    classification: slightly promising\n\n  - headline: Potential denial of service through uncontrolled resource consumption\n    analysis: |\n      Certain operations do not impose limits on resources such as memory, disk space, or network bandwidth. This could allow an attacker to perform a denial of service by consuming excessive resources.\n    cwe: CWE-400\n    function_names:\n    filenames:\n      - convert2rhel/pkghandler.py\n      - convert2rhel/checks.py\n    classification: slightly promising\n\n  - headline: Potential path traversal in file handling\n    analysis: |\n      The code contains file handling routines that do not perform sufficient checks on file paths, leading to potential path traversal attacks allowing access to sensitive system files.\n    cwe: CWE-22\n    function_names:\n      - get_file_content\n      - store_content_to_file\n    filenames:\n      - convert2rhel/utils.py\n    classification: very promising\n```",
      "date": "2024-06-13T10:40:06.102168",
      "usage": {
        "prompt_tokens": 116520,
        "completion_tokens": 860,
        "cost": 0.5955
      }
    }
  ],
  "leads": [
    {
      "headline": "Missing error checking for file operations",
      "analysis": "Multiple instances of file operations (like file reading and writing) lack error handling. This can lead to unexpected crashes or undefined behavior if the files are missing or unreadable.\n",
      "classification": "very promising",
      "cwe": "CWE-252",
      "function_names": [
        "read",
        "store_content_to_file"
      ],
      "filenames": [
        "convert2rhel/__init__.py",
        "convert2rhel/utils.py"
      ]
    },
    {
      "headline": "Absence of permission checks for critical operations",
      "analysis": "Various critical operations such as restarting the system or modifying configuration files do not have proper permissions checks. This can lead to unauthorized use and potential system compromise.\n",
      "classification": "very promising",
      "cwe": "CWE-284",
      "function_names": [
        "restart_system",
        "remove_pkgs"
      ],
      "filenames": [
        "convert2rhel/utils.py",
        "convert2rhel/pkghandler.py"
      ]
    },
    {
      "headline": "Inadequate validation of input arguments",
      "analysis": "Many functions accept arguments without sufficient validation, which could be exploited by an attacker to inject malicious inputs, potentially leading to arbitrary code execution or data manipulation.\n",
      "classification": "very promising",
      "cwe": "CWE-20",
      "function_names": [
        "call_yum_cmd",
        "ensure_compatibility_of_kmods",
        "download_pkg"
      ],
      "filenames": [
        "convert2rhel/pkghandler.py",
        "convert2rhel/checks.py",
        "convert2rhel/utils.py"
      ]
    },
    {
      "headline": "Data exposure through logging",
      "analysis": "Sensitive data such as passwords are logged without proper masking. An attacker with access to the logs can retrieve these sensitive details, leading to potential unauthorized access.\n",
      "classification": "very promising",
      "cwe": "CWE-532",
      "function_names": [
        "call_registration_cmd"
      ],
      "filenames": [
        "convert2rhel/subscription.py"
      ]
    },
    {
      "headline": "Command injection via unsanitized user input",
      "analysis": "There are instances where user inputs are directly included in command-line executions without proper sanitization. This could allow an attacker to inject malicious commands.\n",
      "classification": "very promising",
      "cwe": "CWE-78",
      "function_names": [
        "run_subprocess",
        "run_cmd_in_pty"
      ],
      "filenames": [
        "convert2rhel/utils.py"
      ]
    },
    {
      "headline": "Potential path traversal in file handling",
      "analysis": "The code contains file handling routines that do not perform sufficient checks on file paths, leading to potential path traversal attacks allowing access to sensitive system files.\n",
      "classification": "very promising",
      "cwe": "CWE-22",
      "function_names": [
        "get_file_content",
        "store_content_to_file"
      ],
      "filenames": [
        "convert2rhel/utils.py"
      ]
    }
  ],
  "scores": [
    {
      "stats": {
        "fn": 0,
        "tp": 1,
        "fp": 5
      },
      "mapping": {
        "3": "CVE-2022-0852"
      },
      "vuln_dates": {
        "CVE-2022-0852": "2022-08-29T15:15:10"
      },
      "scoring_model": "claude-3-opus-20240229",
      "type": "llm",
      "instruction_template_hash": "245ace12b6361954d0a2"
    }
  ],
  "instruction_template_hash": "10c0163db4740318a544",
  "version": "0.1.0"
}
