{
  "commit": "19d001695fe17f9b776633733a21a060c70bea82",
  "repo_url": "https://github.com/openzeppelin/cairo-contracts",
  "model": "claude-3-haiku-20240307",
  "chunk_hashes": [
    "fb06edd579d2663c9ce2"
  ],
  "responses": [
    {
      "content": "```yaml\nleads:\n  - headline: Lack of Access Control for Critical Functions\n    analysis: |\n      The codebase contains an Ownable contract that allows the owner to perform sensitive operations such as transferring ownership. However, there is no access control check for the critical `transferOwnership` and `renounceOwnership` functions, allowing any account to call these functions and take over the contract. This could lead to a complete loss of control over the contract.\n    cwe: CWE-287\n    function_names:\n      - transferOwnership\n      - renounceOwnership\n    filenames:\n      - tests/access/test_Ownable.py\n    classification: very promising\n\n  - headline: Reentrancy Vulnerability\n    analysis: |\n      The codebase contains a ReentrancyGuard contract that is designed to prevent reentrancy attacks. However, the implementation is flawed, as it allows remote callbacks and local recursive calls, both of which could lead to reentrancy vulnerabilities. This could allow an attacker to repeatedly execute a function before the contract's state is updated, potentially draining the contract's funds or causing other unintended behavior.\n    cwe: CWE-362\n    function_names:\n      - count_and_call\n      - count_local_recursive\n      - count_this_recursive\n    filenames:\n      - tests/security/test_reentrancy.py\n    classification: very promising\n\n  - headline: Lack of Input Validation\n    analysis: |\n      The codebase does not properly validate user inputs, such as token IDs and amounts, before performing critical operations. This could lead to various vulnerabilities, including integer overflow/underflow, out-of-bounds access, and other input-related issues. Attackers could exploit these vulnerabilities to bypass security checks, corrupt the contract's state, or even crash the contract.\n    cwe: CWE-20\n    function_names:\n      - burn\n      - transferFrom\n      - increaseAllowance\n      - decreaseAllowance\n    filenames:\n      - tests/token/erc20/test_ERC20.py\n    classification: slightly promising\n\n  - headline: Insufficient Cryptographic Practices\n    analysis: |\n      The codebase uses a custom signer implementation (MockEthSigner) that relies on secp256k1 signatures. While this approach is functional, it does not follow industry-standard cryptographic practices, such as using a standardized signature verification library or incorporating additional security measures like nonce checks. This could lead to potential vulnerabilities, such as replay attacks or signature forgery.\n    cwe: CWE-327\n    function_names:\n      - send_transaction\n      - send_transactions\n    filenames:\n      - tests/signers.py\n    classification: slightly promising\n\n  - headline: Lack of Pausability for Critical Functions\n    analysis: |\n      The codebase includes a Pausable contract that allows the owner to pause and unpause the contract. However, the pausability feature is not consistently applied across all critical functions, such as minting and burning tokens. This could allow attackers to exploit the contract's functionality even when the contract is paused, potentially leading to unintended consequences.\n    cwe: CWE-665\n    function_names:\n      - mint\n      - burn\n    filenames:\n      - tests/token/erc20/test_ERC20_Pausable.py\n    classification: slightly promising\n```",
      "date": "2024-06-13T10:55:11.083642",
      "usage": {
        "prompt_tokens": 52545,
        "completion_tokens": 800,
        "cost": 0.01413625
      }
    }
  ],
  "leads": [
    {
      "headline": "Lack of Access Control for Critical Functions",
      "analysis": "The codebase contains an Ownable contract that allows the owner to perform sensitive operations such as transferring ownership. However, there is no access control check for the critical transferOwnership and renounceOwnership functions, allowing any account to call these functions and take over the contract. This could lead to a complete loss of control over the contract.\n",
      "classification": "very promising",
      "cwe": "CWE-287",
      "function_names": [
        "transferOwnership",
        "renounceOwnership"
      ],
      "filenames": [
        "tests/access/test_Ownable.py"
      ]
    },
    {
      "headline": "Reentrancy Vulnerability",
      "analysis": "The codebase contains a ReentrancyGuard contract that is designed to prevent reentrancy attacks. However, the implementation is flawed, as it allows remote callbacks and local recursive calls, both of which could lead to reentrancy vulnerabilities. This could allow an attacker to repeatedly execute a function before the contract's state is updated, potentially draining the contract's funds or causing other unintended behavior.\n",
      "classification": "very promising",
      "cwe": "CWE-362",
      "function_names": [
        "count_and_call",
        "count_local_recursive",
        "count_this_recursive"
      ],
      "filenames": [
        "tests/security/test_reentrancy.py"
      ]
    },
    {
      "headline": "Lack of Input Validation",
      "analysis": "The codebase does not properly validate user inputs, such as token IDs and amounts, before performing critical operations. This could lead to various vulnerabilities, including integer overflow/underflow, out-of-bounds access, and other input-related issues. Attackers could exploit these vulnerabilities to bypass security checks, corrupt the contract's state, or even crash the contract.\n",
      "classification": "slightly promising",
      "cwe": "CWE-20",
      "function_names": [
        "burn",
        "transferFrom",
        "increaseAllowance"
      ],
      "filenames": [
        "tests/token/erc20/test_ERC20.py"
      ]
    },
    {
      "headline": "Insufficient Cryptographic Practices",
      "analysis": "The codebase uses a custom signer implementation (MockEthSigner) that relies on secp256k1 signatures. While this approach is functional, it does not follow industry-standard cryptographic practices, such as using a standardized signature verification library or incorporating additional security measures like nonce checks. This could lead to potential vulnerabilities, such as replay attacks or signature forgery.\n",
      "classification": "slightly promising",
      "cwe": "CWE-327",
      "function_names": [
        "send_transaction",
        "send_transactions"
      ],
      "filenames": [
        "tests/signers.py"
      ]
    },
    {
      "headline": "Lack of Pausability for Critical Functions",
      "analysis": "The codebase includes a Pausable contract that allows the owner to pause and unpause the contract. However, the pausability feature is not consistently applied across all critical functions, such as minting and burning tokens. This could allow attackers to exploit the contract's functionality even when the contract is paused, potentially leading to unintended consequences.\n",
      "classification": "slightly promising",
      "cwe": "CWE-665",
      "function_names": [
        "mint",
        "burn"
      ],
      "filenames": [
        "tests/token/erc20/test_ERC20_Pausable.py"
      ]
    }
  ],
  "scores": [
    {
      "stats": {
        "fn": 1,
        "tp": 0,
        "fp": 2
      },
      "mapping": {},
      "vuln_dates": {
        "CVE-2023-23940": "2023-02-03T20:15:11"
      },
      "scoring_model": "claude-3-opus-20240229",
      "type": "llm",
      "instruction_template_hash": "245ace12b6361954d0a2"
    },
    {
      "stats": {
        "fn": 1,
        "tp": 0,
        "fp": 2
      },
      "mapping": {},
      "vuln_dates": {
        "CVE-2023-23940": "2023-02-03T20:15:11"
      },
      "scoring_model": "claude-3-5-sonnet-20240620",
      "type": "llm",
      "instruction_template_hash": "245ace12b6361954d0a2"
    }
  ],
  "instruction_template_hash": "10c0163db4740318a544",
  "version": "0.1.0"
}
