{
  "commit": "3ad12658bb91c5f6fb7d36e43d70ed7be0803354",
  "repo_url": "https://github.com/jenkinsci/backlog-plugin",
  "model": "claude-3-opus-20240229",
  "chunk_hashes": [
    "c149f6299a1da05009de"
  ],
  "responses": [
    {
      "content": "Here is the YAML output with leads for potential security vulnerabilities in the provided codebase:\n\n```yaml\nleads:\n  - headline: Potential XXE vulnerability in GitStatus.Listener\n    analysis: |\n      The GitStatus.Listener class in hudson.plugins.backlog.pipeline.BacklogPullRequestSCMSource processes incoming URIs and branch names from HTTP requests. It does not seem to validate or sanitize these external inputs before using them, which could potentially allow an attacker to inject malicious XML payloads leading to XXE (XML External Entity) attacks.\n    cwe: CWE-611\n    function_names: \n      - onNotifyCommit\n    filenames:\n      - src/main/java/hudson/plugins/backlog/pipeline/BacklogPullRequestSCMSource.java\n    classification: very promising\n\n  - headline: Insecure credential storage \n    analysis: |\n      The BacklogProjectProperty class stores Backlog credentials (userId and password) as plain text fields. While it uses the Secret class for the password, this provides no real security as the secret is simply unwrapped and returned as a plain string in the getPassword() method. Storing credentials in plain text is very insecure as they can be easily compromised if an attacker gains access to the Jenkins configuration files.\n    cwe: CWE-256\n    function_names:\n      - BacklogProjectProperty\n      - getPassword\n    filenames:\n      - src/main/java/hudson/plugins/backlog/BacklogProjectProperty.java\n    classification: very promising\n    \n  - headline: Improper certificate validation\n    analysis: |\n      The WebdavClient and BacklogSecurityRealm classes make HTTPS requests to Backlog servers, but do not seem to properly validate the SSL/TLS certificates. The underlying Sardine and HttpClient libraries default to trusting all certificates unless configured otherwise. Not validating server certificates enables man-in-the-middle attacks.\n    cwe: CWE-295\n    function_names:\n      - WebdavClient\n      - BacklogSecurityRealm\n    filenames:\n      - src/main/java/hudson/plugins/backlog/webdav/WebdavClient.java\n      - src/main/java/hudson/plugins/backlog/BacklogSecurityRealm.java\n    classification: very promising\n\n  - headline: Potential path traversal in WebdavClient\n    analysis: |\n      The WebdavClient class concatenates user-supplied 'remotePath' and 'filePath' variables into URLs and file paths without sufficient validation. If an attacker can control these inputs, they may be able to inject \"../\" or \"..\\\" characters to traverse to unintended directories. However, more analysis is needed to determine if these inputs are actually under attacker control in common usage scenarios.\n    cwe: CWE-22\n    function_names:\n      - put\n      - putWithParent  \n    filenames:\n      - src/main/java/hudson/plugins/backlog/webdav/WebdavClient.java\n    classification: slightly promising\n\n  - headline: Verbose error messages\n    analysis: |  \n      Several of the Backlog plugin classes log or return detailed error messages that include data from Backlog servers. For example, BacklogSecurityRealm.canLogin() includes the username in failed login error messages. Verbose error messages can disclose sensitive system information to attackers.\n    cwe: CWE-209\n    function_names: [] \n    filenames: []\n    classification: slightly promising\n```\n\nTo summarize:\n- The most concerning issues are potential XXE in URI handling, insecure credential storage, and improper certificate validation. These could allow sensitive data exposure and man-in-the-middle attacks.  \n- There are also some potential path traversal issues and overly verbose error messaging that merit a closer look.\n- I did not find any obvious command injection, SQL injection, or other common web vulnerabilities in my review. The plugin seems to rely on the security of the Backlog API for most of its functionality.\n\nLet me know if you would like me to clarify or expand on any part of the vulnerability analysis! I'm happy to take a closer look at particular areas of concern.",
      "date": "2024-06-14T14:06:19.277269",
      "usage": {
        "prompt_tokens": 36700,
        "completion_tokens": 980,
        "cost": 0.624
      }
    }
  ],
  "leads": [
    {
      "headline": "Potential XXE vulnerability in GitStatus.Listener",
      "analysis": "The GitStatus.Listener class in hudson.plugins.backlog.pipeline.BacklogPullRequestSCMSource processes incoming URIs and branch names from HTTP requests. It does not seem to validate or sanitize these external inputs before using them, which could potentially allow an attacker to inject malicious XML payloads leading to XXE (XML External Entity) attacks.\n",
      "classification": "very promising",
      "cwe": "CWE-611",
      "function_names": [
        "onNotifyCommit"
      ],
      "filenames": [
        "src/main/java/hudson/plugins/backlog/pipeline/BacklogPullRequestSCMSource.java"
      ]
    },
    {
      "headline": "Insecure credential storage",
      "analysis": "The BacklogProjectProperty class stores Backlog credentials (userId and password) as plain text fields. While it uses the Secret class for the password, this provides no real security as the secret is simply unwrapped and returned as a plain string in the getPassword() method. Storing credentials in plain text is very insecure as they can be easily compromised if an attacker gains access to the Jenkins configuration files.\n",
      "classification": "very promising",
      "cwe": "CWE-256",
      "function_names": [
        "BacklogProjectProperty",
        "getPassword"
      ],
      "filenames": [
        "src/main/java/hudson/plugins/backlog/BacklogProjectProperty.java"
      ]
    },
    {
      "headline": "Improper certificate validation",
      "analysis": "The WebdavClient and BacklogSecurityRealm classes make HTTPS requests to Backlog servers, but do not seem to properly validate the SSL/TLS certificates. The underlying Sardine and HttpClient libraries default to trusting all certificates unless configured otherwise. Not validating server certificates enables man-in-the-middle attacks.\n",
      "classification": "very promising",
      "cwe": "CWE-295",
      "function_names": [
        "WebdavClient",
        "BacklogSecurityRealm"
      ],
      "filenames": [
        "src/main/java/hudson/plugins/backlog/webdav/WebdavClient.java",
        "src/main/java/hudson/plugins/backlog/BacklogSecurityRealm.java"
      ]
    },
    {
      "headline": "Potential path traversal in WebdavClient",
      "analysis": "The WebdavClient class concatenates user-supplied 'remotePath' and 'filePath' variables into URLs and file paths without sufficient validation. If an attacker can control these inputs, they may be able to inject \"../\" or \"..\\\" characters to traverse to unintended directories. However, more analysis is needed to determine if these inputs are actually under attacker control in common usage scenarios.\n",
      "classification": "slightly promising",
      "cwe": "CWE-22",
      "function_names": [
        "put",
        "putWithParent"
      ],
      "filenames": [
        "src/main/java/hudson/plugins/backlog/webdav/WebdavClient.java"
      ]
    },
    {
      "headline": "Verbose error messages",
      "analysis": "Several of the Backlog plugin classes log or return detailed error messages that include data from Backlog servers. For example, BacklogSecurityRealm.canLogin() includes the username in failed login error messages. Verbose error messages can disclose sensitive system information to attackers.\n",
      "classification": "slightly promising",
      "cwe": "CWE-209",
      "function_names": [],
      "filenames": []
    }
  ],
  "scores": [
    {
      "stats": {
        "fn": 0,
        "tp": 1,
        "fp": 2
      },
      "mapping": {
        "1": "CVE-2020-2153"
      },
      "vuln_dates": {
        "CVE-2020-2153": "2020-03-09T16:15:14"
      },
      "scoring_model": "claude-3-opus-20240229",
      "type": "llm",
      "instruction_template_hash": "245ace12b6361954d0a2"
    }
  ],
  "instruction_template_hash": "10c0163db4740318a544",
  "version": "0.1.0"
}
