{
  "commit": "1dfe072dfb0f23d2feaa1d00d89f7455020788ff",
  "repo_url": "https://github.com/jenkinsci/pangolin-testrail-connector-plugin",
  "model": "claude-3-opus-20240229",
  "chunk_hashes": [
    "ade31e89abb696cbe263"
  ],
  "responses": [
    {
      "content": "```yaml\nleads:\n  - headline: Improper handling of untrusted data in PangolinRemoteExecutor\n    analysis: |\n      The PangolinRemoteExecutor class executes user-provided code via the VirtualChannel. It deserializes untrusted data received from the master into the BulkUpdateParameters object without proper validation. This could allow an attacker to execute arbitrary code on the agent by providing malicious serialized data.\n    cwe: CWE-502\n    function_names:\n      - PangolinRemoteExecutor.call\n      - PangolinRemoteExecutor.execute\n    filenames:\n      - src/main/java/com/agiletestware/pangolin/PangolinRemoteExecutor.java\n    classification: very promising\n\n  - headline: Improper neutralization of special elements in PangolinPublisher\n    analysis: |\n      The PangolinPublisher class does not properly neutralize special elements in several user-controlled fields such as customProperties, pangolinUrl, testRailUrl, testRailUserName, testRailPassword, etc. before using them to construct OS commands or SQL queries. This could lead to command injection or SQL injection vulnerabilities if the input is not properly validated and sanitized.\n    cwe: CWE-78\n    function_names:\n      - PangolinPublisher.perform\n      - PangolinPublisher.doBulkUpdate\n      - PangolinPublisher.doSaveConnection\n    filenames:\n      - src/main/java/com/agiletestware/pangolin/PangolinPublisher.java\n    classification: very promising\n    \n  - headline: Exposure of sensitive information in JenkinsLogger\n    analysis: |\n      The JenkinsLogger class logs potentially sensitive information such as exception stack traces at the SEVERE level. If the Jenkins logs are accessible to low-privileged users or external parties, this could lead to exposure of sensitive technical details about the application internals that could aid in attacking the system.\n    cwe: CWE-209\n    function_names:\n      - JenkinsLogger.error\n    filenames:  \n      - src/main/java/com/agiletestware/pangolin/JenkinsLogger.java\n    classification: slightly promising\n\n  - headline: Use of a broken or risky cryptographic algorithm in DefaultCustomSecret\n    analysis: |\n      The DefaultCustomSecret class uses a custom encryption scheme based on hudson.util.Secret to encrypt/decrypt sensitive data like the TestRail password. The strength and security of this proprietary cryptographic implementation is unknown. Using a non-standard crypto algorithm is risky as it may have undiscovered vulnerabilities. Well-tested, modern encryption algorithms should be used instead.\n    cwe: CWE-327\n    function_names:\n      - DefaultCustomSecret.getEncryptedValue \n      - DefaultCustomSecret.getPlainText\n    filenames:\n      - src/main/java/com/agiletestware/pangolin/encryption/DefaultCustomSecret.java  \n    classification: slightly promising\n\n```",
      "date": "2024-06-12T18:59:16.414781",
      "usage": {
        "prompt_tokens": 39540,
        "completion_tokens": 721,
        "cost": 0.647175
      }
    }
  ],
  "leads": [
    {
      "headline": "Improper handling of untrusted data in PangolinRemoteExecutor",
      "analysis": "The PangolinRemoteExecutor class executes user-provided code via the VirtualChannel. It deserializes untrusted data received from the master into the BulkUpdateParameters object without proper validation. This could allow an attacker to execute arbitrary code on the agent by providing malicious serialized data.\n",
      "classification": "very promising",
      "cwe": "CWE-502",
      "function_names": [
        "PangolinRemoteExecutor.call",
        "PangolinRemoteExecutor.execute"
      ],
      "filenames": [
        "src/main/java/com/agiletestware/pangolin/PangolinRemoteExecutor.java"
      ]
    },
    {
      "headline": "Improper neutralization of special elements in PangolinPublisher",
      "analysis": "The PangolinPublisher class does not properly neutralize special elements in several user-controlled fields such as customProperties, pangolinUrl, testRailUrl, testRailUserName, testRailPassword, etc. before using them to construct OS commands or SQL queries. This could lead to command injection or SQL injection vulnerabilities if the input is not properly validated and sanitized.\n",
      "classification": "very promising",
      "cwe": "CWE-78",
      "function_names": [
        "PangolinPublisher.perform",
        "PangolinPublisher.doBulkUpdate",
        "PangolinPublisher.doSaveConnection"
      ],
      "filenames": [
        "src/main/java/com/agiletestware/pangolin/PangolinPublisher.java"
      ]
    },
    {
      "headline": "Exposure of sensitive information in JenkinsLogger",
      "analysis": "The JenkinsLogger class logs potentially sensitive information such as exception stack traces at the SEVERE level. If the Jenkins logs are accessible to low-privileged users or external parties, this could lead to exposure of sensitive technical details about the application internals that could aid in attacking the system.\n",
      "classification": "slightly promising",
      "cwe": "CWE-209",
      "function_names": [
        "JenkinsLogger.error"
      ],
      "filenames": [
        "src/main/java/com/agiletestware/pangolin/JenkinsLogger.java"
      ]
    },
    {
      "headline": "Use of a broken or risky cryptographic algorithm in DefaultCustomSecret",
      "analysis": "The DefaultCustomSecret class uses a custom encryption scheme based on hudson.util.Secret to encrypt/decrypt sensitive data like the TestRail password. The strength and security of this proprietary cryptographic implementation is unknown. Using a non-standard crypto algorithm is risky as it may have undiscovered vulnerabilities. Well-tested, modern encryption algorithms should be used instead.\n",
      "classification": "slightly promising",
      "cwe": "CWE-327",
      "function_names": [
        "DefaultCustomSecret.getEncryptedValue",
        "DefaultCustomSecret.getPlainText"
      ],
      "filenames": [
        "src/main/java/com/agiletestware/pangolin/encryption/DefaultCustomSecret.java"
      ]
    }
  ],
  "scores": [
    {
      "stats": {
        "fn": 1,
        "tp": 0,
        "fp": 2
      },
      "mapping": {},
      "vuln_dates": {
        "CVE-2018-1999032": "2018-08-01T13:29:00"
      },
      "scoring_model": "claude-3-opus-20240229",
      "type": "llm",
      "instruction_template_hash": "245ace12b6361954d0a2"
    }
  ],
  "instruction_template_hash": "10c0163db4740318a544",
  "version": "0.1.0"
}
