{
  "commit": "03b393a3d08dcede570ea3d2ab305175eec6327d",
  "repo_url": "https://github.com/bouke/django-two-factor-auth",
  "model": "gpt-4o-2024-05-13",
  "chunk_hashes": [
    "9556a684bbdc57402cf3"
  ],
  "responses": [
    {
      "content": "```yaml\nleads:\n  - headline: \"Hardcoded Secret Key in Settings\"\n    analysis: |\n      The file `example/settings.py` contains a hardcoded secret key (`SECRET_KEY = 'DO NOT USE THIS KEY!'`). Hardcoding secret keys into source files is insecure as it may lead to sensitive information being exposed if the source code is ever published or accessed by unauthorized parties. An attacker could use the secret key to impersonate and exploit the application.\n    cwe: CWE-798\n    function_names: []\n    filenames:\n      - example/settings.py\n    classification: very promising\n\n  - headline: \"Improper Secret Key Management in QR Generator View\"\n    analysis: |\n      In the file `two_factor/views/core.py`, the `QRGeneratorView` class uses a session key name (`django_two_factor-qr_secret_key`) to store a critical piece of information, the secret key for QR code generation. If an attacker can access the session storage, they could potentially retrieve this secret key and generate their own QR codes, compromising the OTP setup process.\n    cwe: CWE-922\n    function_names:\n      - get\n    filenames:\n      - two_factor/views/core.py\n    classification: very promising\n\n  - headline: \"SQL Injection Vulnerability via Dynamic URL Routing\"\n    analysis: |\n      In the file `example/urls.py`, the use of regex patterns directly in URL definitions (`regex=...`) without proper input validation can introduce security risks such as SQL Injection if user input is incorporated into these URLs without sanitation. It's essential to ensure that all inputs used in dynamic routing are properly sanitized and validated.\n    cwe: CWE-89\n    function_names: []\n    filenames:\n      - example/urls.py\n    classification: slightly promising\n\n  - headline: \"Sensitive Information in Logs\"\n    analysis: |\n      The `Fake` class in `two_factor/gateways/fake.py` logs sensitive information such as authentication tokens. While this might be useful for development purposes, logging sensitive information can lead to exposure of tokens if log files are not properly secured.\n    cwe: CWE-532\n    function_names:\n      - make_call\n      - send_sms\n    filenames:\n      - two_factor/gateways/fake.py\n    classification: very promising\n\n  - headline: \"Use of Request Data Without Validation in Twilio Gateway\"\n    analysis: |\n      In `two_factor/gateways/twilio/views.py`, the `TwilioCallApp` class uses request data directly to control the language settings (`locale`) without proper validation. If the data is manipulated, it could lead to inappropriate localization settings or potentially harmful behavior.\n    cwe: CWE-20\n    function_names:\n      - create_response\n    filenames:\n      - two_factor/gateways/twilio/views.py\n    classification: slightly promising\n\n  - headline: \"Dangerous Default Permissions\"\n    analysis: |\n      In the `AdminSiteOTPRequired` class defined in `two_factor/admin.py`, the method `has_permission` relies on the user's OTP verification status for permission. If an admin account's OTP setup is disabled, it could inadvertently grant unauthorized access to the admin panel.\n    cwe: CWE-276\n    function_names:\n      - has_permission\n    filenames:\n      - two_factor/admin.py\n    classification: slightly promising\n\n  - headline: \"Cryptographic Issues in Token Verification\"\n    analysis: |\n      The function `verify_token` in the `PhoneDevice` class (`two_factor/models.py`) uses a TOTP algorithm without adequately limiting the number of allowed time-skew attempts. This presents an opportunity for attackers to successfully guess TOTP tokens by brute-forcing within the six-drift range.\n    cwe: CWE-330\n    function_names:\n      - verify_token\n    filenames:\n      - two_factor/models.py\n    classification: very promising\n\n  - headline: \"Use of HTTP GET for Sending Sensitive Data\"\n    analysis: |\n      The `Twilio` class in `two_factor/gateways/twilio/gateway.py` sends sensitive data via HTTP GET requests when making calls. Using GET requests can expose sensitive information through URLs and query strings which can be logged or cached inadvertently.\n    cwe: CWE-319\n    function_names:\n      - make_call\n    filenames:\n      - two_factor/gateways/twilio/gateway.py\n    classification: very promising\n```",
      "date": "2024-06-12T15:17:39.662319",
      "usage": {
        "prompt_tokens": 42905,
        "completion_tokens": 906,
        "cost": 0.228115
      }
    }
  ],
  "leads": [
    {
      "headline": "Hardcoded Secret Key in Settings",
      "analysis": "The file example/settings.py contains a hardcoded secret key (SECRET_KEY = 'DO NOT USE THIS KEY!'). Hardcoding secret keys into source files is insecure as it may lead to sensitive information being exposed if the source code is ever published or accessed by unauthorized parties. An attacker could use the secret key to impersonate and exploit the application.\n",
      "classification": "very promising",
      "cwe": "CWE-798",
      "function_names": [],
      "filenames": [
        "example/settings.py"
      ]
    },
    {
      "headline": "Improper Secret Key Management in QR Generator View",
      "analysis": "In the file two_factor/views/core.py, the QRGeneratorView class uses a session key name (django_two_factor-qr_secret_key) to store a critical piece of information, the secret key for QR code generation. If an attacker can access the session storage, they could potentially retrieve this secret key and generate their own QR codes, compromising the OTP setup process.\n",
      "classification": "very promising",
      "cwe": "CWE-922",
      "function_names": [
        "get"
      ],
      "filenames": [
        "two_factor/views/core.py"
      ]
    },
    {
      "headline": "SQL Injection Vulnerability via Dynamic URL Routing",
      "analysis": "In the file example/urls.py, the use of regex patterns directly in URL definitions (regex=...) without proper input validation can introduce security risks such as SQL Injection if user input is incorporated into these URLs without sanitation. It's essential to ensure that all inputs used in dynamic routing are properly sanitized and validated.\n",
      "classification": "slightly promising",
      "cwe": "CWE-89",
      "function_names": [],
      "filenames": [
        "example/urls.py"
      ]
    },
    {
      "headline": "Sensitive Information in Logs",
      "analysis": "The Fake class in two_factor/gateways/fake.py logs sensitive information such as authentication tokens. While this might be useful for development purposes, logging sensitive information can lead to exposure of tokens if log files are not properly secured.\n",
      "classification": "very promising",
      "cwe": "CWE-532",
      "function_names": [
        "make_call",
        "send_sms"
      ],
      "filenames": [
        "two_factor/gateways/fake.py"
      ]
    },
    {
      "headline": "Use of Request Data Without Validation in Twilio Gateway",
      "analysis": "In two_factor/gateways/twilio/views.py, the TwilioCallApp class uses request data directly to control the language settings (locale) without proper validation. If the data is manipulated, it could lead to inappropriate localization settings or potentially harmful behavior.\n",
      "classification": "slightly promising",
      "cwe": "CWE-20",
      "function_names": [
        "create_response"
      ],
      "filenames": [
        "two_factor/gateways/twilio/views.py"
      ]
    },
    {
      "headline": "Dangerous Default Permissions",
      "analysis": "In the AdminSiteOTPRequired class defined in two_factor/admin.py, the method has_permission relies on the user's OTP verification status for permission. If an admin account's OTP setup is disabled, it could inadvertently grant unauthorized access to the admin panel.\n",
      "classification": "slightly promising",
      "cwe": "CWE-276",
      "function_names": [
        "has_permission"
      ],
      "filenames": [
        "two_factor/admin.py"
      ]
    },
    {
      "headline": "Cryptographic Issues in Token Verification",
      "analysis": "The function verify_token in the PhoneDevice class (two_factor/models.py) uses a TOTP algorithm without adequately limiting the number of allowed time-skew attempts. This presents an opportunity for attackers to successfully guess TOTP tokens by brute-forcing within the six-drift range.\n",
      "classification": "very promising",
      "cwe": "CWE-330",
      "function_names": [
        "verify_token"
      ],
      "filenames": [
        "two_factor/models.py"
      ]
    },
    {
      "headline": "Use of HTTP GET for Sending Sensitive Data",
      "analysis": "The Twilio class in two_factor/gateways/twilio/gateway.py sends sensitive data via HTTP GET requests when making calls. Using GET requests can expose sensitive information through URLs and query strings which can be logged or cached inadvertently.\n",
      "classification": "very promising",
      "cwe": "CWE-319",
      "function_names": [
        "make_call"
      ],
      "filenames": [
        "two_factor/gateways/twilio/gateway.py"
      ]
    }
  ],
  "scores": [
    {
      "stats": {
        "fn": 1,
        "tp": 0,
        "fp": 5
      },
      "mapping": {},
      "vuln_dates": {
        "CVE-2020-15105": "2020-07-10T21:15:10"
      },
      "scoring_model": "claude-3-opus-20240229",
      "type": "llm",
      "instruction_template_hash": "245ace12b6361954d0a2"
    }
  ],
  "instruction_template_hash": "10c0163db4740318a544",
  "version": "0.1.0"
}
