{
  "commit": "2ad18e0e10e7d7ecd5384c378f25ec8821a10a29",
  "repo_url": "https://github.com/psf/requests",
  "model": "gpt-4-turbo-2024-04-09",
  "chunk_hashes": [
    "5e99fad937fb42697926"
  ],
  "responses": [
    {
      "content": "```yaml\nleads:\n  - headline: \"Improper Authentication Handling\"\n    analysis: |\n      The authentication mechanisms in the code use basic authentication without considering other more secure options. This can allow attackers to use brute force methods to guess usernames and passwords. Moreover, the hashes used for securing passwords may not provide sufficient protection if not properly implemented.\n    cwe: CWE-287\n    function_names:\n      - __call__\n      - handle_401\n    filenames:\n      - requests/auth.py\n    classification: \"very promising\"\n\n  - headline: \"Potential Directory Traversal in Zip File Extraction\"\n    analysis: |\n      The function that extracts zip file paths does not properly sanitize inputs which could allow an attacker to traverse directories. If an attacker can control the input, they could potentially access unauthorized files or directories.\n    cwe: CWE-22\n    function_names:\n      - extract_zipped_paths\n    filenames:\n      - requests/utils.py\n    classification: \"very promising\"\n\n  - headline: \"Sensitive Data Exposure through Logs\"\n    analysis: |\n      There is potential exposure of sensitive information through logs generated during the handling of HTTP headers which include the credentials sent in a form that can be easily intercepted or stored improperly.\n    cwe: CWE-532\n    function_names:\n      - send\n      - build_response\n    filenames:\n      - requests/adapters.py\n    classification: \"slightly promising\"\n\n  - headline: \"Uncontrolled Resource Consumption\"\n    analysis: |\n      The `iter_slices` function does not limit the total number of iterations or the size of the slices allowed. If this function is called with a large data object, it could consume excessive memory or processing power, leading to a denial of service.\n    cwe: CWE-400\n    function_names:\n      - iter_slices\n    filenames:\n      - requests/utils.py\n    classification: \"very promising\"\n\n  - headline: \"Cookie Management Based on Obsolete RFC\"\n    analysis: |\n      The software constructs a cookie header by using methods that adhere to an obsolete version of the RFC that does not account for the modern security practices, potentially leading to the exposure of cookies to attackers.\n    cwe: CWE-296\n    function_names:\n      - extract_cookies_to_jar\n      - get_cookie_header\n    filenames:\n      - requests/cookies.py\n    classification: \"slightly promising\"\n\n  - headline: \"Insufficient Verification of Cryptographic Signature\"\n    analysis: |\n      The requests library does not verify that the public key used to sign a received message matches the expected public key in certain situations. This might allow an attacker who has the ability to generate a valid signature, using their own private key, to authenticate themselves as a different user.\n    cwe: CWE-347\n    function_names:\n      - cert_verify\n    filenames:\n      - requests/adapters.py\n    classification: \"very promising\"\n```",
      "date": "2024-06-09T14:18:25.296755",
      "usage": {
        "prompt_tokens": 86035,
        "completion_tokens": 592,
        "cost": 0.87811
      }
    }
  ],
  "leads": [
    {
      "headline": "Improper Authentication Handling",
      "analysis": "The authentication mechanisms in the code use basic authentication without considering other more secure options. This can allow attackers to use brute force methods to guess usernames and passwords. Moreover, the hashes used for securing passwords may not provide sufficient protection if not properly implemented.\n",
      "classification": "very promising",
      "cwe": "CWE-287",
      "function_names": [
        "__call__",
        "handle_401"
      ],
      "filenames": [
        "requests/auth.py"
      ]
    },
    {
      "headline": "Potential Directory Traversal in Zip File Extraction",
      "analysis": "The function that extracts zip file paths does not properly sanitize inputs which could allow an attacker to traverse directories. If an attacker can control the input, they could potentially access unauthorized files or directories.\n",
      "classification": "very promising",
      "cwe": "CWE-22",
      "function_names": [
        "extract_zipped_paths"
      ],
      "filenames": [
        "requests/utils.py"
      ]
    },
    {
      "headline": "Sensitive Data Exposure through Logs",
      "analysis": "There is potential exposure of sensitive information through logs generated during the handling of HTTP headers which include the credentials sent in a form that can be easily intercepted or stored improperly.\n",
      "classification": "slightly promising",
      "cwe": "CWE-532",
      "function_names": [
        "send",
        "build_response"
      ],
      "filenames": [
        "requests/adapters.py"
      ]
    },
    {
      "headline": "Uncontrolled Resource Consumption",
      "analysis": "The iter_slices function does not limit the total number of iterations or the size of the slices allowed. If this function is called with a large data object, it could consume excessive memory or processing power, leading to a denial of service.\n",
      "classification": "very promising",
      "cwe": "CWE-400",
      "function_names": [
        "iter_slices"
      ],
      "filenames": [
        "requests/utils.py"
      ]
    },
    {
      "headline": "Cookie Management Based on Obsolete RFC",
      "analysis": "The software constructs a cookie header by using methods that adhere to an obsolete version of the RFC that does not account for the modern security practices, potentially leading to the exposure of cookies to attackers.\n",
      "classification": "slightly promising",
      "cwe": "CWE-296",
      "function_names": [
        "extract_cookies_to_jar",
        "get_cookie_header"
      ],
      "filenames": [
        "requests/cookies.py"
      ]
    },
    {
      "headline": "Insufficient Verification of Cryptographic Signature",
      "analysis": "The requests library does not verify that the public key used to sign a received message matches the expected public key in certain situations. This might allow an attacker who has the ability to generate a valid signature, using their own private key, to authenticate themselves as a different user.\n",
      "classification": "very promising",
      "cwe": "CWE-347",
      "function_names": [
        "cert_verify"
      ],
      "filenames": [
        "requests/adapters.py"
      ]
    }
  ],
  "scores": [
    {
      "stats": {
        "fn": 2,
        "tp": 0,
        "fp": 4
      },
      "mapping": {},
      "vuln_dates": {
        "CVE-2023-32681": "2023-05-26T18:15:14",
        "CVE-2024-35195": "2024-05-20T21:15:09"
      },
      "scoring_model": "gpt-4o-2024-05-13",
      "type": "llm",
      "instruction_template_hash": "8998f09cf57fca8a6e03"
    }
  ],
  "instruction_template_hash": "10c0163db4740318a544",
  "version": "0.1.0"
}
