{
  "commit": "409c30c0d2d357f3fbc3abd7a80d5c111a738aa2",
  "repo_url": "https://github.com/tadashi-aikawa/owlmixin",
  "model": "claude-3-haiku-20240307",
  "chunk_hashes": [
    "7e44a5a941e5eae71fc9"
  ],
  "responses": [
    {
      "content": "```yaml\nleads:\n  - headline: Improper Handling of Exceptional Conditions\n    analysis: |\n      The codebase contains potential issues related to the handling of exceptional conditions, which can lead to vulnerabilities. This could include scenarios where errors or unexpected conditions are not properly checked or handled, potentially leading to application crashes, information disclosure, or other security problems.\n    cwe: CWE-755\n    function_names:\n      - release\n      - setup\n    filenames:\n      - release.sh\n      - setup.py\n    classification: slightly promising\n\n  - headline: Improper Input Validation\n    analysis: |\n      The codebase contains potential issues related to improper input validation, which can lead to vulnerabilities such as command injection, code injection, or other injection-based attacks. This could include scenarios where user-supplied input is not properly sanitized or validated before being used in sensitive operations, such as executing system commands or evaluating code.\n    cwe: CWE-20\n    function_names:\n      - replace_keys\n      - to_snake\n    filenames:\n      - owlmixin/util.py\n    classification: slightly promising\n\n  - headline: Improper Neutralization of Special Elements used in an Expression Language Statement ('Expression Language Injection')\n    analysis: |\n      The codebase contains potential issues related to the improper neutralization of special elements used in expression language statements, which can lead to expression language injection vulnerabilities. This could include scenarios where user-supplied input is not properly sanitized or validated before being used in expression language evaluations, potentially allowing attackers to inject malicious code or bypass security controls.\n    cwe: CWE-917\n    function_names:\n      - replace_keys\n      - to_snake\n    filenames:\n      - owlmixin/util.py\n    classification: slightly promising\n\n  - headline: Improper Validation of Specified Quantity in Input\n    analysis: |\n      The codebase contains potential issues related to the improper validation of specified quantities in input, which can lead to vulnerabilities. This could include scenarios where the size or length of user-supplied input is not properly validated, potentially leading to buffer overflow, denial of service, or other security problems.\n    cwe: CWE-1284\n    function_names:\n      - to_csv\n    filenames:\n      - owlmixin/transformers.py\n    classification: slightly promising\n\n  - headline: Improper Neutralization of Formula Elements in a CSV File\n    analysis: |\n      The codebase contains potential issues related to the improper neutralization of formula elements in CSV files, which can lead to formula injection vulnerabilities. This could include scenarios where user-supplied input is not properly sanitized or validated before being used in CSV file generation, potentially allowing attackers to inject malicious formulas that could be executed by spreadsheet software or other applications.\n    cwe: CWE-1236\n    function_names:\n      - dump_csv\n    filenames:\n      - owlmixin/util.py\n    classification: slightly promising\n\n```",
      "date": "2024-07-08T08:52:47.935814",
      "usage": {
        "prompt_tokens": 42039,
        "completion_tokens": 698,
        "cost": 0.01138225
      }
    }
  ],
  "leads": [
    {
      "headline": "Improper Handling of Exceptional Conditions",
      "analysis": "The codebase contains potential issues related to the handling of exceptional conditions, which can lead to vulnerabilities. This could include scenarios where errors or unexpected conditions are not properly checked or handled, potentially leading to application crashes, information disclosure, or other security problems.\n",
      "classification": "slightly promising",
      "cwe": "CWE-755",
      "function_names": [
        "release",
        "setup"
      ],
      "filenames": [
        "release.sh",
        "setup.py"
      ]
    },
    {
      "headline": "Improper Input Validation",
      "analysis": "The codebase contains potential issues related to improper input validation, which can lead to vulnerabilities such as command injection, code injection, or other injection-based attacks. This could include scenarios where user-supplied input is not properly sanitized or validated before being used in sensitive operations, such as executing system commands or evaluating code.\n",
      "classification": "slightly promising",
      "cwe": "CWE-20",
      "function_names": [
        "replace_keys",
        "to_snake"
      ],
      "filenames": [
        "owlmixin/util.py"
      ]
    },
    {
      "headline": "Improper Neutralization of Special Elements used in an Expression Language Statement ('Expression Language Injection')",
      "analysis": "The codebase contains potential issues related to the improper neutralization of special elements used in expression language statements, which can lead to expression language injection vulnerabilities. This could include scenarios where user-supplied input is not properly sanitized or validated before being used in expression language evaluations, potentially allowing attackers to inject malicious code or bypass security controls.\n",
      "classification": "slightly promising",
      "cwe": "CWE-917",
      "function_names": [
        "replace_keys",
        "to_snake"
      ],
      "filenames": [
        "owlmixin/util.py"
      ]
    },
    {
      "headline": "Improper Validation of Specified Quantity in Input",
      "analysis": "The codebase contains potential issues related to the improper validation of specified quantities in input, which can lead to vulnerabilities. This could include scenarios where the size or length of user-supplied input is not properly validated, potentially leading to buffer overflow, denial of service, or other security problems.\n",
      "classification": "slightly promising",
      "cwe": "CWE-1284",
      "function_names": [
        "to_csv"
      ],
      "filenames": [
        "owlmixin/transformers.py"
      ]
    },
    {
      "headline": "Improper Neutralization of Formula Elements in a CSV File",
      "analysis": "The codebase contains potential issues related to the improper neutralization of formula elements in CSV files, which can lead to formula injection vulnerabilities. This could include scenarios where user-supplied input is not properly sanitized or validated before being used in CSV file generation, potentially allowing attackers to inject malicious formulas that could be executed by spreadsheet software or other applications.\n",
      "classification": "slightly promising",
      "cwe": "CWE-1236",
      "function_names": [
        "dump_csv"
      ],
      "filenames": [
        "owlmixin/util.py"
      ]
    }
  ],
  "scores": [
    {
      "stats": {
        "fn": 1,
        "tp": 0,
        "fp": 0
      },
      "mapping": {},
      "vuln_dates": {
        "CVE-2017-16618": "2017-11-08T03:29:00"
      },
      "scoring_model": "claude-3-5-sonnet-20240620",
      "type": "llm",
      "instruction_template_hash": "245ace12b6361954d0a2"
    }
  ],
  "instruction_template_hash": "10c0163db4740318a544",
  "version": "0.1.0"
}
