{
  "commit": "d17da850f1c0083de65e458937b8c6b2fbddaa3b",
  "repo_url": "https://github.com/mikebrady/nqptp",
  "model": "claude-3-5-sonnet-20240620",
  "chunk_hashes": [
    "27a9fb8e6703eeab5e4d"
  ],
  "responses": [
    {
      "content": "```yaml\nleads:\n  - headline: Buffer overflow vulnerability in debug_print_buffer function\n    analysis: |\n      The debug_print_buffer function in nqptp-utilities.c allocates a fixed-size buffer of 16384 bytes to store the hex representation of the input buffer. However, it does not check if the allocated buffer is large enough to hold the entire hex string. For large input buffers, this could lead to a buffer overflow. The function writes to obfp without checking if it has exceeded the allocated size of obf.\n    cwe: CWE-120\n    function_names:\n      - debug_print_buffer\n    filenames:\n      - nqptp-utilities.c\n    classification: slightly promising\n\n  - headline: Potential integer overflow in timespec_to_ns function\n    analysis: |\n      The timespec_to_ns function in general-utilities.c multiplies tn->tv_sec by 1000000000 to convert seconds to nanoseconds. For very large values of tv_sec, this multiplication could cause an integer overflow, resulting in incorrect time calculations. The function does not check for potential overflow before performing the multiplication.\n    cwe: CWE-190 \n    function_names:\n      - timespec_to_ns\n    filenames:\n      - general-utilities.c\n    classification: slightly promising\n\n  - headline: Potential command injection in handle_control_port_messages\n    analysis: |\n      The handle_control_port_messages function in nqptp-message-handlers.c parses and handles messages received on the control port. It uses strsep to parse the message into commands and arguments. However, it does not properly validate or sanitize the input before processing commands like \"T\" that accept IP addresses. An attacker could potentially inject malicious commands or arguments.\n    cwe: CWE-77\n    function_names:\n      - handle_control_port_messages  \n    filenames:\n      - nqptp-message-handlers.c\n    classification: slightly promising\n\n  - headline: Use of deprecated function inet_ntop\n    analysis: |\n      The code uses the deprecated inet_ntop function to convert IP addresses to strings in multiple places. While not a direct security vulnerability, using deprecated functions can lead to compatibility issues and potentially introduce bugs if the function's behavior changes in future versions.\n    cwe: CWE-477\n    function_names:\n      - send_awakening_announcement_sequence\n      - main\n    filenames:\n      - nqptp.c\n    classification: not promising\n\n  - headline: Potential uninitialized variable use in handle_follow_up\n    analysis: |\n      In the handle_follow_up function in nqptp-message-handlers.c, the variable \"jitter\" is used in calculations and conditional statements before it is definitively initialized. If the conditions for setting jitter are not met, it could be used while uninitialized, leading to unpredictable behavior.\n    cwe: CWE-457\n    function_names:\n      - handle_follow_up\n    filenames:\n      - nqptp-message-handlers.c\n    classification: slightly promising\n```",
      "date": "2024-07-08T04:39:51.934384",
      "usage": {
        "prompt_tokens": 34870,
        "completion_tokens": 732,
        "cost": 0.11559
      }
    }
  ],
  "leads": [
    {
      "headline": "Buffer overflow vulnerability in debug_print_buffer function",
      "analysis": "The debug_print_buffer function in nqptp-utilities.c allocates a fixed-size buffer of 16384 bytes to store the hex representation of the input buffer. However, it does not check if the allocated buffer is large enough to hold the entire hex string. For large input buffers, this could lead to a buffer overflow. The function writes to obfp without checking if it has exceeded the allocated size of obf.\n",
      "classification": "slightly promising",
      "cwe": "CWE-120",
      "function_names": [
        "debug_print_buffer"
      ],
      "filenames": [
        "nqptp-utilities.c"
      ]
    },
    {
      "headline": "Potential integer overflow in timespec_to_ns function",
      "analysis": "The timespec_to_ns function in general-utilities.c multiplies tn->tv_sec by 1000000000 to convert seconds to nanoseconds. For very large values of tv_sec, this multiplication could cause an integer overflow, resulting in incorrect time calculations. The function does not check for potential overflow before performing the multiplication.\n",
      "classification": "slightly promising",
      "cwe": "CWE-190",
      "function_names": [
        "timespec_to_ns"
      ],
      "filenames": [
        "general-utilities.c"
      ]
    },
    {
      "headline": "Potential command injection in handle_control_port_messages",
      "analysis": "The handle_control_port_messages function in nqptp-message-handlers.c parses and handles messages received on the control port. It uses strsep to parse the message into commands and arguments. However, it does not properly validate or sanitize the input before processing commands like \"T\" that accept IP addresses. An attacker could potentially inject malicious commands or arguments.\n",
      "classification": "slightly promising",
      "cwe": "CWE-77",
      "function_names": [
        "handle_control_port_messages"
      ],
      "filenames": [
        "nqptp-message-handlers.c"
      ]
    },
    {
      "headline": "Use of deprecated function inet_ntop",
      "analysis": "The code uses the deprecated inet_ntop function to convert IP addresses to strings in multiple places. While not a direct security vulnerability, using deprecated functions can lead to compatibility issues and potentially introduce bugs if the function's behavior changes in future versions.\n",
      "classification": "not promising",
      "cwe": "CWE-477",
      "function_names": [
        "send_awakening_announcement_sequence",
        "main"
      ],
      "filenames": [
        "nqptp.c"
      ]
    },
    {
      "headline": "Potential uninitialized variable use in handle_follow_up",
      "analysis": "In the handle_follow_up function in nqptp-message-handlers.c, the variable \"jitter\" is used in calculations and conditional statements before it is definitively initialized. If the conditions for setting jitter are not met, it could be used while uninitialized, leading to unpredictable behavior.\n",
      "classification": "slightly promising",
      "cwe": "CWE-457",
      "function_names": [
        "handle_follow_up"
      ],
      "filenames": [
        "nqptp-message-handlers.c"
      ]
    }
  ],
  "scores": [
    {
      "stats": {
        "fn": 1,
        "tp": 0,
        "fp": 0
      },
      "mapping": {},
      "vuln_dates": {
        "CVE-2023-43771": "2023-09-22T06:15:10"
      },
      "scoring_model": "claude-3-5-sonnet-20240620",
      "type": "llm",
      "instruction_template_hash": "245ace12b6361954d0a2"
    }
  ],
  "instruction_template_hash": "10c0163db4740318a544",
  "version": "0.1.0"
}
