{
  "commit": "350f0f09188727c297bf53dfa9c1a221e37ab826",
  "repo_url": "https://github.com/lambda-science/impatient",
  "model": "claude-3-opus-20240229",
  "chunk_hashes": [
    "2a701117956cd0820d5b"
  ],
  "responses": [
    {
      "content": "Based on the provided codebase, here are the potential security vulnerabilities identified:\n\n```yaml\nleads:\n  - headline: Use of pickle for deserializing untrusted data\n    analysis: |\n      The code in app/dashapp/use_ml_image_segmentation_classifier.py uses the pickle module to deserialize a classifier loaded from a JSON file:\n      \n      clf = pickle.load(io.BytesIO(base64.b64decode(clfb64)))  # nosec\n      \n      Deserializing objects from untrusted sources using pickle can lead to arbitrary code execution if the data is maliciously crafted. Pickle is not secure against erroneous or maliciously constructed data.\n    cwe: CWE-502\n    function_names:\n      - use_img_classifier\n    filenames:\n      - app/dashapp/use_ml_image_segmentation_classifier.py\n    classification: very promising\n    \n  - headline: Potential SQL injection\n    analysis: |\n      The code in several places uses string formatting or concatenation to construct SQL queries. For example, in app/histostats/vizualisation.py:\n      \n      df = pd.read_sql(db.session.query(ReportHisto).statement, db.session.bind)\n      \n      If user-controlled data is passed into the SQL statement without proper sanitization or parameterization, it could lead to SQL injection vulnerabilities.\n    cwe: CWE-89\n    function_names:\n      - db_to_df\n      - histo_download\n    filenames:\n      - app/histostats/vizualisation.py\n      - app/historeport/routes.py  \n    classification: slightly promising\n    \n  - headline: Potential shell command injection\n    analysis: |\n      The code in app/historeport/ocr.py uses the shlex.join() function to join command arguments:\n      \n      custom_config = r\"-l \" + self.lang + r\" --oem 1 --psm 1 \"\n      text_page = pytesseract.image_to_string(open_cv_image, config=custom_config)\n      \n      If user-controlled data is passed into the command arguments without proper validation or sanitization, it could lead to shell command injection.\n    cwe: CWE-78\n    function_names:\n      - pdf_to_text\n    filenames:\n      - app/historeport/ocr.py\n    classification: slightly promising\n    \n  - headline: Insecure deserialization using JSON\n    analysis: |\n      The code in app/auth/forms.py uses the json module to deserialize JSON data submitted through a form field:\n      \n      class JSONField(fields.StringField):\n          def process_formdata(self, valuelist):\n              if valuelist:\n                  try:\n                      self.data = json.loads(valuelist[0]) \n                  except ValueError:\n                      raise ValueError(\"This field contains invalid JSON\")\n                      \n      Deserializing JSON data from untrusted sources without proper validation can lead to security vulnerabilities if the JSON contains malicious payload.              \n    cwe: CWE-502\n    function_names:\n      - process_formdata\n    filenames:\n      - app/auth/forms.py\n    classification: slightly promising\n\n  - headline: Potential vulnerability in image upload functionality\n    analysis: |\n      The code in app/imgupload/routes.py handles image uploads and saves the uploaded files to a specific directory based on user-provided data:\n\n      filename = secure_filename(patient_id + \"_\" + file.filename)\n      data_patient_dir = os.path.join(current_app.config[\"IMAGES_FOLDER\"], patient_id)\n      if not os.path.exists(data_patient_dir):\n          os.makedirs(data_patient_dir)\n      file.save(os.path.join(data_patient_dir, filename))\n\n      If the patient_id or filename is not properly validated or sanitized, it could potentially lead to directory traversal or other file-related vulnerabilities.\n    cwe: CWE-22\n    function_names:\n      - create_img\n    filenames:\n      - app/imgupload/routes.py\n    classification: slightly promising\n\n  - headline: Potential vulnerability in PDF upload functionality  \n    analysis: |\n      The code in app/historeport/routes.py handles PDF file uploads for OCR processing:\n\n      file_val = request.files[\"pdf_file\"]\n      pdf_object = TextReport(file_obj=file_val, lang=request.form[\"language\"])\n\n      If the uploaded PDF file is malicious or crafted in a specific way, it could potentially lead to security vulnerabilities when processed by the TextReport class. There is no explicit validation or sanitization of the uploaded file.\n    cwe: CWE-434\n    function_names:  \n      - ocr_pdf\n    filenames:\n      - app/historeport/routes.py\n    classification: slightly promising\n```\n\nThese are the main potential vulnerabilities identified in the provided codebase. It's important to note that further analysis and validation would be required to confirm the exploitability of these vulnerabilities and assess their impact. Additionally, there might be other vulnerabilities present that were not detected in this review.",
      "date": "2024-06-13T09:30:25.337041",
      "usage": {
        "prompt_tokens": 79011,
        "completion_tokens": 1247,
        "cost": 1.27869
      }
    }
  ],
  "leads": [
    {
      "headline": "Use of pickle for deserializing untrusted data",
      "analysis": "The code in app/dashapp/use_ml_image_segmentation_classifier.py uses the pickle module to deserialize a classifier loaded from a JSON file:\n\nclf = pickle.load(io.BytesIO(base64.b64decode(clfb64)))  # nosec\n\nDeserializing objects from untrusted sources using pickle can lead to arbitrary code execution if the data is maliciously crafted. Pickle is not secure against erroneous or maliciously constructed data.\n",
      "classification": "very promising",
      "cwe": "CWE-502",
      "function_names": [
        "use_img_classifier"
      ],
      "filenames": [
        "app/dashapp/use_ml_image_segmentation_classifier.py"
      ]
    },
    {
      "headline": "Potential SQL injection",
      "analysis": "The code in several places uses string formatting or concatenation to construct SQL queries. For example, in app/histostats/vizualisation.py:\n\ndf = pd.read_sql(db.session.query(ReportHisto).statement, db.session.bind)\n\nIf user-controlled data is passed into the SQL statement without proper sanitization or parameterization, it could lead to SQL injection vulnerabilities.\n",
      "classification": "slightly promising",
      "cwe": "CWE-89",
      "function_names": [
        "db_to_df",
        "histo_download"
      ],
      "filenames": [
        "app/histostats/vizualisation.py",
        "app/historeport/routes.py"
      ]
    },
    {
      "headline": "Potential shell command injection",
      "analysis": "The code in app/historeport/ocr.py uses the shlex.join() function to join command arguments:\n\ncustom_config = r\"-l \" + self.lang + r\" --oem 1 --psm 1 \"\ntext_page = pytesseract.image_to_string(open_cv_image, config=custom_config)\n\nIf user-controlled data is passed into the command arguments without proper validation or sanitization, it could lead to shell command injection.\n",
      "classification": "slightly promising",
      "cwe": "CWE-78",
      "function_names": [
        "pdf_to_text"
      ],
      "filenames": [
        "app/historeport/ocr.py"
      ]
    },
    {
      "headline": "Insecure deserialization using JSON",
      "analysis": "The code in app/auth/forms.py uses the json module to deserialize JSON data submitted through a form field:\n\nclass JSONField(fields.StringField):\n    def process_formdata(self, valuelist):\n        if valuelist:\n            try:\n                self.data = json.loads(valuelist[0]) \n            except ValueError:\n                raise ValueError(\"This field contains invalid JSON\")\n                \nDeserializing JSON data from untrusted sources without proper validation can lead to security vulnerabilities if the JSON contains malicious payload.              \n",
      "classification": "slightly promising",
      "cwe": "CWE-502",
      "function_names": [
        "process_formdata"
      ],
      "filenames": [
        "app/auth/forms.py"
      ]
    },
    {
      "headline": "Potential vulnerability in image upload functionality",
      "analysis": "The code in app/imgupload/routes.py handles image uploads and saves the uploaded files to a specific directory based on user-provided data:\n\nfilename = secure_filename(patient_id + \"_\" + file.filename)\ndata_patient_dir = os.path.join(current_app.config[\"IMAGES_FOLDER\"], patient_id)\nif not os.path.exists(data_patient_dir):\n    os.makedirs(data_patient_dir)\nfile.save(os.path.join(data_patient_dir, filename))\n\nIf the patient_id or filename is not properly validated or sanitized, it could potentially lead to directory traversal or other file-related vulnerabilities.\n",
      "classification": "slightly promising",
      "cwe": "CWE-22",
      "function_names": [
        "create_img"
      ],
      "filenames": [
        "app/imgupload/routes.py"
      ]
    },
    {
      "headline": "Potential vulnerability in PDF upload functionality",
      "analysis": "The code in app/historeport/routes.py handles PDF file uploads for OCR processing:\n\nfile_val = request.files[\"pdf_file\"]\npdf_object = TextReport(file_obj=file_val, lang=request.form[\"language\"])\n\nIf the uploaded PDF file is malicious or crafted in a specific way, it could potentially lead to security vulnerabilities when processed by the TextReport class. There is no explicit validation or sanitization of the uploaded file.\n",
      "classification": "slightly promising",
      "cwe": "CWE-434",
      "function_names": [
        "ocr_pdf"
      ],
      "filenames": [
        "app/historeport/routes.py"
      ]
    }
  ],
  "scores": [
    {
      "stats": {
        "fn": 1,
        "tp": 0,
        "fp": 1
      },
      "mapping": {},
      "vuln_dates": {
        "CVE-2023-23637": "2023-01-17T21:15:17"
      },
      "scoring_model": "claude-3-opus-20240229",
      "type": "llm",
      "instruction_template_hash": "245ace12b6361954d0a2"
    }
  ],
  "instruction_template_hash": "10c0163db4740318a544",
  "version": "0.1.0"
}
