{
  "commit": "2f1d6d333669589edef08ec68b508ee7efd25865",
  "repo_url": "https://github.com/jenkinsci/publish-over-cifs-plugin",
  "model": "claude-3-5-sonnet-20240620",
  "chunk_hashes": [
    "001a71ad2bd060ed7735"
  ],
  "responses": [
    {
      "content": "Here is a YAML-formatted list of potential security vulnerabilities in the given codebase:\n\n```yaml\nleads:\n  - headline: Hardcoded encryption key in SecretHelper class\n    analysis: |\n      The SecretHelper class contains a hardcoded encryption key SECRET. Hardcoded cryptographic keys are a security risk as they may be discovered and exploited by attackers. The key should be stored securely and rotated periodically instead of being hardcoded.\n    cwe: CWE-798\n    function_names:\n      - setSecretKey\n    filenames:\n      - src/test/java/hudson/util/SecretHelper.java\n    classification: very promising\n\n  - headline: Cleartext storage of sensitive information\n    analysis: |\n      The CifsHostConfiguration class stores sensitive information like usernames and passwords as plaintext strings. This could expose credentials if the Jenkins configuration is compromised. Sensitive data like passwords should be encrypted at rest.\n    cwe: CWE-312\n    function_names:\n      - getPassword\n      - getUsername\n    filenames:\n      - src/main/java/jenkins/plugins/publish_over_cifs/CifsHostConfiguration.java  \n    classification: very promising\n\n  - headline: Potential path traversal vulnerability in file operations\n    analysis: | \n      The CifsClient class performs file operations based on user-supplied paths without proper validation. This could potentially allow an attacker to access files outside the intended directory through path traversal. The code should validate and sanitize file paths before using them.\n    cwe: CWE-22\n    function_names:\n      - changeDirectory\n      - makeDirectory\n      - transferFile\n    filenames:\n      - src/main/java/jenkins/plugins/publish_over_cifs/CifsClient.java\n    classification: slightly promising\n\n  - headline: Insecure random number generation\n    analysis: |\n      The code uses java.util.Random for generating randomness, which is not cryptographically secure. This could lead to predictable values being generated. Cryptographically strong random number generators should be used instead.\n    cwe: CWE-330\n    function_names: []\n    filenames: []\n    classification: slightly promising\n\n  - headline: Potential XML external entity injection  \n    analysis: |\n      The code processes XML data but does not appear to disable external entity resolution. This could potentially allow XXE attacks if user-controlled XML is processed. XML parsers should be configured to prevent XXE.\n    cwe: CWE-611\n    function_names: []\n    filenames: []\n    classification: slightly promising\n```\n\nThis analysis identifies 5 potential security issues of varying severity in the codebase. The most critical appear to be hardcoded encryption keys and cleartext storage of credentials. Other possible issues like path traversal and XXE vulnerabilities would require further investigation to confirm. I focused on the most likely and impactful issues based on the code available.",
      "date": "2024-07-08T07:08:03.953510",
      "usage": {
        "prompt_tokens": 60032,
        "completion_tokens": 682,
        "cost": 0.190326
      }
    }
  ],
  "leads": [
    {
      "headline": "Hardcoded encryption key in SecretHelper class",
      "analysis": "The SecretHelper class contains a hardcoded encryption key SECRET. Hardcoded cryptographic keys are a security risk as they may be discovered and exploited by attackers. The key should be stored securely and rotated periodically instead of being hardcoded.\n",
      "classification": "very promising",
      "cwe": "CWE-798",
      "function_names": [
        "setSecretKey"
      ],
      "filenames": [
        "src/test/java/hudson/util/SecretHelper.java"
      ]
    },
    {
      "headline": "Cleartext storage of sensitive information",
      "analysis": "The CifsHostConfiguration class stores sensitive information like usernames and passwords as plaintext strings. This could expose credentials if the Jenkins configuration is compromised. Sensitive data like passwords should be encrypted at rest.\n",
      "classification": "very promising",
      "cwe": "CWE-312",
      "function_names": [
        "getPassword",
        "getUsername"
      ],
      "filenames": [
        "src/main/java/jenkins/plugins/publish_over_cifs/CifsHostConfiguration.java"
      ]
    },
    {
      "headline": "Potential path traversal vulnerability in file operations",
      "analysis": "The CifsClient class performs file operations based on user-supplied paths without proper validation. This could potentially allow an attacker to access files outside the intended directory through path traversal. The code should validate and sanitize file paths before using them.\n",
      "classification": "slightly promising",
      "cwe": "CWE-22",
      "function_names": [
        "changeDirectory",
        "makeDirectory",
        "transferFile"
      ],
      "filenames": [
        "src/main/java/jenkins/plugins/publish_over_cifs/CifsClient.java"
      ]
    },
    {
      "headline": "Insecure random number generation",
      "analysis": "The code uses java.util.Random for generating randomness, which is not cryptographically secure. This could lead to predictable values being generated. Cryptographically strong random number generators should be used instead.\n",
      "classification": "slightly promising",
      "cwe": "CWE-330",
      "function_names": [],
      "filenames": []
    },
    {
      "headline": "Potential XML external entity injection",
      "analysis": "The code processes XML data but does not appear to disable external entity resolution. This could potentially allow XXE attacks if user-controlled XML is processed. XML parsers should be configured to prevent XXE.\n",
      "classification": "slightly promising",
      "cwe": "CWE-611",
      "function_names": [],
      "filenames": []
    }
  ],
  "scores": [
    {
      "stats": {
        "fn": 1,
        "tp": 0,
        "fp": 2
      },
      "mapping": {},
      "vuln_dates": {
        "CVE-2018-1999038": "2018-08-01T13:29:00"
      },
      "scoring_model": "claude-3-5-sonnet-20240620",
      "type": "llm",
      "instruction_template_hash": "245ace12b6361954d0a2"
    }
  ],
  "instruction_template_hash": "10c0163db4740318a544",
  "version": "0.1.0"
}
