{
  "commit": "0d6592f5db6c86c11cf95799893cb0de81dc6636",
  "repo_url": "https://github.com/jenkinsci/contrast-continuous-application-security-plugin",
  "model": "gpt-4o-2024-05-13",
  "chunk_hashes": [
    "9bd18b3af0e852466c25"
  ],
  "responses": [
    {
      "content": "```yaml\nleads:\n  - headline: Potential Security Configuration Issue in Main Script\n    analysis: |\n      The provided script `run.sh` disables the Jenkins CLI with the option `-Djenkins.CLI.disabled=true`. While this might be intended for security reasons, it's important to ensure that disabling the CLI does not inadvertently affect other security measures or the overall functionality of Jenkins. Additionally, sensitive configurations should be properly documented and reviewed to ensure there are no unintended side effects or security gaps.\n    cwe: CWE-754\n    function_names:\n      - \"\"\n    filenames:\n      - run.sh\n    classification: slightly promising\n\n  - headline: Use of Mocking Without Proper Validation\n    analysis: |\n      The provided test files, like `VulnerabilityTrendRecorderTest.java` and others, extensively make use of PowerMock and Mockito to mock objects and methods. While this is common practice in unit testing, improper use of mocking can sometimes lead to critical paths being left untested or inconsistencies between actual and test environments. This might mask real issues in the production environment.\n    cwe: CWE-754\n    function_names:\n      - \"testSuccessfulBuild\"\n      - \"testUnsuccessfulBuild\"\n      - \"testSuccessfulBuildWithNullCondition\"\n    filenames:\n      - src/test/java/com/aspectsecurity/contrast/contrastjenkins/VulnerabilityTrendRecorderTest.java\n      - src/test/java/com/aspectsecurity/contrast/contrastjenkins/VulnerabilityTrendStepTest.java\n    classification: slightly promising\n\n  - headline: Storing Sensitive Information in Jenkins Configuration\n    analysis: |\n      The `ContrastPluginConfig` class allows storing sensitive information such as Contrast API keys, service keys, and usernames. While passwords and keys are stored using the `Secret` class, it's crucial to ensure that no other sensitive information is exposed in logs, environment variables, or improperly handled in any way.\n    cwe: CWE-312\n    function_names:\n      - \"doTestTeamServerConnection\"\n    filenames:\n      - src/main/java/com/aspectsecurity/contrast/contrastjenkins/ContrastPluginConfig.java\n    classification: very promising\n\n  - headline: Logging Detailed Error Messages with Sensitive Data\n    analysis: |\n      Some methods, such as `doTestTeamServerConnection` in `ContrastPluginConfig`, log detailed error messages that might contain sensitive data. Logging sensitive information can expose the system to information leakage. It's critical to sanitize logs appropriately.\n    cwe: CWE-209\n    function_names:\n      - \"doTestTeamServerConnection\"\n    filenames:\n      - src/main/java/com/aspectsecurity/contrast/contrastjenkins/ContrastPluginConfig.java\n    classification: very promising\n\n  - headline: Potential Improper Input Handling in Helper Methods\n    analysis: |\n      The `VulnerabilityTrendHelper` class contains methods that process inputs, such as `getProfile(String profileName)`. Improper input handling and validation in these methods can lead to unexpected behavior or vulnerabilities. Ensure proper validation and handling of all inputs.\n    cwe: CWE-20\n    function_names:\n      - \"getProfile\"\n    filenames:\n      - src/main/java/com/aspectsecurity/contrast/contrastjenkins/VulnerabilityTrendHelper.java\n    classification: slightly promising\n\n  - headline: Insecure URL Handling in Jenkins Plugin Configuration\n    analysis: |\n      The `ContrastPluginConfig` class contains methods that test the connection to a given URL (`doTestTeamServerConnection`). Ensure that URLs are properly validated and sanitized to avoid SSRF (Server-Side Request Forgery) or similar attack vectors.\n    cwe: CWE-918\n    function_names:\n      - \"doTestTeamServerConnection\"\n    filenames:\n      - src/main/java/com/aspectsecurity/contrast/contrastjenkins/ContrastPluginConfig.java\n    classification: very promising\n```",
      "date": "2024-06-12T18:10:34.336257",
      "usage": {
        "prompt_tokens": 42758,
        "completion_tokens": 786,
        "cost": 0.22558
      }
    }
  ],
  "leads": [
    {
      "headline": "Potential Security Configuration Issue in Main Script",
      "analysis": "The provided script run.sh disables the Jenkins CLI with the option -Djenkins.CLI.disabled=true. While this might be intended for security reasons, it's important to ensure that disabling the CLI does not inadvertently affect other security measures or the overall functionality of Jenkins. Additionally, sensitive configurations should be properly documented and reviewed to ensure there are no unintended side effects or security gaps.\n",
      "classification": "slightly promising",
      "cwe": "CWE-754",
      "function_names": [
        ""
      ],
      "filenames": [
        "run.sh"
      ]
    },
    {
      "headline": "Use of Mocking Without Proper Validation",
      "analysis": "The provided test files, like VulnerabilityTrendRecorderTest.java and others, extensively make use of PowerMock and Mockito to mock objects and methods. While this is common practice in unit testing, improper use of mocking can sometimes lead to critical paths being left untested or inconsistencies between actual and test environments. This might mask real issues in the production environment.\n",
      "classification": "slightly promising",
      "cwe": "CWE-754",
      "function_names": [
        "testSuccessfulBuild",
        "testUnsuccessfulBuild",
        "testSuccessfulBuildWithNullCondition"
      ],
      "filenames": [
        "src/test/java/com/aspectsecurity/contrast/contrastjenkins/VulnerabilityTrendRecorderTest.java",
        "src/test/java/com/aspectsecurity/contrast/contrastjenkins/VulnerabilityTrendStepTest.java"
      ]
    },
    {
      "headline": "Storing Sensitive Information in Jenkins Configuration",
      "analysis": "The ContrastPluginConfig class allows storing sensitive information such as Contrast API keys, service keys, and usernames. While passwords and keys are stored using the Secret class, it's crucial to ensure that no other sensitive information is exposed in logs, environment variables, or improperly handled in any way.\n",
      "classification": "very promising",
      "cwe": "CWE-312",
      "function_names": [
        "doTestTeamServerConnection"
      ],
      "filenames": [
        "src/main/java/com/aspectsecurity/contrast/contrastjenkins/ContrastPluginConfig.java"
      ]
    },
    {
      "headline": "Logging Detailed Error Messages with Sensitive Data",
      "analysis": "Some methods, such as doTestTeamServerConnection in ContrastPluginConfig, log detailed error messages that might contain sensitive data. Logging sensitive information can expose the system to information leakage. It's critical to sanitize logs appropriately.\n",
      "classification": "very promising",
      "cwe": "CWE-209",
      "function_names": [
        "doTestTeamServerConnection"
      ],
      "filenames": [
        "src/main/java/com/aspectsecurity/contrast/contrastjenkins/ContrastPluginConfig.java"
      ]
    },
    {
      "headline": "Potential Improper Input Handling in Helper Methods",
      "analysis": "The VulnerabilityTrendHelper class contains methods that process inputs, such as getProfile(String profileName). Improper input handling and validation in these methods can lead to unexpected behavior or vulnerabilities. Ensure proper validation and handling of all inputs.\n",
      "classification": "slightly promising",
      "cwe": "CWE-20",
      "function_names": [
        "getProfile"
      ],
      "filenames": [
        "src/main/java/com/aspectsecurity/contrast/contrastjenkins/VulnerabilityTrendHelper.java"
      ]
    },
    {
      "headline": "Insecure URL Handling in Jenkins Plugin Configuration",
      "analysis": "The ContrastPluginConfig class contains methods that test the connection to a given URL (doTestTeamServerConnection). Ensure that URLs are properly validated and sanitized to avoid SSRF (Server-Side Request Forgery) or similar attack vectors.\n",
      "classification": "very promising",
      "cwe": "CWE-918",
      "function_names": [
        "doTestTeamServerConnection"
      ],
      "filenames": [
        "src/main/java/com/aspectsecurity/contrast/contrastjenkins/ContrastPluginConfig.java"
      ]
    }
  ],
  "scores": [
    {
      "stats": {
        "fn": 1,
        "tp": 0,
        "fp": 3
      },
      "mapping": {},
      "vuln_dates": {
        "CVE-2022-43420": "2022-10-19T16:15:11"
      },
      "scoring_model": "claude-3-opus-20240229",
      "type": "llm",
      "instruction_template_hash": "245ace12b6361954d0a2"
    }
  ],
  "instruction_template_hash": "10c0163db4740318a544",
  "version": "0.1.0"
}
