{
  "commit": "2dc029ee79b361947803e02adc2b1f7e92e4a8ab",
  "repo_url": "https://github.com/jenkinsci/sinatra-chef-builder-plugin",
  "model": "claude-3-haiku-20240307",
  "chunk_hashes": [
    "e78ac8be21985968e974"
  ],
  "responses": [
    {
      "content": "```yaml\nleads:\n  - headline: Sensitive information exposure in key.html\n    analysis: |\n      The key.html file contains the path to the private key used to connect to remote machines. This sensitive information should not be exposed in a web page that is publicly accessible. An attacker could gain access to the private key and use it to authenticate with the remote systems.\n    cwe: CWE-200\n    function_names: []\n    filenames:\n      - src/main/webapp/key.html\n    classification: very promising\n\n  - headline: Hardcoded URL in ChefXmlParser\n    analysis: |\n      The ChefXmlParser class contains a hardcoded URL (http://192.168.102.126:9980/) to fetch the list of nodes. This URL is hardcoded and not configurable, which could make it difficult to change the URL in the future. An attacker could potentially exploit this by modifying the URL to point to a malicious server and retrieve sensitive information.\n    cwe: CWE-732\n    function_names:\n      - getListofNodes\n    filenames:\n      - src/main/java/org/jenkinsci/plugins/chefbuilder/ChefXmlParser.java\n    classification: slightly promising\n\n  - headline: Potential command injection in ChefThread\n    analysis: |\n      The ChefThread class executes the command specified in the \"command\" parameter using the ChefSshClient.runchefclient() method. This command is not properly sanitized, which could allow an attacker to inject malicious commands and execute them on the remote machines.\n    cwe: CWE-77\n    function_names:\n      - call\n      - run\n    filenames:\n      - src/main/java/org/jenkinsci/plugins/chefbuilder/ChefThread.java\n    classification: very promising\n\n  - headline: Potential path traversal in ChefXmlParser\n    analysis: |\n      The ChefXmlParser class creates temporary files (/tmp/nodesxml.xml and /tmp/project.dtd) to store the XML data fetched from the hardcoded URL. The filenames are not properly sanitized, which could allow an attacker to perform path traversal attacks and access files outside of the intended directory.\n    cwe: CWE-22\n    function_names:\n      - getListofNodes\n    filenames:\n      - src/main/java/org/jenkinsci/plugins/chefbuilder/ChefXmlParser.java\n    classification: slightly promising\n\n  - headline: Lack of input validation in ChefBuilderConfiguration\n    analysis: |\n      The ChefBuilderConfiguration class lacks proper input validation for various parameters, such as the URL, filter, and command. This could lead to vulnerabilities like command injection, path traversal, and other types of injection attacks.\n    cwe: CWE-20\n    function_names:\n      - perform\n    filenames:\n      - src/main/java/org/jenkinsci/plugins/chefbuilder/ChefBuilderConfiguration.java\n    classification: very promising\n\n  - headline: Potential insecure SSH connection in ChefSshClient\n    analysis: |\n      The ChefSshClient class uses the JSch library to establish an SSH connection with the remote machines. However, it does not perform any verification of the host key or the remote server's identity. This could allow an attacker to perform man-in-the-middle attacks and intercept or modify the communication between the Jenkins server and the remote machines.\n    cwe: CWE-295\n    function_names:\n      - runchefclient\n    filenames:\n      - src/main/java/org/jenkinsci/plugins/chefbuilder/ChefSshClient.java\n    classification: slightly promising\n```",
      "date": "2024-06-12T19:11:10.842895",
      "usage": {
        "prompt_tokens": 10043,
        "completion_tokens": 883,
        "cost": 0.0036145
      }
    }
  ],
  "leads": [
    {
      "headline": "Sensitive information exposure in key.html",
      "analysis": "The key.html file contains the path to the private key used to connect to remote machines. This sensitive information should not be exposed in a web page that is publicly accessible. An attacker could gain access to the private key and use it to authenticate with the remote systems.\n",
      "classification": "very promising",
      "cwe": "CWE-200",
      "function_names": [],
      "filenames": [
        "src/main/webapp/key.html"
      ]
    },
    {
      "headline": "Hardcoded URL in ChefXmlParser",
      "analysis": "The ChefXmlParser class contains a hardcoded URL (http://192.168.102.126:9980/) to fetch the list of nodes. This URL is hardcoded and not configurable, which could make it difficult to change the URL in the future. An attacker could potentially exploit this by modifying the URL to point to a malicious server and retrieve sensitive information.\n",
      "classification": "slightly promising",
      "cwe": "CWE-732",
      "function_names": [
        "getListofNodes"
      ],
      "filenames": [
        "src/main/java/org/jenkinsci/plugins/chefbuilder/ChefXmlParser.java"
      ]
    },
    {
      "headline": "Potential command injection in ChefThread",
      "analysis": "The ChefThread class executes the command specified in the \"command\" parameter using the ChefSshClient.runchefclient() method. This command is not properly sanitized, which could allow an attacker to inject malicious commands and execute them on the remote machines.\n",
      "classification": "very promising",
      "cwe": "CWE-77",
      "function_names": [
        "call",
        "run"
      ],
      "filenames": [
        "src/main/java/org/jenkinsci/plugins/chefbuilder/ChefThread.java"
      ]
    },
    {
      "headline": "Potential path traversal in ChefXmlParser",
      "analysis": "The ChefXmlParser class creates temporary files (/tmp/nodesxml.xml and /tmp/project.dtd) to store the XML data fetched from the hardcoded URL. The filenames are not properly sanitized, which could allow an attacker to perform path traversal attacks and access files outside of the intended directory.\n",
      "classification": "slightly promising",
      "cwe": "CWE-22",
      "function_names": [
        "getListofNodes"
      ],
      "filenames": [
        "src/main/java/org/jenkinsci/plugins/chefbuilder/ChefXmlParser.java"
      ]
    },
    {
      "headline": "Lack of input validation in ChefBuilderConfiguration",
      "analysis": "The ChefBuilderConfiguration class lacks proper input validation for various parameters, such as the URL, filter, and command. This could lead to vulnerabilities like command injection, path traversal, and other types of injection attacks.\n",
      "classification": "very promising",
      "cwe": "CWE-20",
      "function_names": [
        "perform"
      ],
      "filenames": [
        "src/main/java/org/jenkinsci/plugins/chefbuilder/ChefBuilderConfiguration.java"
      ]
    },
    {
      "headline": "Potential insecure SSH connection in ChefSshClient",
      "analysis": "The ChefSshClient class uses the JSch library to establish an SSH connection with the remote machines. However, it does not perform any verification of the host key or the remote server's identity. This could allow an attacker to perform man-in-the-middle attacks and intercept or modify the communication between the Jenkins server and the remote machines.\n",
      "classification": "slightly promising",
      "cwe": "CWE-295",
      "function_names": [
        "runchefclient"
      ],
      "filenames": [
        "src/main/java/org/jenkinsci/plugins/chefbuilder/ChefSshClient.java"
      ]
    }
  ],
  "scores": [
    {
      "stats": {
        "fn": 4,
        "tp": 0,
        "fp": 3
      },
      "mapping": {},
      "vuln_dates": {
        "CVE-2019-1003087": "2019-04-04T16:29:01",
        "CVE-2022-25208": "2022-02-15T17:15:11",
        "CVE-2022-25207": "2022-02-15T17:15:11",
        "CVE-2022-25209": "2022-02-15T17:15:11"
      },
      "scoring_model": "claude-3-opus-20240229",
      "type": "llm",
      "instruction_template_hash": "245ace12b6361954d0a2"
    }
  ],
  "instruction_template_hash": "10c0163db4740318a544",
  "version": "0.1.0"
}
