{
  "commit": "4b97c41dbe6af6bd7ed6356053c1ea4e68b9a243",
  "repo_url": "https://github.com/zerocoin/libzerocoin",
  "model": "claude-3-haiku-20240307",
  "chunk_hashes": [
    "922d76ab26016a4c283e"
  ],
  "responses": [
    {
      "content": "Based on the provided codebase, here are the security vulnerabilities I have identified:\n\n```yaml\nleads:\n  - headline: Improper Input Validation in Mint Process\n    analysis: |\n      The `PrivateCoin` class contains two methods, `mintCoin` and `mintCoinFast`, that generate new zerocoin coins. These methods do not properly validate the input parameters, specifically the `denomination` parameter. An attacker could potentially trigger a denial-of-service condition by providing an invalid denomination value, causing the mint process to fail repeatedly.\n    cwe: CWE-20\n    function_names:\n      - PrivateCoin::mintCoin\n      - PrivateCoin::mintCoinFast\n    filenames:\n      - Coin.cpp\n    classification: slightly promising\n  - headline: Insecure Randomness in Coin Generation\n    analysis: |\n      The `PrivateCoin` class uses a call to `Bignum::randBignum` to generate the serial number and randomness for new coins. This function does not use a cryptographically secure random number generator, which could allow an attacker to predict or compromise the generated coins.\n    cwe: CWE-330\n    function_names:\n      - PrivateCoin::mintCoin\n      - PrivateCoin::mintCoinFast\n    filenames:\n      - Coin.cpp\n    classification: slightly promising\n  - headline: Possible Integer Overflow in Accumulator Witness Calculation\n    analysis: |\n      The `AccumulatorWitness` class calculates the witness value by repeatedly adding coins to the accumulator. This operation could potentially overflow the underlying data types, leading to incorrect witness values and a breakdown of the zerocoin protocol.\n    cwe: CWE-190\n    function_names:\n      - AccumulatorWitness::AddElement\n    filenames:\n      - Accumulator.cpp\n    classification: slightly promising\n  - headline: Insecure Serialization in CoinSpend\n    analysis: |\n      The `CoinSpend` class serializes several sensitive values, including the coin serial number and commitment values, using a simple binary serialization approach. This could allow an attacker to potentially deserialized and modify these values, compromising the security of the zerocoin spend.\n    cwe: CWE-502\n    function_names:\n      - CoinSpend::Serialize\n      - CoinSpend::Unserialize\n    filenames:\n      - CoinSpend.cpp\n    classification: slightly promising\n  - headline: Possible Timing Attacks in Commitment Proof of Knowledge\n    analysis: |\n      The `CommitmentProofOfKnowledge` class performs several modular exponentiations and inversions when generating and verifying the proof. These operations could potentially be vulnerable to timing attacks, allowing an attacker to extract sensitive information about the underlying commitments.\n    cwe: CWE-327\n    function_names:\n      - CommitmentProofOfKnowledge::Verify\n    filenames:\n      - Commitment.cpp\n    classification: slightly promising\n```\n\nThe main security vulnerabilities identified in the codebase are:\n\n1. **Improper Input Validation in Mint Process**: The `PrivateCoin` class does not properly validate the input `denomination` parameter, which could lead to a denial-of-service condition.\n\n2. **Insecure Randomness in Coin Generation**: The `PrivateCoin` class uses a non-cryptographic random number generator to generate the serial number and randomness for new coins, which could allow an attacker to predict or compromise the generated coins.\n\n3. **Possible Integer Overflow in Accumulator Witness Calculation**: The `AccumulatorWitness` class could be vulnerable to integer overflow issues when calculating the witness value, potentially leading to a breakdown of the zerocoin protocol.\n\n4. **Insecure Serialization in CoinSpend**: The `CoinSpend` class uses a simple binary serialization approach for sensitive values, which could allow an attacker to deserialize and modify these values.\n\n5. **Possible Timing Attacks in Commitment Proof of Knowledge**: The `CommitmentProofOfKnowledge` class performs operations that could be vulnerable to timing attacks, potentially leaking sensitive information about the underlying commitments.\n\nOverall, the codebase has several promising vulnerabilities that warrant further investigation and remediation.",
      "date": "2024-07-08T09:34:02.831090",
      "usage": {
        "prompt_tokens": 88267,
        "completion_tokens": 1016,
        "cost": 0.02333675
      }
    }
  ],
  "leads": [
    {
      "headline": "Improper Input Validation in Mint Process",
      "analysis": "The PrivateCoin class contains two methods, mintCoin and mintCoinFast, that generate new zerocoin coins. These methods do not properly validate the input parameters, specifically the denomination parameter. An attacker could potentially trigger a denial-of-service condition by providing an invalid denomination value, causing the mint process to fail repeatedly.\n",
      "classification": "slightly promising",
      "cwe": "CWE-20",
      "function_names": [
        "PrivateCoin::mintCoin",
        "PrivateCoin::mintCoinFast"
      ],
      "filenames": [
        "Coin.cpp"
      ]
    },
    {
      "headline": "Insecure Randomness in Coin Generation",
      "analysis": "The PrivateCoin class uses a call to Bignum::randBignum to generate the serial number and randomness for new coins. This function does not use a cryptographically secure random number generator, which could allow an attacker to predict or compromise the generated coins.\n",
      "classification": "slightly promising",
      "cwe": "CWE-330",
      "function_names": [
        "PrivateCoin::mintCoin",
        "PrivateCoin::mintCoinFast"
      ],
      "filenames": [
        "Coin.cpp"
      ]
    },
    {
      "headline": "Possible Integer Overflow in Accumulator Witness Calculation",
      "analysis": "The AccumulatorWitness class calculates the witness value by repeatedly adding coins to the accumulator. This operation could potentially overflow the underlying data types, leading to incorrect witness values and a breakdown of the zerocoin protocol.\n",
      "classification": "slightly promising",
      "cwe": "CWE-190",
      "function_names": [
        "AccumulatorWitness::AddElement"
      ],
      "filenames": [
        "Accumulator.cpp"
      ]
    },
    {
      "headline": "Insecure Serialization in CoinSpend",
      "analysis": "The CoinSpend class serializes several sensitive values, including the coin serial number and commitment values, using a simple binary serialization approach. This could allow an attacker to potentially deserialized and modify these values, compromising the security of the zerocoin spend.\n",
      "classification": "slightly promising",
      "cwe": "CWE-502",
      "function_names": [
        "CoinSpend::Serialize",
        "CoinSpend::Unserialize"
      ],
      "filenames": [
        "CoinSpend.cpp"
      ]
    },
    {
      "headline": "Possible Timing Attacks in Commitment Proof of Knowledge",
      "analysis": "The CommitmentProofOfKnowledge class performs several modular exponentiations and inversions when generating and verifying the proof. These operations could potentially be vulnerable to timing attacks, allowing an attacker to extract sensitive information about the underlying commitments.\n",
      "classification": "slightly promising",
      "cwe": "CWE-327",
      "function_names": [
        "CommitmentProofOfKnowledge::Verify"
      ],
      "filenames": [
        "Commitment.cpp"
      ]
    }
  ],
  "scores": [
    {
      "stats": {
        "fn": 1,
        "tp": 0,
        "fp": 0
      },
      "mapping": {},
      "vuln_dates": {
        "CVE-2017-20180": "2023-03-06T11:15:09"
      },
      "scoring_model": "claude-3-5-sonnet-20240620",
      "type": "llm",
      "instruction_template_hash": "245ace12b6361954d0a2"
    }
  ],
  "instruction_template_hash": "10c0163db4740318a544",
  "version": "0.1.0"
}
