{
  "commit": "2e8d4cce2cf60ac85264c1cdf535702edd731e9a",
  "repo_url": "https://github.com/afichet/openexr-viewer",
  "model": "claude-3-5-sonnet-20240620",
  "chunk_hashes": [
    "1fdbe03a962e07a28535"
  ],
  "responses": [
    {
      "content": "```yaml\nleads:\n  - headline: Use of uninitialized pointer in StdIStream\n    analysis: |\n      In the StdIStream class, the m_stream member variable is not initialized in the constructor. This could lead to undefined behavior if methods like read(), tellg() or seekg() are called before m_stream is properly set. An attacker could potentially exploit this to read or write arbitrary memory.\n    cwe: CWE-824\n    function_names:\n      - StdIStream\n    filenames:\n      - src/model/StdIStream.h\n    classification: slightly promising\n\n  - headline: Potential null pointer dereference in OpenEXRImage destructor\n    analysis: |\n      In the OpenEXRImage destructor, m_headerModel and m_layerModel are deleted without checking if they are null first. If these pointers are null, this could lead to a crash. An attacker could potentially craft a malformed file that causes these pointers to be null, then trigger the destructor to crash the program.\n    cwe: CWE-476  \n    function_names:\n      - ~OpenEXRImage\n    filenames:\n      - src/model/OpenEXRImage.cpp\n    classification: slightly promising\n\n  - headline: Potential buffer overflow in YFramebufferModel\n    analysis: |\n      In the YFramebufferModel::createThumbnail method, there are several places where array indexing is done without bounds checking, such as m_previewBuffer[4 * (yOffset * m_previewSize + x) + colorOffset]. If m_previewSize is set to an unexpectedly large value, this could lead to a buffer overflow. An attacker could potentially exploit this by providing a malformed input file that sets m_previewSize to a large value.\n    cwe: CWE-119\n    function_names:\n      - createThumbnail\n    filenames: \n      - src/model/framebuffer/YFramebufferModel.cpp\n    classification: slightly promising\n\n  - headline: Use of rand() for cryptographic purposes\n    analysis: |\n      While not explicitly shown in the provided code, the use of std::rand() is typically not suitable for cryptographic purposes due to its predictability. If this function is used anywhere in the codebase for generating random values for security-sensitive operations, it could be exploited by an attacker to predict the generated values.\n    cwe: CWE-338\n    function_names: []\n    filenames: []\n    classification: not promising\n\n  - headline: Potential integer overflow in LayerItem\n    analysis: |\n      In the LayerItem class, there are several places where integer arithmetic is performed without checking for overflow, such as in the childIndex method. If an attacker could control the number of child items, they might be able to cause an integer overflow leading to unexpected behavior or crashes.\n    cwe: CWE-190\n    function_names:\n      - childIndex\n    filenames:\n      - src/model/attribute/LayerItem.cpp\n    classification: slightly promising\n```",
      "date": "2024-07-07T20:33:41.212993",
      "usage": {
        "prompt_tokens": 106878,
        "completion_tokens": 718,
        "cost": 0.331404
      }
    }
  ],
  "leads": [
    {
      "headline": "Use of uninitialized pointer in StdIStream",
      "analysis": "In the StdIStream class, the m_stream member variable is not initialized in the constructor. This could lead to undefined behavior if methods like read(), tellg() or seekg() are called before m_stream is properly set. An attacker could potentially exploit this to read or write arbitrary memory.\n",
      "classification": "slightly promising",
      "cwe": "CWE-824",
      "function_names": [
        "StdIStream"
      ],
      "filenames": [
        "src/model/StdIStream.h"
      ]
    },
    {
      "headline": "Potential null pointer dereference in OpenEXRImage destructor",
      "analysis": "In the OpenEXRImage destructor, m_headerModel and m_layerModel are deleted without checking if they are null first. If these pointers are null, this could lead to a crash. An attacker could potentially craft a malformed file that causes these pointers to be null, then trigger the destructor to crash the program.\n",
      "classification": "slightly promising",
      "cwe": "CWE-476",
      "function_names": [
        "~OpenEXRImage"
      ],
      "filenames": [
        "src/model/OpenEXRImage.cpp"
      ]
    },
    {
      "headline": "Potential buffer overflow in YFramebufferModel",
      "analysis": "In the YFramebufferModel::createThumbnail method, there are several places where array indexing is done without bounds checking, such as m_previewBuffer[4 * (yOffset * m_previewSize + x) + colorOffset]. If m_previewSize is set to an unexpectedly large value, this could lead to a buffer overflow. An attacker could potentially exploit this by providing a malformed input file that sets m_previewSize to a large value.\n",
      "classification": "slightly promising",
      "cwe": "CWE-119",
      "function_names": [
        "createThumbnail"
      ],
      "filenames": [
        "src/model/framebuffer/YFramebufferModel.cpp"
      ]
    },
    {
      "headline": "Use of rand() for cryptographic purposes",
      "analysis": "While not explicitly shown in the provided code, the use of std::rand() is typically not suitable for cryptographic purposes due to its predictability. If this function is used anywhere in the codebase for generating random values for security-sensitive operations, it could be exploited by an attacker to predict the generated values.\n",
      "classification": "not promising",
      "cwe": "CWE-338",
      "function_names": [],
      "filenames": []
    },
    {
      "headline": "Potential integer overflow in LayerItem",
      "analysis": "In the LayerItem class, there are several places where integer arithmetic is performed without checking for overflow, such as in the childIndex method. If an attacker could control the number of child items, they might be able to cause an integer overflow leading to unexpected behavior or crashes.\n",
      "classification": "slightly promising",
      "cwe": "CWE-190",
      "function_names": [
        "childIndex"
      ],
      "filenames": [
        "src/model/attribute/LayerItem.cpp"
      ]
    }
  ],
  "scores": [
    {
      "stats": {
        "fn": 1,
        "tp": 0,
        "fp": 0
      },
      "mapping": {},
      "vuln_dates": {
        "CVE-2023-50245": "2023-12-11T23:15:08"
      },
      "scoring_model": "claude-3-5-sonnet-20240620",
      "type": "llm",
      "instruction_template_hash": "245ace12b6361954d0a2"
    }
  ],
  "instruction_template_hash": "10c0163db4740318a544",
  "version": "0.1.0"
}
