{
  "commit": "3d0c91ebb05cbb700c2343a29cd2955b9ceb4fb6",
  "repo_url": "https://github.com/netease-youdao/qanything",
  "model": "gpt-4o-2024-05-13",
  "chunk_hashes": [
    "d265cbab9a11995a3fa4"
  ],
  "responses": [
    {
      "content": "```yaml\nleads:\n  - headline: \"Possible Command Injection in close.sh Script\"\n    analysis: |\n      The \"close.sh\" script checks whether it is running under WSL or native Linux by examining the content of \"/proc/version\". \n      The issue arises when unsanitized input, such as the content of \"/proc/version\", is handled directly within the script. This script \n      evaluates the command and executes \"docker-compose ... down\" commands based on the string comparison. If an attacker has control over\n      input read from \"/proc/version\", they could inject malicious commands leading to a Command Injection vulnerability.\n    cwe: CWE-77\n    function_names: []\n    filenames:\n      - close.sh\n    classification: very promising\n    \n  - headline: \"Insecure Use of Docker Compose in run.sh Script\"\n    analysis: |\n      The \"run.sh\" script builds and manages Docker Compose commands based on the platform it is running on. It reads the content of files and executes Docker Compose commands dynamically.\n      However, the script does not adequately sanitize the GPU IDs, host input, or Docker Compose commands. There are potential security risks if these values are manipulated by an attacker.\n      For instance, improper validation of GPU IDs within the script may lead to command injections.\n    cwe: CWE-77\n    function_names: []\n    filenames:\n      - run.sh\n    classification: very promising\n\n  - headline: \"Hardcoded Credentials and Database Credentials in model_config.py\"\n    analysis: |\n      The \"qanything_kernel/configs/model_config.py\" file contains hardcoded credentials for MySQL databases, as seen in the MYSQL_USER and MYSQL_PASSWORD fields. The presence\n      of these hardcoded credentials shows a severe security risk, especially since they are stored directly within the source code. These credentials can be exposed, leading\n      to potential unauthorized access to the database.\n    cwe: CWE-798\n    function_names: []\n    filenames:\n      - qanything_kernel/configs/model_config.py\n    classification: very promising\n\n  - headline: \"Possible Information Disclosure and Logging of Sensitive Data in General Utilities\"\n    analysis: |\n      The logging configuration within various utility scripts, such as \"utils/general_utils.py\", may inadvertently log sensitive information. This is especially true given that the logging level \n      is set to \"INFO\", which can result in sensitive data being exposed in log files. Proper filtering and handling of sensitive data in logs is critical to prevent information disclosure.\n    cwe: CWE-532\n    function_names: []\n    filenames:\n      - qanything_kernel/utils/general_utils.py\n    classification: very promising\n    \n  - headline: \"Inadequate Input Validation for KnowledgeBaseManager class in mysql_client.py\"\n    analysis: |\n      The KnowledgeBaseManager class found in \"qanything_kernel/connector/database/mysql/mysql_client.py\" demonstrates a potential vulnerability \n      tied to improper input validation. Parameters received from users, such as user IDs and knowledge base IDs, are not rigorously validated or sanitized before being \n      incorporated into SQL queries. This raises risks related to SQL Injection attacks where maliciously crafted input can manipulate SQL queries and compromise the database.\n    cwe: CWE-89\n    function_names: \n      - check_file_exist\n      - check_file_exist_by_name\n      - execute_query_\n    filenames:\n      - qanything_kernel/connector/database/mysql/mysql_client.py\n    classification: very promising\n\n  - headline: \"Potential Path Traversal Vulnerability in LocalFile Class\"\n    analysis: |\n      The LocalFile class located in \"qanything_kernel/core/local_file.py\" processes file paths without comprehensive sanitization, showcasing a potential threat of\n      Path Traversal. If attackers can influence the file path, they may leverage this to gain unauthorized file system access, reading or writing files outside the designated directory.\n    cwe: CWE-22\n    function_names:\n      - __init__\n    filenames:\n      - qanything_kernel/core/local_file.py\n    classification: very promising\n```",
      "date": "2024-06-09T13:44:38.827340",
      "usage": {
        "prompt_tokens": 62875,
        "completion_tokens": 820,
        "cost": 0.326675
      }
    }
  ],
  "leads": [
    {
      "headline": "Possible Command Injection in close.sh Script",
      "analysis": "The \"close.sh\" script checks whether it is running under WSL or native Linux by examining the content of \"/proc/version\". \nThe issue arises when unsanitized input, such as the content of \"/proc/version\", is handled directly within the script. This script \nevaluates the command and executes \"docker-compose ... down\" commands based on the string comparison. If an attacker has control over\ninput read from \"/proc/version\", they could inject malicious commands leading to a Command Injection vulnerability.\n",
      "classification": "very promising",
      "cwe": "CWE-77",
      "function_names": [],
      "filenames": [
        "close.sh"
      ]
    },
    {
      "headline": "Insecure Use of Docker Compose in run.sh Script",
      "analysis": "The \"run.sh\" script builds and manages Docker Compose commands based on the platform it is running on. It reads the content of files and executes Docker Compose commands dynamically.\nHowever, the script does not adequately sanitize the GPU IDs, host input, or Docker Compose commands. There are potential security risks if these values are manipulated by an attacker.\nFor instance, improper validation of GPU IDs within the script may lead to command injections.\n",
      "classification": "very promising",
      "cwe": "CWE-77",
      "function_names": [],
      "filenames": [
        "run.sh"
      ]
    },
    {
      "headline": "Hardcoded Credentials and Database Credentials in model_config.py",
      "analysis": "The \"qanything_kernel/configs/model_config.py\" file contains hardcoded credentials for MySQL databases, as seen in the MYSQL_USER and MYSQL_PASSWORD fields. The presence\nof these hardcoded credentials shows a severe security risk, especially since they are stored directly within the source code. These credentials can be exposed, leading\nto potential unauthorized access to the database.\n",
      "classification": "very promising",
      "cwe": "CWE-798",
      "function_names": [],
      "filenames": [
        "qanything_kernel/configs/model_config.py"
      ]
    },
    {
      "headline": "Possible Information Disclosure and Logging of Sensitive Data in General Utilities",
      "analysis": "The logging configuration within various utility scripts, such as \"utils/general_utils.py\", may inadvertently log sensitive information. This is especially true given that the logging level \nis set to \"INFO\", which can result in sensitive data being exposed in log files. Proper filtering and handling of sensitive data in logs is critical to prevent information disclosure.\n",
      "classification": "very promising",
      "cwe": "CWE-532",
      "function_names": [],
      "filenames": [
        "qanything_kernel/utils/general_utils.py"
      ]
    },
    {
      "headline": "Inadequate Input Validation for KnowledgeBaseManager class in mysql_client.py",
      "analysis": "The KnowledgeBaseManager class found in \"qanything_kernel/connector/database/mysql/mysql_client.py\" demonstrates a potential vulnerability \ntied to improper input validation. Parameters received from users, such as user IDs and knowledge base IDs, are not rigorously validated or sanitized before being \nincorporated into SQL queries. This raises risks related to SQL Injection attacks where maliciously crafted input can manipulate SQL queries and compromise the database.\n",
      "classification": "very promising",
      "cwe": "CWE-89",
      "function_names": [
        "check_file_exist",
        "check_file_exist_by_name",
        "execute_query_"
      ],
      "filenames": [
        "qanything_kernel/connector/database/mysql/mysql_client.py"
      ]
    },
    {
      "headline": "Potential Path Traversal Vulnerability in LocalFile Class",
      "analysis": "The LocalFile class located in \"qanything_kernel/core/local_file.py\" processes file paths without comprehensive sanitization, showcasing a potential threat of\nPath Traversal. If attackers can influence the file path, they may leverage this to gain unauthorized file system access, reading or writing files outside the designated directory.\n",
      "classification": "very promising",
      "cwe": "CWE-22",
      "function_names": [
        "__init__"
      ],
      "filenames": [
        "qanything_kernel/core/local_file.py"
      ]
    }
  ],
  "scores": [
    {
      "stats": {
        "fn": 0,
        "tp": 1,
        "fp": 5
      },
      "mapping": {
        "4": "CVE-2024-25722"
      },
      "vuln_dates": {
        "CVE-2024-25722": "2024-02-11T05:15:08"
      },
      "scoring_model": "gpt-4o-2024-05-13",
      "type": "llm",
      "instruction_template_hash": "8998f09cf57fca8a6e03"
    }
  ],
  "instruction_template_hash": "10c0163db4740318a544",
  "version": "0.1.0"
}
