{
  "commit": "19bb72ef1cf1c4f291fd858ca2a44cef785c301c",
  "repo_url": "https://github.com/parisneo/lollms",
  "model": "gpt-4o-2024-05-13",
  "chunk_hashes": [
    "56e7d085548432af961c"
  ],
  "responses": [
    {
      "content": "```yaml\nleads:\n  - headline: Potential Injection Vulnerabilities in lollms/terminal.py\n    analysis: |\n      There are improper input sanitization issues in methods like show_other_options and install_model. User input is directly incorporated without validation or sanitization, potentially leading to injection attacks, including command injection and path traversal vulnerabilities.\n    cwe: CWE-78\n    function_names:\n      - show_other_options\n      - install_model\n    filenames:\n      - lollms/terminal.py\n    classification: very promising\n\n  - headline: Hardcoded Credentials in setup.py\n    analysis: |\n      Hardcoded credentials are found in setup.py file, especially in the email field. This can expose the system to unauthorized access if these credentials are used elsewhere without proper encryption or safeguarding.\n    cwe: CWE-798\n    function_names:\n    filenames:\n      - setup.py\n    classification: very promising\n\n  - headline: Insecure File Downloading in lollms/binding.py\n    analysis: |\n      The download_and_install_wheel function downloads and installs a file from an external URL without verifying its integrity via cryptographic signatures, leading to potential execution of malicious code.\n    cwe: CWE-494\n    function_names:\n      - download_and_install_wheel\n    filenames:\n      - lollms/binding.py\n    classification: very promising\n\n  - headline: Missing Encryption of Sensitive Data in lollms/data.py\n    analysis: |\n      The class SocketIOFile transfers files without encryption. This could lead to sensitive information being intercepted during transmission.\n    cwe: CWE-319\n    function_names:\n      - send_file\n      - save_file\n    filenames:\n      - lollms/data.py\n    classification: very promising\n\n  - headline: Potential Buffer Overflow in lollms/binding.py\n    analysis: |\n      The function searchModelPath does not properly validate the size of the model_name, which can lead to buffer overflow vulnerabilities if the filename is too long, thereby overflowing the buffer and corrupting memory.\n    cwe: CWE-120\n    function_names:\n      - searchModelPath\n    filenames:\n      - lollms/binding.py\n    classification: slightly promising\n\n  - headline: Unsanitized User Input in lollms_server\n    analysis: |\n      The server routes in LoLLMsServer do not sanitize user inputs properly before string concatenation, which may lead to XSS attacks if user input includes JavaScript code.\n    cwe: CWE-79\n    function_names:\n    filenames:\n      - lollms/apps/server/__init__.py\n    classification: very promising\n\n  - headline: Use of Insecure Random Number Generator in lollms/config.py\n    analysis: |\n      No secure random number generator is used for seeding purposes. This can lead to predictable values being generated, reducing cryptographic security.\n    cwe: CWE-338\n    function_names:\n    filenames:\n      - lollms/config.py\n    classification: slightly promising\n```",
      "date": "2024-06-09T14:00:21.944260",
      "usage": {
        "prompt_tokens": 78541,
        "completion_tokens": 623,
        "cost": 0.40205
      }
    }
  ],
  "leads": [
    {
      "headline": "Potential Injection Vulnerabilities in lollms/terminal.py",
      "analysis": "There are improper input sanitization issues in methods like show_other_options and install_model. User input is directly incorporated without validation or sanitization, potentially leading to injection attacks, including command injection and path traversal vulnerabilities.\n",
      "classification": "very promising",
      "cwe": "CWE-78",
      "function_names": [
        "show_other_options",
        "install_model"
      ],
      "filenames": [
        "lollms/terminal.py"
      ]
    },
    {
      "headline": "Insecure File Downloading in lollms/binding.py",
      "analysis": "The download_and_install_wheel function downloads and installs a file from an external URL without verifying its integrity via cryptographic signatures, leading to potential execution of malicious code.\n",
      "classification": "very promising",
      "cwe": "CWE-494",
      "function_names": [
        "download_and_install_wheel"
      ],
      "filenames": [
        "lollms/binding.py"
      ]
    },
    {
      "headline": "Missing Encryption of Sensitive Data in lollms/data.py",
      "analysis": "The class SocketIOFile transfers files without encryption. This could lead to sensitive information being intercepted during transmission.\n",
      "classification": "very promising",
      "cwe": "CWE-319",
      "function_names": [
        "send_file",
        "save_file"
      ],
      "filenames": [
        "lollms/data.py"
      ]
    },
    {
      "headline": "Potential Buffer Overflow in lollms/binding.py",
      "analysis": "The function searchModelPath does not properly validate the size of the model_name, which can lead to buffer overflow vulnerabilities if the filename is too long, thereby overflowing the buffer and corrupting memory.\n",
      "classification": "slightly promising",
      "cwe": "CWE-120",
      "function_names": [
        "searchModelPath"
      ],
      "filenames": [
        "lollms/binding.py"
      ]
    }
  ],
  "scores": [
    {
      "stats": {
        "fn": 1,
        "tp": 0,
        "fp": 3
      },
      "mapping": {},
      "vuln_dates": {
        "CVE-2024-4078": "2024-05-16T09:15:15"
      },
      "scoring_model": "gpt-4o-2024-05-13",
      "type": "llm",
      "instruction_template_hash": "8998f09cf57fca8a6e03"
    }
  ],
  "instruction_template_hash": "10c0163db4740318a544",
  "version": "0.1.0"
}
