{
  "commit": "1b0f3917b8f908c81bb646ce42f29cf7c86443a1",
  "repo_url": "https://github.com/lipnitsk/libcue",
  "model": "claude-3-haiku-20240307",
  "chunk_hashes": [
    "05312507afe9cc8b8ce0"
  ],
  "responses": [
    {
      "content": "```yaml\nleads:\n  - headline: Improper Neutralization of Special Elements used in an SQL Command ('SQL Injection')\n    analysis: |\n      The codebase contains a vulnerability to SQL injection attacks. The `track_get_filename()`, `cdtext_get()`, and `rem_get()` functions are used to retrieve data from the parsed CUE file, but the input is not properly validated or sanitized before being used in SQL queries or other operations. An attacker could potentially inject malicious SQL commands into the CUE file, which would then be executed when the data is retrieved, leading to unauthorized access, data manipulation, or other malicious actions.\n    cwe: CWE-89\n    function_names:\n      - track_get_filename\n      - cdtext_get\n      - rem_get\n    filenames:\n      - cd.c\n      - cdtext.c\n      - rem.c\n    classification: very promising\n\n  - headline: Improper Neutralization of Input During Web Page Generation ('Cross-site Scripting')\n    analysis: |\n      The codebase contains a vulnerability to cross-site scripting (XSS) attacks. The `cdtext_get()` and `rem_get()` functions are used to retrieve data from the parsed CUE file, but the input is not properly validated or sanitized before being used in output, such as when printing the CD or track information. An attacker could potentially inject malicious HTML or JavaScript into the CUE file, which would then be executed when the data is displayed, allowing the attacker to steal user data, hijack user sessions, or perform other malicious actions.\n    cwe: CWE-79\n    function_names:\n      - cdtext_get\n      - rem_get\n    filenames:\n      - cdtext.c\n      - rem.c\n    classification: very promising\n\n  - headline: Use of Externally-Controlled Input to Select Classes or Code ('Unsafe Reflection')\n    analysis: |\n      The codebase contains a vulnerability to unsafe reflection attacks. The `cdtext_get()` and `rem_get()` functions are used to retrieve data from the parsed CUE file, and this data is then used to select and execute code paths within the application. An attacker could potentially inject malicious code into the CUE file, which would then be executed when the data is processed, leading to arbitrary code execution, information disclosure, or other malicious actions.\n    cwe: CWE-470\n    function_names:\n      - cdtext_get\n      - rem_get\n    filenames:\n      - cdtext.c\n      - rem.c\n    classification: very promising\n\n  - headline: Deserialization of Untrusted Data\n    analysis: |\n      The codebase contains a vulnerability to deserialization attacks. The `cue_parse_file()` and `cue_parse_string()` functions are used to deserialize data from the CUE file, but the input is not properly validated or sanitized before being deserialized. An attacker could potentially craft a malicious CUE file that, when deserialized, could lead to arbitrary code execution, information disclosure, or other malicious actions.\n    cwe: CWE-502\n    function_names:\n      - cue_parse_file\n      - cue_parse_string\n    filenames:\n      - libcue.h\n    classification: very promising\n\n  - headline: Incorrect Default Permissions\n    analysis: |\n      The codebase does not properly handle file permissions. The `track_delete()` and `cd_delete()` functions free memory allocated for track and CD data, but they do not properly clean up or release any associated files or resources. An attacker could potentially exploit this by creating a malicious CUE file that causes the application to leak or improperly handle sensitive files, leading to information disclosure or other security issues.\n    cwe: CWE-276\n    function_names:\n      - track_delete\n      - cd_delete\n    filenames:\n      - cd.c\n    classification: slightly promising\n\n  - headline: Improper Check for Dropped Privileges\n    analysis: |\n      The codebase does not properly handle dropped privileges. The `cd_init()` function allocates memory for a CD structure, but it does not perform any checks to ensure that the memory allocation was successful. An attacker could potentially exploit this by creating a malicious CUE file that triggers a failed memory allocation, which could lead to unexpected program behavior or crashes, potentially allowing the attacker to escalate privileges or achieve other malicious goals.\n    cwe: CWE-273\n    function_names:\n      - cd_init\n    filenames:\n      - cd.c\n    classification: slightly promising\n\n  - headline: NULL Pointer Dereference\n    analysis: |\n      The codebase contains a vulnerability to null pointer dereferences. The `track_get_cdtext()` and `track_get_rem()` functions return pointers to CDText and REM data, respectively, but they do not check if the input Track pointer is null before dereferencing it. An attacker could potentially exploit this by creating a malicious CUE file that triggers a null pointer dereference, which could lead to crashes or other unexpected program behavior.\n    cwe: CWE-476\n    function_names:\n      - track_get_cdtext\n      - track_get_rem\n    filenames:\n      - cd.c\n    classification: slightly promising\n```",
      "date": "2024-06-09T13:13:45.496112",
      "usage": {
        "prompt_tokens": 20488,
        "completion_tokens": 1260,
        "cost": 0.006697
      }
    }
  ],
  "leads": [
    {
      "headline": "Improper Neutralization of Special Elements used in an SQL Command ('SQL Injection')",
      "analysis": "The codebase contains a vulnerability to SQL injection attacks. The track_get_filename(), cdtext_get(), and rem_get() functions are used to retrieve data from the parsed CUE file, but the input is not properly validated or sanitized before being used in SQL queries or other operations. An attacker could potentially inject malicious SQL commands into the CUE file, which would then be executed when the data is retrieved, leading to unauthorized access, data manipulation, or other malicious actions.\n",
      "classification": "very promising",
      "cwe": "CWE-89",
      "function_names": [
        "track_get_filename",
        "cdtext_get",
        "rem_get"
      ],
      "filenames": [
        "cd.c",
        "cdtext.c",
        "rem.c"
      ]
    },
    {
      "headline": "Improper Neutralization of Input During Web Page Generation ('Cross-site Scripting')",
      "analysis": "The codebase contains a vulnerability to cross-site scripting (XSS) attacks. The cdtext_get() and rem_get() functions are used to retrieve data from the parsed CUE file, but the input is not properly validated or sanitized before being used in output, such as when printing the CD or track information. An attacker could potentially inject malicious HTML or JavaScript into the CUE file, which would then be executed when the data is displayed, allowing the attacker to steal user data, hijack user sessions, or perform other malicious actions.\n",
      "classification": "very promising",
      "cwe": "CWE-79",
      "function_names": [
        "cdtext_get",
        "rem_get"
      ],
      "filenames": [
        "cdtext.c",
        "rem.c"
      ]
    },
    {
      "headline": "Use of Externally-Controlled Input to Select Classes or Code ('Unsafe Reflection')",
      "analysis": "The codebase contains a vulnerability to unsafe reflection attacks. The cdtext_get() and rem_get() functions are used to retrieve data from the parsed CUE file, and this data is then used to select and execute code paths within the application. An attacker could potentially inject malicious code into the CUE file, which would then be executed when the data is processed, leading to arbitrary code execution, information disclosure, or other malicious actions.\n",
      "classification": "very promising",
      "cwe": "CWE-470",
      "function_names": [
        "cdtext_get",
        "rem_get"
      ],
      "filenames": [
        "cdtext.c",
        "rem.c"
      ]
    },
    {
      "headline": "Deserialization of Untrusted Data",
      "analysis": "The codebase contains a vulnerability to deserialization attacks. The cue_parse_file() and cue_parse_string() functions are used to deserialize data from the CUE file, but the input is not properly validated or sanitized before being deserialized. An attacker could potentially craft a malicious CUE file that, when deserialized, could lead to arbitrary code execution, information disclosure, or other malicious actions.\n",
      "classification": "very promising",
      "cwe": "CWE-502",
      "function_names": [
        "cue_parse_file",
        "cue_parse_string"
      ],
      "filenames": [
        "libcue.h"
      ]
    },
    {
      "headline": "Incorrect Default Permissions",
      "analysis": "The codebase does not properly handle file permissions. The track_delete() and cd_delete() functions free memory allocated for track and CD data, but they do not properly clean up or release any associated files or resources. An attacker could potentially exploit this by creating a malicious CUE file that causes the application to leak or improperly handle sensitive files, leading to information disclosure or other security issues.\n",
      "classification": "slightly promising",
      "cwe": "CWE-276",
      "function_names": [
        "track_delete",
        "cd_delete"
      ],
      "filenames": [
        "cd.c"
      ]
    },
    {
      "headline": "Improper Check for Dropped Privileges",
      "analysis": "The codebase does not properly handle dropped privileges. The cd_init() function allocates memory for a CD structure, but it does not perform any checks to ensure that the memory allocation was successful. An attacker could potentially exploit this by creating a malicious CUE file that triggers a failed memory allocation, which could lead to unexpected program behavior or crashes, potentially allowing the attacker to escalate privileges or achieve other malicious goals.\n",
      "classification": "slightly promising",
      "cwe": "CWE-273",
      "function_names": [
        "cd_init"
      ],
      "filenames": [
        "cd.c"
      ]
    },
    {
      "headline": "NULL Pointer Dereference",
      "analysis": "The codebase contains a vulnerability to null pointer dereferences. The track_get_cdtext() and track_get_rem() functions return pointers to CDText and REM data, respectively, but they do not check if the input Track pointer is null before dereferencing it. An attacker could potentially exploit this by creating a malicious CUE file that triggers a null pointer dereference, which could lead to crashes or other unexpected program behavior.\n",
      "classification": "slightly promising",
      "cwe": "CWE-476",
      "function_names": [
        "track_get_cdtext",
        "track_get_rem"
      ],
      "filenames": [
        "cd.c"
      ]
    }
  ],
  "scores": [
    {
      "stats": {
        "fn": 1,
        "tp": 0,
        "fp": 4
      },
      "mapping": {},
      "vuln_dates": {
        "CVE-2023-43641": "2023-10-09T22:15:12"
      },
      "scoring_model": "gpt-4o-2024-05-13",
      "type": "llm",
      "instruction_template_hash": "8998f09cf57fca8a6e03"
    }
  ],
  "instruction_template_hash": "10c0163db4740318a544",
  "version": "0.1.0"
}
