{
  "commit": "1da1f26b797691777b456c02af47dce1627b7bc0",
  "repo_url": "https://github.com/citymont/symetrie",
  "model": "claude-3-opus-20240229",
  "chunk_hashes": [
    "12fdd383e73cb1474479"
  ],
  "responses": [
    {
      "content": "Here is the YAML output with possible security vulnerabilities in the provided codebase:\n\n```yaml\nleads:\n  - headline: Potential XSS vulnerability in img tags\n    analysis: |\n      The 'img1' and 'img2' elements with the 'contenteditable' attribute set to true allow\n      inserting image tags. If unsanitized user input is allowed in these fields, an attacker \n      could inject malicious scripts via 'onerror' or other attributes on the img tag. When\n      this HTML is rendered, the injected scripts would execute, leading to XSS.\n    cwe: CWE-79\n    function_names: []\n    filenames:\n      - app/model/index.editable.html\n    classification: very promising\n\n  - headline: Client-side template injection \n    analysis: |\n      The contenteditable elements in index.editable.html, if rendered on the client-side\n      using an unsafe templating engine, may allow an attacker to inject malicious template  \n      syntax that breaks out of the element context and executes arbitrary JavaScript when\n      the template is rendered. This could lead to XSS or sensitive data exposure.\n    cwe: CWE-1336\n    function_names: []\n    filenames:\n      - app/model/index.editable.html\n    classification: slightly promising\n  \n  - headline: Improper access control on content editing \n    analysis: |\n      Multiple elements in index.editable.html have contenteditable set to true, allowing\n      modification of content. If proper access controls and authorization checks are not\n      in place on the server-side when processing and persisting this user-modified content, \n      an attacker could make unauthorized changes, deface the site, or inject malicious content.\n    cwe: CWE-284\n    function_names: []\n    filenames:\n      - app/model/index.editable.html\n    classification: promising\n\n  - headline: Lack of CSRF protection on content update  \n    analysis: |\n      The extra.js code shows content being saved to the server via AJAX requests when \n      onSaveDoc() is called. If the endpoint handling this request does not implement proper\n      CSRF protection measures, an attacker could craft a malicious page to make a cross-origin\n      request to the save endpoint and modify content without the user's knowledge.\n    cwe: CWE-352\n    function_names:\n      - onSaveDoc\n    filenames: \n      - public/assets/admin/js/extra.js\n    classification: very promising\n\n  - headline: Client-side data manipulation and spoofing\n    analysis: |\n      Various JS functions in extra.js (onSaveDoc, findElementsEditable, etc.) read data from\n      the DOM and localStorage to send to the server. An attacker could manipulate this data in\n      the browser before it is sent, potentially tricking the server. Also, any client-side \n      access controls based on className could be bypassed by modifying the DOM. All sensitive\n      actions and access control checks must be performed server-side.\n    cwe: CWE-602\n    function_names:\n      - onSaveDoc\n      - findElementsEditable\n      - loadHistoryData\n    filenames:\n      - public/assets/admin/js/extra.js  \n    classification: promising\n\n  - headline: Potential arbitrary file upload\n    analysis: |\n      The createUploadDiv function in extra.js initializes a Dropzone for uploading files.\n      Depending on how the server handles the uploaded files, and missing file type and content \n      validation, this could potentially be abused by an attacker to upload malicious files (e.g.\n      web shell) and gain unauthorized access on the server.\n    cwe: CWE-434\n    function_names:\n      - createUploadDiv\n    filenames:\n      - public/assets/admin/js/extra.js\n    classification: slightly promising\n\n  - headline: SSRF in image thumbnail creation\n    analysis: |\n      Dropzone.prototype.createThumbnailFromUrl in dropzone.js takes a user-supplied URL to \n      generate a thumbnail image. If the server allows remote URLs, an attacker could exploit \n      this to make the server issue requests to arbitrary URLs, potentially accessing internal\n      services or aiding in port scanning and service discovery.\n    cwe: CWE-918\n    function_names:\n      - Dropzone.prototype.createThumbnailFromUrl\n    filenames:\n      - public/assets/admin/js/vendor/dropzone.js\n    classification: very promising\n\n  - headline: Client-side enforcement of access control\n    analysis: |\n      The checkTextHighlighting function in editor.js applies access controls based on element\n      classes to determine if certain operations are allowed on an element. Access control based \n      on client-side data is bypassable by modifying the DOM. Any sensitive access control \n      decisions must be enforced server-side.\n    cwe: CWE-602\n    function_names:\n      - checkTextHighlighting\n    filenames:\n      - public/assets/admin/js/vendor/zenpen/js/editor.js\n    classification: slightly promising\n```\n\nThe key vulnerabilities identified are potential XSS, client-side template injection, improper access control on editable content, lack of CSRF protection, spoofing of client-side data, unsafe file uploads, SSRF in thumbnail creation, and reliance on client-side access controls. Further investigation and validation is recommended to determine exploitability and impact of these issues.",
      "date": "2024-06-12T15:37:41.684754",
      "usage": {
        "prompt_tokens": 31418,
        "completion_tokens": 1308,
        "cost": 0.56937
      }
    }
  ],
  "leads": [
    {
      "headline": "Potential XSS vulnerability in img tags",
      "analysis": "The 'img1' and 'img2' elements with the 'contenteditable' attribute set to true allow\ninserting image tags. If unsanitized user input is allowed in these fields, an attacker \ncould inject malicious scripts via 'onerror' or other attributes on the img tag. When\nthis HTML is rendered, the injected scripts would execute, leading to XSS.\n",
      "classification": "very promising",
      "cwe": "CWE-79",
      "function_names": [],
      "filenames": [
        "app/model/index.editable.html"
      ]
    },
    {
      "headline": "Client-side template injection",
      "analysis": "The contenteditable elements in index.editable.html, if rendered on the client-side\nusing an unsafe templating engine, may allow an attacker to inject malicious template  \nsyntax that breaks out of the element context and executes arbitrary JavaScript when\nthe template is rendered. This could lead to XSS or sensitive data exposure.\n",
      "classification": "slightly promising",
      "cwe": "CWE-1336",
      "function_names": [],
      "filenames": [
        "app/model/index.editable.html"
      ]
    },
    {
      "headline": "Lack of CSRF protection on content update",
      "analysis": "The extra.js code shows content being saved to the server via AJAX requests when \nonSaveDoc() is called. If the endpoint handling this request does not implement proper\nCSRF protection measures, an attacker could craft a malicious page to make a cross-origin\nrequest to the save endpoint and modify content without the user's knowledge.\n",
      "classification": "very promising",
      "cwe": "CWE-352",
      "function_names": [
        "onSaveDoc"
      ],
      "filenames": [
        "public/assets/admin/js/extra.js"
      ]
    },
    {
      "headline": "Potential arbitrary file upload",
      "analysis": "The createUploadDiv function in extra.js initializes a Dropzone for uploading files.\nDepending on how the server handles the uploaded files, and missing file type and content \nvalidation, this could potentially be abused by an attacker to upload malicious files (e.g.\nweb shell) and gain unauthorized access on the server.\n",
      "classification": "slightly promising",
      "cwe": "CWE-434",
      "function_names": [
        "createUploadDiv"
      ],
      "filenames": [
        "public/assets/admin/js/extra.js"
      ]
    },
    {
      "headline": "SSRF in image thumbnail creation",
      "analysis": "Dropzone.prototype.createThumbnailFromUrl in dropzone.js takes a user-supplied URL to \ngenerate a thumbnail image. If the server allows remote URLs, an attacker could exploit \nthis to make the server issue requests to arbitrary URLs, potentially accessing internal\nservices or aiding in port scanning and service discovery.\n",
      "classification": "very promising",
      "cwe": "CWE-918",
      "function_names": [
        "Dropzone.prototype.createThumbnailFromUrl"
      ],
      "filenames": [
        "public/assets/admin/js/vendor/dropzone.js"
      ]
    },
    {
      "headline": "Client-side enforcement of access control",
      "analysis": "The checkTextHighlighting function in editor.js applies access controls based on element\nclasses to determine if certain operations are allowed on an element. Access control based \non client-side data is bypassable by modifying the DOM. Any sensitive access control \ndecisions must be enforced server-side.\n",
      "classification": "slightly promising",
      "cwe": "CWE-602",
      "function_names": [
        "checkTextHighlighting"
      ],
      "filenames": [
        "public/assets/admin/js/vendor/zenpen/js/editor.js"
      ]
    }
  ],
  "scores": [
    {
      "stats": {
        "fn": 1,
        "tp": 0,
        "fp": 3
      },
      "mapping": {},
      "vuln_dates": {
        "CVE-2017-7386": "2017-04-01T00:59:00"
      },
      "scoring_model": "claude-3-opus-20240229",
      "type": "llm",
      "instruction_template_hash": "245ace12b6361954d0a2"
    }
  ],
  "instruction_template_hash": "10c0163db4740318a544",
  "version": "0.1.0"
}
