{
  "commit": "284d9162b9903c1828aa13ab56420c1183c49d40",
  "repo_url": "https://github.com/projen/projen",
  "model": "claude-3-5-sonnet-20240620",
  "chunk_hashes": [
    "c44bb8f37e02d4c37eb4"
  ],
  "responses": [
    {
      "content": "```yaml\nleads:\n  - headline: \"Potential command injection vulnerability in exec function\"\n    analysis: |\n      The exec function in src/util.ts uses template literals to construct the command string, which could allow command injection if untrusted input is passed in. The command is executed using child_process.execSync, which spawns a shell. An attacker could potentially inject additional commands by including shell metacharacters in the input.\n    cwe: CWE-78\n    function_names:\n      - exec\n    filenames:\n      - src/util.ts\n    classification: \"very promising\"\n\n  - headline: \"Potential prototype pollution vulnerability in deepMerge function\"\n    analysis: |\n      The deepMerge function in src/util.ts recursively merges objects, including their prototypes. This could potentially allow an attacker to pollute the prototype of built-in objects if untrusted data is passed to this function. The function does not appear to have any checks to prevent modification of object prototypes.\n    cwe: CWE-1321  \n    function_names:\n      - deepMerge\n    filenames:\n      - src/util.ts\n    classification: \"very promising\"\n\n  - headline: \"Use of eval-like function in renderDefault\"\n    analysis: |\n      The renderDefault function in src/cli/new.ts uses JSON.parse to evaluate default values. This could potentially execute arbitrary code if an attacker can control the input to this function. While JSON.parse is safer than eval, it can still execute getter functions or constructors in some cases.\n    cwe: CWE-95\n    function_names:\n      - renderDefault  \n    filenames:\n      - src/cli/new.ts\n    classification: \"slightly promising\"\n\n  - headline: \"Potential path traversal vulnerability in FileBase class\"\n    analysis: |\n      The FileBase class in src/file.ts constructs file paths using user-provided values without sufficient validation. This could potentially allow an attacker to access files outside the intended directory via path traversal. The class does not appear to have checks to prevent \"..\" or other potentially malicious path components.\n    cwe: CWE-22\n    function_names:\n      - FileBase\n    filenames:\n      - src/file.ts  \n    classification: \"slightly promising\"\n\n  - headline: \"Use of insecure cryptographic algorithm (MD5) in exec function\"\n    analysis: |\n      The exec function in src/util.ts appears to use the MD5 hashing algorithm, based on the comment mentioning \"md5 hash\". MD5 is considered cryptographically broken and should not be used for security purposes. However, without seeing the actual usage, it's unclear if this poses a real security risk in this context.\n    cwe: CWE-327\n    function_names:\n      - exec\n    filenames:\n      - src/util.ts\n    classification: \"not promising\"\n```",
      "date": "2024-07-08T08:18:33.244793",
      "usage": {
        "prompt_tokens": 179229,
        "completion_tokens": 680,
        "cost": 0.547887
      }
    }
  ],
  "leads": [
    {
      "headline": "Potential command injection vulnerability in exec function",
      "analysis": "The exec function in src/util.ts uses template literals to construct the command string, which could allow command injection if untrusted input is passed in. The command is executed using child_process.execSync, which spawns a shell. An attacker could potentially inject additional commands by including shell metacharacters in the input.\n",
      "classification": "very promising",
      "cwe": "CWE-78",
      "function_names": [
        "exec"
      ],
      "filenames": [
        "src/util.ts"
      ]
    },
    {
      "headline": "Potential prototype pollution vulnerability in deepMerge function",
      "analysis": "The deepMerge function in src/util.ts recursively merges objects, including their prototypes. This could potentially allow an attacker to pollute the prototype of built-in objects if untrusted data is passed to this function. The function does not appear to have any checks to prevent modification of object prototypes.\n",
      "classification": "very promising",
      "cwe": "CWE-1321",
      "function_names": [
        "deepMerge"
      ],
      "filenames": [
        "src/util.ts"
      ]
    },
    {
      "headline": "Use of eval-like function in renderDefault",
      "analysis": "The renderDefault function in src/cli/new.ts uses JSON.parse to evaluate default values. This could potentially execute arbitrary code if an attacker can control the input to this function. While JSON.parse is safer than eval, it can still execute getter functions or constructors in some cases.\n",
      "classification": "slightly promising",
      "cwe": "CWE-95",
      "function_names": [
        "renderDefault"
      ],
      "filenames": [
        "src/cli/new.ts"
      ]
    },
    {
      "headline": "Potential path traversal vulnerability in FileBase class",
      "analysis": "The FileBase class in src/file.ts constructs file paths using user-provided values without sufficient validation. This could potentially allow an attacker to access files outside the intended directory via path traversal. The class does not appear to have checks to prevent \"..\" or other potentially malicious path components.\n",
      "classification": "slightly promising",
      "cwe": "CWE-22",
      "function_names": [
        "FileBase"
      ],
      "filenames": [
        "src/file.ts"
      ]
    },
    {
      "headline": "Use of insecure cryptographic algorithm (MD5) in exec function",
      "analysis": "The exec function in src/util.ts appears to use the MD5 hashing algorithm, based on the comment mentioning \"md5 hash\". MD5 is considered cryptographically broken and should not be used for security purposes. However, without seeing the actual usage, it's unclear if this poses a real security risk in this context.\n",
      "classification": "not promising",
      "cwe": "CWE-327",
      "function_names": [
        "exec"
      ],
      "filenames": [
        "src/util.ts"
      ]
    }
  ],
  "scores": [
    {
      "stats": {
        "fn": 1,
        "tp": 0,
        "fp": 2
      },
      "mapping": {},
      "vuln_dates": {
        "CVE-2021-21423": "2021-04-06T19:15:14"
      },
      "scoring_model": "claude-3-5-sonnet-20240620",
      "type": "llm",
      "instruction_template_hash": "245ace12b6361954d0a2"
    }
  ],
  "instruction_template_hash": "10c0163db4740318a544",
  "version": "0.1.0"
}
