{
  "commit": "0951f227aa9399ce0bb721cb7c51169eaa517633",
  "repo_url": "https://github.com/jenkinsci/ghprb-plugin",
  "model": "claude-3-haiku-20240307",
  "chunk_hashes": [
    "00d65da818c2b6e67c66"
  ],
  "responses": [
    {
      "content": "Here is the YAML output:\n\n```yaml\nleads:\n  - headline: Improper Input Validation\n    analysis: |\n      The codebase contains several instances of improper input validation, which could lead to security vulnerabilities such as buffer overflow, out-of-bounds read/write, and integer overflow/underflow. These issues are often exploitable and can lead to remote code execution, denial of service, or other malicious activities.\n    cwe: CWE-20\n    function_names:\n      - GhprbPullRequest.check\n      - GhprbPullRequest.updatePR\n    filenames:\n      - src/main/java/org/jenkinsci/plugins/ghprb/GhprbPullRequest.java\n    classification: very promising\n\n  - headline: Injection\n    analysis: |\n      The codebase contains several instances of improper input validation, which could lead to injection vulnerabilities such as command injection, SQL injection, and XML injection. These vulnerabilities can allow an attacker to execute arbitrary code, access sensitive data, or perform other malicious actions.\n    cwe: CWE-74\n    function_names:\n      - GhprbRepository.onIssueCommentHook\n      - GhprbRepository.onPullRequestHook\n    filenames:\n      - src/main/java/org/jenkinsci/plugins/ghprb/GhprbRepository.java\n    classification: very promising\n\n  - headline: Improper Neutralization of Output\n    analysis: |\n      The codebase contains instances of improper neutralization of output, which could lead to cross-site scripting (XSS) vulnerabilities. These vulnerabilities can allow an attacker to inject malicious scripts into the application's output, potentially allowing them to steal sensitive information or perform other malicious actions on behalf of the victim.\n    cwe: CWE-116\n    function_names:\n      - GhprbCause.getTitle\n      - GhprbCause.getDescription\n    filenames:\n      - src/main/java/org/jenkinsci/plugins/ghprb/GhprbCause.java\n    classification: slightly promising\n\n  - headline: Improper Privilege Management\n    analysis: |\n      The codebase contains instances of improper privilege management, which could lead to escalation of privileges or unauthorized access. These vulnerabilities can allow an attacker to perform actions or access resources that they should not have access to.\n    cwe: CWE-269\n    function_names:\n      - Ghprb.isAdmin\n      - Ghprb.isWhitelisted\n    filenames:\n      - src/main/java/org/jenkinsci/plugins/ghprb/Ghprb.java\n    classification: slightly promising\n\n  - headline: Improper Authentication\n    analysis: |\n      The codebase contains instances of improper authentication, which could lead to authentication bypass or weak password requirements. These vulnerabilities can allow an attacker to gain unauthorized access to the system or sensitive data.\n    cwe: CWE-287\n    function_names:\n      - GhprbGitHubAuth.checkSignature\n      - GhprbGitHubAuth.getConnection\n    filenames:\n      - src/main/java/org/jenkinsci/plugins/ghprb/GhprbGitHubAuth.java\n    classification: slightly promising\n```",
      "date": "2024-06-12T18:26:05.539931",
      "usage": {
        "prompt_tokens": 121941,
        "completion_tokens": 797,
        "cost": 0.0314815
      }
    }
  ],
  "leads": [
    {
      "headline": "Improper Input Validation",
      "analysis": "The codebase contains several instances of improper input validation, which could lead to security vulnerabilities such as buffer overflow, out-of-bounds read/write, and integer overflow/underflow. These issues are often exploitable and can lead to remote code execution, denial of service, or other malicious activities.\n",
      "classification": "very promising",
      "cwe": "CWE-20",
      "function_names": [
        "GhprbPullRequest.check",
        "GhprbPullRequest.updatePR"
      ],
      "filenames": [
        "src/main/java/org/jenkinsci/plugins/ghprb/GhprbPullRequest.java"
      ]
    },
    {
      "headline": "Injection",
      "analysis": "The codebase contains several instances of improper input validation, which could lead to injection vulnerabilities such as command injection, SQL injection, and XML injection. These vulnerabilities can allow an attacker to execute arbitrary code, access sensitive data, or perform other malicious actions.\n",
      "classification": "very promising",
      "cwe": "CWE-74",
      "function_names": [
        "GhprbRepository.onIssueCommentHook",
        "GhprbRepository.onPullRequestHook"
      ],
      "filenames": [
        "src/main/java/org/jenkinsci/plugins/ghprb/GhprbRepository.java"
      ]
    },
    {
      "headline": "Improper Neutralization of Output",
      "analysis": "The codebase contains instances of improper neutralization of output, which could lead to cross-site scripting (XSS) vulnerabilities. These vulnerabilities can allow an attacker to inject malicious scripts into the application's output, potentially allowing them to steal sensitive information or perform other malicious actions on behalf of the victim.\n",
      "classification": "slightly promising",
      "cwe": "CWE-116",
      "function_names": [
        "GhprbCause.getTitle",
        "GhprbCause.getDescription"
      ],
      "filenames": [
        "src/main/java/org/jenkinsci/plugins/ghprb/GhprbCause.java"
      ]
    },
    {
      "headline": "Improper Privilege Management",
      "analysis": "The codebase contains instances of improper privilege management, which could lead to escalation of privileges or unauthorized access. These vulnerabilities can allow an attacker to perform actions or access resources that they should not have access to.\n",
      "classification": "slightly promising",
      "cwe": "CWE-269",
      "function_names": [
        "Ghprb.isAdmin",
        "Ghprb.isWhitelisted"
      ],
      "filenames": [
        "src/main/java/org/jenkinsci/plugins/ghprb/Ghprb.java"
      ]
    },
    {
      "headline": "Improper Authentication",
      "analysis": "The codebase contains instances of improper authentication, which could lead to authentication bypass or weak password requirements. These vulnerabilities can allow an attacker to gain unauthorized access to the system or sensitive data.\n",
      "classification": "slightly promising",
      "cwe": "CWE-287",
      "function_names": [
        "GhprbGitHubAuth.checkSignature",
        "GhprbGitHubAuth.getConnection"
      ],
      "filenames": [
        "src/main/java/org/jenkinsci/plugins/ghprb/GhprbGitHubAuth.java"
      ]
    }
  ],
  "scores": [
    {
      "stats": {
        "fn": 6,
        "tp": 0,
        "fp": 2
      },
      "mapping": {},
      "vuln_dates": {
        "CVE-2023-24436": "2023-01-26T21:18:17",
        "CVE-2023-24435": "2023-01-26T21:18:17",
        "CVE-2023-24434": "2023-01-26T21:18:17",
        "CVE-2018-1000143": "2018-04-05T13:29:00",
        "CVE-2018-1000142": "2018-04-05T13:29:00",
        "CVE-2018-1000186": "2018-06-05T20:29:00"
      },
      "scoring_model": "claude-3-opus-20240229",
      "type": "llm",
      "instruction_template_hash": "245ace12b6361954d0a2"
    }
  ],
  "instruction_template_hash": "10c0163db4740318a544",
  "version": "0.1.0"
}
