{
  "commit": "1c517ffafcf8907b159146ae51d897cd3bcddbfe",
  "repo_url": "https://github.com/datadog/guarddog",
  "model": "gpt-4-turbo-2024-04-09",
  "chunk_hashes": [
    "4c404fd2d4b50c07f486"
  ],
  "responses": [
    {
      "content": "```yaml\nleads:\n  - headline: Arbitrary command execution via eval and exec\n    analysis: |\n      The codebase contains multiple instances where it uses functions like `eval()` and `exec()` to execute dynamically generated code or code derived from user-editable files, which can lead to arbitrary command execution if an attacker can manipulate these inputs.\n    cwe: CWE-94\n    function_names:\n      - test_requirements_scanner_on_non_existing_package\n      - scan_local\n      - RequirementsScanner.scan_requirements\n    filenames:\n      - tests/core/test_requirements_scanner.py\n      - guarddog/scanners/package_scanner.py\n      - guarddog/scanners/project_scanner.py\n    classification: very promising\n\n  - headline: Possible download and execution of malicious executables\n    analysis: |\n      There are portions of the analyzed code that demonstrate patterns indicating the download of external files followed by attempts to execute these files. This type of behavior is common in dropper-type malware, which downloads and executes malicious payloads.\n    cwe: CWE-94\n    function_names:\n      - _scan_remote\n      - test_typosquats\n    filenames:\n      - guarddog/scanners/package_scanner.py\n      - tests/analyzer/metadata/test_typosquatting.py\n    classification: very promising\n\n  - headline: Evaluation scripts potential misuse leading to code execution\n    analysis: |\n      The evaluator script loads packages and potentially executes commands within the context of analyzing and evaluating them. If an attacker can influence the packages being evaluated, this might lead to arbitrary command execution.\n    cwe: CWE-94\n    function_names:\n      - Evaluator.evaluate\n      - Evaluator._download_benign\n    filenames:\n      - scripts/evaluator/evaluator.py\n    classification: slightly promising\n\n  - headline: Insecure handling of file paths and URLs\n    analysis: |\n      Several methods within the analysis framework involve generating file paths or URLs dynamically, potentially leading to path traversal, insecure file access or URL-based attacks if not properly sanitized.\n    cwe: CWE-706\n    function_names:\n      - Evaluator._evaluate_benign\n      - Evaluator._download_benign\n    filenames:\n      - scripts/evaluator/evaluator.py\n    classification: slightly promising\n\n  - headline: Improper package validation causing security bypass\n    analysis: |\n      There's a lack of comprehensive validation on some methods that process and install packages externally. This could allow malicious packages to bypass existing security measures, leading to broader system compromise.\n    cwe: CWE-20\n    function_names:\n      - PackageScanner.download_package\n      - PackageScanner.scan_local\n    filenames:\n      - guarddog/scanners/package_scanner.py\n    classification: very promising\n\n  - headline: Potential leakage of sensitive data via inadequate masking\n    analysis: |\n      Some methods are designed to handle sensitive information, such as API keys or package metadata, which, due to inadequate processing, may end up being logged or exposed in a manner that is accessible to unauthorized parties.\n    cwe: CWE-200\n    function_names:\n      - RequirementsScanner._authenticate_by_access_token\n      - PackageScanner._scan_remote\n    filenames:\n      - guarddog/scanners/project_scanner.py\n      - guarddog/scanners/package_scanner.py\n    classification: very promising\n```",
      "date": "2024-06-12T15:53:28.585032",
      "usage": {
        "prompt_tokens": 25346,
        "completion_tokens": 688,
        "cost": 0.2741
      }
    }
  ],
  "leads": [
    {
      "headline": "Arbitrary command execution via eval and exec",
      "analysis": "The codebase contains multiple instances where it uses functions like eval() and exec() to execute dynamically generated code or code derived from user-editable files, which can lead to arbitrary command execution if an attacker can manipulate these inputs.\n",
      "classification": "very promising",
      "cwe": "CWE-94",
      "function_names": [
        "test_requirements_scanner_on_non_existing_package",
        "scan_local",
        "RequirementsScanner.scan_requirements"
      ],
      "filenames": [
        "tests/core/test_requirements_scanner.py",
        "guarddog/scanners/package_scanner.py",
        "guarddog/scanners/project_scanner.py"
      ]
    },
    {
      "headline": "Possible download and execution of malicious executables",
      "analysis": "There are portions of the analyzed code that demonstrate patterns indicating the download of external files followed by attempts to execute these files. This type of behavior is common in dropper-type malware, which downloads and executes malicious payloads.\n",
      "classification": "very promising",
      "cwe": "CWE-94",
      "function_names": [
        "_scan_remote",
        "test_typosquats"
      ],
      "filenames": [
        "guarddog/scanners/package_scanner.py",
        "tests/analyzer/metadata/test_typosquatting.py"
      ]
    },
    {
      "headline": "Evaluation scripts potential misuse leading to code execution",
      "analysis": "The evaluator script loads packages and potentially executes commands within the context of analyzing and evaluating them. If an attacker can influence the packages being evaluated, this might lead to arbitrary command execution.\n",
      "classification": "slightly promising",
      "cwe": "CWE-94",
      "function_names": [
        "Evaluator.evaluate",
        "Evaluator._download_benign"
      ],
      "filenames": [
        "scripts/evaluator/evaluator.py"
      ]
    },
    {
      "headline": "Insecure handling of file paths and URLs",
      "analysis": "Several methods within the analysis framework involve generating file paths or URLs dynamically, potentially leading to path traversal, insecure file access or URL-based attacks if not properly sanitized.\n",
      "classification": "slightly promising",
      "cwe": "CWE-706",
      "function_names": [
        "Evaluator._evaluate_benign",
        "Evaluator._download_benign"
      ],
      "filenames": [
        "scripts/evaluator/evaluator.py"
      ]
    },
    {
      "headline": "Improper package validation causing security bypass",
      "analysis": "There's a lack of comprehensive validation on some methods that process and install packages externally. This could allow malicious packages to bypass existing security measures, leading to broader system compromise.\n",
      "classification": "very promising",
      "cwe": "CWE-20",
      "function_names": [
        "PackageScanner.download_package",
        "PackageScanner.scan_local"
      ],
      "filenames": [
        "guarddog/scanners/package_scanner.py"
      ]
    },
    {
      "headline": "Potential leakage of sensitive data via inadequate masking",
      "analysis": "Some methods are designed to handle sensitive information, such as API keys or package metadata, which, due to inadequate processing, may end up being logged or exposed in a manner that is accessible to unauthorized parties.\n",
      "classification": "very promising",
      "cwe": "CWE-200",
      "function_names": [
        "RequirementsScanner._authenticate_by_access_token",
        "PackageScanner._scan_remote"
      ],
      "filenames": [
        "guarddog/scanners/project_scanner.py",
        "guarddog/scanners/package_scanner.py"
      ]
    }
  ],
  "scores": [
    {
      "stats": {
        "fn": 2,
        "tp": 0,
        "fp": 4
      },
      "mapping": {},
      "vuln_dates": {
        "CVE-2022-23530": "2022-12-16T23:15:09",
        "CVE-2022-23531": "2022-12-17T00:15:08"
      },
      "scoring_model": "claude-3-opus-20240229",
      "type": "llm",
      "instruction_template_hash": "245ace12b6361954d0a2"
    }
  ],
  "instruction_template_hash": "10c0163db4740318a544",
  "version": "0.1.0"
}
