{
  "commit": "03b393a3d08dcede570ea3d2ab305175eec6327d",
  "repo_url": "https://github.com/bouke/django-two-factor-auth",
  "model": "claude-3-sonnet-20240229",
  "chunk_hashes": [
    "9556a684bbdc57402cf3"
  ],
  "responses": [
    {
      "content": "```yaml\nleads:\n  - headline: Potential command injection vulnerability\n    analysis: |\n      The code in `two_factor/gateways/twilio/views.py` creates an XML response string based on user input (locale and token parameters) without properly sanitizing or escaping the input. Specifically, the `create_response` method constructs an XML string by interpolating the `locale` and `token` values into the response templates. If an attacker can control these values, they could potentially inject malicious XML or other code into the response.\n    cwe: CWE-77\n    function_names:\n      - create_response\n      - get_prompt_context\n    filenames:\n      - two_factor/gateways/twilio/views.py\n    classification: slightly promising\n\n  - headline: Potential open redirect vulnerability\n    analysis: |\n      The `LoginView` class in `two_factor/views/core.py` redirects the user to the URL specified in the `next` parameter after successful login. However, the code does not appear to validate or sanitize this URL, potentially allowing an attacker to redirect users to a malicious site.\n    cwe: CWE-601\n    function_names:\n      - done\n    filenames:\n      - two_factor/views/core.py\n    classification: very promising\n\n  - headline: Potential exposure of sensitive information\n    analysis: |\n      The `Fake` gateway class in `two_factor/gateways/fake.py` logs the user's phone number and authentication token to the application's logger. If the log files are not properly secured, this could expose sensitive information to unauthorized parties.\n    cwe: CWE-532\n    function_names:\n      - make_call\n      - send_sms\n    filenames:\n      - two_factor/gateways/fake.py\n    classification: very promising\n\n  - headline: Potential code injection vulnerability\n    analysis: |\n      The `SetupView` class in `two_factor/views/core.py` uses the `import_string` function to dynamically import a class based on the `TWO_FACTOR_QR_FACTORY` setting. If this setting can be controlled by an attacker, they could potentially cause arbitrary code to be executed.\n    cwe: CWE-470\n    function_names:\n      - get\n    filenames:\n      - two_factor/views/core.py\n    classification: slightly promising\n\n  - headline: Potential validation vulnerability\n    analysis: |\n      The `TOTPDeviceForm` class in `two_factor/forms.py` validates the user-provided token by comparing it to a set of expected values generated using the user's secret key. However, the validation logic appears to be overly permissive, potentially allowing an attacker to bypass the validation by providing a carefully crafted token.\n    cwe: CWE-20\n    function_names:\n      - clean_token\n    filenames:\n      - two_factor/forms.py\n    classification: slightly promising\n```\n\nThe main potential vulnerabilities identified in the codebase are:\n\n1. **Command injection**: User-controlled input is used to construct an XML response without proper sanitization, potentially allowing command injection.\n2. **Open redirect**: The `next` parameter is not properly validated before redirecting the user after login, enabling potential open redirect vulnerabilities.\n3. **Exposure of sensitive information**: The `Fake` gateway logs sensitive information (phone numbers and tokens) to the application logger, potentially exposing this data if logs are not secured.\n4. **Code injection**: The application uses `import_string` to dynamically load a class based on a configuration setting, potentially allowing code injection if the setting is controlled by an attacker.\n5. **Validation vulnerability**: The token validation logic in the `TOTPDeviceForm` appears to be overly permissive, potentially allowing an attacker to bypass validation with a carefully crafted token.\n\nNote that some of these issues are marked as \"slightly promising\" because further analysis would be required to determine their exploitability and severity in practice.",
      "date": "2024-06-12T15:17:49.385593",
      "usage": {
        "prompt_tokens": 56281,
        "completion_tokens": 930,
        "cost": 0.182793
      }
    }
  ],
  "leads": [
    {
      "headline": "Potential command injection vulnerability",
      "analysis": "The code in two_factor/gateways/twilio/views.py creates an XML response string based on user input (locale and token parameters) without properly sanitizing or escaping the input. Specifically, the create_response method constructs an XML string by interpolating the locale and token values into the response templates. If an attacker can control these values, they could potentially inject malicious XML or other code into the response.\n",
      "classification": "slightly promising",
      "cwe": "CWE-77",
      "function_names": [
        "create_response",
        "get_prompt_context"
      ],
      "filenames": [
        "two_factor/gateways/twilio/views.py"
      ]
    },
    {
      "headline": "Potential open redirect vulnerability",
      "analysis": "The LoginView class in two_factor/views/core.py redirects the user to the URL specified in the next parameter after successful login. However, the code does not appear to validate or sanitize this URL, potentially allowing an attacker to redirect users to a malicious site.\n",
      "classification": "very promising",
      "cwe": "CWE-601",
      "function_names": [
        "done"
      ],
      "filenames": [
        "two_factor/views/core.py"
      ]
    },
    {
      "headline": "Potential exposure of sensitive information",
      "analysis": "The Fake gateway class in two_factor/gateways/fake.py logs the user's phone number and authentication token to the application's logger. If the log files are not properly secured, this could expose sensitive information to unauthorized parties.\n",
      "classification": "very promising",
      "cwe": "CWE-532",
      "function_names": [
        "make_call",
        "send_sms"
      ],
      "filenames": [
        "two_factor/gateways/fake.py"
      ]
    },
    {
      "headline": "Potential code injection vulnerability",
      "analysis": "The SetupView class in two_factor/views/core.py uses the import_string function to dynamically import a class based on the TWO_FACTOR_QR_FACTORY setting. If this setting can be controlled by an attacker, they could potentially cause arbitrary code to be executed.\n",
      "classification": "slightly promising",
      "cwe": "CWE-470",
      "function_names": [
        "get"
      ],
      "filenames": [
        "two_factor/views/core.py"
      ]
    },
    {
      "headline": "Potential validation vulnerability",
      "analysis": "The TOTPDeviceForm class in two_factor/forms.py validates the user-provided token by comparing it to a set of expected values generated using the user's secret key. However, the validation logic appears to be overly permissive, potentially allowing an attacker to bypass the validation by providing a carefully crafted token.\n",
      "classification": "slightly promising",
      "cwe": "CWE-20",
      "function_names": [
        "clean_token"
      ],
      "filenames": [
        "two_factor/forms.py"
      ]
    }
  ],
  "scores": [
    {
      "stats": {
        "fn": 1,
        "tp": 0,
        "fp": 2
      },
      "mapping": {},
      "vuln_dates": {
        "CVE-2020-15105": "2020-07-10T21:15:10"
      },
      "scoring_model": "claude-3-opus-20240229",
      "type": "llm",
      "instruction_template_hash": "245ace12b6361954d0a2"
    },
    {
      "stats": {
        "fn": 1,
        "tp": 0,
        "fp": 2
      },
      "mapping": {},
      "vuln_dates": {
        "CVE-2020-15105": "2020-07-10T21:15:10"
      },
      "scoring_model": "claude-3-5-sonnet-20240620",
      "type": "llm",
      "instruction_template_hash": "245ace12b6361954d0a2"
    }
  ],
  "instruction_template_hash": "10c0163db4740318a544",
  "version": "0.1.0"
}
