{
  "commit": "f3b1b183df3bd9f2163349314d04306eafeb1320",
  "repo_url": "https://github.com/peppermint-lab/peppermint",
  "model": "gpt-4-turbo-2024-04-09",
  "chunk_hashes": [
    "93263371cc4b2406fd63"
  ],
  "responses": [
    {
      "content": "```yaml\nleads:\n  - headline: \"Use of Hard-coded Credentials in NextAuth\"\n    analysis: |\n      The NextAuth authentication provider setup uses a hard-coded 'secret' variable within the [...nextauth].js configuration file. This practice is risky as it exposes the application to potential attacks where the hardcoded secret may be discovered by a malicious actor analyzing the code, enabling them to potentially forge session tokens or conduct attacks that depend on the secrecy of this value.\n    cwe: CWE-798\n    function_names:\n      - authorize\n    filenames:\n      - pages/api/auth/[...nextauth].js\n    classification: very promising\n  \n  - headline: \"Improper File Path Sanitization Leading to Potential Directory Traversal\"\n    analysis: |\n      The file download utilities within the pages/api/v1/users/file/download.js and pages/api/v1/ticket/[id]/file/download.js allow for user controlled input to dictate file paths without sufficient sanitization checks. This could potentially lead to directory traversal, where an attacker could access or manipulate files outside of the intended directories by using relative file paths.\n    cwe: CWE-22\n    function_names:\n      - listFiles\n      - downloadFile\n    filenames:\n      - pages/api/vfind/ticket/[id]/file/download.js\n      - pages/api/v1/users/file/download.js\n    classification: very promising\n  \n  - headline: \"Use of Unprotected Formidable Module Data Leading to Overwritten Files\"\n    analysis: |\n      The application uses the Formidable module for parsing form data, specifically file uploads. In pages/api/v1/users/file/upload.js and pages/api/v1/ticket/[id]/file/upload.js, the files are saved to directories using user-controllable file names without proper checks. This behavior could lead to files being overwritten if a user repeats a file name intentionally or accidentally.\n    cwe: CWE-732\n    function_names:\n      - UploadFile\n    filenames:\n      - pages/api/v1/users/fil/upload.js\n      - pages/api/v1/ticket/[id]/file/upload.js\n    classification: very promising\n  \n  - headline: \"Lack of Authentication Checks in Client-Side Routes\"\n    analysis: |\n      Various client-side pages and API endpoints do not implement checks to verify if a user is authenticated or authorized to perform certain actions like accessing user files or updating sensitive user information. This oversight may allow unauthorized parties to access or manipulate data or perform restricted actions.\n    cwe: CWE-862\n    function_names:\n      - getAllClients\n      - userProfile\n      - editUser\n    filenames:\n      - pages/api/v1/users/[id]/profile.js\n      - pages/api/v1/clients/all.js\n    classification: very promising\n  \n  - headline: \"Potential SQL Injection via Direct Injection of Parameters into SQL Queries\"\n    analysis: |\n      In several API routes, the parameters taken from requests are concatenated directly into SQL queries without sanitization or parameterization, creating potential for SQL injection attacks, where a malicious actor could manipulate queries to modify query logic, leading to unauthorized data exposure or manipulation.\n    cwe: CWE-89\n    function_names:\n      - updateClient\n      - createUser\n    filenames:\n      - pages/api/v1/admin/client/create.js\n      - pages/api/v1/admin/user/create.js\n    classification: very promising\n```",
      "date": "2024-06-09T14:02:42.529636",
      "usage": {
        "prompt_tokens": 59573,
        "completion_tokens": 687,
        "cost": 0.61634
      }
    }
  ],
  "leads": [
    {
      "headline": "Use of Hard-coded Credentials in NextAuth",
      "analysis": "The NextAuth authentication provider setup uses a hard-coded 'secret' variable within the [...nextauth].js configuration file. This practice is risky as it exposes the application to potential attacks where the hardcoded secret may be discovered by a malicious actor analyzing the code, enabling them to potentially forge session tokens or conduct attacks that depend on the secrecy of this value.\n",
      "classification": "very promising",
      "cwe": "CWE-798",
      "function_names": [
        "authorize"
      ],
      "filenames": [
        "pages/api/auth/[...nextauth].js"
      ]
    },
    {
      "headline": "Improper File Path Sanitization Leading to Potential Directory Traversal",
      "analysis": "The file download utilities within the pages/api/v1/users/file/download.js and pages/api/v1/ticket/[id]/file/download.js allow for user controlled input to dictate file paths without sufficient sanitization checks. This could potentially lead to directory traversal, where an attacker could access or manipulate files outside of the intended directories by using relative file paths.\n",
      "classification": "very promising",
      "cwe": "CWE-22",
      "function_names": [
        "listFiles",
        "downloadFile"
      ],
      "filenames": [
        "pages/api/vfind/ticket/[id]/file/download.js",
        "pages/api/v1/users/file/download.js"
      ]
    },
    {
      "headline": "Use of Unprotected Formidable Module Data Leading to Overwritten Files",
      "analysis": "The application uses the Formidable module for parsing form data, specifically file uploads. In pages/api/v1/users/file/upload.js and pages/api/v1/ticket/[id]/file/upload.js, the files are saved to directories using user-controllable file names without proper checks. This behavior could lead to files being overwritten if a user repeats a file name intentionally or accidentally.\n",
      "classification": "very promising",
      "cwe": "CWE-732",
      "function_names": [
        "UploadFile"
      ],
      "filenames": [
        "pages/api/v1/users/fil/upload.js",
        "pages/api/v1/ticket/[id]/file/upload.js"
      ]
    },
    {
      "headline": "Lack of Authentication Checks in Client-Side Routes",
      "analysis": "Various client-side pages and API endpoints do not implement checks to verify if a user is authenticated or authorized to perform certain actions like accessing user files or updating sensitive user information. This oversight may allow unauthorized parties to access or manipulate data or perform restricted actions.\n",
      "classification": "very promising",
      "cwe": "CWE-862",
      "function_names": [
        "getAllClients",
        "userProfile",
        "editUser"
      ],
      "filenames": [
        "pages/api/v1/users/[id]/profile.js",
        "pages/api/v1/clients/all.js"
      ]
    },
    {
      "headline": "Potential SQL Injection via Direct Injection of Parameters into SQL Queries",
      "analysis": "In several API routes, the parameters taken from requests are concatenated directly into SQL queries without sanitization or parameterization, creating potential for SQL injection attacks, where a malicious actor could manipulate queries to modify query logic, leading to unauthorized data exposure or manipulation.\n",
      "classification": "very promising",
      "cwe": "CWE-89",
      "function_names": [
        "updateClient",
        "createUser"
      ],
      "filenames": [
        "pages/api/v1/admin/client/create.js",
        "pages/api/v1/admin/user/create.js"
      ]
    }
  ],
  "scores": [
    {
      "stats": {
        "fn": 3,
        "tp": 1,
        "fp": 4
      },
      "mapping": {
        "1": "CVE-2023-46864"
      },
      "vuln_dates": {
        "CVE-2023-42328": "2023-09-18T16:15:45",
        "CVE-2023-26984": "2023-03-29T18:15:07",
        "CVE-2023-46864": "2023-10-30T00:15:39",
        "CVE-2023-46863": "2023-10-30T00:15:39"
      },
      "scoring_model": "gpt-4o-2024-05-13",
      "type": "llm",
      "instruction_template_hash": "8998f09cf57fca8a6e03"
    }
  ],
  "instruction_template_hash": "10c0163db4740318a544",
  "version": "0.1.0"
}
