{
  "commit": "3ad12658bb91c5f6fb7d36e43d70ed7be0803354",
  "repo_url": "https://github.com/jenkinsci/backlog-plugin",
  "model": "claude-3-haiku-20240307",
  "chunk_hashes": [
    "c149f6299a1da05009de"
  ],
  "responses": [
    {
      "content": "Here is the YAML output for the security vulnerabilities found in the codebase:\n\n```yaml\nleads:\n  - headline: Improper Neutralization of Input During Web Page Generation (Cross-site Scripting)\n    analysis: |\n      The codebase does not properly sanitize user input, which could lead to Cross-site Scripting (XSS) vulnerabilities. Specifically, the BacklogRepositoryBrowser and BacklogGitRepositoryBrowser classes use the URL parameters passed in to generate links, which could potentially contain malicious scripts that would be executed in the user's browser.\n    cwe: CWE-79\n    function_names:\n      - getFileLink\n      - getDiffLink\n      - getChangeSetLink\n    filenames:\n      - hudson/plugins/backlog/BacklogRepositoryBrowser.java\n      - hudson/plugins/backlog/BacklogGitRepositoryBrowser.java\n    classification: slightly promising\n\n  - headline: Improper Neutralization of Special Elements used in an OS Command (OS Command Injection)\n    analysis: |\n      The BacklogWebdavPublisher class uses user-supplied input to construct a remote directory path, which could potentially be used to inject malicious commands that would be executed on the server. This could allow an attacker to execute arbitrary commands on the server.\n    cwe: CWE-78\n    function_names:\n      - getFormattedRemoteDirectory\n    filenames:\n      - hudson/plugins/backlog/BacklogWebdavPublisher.java\n    classification: very promising\n\n  - headline: Use of Externally-Controlled Input to Select Classes or Code (Unsafe Reflection)\n    analysis: |\n      The BacklogPullRequestSCMSource class uses user-supplied input to select the Git repository browser to use, which could potentially be used to load arbitrary classes and execute malicious code. This could allow an attacker to execute arbitrary code on the server.\n    cwe: CWE-470\n    function_names:\n      - getBrowser\n      - setBrowser\n    filenames:\n      - hudson/plugins/backlog/pipeline/BacklogPullRequestSCMSource.java\n    classification: very promising\n\n  - headline: Deserialization of Untrusted Data\n    analysis: |\n      The BacklogProjectProperty class uses the Stapler framework to deserialize user-supplied input, which could potentially be used to deserialize malicious objects and execute arbitrary code. This could allow an attacker to execute arbitrary code on the server.\n    cwe: CWE-502\n    function_names:\n      - newInstance\n    filenames:\n      - hudson/plugins/backlog/BacklogProjectProperty.java\n    classification: very promising\n\n  - headline: Improper Neutralization of Special Elements used in an Expression Language Statement (Expression Language Injection)\n    analysis: |\n      The BacklogWebdavPublisher class uses user-supplied input to construct a remote directory path, which could potentially be used to inject malicious expression language statements that would be evaluated on the server. This could allow an attacker to execute arbitrary code on the server.\n    cwe: CWE-917\n    function_names:\n      - getFormattedRemoteDirectory\n    filenames:\n      - hudson/plugins/backlog/BacklogWebdavPublisher.java\n    classification: very promising\n\n  - headline: Improper Restriction of Rendered UI Layers or Frames\n    analysis: |\n      The BacklogPullRequestLinkAction class generates a URL that could potentially be used to load content from an untrusted source, which could be used to perform a clickjacking attack. This could allow an attacker to trick the user into performing unintended actions.\n    cwe: CWE-1021\n    function_names:\n      - getUrlName\n    filenames:\n      - hudson/plugins/backlog/pipeline/BacklogPullRequestLinkAction.java\n    classification: slightly promising\n\n  - headline: Improperly Controlled Modification of Object Prototype Attributes (Prototype Pollution)\n    analysis: |\n      The BacklogPullRequestSCMSource class uses user-supplied input to modify the Git repository browser and Git tool, which could potentially be used to modify the prototype of these objects and inject malicious code. This could allow an attacker to execute arbitrary code on the server.\n    cwe: CWE-1321\n    function_names:\n      - setBrowser\n      - setGitTool\n    filenames:\n      - hudson/plugins/backlog/pipeline/BacklogPullRequestSCMSource.java\n    classification: very promising\n```",
      "date": "2024-06-14T14:05:37.718256",
      "usage": {
        "prompt_tokens": 36700,
        "completion_tokens": 1066,
        "cost": 0.0105075
      }
    }
  ],
  "leads": [
    {
      "headline": "Improper Neutralization of Input During Web Page Generation (Cross-site Scripting)",
      "analysis": "The codebase does not properly sanitize user input, which could lead to Cross-site Scripting (XSS) vulnerabilities. Specifically, the BacklogRepositoryBrowser and BacklogGitRepositoryBrowser classes use the URL parameters passed in to generate links, which could potentially contain malicious scripts that would be executed in the user's browser.\n",
      "classification": "slightly promising",
      "cwe": "CWE-79",
      "function_names": [
        "getFileLink",
        "getDiffLink",
        "getChangeSetLink"
      ],
      "filenames": [
        "hudson/plugins/backlog/BacklogRepositoryBrowser.java",
        "hudson/plugins/backlog/BacklogGitRepositoryBrowser.java"
      ]
    },
    {
      "headline": "Improper Neutralization of Special Elements used in an OS Command (OS Command Injection)",
      "analysis": "The BacklogWebdavPublisher class uses user-supplied input to construct a remote directory path, which could potentially be used to inject malicious commands that would be executed on the server. This could allow an attacker to execute arbitrary commands on the server.\n",
      "classification": "very promising",
      "cwe": "CWE-78",
      "function_names": [
        "getFormattedRemoteDirectory"
      ],
      "filenames": [
        "hudson/plugins/backlog/BacklogWebdavPublisher.java"
      ]
    },
    {
      "headline": "Use of Externally-Controlled Input to Select Classes or Code (Unsafe Reflection)",
      "analysis": "The BacklogPullRequestSCMSource class uses user-supplied input to select the Git repository browser to use, which could potentially be used to load arbitrary classes and execute malicious code. This could allow an attacker to execute arbitrary code on the server.\n",
      "classification": "very promising",
      "cwe": "CWE-470",
      "function_names": [
        "getBrowser",
        "setBrowser"
      ],
      "filenames": [
        "hudson/plugins/backlog/pipeline/BacklogPullRequestSCMSource.java"
      ]
    },
    {
      "headline": "Deserialization of Untrusted Data",
      "analysis": "The BacklogProjectProperty class uses the Stapler framework to deserialize user-supplied input, which could potentially be used to deserialize malicious objects and execute arbitrary code. This could allow an attacker to execute arbitrary code on the server.\n",
      "classification": "very promising",
      "cwe": "CWE-502",
      "function_names": [
        "newInstance"
      ],
      "filenames": [
        "hudson/plugins/backlog/BacklogProjectProperty.java"
      ]
    },
    {
      "headline": "Improper Neutralization of Special Elements used in an Expression Language Statement (Expression Language Injection)",
      "analysis": "The BacklogWebdavPublisher class uses user-supplied input to construct a remote directory path, which could potentially be used to inject malicious expression language statements that would be evaluated on the server. This could allow an attacker to execute arbitrary code on the server.\n",
      "classification": "very promising",
      "cwe": "CWE-917",
      "function_names": [
        "getFormattedRemoteDirectory"
      ],
      "filenames": [
        "hudson/plugins/backlog/BacklogWebdavPublisher.java"
      ]
    },
    {
      "headline": "Improper Restriction of Rendered UI Layers or Frames",
      "analysis": "The BacklogPullRequestLinkAction class generates a URL that could potentially be used to load content from an untrusted source, which could be used to perform a clickjacking attack. This could allow an attacker to trick the user into performing unintended actions.\n",
      "classification": "slightly promising",
      "cwe": "CWE-1021",
      "function_names": [
        "getUrlName"
      ],
      "filenames": [
        "hudson/plugins/backlog/pipeline/BacklogPullRequestLinkAction.java"
      ]
    },
    {
      "headline": "Improperly Controlled Modification of Object Prototype Attributes (Prototype Pollution)",
      "analysis": "The BacklogPullRequestSCMSource class uses user-supplied input to modify the Git repository browser and Git tool, which could potentially be used to modify the prototype of these objects and inject malicious code. This could allow an attacker to execute arbitrary code on the server.\n",
      "classification": "very promising",
      "cwe": "CWE-1321",
      "function_names": [
        "setBrowser",
        "setGitTool"
      ],
      "filenames": [
        "hudson/plugins/backlog/pipeline/BacklogPullRequestSCMSource.java"
      ]
    }
  ],
  "scores": [
    {
      "stats": {
        "fn": 1,
        "tp": 0,
        "fp": 5
      },
      "mapping": {},
      "vuln_dates": {
        "CVE-2020-2153": "2020-03-09T16:15:14"
      },
      "scoring_model": "claude-3-opus-20240229",
      "type": "llm",
      "instruction_template_hash": "245ace12b6361954d0a2"
    },
    {
      "stats": {
        "fn": 1,
        "tp": 0,
        "fp": 5
      },
      "mapping": {},
      "vuln_dates": {
        "CVE-2020-2153": "2020-03-09T16:15:14"
      },
      "scoring_model": "claude-3-5-sonnet-20240620",
      "type": "llm",
      "instruction_template_hash": "245ace12b6361954d0a2"
    }
  ],
  "instruction_template_hash": "10c0163db4740318a544",
  "version": "0.1.0"
}
