{
  "commit": "72c017717800c17ff7aee66506bf3976783c5efd",
  "repo_url": "https://github.com/redon-tech/redon-hub",
  "model": "gpt-4o-2024-05-13",
  "chunk_hashes": [
    "1d8ca55377e8cd7bf003"
  ],
  "responses": [
    {
      "content": "```yaml\nleads:\n  - headline: \"Hardcoded Token in Environment Variable\"\n    analysis: |\n      Token used for the `bot.run` function is retrieved using `os.getenv(\"token\")`. If this token is hardcoded or misconfigured in the environment variables, it could lead to unauthorized access.\n    cwe: CWE-798\n    function_names:\n      - main\n    filenames:\n      - launcher.py\n    classification: very promising\n\n  - headline: \"Insufficient Encryption for API Key\"\n    analysis: |\n      The API key used for authentication is stored in plain text and transmitted without sufficient encryption, making it susceptible to interception and unauthorized access.\n    cwe: CWE-311\n    function_names: []\n    filenames:\n      - bot/cogs/api_v1.py\n    classification: very promising\n\n  - headline: \"Hardcoded Discord Owner IDs\"\n    analysis: |\n      The bot owner IDs are hardcoded and loaded from `config.Bot.Owners`. If these IDs are exposed or if an unauthorized ID is accidentally added, it can lead to privilege escalation.\n    cwe: CWE-798\n    function_names:\n      - Bot.__init__\n    filenames:\n      - bot/__init__.py\n    classification: slightly promising\n\n  - headline: \"Unsecured Database Connection\"\n    analysis: |\n      The database connection does not appear to use encryption, making data in transit potentially vulnerable to interception and tampering.\n    cwe: CWE-319\n    function_names: []\n    filenames:\n      - bot/data/__init__.py\n    classification: very promising\n\n  - headline: \"Potential Race Condition in Extension Loading\"\n    analysis: |\n      The `load_extensions` method uses asynchronous tasks to load extensions, which may result in race conditions if not properly synchronized, leading to inconsistent bot behavior or unintentional crashes.\n    cwe: CWE-362\n    function_names:\n      - Bot.load_extensions\n    filenames:\n      - bot/__init__.py\n    classification: slightly promising\n\n  - headline: \"Sensitive Data Exposure via Error Messages\"\n    analysis: |\n      Detailed error messages, including stack traces, are logged and potentially exposed, which may contain sensitive information useful for attackers.\n    cwe: CWE-209\n    function_names: []\n    filenames:\n      - bot/cogs/user.py\n      - bot/cogs/product.py\n      - bot/cogs/migrate.py\n    classification: very promising\n\n  - headline: \"Insecure Default Configuration Loading\"\n    analysis: |\n      Configuration files such as `config.json` are loaded without validation, and there is an improper recursive update which can lead to insecure configurations being applied.\n    cwe: CWE-1188\n    function_names: []\n    filenames:\n      - bot/config.py\n    classification: slightly promising\n\n  - headline: \"User Input Not Properly Sanitized\"\n    analysis: |\n      User inputs, such as messages and commands, are directly incorporated into processes or data manipulations without proper sanitization, making the application vulnerable to injection attacks.\n    cwe: CWE-20\n    function_names:\n      - user_profile\n      - user_retrieve\n      - user_transfer\n    filenames:\n      - bot/cogs/user.py\n    classification: very promising\n\n  - headline: \"External Request without Input Validation\"\n    analysis: |\n      The bot performs external requests (e.g., for vendr migration) without thoroughly validating input data or responses, exposing it to external threats and data manipulation.\n    cwe: CWE-74\n    function_names:\n      - vendrMigrate\n    filenames:\n      - bot/cogs/migrate.py\n    classification: very promising\n\n  - headline: \"Unencrypted Storage of Sensitive Information\"\n    analysis: |\n      Sensitive user and product information is stored without encryption, making it accessible to unauthorized parties if the database is compromised.\n    cwe: CWE-312\n    function_names: []\n    filenames:\n      - bot/data/__init__.py\n      - bot/data/prisma/user.py\n      - bot/data/prisma/product.py\n    classification: very promising\n```",
      "date": "2024-06-09T14:30:50.946517",
      "usage": {
        "prompt_tokens": 29490,
        "completion_tokens": 840,
        "cost": 0.16005
      }
    }
  ],
  "leads": [
    {
      "headline": "Hardcoded Token in Environment Variable",
      "analysis": "Token used for the bot.run function is retrieved using os.getenv(\"token\"). If this token is hardcoded or misconfigured in the environment variables, it could lead to unauthorized access.\n",
      "classification": "very promising",
      "cwe": "CWE-798",
      "function_names": [
        "main"
      ],
      "filenames": [
        "launcher.py"
      ]
    },
    {
      "headline": "Insufficient Encryption for API Key",
      "analysis": "The API key used for authentication is stored in plain text and transmitted without sufficient encryption, making it susceptible to interception and unauthorized access.\n",
      "classification": "very promising",
      "cwe": "CWE-311",
      "function_names": [],
      "filenames": [
        "bot/cogs/api_v1.py"
      ]
    },
    {
      "headline": "Hardcoded Discord Owner IDs",
      "analysis": "The bot owner IDs are hardcoded and loaded from config.Bot.Owners. If these IDs are exposed or if an unauthorized ID is accidentally added, it can lead to privilege escalation.\n",
      "classification": "slightly promising",
      "cwe": "CWE-798",
      "function_names": [
        "Bot.__init__"
      ],
      "filenames": [
        "bot/__init__.py"
      ]
    },
    {
      "headline": "Unsecured Database Connection",
      "analysis": "The database connection does not appear to use encryption, making data in transit potentially vulnerable to interception and tampering.\n",
      "classification": "very promising",
      "cwe": "CWE-319",
      "function_names": [],
      "filenames": [
        "bot/data/__init__.py"
      ]
    },
    {
      "headline": "Potential Race Condition in Extension Loading",
      "analysis": "The load_extensions method uses asynchronous tasks to load extensions, which may result in race conditions if not properly synchronized, leading to inconsistent bot behavior or unintentional crashes.\n",
      "classification": "slightly promising",
      "cwe": "CWE-362",
      "function_names": [
        "Bot.load_extensions"
      ],
      "filenames": [
        "bot/__init__.py"
      ]
    },
    {
      "headline": "Sensitive Data Exposure via Error Messages",
      "analysis": "Detailed error messages, including stack traces, are logged and potentially exposed, which may contain sensitive information useful for attackers.\n",
      "classification": "very promising",
      "cwe": "CWE-209",
      "function_names": [],
      "filenames": [
        "bot/cogs/user.py",
        "bot/cogs/product.py",
        "bot/cogs/migrate.py"
      ]
    },
    {
      "headline": "Insecure Default Configuration Loading",
      "analysis": "Configuration files such as config.json are loaded without validation, and there is an improper recursive update which can lead to insecure configurations being applied.\n",
      "classification": "slightly promising",
      "cwe": "CWE-1188",
      "function_names": [],
      "filenames": [
        "bot/config.py"
      ]
    },
    {
      "headline": "User Input Not Properly Sanitized",
      "analysis": "User inputs, such as messages and commands, are directly incorporated into processes or data manipulations without proper sanitization, making the application vulnerable to injection attacks.\n",
      "classification": "very promising",
      "cwe": "CWE-20",
      "function_names": [
        "user_profile",
        "user_retrieve",
        "user_transfer"
      ],
      "filenames": [
        "bot/cogs/user.py"
      ]
    },
    {
      "headline": "External Request without Input Validation",
      "analysis": "The bot performs external requests (e.g., for vendr migration) without thoroughly validating input data or responses, exposing it to external threats and data manipulation.\n",
      "classification": "very promising",
      "cwe": "CWE-74",
      "function_names": [
        "vendrMigrate"
      ],
      "filenames": [
        "bot/cogs/migrate.py"
      ]
    },
    {
      "headline": "Unencrypted Storage of Sensitive Information",
      "analysis": "Sensitive user and product information is stored without encryption, making it accessible to unauthorized parties if the database is compromised.\n",
      "classification": "very promising",
      "cwe": "CWE-312",
      "function_names": [],
      "filenames": [
        "bot/data/__init__.py",
        "bot/data/prisma/user.py",
        "bot/data/prisma/product.py"
      ]
    }
  ],
  "scores": [
    {
      "stats": {
        "fn": 1,
        "tp": 0,
        "fp": 7
      },
      "mapping": {},
      "vuln_dates": {
        "CVE-2024-31442": "2024-04-08T16:15:07"
      },
      "scoring_model": "gpt-4o-2024-05-13",
      "type": "llm",
      "instruction_template_hash": "8998f09cf57fca8a6e03"
    },
    {
      "stats": {
        "fn": 1,
        "tp": 0,
        "fp": 7
      },
      "mapping": {},
      "vuln_dates": {
        "CVE-2024-31442": "2024-04-08T16:15:07"
      },
      "scoring_model": "claude-3-opus-20240229",
      "type": "llm",
      "instruction_template_hash": "245ace12b6361954d0a2"
    },
    {
      "stats": {
        "fn": 1,
        "tp": 0,
        "fp": 7
      },
      "mapping": {},
      "vuln_dates": {
        "CVE-2024-31442": "2024-04-08T16:15:07"
      },
      "scoring_model": "claude-3-5-sonnet-20240620",
      "type": "llm",
      "instruction_template_hash": "245ace12b6361954d0a2"
    }
  ],
  "instruction_template_hash": "10c0163db4740318a544",
  "version": "0.1.0"
}
