{
  "commit": "3d92db495900bfe3e01ffa0c81de880355eb0387",
  "repo_url": "https://github.com/onc-healthit/code-validator-api",
  "model": "gpt-4-turbo-2024-04-09",
  "chunk_hashes": [
    "6a5c73f7d4d8ef6ef183"
  ],
  "responses": [
    {
      "content": "```yaml\nleads:\n  - headline: \"Static Method Vulnerability in Log Results to Console\"\n    analysis: |\n      The `println` method in `ValidationLogger` class may potentially expose sensitive data, as it conditionally emits output to the console based on a boolean flag without sanitizing or restricting the output. This practice might facilitate information leakage if the log contains sensitive or debugging information that should not be exposed in production environments.\n    cwe: CWE-532\n    function_names:\n      - println\n      - print\n    filenames:\n      - src/test/java/org/sitenv/vocabularies/test/other/ValidationLogger.java\n    classification: slightly promising\n\n  - headline: \"XPath Injection Vulnerability\"\n    analysis: |\n      The application's method `findAllDocumentNodesByXpathExpression` in `VocabularyValidationService` could potentially be vulnerable to XPath injection, where malicious input can alter the query to access unauthorized data. The method constructs XPath queries using string concatenation, which may include user input, allowing an attacker to manipulate the query.\n    cwe: CWE-643\n    function_names:\n      - findAllDocumentNodesByXpathExpression\n    filenames:\n      - src/main/java/org/sitenv/vocabularies/validation/services/VocabularyValidationService.java\n    classification: very promising\n\n  - headline: \"Exposure of Sensitive Information via Error Messages\"\n    analysis: |\n      Exception handling in `VocabularyLoaderFactory` may lead to unintentional disclosure of sensitive data through detailed error messages that are generated during application failures. Such information may assist an adversary in crafting further attacks.\n    cwe: CWE-209\n    function_names:\n      - vocabularyLoaderFactory\n    filenames:\n      - src/main/java/org/sitenv/vocabularies/configuration/CodeValidatorApiConfiguration.java\n    classification: slightly promising\n\n  - headline: \"Insufficient Resource Consumption Limit\"\n    analysis: |\n      In `VsacLoader`, `load` method reads excel files using a library that builds the entire document model in memory. For very large files, this behavior can lead to excessive memory consumption, potentially causing denial of service or memory exhaustion issues.\n    cwe: CWE-770\n    function_names:\n      - load\n    filenames:\n      - src/main/java/org/sitenv/vocabularies/loader/valuesets/VsacLoader.java\n    classification: slightly promising\n\n  - headline: \"Improper Handling of File Path Delimiter\"\n    analysis: |\n      The method `createFullFilePath` in `ValidationConfigurationLoader` constructs file paths by concatenating strings. If an attacker can control the input parameters or if the input is not properly validated, this method may improperly handle file path delimiters leading to path traversal vulnerabilities.\n    cwe: CWE-22\n    function_names:\n      - createFullFilePath\n    filenames:\n      - src/main/java/org/sitenv/vocabularies/configuration/ValidationConfigurationLoader.java\n    classification: very promising\n```",
      "date": "2024-06-14T15:03:22.519230",
      "usage": {
        "prompt_tokens": 41988,
        "completion_tokens": 608,
        "cost": 0.43812
      }
    }
  ],
  "leads": [
    {
      "headline": "Static Method Vulnerability in Log Results to Console",
      "analysis": "The println method in ValidationLogger class may potentially expose sensitive data, as it conditionally emits output to the console based on a boolean flag without sanitizing or restricting the output. This practice might facilitate information leakage if the log contains sensitive or debugging information that should not be exposed in production environments.\n",
      "classification": "slightly promising",
      "cwe": "CWE-532",
      "function_names": [
        "println",
        "print"
      ],
      "filenames": [
        "src/test/java/org/sitenv/vocabularies/test/other/ValidationLogger.java"
      ]
    },
    {
      "headline": "XPath Injection Vulnerability",
      "analysis": "The application's method findAllDocumentNodesByXpathExpression in VocabularyValidationService could potentially be vulnerable to XPath injection, where malicious input can alter the query to access unauthorized data. The method constructs XPath queries using string concatenation, which may include user input, allowing an attacker to manipulate the query.\n",
      "classification": "very promising",
      "cwe": "CWE-643",
      "function_names": [
        "findAllDocumentNodesByXpathExpression"
      ],
      "filenames": [
        "src/main/java/org/sitenv/vocabularies/validation/services/VocabularyValidationService.java"
      ]
    },
    {
      "headline": "Exposure of Sensitive Information via Error Messages",
      "analysis": "Exception handling in VocabularyLoaderFactory may lead to unintentional disclosure of sensitive data through detailed error messages that are generated during application failures. Such information may assist an adversary in crafting further attacks.\n",
      "classification": "slightly promising",
      "cwe": "CWE-209",
      "function_names": [
        "vocabularyLoaderFactory"
      ],
      "filenames": [
        "src/main/java/org/sitenv/vocabularies/configuration/CodeValidatorApiConfiguration.java"
      ]
    },
    {
      "headline": "Insufficient Resource Consumption Limit",
      "analysis": "In VsacLoader, load method reads excel files using a library that builds the entire document model in memory. For very large files, this behavior can lead to excessive memory consumption, potentially causing denial of service or memory exhaustion issues.\n",
      "classification": "slightly promising",
      "cwe": "CWE-770",
      "function_names": [
        "load"
      ],
      "filenames": [
        "src/main/java/org/sitenv/vocabularies/loader/valuesets/VsacLoader.java"
      ]
    },
    {
      "headline": "Improper Handling of File Path Delimiter",
      "analysis": "The method createFullFilePath in ValidationConfigurationLoader constructs file paths by concatenating strings. If an attacker can control the input parameters or if the input is not properly validated, this method may improperly handle file path delimiters leading to path traversal vulnerabilities.\n",
      "classification": "very promising",
      "cwe": "CWE-22",
      "function_names": [
        "createFullFilePath"
      ],
      "filenames": [
        "src/main/java/org/sitenv/vocabularies/configuration/ValidationConfigurationLoader.java"
      ]
    }
  ],
  "scores": [
    {
      "stats": {
        "fn": 1,
        "tp": 0,
        "fp": 2
      },
      "mapping": {},
      "vuln_dates": {
        "CVE-2021-4295": "2022-12-29T09:15:08"
      },
      "scoring_model": "claude-3-opus-20240229",
      "type": "llm",
      "instruction_template_hash": "245ace12b6361954d0a2"
    },
    {
      "stats": {
        "fn": 1,
        "tp": 0,
        "fp": 2
      },
      "mapping": {},
      "vuln_dates": {
        "CVE-2021-4295": "2022-12-29T09:15:08"
      },
      "scoring_model": "claude-3-5-sonnet-20240620",
      "type": "llm",
      "instruction_template_hash": "245ace12b6361954d0a2"
    }
  ],
  "instruction_template_hash": "10c0163db4740318a544",
  "version": "0.1.0"
}
