{
  "commit": "03129504e89707cb046922cdeb9958d77d275913",
  "repo_url": "https://github.com/blitz-js/superjson",
  "model": "gpt-4-turbo-2024-04-09",
  "chunk_hashes": [
    "edea9adfb9cce60bce31"
  ],
  "responses": [
    {
      "content": "```yaml\nleads:\n  - headline: Duplicate Key Assignment in Object Literal in benchmark.js\n    analysis: |\n      In the 'toy example' inside 'instances' in benchmark.js, there is a duplicated key 'a' in the object, resulting in an overwrite of the first 'a' key's value with a regular expression. This can lead to potential data loss as the Map initially assigned to 'a' becomes unreferenced.\n    cwe: CWE-1236\n    function_names:\n      - \"\"\n    filenames:\n      - benchmark.js\n    classification: slightly promising\n\n  - headline: Type Confusion Vulnerability in setDeep Function in accessDeep.ts\n    analysis: |\n      The function `setDeep` attempts to type-cast and access keys and values of potentially non-indexable types (e.g., applying index operations on Sets and Maps which are not natively indexable). This behavior can result in erroneous logic and type confusion when unexpected input types are passed that are not properly validated before indexing.\n    cwe: CWE-843\n    function_names:\n      - setDeep\n    filenames:\n      - src/accessDeep.ts\n    classification: very promising\n\n  - headline: Recursive Serialization Invocation in benchmark.js\n    analysis: |\n      The lambda function declared in 'benchmark.js' recursively invokes serialization and deserialization without bounds checks or termination conditions evident, which can manifest as a performance issue or, in worst cases, cause a stack overflow (Denial of Service).\n    cwe: CWE-674\n    function_names:\n      - lambda in instances 'deep nested'\n    filenames:\n      - benchmark.js\n    classification: slightly promising\n\n  - headline: Insecure Error Information Handling in transformer.ts\n    analysis: |\n      In transformer.ts, simpleTransformation for errors (`isError` used in `simpleTransformation`) proposes to copy error properties arbitrarily without considering the content's sensitivity. This can result in sensitive information leakage if error objects contain confidential data in user-defined properties.\n    cwe: CWE-532\n    function_names:\n      - simpleTransformation\n    filenames:\n      - src/transformer.ts\n    classification: slightly promising\n\n  - headline: Incorrect Handling of NaN Values and BigInt Handling in transformer.ts\n    analysis: |\n      The transformation logic for NaN values and BigInt conversions in transformer.ts does not account for cases where `BigInt` might not be supported in the environment, and provides a console error as a fallback which doesn't actually handle the case functionally. This oversight could lead to failures or partial unavailability of functionality in environments where BigInt is unsupported.\n    cwe: CWE-754\n    function_names:\n      - simpleTransformation\n    filenames:\n      - src/transformer.ts\n    classification: slightly promising\n\n  - headline: Uncontrolled Resource Consumption via Recursive Serialization/Deserialization Calls\n    analysis: |\n      The code snippet observed in 'benchmark.js' creates a potentially excessive recursive call load by repeatedly serializing and deserializing complex nested objects within a performance benchmark loop, which could be exploited to cause resource exhaustion.\n    cwe: CWE-400\n    function_names:\n      - suite.add\n    filenames:\n      - benchmark.js\n    classification: slightly promising\n```",
      "date": "2024-06-12T15:13:50.057982",
      "usage": {
        "prompt_tokens": 16722,
        "completion_tokens": 654,
        "cost": 0.18684
      }
    }
  ],
  "leads": [
    {
      "headline": "Duplicate Key Assignment in Object Literal in benchmark.js",
      "analysis": "In the 'toy example' inside 'instances' in benchmark.js, there is a duplicated key 'a' in the object, resulting in an overwrite of the first 'a' key's value with a regular expression. This can lead to potential data loss as the Map initially assigned to 'a' becomes unreferenced.\n",
      "classification": "slightly promising",
      "cwe": "CWE-1236",
      "function_names": [
        ""
      ],
      "filenames": [
        "benchmark.js"
      ]
    },
    {
      "headline": "Type Confusion Vulnerability in setDeep Function in accessDeep.ts",
      "analysis": "The function setDeep attempts to type-cast and access keys and values of potentially non-indexable types (e.g., applying index operations on Sets and Maps which are not natively indexable). This behavior can result in erroneous logic and type confusion when unexpected input types are passed that are not properly validated before indexing.\n",
      "classification": "very promising",
      "cwe": "CWE-843",
      "function_names": [
        "setDeep"
      ],
      "filenames": [
        "src/accessDeep.ts"
      ]
    },
    {
      "headline": "Recursive Serialization Invocation in benchmark.js",
      "analysis": "The lambda function declared in 'benchmark.js' recursively invokes serialization and deserialization without bounds checks or termination conditions evident, which can manifest as a performance issue or, in worst cases, cause a stack overflow (Denial of Service).\n",
      "classification": "slightly promising",
      "cwe": "CWE-674",
      "function_names": [
        "lambda in instances 'deep nested'"
      ],
      "filenames": [
        "benchmark.js"
      ]
    },
    {
      "headline": "Insecure Error Information Handling in transformer.ts",
      "analysis": "In transformer.ts, simpleTransformation for errors (isError used in simpleTransformation) proposes to copy error properties arbitrarily without considering the content's sensitivity. This can result in sensitive information leakage if error objects contain confidential data in user-defined properties.\n",
      "classification": "slightly promising",
      "cwe": "CWE-532",
      "function_names": [
        "simpleTransformation"
      ],
      "filenames": [
        "src/transformer.ts"
      ]
    },
    {
      "headline": "Incorrect Handling of NaN Values and BigInt Handling in transformer.ts",
      "analysis": "The transformation logic for NaN values and BigInt conversions in transformer.ts does not account for cases where BigInt might not be supported in the environment, and provides a console error as a fallback which doesn't actually handle the case functionally. This oversight could lead to failures or partial unavailability of functionality in environments where BigInt is unsupported.\n",
      "classification": "slightly promising",
      "cwe": "CWE-754",
      "function_names": [
        "simpleTransformation"
      ],
      "filenames": [
        "src/transformer.ts"
      ]
    },
    {
      "headline": "Uncontrolled Resource Consumption via Recursive Serialization/Deserialization Calls",
      "analysis": "The code snippet observed in 'benchmark.js' creates a potentially excessive recursive call load by repeatedly serializing and deserializing complex nested objects within a performance benchmark loop, which could be exploited to cause resource exhaustion.\n",
      "classification": "slightly promising",
      "cwe": "CWE-400",
      "function_names": [
        "suite.add"
      ],
      "filenames": [
        "benchmark.js"
      ]
    }
  ],
  "scores": [
    {
      "stats": {
        "fn": 1,
        "tp": 0,
        "fp": 1
      },
      "mapping": {},
      "vuln_dates": {
        "CVE-2022-23631": "2022-02-09T22:15:07"
      },
      "scoring_model": "claude-3-opus-20240229",
      "type": "llm",
      "instruction_template_hash": "245ace12b6361954d0a2"
    }
  ],
  "instruction_template_hash": "10c0163db4740318a544",
  "version": "0.1.0"
}
