{
  "commit": "2bf377194efc6b4f13b6bc6cd9272b935f64793e",
  "repo_url": "https://github.com/semantic-release/semantic-release",
  "model": "gpt-4o-2024-05-13",
  "chunk_hashes": [
    "3f366b9c0e28df3ca722"
  ],
  "responses": [
    {
      "content": "```yaml\nleads:\n  - headline: Potential Command Injection\n    analysis: |\n      The presence of the 'hook-std' package together with user provided inputs can lead to command injection vulnerabilities. Specifically, if the user inputs are not properly sanitized before being used in the 'hook-std' functions, an attacker could inject arbitrary OS commands, leading to full system compromise.\n    cwe: CWE-78\n    function_names:\n      - \"const {stdout, stderr} = await hookStd(...)\"\n    filenames:\n      - index.js\n    classification: very promising\n\n  - headline: Exposing Tokens in Logs\n    analysis: |\n      The logging mechanism uses the 'get-logger' module which writes logs to stdout and stderr directly. If 'MY_TOKEN' or similar sensitive environment variables are logged without filtering, this can expose sensitive data.\n    cwe: CWE-532\n    function_names:\n      - \"logger.log(...)\"\n      - \"logger.error(...)\"\n    filenames:\n      - lib/get-logger.js\n      - test/index.test.js\n    classification: slightly promising\n\n  - headline: Weak Cryptographic Algorithm\n    analysis: |\n      If the 'hideSensitive' functionality does not use secure cryptographic algorithms to obscure sensitive information, it might be possible for an attacker to reverse engineer and retrieve the original information. This is especially critical when dealing with tokens and passwords.\n    cwe: CWE-327\n    function_names:\n      - \"const hideSensitive = require('./hide-sensitive');\"\n    filenames:\n      - lib/utils.js\n    classification: very promising\n\n  - headline: Potential Path Traversal\n    analysis: |\n      The usage of file paths without proper validation or sanitization can lead to path traversal vulnerabilities. If an attacker can control the file path argument in 'require' or 'readJson' functions, they may gain unauthorized access to the file system.\n    cwe: CWE-22\n    function_names:\n      - \"require(...)\"\n      - \"readJson(...)\"\n    filenames:\n      - lib/get-config.js\n      - lib/plugins/utils.js\n    classification: very promising\n\n  - headline: Insecure Deserialization\n    analysis: |\n      The code might be susceptible to insecure deserialization attacks if user-controllable data is being deserialized without proper checks. This can potentially lead to remote code execution.\n    cwe: CWE-502\n    function_names: []\n    filenames:\n      - lib/utils.js\n      - test/definitions/plugins.test.js\n    classification: slightly promising\n\n  - headline: Insufficient Validation in Branch Configuration\n    analysis: |\n      The branch configuration validation does not adequately ensure that the branch names conform to necessary security constraints. This, combined with potential user input, could lead to security misconfigurations or injection vulnerabilities.\n    cwe: CWE-20\n    function_names:\n      - \"normalizeBranchConfig(...)\"\n    filenames:\n      - lib/branches/index.js\n    classification: slightly promising\n\n  - headline: Inefficient Regular Expression Complexity\n    analysis: |\n      The file-linting regular expressions, if overly complex and not properly safeguarded, can lead to Denial of Service (DoS) through ReDoS (Regular expression Denial of Service).\n    cwe: CWE-1333\n    function_names: []\n    filenames:\n      - lib/definitions/regexes.js\n    classification: slightly promising\n```",
      "date": "2024-06-13T11:39:39.088394",
      "usage": {
        "prompt_tokens": 104242,
        "completion_tokens": 696,
        "cost": 0.53165
      }
    }
  ],
  "leads": [
    {
      "headline": "Potential Command Injection",
      "analysis": "The presence of the 'hook-std' package together with user provided inputs can lead to command injection vulnerabilities. Specifically, if the user inputs are not properly sanitized before being used in the 'hook-std' functions, an attacker could inject arbitrary OS commands, leading to full system compromise.\n",
      "classification": "very promising",
      "cwe": "CWE-78",
      "function_names": [
        "const {stdout, stderr} = await hookStd(...)"
      ],
      "filenames": [
        "index.js"
      ]
    },
    {
      "headline": "Exposing Tokens in Logs",
      "analysis": "The logging mechanism uses the 'get-logger' module which writes logs to stdout and stderr directly. If 'MY_TOKEN' or similar sensitive environment variables are logged without filtering, this can expose sensitive data.\n",
      "classification": "slightly promising",
      "cwe": "CWE-532",
      "function_names": [
        "logger.log(...)",
        "logger.error(...)"
      ],
      "filenames": [
        "lib/get-logger.js",
        "test/index.test.js"
      ]
    },
    {
      "headline": "Weak Cryptographic Algorithm",
      "analysis": "If the 'hideSensitive' functionality does not use secure cryptographic algorithms to obscure sensitive information, it might be possible for an attacker to reverse engineer and retrieve the original information. This is especially critical when dealing with tokens and passwords.\n",
      "classification": "very promising",
      "cwe": "CWE-327",
      "function_names": [
        "const hideSensitive = require('./hide-sensitive');"
      ],
      "filenames": [
        "lib/utils.js"
      ]
    },
    {
      "headline": "Potential Path Traversal",
      "analysis": "The usage of file paths without proper validation or sanitization can lead to path traversal vulnerabilities. If an attacker can control the file path argument in 'require' or 'readJson' functions, they may gain unauthorized access to the file system.\n",
      "classification": "very promising",
      "cwe": "CWE-22",
      "function_names": [
        "require(...)",
        "readJson(...)"
      ],
      "filenames": [
        "lib/get-config.js",
        "lib/plugins/utils.js"
      ]
    },
    {
      "headline": "Insecure Deserialization",
      "analysis": "The code might be susceptible to insecure deserialization attacks if user-controllable data is being deserialized without proper checks. This can potentially lead to remote code execution.\n",
      "classification": "slightly promising",
      "cwe": "CWE-502",
      "function_names": [],
      "filenames": [
        "lib/utils.js",
        "test/definitions/plugins.test.js"
      ]
    },
    {
      "headline": "Insufficient Validation in Branch Configuration",
      "analysis": "The branch configuration validation does not adequately ensure that the branch names conform to necessary security constraints. This, combined with potential user input, could lead to security misconfigurations or injection vulnerabilities.\n",
      "classification": "slightly promising",
      "cwe": "CWE-20",
      "function_names": [
        "normalizeBranchConfig(...)"
      ],
      "filenames": [
        "lib/branches/index.js"
      ]
    },
    {
      "headline": "Inefficient Regular Expression Complexity",
      "analysis": "The file-linting regular expressions, if overly complex and not properly safeguarded, can lead to Denial of Service (DoS) through ReDoS (Regular expression Denial of Service).\n",
      "classification": "slightly promising",
      "cwe": "CWE-1333",
      "function_names": [],
      "filenames": [
        "lib/definitions/regexes.js"
      ]
    }
  ],
  "scores": [
    {
      "stats": {
        "fn": 2,
        "tp": 0,
        "fp": 3
      },
      "mapping": {},
      "vuln_dates": {
        "CVE-2020-26226": "2020-11-18T22:15:12",
        "CVE-2022-31051": "2022-06-09T20:15:08"
      },
      "scoring_model": "claude-3-opus-20240229",
      "type": "llm",
      "instruction_template_hash": "245ace12b6361954d0a2"
    },
    {
      "stats": {
        "fn": 2,
        "tp": 0,
        "fp": 3
      },
      "mapping": {},
      "vuln_dates": {
        "CVE-2020-26226": "2020-11-18T22:15:12",
        "CVE-2022-31051": "2022-06-09T20:15:08"
      },
      "scoring_model": "claude-3-5-sonnet-20240620",
      "type": "llm",
      "instruction_template_hash": "245ace12b6361954d0a2"
    }
  ],
  "instruction_template_hash": "10c0163db4740318a544",
  "version": "0.1.0"
}
