{
  "commit": "3b361032b78d787ec5c1134b9bad8f1e6bbcb0d1",
  "repo_url": "https://github.com/flatlogic/react-dashboard",
  "model": "claude-3-sonnet-20240229",
  "chunk_hashes": [
    "c600b627d576ccbbdbd6"
  ],
  "responses": [
    {
      "content": "```yaml\nleads:\n  - headline: Improper Input Validation\n    analysis: |\n      The application does not properly validate user input, which could lead to various security vulnerabilities such as cross-site scripting (XSS), SQL injection, or other injection attacks. User input should be sanitized and validated before being used in any security-sensitive operation.\n    cwe: CWE-20\n    function_names:\n      - changeLogin\n      - changePassword\n      - changeTitle\n      - changeContent\n    filenames:\n      - src/pages/login/Login.js\n      - src/pages/posts/new/PostNew.js\n    classification: very promising\n\n  - headline: Use of Hard-coded Credentials\n    analysis: |\n      The application uses hard-coded credentials (username \"user\" and password \"password\") for authentication, which is a significant security risk. Hard-coded credentials should never be used in production environments as they are easily discoverable and can be exploited by attackers.\n    cwe: CWE-798\n    function_names:\n      - undefined\n    filenames:\n      - server/server.js\n    classification: very promising\n\n  - headline: Missing Authentication for Critical Function\n    analysis: |\n      The application does not require authentication for creating new posts, which is a critical function. This could allow unauthorized users to create and publish posts, potentially leading to content pollution or other security issues.\n    cwe: CWE-306\n    function_names:\n      - createPost\n    filenames:\n      - src/actions/posts.js\n    classification: very promising\n\n  - headline: Insecure Communication\n    analysis: |\n      The application transmits sensitive data (authentication tokens) in cleartext, which can be intercepted by attackers. Sensitive data should be encrypted during transmission to prevent unauthorized access or modification.\n    cwe: CWE-319\n    function_names:\n      - loginUser\n    filenames:\n      - src/actions/user.js\n    classification: very promising\n\n  - headline: Potential Cross-Site Scripting (XSS)\n    analysis: |\n      The application does not properly sanitize user input when rendering post content, which could lead to cross-site scripting (XSS) vulnerabilities. XSS attacks can enable attackers to inject malicious scripts into web pages, potentially compromising user data or taking control of the application.\n    cwe: CWE-79\n    function_names:\n      - undefined\n    filenames:\n      - src/pages/posts/list/PostList.js\n    classification: slightly promising\n```\n\nThe codebase contains several security vulnerabilities, primarily related to improper input validation, use of hard-coded credentials, missing authentication for critical functions, insecure communication, and potential cross-site scripting (XSS) vulnerabilities. These vulnerabilities could lead to various attacks, such as injection attacks, unauthorized access, data exposure, and content pollution.",
      "date": "2024-06-09T12:02:47.399450",
      "usage": {
        "prompt_tokens": 109152,
        "completion_tokens": 669,
        "cost": 0.337491
      }
    }
  ],
  "leads": [
    {
      "headline": "Improper Input Validation",
      "analysis": "The application does not properly validate user input, which could lead to various security vulnerabilities such as cross-site scripting (XSS), SQL injection, or other injection attacks. User input should be sanitized and validated before being used in any security-sensitive operation.\n",
      "classification": "very promising",
      "cwe": "CWE-20",
      "function_names": [
        "changeLogin",
        "changePassword",
        "changeTitle"
      ],
      "filenames": [
        "src/pages/login/Login.js",
        "src/pages/posts/new/PostNew.js"
      ]
    },
    {
      "headline": "Use of Hard-coded Credentials",
      "analysis": "The application uses hard-coded credentials (username \"user\" and password \"password\") for authentication, which is a significant security risk. Hard-coded credentials should never be used in production environments as they are easily discoverable and can be exploited by attackers.\n",
      "classification": "very promising",
      "cwe": "CWE-798",
      "function_names": [
        "undefined"
      ],
      "filenames": [
        "server/server.js"
      ]
    },
    {
      "headline": "Missing Authentication for Critical Function",
      "analysis": "The application does not require authentication for creating new posts, which is a critical function. This could allow unauthorized users to create and publish posts, potentially leading to content pollution or other security issues.\n",
      "classification": "very promising",
      "cwe": "CWE-306",
      "function_names": [
        "createPost"
      ],
      "filenames": [
        "src/actions/posts.js"
      ]
    },
    {
      "headline": "Insecure Communication",
      "analysis": "The application transmits sensitive data (authentication tokens) in cleartext, which can be intercepted by attackers. Sensitive data should be encrypted during transmission to prevent unauthorized access or modification.\n",
      "classification": "very promising",
      "cwe": "CWE-319",
      "function_names": [
        "loginUser"
      ],
      "filenames": [
        "src/actions/user.js"
      ]
    },
    {
      "headline": "Potential Cross-Site Scripting (XSS)",
      "analysis": "The application does not properly sanitize user input when rendering post content, which could lead to cross-site scripting (XSS) vulnerabilities. XSS attacks can enable attackers to inject malicious scripts into web pages, potentially compromising user data or taking control of the application.\n",
      "classification": "slightly promising",
      "cwe": "CWE-79",
      "function_names": [
        "undefined"
      ],
      "filenames": [
        "src/pages/posts/list/PostList.js"
      ]
    }
  ],
  "scores": [
    {
      "stats": {
        "fn": 1,
        "tp": 0,
        "fp": 4
      },
      "mapping": {},
      "vuln_dates": {
        "CVE-2023-51843": "2024-01-30T01:15:58"
      },
      "scoring_model": "gpt-4o-2024-05-13",
      "type": "llm",
      "instruction_template_hash": "8998f09cf57fca8a6e03"
    }
  ],
  "instruction_template_hash": "10c0163db4740318a544",
  "version": "0.1.0"
}
