{
  "commit": "72c017717800c17ff7aee66506bf3976783c5efd",
  "repo_url": "https://github.com/redon-tech/redon-hub",
  "model": "gemini/gemini-1.5-pro",
  "chunk_hashes": [
    "1d8ca55377e8cd7bf003"
  ],
  "responses": [
    {
      "content": "```yaml\nleads:\n  - headline: Hardcoded API Key and Bot Token\n    analysis: |\n      The `config.API.Key` and `os.getenv(\"token\")` values are hardcoded in the code, making them accessible to anyone with access to the repository. This means an attacker could potentially gain unauthorized access to the API and control the bot.\n    cwe: CWE-798\n    function_names:\n      - api_auth\n      - main\n    filenames:\n      - bot/cogs/api_v1.py\n      - launcher.py\n    classification: very promising\n  - headline: Missing Input Validation in API Endpoints\n    analysis: |\n      Several API endpoints, such as `/v1/users/{user_id}/{product_id}` and `/v1/products/{product_id}`, accept user-provided input (user_id, product_id) without sufficient validation. This could lead to various attacks, including SQL injection or path traversal, depending on how the data is used downstream.\n    cwe: CWE-20\n    function_names:\n      - users_give_user_product\n      - users_revoke_user_product\n      - products_get_product\n      - products_patch\n      - products_delete\n    filenames:\n      - bot/cogs/api_v1.py\n    classification: slightly promising\n  - headline: Unrestricted File Uploads\n    analysis: |\n      The `promptChooseAttachments` function allows users to submit URLs, which are later used as attachments for products. This mechanism lacks validation for the type and content of the files being linked, potentially allowing attackers to upload malicious files.\n    cwe: CWE-434\n    function_names:\n      - promptChooseAttachments\n    filenames:\n      - bot/cogs/product.py\n    classification: slightly promising\n  - headline: Potential for Cross-Site Scripting (XSS)\n    analysis: |\n      The `promptChooseAttachments` function, used for handling product attachments, accepts URLs from users without proper sanitization. This could allow attackers to inject malicious scripts into the URLs, potentially leading to XSS attacks when those URLs are rendered on the client-side. \n    cwe: CWE-79\n    function_names:\n      - promptChooseAttachments\n    filenames:\n      - bot/cogs/product.py\n    classification: slightly promising\n  - headline: Sensitive Information in Error Messages\n    analysis: |\n      Some error handling sections, like those in `users_give_user_product`, `users_revoke_user_product`, `products_patch`, and `tags_patch` may leak internal error messages (including exceptions) directly to the API response. This can unintentionally expose sensitive information about the application's internals to attackers.\n    cwe: CWE-209\n    function_names:\n      - users_give_user_product\n      - users_revoke_user_product\n      - products_patch\n      - tags_patch\n    filenames:\n      - bot/cogs/api_v1.py\n    classification: slightly promising\n  - headline: Missing Rate Limiting on API Endpoints\n    analysis: |\n      The API endpoints lack rate limiting, making them vulnerable to denial-of-service (DoS) attacks. An attacker could send a large number of requests to an endpoint, overwhelming the server and making it unavailable to legitimate users.\n    cwe: CWE-770\n    function_names: []\n    filenames:\n      - bot/cogs/api_v1.py\n    classification: slightly promising\n```",
      "date": "2024-06-12T13:47:37.048886",
      "usage": {
        "prompt_tokens": 29352,
        "completion_tokens": 691,
        "cost": 0.019640625000000002
      }
    }
  ],
  "leads": [
    {
      "headline": "Hardcoded API Key and Bot Token",
      "analysis": "The config.API.Key and os.getenv(\"token\") values are hardcoded in the code, making them accessible to anyone with access to the repository. This means an attacker could potentially gain unauthorized access to the API and control the bot.\n",
      "classification": "very promising",
      "cwe": "CWE-798",
      "function_names": [
        "api_auth",
        "main"
      ],
      "filenames": [
        "bot/cogs/api_v1.py",
        "launcher.py"
      ]
    },
    {
      "headline": "Missing Input Validation in API Endpoints",
      "analysis": "Several API endpoints, such as /v1/users/{user_id}/{product_id} and /v1/products/{product_id}, accept user-provided input (user_id, product_id) without sufficient validation. This could lead to various attacks, including SQL injection or path traversal, depending on how the data is used downstream.\n",
      "classification": "slightly promising",
      "cwe": "CWE-20",
      "function_names": [
        "users_give_user_product",
        "users_revoke_user_product",
        "products_get_product"
      ],
      "filenames": [
        "bot/cogs/api_v1.py"
      ]
    },
    {
      "headline": "Unrestricted File Uploads",
      "analysis": "The promptChooseAttachments function allows users to submit URLs, which are later used as attachments for products. This mechanism lacks validation for the type and content of the files being linked, potentially allowing attackers to upload malicious files.\n",
      "classification": "slightly promising",
      "cwe": "CWE-434",
      "function_names": [
        "promptChooseAttachments"
      ],
      "filenames": [
        "bot/cogs/product.py"
      ]
    },
    {
      "headline": "Potential for Cross-Site Scripting (XSS)",
      "analysis": "The promptChooseAttachments function, used for handling product attachments, accepts URLs from users without proper sanitization. This could allow attackers to inject malicious scripts into the URLs, potentially leading to XSS attacks when those URLs are rendered on the client-side. \n",
      "classification": "slightly promising",
      "cwe": "CWE-79",
      "function_names": [
        "promptChooseAttachments"
      ],
      "filenames": [
        "bot/cogs/product.py"
      ]
    },
    {
      "headline": "Sensitive Information in Error Messages",
      "analysis": "Some error handling sections, like those in users_give_user_product, users_revoke_user_product, products_patch, and tags_patch may leak internal error messages (including exceptions) directly to the API response. This can unintentionally expose sensitive information about the application's internals to attackers.\n",
      "classification": "slightly promising",
      "cwe": "CWE-209",
      "function_names": [
        "users_give_user_product",
        "users_revoke_user_product",
        "products_patch"
      ],
      "filenames": [
        "bot/cogs/api_v1.py"
      ]
    },
    {
      "headline": "Missing Rate Limiting on API Endpoints",
      "analysis": "The API endpoints lack rate limiting, making them vulnerable to denial-of-service (DoS) attacks. An attacker could send a large number of requests to an endpoint, overwhelming the server and making it unavailable to legitimate users.\n",
      "classification": "slightly promising",
      "cwe": "CWE-770",
      "function_names": [],
      "filenames": [
        "bot/cogs/api_v1.py"
      ]
    }
  ],
  "scores": [
    {
      "stats": {
        "fn": 1,
        "tp": 0,
        "fp": 1
      },
      "mapping": {},
      "vuln_dates": {
        "CVE-2024-31442": "2024-04-08T16:15:07"
      },
      "scoring_model": "claude-3-opus-20240229",
      "type": "llm",
      "instruction_template_hash": "245ace12b6361954d0a2"
    }
  ],
  "instruction_template_hash": "10c0163db4740318a544",
  "version": "0.1.0"
}
