{
  "commit": "34e86f0d4bccee3232c0d1a6aff59a45cd04f1b9",
  "repo_url": "https://github.com/jenkinsci/dingding-notifications-plugin",
  "model": "claude-3-sonnet-20240229",
  "chunk_hashes": [
    "c174494d01b51c2e0467"
  ],
  "responses": [
    {
      "content": "```yaml\nleads:\n  - headline: Lack of Input Validation\n    analysis: |\n      The codebase does not perform proper input validation, which could allow an attacker\n      to inject malicious data into the application. This could potentially lead to various\n      security vulnerabilities such as cross-site scripting (XSS), SQL injection, code injection,\n      or other types of injection attacks.\n    cwe: CWE-20\n    function_names:\n      - DingdingNotifier\n      - DingTalkNotifier\n    filenames:\n      - src/main/java/com/ztbsuper/dingding/DingdingNotifier.java\n      - src/main/java/com/ztbsuper/dingtalk/DingTalkNotifier.java\n    classification: very promising\n\n  - headline: Use of Externally-Controlled Input in Redirect\n    analysis: |\n      The DingTalkNotifier class allows external input to be used in constructing a redirect URL\n      without proper validation. This could potentially lead to an open redirect vulnerability,\n      where an attacker could craft a malicious URL to redirect users to an untrusted site.\n    cwe: CWE-601\n    function_names:\n      - DingTalkNotifier\n    filenames:\n      - src/main/java/com/ztbsuper/dingtalk/DingTalkNotifier.java\n    classification: very promising\n\n  - headline: Insecure Transmission of Sensitive Information\n    analysis: |\n      The codebase appears to transmit sensitive information, such as the access token, over\n      an unencrypted channel (HTTP). This could potentially allow an attacker to intercept and\n      compromise the sensitive data.\n    cwe: CWE-319\n    function_names:\n      - DingdingServiceImpl\n      - DingTalkNotifier\n    filenames:\n      - src/main/java/com/ztbsuper/dingding/DingdingServiceImpl.java\n      - src/main/java/com/ztbsuper/dingtalk/DingTalkNotifier.java\n    classification: very promising\n\n  - headline: Insecure Storage of Sensitive Information\n    analysis: |\n      The codebase may store sensitive information, such as access tokens or credentials, in an\n      insecure manner, potentially exposing it to unauthorized access or misuse.\n    cwe: CWE-312\n    function_names: []\n    filenames: []\n    classification: slightly promising\n\n  - headline: Potential CSRF Vulnerability\n    analysis: |\n      The codebase does not appear to implement any Cross-Site Request Forgery (CSRF) protection\n      mechanisms. This could potentially allow an attacker to perform unauthorized actions on\n      behalf of an authenticated user.\n    cwe: CWE-352\n    function_names: []\n    filenames: []\n    classification: slightly promising\n\n  - headline: Lack of Authentication and Authorization\n    analysis: |\n      The codebase does not appear to implement any authentication or authorization mechanisms.\n      This could potentially allow unauthorized access to sensitive functionality or data.\n    cwe: CWE-306\n    function_names: []\n    filenames: []\n    classification: slightly promising\n```",
      "date": "2024-06-12T18:19:00.298415",
      "usage": {
        "prompt_tokens": 8046,
        "completion_tokens": 771,
        "cost": 0.035703
      }
    }
  ],
  "leads": [
    {
      "headline": "Lack of Input Validation",
      "analysis": "The codebase does not perform proper input validation, which could allow an attacker\nto inject malicious data into the application. This could potentially lead to various\nsecurity vulnerabilities such as cross-site scripting (XSS), SQL injection, code injection,\nor other types of injection attacks.\n",
      "classification": "very promising",
      "cwe": "CWE-20",
      "function_names": [
        "DingdingNotifier",
        "DingTalkNotifier"
      ],
      "filenames": [
        "src/main/java/com/ztbsuper/dingding/DingdingNotifier.java",
        "src/main/java/com/ztbsuper/dingtalk/DingTalkNotifier.java"
      ]
    },
    {
      "headline": "Use of Externally-Controlled Input in Redirect",
      "analysis": "The DingTalkNotifier class allows external input to be used in constructing a redirect URL\nwithout proper validation. This could potentially lead to an open redirect vulnerability,\nwhere an attacker could craft a malicious URL to redirect users to an untrusted site.\n",
      "classification": "very promising",
      "cwe": "CWE-601",
      "function_names": [
        "DingTalkNotifier"
      ],
      "filenames": [
        "src/main/java/com/ztbsuper/dingtalk/DingTalkNotifier.java"
      ]
    },
    {
      "headline": "Insecure Transmission of Sensitive Information",
      "analysis": "The codebase appears to transmit sensitive information, such as the access token, over\nan unencrypted channel (HTTP). This could potentially allow an attacker to intercept and\ncompromise the sensitive data.\n",
      "classification": "very promising",
      "cwe": "CWE-319",
      "function_names": [
        "DingdingServiceImpl",
        "DingTalkNotifier"
      ],
      "filenames": [
        "src/main/java/com/ztbsuper/dingding/DingdingServiceImpl.java",
        "src/main/java/com/ztbsuper/dingtalk/DingTalkNotifier.java"
      ]
    },
    {
      "headline": "Insecure Storage of Sensitive Information",
      "analysis": "The codebase may store sensitive information, such as access tokens or credentials, in an\ninsecure manner, potentially exposing it to unauthorized access or misuse.\n",
      "classification": "slightly promising",
      "cwe": "CWE-312",
      "function_names": [],
      "filenames": []
    },
    {
      "headline": "Potential CSRF Vulnerability",
      "analysis": "The codebase does not appear to implement any Cross-Site Request Forgery (CSRF) protection\nmechanisms. This could potentially allow an attacker to perform unauthorized actions on\nbehalf of an authenticated user.\n",
      "classification": "slightly promising",
      "cwe": "CWE-352",
      "function_names": [],
      "filenames": []
    },
    {
      "headline": "Lack of Authentication and Authorization",
      "analysis": "The codebase does not appear to implement any authentication or authorization mechanisms.\nThis could potentially allow unauthorized access to sensitive functionality or data.\n",
      "classification": "slightly promising",
      "cwe": "CWE-306",
      "function_names": [],
      "filenames": []
    }
  ],
  "scores": [
    {
      "stats": {
        "fn": 1,
        "tp": 0,
        "fp": 3
      },
      "mapping": {},
      "vuln_dates": {
        "CVE-2019-10433": "2019-10-01T14:15:28"
      },
      "scoring_model": "claude-3-opus-20240229",
      "type": "llm",
      "instruction_template_hash": "245ace12b6361954d0a2"
    }
  ],
  "instruction_template_hash": "10c0163db4740318a544",
  "version": "0.1.0"
}
