{
  "commit": "0dbed1fdbd78c88911207c29b796d5616234b501",
  "repo_url": "https://github.com/tarantool/msgpuck",
  "model": "claude-3-5-sonnet-20240620",
  "chunk_hashes": [
    "29e3438ce7913e4d8a8e"
  ],
  "responses": [
    {
      "content": "```yaml\nleads:\n  - headline: Buffer overflow vulnerability in mp_encode_str and mp_encode_bin functions\n    analysis: |\n      The mp_encode_str and mp_encode_bin functions do not validate that the input length fits within the destination buffer before writing. This could allow an attacker to cause a buffer overflow by providing a malicious length value. The overflow could potentially be exploited to execute arbitrary code or crash the program.\n    cwe: CWE-120\n    function_names:\n      - mp_encode_str\n      - mp_encode_bin  \n    filenames:\n      - msgpuck.h\n    classification: very promising\n\n  - headline: Integer overflow vulnerability in mp_sizeof functions\n    analysis: |\n      The mp_sizeof_* functions that take a uint32_t size parameter do not check for integer overflow before performing size calculations. This could lead to allocation of a buffer that is too small to hold the actual data, potentially causing a buffer overflow. An attacker could exploit this by providing a very large size value.\n    cwe: CWE-190\n    function_names:\n      - mp_sizeof_array\n      - mp_sizeof_map\n      - mp_sizeof_strl\n      - mp_sizeof_binl\n    filenames:\n      - msgpuck.h\n    classification: slightly promising\n\n  - headline: Potential null pointer dereference in mp_decode_str and mp_decode_bin\n    analysis: |\n      The mp_decode_str and mp_decode_bin functions do not check if the len parameter is NULL before dereferencing it. If a NULL pointer is passed, this could lead to a null pointer dereference and program crash. An attacker could potentially exploit this to cause a denial of service.\n    cwe: CWE-476\n    function_names:\n      - mp_decode_str\n      - mp_decode_bin\n    filenames:\n      - msgpuck.h  \n    classification: slightly promising\n\n  - headline: Use of unsafe snprintf in mp_format function\n    analysis: |\n      The mp_format function uses snprintf to format strings, but does not check the return value to ensure the entire string was written. This could potentially lead to truncation of data if the buffer is too small. While not directly exploitable, it could cause unexpected behavior or information disclosure.\n    cwe: CWE-119\n    function_names:\n      - mp_format\n    filenames:\n      - msgpuck.h\n    classification: not promising\n```",
      "date": "2024-07-08T08:55:10.263416",
      "usage": {
        "prompt_tokens": 47286,
        "completion_tokens": 574,
        "cost": 0.150468
      }
    }
  ],
  "leads": [
    {
      "headline": "Buffer overflow vulnerability in mp_encode_str and mp_encode_bin functions",
      "analysis": "The mp_encode_str and mp_encode_bin functions do not validate that the input length fits within the destination buffer before writing. This could allow an attacker to cause a buffer overflow by providing a malicious length value. The overflow could potentially be exploited to execute arbitrary code or crash the program.\n",
      "classification": "very promising",
      "cwe": "CWE-120",
      "function_names": [
        "mp_encode_str",
        "mp_encode_bin"
      ],
      "filenames": [
        "msgpuck.h"
      ]
    },
    {
      "headline": "Integer overflow vulnerability in mp_sizeof functions",
      "analysis": "The mp_sizeof_* functions that take a uint32_t size parameter do not check for integer overflow before performing size calculations. This could lead to allocation of a buffer that is too small to hold the actual data, potentially causing a buffer overflow. An attacker could exploit this by providing a very large size value.\n",
      "classification": "slightly promising",
      "cwe": "CWE-190",
      "function_names": [
        "mp_sizeof_array",
        "mp_sizeof_map",
        "mp_sizeof_strl"
      ],
      "filenames": [
        "msgpuck.h"
      ]
    },
    {
      "headline": "Potential null pointer dereference in mp_decode_str and mp_decode_bin",
      "analysis": "The mp_decode_str and mp_decode_bin functions do not check if the len parameter is NULL before dereferencing it. If a NULL pointer is passed, this could lead to a null pointer dereference and program crash. An attacker could potentially exploit this to cause a denial of service.\n",
      "classification": "slightly promising",
      "cwe": "CWE-476",
      "function_names": [
        "mp_decode_str",
        "mp_decode_bin"
      ],
      "filenames": [
        "msgpuck.h"
      ]
    },
    {
      "headline": "Use of unsafe snprintf in mp_format function",
      "analysis": "The mp_format function uses snprintf to format strings, but does not check the return value to ensure the entire string was written. This could potentially lead to truncation of data if the buffer is too small. While not directly exploitable, it could cause unexpected behavior or information disclosure.\n",
      "classification": "not promising",
      "cwe": "CWE-119",
      "function_names": [
        "mp_format"
      ],
      "filenames": [
        "msgpuck.h"
      ]
    }
  ],
  "scores": [
    {
      "stats": {
        "fn": 1,
        "tp": 0,
        "fp": 1
      },
      "mapping": {},
      "vuln_dates": {
        "CVE-2016-9036": "2016-12-23T22:59:00"
      },
      "scoring_model": "claude-3-5-sonnet-20240620",
      "type": "llm",
      "instruction_template_hash": "245ace12b6361954d0a2"
    }
  ],
  "instruction_template_hash": "10c0163db4740318a544",
  "version": "0.1.0"
}
