{
  "commit": "022603ddf92d43d23dd3f70ad263591e24defda5",
  "repo_url": "https://github.com/gotify/server",
  "model": "gpt-4o-2024-05-13",
  "chunk_hashes": [
    "e4f4866deda34501a387"
  ],
  "responses": [
    {
      "content": "```yaml\nleads:\n  - headline: \"Improper Validation and Persistence of Local Storage Token\"\n    analysis: |\n      The CurrentUser class relies on a token stored in localStorage (`window.localStorage.getItem(tokenKey)`) which is directly retrieved and used in the `token` method without proper validation. This could allow attackers to manipulate the token stored in the client\u2019s local storage to gain access to protected resources without proper authentication.\n    cwe: CWE-1284\n    function_names:\n      - \"CurrentUser.token\"\n    filenames:\n      - \"ui/src/CurrentUser.ts\"\n    classification: very promising\n\n  - headline: \"Plaintext Storage of Sensitive Information\"\n    analysis: |\n      The password is transmitted in plaintext during the registration and login processes. Specifically, the password is included in the payload (`{name, pass}`) of a POST request sent to `config.get('url') + 'user'` and `config.get('url') + 'client'`. This is insecure as anyone with access to the network traffic can intercept these passwords.\n    cwe: CWE-319\n    function_names:\n      - \"CurrentUser.register\"\n      - \"CurrentUser.login\"\n    filenames:\n      - \"ui/src/CurrentUser.ts\"\n    classification: very promising\n\n  - headline: \"Improper Error Handling and Information Exposure\"\n    analysis: |\n      Error messages returned from the server are directly shown to the user via the `snack` method. This can expose internal server information, error stack traces, and other sensitive data which can be leveraged by attackers for further exploitation.\n    cwe: CWE-209\n    function_names:\n      - \"CurrentUser.register\"\n      - \"CurrentUser.login\"\n      - \"CurrentUser.tryAuthenticate\"\n    filenames:\n      - \"ui/src/CurrentUser.ts\"\n    classification: slightly promising\n\n  - headline: \"Weak Password Requirements\"\n    analysis: |\n      There are no enforced requirements for password strength during the user registration process (`CurrentUser.register`) and passwords as weak as '123' or '1' are permissible. This puts user accounts at risk by allowing the use of weak and easily guessable passwords.\n    cwe: CWE-521\n    function_names:\n      - \"CurrentUser.register\"\n    filenames:\n      - \"ui/src/CurrentUser.ts\"\n    classification: very promising\n\n  - headline: \"Cross-Site Scripting (XSS) via User Messages\"\n    analysis: |\n      User-generated content in messages (specifically `msg.title` and `msg.message`) are rendered on the client without any apparent sanitization. An attacker could inject malicious scripts in their messages which will be executed in the context of the victim user's browser potentially leading to account hijacking or data theft.\n    cwe: CWE-79\n    function_names:\n      - \"notifyNewMessage\"\n    filenames:\n      - \"ui/src/snack/browserNotification.ts\"\n    classification: very promising\n\n  - headline: \"Unrestricted Plugin Upload\"\n    analysis: |\n      There is no limit or validation on the types of plugins that can be uploaded to the server directory, potentially allowing the upload and execution of malicious plugins. This can lead to unauthorized code execution on the server.\n    cwe: CWE-434\n    function_names: []\n    filenames:\n      - \"ui/src/setupTests.ts\"\n    classification: very promising\n\n  - headline: \"Missing Encryption for WebSocket Communication\"\n    analysis: |\n      The WebSocket connection URL in `ws.listen` method downgrades the protocol from HTTPS to WS, which results in unencrypted communications even when HTTPS is available. This exposes the communication channel to man-in-the-middle attacks.\n    cwe: CWE-319\n    function_names:\n      - \"WebSocketStore.listen\"\n    filenames:\n      - \"ui/src/message/WebSocketStore.ts\"\n    classification: very promising\n\n  - headline: \"Lack of Protection against CSRF\"\n    analysis: |\n      The application uses tokens to authenticate API requests, but there is no clear indication of CSRF protection mechanisms such as anti-CSRF tokens in forms and headers to prevent Cross-Site Request Forgery attacks.\n    cwe: CWE-352\n    function_names: []\n    filenames: []\n    classification: very promising\n\n  - headline: \"XML External Entity (XXE) Injection\"\n    analysis: |\n      If the application parses XML and does not disable external entities, there can be a risk of XXE attacks where an attacker can retrieve files from the server or perform SSRF attacks by manipulating the external entities.\n    cwe: CWE-611\n    function_names: []\n    filenames: []\n    classification: not promising\n\n  - headline: \"Insecure Random Number Generation\"\n    analysis: |\n      There is no visible use of secure random numbers for generating any critical tokens, keys, or nonces that should use cryptographically secure pseudo-random number generators. If any secure operations rely on randomness, this needs investigating.\n    cwe: CWE-330\n    function_names: []\n    filenames: []\n    classification: slightly promising\n```",
      "date": "2024-06-12T17:05:25.789296",
      "usage": {
        "prompt_tokens": 19096,
        "completion_tokens": 1041,
        "cost": 0.111095
      }
    }
  ],
  "leads": [
    {
      "headline": "Improper Validation and Persistence of Local Storage Token",
      "analysis": "The CurrentUser class relies on a token stored in localStorage (window.localStorage.getItem(tokenKey)) which is directly retrieved and used in the token method without proper validation. This could allow attackers to manipulate the token stored in the client\u2019s local storage to gain access to protected resources without proper authentication.\n",
      "classification": "very promising",
      "cwe": "CWE-1284",
      "function_names": [
        "CurrentUser.token"
      ],
      "filenames": [
        "ui/src/CurrentUser.ts"
      ]
    },
    {
      "headline": "Plaintext Storage of Sensitive Information",
      "analysis": "The password is transmitted in plaintext during the registration and login processes. Specifically, the password is included in the payload ({name, pass}) of a POST request sent to config.get('url') + 'user' and config.get('url') + 'client'. This is insecure as anyone with access to the network traffic can intercept these passwords.\n",
      "classification": "very promising",
      "cwe": "CWE-319",
      "function_names": [
        "CurrentUser.register",
        "CurrentUser.login"
      ],
      "filenames": [
        "ui/src/CurrentUser.ts"
      ]
    },
    {
      "headline": "Improper Error Handling and Information Exposure",
      "analysis": "Error messages returned from the server are directly shown to the user via the snack method. This can expose internal server information, error stack traces, and other sensitive data which can be leveraged by attackers for further exploitation.\n",
      "classification": "slightly promising",
      "cwe": "CWE-209",
      "function_names": [
        "CurrentUser.register",
        "CurrentUser.login",
        "CurrentUser.tryAuthenticate"
      ],
      "filenames": [
        "ui/src/CurrentUser.ts"
      ]
    },
    {
      "headline": "Weak Password Requirements",
      "analysis": "There are no enforced requirements for password strength during the user registration process (CurrentUser.register) and passwords as weak as '123' or '1' are permissible. This puts user accounts at risk by allowing the use of weak and easily guessable passwords.\n",
      "classification": "very promising",
      "cwe": "CWE-521",
      "function_names": [
        "CurrentUser.register"
      ],
      "filenames": [
        "ui/src/CurrentUser.ts"
      ]
    },
    {
      "headline": "Cross-Site Scripting (XSS) via User Messages",
      "analysis": "User-generated content in messages (specifically msg.title and msg.message) are rendered on the client without any apparent sanitization. An attacker could inject malicious scripts in their messages which will be executed in the context of the victim user's browser potentially leading to account hijacking or data theft.\n",
      "classification": "very promising",
      "cwe": "CWE-79",
      "function_names": [
        "notifyNewMessage"
      ],
      "filenames": [
        "ui/src/snack/browserNotification.ts"
      ]
    },
    {
      "headline": "Unrestricted Plugin Upload",
      "analysis": "There is no limit or validation on the types of plugins that can be uploaded to the server directory, potentially allowing the upload and execution of malicious plugins. This can lead to unauthorized code execution on the server.\n",
      "classification": "very promising",
      "cwe": "CWE-434",
      "function_names": [],
      "filenames": [
        "ui/src/setupTests.ts"
      ]
    },
    {
      "headline": "Missing Encryption for WebSocket Communication",
      "analysis": "The WebSocket connection URL in ws.listen method downgrades the protocol from HTTPS to WS, which results in unencrypted communications even when HTTPS is available. This exposes the communication channel to man-in-the-middle attacks.\n",
      "classification": "very promising",
      "cwe": "CWE-319",
      "function_names": [
        "WebSocketStore.listen"
      ],
      "filenames": [
        "ui/src/message/WebSocketStore.ts"
      ]
    },
    {
      "headline": "Lack of Protection against CSRF",
      "analysis": "The application uses tokens to authenticate API requests, but there is no clear indication of CSRF protection mechanisms such as anti-CSRF tokens in forms and headers to prevent Cross-Site Request Forgery attacks.\n",
      "classification": "very promising",
      "cwe": "CWE-352",
      "function_names": [],
      "filenames": []
    },
    {
      "headline": "XML External Entity (XXE) Injection",
      "analysis": "If the application parses XML and does not disable external entities, there can be a risk of XXE attacks where an attacker can retrieve files from the server or perform SSRF attacks by manipulating the external entities.\n",
      "classification": "not promising",
      "cwe": "CWE-611",
      "function_names": [],
      "filenames": []
    },
    {
      "headline": "Insecure Random Number Generation",
      "analysis": "There is no visible use of secure random numbers for generating any critical tokens, keys, or nonces that should use cryptographically secure pseudo-random number generators. If any secure operations rely on randomness, this needs investigating.\n",
      "classification": "slightly promising",
      "cwe": "CWE-330",
      "function_names": [],
      "filenames": []
    }
  ],
  "scores": [
    {
      "stats": {
        "fn": 1,
        "tp": 0,
        "fp": 7
      },
      "mapping": {},
      "vuln_dates": {
        "CVE-2022-46181": "2022-12-29T19:15:08"
      },
      "scoring_model": "claude-3-opus-20240229",
      "type": "llm",
      "instruction_template_hash": "245ace12b6361954d0a2"
    },
    {
      "stats": {
        "fn": 1,
        "tp": 0,
        "fp": 7
      },
      "mapping": {},
      "vuln_dates": {
        "CVE-2022-46181": "2022-12-29T19:15:08"
      },
      "scoring_model": "claude-3-5-sonnet-20240620",
      "type": "llm",
      "instruction_template_hash": "245ace12b6361954d0a2"
    }
  ],
  "instruction_template_hash": "10c0163db4740318a544",
  "version": "0.1.0"
}
