{
  "commit": "3a0699d2a90544a0f8928c40947b119e9491c2fa",
  "repo_url": "https://github.com/senchalabs/connect",
  "model": "claude-3-opus-20240229",
  "chunk_hashes": [
    "1fe5273731f7746154fc"
  ],
  "responses": [
    {
      "content": "Here is the YAML output with potential security vulnerabilities in the given codebase:\n\n```yaml\nleads:\n  - headline: Potential Command Injection via child_process module\n    analysis: |\n      The upload-stream.js example uses the child_process module to spawn a process\n      with the uploaded filename as an argument. If the filename is not properly \n      validated or sanitized, it could allow an attacker to inject arbitrary commands.\n      The risk depends on how the uploaded files are named and where the upload \n      directory is located.\n    cwe: CWE-78\n    function_names:\n      - upload\n    filenames: \n      - examples/upload-stream.js\n    classification: slightly promising\n\n  - headline: Directory Traversal via Connect static middleware\n    analysis: |\n      The Connect static file serving middleware does not properly prevent \n      directory traversal attacks. Requests containing ../ path segments can \n      access files outside the root directory specified. This could allow \n      an attacker to access sensitive files on the server filesystem.\n    cwe: CWE-22\n    function_names:\n      - directory\n    filenames:\n      - lib/middleware/static.js  \n    classification: very promising\n\n  - headline: Potential NoSQL Injection in MemoryStore\n    analysis: |\n      The MemoryStore session storage implementation uses JSON.parse() \n      to deserialize stored sessions. However, it does not validate that\n      the input is well-formed JSON. If an attacker can control the value\n      of a session, they may be able to inject arbitrary JavaScript and gain RCE.\n      The exposure depends on how the parsed session data is later used.\n    cwe: CWE-94\n    function_names:\n      - get\n    filenames:\n      - lib/middleware/session/memory.js\n    classification: slightly promising\n\n  - headline: Sensitive Information Disclosure via Error Messages\n    analysis: |\n      The Connect errorHandler middleware includes stack traces containing\n      file paths and line numbers in HTML error pages when not in production.\n      This can expose sensitive information about the application and server. \n    cwe: CWE-209 \n    function_names:\n      - errorHandler \n    filenames:\n      - lib/middleware/errorHandler.js\n    classification: slightly promising\n\n  - headline: Potential Open Redirect via res.redirect()\n    analysis: |\n      Several places in the codebase use res.redirect() to send HTTP redirects.\n      If the target URL used in the redirect is based on user input and not \n      validated, it could allow open redirect attacks. An attacker could craft \n      URLs to redirect users to external malicious sites. The risk depends on\n      how the redirect target is determined.\n    cwe: CWE-601\n    function_names:\n      - directory\n      - staticMiddleware\n    filenames:\n      - lib/middleware/directory.js\n      - lib/middleware/static.js\n    classification: slightly promising\n```",
      "date": "2024-06-14T15:31:50.437170",
      "usage": {
        "prompt_tokens": 125120,
        "completion_tokens": 694,
        "cost": 1.92885
      }
    }
  ],
  "leads": [
    {
      "headline": "Potential Command Injection via child_process module",
      "analysis": "The upload-stream.js example uses the child_process module to spawn a process\nwith the uploaded filename as an argument. If the filename is not properly \nvalidated or sanitized, it could allow an attacker to inject arbitrary commands.\nThe risk depends on how the uploaded files are named and where the upload \ndirectory is located.\n",
      "classification": "slightly promising",
      "cwe": "CWE-78",
      "function_names": [
        "upload"
      ],
      "filenames": [
        "examples/upload-stream.js"
      ]
    },
    {
      "headline": "Directory Traversal via Connect static middleware",
      "analysis": "The Connect static file serving middleware does not properly prevent \ndirectory traversal attacks. Requests containing ../ path segments can \naccess files outside the root directory specified. This could allow \nan attacker to access sensitive files on the server filesystem.\n",
      "classification": "very promising",
      "cwe": "CWE-22",
      "function_names": [
        "directory"
      ],
      "filenames": [
        "lib/middleware/static.js"
      ]
    },
    {
      "headline": "Potential NoSQL Injection in MemoryStore",
      "analysis": "The MemoryStore session storage implementation uses JSON.parse() \nto deserialize stored sessions. However, it does not validate that\nthe input is well-formed JSON. If an attacker can control the value\nof a session, they may be able to inject arbitrary JavaScript and gain RCE.\nThe exposure depends on how the parsed session data is later used.\n",
      "classification": "slightly promising",
      "cwe": "CWE-94",
      "function_names": [
        "get"
      ],
      "filenames": [
        "lib/middleware/session/memory.js"
      ]
    },
    {
      "headline": "Sensitive Information Disclosure via Error Messages",
      "analysis": "The Connect errorHandler middleware includes stack traces containing\nfile paths and line numbers in HTML error pages when not in production.\nThis can expose sensitive information about the application and server. \n",
      "classification": "slightly promising",
      "cwe": "CWE-209",
      "function_names": [
        "errorHandler"
      ],
      "filenames": [
        "lib/middleware/errorHandler.js"
      ]
    },
    {
      "headline": "Potential Open Redirect via res.redirect()",
      "analysis": "Several places in the codebase use res.redirect() to send HTTP redirects.\nIf the target URL used in the redirect is based on user input and not \nvalidated, it could allow open redirect attacks. An attacker could craft \nURLs to redirect users to external malicious sites. The risk depends on\nhow the redirect target is determined.\n",
      "classification": "slightly promising",
      "cwe": "CWE-601",
      "function_names": [
        "directory",
        "staticMiddleware"
      ],
      "filenames": [
        "lib/middleware/directory.js",
        "lib/middleware/static.js"
      ]
    }
  ],
  "scores": [
    {
      "stats": {
        "fn": 1,
        "tp": 0,
        "fp": 1
      },
      "mapping": {},
      "vuln_dates": {
        "CVE-2018-3717": "2018-06-07T02:29:08"
      },
      "scoring_model": "claude-3-opus-20240229",
      "type": "llm",
      "instruction_template_hash": "245ace12b6361954d0a2"
    }
  ],
  "instruction_template_hash": "10c0163db4740318a544",
  "version": "0.1.0"
}
