{
  "commit": "3f9527977cc5dee860fab221e23e2290063c3045",
  "repo_url": "https://github.com/goreleaser/nfpm",
  "model": "claude-3-sonnet-20240229",
  "chunk_hashes": [
    "7a73f173df39b9f1db3a"
  ],
  "responses": [
    {
      "content": "```yaml\nleads:\n  - headline: Potential command injection vulnerability\n    analysis: |\n      The `cmd/nfpm` command seems to be executing shell commands using `go run`, which can potentially lead to command injection vulnerabilities if user input is passed to these commands without proper sanitization. This could allow an attacker to execute arbitrary commands on the system.\n    cwe: CWE-77\n    function_names:\n      - main\n    filenames:\n      - scripts/cmd_docs.sh\n      - scripts/completions.sh\n      - scripts/manpages.sh\n    classification: very promising\n\n  - headline: Potential race condition in package install/remove scripts\n    analysis: |\n      The install/remove scripts in `testdata/acceptance/scripts` and `testdata/scripts` are executed in a concurrent manner during package installation/removal. If these scripts access shared resources without proper synchronization, it could lead to race conditions and undefined behavior.\n    cwe: CWE-362\n    function_names: []\n    filenames:\n      - testdata/acceptance/scripts/postinstall.sh\n      - testdata/acceptance/scripts/preinstall.sh\n      - testdata/acceptance/scripts/postupgrade.sh\n      - testdata/acceptance/scripts/preupgrade.sh\n      - testdata/acceptance/scripts/postremove.sh\n      - testdata/acceptance/scripts/preremove.sh\n      - testdata/scripts/postinstall.sh\n      - testdata/scripts/preinstall.sh\n      - testdata/scripts/postupgrade.sh\n      - testdata/scripts/preupgrade.sh\n      - testdata/scripts/preremove.sh\n    classification: slightly promising\n\n  - headline: Potential path traversal vulnerability\n    analysis: |\n      The package scripts might be vulnerable to path traversal attacks if they accept user input for file paths without proper sanitization. An attacker could potentially access or modify files outside the intended directory.\n    cwe: CWE-22\n    function_names: []\n    filenames: []\n    classification: slightly promising\n\n  - headline: Use of unsafe temporary file creation\n    analysis: |\n      Some scripts in the codebase are creating temporary files using an insecure method (e.g., `echo \"Ok\" > /tmp/trigger-proof`). This could lead to insecure file operations, race conditions, or symlink attacks if the temporary file is predictable or world-writable.\n    cwe: CWE-377\n    function_names: []\n    filenames:\n      - testdata/acceptance/scripts/postinstall_trigger.sh\n    classification: slightly promising\n\n  - headline: Potential environment variable injection vulnerability\n    analysis: |\n      Some scripts in the codebase are using environment variables without proper sanitization (e.g., `$GITHUB_TOKEN`). If an attacker can control these environment variables, they could potentially perform code injection or other unintended actions.\n    cwe: CWE-88\n    function_names: []\n    filenames:\n      - scripts/pages/releases.sh\n    classification: slightly promising\n\n  - headline: Potential insecure file permissions\n    analysis: |\n      Some scripts in the codebase are creating files without explicitly setting secure file permissions. This could potentially lead to unauthorized access or modification of sensitive files.\n    cwe: CWE-732\n    function_names: []\n    filenames: []\n    classification: not promising\n```",
      "date": "2024-06-14T13:39:43.431783",
      "usage": {
        "prompt_tokens": 5422,
        "completion_tokens": 799,
        "cost": 0.028251
      }
    }
  ],
  "leads": [
    {
      "headline": "Potential command injection vulnerability",
      "analysis": "The cmd/nfpm command seems to be executing shell commands using go run, which can potentially lead to command injection vulnerabilities if user input is passed to these commands without proper sanitization. This could allow an attacker to execute arbitrary commands on the system.\n",
      "classification": "very promising",
      "cwe": "CWE-77",
      "function_names": [
        "main"
      ],
      "filenames": [
        "scripts/cmd_docs.sh",
        "scripts/completions.sh",
        "scripts/manpages.sh"
      ]
    },
    {
      "headline": "Potential race condition in package install/remove scripts",
      "analysis": "The install/remove scripts in testdata/acceptance/scripts and testdata/scripts are executed in a concurrent manner during package installation/removal. If these scripts access shared resources without proper synchronization, it could lead to race conditions and undefined behavior.\n",
      "classification": "slightly promising",
      "cwe": "CWE-362",
      "function_names": [],
      "filenames": [
        "testdata/acceptance/scripts/postinstall.sh",
        "testdata/acceptance/scripts/preinstall.sh",
        "testdata/acceptance/scripts/postupgrade.sh"
      ]
    },
    {
      "headline": "Potential path traversal vulnerability",
      "analysis": "The package scripts might be vulnerable to path traversal attacks if they accept user input for file paths without proper sanitization. An attacker could potentially access or modify files outside the intended directory.\n",
      "classification": "slightly promising",
      "cwe": "CWE-22",
      "function_names": [],
      "filenames": []
    },
    {
      "headline": "Use of unsafe temporary file creation",
      "analysis": "Some scripts in the codebase are creating temporary files using an insecure method (e.g., echo \"Ok\" > /tmp/trigger-proof). This could lead to insecure file operations, race conditions, or symlink attacks if the temporary file is predictable or world-writable.\n",
      "classification": "slightly promising",
      "cwe": "CWE-377",
      "function_names": [],
      "filenames": [
        "testdata/acceptance/scripts/postinstall_trigger.sh"
      ]
    },
    {
      "headline": "Potential environment variable injection vulnerability",
      "analysis": "Some scripts in the codebase are using environment variables without proper sanitization (e.g., $GITHUB_TOKEN). If an attacker can control these environment variables, they could potentially perform code injection or other unintended actions.\n",
      "classification": "slightly promising",
      "cwe": "CWE-88",
      "function_names": [],
      "filenames": [
        "scripts/pages/releases.sh"
      ]
    },
    {
      "headline": "Potential insecure file permissions",
      "analysis": "Some scripts in the codebase are creating files without explicitly setting secure file permissions. This could potentially lead to unauthorized access or modification of sensitive files.\n",
      "classification": "not promising",
      "cwe": "CWE-732",
      "function_names": [],
      "filenames": []
    }
  ],
  "scores": [
    {
      "stats": {
        "fn": 1,
        "tp": 0,
        "fp": 1
      },
      "mapping": {},
      "vuln_dates": {
        "CVE-2023-32698": "2023-05-30T04:15:10"
      },
      "scoring_model": "claude-3-opus-20240229",
      "type": "llm",
      "instruction_template_hash": "245ace12b6361954d0a2"
    }
  ],
  "instruction_template_hash": "10c0163db4740318a544",
  "version": "0.1.0"
}
