{
  "commit": "3dddadbedbceb407f140dfb78964caa3b002cef9",
  "repo_url": "https://github.com/floragunncom/search-guard-kibana-plugin",
  "model": "gpt-4o-2024-05-13",
  "chunk_hashes": [
    "944c8e893f8e89cb9d81"
  ],
  "responses": [
    {
      "content": "```yaml\nleads:\n  - headline: \"Default Cookie Password Set\"\n    analysis: |\n      The configuration file sets a default cookie password `searchguard_cookie_default_password`. Using default passwords for sensitive data can lead to unauthorized access. Attackers could exploit this by gaining access to user sessions.\n    cwe: CWE-798\n    function_names: []\n    filenames:\n      - index.js\n    classification: very promising\n\n  - headline: \"Cookies Transmitted Over Unsecure HTTP\"\n    analysis: |\n      The configuration sets `cookie.secure` to `false` by default, transmitting cookies over an unencrypted HTTP connection. This could allow attackers to intercept cookies and gain unauthorized access to users' sessions and data.\n    cwe: CWE-319\n    function_names: []\n    filenames:\n      - index.js\n    classification: very promising\n\n  - headline: \"Hardcoded S3 API Key\"\n    analysis: |\n      The script `upload_snapshot.sh` implicitly mentions using a `FILESTACK_KEY` for S3 uploads without any validation layer or secure management mechanism. This kind of information leak could help attackers to perform malicious activities using these credentials.\n    cwe: CWE-798\n    function_names: []\n    filenames:\n      - upload_snapshot.sh\n    classification: slightly promising\n\n  - headline: \"Insecure JWT Storage\"\n    analysis: |\n      In both `lib/jwt/headers.js` and `index.js`, there is a lack of secure management and storage for JWT tokens, making them vulnerable to theft, which could then be used by an attacker to impersonate a user and gain unauthorized access.\n    cwe: CWE-319\n    function_names: []\n    filenames:\n      - lib/jwt/headers.js\n      - index.js\n    classification: very promising\n\n  - headline: \"Server-Side Cookie Configuration Insecure\"\n    analysis: |\n      When configuring cookies in `index.js`, the 'isSecure' attribute is set to false, and 'isHttpOnly' is also set to false, which can lead to cookie theft and session hijacking.\n    cwe: CWE-319\n    function_names: []\n    filenames:\n      - index.js\n    classification: very promising\n\n  - headline: \"Cleartext Authentication in HTTP Headers\"\n    analysis: |\n      The basic authentication header `authorization` is created using base64 encoding without any encryption. Base64 is easily decodable and does not provide secure authentication mechanisms.\n    cwe: CWE-319\n    function_names: []\n    filenames:\n      - lib/backend/searchguard.js\n    classification: very promising\n\n  - headline: \"No Rate Limiting on Login Attempts\"\n    analysis: |\n      There is no evidence of rate limiting in the login endpoint, making it vulnerable to brute force attacks where attackers can try numerous username and password combinations until successful.\n    cwe: CWE-307\n    function_names:\n      - handler\n    filenames:\n      - lib/auth/routes.js\n    classification: very promising\n\n  - headline: \"Unvalidated Data in Redirect URL\"\n    analysis: |\n      The `nextUrl` parameter for redirects is taken directly from the query string without validation, which could be exploited for open redirect attacks.\n    cwe: CWE-601\n    function_names: []\n    filenames:\n      - lib/hapi/auth.js\n    classification: slightly promising\n\n  - headline: \"Mismatch Between Configured Kibana Server Usernames in Elasticsearch and Kibana\"\n    analysis: |\n      The script checks for mismatched Kibana server usernames in Elasticsearch and Kibana but does not enforce or prevent operation if a mismatch is detected. This could lead to unexpected multitenancy behavior and possibly data leakage.\n    cwe: CWE-346\n    function_names:\n      - $http.get\n    filenames:\n      - public/apps/multitenancy/multitenancy.js\n    classification: slightly promising\n\n  - headline: \"Weak Session Management\"\n    analysis: |\n      The session validation logic only checks for expiration time but does not perform any additional security validations which could be needed to ensure the integrity and authenticity of the session. This could result in session fixation or hijacking attacks.\n    cwe: CWE-665\n    function_names: []\n    filenames:\n      - lib/session/validate.js\n    classification: slightly promising\n\n  - headline: \"Insecure Upload to S3\"\n    analysis: |\n      The `upload_snapshot.sh` script manages file uploads to S3 without any integrity checks. This could allow an attacker to tamper with or intercept the files being uploaded.\n    cwe: CWE-494\n    function_names: []\n    filenames:\n      - upload_snapshot.sh\n    classification: slightly promising\n```",
      "date": "2024-06-14T13:33:50.145355",
      "usage": {
        "prompt_tokens": 16760,
        "completion_tokens": 961,
        "cost": 0.098215
      }
    }
  ],
  "leads": [
    {
      "headline": "Default Cookie Password Set",
      "analysis": "The configuration file sets a default cookie password searchguard_cookie_default_password. Using default passwords for sensitive data can lead to unauthorized access. Attackers could exploit this by gaining access to user sessions.\n",
      "classification": "very promising",
      "cwe": "CWE-798",
      "function_names": [],
      "filenames": [
        "index.js"
      ]
    },
    {
      "headline": "Cookies Transmitted Over Unsecure HTTP",
      "analysis": "The configuration sets cookie.secure to false by default, transmitting cookies over an unencrypted HTTP connection. This could allow attackers to intercept cookies and gain unauthorized access to users' sessions and data.\n",
      "classification": "very promising",
      "cwe": "CWE-319",
      "function_names": [],
      "filenames": [
        "index.js"
      ]
    },
    {
      "headline": "Hardcoded S3 API Key",
      "analysis": "The script upload_snapshot.sh implicitly mentions using a FILESTACK_KEY for S3 uploads without any validation layer or secure management mechanism. This kind of information leak could help attackers to perform malicious activities using these credentials.\n",
      "classification": "slightly promising",
      "cwe": "CWE-798",
      "function_names": [],
      "filenames": [
        "upload_snapshot.sh"
      ]
    },
    {
      "headline": "Insecure JWT Storage",
      "analysis": "In both lib/jwt/headers.js and index.js, there is a lack of secure management and storage for JWT tokens, making them vulnerable to theft, which could then be used by an attacker to impersonate a user and gain unauthorized access.\n",
      "classification": "very promising",
      "cwe": "CWE-319",
      "function_names": [],
      "filenames": [
        "lib/jwt/headers.js",
        "index.js"
      ]
    },
    {
      "headline": "Server-Side Cookie Configuration Insecure",
      "analysis": "When configuring cookies in index.js, the 'isSecure' attribute is set to false, and 'isHttpOnly' is also set to false, which can lead to cookie theft and session hijacking.\n",
      "classification": "very promising",
      "cwe": "CWE-319",
      "function_names": [],
      "filenames": [
        "index.js"
      ]
    },
    {
      "headline": "Cleartext Authentication in HTTP Headers",
      "analysis": "The basic authentication header authorization is created using base64 encoding without any encryption. Base64 is easily decodable and does not provide secure authentication mechanisms.\n",
      "classification": "very promising",
      "cwe": "CWE-319",
      "function_names": [],
      "filenames": [
        "lib/backend/searchguard.js"
      ]
    },
    {
      "headline": "No Rate Limiting on Login Attempts",
      "analysis": "There is no evidence of rate limiting in the login endpoint, making it vulnerable to brute force attacks where attackers can try numerous username and password combinations until successful.\n",
      "classification": "very promising",
      "cwe": "CWE-307",
      "function_names": [
        "handler"
      ],
      "filenames": [
        "lib/auth/routes.js"
      ]
    },
    {
      "headline": "Unvalidated Data in Redirect URL",
      "analysis": "The nextUrl parameter for redirects is taken directly from the query string without validation, which could be exploited for open redirect attacks.\n",
      "classification": "slightly promising",
      "cwe": "CWE-601",
      "function_names": [],
      "filenames": [
        "lib/hapi/auth.js"
      ]
    },
    {
      "headline": "Mismatch Between Configured Kibana Server Usernames in Elasticsearch and Kibana",
      "analysis": "The script checks for mismatched Kibana server usernames in Elasticsearch and Kibana but does not enforce or prevent operation if a mismatch is detected. This could lead to unexpected multitenancy behavior and possibly data leakage.\n",
      "classification": "slightly promising",
      "cwe": "CWE-346",
      "function_names": [
        "$http.get"
      ],
      "filenames": [
        "public/apps/multitenancy/multitenancy.js"
      ]
    },
    {
      "headline": "Weak Session Management",
      "analysis": "The session validation logic only checks for expiration time but does not perform any additional security validations which could be needed to ensure the integrity and authenticity of the session. This could result in session fixation or hijacking attacks.\n",
      "classification": "slightly promising",
      "cwe": "CWE-665",
      "function_names": [],
      "filenames": [
        "lib/session/validate.js"
      ]
    },
    {
      "headline": "Insecure Upload to S3",
      "analysis": "The upload_snapshot.sh script manages file uploads to S3 without any integrity checks. This could allow an attacker to tamper with or intercept the files being uploaded.\n",
      "classification": "slightly promising",
      "cwe": "CWE-494",
      "function_names": [],
      "filenames": [
        "upload_snapshot.sh"
      ]
    }
  ],
  "scores": [
    {
      "stats": {
        "fn": 3,
        "tp": 0,
        "fp": 6
      },
      "mapping": {},
      "vuln_dates": {
        "CVE-2019-13422": "2019-08-23T14:15:11",
        "CVE-2019-13423": "2019-08-23T14:15:11",
        "CVE-2018-20698": "2019-04-09T18:29:00"
      },
      "scoring_model": "claude-3-opus-20240229",
      "type": "llm",
      "instruction_template_hash": "245ace12b6361954d0a2"
    }
  ],
  "instruction_template_hash": "10c0163db4740318a544",
  "version": "0.1.0"
}
