{
  "commit": "965591c4a2db2f22b38a415e422f38bddb6cf122",
  "repo_url": "https://github.com/nt1m/livemarks",
  "model": "claude-3-5-sonnet-20240620",
  "chunk_hashes": [
    "133d078375a8f28aa3f3"
  ],
  "responses": [
    {
      "content": "```yaml\nleads:\n  - headline: Insecure Input Handling\n    analysis: |\n      The extension accepts and processes user input without proper validation or sanitization in several places. For example, in settings.js, the importOPML function parses XML data from a user-supplied file without any sanitization. This could allow an attacker to inject malicious XML payloads. Similarly, the subscribe.js file accepts a user-provided feed URL and passes it directly to FeedParser.getFeed() without validation. Proper input validation and sanitization should be implemented to prevent potential injection attacks.\n    cwe: CWE-20\n    function_names:\n      - importOPML\n      - main\n    filenames: \n      - pages/settings/settings.js\n      - pages/subscribe/subscribe.js\n    classification: very promising\n\n  - headline: Potential Cross-Site Scripting (XSS) \n    analysis: |\n      The extension renders HTML content from feed items directly into the page without proper sanitization. In reader.js, the getPreviewHTML function uses innerHTML to insert feed item descriptions, which could contain malicious scripts. This allows potential XSS attacks if a malicious feed is processed. The extension should use safe DOM manipulation methods or a library like DOMPurify to sanitize HTML content before rendering.\n    cwe: CWE-79\n    function_names:\n      - getPreviewHTML\n    filenames:\n      - pages/reader/reader.js\n    classification: very promising\n\n  - headline: Insufficient URL Validation\n    analysis: |\n      The extension does not properly validate URLs in several places. For example, in subscribe.js, the feedUrl is only checked using a basic URL constructor without any additional validation. This could allow attackers to inject malicious URLs. More robust URL validation should be implemented, including checking for allowed protocols and domains.\n    cwe: CWE-20\n    function_names:\n      - main\n    filenames:\n      - pages/subscribe/subscribe.js\n    classification: slightly promising\n\n  - headline: Potential Open Redirect\n    analysis: |\n      In popup.js, the preview function opens a new tab with a URL constructed from user-provided input without validation. This could potentially be exploited for open redirects if an attacker can control the feed_url parameter. The URL should be properly validated before being used to open a new tab.\n    cwe: CWE-601\n    function_names:\n      - preview\n    filenames:\n      - popup/popup.js\n    classification: slightly promising\n\n  - headline: Insecure Data Storage\n    analysis: |\n      The extension stores sensitive data like feed URLs and bookmark information using the browser's storage API without encryption. While the browser's storage is generally considered secure, encrypting sensitive data before storage would add an extra layer of protection against potential local attacks or data leaks.\n    cwe: CWE-312\n    function_names:\n      - add\n      - edit\n    filenames:\n      - shared/livemark-store.js\n    classification: slightly promising\n```",
      "date": "2024-07-08T04:47:26.235742",
      "usage": {
        "prompt_tokens": 22901,
        "completion_tokens": 699,
        "cost": 0.079188
      }
    }
  ],
  "leads": [
    {
      "headline": "Insecure Input Handling",
      "analysis": "The extension accepts and processes user input without proper validation or sanitization in several places. For example, in settings.js, the importOPML function parses XML data from a user-supplied file without any sanitization. This could allow an attacker to inject malicious XML payloads. Similarly, the subscribe.js file accepts a user-provided feed URL and passes it directly to FeedParser.getFeed() without validation. Proper input validation and sanitization should be implemented to prevent potential injection attacks.\n",
      "classification": "very promising",
      "cwe": "CWE-20",
      "function_names": [
        "importOPML",
        "main"
      ],
      "filenames": [
        "pages/settings/settings.js",
        "pages/subscribe/subscribe.js"
      ]
    },
    {
      "headline": "Potential Cross-Site Scripting (XSS)",
      "analysis": "The extension renders HTML content from feed items directly into the page without proper sanitization. In reader.js, the getPreviewHTML function uses innerHTML to insert feed item descriptions, which could contain malicious scripts. This allows potential XSS attacks if a malicious feed is processed. The extension should use safe DOM manipulation methods or a library like DOMPurify to sanitize HTML content before rendering.\n",
      "classification": "very promising",
      "cwe": "CWE-79",
      "function_names": [
        "getPreviewHTML"
      ],
      "filenames": [
        "pages/reader/reader.js"
      ]
    },
    {
      "headline": "Insufficient URL Validation",
      "analysis": "The extension does not properly validate URLs in several places. For example, in subscribe.js, the feedUrl is only checked using a basic URL constructor without any additional validation. This could allow attackers to inject malicious URLs. More robust URL validation should be implemented, including checking for allowed protocols and domains.\n",
      "classification": "slightly promising",
      "cwe": "CWE-20",
      "function_names": [
        "main"
      ],
      "filenames": [
        "pages/subscribe/subscribe.js"
      ]
    },
    {
      "headline": "Potential Open Redirect",
      "analysis": "In popup.js, the preview function opens a new tab with a URL constructed from user-provided input without validation. This could potentially be exploited for open redirects if an attacker can control the feed_url parameter. The URL should be properly validated before being used to open a new tab.\n",
      "classification": "slightly promising",
      "cwe": "CWE-601",
      "function_names": [
        "preview"
      ],
      "filenames": [
        "popup/popup.js"
      ]
    },
    {
      "headline": "Insecure Data Storage",
      "analysis": "The extension stores sensitive data like feed URLs and bookmark information using the browser's storage API without encryption. While the browser's storage is generally considered secure, encrypting sensitive data before storage would add an extra layer of protection against potential local attacks or data leaks.\n",
      "classification": "slightly promising",
      "cwe": "CWE-312",
      "function_names": [
        "add",
        "edit"
      ],
      "filenames": [
        "shared/livemark-store.js"
      ]
    }
  ],
  "scores": [
    {
      "stats": {
        "fn": 1,
        "tp": 0,
        "fp": 2
      },
      "mapping": {},
      "vuln_dates": {
        "CVE-2024-30252": "2024-04-04T19:15:08"
      },
      "scoring_model": "claude-3-5-sonnet-20240620",
      "type": "llm",
      "instruction_template_hash": "245ace12b6361954d0a2"
    }
  ],
  "instruction_template_hash": "10c0163db4740318a544",
  "version": "0.1.0"
}
