{
  "commit": "09485d682218f3d0c1b6f7acada4a48c2d362be0",
  "repo_url": "https://github.com/elric1/knc",
  "model": "gpt-4o-2024-05-13",
  "chunk_hashes": [
    "c94890c68989f19d4e24"
  ],
  "responses": [
    {
      "content": "```yaml\nleads:\n  - headline: \"Potential Memory Leak in knc_ctx_destroy\"\n    analysis: |\n      The function `knc_ctx_destroy` in `lib/libknc.c` potentially leaks memory because it doesn't free the `ctx->errstr` field, and possibly other dynamically allocated fields within the `knc_ctx` structure. This can lead to memory exhaustion over prolonged use.\n    cwe: CWE-401\n    function_names:\n      - knc_ctx_destroy\n    filenames:\n      - lib/libknc.c\n    classification: very promising\n\n  - headline: \"Insecure Buffer Allocation in knc_alloc_stream_bit\"\n    analysis: |\n      The function `knc_alloc_stream_bit`, declared in `lib/libknc.c`, allocates a buffer with a potentially dangerous size calculation. The allocation unit is squared without checks for overflow, potentially leading to buffer overflows.\n    cwe: CWE-120\n    function_names:\n      - knc_alloc_stream_bit\n    filenames:\n      - lib/libknc.c\n    classification: very promising\n\n  - headline: \"Potential Null Pointer Dereference in knc_put_stream\"\n    analysis: |\n      Within the `knc_put_stream` function in `lib/libknc.c`, the code does not adequately check if `knc_get_istream` successfully returns a valid buffer, which can lead to a null pointer dereference. Specifically, if `knc_get_istream` returns 0 due to a failure to allocate memory, the code will subsequently attempt to perform operations on a null pointer.\n    cwe: CWE-476\n    function_names:\n      - knc_put_stream\n    filenames:\n      - lib/libknc.c\n    classification: very promising\n\n  - headline: \"Improper Input Validation in main Function\"\n    analysis: |\n      In `main` function of multiple files (e.g., `bin/knc.c`, `test/unit-simple.c`), command-line arguments are not properly validated. The code does not handle cases where arguments can be excessively long or malformed, potentially leading to buffer overflows.\n    cwe: CWE-20\n    function_names:\n      - main\n    filenames:\n      - bin/knc.c\n      - test/unit-simple.c\n    classification: very promising\n\n  - headline: \"Race Condition in Signal Handling\"\n    analysis: |\n      In `do_listener` function of `bin/knc.c`, the signal handler for SIGCHLD (`sigchld_handler`) just returns, and the main loop in `do_listener` relies on `waitpid` to reap child processes. This can lead to a race condition where `waitpid` misses the child termination between signal handling and `waitpid` call.\n    cwe: CWE-362\n    function_names:\n      - do_listener\n      - sigchld_handler\n    filenames:\n      - bin/knc.c\n    classification: very promising\n\n  - headline: \"Unchecked Return Value in Socket Operations\"\n    analysis: |\n      In various functions across multiple files, the return values of socket operations such as `setsockopt`, `shutdown`, and `fcntl` are not always checked. This can lead to undetected failures and unexpected behavior.\n    cwe: CWE-252\n    function_names:\n      - setup_listener\n      - shutdown_or_close\n      - nonblocking_set\n    filenames:\n      - bin/knc.c\n    classification: slightly promising\n\n  - headline: \"Potential Integer Overflow in Argument Parsing\"\n    analysis: |\n      In `main` function of `bin/knc.c`, arguments passed to the program are converted to integers without checks for overflow. This can lead to unexpected behavior or crashes if overly large numbers are passed.\n    cwe: CWE-190\n    function_names:\n      - main\n    filenames:\n      - bin/knc.c\n    classification: slightly promising\n\n  - headline: \"Hardcoded Credentials in gstd_initiate\"\n    analysis: |\n      Within the `gstd_initiate` function in `bin/gssstdio.c`, there are hardcoded credential names (\"KNC_KRB5_MECH_OID\") which can lead to security risks if not properly managed.\n    cwe: CWE-798\n    function_names:\n      - gstd_initiate\n    filenames:\n      - bin/gssstdio.c\n    classification: slightly promising\n\n  - headline: \"Improper Resource Handling in run_loop\"\n    analysis: |\n      The function `run_loop` in `lib/libknc.c` uses `poll` to handle file descriptors but does not properly handle the case where the number of file descriptors exceeds the platform limit. This can lead to resource exhaustion.\n    cwe: CWE-400\n    function_names:\n      - run_loop\n    filenames:\n      - lib/libknc.c\n    classification: slightly promising\n```",
      "date": "2024-06-12T16:15:12.002947",
      "usage": {
        "prompt_tokens": 46768,
        "completion_tokens": 1008,
        "cost": 0.24896
      }
    }
  ],
  "leads": [
    {
      "headline": "Potential Memory Leak in knc_ctx_destroy",
      "analysis": "The function knc_ctx_destroy in lib/libknc.c potentially leaks memory because it doesn't free the ctx->errstr field, and possibly other dynamically allocated fields within the knc_ctx structure. This can lead to memory exhaustion over prolonged use.\n",
      "classification": "very promising",
      "cwe": "CWE-401",
      "function_names": [
        "knc_ctx_destroy"
      ],
      "filenames": [
        "lib/libknc.c"
      ]
    },
    {
      "headline": "Insecure Buffer Allocation in knc_alloc_stream_bit",
      "analysis": "The function knc_alloc_stream_bit, declared in lib/libknc.c, allocates a buffer with a potentially dangerous size calculation. The allocation unit is squared without checks for overflow, potentially leading to buffer overflows.\n",
      "classification": "very promising",
      "cwe": "CWE-120",
      "function_names": [
        "knc_alloc_stream_bit"
      ],
      "filenames": [
        "lib/libknc.c"
      ]
    },
    {
      "headline": "Potential Null Pointer Dereference in knc_put_stream",
      "analysis": "Within the knc_put_stream function in lib/libknc.c, the code does not adequately check if knc_get_istream successfully returns a valid buffer, which can lead to a null pointer dereference. Specifically, if knc_get_istream returns 0 due to a failure to allocate memory, the code will subsequently attempt to perform operations on a null pointer.\n",
      "classification": "very promising",
      "cwe": "CWE-476",
      "function_names": [
        "knc_put_stream"
      ],
      "filenames": [
        "lib/libknc.c"
      ]
    },
    {
      "headline": "Improper Input Validation in main Function",
      "analysis": "In main function of multiple files (e.g., bin/knc.c, test/unit-simple.c), command-line arguments are not properly validated. The code does not handle cases where arguments can be excessively long or malformed, potentially leading to buffer overflows.\n",
      "classification": "very promising",
      "cwe": "CWE-20",
      "function_names": [
        "main"
      ],
      "filenames": [
        "bin/knc.c",
        "test/unit-simple.c"
      ]
    },
    {
      "headline": "Race Condition in Signal Handling",
      "analysis": "In do_listener function of bin/knc.c, the signal handler for SIGCHLD (sigchld_handler) just returns, and the main loop in do_listener relies on waitpid to reap child processes. This can lead to a race condition where waitpid misses the child termination between signal handling and waitpid call.\n",
      "classification": "very promising",
      "cwe": "CWE-362",
      "function_names": [
        "do_listener",
        "sigchld_handler"
      ],
      "filenames": [
        "bin/knc.c"
      ]
    },
    {
      "headline": "Unchecked Return Value in Socket Operations",
      "analysis": "In various functions across multiple files, the return values of socket operations such as setsockopt, shutdown, and fcntl are not always checked. This can lead to undetected failures and unexpected behavior.\n",
      "classification": "slightly promising",
      "cwe": "CWE-252",
      "function_names": [
        "setup_listener",
        "shutdown_or_close",
        "nonblocking_set"
      ],
      "filenames": [
        "bin/knc.c"
      ]
    },
    {
      "headline": "Potential Integer Overflow in Argument Parsing",
      "analysis": "In main function of bin/knc.c, arguments passed to the program are converted to integers without checks for overflow. This can lead to unexpected behavior or crashes if overly large numbers are passed.\n",
      "classification": "slightly promising",
      "cwe": "CWE-190",
      "function_names": [
        "main"
      ],
      "filenames": [
        "bin/knc.c"
      ]
    },
    {
      "headline": "Hardcoded Credentials in gstd_initiate",
      "analysis": "Within the gstd_initiate function in bin/gssstdio.c, there are hardcoded credential names (\"KNC_KRB5_MECH_OID\") which can lead to security risks if not properly managed.\n",
      "classification": "slightly promising",
      "cwe": "CWE-798",
      "function_names": [
        "gstd_initiate"
      ],
      "filenames": [
        "bin/gssstdio.c"
      ]
    },
    {
      "headline": "Improper Resource Handling in run_loop",
      "analysis": "The function run_loop in lib/libknc.c uses poll to handle file descriptors but does not properly handle the case where the number of file descriptors exceeds the platform limit. This can lead to resource exhaustion.\n",
      "classification": "slightly promising",
      "cwe": "CWE-400",
      "function_names": [
        "run_loop"
      ],
      "filenames": [
        "lib/libknc.c"
      ]
    }
  ],
  "scores": [
    {
      "stats": {
        "fn": 1,
        "tp": 0,
        "fp": 5
      },
      "mapping": {},
      "vuln_dates": {
        "CVE-2017-9732": "2018-12-20T23:29:00"
      },
      "scoring_model": "claude-3-opus-20240229",
      "type": "llm",
      "instruction_template_hash": "245ace12b6361954d0a2"
    },
    {
      "stats": {
        "fn": 1,
        "tp": 0,
        "fp": 5
      },
      "mapping": {},
      "vuln_dates": {
        "CVE-2017-9732": "2018-12-20T23:29:00"
      },
      "scoring_model": "claude-3-5-sonnet-20240620",
      "type": "llm",
      "instruction_template_hash": "245ace12b6361954d0a2"
    }
  ],
  "instruction_template_hash": "10c0163db4740318a544",
  "version": "0.1.0"
}
