{
  "commit": "1fe15cd707fa05bd558d6bb5b6c489d483179ace",
  "repo_url": "https://github.com/trustedsec/trevorc2",
  "model": "claude-3-sonnet-20240229",
  "chunk_hashes": [
    "0ab784f42c75eada2d72"
  ],
  "responses": [
    {
      "content": "```yaml\nleads:\n  - headline: Insecure Transmission of Sensitive Information\n    analysis: |\n      The TrevorC2 client and server communicate over plaintext HTTP or HTTPS (if enabled) without any encryption of the transmitted data. This means that any sensitive information exchanged between the client and server, such as commands, command output, and encryption keys, can be intercepted and read by an attacker on the network. This exposes the entire communication channel and defeats the purpose of a covert command and control channel.\n    cwe: CWE-319\n    function_names:\n      - connect_trevor\n      - main\n    filenames:\n      - trevorc2_client.py\n      - trevorc2_client.java\n      - trevorc2_server.py\n    classification: very promising\n\n  - headline: Use of Hardcoded Credentials\n    analysis: |\n      The TrevorC2 client and server use a hardcoded encryption key (CIPHER) for encrypting and decrypting their communication. This key is the same across all instances of the client and server, and if compromised, would allow an attacker to decrypt the entire communication channel. Hardcoded credentials or encryption keys are a security risk as they cannot be easily changed and are often reused across multiple systems or deployments.\n    cwe: CWE-798\n    function_names:\n      - __init__\n    filenames:\n      - trevorc2_client.py\n      - trevorc2_client.java\n      - trevorc2_server.py\n    classification: very promising\n\n  - headline: Insecure Cryptographic Algorithm\n    analysis: |\n      The TrevorC2 client and server use the AES encryption algorithm in CBC mode for encrypting their communication. While AES is a secure algorithm, the implementation details are not provided, and the use of CBC mode without proper initialization vector (IV) management can be insecure and vulnerable to chosen-plaintext attacks. Additionally, the AES key is derived from a SHA-256 hash of the hardcoded CIPHER key, which may not provide sufficient entropy for the key if the CIPHER is known or guessable.\n    cwe: CWE-327\n    function_names:\n      - __init__\n      - encrypt\n      - decrypt\n    filenames:\n      - trevorc2_client.py\n      - trevorc2_client.java\n      - trevorc2_server.py\n    classification: slightly promising\n\n  - headline: Insecure Pseudo-Random Number Generation\n    analysis: |\n      The TrevorC2 client and server use insecure or predictable random number generation for various purposes, such as generating session IDs and initialization vectors for encryption. In the Python client, the `random` module is used, which is a pseudorandom number generator (PRNG) that is not designed for cryptographic purposes. In the Java client, the default `Random` class is used, which is also not a cryptographically secure PRNG. The use of insecure PRNGs can lead to predictable values, which can compromise the security of encryption, session IDs, and other security mechanisms.\n    cwe: CWE-338\n    function_names:\n      - randomString\n      - random_interval\n    filenames:\n      - trevorc2_client.py\n      - trevorc2_client.java\n      - trevorc2_server.py\n    classification: slightly promising\n\n  - headline: Improper Input Validation\n    analysis: |\n      The TrevorC2 server appears to lack proper input validation for various user-supplied data, such as the `X-Forwarded-For` header used for obtaining the client's IP address. While the server uses the `bleach` library to sanitize this input, it is not clear if this sanitization is sufficient or applied consistently across all input sources. Improper input validation can lead to various injection vulnerabilities, such as cross-site scripting (XSS) or code injection, if user-supplied data is not properly sanitized before being used in dangerous contexts.\n    cwe: CWE-20\n    function_names: []\n    filenames:\n      - trevorc2_server.py\n    classification: slightly promising\n\n  - headline: Exposure of Sensitive Information\n    analysis: |\n      The TrevorC2 server logs incoming requests, including the client's IP address and hostname. While this logging may be intended for debugging or monitoring purposes, it can lead to the exposure of sensitive information if the log files are accessible to unauthorized parties or not properly secured. Additionally, the server appears to write received command output to files named `received_<sessionid>.txt` in the `clone_site` directory, which could also expose sensitive information if this directory is not properly secured.\n    cwe: CWE-200\n    function_names: []\n    filenames:\n      - trevorc2_server.py\n    classification: slightly promising\n\n  - headline: Lack of Proper Authentication and Authorization\n    analysis: |\n      The TrevorC2 client and server do not appear to implement any form of authentication or authorization mechanisms. The server generates a random session ID and assigns it to the client via a cookie, but there is no verification of the client's identity or authorization to execute commands on the server. This lack of authentication and authorization could potentially allow unauthorized parties to gain control of the command and control channel or execute arbitrary commands on the server.\n    cwe: CWE-287\n    function_names: []\n    filenames:\n      - trevorc2_client.py\n      - trevorc2_client.java\n      - trevorc2_server.py\n    classification: very promising\n```",
      "date": "2024-06-13T17:19:06.711154",
      "usage": {
        "prompt_tokens": 14643,
        "completion_tokens": 1306,
        "cost": 0.063519
      }
    }
  ],
  "leads": [
    {
      "headline": "Insecure Transmission of Sensitive Information",
      "analysis": "The TrevorC2 client and server communicate over plaintext HTTP or HTTPS (if enabled) without any encryption of the transmitted data. This means that any sensitive information exchanged between the client and server, such as commands, command output, and encryption keys, can be intercepted and read by an attacker on the network. This exposes the entire communication channel and defeats the purpose of a covert command and control channel.\n",
      "classification": "very promising",
      "cwe": "CWE-319",
      "function_names": [
        "connect_trevor",
        "main"
      ],
      "filenames": [
        "trevorc2_client.py",
        "trevorc2_client.java",
        "trevorc2_server.py"
      ]
    },
    {
      "headline": "Use of Hardcoded Credentials",
      "analysis": "The TrevorC2 client and server use a hardcoded encryption key (CIPHER) for encrypting and decrypting their communication. This key is the same across all instances of the client and server, and if compromised, would allow an attacker to decrypt the entire communication channel. Hardcoded credentials or encryption keys are a security risk as they cannot be easily changed and are often reused across multiple systems or deployments.\n",
      "classification": "very promising",
      "cwe": "CWE-798",
      "function_names": [
        "__init__"
      ],
      "filenames": [
        "trevorc2_client.py",
        "trevorc2_client.java",
        "trevorc2_server.py"
      ]
    },
    {
      "headline": "Insecure Cryptographic Algorithm",
      "analysis": "The TrevorC2 client and server use the AES encryption algorithm in CBC mode for encrypting their communication. While AES is a secure algorithm, the implementation details are not provided, and the use of CBC mode without proper initialization vector (IV) management can be insecure and vulnerable to chosen-plaintext attacks. Additionally, the AES key is derived from a SHA-256 hash of the hardcoded CIPHER key, which may not provide sufficient entropy for the key if the CIPHER is known or guessable.\n",
      "classification": "slightly promising",
      "cwe": "CWE-327",
      "function_names": [
        "__init__",
        "encrypt",
        "decrypt"
      ],
      "filenames": [
        "trevorc2_client.py",
        "trevorc2_client.java",
        "trevorc2_server.py"
      ]
    },
    {
      "headline": "Insecure Pseudo-Random Number Generation",
      "analysis": "The TrevorC2 client and server use insecure or predictable random number generation for various purposes, such as generating session IDs and initialization vectors for encryption. In the Python client, the random module is used, which is a pseudorandom number generator (PRNG) that is not designed for cryptographic purposes. In the Java client, the default Random class is used, which is also not a cryptographically secure PRNG. The use of insecure PRNGs can lead to predictable values, which can compromise the security of encryption, session IDs, and other security mechanisms.\n",
      "classification": "slightly promising",
      "cwe": "CWE-338",
      "function_names": [
        "randomString",
        "random_interval"
      ],
      "filenames": [
        "trevorc2_client.py",
        "trevorc2_client.java",
        "trevorc2_server.py"
      ]
    },
    {
      "headline": "Improper Input Validation",
      "analysis": "The TrevorC2 server appears to lack proper input validation for various user-supplied data, such as the X-Forwarded-For header used for obtaining the client's IP address. While the server uses the bleach library to sanitize this input, it is not clear if this sanitization is sufficient or applied consistently across all input sources. Improper input validation can lead to various injection vulnerabilities, such as cross-site scripting (XSS) or code injection, if user-supplied data is not properly sanitized before being used in dangerous contexts.\n",
      "classification": "slightly promising",
      "cwe": "CWE-20",
      "function_names": [],
      "filenames": [
        "trevorc2_server.py"
      ]
    },
    {
      "headline": "Exposure of Sensitive Information",
      "analysis": "The TrevorC2 server logs incoming requests, including the client's IP address and hostname. While this logging may be intended for debugging or monitoring purposes, it can lead to the exposure of sensitive information if the log files are accessible to unauthorized parties or not properly secured. Additionally, the server appears to write received command output to files named received_<sessionid>.txt in the clone_site directory, which could also expose sensitive information if this directory is not properly secured.\n",
      "classification": "slightly promising",
      "cwe": "CWE-200",
      "function_names": [],
      "filenames": [
        "trevorc2_server.py"
      ]
    },
    {
      "headline": "Lack of Proper Authentication and Authorization",
      "analysis": "The TrevorC2 client and server do not appear to implement any form of authentication or authorization mechanisms. The server generates a random session ID and assigns it to the client via a cookie, but there is no verification of the client's identity or authorization to execute commands on the server. This lack of authentication and authorization could potentially allow unauthorized parties to gain control of the command and control channel or execute arbitrary commands on the server.\n",
      "classification": "very promising",
      "cwe": "CWE-287",
      "function_names": [],
      "filenames": [
        "trevorc2_client.py",
        "trevorc2_client.java",
        "trevorc2_server.py"
      ]
    }
  ],
  "scores": [
    {
      "stats": {
        "fn": 1,
        "tp": 0,
        "fp": 3
      },
      "mapping": {},
      "vuln_dates": {
        "CVE-2019-18850": "2019-12-04T13:15:10"
      },
      "scoring_model": "claude-3-opus-20240229",
      "type": "llm",
      "instruction_template_hash": "245ace12b6361954d0a2"
    },
    {
      "stats": {
        "fn": 1,
        "tp": 0,
        "fp": 3
      },
      "mapping": {},
      "vuln_dates": {
        "CVE-2019-18850": "2019-12-04T13:15:10"
      },
      "scoring_model": "claude-3-5-sonnet-20240620",
      "type": "llm",
      "instruction_template_hash": "245ace12b6361954d0a2"
    }
  ],
  "instruction_template_hash": "10c0163db4740318a544",
  "version": "0.1.0"
}
