{
  "commit": "2423fee143459247c6b961beffed4c13b31c2a3b",
  "repo_url": "https://github.com/weaveworks/vscode-gitops-tools",
  "model": "gpt-4o-2024-05-13",
  "chunk_hashes": [
    "52539c216eaa060bbac4"
  ],
  "responses": [
    {
      "content": "```yaml\nleads:\n  - headline: Potential Command Injection Vulnerability in Shell Commands\n    analysis: |\n      The `shell.execWithOutput` function in multiple parts of the codebase potentially allows for command injection. Commands like `git clone`, `flux create source git`, and similar can be influenced by user inputs (e.g., URLs, branches, SSH keys) which might not be sanitized properly. If an attacker can manipulate these inputs, they could inject and execute arbitrary shell commands.\n    cwe: CWE-77\n    function_names:\n      - shell.execWithOutput\n    filenames:\n      - src/install.ts\n      - src/commands/pullGitRepository.ts\n      - src/commands/createSource.ts\n    classification: very promising\n\n  - headline: Insecure Randomness in Encryption Keys\n    analysis: |\n      In `createSourceGitGenericCluster`, when handling Azure DevOps repositories, the `sshKeyAlgorithm` is switched to 'rsa'. However, there is no mention of proper key generation parameters, and it might rely on defaults that are insecure. The randomness and security of the keys are critical in SSH algorithms.\n    cwe: CWE-330\n    function_names:\n      - createSourceGitGenericCluster\n    filenames:\n      - src/commands/createSource.ts\n    classification: slightly promising\n\n  - headline: Hardcoded Sensitive Information in Telemetry Initialization\n    analysis: |\n      The API key used for telemetry initialization in `Telemetry.constructor` appears to be a reversed string within the source code. This method of hiding sensitive information is inadequate and an attacker can easily reverse it to access the key.\n    cwe: CWE-798\n    function_names:\n      - Telemetry.constructor\n    filenames:\n      - src/telemetry.ts\n    classification: very promising\n\n  - headline: Potential Directory Traversal in File System Operations\n    analysis: |\n      Functions that handle file and directory paths, such as in the `downloadFile`, `unzipFile`, and `moveFile` methods, might be vulnerable to directory traversal attacks. Without proper sanitization, an attacker could manipulate file paths to access restricted parts of the filesystem.\n    cwe: CWE-22\n    function_names:\n      - downloadFile\n      - unzipFile\n      - moveFile\n    filenames:\n      - src/utils/fsUtils.ts\n    classification: very promising\n\n  - headline: Weak Error Handling and Logging Revealing Sensitive Information\n    analysis: |\n      Error messages in functions like `execWithOutput` and other shell-related executions often include detailed error messages from the shell. These error messages can reveal sensitive paths, configurations, or potentially provide attackers with information to fine-tune their exploits.\n    cwe: CWE-209\n    function_names:\n      - shell.execWithOutput\n    filenames:\n      - src/shell.ts\n      - src/commands/pullGitRepository.ts\n    classification: slightly promising\n\n  - headline: Inadequate Validation of Input Data Parameters\n    analysis: |\n      Throughout the codebase, particularly in commands handling user inputs for URLs, paths, and other parameters, there's a lack of robust validation. This can lead to various vulnerabilities including injections, path traversals, and more. The code relies on several unchecked user inputs which can be manipulated.\n    cwe: CWE-20\n    function_names:\n      - createGitRepositoryGenericCluster\n      - enableDisableGitOps\n    filenames:\n      - src/commands/createSource.ts\n      - src/commands/enableDisableGitOps.ts\n    classification: slightly promising\n```",
      "date": "2024-06-13T18:06:02.912440",
      "usage": {
        "prompt_tokens": 82297,
        "completion_tokens": 728,
        "cost": 0.422405
      }
    }
  ],
  "leads": [
    {
      "headline": "Potential Command Injection Vulnerability in Shell Commands",
      "analysis": "The shell.execWithOutput function in multiple parts of the codebase potentially allows for command injection. Commands like git clone, flux create source git, and similar can be influenced by user inputs (e.g., URLs, branches, SSH keys) which might not be sanitized properly. If an attacker can manipulate these inputs, they could inject and execute arbitrary shell commands.\n",
      "classification": "very promising",
      "cwe": "CWE-77",
      "function_names": [
        "shell.execWithOutput"
      ],
      "filenames": [
        "src/install.ts",
        "src/commands/pullGitRepository.ts",
        "src/commands/createSource.ts"
      ]
    },
    {
      "headline": "Insecure Randomness in Encryption Keys",
      "analysis": "In createSourceGitGenericCluster, when handling Azure DevOps repositories, the sshKeyAlgorithm is switched to 'rsa'. However, there is no mention of proper key generation parameters, and it might rely on defaults that are insecure. The randomness and security of the keys are critical in SSH algorithms.\n",
      "classification": "slightly promising",
      "cwe": "CWE-330",
      "function_names": [
        "createSourceGitGenericCluster"
      ],
      "filenames": [
        "src/commands/createSource.ts"
      ]
    },
    {
      "headline": "Hardcoded Sensitive Information in Telemetry Initialization",
      "analysis": "The API key used for telemetry initialization in Telemetry.constructor appears to be a reversed string within the source code. This method of hiding sensitive information is inadequate and an attacker can easily reverse it to access the key.\n",
      "classification": "very promising",
      "cwe": "CWE-798",
      "function_names": [
        "Telemetry.constructor"
      ],
      "filenames": [
        "src/telemetry.ts"
      ]
    },
    {
      "headline": "Potential Directory Traversal in File System Operations",
      "analysis": "Functions that handle file and directory paths, such as in the downloadFile, unzipFile, and moveFile methods, might be vulnerable to directory traversal attacks. Without proper sanitization, an attacker could manipulate file paths to access restricted parts of the filesystem.\n",
      "classification": "very promising",
      "cwe": "CWE-22",
      "function_names": [
        "downloadFile",
        "unzipFile",
        "moveFile"
      ],
      "filenames": [
        "src/utils/fsUtils.ts"
      ]
    },
    {
      "headline": "Weak Error Handling and Logging Revealing Sensitive Information",
      "analysis": "Error messages in functions like execWithOutput and other shell-related executions often include detailed error messages from the shell. These error messages can reveal sensitive paths, configurations, or potentially provide attackers with information to fine-tune their exploits.\n",
      "classification": "slightly promising",
      "cwe": "CWE-209",
      "function_names": [
        "shell.execWithOutput"
      ],
      "filenames": [
        "src/shell.ts",
        "src/commands/pullGitRepository.ts"
      ]
    },
    {
      "headline": "Inadequate Validation of Input Data Parameters",
      "analysis": "Throughout the codebase, particularly in commands handling user inputs for URLs, paths, and other parameters, there's a lack of robust validation. This can lead to various vulnerabilities including injections, path traversals, and more. The code relies on several unchecked user inputs which can be manipulated.\n",
      "classification": "slightly promising",
      "cwe": "CWE-20",
      "function_names": [
        "createGitRepositoryGenericCluster",
        "enableDisableGitOps"
      ],
      "filenames": [
        "src/commands/createSource.ts",
        "src/commands/enableDisableGitOps.ts"
      ]
    }
  ],
  "scores": [
    {
      "stats": {
        "fn": 1,
        "tp": 0,
        "fp": 3
      },
      "mapping": {},
      "vuln_dates": {
        "CVE-2022-35976": "2022-08-18T19:15:14"
      },
      "scoring_model": "claude-3-opus-20240229",
      "type": "llm",
      "instruction_template_hash": "245ace12b6361954d0a2"
    }
  ],
  "instruction_template_hash": "10c0163db4740318a544",
  "version": "0.1.0"
}
