{
  "commit": "3a97ea156d07aaccca101ed8f0a1606eea8dfc2d",
  "repo_url": "https://github.com/felixrieseberg/windows-build-tools",
  "model": "gpt-4o-2024-05-13",
  "chunk_hashes": [
    "4e55df63c81c07438dd3"
  ],
  "responses": [
    {
      "content": "```yaml\nleads:\n  - headline: \"Weak SSL/TLS Configuration in HTTP Requests\"\n    analysis: |\n      In the `downloadTools` function of `src/download.js`, the SSL/TLS validation is disabled by setting `strictSSL: false` in the nugget options. This might allow MITM (Man-in-the-Middle) attacks where an attacker could intercept and manipulate the data being downloaded. Disabling SSL/TLS validation severely undermines the security measures provided by HTTPS, potentially leading to unauthorized code execution or manipulation.\n    cwe: CWE-295\n    function_names:\n      - downloadTools\n    filenames:\n      - src/download.js\n    classification: very promising\n\n  - headline: \"Hardcoded URLs for Software Downloads\"\n    analysis: |\n      The source files `src/constants.js` and `src/download.js` contain hardcoded URLs for downloading software packages (e.g., Visual Studio Build Tools and Python installer). These URLs are not validated for authenticity or integrity, allowing potential attackers to substitute the legitimate download URLs with malicious ones. This could lead to the download and execution of malicious code on the victim's machine.\n    cwe: CWE-494\n    function_names: []\n    filenames:\n      - src/constants.js\n      - src/download.js\n    classification: very promising\n\n  - headline: \"Uncaught Exceptions Leading to Weak Error Handling\"\n    analysis: |\n      In various parts of the codebase, especially in `utils.js`, there are try-catch blocks that simply log errors to the console without taking appropriate actions to handle the exceptions. This may lead to file system inconsistencies or a false sense of security if the user believes the operations were successful. Instances can be found in functions like `getWorkDirectory`.\n    cwe: CWE-755\n    function_names:\n      - getWorkDirectory\n    filenames:\n      - src/utils.js\n    classification: slightly promising\n\n  - headline: \"Improper Restriction of Platforms in Initialization Scripts\"\n    analysis: |\n      The `ensureWindows` function in `src/utils.js` checks if the platform is Windows and exits if it's not. However, similar checks in `src/compatible.js` throw an error without proper handling. This lack of consistency may lead to unexpected behavior or partial execution of the script, resulting in a confusing user experience.\n    cwe: CWE-754\n    function_names:\n      - ensureWindows\n    filenames:\n      - src/utils.js\n      - src/compatible.js\n    classification: slightly promising\n\n  - headline: \"Use of Insecure Package Download Methods\"\n    analysis: |\n      The `downloadTools` function in `src/download.js` uses the nugget package to download resources. Nugget itself may not provide adequate security checks, and the lack of hash verification after download means that any downloaded file could be tampered with without detection. This creates a significant security risk for code execution.\n    cwe: CWE-494\n    function_names:\n      - downloadTools\n    filenames:\n      - src/download.js\n    classification: very promising\n\n  - headline: \"Potential Command Injection in PowerShell Execution\"\n    analysis: |\n      In `src/environment.js` and `src/install/launch.js`, commands are constructed dynamically for PowerShell execution. This can pose a security risk if any part of the command can be controlled by user input. Although there is no direct user input in these instances, it is a vector worth close examination, as dynamically constructed commands can lead to command injection attacks.\n    cwe: CWE-78\n    function_names:\n      - setEnvironment\n      - launchInstaller\n    filenames:\n      - src/environment.js\n      - src/install/launch.js\n    classification: slightly promising\n\n  - headline: \"Insecure Log File Handling\"\n    analysis: |\n      The `Tailer` class in `src/install/tailer.js` reads log files for installation success or failure statuses. The handling of these log files is insecure as it does not validate the content or check for any potential tampering. Malicious actors can modify the log files to simulate successful installations even if they have been compromised.\n    cwe: CWE-284\n    function_names:\n      - handleData\n    filenames:\n      - src/install/tailer.js\n    classification: slightly promising\n```",
      "date": "2024-06-14T13:33:13.298237",
      "usage": {
        "prompt_tokens": 7696,
        "completion_tokens": 877,
        "cost": 0.051635
      }
    }
  ],
  "leads": [
    {
      "headline": "Weak SSL/TLS Configuration in HTTP Requests",
      "analysis": "In the downloadTools function of src/download.js, the SSL/TLS validation is disabled by setting strictSSL: false in the nugget options. This might allow MITM (Man-in-the-Middle) attacks where an attacker could intercept and manipulate the data being downloaded. Disabling SSL/TLS validation severely undermines the security measures provided by HTTPS, potentially leading to unauthorized code execution or manipulation.\n",
      "classification": "very promising",
      "cwe": "CWE-295",
      "function_names": [
        "downloadTools"
      ],
      "filenames": [
        "src/download.js"
      ]
    },
    {
      "headline": "Hardcoded URLs for Software Downloads",
      "analysis": "The source files src/constants.js and src/download.js contain hardcoded URLs for downloading software packages (e.g., Visual Studio Build Tools and Python installer). These URLs are not validated for authenticity or integrity, allowing potential attackers to substitute the legitimate download URLs with malicious ones. This could lead to the download and execution of malicious code on the victim's machine.\n",
      "classification": "very promising",
      "cwe": "CWE-494",
      "function_names": [],
      "filenames": [
        "src/constants.js",
        "src/download.js"
      ]
    },
    {
      "headline": "Uncaught Exceptions Leading to Weak Error Handling",
      "analysis": "In various parts of the codebase, especially in utils.js, there are try-catch blocks that simply log errors to the console without taking appropriate actions to handle the exceptions. This may lead to file system inconsistencies or a false sense of security if the user believes the operations were successful. Instances can be found in functions like getWorkDirectory.\n",
      "classification": "slightly promising",
      "cwe": "CWE-755",
      "function_names": [
        "getWorkDirectory"
      ],
      "filenames": [
        "src/utils.js"
      ]
    },
    {
      "headline": "Improper Restriction of Platforms in Initialization Scripts",
      "analysis": "The ensureWindows function in src/utils.js checks if the platform is Windows and exits if it's not. However, similar checks in src/compatible.js throw an error without proper handling. This lack of consistency may lead to unexpected behavior or partial execution of the script, resulting in a confusing user experience.\n",
      "classification": "slightly promising",
      "cwe": "CWE-754",
      "function_names": [
        "ensureWindows"
      ],
      "filenames": [
        "src/utils.js",
        "src/compatible.js"
      ]
    },
    {
      "headline": "Use of Insecure Package Download Methods",
      "analysis": "The downloadTools function in src/download.js uses the nugget package to download resources. Nugget itself may not provide adequate security checks, and the lack of hash verification after download means that any downloaded file could be tampered with without detection. This creates a significant security risk for code execution.\n",
      "classification": "very promising",
      "cwe": "CWE-494",
      "function_names": [
        "downloadTools"
      ],
      "filenames": [
        "src/download.js"
      ]
    },
    {
      "headline": "Potential Command Injection in PowerShell Execution",
      "analysis": "In src/environment.js and src/install/launch.js, commands are constructed dynamically for PowerShell execution. This can pose a security risk if any part of the command can be controlled by user input. Although there is no direct user input in these instances, it is a vector worth close examination, as dynamically constructed commands can lead to command injection attacks.\n",
      "classification": "slightly promising",
      "cwe": "CWE-78",
      "function_names": [
        "setEnvironment",
        "launchInstaller"
      ],
      "filenames": [
        "src/environment.js",
        "src/install/launch.js"
      ]
    },
    {
      "headline": "Insecure Log File Handling",
      "analysis": "The Tailer class in src/install/tailer.js reads log files for installation success or failure statuses. The handling of these log files is insecure as it does not validate the content or check for any potential tampering. Malicious actors can modify the log files to simulate successful installations even if they have been compromised.\n",
      "classification": "slightly promising",
      "cwe": "CWE-284",
      "function_names": [
        "handleData"
      ],
      "filenames": [
        "src/install/tailer.js"
      ]
    }
  ],
  "scores": [
    {
      "stats": {
        "fn": 0,
        "tp": 1,
        "fp": 0
      },
      "mapping": {
        "0": "CVE-2017-16003",
        "1": "CVE-2017-16003",
        "2": "CVE-2017-16003"
      },
      "vuln_dates": {
        "CVE-2017-16003": "2018-05-29T20:29:02"
      },
      "scoring_model": "claude-3-opus-20240229",
      "type": "llm",
      "instruction_template_hash": "245ace12b6361954d0a2"
    },
    {
      "stats": {
        "fn": 0,
        "tp": 1,
        "fp": 0
      },
      "mapping": {
        "0": "CVE-2017-16003",
        "1": "CVE-2017-16003",
        "2": "CVE-2017-16003"
      },
      "vuln_dates": {
        "CVE-2017-16003": "2018-05-29T20:29:02"
      },
      "scoring_model": "claude-3-5-sonnet-20240620",
      "type": "llm",
      "instruction_template_hash": "245ace12b6361954d0a2"
    }
  ],
  "instruction_template_hash": "10c0163db4740318a544",
  "version": "0.1.0"
}
