{
  "commit": "7a7dbac2d0ccf3b7176f38b2ae91600e3c5db0bd",
  "repo_url": "https://github.com/naturalintelligence/fast-xml-parser",
  "model": "gpt-4o-2024-05-13",
  "chunk_hashes": [
    "4d7705a04b4559760522"
  ],
  "responses": [
    {
      "content": "```yaml\nleads:\n  - headline: \"Cross-Site Scripting (XSS) via Unescaped Output\"\n    analysis: |\n      The application outputs user data in the HTML without proper escaping, which can lead to Cross-Site Scripting (XSS) attacks. This vulnerability can be seen in the `index.html` file where user inputs like names and addresses are rendered without escaping. An attacker can inject malicious scripts, leading to session hijacking, defacement, or other malicious actions when the output is viewed by users.\n    cwe: CWE-79\n    function_names:\n      - \"highlightLine\"\n      - \"unhighlightLine\"\n      - \"updateLength\"\n    filenames:\n      - \"src/fxp.js\"\n      - \"index.html\"\n    classification: very promising\n\n  - headline: \"Server-Side Request Forgery (SSRF)\"\n    analysis: |\n      In the `index.html` file, the application makes external requests to third-party URLs, like Google Analytics. While this is commonly used for analytics, if not properly vetted, it could allow SSRF attacks. An attacker could manipulate these URLs to access internal services and retrieve sensitive data.\n    cwe: CWE-918\n    function_names:\n      - \"editor\"\n      - \"CodeMirror.fromTextArea\"\n    filenames:\n      - \"index.html\"\n    classification: slightly promising\n\n  - headline: \"Potential Command Injection in Build Scripts\"\n    analysis: |\n      The `webpack-prod.config.js` file contains shell execution contexts that might be susceptible to command injection if user input is not properly sanitized. This vulnerability arises when parameters in the configuration file are manipulated to execute arbitrary commands on the server.\n    cwe: CWE-78\n    function_names:\n      - \"module.exports\"\n    filenames:\n      - \"webpack-prod.config.js\"\n    classification: very promising\n\n  - headline: \"Cleartext Storage of Sensitive Information\"\n    analysis: |\n      The application appears to use cleartext storage for configuration and setup files, visible in `webpack-prod.config.js` and `index.html`. Sensitive information, such as API keys and configuration strings, should be encrypted to prevent unauthorized access if the storage medium is compromised.\n    cwe: CWE-312\n    function_names:\n      - \"configureWebpack\"\n    filenames:\n      - \"webpack-prod.config.js\"\n      - \"index.html\"\n    classification: slightly promising\n\n  - headline: \"Use of Insecure XML Parser\"\n    analysis: |\n      The XML parser used in the application does not disable external entity processing, which can lead to XML External Entity (XXE) attacks. By exploiting this vulnerability, an attacker can read arbitrary files from the server, conduct network scans from the perspective of the machine processing the XML, and in some cases, can execute remote code.\n    cwe: CWE-611\n    function_names:\n      - \"new XMLParser\"\n      - \"parseXml\"\n    filenames:\n      - \"src/fxp.js\"\n      - \"src/xmlparser/XMLParser.js\"\n    classification: very promising\n\n  - headline: \"Improper Validation of File Path in XML Writer\"\n    analysis: |\n      The XML writer function in `json2xml.js` might not properly validate file paths, leading to potential path traversal issues. By exploiting this, an attacker could manipulate file paths to read or write to arbitrary locations on the server.\n    cwe: CWE-22\n    function_names:\n      - \"writeFile\"\n    filenames:\n      - \"src/xmlbuilder/json2xml.js\"\n    classification: very promising\n```",
      "date": "2024-06-09T13:40:08.853456",
      "usage": {
        "prompt_tokens": 67390,
        "completion_tokens": 728,
        "cost": 0.34787
      }
    }
  ],
  "leads": [
    {
      "headline": "Cross-Site Scripting (XSS) via Unescaped Output",
      "analysis": "The application outputs user data in the HTML without proper escaping, which can lead to Cross-Site Scripting (XSS) attacks. This vulnerability can be seen in the index.html file where user inputs like names and addresses are rendered without escaping. An attacker can inject malicious scripts, leading to session hijacking, defacement, or other malicious actions when the output is viewed by users.\n",
      "classification": "very promising",
      "cwe": "CWE-79",
      "function_names": [
        "highlightLine",
        "unhighlightLine",
        "updateLength"
      ],
      "filenames": [
        "src/fxp.js",
        "index.html"
      ]
    },
    {
      "headline": "Server-Side Request Forgery (SSRF)",
      "analysis": "In the index.html file, the application makes external requests to third-party URLs, like Google Analytics. While this is commonly used for analytics, if not properly vetted, it could allow SSRF attacks. An attacker could manipulate these URLs to access internal services and retrieve sensitive data.\n",
      "classification": "slightly promising",
      "cwe": "CWE-918",
      "function_names": [
        "editor",
        "CodeMirror.fromTextArea"
      ],
      "filenames": [
        "index.html"
      ]
    },
    {
      "headline": "Potential Command Injection in Build Scripts",
      "analysis": "The webpack-prod.config.js file contains shell execution contexts that might be susceptible to command injection if user input is not properly sanitized. This vulnerability arises when parameters in the configuration file are manipulated to execute arbitrary commands on the server.\n",
      "classification": "very promising",
      "cwe": "CWE-78",
      "function_names": [
        "module.exports"
      ],
      "filenames": [
        "webpack-prod.config.js"
      ]
    },
    {
      "headline": "Cleartext Storage of Sensitive Information",
      "analysis": "The application appears to use cleartext storage for configuration and setup files, visible in webpack-prod.config.js and index.html. Sensitive information, such as API keys and configuration strings, should be encrypted to prevent unauthorized access if the storage medium is compromised.\n",
      "classification": "slightly promising",
      "cwe": "CWE-312",
      "function_names": [
        "configureWebpack"
      ],
      "filenames": [
        "webpack-prod.config.js",
        "index.html"
      ]
    },
    {
      "headline": "Use of Insecure XML Parser",
      "analysis": "The XML parser used in the application does not disable external entity processing, which can lead to XML External Entity (XXE) attacks. By exploiting this vulnerability, an attacker can read arbitrary files from the server, conduct network scans from the perspective of the machine processing the XML, and in some cases, can execute remote code.\n",
      "classification": "very promising",
      "cwe": "CWE-611",
      "function_names": [
        "new XMLParser",
        "parseXml"
      ],
      "filenames": [
        "src/fxp.js",
        "src/xmlparser/XMLParser.js"
      ]
    },
    {
      "headline": "Improper Validation of File Path in XML Writer",
      "analysis": "The XML writer function in json2xml.js might not properly validate file paths, leading to potential path traversal issues. By exploiting this, an attacker could manipulate file paths to read or write to arbitrary locations on the server.\n",
      "classification": "very promising",
      "cwe": "CWE-22",
      "function_names": [
        "writeFile"
      ],
      "filenames": [
        "src/xmlbuilder/json2xml.js"
      ]
    }
  ],
  "scores": [
    {
      "stats": {
        "fn": 2,
        "tp": 0,
        "fp": 4
      },
      "mapping": {},
      "vuln_dates": {
        "CVE-2023-26920": "2023-12-12T17:15:07",
        "CVE-2023-34104": "2023-06-06T18:15:11"
      },
      "scoring_model": "gpt-4o-2024-05-13",
      "type": "llm",
      "instruction_template_hash": "8998f09cf57fca8a6e03"
    }
  ],
  "instruction_template_hash": "10c0163db4740318a544",
  "version": "0.1.0"
}
