{
  "commit": "284d9162b9903c1828aa13ab56420c1183c49d40",
  "repo_url": "https://github.com/projen/projen",
  "model": "gemini/gemini-1.5-pro",
  "chunk_hashes": [
    "c44bb8f37e02d4c37eb4"
  ],
  "responses": [
    {
      "content": "```yaml\nleads:\n  - headline: Missing input validation for port number in docker-compose\n    analysis: |\n      The `addPorts` function in `src/docker-compose.ts` does not validate the input port numbers. This could lead to unexpected behavior or potential vulnerabilities if an attacker can control the port number. For example, specifying a very large port number could cause resource exhaustion or denial of service.\n    cwe: CWE-20\n    function_names:\n      - addPorts\n    filenames:\n      - src/docker-compose.ts\n    classification: slightly promising\n  - headline: Missing input validation for volume configuration in docker-compose\n    analysis: |\n      The `addVolumeConfiguration` function in `src/docker-compose.ts` does not validate the input volume configuration. An attacker might be able to specify malicious driver options, leading to unexpected behavior or vulnerabilities. For example, a malicious driver could exfiltrate data or execute arbitrary code on the host.\n    cwe: CWE-20\n    function_names:\n      - addVolumeConfiguration\n    filenames:\n      - src/docker-compose.ts\n    classification: slightly promising\n  - headline: Unvalidated redirect in 'yarn add' command\n    analysis: |\n      The `yarnAdd` function in `src/cli/cmds/new.ts` uses `yarn add` to install dependencies from a user-provided spec. If this spec is a URL to a tarball, yarn will download and install it. However, yarn might follow redirects during the download process, potentially leading to installing a package from an untrusted source.\n    cwe: CWE-601\n    function_names:\n      - yarnAdd\n    filenames:\n      - src/cli/cmds/new.ts\n    classification: slightly promising\n  - headline: Insecure default permissions on 'deps.json'\n    analysis: |\n      In `src/__tests__/integration/cdk8s/cdk8s.projenrc.js`, the `deps.json` file is given world-writable permissions using `chmodSync(depsPath, '777')`. This could allow an attacker to modify the dependencies of the project, potentially leading to installing malicious packages.\n    cwe: CWE-276\n    function_names: []\n    filenames:\n      - src/__tests__/integration/cdk8s/cdk8s.projenrc.js\n    classification: not promising\n  - headline: Insufficient validation of 'jsii-release' version in 'publishToNpm'\n    analysis: |\n      The `publishToNpm` function in `src/publisher.ts` uses `npx -p jsii-release@${this.jsiiReleaseVersion} jsii-release-npm` to publish to NPM. The `jsiiReleaseVersion` is configurable, and if it's not properly validated, an attacker could specify a malicious version of `jsii-release`, leading to arbitrary code execution during the publish process.\n    cwe: CWE-20\n    function_names:\n      - publishToNpm\n    filenames:\n      - src/publisher.ts\n    classification: slightly promising\n  - headline: Hardcoded credentials in projenrc.java generation\n    analysis: |\n      The `generateProjenrc` function in `src/java/projenrc.ts` hardcodes a Projen dependency version (`com.github.eladb/projen@${projenVersion}`). This could lead to vulnerabilities if a malicious version of Projen is released.\n    cwe: CWE-798\n    function_names:\n      - generateProjenrc\n    filenames:\n      - src/java/projenrc.ts\n    classification: not promising\n  - headline: Unrestricted file uploads in `DockerCompose.bindVolume`\n    analysis: |\n      The `DockerCompose.bindVolume` function in `src/docker-compose.ts` allows binding any host directory to a container path. An attacker could potentially bind a sensitive directory on the host, leading to information disclosure.\n    cwe: CWE-434\n    function_names:\n      - bindVolume\n    filenames:\n      - src/docker-compose.ts\n    classification: not promising\n```",
      "date": "2024-06-13T11:08:37.132652",
      "usage": {
        "prompt_tokens": 141301,
        "completion_tokens": 830,
        "cost": 0.089869375
      }
    }
  ],
  "leads": [
    {
      "headline": "Missing input validation for port number in docker-compose",
      "analysis": "The addPorts function in src/docker-compose.ts does not validate the input port numbers. This could lead to unexpected behavior or potential vulnerabilities if an attacker can control the port number. For example, specifying a very large port number could cause resource exhaustion or denial of service.\n",
      "classification": "slightly promising",
      "cwe": "CWE-20",
      "function_names": [
        "addPorts"
      ],
      "filenames": [
        "src/docker-compose.ts"
      ]
    },
    {
      "headline": "Missing input validation for volume configuration in docker-compose",
      "analysis": "The addVolumeConfiguration function in src/docker-compose.ts does not validate the input volume configuration. An attacker might be able to specify malicious driver options, leading to unexpected behavior or vulnerabilities. For example, a malicious driver could exfiltrate data or execute arbitrary code on the host.\n",
      "classification": "slightly promising",
      "cwe": "CWE-20",
      "function_names": [
        "addVolumeConfiguration"
      ],
      "filenames": [
        "src/docker-compose.ts"
      ]
    },
    {
      "headline": "Unvalidated redirect in 'yarn add' command",
      "analysis": "The yarnAdd function in src/cli/cmds/new.ts uses yarn add to install dependencies from a user-provided spec. If this spec is a URL to a tarball, yarn will download and install it. However, yarn might follow redirects during the download process, potentially leading to installing a package from an untrusted source.\n",
      "classification": "slightly promising",
      "cwe": "CWE-601",
      "function_names": [
        "yarnAdd"
      ],
      "filenames": [
        "src/cli/cmds/new.ts"
      ]
    },
    {
      "headline": "Insecure default permissions on 'deps.json'",
      "analysis": "In src/__tests__/integration/cdk8s/cdk8s.projenrc.js, the deps.json file is given world-writable permissions using chmodSync(depsPath, '777'). This could allow an attacker to modify the dependencies of the project, potentially leading to installing malicious packages.\n",
      "classification": "not promising",
      "cwe": "CWE-276",
      "function_names": [],
      "filenames": [
        "src/__tests__/integration/cdk8s/cdk8s.projenrc.js"
      ]
    },
    {
      "headline": "Insufficient validation of 'jsii-release' version in 'publishToNpm'",
      "analysis": "The publishToNpm function in src/publisher.ts uses npx -p jsii-release@${this.jsiiReleaseVersion} jsii-release-npm to publish to NPM. The jsiiReleaseVersion is configurable, and if it's not properly validated, an attacker could specify a malicious version of jsii-release, leading to arbitrary code execution during the publish process.\n",
      "classification": "slightly promising",
      "cwe": "CWE-20",
      "function_names": [
        "publishToNpm"
      ],
      "filenames": [
        "src/publisher.ts"
      ]
    },
    {
      "headline": "Hardcoded credentials in projenrc.java generation",
      "analysis": "The generateProjenrc function in src/java/projenrc.ts hardcodes a Projen dependency version (com.github.eladb/projen@${projenVersion}). This could lead to vulnerabilities if a malicious version of Projen is released.\n",
      "classification": "not promising",
      "cwe": "CWE-798",
      "function_names": [
        "generateProjenrc"
      ],
      "filenames": [
        "src/java/projenrc.ts"
      ]
    },
    {
      "headline": "Unrestricted file uploads in DockerCompose.bindVolume",
      "analysis": "The DockerCompose.bindVolume function in src/docker-compose.ts allows binding any host directory to a container path. An attacker could potentially bind a sensitive directory on the host, leading to information disclosure.\n",
      "classification": "not promising",
      "cwe": "CWE-434",
      "function_names": [
        "bindVolume"
      ],
      "filenames": [
        "src/docker-compose.ts"
      ]
    }
  ],
  "scores": [
    {
      "stats": {
        "fn": 1,
        "tp": 0,
        "fp": 0
      },
      "mapping": {},
      "vuln_dates": {
        "CVE-2021-21423": "2021-04-06T19:15:14"
      },
      "scoring_model": "claude-3-opus-20240229",
      "type": "llm",
      "instruction_template_hash": "245ace12b6361954d0a2"
    }
  ],
  "instruction_template_hash": "10c0163db4740318a544",
  "version": "0.1.0"
}
