{
  "commit": "a6d143d1ae30cc58fce8e9769e2a489db1e55b7d",
  "repo_url": "https://github.com/xwikisas/identity-oauth",
  "model": "claude-3-5-sonnet-20240620",
  "chunk_hashes": [
    "dbc8de846abdbb39fecc"
  ],
  "responses": [
    {
      "content": "```yaml\nleads:\n  - headline: Insecure storage of sensitive information in session\n    analysis: |\n      The IdentityOAuthSessionInfo class stores sensitive OAuth tokens and authorization codes in the user's session as plain text. This information could potentially be accessed if an attacker gains access to the session data. Storing this sensitive data unencrypted in the session poses a security risk.\n    cwe: CWE-312\n    function_names:\n      - setAuthorizationCode\n      - setToken  \n    filenames:\n      - api/src/main/java/com/xwiki/identityoauth/internal/IdentityOAuthSessionInfo.java\n    classification: very promising\n\n  - headline: Potential for session fixation attack  \n    analysis: |\n      The setXredirect method in IdentityOAuthSessionInfo allows setting an arbitrary redirect URL that is later used in pickXredirect. This could potentially be exploited for session fixation if an attacker can control the redirect URL. There does not appear to be any validation on the redirect URL before it is set or used.\n    cwe: CWE-384\n    function_names: \n      - setXredirect\n      - pickXredirect\n    filenames:\n      - api/src/main/java/com/xwiki/identityoauth/internal/IdentityOAuthSessionInfo.java\n    classification: slightly promising\n\n  - headline: Weak encryption key generation for cookie encryption\n    analysis: |\n      In CookieAuthenticationPersistence, the encryption key for cookie data is derived by simply taking the first 24 bytes of a configured secret key. This results in a relatively weak encryption key that could potentially be brute forced. A more secure key derivation function should be used instead.\n    cwe: CWE-326\n    function_names:\n      - getCipher\n    filenames:\n      - api/src/main/java/com/xwiki/identityoauth/internal/CookieAuthenticationPersistence.java  \n    classification: slightly promising\n\n  - headline: Potential for CSRF attack on OAuth flow\n    analysis: |\n      The processOAuthReturn method does not appear to validate the state parameter to prevent CSRF attacks on the OAuth flow. An attacker could potentially initiate an OAuth flow with their own account and trick a victim into completing it, potentially associating the victim's XWiki account with the attacker's OAuth identity.\n    cwe: CWE-352\n    function_names:\n      - processOAuthReturn\n    filenames:\n      - api/src/main/java/com/xwiki/identityoauth/internal/DefaultIdentityOAuthManager.java\n    classification: slightly promising\n\n  - headline: Insecure direct object reference in getProvider method\n    analysis: |\n      The getProvider method in IdentityOAuthScriptService allows retrieving provider objects by name without proper access control. While it does check for admin rights, this check could potentially be bypassed. Exposing internal objects directly to scripts is generally risky.\n    cwe: CWE-639\n    function_names:\n      - getProvider\n    filenames:\n      - api/src/main/java/com/xwiki/identityoauth/IdentityOAuthScriptService.java\n    classification: slightly promising\n```",
      "date": "2024-07-08T05:26:01.578989",
      "usage": {
        "prompt_tokens": 32258,
        "completion_tokens": 768,
        "cost": 0.108294
      }
    }
  ],
  "leads": [
    {
      "headline": "Insecure storage of sensitive information in session",
      "analysis": "The IdentityOAuthSessionInfo class stores sensitive OAuth tokens and authorization codes in the user's session as plain text. This information could potentially be accessed if an attacker gains access to the session data. Storing this sensitive data unencrypted in the session poses a security risk.\n",
      "classification": "very promising",
      "cwe": "CWE-312",
      "function_names": [
        "setAuthorizationCode",
        "setToken"
      ],
      "filenames": [
        "api/src/main/java/com/xwiki/identityoauth/internal/IdentityOAuthSessionInfo.java"
      ]
    },
    {
      "headline": "Potential for session fixation attack",
      "analysis": "The setXredirect method in IdentityOAuthSessionInfo allows setting an arbitrary redirect URL that is later used in pickXredirect. This could potentially be exploited for session fixation if an attacker can control the redirect URL. There does not appear to be any validation on the redirect URL before it is set or used.\n",
      "classification": "slightly promising",
      "cwe": "CWE-384",
      "function_names": [
        "setXredirect",
        "pickXredirect"
      ],
      "filenames": [
        "api/src/main/java/com/xwiki/identityoauth/internal/IdentityOAuthSessionInfo.java"
      ]
    },
    {
      "headline": "Weak encryption key generation for cookie encryption",
      "analysis": "In CookieAuthenticationPersistence, the encryption key for cookie data is derived by simply taking the first 24 bytes of a configured secret key. This results in a relatively weak encryption key that could potentially be brute forced. A more secure key derivation function should be used instead.\n",
      "classification": "slightly promising",
      "cwe": "CWE-326",
      "function_names": [
        "getCipher"
      ],
      "filenames": [
        "api/src/main/java/com/xwiki/identityoauth/internal/CookieAuthenticationPersistence.java"
      ]
    },
    {
      "headline": "Potential for CSRF attack on OAuth flow",
      "analysis": "The processOAuthReturn method does not appear to validate the state parameter to prevent CSRF attacks on the OAuth flow. An attacker could potentially initiate an OAuth flow with their own account and trick a victim into completing it, potentially associating the victim's XWiki account with the attacker's OAuth identity.\n",
      "classification": "slightly promising",
      "cwe": "CWE-352",
      "function_names": [
        "processOAuthReturn"
      ],
      "filenames": [
        "api/src/main/java/com/xwiki/identityoauth/internal/DefaultIdentityOAuthManager.java"
      ]
    },
    {
      "headline": "Insecure direct object reference in getProvider method",
      "analysis": "The getProvider method in IdentityOAuthScriptService allows retrieving provider objects by name without proper access control. While it does check for admin rights, this check could potentially be bypassed. Exposing internal objects directly to scripts is generally risky.\n",
      "classification": "slightly promising",
      "cwe": "CWE-639",
      "function_names": [
        "getProvider"
      ],
      "filenames": [
        "api/src/main/java/com/xwiki/identityoauth/IdentityOAuthScriptService.java"
      ]
    }
  ],
  "scores": [
    {
      "stats": {
        "fn": 1,
        "tp": 0,
        "fp": 1
      },
      "mapping": {},
      "vuln_dates": {
        "CVE-2023-45144": "2023-10-16T21:15:11"
      },
      "scoring_model": "claude-3-5-sonnet-20240620",
      "type": "llm",
      "instruction_template_hash": "245ace12b6361954d0a2"
    }
  ],
  "instruction_template_hash": "10c0163db4740318a544",
  "version": "0.1.0"
}
