{
  "commit": "228f357af22643dd8be7464c39e04e009af2d2ee",
  "repo_url": "https://github.com/maxtortime/setupbox",
  "model": "gpt-4-turbo-2024-04-09",
  "chunk_hashes": [
    "12299c1340cd2175c350"
  ],
  "responses": [
    {
      "content": "```yaml\nleads:\n  - headline: \"Improper handling of file paths and directories\"\n    analysis: |\n      The server does not adequately check user input for directory paths, which can result in unauthorized information disclosure or manipulation. This occurs in various parts of the code, where user-supplied input is used to construct file system paths directly. An attacker could potentially manipulate these paths to access, modify, or delete arbitrary files on the server file system, leading to a loss of integrity and availability of data.\n    cwe: CWE-22\n    function_names:\n      - set_dir\n      - explorer\n      - create_directory\n    filenames:\n      - web_server/runserver.py\n    classification: very promising\n\n  - headline: \"Use of hard-coded credentials\"\n    analysis: |\n      Found hard-coded credentials in the configuration file which represents a severe security risk, allowing an attacker to gain unauthorized access to system components or sensitive data.\n    cwe: CWE-798\n    function_names:\n      - \"\"\n    filenames:\n      - web_server/config.py\n    classification: very promising\n\n  - headline: \"SQL Injection through unsanitized input\"\n    analysis: |\n      User parameters are incorporated into SQL queries without proper sanitization, leading to SQL injection vulnerabilities. This allows an attacker to manipulate SQL queries by injecting arbitrary SQL code, which can perform unauthorized database operations suchize as data leakage, deletion, or modification.\n    cwe: CWE-89\n    function_names:\n      - create_db\n    filenames:\n      - web_server/db.py\n    classification: very promising\n\n  - headline: \"Command injection vulnerability in installation script\"\n    analysis: |\n      The server_install.sh script uses unsanitized input for commands that are executed on the system shell. An attacker could inject additional shell commands that will be executed by the system, potentially allowing unauthorized system access, data leakage, or denial of service.\n    cwe: CWE-77\n    function_names:\n      - \"\"\n    filenames:\n      - server_install.sh\n    heatline: \"Command injection vulnerability in installation script\"\n    classification: very promising\n\n  - headline: \"Arbitrary file upload leading to remote code execution\"\n    analysis: |\n      The application allows users to upload executable files without proper validation, which can be executed on the server. This vulnerability could be exploited to execute arbitrary code on the server, compromise the server, and spread malware.\n    cwe: CWE-434\n    function_names:\n      - upload_file\n    filenames:\n      - web_server/runserver.py\n    classification: very promising\n\n  - headline: \"Improper access control mechanism\"\n    analysis: |\n      The system does not properly restrict access to certain functionalities, which may allow an unauthorized actor to access sensitive functions that could compromise the security of the application.\n    cwe: CWE-284\n    function_names:\n      - explorer\n      - create_directory\n      - upload_file\n      - file_delete\n    filenames:\n      - web_server/runserver.py\n    classification: very promising\n```",
      "date": "2024-06-13T10:03:39.857837",
      "usage": {
        "prompt_tokens": 15146,
        "completion_tokens": 619,
        "cost": 0.17003
      }
    }
  ],
  "leads": [
    {
      "headline": "Improper handling of file paths and directories",
      "analysis": "The server does not adequately check user input for directory paths, which can result in unauthorized information disclosure or manipulation. This occurs in various parts of the code, where user-supplied input is used to construct file system paths directly. An attacker could potentially manipulate these paths to access, modify, or delete arbitrary files on the server file system, leading to a loss of integrity and availability of data.\n",
      "classification": "very promising",
      "cwe": "CWE-22",
      "function_names": [
        "set_dir",
        "explorer",
        "create_directory"
      ],
      "filenames": [
        "web_server/runserver.py"
      ]
    },
    {
      "headline": "Use of hard-coded credentials",
      "analysis": "Found hard-coded credentials in the configuration file which represents a severe security risk, allowing an attacker to gain unauthorized access to system components or sensitive data.\n",
      "classification": "very promising",
      "cwe": "CWE-798",
      "function_names": [
        ""
      ],
      "filenames": [
        "web_server/config.py"
      ]
    },
    {
      "headline": "SQL Injection through unsanitized input",
      "analysis": "User parameters are incorporated into SQL queries without proper sanitization, leading to SQL injection vulnerabilities. This allows an attacker to manipulate SQL queries by injecting arbitrary SQL code, which can perform unauthorized database operations suchize as data leakage, deletion, or modification.\n",
      "classification": "very promising",
      "cwe": "CWE-89",
      "function_names": [
        "create_db"
      ],
      "filenames": [
        "web_server/db.py"
      ]
    },
    {
      "headline": "Command injection vulnerability in installation script",
      "analysis": "The server_install.sh script uses unsanitized input for commands that are executed on the system shell. An attacker could inject additional shell commands that will be executed by the system, potentially allowing unauthorized system access, data leakage, or denial of service.\n",
      "classification": "very promising",
      "cwe": "CWE-77",
      "function_names": [
        ""
      ],
      "filenames": [
        "server_install.sh"
      ]
    },
    {
      "headline": "Arbitrary file upload leading to remote code execution",
      "analysis": "The application allows users to upload executable files without proper validation, which can be executed on the server. This vulnerability could be exploited to execute arbitrary code on the server, compromise the server, and spread malware.\n",
      "classification": "very promising",
      "cwe": "CWE-434",
      "function_names": [
        "upload_file"
      ],
      "filenames": [
        "web_server/runserver.py"
      ]
    },
    {
      "headline": "Improper access control mechanism",
      "analysis": "The system does not properly restrict access to certain functionalities, which may allow an unauthorized actor to access sensitive functions that could compromise the security of the application.\n",
      "classification": "very promising",
      "cwe": "CWE-284",
      "function_names": [
        "explorer",
        "create_directory",
        "upload_file"
      ],
      "filenames": [
        "web_server/runserver.py"
      ]
    }
  ],
  "scores": [
    {
      "stats": {
        "fn": 1,
        "tp": 0,
        "fp": 6
      },
      "mapping": {},
      "vuln_dates": {
        "CVE-2022-31543": "2022-07-11T01:15:09"
      },
      "scoring_model": "claude-3-opus-20240229",
      "type": "llm",
      "instruction_template_hash": "245ace12b6361954d0a2"
    },
    {
      "stats": {
        "fn": 0,
        "tp": 1,
        "fp": 5
      },
      "mapping": {
        "0": "CVE-2022-31543"
      },
      "vuln_dates": {
        "CVE-2022-31543": "2022-07-11T01:15:09"
      },
      "scoring_model": "claude-3-5-sonnet-20240620",
      "type": "llm",
      "instruction_template_hash": "245ace12b6361954d0a2"
    }
  ],
  "instruction_template_hash": "10c0163db4740318a544",
  "version": "0.1.0"
}
