{
  "commit": "4b97c41dbe6af6bd7ed6356053c1ea4e68b9a243",
  "repo_url": "https://github.com/zerocoin/libzerocoin",
  "model": "gpt-4o-2024-05-13",
  "chunk_hashes": [
    "922d76ab26016a4c283e"
  ],
  "responses": [
    {
      "content": "```yaml\nleads:\n  - headline: \"Possible Integer Overflow\"\n    analysis: |\n      The codebase makes use of arithmetic operations without proper checks for potential overflows. Specifically, in several places, integer additions, multiplications, and shifts are performed without verifying if the result fits within the allocated number of bits, which can lead to unexpected behavior or vulnerabilities if the result wraps around.\n    cwe: CWE-190\n    function_names:\n      - CalculateParams\n      - generateRandomPrime\n      - pow_mod\n    filenames:\n      - ParamGeneration.cpp\n      - bignum.h\n      - Accumulator.cpp\n    classification: very promising\n\n  - headline: \"Uninitialized Pointer Use\"\n    analysis: |\n      There is use of potentially uninitialized pointers, particularly within the constructor of `SharedResource` in `Zerocoin.h`. If the pointers are not properly initialized before use, it can lead to undefined behavior, crashes, or exploitation.\n    cwe: CWE-824\n    function_names:\n      - SharedResource::SharedResource\n    filenames:\n      - Zerocoin.h\n    classification: very promising\n\n  - headline: \"Improper Validation of Input\"\n    analysis: |\n      Functions that handle external inputs, such as `SpendMetaData`, do not adequately validate that the data meets expected formats or value ranges. This can lead to various issues, including crashes, unexpected behavior, or security vulnerabilities if invalid data propagates through the system unchecked.\n    cwe: CWE-20\n    function_names:\n      - SpendMetaData::SpendMetaData\n    filenames:\n      - SpendMetaData.cpp\n    classification: very promising\n\n  - headline: \"Insecure Random Number Generation\"\n    analysis: |\n      The randBignum function generates random numbers for critical cryptographic operations but does not sufficiently ensure that the randomness is unpredictable or secure. This might make the derived cryptographic keys susceptible to prediction or brute-force attacks.\n    cwe: CWE-330\n    function_names:\n      - randBignum\n    filenames:\n      - bignum.h\n    classification: slightly promising\n\n  - headline: \"Potential Race Condition\"\n    analysis: |\n      The library uses shared resources such as the accumulator without implementing proper synchronization mechanisms. Lack of proper locking can cause race conditions, where concurrent accesses lead to inconsistent states or data corruption.\n    cwe: CWE-362\n    function_names: []\n    filenames:\n      - Accumulator.h\n      - libzerocoin.h\n    classification: very promising\n\n  - headline: \"Missing Encryption of Sensitive Data\"\n    analysis: |\n      Private data, such as cryptographic keys and critical parameters, are stored in cleartext within the memory. Without encryption or adequate protection, unauthorized access to these values can compromise the entire security model.\n    cwe: CWE-311\n    function_names: []\n    filenames:\n      - PrivateCoin.h\n      - Accumulator.cpp\n    classification: very promising\n\n  - headline: \"Improper Resource Handling\"\n    analysis: |\n      Resources such as file handles and memory are not adequately released after their usage, leading to potential resource leaks. For example, in CAutoFile class, if not properly handled, resources may persist beyond their operational requirement, causing inefficiencies or exhaustion.\n    cwe: CWE-404\n    function_names:\n      - CAutoFile::fclose\n    filenames:\n      - serialize.h\n    classification: very promising\n\n  - headline: \"Use of Weak Hashing Algorithms\"\n    analysis: |\n      The usage of SHA-256 in certain cryptographic operations without considering modern alternatives like SHA-3 or more rigorous constructions can be seen as a potential threat if newer cryptanalytic techniques arise that target SHA-2 family.\n    cwe: CWE-328\n    function_names:\n      - CHashWriter::GetHash\n    filenames:\n      - hash.h\n    classification: slightly promising\n```",
      "date": "2024-07-08T09:34:08.966664",
      "usage": {
        "prompt_tokens": 70730,
        "completion_tokens": 804,
        "cost": 0.36571
      }
    }
  ],
  "leads": [
    {
      "headline": "Possible Integer Overflow",
      "analysis": "The codebase makes use of arithmetic operations without proper checks for potential overflows. Specifically, in several places, integer additions, multiplications, and shifts are performed without verifying if the result fits within the allocated number of bits, which can lead to unexpected behavior or vulnerabilities if the result wraps around.\n",
      "classification": "very promising",
      "cwe": "CWE-190",
      "function_names": [
        "CalculateParams",
        "generateRandomPrime",
        "pow_mod"
      ],
      "filenames": [
        "ParamGeneration.cpp",
        "bignum.h",
        "Accumulator.cpp"
      ]
    },
    {
      "headline": "Uninitialized Pointer Use",
      "analysis": "There is use of potentially uninitialized pointers, particularly within the constructor of SharedResource in Zerocoin.h. If the pointers are not properly initialized before use, it can lead to undefined behavior, crashes, or exploitation.\n",
      "classification": "very promising",
      "cwe": "CWE-824",
      "function_names": [
        "SharedResource::SharedResource"
      ],
      "filenames": [
        "Zerocoin.h"
      ]
    },
    {
      "headline": "Improper Validation of Input",
      "analysis": "Functions that handle external inputs, such as SpendMetaData, do not adequately validate that the data meets expected formats or value ranges. This can lead to various issues, including crashes, unexpected behavior, or security vulnerabilities if invalid data propagates through the system unchecked.\n",
      "classification": "very promising",
      "cwe": "CWE-20",
      "function_names": [
        "SpendMetaData::SpendMetaData"
      ],
      "filenames": [
        "SpendMetaData.cpp"
      ]
    },
    {
      "headline": "Insecure Random Number Generation",
      "analysis": "The randBignum function generates random numbers for critical cryptographic operations but does not sufficiently ensure that the randomness is unpredictable or secure. This might make the derived cryptographic keys susceptible to prediction or brute-force attacks.\n",
      "classification": "slightly promising",
      "cwe": "CWE-330",
      "function_names": [
        "randBignum"
      ],
      "filenames": [
        "bignum.h"
      ]
    },
    {
      "headline": "Potential Race Condition",
      "analysis": "The library uses shared resources such as the accumulator without implementing proper synchronization mechanisms. Lack of proper locking can cause race conditions, where concurrent accesses lead to inconsistent states or data corruption.\n",
      "classification": "very promising",
      "cwe": "CWE-362",
      "function_names": [],
      "filenames": [
        "Accumulator.h",
        "libzerocoin.h"
      ]
    },
    {
      "headline": "Missing Encryption of Sensitive Data",
      "analysis": "Private data, such as cryptographic keys and critical parameters, are stored in cleartext within the memory. Without encryption or adequate protection, unauthorized access to these values can compromise the entire security model.\n",
      "classification": "very promising",
      "cwe": "CWE-311",
      "function_names": [],
      "filenames": [
        "PrivateCoin.h",
        "Accumulator.cpp"
      ]
    },
    {
      "headline": "Improper Resource Handling",
      "analysis": "Resources such as file handles and memory are not adequately released after their usage, leading to potential resource leaks. For example, in CAutoFile class, if not properly handled, resources may persist beyond their operational requirement, causing inefficiencies or exhaustion.\n",
      "classification": "very promising",
      "cwe": "CWE-404",
      "function_names": [
        "CAutoFile::fclose"
      ],
      "filenames": [
        "serialize.h"
      ]
    },
    {
      "headline": "Use of Weak Hashing Algorithms",
      "analysis": "The usage of SHA-256 in certain cryptographic operations without considering modern alternatives like SHA-3 or more rigorous constructions can be seen as a potential threat if newer cryptanalytic techniques arise that target SHA-2 family.\n",
      "classification": "slightly promising",
      "cwe": "CWE-328",
      "function_names": [
        "CHashWriter::GetHash"
      ],
      "filenames": [
        "hash.h"
      ]
    }
  ],
  "scores": [
    {
      "stats": {
        "fn": 1,
        "tp": 0,
        "fp": 6
      },
      "mapping": {},
      "vuln_dates": {
        "CVE-2017-20180": "2023-03-06T11:15:09"
      },
      "scoring_model": "claude-3-5-sonnet-20240620",
      "type": "llm",
      "instruction_template_hash": "245ace12b6361954d0a2"
    }
  ],
  "instruction_template_hash": "10c0163db4740318a544",
  "version": "0.1.0"
}
