{
  "commit": "40aaeff558035334fd29dca90f5c140c43664041",
  "repo_url": "https://github.com/zenoss/zenpacks.zenoss.dashboard",
  "model": "gpt-4o-2024-05-13",
  "chunk_hashes": [
    "d6f69be0314a3fd48b26"
  ],
  "responses": [
    {
      "content": "```yaml\nleads:\n  - headline: \"Potential Command Injection Vulnerability in `add_virtual_root` function\"\n    analysis: |\n      The usage of `add_virtual_root` function can be vulnerable to command injection. Specifically, if the function is used in scenarios where unvalidated or unsanitized input is passed to it, an attacker could inject malicious commands. Such an injection could potentially be leveraged to gain unauthorized command execution on the hosting server. The associated risk is further compounded by the function's backward compatibility attempts and dependency on third-party utilities which might be manipulated.\n    cwe: CWE-77\n    function_names:\n      - getUtility\n      - add_virtual_root\n    filenames:\n      - ZenPacks/zenoss/Dashboard/__init__.py\n      - ZenPacks/zenoss/Dashboard/migrate/updateDefaultGMapLocation.py\n      - ZenPacks/zenoss/Dashboard/migrate/updateDenaliDefaultSiteUrl.py\n    classification: slightly promising\n  - headline: \"Potential Hard-Coded Credentials in Default Dashboard\"\n    analysis: |\n      The `DEFAULT_DASHBOARD_STATE` in the `ZenPack` class initialization sets certain default states and URLs which might potentially include hard-coded credentials or sensitive information. This is particularly risky if such hard-coded values are used in production environments without proper sanitization or updates. Attackers could misuse these details to gain unauthorized access or to manipulate the dashboard.\n    cwe: CWE-798\n    function_names:\n      - ZenPack\n    filenames:\n      - ZenPacks/zenoss/Dashboard/__init__.py\n    classification: slightly promising\n  - headline: \"Cross-Site Scripting (XSS) via Dynamic Dashboard Content\"\n    analysis: |\n      Various dashboard-related functionalities such as the `HTMLPortlet`, `SiteWindowPortlet`, and functions handling event summaries (e.g., `eventRenderer`, `loadData`, etc.) dynamically include content which might not be adequately sanitized before rendering. Malicious code or content injected into these dynamically handled portions could result in a cross-site scripting (XSS) vulnerability, thereby allowing attackers to execute arbitrary scripts in the context of the user's session on the dashboard.\n    cwe: CWE-79\n    function_names:\n      - HTMLPortlet\n      - SiteWindowPortlet\n      - eventRenderer\n      - loadData\n    filenames:\n      - ZenPacks/zenoss/Dashboard/browser/resources/js/defaultportlets.js\n      - ZenPacks/zenoss/Dashboard/browser/resources/js/europaportlets.js\n    classification: very promising\n  - headline: \"Potential Insecure Deserialization in Facade and Router Classes\"\n    analysis: |\n      The various usage of JSON serialization and deserialization functions in facade and router classes might indicate the risk of insecure deserialization vulnerabilities. Specially crafted payloads through network calls that manipulate the input to these deserialization functions could lead to potential execution of arbitrary code or further injection attacks, especially if critical processes fail to validate input properly prior to deserialization.\n    cwe: CWE-502\n    function_names:\n      - saveDashboardState\n      - getMultiGraphReportGroups\n      - applyConfig\n    filenames:\n      - ZenPacks/zenoss/Dashboard/routers.py\n      - ZenPacks/zenoss/Dashboard/facades.py\n      - ZenPacks/zenoss/Dashboard/browser/resources/js/view/DashboardPanel.js\n    classification: very promising\n```",
      "date": "2024-07-08T09:33:17.595914",
      "usage": {
        "prompt_tokens": 44205,
        "completion_tokens": 703,
        "cost": 0.23157
      }
    }
  ],
  "leads": [
    {
      "headline": "Potential Command Injection Vulnerability in add_virtual_root function",
      "analysis": "The usage of add_virtual_root function can be vulnerable to command injection. Specifically, if the function is used in scenarios where unvalidated or unsanitized input is passed to it, an attacker could inject malicious commands. Such an injection could potentially be leveraged to gain unauthorized command execution on the hosting server. The associated risk is further compounded by the function's backward compatibility attempts and dependency on third-party utilities which might be manipulated.\n",
      "classification": "slightly promising",
      "cwe": "CWE-77",
      "function_names": [
        "getUtility",
        "add_virtual_root"
      ],
      "filenames": [
        "ZenPacks/zenoss/Dashboard/__init__.py",
        "ZenPacks/zenoss/Dashboard/migrate/updateDefaultGMapLocation.py",
        "ZenPacks/zenoss/Dashboard/migrate/updateDenaliDefaultSiteUrl.py"
      ]
    },
    {
      "headline": "Potential Hard-Coded Credentials in Default Dashboard",
      "analysis": "The DEFAULT_DASHBOARD_STATE in the ZenPack class initialization sets certain default states and URLs which might potentially include hard-coded credentials or sensitive information. This is particularly risky if such hard-coded values are used in production environments without proper sanitization or updates. Attackers could misuse these details to gain unauthorized access or to manipulate the dashboard.\n",
      "classification": "slightly promising",
      "cwe": "CWE-798",
      "function_names": [
        "ZenPack"
      ],
      "filenames": [
        "ZenPacks/zenoss/Dashboard/__init__.py"
      ]
    },
    {
      "headline": "Cross-Site Scripting (XSS) via Dynamic Dashboard Content",
      "analysis": "Various dashboard-related functionalities such as the HTMLPortlet, SiteWindowPortlet, and functions handling event summaries (e.g., eventRenderer, loadData, etc.) dynamically include content which might not be adequately sanitized before rendering. Malicious code or content injected into these dynamically handled portions could result in a cross-site scripting (XSS) vulnerability, thereby allowing attackers to execute arbitrary scripts in the context of the user's session on the dashboard.\n",
      "classification": "very promising",
      "cwe": "CWE-79",
      "function_names": [
        "HTMLPortlet",
        "SiteWindowPortlet",
        "eventRenderer"
      ],
      "filenames": [
        "ZenPacks/zenoss/Dashboard/browser/resources/js/defaultportlets.js",
        "ZenPacks/zenoss/Dashboard/browser/resources/js/europaportlets.js"
      ]
    },
    {
      "headline": "Potential Insecure Deserialization in Facade and Router Classes",
      "analysis": "The various usage of JSON serialization and deserialization functions in facade and router classes might indicate the risk of insecure deserialization vulnerabilities. Specially crafted payloads through network calls that manipulate the input to these deserialization functions could lead to potential execution of arbitrary code or further injection attacks, especially if critical processes fail to validate input properly prior to deserialization.\n",
      "classification": "very promising",
      "cwe": "CWE-502",
      "function_names": [
        "saveDashboardState",
        "getMultiGraphReportGroups",
        "applyConfig"
      ],
      "filenames": [
        "ZenPacks/zenoss/Dashboard/routers.py",
        "ZenPacks/zenoss/Dashboard/facades.py",
        "ZenPacks/zenoss/Dashboard/browser/resources/js/view/DashboardPanel.js"
      ]
    }
  ],
  "scores": [
    {
      "stats": {
        "fn": 0,
        "tp": 1,
        "fp": 1
      },
      "mapping": {
        "0": "CVE-2018-25063"
      },
      "vuln_dates": {
        "CVE-2018-25063": "2023-01-01T09:15:09"
      },
      "scoring_model": "claude-3-5-sonnet-20240620",
      "type": "llm",
      "instruction_template_hash": "245ace12b6361954d0a2"
    }
  ],
  "instruction_template_hash": "10c0163db4740318a544",
  "version": "0.1.0"
}
