{
  "commit": "48acf4365a6575d7c5fdae329b6383c20ad5eddb",
  "repo_url": "https://github.com/ros2/sros2",
  "model": "claude-3-sonnet-20240229",
  "chunk_hashes": [
    "799dfdedaa0016076b17"
  ],
  "responses": [
    {
      "content": "```yaml\nleads:\n  - headline: Incorrect handling of XML entities (XXE)\n    analysis: |\n      The sros2 package does not properly handle XML external entity references, which can enable XML External Entity (XXE) attacks. An attacker could craft a malicious XML file that includes external entity references to gain access to sensitive files on the system or cause denial of service.\n    cwe: CWE-611\n    function_names:\n      - sros2.policy.load_policy\n    filenames:\n      - sros2/sros2/policy/__init__.py\n    classification: very promising\n\n  - headline: Use of a broken cryptographic implementation\n    analysis: |\n      The sros2 package uses the cryptography library, but it may be using a vulnerable or outdated version of the library. The cryptography library has had numerous vulnerabilities in the past, including side-channel attacks, insecure default configurations, and other issues related to cryptographic implementations. An attacker could potentially exploit vulnerabilities in the cryptography library to compromise the security of the system.\n    cwe: CWE-327\n    function_names:\n      - sros2.api._write_key\n      - sros2.api._write_cert\n      - sros2.api._create_smime_signed_file\n      - sros2.api._build_key_and_cert\n      - sros2.api._create_key_and_cert\n    filenames:\n      - sros2/sros2/api/__init__.py\n    classification: slightly promising\n\n  - headline: Improper validation of file paths\n    analysis: |\n      The sros2 package does not properly validate file paths used for loading and saving various files. An attacker could potentially craft malicious file paths to cause directory traversal or overwrite sensitive files on the system.\n    cwe: CWE-22\n    function_names:\n      - sros2.api.create_keystore\n      - sros2.api.create_key\n      - sros2.api.load_policy\n      - sros2.policy.load_policy\n    filenames:\n      - sros2/sros2/api/__init__.py\n      - sros2/sros2/policy/__init__.py\n    classification: very promising\n\n  - headline: Use of an insecure cryptographic algorithm or configuration\n    analysis: |\n      The sros2 package uses the EC256 elliptic curve algorithm for generating cryptographic keys. While EC256 is generally considered secure, it may not be suitable for all applications or environments. Additionally, the implementation may have insecure default configurations or use weak parameters. An attacker could potentially exploit weaknesses in the cryptographic implementation to compromise the security of the system.\n    cwe: CWE-327\n    function_names:\n      - sros2.api._build_key_and_cert\n    filenames:\n      - sros2/sros2/api/__init__.py\n    classification: slightly promising\n\n  - headline: Improper handling of exceptions\n    analysis: |\n      The sros2 package does not properly handle exceptions in some cases, leading to incomplete error handling or information disclosure. An attacker could potentially cause the application to crash or leak sensitive information through crafted input that triggers unhandled exceptions.\n    cwe: CWE-755\n    function_names:\n      - sros2.verb.create_permission.CreatePermissionVerb.main\n      - sros2.verb.generate_artifacts.GenerateArtifactsVerb.main\n    filenames:\n      - sros2/sros2/verb/create_permission.py\n      - sros2/sros2/verb/generate_artifacts.py\n    classification: slightly promising\n```\n\nThe analysis identifies several potential security vulnerabilities in the sros2 codebase, including:\n\n1. **Incorrect handling of XML entities (XXE)**: This is a critical vulnerability that could allow an attacker to read arbitrary files on the system or cause a denial of service. It is related to the `load_policy` function in the `sros2.policy` module not properly handling external entity references in XML files.\n\n2. **Use of a broken cryptographic implementation**: While the sros2 package uses the cryptography library, the specific version or configuration used may be vulnerable to various attacks, such as side-channel attacks or insecure default configurations.\n\n3. **Improper validation of file paths**: Several functions in the `sros2.api` and `sros2.policy` modules do not properly validate file paths, potentially allowing directory traversal or overwriting sensitive files.\n\n4. **Use of an insecure cryptographic algorithm or configuration**: The sros2 package uses the EC256 elliptic curve algorithm for generating cryptographic keys. While EC256 is generally considered secure, the implementation or configuration may have weaknesses that could be exploited.\n\n5. **Improper handling of exceptions**: Some functions in the `sros2.verb` module do not properly handle exceptions, leading to incomplete error handling or potential information disclosure.\n\nThe analysis provides a good starting point for further investigation and remediation of these potential vulnerabilities, with specific function names and file paths identified for each issue.",
      "date": "2024-06-14T15:28:59.923065",
      "usage": {
        "prompt_tokens": 24032,
        "completion_tokens": 1192,
        "cost": 0.089976
      }
    }
  ],
  "leads": [
    {
      "headline": "Incorrect handling of XML entities (XXE)",
      "analysis": "The sros2 package does not properly handle XML external entity references, which can enable XML External Entity (XXE) attacks. An attacker could craft a malicious XML file that includes external entity references to gain access to sensitive files on the system or cause denial of service.\n",
      "classification": "very promising",
      "cwe": "CWE-611",
      "function_names": [
        "sros2.policy.load_policy"
      ],
      "filenames": [
        "sros2/sros2/policy/__init__.py"
      ]
    },
    {
      "headline": "Use of a broken cryptographic implementation",
      "analysis": "The sros2 package uses the cryptography library, but it may be using a vulnerable or outdated version of the library. The cryptography library has had numerous vulnerabilities in the past, including side-channel attacks, insecure default configurations, and other issues related to cryptographic implementations. An attacker could potentially exploit vulnerabilities in the cryptography library to compromise the security of the system.\n",
      "classification": "slightly promising",
      "cwe": "CWE-327",
      "function_names": [
        "sros2.api._write_key",
        "sros2.api._write_cert",
        "sros2.api._create_smime_signed_file"
      ],
      "filenames": [
        "sros2/sros2/api/__init__.py"
      ]
    },
    {
      "headline": "Improper validation of file paths",
      "analysis": "The sros2 package does not properly validate file paths used for loading and saving various files. An attacker could potentially craft malicious file paths to cause directory traversal or overwrite sensitive files on the system.\n",
      "classification": "very promising",
      "cwe": "CWE-22",
      "function_names": [
        "sros2.api.create_keystore",
        "sros2.api.create_key",
        "sros2.api.load_policy"
      ],
      "filenames": [
        "sros2/sros2/api/__init__.py",
        "sros2/sros2/policy/__init__.py"
      ]
    },
    {
      "headline": "Use of an insecure cryptographic algorithm or configuration",
      "analysis": "The sros2 package uses the EC256 elliptic curve algorithm for generating cryptographic keys. While EC256 is generally considered secure, it may not be suitable for all applications or environments. Additionally, the implementation may have insecure default configurations or use weak parameters. An attacker could potentially exploit weaknesses in the cryptographic implementation to compromise the security of the system.\n",
      "classification": "slightly promising",
      "cwe": "CWE-327",
      "function_names": [
        "sros2.api._build_key_and_cert"
      ],
      "filenames": [
        "sros2/sros2/api/__init__.py"
      ]
    },
    {
      "headline": "Improper handling of exceptions",
      "analysis": "The sros2 package does not properly handle exceptions in some cases, leading to incomplete error handling or information disclosure. An attacker could potentially cause the application to crash or leak sensitive information through crafted input that triggers unhandled exceptions.\n",
      "classification": "slightly promising",
      "cwe": "CWE-755",
      "function_names": [
        "sros2.verb.create_permission.CreatePermissionVerb.main",
        "sros2.verb.generate_artifacts.GenerateArtifactsVerb.main"
      ],
      "filenames": [
        "sros2/sros2/verb/create_permission.py",
        "sros2/sros2/verb/generate_artifacts.py"
      ]
    }
  ],
  "scores": [
    {
      "stats": {
        "fn": 2,
        "tp": 0,
        "fp": 2
      },
      "mapping": {},
      "vuln_dates": {
        "CVE-2019-19625": "2019-12-06T16:15:11",
        "CVE-2019-19627": "2019-12-06T16:15:11"
      },
      "scoring_model": "claude-3-opus-20240229",
      "type": "llm",
      "instruction_template_hash": "245ace12b6361954d0a2"
    },
    {
      "stats": {
        "fn": 2,
        "tp": 0,
        "fp": 2
      },
      "mapping": {},
      "vuln_dates": {
        "CVE-2019-19625": "2019-12-06T16:15:11",
        "CVE-2019-19627": "2019-12-06T16:15:11"
      },
      "scoring_model": "claude-3-5-sonnet-20240620",
      "type": "llm",
      "instruction_template_hash": "245ace12b6361954d0a2"
    }
  ],
  "instruction_template_hash": "10c0163db4740318a544",
  "version": "0.1.0"
}
