{
  "commit": "2e71bdf10b2c719276d0cea38870afc91486aede",
  "repo_url": "https://github.com/jenkinsci/periodicbackup-plugin",
  "model": "gpt-4o-2024-05-13",
  "chunk_hashes": [
    "86b0e7811ffc9342322b"
  ],
  "responses": [
    {
      "content": "```yaml\nleads:\n  - headline: \"Potential Directory Traversal via Resources.getResource\"\n    analysis: |\n      The use of `Resources.getResource` in multiple instances can lead to directory traversal attacks if the input file path is derived from an untrusted source. This functionality is located in various test files and could enable an attacker to access unauthorized files and directories by manipulating the file paths.\n    cwe: CWE-22\n    function_names: []\n    filenames:\n      - src/test/java/org/jenkinsci/plugins/periodicbackup/NullStorageTest.java\n      - src/test/java/org/jenkinsci/plugins/periodicbackup/UtilTest.java\n      - src/test/java/org/jenkinsci/plugins/periodicbackup/TarGzStorageTest.java\n      - src/test/java/org/jenkinsci/plugins/periodicbackup/LocalDirectoryTest.java\n    classification: very promising\n  - headline: \"Missing Encryption for Sensitive Data during Backup\"\n    analysis: |\n      The current implementation does not utilize encryption to protect sensitive data during the backup process. Both `ZipStorage` and `TarGzStorage` store data in plain text, making it vulnerable to data theft and unauthorized access.\n    cwe: CWE-311\n    function_names: []\n    filenames:\n      - src/main/java/org/jenkinsci/plugins/periodicbackup/ZipStorage.java\n      - src/main/java/org/jenkinsci/plugins/periodicbackup/TarGzStorage.java\n    classification: very promising\n  - headline: \"Weak or Uncontrolled Resource Consumption\"\n    analysis: |\n      The backup process might be vulnerable to resource consumption attacks due to the lack of controls on the size and number of files being backed up, which can lead to potential denial of service (DoS) conditions. This is a concern specifically for the `backupAddFile` and `backupStart` methods.\n    cwe: CWE-400\n    function_names:\n      - backupAddFile\n      - backupStart\n    filenames:\n      - src/main/java/org/jenkinsci/plugins/periodicbackup/ZipStorage.java\n      - src/main/java/org/jenkinsci/plugins/periodicbackup/TarGzStorage.java\n    classification: slightly promising\n  - headline: \"Hardcoded Cryptographic Keys\"\n    analysis: |\n      The `ZipStorage` class has the capability for multi-volume storage size setting, but it does not use any cryptographic means to ensure the integrity or confidentiality of the data. If cryptographic keys were hardcoded, it would introduce significant security risks. \n    cwe: CWE-798\n    function_names: []\n    filenames:\n      - src/main/java/org/jenkinsci/plugins/periodicbackup/ZipStorage.java\n    classification: slightly promising\n  - headline: \"Deserialization of Untrusted Data\"\n    analysis: |\n      The `BackupObject.getFromFile()` method reads and deserializes XML data from files without validating the content, which could lead to deserialization attacks. Maliciously crafted XML files could exploit this vulnerability to execute arbitrary code.\n    cwe: CWE-502\n    function_names:\n      - getFromFile\n    filenames:\n      - src/main/java/org/jenkinsci/plugins/periodicbackup/BackupObject.java\n    classification: very promising\n```",
      "date": "2024-06-12T19:01:30.081245",
      "usage": {
        "prompt_tokens": 31758,
        "completion_tokens": 684,
        "cost": 0.16905
      }
    }
  ],
  "leads": [
    {
      "headline": "Potential Directory Traversal via Resources.getResource",
      "analysis": "The use of Resources.getResource in multiple instances can lead to directory traversal attacks if the input file path is derived from an untrusted source. This functionality is located in various test files and could enable an attacker to access unauthorized files and directories by manipulating the file paths.\n",
      "classification": "very promising",
      "cwe": "CWE-22",
      "function_names": [],
      "filenames": [
        "src/test/java/org/jenkinsci/plugins/periodicbackup/NullStorageTest.java",
        "src/test/java/org/jenkinsci/plugins/periodicbackup/UtilTest.java",
        "src/test/java/org/jenkinsci/plugins/periodicbackup/TarGzStorageTest.java"
      ]
    },
    {
      "headline": "Missing Encryption for Sensitive Data during Backup",
      "analysis": "The current implementation does not utilize encryption to protect sensitive data during the backup process. Both ZipStorage and TarGzStorage store data in plain text, making it vulnerable to data theft and unauthorized access.\n",
      "classification": "very promising",
      "cwe": "CWE-311",
      "function_names": [],
      "filenames": [
        "src/main/java/org/jenkinsci/plugins/periodicbackup/ZipStorage.java",
        "src/main/java/org/jenkinsci/plugins/periodicbackup/TarGzStorage.java"
      ]
    },
    {
      "headline": "Weak or Uncontrolled Resource Consumption",
      "analysis": "The backup process might be vulnerable to resource consumption attacks due to the lack of controls on the size and number of files being backed up, which can lead to potential denial of service (DoS) conditions. This is a concern specifically for the backupAddFile and backupStart methods.\n",
      "classification": "slightly promising",
      "cwe": "CWE-400",
      "function_names": [
        "backupAddFile",
        "backupStart"
      ],
      "filenames": [
        "src/main/java/org/jenkinsci/plugins/periodicbackup/ZipStorage.java",
        "src/main/java/org/jenkinsci/plugins/periodicbackup/TarGzStorage.java"
      ]
    },
    {
      "headline": "Hardcoded Cryptographic Keys",
      "analysis": "The ZipStorage class has the capability for multi-volume storage size setting, but it does not use any cryptographic means to ensure the integrity or confidentiality of the data. If cryptographic keys were hardcoded, it would introduce significant security risks. \n",
      "classification": "slightly promising",
      "cwe": "CWE-798",
      "function_names": [],
      "filenames": [
        "src/main/java/org/jenkinsci/plugins/periodicbackup/ZipStorage.java"
      ]
    },
    {
      "headline": "Deserialization of Untrusted Data",
      "analysis": "The BackupObject.getFromFile() method reads and deserializes XML data from files without validating the content, which could lead to deserialization attacks. Maliciously crafted XML files could exploit this vulnerability to execute arbitrary code.\n",
      "classification": "very promising",
      "cwe": "CWE-502",
      "function_names": [
        "getFromFile"
      ],
      "filenames": [
        "src/main/java/org/jenkinsci/plugins/periodicbackup/BackupObject.java"
      ]
    }
  ],
  "scores": [
    {
      "stats": {
        "fn": 1,
        "tp": 0,
        "fp": 3
      },
      "mapping": {},
      "vuln_dates": {
        "CVE-2017-1000086": "2017-10-05T01:29:03"
      },
      "scoring_model": "claude-3-opus-20240229",
      "type": "llm",
      "instruction_template_hash": "245ace12b6361954d0a2"
    }
  ],
  "instruction_template_hash": "10c0163db4740318a544",
  "version": "0.1.0"
}
