{
  "commit": "5a0d31719e2af188225cee2ff26e81938e1f43d9",
  "repo_url": "https://github.com/node-saml/xml-crypto",
  "model": "gpt-4o-2024-05-13",
  "chunk_hashes": [
    "d2e1b57146da2689dcff"
  ],
  "responses": [
    {
      "content": "```yaml\nleads:\n  - headline: \"Improper Validation of XML Signature Reference URIs\"\n    analysis: |\n      The `validateReference` method in `signed-xml.ts` assumes that the URI in the reference can be safely accessed via XPath to find the corresponding element in the XML document. It does not check for maliciously crafted URIs that include dangerous characters, such as quotes or control characters. These can lead to XPath injection attacks where an attacker can manipulate the XPath queries to retrieve unintended data or bypass signature validation.\n    cwe: \"CWE-74\"\n    function_names:\n      - \"validateReference\"\n    filenames:\n      - \"src/signed-xml.ts\"\n    classification: \"very promising\"\n  \n  - headline: \"Insufficient Validation for XML Canonicalization\"\n    analysis: |\n      The `C14nCanonicalization` and `ExclusiveCanonicalization` classes do not handle certain edge cases properly, leading to potential vulnerabilities when canonicalizing XML documents. This can result in incorrect calculations of digest values and signatures, thereby bypassing security mechanisms that rely on accurate canonical representation of XML.\n    cwe: \"CWE-20\"\n    function_names:\n      - \"processInner\"\n      - \"renderAttrs\"\n    filenames:\n      - \"src/c14n-canonicalization.ts\"\n      - \"src/exclusive-canonicalization.ts\"\n    classification: \"slightly promising\"\n    \n  - headline: \"Potential Key Information Exposure in Signature Computation\"\n    analysis: |\n      The use of both `publicCert` and `privateKey` fields interchangeably for the same functionality could result in unintended disclosure of sensitive key material, especially if private keys are accidentally included in public-facing certificate fields.\n    cwe: \"CWE-311\"\n    function_names:\n      - \"computeSignature\"\n    filenames:\n      - \"src/signed-xml.ts\"\n    classification: \"slightly promising\"\n\n  - headline: \"Weak Hash Algorithms in XML Digital Signatures\"\n    analysis: |\n      The `hash-algorithms.ts` file includes implementations of outdated and weak hash algorithms such as SHA-1 and SHA-256. These algorithms are considered insecure and their continued use can expose systems to collision and pre-image attacks, thereby compromising the integrity and authenticity of digital signatures.\n    cwe: \"CWE-327\"\n    function_names:\n      - \"Sha1\"\n      - \"Sha256\"\n    filenames:\n      - \"src/hash-algorithms.ts\"\n    classification: \"very promising\"\n    \n  - headline: \"HMAC Keys Usage Without Proper Restrictions\"\n    analysis: |\n      The `HmacSha1` class in `signature-algorithms.ts` allows for the use of HMAC (Hash-based Message Authentication Code) keys without enforcing proper key restrictions. This can lead to weakened security as poorly managed or weak keys can be exploited by attackers to forge messages or bypass authentication.\n    cwe: \"CWE-521\"\n    function_names:\n      - \"HmacSha1\"\n    filenames:\n      - \"src/signature-algorithms.ts\"\n    classification: \"slightly promising\"\n```",
      "date": "2024-06-09T13:51:21.270737",
      "usage": {
        "prompt_tokens": 64562,
        "completion_tokens": 637,
        "cost": 0.332365
      }
    }
  ],
  "leads": [
    {
      "headline": "Improper Validation of XML Signature Reference URIs",
      "analysis": "The validateReference method in signed-xml.ts assumes that the URI in the reference can be safely accessed via XPath to find the corresponding element in the XML document. It does not check for maliciously crafted URIs that include dangerous characters, such as quotes or control characters. These can lead to XPath injection attacks where an attacker can manipulate the XPath queries to retrieve unintended data or bypass signature validation.\n",
      "classification": "very promising",
      "cwe": "CWE-74",
      "function_names": [
        "validateReference"
      ],
      "filenames": [
        "src/signed-xml.ts"
      ]
    },
    {
      "headline": "Insufficient Validation for XML Canonicalization",
      "analysis": "The C14nCanonicalization and ExclusiveCanonicalization classes do not handle certain edge cases properly, leading to potential vulnerabilities when canonicalizing XML documents. This can result in incorrect calculations of digest values and signatures, thereby bypassing security mechanisms that rely on accurate canonical representation of XML.\n",
      "classification": "slightly promising",
      "cwe": "CWE-20",
      "function_names": [
        "processInner",
        "renderAttrs"
      ],
      "filenames": [
        "src/c14n-canonicalization.ts",
        "src/exclusive-canonicalization.ts"
      ]
    },
    {
      "headline": "Potential Key Information Exposure in Signature Computation",
      "analysis": "The use of both publicCert and privateKey fields interchangeably for the same functionality could result in unintended disclosure of sensitive key material, especially if private keys are accidentally included in public-facing certificate fields.\n",
      "classification": "slightly promising",
      "cwe": "CWE-311",
      "function_names": [
        "computeSignature"
      ],
      "filenames": [
        "src/signed-xml.ts"
      ]
    },
    {
      "headline": "Weak Hash Algorithms in XML Digital Signatures",
      "analysis": "The hash-algorithms.ts file includes implementations of outdated and weak hash algorithms such as SHA-1 and SHA-256. These algorithms are considered insecure and their continued use can expose systems to collision and pre-image attacks, thereby compromising the integrity and authenticity of digital signatures.\n",
      "classification": "very promising",
      "cwe": "CWE-327",
      "function_names": [
        "Sha1",
        "Sha256"
      ],
      "filenames": [
        "src/hash-algorithms.ts"
      ]
    },
    {
      "headline": "HMAC Keys Usage Without Proper Restrictions",
      "analysis": "The HmacSha1 class in signature-algorithms.ts allows for the use of HMAC (Hash-based Message Authentication Code) keys without enforcing proper key restrictions. This can lead to weakened security as poorly managed or weak keys can be exploited by attackers to forge messages or bypass authentication.\n",
      "classification": "slightly promising",
      "cwe": "CWE-521",
      "function_names": [
        "HmacSha1"
      ],
      "filenames": [
        "src/signature-algorithms.ts"
      ]
    }
  ],
  "scores": [
    {
      "stats": {
        "fn": 1,
        "tp": 0,
        "fp": 2
      },
      "mapping": {},
      "vuln_dates": {
        "CVE-2024-32962": "2024-05-02T07:15:21"
      },
      "scoring_model": "gpt-4o-2024-05-13",
      "type": "llm",
      "instruction_template_hash": "8998f09cf57fca8a6e03"
    },
    {
      "stats": {
        "fn": 1,
        "tp": 0,
        "fp": 2
      },
      "mapping": {},
      "vuln_dates": {
        "CVE-2024-32962": "2024-05-02T07:15:21"
      },
      "scoring_model": "claude-3-opus-20240229",
      "type": "llm",
      "instruction_template_hash": "245ace12b6361954d0a2"
    }
  ],
  "instruction_template_hash": "10c0163db4740318a544",
  "version": "0.1.0"
}
