{
  "commit": "2cd9997382a9d29e97806fce9086f83409cb077e",
  "repo_url": "https://github.com/jenkinsci/mantis-plugin",
  "model": "claude-3-haiku-20240307",
  "chunk_hashes": [
    "e56a63e502f475750918"
  ],
  "responses": [
    {
      "content": "Here is the YAML object equivalent to type LeadList, based on the provided Pydantic definitions, with the identified security vulnerabilities:\n\n```yaml\nleads:\n  - headline: Improper Neutralization of Special Elements in Output Used by a Downstream Component ('Injection')\n    analysis: |\n      The codebase contains instances of improper neutralization of special elements in output, which can lead to injection vulnerabilities. This includes potential command injection, SQL injection, XML injection, and expression language injection. The affected functions and files are not clearly mapped to specific vulnerabilities, so further investigation and testing would be required to develop a proof-of-concept exploit.\n    cwe: CWE-74\n    function_names:\n      - Utility.escapeRegexp\n      - MantisSite.getIssue\n      - MantisSite.updateIssue\n      - MantisSite.addIssue\n    filenames:\n      - src/main/java/hudson/plugins/mantis/Utility.java\n      - src/main/java/hudson/plugins/mantis/MantisSite.java\n      - src/main/java/hudson/plugins/mantis/soap/mantis110/MantisSessionImpl.java\n      - src/main/java/hudson/plugins/mantis/soap/mantis120/MantisSessionImpl.java\n    classification: slightly promising\n\n  - headline: Improper Restriction of Operations within the Bounds of a Memory Buffer\n    analysis: |\n      The codebase contains instances of improper restriction of operations within the bounds of a memory buffer, which can lead to buffer overflow and out-of-bounds read/write vulnerabilities. The affected functions and files are not clearly mapped to specific vulnerabilities, so further investigation and testing would be required to develop a proof-of-concept exploit.\n    cwe: CWE-119\n    function_names:\n      - MantisIssueRegister.createIssue\n    filenames:\n      - src/main/java/hudson/plugins/mantis/MantisIssueRegister.java\n    classification: slightly promising\n\n  - headline: Improper Authentication\n    analysis: |\n      The codebase contains instances of improper authentication, which can lead to authentication bypass vulnerabilities. This includes potential issues with certificate validation, excessive authentication attempts, and use of hard-coded credentials. The affected functions and files are not clearly mapped to specific vulnerabilities, so further investigation and testing would be required to develop a proof-of-concept exploit.\n    cwe: CWE-287\n    function_names:\n      - MantisSite.isConnect\n      - MantisSite.createSession\n    filenames:\n      - src/main/java/hudson/plugins/mantis/MantisSite.java\n      - src/main/java/hudson/plugins/mantis/soap/AbstractMantisSession.java\n      - src/main/java/hudson/plugins/mantis/soap/mantis110/MantisSessionImpl.java\n      - src/main/java/hudson/plugins/mantis/soap/mantis120/MantisSessionImpl.java\n    classification: slightly promising\n\n  - headline: Externally Controlled Reference to a Resource in Another Sphere\n    analysis: |\n      The codebase contains instances of externally controlled references to resources in another sphere, which can lead to vulnerabilities such as open redirect, XML external entity (XXE) injection, and server-side request forgery (SSRF). The affected functions and files are not clearly mapped to specific vulnerabilities, so further investigation and testing would be required to develop a proof-of-concept exploit.\n    cwe: CWE-610\n    function_names:\n      - MantisLinkAnnotator.annotate\n    filenames:\n      - src/main/java/hudson/plugins/mantis/MantisLinkAnnotator.java\n    classification: slightly promising\n\n  - headline: Incorrect Resource Transfer Between Spheres\n    analysis: |\n      The codebase contains instances of incorrect resource transfer between spheres, which can lead to vulnerabilities such as sensitive information disclosure, unrestricted file upload, and inclusion of untrusted functionality. The affected functions and files are not clearly mapped to specific vulnerabilities, so further investigation and testing would be required to develop a proof-of-concept exploit.\n    cwe: CWE-669\n    function_names:\n      - MantisIssueRegister.createIssue\n    filenames:\n      - src/main/java/hudson/plugins/mantis/MantisIssueRegister.java\n    classification: slightly promising\n```",
      "date": "2024-06-12T18:49:20.729512",
      "usage": {
        "prompt_tokens": 32323,
        "completion_tokens": 1059,
        "cost": 0.0094045
      }
    }
  ],
  "leads": [
    {
      "headline": "Improper Neutralization of Special Elements in Output Used by a Downstream Component ('Injection')",
      "analysis": "The codebase contains instances of improper neutralization of special elements in output, which can lead to injection vulnerabilities. This includes potential command injection, SQL injection, XML injection, and expression language injection. The affected functions and files are not clearly mapped to specific vulnerabilities, so further investigation and testing would be required to develop a proof-of-concept exploit.\n",
      "classification": "slightly promising",
      "cwe": "CWE-74",
      "function_names": [
        "Utility.escapeRegexp",
        "MantisSite.getIssue",
        "MantisSite.updateIssue"
      ],
      "filenames": [
        "src/main/java/hudson/plugins/mantis/Utility.java",
        "src/main/java/hudson/plugins/mantis/MantisSite.java",
        "src/main/java/hudson/plugins/mantis/soap/mantis110/MantisSessionImpl.java"
      ]
    },
    {
      "headline": "Improper Restriction of Operations within the Bounds of a Memory Buffer",
      "analysis": "The codebase contains instances of improper restriction of operations within the bounds of a memory buffer, which can lead to buffer overflow and out-of-bounds read/write vulnerabilities. The affected functions and files are not clearly mapped to specific vulnerabilities, so further investigation and testing would be required to develop a proof-of-concept exploit.\n",
      "classification": "slightly promising",
      "cwe": "CWE-119",
      "function_names": [
        "MantisIssueRegister.createIssue"
      ],
      "filenames": [
        "src/main/java/hudson/plugins/mantis/MantisIssueRegister.java"
      ]
    },
    {
      "headline": "Improper Authentication",
      "analysis": "The codebase contains instances of improper authentication, which can lead to authentication bypass vulnerabilities. This includes potential issues with certificate validation, excessive authentication attempts, and use of hard-coded credentials. The affected functions and files are not clearly mapped to specific vulnerabilities, so further investigation and testing would be required to develop a proof-of-concept exploit.\n",
      "classification": "slightly promising",
      "cwe": "CWE-287",
      "function_names": [
        "MantisSite.isConnect",
        "MantisSite.createSession"
      ],
      "filenames": [
        "src/main/java/hudson/plugins/mantis/MantisSite.java",
        "src/main/java/hudson/plugins/mantis/soap/AbstractMantisSession.java",
        "src/main/java/hudson/plugins/mantis/soap/mantis110/MantisSessionImpl.java"
      ]
    },
    {
      "headline": "Externally Controlled Reference to a Resource in Another Sphere",
      "analysis": "The codebase contains instances of externally controlled references to resources in another sphere, which can lead to vulnerabilities such as open redirect, XML external entity (XXE) injection, and server-side request forgery (SSRF). The affected functions and files are not clearly mapped to specific vulnerabilities, so further investigation and testing would be required to develop a proof-of-concept exploit.\n",
      "classification": "slightly promising",
      "cwe": "CWE-610",
      "function_names": [
        "MantisLinkAnnotator.annotate"
      ],
      "filenames": [
        "src/main/java/hudson/plugins/mantis/MantisLinkAnnotator.java"
      ]
    },
    {
      "headline": "Incorrect Resource Transfer Between Spheres",
      "analysis": "The codebase contains instances of incorrect resource transfer between spheres, which can lead to vulnerabilities such as sensitive information disclosure, unrestricted file upload, and inclusion of untrusted functionality. The affected functions and files are not clearly mapped to specific vulnerabilities, so further investigation and testing would be required to develop a proof-of-concept exploit.\n",
      "classification": "slightly promising",
      "cwe": "CWE-669",
      "function_names": [
        "MantisIssueRegister.createIssue"
      ],
      "filenames": [
        "src/main/java/hudson/plugins/mantis/MantisIssueRegister.java"
      ]
    }
  ],
  "scores": [
    {
      "stats": {
        "fn": 1,
        "tp": 0,
        "fp": 0
      },
      "mapping": {},
      "vuln_dates": {
        "CVE-2019-16569": "2019-12-17T15:15:22"
      },
      "scoring_model": "claude-3-opus-20240229",
      "type": "llm",
      "instruction_template_hash": "245ace12b6361954d0a2"
    },
    {
      "stats": {
        "fn": 1,
        "tp": 0,
        "fp": 0
      },
      "mapping": {},
      "vuln_dates": {
        "CVE-2019-16569": "2019-12-17T15:15:22"
      },
      "scoring_model": "claude-3-5-sonnet-20240620",
      "type": "llm",
      "instruction_template_hash": "245ace12b6361954d0a2"
    }
  ],
  "instruction_template_hash": "10c0163db4740318a544",
  "version": "0.1.0"
}
