{
  "commit": "14c85144f2f1c45f938ce5257f30311fa1b11480",
  "repo_url": "https://github.com/csaf-tools/cvrf-csaf-converter",
  "model": "claude-3-5-sonnet-20240620",
  "chunk_hashes": [
    "9dba9213b8fe8389a18f"
  ],
  "responses": [
    {
      "content": "```yaml\nleads:\n  - headline: Command injection vulnerability in setup.py\n    analysis: |\n      The setup.py file uses subprocess.check_output() to execute a git command and get the version number. This command is executed with shell=True by default, which can allow command injection if an attacker can control the git repository or working directory. An attacker could potentially execute arbitrary commands by manipulating the git repository to return malicious data that gets executed as part of the shell command.\n    cwe: CWE-78\n    function_names:\n      - get_version\n    filenames:\n      - setup.py\n    classification: very promising\n\n  - headline: Use of hard-coded credentials in cvrf2csaf.py\n    analysis: |\n      The cvrf2csaf.py file contains references to hard-coded credentials in the form of XML catalog files. Specifically, the CATALOG_FILE constant points to a hard-coded catalog file path. This could potentially contain sensitive information or credentials. Hard-coded credentials are a security risk as they can be discovered through reverse engineering and cannot be easily changed.\n    cwe: CWE-798\n    function_names:\n      - DocumentHandler\n    filenames:  \n      - cvrf2csaf/cvrf2csaf.py\n    classification: slightly promising\n\n  - headline: Potential XML external entity injection in cvrf2csaf.py\n    analysis: |\n      The cvrf2csaf.py file uses lxml to parse XML input. By default, lxml is vulnerable to XML external entity (XXE) injection attacks. The code does not explicitly disable external entity processing, which could allow an attacker to include external entities and potentially access sensitive files on the system or perform other malicious actions. This vulnerability requires crafted XML input to exploit.\n    cwe: CWE-611\n    function_names:\n      - _open_and_validate_file\n    filenames:\n      - cvrf2csaf/cvrf2csaf.py  \n    classification: slightly promising\n\n  - headline: Unsafe deserialization of YAML config in utils.py\n    analysis: |\n      The utils.py file uses yaml.safe_load() to parse YAML configuration data. While safer than yaml.load(), this still allows deserialization of custom Python objects which could lead to arbitrary code execution if an attacker can control the YAML input. A safer approach would be to use yaml.safe_load() with explicitly allowed tags.\n    cwe: CWE-502\n    function_names:\n      - get_config_from_file\n    filenames:\n      - cvrf2csaf/common/utils.py\n    classification: slightly promising\n\n  - headline: Insufficient input validation on version string in document_tracking.py\n    analysis: |\n      The document_tracking.py file uses a regular expression to validate version strings, but the regex is not strict enough. It allows arbitrary strings between dots, which could potentially lead to unexpected behavior or crashes if given malformed input. A stricter regex or additional validation should be used to ensure only valid version strings are accepted.\n    cwe: CWE-20\n    function_names:\n      - check_for_version_t\n    filenames:\n      - cvrf2csaf/section_handlers/document_tracking.py\n    classification: slightly promising\n```",
      "date": "2024-07-08T05:56:21.697668",
      "usage": {
        "prompt_tokens": 21690,
        "completion_tokens": 749,
        "cost": 0.076305
      }
    }
  ],
  "leads": [
    {
      "headline": "Command injection vulnerability in setup.py",
      "analysis": "The setup.py file uses subprocess.check_output() to execute a git command and get the version number. This command is executed with shell=True by default, which can allow command injection if an attacker can control the git repository or working directory. An attacker could potentially execute arbitrary commands by manipulating the git repository to return malicious data that gets executed as part of the shell command.\n",
      "classification": "very promising",
      "cwe": "CWE-78",
      "function_names": [
        "get_version"
      ],
      "filenames": [
        "setup.py"
      ]
    },
    {
      "headline": "Use of hard-coded credentials in cvrf2csaf.py",
      "analysis": "The cvrf2csaf.py file contains references to hard-coded credentials in the form of XML catalog files. Specifically, the CATALOG_FILE constant points to a hard-coded catalog file path. This could potentially contain sensitive information or credentials. Hard-coded credentials are a security risk as they can be discovered through reverse engineering and cannot be easily changed.\n",
      "classification": "slightly promising",
      "cwe": "CWE-798",
      "function_names": [
        "DocumentHandler"
      ],
      "filenames": [
        "cvrf2csaf/cvrf2csaf.py"
      ]
    },
    {
      "headline": "Potential XML external entity injection in cvrf2csaf.py",
      "analysis": "The cvrf2csaf.py file uses lxml to parse XML input. By default, lxml is vulnerable to XML external entity (XXE) injection attacks. The code does not explicitly disable external entity processing, which could allow an attacker to include external entities and potentially access sensitive files on the system or perform other malicious actions. This vulnerability requires crafted XML input to exploit.\n",
      "classification": "slightly promising",
      "cwe": "CWE-611",
      "function_names": [
        "_open_and_validate_file"
      ],
      "filenames": [
        "cvrf2csaf/cvrf2csaf.py"
      ]
    },
    {
      "headline": "Unsafe deserialization of YAML config in utils.py",
      "analysis": "The utils.py file uses yaml.safe_load() to parse YAML configuration data. While safer than yaml.load(), this still allows deserialization of custom Python objects which could lead to arbitrary code execution if an attacker can control the YAML input. A safer approach would be to use yaml.safe_load() with explicitly allowed tags.\n",
      "classification": "slightly promising",
      "cwe": "CWE-502",
      "function_names": [
        "get_config_from_file"
      ],
      "filenames": [
        "cvrf2csaf/common/utils.py"
      ]
    },
    {
      "headline": "Insufficient input validation on version string in document_tracking.py",
      "analysis": "The document_tracking.py file uses a regular expression to validate version strings, but the regex is not strict enough. It allows arbitrary strings between dots, which could potentially lead to unexpected behavior or crashes if given malformed input. A stricter regex or additional validation should be used to ensure only valid version strings are accepted.\n",
      "classification": "slightly promising",
      "cwe": "CWE-20",
      "function_names": [
        "check_for_version_t"
      ],
      "filenames": [
        "cvrf2csaf/section_handlers/document_tracking.py"
      ]
    }
  ],
  "scores": [
    {
      "stats": {
        "fn": 1,
        "tp": 0,
        "fp": 1
      },
      "mapping": {},
      "vuln_dates": {
        "CVE-2022-27193": "2022-03-15T05:15:07"
      },
      "scoring_model": "claude-3-5-sonnet-20240620",
      "type": "llm",
      "instruction_template_hash": "245ace12b6361954d0a2"
    }
  ],
  "instruction_template_hash": "10c0163db4740318a544",
  "version": "0.1.0"
}
