{
  "commit": "3ad12658bb91c5f6fb7d36e43d70ed7be0803354",
  "repo_url": "https://github.com/jenkinsci/backlog-plugin",
  "model": "claude-3-sonnet-20240229",
  "chunk_hashes": [
    "c149f6299a1da05009de"
  ],
  "responses": [
    {
      "content": "```yaml\nleads:\n  - headline: Improper Restriction of Operations within the Bounds of a Memory Buffer\n    analysis: |\n      The codebase appears to be using FilePath objects, which represent filesystem paths, to read and write data. While this does not directly lead to a vulnerability, it is possible that mishandling these FilePath objects could result in Out-of-bounds Read (CWE-125) or Out-of-bounds Write (CWE-787) vulnerabilities if the paths are not properly validated or sanitized. However, no specific instances of this vulnerability were identified in the provided code.\n    cwe: CWE-119\n    function_names: []\n    filenames:\n      - src/main/java/hudson/plugins/backlog/webdav/FilePathEntity.java\n      - src/main/java/hudson/plugins/backlog/webdav/WebdavClient.java\n    classification: slightly promising\n\n  - headline: Improper Neutralization of Special Elements used in an Expression Language Statement ('Expression Language Injection')\n    analysis: |\n      The codebase includes functionality for marking up text and creating hyperlinks using regular expressions. The BacklogChangelogAnnotator class uses a regular expression pattern (ISSUE_KEY_PATTERN) to identify issue keys in commit messages and create hyperlinks for them. If the issue key pattern is not properly validated or sanitized, it could potentially lead to Expression Language Injection (CWE-917) vulnerabilities. However, no specific instances of this vulnerability were identified in the provided code.\n    cwe: CWE-917\n    function_names:\n      - annotate\n    filenames:\n      - src/main/java/hudson/plugins/backlog/BacklogChangelogAnnotator.java\n    classification: slightly promising\n\n  - headline: Improper Validation of Array Index\n    analysis: |\n      The codebase does not appear to contain any specific instances of Improper Validation of Array Index (CWE-129) vulnerabilities. However, it is worth noting that the codebase includes functionality for handling file paths and Git repositories, which could potentially lead to such vulnerabilities if the input data is not properly validated or sanitized.\n    cwe: CWE-129\n    function_names: []\n    filenames: []\n    classification: not promising\n\n  - headline: Use of Hard-coded Credentials\n    analysis: |\n      The BacklogSecurityRealm class in the codebase appears to use hard-coded credentials for authentication with the Backlog API. Specifically, the canLogin method uses the provided username and password to make an HTTP request to the Backlog API endpoint. While this functionality may be intended for testing or demonstration purposes, using hard-coded credentials in production code can lead to Use of Hard-coded Credentials (CWE-798) vulnerabilities if the credentials are compromised.\n    cwe: CWE-798\n    function_names:\n      - canLogin\n    filenames:\n      - src/main/java/hudson/plugins/backlog/BacklogSecurityRealm.java\n    classification: very promising\n\n  - headline: Improper Restriction of Rendered UI Layers or Frames\n    analysis: |\n      The codebase includes functionality for rendering user interface elements, such as displaying pull request information and links in the Jenkins UI. While the provided code does not contain any specific instances of Improper Restriction of Rendered UI Layers or Frames (CWE-1021) vulnerabilities, it is important to ensure that any user input or data displayed in the UI is properly sanitized and validated to prevent potential security issues like Cross-Site Scripting (XSS) or Cross-Site Request Forgery (CSRF).\n    cwe: CWE-1021\n    function_names: []\n    filenames:\n      - src/main/java/hudson/plugins/backlog/pipeline/BacklogPullRequestBranchProperty.java\n      - src/main/java/hudson/plugins/backlog/pipeline/BacklogPullRequestLinkAction.java\n    classification: slightly promising\n```\n\nThe analysis identified a few potential security vulnerabilities in the codebase:\n\n1. **Improper Restriction of Operations within the Bounds of a Memory Buffer (CWE-119)**: This vulnerability is related to the handling of FilePath objects, which represent filesystem paths. While no specific instances were found, improper validation or sanitization of these paths could potentially lead to Out-of-bounds Read or Out-of-bounds Write vulnerabilities.\n\n2. **Improper Neutralization of Special Elements used in an Expression Language Statement ('Expression Language Injection') (CWE-917)**: The BacklogChangelogAnnotator class uses a regular expression pattern to identify issue keys and create hyperlinks. If this pattern is not properly validated or sanitized, it could potentially lead to Expression Language Injection vulnerabilities.\n\n3. **Use of Hard-coded Credentials (CWE-798)**: The BacklogSecurityRealm class appears to use hard-coded credentials for authentication with the Backlog API, which can be a significant security risk if the credentials are compromised.\n\n4. **Improper Restriction of Rendered UI Layers or Frames (CWE-1021)**: While no specific instances were found, the codebase includes functionality for rendering user interface elements. Any user input or data displayed in the UI should be properly sanitized and validated to prevent potential security issues like Cross-Site Scripting (XSS) or Cross-Site Request Forgery (CSRF).\n\nThe analysis also identified two other potential vulnerabilities classified as \"slightly promising\":\n\n- **Improper Validation of Array Index (CWE-129)**: No specific instances were found, but the codebase handles file paths and Git repositories, which could potentially lead to such vulnerabilities if the input data is not properly validated or sanitized.\n\n- **Improper Neutralization of Special Elements used in an Expression Language Statement ('Expression Language Injection') (CWE-917)**: This vulnerability is related to the regular expression pattern used for identifying issue keys, as mentioned earlier.\n\nOverall, the analysis highlights the importance of proper input validation, sanitization, and secure handling of sensitive data, such as credentials, to mitigate potential security vulnerabilities in the codebase.",
      "date": "2024-06-14T14:05:52.324405",
      "usage": {
        "prompt_tokens": 36700,
        "completion_tokens": 1418,
        "cost": 0.13137
      }
    }
  ],
  "leads": [
    {
      "headline": "Improper Restriction of Operations within the Bounds of a Memory Buffer",
      "analysis": "The codebase appears to be using FilePath objects, which represent filesystem paths, to read and write data. While this does not directly lead to a vulnerability, it is possible that mishandling these FilePath objects could result in Out-of-bounds Read (CWE-125) or Out-of-bounds Write (CWE-787) vulnerabilities if the paths are not properly validated or sanitized. However, no specific instances of this vulnerability were identified in the provided code.\n",
      "classification": "slightly promising",
      "cwe": "CWE-119",
      "function_names": [],
      "filenames": [
        "src/main/java/hudson/plugins/backlog/webdav/FilePathEntity.java",
        "src/main/java/hudson/plugins/backlog/webdav/WebdavClient.java"
      ]
    },
    {
      "headline": "Improper Neutralization of Special Elements used in an Expression Language Statement ('Expression Language Injection')",
      "analysis": "The codebase includes functionality for marking up text and creating hyperlinks using regular expressions. The BacklogChangelogAnnotator class uses a regular expression pattern (ISSUE_KEY_PATTERN) to identify issue keys in commit messages and create hyperlinks for them. If the issue key pattern is not properly validated or sanitized, it could potentially lead to Expression Language Injection (CWE-917) vulnerabilities. However, no specific instances of this vulnerability were identified in the provided code.\n",
      "classification": "slightly promising",
      "cwe": "CWE-917",
      "function_names": [
        "annotate"
      ],
      "filenames": [
        "src/main/java/hudson/plugins/backlog/BacklogChangelogAnnotator.java"
      ]
    },
    {
      "headline": "Improper Validation of Array Index",
      "analysis": "The codebase does not appear to contain any specific instances of Improper Validation of Array Index (CWE-129) vulnerabilities. However, it is worth noting that the codebase includes functionality for handling file paths and Git repositories, which could potentially lead to such vulnerabilities if the input data is not properly validated or sanitized.\n",
      "classification": "not promising",
      "cwe": "CWE-129",
      "function_names": [],
      "filenames": []
    },
    {
      "headline": "Use of Hard-coded Credentials",
      "analysis": "The BacklogSecurityRealm class in the codebase appears to use hard-coded credentials for authentication with the Backlog API. Specifically, the canLogin method uses the provided username and password to make an HTTP request to the Backlog API endpoint. While this functionality may be intended for testing or demonstration purposes, using hard-coded credentials in production code can lead to Use of Hard-coded Credentials (CWE-798) vulnerabilities if the credentials are compromised.\n",
      "classification": "very promising",
      "cwe": "CWE-798",
      "function_names": [
        "canLogin"
      ],
      "filenames": [
        "src/main/java/hudson/plugins/backlog/BacklogSecurityRealm.java"
      ]
    },
    {
      "headline": "Improper Restriction of Rendered UI Layers or Frames",
      "analysis": "The codebase includes functionality for rendering user interface elements, such as displaying pull request information and links in the Jenkins UI. While the provided code does not contain any specific instances of Improper Restriction of Rendered UI Layers or Frames (CWE-1021) vulnerabilities, it is important to ensure that any user input or data displayed in the UI is properly sanitized and validated to prevent potential security issues like Cross-Site Scripting (XSS) or Cross-Site Request Forgery (CSRF).\n",
      "classification": "slightly promising",
      "cwe": "CWE-1021",
      "function_names": [],
      "filenames": [
        "src/main/java/hudson/plugins/backlog/pipeline/BacklogPullRequestBranchProperty.java",
        "src/main/java/hudson/plugins/backlog/pipeline/BacklogPullRequestLinkAction.java"
      ]
    }
  ],
  "scores": [
    {
      "stats": {
        "fn": 1,
        "tp": 0,
        "fp": 1
      },
      "mapping": {},
      "vuln_dates": {
        "CVE-2020-2153": "2020-03-09T16:15:14"
      },
      "scoring_model": "claude-3-opus-20240229",
      "type": "llm",
      "instruction_template_hash": "245ace12b6361954d0a2"
    }
  ],
  "instruction_template_hash": "10c0163db4740318a544",
  "version": "0.1.0"
}
