{
  "commit": "20d419f21ebb7d43500fbf9c872457553562f35a",
  "repo_url": "https://github.com/reg-viz/reg-suit",
  "model": "claude-3-5-sonnet-20240620",
  "chunk_hashes": [
    "4666f3e950a20195cbe4"
  ],
  "responses": [
    {
      "content": "```yaml\nleads:\n  - headline: Insecure S3 bucket configuration\n    analysis: |\n      The S3BucketPreparer class in s3-bucket-preparer.ts creates an S3 bucket with a policy that allows public read access to all objects. This is done by setting the ACL to \"public-read\" and adding a policy that grants s3:GetObject permission to all principals (*). While this allows easy access to published reports, it also exposes all data in the bucket publicly which could lead to unauthorized access or data leaks if sensitive information is accidentally uploaded.\n    cwe: CWE-284\n    function_names:\n      - _createBucket\n      - _updatePolicy  \n    filenames:\n      - packages/reg-publish-s3-plugin/src/s3-bucket-preparer.ts\n    classification: very promising\n\n  - headline: Hardcoded AWS credentials\n    analysis: |\n      The S3PublisherPlugin class in s3-publisher-plugin.ts initializes an S3 client without explicitly providing credentials. This likely relies on hardcoded or environment variable AWS credentials, which is not a secure practice. If the credentials are compromised, an attacker could gain access to the S3 bucket and its contents. A more secure approach would be to use temporary credentials or IAM roles.\n    cwe: CWE-798\n    function_names:\n      - init\n    filenames:  \n      - packages/reg-publish-s3-plugin/src/s3-publisher-plugin.ts\n    classification: very promising\n\n  - headline: Lack of input validation on S3 key names\n    analysis: |\n      The uploadItem and downloadItem methods in s3-publisher-plugin.ts do not validate or sanitize the key names used for S3 objects. This could potentially allow path traversal or injection of unexpected characters if the key names are derived from user input. An attacker could potentially access or overwrite unintended files in the S3 bucket.\n    cwe: CWE-20\n    function_names:\n      - uploadItem\n      - downloadItem\n    filenames:\n      - packages/reg-publish-s3-plugin/src/s3-publisher-plugin.ts  \n    classification: slightly promising\n\n  - headline: Use of weak cryptographic algorithm\n    analysis: |\n      The uploadItem method in s3-publisher-plugin.ts uses gzip compression on uploaded files. While gzip provides some obfuscation, it is not a cryptographically secure encryption algorithm. Sensitive data uploaded to S3 would not be adequately protected. A stronger encryption algorithm should be used if data confidentiality is required.\n    cwe: CWE-327\n    function_names:\n      - uploadItem\n    filenames:\n      - packages/reg-publish-s3-plugin/src/s3-publisher-plugin.ts\n    classification: slightly promising\n\n  - headline: Potential command injection in CLI arguments\n    analysis: |\n      The cli.ts file processes command line arguments without proper sanitization. If these arguments are passed to shell commands or APIs, it could allow command injection attacks. An attacker could potentially execute arbitrary commands by crafting malicious input. The yargs library used for parsing does provide some protection, but additional validation may be needed depending on how the arguments are used.\n    cwe: CWE-77\n    function_names: []\n    filenames:\n      - packages/reg-suit-cli/src/cli.ts  \n    classification: slightly promising\n```",
      "date": "2024-07-08T08:22:46.495436",
      "usage": {
        "prompt_tokens": 61344,
        "completion_tokens": 805,
        "cost": 0.196107
      }
    }
  ],
  "leads": [
    {
      "headline": "Insecure S3 bucket configuration",
      "analysis": "The S3BucketPreparer class in s3-bucket-preparer.ts creates an S3 bucket with a policy that allows public read access to all objects. This is done by setting the ACL to \"public-read\" and adding a policy that grants s3:GetObject permission to all principals (*). While this allows easy access to published reports, it also exposes all data in the bucket publicly which could lead to unauthorized access or data leaks if sensitive information is accidentally uploaded.\n",
      "classification": "very promising",
      "cwe": "CWE-284",
      "function_names": [
        "_createBucket",
        "_updatePolicy"
      ],
      "filenames": [
        "packages/reg-publish-s3-plugin/src/s3-bucket-preparer.ts"
      ]
    },
    {
      "headline": "Hardcoded AWS credentials",
      "analysis": "The S3PublisherPlugin class in s3-publisher-plugin.ts initializes an S3 client without explicitly providing credentials. This likely relies on hardcoded or environment variable AWS credentials, which is not a secure practice. If the credentials are compromised, an attacker could gain access to the S3 bucket and its contents. A more secure approach would be to use temporary credentials or IAM roles.\n",
      "classification": "very promising",
      "cwe": "CWE-798",
      "function_names": [
        "init"
      ],
      "filenames": [
        "packages/reg-publish-s3-plugin/src/s3-publisher-plugin.ts"
      ]
    },
    {
      "headline": "Lack of input validation on S3 key names",
      "analysis": "The uploadItem and downloadItem methods in s3-publisher-plugin.ts do not validate or sanitize the key names used for S3 objects. This could potentially allow path traversal or injection of unexpected characters if the key names are derived from user input. An attacker could potentially access or overwrite unintended files in the S3 bucket.\n",
      "classification": "slightly promising",
      "cwe": "CWE-20",
      "function_names": [
        "uploadItem",
        "downloadItem"
      ],
      "filenames": [
        "packages/reg-publish-s3-plugin/src/s3-publisher-plugin.ts"
      ]
    },
    {
      "headline": "Use of weak cryptographic algorithm",
      "analysis": "The uploadItem method in s3-publisher-plugin.ts uses gzip compression on uploaded files. While gzip provides some obfuscation, it is not a cryptographically secure encryption algorithm. Sensitive data uploaded to S3 would not be adequately protected. A stronger encryption algorithm should be used if data confidentiality is required.\n",
      "classification": "slightly promising",
      "cwe": "CWE-327",
      "function_names": [
        "uploadItem"
      ],
      "filenames": [
        "packages/reg-publish-s3-plugin/src/s3-publisher-plugin.ts"
      ]
    },
    {
      "headline": "Potential command injection in CLI arguments",
      "analysis": "The cli.ts file processes command line arguments without proper sanitization. If these arguments are passed to shell commands or APIs, it could allow command injection attacks. An attacker could potentially execute arbitrary commands by crafting malicious input. The yargs library used for parsing does provide some protection, but additional validation may be needed depending on how the arguments are used.\n",
      "classification": "slightly promising",
      "cwe": "CWE-77",
      "function_names": [],
      "filenames": [
        "packages/reg-suit-cli/src/cli.ts"
      ]
    }
  ],
  "scores": [
    {
      "stats": {
        "fn": 1,
        "tp": 0,
        "fp": 2
      },
      "mapping": {},
      "vuln_dates": {
        "CVE-2021-32673": "2021-06-08T17:15:07"
      },
      "scoring_model": "claude-3-5-sonnet-20240620",
      "type": "llm",
      "instruction_template_hash": "245ace12b6361954d0a2"
    }
  ],
  "instruction_template_hash": "10c0163db4740318a544",
  "version": "0.1.0"
}
