{
  "commit": "140314ff47a72ee5a7c73d0c2d4573ef1cdb06f1",
  "repo_url": "https://github.com/nuxtlabs/github-module",
  "model": "claude-3-haiku-20240307",
  "chunk_hashes": [
    "6a7dac3130f673f0e254"
  ],
  "responses": [
    {
      "content": "Here is the YAML output for the security vulnerabilities found in the codebase:\n\n```yaml\nleads:\n  - headline: Improper Neutralization of Special Elements used in an OS Command ('OS Command Injection')\n    analysis: |\n      The codebase contains several instances where user-provided input is used to construct OS commands without proper sanitization. This could allow an attacker to inject malicious commands that would be executed on the server. Specifically, the `fetchCommits` function in `src/runtime/server/utils/queries.ts` constructs a GraphQL query using user-provided `source` parameter, which could be used to inject arbitrary OS commands.\n    cwe: CWE-78\n    function_names:\n      - fetchCommits\n    filenames:\n      - src/runtime/server/utils/queries.ts\n    classification: very promising\n\n  - headline: Improper Neutralization of Argument Delimiters in a Command ('Argument Injection')\n    analysis: |\n      Similar to the OS Command Injection vulnerability, the codebase also contains instances where user-provided input is used to construct command arguments without proper sanitization. This could allow an attacker to inject malicious arguments that would be executed on the server. Specifically, the `fetchCommits` function in `src/runtime/server/utils/queries.ts` constructs a GraphQL query using user-provided `date` parameter, which could be used to inject arbitrary command arguments.\n    cwe: CWE-88\n    function_names:\n      - fetchCommits\n    filenames:\n      - src/runtime/server/utils/queries.ts\n    classification: very promising\n\n  - headline: Improper Neutralization of Formula Elements in a CSV File\n    analysis: |\n      The codebase does not properly sanitize user-provided input when constructing URLs for the GitHub API. This could allow an attacker to inject malicious formulas that would be executed when the CSV file is opened. Specifically, the `encodeParams` function in `src/runtime/composables/useGithub.ts` constructs URLs using user-provided parameters, which could be used to inject malicious formulas.\n    cwe: CWE-1236\n    function_names:\n      - encodeParams\n    filenames:\n      - src/runtime/composables/useGithub.ts\n    classification: slightly promising\n\n  - headline: Improper Validation of Specified Quantity in Input\n    analysis: |\n      The codebase does not properly validate the `max` parameter in the `fetchFileContributors` and `fetchRepositoryContributors` functions in `src/runtime/server/utils/queries.ts`. An attacker could provide a large value for this parameter, which could lead to resource exhaustion on the server.\n    cwe: CWE-1284\n    function_names:\n      - fetchFileContributors\n      - fetchRepositoryContributors\n    filenames:\n      - src/runtime/server/utils/queries.ts\n    classification: slightly promising\n\n  - headline: Improper Handling of Exceptional Conditions\n    analysis: |\n      The codebase does not properly handle errors that occur during API requests to GitHub. The `fetchRepository`, `fetchReleases`, `fetchContributors`, `fetchFileContributors`, and `fetchReadme` functions in `src/runtime/server/utils/queries.ts` all catch and silently ignore errors, which could lead to unexpected behavior or information disclosure.\n    cwe: CWE-755\n    function_names:\n      - fetchRepository\n      - fetchReleases\n      - fetchContributors\n      - fetchFileContributors\n      - fetchReadme\n    filenames:\n      - src/runtime/server/utils/queries.ts\n    classification: slightly promising\n```",
      "date": "2024-06-13T10:36:22.050747",
      "usage": {
        "prompt_tokens": 18046,
        "completion_tokens": 874,
        "cost": 0.005604
      }
    }
  ],
  "leads": [
    {
      "headline": "Improper Neutralization of Special Elements used in an OS Command ('OS Command Injection')",
      "analysis": "The codebase contains several instances where user-provided input is used to construct OS commands without proper sanitization. This could allow an attacker to inject malicious commands that would be executed on the server. Specifically, the fetchCommits function in src/runtime/server/utils/queries.ts constructs a GraphQL query using user-provided source parameter, which could be used to inject arbitrary OS commands.\n",
      "classification": "very promising",
      "cwe": "CWE-78",
      "function_names": [
        "fetchCommits"
      ],
      "filenames": [
        "src/runtime/server/utils/queries.ts"
      ]
    },
    {
      "headline": "Improper Neutralization of Argument Delimiters in a Command ('Argument Injection')",
      "analysis": "Similar to the OS Command Injection vulnerability, the codebase also contains instances where user-provided input is used to construct command arguments without proper sanitization. This could allow an attacker to inject malicious arguments that would be executed on the server. Specifically, the fetchCommits function in src/runtime/server/utils/queries.ts constructs a GraphQL query using user-provided date parameter, which could be used to inject arbitrary command arguments.\n",
      "classification": "very promising",
      "cwe": "CWE-88",
      "function_names": [
        "fetchCommits"
      ],
      "filenames": [
        "src/runtime/server/utils/queries.ts"
      ]
    },
    {
      "headline": "Improper Neutralization of Formula Elements in a CSV File",
      "analysis": "The codebase does not properly sanitize user-provided input when constructing URLs for the GitHub API. This could allow an attacker to inject malicious formulas that would be executed when the CSV file is opened. Specifically, the encodeParams function in src/runtime/composables/useGithub.ts constructs URLs using user-provided parameters, which could be used to inject malicious formulas.\n",
      "classification": "slightly promising",
      "cwe": "CWE-1236",
      "function_names": [
        "encodeParams"
      ],
      "filenames": [
        "src/runtime/composables/useGithub.ts"
      ]
    },
    {
      "headline": "Improper Validation of Specified Quantity in Input",
      "analysis": "The codebase does not properly validate the max parameter in the fetchFileContributors and fetchRepositoryContributors functions in src/runtime/server/utils/queries.ts. An attacker could provide a large value for this parameter, which could lead to resource exhaustion on the server.\n",
      "classification": "slightly promising",
      "cwe": "CWE-1284",
      "function_names": [
        "fetchFileContributors",
        "fetchRepositoryContributors"
      ],
      "filenames": [
        "src/runtime/server/utils/queries.ts"
      ]
    },
    {
      "headline": "Improper Handling of Exceptional Conditions",
      "analysis": "The codebase does not properly handle errors that occur during API requests to GitHub. The fetchRepository, fetchReleases, fetchContributors, fetchFileContributors, and fetchReadme functions in src/runtime/server/utils/queries.ts all catch and silently ignore errors, which could lead to unexpected behavior or information disclosure.\n",
      "classification": "slightly promising",
      "cwe": "CWE-755",
      "function_names": [
        "fetchRepository",
        "fetchReleases",
        "fetchContributors"
      ],
      "filenames": [
        "src/runtime/server/utils/queries.ts"
      ]
    }
  ],
  "scores": [
    {
      "stats": {
        "fn": 1,
        "tp": 0,
        "fp": 2
      },
      "mapping": {},
      "vuln_dates": {
        "CVE-2023-2138": "2023-04-18T01:15:07"
      },
      "scoring_model": "claude-3-opus-20240229",
      "type": "llm",
      "instruction_template_hash": "245ace12b6361954d0a2"
    }
  ],
  "instruction_template_hash": "10c0163db4740318a544",
  "version": "0.1.0"
}
