{
  "commit": "0917e516ad6f1dba45bbecb8a3be2b7e33821dbe",
  "repo_url": "https://github.com/fracpete/vfsjfilechooser2",
  "model": "gpt-4o-2024-05-13",
  "chunk_hashes": [
    "fa7afbbdcca98b4783ac"
  ],
  "responses": [
    {
      "content": "```yaml\nleads:\n  - headline: Hardcoded Password Presence\n    analysis: |\n      The code contains hardcoded credentials in `Credentials.java` and `BookmarksWriter.java`. Specifically, passwords are embedded directly within the code, potentially compromising system security if the source code is leaked or accessed by unauthorized individuals. Hardcoding sensitive information like passwords can lead to severe security breaches.\n    cwe: CWE-798\n    function_names:\n      - build\n    filenames:\n      - src/main/java/com/googlecode/vfsjfilechooser2/accessories/connection/Credentials.java\n      - src/main/java/com/googlecode/vfsjfilechooser2/accessories/bookmarks/BookmarksWriter.java\n    classification: very promising\n\n  - headline: Use of Obsolete Cryptographic Algorithm (Blowfish)\n    analysis: |\n      The usage of the Blowfish cryptographic algorithm in `BookmarksWriter.java` is potentially insecure given modern cryptographic standards. Although Blowfish has not been widely broken, it is not recommended for use in new systems as safer alternatives with more rigorous scrutiny, such as AES, are available.\n    cwe: CWE-327\n    function_names:\n      - writeToFile\n    filenames:\n      - src/main/java/com/googlecode/vfsjfilechooser2/accessories/bookmarks/BookmarksWriter.java\n    classification: very promising\n\n  - headline: XML External Entity Injection (XXE)\n    analysis: |\n      The `BookmarksReader.java` uses `XMLReader` without disabling external entity references. This can lead to XXE attacks allowing an attacker to access the file system, make network requests, or cause denial of service.\n    cwe: CWE-611\n    function_names:\n      - <init>\n    filenames:\n      - src/main/java/com/googlecode/vfsjfilechooser2/accessories/bookmarks/BookmarksReader.java\n    classification: very promising\n  \n  - headline: Potential URL Redirection to Untrusted Site (Open Redirect)\n    analysis: |\n      The code does not seem to sanitize URLs properly in `ConnectionDialog.java` and `BookmarksEditorPanel.java` before usage. This could make it susceptible to Open Redirect attacks, allowing attackers to redirect users to malicious websites by manipulating URLs.\n    cwe: CWE-601\n    function_names:\n      - actionPerformed\n    filenames:\n      - src/main/java/com/googlecode/vfsjfilechooser2/accessories/connection/ConnectionDialog.java\n      - src/main/java/com/googlecode/vfsjfilechooser2/accessories/bookmarks/BookmarksEditorPanel.java\n    classification: slightly promising\n\n  - headline: Path Traversal\n    analysis: |\n      The code in `VFSUtils.java` that handles file paths might be vulnerable to Path Traversal attacks. If untrusted input is passed to these methods, an attacker could manipulate the path to access files or directories that are outside the intended directory.\n    cwe: CWE-22\n    function_names:\n      - resolveFileObject\n      - toFileObject\n    filenames:\n      - src/main/java/com/googlecode/vfsjfilechooser2/utils/VFSUtils.java\n    classification: very promising\n\n  - headline: Insufficient Logging\n    analysis: |\n      Security-relevant actions, especially access control decisions and administrative functions in the methods handling Bookmarks in `Bookmarks.java`, are poorly logged or not logged at all. This might make it hard to detect and respond to malicious activities or system misuse.\n    cwe: CWE-778\n    function_names:\n      - save\n    filenames:\n      - src/main/java/com/googlecode/vfsjfilechooser2/accessories/bookmarks/Bookmarks.java\n    classification: slightly promising\n\n  - headline: Inadequate Error Handling\n    analysis: |\n      The `BookmarksManagerPanel.java` and `ConnectionDialog.java` have several methods that catch generic exceptions and only log or print stack traces without proper error handling. This can result in inadequate awareness of the issues and may not provide sufficient information to the user about the error.\n    cwe: CWE-390\n    function_names:\n      - actionPerformed\n    filenames:\n      - src/main/java/com/googlecode/vfsjfilechooser2/accessories/bookmarks/BookmarksManagerPanel.java\n      - src/main/java/com/googlecode/vfsjfilechooser2/accessories/connection/ConnectionDialog.java\n    classification: slightly promising\n```",
      "date": "2024-06-12T16:35:38.469120",
      "usage": {
        "prompt_tokens": 119388,
        "completion_tokens": 891,
        "cost": 0.610305
      }
    }
  ],
  "leads": [
    {
      "headline": "Hardcoded Password Presence",
      "analysis": "The code contains hardcoded credentials in Credentials.java and BookmarksWriter.java. Specifically, passwords are embedded directly within the code, potentially compromising system security if the source code is leaked or accessed by unauthorized individuals. Hardcoding sensitive information like passwords can lead to severe security breaches.\n",
      "classification": "very promising",
      "cwe": "CWE-798",
      "function_names": [
        "build"
      ],
      "filenames": [
        "src/main/java/com/googlecode/vfsjfilechooser2/accessories/connection/Credentials.java",
        "src/main/java/com/googlecode/vfsjfilechooser2/accessories/bookmarks/BookmarksWriter.java"
      ]
    },
    {
      "headline": "Use of Obsolete Cryptographic Algorithm (Blowfish)",
      "analysis": "The usage of the Blowfish cryptographic algorithm in BookmarksWriter.java is potentially insecure given modern cryptographic standards. Although Blowfish has not been widely broken, it is not recommended for use in new systems as safer alternatives with more rigorous scrutiny, such as AES, are available.\n",
      "classification": "very promising",
      "cwe": "CWE-327",
      "function_names": [
        "writeToFile"
      ],
      "filenames": [
        "src/main/java/com/googlecode/vfsjfilechooser2/accessories/bookmarks/BookmarksWriter.java"
      ]
    },
    {
      "headline": "XML External Entity Injection (XXE)",
      "analysis": "The BookmarksReader.java uses XMLReader without disabling external entity references. This can lead to XXE attacks allowing an attacker to access the file system, make network requests, or cause denial of service.\n",
      "classification": "very promising",
      "cwe": "CWE-611",
      "function_names": [
        "<init>"
      ],
      "filenames": [
        "src/main/java/com/googlecode/vfsjfilechooser2/accessories/bookmarks/BookmarksReader.java"
      ]
    },
    {
      "headline": "Potential URL Redirection to Untrusted Site (Open Redirect)",
      "analysis": "The code does not seem to sanitize URLs properly in ConnectionDialog.java and BookmarksEditorPanel.java before usage. This could make it susceptible to Open Redirect attacks, allowing attackers to redirect users to malicious websites by manipulating URLs.\n",
      "classification": "slightly promising",
      "cwe": "CWE-601",
      "function_names": [
        "actionPerformed"
      ],
      "filenames": [
        "src/main/java/com/googlecode/vfsjfilechooser2/accessories/connection/ConnectionDialog.java",
        "src/main/java/com/googlecode/vfsjfilechooser2/accessories/bookmarks/BookmarksEditorPanel.java"
      ]
    },
    {
      "headline": "Path Traversal",
      "analysis": "The code in VFSUtils.java that handles file paths might be vulnerable to Path Traversal attacks. If untrusted input is passed to these methods, an attacker could manipulate the path to access files or directories that are outside the intended directory.\n",
      "classification": "very promising",
      "cwe": "CWE-22",
      "function_names": [
        "resolveFileObject",
        "toFileObject"
      ],
      "filenames": [
        "src/main/java/com/googlecode/vfsjfilechooser2/utils/VFSUtils.java"
      ]
    },
    {
      "headline": "Insufficient Logging",
      "analysis": "Security-relevant actions, especially access control decisions and administrative functions in the methods handling Bookmarks in Bookmarks.java, are poorly logged or not logged at all. This might make it hard to detect and respond to malicious activities or system misuse.\n",
      "classification": "slightly promising",
      "cwe": "CWE-778",
      "function_names": [
        "save"
      ],
      "filenames": [
        "src/main/java/com/googlecode/vfsjfilechooser2/accessories/bookmarks/Bookmarks.java"
      ]
    },
    {
      "headline": "Inadequate Error Handling",
      "analysis": "The BookmarksManagerPanel.java and ConnectionDialog.java have several methods that catch generic exceptions and only log or print stack traces without proper error handling. This can result in inadequate awareness of the issues and may not provide sufficient information to the user about the error.\n",
      "classification": "slightly promising",
      "cwe": "CWE-390",
      "function_names": [
        "actionPerformed"
      ],
      "filenames": [
        "src/main/java/com/googlecode/vfsjfilechooser2/accessories/bookmarks/BookmarksManagerPanel.java",
        "src/main/java/com/googlecode/vfsjfilechooser2/accessories/connection/ConnectionDialog.java"
      ]
    }
  ],
  "scores": [
    {
      "stats": {
        "fn": 1,
        "tp": 0,
        "fp": 4
      },
      "mapping": {},
      "vuln_dates": {
        "CVE-2021-29061": "2021-06-21T20:15:09"
      },
      "scoring_model": "claude-3-opus-20240229",
      "type": "llm",
      "instruction_template_hash": "245ace12b6361954d0a2"
    }
  ],
  "instruction_template_hash": "10c0163db4740318a544",
  "version": "0.1.0"
}
