{
  "commit": "07538893fb6c2a9539678c45f9dbbf1e4f222b46",
  "repo_url": "https://github.com/freifunk-gluon/ecdsautils",
  "model": "gpt-4o-2024-05-13",
  "chunk_hashes": [
    "e4398e9878434ce0da12"
  ],
  "responses": [
    {
      "content": "```yaml\nleads:\n  - headline: \"Potential Randomness Issues\"\n    analysis: |\n      The random_bytes function in 'src/cli/random.c' reads random bytes from /dev/random, which could block if the entropy pool is insufficient. Additionally, the non-cryptographic handling of errors without any retries or fallbacks to another entropy source may result in unpredictable behavior. The current implementation does not account for potential blocking or insufficient entropy scenarios.\n    cwe: CWE-330\n    function_names:\n      - random_bytes\n    filenames:\n      - src/cli/random.c\n    classification: very promising\n\n  - headline: \"Fixed Seed for Randomness\"\n    analysis: |\n      The request for random bytes is handled without ensuring the cryptographic randomness of the seed in the function 'new_secret' and 'generate_k_prepare'. Given the deterministic nature of the generation algorithm for key material or IDs, there can be concerns about predictability, especially in constrained environments.\n    cwe: CWE-338\n    function_names:\n      - new_secret\n      - generate_k_prepare\n    filenames:\n      - src/cli/keygen.c\n      - src/lib/ecdsa.c\n    classification: very promising\n\n  - headline: \"Potential Buffer Overflow\"\n    analysis: |\n      The 'parsehex' function in 'src/cli/hexutil.c' does not properly account for the length of the input string, and improper length checks could lead to a buffer overflow if the input length does not match the expected format. This could potentially be exploited, especially if input is taken directly from user sources.\n    cwe: CWE-120\n    function_names:\n      - parsehex\n    filenames:\n      - src/cli/hexutil.c\n    classification: very promising\n\n  - headline: \"Unchecked Return Value in File Handling\"\n    analysis: |\n      The open and close operations within 'random_bytes' and 'sha256_file' functions do not fully validate the return values of file operations (e.g., close), which might leave file descriptor leaks. There is a lack of proper handling to ensure all file descriptors are closed in all code paths.\n    cwe: CWE-252\n    function_names:\n      - random_bytes\n      - sha256_file\n    filenames:\n      - src/cli/random.c\n      - src/cli/sha256_file.c\n    classification: slightly promising\n\n  - headline: \"Command Injection Risk\"\n    analysis: |\n      In the function 'sign', reading the secret key directly from standard input without sanitizing the input can lead to the manipulation of file descriptors, especially if inputs are uncontrolled. Additionally, direct input reads without checks could inadvertently accept and perform on unexpected data.\n    cwe: CWE-78\n    function_names:\n      - sign\n    filenames:\n      - src/cli/sign.c\n    classification: slightly promising\n\n  - headline: \"Insecure Hash Function Usage\"\n    analysis: |\n      The usage of SHA-256 in different parts of the code without considering current best practices in cryptographic strength and potential vulnerabilities (like length extension attacks) poses a risk. The implementation details in 'src/lib/sha256.c' suggest non-adaptive mechanism utilization.\n    cwe: CWE-327\n    function_names:\n      - ecdsa_sha256_init\n      - ecdsa_sha256_update\n      - ecdsa_sha256_final\n    filenames:\n      - src/lib/sha256.c\n    classification: slightly promising\n```",
      "date": "2024-06-12T16:42:28.167151",
      "usage": {
        "prompt_tokens": 19151,
        "completion_tokens": 713,
        "cost": 0.10645
      }
    }
  ],
  "leads": [
    {
      "headline": "Potential Randomness Issues",
      "analysis": "The random_bytes function in 'src/cli/random.c' reads random bytes from /dev/random, which could block if the entropy pool is insufficient. Additionally, the non-cryptographic handling of errors without any retries or fallbacks to another entropy source may result in unpredictable behavior. The current implementation does not account for potential blocking or insufficient entropy scenarios.\n",
      "classification": "very promising",
      "cwe": "CWE-330",
      "function_names": [
        "random_bytes"
      ],
      "filenames": [
        "src/cli/random.c"
      ]
    },
    {
      "headline": "Fixed Seed for Randomness",
      "analysis": "The request for random bytes is handled without ensuring the cryptographic randomness of the seed in the function 'new_secret' and 'generate_k_prepare'. Given the deterministic nature of the generation algorithm for key material or IDs, there can be concerns about predictability, especially in constrained environments.\n",
      "classification": "very promising",
      "cwe": "CWE-338",
      "function_names": [
        "new_secret",
        "generate_k_prepare"
      ],
      "filenames": [
        "src/cli/keygen.c",
        "src/lib/ecdsa.c"
      ]
    },
    {
      "headline": "Potential Buffer Overflow",
      "analysis": "The 'parsehex' function in 'src/cli/hexutil.c' does not properly account for the length of the input string, and improper length checks could lead to a buffer overflow if the input length does not match the expected format. This could potentially be exploited, especially if input is taken directly from user sources.\n",
      "classification": "very promising",
      "cwe": "CWE-120",
      "function_names": [
        "parsehex"
      ],
      "filenames": [
        "src/cli/hexutil.c"
      ]
    },
    {
      "headline": "Unchecked Return Value in File Handling",
      "analysis": "The open and close operations within 'random_bytes' and 'sha256_file' functions do not fully validate the return values of file operations (e.g., close), which might leave file descriptor leaks. There is a lack of proper handling to ensure all file descriptors are closed in all code paths.\n",
      "classification": "slightly promising",
      "cwe": "CWE-252",
      "function_names": [
        "random_bytes",
        "sha256_file"
      ],
      "filenames": [
        "src/cli/random.c",
        "src/cli/sha256_file.c"
      ]
    },
    {
      "headline": "Command Injection Risk",
      "analysis": "In the function 'sign', reading the secret key directly from standard input without sanitizing the input can lead to the manipulation of file descriptors, especially if inputs are uncontrolled. Additionally, direct input reads without checks could inadvertently accept and perform on unexpected data.\n",
      "classification": "slightly promising",
      "cwe": "CWE-78",
      "function_names": [
        "sign"
      ],
      "filenames": [
        "src/cli/sign.c"
      ]
    },
    {
      "headline": "Insecure Hash Function Usage",
      "analysis": "The usage of SHA-256 in different parts of the code without considering current best practices in cryptographic strength and potential vulnerabilities (like length extension attacks) poses a risk. The implementation details in 'src/lib/sha256.c' suggest non-adaptive mechanism utilization.\n",
      "classification": "slightly promising",
      "cwe": "CWE-327",
      "function_names": [
        "ecdsa_sha256_init",
        "ecdsa_sha256_update",
        "ecdsa_sha256_final"
      ],
      "filenames": [
        "src/lib/sha256.c"
      ]
    }
  ],
  "scores": [
    {
      "stats": {
        "fn": 1,
        "tp": 0,
        "fp": 3
      },
      "mapping": {},
      "vuln_dates": {
        "CVE-2022-24884": "2022-05-06T00:15:07"
      },
      "scoring_model": "claude-3-opus-20240229",
      "type": "llm",
      "instruction_template_hash": "245ace12b6361954d0a2"
    }
  ],
  "instruction_template_hash": "10c0163db4740318a544",
  "version": "0.1.0"
}
