{
  "commit": "085bb77ca3b493eb28c9ea0930e2e39c5a7bb72d",
  "repo_url": "https://github.com/tankywoo/simiki",
  "model": "claude-3-5-sonnet-20240620",
  "chunk_hashes": [
    "8b62a295714d576b3f09"
  ],
  "responses": [
    {
      "content": "Based on my analysis, here are the key security vulnerabilities I identified in the codebase:\n\n```yaml\nleads:\n  - headline: Arbitrary command execution via shell injection in release.sh\n    analysis: |\n      The release.sh script executes shell commands using variables that could be controlled by an attacker. For example, the $INDEX variable is used directly in a shell command without proper sanitization. An attacker who can control this variable could inject arbitrary commands to be executed on the system.\n    cwe: CWE-78\n    function_names:\n      - release.sh main script\n    filenames:\n      - release.sh\n    classification: very promising\n\n  - headline: Use of unsafe yaml.load() function allows arbitrary code execution\n    analysis: | \n      The config.py file uses yaml.load() to parse YAML config files. This is unsafe as it can execute arbitrary Python code embedded in the YAML. An attacker who can control the contents of _config.yml could execute malicious code on the system. The safer yaml.safe_load() should be used instead.\n    cwe: CWE-94\n    function_names:\n      - parse_config\n    filenames:\n      - simiki/config.py\n    classification: very promising\n\n  - headline: Unsafe use of os.path.join allows directory traversal\n    analysis: |\n      Several places in the codebase use os.path.join to construct file paths, but do not properly sanitize user-supplied path components. This could allow an attacker to traverse directories and access files outside of the intended directory. For example, in PageGenerator.get_category_and_file(), the category and filename are joined without sanitization.\n    cwe: CWE-22\n    function_names: \n      - PageGenerator.get_category_and_file\n      - PageGenerator.get_meta_and_content\n    filenames:\n      - simiki/generators.py\n    classification: slightly promising\n\n  - headline: Use of MD5 hash algorithm for file integrity checks\n    analysis: |\n      The codebase uses the MD5 hash algorithm in several places to check file integrity or generate checksums. MD5 is considered cryptographically broken and should not be relied on for security purposes. A stronger algorithm like SHA-256 should be used instead.\n    cwe: CWE-327\n    function_names:\n      - get_md5\n      - get_dir_md5  \n    filenames:\n      - simiki/utils.py\n    classification: slightly promising\n\n  - headline: Potential for directory traversal in FTP upload functionality  \n    analysis: |\n      The deploy_ftp function in fabfile.py constructs remote file paths by joining user-supplied values without proper sanitization. An attacker who can control these values could potentially upload files to arbitrary locations on the FTP server via directory traversal.\n    cwe: CWE-22\n    function_names:\n      - deploy_ftp\n    filenames:\n      - simiki/conf_templates/fabfile.py  \n    classification: slightly promising\n```\n\nThese are the most significant security issues I identified in the codebase. The command injection and unsafe YAML loading vulnerabilities are particularly concerning and should be addressed as a high priority. The other issues are less severe but still represent security weaknesses that should be remediated.",
      "date": "2024-07-08T08:54:45.922357",
      "usage": {
        "prompt_tokens": 38174,
        "completion_tokens": 759,
        "cost": 0.125907
      }
    }
  ],
  "leads": [
    {
      "headline": "Arbitrary command execution via shell injection in release.sh",
      "analysis": "The release.sh script executes shell commands using variables that could be controlled by an attacker. For example, the $INDEX variable is used directly in a shell command without proper sanitization. An attacker who can control this variable could inject arbitrary commands to be executed on the system.\n",
      "classification": "very promising",
      "cwe": "CWE-78",
      "function_names": [
        "release.sh main script"
      ],
      "filenames": [
        "release.sh"
      ]
    },
    {
      "headline": "Use of unsafe yaml.load() function allows arbitrary code execution",
      "analysis": "The config.py file uses yaml.load() to parse YAML config files. This is unsafe as it can execute arbitrary Python code embedded in the YAML. An attacker who can control the contents of _config.yml could execute malicious code on the system. The safer yaml.safe_load() should be used instead.\n",
      "classification": "very promising",
      "cwe": "CWE-94",
      "function_names": [
        "parse_config"
      ],
      "filenames": [
        "simiki/config.py"
      ]
    },
    {
      "headline": "Unsafe use of os.path.join allows directory traversal",
      "analysis": "Several places in the codebase use os.path.join to construct file paths, but do not properly sanitize user-supplied path components. This could allow an attacker to traverse directories and access files outside of the intended directory. For example, in PageGenerator.get_category_and_file(), the category and filename are joined without sanitization.\n",
      "classification": "slightly promising",
      "cwe": "CWE-22",
      "function_names": [
        "PageGenerator.get_category_and_file",
        "PageGenerator.get_meta_and_content"
      ],
      "filenames": [
        "simiki/generators.py"
      ]
    },
    {
      "headline": "Use of MD5 hash algorithm for file integrity checks",
      "analysis": "The codebase uses the MD5 hash algorithm in several places to check file integrity or generate checksums. MD5 is considered cryptographically broken and should not be relied on for security purposes. A stronger algorithm like SHA-256 should be used instead.\n",
      "classification": "slightly promising",
      "cwe": "CWE-327",
      "function_names": [
        "get_md5",
        "get_dir_md5"
      ],
      "filenames": [
        "simiki/utils.py"
      ]
    },
    {
      "headline": "Potential for directory traversal in FTP upload functionality",
      "analysis": "The deploy_ftp function in fabfile.py constructs remote file paths by joining user-supplied values without proper sanitization. An attacker who can control these values could potentially upload files to arbitrary locations on the FTP server via directory traversal.\n",
      "classification": "slightly promising",
      "cwe": "CWE-22",
      "function_names": [
        "deploy_ftp"
      ],
      "filenames": [
        "simiki/conf_templates/fabfile.py"
      ]
    }
  ],
  "scores": [
    {
      "stats": {
        "fn": 1,
        "tp": 1,
        "fp": 1
      },
      "mapping": {
        "1": "CVE-2020-19001"
      },
      "vuln_dates": {
        "CVE-2020-19001": "2021-08-27T19:15:07",
        "CVE-2020-19000": "2021-08-27T19:15:07"
      },
      "scoring_model": "claude-3-5-sonnet-20240620",
      "type": "llm",
      "instruction_template_hash": "245ace12b6361954d0a2"
    }
  ],
  "instruction_template_hash": "10c0163db4740318a544",
  "version": "0.1.0"
}
