{
  "commit": "45be0f99c7065f345ad76fd9767dae1c19cd01d5",
  "repo_url": "https://github.com/redon-tech/roblox-purchasing-hub",
  "model": "gpt-4o-2024-05-13",
  "chunk_hashes": [
    "c1d9834b7ece9e000d10"
  ],
  "responses": [
    {
      "content": "```yaml\nleads:\n  - headline: \"Possible Insecure Handling of Dangerous Characters in User Input\"\n    analysis: |\n      The code in `lib/cogs/product.py` and `lib/cogs/user.py` does not sanitize or validate user inputs properly. This leaves the bot vulnerable to command injection, SQL injection, and other forms of injection attacks. For example, in the commands like `giveproduct` and `revokeproduct`, user inputs directly influence the updates and commands without any sanitization.\n    cwe: CWE-74\n    function_names:\n      - \"giveproduct\"\n      - \"revokeproduct\"\n    filenames:\n      - \"lib/cogs/product.py\"\n      - \"lib/cogs/user.py\"\n    classification: very promising\n\n  - headline: \"Buffer Overflow and Resource Exhaustion Potential\"\n    analysis: |\n      The absence of checks on the number of users and product names being processed in `giveproduct` and `revokeproduct` commands along with the potential buffer overload in `attachments` handling in `createproduct` function exposes the bot to buffer overflow attacks and uncontrolled resource consumption.\n    cwe: CWE-770\n    function_names:\n      - \"giveproduct\"\n      - \"revokeproduct\"\n      - \"update_attachments\"\n      - \"createproduct\"\n    filenames:\n      - \"lib/cogs/product.py\"\n      - \"lib/cogs/user.py\"\n    classification: slightly promising\n\n  - headline: \"Hardcoded API Key Exposure\"\n    analysis: |\n      The API key is hardcoded in the `config.json` file which is loaded without encryption. Hardcoded keys can be easily extracted and misused if someone gains unauthorized access to the repository. The file `lib/utils/util.py` fetches this key for request validation.\n    cwe: CWE-798\n    function_names:\n      - \"require_apikey\"\n    filenames:\n      - \"lib/utils/util.py\"\n    classification: very promising\n\n  - headline: \"Potential Security Bypass Through Improper Exception Handling\"\n    analysis: |\n      Functions such as `verify_user`, `give_product`, and `revoke_product` do not catch specific exceptions. Instead, they catch all exceptions without detailed handling, which can be abused to bypass security checks or lead to insufficient logging of error sources or their causes.\n    cwe: CWE-754\n    function_names:\n      - \"verify_user\"\n      - \"give_product\"\n      - \"revoke_product\"\n    filenames:\n      - \"lib/cogs/website.py\"\n    classification: slightly promising\n\n  - headline: \"Inadequate Rate-Limiting on Critical API Endpoints\"\n    analysis: |\n      The API endpoints that handle sensitive operations such as `create_product`, `update_product`, `delete_product`, and user verification do not have rate limiting implemented. This can lead to brute-force attacks, denial of service attacks, and other resource abuse scenarios.\n    cwe: CWE-307\n    function_names:\n      - \"create_product\"\n      - \"update_product\"\n      - \"delete_product\"\n      - \"verify_user\"\n    filenames:\n      - \"lib/cogs/website.py\"\n    classification: very promising\n    \n  - headline: \"Improper Storage of Sensitive Information\"\n    analysis: |\n      Sensitive information such as MongoDB connection strings and API keys are stored in plaintext within the `config.json` file. This practice is insecure and can lead to unauthorized access if the configuration file is exposed.\n    cwe: CWE-312\n    function_names: []\n    filenames:\n      - \"lib/bot/config.json\"\n    classification: very promising\n```",
      "date": "2024-06-14T15:24:52.708258",
      "usage": {
        "prompt_tokens": 14272,
        "completion_tokens": 739,
        "cost": 0.082445
      }
    }
  ],
  "leads": [
    {
      "headline": "Possible Insecure Handling of Dangerous Characters in User Input",
      "analysis": "The code in lib/cogs/product.py and lib/cogs/user.py does not sanitize or validate user inputs properly. This leaves the bot vulnerable to command injection, SQL injection, and other forms of injection attacks. For example, in the commands like giveproduct and revokeproduct, user inputs directly influence the updates and commands without any sanitization.\n",
      "classification": "very promising",
      "cwe": "CWE-74",
      "function_names": [
        "giveproduct",
        "revokeproduct"
      ],
      "filenames": [
        "lib/cogs/product.py",
        "lib/cogs/user.py"
      ]
    },
    {
      "headline": "Buffer Overflow and Resource Exhaustion Potential",
      "analysis": "The absence of checks on the number of users and product names being processed in giveproduct and revokeproduct commands along with the potential buffer overload in attachments handling in createproduct function exposes the bot to buffer overflow attacks and uncontrolled resource consumption.\n",
      "classification": "slightly promising",
      "cwe": "CWE-770",
      "function_names": [
        "giveproduct",
        "revokeproduct",
        "update_attachments"
      ],
      "filenames": [
        "lib/cogs/product.py",
        "lib/cogs/user.py"
      ]
    },
    {
      "headline": "Hardcoded API Key Exposure",
      "analysis": "The API key is hardcoded in the config.json file which is loaded without encryption. Hardcoded keys can be easily extracted and misused if someone gains unauthorized access to the repository. The file lib/utils/util.py fetches this key for request validation.\n",
      "classification": "very promising",
      "cwe": "CWE-798",
      "function_names": [
        "require_apikey"
      ],
      "filenames": [
        "lib/utils/util.py"
      ]
    },
    {
      "headline": "Potential Security Bypass Through Improper Exception Handling",
      "analysis": "Functions such as verify_user, give_product, and revoke_product do not catch specific exceptions. Instead, they catch all exceptions without detailed handling, which can be abused to bypass security checks or lead to insufficient logging of error sources or their causes.\n",
      "classification": "slightly promising",
      "cwe": "CWE-754",
      "function_names": [
        "verify_user",
        "give_product",
        "revoke_product"
      ],
      "filenames": [
        "lib/cogs/website.py"
      ]
    },
    {
      "headline": "Inadequate Rate-Limiting on Critical API Endpoints",
      "analysis": "The API endpoints that handle sensitive operations such as create_product, update_product, delete_product, and user verification do not have rate limiting implemented. This can lead to brute-force attacks, denial of service attacks, and other resource abuse scenarios.\n",
      "classification": "very promising",
      "cwe": "CWE-307",
      "function_names": [
        "create_product",
        "update_product",
        "delete_product"
      ],
      "filenames": [
        "lib/cogs/website.py"
      ]
    },
    {
      "headline": "Improper Storage of Sensitive Information",
      "analysis": "Sensitive information such as MongoDB connection strings and API keys are stored in plaintext within the config.json file. This practice is insecure and can lead to unauthorized access if the configuration file is exposed.\n",
      "classification": "very promising",
      "cwe": "CWE-312",
      "function_names": [],
      "filenames": [
        "lib/bot/config.json"
      ]
    }
  ],
  "scores": [
    {
      "stats": {
        "fn": 1,
        "tp": 0,
        "fp": 4
      },
      "mapping": {},
      "vuln_dates": {
        "CVE-2021-41191": "2021-10-27T21:15:08"
      },
      "scoring_model": "claude-3-opus-20240229",
      "type": "llm",
      "instruction_template_hash": "245ace12b6361954d0a2"
    }
  ],
  "instruction_template_hash": "10c0163db4740318a544",
  "version": "0.1.0"
}
