{
  "commit": "5647855a7ddd322e0e9ced1134e5ea6cc100904e",
  "repo_url": "https://github.com/libfuse/libfuse",
  "model": "gemini/gemini-1.5-pro",
  "chunk_hashes": [
    "de47eb8b02e883407dc9"
  ],
  "responses": [
    {
      "content": "```yaml\nleads:\n  - headline: Path Traversal in fusexmp.c:xmp_getattr\n    analysis: |\n      The `xmp_getattr` function in `fusexmp.c` takes a `path` argument and directly passes it to the `lstat` system call without any sanitization.\n      If the `path` argument is externally controlled and contains path traversal sequences like \"../\", an attacker can access and manipulate files outside the intended mount directory. \n    cwe: CWE-22\n    function_names:\n      - xmp_getattr\n    filenames:\n      - example/fusexmp.c\n    classification: very promising\n  - headline: Path Traversal in fusexmp.c:xmp_readlink\n    analysis: |\n      The `xmp_readlink` function in `fusexmp.c` is vulnerable to path traversal.\n      It takes a user-controlled `path` argument and directly uses it in the `readlink` system call without any validation. \n      An attacker could provide a path with \"../\" sequences to access symbolic links outside the intended directory.\n    cwe: CWE-22\n    function_names:\n      - xmp_readlink\n    filenames:\n      - example/fusexmp.c\n    classification: very promising\n  - headline: Path Traversal in fusexmp.c:xmp_readdir\n    analysis: |\n      The `xmp_readdir` function in `fusexmp.c` is susceptible to path traversal.\n      It takes a `path` argument and calls `opendir` without sanitizing the path.\n      This allows an attacker to read directory listings outside the intended mount point by providing a malicious path.\n    cwe: CWE-22\n    function_names:\n      - xmp_readdir\n    filenames:\n      - example/fusexmp.c\n    classification: very promising\n  - headline: Path Traversal in fusexmp.c:xmp_mknod\n    analysis: |\n      The `xmp_mknod` function in `fusexmp.c` is vulnerable to a path traversal attack.\n      The function takes a user-provided `path` argument and passes it directly to the `mknod` system call without any sanitization.\n      An attacker could provide a path with path traversal sequences (e.g., \"../\") to create device nodes outside the intended mount point.\n    cwe: CWE-22\n    function_names:\n      - xmp_mknod\n    filenames:\n      - example/fusexmp.c\n    classification: very promising\n  - headline: Path Traversal in fusexmp.c:xmp_mkdir\n    analysis: |\n      The `xmp_mkdir` function in `fusexmp.c` is vulnerable to path traversal.\n      It directly uses the user-supplied `path` in a call to `mkdir` without any validation.\n      An attacker could create directories outside the intended filesystem root by providing a crafted path.\n    cwe: CWE-22\n    function_names:\n      - xmp_mkdir\n    filenames:\n      - example/fusexmp.c\n    classification: very promising\n  - headline: Path Traversal in fusexmp.c:xmp_unlink\n    analysis: |\n      The function `xmp_unlink` in `fusexmp.c` is vulnerable to path traversal.\n      It takes a `path` argument directly from the user and uses it in the `unlink` system call without any sanitization. \n      An attacker could use \"../\" sequences in the path to delete files outside the intended directory.\n    cwe: CWE-22\n    function_names:\n      - xmp_unlink\n    filenames:\n      - example/fusexmp.c\n    classification: very promising\n  - headline: Path Traversal in fusexmp.c:xmp_rmdir\n    analysis: |\n      The `xmp_rmdir` function in `fusexmp.c` is vulnerable to path traversal because it passes the user-supplied `path` argument directly to `rmdir` without any validation or sanitization.\n      This could allow an attacker to delete directories outside the intended mount point by crafting a malicious path.\n    cwe: CWE-22\n    function_names:\n      - xmp_rmdir\n    filenames:\n      - example/fusexmp.c\n    classification: very promising\n  - headline: Path Traversal in fusexmp.c:xmp_symlink\n    analysis: |\n      The `xmp_symlink` function in `fusexmp.c` takes both `from` and `to` path arguments directly from user input and passes them to the `symlink` system call without any sanitization.\n      An attacker could craft paths containing \"../\" sequences to create symbolic links pointing to sensitive locations outside the expected directory. \n    cwe: CWE-22\n    function_names:\n      - xmp_symlink\n    filenames:\n      - example/fusexmp.c\n    classification: very promising\n  - headline: Path Traversal in fusexmp.c:xmp_rename\n    analysis: |\n      The `xmp_rename` function in `fusexmp.c` is vulnerable to path traversal. \n      It uses both the `from` and `to` arguments, taken directly from user input, in the `rename` system call without any path sanitization.\n      An attacker could provide malicious paths containing \"../\" sequences to move files outside the intended directory structure.\n    cwe: CWE-22\n    function_names:\n      - xmp_rename\n    filenames:\n      - example/fusexmp.c\n    classification: very promising\n  - headline: Path Traversal in fusexmp.c:xmp_link\n    analysis: |\n      The function `xmp_link` in `fusexmp.c` is vulnerable to a path traversal attack.\n      It accepts `from` and `to` arguments directly from user input and uses them in the `link` system call without any sanitization.\n      By providing a carefully crafted `from` path containing \"../\" sequences, an attacker could create a hard link to a file outside the expected directory. \n    cwe: CWE-22\n    function_names:\n      - xmp_link\n    filenames:\n      - example/fusexmp.c\n    classification: very promising\n  - headline: Path Traversal in fusexmp.c:xmp_chmod\n    analysis: |\n      The `xmp_chmod` function in `fusexmp.c` is vulnerable to path traversal.\n      It accepts a user-controlled `path` argument and passes it to the `chmod` system call without sanitization. \n      An attacker could use \"..\" segments in the path to change permissions of files outside the intended directory.\n    cwe: CWE-22\n    function_names:\n      - xmp_chmod\n    filenames:\n      - example/fusexmp.c\n    classification: very promising\n  - headline: Path Traversal in fusexmp.c:xmp_chown\n    analysis: |\n      The function `xmp_chown` in `fusexmp.c` takes a `path` argument and directly uses it in a call to `lchown` without any sanitization. \n      If the `path` argument is provided by an attacker and contains \"../\" sequences, it could lead to a path traversal vulnerability, allowing an attacker to change the owner and group of files outside the intended directory.\n    cwe: CWE-22\n    function_names:\n      - xmp_chown\n    filenames:\n      - example/fusexmp.c\n    classification: very promising\n  - headline: Path Traversal in fusexmp.c:xmp_truncate\n    analysis: |\n      The `xmp_truncate` function in `fusexmp.c` takes a `path` parameter which is not properly sanitized before being used in the `truncate` system call.\n      If an attacker can control the `path` parameter, they could use path traversal sequences like \"../\" to modify the size of files outside the intended mount point. \n    cwe: CWE-22\n    function_names:\n      - xmp_truncate\n    filenames:\n      - example/fusexmp.c\n    classification: very promising\n  - headline: Path Traversal in fusexmp.c:xmp_utime\n    analysis: |\n      The `xmp_utime` function in `fusexmp.c` takes a `path` argument and uses it in a call to `utime` without any validation or sanitization. \n      This makes the function vulnerable to path traversal attacks. \n      An attacker could provide a specially crafted path with \"..\" segments to modify the access and modification timestamps of files outside the intended directory.\n    cwe: CWE-22\n    function_names:\n      - xmp_utime\n    filenames:\n      - example/fusexmp.c\n    classification: very promising\n  - headline: Path Traversal in fusexmp.c:xmp_open\n    analysis: |\n      The `xmp_open` function in `fusexmp.c` is vulnerable to a path traversal attack because it uses the user-supplied `path` directly in a call to `open` without any validation.\n      This means an attacker could potentially open files outside the intended directory by providing a path with \"../\" sequences.\n    cwe: CWE-22\n    function_names:\n      - xmp_open\n    filenames:\n      - example/fusexmp.c\n    classification: very promising\n  - headline: Path Traversal in fusexmp.c:xmp_read\n    analysis: |\n      The `xmp_read` function in `fusexmp.c` is vulnerable to path traversal. \n      It uses the `path` argument, which comes directly from user input, to open a file with `open(path, O_RDONLY)`.\n      If an attacker can control the `path` parameter, they could use traversal sequences like \"../\" to read arbitrary files outside the intended directory.\n    cwe: CWE-22\n    function_names:\n      - xmp_read\n    filenames:\n      - example/fusexmp.c\n    classification: very promising\n  - headline: Path Traversal in fusexmp.c:xmp_write\n    analysis: |\n      The function `xmp_write` in `fusexmp.c` is susceptible to a path traversal vulnerability. It takes a user-controlled `path` argument and uses it directly in the `open` system call without any validation. \n      This could allow an attacker to write data to arbitrary files outside the intended directory by crafting a malicious path string containing \"../\" sequences.\n    cwe: CWE-22\n    function_names:\n      - xmp_write\n    filenames:\n      - example/fusexmp.c\n    classification: very promising\n  - headline: Path Traversal in fusexmp.c:xmp_statfs\n    analysis: |\n      The `xmp_statfs` function in `fusexmp.c` is vulnerable to path traversal because it takes a user-provided `path` argument and passes it directly to `statfs` without any validation. \n      This could allow an attacker to retrieve filesystem statistics for directories outside the intended mount point by supplying a malicious path. \n    cwe: CWE-22\n    function_names:\n      - xmp_statfs\n    filenames:\n      - example/fusexmp.c\n    classification: very promising\n  - headline: Path Traversal in fusexmp.c:xmp_setxattr\n    analysis: |\n      The `xmp_setxattr` function in `fusexmp.c` is vulnerable to a path traversal attack. \n      It directly uses the user-provided `path` argument in the `lsetxattr` system call without any validation or sanitization.\n      An attacker could use \"..\" sequences in the path to set extended attributes on files outside the expected directory, potentially allowing them to manipulate file metadata or gain unauthorized access.\n    cwe: CWE-22\n    function_names:\n      - xmp_setxattr\n    filenames:\n      - example/fusexmp.c\n    classification: very promising\n  - headline: Path Traversal in fusexmp.c:xmp_getxattr\n    analysis: |\n      The `xmp_getxattr` function in `fusexmp.c` takes the `path` argument from user input and passes it directly to `lgetxattr` without any sanitization. \n      An attacker could use \"..\" or similar sequences in the `path` to read extended attributes of files outside the intended directory, potentially leaking sensitive information. \n    cwe: CWE-22\n    function_names:\n      - xmp_getxattr\n    filenames:\n      - example/fusexmp.c\n    classification: very promising\n  - headline: Path Traversal in fusexmp.c:xmp_listxattr\n    analysis: |\n      The function `xmp_listxattr` in `fusexmp.c` is vulnerable to path traversal.\n      It uses the user-provided `path` directly in the `llistxattr` system call without any validation.\n      An attacker could craft a path containing \"../\" sequences to list extended attributes of files outside the intended directory, potentially exposing sensitive information.\n    cwe: CWE-22\n    function_names:\n      - xmp_listxattr\n    filenames:\n      - example/fusexmp.c\n    classification: very promising\n  - headline: Path Traversal in fusexmp.c:xmp_removexattr\n    analysis: |\n      The `xmp_removexattr` function in `fusexmp.c` is vulnerable to a path traversal attack.\n      It takes a user-supplied `path` argument and passes it directly to the `lremovexattr` system call without any validation.\n      An attacker could use \"..\" sequences in the `path` to remove extended attributes from files outside the intended directory, potentially affecting file security or integrity. \n    cwe: CWE-22\n    function_names:\n      - xmp_removexattr\n    filenames:\n      - example/fusexmp.c\n    classification: very promising\n  - headline: Possible Integer Overflow in lib/fuse.c:get_path_name\n    analysis: |\n      The `get_path_name` function in `lib/fuse.c` uses a fixed-size buffer (`buf`) to construct the path string. \n      While it checks for buffer overflow when adding individual components (`add_name` function), there's no check for the overall path length.\n      If an attacker can create a deeply nested directory structure, it might be possible to cause a buffer overflow in `buf`, leading to potential denial of service or code execution vulnerabilities.\n    cwe: CWE-190\n    function_names:\n      - get_path_name\n    filenames:\n      - lib/fuse.c\n    classification: slightly promising\n  - headline: Possible Integer Overflow in lib/helper.c:add_option_to\n    analysis: |\n      The function `add_option_to` in `lib/helper.c` reallocates memory for the option string without checking for integer overflow in the calculation `oldlen + 1 + len + 1`. \n      If an attacker can control the size of the options (`oldlen` and `len`), they may be able to trigger an integer overflow. \n    cwe: CWE-190\n    function_names:\n      - add_option_to\n    filenames:\n      - lib/helper.c\n    classification: slightly promising\n  - headline: Potential Denial of Service in lib/fuse.c:fuse_process_cmd\n    analysis: |\n      The `fuse_process_cmd` function in `lib/fuse.c` doesn't check for the size of the incoming command before calling `malloc` to allocate `buf`. \n      If an attacker can send a very large command, it could lead to excessive memory allocation, potentially causing a denial of service.\n    cwe: CWE-770\n    function_names:\n      - fuse_process_cmd\n    filenames:\n      - lib/fuse.c\n    classification: not promising\n  - headline: Potential Denial of Service in lib/fuse.c:fuse_read_cmd\n    analysis: |\n      The `fuse_read_cmd` function allocates a buffer of size `FUSE_MAX_IN` without checking if a smaller command could be received.\n      This could lead to unnecessary memory consumption if an attacker repeatedly sends small commands, potentially contributing to a denial of service.\n    cwe: CWE-770\n    function_names:\n      - fuse_read_cmd\n    filenames:\n      - lib/fuse.c\n    classification: not promising\n```",
      "date": "2024-06-12T13:06:58.212572",
      "usage": {
        "prompt_tokens": 79712,
        "completion_tokens": 3417,
        "cost": 0.3148705
      }
    }
  ],
  "leads": [
    {
      "headline": "Path Traversal in fusexmp.c:xmp_getattr",
      "analysis": "The xmp_getattr function in fusexmp.c takes a path argument and directly passes it to the lstat system call without any sanitization.\nIf the path argument is externally controlled and contains path traversal sequences like \"../\", an attacker can access and manipulate files outside the intended mount directory. \n",
      "classification": "very promising",
      "cwe": "CWE-22",
      "function_names": [
        "xmp_getattr"
      ],
      "filenames": [
        "example/fusexmp.c"
      ]
    },
    {
      "headline": "Path Traversal in fusexmp.c:xmp_readlink",
      "analysis": "The xmp_readlink function in fusexmp.c is vulnerable to path traversal.\nIt takes a user-controlled path argument and directly uses it in the readlink system call without any validation. \nAn attacker could provide a path with \"../\" sequences to access symbolic links outside the intended directory.\n",
      "classification": "very promising",
      "cwe": "CWE-22",
      "function_names": [
        "xmp_readlink"
      ],
      "filenames": [
        "example/fusexmp.c"
      ]
    },
    {
      "headline": "Path Traversal in fusexmp.c:xmp_readdir",
      "analysis": "The xmp_readdir function in fusexmp.c is susceptible to path traversal.\nIt takes a path argument and calls opendir without sanitizing the path.\nThis allows an attacker to read directory listings outside the intended mount point by providing a malicious path.\n",
      "classification": "very promising",
      "cwe": "CWE-22",
      "function_names": [
        "xmp_readdir"
      ],
      "filenames": [
        "example/fusexmp.c"
      ]
    },
    {
      "headline": "Path Traversal in fusexmp.c:xmp_mknod",
      "analysis": "The xmp_mknod function in fusexmp.c is vulnerable to a path traversal attack.\nThe function takes a user-provided path argument and passes it directly to the mknod system call without any sanitization.\nAn attacker could provide a path with path traversal sequences (e.g., \"../\") to create device nodes outside the intended mount point.\n",
      "classification": "very promising",
      "cwe": "CWE-22",
      "function_names": [
        "xmp_mknod"
      ],
      "filenames": [
        "example/fusexmp.c"
      ]
    },
    {
      "headline": "Path Traversal in fusexmp.c:xmp_mkdir",
      "analysis": "The xmp_mkdir function in fusexmp.c is vulnerable to path traversal.\nIt directly uses the user-supplied path in a call to mkdir without any validation.\nAn attacker could create directories outside the intended filesystem root by providing a crafted path.\n",
      "classification": "very promising",
      "cwe": "CWE-22",
      "function_names": [
        "xmp_mkdir"
      ],
      "filenames": [
        "example/fusexmp.c"
      ]
    },
    {
      "headline": "Path Traversal in fusexmp.c:xmp_unlink",
      "analysis": "The function xmp_unlink in fusexmp.c is vulnerable to path traversal.\nIt takes a path argument directly from the user and uses it in the unlink system call without any sanitization. \nAn attacker could use \"../\" sequences in the path to delete files outside the intended directory.\n",
      "classification": "very promising",
      "cwe": "CWE-22",
      "function_names": [
        "xmp_unlink"
      ],
      "filenames": [
        "example/fusexmp.c"
      ]
    },
    {
      "headline": "Path Traversal in fusexmp.c:xmp_rmdir",
      "analysis": "The xmp_rmdir function in fusexmp.c is vulnerable to path traversal because it passes the user-supplied path argument directly to rmdir without any validation or sanitization.\nThis could allow an attacker to delete directories outside the intended mount point by crafting a malicious path.\n",
      "classification": "very promising",
      "cwe": "CWE-22",
      "function_names": [
        "xmp_rmdir"
      ],
      "filenames": [
        "example/fusexmp.c"
      ]
    },
    {
      "headline": "Path Traversal in fusexmp.c:xmp_symlink",
      "analysis": "The xmp_symlink function in fusexmp.c takes both from and to path arguments directly from user input and passes them to the symlink system call without any sanitization.\nAn attacker could craft paths containing \"../\" sequences to create symbolic links pointing to sensitive locations outside the expected directory. \n",
      "classification": "very promising",
      "cwe": "CWE-22",
      "function_names": [
        "xmp_symlink"
      ],
      "filenames": [
        "example/fusexmp.c"
      ]
    },
    {
      "headline": "Path Traversal in fusexmp.c:xmp_rename",
      "analysis": "The xmp_rename function in fusexmp.c is vulnerable to path traversal. \nIt uses both the from and to arguments, taken directly from user input, in the rename system call without any path sanitization.\nAn attacker could provide malicious paths containing \"../\" sequences to move files outside the intended directory structure.\n",
      "classification": "very promising",
      "cwe": "CWE-22",
      "function_names": [
        "xmp_rename"
      ],
      "filenames": [
        "example/fusexmp.c"
      ]
    },
    {
      "headline": "Path Traversal in fusexmp.c:xmp_link",
      "analysis": "The function xmp_link in fusexmp.c is vulnerable to a path traversal attack.\nIt accepts from and to arguments directly from user input and uses them in the link system call without any sanitization.\nBy providing a carefully crafted from path containing \"../\" sequences, an attacker could create a hard link to a file outside the expected directory. \n",
      "classification": "very promising",
      "cwe": "CWE-22",
      "function_names": [
        "xmp_link"
      ],
      "filenames": [
        "example/fusexmp.c"
      ]
    },
    {
      "headline": "Path Traversal in fusexmp.c:xmp_chmod",
      "analysis": "The xmp_chmod function in fusexmp.c is vulnerable to path traversal.\nIt accepts a user-controlled path argument and passes it to the chmod system call without sanitization. \nAn attacker could use \"..\" segments in the path to change permissions of files outside the intended directory.\n",
      "classification": "very promising",
      "cwe": "CWE-22",
      "function_names": [
        "xmp_chmod"
      ],
      "filenames": [
        "example/fusexmp.c"
      ]
    },
    {
      "headline": "Path Traversal in fusexmp.c:xmp_chown",
      "analysis": "The function xmp_chown in fusexmp.c takes a path argument and directly uses it in a call to lchown without any sanitization. \nIf the path argument is provided by an attacker and contains \"../\" sequences, it could lead to a path traversal vulnerability, allowing an attacker to change the owner and group of files outside the intended directory.\n",
      "classification": "very promising",
      "cwe": "CWE-22",
      "function_names": [
        "xmp_chown"
      ],
      "filenames": [
        "example/fusexmp.c"
      ]
    },
    {
      "headline": "Path Traversal in fusexmp.c:xmp_truncate",
      "analysis": "The xmp_truncate function in fusexmp.c takes a path parameter which is not properly sanitized before being used in the truncate system call.\nIf an attacker can control the path parameter, they could use path traversal sequences like \"../\" to modify the size of files outside the intended mount point. \n",
      "classification": "very promising",
      "cwe": "CWE-22",
      "function_names": [
        "xmp_truncate"
      ],
      "filenames": [
        "example/fusexmp.c"
      ]
    },
    {
      "headline": "Path Traversal in fusexmp.c:xmp_utime",
      "analysis": "The xmp_utime function in fusexmp.c takes a path argument and uses it in a call to utime without any validation or sanitization. \nThis makes the function vulnerable to path traversal attacks. \nAn attacker could provide a specially crafted path with \"..\" segments to modify the access and modification timestamps of files outside the intended directory.\n",
      "classification": "very promising",
      "cwe": "CWE-22",
      "function_names": [
        "xmp_utime"
      ],
      "filenames": [
        "example/fusexmp.c"
      ]
    },
    {
      "headline": "Path Traversal in fusexmp.c:xmp_open",
      "analysis": "The xmp_open function in fusexmp.c is vulnerable to a path traversal attack because it uses the user-supplied path directly in a call to open without any validation.\nThis means an attacker could potentially open files outside the intended directory by providing a path with \"../\" sequences.\n",
      "classification": "very promising",
      "cwe": "CWE-22",
      "function_names": [
        "xmp_open"
      ],
      "filenames": [
        "example/fusexmp.c"
      ]
    },
    {
      "headline": "Path Traversal in fusexmp.c:xmp_read",
      "analysis": "The xmp_read function in fusexmp.c is vulnerable to path traversal. \nIt uses the path argument, which comes directly from user input, to open a file with open(path, O_RDONLY).\nIf an attacker can control the path parameter, they could use traversal sequences like \"../\" to read arbitrary files outside the intended directory.\n",
      "classification": "very promising",
      "cwe": "CWE-22",
      "function_names": [
        "xmp_read"
      ],
      "filenames": [
        "example/fusexmp.c"
      ]
    },
    {
      "headline": "Path Traversal in fusexmp.c:xmp_write",
      "analysis": "The function xmp_write in fusexmp.c is susceptible to a path traversal vulnerability. It takes a user-controlled path argument and uses it directly in the open system call without any validation. \nThis could allow an attacker to write data to arbitrary files outside the intended directory by crafting a malicious path string containing \"../\" sequences.\n",
      "classification": "very promising",
      "cwe": "CWE-22",
      "function_names": [
        "xmp_write"
      ],
      "filenames": [
        "example/fusexmp.c"
      ]
    },
    {
      "headline": "Path Traversal in fusexmp.c:xmp_statfs",
      "analysis": "The xmp_statfs function in fusexmp.c is vulnerable to path traversal because it takes a user-provided path argument and passes it directly to statfs without any validation. \nThis could allow an attacker to retrieve filesystem statistics for directories outside the intended mount point by supplying a malicious path. \n",
      "classification": "very promising",
      "cwe": "CWE-22",
      "function_names": [
        "xmp_statfs"
      ],
      "filenames": [
        "example/fusexmp.c"
      ]
    },
    {
      "headline": "Path Traversal in fusexmp.c:xmp_setxattr",
      "analysis": "The xmp_setxattr function in fusexmp.c is vulnerable to a path traversal attack. \nIt directly uses the user-provided path argument in the lsetxattr system call without any validation or sanitization.\nAn attacker could use \"..\" sequences in the path to set extended attributes on files outside the expected directory, potentially allowing them to manipulate file metadata or gain unauthorized access.\n",
      "classification": "very promising",
      "cwe": "CWE-22",
      "function_names": [
        "xmp_setxattr"
      ],
      "filenames": [
        "example/fusexmp.c"
      ]
    },
    {
      "headline": "Path Traversal in fusexmp.c:xmp_getxattr",
      "analysis": "The xmp_getxattr function in fusexmp.c takes the path argument from user input and passes it directly to lgetxattr without any sanitization. \nAn attacker could use \"..\" or similar sequences in the path to read extended attributes of files outside the intended directory, potentially leaking sensitive information. \n",
      "classification": "very promising",
      "cwe": "CWE-22",
      "function_names": [
        "xmp_getxattr"
      ],
      "filenames": [
        "example/fusexmp.c"
      ]
    },
    {
      "headline": "Path Traversal in fusexmp.c:xmp_listxattr",
      "analysis": "The function xmp_listxattr in fusexmp.c is vulnerable to path traversal.\nIt uses the user-provided path directly in the llistxattr system call without any validation.\nAn attacker could craft a path containing \"../\" sequences to list extended attributes of files outside the intended directory, potentially exposing sensitive information.\n",
      "classification": "very promising",
      "cwe": "CWE-22",
      "function_names": [
        "xmp_listxattr"
      ],
      "filenames": [
        "example/fusexmp.c"
      ]
    },
    {
      "headline": "Path Traversal in fusexmp.c:xmp_removexattr",
      "analysis": "The xmp_removexattr function in fusexmp.c is vulnerable to a path traversal attack.\nIt takes a user-supplied path argument and passes it directly to the lremovexattr system call without any validation.\nAn attacker could use \"..\" sequences in the path to remove extended attributes from files outside the intended directory, potentially affecting file security or integrity. \n",
      "classification": "very promising",
      "cwe": "CWE-22",
      "function_names": [
        "xmp_removexattr"
      ],
      "filenames": [
        "example/fusexmp.c"
      ]
    },
    {
      "headline": "Possible Integer Overflow in lib/fuse.c:get_path_name",
      "analysis": "The get_path_name function in lib/fuse.c uses a fixed-size buffer (buf) to construct the path string. \nWhile it checks for buffer overflow when adding individual components (add_name function), there's no check for the overall path length.\nIf an attacker can create a deeply nested directory structure, it might be possible to cause a buffer overflow in buf, leading to potential denial of service or code execution vulnerabilities.\n",
      "classification": "slightly promising",
      "cwe": "CWE-190",
      "function_names": [
        "get_path_name"
      ],
      "filenames": [
        "lib/fuse.c"
      ]
    },
    {
      "headline": "Possible Integer Overflow in lib/helper.c:add_option_to",
      "analysis": "The function add_option_to in lib/helper.c reallocates memory for the option string without checking for integer overflow in the calculation oldlen + 1 + len + 1. \nIf an attacker can control the size of the options (oldlen and len), they may be able to trigger an integer overflow. \n",
      "classification": "slightly promising",
      "cwe": "CWE-190",
      "function_names": [
        "add_option_to"
      ],
      "filenames": [
        "lib/helper.c"
      ]
    },
    {
      "headline": "Potential Denial of Service in lib/fuse.c:fuse_process_cmd",
      "analysis": "The fuse_process_cmd function in lib/fuse.c doesn't check for the size of the incoming command before calling malloc to allocate buf. \nIf an attacker can send a very large command, it could lead to excessive memory allocation, potentially causing a denial of service.\n",
      "classification": "not promising",
      "cwe": "CWE-770",
      "function_names": [
        "fuse_process_cmd"
      ],
      "filenames": [
        "lib/fuse.c"
      ]
    },
    {
      "headline": "Potential Denial of Service in lib/fuse.c:fuse_read_cmd",
      "analysis": "The fuse_read_cmd function allocates a buffer of size FUSE_MAX_IN without checking if a smaller command could be received.\nThis could lead to unnecessary memory consumption if an attacker repeatedly sends small commands, potentially contributing to a denial of service.\n",
      "classification": "not promising",
      "cwe": "CWE-770",
      "function_names": [
        "fuse_read_cmd"
      ],
      "filenames": [
        "lib/fuse.c"
      ]
    }
  ],
  "scores": [
    {
      "stats": {
        "fn": 1,
        "tp": 0,
        "fp": 22
      },
      "mapping": {},
      "vuln_dates": {
        "CVE-2023-1108": "2023-09-14T15:15:08"
      },
      "scoring_model": "claude-3-opus-20240229",
      "type": "llm",
      "instruction_template_hash": "245ace12b6361954d0a2"
    },
    {
      "stats": {
        "fn": 1,
        "tp": 0,
        "fp": 22
      },
      "mapping": {},
      "vuln_dates": {
        "CVE-2023-1108": "2023-09-14T15:15:08"
      },
      "scoring_model": "claude-3-5-sonnet-20240620",
      "type": "llm",
      "instruction_template_hash": "245ace12b6361954d0a2"
    }
  ],
  "instruction_template_hash": "10c0163db4740318a544",
  "version": "0.1.0"
}
