{
  "commit": "80723bafd1246dffe25b7c2544f5453ca408354a",
  "repo_url": "https://github.com/andrei-tatar/nora-firebase-common",
  "model": "claude-3-sonnet-20240229",
  "chunk_hashes": [
    "f1d8ccc2d3be01018eea"
  ],
  "responses": [
    {
      "content": "```yaml\nleads:\n  - headline: Improper input validation in the 'generate-schema.mjs' file\n    analysis: |\n      The 'generate-schema.mjs' file is responsible for generating the schema for device data structures. However, it reads and writes files from the file system without any sanitization or input validation. This could potentially lead to path traversal vulnerabilities or arbitrary file overwrite vulnerabilities if the file paths are controlled by user input.\n    cwe: CWE-22\n    function_names:\n      - readFileSync\n      - writeFileSync\n    filenames:\n      - generate-schema.mjs\n    classification: very promising\n\n  - headline: Use of third-party libraries with known vulnerabilities\n    analysis: |\n      The project uses the 'ts-json-schema-generator' library for generating JSON schemas from TypeScript types. However, it's important to ensure that the library is up-to-date and does not have any known vulnerabilities. Using outdated or vulnerable third-party libraries can introduce security risks to the application.\n    cwe: CWE-1035\n    function_names:\n      - createGenerator\n    filenames:\n      - generate-schema.mjs\n    classification: slightly promising\n\n  - headline: Potential denial of service vulnerability in the 'updateState' function\n    analysis: |\n      The 'updateState' function in the 'update-state.ts' file performs deep copying of objects using JSON.stringify and JSON.parse. However, this approach can lead to performance issues and potential denial of service vulnerabilities if the objects being copied are excessively large or contain circular references.\n    cwe: CWE-400\n    function_names:\n      - deepClone\n    filenames:\n      - update-state.ts\n    classification: slightly promising\n\n  - headline: Potential command injection vulnerability in the 'executeCommand' function\n    analysis: |\n      The 'executeCommand' function in the 'execute/execute.ts' file takes command and parameter input without any validation or sanitization. If these inputs are derived from untrusted sources, it could potentially lead to command injection vulnerabilities.\n    cwe: CWE-77\n    function_names:\n      - executeCommand\n    filenames:\n      - execute/execute.ts\n    classification: very promising\n\n  - headline: Insecure usage of cryptographic functions in the 'secondary-verification.ts' file\n    analysis: |\n      The 'secondary-verification.ts' file implements two-factor authentication using a PIN code. However, the PIN code is compared directly in plaintext, which is insecure. Instead, the PIN code should be securely hashed and the hash values should be compared to prevent potential leakage of sensitive information.\n    cwe: CWE-312\n    function_names:\n      - checkSecondaryVerification\n    filenames:\n      - execute/secondary-verification.ts\n    classification: very promising\n```",
      "date": "2024-06-08T22:15:18.274444",
      "usage": {
        "prompt_tokens": 30133,
        "completion_tokens": 675,
        "cost": 0.100524
      }
    }
  ],
  "leads": [
    {
      "headline": "Improper input validation in the 'generate-schema.mjs' file",
      "analysis": "The 'generate-schema.mjs' file is responsible for generating the schema for device data structures. However, it reads and writes files from the file system without any sanitization or input validation. This could potentially lead to path traversal vulnerabilities or arbitrary file overwrite vulnerabilities if the file paths are controlled by user input.\n",
      "classification": "very promising",
      "cwe": "CWE-22",
      "function_names": [
        "readFileSync",
        "writeFileSync"
      ],
      "filenames": [
        "generate-schema.mjs"
      ]
    },
    {
      "headline": "Use of third-party libraries with known vulnerabilities",
      "analysis": "The project uses the 'ts-json-schema-generator' library for generating JSON schemas from TypeScript types. However, it's important to ensure that the library is up-to-date and does not have any known vulnerabilities. Using outdated or vulnerable third-party libraries can introduce security risks to the application.\n",
      "classification": "slightly promising",
      "cwe": "CWE-1035",
      "function_names": [
        "createGenerator"
      ],
      "filenames": [
        "generate-schema.mjs"
      ]
    },
    {
      "headline": "Potential denial of service vulnerability in the 'updateState' function",
      "analysis": "The 'updateState' function in the 'update-state.ts' file performs deep copying of objects using JSON.stringify and JSON.parse. However, this approach can lead to performance issues and potential denial of service vulnerabilities if the objects being copied are excessively large or contain circular references.\n",
      "classification": "slightly promising",
      "cwe": "CWE-400",
      "function_names": [
        "deepClone"
      ],
      "filenames": [
        "update-state.ts"
      ]
    },
    {
      "headline": "Potential command injection vulnerability in the 'executeCommand' function",
      "analysis": "The 'executeCommand' function in the 'execute/execute.ts' file takes command and parameter input without any validation or sanitization. If these inputs are derived from untrusted sources, it could potentially lead to command injection vulnerabilities.\n",
      "classification": "very promising",
      "cwe": "CWE-77",
      "function_names": [
        "executeCommand"
      ],
      "filenames": [
        "execute/execute.ts"
      ]
    },
    {
      "headline": "Insecure usage of cryptographic functions in the 'secondary-verification.ts' file",
      "analysis": "The 'secondary-verification.ts' file implements two-factor authentication using a PIN code. However, the PIN code is compared directly in plaintext, which is insecure. Instead, the PIN code should be securely hashed and the hash values should be compared to prevent potential leakage of sensitive information.\n",
      "classification": "very promising",
      "cwe": "CWE-312",
      "function_names": [
        "checkSecondaryVerification"
      ],
      "filenames": [
        "execute/secondary-verification.ts"
      ]
    }
  ],
  "scores": [
    {
      "stats": {
        "fn": 1,
        "tp": 0,
        "fp": 3
      },
      "mapping": {},
      "vuln_dates": {
        "CVE-2024-30564": "2024-04-18T15:15:30"
      },
      "scoring_model": "gpt-4o-2024-05-13",
      "type": "llm",
      "instruction_template_hash": "8998f09cf57fca8a6e03"
    }
  ],
  "instruction_template_hash": "10c0163db4740318a544",
  "version": "0.1.0"
}
