{
  "commit": "26703f4dd9798a493149b5a45517afc7bde6eb1c",
  "repo_url": "https://github.com/mansuf/mangadex-downloader",
  "model": "claude-3-sonnet-20240229",
  "chunk_hashes": [
    "7ca2164ca97959219b37"
  ],
  "responses": [
    {
      "content": "Here is the YAML representation of potential security vulnerabilities in the provided codebase, according to the Pydantic model definitions:\n\n```yaml\nleads:\n  - headline: Use of insufficiently random values\n    analysis: |\n      The `range` module uses a seeded random number generator to generate the range pattern for chapters and pages to download. However, the implementation does not specify how the seed is generated, which could potentially lead to predictable or weak random values being used. This could allow an attacker to predict the range pattern and potentially gain unauthorized access to chapters or pages.\n    cwe: CWE-330\n    function_names:\n      - RangeChecker.__init__\n      - _Pattern.get_type\n    filenames:\n      - mangadex_downloader/range.py\n    classification: slightly promising\n\n  - headline: Use of hard-coded credentials\n    analysis: |\n      The `network` module contains a hard-coded user agent string that includes the application name and version. While not a direct credential, this information could potentially be used by an attacker to identify and target the application.\n    cwe: CWE-798\n    function_names:\n      - requestsMangaDexSession.__init__\n    filenames:\n      - mangadex_downloader/network.py\n    classification: slightly promising\n\n  - headline: Missing encryption of sensitive data\n    analysis: |\n      The `config` module stores authentication tokens in cleartext in a file on the user's system. These tokens could potentially be accessed by an attacker if the system is compromised, allowing them to impersonate the user on the MangaDex platform.\n    cwe: CWE-312\n    function_names:\n      - AuthCacheManager._write\n    filenames:\n      - mangadex_downloader/config.py\n    classification: very promising\n\n  - headline: Improper input validation\n    analysis: |\n      The `cli.validator` module allows users to input URLs and other parameters from the command line or a file. There appears to be minimal validation or sanitization of this input, which could potentially lead to injection attacks or other security vulnerabilities if the input is not properly validated.\n    cwe: CWE-20\n    function_names:\n      - validate_url\n    filenames:\n      - mangadex_downloader/cli/validator.py\n    classification: very promising\n\n  - headline: Use of a broken or risky cryptographic algorithm\n    analysis: |\n      The `config` module uses the `jwt` library to decode and extract expiration times from authentication tokens. However, the implementation does not specify the algorithm used for decoding, which could potentially be a weak or broken algorithm. If a weak algorithm is used, it could allow an attacker to forge or tamper with the tokens.\n    cwe: CWE-327\n    function_names:\n      - AuthCacheManager.get_expiration_time\n    filenames:\n      - mangadex_downloader/config.py\n    classification: slightly promising\n\n  - headline: Improper handling of exceptional conditions\n    analysis: |\n      The `downloader` module appears to handle exceptions and errors in various ways, but there is no consistent or centralized approach to handling and logging exceptions. This could potentially lead to sensitive information being exposed in error messages or logs, or errors being silently ignored or mishandled.\n    cwe: CWE-755\n    function_names:\n      - ChapterPageDownloader.download\n    filenames:\n      - mangadex_downloader/downloader.py\n    classification: slightly promising\n```\n\nNote that this analysis is based on the provided code and may not be exhaustive. Additionally, the classification of vulnerabilities as \"very promising,\" \"slightly promising,\" or \"not promising\" is subjective and may vary based on the specific context and risk assessment.",
      "date": "2024-06-13T09:59:02.243563",
      "usage": {
        "prompt_tokens": 85591,
        "completion_tokens": 868,
        "cost": 0.269793
      }
    }
  ],
  "leads": [
    {
      "headline": "Use of insufficiently random values",
      "analysis": "The range module uses a seeded random number generator to generate the range pattern for chapters and pages to download. However, the implementation does not specify how the seed is generated, which could potentially lead to predictable or weak random values being used. This could allow an attacker to predict the range pattern and potentially gain unauthorized access to chapters or pages.\n",
      "classification": "slightly promising",
      "cwe": "CWE-330",
      "function_names": [
        "RangeChecker.__init__",
        "_Pattern.get_type"
      ],
      "filenames": [
        "mangadex_downloader/range.py"
      ]
    },
    {
      "headline": "Use of hard-coded credentials",
      "analysis": "The network module contains a hard-coded user agent string that includes the application name and version. While not a direct credential, this information could potentially be used by an attacker to identify and target the application.\n",
      "classification": "slightly promising",
      "cwe": "CWE-798",
      "function_names": [
        "requestsMangaDexSession.__init__"
      ],
      "filenames": [
        "mangadex_downloader/network.py"
      ]
    },
    {
      "headline": "Missing encryption of sensitive data",
      "analysis": "The config module stores authentication tokens in cleartext in a file on the user's system. These tokens could potentially be accessed by an attacker if the system is compromised, allowing them to impersonate the user on the MangaDex platform.\n",
      "classification": "very promising",
      "cwe": "CWE-312",
      "function_names": [
        "AuthCacheManager._write"
      ],
      "filenames": [
        "mangadex_downloader/config.py"
      ]
    },
    {
      "headline": "Improper input validation",
      "analysis": "The cli.validator module allows users to input URLs and other parameters from the command line or a file. There appears to be minimal validation or sanitization of this input, which could potentially lead to injection attacks or other security vulnerabilities if the input is not properly validated.\n",
      "classification": "very promising",
      "cwe": "CWE-20",
      "function_names": [
        "validate_url"
      ],
      "filenames": [
        "mangadex_downloader/cli/validator.py"
      ]
    },
    {
      "headline": "Use of a broken or risky cryptographic algorithm",
      "analysis": "The config module uses the jwt library to decode and extract expiration times from authentication tokens. However, the implementation does not specify the algorithm used for decoding, which could potentially be a weak or broken algorithm. If a weak algorithm is used, it could allow an attacker to forge or tamper with the tokens.\n",
      "classification": "slightly promising",
      "cwe": "CWE-327",
      "function_names": [
        "AuthCacheManager.get_expiration_time"
      ],
      "filenames": [
        "mangadex_downloader/config.py"
      ]
    },
    {
      "headline": "Improper handling of exceptional conditions",
      "analysis": "The downloader module appears to handle exceptions and errors in various ways, but there is no consistent or centralized approach to handling and logging exceptions. This could potentially lead to sensitive information being exposed in error messages or logs, or errors being silently ignored or mishandled.\n",
      "classification": "slightly promising",
      "cwe": "CWE-755",
      "function_names": [
        "ChapterPageDownloader.download"
      ],
      "filenames": [
        "mangadex_downloader/downloader.py"
      ]
    }
  ],
  "scores": [
    {
      "stats": {
        "fn": 1,
        "tp": 0,
        "fp": 2
      },
      "mapping": {},
      "vuln_dates": {
        "CVE-2022-36082": "2022-09-07T22:15:08"
      },
      "scoring_model": "claude-3-opus-20240229",
      "type": "llm",
      "instruction_template_hash": "245ace12b6361954d0a2"
    }
  ],
  "instruction_template_hash": "10c0163db4740318a544",
  "version": "0.1.0"
}
