{
  "commit": "48063aeb0dd2065a8af7c976d6650d49980949a4",
  "repo_url": "https://github.com/snowflakedb/snowflake-hive-metastore-connector",
  "model": "claude-3-5-sonnet-20240620",
  "chunk_hashes": [
    "cf53e68c6375f8df4e66"
  ],
  "responses": [
    {
      "content": "```yaml\nleads:\n  - headline: Hard-coded AWS credentials in deploy.sh script\n    analysis: |\n      The deploy.sh script contains hard-coded AWS access key ID and secret access key values. These are sensitive credentials that should not be stored in plain text in source code. Storing credentials this way could allow an attacker who gains access to the source code to compromise the associated AWS account.\n    cwe: CWE-798\n    function_names:\n      - generateCredentialsString\n    filenames:\n      - deploy.sh\n      - src/main/java/net/snowflake/hivemetastoreconnector/util/StageCredentialUtil.java  \n    classification: very promising\n\n  - headline: Potential SQL injection in CreateExternalTable class\n    analysis: |\n      The CreateExternalTable class constructs SQL queries by concatenating user-provided input (e.g. table names) directly into query strings. This could allow SQL injection attacks if the input is not properly sanitized. While some escaping is done, it may not be comprehensive enough to prevent all injection scenarios.\n    cwe: CWE-89\n    function_names:\n      - generateCreateTableCommand\n      - generateCreateStageCommand  \n    filenames:\n      - src/main/java/net/snowflake/hivemetastoreconnector/commands/CreateExternalTable.java\n    classification: slightly promising\n\n  - headline: Unsafe deserialization in HiveSyncTool\n    analysis: |\n      The HiveSyncTool class deserializes data from an untrusted source (Hive metastore) without proper validation. This could potentially allow an attacker to execute arbitrary code by manipulating the serialized data. The deserialization happens when retrieving tables and partitions from the Hive metastore client.\n    cwe: CWE-502\n    function_names:\n      - sync\n    filenames:\n      - src/main/java/net/snowflake/hivemetastoreconnector/core/HiveSyncTool.java\n    classification: slightly promising\n\n  - headline: Insufficient input validation in SnowflakeClient\n    analysis: |\n      The SnowflakeClient class executes SQL queries constructed from user input without sufficient validation. While some escaping is done, it may not cover all cases of malicious input. This could potentially allow SQL injection or command injection attacks.\n    cwe: CWE-20\n    function_names:\n      - executeStatement\n      - generateAndExecuteSnowflakeStatements\n    filenames:\n      - src/main/java/net/snowflake/hivemetastoreconnector/core/SnowflakeClient.java\n    classification: slightly promising\n\n  - headline: Weak password requirements in SnowflakeConf\n    analysis: |\n      The SnowflakeConf class handles authentication details like usernames and passwords, but does not enforce any password strength requirements. This could allow weak passwords to be used, making it easier for attackers to guess or brute force credentials.\n    cwe: CWE-521\n    function_names: []\n    filenames:\n      - src/main/java/net/snowflake/hivemetastoreconnector/SnowflakeConf.java  \n    classification: slightly promising\n```",
      "date": "2024-07-08T05:11:02.884840",
      "usage": {
        "prompt_tokens": 72270,
        "completion_tokens": 762,
        "cost": 0.22824
      }
    }
  ],
  "leads": [
    {
      "headline": "Hard-coded AWS credentials in deploy.sh script",
      "analysis": "The deploy.sh script contains hard-coded AWS access key ID and secret access key values. These are sensitive credentials that should not be stored in plain text in source code. Storing credentials this way could allow an attacker who gains access to the source code to compromise the associated AWS account.\n",
      "classification": "very promising",
      "cwe": "CWE-798",
      "function_names": [
        "generateCredentialsString"
      ],
      "filenames": [
        "deploy.sh",
        "src/main/java/net/snowflake/hivemetastoreconnector/util/StageCredentialUtil.java"
      ]
    },
    {
      "headline": "Potential SQL injection in CreateExternalTable class",
      "analysis": "The CreateExternalTable class constructs SQL queries by concatenating user-provided input (e.g. table names) directly into query strings. This could allow SQL injection attacks if the input is not properly sanitized. While some escaping is done, it may not be comprehensive enough to prevent all injection scenarios.\n",
      "classification": "slightly promising",
      "cwe": "CWE-89",
      "function_names": [
        "generateCreateTableCommand",
        "generateCreateStageCommand"
      ],
      "filenames": [
        "src/main/java/net/snowflake/hivemetastoreconnector/commands/CreateExternalTable.java"
      ]
    },
    {
      "headline": "Unsafe deserialization in HiveSyncTool",
      "analysis": "The HiveSyncTool class deserializes data from an untrusted source (Hive metastore) without proper validation. This could potentially allow an attacker to execute arbitrary code by manipulating the serialized data. The deserialization happens when retrieving tables and partitions from the Hive metastore client.\n",
      "classification": "slightly promising",
      "cwe": "CWE-502",
      "function_names": [
        "sync"
      ],
      "filenames": [
        "src/main/java/net/snowflake/hivemetastoreconnector/core/HiveSyncTool.java"
      ]
    },
    {
      "headline": "Insufficient input validation in SnowflakeClient",
      "analysis": "The SnowflakeClient class executes SQL queries constructed from user input without sufficient validation. While some escaping is done, it may not cover all cases of malicious input. This could potentially allow SQL injection or command injection attacks.\n",
      "classification": "slightly promising",
      "cwe": "CWE-20",
      "function_names": [
        "executeStatement",
        "generateAndExecuteSnowflakeStatements"
      ],
      "filenames": [
        "src/main/java/net/snowflake/hivemetastoreconnector/core/SnowflakeClient.java"
      ]
    },
    {
      "headline": "Weak password requirements in SnowflakeConf",
      "analysis": "The SnowflakeConf class handles authentication details like usernames and passwords, but does not enforce any password strength requirements. This could allow weak passwords to be used, making it easier for attackers to guess or brute force credentials.\n",
      "classification": "slightly promising",
      "cwe": "CWE-521",
      "function_names": [],
      "filenames": [
        "src/main/java/net/snowflake/hivemetastoreconnector/SnowflakeConf.java"
      ]
    }
  ],
  "scores": [
    {
      "stats": {
        "fn": 1,
        "tp": 0,
        "fp": 1
      },
      "mapping": {},
      "vuln_dates": {
        "CVE-2024-28851": "2024-03-15T19:15:07"
      },
      "scoring_model": "claude-3-5-sonnet-20240620",
      "type": "llm",
      "instruction_template_hash": "245ace12b6361954d0a2"
    }
  ],
  "instruction_template_hash": "10c0163db4740318a544",
  "version": "0.1.0"
}
