{
  "commit": "000a21240da490d27d4032e26c5f6c42a8353fbc",
  "repo_url": "https://github.com/azuread/passport-azure-ad",
  "model": "gpt-4o-2024-05-13",
  "chunk_hashes": [
    "911674a43625de430612"
  ],
  "responses": [
    {
      "content": "```yaml\nleads:\n  - headline: \"Hardcoded clientSecret in server-oauth2-b2c/server_config.js\"\n    analysis: |\n      The file server-oauth2-b2c/server_config.js contains hardcoded clientSecret in the creds object. Hardcoding secrets in source code can lead to unauthorized access if the source code is ever exposed or leaked.\n    cwe: CWE-798\n    function_names: []\n    filenames:\n      - \"examples/server-oauth2-b2c/server_config.js\"\n    classification: very promising\n\n  - headline: \"Original URL vulnerability in common/utils.js\"\n    analysis: |\n      The function `originalURL` in the file utils.js constructs the original URL of the request using user-supplied headers like `x-forwarded-proto`. This can lead to URL-based attacks such as Host Header Injection if not properly sanitized or validated.\n    cwe: CWE-22\n    function_names:\n      - \"originalURL\"\n    filenames:\n      - \"lib/passport-azure-ad/aadutils.js\"\n    classification: slightly promising\n\n  - headline: \"No validation of audience in bearer strategy\"\n    analysis: |\n      The bearerstrategy.js file retrieves the audience from token and metadata but does not implement strict checks for expected audience values. This can lead to security issues if tokens intended for different audiences are accepted as valid.\n    cwe: CWE-347\n    function_names:\n      - \"jwtVerify\"\n    filenames:\n      - \"lib/passport-azure-ad/bearerstrategy.js\"\n    classification: very promising\n\n  - headline: \"Weak logging configuration\"\n    analysis: |\n      The logging configuration is initialized without specifying a file or proper log rotation mechanism, leading to potential data loss or overflow of log files.\n    cwe: CWE-778\n    function_names: []\n    filenames:\n      - \"lib/passport-azure-ad/logging.js\"\n    classification: slightly promising\n\n  - headline: \"Improper TLS verification\"\n    analysis: |\n      The library seems to accept all certificates without checking the validity (e.g., expiration, revocation) of the certificate. This can be risky in scenarios where the metadata URL or other resources are transmitted over HTTPS.\n    cwe: CWE-295\n    function_names: []\n    filenames:\n      - \"lib/passport-azure-ad/metadata.js\"\n    classification: slightly promising\n\n  - headline: \"Unsanitized inputs in XML parsing\"\n    analysis: |\n      Several files (oidcstrategy.js, wsfedsaml.js) parse XML from external sources without proper sanitization. This can lead to XML external entity (XXE) attacks if the XML is crafted in a malicious way.\n    cwe: CWE-611\n    function_names:\n      - \"validateResponse\"\n      - \"validateSignature\"\n    filenames:\n      - \"lib/passport-azure-ad/oidcstrategy.js\"\n      - \"lib/passport-azure-ad/wsfedsaml.js\"\n    classification: very promising\n```",
      "date": "2024-06-12T15:09:36.546939",
      "usage": {
        "prompt_tokens": 51765,
        "completion_tokens": 617,
        "cost": 0.26808
      }
    }
  ],
  "leads": [
    {
      "headline": "Hardcoded clientSecret in server-oauth2-b2c/server_config.js",
      "analysis": "The file server-oauth2-b2c/server_config.js contains hardcoded clientSecret in the creds object. Hardcoding secrets in source code can lead to unauthorized access if the source code is ever exposed or leaked.\n",
      "classification": "very promising",
      "cwe": "CWE-798",
      "function_names": [],
      "filenames": [
        "examples/server-oauth2-b2c/server_config.js"
      ]
    },
    {
      "headline": "Original URL vulnerability in common/utils.js",
      "analysis": "The function originalURL in the file utils.js constructs the original URL of the request using user-supplied headers like x-forwarded-proto. This can lead to URL-based attacks such as Host Header Injection if not properly sanitized or validated.\n",
      "classification": "slightly promising",
      "cwe": "CWE-22",
      "function_names": [
        "originalURL"
      ],
      "filenames": [
        "lib/passport-azure-ad/aadutils.js"
      ]
    },
    {
      "headline": "No validation of audience in bearer strategy",
      "analysis": "The bearerstrategy.js file retrieves the audience from token and metadata but does not implement strict checks for expected audience values. This can lead to security issues if tokens intended for different audiences are accepted as valid.\n",
      "classification": "very promising",
      "cwe": "CWE-347",
      "function_names": [
        "jwtVerify"
      ],
      "filenames": [
        "lib/passport-azure-ad/bearerstrategy.js"
      ]
    },
    {
      "headline": "Weak logging configuration",
      "analysis": "The logging configuration is initialized without specifying a file or proper log rotation mechanism, leading to potential data loss or overflow of log files.\n",
      "classification": "slightly promising",
      "cwe": "CWE-778",
      "function_names": [],
      "filenames": [
        "lib/passport-azure-ad/logging.js"
      ]
    },
    {
      "headline": "Improper TLS verification",
      "analysis": "The library seems to accept all certificates without checking the validity (e.g., expiration, revocation) of the certificate. This can be risky in scenarios where the metadata URL or other resources are transmitted over HTTPS.\n",
      "classification": "slightly promising",
      "cwe": "CWE-295",
      "function_names": [],
      "filenames": [
        "lib/passport-azure-ad/metadata.js"
      ]
    },
    {
      "headline": "Unsanitized inputs in XML parsing",
      "analysis": "Several files (oidcstrategy.js, wsfedsaml.js) parse XML from external sources without proper sanitization. This can lead to XML external entity (XXE) attacks if the XML is crafted in a malicious way.\n",
      "classification": "very promising",
      "cwe": "CWE-611",
      "function_names": [
        "validateResponse",
        "validateSignature"
      ],
      "filenames": [
        "lib/passport-azure-ad/oidcstrategy.js",
        "lib/passport-azure-ad/wsfedsaml.js"
      ]
    }
  ],
  "scores": [
    {
      "stats": {
        "fn": 0,
        "tp": 1,
        "fp": 2
      },
      "mapping": {
        "1": "CVE-2016-7191"
      },
      "vuln_dates": {
        "CVE-2016-7191": "2016-09-28T20:59:00"
      },
      "scoring_model": "claude-3-opus-20240229",
      "type": "llm",
      "instruction_template_hash": "245ace12b6361954d0a2"
    },
    {
      "stats": {
        "fn": 1,
        "tp": 0,
        "fp": 3
      },
      "mapping": {},
      "vuln_dates": {
        "CVE-2016-7191": "2016-09-28T20:59:00"
      },
      "scoring_model": "claude-3-5-sonnet-20240620",
      "type": "llm",
      "instruction_template_hash": "245ace12b6361954d0a2"
    }
  ],
  "instruction_template_hash": "10c0163db4740318a544",
  "version": "0.1.0"
}
