{
  "commit": "4b0484662bae2dae121af501a84360719b5b6eb1",
  "repo_url": "https://github.com/pagehelper/mybatis-pagehelper",
  "model": "gpt-4o-2024-05-13",
  "chunk_hashes": [
    "b17d43b2a291f2ba8487"
  ],
  "responses": [
    {
      "content": "```yaml\nleads:\n  - headline: \"Potential SQL Injection\"\n    analysis: |\n      In the `UserMapper` interface, methods like `selectByOrder` and `selectByOrder2` use string concatenation to include the `order` parameter directly into the SQL query. This can allow an attacker to manipulate the `order` parameter to perform an SQL Injection attack.\n    cwe: CWE-89\n    function_names:\n      - selectByOrder\n      - selectByOrder2\n    filenames:\n      - src/test/java/com/github/pagehelper/mapper/UserMapper.java\n    classification: very promising\n\n  - headline: \"Potential Command Injection\"\n    analysis: |\n      In the file `SqlServerTest.java`, raw SQL strings are constructed using concatenation of external input parameters. For example, the method `testSqlLeftJoin` constructs SQL by concatenation which can be manipulated if the input is not properly sanitized.\n    cwe: CWE-77\n    function_names:\n      - testSqlLeftJoin\n    filenames:\n      - src/test/java/com/github/pagehelper/sql/SqlServerTest.java\n    classification: slightly promising\n\n  - headline: \"Potential Improper Logging of Sensitive Information\"\n    analysis: |\n      In the `ExecutorUtil` class, sensitive SQL statements and parameters are logged. If these logs are accessible to unauthorized users, this can lead to exposure of sensitive information such as credentials or personal data.\n    cwe: CWE-532\n    function_names:\n      - executeManualCount\n      - executeAutoCount\n      - pageQuery\n    filenames:\n      - src/main/java/com/github/pagehelper/util/ExecutorUtil.java\n    classification: very promising\n\n  - headline: \"Reflected XSS in Dynamic Error Messages\"\n    analysis: |\n      In the `SqlServerParser` and other related classes, error messages are constructed using external inputs which might not be properly sanitized. This can lead to reflected Cross-Site Scripting (XSS) if those errors are displayed in a web application context without proper encoding.\n    cwe: CWE-79\n    function_names:\n      - convertToPageSql\n    filenames:\n      - src/main/java/com/github/pagehelper/parser/SqlServerParser.java\n    classification: slightly promising\n\n  - headline: \"Hardcoded Credentials\"\n    analysis: |\n      In multiple files, hardcoded credentials and keys are found which can lead to serious security risks if accessed by unauthorized users. For instance, \"PageRowBoundsTest.java\" and other test files may contain hardcoded sensitive data used for database connections.\n    cwe: CWE-798\n    function_names: []\n    filenames:\n      - src/test/java/com/github/pagehelper/rowbounds/test/PageRowBoundsTest.java\n      - src/test/java/com/github/pagehelper/util/MybatisAutoDialectHelper.java\n    classification: very promising\n\n  - headline: \"Use of Insecure Hashing Algorithms\"\n    analysis: |\n      Usage of MD5 and other insecure hashing algorithms can be found, which are known to be vulnerable to collision attacks. For example, in the `TestBoundSqlInterceptor` class, hashing mechanisms might be used insecurely.\n    cwe: CWE-327\n    function_names:\n      - doBoundSql\n    filenames:\n      - src/test/java/com/github/pagehelper/test/basic/provider/TestBoundSqlInterceptor.java\n    classification: slightly promising\n```\n\nThis YAML object identifies several security vulnerabilities present in the codebase, including potential SQL injection, command injection, improper logging of sensitive information, reflected XSS, hardcoded credentials, and the use of insecure hashing algorithms. It classifies each vulnerability based on its potential impact and provides specific references to affected files and functions.",
      "date": "2024-06-14T15:12:35.851631",
      "usage": {
        "prompt_tokens": 126324,
        "completion_tokens": 756,
        "cost": 0.64296
      }
    }
  ],
  "leads": [
    {
      "headline": "Potential SQL Injection",
      "analysis": "In the UserMapper interface, methods like selectByOrder and selectByOrder2 use string concatenation to include the order parameter directly into the SQL query. This can allow an attacker to manipulate the order parameter to perform an SQL Injection attack.\n",
      "classification": "very promising",
      "cwe": "CWE-89",
      "function_names": [
        "selectByOrder",
        "selectByOrder2"
      ],
      "filenames": [
        "src/test/java/com/github/pagehelper/mapper/UserMapper.java"
      ]
    },
    {
      "headline": "Potential Command Injection",
      "analysis": "In the file SqlServerTest.java, raw SQL strings are constructed using concatenation of external input parameters. For example, the method testSqlLeftJoin constructs SQL by concatenation which can be manipulated if the input is not properly sanitized.\n",
      "classification": "slightly promising",
      "cwe": "CWE-77",
      "function_names": [
        "testSqlLeftJoin"
      ],
      "filenames": [
        "src/test/java/com/github/pagehelper/sql/SqlServerTest.java"
      ]
    },
    {
      "headline": "Potential Improper Logging of Sensitive Information",
      "analysis": "In the ExecutorUtil class, sensitive SQL statements and parameters are logged. If these logs are accessible to unauthorized users, this can lead to exposure of sensitive information such as credentials or personal data.\n",
      "classification": "very promising",
      "cwe": "CWE-532",
      "function_names": [
        "executeManualCount",
        "executeAutoCount",
        "pageQuery"
      ],
      "filenames": [
        "src/main/java/com/github/pagehelper/util/ExecutorUtil.java"
      ]
    },
    {
      "headline": "Reflected XSS in Dynamic Error Messages",
      "analysis": "In the SqlServerParser and other related classes, error messages are constructed using external inputs which might not be properly sanitized. This can lead to reflected Cross-Site Scripting (XSS) if those errors are displayed in a web application context without proper encoding.\n",
      "classification": "slightly promising",
      "cwe": "CWE-79",
      "function_names": [
        "convertToPageSql"
      ],
      "filenames": [
        "src/main/java/com/github/pagehelper/parser/SqlServerParser.java"
      ]
    },
    {
      "headline": "Hardcoded Credentials",
      "analysis": "In multiple files, hardcoded credentials and keys are found which can lead to serious security risks if accessed by unauthorized users. For instance, \"PageRowBoundsTest.java\" and other test files may contain hardcoded sensitive data used for database connections.\n",
      "classification": "very promising",
      "cwe": "CWE-798",
      "function_names": [],
      "filenames": [
        "src/test/java/com/github/pagehelper/rowbounds/test/PageRowBoundsTest.java",
        "src/test/java/com/github/pagehelper/util/MybatisAutoDialectHelper.java"
      ]
    },
    {
      "headline": "Use of Insecure Hashing Algorithms",
      "analysis": "Usage of MD5 and other insecure hashing algorithms can be found, which are known to be vulnerable to collision attacks. For example, in the TestBoundSqlInterceptor class, hashing mechanisms might be used insecurely.\n",
      "classification": "slightly promising",
      "cwe": "CWE-327",
      "function_names": [
        "doBoundSql"
      ],
      "filenames": [
        "src/test/java/com/github/pagehelper/test/basic/provider/TestBoundSqlInterceptor.java"
      ]
    }
  ],
  "scores": [
    {
      "stats": {
        "fn": 0,
        "tp": 1,
        "fp": 2
      },
      "mapping": {
        "0": "CVE-2022-28111"
      },
      "vuln_dates": {
        "CVE-2022-28111": "2022-05-04T13:15:08"
      },
      "scoring_model": "claude-3-opus-20240229",
      "type": "llm",
      "instruction_template_hash": "245ace12b6361954d0a2"
    }
  ],
  "instruction_template_hash": "10c0163db4740318a544",
  "version": "0.1.0"
}
