{
  "commit": "4820ebf4c74a5d97f727ed995759902075571abc",
  "repo_url": "https://github.com/jberger/galileo",
  "model": "gpt-4o-2024-05-13",
  "chunk_hashes": [
    "1db2fbea9896c5872e1b"
  ],
  "responses": [
    {
      "content": "```yaml\nleads:\n  - headline: \"Potential SQL Injection in Database Connection\"\n    analysis: |\n      The code appears to allow raw SQL queries to be constructed using unvalidated user inputs. This is inferred from the lack of any input sanitization in the database connection logic, especially in the sections handling the loading of the database schema and executing raw SQL statements.\n    cwe: CWE-89\n    function_names:\n      - connect\n    filenames:\n      - lib/Galileo.pm\n      - Build.PL\n    classification: very promising\n\n  - headline: \"Potential Command Injection through WebSocket Endpoint\"\n    analysis: |\n      The WebSocket handlers in the codebase do not appear to validate their inputs properly. An attacker could potentially exploit these endpoints to inject and execute malicious commands on the server.\n    cwe: CWE-77\n    function_names:\n      - sendViaWS\n    filenames:\n      - lib/Galileo/files/public/galileo-edit.js\n    classification: very promising\n\n  - headline: \"Information Disclosure through Detailed Error Messages\"\n    analysis: |\n      Detailed error messages are present in the codebase that could potentially leak sensitive information about the underlying system and database schema.\n    cwe: CWE-209\n    function_names: []\n    filenames:\n      - lib/Galileo.pm\n      - lib/Galileo/DB/Deploy.pm\n    classification: slightly promising\n\n  - headline: \"XSS Vulnerability in HTML Content Rendering\"\n    analysis: |\n      The code that handles rendering of HTML content from user inputs does not appear to properly sanitize the inputs. This can lead to cross-site scripting (XSS) attacks.\n    cwe: CWE-79\n    function_names:\n      - convertSpans\n    filenames:\n      - lib/Galileo/files/public/assets/pagedown-extra/Markdown.Extra.js\n    classification: very promising\n\n  - headline: \"Weak Password Storage Mechanism\"\n    analysis: |\n      The codebase uses a relatively weak bcrypt cost factor for password hashing (cost factor of 8). A higher cost factor would make the hashing more secure by making brute-force attacks more computationally expensive.\n    cwe: CWE-916\n    function_names: []\n    filenames:\n      - lib/Galileo/DB/Schema/Result/User.pm\n    classification: slightly promising\n\n  - headline: \"Potential Hard-Coded Credentials\"\n    analysis: |\n      The codebase may contain hard-coded credentials or API keys based on the patterns observed. This could lead to unauthorized access if attackers are able to exploit these credentials.\n    cwe: CWE-798\n    function_names: []\n    filenames:\n      - lib/Galileo/Command/setup.pm\n      - lib/Galileo/Command/author_tool.pm\n    classification: not promising\n\n```",
      "date": "2024-06-14T13:58:24.568642",
      "usage": {
        "prompt_tokens": 63965,
        "completion_tokens": 573,
        "cost": 0.32842
      }
    }
  ],
  "leads": [
    {
      "headline": "Potential SQL Injection in Database Connection",
      "analysis": "The code appears to allow raw SQL queries to be constructed using unvalidated user inputs. This is inferred from the lack of any input sanitization in the database connection logic, especially in the sections handling the loading of the database schema and executing raw SQL statements.\n",
      "classification": "very promising",
      "cwe": "CWE-89",
      "function_names": [
        "connect"
      ],
      "filenames": [
        "lib/Galileo.pm",
        "Build.PL"
      ]
    },
    {
      "headline": "Potential Command Injection through WebSocket Endpoint",
      "analysis": "The WebSocket handlers in the codebase do not appear to validate their inputs properly. An attacker could potentially exploit these endpoints to inject and execute malicious commands on the server.\n",
      "classification": "very promising",
      "cwe": "CWE-77",
      "function_names": [
        "sendViaWS"
      ],
      "filenames": [
        "lib/Galileo/files/public/galileo-edit.js"
      ]
    },
    {
      "headline": "Information Disclosure through Detailed Error Messages",
      "analysis": "Detailed error messages are present in the codebase that could potentially leak sensitive information about the underlying system and database schema.\n",
      "classification": "slightly promising",
      "cwe": "CWE-209",
      "function_names": [],
      "filenames": [
        "lib/Galileo.pm",
        "lib/Galileo/DB/Deploy.pm"
      ]
    },
    {
      "headline": "XSS Vulnerability in HTML Content Rendering",
      "analysis": "The code that handles rendering of HTML content from user inputs does not appear to properly sanitize the inputs. This can lead to cross-site scripting (XSS) attacks.\n",
      "classification": "very promising",
      "cwe": "CWE-79",
      "function_names": [
        "convertSpans"
      ],
      "filenames": [
        "lib/Galileo/files/public/assets/pagedown-extra/Markdown.Extra.js"
      ]
    },
    {
      "headline": "Weak Password Storage Mechanism",
      "analysis": "The codebase uses a relatively weak bcrypt cost factor for password hashing (cost factor of 8). A higher cost factor would make the hashing more secure by making brute-force attacks more computationally expensive.\n",
      "classification": "slightly promising",
      "cwe": "CWE-916",
      "function_names": [],
      "filenames": [
        "lib/Galileo/DB/Schema/Result/User.pm"
      ]
    },
    {
      "headline": "Potential Hard-Coded Credentials",
      "analysis": "The codebase may contain hard-coded credentials or API keys based on the patterns observed. This could lead to unauthorized access if attackers are able to exploit these credentials.\n",
      "classification": "not promising",
      "cwe": "CWE-798",
      "function_names": [],
      "filenames": [
        "lib/Galileo/Command/setup.pm",
        "lib/Galileo/Command/author_tool.pm"
      ]
    }
  ],
  "scores": [
    {
      "stats": {
        "fn": 1,
        "tp": 0,
        "fp": 3
      },
      "mapping": {},
      "vuln_dates": {
        "CVE-2019-7410": "2020-08-14T14:15:12"
      },
      "scoring_model": "claude-3-opus-20240229",
      "type": "llm",
      "instruction_template_hash": "245ace12b6361954d0a2"
    }
  ],
  "instruction_template_hash": "10c0163db4740318a544",
  "version": "0.1.0"
}
