{
  "commit": "293124cd59d6abc69f508b7638e383cfc791b287",
  "repo_url": "https://github.com/linux-application-whitelisting/fapolicyd",
  "model": "gpt-4o-2024-05-13",
  "chunk_hashes": [
    "a4be2d637bca0ce238f3"
  ],
  "responses": [
    {
      "content": "```yaml\nleads:\n  - headline: \"Potential Buffer Overflow in gid_proc_test.c\"\n    analysis: |\n      The `gid_proc_test.c` file has a potential buffer overflow vulnerability. In the function `main`, user-defined group IDs are fetched into a 'gids' array with a fixed size of 16. If the number of groups exceeds 16, the later parts of the array could lead to potential overflows.\n    cwe: CWE-120\n    function_names:\n      - main\n    filenames:\n      - src/tests/gid_proc_test.c\n    classification: very promising\n\n  - headline: \"Use After Free in gid_proc_test.c\"\n    analysis: |\n      The `gid_proc_test.c` file has a use-after-free vulnerability. The `groups` pointer is passed to `destroy_attr_set` and then freed, but it is subsequently used to call `free(groups)` without checking its status after the `destroy_attr_set` call.\n    cwe: CWE-416\n    function_names:\n      - main\n    filenames:\n      - src/tests/gid_proc_test.c\n    classification: very promising\n\n  - headline: \"Missing Check for NULL Pointer Dereference in avl_test.c\"\n    analysis: |\n      In `avl_test.c`, the `data` pointer returned by the `malloc()` function in the `append` function is not checked for NULL before dereferencing. This can lead to a NULL pointer dereference if memory allocation fails.\n    cwe: CWE-476\n    function_names:\n      - append\n    filenames:\n      - src/tests/avl_test.c\n    classification: very promising\n\n  - headline: \"Potential Command Injection in fapolicyd-cli.c\"\n    analysis: |\n      In `fapolicyd-cli.c`, several instances can lead to command injection, especially in the `do_ftype` and `do_update` functions where unsanitized user inputs might be included in commands being run via `system` call.\n    cwe: CWE-78\n    function_names:\n      - do_ftype\n      - do_update\n    filenames:\n      - src/cli/fapolicyd-cli.c\n    classification: very promising\n\n  - headline: \"Race Condition in do_update Function\"\n    analysis: |\n      In `fapolicyd-cli.c`, the `do_update` function which opens the pipe `/run/fapolicyd/fapolicyd.fifo` suffers from a race condition due to the separate calls to `open` and `stat`. An attacker could compromise this by replacing the pipe with a malicious one after the check.\n    cwe: CWE-367\n    function_names:\n      - do_update\n    filenames:\n      - src/cli/fapolicyd-cli.c\n    classification: very promising\n\n  - headline: \"Buffer Overflow in fapolicyd-cli.c\"\n    analysis: |\n      The function `do_dump_db` in `fapolicyd-cli.c` reads data and uses `sscanf` without properly ensuring the size of the `data` buffer, which can lead to buffer overflow if properly crafted input is passed.\n    cwe: CWE-120\n    function_names:\n      - do_dump_db\n    filenames:\n      - src/cli/fapolicyd-cli.c\n    classification: very promising\n\n  - headline: \"Potential Time-of-check to Time-of-use (TOCTOU) Race Condition in mount.c\"\n    analysis: |\n      In `mounts.c`, during the `handle_mounts` function, there is a potential TOCTOU race condition as it checks the mount details and later manipulates them without holding a lock, enabling the potential inconsistency between checks and manipulations.\n    cwe: CWE-367\n    function_names:\n      - handle_mounts\n    filenames:\n      - src/daemon/mounts.c\n    classification: very promising\n\n  - headline: \"Improper Handling of Exceptional Conditions in notify.c\"\n    analysis: |\n      In `notify.c`, particularly within the `decision_thread_main` and `handle_events` functions, some error conditions (like memory allocation failure or I/O failures) are not properly handled, which can lead to potential runtime exceptions and crashes.\n    cwe: CWE-755\n    function_names:\n      - decision_thread_main\n      - handle_events\n    filenames:\n      - src/daemon/notify.c\n    classification: very promising\n```",
      "date": "2024-06-13T09:48:57.404969",
      "usage": {
        "prompt_tokens": 93780,
        "completion_tokens": 912,
        "cost": 0.48258
      }
    }
  ],
  "leads": [
    {
      "headline": "Potential Buffer Overflow in gid_proc_test.c",
      "analysis": "The gid_proc_test.c file has a potential buffer overflow vulnerability. In the function main, user-defined group IDs are fetched into a 'gids' array with a fixed size of 16. If the number of groups exceeds 16, the later parts of the array could lead to potential overflows.\n",
      "classification": "very promising",
      "cwe": "CWE-120",
      "function_names": [
        "main"
      ],
      "filenames": [
        "src/tests/gid_proc_test.c"
      ]
    },
    {
      "headline": "Use After Free in gid_proc_test.c",
      "analysis": "The gid_proc_test.c file has a use-after-free vulnerability. The groups pointer is passed to destroy_attr_set and then freed, but it is subsequently used to call free(groups) without checking its status after the destroy_attr_set call.\n",
      "classification": "very promising",
      "cwe": "CWE-416",
      "function_names": [
        "main"
      ],
      "filenames": [
        "src/tests/gid_proc_test.c"
      ]
    },
    {
      "headline": "Missing Check for NULL Pointer Dereference in avl_test.c",
      "analysis": "In avl_test.c, the data pointer returned by the malloc() function in the append function is not checked for NULL before dereferencing. This can lead to a NULL pointer dereference if memory allocation fails.\n",
      "classification": "very promising",
      "cwe": "CWE-476",
      "function_names": [
        "append"
      ],
      "filenames": [
        "src/tests/avl_test.c"
      ]
    },
    {
      "headline": "Potential Command Injection in fapolicyd-cli.c",
      "analysis": "In fapolicyd-cli.c, several instances can lead to command injection, especially in the do_ftype and do_update functions where unsanitized user inputs might be included in commands being run via system call.\n",
      "classification": "very promising",
      "cwe": "CWE-78",
      "function_names": [
        "do_ftype",
        "do_update"
      ],
      "filenames": [
        "src/cli/fapolicyd-cli.c"
      ]
    },
    {
      "headline": "Race Condition in do_update Function",
      "analysis": "In fapolicyd-cli.c, the do_update function which opens the pipe /run/fapolicyd/fapolicyd.fifo suffers from a race condition due to the separate calls to open and stat. An attacker could compromise this by replacing the pipe with a malicious one after the check.\n",
      "classification": "very promising",
      "cwe": "CWE-367",
      "function_names": [
        "do_update"
      ],
      "filenames": [
        "src/cli/fapolicyd-cli.c"
      ]
    },
    {
      "headline": "Buffer Overflow in fapolicyd-cli.c",
      "analysis": "The function do_dump_db in fapolicyd-cli.c reads data and uses sscanf without properly ensuring the size of the data buffer, which can lead to buffer overflow if properly crafted input is passed.\n",
      "classification": "very promising",
      "cwe": "CWE-120",
      "function_names": [
        "do_dump_db"
      ],
      "filenames": [
        "src/cli/fapolicyd-cli.c"
      ]
    },
    {
      "headline": "Potential Time-of-check to Time-of-use (TOCTOU) Race Condition in mount.c",
      "analysis": "In mounts.c, during the handle_mounts function, there is a potential TOCTOU race condition as it checks the mount details and later manipulates them without holding a lock, enabling the potential inconsistency between checks and manipulations.\n",
      "classification": "very promising",
      "cwe": "CWE-367",
      "function_names": [
        "handle_mounts"
      ],
      "filenames": [
        "src/daemon/mounts.c"
      ]
    },
    {
      "headline": "Improper Handling of Exceptional Conditions in notify.c",
      "analysis": "In notify.c, particularly within the decision_thread_main and handle_events functions, some error conditions (like memory allocation failure or I/O failures) are not properly handled, which can lead to potential runtime exceptions and crashes.\n",
      "classification": "very promising",
      "cwe": "CWE-755",
      "function_names": [
        "decision_thread_main",
        "handle_events"
      ],
      "filenames": [
        "src/daemon/notify.c"
      ]
    }
  ],
  "scores": [
    {
      "stats": {
        "fn": 1,
        "tp": 0,
        "fp": 8
      },
      "mapping": {},
      "vuln_dates": {
        "CVE-2022-1117": "2022-08-29T15:15:10"
      },
      "scoring_model": "claude-3-opus-20240229",
      "type": "llm",
      "instruction_template_hash": "245ace12b6361954d0a2"
    },
    {
      "stats": {
        "fn": 1,
        "tp": 0,
        "fp": 8
      },
      "mapping": {},
      "vuln_dates": {
        "CVE-2022-1117": "2022-08-29T15:15:10"
      },
      "scoring_model": "claude-3-5-sonnet-20240620",
      "type": "llm",
      "instruction_template_hash": "245ace12b6361954d0a2"
    }
  ],
  "instruction_template_hash": "10c0163db4740318a544",
  "version": "0.1.0"
}
