{
  "commit": "2df95ccff5bdce2e13040f17d323564f29d74f0c",
  "repo_url": "https://github.com/lukasavicus/windmill",
  "model": "claude-3-sonnet-20240229",
  "chunk_hashes": [
    "7c73d333ca9739286fbc"
  ],
  "responses": [
    {
      "content": "Based on the code provided, I identified the following potential security vulnerabilities:\n\n```yaml\nleads:\n  - headline: Unrestricted File Upload\n    analysis: |\n      The application allows users to upload files without proper validation of the file extension and content. An attacker could potentially upload malicious scripts or other harmful content to the server.\n    cwe: CWE-434\n    function_names:\n      - upload_file\n    filenames:\n      - windmill/archives/routes.py\n    classification: very promising\n\n  - headline: Insecure Deserialization\n    analysis: |\n      The application deserializes untrusted data from the MongoDB database, which could potentially lead to arbitrary code execution or other security issues if the deserialized data is not properly sanitized.\n    cwe: CWE-502\n    function_names:\n      - _new_job\n    filenames:\n      - windmill/models.py\n    classification: very promising\n\n  - headline: Hardcoded Credentials\n    analysis: |\n      The application appears to have a hardcoded MongoDB connection URI, which could potentially expose sensitive information if the URI contains credentials.\n    cwe: CWE-798\n    function_names: []\n    filenames:\n      - windmill/__init__.py\n    classification: slightly promising\n\n  - headline: Potential Command Injection\n    analysis: |\n      The application allows users to execute system commands without proper sanitization, which could potentially lead to command injection vulnerabilities.\n    cwe: CWE-78\n    function_names:\n      - dev_cmd\n    filenames:\n      - windmill/dev/routes.py\n    classification: very promising\n\n  - headline: Potential Open Redirect\n    analysis: |\n      The application appears to redirect users to external URLs without proper validation, which could potentially lead to open redirect vulnerabilities.\n    cwe: CWE-601\n    function_names:\n      - login\n    filenames:\n      - windmill/main/routes.py\n    classification: slightly promising\n```\n\nPlease note that a more thorough analysis would require reviewing the entire codebase, testing the application, and understanding the specific context and requirements of the application.",
      "date": "2024-06-13T09:55:25.307943",
      "usage": {
        "prompt_tokens": 68138,
        "completion_tokens": 502,
        "cost": 0.211944
      }
    }
  ],
  "leads": [
    {
      "headline": "Unrestricted File Upload",
      "analysis": "The application allows users to upload files without proper validation of the file extension and content. An attacker could potentially upload malicious scripts or other harmful content to the server.\n",
      "classification": "very promising",
      "cwe": "CWE-434",
      "function_names": [
        "upload_file"
      ],
      "filenames": [
        "windmill/archives/routes.py"
      ]
    },
    {
      "headline": "Insecure Deserialization",
      "analysis": "The application deserializes untrusted data from the MongoDB database, which could potentially lead to arbitrary code execution or other security issues if the deserialized data is not properly sanitized.\n",
      "classification": "very promising",
      "cwe": "CWE-502",
      "function_names": [
        "_new_job"
      ],
      "filenames": [
        "windmill/models.py"
      ]
    },
    {
      "headline": "Hardcoded Credentials",
      "analysis": "The application appears to have a hardcoded MongoDB connection URI, which could potentially expose sensitive information if the URI contains credentials.\n",
      "classification": "slightly promising",
      "cwe": "CWE-798",
      "function_names": [],
      "filenames": [
        "windmill/__init__.py"
      ]
    },
    {
      "headline": "Potential Command Injection",
      "analysis": "The application allows users to execute system commands without proper sanitization, which could potentially lead to command injection vulnerabilities.\n",
      "classification": "very promising",
      "cwe": "CWE-78",
      "function_names": [
        "dev_cmd"
      ],
      "filenames": [
        "windmill/dev/routes.py"
      ]
    },
    {
      "headline": "Potential Open Redirect",
      "analysis": "The application appears to redirect users to external URLs without proper validation, which could potentially lead to open redirect vulnerabilities.\n",
      "classification": "slightly promising",
      "cwe": "CWE-601",
      "function_names": [
        "login"
      ],
      "filenames": [
        "windmill/main/routes.py"
      ]
    }
  ],
  "scores": [
    {
      "stats": {
        "fn": 1,
        "tp": 0,
        "fp": 3
      },
      "mapping": {},
      "vuln_dates": {
        "CVE-2022-31519": "2022-07-11T01:15:08"
      },
      "scoring_model": "claude-3-opus-20240229",
      "type": "llm",
      "instruction_template_hash": "245ace12b6361954d0a2"
    },
    {
      "stats": {
        "fn": 1,
        "tp": 0,
        "fp": 3
      },
      "mapping": {},
      "vuln_dates": {
        "CVE-2022-31519": "2022-07-11T01:15:08"
      },
      "scoring_model": "claude-3-5-sonnet-20240620",
      "type": "llm",
      "instruction_template_hash": "245ace12b6361954d0a2"
    }
  ],
  "instruction_template_hash": "10c0163db4740318a544",
  "version": "0.1.0"
}
