{
  "commit": "1fe15cd707fa05bd558d6bb5b6c489d483179ace",
  "repo_url": "https://github.com/trustedsec/trevorc2",
  "model": "gpt-4o-2024-05-13",
  "chunk_hashes": [
    "0ab784f42c75eada2d72"
  ],
  "responses": [
    {
      "content": "```yaml\nleads:\n  - headline: Hard-coded Cipher Key\n    analysis: |\n      In the\u00a0codebase, there is a hard-coded encryption key labeled\u202fTr3v0rC2R0x@nd1s@w350m3#TrevorForget.\u202fThis key is shared between the server and the client, meaning if someone obtains one part of the infrastructure (server or client) the encryption key is immediately exposed. Thus, the whole communication system is compromised.\n    cwe: CWE-798\n    function_names: []\n    filenames: \n      - trevorc2_client.py\n      - trevorc2_client.java\n      - trevorc2_server.py\n    classification: very promising\n  - headline: Usage of Insecure URL (HTTP) \n    analysis: |\n      The code uses HTTP URLs instead of HTTPS for communication between the client and server. Using HTTP exposes communication to eavesdropping, tampering, and man-in-the-middle attacks.\n    cwe: CWE-319\n    function_names: []\n    filenames:\n      - trevorc2_client.py\n      - trevorc2_client.java\n    classification: very promising\n  - headline: Command Injection\n    analysis: |\n      The server takes commands input by an interactive user and transmits them to the client, which then executes them using subprocess.Popen (in Python) or ProcessBuilder (in Java). If an attacker manages to compromise the server, they could potentially execute arbitrary commands on all connected clients.\n    cwe: CWE-78\n    function_names:\n      - main\n    filenames: \n      - trevorc2_client.py\n      - trevorc2_client.java\n    classification: very promising\n  - headline: Missing Input Validation and Sanitation\n    analysis: |\n      There is a lack of thorough input validation and sanitization when handling hostname and user inputs in commands. Without proper sanitization, these inputs can lead to security vulnerabilities like command injection or cascading input manipulation vulnerabilities.\n    cwe: CWE-20\n    function_names:\n      - connect_trevor\n    filenames: \n      - trevorc2_client.py\n    classification: slightly promising\n  - headline: Inadequate Error Handling\n    analysis: |\n      Exception handling in the codebase often seems to pass without taking action, specifically in network communications. This may result in undetected failures and a compromised state without proper error recovery or alert mechanisms.\n    cwe: CWE-755\n    function_names:\n      - connect_trevor\n    filenames:\n      - trevorc2_client.py\n      - trevorc2_client.java\n    classification: slightly promising\n  - headline: Insecure Random Number Generation for Session IDs\n    analysis: |\n      The randomSessionID function uses the default random library to generate session IDs, but it does not employ a cryptographically secure pseudo-random number generator (CSPRNG), which can lead to predictable session IDs and make it easier for attackers to guess or brute-force them.\n    cwe: CWE-330\n    function_names:\n      - randomString\n    filenames:\n      - trevorc2_server.py\n    classification: very promising\n  - headline: Disclosure of Internal IP Address\n    analysis: |\n      The code contains IP address 127.0.0.1 in the SITE_URL variable for both the client and the server, which might lead to inadvertent disclosure of internal infrastructure details if exposed or misconfigured.\n    cwe: CWE-200\n    function_names: []\n    filenames:\n      - trevorc2_client.py\n      - trevorc2_client.java\n      - trevorc2_server.py\n    classification: slightly promising\n```",
      "date": "2024-06-13T17:19:04.521722",
      "usage": {
        "prompt_tokens": 11324,
        "completion_tokens": 765,
        "cost": 0.068095
      }
    }
  ],
  "leads": [
    {
      "headline": "Hard-coded Cipher Key",
      "analysis": "In the\u00a0codebase, there is a hard-coded encryption key labeled\u202fTr3v0rC2R0x@nd1s@w350m3#TrevorForget.\u202fThis key is shared between the server and the client, meaning if someone obtains one part of the infrastructure (server or client) the encryption key is immediately exposed. Thus, the whole communication system is compromised.\n",
      "classification": "very promising",
      "cwe": "CWE-798",
      "function_names": [],
      "filenames": [
        "trevorc2_client.py",
        "trevorc2_client.java",
        "trevorc2_server.py"
      ]
    },
    {
      "headline": "Usage of Insecure URL (HTTP)",
      "analysis": "The code uses HTTP URLs instead of HTTPS for communication between the client and server. Using HTTP exposes communication to eavesdropping, tampering, and man-in-the-middle attacks.\n",
      "classification": "very promising",
      "cwe": "CWE-319",
      "function_names": [],
      "filenames": [
        "trevorc2_client.py",
        "trevorc2_client.java"
      ]
    },
    {
      "headline": "Command Injection",
      "analysis": "The server takes commands input by an interactive user and transmits them to the client, which then executes them using subprocess.Popen (in Python) or ProcessBuilder (in Java). If an attacker manages to compromise the server, they could potentially execute arbitrary commands on all connected clients.\n",
      "classification": "very promising",
      "cwe": "CWE-78",
      "function_names": [
        "main"
      ],
      "filenames": [
        "trevorc2_client.py",
        "trevorc2_client.java"
      ]
    },
    {
      "headline": "Missing Input Validation and Sanitation",
      "analysis": "There is a lack of thorough input validation and sanitization when handling hostname and user inputs in commands. Without proper sanitization, these inputs can lead to security vulnerabilities like command injection or cascading input manipulation vulnerabilities.\n",
      "classification": "slightly promising",
      "cwe": "CWE-20",
      "function_names": [
        "connect_trevor"
      ],
      "filenames": [
        "trevorc2_client.py"
      ]
    },
    {
      "headline": "Inadequate Error Handling",
      "analysis": "Exception handling in the codebase often seems to pass without taking action, specifically in network communications. This may result in undetected failures and a compromised state without proper error recovery or alert mechanisms.\n",
      "classification": "slightly promising",
      "cwe": "CWE-755",
      "function_names": [
        "connect_trevor"
      ],
      "filenames": [
        "trevorc2_client.py",
        "trevorc2_client.java"
      ]
    },
    {
      "headline": "Insecure Random Number Generation for Session IDs",
      "analysis": "The randomSessionID function uses the default random library to generate session IDs, but it does not employ a cryptographically secure pseudo-random number generator (CSPRNG), which can lead to predictable session IDs and make it easier for attackers to guess or brute-force them.\n",
      "classification": "very promising",
      "cwe": "CWE-330",
      "function_names": [
        "randomString"
      ],
      "filenames": [
        "trevorc2_server.py"
      ]
    },
    {
      "headline": "Disclosure of Internal IP Address",
      "analysis": "The code contains IP address 127.0.0.1 in the SITE_URL variable for both the client and the server, which might lead to inadvertent disclosure of internal infrastructure details if exposed or misconfigured.\n",
      "classification": "slightly promising",
      "cwe": "CWE-200",
      "function_names": [],
      "filenames": [
        "trevorc2_client.py",
        "trevorc2_client.java",
        "trevorc2_server.py"
      ]
    }
  ],
  "scores": [
    {
      "stats": {
        "fn": 1,
        "tp": 0,
        "fp": 4
      },
      "mapping": {},
      "vuln_dates": {
        "CVE-2019-18850": "2019-12-04T13:15:10"
      },
      "scoring_model": "claude-3-opus-20240229",
      "type": "llm",
      "instruction_template_hash": "245ace12b6361954d0a2"
    }
  ],
  "instruction_template_hash": "10c0163db4740318a544",
  "version": "0.1.0"
}
